{
  "type": "Feature",
  "properties": {
    "addr:full":"Rue De Namur 95 Brussel/bruxelles Bruxelles-Capitale 1000",
    "addr:housenumber":"95",
    "addr:postcode":"1000",
    "addr:street":"Rue De Namur;/",
    "iso:country":"BE",
    "sg:address":"Rue De Namur 95",
    "sg:city":"Brussel/bruxelles",
    "sg:orig_category":"Opticiens",
    "sg:phone":"+32 2 512 42 83",
    "sg:postcode":"1000",
    "sg:province":"Bruxelles-Capitale",
    "wof:name":"Shifner Opticien",
    "wof:placetype":"venue"
},
  "geometry": {"coordinates":[4.3614649773,50.8390235901],"type":"Point"}
}