{
  "type": "Feature",
  "properties": {
    "addr:full":"Zwarte Nonnenstraat 35 Veurne West-Vlaanderen 8630",
    "addr:housenumber":"35",
    "addr:postcode":"8630",
    "addr:street":"Zwarte Nonnenstraat",
    "iso:country":"BE",
    "sg:address":"Zwarte Nonnenstraat 35",
    "sg:city":"Veurne",
    "sg:orig_category":"Antiek",
    "sg:phone":"+32 58 31 21 97",
    "sg:postcode":"8630",
    "sg:province":"West-Vlaanderen",
    "wof:name":"Guido De Beus",
    "wof:placetype":"venue"
},
  "geometry": {"coordinates":[2.6598060131,51.0736274719],"type":"Point"}
}