{
  "type": "Feature",
  "properties": {
    "addr:full":"Conterschep 130 Antwerpen Antwerpen 2040",
    "addr:housenumber":"130",
    "addr:postcode":"2040",
    "iso:country":"BE",
    "sg:address":"Conterschep 130",
    "sg:city":"Antwerpen",
    "sg:orig_category":"Tuinen",
    "sg:phone":"+32 3 568 61 76",
    "sg:postcode":"2040",
    "sg:province":"Antwerpen",
    "wof:name":"De Schutter Jos",
    "wof:placetype":"venue"
},
  "geometry": {"coordinates":[4.3141150475,51.3429756165],"type":"Point"}
}