{
  "type": "Feature",
  "properties": {
    "addr:full":"Chemin Du Tuquet 5 Mont-de-l'enclus (anseroeul) Hainaut 7750",
    "addr:housenumber":"5",
    "addr:postcode":"7750",
    "addr:street":"Chemin Du Tuquet;Hainaut",
    "iso:country":"BE",
    "sg:address":"Chemin Du Tuquet 5",
    "sg:city":"Mont-de-l'enclus (anseroeul)",
    "sg:classifiers":[
        {
            "category":"Building & Trades",
            "subcategory":"Landscaping Services",
            "type":"Services"
        }
    ],
    "sg:phone":"+32 69 76 82 10",
    "sg:postcode":"7750",
    "sg:province":"Hainaut",
    "sg:tags":[
        "gardening",
        "garden",
        "maintenance"
    ],
    "wof:name":"Dhonte Jean-christophe",
    "wof:placetype":"venue"
},
  "geometry": {"coordinates":[5.7178230286,47.0204772949],"type":"Point"}
}