{
  "type": "Feature",
  "properties": {
    "iso:country":"BE",
    "sg:address":"Wynendalestraat 77",
    "sg:city":"Diksmuide",
    "sg:orig_category":"Pain, p\u00e2tisseries and confiseries",
    "sg:phone":"+32 51 50 06 88",
    "sg:postcode":"8600",
    "sg:province":"West-Vlaanderen",
    "wof:name":"Gery Vanduyfhuys",
    "wof:placetype":"venue"
},
  "geometry": {"coordinates":[2.8657801151,51.0334663391],"type":"Point"}
}