{
  "type": "Feature",
  "properties": {
    "iso:country":"BE",
    "sg:address":"Potterstraat 10",
    "sg:city":"Sint-gillis-waas",
    "sg:orig_category":"Boissons Gr",
    "sg:phone":"+32 3 776 42 63",
    "sg:postcode":"9170",
    "sg:province":"Oost-Vlaanderen",
    "wof:name":"Fa. De Cock",
    "wof:placetype":"venue"
},
  "geometry": {"coordinates":[4.0989489555,51.1930160522],"type":"Point"}
}