{
  "type": "Feature",
  "properties": {
    "addr:full":"Kapelsestraat 38 Kapellen Antwerpen 2950",
    "addr:housenumber":"38",
    "addr:postcode":"2950",
    "addr:street":"Kapelsestraat",
    "iso:country":"BE",
    "sg:address":"Kapelsestraat 38",
    "sg:city":"Kapellen",
    "sg:classifiers":[
        {
            "category":"Insurance",
            "subcategory":"Insurance Agent",
            "type":"Services"
        }
    ],
    "sg:phone":"+32 3 660 13 11",
    "sg:postcode":"2950",
    "sg:province":"Antwerpen",
    "sg:tags":[
        "verzekeringsmakelaars",
        "expert"
    ],
    "wof:name":"P&v",
    "wof:placetype":"venue"
},
  "geometry": {"coordinates":[4.4246177673,51.320274353],"type":"Point"}
}