{
  "type": "Feature",
  "properties": {
    "iso:country":"BE",
    "sg:address":"Rue Croix Colson 12",
    "sg:city":"Doische (romer\u00e9e)",
    "sg:classifiers":[
        {
            "category":"Communications",
            "subcategory":"Television Station",
            "type":"Services"
        }
    ],
    "sg:phone":"+32 82 67 79 20",
    "sg:postcode":"5680",
    "sg:province":"Namur",
    "sg:tags":[
        "antenna"
    ],
    "wof:name":"Unikom Sprl",
    "wof:placetype":"venue"
},
  "geometry": {"coordinates":[4.6872258186,50.1354293823],"type":"Point"}
}