{
  "type": "Feature",
  "properties": {
    "iso:country":"BE",
    "sg:address":"Rooigemlaan 563",
    "sg:city":"Gent-centrum",
    "sg:orig_category":"Meubles D\u00e9taillants, Am\u00e9nagement de B\u00e2timents et de Cuisines",
    "sg:phone":"+32 9 226 17 71",
    "sg:postcode":"9000",
    "sg:province":"Oost-Vlaanderen",
    "wof:name":"Sleepy Gent",
    "wof:placetype":"venue"
},
  "geometry": {"coordinates":[3.6966478825,51.0649185181],"type":"Point"}
}