{
  "type": "Feature",
  "properties": {
    "addr:full":"Rue L\u00e9opold I 319 Bruxelles (jette) Bruxelles-Capitale 1090",
    "addr:housenumber":"319",
    "addr:postcode":"1090",
    "addr:street":"Rue Le\u0301Opold I",
    "iso:country":"BE",
    "sg:address":"Rue L\u00e9opold I 319",
    "sg:city":"Bruxelles (jette)",
    "sg:classifiers":[
        {
            "category":"Professional",
            "subcategory":"Management & Consulting",
            "type":"Services"
        }
    ],
    "sg:phone":"+32 2 424 38 40",
    "sg:postcode":"1090",
    "sg:province":"Bruxelles-Capitale",
    "sg:tags":[
        "consultant",
        "law"
    ],
    "wof:name":"Lancaster Martial",
    "wof:placetype":"venue"
},
  "geometry": {"coordinates":[4.3378720284,50.8764305115],"type":"Point"}
}