{
  "type": "Feature",
  "properties": {
    "addr:full":"Wespelaarsebaan 131 Boortmeerbeek Vlaams-Brabant 3190",
    "addr:housenumber":"131",
    "addr:postcode":"3190",
    "addr:street":"Wespelaarsebaan",
    "iso:country":"BE",
    "sg:address":"Wespelaarsebaan 131",
    "sg:city":"Boortmeerbeek",
    "sg:orig_category":"Entretien and r\u00e9parations de voitures",
    "sg:phone":"+32 16 60 26 61",
    "sg:postcode":"3190",
    "sg:province":"Vlaams-Brabant",
    "wof:name":"Garage De Lessine",
    "wof:placetype":"venue"
},
  "geometry": {"coordinates":[4.5970878601,50.9710006714],"type":"Point"}
}