{
  "type": "Feature",
  "properties": {
    "addr:full":"Lepelstraat 11 Laarne Oost-Vlaanderen 9270",
    "addr:housenumber":"11",
    "addr:postcode":"9270",
    "addr:street":"Lepelstraat",
    "iso:country":"BE",
    "sg:address":"Lepelstraat 11",
    "sg:city":"Laarne",
    "sg:orig_category":"Banken and kredietinstellingen",
    "sg:phone":"+32 9 369 39 00",
    "sg:postcode":"9270",
    "sg:province":"Oost-Vlaanderen",
    "wof:name":"Bacob",
    "wof:placetype":"venue"
},
  "geometry": {"coordinates":[3.8518719673,51.0302314758],"type":"Point"}
}