{
  "type": "Feature",
  "properties": {
    "iso:country":"BE",
    "sg:address":"Centrumstraat 72",
    "sg:city":"Zulte",
    "sg:orig_category":"Assistances juridiques",
    "sg:phone":"+32 475 97 09 35",
    "sg:postcode":"9870",
    "sg:province":"Oost-Vlaanderen",
    "wof:name":"Den Ateljee",
    "wof:placetype":"venue"
},
  "geometry": {"coordinates":[3.469201088,50.9323120117],"type":"Point"}
}