{
  "type": "Feature",
  "properties": {
    "addr:full":"Sinaaistraat 3 Lokeren Oost-Vlaanderen 9160",
    "addr:housenumber":"3",
    "addr:postcode":"9160",
    "addr:street":"Sinaaistraat",
    "iso:country":"BE",
    "sg:address":"Sinaaistraat 3",
    "sg:city":"Lokeren",
    "sg:orig_category":"Computers and computerapparatuur Software ontwikkeling and ontwerp",
    "sg:phone":"+32 9 348 95 62",
    "sg:postcode":"9160",
    "sg:province":"Oost-Vlaanderen",
    "wof:name":"Softaccount",
    "wof:placetype":"venue"
},
  "geometry": {"coordinates":[4.0091328621,51.1264457703],"type":"Point"}
}