{
  "type": "Feature",
  "properties": {
    "addr:full":"Ommegang Zuid 23 Staden West-Vlaanderen 8840",
    "addr:housenumber":"23",
    "addr:postcode":"8840",
    "addr:street":"Ommegang Zuid",
    "iso:country":"BE",
    "sg:address":"Ommegang Zuid 23",
    "sg:city":"Staden",
    "sg:orig_category":"Schoenen",
    "sg:phone":"+32 51 77 80 57",
    "sg:postcode":"8840",
    "sg:province":"West-Vlaanderen",
    "wof:name":"Huis Arlette",
    "wof:placetype":"venue"
},
  "geometry": {"coordinates":[3.0103459358,50.9277839661],"type":"Point"}
}