{
  "type": "Feature",
  "properties": {
    "iso:country":"BE",
    "sg:address":"Bagattenstraat 1",
    "sg:city":"Gent",
    "sg:classifiers":[
        {
            "category":"Professional",
            "subcategory":"Art Services",
            "type":"Services"
        }
    ],
    "sg:phone":"+32 9 224 36 92",
    "sg:postcode":"9000",
    "sg:province":"Oost-Vlaanderen",
    "sg:tags":[
        "graphic",
        "designer"
    ],
    "wof:name":"Pro-graph",
    "wof:placetype":"venue"
},
  "geometry": {"coordinates":[3.7218840122,51.0474700928],"type":"Point"}
}