{
  "type": "Feature",
  "properties": {
    "addr:full":"Ondernemingsstraat 9 Veurne West-Vlaanderen 8630",
    "addr:housenumber":"9",
    "addr:postcode":"8630",
    "addr:street":"Ondernemingsstraat",
    "iso:country":"BE",
    "sg:address":"Ondernemingsstraat 9",
    "sg:city":"Veurne",
    "sg:orig_category":"Diverse producten Gh Dranken",
    "sg:phone":"+32 58 31 59 60",
    "sg:postcode":"8630",
    "sg:province":"West-Vlaanderen",
    "wof:name":"Coulier Wijnhandel",
    "wof:placetype":"venue"
},
  "geometry": {"coordinates":[2.677850008,51.0620689392],"type":"Point"}
}