{
  "type": "Feature",
  "properties": {
    "iso:country":"BE",
    "sg:address":"Industrielaan 35",
    "sg:city":"Torhout",
    "sg:orig_category":"Installatie van houten of kunststof schrijnwerk",
    "sg:phone":"+32 50 21 29 49",
    "sg:postcode":"8820",
    "sg:province":"West-Vlaanderen",
    "wof:name":"Luc Degrande",
    "wof:placetype":"venue"
},
  "geometry": {"coordinates":[3.1022589207,51.0760955811],"type":"Point"}
}