{
  "type": "Feature",
  "properties": {
    "addr:full":"Geitestraat 15 Mechelen Antwerpen 2800",
    "addr:housenumber":"15",
    "addr:postcode":"2800",
    "addr:street":"Geitestraat",
    "iso:country":"BE",
    "sg:address":"Geitestraat 15",
    "sg:city":"Mechelen",
    "sg:classifiers":[
        {
            "category":"Shopping",
            "subcategory":"Clothing, Apparel, & Fashions",
            "type":"Retail Goods"
        }
    ],
    "sg:phone":"+32 15 20 42 99",
    "sg:postcode":"2800",
    "sg:province":"Antwerpen",
    "sg:tags":[
        "boutique"
    ],
    "wof:name":"La Gaviotta",
    "wof:placetype":"venue"
},
  "geometry": {"coordinates":[4.4800238609,51.0270042419],"type":"Point"}
}