{
  "type": "Feature",
  "properties": {
    "iso:country":"BE",
    "sg:address":"Knaptandstraat 4",
    "sg:city":"Sint-niklaas",
    "sg:orig_category":"Industri\u00eble and commerci\u00eble bouw Woningbouw",
    "sg:phone":"+32 3 776 77 02",
    "sg:postcode":"9100",
    "sg:province":"Oost-Vlaanderen",
    "wof:name":"Immocenter Van Goethem",
    "wof:placetype":"venue"
},
  "geometry": {"coordinates":[4.1429820061,51.1605949402],"type":"Point"}
}