{
  "type": "Feature",
  "properties": {
    "addr:full":"Tennisstraat 55 Beringen Limburg 3582",
    "addr:housenumber":"55",
    "addr:postcode":"3582",
    "addr:street":"Tennisstraat",
    "iso:country":"BE",
    "sg:address":"Tennisstraat 55",
    "sg:city":"Beringen",
    "sg:orig_category":"Sportclubs",
    "sg:phone":"+32 11 42 27 09",
    "sg:postcode":"3582",
    "sg:province":"Limburg",
    "wof:name":"Beringen Tennisclub\u00b5",
    "wof:placetype":"venue"
},
  "geometry": {"coordinates":[5.2185411453,51.0676956177],"type":"Point"}
}