{
  "type": "Feature",
  "properties": {
    "addr:full":"Leeststraat 73 Merksplas Antwerpen 2330",
    "addr:housenumber":"73",
    "addr:postcode":"2330",
    "addr:street":"Leeststraat",
    "iso:country":"BE",
    "sg:address":"Leeststraat 73",
    "sg:city":"Merksplas",
    "sg:orig_category":"V\u00e9hicules automobiles. Entretien and r\u00e9parations de voitures",
    "sg:phone":"+32 14 63 30 24",
    "sg:postcode":"2330",
    "sg:province":"Antwerpen",
    "wof:name":"Karel Jacobs",
    "wof:placetype":"venue"
},
  "geometry": {"coordinates":[4.8584499359,51.3559608459],"type":"Point"}
}