{
  "type": "Feature",
  "properties": {
    "iso:country":"BE",
    "sg:address":"Churchilllaan 267",
    "sg:city":"Schoten",
    "sg:classifiers":[
        {
            "category":"Retail",
            "subcategory":"Repair Shop",
            "type":"Services"
        }
    ],
    "sg:phone":"+32 3 658 66 64",
    "sg:postcode":"2900",
    "sg:province":"Antwerpen",
    "wof:name":"Heylen F",
    "wof:placetype":"venue"
},
  "geometry": {"coordinates":[4.4834971428,51.2493515015],"type":"Point"}
}