{
  "type": "Feature",
  "properties": {
    "addr:full":"Rue Isidore Hoton 40 Ath Hainaut 7800",
    "addr:housenumber":"40",
    "addr:postcode":"7800",
    "addr:street":"Rue Isidore Hoton",
    "iso:country":"BE",
    "sg:address":"Rue Isidore Hoton 40",
    "sg:city":"Ath",
    "sg:orig_category":"M\u00e9decins and sp\u00e9cialistes",
    "sg:phone":"+32 68 28 46 05",
    "sg:postcode":"7800",
    "sg:province":"Hainaut",
    "wof:name":"Alain Rivi\u00c8re",
    "wof:placetype":"venue"
},
  "geometry": {"coordinates":[3.7827739716,50.6330223083],"type":"Point"}
}