{
  "type": "Feature",
  "properties": {
    "addr:full":"Mechelsesteenweg 450 Zaventem (nossegem) Vlaams-Brabant 1930",
    "addr:housenumber":"450",
    "addr:postcode":"1930",
    "addr:street":"Mechelsesteenweg",
    "iso:country":"BE",
    "sg:address":"Mechelsesteenweg 450",
    "sg:city":"Zaventem (nossegem)",
    "sg:classifiers":[
        {
            "category":"Professional",
            "subcategory":"Printing & Photocopies",
            "type":"Services"
        }
    ],
    "sg:phone":"+32 2 759 81 15",
    "sg:postcode":"1930",
    "sg:province":"Vlaams-Brabant",
    "sg:tags":[
        "engraving"
    ],
    "wof:name":"Publicoen Bvba",
    "wof:placetype":"venue"
},
  "geometry": {"coordinates":[4.5075030327,50.8773269653],"type":"Point"}
}