{
  "type": "Feature",
  "properties": {
    "addr:full":"Halmaalweg 170 Sint-truiden Limburg 3800",
    "addr:housenumber":"170",
    "addr:postcode":"3800",
    "addr:street":"Halmaalweg",
    "iso:country":"BE",
    "sg:address":"Halmaalweg 170",
    "sg:city":"Sint-truiden",
    "sg:orig_category":"Eleveurs de bovins. Producteurs de fruits. Eleveurs and marchands de porcs",
    "sg:phone":"+32 11 68 27 88",
    "sg:postcode":"3800",
    "sg:province":"Limburg",
    "wof:name":"Valere Blavier",
    "wof:placetype":"venue"
},
  "geometry": {"coordinates":[5.1566581726,50.8065834045],"type":"Point"}
}