{
  "type": "Feature",
  "properties": {
    "addr:full":"Terlindenhofstraat 36 Antwerpen Antwerpen 2170",
    "addr:housenumber":"36",
    "addr:postcode":"2170",
    "addr:street":"Terlindenhofstraat",
    "iso:country":"BE",
    "sg:address":"Terlindenhofstraat 36",
    "sg:city":"Antwerpen",
    "sg:orig_category":"Ramassage and traitement des d\u00e9chets m\u00e9nagers",
    "sg:phone":"+32 3 646 21 12",
    "sg:postcode":"2170",
    "sg:province":"Antwerpen",
    "wof:name":"Ocean Combustion Service",
    "wof:placetype":"venue"
},
  "geometry": {"coordinates":[4.4505147934,51.246723175],"type":"Point"}
}