{
  "type": "Feature",
  "properties": {
    "addr:full":"Bulskampstraat 39 Veurne West-Vlaanderen 8630",
    "addr:housenumber":"39",
    "addr:postcode":"8630",
    "addr:street":"Bulskampstraat",
    "iso:country":"BE",
    "sg:address":"Bulskampstraat 39",
    "sg:city":"Veurne",
    "sg:classifiers":[
        {
            "category":"Health Services",
            "subcategory":"Nursing And Care Facility",
            "type":"Services"
        }
    ],
    "sg:phone":"+32 58 31 31 67",
    "sg:postcode":"8630",
    "sg:province":"West-Vlaanderen",
    "sg:tags":[
        "home",
        "rest"
    ],
    "wof:name":"Sint Anna Voorzieningen Voor Ouderenzorg",
    "wof:placetype":"venue"
},
  "geometry": {"coordinates":[2.6489899158,51.0528793335],"type":"Point"}
}