{
  "type": "Feature",
  "properties": {
    "addr:full":"Maastrichtersteenweg 358 Tongeren Limburg 3700",
    "addr:housenumber":"358",
    "addr:postcode":"3700",
    "addr:street":"Maastrichtersteenweg",
    "iso:country":"BE",
    "sg:address":"Maastrichtersteenweg 358",
    "sg:city":"Tongeren",
    "sg:orig_category":"Autombile concessionaires",
    "sg:phone":"+32 12 39 12 73",
    "sg:postcode":"3700",
    "sg:province":"Limburg",
    "wof:name":"Gar Botta",
    "wof:placetype":"venue"
},
  "geometry": {"coordinates":[5.5269751549,50.792640686],"type":"Point"}
}