{
  "type": "Feature",
  "properties": {
    "addr:full":"Rue De La Station 50 Ans Li\u00e8ge 4430",
    "addr:housenumber":"50",
    "addr:postcode":"4430",
    "addr:street":"Rue De La Station",
    "iso:country":"BE",
    "sg:address":"Rue De La Station 50",
    "sg:city":"Ans",
    "sg:classifiers":[
        {
            "category":"Personal",
            "subcategory":"Beauty Salon",
            "type":"Services"
        }
    ],
    "sg:phone":"+32 4 263 42 23",
    "sg:postcode":"4430",
    "sg:province":"Li\u00e8ge",
    "sg:tags":[
        "de",
        "coiffure"
    ],
    "wof:name":"Coiffure Lucine",
    "wof:placetype":"venue"
},
  "geometry": {"coordinates":[5.5102910995,50.6622772217],"type":"Point"}
}