{
  "type": "Feature",
  "properties": {
    "addr:full":"Rue F\u00e9lix Defays 1 Pepinster Li\u00e8ge 4860",
    "addr:housenumber":"1",
    "addr:postcode":"4860",
    "addr:street":"Rue Fe\u0301Lix Defays",
    "iso:country":"BE",
    "sg:address":"Rue F\u00e9lix Defays 1",
    "sg:city":"Pepinster",
    "sg:classifiers":[
        {
            "category":"Health Services",
            "subcategory":"Doctor",
            "type":"Services"
        }
    ],
    "sg:phone":"+32 87 22 40 40",
    "sg:postcode":"4860",
    "sg:province":"Li\u00e8ge",
    "sg:tags":[
        "medicinephysicians",
        "surgeon"
    ],
    "wof:name":"Gilliquet Anne",
    "wof:placetype":"venue"
},
  "geometry": {"coordinates":[5.8029098511,50.5646514893],"type":"Point"}
}