{
  "type": "Feature",
  "properties": {
    "addr:full":"Heerstraat 17bb Kortenaken Vlaams-Brabant 3470",
    "addr:housenumber":"17bb",
    "addr:postcode":"3470",
    "addr:street":"Heerstraat",
    "iso:country":"BE",
    "sg:address":"Heerstraat 17bb",
    "sg:city":"Kortenaken",
    "sg:orig_category":"Fruitteelt Varkenskwekers",
    "sg:phone":"+32 11 58 96 53",
    "sg:postcode":"3470",
    "sg:province":"Vlaams-Brabant",
    "wof:name":"Paul Beelen",
    "wof:placetype":"venue"
},
  "geometry": {"coordinates":[5.0560088158,50.8991470337],"type":"Point"}
}