{
  "type": "Feature",
  "properties": {
    "addr:full":"Lenniksestraat 97 Gooik (groot) Vlaams-Brabant 1755",
    "addr:housenumber":"97",
    "addr:postcode":"1755",
    "addr:street":"Lenniksestraat;Groot Vlaams-Brabant",
    "iso:country":"BE",
    "sg:address":"Lenniksestraat 97",
    "sg:city":"Gooik (groot)",
    "sg:orig_category":"Benzinestations and brandstoffen Herstellingen and onderhoud van auto's Voertuigen",
    "sg:phone":"+32 54 56 60 01",
    "sg:postcode":"1755",
    "sg:province":"Vlaams-Brabant",
    "wof:name":"Garage Bogemans",
    "wof:placetype":"venue"
},
  "geometry": {"coordinates":[4.0880727768,50.7783737183],"type":"Point"}
}