{
  "type": "Feature",
  "properties": {
    "iso:country":"BE",
    "sg:address":"Leuvensestraat 48",
    "sg:city":"Diest",
    "sg:classifiers":[
        {
            "category":"Recreation",
            "subcategory":"Gun Range",
            "type":"Entertainment"
        }
    ],
    "sg:phone":"+32 13 33 36 26",
    "sg:postcode":"3290",
    "sg:province":"Vlaams-Brabant",
    "sg:tags":[
        "ammunition",
        "-",
        "retail"
    ],
    "wof:name":"Topgun",
    "wof:placetype":"venue"
},
  "geometry": {"coordinates":[5.0501041412,50.9821090698],"type":"Point"}
}