{
  "type": "Feature",
  "properties": {
    "iso:country":"BE",
    "sg:address":"Vriesenhof 3b3",
    "sg:city":"Leuven",
    "sg:orig_category":"Diverse grafische activiteiten",
    "sg:phone":"+32 16 20 26 92",
    "sg:postcode":"3000",
    "sg:province":"Vlaams-Brabant",
    "wof:name":"Bureau Jeroen",
    "wof:placetype":"venue"
},
  "geometry": {"coordinates":[4.6926851273,50.8816680908],"type":"Point"}
}