{
  "type": "Feature",
  "properties": {
    "addr:full":"Warandestraat 97 Turnhout Antwerpen 2300",
    "addr:housenumber":"97",
    "addr:postcode":"2300",
    "addr:street":"Warandestraat",
    "iso:country":"BE",
    "sg:address":"Warandestraat 97",
    "sg:city":"Turnhout",
    "sg:orig_category":"Souvenirs and objets artisanaux",
    "sg:phone":"+32 14 42 15 13",
    "sg:postcode":"2300",
    "sg:province":"Antwerpen",
    "wof:name":"De Banier",
    "wof:placetype":"venue"
},
  "geometry": {"coordinates":[4.9406890869,51.3240852356],"type":"Point"}
}