{
  "type": "Feature",
  "properties": {
    "iso:country":"BE",
    "sg:address":"Rue Saint-jean 28",
    "sg:city":"Tournai",
    "sg:classifiers":[
        {
            "category":"Bars & Pubs",
            "type":"Food & Drink"
        }
    ],
    "sg:phone":"+32 69 22 68 78",
    "sg:postcode":"7500",
    "sg:province":"Hainaut",
    "wof:name":"Petit St Jean (du)",
    "wof:placetype":"venue"
},
  "geometry": {"coordinates":[3.3996698856,50.6055488586],"type":"Point"}
}