{
  "type": "Feature",
  "properties": {
    "iso:country":"BE",
    "sg:address":"Bloemenstraat 23b2",
    "sg:city":"Hasselt",
    "sg:classifiers":[
        {
            "category":"Arena",
            "subcategory":"Sports Club",
            "type":"Entertainment"
        }
    ],
    "sg:phone":"+32 11 28 55 43",
    "sg:postcode":"3500",
    "sg:province":"Limburg",
    "sg:tags":[
        "de"
    ],
    "wof:name":"Eeuwig Jong Vleugt",
    "wof:placetype":"venue"
},
  "geometry": {"coordinates":[5.334318161,50.9242172241],"type":"Point"}
}