{
  "type": "Feature",
  "properties": {
    "iso:country":"BE",
    "sg:address":"Bierbeekstraat 139",
    "sg:city":"Bierbeek",
    "sg:orig_category":"Boekbinderijen and afwerking",
    "sg:phone":"+32 16 46 23 19",
    "sg:postcode":"3360",
    "sg:province":"Vlaams-Brabant",
    "wof:name":"Atelier Kaftwerk",
    "wof:placetype":"venue"
},
  "geometry": {"coordinates":[4.7610311508,50.8530883789],"type":"Point"}
}