{
  "type": "Feature",
  "properties": {
    "addr:full":"Groenestraat 84 Alveringem West-Vlaanderen 8691",
    "addr:housenumber":"84",
    "addr:postcode":"8691",
    "addr:street":"Groenestraat",
    "iso:country":"BE",
    "sg:address":"Groenestraat 84",
    "sg:city":"Alveringem",
    "sg:orig_category":"RESTAURANTS: LIVRAISON \u00c0 DOMICILE. RESTAURANTS",
    "sg:phone":"+32 58 29 81 67",
    "sg:postcode":"8691",
    "sg:province":"West-Vlaanderen",
    "wof:name":"Bachten Ten Kupe",
    "wof:placetype":"venue"
},
  "geometry": {"coordinates":[2.6652519703,50.9701004028],"type":"Point"}
}