{
  "type": "Feature",
  "properties": {
    "iso:country":"BE",
    "sg:address":"Baan Naar Bree 71",
    "sg:city":"Peer",
    "sg:orig_category":"Herstellingen and onderhoud van auto's Voertuigen",
    "sg:phone":"+32 11 63 16 62",
    "sg:postcode":"3990",
    "sg:province":"Limburg",
    "wof:name":"Garage Ulenaers",
    "wof:placetype":"venue"
},
  "geometry": {"coordinates":[5.4683208466,51.1329498291],"type":"Point"}
}