{
  "type": "Feature",
  "properties": {
    "iso:country":"BE",
    "sg:address":"Avenue Louise 521",
    "sg:city":"Bruxelles",
    "sg:classifiers":[
        {
            "category":"Professional",
            "subcategory":"Employment Agencies",
            "type":"Services"
        }
    ],
    "sg:phone":"+32 2 600 70 00",
    "sg:postcode":"1050",
    "sg:province":"Bruxelles-Capitale",
    "sg:tags":[
        "personnel",
        "temporary"
    ],
    "wof:name":"Unique Interim S.a.",
    "wof:placetype":"venue"
},
  "geometry": {"coordinates":[4.3717918396,50.8154830933],"type":"Point"}
}