{
  "type": "Feature",
  "properties": {
    "addr:full":"Hooghofstraat 28 Heuvelland West-Vlaanderen 8952",
    "addr:housenumber":"28",
    "addr:postcode":"8952",
    "addr:street":"Hooghofstraat",
    "iso:country":"BE",
    "sg:address":"Hooghofstraat 28",
    "sg:city":"Heuvelland",
    "sg:orig_category":"Rundveehouders Varkenskwekers",
    "sg:phone":"+32 57 44 47 65",
    "sg:postcode":"8952",
    "sg:province":"West-Vlaanderen",
    "wof:name":"Georges Pyck",
    "wof:placetype":"venue"
},
  "geometry": {"coordinates":[2.8456640244,50.7635269165],"type":"Point"}
}