{
  "type": "Feature",
  "properties": {
    "addr:full":"Weeldestraat 160 Ravels Antwerpen 2381",
    "addr:housenumber":"160",
    "addr:postcode":"2381",
    "addr:street":"Weeldestraat",
    "iso:country":"BE",
    "sg:address":"Weeldestraat 160",
    "sg:city":"Ravels",
    "sg:classifiers":[
        {
            "category":"Cafe",
            "type":"Food & Drink"
        }
    ],
    "sg:phone":"+32 14 65 81 12",
    "sg:postcode":"2381",
    "sg:province":"Antwerpen",
    "sg:tags":[
        "caf\u00e9s"
    ],
    "wof:name":"Andreas Leemans",
    "wof:placetype":"venue"
},
  "geometry": {"coordinates":[5.006374836,51.4099845886],"type":"Point"}
}