{
  "type": "Feature",
  "properties": {
    "iso:country":"BE",
    "sg:address":"Heidestraat 23",
    "sg:city":"Ternat (sint-katherina-lombeek)",
    "sg:classifiers":[
        {
            "category":"Retail",
            "subcategory":"Repair Shop",
            "type":"Services"
        }
    ],
    "sg:phone":"+32 2 582 72 93",
    "sg:postcode":"1742",
    "sg:province":"Vlaams-Brabant",
    "sg:tags":[
        "machine",
        "sewing",
        "-"
    ],
    "wof:name":"Roosens R",
    "wof:placetype":"venue"
},
  "geometry": {"coordinates":[4.1464810371,50.8711357117],"type":"Point"}
}