{
  "type": "Feature",
  "properties": {
    "iso:country":"BE",
    "sg:address":"Rue Des Preys 200",
    "sg:city":"Charleroi (montignies-sur-sambre)",
    "sg:classifiers":[
        {
            "category":"Building & Trades",
            "subcategory":"Construction",
            "type":"Services"
        }
    ],
    "sg:phone":"+32 71 31 53 69",
    "sg:postcode":"6061",
    "sg:province":"Hainaut",
    "sg:tags":[
        "carpenter"
    ],
    "wof:name":"Delhomme E & N",
    "wof:placetype":"venue"
},
  "geometry": {"coordinates":[4.4868388176,50.4047889709],"type":"Point"}
}