{
  "type": "Feature",
  "properties": {
    "iso:country":"BE",
    "sg:address":"Rue De La Station 73",
    "sg:city":"Anderlues",
    "sg:orig_category":"Pain, p\u00e2tisseries and confiseries",
    "sg:phone":"+32 71 52 39 23",
    "sg:postcode":"6150",
    "sg:province":"Hainaut",
    "wof:name":"Laurent Maene",
    "wof:placetype":"venue"
},
  "geometry": {"coordinates":[4.2823967934,50.4000854492],"type":"Point"}
}