{
  "type": "Feature",
  "properties": {
    "addr:full":"Rue Alsaut 25 Farciennes Hainaut 6240",
    "addr:housenumber":"25",
    "addr:postcode":"6240",
    "addr:street":"Rue Alsaut",
    "iso:country":"BE",
    "sg:address":"Rue Alsaut 25",
    "sg:city":"Farciennes",
    "sg:orig_category":"Kapsalons Mobiele kappers",
    "sg:phone":"+32 71 40 37 63",
    "sg:postcode":"6240",
    "sg:province":"Hainaut",
    "wof:name":"Ga\u00cbtane Puelinckx",
    "wof:placetype":"venue"
},
  "geometry": {"coordinates":[4.5555791855,50.4268875122],"type":"Point"}
}