{
  "type": "Feature",
  "properties": {
    "iso:country":"BE",
    "sg:address":"Mechelsestraat 25",
    "sg:city":"Lier",
    "sg:orig_category":"Enseignement maternel and primaire",
    "sg:phone":"+32 3 480 80 37",
    "sg:postcode":"2500",
    "sg:province":"Antwerpen",
    "wof:name":"Vrije Kleuterschool",
    "wof:placetype":"venue"
},
  "geometry": {"coordinates":[4.564098835,51.1310844421],"type":"Point"}
}