{
  "type": "Feature",
  "properties": {
    "addr:full":"Lossestraat 7 Pepingen Vlaams-Brabant 1670",
    "addr:housenumber":"7",
    "addr:postcode":"1670",
    "addr:street":"Lossestraat",
    "iso:country":"BE",
    "sg:address":"Lossestraat 7",
    "sg:city":"Pepingen",
    "sg:orig_category":"Varkenskwekers",
    "sg:phone":"+32 2 532 50 74",
    "sg:postcode":"1670",
    "sg:province":"Vlaams-Brabant",
    "wof:name":"Prosper Geerts",
    "wof:placetype":"venue"
},
  "geometry": {"coordinates":[4.1566710472,50.7702522278],"type":"Point"}
}