{
  "type": "Feature",
  "properties": {
    "iso:country":"BE",
    "sg:address":"Rue Plein Harenq 34",
    "sg:city":"Herstal",
    "sg:classifiers":[
        {
            "category":"Building & Trades",
            "subcategory":"Electrical",
            "type":"Services"
        }
    ],
    "sg:phone":"+32 477 28 49 32",
    "sg:postcode":"4040",
    "sg:province":"Li\u00e8ge",
    "sg:tags":[
        "electric",
        "-",
        "housewiring",
        "contractor"
    ],
    "wof:name":"Befra Elec",
    "wof:placetype":"venue"
},
  "geometry": {"coordinates":[5.5997600555,50.6791114807],"type":"Point"}
}