{
  "type": "Feature",
  "properties": {
    "addr:full":"Sint-jansberg 32 Maaseik Limburg 3680",
    "addr:housenumber":"32",
    "addr:postcode":"3680",
    "addr:street":"Sint-Jansberg",
    "iso:country":"BE",
    "sg:address":"Sint-jansberg 32",
    "sg:city":"Maaseik",
    "sg:orig_category":"Instituts de beaut\u00e9",
    "sg:phone":"+32 89 56 57 62",
    "sg:postcode":"3680",
    "sg:province":"Limburg",
    "wof:name":"Pedicure Corstjens",
    "wof:placetype":"venue"
},
  "geometry": {"coordinates":[5.7827620506,51.1070594788],"type":"Point"}
}