{
  "type": "Feature",
  "properties": {
    "addr:full":"Fonteinstraat 48 Leuven Vlaams-Brabant 3000",
    "addr:housenumber":"48",
    "addr:postcode":"3000",
    "addr:street":"Fonteinstraat",
    "iso:country":"BE",
    "sg:address":"Fonteinstraat 48",
    "sg:city":"Leuven",
    "sg:orig_category":"Non-Classified Establishments",
    "sg:phone":"+32 16 22 84 37",
    "sg:postcode":"3000",
    "sg:province":"Vlaams-Brabant",
    "wof:name":"Auto Lux A.m.v.",
    "wof:placetype":"venue"
},
  "geometry": {"coordinates":[4.6943669319,50.8861694336],"type":"Point"}
}