{
  "type": "Feature",
  "properties": {
    "addr:full":"Treurwilgenlaan 10 Overijse Vlaams-Brabant 3090",
    "addr:housenumber":"10",
    "addr:postcode":"3090",
    "addr:street":"Treurwilgenlaan",
    "iso:country":"BE",
    "sg:address":"Treurwilgenlaan 10",
    "sg:city":"Overijse",
    "sg:classifiers":[
        {
            "category":"Professional",
            "subcategory":"Management & Consulting",
            "type":"Services"
        }
    ],
    "sg:phone":"+32 2 657 55 45",
    "sg:postcode":"3090",
    "sg:province":"Vlaams-Brabant",
    "sg:tags":[
        "consultant"
    ],
    "wof:name":"Riskovery Consult Bvba",
    "wof:placetype":"venue"
},
  "geometry": {"coordinates":[4.4845018387,50.788646698],"type":"Point"}
}