{
  "type": "Feature",
  "properties": {
    "iso:country":"BE",
    "sg:address":"Kleine Dries 6",
    "sg:city":"Diksmuide",
    "sg:orig_category":"Graanmeel Fab",
    "sg:phone":"+32 51 50 08 01",
    "sg:postcode":"8600",
    "sg:province":"West-Vlaanderen",
    "wof:name":"Bloemmolens Van Diksmuide",
    "wof:placetype":"venue"
},
  "geometry": {"coordinates":[2.8573000431,51.0185966492],"type":"Point"}
}