{
  "type": "Feature",
  "properties": {
    "addr:full":"Vierentwintigste Liniestraat 6 Houthulst West-Vlaanderen 8650",
    "addr:housenumber":"6",
    "addr:postcode":"8650",
    "addr:street":"Vierentwintigste Liniestraat",
    "iso:country":"BE",
    "sg:address":"Vierentwintigste Liniestraat 6",
    "sg:city":"Houthulst",
    "sg:classifiers":[
        {
            "category":"Professional",
            "subcategory":"Lawyer & Legal Services",
            "type":"Services"
        }
    ],
    "sg:phone":"+32 51 70 27 01",
    "sg:postcode":"8650",
    "sg:province":"West-Vlaanderen",
    "wof:name":"Crombez Didier",
    "wof:placetype":"venue"
},
  "geometry": {"coordinates":[2.9529590607,50.9841690063],"type":"Point"}
}