{
  "type": "Feature",
  "properties": {
    "iso:country":"BE",
    "sg:address":"Steenweg Op Oosthoven 92",
    "sg:city":"Turnhout",
    "sg:classifiers":[
        {
            "category":"Personal",
            "subcategory":"Nail Salon",
            "type":"Services"
        }
    ],
    "sg:phone":"+32 14 41 18 93",
    "sg:postcode":"2300",
    "sg:province":"Antwerpen",
    "sg:tags":[
        "pedicure"
    ],
    "wof:name":"Van Horebeek Y",
    "wof:placetype":"venue"
},
  "geometry": {"coordinates":[4.9536218643,51.330242157],"type":"Point"}
}