{
  "type": "Feature",
  "properties": {
    "iso:country":"BE",
    "sg:address":"Genkerbaan 122",
    "sg:city":"Zonhoven",
    "sg:classifiers":[
        {
            "category":"Building & Trades",
            "subcategory":"Construction",
            "type":"Services"
        }
    ],
    "sg:phone":"+32 11 81 84 20",
    "sg:postcode":"3520",
    "sg:province":"Limburg",
    "sg:tags":[
        "carpenter"
    ],
    "wof:name":"Timmermans Interieurbouw Bvba",
    "wof:placetype":"venue"
},
  "geometry": {"coordinates":[5.3792128563,50.9915962219],"type":"Point"}
}