{
  "type": "Feature",
  "properties": {
    "iso:country":"BE",
    "sg:address":"Rue De Lenny 7",
    "sg:city":"Hamois (natoye)",
    "sg:classifiers":[
        {
            "category":"Real Estate",
            "subcategory":"Surveying",
            "type":"Services"
        }
    ],
    "sg:phone":"+32 83 21 44 94",
    "sg:postcode":"5360",
    "sg:province":"Namur",
    "sg:tags":[
        "surveyor",
        "land"
    ],
    "wof:name":"Binam\u00e9 Ph",
    "wof:placetype":"venue"
},
  "geometry": {"coordinates":[5.0605092049,50.3349266052],"type":"Point"}
}