{
  "type": "Feature",
  "properties": {
    "addr:full":"Kortrijksesteenweg 207 Harelbeke West-Vlaanderen 8530",
    "addr:housenumber":"207",
    "addr:postcode":"8530",
    "addr:street":"Kortrijksesteenweg",
    "iso:country":"BE",
    "sg:address":"Kortrijksesteenweg 207",
    "sg:city":"Harelbeke",
    "sg:classifiers":[
        {
            "category":"Shopping",
            "subcategory":"Crafts & Fabrics",
            "type":"Retail Goods"
        }
    ],
    "sg:phone":"+32 56 71 43 01",
    "sg:postcode":"8530",
    "sg:province":"West-Vlaanderen",
    "sg:tags":[
        "needlework",
        "lady"
    ],
    "wof:name":"Patchwork Studio",
    "wof:placetype":"venue"
},
  "geometry": {"coordinates":[3.2970130444,50.8463668823],"type":"Point"}
}