{
  "type": "Feature",
  "properties": {
    "addr:full":"Leopoldplein 39-41 Lier Antwerpen 2500",
    "addr:postcode":"39-41;2500",
    "addr:street":"Leopoldplein",
    "iso:country":"BE",
    "sg:address":"Leopoldplein 39-41",
    "sg:city":"Lier",
    "sg:classifiers":[
        {
            "category":"Travel",
            "subcategory":"Hotels & Motels",
            "type":"Entertainment"
        }
    ],
    "sg:phone":"+32 3 480 03 10",
    "sg:postcode":"2500",
    "sg:province":"Antwerpen",
    "wof:name":"Handelshof",
    "wof:placetype":"venue"
},
  "geometry": {"coordinates":[4.5622200966,51.1354064941],"type":"Point"}
}