{
  "type": "Feature",
  "properties": {
    "addr:full":"Nati\u00ebnlaan 161 Knokke-heist (knokke) West-Vlaanderen 8300",
    "addr:housenumber":"161",
    "addr:postcode":"8300",
    "addr:street":"Natie\u0308Nlaan",
    "iso:country":"BE",
    "sg:address":"Nati\u00ebnlaan 161",
    "sg:city":"Knokke-heist (knokke)",
    "sg:classifiers":[
        {
            "category":"Home & Garden",
            "subcategory":"Household Appliances",
            "type":"Retail Goods"
        }
    ],
    "sg:phone":"+32 50 61 54 49",
    "sg:postcode":"8300",
    "sg:province":"West-Vlaanderen",
    "sg:tags":[
        "heating",
        "apparatus"
    ],
    "wof:name":"El Solar",
    "wof:placetype":"venue"
},
  "geometry": {"coordinates":[3.2890501022,51.3361816406],"type":"Point"}
}