{
  "type": "Feature",
  "properties": {
    "addr:full":"Seringenlaan 7 Rumst Antwerpen 2840",
    "addr:housenumber":"7",
    "addr:postcode":"2840",
    "addr:street":"Seringenlaan",
    "iso:country":"BE",
    "sg:address":"Seringenlaan 7",
    "sg:city":"Rumst",
    "sg:orig_category":"Slagers",
    "sg:phone":"+32 3 888 04 03",
    "sg:postcode":"2840",
    "sg:province":"Antwerpen",
    "wof:name":"Dirk D'haese",
    "wof:placetype":"venue"
},
  "geometry": {"coordinates":[4.3897018433,51.1077728271],"type":"Point"}
}