{
  "type": "Feature",
  "properties": {
    "iso:country":"BE",
    "sg:address":"Koopcentrum Waasland",
    "sg:city":"Sint-niklaas",
    "sg:orig_category":"Disquaires. Videosquare and Extrazone",
    "sg:phone":"+32 3 766 63 81",
    "sg:postcode":"9100",
    "sg:province":"Oost-Vlaanderen",
    "wof:name":"Extrazone Sint-niklaas",
    "wof:placetype":"venue"
},
  "geometry": {"coordinates":[4.1582250595,51.1524238586],"type":"Point"}
}