{
  "type": "Feature",
  "properties": {
    "addr:full":"Nederwijk Oost 279 Ninove Oost-Vlaanderen 9400",
    "addr:housenumber":"279",
    "addr:postcode":"9400",
    "addr:street":"Nederwijk Oost",
    "iso:country":"BE",
    "sg:address":"Nederwijk Oost 279",
    "sg:city":"Ninove",
    "sg:classifiers":[
        {
            "category":"Home & Garden",
            "subcategory":"Carpets & Floor Coverings",
            "type":"Retail Goods"
        }
    ],
    "sg:phone":"+32 54 33 45 11",
    "sg:postcode":"9400",
    "sg:province":"Oost-Vlaanderen",
    "sg:tags":[
        "prefab",
        "element"
    ],
    "wof:name":"Megaton Nv",
    "wof:placetype":"venue"
},
  "geometry": {"coordinates":[4.0454211235,50.8418693542],"type":"Point"}
}