{
  "type": "Feature",
  "properties": {
    "iso:country":"BE",
    "sg:address":"Nijverheidsstraat 14",
    "sg:city":"Poperinge",
    "sg:orig_category":"Non-Classified Establishments",
    "sg:phone":"+32 57 33 45 01",
    "sg:postcode":"8970",
    "sg:province":"West-Vlaanderen",
    "wof:name":"Boone Nv",
    "wof:placetype":"venue"
},
  "geometry": {"coordinates":[2.7364358902,50.8514671326],"type":"Point"}
}