{
  "type": "Feature",
  "properties": {
    "iso:country":"BE",
    "sg:address":"Egemsesteenweg 59",
    "sg:city":"Tielt",
    "sg:orig_category":"IJzerwaren, bouw- and verfmaterialen Installatie van houten of kunststof schrijnwerk Tuinbenodigdhed",
    "sg:phone":"+32 51 40 17 78",
    "sg:postcode":"8700",
    "sg:province":"West-Vlaanderen",
    "wof:name":"G Defreyne En Zoon",
    "wof:placetype":"venue"
},
  "geometry": {"coordinates":[3.304680109,51.0018768311],"type":"Point"}
}