{
  "type": "Feature",
  "properties": {
    "iso:country":"BE",
    "sg:address":"Rue Notre Seigneur 11",
    "sg:city":"Brussel",
    "sg:orig_category":"Agences d'exp\u00e9dition",
    "sg:phone":"+32 2 512 11 45",
    "sg:postcode":"1000",
    "sg:province":"Bruxelles-Capitale",
    "wof:name":"Medigral",
    "wof:placetype":"venue"
},
  "geometry": {"coordinates":[4.3494939804,50.8405799866],"type":"Point"}
}