{
  "type": "Feature",
  "properties": {
    "iso:country":"BE",
    "sg:address":"Chauss\u00c9e De Waterloo 1178",
    "sg:city":"Ukkel",
    "sg:orig_category":"Meubles Fab. Meubles D\u00e9taillants, Am\u00e9nagement de B\u00e2timents et de Cuisines",
    "sg:phone":"+32 2 374 88 33",
    "sg:postcode":"1180",
    "sg:province":"Bruxelles-Capitale",
    "wof:name":"Les As Du Placard",
    "wof:placetype":"venue"
},
  "geometry": {"coordinates":[4.3736848831,50.7954063416],"type":"Point"}
}