{
  "type": "Feature",
  "properties": {
    "iso:country":"BE",
    "sg:address":"Grand'rue 235",
    "sg:city":"Trooz",
    "sg:orig_category":"Journaux. Tabac",
    "sg:phone":"+32 4 351 75 18",
    "sg:postcode":"4870",
    "sg:province":"Li\u00e8ge",
    "wof:name":"Librairie Van Damme",
    "wof:placetype":"venue"
},
  "geometry": {"coordinates":[5.6895260811,50.5719566345],"type":"Point"}
}