{
  "type": "Feature",
  "properties": {
    "addr:full":"Kerkstraat 46 Rumst Antwerpen 2840",
    "addr:housenumber":"46",
    "addr:postcode":"2840",
    "addr:street":"Kerkstraat",
    "iso:country":"BE",
    "sg:address":"Kerkstraat 46",
    "sg:city":"Rumst",
    "sg:classifiers":[
        {
            "category":"Health Services",
            "subcategory":"Doctor",
            "type":"Services"
        }
    ],
    "sg:phone":"+32 3 888 04 40",
    "sg:postcode":"2840",
    "sg:province":"Antwerpen",
    "sg:tags":[
        "medicinephysicians",
        "surgeon"
    ],
    "wof:name":"De Backer Luc",
    "wof:placetype":"venue"
},
  "geometry": {"coordinates":[4.4288878441,51.0782394409],"type":"Point"}
}