{
  "type": "Feature",
  "properties": {
    "iso:country":"BE",
    "sg:address":"Kerkeneind 1",
    "sg:city":"Essen",
    "sg:orig_category":"Overheidsdiensten",
    "sg:phone":"+32 3 667 60 38",
    "sg:postcode":"2910",
    "sg:province":"Antwerpen",
    "wof:name":"O.c.m.w.",
    "wof:placetype":"venue"
},
  "geometry": {"coordinates":[4.4686121941,51.4676551819],"type":"Point"}
}