{
  "type": "Feature",
  "properties": {
    "addr:full":"Liersesteenweg 267 Heist-op-den-berg Antwerpen 2220",
    "addr:housenumber":"267",
    "addr:postcode":"2220",
    "addr:street":"Liersesteenweg",
    "iso:country":"BE",
    "sg:address":"Liersesteenweg 267",
    "sg:city":"Heist-op-den-berg",
    "sg:orig_category":"Artsen and specialisten",
    "sg:phone":"+32 15 25 89 11",
    "sg:postcode":"2220",
    "sg:province":"Antwerpen",
    "wof:name":"Somedi",
    "wof:placetype":"venue"
},
  "geometry": {"coordinates":[4.694644928,51.069732666],"type":"Point"}
}