{
  "type": "Feature",
  "properties": {
    "addr:full":"Gravestraat 9a Wingene West-Vlaanderen 8750",
    "addr:housenumber":"9a",
    "addr:postcode":"8750",
    "addr:street":"Gravestraat",
    "iso:country":"BE",
    "sg:address":"Gravestraat 9a",
    "sg:city":"Wingene",
    "sg:classifiers":[
        {
            "category":"Home & Garden",
            "subcategory":"Building Materials",
            "type":"Retail Goods"
        }
    ],
    "sg:phone":"+32 51 65 63 73",
    "sg:postcode":"8750",
    "sg:province":"West-Vlaanderen",
    "sg:tags":[
        "aluminium",
        "construction",
        "-"
    ],
    "wof:name":"Aluhavan Bvba",
    "wof:placetype":"venue"
},
  "geometry": {"coordinates":[3.2950000763,51.0813522339],"type":"Point"}
}