{
  "type": "Feature",
  "properties": {
    "addr:full":"Rue Ainseveau 44 Viroinval Namur 5670",
    "addr:housenumber":"44",
    "addr:postcode":"5670",
    "addr:street":"Rue Ainseveau",
    "iso:country":"BE",
    "sg:address":"Rue Ainseveau 44",
    "sg:city":"Viroinval",
    "sg:classifiers":[
        {
            "category":"Health Services",
            "subcategory":"Nursing And Care Facility",
            "type":"Services"
        }
    ],
    "sg:phone":"+32 60 31 24 90",
    "sg:postcode":"5670",
    "sg:province":"Namur",
    "sg:tags":[
        "public"
    ],
    "wof:name":"C.p.a.s.",
    "wof:placetype":"venue"
},
  "geometry": {"coordinates":[4.5448141098,50.0749473572],"type":"Point"}
}