{
  "type": "Feature",
  "properties": {
    "iso:country":"BE",
    "sg:address":"Stuurstraat 29",
    "sg:city":"Beveren",
    "sg:orig_category":"M\u00e9decins and sp\u00e9cialistes",
    "sg:phone":"+32 3 775 89 60",
    "sg:postcode":"9120",
    "sg:province":"Oost-Vlaanderen",
    "wof:name":"Luc Geerinckx",
    "wof:placetype":"venue"
},
  "geometry": {"coordinates":[4.2293829918,51.1881065369],"type":"Point"}
}