{
  "type": "Feature",
  "properties": {
    "addr:full":"Scheepswerfstr 7 Baasrode 9350",
    "addr:housenumber":"7",
    "addr:postcode":"9350",
    "addr:street":"Scheepswerfstr",
    "iso:country":"BE",
    "sg:address":"Scheepswerfstr 7",
    "sg:city":"Baasrode",
    "sg:classifiers":[
        {
            "category":"Banks & Credit Unions",
            "subcategory":"Bank",
            "type":"Services"
        }
    ],
    "sg:phone":"+32 52 33 60 20",
    "sg:postcode":"9350",
    "wof:name":"Krediet Nuverheid",
    "wof:placetype":"venue"
},
  "geometry": {"coordinates":[168.3840637207,-44.849861145],"type":"Point"}
}