{
  "type": "Feature",
  "properties": {
    "iso:country":"BE",
    "sg:address":"Rue Des D\u00e9port\u00e9s 149",
    "sg:city":"Jurbise (masnuy-saint-jean)",
    "sg:classifiers":[
        {
            "category":"Retail",
            "subcategory":"Event Space",
            "type":"Services"
        }
    ],
    "sg:phone":"+32 65 22 61 21",
    "sg:postcode":"7050",
    "sg:province":"Hainaut",
    "sg:tags":[
        "rental",
        "-",
        "hall"
    ],
    "wof:name":"Brocqueroy (salle Du)",
    "wof:placetype":"venue"
},
  "geometry": {"coordinates":[3.9499249458,50.5095291138],"type":"Point"}
}