{
  "type": "Feature",
  "properties": {
    "iso:country":"BE",
    "sg:address":"Rue Des Egyptiens 1",
    "sg:city":"Elsene/ixelles",
    "sg:orig_category":"Editeurs de livres",
    "sg:phone":"+32 2 649 33 23",
    "sg:postcode":"1050",
    "sg:province":"Bruxelles-Capitale",
    "wof:name":"Kara H.-petit Fr.",
    "wof:placetype":"venue"
},
  "geometry": {"coordinates":[4.3896741867,50.8146247864],"type":"Point"}
}