{
  "type": "Feature",
  "properties": {
    "iso:country":"BE",
    "sg:address":"Lampernissestraat 12",
    "sg:city":"Ardooie",
    "sg:classifiers":[
        {
            "category":"Farming",
            "subcategory":"Livestock Farm",
            "type":"Manufacturing & Wholesale Goods"
        }
    ],
    "sg:phone":"+32 51 74 62 43",
    "sg:postcode":"8850",
    "sg:province":"West-Vlaanderen",
    "sg:tags":[
        "breeding"
    ],
    "wof:name":"Arkova",
    "wof:placetype":"venue"
},
  "geometry": {"coordinates":[3.1984419823,50.9922103882],"type":"Point"}
}