{
  "type": "Feature",
  "properties": {
    "iso:country":"BE",
    "sg:address":"Rue Du Gay-village 12bb",
    "sg:city":"Li\u00c8ge",
    "sg:orig_category":"Sportterreinen and installaties behalve sportcentra",
    "sg:phone":"+32 4 377 67 17",
    "sg:postcode":"4020",
    "sg:province":"Li\u00e8ge",
    "wof:name":"Sokali\u00c8ge",
    "wof:placetype":"venue"
},
  "geometry": {"coordinates":[5.6265859604,50.6504516602],"type":"Point"}
}