{
  "type": "Feature",
  "properties": {
    "iso:country":"BE",
    "sg:address":"Berkenenstraat 45ba",
    "sg:city":"Zonhoven",
    "sg:orig_category":"Traitements param\u00e9dicaux",
    "sg:phone":"+32 11 81 10 91",
    "sg:postcode":"3520",
    "sg:province":"Limburg",
    "wof:name":"L. Vaes",
    "wof:placetype":"venue"
},
  "geometry": {"coordinates":[5.381070137,51.0053367615],"type":"Point"}
}