{
  "type": "Feature",
  "properties": {
    "addr:full":"Rue Cervant\u00e8s 47 Bruxelles (forest) Bruxelles-Capitale 1190",
    "addr:housenumber":"47",
    "addr:postcode":"1190",
    "addr:street":"Rue Cervante\u0300S",
    "iso:country":"BE",
    "sg:address":"Rue Cervant\u00e8s 47",
    "sg:city":"Bruxelles (forest)",
    "sg:classifiers":[
        {
            "category":"Health Services",
            "subcategory":"Doctor",
            "type":"Services"
        }
    ],
    "sg:phone":"+32 2 346 12 93",
    "sg:postcode":"1190",
    "sg:province":"Bruxelles-Capitale",
    "sg:tags":[
        "medicinephysicians",
        "surgeon"
    ],
    "wof:name":"Friedmann Georges",
    "wof:placetype":"venue"
},
  "geometry": {"coordinates":[4.3383898735,50.8180198669],"type":"Point"}
}