{
  "type": "Feature",
  "properties": {
    "iso:country":"BE",
    "sg:address":"Sint-quentinstraat 21",
    "sg:city":"Brussel/bruxelles",
    "sg:orig_category":"Woningbouw",
    "sg:phone":"+32 2 230 84 21",
    "sg:postcode":"1000",
    "sg:province":"Bruxelles-Capitale",
    "wof:name":"Fe. De Ronge Charles",
    "wof:placetype":"venue"
},
  "geometry": {"coordinates":[4.3810648918,50.8449134827],"type":"Point"}
}