{
  "type": "Feature",
  "properties": {
    "addr:full":"Impasse Desmet 1 Mons Hainaut 7000",
    "addr:housenumber":"1",
    "addr:postcode":"7000",
    "addr:street":"Impasse Desmet;Hainaut",
    "iso:country":"BE",
    "sg:address":"Impasse Desmet 1",
    "sg:city":"Mons",
    "sg:classifiers":[
        {
            "category":"Shopping Center",
            "type":"Public Place"
        }
    ],
    "sg:phone":"+32 65 33 68 86",
    "sg:postcode":"7000",
    "sg:province":"Hainaut",
    "sg:tags":[
        "enseignement",
        "formation"
    ],
    "wof:name":"Centre Form & Perf. Prof.",
    "wof:placetype":"venue"
},
  "geometry": {"coordinates":[3.9728798866,50.4535484314],"type":"Point"}
}