{
  "type": "Feature",
  "properties": {
    "addr:full":"Wassenkerkhofstraat 19 Gavere Oost-Vlaanderen 9890",
    "addr:housenumber":"19",
    "addr:postcode":"9890",
    "addr:street":"Wassenkerkhofstraat",
    "iso:country":"BE",
    "sg:address":"Wassenkerkhofstraat 19",
    "sg:city":"Gavere",
    "sg:orig_category":"Sportterreinen and installaties behalve sportcentra",
    "sg:phone":"+32 9 384 22 59",
    "sg:postcode":"9890",
    "sg:province":"Oost-Vlaanderen",
    "wof:name":"Man\u00c8ge Green Corner",
    "wof:placetype":"venue"
},
  "geometry": {"coordinates":[3.6588599682,50.9283752441],"type":"Point"}
}