{
  "type": "Feature",
  "properties": {
    "iso:country":"BE",
    "sg:address":"Rue Du Charbonnage 36",
    "sg:city":"Gr\u00e2ce-hollogne (gr\u00e2ce-berleur)",
    "sg:classifiers":[
        {
            "category":"Organizations",
            "subcategory":"Professional Association",
            "type":"Services"
        }
    ],
    "sg:phone":"+32 4 263 14 97",
    "sg:postcode":"4460",
    "sg:province":"Li\u00e8ge",
    "sg:tags":[
        "trade-union",
        "federation"
    ],
    "wof:name":"Regionali Santi Asbl",
    "wof:placetype":"venue"
},
  "geometry": {"coordinates":[5.5019330978,50.6470870972],"type":"Point"}
}