{
  "type": "Feature",
  "properties": {
    "iso:country":"BE",
    "sg:address":"Hulstplein 19",
    "sg:city":"Tielt",
    "sg:orig_category":"Epiceries",
    "sg:phone":"+32 51 40 78 30",
    "sg:postcode":"8700",
    "sg:province":"West-Vlaanderen",
    "wof:name":"The Shop",
    "wof:placetype":"venue"
},
  "geometry": {"coordinates":[3.3317730427,50.9978637695],"type":"Point"}
}