{
  "type": "Feature",
  "properties": {
    "iso:country":"BE",
    "sg:address":"Rue Du Noir Chien 10ba",
    "sg:city":"Mettet",
    "sg:orig_category":"Maisons de repos and r\u00e9sidences",
    "sg:phone":"+32 71 72 78 36",
    "sg:postcode":"5640",
    "sg:province":"Namur",
    "wof:name":"R.s.j.",
    "wof:placetype":"venue"
},
  "geometry": {"coordinates":[4.6551589966,50.3295097351],"type":"Point"}
}