{
  "type": "Feature",
  "properties": {
    "addr:full":"Hooghaag 18 Hamont-achel Limburg 3930",
    "addr:housenumber":"18",
    "addr:postcode":"3930",
    "addr:street":"Hooghaag",
    "iso:country":"BE",
    "sg:address":"Hooghaag 18",
    "sg:city":"Hamont-achel",
    "sg:orig_category":"Installation de menuiserie m\u00e9tallique. Installation de menuiserie en bois and plastique",
    "sg:phone":"+32 11 80 15 22",
    "sg:postcode":"3930",
    "sg:province":"Limburg",
    "wof:name":"Stas Veranda's",
    "wof:placetype":"venue"
},
  "geometry": {"coordinates":[5.475230217,51.2498245239],"type":"Point"}
}