{
  "type": "Feature",
  "properties": {
    "iso:country":"BE",
    "sg:address":"Sint-jacobsplein 17",
    "sg:city":"Leuven",
    "sg:classifiers":[
        {
            "category":"Education",
            "subcategory":"University",
            "type":"Public Place"
        }
    ],
    "sg:phone":"+32 16 20 36 36",
    "sg:postcode":"3000",
    "sg:province":"Vlaams-Brabant",
    "sg:tags":[
        "higher"
    ],
    "wof:name":"Memento-mementec-memodi",
    "wof:placetype":"venue"
},
  "geometry": {"coordinates":[4.6899170876,50.8796615601],"type":"Point"}
}