{
  "type": "Feature",
  "properties": {
    "iso:country":"BE",
    "sg:address":"Meir 52",
    "sg:city":"Antwerpen",
    "sg:orig_category":"Baby- and kinderkleding Dameskledingzaken Herenkledingzaken",
    "sg:phone":"+32 3 233 60 20",
    "sg:postcode":"2000",
    "sg:province":"Antwerpen",
    "wof:name":"Esprit",
    "wof:placetype":"venue"
},
  "geometry": {"coordinates":[4.409309864,51.2179718018],"type":"Point"}
}