{
  "type": "Feature",
  "properties": {
    "addr:full":"Zuidstraat 106 Veurne West-Vlaanderen 8630",
    "addr:housenumber":"106",
    "addr:postcode":"8630",
    "addr:street":"Zuidstraat",
    "iso:country":"BE",
    "sg:address":"Zuidstraat 106",
    "sg:city":"Veurne",
    "sg:classifiers":[
        {
            "category":"Banks & Credit Unions",
            "subcategory":"Investment Brokerage",
            "type":"Services"
        }
    ],
    "sg:phone":"+32 58 31 25 26",
    "sg:postcode":"8630",
    "sg:province":"West-Vlaanderen",
    "wof:name":"Debandt-bulcke",
    "wof:placetype":"venue"
},
  "geometry": {"coordinates":[2.6643400192,51.0681800842],"type":"Point"}
}