{
  "type": "Feature",
  "properties": {
    "addr:full":"Rue Des Combattants Et D\u00e9port\u00e9s 50 Thuin (thuillies) Hainaut 6536",
    "addr:housenumber":"50",
    "addr:postcode":"6536",
    "addr:street":"Rue Des Combattants Et De\u0301Porte\u0301S",
    "iso:country":"BE",
    "sg:address":"Rue Des Combattants Et D\u00e9port\u00e9s 50",
    "sg:city":"Thuin (thuillies)",
    "sg:classifiers":[
        {
            "category":"Food & Beverages",
            "subcategory":"Groceries & Convenience Stores",
            "type":"Retail Goods"
        }
    ],
    "sg:phone":"+32 71 53 31 23",
    "sg:postcode":"6536",
    "sg:province":"Hainaut",
    "sg:tags":[
        "grocer"
    ],
    "wof:name":"Werry",
    "wof:placetype":"venue"
},
  "geometry": {"coordinates":[4.3339657784,50.2962608337],"type":"Point"}
}