{
  "type": "Feature",
  "properties": {
    "iso:country":"BE",
    "sg:address":"Poederstraat 8",
    "sg:city":"Arendonk",
    "sg:classifiers":[
        {
            "category":"Building & Trades",
            "subcategory":"Construction",
            "type":"Services"
        }
    ],
    "sg:phone":"+32 14 67 21 87",
    "sg:postcode":"2370",
    "sg:province":"Antwerpen",
    "sg:tags":[
        "installation",
        "-",
        "central",
        "heating"
    ],
    "wof:name":"Bols P",
    "wof:placetype":"venue"
},
  "geometry": {"coordinates":[5.109413147,51.336643219],"type":"Point"}
}