{
  "type": "Feature",
  "properties": {
    "addr:full":"Altenaken 16 Hoegaarden Vlaams-Brabant 3320",
    "addr:housenumber":"16",
    "addr:postcode":"3320",
    "addr:street":"Altenaken",
    "iso:country":"BE",
    "sg:address":"Altenaken 16",
    "sg:city":"Hoegaarden",
    "sg:classifiers":[
        {
            "category":"Professional",
            "subcategory":"Accounting & Tax Preparation",
            "type":"Services"
        }
    ],
    "sg:phone":"+32 16 76 76 41",
    "sg:postcode":"3320",
    "sg:province":"Vlaams-Brabant",
    "sg:tags":[
        "bookkeeper"
    ],
    "wof:name":"Vercammen L",
    "wof:placetype":"venue"
},
  "geometry": {"coordinates":[4.9035830498,50.7727279663],"type":"Point"}
}