{
  "type": "Feature",
  "properties": {
    "addr:full":"Rue Des Chasseurs Ardennais 11 Messancy Luxembourg 6780",
    "addr:housenumber":"11",
    "addr:postcode":"6780",
    "addr:street":"Rue Des Chasseurs Ardennais",
    "iso:country":"BE",
    "sg:address":"Rue Des Chasseurs Ardennais 11",
    "sg:city":"Messancy",
    "sg:classifiers":[
        {
            "category":"Shopping",
            "subcategory":"Books",
            "type":"Retail Goods"
        }
    ],
    "sg:phone":"+32 63 38 48 40",
    "sg:postcode":"6780",
    "sg:province":"Luxembourg",
    "sg:tags":[
        "bookseller"
    ],
    "wof:name":"Librairie Du Centre",
    "wof:placetype":"venue"
},
  "geometry": {"coordinates":[5.8162298203,49.5932617188],"type":"Point"}
}