{
  "type": "Feature",
  "properties": {
    "iso:country":"BE",
    "sg:address":"Clevenstraat 13",
    "sg:city":"Koekelare",
    "sg:orig_category":"Rundveehouders Varkenskwekers",
    "sg:phone":"+32 59 27 70 91",
    "sg:postcode":"8680",
    "sg:province":"West-Vlaanderen",
    "wof:name":"Noel Montaigne",
    "wof:placetype":"venue"
},
  "geometry": {"coordinates":[2.9805629253,51.1162109375],"type":"Point"}
}