{
  "type": "Feature",
  "properties": {
    "iso:country":"BE",
    "sg:address":"Langestraat 19",
    "sg:city":"Kampenhout",
    "sg:orig_category":"Producteurs de l\u00e9gumes",
    "sg:phone":"+32 16 65 72 68",
    "sg:postcode":"1910",
    "sg:province":"Vlaams-Brabant",
    "wof:name":"Guido Janssens",
    "wof:placetype":"venue"
},
  "geometry": {"coordinates":[4.5471458435,50.9539489746],"type":"Point"}
}