{
  "type": "Feature",
  "properties": {
    "addr:full":"Kolonel Dusartplein 52 Hasselt Limburg 3500",
    "addr:housenumber":"52",
    "addr:postcode":"3500",
    "addr:street":"Kolonel Dusartplein",
    "iso:country":"BE",
    "sg:address":"Kolonel Dusartplein 52",
    "sg:city":"Hasselt",
    "sg:classifiers":[
        {
            "category":"Restaurant",
            "type":"Food & Drink"
        }
    ],
    "sg:phone":"+32 11 22 40 70",
    "sg:postcode":"3500",
    "sg:province":"Limburg",
    "wof:name":"Staekhouse Cara",
    "wof:placetype":"venue"
},
  "geometry": {"coordinates":[5.3421711922,50.9320793152],"type":"Point"}
}