{
  "type": "Feature",
  "properties": {
    "addr:full":"Kwakkelhoekstraat 86 Sint-niklaas (nieuwkerken-waas) Oost-Vlaanderen 9100",
    "addr:housenumber":"86",
    "addr:postcode":"9100",
    "addr:street":"Kwakkelhoekstraat",
    "iso:country":"BE",
    "sg:address":"Kwakkelhoekstraat 86",
    "sg:city":"Sint-niklaas (nieuwkerken-waas)",
    "sg:classifiers":[
        {
            "category":"Quarry",
            "type":"Physical Feature"
        }
    ],
    "sg:phone":"+32 3 776 24 12",
    "sg:postcode":"9100",
    "sg:province":"Oost-Vlaanderen",
    "sg:tags":[
        "granite",
        "work",
        "marble"
    ],
    "wof:name":"Windey",
    "wof:placetype":"venue"
},
  "geometry": {"coordinates":[4.1862001419,51.1930007935],"type":"Point"}
}