{
  "type": "Feature",
  "properties": {
    "addr:full":"Chauss\u00c9e De Wavre 1542-1544 Oudergem/auderghem Bruxelles-Capitale 1160",
    "addr:postcode":"1542-1544;1160",
    "addr:street":"Chausse\u0301E De Wavre",
    "iso:country":"BE",
    "sg:address":"Chauss\u00c9e De Wavre 1542-1544",
    "sg:city":"Oudergem/auderghem",
    "sg:orig_category":"Herstellingen and onderhoud van auto's",
    "sg:phone":"+32 2 673 08 61",
    "sg:postcode":"1160",
    "sg:province":"Bruxelles-Capitale",
    "wof:name":"Locatelli Carrosserie",
    "wof:placetype":"venue"
},
  "geometry": {"coordinates":[4.422164917,50.8174095154],"type":"Point"}
}