{
  "type": "Feature",
  "properties": {
    "addr:full":"Rue De St-ethon 29 Seneffe Hainaut 7181",
    "addr:housenumber":"29",
    "addr:postcode":"7181",
    "addr:street":"Rue De St-Ethon",
    "iso:country":"BE",
    "sg:address":"Rue De St-ethon 29",
    "sg:city":"Seneffe",
    "sg:orig_category":"Installation \u00e9lectrique r\u00e9sidentielle",
    "sg:phone":"+32 67 87 90 09",
    "sg:postcode":"7181",
    "sg:province":"Hainaut",
    "wof:name":"E.m.v.",
    "wof:placetype":"venue"
},
  "geometry": {"coordinates":[4.2554302216,50.5584106445],"type":"Point"}
}