{
  "type": "Feature",
  "properties": {
    "iso:country":"BE",
    "sg:address":"Av. R. Vandendriessche 2",
    "sg:city":"Sint-pieters-woluwe/woluwe-saint-pierre",
    "sg:orig_category":"Antiquit\u00e9s",
    "sg:phone":"+32 2 771 47 56",
    "sg:postcode":"1150",
    "sg:province":"Bruxelles-Capitale",
    "wof:name":"Robert Zurcher",
    "wof:placetype":"venue"
},
  "geometry": {"coordinates":[4.4148650169,50.8351669312],"type":"Point"}
}