{
  "type": "Feature",
  "properties": {
    "addr:full":"Pulse Steenweg 4 Grobbendonk Antwerpen 2280",
    "addr:housenumber":"4",
    "addr:postcode":"2280",
    "addr:street":"Steenweg",
    "iso:country":"BE",
    "sg:address":"Pulse Steenweg 4",
    "sg:city":"Grobbendonk",
    "sg:classifiers":[
        {
            "category":"Professional",
            "subcategory":"Lawyer & Legal Services",
            "type":"Services"
        }
    ],
    "sg:phone":"+32 14 50 65 88",
    "sg:postcode":"2280",
    "sg:province":"Antwerpen",
    "wof:name":"Van Genechten Gino",
    "wof:placetype":"venue"
},
  "geometry": {"coordinates":[4.7188458443,51.1953468323],"type":"Point"}
}