{
  "type": "Feature",
  "properties": {
    "addr:full":"Rue D'eghez\u00e9e 54 Sambreville (auvelais) Namur 5060",
    "addr:housenumber":"54",
    "addr:postcode":"5060",
    "addr:street":"Rue D'Egheze \u0301E",
    "iso:country":"BE",
    "sg:address":"Rue D'eghez\u00e9e 54",
    "sg:city":"Sambreville (auvelais)",
    "sg:classifiers":[
        {
            "category":"Health Services",
            "subcategory":"Nursing And Care Facility",
            "type":"Services"
        }
    ],
    "sg:phone":"+32 71 26 61 90",
    "sg:postcode":"5060",
    "sg:province":"Namur",
    "sg:tags":[
        "home",
        "rest"
    ],
    "wof:name":"Les Charmilles",
    "wof:placetype":"venue"
},
  "geometry": {"coordinates":[4.6381850243,50.450969696],"type":"Point"}
}