{
  "type": "Feature",
  "properties": {
    "iso:country":"BE",
    "sg:address":"Rue De Lannoy 9",
    "sg:city":"Pecq",
    "sg:classifiers":[
        {
            "category":"Food & Beverages",
            "subcategory":"Fruits & Vegetables",
            "type":"Retail Goods"
        }
    ],
    "sg:phone":"+32 69 55 85 04",
    "sg:postcode":"7740",
    "sg:province":"Hainaut",
    "sg:tags":[
        "groenten"
    ],
    "wof:name":"Michele Thulier",
    "wof:placetype":"venue"
},
  "geometry": {"coordinates":[3.3379030228,50.6856575012],"type":"Point"}
}