{
  "type": "Feature",
  "properties": {
    "addr:full":"Moerlandstraat 23 Sint-niklaas Oost-Vlaanderen 9100",
    "addr:housenumber":"23",
    "addr:postcode":"9100",
    "addr:street":"Moerlandstraat",
    "iso:country":"BE",
    "sg:address":"Moerlandstraat 23",
    "sg:city":"Sint-niklaas",
    "sg:classifiers":[
        {
            "category":"Insurance",
            "subcategory":"Insurance Agent",
            "type":"Services"
        }
    ],
    "sg:phone":"+32 3 777 32 19",
    "sg:postcode":"9100",
    "sg:province":"Oost-Vlaanderen",
    "sg:tags":[
        "broker"
    ],
    "wof:name":"Van Den Broeck & Schelfhout Bvba",
    "wof:placetype":"venue"
},
  "geometry": {"coordinates":[4.1464247704,51.159488678],"type":"Point"}
}