{
  "type": "Feature",
  "properties": {
    "iso:country":"BE",
    "sg:address":"Rue Saint-vincent 6",
    "sg:city":"Jodoigne (pi\u00e9train)",
    "sg:classifiers":[
        {
            "category":"Building & Trades",
            "subcategory":"Plumbing",
            "type":"Services"
        }
    ],
    "sg:phone":"+32 10 81 30 40",
    "sg:postcode":"1370",
    "sg:province":"Brabant Wallon",
    "sg:tags":[
        "contractor"
    ],
    "wof:name":"Genicot P",
    "wof:placetype":"venue"
},
  "geometry": {"coordinates":[4.9333901405,50.7334709167],"type":"Point"}
}