{
  "type": "Feature",
  "properties": {
    "iso:country":"BE",
    "sg:address":"Rue Gabrielle 82bte 1",
    "sg:city":"Bruxelles",
    "sg:classifiers":[
        {
            "category":"Communications",
            "subcategory":"Film & Video Production",
            "type":"Services"
        }
    ],
    "sg:phone":"+32 2 346 20 12",
    "sg:postcode":"1180",
    "sg:province":"Bruxelles-Capitale",
    "sg:tags":[
        "photograph",
        "industrial"
    ],
    "wof:name":"Thierry Dauwe Photographe",
    "wof:placetype":"venue"
},
  "geometry": {"coordinates":[4.3602070808,50.8130226135],"type":"Point"}
}