{
  "type": "Feature",
  "properties": {
    "addr:full":"Rue Lambert Macours 15 Awans Li\u00e8ge 4340",
    "addr:housenumber":"15",
    "addr:postcode":"4340",
    "addr:street":"Rue Lambert Macours",
    "iso:country":"BE",
    "sg:address":"Rue Lambert Macours 15",
    "sg:city":"Awans",
    "sg:orig_category":"Banques and organismes de cr\u00e9dit",
    "sg:phone":"+32 4 257 40 94",
    "sg:postcode":"4340",
    "sg:province":"Li\u00e8ge",
    "wof:name":"Bbl",
    "wof:placetype":"venue"
},
  "geometry": {"coordinates":[5.4664821625,50.7138900757],"type":"Point"}
}