{
  "type": "Feature",
  "properties": {
    "addr:full":"Gebroeders Vandeveldestraat 68 Gent Oost-Vlaanderen 9000",
    "addr:housenumber":"68",
    "addr:postcode":"9000",
    "addr:street":"Gebroeders Vandeveldestraat;Oost-Vlaanderen",
    "iso:country":"BE",
    "sg:address":"Gebroeders Vandeveldestraat 68",
    "sg:city":"Gent",
    "sg:classifiers":[
        {
            "category":"Professional",
            "subcategory":"Lawyer & Legal Services",
            "type":"Services"
        }
    ],
    "sg:phone":"+32 9 265 76 20",
    "sg:postcode":"9000",
    "sg:province":"Oost-Vlaanderen",
    "wof:name":"Van Den Branden Isabelle",
    "wof:placetype":"venue"
},
  "geometry": {"coordinates":[3.7172510624,51.0501480103],"type":"Point"}
}