{
  "type": "Feature",
  "properties": {
    "iso:country":"BE",
    "sg:address":"Rue Du Bois De Linthout 16",
    "sg:city":"Sint-lambrechts-woluwe/woluwe-saint-lambert",
    "sg:orig_category":"M\u00e9decins and sp\u00e9cialistes",
    "sg:phone":"+32 2 734 00 88",
    "sg:postcode":"1200",
    "sg:province":"Bruxelles-Capitale",
    "wof:name":"Gilbert Bruyneel",
    "wof:placetype":"venue"
},
  "geometry": {"coordinates":[4.4129362106,50.8444328308],"type":"Point"}
}