{
  "type": "Feature",
  "properties": {
    "addr:full":"Rue Du P\u00c2turage 43 Brussel/bruxelles Bruxelles-Capitale 1120",
    "addr:housenumber":"43",
    "addr:postcode":"1120",
    "addr:street":"Rue Du Pa\u0302Turage;/",
    "iso:country":"BE",
    "sg:address":"Rue Du P\u00c2turage 43",
    "sg:city":"Brussel/bruxelles",
    "sg:orig_category":"M\u00e9decins and sp\u00e9cialistes",
    "sg:phone":"+32 2 268 03 96",
    "sg:postcode":"1120",
    "sg:province":"Bruxelles-Capitale",
    "wof:name":"Pierre Verbruggen",
    "wof:placetype":"venue"
},
  "geometry": {"coordinates":[4.3805627823,50.8945083618],"type":"Point"}
}