{
  "type": "Feature",
  "properties": {
    "addr:full":"Brusselsestraat 33 Leuven Vlaams-Brabant 3000",
    "addr:housenumber":"33",
    "addr:postcode":"3000",
    "addr:street":"Brusselsestraat",
    "iso:country":"BE",
    "sg:address":"Brusselsestraat 33",
    "sg:city":"Leuven",
    "sg:orig_category":"Randstad",
    "sg:phone":"+32 16 29 42 15",
    "sg:postcode":"3000",
    "sg:province":"Vlaams-Brabant",
    "wof:name":"Randstad",
    "wof:placetype":"venue"
},
  "geometry": {"coordinates":[4.6988148689,50.8796005249],"type":"Point"}
}