{
  "type": "Feature",
  "properties": {
    "iso:country":"BE",
    "sg:address":"Ninoofsesteenweg 607",
    "sg:city":"Ronse",
    "sg:orig_category":"Installation de menuiserie en bois and plastique. Meubles D\u00e9taillants, Am\u00e9nagement de B\u00e2timents et d",
    "sg:phone":"+32 55 21 64 86",
    "sg:postcode":"9600",
    "sg:province":"Oost-Vlaanderen",
    "wof:name":"Interstock",
    "wof:placetype":"venue"
},
  "geometry": {"coordinates":[3.6589109898,50.7542610168],"type":"Point"}
}