{
  "type": "Feature",
  "properties": {
    "addr:full":"Statiestraat 20 Buggenhout Oost-Vlaanderen 9255",
    "addr:housenumber":"20",
    "addr:postcode":"9255",
    "addr:street":"Statiestraat",
    "iso:country":"BE",
    "sg:address":"Statiestraat 20",
    "sg:city":"Buggenhout",
    "sg:orig_category":"Dranken",
    "sg:phone":"+32 52 34 12 20",
    "sg:postcode":"9255",
    "sg:province":"Oost-Vlaanderen",
    "wof:name":"Cooreman",
    "wof:placetype":"venue"
},
  "geometry": {"coordinates":[4.2018060684,51.0139122009],"type":"Point"}
}