{
  "type": "Feature",
  "properties": {
    "iso:country":"BE",
    "sg:address":"Jagerstraat 18",
    "sg:city":"Nazareth",
    "sg:orig_category":"Eleveurs and marchands de porcs",
    "sg:phone":"+32 9 384 35 44",
    "sg:postcode":"9810",
    "sg:province":"Oost-Vlaanderen",
    "wof:name":"Roland Vande Steene",
    "wof:placetype":"venue"
},
  "geometry": {"coordinates":[3.6312150955,50.9437179565],"type":"Point"}
}