{
  "type": "Feature",
  "properties": {
    "addr:full":"Leopoldlaan 82 Eeklo Oost-Vlaanderen 9900",
    "addr:housenumber":"82",
    "addr:postcode":"9900",
    "addr:street":"Leopoldlaan",
    "iso:country":"BE",
    "sg:address":"Leopoldlaan 82",
    "sg:city":"Eeklo",
    "sg:orig_category":"Studios photographiques. Equipement photographique",
    "sg:phone":"+32 9 377 24 23",
    "sg:postcode":"9900",
    "sg:province":"Oost-Vlaanderen",
    "wof:name":"Foto Verstraeten",
    "wof:placetype":"venue"
},
  "geometry": {"coordinates":[3.540982008,51.1957626343],"type":"Point"}
}