{
  "type": "Feature",
  "properties": {
    "iso:country":"BE",
    "sg:address":"Nestor De Ti\u00e8restraat 78",
    "sg:city":"Oudenaarde",
    "sg:classifiers":[
        {
            "category":"Personal",
            "subcategory":"Beauty Salon",
            "type":"Services"
        }
    ],
    "sg:phone":"+32 55 31 27 14",
    "sg:postcode":"9700",
    "sg:province":"Oost-Vlaanderen",
    "sg:tags":[
        "lady",
        "-",
        "hairdressing"
    ],
    "wof:name":"Peyskens A",
    "wof:placetype":"venue"
},
  "geometry": {"coordinates":[3.6167080402,50.8659934998],"type":"Point"}
}