{
  "type": "Feature",
  "properties": {
    "addr:full":"Rue Auguste-ponson 28 Li\u00c8ge Li\u00e8ge 4020",
    "addr:housenumber":"28",
    "addr:postcode":"4020",
    "addr:street":"Rue Auguste-Ponson",
    "iso:country":"BE",
    "sg:address":"Rue Auguste-ponson 28",
    "sg:city":"Li\u00c8ge",
    "sg:orig_category":"M\u00e9decins and sp\u00e9cialistes",
    "sg:phone":"+32 4 362 85 21",
    "sg:postcode":"4020",
    "sg:province":"Li\u00e8ge",
    "wof:name":"Jean Perrier D'hauterive",
    "wof:placetype":"venue"
},
  "geometry": {"coordinates":[5.597987175,50.6353530884],"type":"Point"}
}