{
  "type": "Feature",
  "properties": {
    "iso:country":"BE",
    "sg:address":"Avenue Huart Hamoir 43",
    "sg:city":"Schaarbeek/schaerbeek",
    "sg:orig_category":"R\u00e9cup\u00e9ration de mati\u00e8res m\u00e9talliques recyclables and d\u00e9molisseurs de voitures. Entretien et r\u00e9parati",
    "sg:phone":"+32 2 215 45 10",
    "sg:postcode":"1030",
    "sg:province":"Bruxelles-Capitale",
    "wof:name":"Carrosserie Dierickx",
    "wof:placetype":"venue"
},
  "geometry": {"coordinates":[4.3814949989,50.8765258789],"type":"Point"}
}