{
  "type": "Feature",
  "properties": {
    "addr:full":"Rue De L'union 23 Sint-joost-ten-node/saint-joss Bruxelles-Capitale 1210",
    "addr:housenumber":"23",
    "addr:postcode":"1210",
    "addr:street":"Rue De L'Union",
    "iso:country":"BE",
    "sg:address":"Rue De L'union 23",
    "sg:city":"Sint-joost-ten-node/saint-joss",
    "sg:orig_category":"Cliniques and h\u00f4pitaux",
    "sg:phone":"+32 2 223 49 52",
    "sg:postcode":"1210",
    "sg:province":"Bruxelles-Capitale",
    "wof:name":"Messidor",
    "wof:placetype":"venue"
},
  "geometry": {"coordinates":[4.3710961342,50.852771759],"type":"Point"}
}