{
  "type": "Feature",
  "properties": {
    "iso:country":"BE",
    "sg:address":"Place Emile Vinck",
    "sg:city":"Fl\u00e9malle",
    "sg:classifiers":[
        {
            "category":"Education",
            "subcategory":"School",
            "type":"Public Place"
        }
    ],
    "sg:phone":"+32 4 275 62 22",
    "sg:postcode":"4400",
    "sg:province":"Li\u00e8ge",
    "sg:tags":[
        "primary"
    ],
    "wof:name":"Ecole Communale Pl Vinck",
    "wof:placetype":"venue"
},
  "geometry": {"coordinates":[5.4458022118,50.6018257141],"type":"Point"}
}