{
  "type": "Feature",
  "properties": {
    "addr:full":"Avenue Saint-augustin 25 Vorst/forest Bruxelles-Capitale 1190",
    "addr:housenumber":"25",
    "addr:postcode":"1190",
    "addr:street":"Avenue Saint-Augustin;/ Forest",
    "iso:country":"BE",
    "sg:address":"Avenue Saint-augustin 25",
    "sg:city":"Vorst/forest",
    "sg:orig_category":"Instituts de beaut\u00e9",
    "sg:phone":"+32 2 347 28 53",
    "sg:postcode":"1190",
    "sg:province":"Bruxelles-Capitale",
    "wof:name":"Anna Krason",
    "wof:placetype":"venue"
},
  "geometry": {"coordinates":[4.3386230469,50.8165016174],"type":"Point"}
}