{
  "type": "Feature",
  "properties": {
    "addr:full":"Rue De La Hulpe 105 Rixensart Brabant Wallon 1331",
    "addr:housenumber":"105",
    "addr:postcode":"1331",
    "addr:street":"Rue De La Hulpe;Wallon",
    "iso:country":"BE",
    "sg:address":"Rue De La Hulpe 105",
    "sg:city":"Rixensart",
    "sg:orig_category":"Services de Nettoyage and de D\u00e9sinfection",
    "sg:phone":"+32 2 654 15 82",
    "sg:postcode":"1331",
    "sg:province":"Brabant Wallon",
    "wof:name":"Ghislain Vanhove",
    "wof:placetype":"venue"
},
  "geometry": {"coordinates":[4.5383591652,50.7275772095],"type":"Point"}
}