{
  "type": "Feature",
  "properties": {
    "iso:country":"BE",
    "sg:address":"Lakensestraat 88",
    "sg:city":"Brussel/bruxelles",
    "sg:orig_category":"Binnenhuisarchitecten",
    "sg:phone":"+32 2 219 51 77",
    "sg:postcode":"1000",
    "sg:province":"Bruxelles-Capitale",
    "wof:name":"Tine Loncin",
    "wof:placetype":"venue"
},
  "geometry": {"coordinates":[4.3515930176,50.8539085388],"type":"Point"}
}