{
  "type": "Feature",
  "properties": {
    "addr:full":"Zeedijk 366 Oostende West-Vlaanderen 8400",
    "addr:housenumber":"366",
    "addr:postcode":"8400",
    "addr:street":"Zeedijk",
    "iso:country":"BE",
    "sg:address":"Zeedijk 366",
    "sg:city":"Oostende",
    "sg:classifiers":[
        {
            "category":"Shopping",
            "subcategory":"Clothing, Apparel, & Fashions",
            "type":"Retail Goods"
        }
    ],
    "sg:phone":"+32 59 51 06 17",
    "sg:postcode":"8400",
    "sg:province":"West-Vlaanderen",
    "sg:tags":[
        "designer",
        "stylist"
    ],
    "wof:name":"Claeys T",
    "wof:placetype":"venue"
},
  "geometry": {"coordinates":[2.8433520794,51.2001838684],"type":"Point"}
}