{
  "type": "Feature",
  "properties": {
    "iso:country":"BE",
    "sg:address":"Kuringersteenweg 275",
    "sg:city":"Hasselt",
    "sg:classifiers":[
        {
            "category":"Home & Garden",
            "subcategory":"Carpets & Floor Coverings",
            "type":"Retail Goods"
        }
    ],
    "sg:phone":"+32 11 25 41 41",
    "sg:postcode":"3500",
    "sg:province":"Limburg",
    "sg:tags":[
        "oriental"
    ],
    "wof:name":"Acterio",
    "wof:placetype":"venue"
},
  "geometry": {"coordinates":[5.314620018,50.9374809265],"type":"Point"}
}