{
  "type": "Feature",
  "properties": {
    "addr:full":"Keizer Karelstraat 164 Gent Oost-Vlaanderen 9000",
    "addr:housenumber":"164",
    "addr:postcode":"9000",
    "addr:street":"Keizer Karelstraat;Oost-Vlaanderen",
    "iso:country":"BE",
    "sg:address":"Keizer Karelstraat 164",
    "sg:city":"Gent",
    "sg:orig_category":"Diverse opleidingen and onderwijs",
    "sg:phone":"+32 9 233 33 03",
    "sg:postcode":"9000",
    "sg:province":"Oost-Vlaanderen",
    "wof:name":"Claude Aburbe & Ass. Eur.",
    "wof:placetype":"venue"
},
  "geometry": {"coordinates":[3.7329199314,51.0511283875],"type":"Point"}
}