{
  "type": "Feature",
  "properties": {
    "iso:country":"BE",
    "sg:address":"Avenue De La Sideho 2",
    "sg:city":"Comines-warneton (comines)",
    "sg:classifiers":[
        {
            "category":"Wholesale",
            "subcategory":"Beer",
            "type":"Manufacturing & Wholesale Goods"
        }
    ],
    "sg:phone":"+32 56 55 57 93",
    "sg:postcode":"7780",
    "sg:province":"Hainaut",
    "sg:tags":[
        "ale",
        "-"
    ],
    "wof:name":"Caytan C",
    "wof:placetype":"venue"
},
  "geometry": {"coordinates":[3.0002019405,50.768611908],"type":"Point"}
}