{
  "type": "Feature",
  "properties": {
    "iso:country":"BE",
    "sg:address":"Leedsestraat 8",
    "sg:city":"Kruishoutem (wannegem-lede)",
    "sg:classifiers":[
        {
            "category":"Food & Beverages",
            "subcategory":"Meat & Fish",
            "type":"Retail Goods"
        }
    ],
    "sg:phone":"+32 9 383 51 19",
    "sg:postcode":"9772",
    "sg:province":"Oost-Vlaanderen",
    "sg:tags":[
        "-",
        "livestock"
    ],
    "wof:name":"Van Den Broecke Voeders",
    "wof:placetype":"venue"
},
  "geometry": {"coordinates":[3.570734024,50.8843994141],"type":"Point"}
}