{
  "type": "Feature",
  "properties": {
    "addr:full":"Leuvensebaan 67 Huldenberg (ottenburg) Vlaams-Brabant 3040",
    "addr:housenumber":"67",
    "addr:postcode":"3040",
    "addr:street":"Leuvensebaan",
    "iso:country":"BE",
    "sg:address":"Leuvensebaan 67",
    "sg:city":"Huldenberg (ottenburg)",
    "sg:classifiers":[
        {
            "category":"Bars & Pubs",
            "type":"Food & Drink"
        }
    ],
    "sg:phone":"+32 16 47 24 06",
    "sg:postcode":"3040",
    "sg:province":"Vlaams-Brabant",
    "wof:name":"Welkom (de)",
    "wof:placetype":"venue"
},
  "geometry": {"coordinates":[4.6157588959,50.7525100708],"type":"Point"}
}