{
  "type": "Feature",
  "properties": {
    "addr:full":"Yzerhand 2 Beveren (beveren-waas) Oost-Vlaanderen 9120",
    "addr:housenumber":"2",
    "addr:postcode":"9120",
    "addr:street":"Yzerhand;Oost-Vlaanderen",
    "iso:country":"BE",
    "sg:address":"Yzerhand 2",
    "sg:city":"Beveren (beveren-waas)",
    "sg:classifiers":[
        {
            "category":"Shopping",
            "subcategory":"Clothing, Apparel, & Fashions",
            "type":"Retail Goods"
        }
    ],
    "sg:phone":"+32 3 775 49 13",
    "sg:postcode":"9120",
    "sg:province":"Oost-Vlaanderen",
    "sg:tags":[
        "clothing",
        "-",
        "gentleman"
    ],
    "wof:name":"Bas'il",
    "wof:placetype":"venue"
},
  "geometry": {"coordinates":[4.2527971268,51.2151527405],"type":"Point"}
}