{
  "type": "Feature",
  "properties": {
    "addr:full":"Tuinweg 14 Zandhoven Antwerpen 2242",
    "addr:housenumber":"14",
    "addr:postcode":"2242",
    "addr:street":"Tuinweg",
    "iso:country":"BE",
    "sg:address":"Tuinweg 14",
    "sg:city":"Zandhoven",
    "sg:orig_category":"Rev\u00eatements de sols and murs. Meubles D\u00e9taillants, Am\u00e9nagement de B\u00e2timents et de Cuisines",
    "sg:phone":"+32 3 484 41 28",
    "sg:postcode":"2242",
    "sg:province":"Antwerpen",
    "wof:name":"Koenraad Vermeire",
    "wof:placetype":"venue"
},
  "geometry": {"coordinates":[4.6948399544,51.2148284912],"type":"Point"}
}