{
  "type": "Feature",
  "properties": {
    "addr:full":"Rue De La Grande Rh\u00c9e 153 Wasseiges Li\u00e8ge 4219",
    "addr:housenumber":"153",
    "addr:postcode":"4219",
    "addr:street":"Rue De La Grande Rhe\u0301E",
    "iso:country":"BE",
    "sg:address":"Rue De La Grande Rh\u00c9e 153",
    "sg:city":"Wasseiges",
    "sg:orig_category":"Eleveurs de bovins",
    "sg:phone":"+32 81 85 61 24",
    "sg:postcode":"4219",
    "sg:province":"Li\u00e8ge",
    "wof:name":"De Marneffe H. & P.",
    "wof:placetype":"venue"
},
  "geometry": {"coordinates":[5.0181298256,50.6039199829],"type":"Point"}
}