{
  "type": "Feature",
  "properties": {
    "addr:full":". Doische (groot) Namur 5680",
    "addr:postcode":"5680",
    "addr:street":"Groot Namur",
    "iso:country":"BE",
    "sg:address":".",
    "sg:city":"Doische (groot)",
    "sg:orig_category":"Apotheken",
    "sg:phone":"+32 900 10 500",
    "sg:postcode":"5680",
    "sg:province":"Namur",
    "wof:name":"Apothekers Van Wacht",
    "wof:placetype":"venue"
},
  "geometry": {"coordinates":[4.7456698418,50.1359405518],"type":"Point"}
}