{
  "type": "Feature",
  "properties": {
    "addr:full":"Waterleliestraat 4 Kortrijk West-Vlaanderen 8500",
    "addr:housenumber":"4",
    "addr:postcode":"8500",
    "addr:street":"Waterleliestraat",
    "iso:country":"BE",
    "sg:address":"Waterleliestraat 4",
    "sg:city":"Kortrijk",
    "sg:classifiers":[
        {
            "category":"Shopping",
            "subcategory":"Antiques",
            "type":"Retail Goods"
        }
    ],
    "sg:phone":"+32 56 20 00 37",
    "sg:postcode":"8500",
    "sg:province":"West-Vlaanderen",
    "wof:name":"Liberty",
    "wof:placetype":"venue"
},
  "geometry": {"coordinates":[3.2899730206,50.8283843994],"type":"Point"}
}