{
  "type": "Feature",
  "properties": {
    "addr:full":"Rue Sous La Ville 8b3 Sambreville Namur 5060",
    "addr:housenumber":"8b3",
    "addr:postcode":"5060",
    "addr:street":"Rue Sous La Ville",
    "iso:country":"BE",
    "sg:address":"Rue Sous La Ville 8b3",
    "sg:city":"Sambreville",
    "sg:classifiers":[
        {
            "category":"Insurance",
            "subcategory":"Life Insurance",
            "type":"Services"
        }
    ],
    "sg:phone":"+32 71 74 03 03",
    "sg:postcode":"5060",
    "sg:province":"Namur",
    "sg:tags":[
        "assurance"
    ],
    "wof:name":"R. Legrand",
    "wof:placetype":"venue"
},
  "geometry": {"coordinates":[4.6285200119,50.4448738098],"type":"Point"}
}