{
  "type": "Feature",
  "properties": {
    "iso:country":"BE",
    "sg:address":"Chauss\u00e9e De Wemmel 167",
    "sg:city":"Bruxelles (jette)",
    "sg:classifiers":[
        {
            "category":"Personal",
            "subcategory":"Beauty Salon",
            "type":"Services"
        }
    ],
    "sg:phone":"+32 2 427 04 52",
    "sg:postcode":"1090",
    "sg:province":"Bruxelles-Capitale",
    "sg:tags":[
        "lady",
        "-",
        "hairdressing"
    ],
    "wof:name":"Rachel",
    "wof:placetype":"venue"
},
  "geometry": {"coordinates":[4.3237137794,50.8774871826],"type":"Point"}
}