{
  "type": "Feature",
  "properties": {
    "addr:full":"Rue Des Viaducs 85 Mons Hainaut 7020",
    "addr:housenumber":"85",
    "addr:postcode":"7020",
    "addr:street":"Rue Des Viaducs;Hainaut",
    "iso:country":"BE",
    "sg:address":"Rue Des Viaducs 85",
    "sg:city":"Mons",
    "sg:orig_category":"Kansspelen",
    "sg:phone":"+32 65 31 46 73",
    "sg:postcode":"7020",
    "sg:province":"Hainaut",
    "wof:name":"Ladbroke",
    "wof:placetype":"venue"
},
  "geometry": {"coordinates":[3.9553449154,50.4761772156],"type":"Point"}
}