{
  "type": "Feature",
  "properties": {
    "iso:country":"BE",
    "sg:address":"Galerie Bernard",
    "sg:city":"Charleroi",
    "sg:classifiers":[
        {
            "category":"Professional",
            "subcategory":"Lawyer & Legal Services",
            "type":"Services"
        }
    ],
    "sg:phone":"+32 71 34 48 95",
    "sg:postcode":"6000",
    "sg:province":"Hainaut",
    "wof:name":"Dizier Jean-fran\u00e7ois",
    "wof:placetype":"venue"
},
  "geometry": {"coordinates":[4.4443449974,50.4080581665],"type":"Point"}
}