{
  "type": "Feature",
  "properties": {
    "addr:full":"Place Du M\u00d4le 25 Braine-l\u00b4alleud Brabant Wallon 1420",
    "addr:housenumber":"25",
    "addr:postcode":"1420",
    "addr:street":"Place Du Mo\u0302Le;Brabant Wallon",
    "iso:country":"BE",
    "sg:address":"Place Du M\u00d4le 25",
    "sg:city":"Braine-l\u00b4alleud",
    "sg:orig_category":"Epiceries",
    "sg:phone":"+32 2 384 23 97",
    "sg:postcode":"1420",
    "sg:province":"Brabant Wallon",
    "wof:name":"Super G.b. Partner",
    "wof:placetype":"venue"
},
  "geometry": {"coordinates":[4.3706898689,50.6840896606],"type":"Point"}
}