{
  "type": "Feature",
  "properties": {
    "addr:full":"Eksaardserijweg 165 Gent (oostakker) Oost-Vlaanderen 9041",
    "addr:housenumber":"165",
    "addr:postcode":"9041",
    "iso:country":"BE",
    "sg:address":"Eksaardserijweg 165",
    "sg:city":"Gent (oostakker)",
    "sg:classifiers":[
        {
            "category":"Manufacturing",
            "subcategory":"Signs",
            "type":"Manufacturing & Wholesale Goods"
        }
    ],
    "sg:phone":"+32 9 251 62 04",
    "sg:postcode":"9041",
    "sg:province":"Oost-Vlaanderen",
    "sg:tags":[
        "-",
        "illuminated"
    ],
    "wof:name":"Gentse Neoncentrale Nv",
    "wof:placetype":"venue"
},
  "geometry": {"coordinates":[3.7761991024,51.0932807922],"type":"Point"}
}