{
  "type": "Feature",
  "properties": {
    "addr:full":"Drapstraat 95 Hamme Oost-Vlaanderen 9220",
    "addr:housenumber":"95",
    "addr:postcode":"9220",
    "addr:street":"Drapstraat",
    "iso:country":"BE",
    "sg:address":"Drapstraat 95",
    "sg:city":"Hamme",
    "sg:classifiers":[
        {
            "category":"Retail",
            "subcategory":"Animal Services",
            "type":"Services"
        }
    ],
    "sg:phone":"+32 477 32 41 88",
    "sg:postcode":"9220",
    "sg:province":"Oost-Vlaanderen",
    "sg:tags":[
        "grooming",
        "-",
        "dog"
    ],
    "wof:name":"Trimshop Ricky Boone G",
    "wof:placetype":"venue"
},
  "geometry": {"coordinates":[4.1435489655,51.0996284485],"type":"Point"}
}