{
  "type": "Feature",
  "properties": {
    "addr:full":"Mereldreef 2 Essen Antwerpen 2910",
    "addr:housenumber":"2",
    "addr:postcode":"2910",
    "addr:street":"Mereldreef",
    "iso:country":"BE",
    "sg:address":"Mereldreef 2",
    "sg:city":"Essen",
    "sg:classifiers":[
        {
            "category":"Government",
            "subcategory":"Police Station",
            "type":"Public Place"
        }
    ],
    "sg:phone":"+32 3 667 27 24",
    "sg:postcode":"2910",
    "sg:province":"Antwerpen",
    "sg:tags":[
        "fidelity",
        "issuing",
        "-",
        "card"
    ],
    "wof:name":"Din-out Circle",
    "wof:placetype":"venue"
},
  "geometry": {"coordinates":[4.4456701279,51.4303665161],"type":"Point"}
}