{
  "type": "Feature",
  "properties": {
    "addr:full":"Kortrijksesteenweg 147-149 Sint-martens-latem Oost-Vlaanderen 9830",
    "addr:housenumber":"147-149",
    "addr:postcode":"9830",
    "addr:street":"Kortrijksesteenweg",
    "iso:country":"BE",
    "sg:address":"Kortrijksesteenweg 147-149",
    "sg:city":"Sint-martens-latem",
    "sg:classifiers":[
        {
            "category":"Wholesale",
            "subcategory":"Wine & Distilled Alcoholic Beverages",
            "type":"Manufacturing & Wholesale Goods"
        }
    ],
    "sg:phone":"+32 9 222 34 45",
    "sg:postcode":"9830",
    "sg:province":"Oost-Vlaanderen",
    "sg:tags":[
        "whol",
        "-",
        "spirit",
        "mfg"
    ],
    "wof:name":"Rouseu Wijnen & Likeuren Bvba",
    "wof:placetype":"venue"
},
  "geometry": {"coordinates":[3.6358850002,51.0099029541],"type":"Point"}
}