{
  "type": "Feature",
  "properties": {
    "iso:country":"BE",
    "sg:address":"Moerkerkesteenweg 605",
    "sg:city":"Brugge",
    "sg:orig_category":"Bloemen and planten Huisdieren and benodigdheden Royal Canin Tuinbenodigdheden",
    "sg:phone":"+32 50 36 16 95",
    "sg:postcode":"8000",
    "sg:province":"West-Vlaanderen",
    "wof:name":"Sneppe Marleen",
    "wof:placetype":"venue"
},
  "geometry": {"coordinates":[3.2370400429,51.207611084],"type":"Point"}
}