{
  "type": "Feature",
  "properties": {
    "iso:country":"BE",
    "sg:address":"Damse Vaart-west 7",
    "sg:city":"Damme",
    "sg:classifiers":[
        {
            "category":"Shopping",
            "subcategory":"Antiques",
            "type":"Retail Goods"
        }
    ],
    "sg:phone":"+32 50 34 10 17",
    "sg:postcode":"8340",
    "sg:province":"West-Vlaanderen",
    "wof:name":"Van Lerberghe Ph",
    "wof:placetype":"venue"
},
  "geometry": {"coordinates":[3.2835690975,51.2556266785],"type":"Point"}
}