{
  "type": "Feature",
  "properties": {
    "addr:full":"Strandlaan 234 Koksijde West-Vlaanderen 8670",
    "addr:housenumber":"234",
    "addr:postcode":"8670",
    "addr:street":"Strandlaan",
    "iso:country":"BE",
    "sg:address":"Strandlaan 234",
    "sg:city":"Koksijde",
    "sg:classifiers":[
        {
            "category":"Insurance",
            "subcategory":"Insurance Agent",
            "type":"Services"
        }
    ],
    "sg:phone":"+32 58 52 23 45",
    "sg:postcode":"8670",
    "sg:province":"West-Vlaanderen",
    "sg:tags":[
        "broker"
    ],
    "wof:name":"Delie Verzekeringen",
    "wof:placetype":"venue"
},
  "geometry": {"coordinates":[2.6132209301,51.1087913513],"type":"Point"}
}