{
  "type": "Feature",
  "properties": {
    "addr:full":"Leopoldstraat 36-38 Blankenberge West-Vlaanderen 8370",
    "addr:housenumber":"36-38",
    "addr:postcode":"8370",
    "addr:street":"Leopoldstraat",
    "iso:country":"BE",
    "sg:address":"Leopoldstraat 36-38",
    "sg:city":"Blankenberge",
    "sg:classifiers":[
        {
            "category":"Bars & Pubs",
            "type":"Food & Drink"
        }
    ],
    "sg:phone":"+32 50 41 41 34",
    "sg:postcode":"8370",
    "sg:province":"West-Vlaanderen",
    "wof:name":"Brasserie Den Brasseur",
    "wof:placetype":"venue"
},
  "geometry": {"coordinates":[3.1234920025,51.3136749268],"type":"Point"}
}