{
  "type": "Feature",
  "properties": {
    "addr:full":"Place Communale 18 Trois-ponts - Fosse Li\u00e8ge 4980",
    "addr:housenumber":"18",
    "addr:postcode":"4980",
    "addr:street":"Place Communale;Fosse",
    "iso:country":"BE",
    "sg:address":"Place Communale 18",
    "sg:city":"Trois-ponts - Fosse",
    "sg:classifiers":[
        {
            "category":"Real Estate",
            "subcategory":"Real Estate Services",
            "type":"Services"
        }
    ],
    "sg:phone":"+32 80 68 52 35",
    "sg:postcode":"4980",
    "sg:province":"Li\u00e8ge",
    "wof:name":"Dethier",
    "wof:placetype":"venue"
},
  "geometry": {"coordinates":[5.8713760376,50.3714370728],"type":"Point"}
}