{
  "type": "Feature",
  "properties": {
    "iso:country":"BE",
    "sg:address":"Passendalestraat 80",
    "sg:city":"Passendale",
    "sg:classifiers":[
        {
            "category":"Food & Beverages",
            "subcategory":"Fruits & Vegetables",
            "type":"Retail Goods"
        }
    ],
    "sg:phone":"+32 51 78 07 80",
    "sg:postcode":"8980",
    "sg:province":"West-Vlaanderen",
    "sg:tags":[
        "frozen",
        "product",
        "related"
    ],
    "wof:name":"Pasfrost Nv",
    "wof:placetype":"venue"
},
  "geometry": {"coordinates":[3.0084760189,50.886554718],"type":"Point"}
}