{
  "type": "Feature",
  "properties": {
    "addr:full":"Rue De La Gare 2 Malmedy/malmedy Li\u00e8ge 4960",
    "addr:housenumber":"2",
    "addr:postcode":"4960",
    "addr:street":"Rue De La Gare",
    "iso:country":"BE",
    "sg:address":"Rue De La Gare 2",
    "sg:city":"Malmedy/malmedy",
    "sg:classifiers":[
        {
            "category":"Health Services",
            "subcategory":"Nursing And Care Facility",
            "type":"Services"
        }
    ],
    "sg:phone":"+32 80 33 09 56",
    "sg:postcode":"4960",
    "sg:province":"Li\u00e8ge",
    "sg:tags":[
        "public"
    ],
    "wof:name":"Admin. Contrib. Directes",
    "wof:placetype":"venue"
},
  "geometry": {"coordinates":[6.0551772118,50.37657547],"type":"Point"}
}