{
  "type": "Feature",
  "properties": {
    "iso:country":"BE",
    "sg:address":"Rue De Tellin 44",
    "sg:city":"Tellin (bure)",
    "sg:classifiers":[
        {
            "category":"Professional",
            "subcategory":"Accounting & Tax Preparation",
            "type":"Services"
        }
    ],
    "sg:phone":"+32 84 36 63 95",
    "sg:postcode":"6927",
    "sg:province":"Luxembourg",
    "sg:tags":[
        "bookkeeper"
    ],
    "wof:name":"Louviaux A",
    "wof:placetype":"venue"
},
  "geometry": {"coordinates":[5.2550082207,50.0878143311],"type":"Point"}
}