{
  "type": "Feature",
  "properties": {
    "addr:full":"Place De La Gare 23 Mouscron Hainaut 7700",
    "addr:housenumber":"23",
    "addr:postcode":"7700",
    "addr:street":"Place De La Gare",
    "iso:country":"BE",
    "sg:address":"Place De La Gare 23",
    "sg:city":"Mouscron",
    "sg:classifiers":[
        {
            "category":"Real Estate",
            "subcategory":"Architect",
            "type":"Services"
        }
    ],
    "sg:phone":"+32 56 84 08 09",
    "sg:postcode":"7700",
    "sg:province":"Hainaut",
    "wof:name":"Delusinne C",
    "wof:placetype":"venue"
},
  "geometry": {"coordinates":[3.227077961,50.7402954102],"type":"Point"}
}