{
  "type": "Feature",
  "properties": {
    "addr:full":"Crokaertlaan 2 Sint-pieters-woluwe/woluwe-sai Bruxelles-Capitale 1150",
    "addr:housenumber":"2",
    "addr:postcode":"1150",
    "addr:street":"Crokaertlaan",
    "iso:country":"BE",
    "sg:address":"Crokaertlaan 2",
    "sg:city":"Sint-pieters-woluwe/woluwe-sai",
    "sg:orig_category":"Artsen and specialisten",
    "sg:phone":"+32 2 771 10 43",
    "sg:postcode":"1150",
    "sg:province":"Bruxelles-Capitale",
    "wof:name":"Rolland Florence",
    "wof:placetype":"venue"
},
  "geometry": {"coordinates":[4.4574651718,50.8251342773],"type":"Point"}
}