{
  "type": "Feature",
  "properties": {
    "addr:full":"Broekstraat 47 Leuven (heverlee) Vlaams-Brabant 3001",
    "addr:housenumber":"47",
    "addr:postcode":"3001",
    "addr:street":"Broekstraat",
    "iso:country":"BE",
    "sg:address":"Broekstraat 47",
    "sg:city":"Leuven (heverlee)",
    "sg:classifiers":[
        {
            "category":"Wholesale",
            "subcategory":"Tobacco Products",
            "type":"Manufacturing & Wholesale Goods"
        }
    ],
    "sg:phone":"+32 16 30 96 98",
    "sg:postcode":"3001",
    "sg:province":"Vlaams-Brabant",
    "sg:tags":[
        "-",
        "biotechnology",
        "installation",
        "equipment"
    ],
    "wof:name":"Remynd Nv",
    "wof:placetype":"venue"
},
  "geometry": {"coordinates":[4.7012338638,50.8668403625],"type":"Point"}
}