{
  "type": "Feature",
  "properties": {
    "addr:full":"Vinkenlaan 31 Bornem-branst Antwerpen 2830",
    "addr:housenumber":"31",
    "addr:postcode":"2830",
    "addr:street":"Vinkenlaan",
    "iso:country":"BE",
    "sg:address":"Vinkenlaan 31",
    "sg:city":"Bornem-branst",
    "sg:orig_category":"Royal Canin. Animaux domestiques and accessoires",
    "sg:phone":"+32 3 899 13 22",
    "sg:postcode":"2830",
    "sg:province":"Antwerpen",
    "wof:name":"Hugel",
    "wof:placetype":"venue"
},
  "geometry": {"coordinates":[4.355424881,51.0601081848],"type":"Point"}
}