{
  "type": "Feature",
  "properties": {
    "iso:country":"BE",
    "sg:address":"Puttestraat 67",
    "sg:city":"Stabroek",
    "sg:orig_category":"Herstelling horloges and juwelen Juwelen and horloges",
    "sg:phone":"+32 3 664 15 07",
    "sg:postcode":"2940",
    "sg:province":"Antwerpen",
    "wof:name":"Gold-vision",
    "wof:placetype":"venue"
},
  "geometry": {"coordinates":[4.3960337639,51.3539276123],"type":"Point"}
}