{
  "type": "Feature",
  "properties": {
    "addr:full":"Berkemei 161 Zoersel (halle) Antwerpen 2980",
    "addr:housenumber":"161",
    "addr:postcode":"2980",
    "addr:street":"Zoersel Halle",
    "iso:country":"BE",
    "sg:address":"Berkemei 161",
    "sg:city":"Zoersel (halle)",
    "sg:classifiers":[
        {
            "category":"Shopping",
            "subcategory":"Florist",
            "type":"Retail Goods"
        }
    ],
    "sg:phone":"+32 3 324 76 68",
    "sg:postcode":"2980",
    "sg:province":"Antwerpen",
    "wof:name":"Mertens-verspreet",
    "wof:placetype":"venue"
},
  "geometry": {"coordinates":[4.6638979912,51.2493934631],"type":"Point"}
}