{
  "type": "Feature",
  "properties": {
    "iso:country":"BE",
    "sg:address":"La Schockaertstraat 55",
    "sg:city":"Sint-pieters-leeuw",
    "sg:classifiers":[
        {
            "category":"Transit Center",
            "subcategory":"Freight",
            "type":"Transportation"
        }
    ],
    "sg:phone":"+32 2 377 50 70",
    "sg:postcode":"1600",
    "sg:province":"Vlaams-Brabant",
    "sg:tags":[
        "metallurgy",
        "pipe",
        "metalworking",
        "sheet"
    ],
    "wof:name":"Cassart Special Products Nv",
    "wof:placetype":"venue"
},
  "geometry": {"coordinates":[4.2829499245,50.8029403687],"type":"Point"}
}