{
  "type": "Feature",
  "properties": {
    "iso:country":"BE",
    "sg:address":"Rue Van Ysendyck 24",
    "sg:city":"Schaarbeek/schaerbeek",
    "sg:orig_category":"Enseignement maternel and primaire",
    "sg:phone":"+32 2 215 87 79",
    "sg:postcode":"1030",
    "sg:province":"Bruxelles-Capitale",
    "wof:name":"Basisschool",
    "wof:placetype":"venue"
},
  "geometry": {"coordinates":[4.3797907829,50.8686523438],"type":"Point"}
}