{
  "type": "Feature",
  "properties": {
    "iso:country":"BE",
    "sg:address":"Van Volxemlaan 85",
    "sg:city":"Vorst/forest",
    "sg:orig_category":"Kinderopvang",
    "sg:phone":"+32 2 347 58 93",
    "sg:postcode":"1190",
    "sg:province":"Bruxelles-Capitale",
    "wof:name":"Kinderdagverbl. Mallemuis",
    "wof:placetype":"venue"
},
  "geometry": {"coordinates":[4.3254871368,50.8161888123],"type":"Point"}
}