{
  "type": "Feature",
  "properties": {
    "addr:full":"Avenue Des Muguets 3 Braine-l'alleud Brabant Wallon 1420",
    "addr:housenumber":"3",
    "addr:postcode":"1420",
    "addr:street":"Avenue Des Muguets",
    "iso:country":"BE",
    "sg:address":"Avenue Des Muguets 3",
    "sg:city":"Braine-l'alleud",
    "sg:orig_category":"M\u00e9decins and sp\u00e9cialistes",
    "sg:phone":"+32 2 354 69 24",
    "sg:postcode":"1420",
    "sg:province":"Brabant Wallon",
    "wof:name":"Nathalie Boon",
    "wof:placetype":"venue"
},
  "geometry": {"coordinates":[-0.7004899979,47.369140625],"type":"Point"}
}