{
  "type": "Feature",
  "properties": {
    "iso:country":"BE",
    "sg:address":"Woeker 22",
    "sg:city":"Oudenaarde",
    "sg:orig_category":"Opticiens",
    "sg:phone":"+32 55 31 30 38",
    "sg:postcode":"9700",
    "sg:province":"Oost-Vlaanderen",
    "wof:name":"Ophtalmo Service",
    "wof:placetype":"venue"
},
  "geometry": {"coordinates":[3.6058239937,50.8453903198],"type":"Point"}
}