{
  "type": "Feature",
  "properties": {
    "addr:full":"Antwerpsesteenweg 358 Gent Oost-Vlaanderen 9040",
    "addr:housenumber":"358",
    "addr:postcode":"9040",
    "addr:street":"Antwerpsesteenweg;Oost-Vlaanderen",
    "iso:country":"BE",
    "sg:address":"Antwerpsesteenweg 358",
    "sg:city":"Gent",
    "sg:orig_category":"Banken and kredietinstellingen",
    "sg:phone":"+32 9 228 48 73",
    "sg:postcode":"9040",
    "sg:province":"Oost-Vlaanderen",
    "wof:name":"V.d.k. Spaarbank",
    "wof:placetype":"venue"
},
  "geometry": {"coordinates":[3.7489259243,51.0613517761],"type":"Point"}
}