{
  "type": "Feature",
  "properties": {
    "addr:full":"Boulevard De L'europe 3 Wavre Brabant Wallon 1301",
    "addr:housenumber":"3;1301",
    "addr:street":"Boulevard De L'Europe",
    "iso:country":"BE",
    "sg:address":"Boulevard De L'europe 3",
    "sg:city":"Wavre",
    "sg:orig_category":"Jeux and jouets. Supermarch\u00e9s. Hypermarch\u00e9s. Mat\u00e9riel de T\u00e9l\u00e9communication",
    "sg:phone":"+32 10 23 18 11",
    "sg:postcode":"1301",
    "sg:province":"Brabant Wallon",
    "wof:name":"Carrefour - Maxitec",
    "wof:placetype":"venue"
},
  "geometry": {"coordinates":[4.6100921631,50.7142791748],"type":"Point"}
}