{
  "type": "Feature",
  "properties": {
    "addr:full":"Wijngaardstraat 1a Diest Vlaams-Brabant 3290",
    "addr:housenumber":"1a",
    "addr:postcode":"3290",
    "addr:street":"Wijngaardstraat",
    "iso:country":"BE",
    "sg:address":"Wijngaardstraat 1a",
    "sg:city":"Diest",
    "sg:orig_category":"Kapsalons",
    "sg:phone":"+32 13 33 64 28",
    "sg:postcode":"3290",
    "sg:province":"Vlaams-Brabant",
    "wof:name":"Coiffure Ronny",
    "wof:placetype":"venue"
},
  "geometry": {"coordinates":[5.0574498177,50.9789848328],"type":"Point"}
}