{
  "type": "Feature",
  "properties": {
    "addr:full":"Rue Des Petites Carmes 19 Brussel/bruxelles Bruxelles-Capitale 1000",
    "addr:housenumber":"19",
    "addr:postcode":"1000",
    "addr:street":"Rue Des Petites Carmes;/",
    "iso:country":"BE",
    "sg:address":"Rue Des Petites Carmes 19",
    "sg:city":"Brussel/bruxelles",
    "sg:classifiers":[
        {
            "category":"Health Services",
            "subcategory":"Nursing And Care Facility",
            "type":"Services"
        }
    ],
    "sg:phone":"+32 2 501 80 99",
    "sg:postcode":"1000",
    "sg:province":"Bruxelles-Capitale",
    "sg:tags":[
        "public"
    ],
    "wof:name":"Minist\u00c8re Des Affaires Etrang\u00c8res",
    "wof:placetype":"venue"
},
  "geometry": {"coordinates":[4.3513898849,50.8584594727],"type":"Point"}
}