{
  "type": "Feature",
  "properties": {
    "iso:country":"BE",
    "sg:address":"Jagersweg 22",
    "sg:city":"Malle",
    "sg:orig_category":"Boekhouders",
    "sg:phone":"+32 3 385 21 10",
    "sg:postcode":"2390",
    "sg:province":"Antwerpen",
    "wof:name":"Marcel Wouters",
    "wof:placetype":"venue"
},
  "geometry": {"coordinates":[4.6487751007,51.2778434753],"type":"Point"}
}