{
  "type": "Feature",
  "properties": {
    "addr:full":"Weg Naar Zwartberg 362 Opglabbeek Limburg 3660",
    "addr:housenumber":"362",
    "addr:postcode":"3660",
    "addr:street":"Weg Naar Zwartberg",
    "iso:country":"BE",
    "sg:address":"Weg Naar Zwartberg 362",
    "sg:city":"Opglabbeek",
    "sg:classifiers":[
        {
            "category":"Health Services",
            "subcategory":"Health Practitioner",
            "type":"Services"
        }
    ],
    "sg:phone":"+32 89 85 74 54",
    "sg:postcode":"3660",
    "sg:province":"Limburg",
    "sg:tags":[
        "physiotherapist"
    ],
    "wof:name":"Cardeynaels Carl",
    "wof:placetype":"venue"
},
  "geometry": {"coordinates":[5.5387592316,51.0300598145],"type":"Point"}
}