{
  "type": "Feature",
  "properties": {
    "iso:country":"BE",
    "sg:address":"Venlosesteenweg 11",
    "sg:city":"Maaseik",
    "sg:orig_category":"Industri\u00eble and commerci\u00eble bouw Installatie van houten of kunststof schrijnwerk Plaatsen van vloer-",
    "sg:phone":"+32 89 56 42 42",
    "sg:postcode":"3680",
    "sg:province":"Limburg",
    "wof:name":"Van Montfort J",
    "wof:placetype":"venue"
},
  "geometry": {"coordinates":[5.795648098,51.09765625],"type":"Point"}
}