{
  "type": "Feature",
  "properties": {
    "iso:country":"BE",
    "sg:address":"Bollenberg 102",
    "sg:city":"Lubbeek",
    "sg:classifiers":[
        {
            "category":"Wholesale",
            "subcategory":"Plants",
            "type":"Manufacturing & Wholesale Goods"
        }
    ],
    "sg:phone":"+32 16 22 36 74",
    "sg:postcode":"3210",
    "sg:province":"Vlaams-Brabant",
    "sg:tags":[
        "decoration",
        "flower",
        "-"
    ],
    "wof:name":"Lammerhof (het)",
    "wof:placetype":"venue"
},
  "geometry": {"coordinates":[4.8153891563,50.8777809143],"type":"Point"}
}