{
  "type": "Feature",
  "properties": {
    "iso:country":"BE",
    "sg:address":"Rue Omer Lef\u00e8vre 36",
    "sg:city":"La Louvi\u00e8re",
    "sg:classifiers":[
        {
            "category":"Health Services",
            "subcategory":"Doctor",
            "type":"Services"
        }
    ],
    "sg:phone":"+32 64 22 81 78",
    "sg:postcode":"7100",
    "sg:province":"Hainaut",
    "sg:tags":[
        "medicinephysicians",
        "surgeon"
    ],
    "wof:name":"Luyx A",
    "wof:placetype":"venue"
},
  "geometry": {"coordinates":[4.1942281723,50.4759635925],"type":"Point"}
}