{
  "type": "Feature",
  "properties": {
    "addr:full":"Rue A. Stevart 2 Liege Li\u00e8ge 4000",
    "addr:housenumber":"2",
    "addr:postcode":"4000",
    "addr:street":"Rue A. Stevart",
    "iso:country":"BE",
    "sg:address":"Rue A. Stevart 2",
    "sg:city":"Liege",
    "sg:orig_category":"Diverse opleidingen and onderwijs",
    "sg:phone":"+32 4 366 90 50",
    "sg:postcode":"4000",
    "sg:province":"Li\u00e8ge",
    "wof:name":"Ste Formations",
    "wof:placetype":"venue"
},
  "geometry": {"coordinates":[5.541164875,50.6114616394],"type":"Point"}
}