{
  "type": "Feature",
  "properties": {
    "iso:country":"BE",
    "sg:address":"Rue De L` Universite 20",
    "sg:city":"Liege",
    "sg:orig_category":"R\u00e9parations d'appareils \u00e9lectrom\u00e9nagers. Mat\u00e9riel de T\u00e9l\u00e9communication. Electrom\u00e9nager, t\u00e9l\u00e9visions ",
    "sg:phone":"+32 4 223 24 96",
    "sg:postcode":"4000",
    "sg:province":"Li\u00e8ge",
    "wof:name":"Kr\u00cbfel",
    "wof:placetype":"venue"
},
  "geometry": {"coordinates":[5.5731167793,50.64220047],"type":"Point"}
}