{
  "type": "Feature",
  "properties": {
    "addr:full":"Route De L'etat 5b9 Lasne Brabant Wallon 1380",
    "addr:housenumber":"5b9",
    "addr:postcode":"1380",
    "addr:street":"Route De L'Etat",
    "iso:country":"BE",
    "sg:address":"Route De L'etat 5b9",
    "sg:city":"Lasne",
    "sg:orig_category":"Belastingconsulenten Diverse juridische dienstverlening",
    "sg:phone":"+32 2 633 54 12",
    "sg:postcode":"1380",
    "sg:province":"Brabant Wallon",
    "wof:name":"Algonquin Trust",
    "wof:placetype":"venue"
},
  "geometry": {"coordinates":[4.4789261818,50.6810188293],"type":"Point"}
}