{
  "type": "Feature",
  "properties": {
    "iso:country":"BE",
    "sg:address":"Rue Du Commerce 80",
    "sg:city":"Ciney",
    "sg:classifiers":[
        {
            "category":"Personal",
            "subcategory":"Beauty Salon",
            "type":"Services"
        }
    ],
    "sg:phone":"+32 83 21 84 00",
    "sg:postcode":"5590",
    "sg:province":"Namur",
    "sg:tags":[
        "lady",
        "-",
        "hairdressing"
    ],
    "wof:name":"Hair Club",
    "wof:placetype":"venue"
},
  "geometry": {"coordinates":[5.0964589119,50.292301178],"type":"Point"}
}