{
  "type": "Feature",
  "properties": {
    "iso:country":"BE",
    "sg:address":"Rozendaalstraat 29-31",
    "sg:city":"Alveringem",
    "sg:classifiers":[
        {
            "category":"Building & Trades",
            "subcategory":"Construction",
            "type":"Services"
        }
    ],
    "sg:phone":"+32 58 28 81 21",
    "sg:postcode":"8690",
    "sg:province":"West-Vlaanderen",
    "sg:tags":[
        "carpenter"
    ],
    "wof:name":"Timmerbedrijf M. Pauwels Bvba",
    "wof:placetype":"venue"
},
  "geometry": {"coordinates":[2.7203729153,51.0141868591],"type":"Point"}
}