{
  "type": "Feature",
  "properties": {
    "iso:country":"BE",
    "sg:address":"Veurnestraat 8",
    "sg:city":"Diksmuide",
    "sg:orig_category":"Kapsalons",
    "sg:phone":"+32 51 55 56 01",
    "sg:postcode":"8600",
    "sg:province":"West-Vlaanderen",
    "wof:name":"Hair Design Lies",
    "wof:placetype":"venue"
},
  "geometry": {"coordinates":[2.7927050591,51.0733985901],"type":"Point"}
}