{
  "type": "Feature",
  "properties": {
    "iso:country":"BE",
    "sg:address":"Oudenaardsestraat 57",
    "sg:city":"Brakel",
    "sg:orig_category":"Installation \u00e9lectrique r\u00e9sidentielle",
    "sg:phone":"+32 55 42 39 33",
    "sg:postcode":"9660",
    "sg:province":"Oost-Vlaanderen",
    "wof:name":"Bruneel",
    "wof:placetype":"venue"
},
  "geometry": {"coordinates":[3.7302520275,50.8147277832],"type":"Point"}
}