{
  "type": "Feature",
  "properties": {
    "addr:full":"Lindekensbaan 1d Nijlen (kessel) Antwerpen 2560",
    "addr:housenumber":"1d",
    "addr:postcode":"2560",
    "addr:street":"Lindekensbaan",
    "iso:country":"BE",
    "sg:address":"Lindekensbaan 1d",
    "sg:city":"Nijlen (kessel)",
    "sg:classifiers":[
        {
            "category":"Manufacturing",
            "subcategory":"Metals",
            "type":"Manufacturing & Wholesale Goods"
        }
    ],
    "sg:phone":"+32 477 13 86 14",
    "sg:postcode":"2560",
    "sg:province":"Antwerpen",
    "sg:tags":[
        "ironwork"
    ],
    "wof:name":"Theunis Bouwsmederij",
    "wof:placetype":"venue"
},
  "geometry": {"coordinates":[4.6175179482,51.1519775391],"type":"Point"}
}