{
  "type": "Feature",
  "properties": {
    "addr:full":"Rue Du Perron 1a Courcelles (gouy-lez-pi\u00e9ton) Hainaut 6181",
    "addr:housenumber":"1a",
    "addr:postcode":"6181",
    "addr:street":"Rue Du Perron",
    "iso:country":"BE",
    "sg:address":"Rue Du Perron 1a",
    "sg:city":"Courcelles (gouy-lez-pi\u00e9ton)",
    "sg:classifiers":[
        {
            "category":"Autos & Motor Vehicles",
            "subcategory":"Motorcycle Sales",
            "type":"Retail Goods"
        }
    ],
    "sg:phone":"+32 71 84 22 97",
    "sg:postcode":"6181",
    "sg:province":"Hainaut",
    "sg:tags":[
        "scooter",
        "-",
        "moped"
    ],
    "wof:name":"Alberghini O",
    "wof:placetype":"venue"
},
  "geometry": {"coordinates":[4.3284378052,50.4860267639],"type":"Point"}
}