{
  "type": "Feature",
  "properties": {
    "iso:country":"BE",
    "sg:address":"Kachtemsestraat 22",
    "sg:city":"Izegem",
    "sg:classifiers":[
        {
            "category":"Building & Trades",
            "subcategory":"Electrical",
            "type":"Services"
        }
    ],
    "sg:phone":"+32 51 30 70 38",
    "sg:postcode":"8870",
    "sg:province":"West-Vlaanderen",
    "sg:tags":[
        "industrial",
        "-",
        "electric",
        "contractor"
    ],
    "wof:name":"Electro Vroman",
    "wof:placetype":"venue"
},
  "geometry": {"coordinates":[3.2099699974,50.9288597107],"type":"Point"}
}