{
  "type": "Feature",
  "properties": {
    "addr:full":"Rue Fontaine D'amour 16 Bruxelles (schaerbeek) Bruxelles-Capitale 1030",
    "addr:housenumber":"16",
    "addr:postcode":"1030",
    "addr:street":"Rue Fontaine D'Amour",
    "iso:country":"BE",
    "sg:address":"Rue Fontaine D'amour 16",
    "sg:city":"Bruxelles (schaerbeek)",
    "sg:classifiers":[
        {
            "category":"Freight",
            "type":"Transportation"
        }
    ],
    "sg:phone":"+32 2 242 51 77",
    "sg:postcode":"1030",
    "sg:province":"Bruxelles-Capitale",
    "sg:tags":[
        "express",
        "transport"
    ],
    "wof:name":"All Fret",
    "wof:placetype":"venue"
},
  "geometry": {"coordinates":[4.3826241493,50.8605995178],"type":"Point"}
}