{
  "type": "Feature",
  "properties": {
    "addr:full":"Sweynbeerstraat 42 Zemst (elewijt) Vlaams-Brabant 1982",
    "addr:housenumber":"42",
    "addr:postcode":"1982",
    "addr:street":"Sweynbeerstraat",
    "iso:country":"BE",
    "sg:address":"Sweynbeerstraat 42",
    "sg:city":"Zemst (elewijt)",
    "sg:classifiers":[
        {
            "category":"Airport",
            "subcategory":"International",
            "type":"Transportation"
        }
    ],
    "sg:phone":"+32 475 92 53 32",
    "sg:postcode":"1982",
    "sg:province":"Vlaams-Brabant",
    "sg:tags":[
        "-",
        "transport"
    ],
    "wof:name":"Milis",
    "wof:placetype":"venue"
},
  "geometry": {"coordinates":[4.4973697662,50.9663658142],"type":"Point"}
}