{
  "type": "Feature",
  "properties": {
    "iso:country":"BE",
    "sg:address":"Grote Kerkstraat 7",
    "sg:city":"Kinrooi",
    "sg:classifiers":[
        {
            "category":"Cafe",
            "type":"Food & Drink"
        }
    ],
    "sg:phone":"+32 89 70 24 88",
    "sg:postcode":"3640",
    "sg:province":"Limburg",
    "sg:tags":[
        "caf\u00e9s"
    ],
    "wof:name":"Parochiale Werken Kinrooi",
    "wof:placetype":"venue"
},
  "geometry": {"coordinates":[5.7406039238,51.1451072693],"type":"Point"}
}