{
  "type": "Feature",
  "properties": {
    "addr:full":"Rue Des Croisiers 20 Namur Namur 5000",
    "addr:housenumber":"20",
    "addr:postcode":"5000",
    "addr:street":"Rue Des Croisiers",
    "iso:country":"BE",
    "sg:address":"Rue Des Croisiers 20",
    "sg:city":"Namur",
    "sg:orig_category":"Jeux and jouets",
    "sg:phone":"+32 81 22 12 29",
    "sg:postcode":"5000",
    "sg:province":"Namur",
    "wof:name":"Mary Hobby",
    "wof:placetype":"venue"
},
  "geometry": {"coordinates":[4.8645401001,50.4674224854],"type":"Point"}
}