{
  "type": "Feature",
  "properties": {
    "iso:country":"BE",
    "sg:address":"Antwerpsesteenweg 265",
    "sg:city":"Mechelen",
    "sg:classifiers":[
        {
            "category":"Retail",
            "subcategory":"Repair Shop",
            "type":"Services"
        }
    ],
    "sg:phone":"+32 15 21 82 49",
    "sg:postcode":"2800",
    "sg:province":"Antwerpen",
    "sg:tags":[
        "upholsterer"
    ],
    "wof:name":"Arista Bvba",
    "wof:placetype":"venue"
},
  "geometry": {"coordinates":[4.4599847794,51.0585594177],"type":"Point"}
}