{
  "type": "Feature",
  "properties": {
    "iso:country":"BE",
    "sg:address":"Rue De Gobc\u00c9 83",
    "sg:city":"Blegny",
    "sg:orig_category":"Plomberie, chauffage and installations sanitaires. Quincailleries. Installation de piscines",
    "sg:phone":"+32 4 387 71 21",
    "sg:postcode":"4670",
    "sg:province":"Li\u00e8ge",
    "wof:name":"Swinnen F.",
    "wof:placetype":"venue"
},
  "geometry": {"coordinates":[5.7335300446,50.6707000732],"type":"Point"}
}