{
  "type": "Feature",
  "properties": {
    "addr:full":"Rue Marie-th\u00e9r\u00e8se 114 Box 114 Bruxelles (saint-josse-ten-noode) Bruxelles-Capitale 1210",
    "addr:housenumber":"114",
    "addr:postcode":"1210",
    "addr:street":"Rue Marie-The\u0301Re\u0300Se;Box 114",
    "iso:country":"BE",
    "sg:address":"Rue Marie-th\u00e9r\u00e8se 114 Box 114",
    "sg:city":"Bruxelles (saint-josse-ten-noode)",
    "sg:classifiers":[
        {
            "category":"Professional",
            "subcategory":"Art Services",
            "type":"Services"
        }
    ],
    "sg:phone":"+32 2 218 56 48",
    "sg:postcode":"1210",
    "sg:province":"Bruxelles-Capitale",
    "sg:tags":[
        "-",
        "painter",
        "artist"
    ],
    "wof:name":"De Ti\u00e8ge M",
    "wof:placetype":"venue"
},
  "geometry": {"coordinates":[4.3727931976,50.8497467041],"type":"Point"}
}