{
  "type": "Feature",
  "properties": {
    "addr:full":"Leopold Debruynestraat 56 Brugge West-Vlaanderen 8310",
    "addr:housenumber":"56",
    "addr:postcode":"8310",
    "addr:street":"Debruynestraat",
    "iso:country":"BE",
    "sg:address":"Leopold Debruynestraat 56",
    "sg:city":"Brugge",
    "sg:orig_category":"Enseignement maternel and primaire",
    "sg:phone":"+32 50 37 76 78",
    "sg:postcode":"8310",
    "sg:province":"West-Vlaanderen",
    "wof:name":"B.s.g.o. De Tandem",
    "wof:placetype":"venue"
},
  "geometry": {"coordinates":[3.2521560192,51.2108230591],"type":"Point"}
}