{
  "type": "Feature",
  "properties": {
    "iso:country":"BE",
    "sg:address":"Rue De La D\u00c9portation 27",
    "sg:city":"La Louviere",
    "sg:orig_category":"M\u00e9decins and sp\u00e9cialistes",
    "sg:phone":"+32 64 26 37 64",
    "sg:postcode":"7100",
    "sg:province":"Hainaut",
    "wof:name":"Philippe Greant",
    "wof:placetype":"venue"
},
  "geometry": {"coordinates":[4.199860096,50.4648284912],"type":"Point"}
}