{
  "type": "Feature",
  "properties": {
    "iso:country":"BE",
    "sg:address":"Olmenstraat 7",
    "sg:city":"Hasselt",
    "sg:orig_category":"Antiek",
    "sg:phone":"+32 11 28 19 57",
    "sg:postcode":"3500",
    "sg:province":"Limburg",
    "wof:name":"Kathan",
    "wof:placetype":"venue"
},
  "geometry": {"coordinates":[5.3239789009,50.925075531],"type":"Point"}
}