{
  "type": "Feature",
  "properties": {
    "iso:country":"BE",
    "sg:address":"Rue De Fer 24",
    "sg:city":"Namur",
    "sg:orig_category":"Biblioth\u00e8ques and archives publiques",
    "sg:phone":"+32 81 22 43 62",
    "sg:postcode":"5000",
    "sg:province":"Namur",
    "wof:name":"Soci\u00c9t\u00c9 Arch\u00c9ologique",
    "wof:placetype":"venue"
},
  "geometry": {"coordinates":[4.865377903,50.4655151367],"type":"Point"}
}