{
  "type": "Feature",
  "properties": {
    "addr:full":"Deinzestr.65 Oudenaarde Oost-Vlaanderen 9700",
    "addr:postcode":"9700",
    "addr:street":"Oost-Vlaanderen",
    "iso:country":"BE",
    "sg:address":"Deinzestr.65",
    "sg:city":"Oudenaarde",
    "sg:classifiers":[
        {
            "category":"Shopping",
            "subcategory":"Computers & Home Electronics",
            "type":"Retail Goods"
        }
    ],
    "sg:phone":"+32 55 38 82 84",
    "sg:postcode":"9700",
    "sg:province":"Oost-Vlaanderen",
    "sg:tags":[
        "household",
        "appliance",
        "telecommunication",
        "audio-visual"
    ],
    "wof:name":"Anex Nv",
    "wof:placetype":"venue"
},
  "geometry": {"coordinates":[3.5924100876,50.8542900085],"type":"Point"}
}