{
  "type": "Feature",
  "properties": {
    "iso:country":"BE",
    "sg:address":"Van Souststraat 612",
    "sg:city":"Dilbeek",
    "sg:classifiers":[
        {
            "category":"Restaurant",
            "type":"Food & Drink"
        }
    ],
    "sg:phone":"+32 2 466 34 60",
    "sg:postcode":"1700",
    "sg:province":"Vlaams-Brabant",
    "sg:tags":[
        "caf\u00e9s"
    ],
    "wof:name":"Taverne Monico Tourelle",
    "wof:placetype":"venue"
},
  "geometry": {"coordinates":[4.2842798233,50.8456802368],"type":"Point"}
}