{
  "type": "Feature",
  "properties": {
    "iso:country":"BE",
    "sg:address":"Rue De Masbourg 10",
    "sg:city":"Nassogne",
    "sg:orig_category":"Instituts de beaut\u00e9",
    "sg:phone":"+32 84 22 22 78",
    "sg:postcode":"6950",
    "sg:province":"Luxembourg",
    "wof:name":"Anne France",
    "wof:placetype":"venue"
},
  "geometry": {"coordinates":[5.3400068283,50.1281547546],"type":"Point"}
}