{
  "type": "Feature",
  "properties": {
    "iso:country":"BE",
    "sg:address":"Beverlo-dorp 24",
    "sg:city":"Beringen",
    "sg:orig_category":"Kapsalons",
    "sg:phone":"+32 11 40 11 26",
    "sg:postcode":"3581",
    "sg:province":"Limburg",
    "wof:name":"Caroline Spysschaert",
    "wof:placetype":"venue"
},
  "geometry": {"coordinates":[5.2210588455,51.0876960754],"type":"Point"}
}