{
  "type": "Feature",
  "properties": {
    "addr:full":"Rue Bruy\u00e8re 91 Ellezelles Hainaut 7890",
    "addr:housenumber":"91",
    "addr:postcode":"7890",
    "addr:street":"Rue Bruye\u0300Re",
    "iso:country":"BE",
    "sg:address":"Rue Bruy\u00e8re 91",
    "sg:city":"Ellezelles",
    "sg:classifiers":[
        {
            "category":"Health Services",
            "subcategory":"Doctor",
            "type":"Services"
        }
    ],
    "sg:phone":"+32 68 54 26 43",
    "sg:postcode":"7890",
    "sg:province":"Hainaut",
    "sg:tags":[
        "medicinephysicians",
        "surgeon"
    ],
    "wof:name":"Burion J",
    "wof:placetype":"venue"
},
  "geometry": {"coordinates":[3.7050209045,50.7373161316],"type":"Point"}
}