{
  "type": "Feature",
  "properties": {
    "addr:full":"Belven 118ba Raeren/raeren Li\u00e8ge 4730",
    "addr:postcode":"4730",
    "addr:street":"Belven 118Ba",
    "iso:country":"BE",
    "sg:address":"Belven 118ba",
    "sg:city":"Raeren/raeren",
    "sg:orig_category":"Stations-service and carburants. D\u00e9taillants en pi\u00e8ces and accessoires de voitures. Combustibles",
    "sg:phone":"+32 87 85 15 22",
    "sg:postcode":"4730",
    "sg:province":"Li\u00e8ge",
    "wof:name":"Fe. Radermacher",
    "wof:placetype":"venue"
},
  "geometry": {"coordinates":[6.0901751518,50.7137184143],"type":"Point"}
}