{
  "type": "Feature",
  "properties": {
    "iso:country":"BE",
    "sg:address":"Nevelestraat 34",
    "sg:city":"Aalter",
    "sg:orig_category":"ACCOUNTANTS Belastingconsulenten Diverse juridische dienstverlening",
    "sg:phone":"+32 51 68 92 16",
    "sg:postcode":"9880",
    "sg:province":"Oost-Vlaanderen",
    "wof:name":"Pierre Sergeant",
    "wof:placetype":"venue"
},
  "geometry": {"coordinates":[3.4740669727,51.0454177856],"type":"Point"}
}