{
  "type": "Feature",
  "properties": {
    "iso:country":"BE",
    "sg:address":"Groenstraat 55",
    "sg:city":"Tongeren",
    "sg:orig_category":"Goederenvervoer over de weg",
    "sg:phone":"+32 12 26 31 36",
    "sg:postcode":"3700",
    "sg:province":"Limburg",
    "wof:name":"Faro Express",
    "wof:placetype":"venue"
},
  "geometry": {"coordinates":[5.4541749954,50.7900543213],"type":"Point"}
}