{
  "type": "Feature",
  "properties": {
    "addr:full":"Windmolenstraat 11 Oudenaarde Oost-Vlaanderen 9700",
    "addr:housenumber":"11",
    "addr:postcode":"9700",
    "addr:street":"Windmolenstraat",
    "iso:country":"BE",
    "sg:address":"Windmolenstraat 11",
    "sg:city":"Oudenaarde",
    "sg:classifiers":[
        {
            "category":"Personal",
            "subcategory":"Beauty Salon",
            "type":"Services"
        }
    ],
    "sg:phone":"+32 55 31 40 33",
    "sg:postcode":"9700",
    "sg:province":"Oost-Vlaanderen",
    "sg:tags":[
        "lady",
        "-",
        "hairdressing"
    ],
    "wof:name":"Ingrid",
    "wof:placetype":"venue"
},
  "geometry": {"coordinates":[3.5886199474,50.8523750305],"type":"Point"}
}