{
  "type": "Feature",
  "properties": {
    "iso:country":"BE",
    "sg:address":"Rue De Tongres 253a",
    "sg:city":"Oupeye (haccourt)",
    "sg:classifiers":[
        {
            "category":"Manufacturing",
            "subcategory":"Glass & Minerals",
            "type":"Manufacturing & Wholesale Goods"
        }
    ],
    "sg:phone":"+32 4 379 61 76",
    "sg:postcode":"4684",
    "sg:province":"Li\u00e8ge",
    "sg:tags":[
        "safety"
    ],
    "wof:name":"Campagnolo & Fils",
    "wof:placetype":"venue"
},
  "geometry": {"coordinates":[5.6547789574,50.7404136658],"type":"Point"}
}