{
  "type": "Feature",
  "properties": {
    "addr:full":"Neringenstraat 59 Tielt West-Vlaanderen 8700",
    "addr:housenumber":"59",
    "addr:postcode":"8700",
    "addr:street":"Neringenstraat",
    "iso:country":"BE",
    "sg:address":"Neringenstraat 59",
    "sg:city":"Tielt",
    "sg:orig_category":"Traitement and fa\u00e7onnage de la pierre. Magasins sp\u00e9cialis\u00e9s",
    "sg:phone":"+32 51 63 35 04",
    "sg:postcode":"8700",
    "sg:province":"West-Vlaanderen",
    "wof:name":"Marmerbedrijf Bearelle",
    "wof:placetype":"venue"
},
  "geometry": {"coordinates":[3.416877985,51.0005111694],"type":"Point"}
}