{
  "type": "Feature",
  "properties": {
    "addr:full":"Longvilly 14 Bastogne Luxembourg 6600",
    "addr:housenumber":"14",
    "addr:postcode":"6600",
    "addr:street":"Longvilly",
    "iso:country":"BE",
    "sg:address":"Longvilly 14",
    "sg:city":"Bastogne",
    "sg:orig_category":"Eleveurs de bovins",
    "sg:phone":"+32 61 21 28 02",
    "sg:postcode":"6600",
    "sg:province":"Luxembourg",
    "wof:name":"Raymond Thimothee",
    "wof:placetype":"venue"
},
  "geometry": {"coordinates":[5.7148199081,50.0007820129],"type":"Point"}
}