{
  "type": "Feature",
  "properties": {
    "addr:full":"Chauss\u00e9e De Namur 67 Nivelles Brabant Wallon 1400",
    "addr:housenumber":"67",
    "addr:postcode":"1400",
    "addr:street":"Chausse\u0301E De Namur",
    "iso:country":"BE",
    "sg:address":"Chauss\u00e9e De Namur 67",
    "sg:city":"Nivelles",
    "sg:classifiers":[
        {
            "category":"Retail",
            "subcategory":"Auto Repair",
            "type":"Services"
        }
    ],
    "sg:phone":"+32 67 21 51 11",
    "sg:postcode":"1400",
    "sg:province":"Brabant Wallon",
    "sg:tags":[
        "garage"
    ],
    "wof:name":"Weber Ch Sprl",
    "wof:placetype":"venue"
},
  "geometry": {"coordinates":[4.3584051132,50.5973587036],"type":"Point"}
}