{
  "type": "Feature",
  "properties": {
    "addr:full":"Zeelaan 110 De Panne West-Vlaanderen 8660",
    "addr:housenumber":"110",
    "addr:postcode":"8660",
    "addr:street":"Zeelaan",
    "iso:country":"BE",
    "sg:address":"Zeelaan 110",
    "sg:city":"De Panne",
    "sg:classifiers":[
        {
            "category":"Shopping",
            "subcategory":"Shoes",
            "type":"Retail Goods"
        }
    ],
    "sg:phone":"+32 58 41 35 66",
    "sg:postcode":"8660",
    "sg:province":"West-Vlaanderen",
    "sg:tags":[
        "slipper",
        "-"
    ],
    "wof:name":"Pillini",
    "wof:placetype":"venue"
},
  "geometry": {"coordinates":[2.592468977,51.1004638672],"type":"Point"}
}