{
  "type": "Feature",
  "properties": {
    "addr:full":"Rue Des Bruy\u00e8res 2 Grez-doiceau (biez) Brabant Wallon 1390",
    "addr:housenumber":"2",
    "addr:postcode":"1390",
    "addr:street":"Rue Des Bruye\u0300Res",
    "iso:country":"BE",
    "sg:address":"Rue Des Bruy\u00e8res 2",
    "sg:city":"Grez-doiceau (biez)",
    "sg:classifiers":[
        {
            "category":"Professional",
            "subcategory":"Art Services",
            "type":"Services"
        }
    ],
    "sg:phone":"+32 10 84 58 14",
    "sg:postcode":"1390",
    "sg:province":"Brabant Wallon",
    "sg:tags":[
        "-",
        "painter",
        "artist"
    ],
    "wof:name":"Delta Plane",
    "wof:placetype":"venue"
},
  "geometry": {"coordinates":[4.7022461891,50.7252235413],"type":"Point"}
}