{
  "type": "Feature",
  "properties": {
    "addr:full":"Chauss\u00c9e De Bruxelles 330 Tournai Hainaut 7500",
    "addr:housenumber":"330",
    "addr:postcode":"7500",
    "addr:street":"Chausse\u0301E De Bruxelles",
    "iso:country":"BE",
    "sg:address":"Chauss\u00c9e De Bruxelles 330",
    "sg:city":"Tournai",
    "sg:orig_category":"Artsen and specialisten",
    "sg:phone":"+32 69 23 21 48",
    "sg:postcode":"7500",
    "sg:province":"Hainaut",
    "wof:name":"Nadine Van Den Broeck",
    "wof:placetype":"venue"
},
  "geometry": {"coordinates":[3.4198899269,50.6035385132],"type":"Point"}
}