{
  "type": "Feature",
  "properties": {
    "addr:full":"Rue De Boussu 41 Saint-ghislain Hainaut 7333",
    "addr:housenumber":"41",
    "addr:postcode":"7333",
    "addr:street":"Rue De Boussu;Hainaut",
    "iso:country":"BE",
    "sg:address":"Rue De Boussu 41",
    "sg:city":"Saint-ghislain",
    "sg:orig_category":"Epiceries",
    "sg:phone":"+32 65 62 17 75",
    "sg:postcode":"7333",
    "sg:province":"Hainaut",
    "wof:name":"Marie Vanesche",
    "wof:placetype":"venue"
},
  "geometry": {"coordinates":[3.7857708931,50.4550971985],"type":"Point"}
}