{
  "type": "Feature",
  "properties": {
    "iso:country":"BE",
    "sg:address":"Markekerkstraat 29",
    "sg:city":"Kortrijk",
    "sg:orig_category":"Boucheries",
    "sg:phone":"+32 56 20 15 18",
    "sg:postcode":"8510",
    "sg:province":"West-Vlaanderen",
    "wof:name":"Slagerij 't Groothof",
    "wof:placetype":"venue"
},
  "geometry": {"coordinates":[3.2319550514,50.8076820374],"type":"Point"}
}