{
  "type": "Feature",
  "properties": {
    "iso:country":"BE",
    "sg:address":"Bulmolenweg 24",
    "sg:city":"Dentergem (markegem)",
    "sg:classifiers":[
        {
            "category":"Building & Trades",
            "subcategory":"Landscaping Services",
            "type":"Services"
        }
    ],
    "sg:phone":"+32 51 63 71 31",
    "sg:postcode":"8720",
    "sg:province":"West-Vlaanderen",
    "sg:tags":[
        "gardening",
        "garden",
        "maintenance"
    ],
    "wof:name":"De Rore B",
    "wof:placetype":"venue"
},
  "geometry": {"coordinates":[3.3962569237,50.9469070435],"type":"Point"}
}