{
  "type": "Feature",
  "properties": {
    "iso:country":"BE",
    "sg:address":"Rue De Sart Lez Moulin 6",
    "sg:city":"Courcelles",
    "sg:classifiers":[
        {
            "category":"Food & Beverages",
            "subcategory":"Groceries & Convenience Stores",
            "type":"Retail Goods"
        }
    ],
    "sg:phone":"+32 71 46 17 29",
    "sg:postcode":"6180",
    "sg:province":"Hainaut",
    "sg:tags":[
        "grocer"
    ],
    "wof:name":"Caf",
    "wof:placetype":"venue"
},
  "geometry": {"coordinates":[4.3576998711,50.4420700073],"type":"Point"}
}