{
  "type": "Feature",
  "properties": {
    "addr:full":"Rue Du Village 24 Orp-jauche Brabant Wallon 1350",
    "addr:housenumber":"24",
    "addr:postcode":"1350",
    "addr:street":"Rue Du Village",
    "iso:country":"BE",
    "sg:address":"Rue Du Village 24",
    "sg:city":"Orp-jauche",
    "sg:classifiers":[
        {
            "category":"Arena",
            "subcategory":"Sports Club",
            "type":"Entertainment"
        }
    ],
    "sg:phone":"+32 19 63 36 76",
    "sg:postcode":"1350",
    "sg:province":"Brabant Wallon",
    "sg:tags":[
        "de"
    ],
    "wof:name":"Tennis De La Cure",
    "wof:placetype":"venue"
},
  "geometry": {"coordinates":[4.97920084,50.6738891602],"type":"Point"}
}