{
  "type": "Feature",
  "properties": {
    "addr:full":"Lange Lobroekstraat 39 Antwerpen Antwerpen 2060",
    "addr:housenumber":"39",
    "addr:postcode":"2060",
    "addr:street":"Lange Lobroekstraat",
    "iso:country":"BE",
    "sg:address":"Lange Lobroekstraat 39",
    "sg:city":"Antwerpen",
    "sg:classifiers":[
        {
            "category":"Bars & Pubs",
            "type":"Food & Drink"
        }
    ],
    "sg:phone":"+32 3 235 24 39",
    "sg:postcode":"2060",
    "sg:province":"Antwerpen",
    "wof:name":"Draver (den)",
    "wof:placetype":"venue"
},
  "geometry": {"coordinates":[4.4335727692,51.2286911011],"type":"Point"}
}