{
  "type": "Feature",
  "properties": {
    "addr:full":"Suikerstraat 10 Moerbeke (moerbeke-waas) Oost-Vlaanderen 9180",
    "addr:housenumber":"10",
    "addr:postcode":"9180",
    "addr:street":"Suikerstraat",
    "iso:country":"BE",
    "sg:address":"Suikerstraat 10",
    "sg:city":"Moerbeke (moerbeke-waas)",
    "sg:orig_category":"Non-Classified Establishments",
    "sg:phone":"+32 9 346 91 88",
    "sg:postcode":"9180",
    "sg:province":"Oost-Vlaanderen",
    "wof:name":"De Jaeck D",
    "wof:placetype":"venue"
},
  "geometry": {"coordinates":[3.94987607,51.1741218567],"type":"Point"}
}