{
  "type": "Feature",
  "properties": {
    "addr:full":"Lange Akker 12 Zele Oost-Vlaanderen 9240",
    "addr:housenumber":"12",
    "addr:postcode":"9240",
    "addr:street":"Lange Akker",
    "iso:country":"BE",
    "sg:address":"Lange Akker 12",
    "sg:city":"Zele",
    "sg:classifiers":[
        {
            "category":"Cafe",
            "type":"Food & Drink"
        }
    ],
    "sg:phone":"+32 52 45 09 79",
    "sg:postcode":"9240",
    "sg:province":"Oost-Vlaanderen",
    "sg:tags":[
        "caf\u00e9s"
    ],
    "wof:name":"Tenniscentrum Topspin",
    "wof:placetype":"venue"
},
  "geometry": {"coordinates":[4.0290970802,51.0671768188],"type":"Point"}
}