{
  "type": "Feature",
  "properties": {
    "iso:country":"BE",
    "sg:address":"Pastoor De Molderlaan 2",
    "sg:city":"Malle",
    "sg:orig_category":"Boekhouders",
    "sg:phone":"+32 3 309 92 41",
    "sg:postcode":"2390",
    "sg:province":"Antwerpen",
    "wof:name":"Paul Segers",
    "wof:placetype":"venue"
},
  "geometry": {"coordinates":[4.7305688858,51.302154541],"type":"Point"}
}