{
  "type": "Feature",
  "properties": {
    "iso:country":"BE",
    "sg:address":"Kastanjelaan 1",
    "sg:city":"Wingene (zwevezele)",
    "sg:classifiers":[
        {
            "category":"Health Services",
            "subcategory":"Dentist",
            "type":"Services"
        }
    ],
    "sg:phone":"+32 51 61 22 31",
    "sg:postcode":"8750",
    "sg:province":"West-Vlaanderen",
    "wof:name":"Barbier K",
    "wof:placetype":"venue"
},
  "geometry": {"coordinates":[3.2173860073,51.0356559753],"type":"Point"}
}