{
  "type": "Feature",
  "properties": {
    "iso:country":"BE",
    "sg:address":"Rue De La Blocqui\u00e8re 19",
    "sg:city":"Mont-saint-guibert",
    "sg:classifiers":[
        {
            "category":"Building & Trades",
            "subcategory":"Cleaning & Sanitation",
            "type":"Services"
        }
    ],
    "sg:phone":"+32 10 65 76 92",
    "sg:postcode":"1435",
    "sg:province":"Brabant Wallon",
    "sg:tags":[
        "janitor"
    ],
    "wof:name":"Soudey D",
    "wof:placetype":"venue"
},
  "geometry": {"coordinates":[4.6077451706,50.6314735413],"type":"Point"}
}