{
  "type": "Feature",
  "properties": {
    "addr:full":"Zeedijk-het Zoute 704 Knokke-heist (knokke) West-Vlaanderen 8300",
    "addr:housenumber":"704",
    "addr:postcode":"8300",
    "addr:street":"Zoute",
    "iso:country":"BE",
    "sg:address":"Zeedijk-het Zoute 704",
    "sg:city":"Knokke-heist (knokke)",
    "sg:classifiers":[
        {
            "category":"Travel",
            "subcategory":"Hotels & Motels",
            "type":"Entertainment"
        }
    ],
    "sg:phone":"+32 50 61 99 11",
    "sg:postcode":"8300",
    "sg:province":"West-Vlaanderen",
    "wof:name":"Hotel Des Nations",
    "wof:placetype":"venue"
},
  "geometry": {"coordinates":[3.3267199993,51.3504714966],"type":"Point"}
}