{
  "type": "Feature",
  "properties": {
    "iso:country":"BE",
    "sg:address":"Dorpsstraat 89",
    "sg:city":"Kortenaken",
    "sg:orig_category":"Bruids- and ceremoniekledij Dameskledingzaken Herenkledingzaken",
    "sg:phone":"+32 11 58 74 39",
    "sg:postcode":"3470",
    "sg:province":"Vlaams-Brabant",
    "wof:name":"Modehuis Magda",
    "wof:placetype":"venue"
},
  "geometry": {"coordinates":[5.0360360146,50.8735542297],"type":"Point"}
}