{
  "type": "Feature",
  "properties": {
    "iso:country":"BE",
    "sg:address":"B\u00fcllingen 205",
    "sg:city":"B\u00fcllingen",
    "sg:classifiers":[
        {
            "category":"Cinema",
            "subcategory":"Movie Theater",
            "type":"Entertainment"
        }
    ],
    "sg:phone":"+32 80 64 72 14",
    "sg:postcode":"4760",
    "sg:province":"Li\u00e8ge",
    "wof:name":"Scala Kino",
    "wof:placetype":"venue"
},
  "geometry": {"coordinates":[6.2557492256,50.4061813354],"type":"Point"}
}