{
  "type": "Feature",
  "properties": {
    "iso:country":"BE",
    "sg:address":"Rue Fran\u00e7ois Chefnay 16",
    "sg:city":"Fl\u00e9malle (ivoz-ramet)",
    "sg:classifiers":[
        {
            "category":"Building & Trades",
            "subcategory":"Locksmith",
            "type":"Services"
        }
    ],
    "sg:phone":"+32 4 275 21 73",
    "sg:postcode":"4400",
    "sg:province":"Li\u00e8ge",
    "sg:tags":[
        "lock",
        "key"
    ],
    "wof:name":"Ars\u00e8ne Lupin",
    "wof:placetype":"venue"
},
  "geometry": {"coordinates":[5.4576430321,50.5693130493],"type":"Point"}
}