{
  "type": "Feature",
  "properties": {
    "addr:full":"Hougoumontlaan 4 Ukkel/uccle Bruxelles-Capitale 1180",
    "addr:housenumber":"4",
    "addr:postcode":"1180",
    "addr:street":"Hougoumontlaan;/",
    "iso:country":"BE",
    "sg:address":"Hougoumontlaan 4",
    "sg:city":"Ukkel/uccle",
    "sg:classifiers":[
        {
            "category":"Professional",
            "subcategory":"Accounting & Tax Preparation",
            "type":"Services"
        }
    ],
    "sg:phone":"+32 2 375 59 19",
    "sg:postcode":"1180",
    "sg:province":"Bruxelles-Capitale",
    "sg:tags":[
        "accountant"
    ],
    "wof:name":"Roland Bougard",
    "wof:placetype":"venue"
},
  "geometry": {"coordinates":[4.3813557625,50.7752151489],"type":"Point"}
}