{
  "type": "Feature",
  "properties": {
    "iso:country":"BE",
    "sg:address":"Antwerpsestraat 27",
    "sg:city":"Mortsel",
    "sg:orig_category":"Parfumeries",
    "sg:phone":"+32 3 449 21 48",
    "sg:postcode":"2640",
    "sg:province":"Antwerpen",
    "wof:name":"Huis Merces",
    "wof:placetype":"venue"
},
  "geometry": {"coordinates":[4.4476699829,51.1714324951],"type":"Point"}
}