{
  "type": "Feature",
  "properties": {
    "addr:full":"Heibrikstraat 41 Hoeselt Limburg 3730",
    "addr:housenumber":"41",
    "addr:postcode":"3730",
    "addr:street":"Heibrikstraat",
    "iso:country":"BE",
    "sg:address":"Heibrikstraat 41",
    "sg:city":"Hoeselt",
    "sg:classifiers":[
        {
            "category":"Building & Trades",
            "subcategory":"Construction",
            "type":"Services"
        }
    ],
    "sg:phone":"+32 89 41 29 72",
    "sg:postcode":"3730",
    "sg:province":"Limburg",
    "sg:tags":[
        "stucco",
        "contractor"
    ],
    "wof:name":"Haenen Jean",
    "wof:placetype":"venue"
},
  "geometry": {"coordinates":[5.4792761803,50.8552131653],"type":"Point"}
}