{
  "type": "Feature",
  "properties": {
    "addr:full":"Paterstraat 48 Temse Oost-Vlaanderen 9140",
    "addr:housenumber":"48",
    "addr:postcode":"9140",
    "addr:street":"Paterstraat",
    "iso:country":"BE",
    "sg:address":"Paterstraat 48",
    "sg:city":"Temse",
    "sg:orig_category":"Boucheries",
    "sg:phone":"+32 3 771 50 18",
    "sg:postcode":"9140",
    "sg:province":"Oost-Vlaanderen",
    "wof:name":"De Vleesmeesters",
    "wof:placetype":"venue"
},
  "geometry": {"coordinates":[4.211083889,51.1264381409],"type":"Point"}
}