{
  "type": "Feature",
  "properties": {
    "iso:country":"BE",
    "sg:address":"Beigemsesteenweg 362",
    "sg:city":"Grimbergen",
    "sg:orig_category":"Drogisterijen",
    "sg:phone":"+32 2 269 42 41",
    "sg:postcode":"1852",
    "sg:province":"Vlaams-Brabant",
    "wof:name":"Huis Van Der Linden",
    "wof:placetype":"venue"
},
  "geometry": {"coordinates":[4.3651652336,50.9564476013],"type":"Point"}
}