{
  "type": "Feature",
  "properties": {
    "addr:full":"Bp 127 Beaumont Cedex 63541",
    "addr:housenumber":"127",
    "addr:postcode":"cedex 63541",
    "addr:street":"Beaumont",
    "iso:country":"BE",
    "sg:address":"Bp 127",
    "sg:city":"Beaumont Cedex",
    "sg:classifiers":[
        {
            "category":"Autos & Motor Vehicles",
            "subcategory":"Motorcycle Sales",
            "type":"Retail Goods"
        }
    ],
    "sg:phone":"+32 473 28 69 96",
    "sg:postcode":"63541",
    "sg:tags":[
        "motorbike"
    ],
    "wof:name":"Dafy Moto",
    "wof:placetype":"venue"
},
  "geometry": {"coordinates":[3.0856199265,45.7502403259],"type":"Point"}
}