{
  "type": "Feature",
  "properties": {
    "iso:country":"BE",
    "sg:address":"Rue Louis Jamme 5",
    "sg:city":"Liege",
    "sg:orig_category":"Biens d'occasion",
    "sg:phone":"+32 4 344 27 59",
    "sg:postcode":"4020",
    "sg:province":"Li\u00e8ge",
    "wof:name":"C\u00d4t\u00c9 Brocante",
    "wof:placetype":"venue"
},
  "geometry": {"coordinates":[5.5829210281,50.6385040283],"type":"Point"}
}