{
  "type": "Feature",
  "properties": {
    "addr:full":"Gasthuisstraat 3 Poperinge West-Vlaanderen 8970",
    "addr:housenumber":"3",
    "addr:postcode":"8970",
    "addr:street":"Gasthuisstraat",
    "iso:country":"BE",
    "sg:address":"Gasthuisstraat 3",
    "sg:city":"Poperinge",
    "sg:orig_category":"Rusthuizen and serviceflats",
    "sg:phone":"+32 57 33 40 30",
    "sg:postcode":"8970",
    "sg:province":"West-Vlaanderen",
    "wof:name":"Rusthuis O.c.m.w.",
    "wof:placetype":"venue"
},
  "geometry": {"coordinates":[2.7253799438,50.8559646606],"type":"Point"}
}