{
  "type": "Feature",
  "properties": {
    "iso:country":"BE",
    "sg:address":"Rue Fosse-saint-jean 6",
    "sg:city":"Komen-waasten/comines-warneton",
    "sg:classifiers":[
        {
            "category":"Arena",
            "subcategory":"Sports Club",
            "type":"Entertainment"
        }
    ],
    "sg:phone":"+32 56 55 97 63",
    "sg:postcode":"7780",
    "sg:province":"Hainaut",
    "sg:tags":[
        "de"
    ],
    "wof:name":"La Royale Pedale Cycliste",
    "wof:placetype":"venue"
},
  "geometry": {"coordinates":[2.9927148819,50.780254364],"type":"Point"}
}