{
  "type": "Feature",
  "properties": {
    "iso:country":"BE",
    "sg:address":"Retoricastraat 19",
    "sg:city":"Sint-gillis/saint-gilles",
    "sg:orig_category":"Zalen voor culturele evenementen",
    "sg:phone":"+32 2 538 36 09",
    "sg:postcode":"1060",
    "sg:province":"Bruxelles-Capitale",
    "wof:name":"L.i.b.",
    "wof:placetype":"venue"
},
  "geometry": {"coordinates":[4.3461899757,50.8275375366],"type":"Point"}
}