{
  "type": "Feature",
  "properties": {
    "addr:full":"Hector Plancqaertstraat 2 Wortegem-petegem Oost-Vlaanderen 9790",
    "addr:housenumber":"2",
    "addr:postcode":"9790",
    "addr:street":"Hector Plancqaertstraat",
    "iso:country":"BE",
    "sg:address":"Hector Plancqaertstraat 2",
    "sg:city":"Wortegem-petegem",
    "sg:orig_category":"Plomberie, chauffage and installations sanitaires",
    "sg:phone":"+32 56 68 08 49",
    "sg:postcode":"9790",
    "sg:province":"Oost-Vlaanderen",
    "wof:name":"Verbeke Frank",
    "wof:placetype":"venue"
},
  "geometry": {"coordinates":[3.5223050117,50.8559684753],"type":"Point"}
}