{
  "type": "Feature",
  "properties": {
    "iso:country":"BE",
    "sg:address":"Krakelaarsveld 34",
    "sg:city":"Herentals",
    "sg:classifiers":[
        {
            "category":"Fast Food",
            "type":"Food & Drink"
        }
    ],
    "sg:phone":"+32 14 22 07 40",
    "sg:postcode":"2200",
    "sg:province":"Antwerpen",
    "sg:tags":[
        "meeneem",
        "restaurant"
    ],
    "wof:name":"Alen",
    "wof:placetype":"venue"
},
  "geometry": {"coordinates":[4.8136429787,51.1645927429],"type":"Point"}
}