{
  "type": "Feature",
  "properties": {
    "iso:country":"BE",
    "sg:address":"Diestsestraat 3ba",
    "sg:city":"Leuven",
    "sg:orig_category":"Warenhuizen",
    "sg:phone":"+32 16 22 77 35",
    "sg:postcode":"3000",
    "sg:province":"Vlaams-Brabant",
    "wof:name":"Linway",
    "wof:placetype":"venue"
},
  "geometry": {"coordinates":[4.7021379471,50.8797073364],"type":"Point"}
}