{
  "type": "Feature",
  "properties": {
    "iso:country":"BE",
    "sg:address":"Chauss\u00c9e De Wavre 1712",
    "sg:city":"Oudergem/auderghem",
    "sg:orig_category":"Services fun\u00e9raires",
    "sg:phone":"+32 2 660 89 51",
    "sg:postcode":"1160",
    "sg:province":"Bruxelles-Capitale",
    "wof:name":"B.c. Crematie",
    "wof:placetype":"venue"
},
  "geometry": {"coordinates":[4.4297938347,50.8160743713],"type":"Point"}
}