{
  "type": "Feature",
  "properties": {
    "addr:full":"Rue Eug\u00c8ne Gilles 6ba Les Bons Villers Hainaut 6210",
    "addr:housenumber":"6ba",
    "addr:postcode":"6210",
    "addr:street":"Rue Euge\u0300Ne Gilles",
    "iso:country":"BE",
    "sg:address":"Rue Eug\u00c8ne Gilles 6ba",
    "sg:city":"Les Bons Villers",
    "sg:orig_category":"Woningbouw",
    "sg:phone":"+32 71 85 17 58",
    "sg:postcode":"6210",
    "sg:province":"Hainaut",
    "wof:name":"Meerts",
    "wof:placetype":"venue"
},
  "geometry": {"coordinates":[4.4511561394,50.5378227234],"type":"Point"}
}