{
  "type": "Feature",
  "properties": {
    "addr:full":"Zonnebeekseweg 221 Ieper West-Vlaanderen 8900",
    "addr:housenumber":"221",
    "addr:postcode":"8900",
    "iso:country":"BE",
    "sg:address":"Zonnebeekseweg 221",
    "sg:city":"Ieper",
    "sg:classifiers":[
        {
            "category":"Home & Garden",
            "subcategory":"Building Materials",
            "type":"Retail Goods"
        }
    ],
    "sg:phone":"+32 57 20 21 48",
    "sg:postcode":"8900",
    "sg:province":"West-Vlaanderen",
    "sg:tags":[
        "bathroom",
        "installation",
        "accessory"
    ],
    "wof:name":"Stevens Keukens Bvba",
    "wof:placetype":"venue"
},
  "geometry": {"coordinates":[2.9077730179,50.8585929871],"type":"Point"}
}