{
  "type": "Feature",
  "properties": {
    "addr:full":"All\u00e9e Des Tilleuls 1 Beaumont (barben\u00e7on) Hainaut 6500",
    "addr:housenumber":"1",
    "addr:postcode":"6500",
    "addr:street":"Alle\u0301E Des Tilleuls",
    "iso:country":"BE",
    "sg:address":"All\u00e9e Des Tilleuls 1",
    "sg:city":"Beaumont (barben\u00e7on)",
    "sg:classifiers":[
        {
            "category":"Bars & Pubs",
            "type":"Food & Drink"
        }
    ],
    "sg:phone":"+32 71 58 99 59",
    "sg:postcode":"6500",
    "sg:province":"Hainaut",
    "sg:tags":[
        "tavern"
    ],
    "wof:name":"Le Lac De Barben\u00e7on",
    "wof:placetype":"venue"
},
  "geometry": {"coordinates":[4.2353200912,50.2372131348],"type":"Point"}
}