{
  "type": "Feature",
  "properties": {
    "addr:full":"Welriekende Dreef 117 Overijse Vlaams-Brabant 3090",
    "addr:housenumber":"117",
    "addr:postcode":"3090",
    "addr:street":"Dreef",
    "iso:country":"BE",
    "sg:address":"Welriekende Dreef 117",
    "sg:city":"Overijse",
    "sg:orig_category":"Tuinen",
    "sg:phone":"+32 2 657 10 69",
    "sg:postcode":"3090",
    "sg:province":"Vlaams-Brabant",
    "wof:name":"Holiday Garden",
    "wof:placetype":"venue"
},
  "geometry": {"coordinates":[4.5476498604,50.7754592896],"type":"Point"}
}