{
  "type": "Feature",
  "properties": {
    "iso:country":"BE",
    "sg:address":"Gentsestraat 79",
    "sg:city":"Aalst",
    "sg:classifiers":[
        {
            "category":"Fast Food",
            "type":"Food & Drink"
        }
    ],
    "sg:phone":"+32 53 71 14 15",
    "sg:postcode":"9300",
    "sg:province":"Oost-Vlaanderen",
    "sg:tags":[
        "\u00c0",
        "restaurants",
        "emporter",
        "restaurant"
    ],
    "wof:name":"Pizza Italia",
    "wof:placetype":"venue"
},
  "geometry": {"coordinates":[4.0302481651,50.9377937317],"type":"Point"}
}