{
  "type": "Feature",
  "properties": {
    "addr:full":"Rodenbachstraat 43 Denderleeuw Oost-Vlaanderen 9470",
    "addr:housenumber":"43",
    "addr:postcode":"9470",
    "addr:street":"Rodenbachstraat",
    "iso:country":"BE",
    "sg:address":"Rodenbachstraat 43",
    "sg:city":"Denderleeuw",
    "sg:orig_category":"Maatschappelijke dienstverlening",
    "sg:phone":"+32 53 66 03 87",
    "sg:postcode":"9470",
    "sg:province":"Oost-Vlaanderen",
    "wof:name":"Rode Kruis Denderleeuw",
    "wof:placetype":"venue"
},
  "geometry": {"coordinates":[4.0806999207,50.8829154968],"type":"Point"}
}