{
  "type": "Feature",
  "properties": {
    "iso:country":"BE",
    "sg:address":"Pontweg 89",
    "sg:city":"Haaltert",
    "sg:orig_category":"Bloemen and planten",
    "sg:phone":"+32 53 83 80 25",
    "sg:postcode":"9450",
    "sg:province":"Oost-Vlaanderen",
    "wof:name":"Michel Hendrickx",
    "wof:placetype":"venue"
},
  "geometry": {"coordinates":[3.983618021,50.8987007141],"type":"Point"}
}