{
  "type": "Feature",
  "properties": {
    "addr:full":"Rue De La Justice 7ba Soignies Hainaut 7063",
    "addr:postcode":"7063",
    "addr:street":"Rue De La Justice 7Ba;Hainaut",
    "iso:country":"BE",
    "sg:address":"Rue De La Justice 7ba",
    "sg:city":"Soignies",
    "sg:orig_category":"Instituts de beaut\u00e9",
    "sg:phone":"+32 67 41 02 41",
    "sg:postcode":"7063",
    "sg:province":"Hainaut",
    "wof:name":"Eliane Lorette",
    "wof:placetype":"venue"
},
  "geometry": {"coordinates":[3.9912950993,50.5800514221],"type":"Point"}
}