{
  "type": "Feature",
  "properties": {
    "addr:full":"Rue De La Hocaille 2 Grez-doiceau (archennes) Brabant Wallon 1390",
    "addr:housenumber":"2",
    "addr:postcode":"1390",
    "addr:street":"Rue De La Hocaille;Wallon",
    "iso:country":"BE",
    "sg:address":"Rue De La Hocaille 2",
    "sg:city":"Grez-doiceau (archennes)",
    "sg:classifiers":[
        {
            "category":"Real Estate",
            "subcategory":"Architect",
            "type":"Services"
        }
    ],
    "sg:phone":"+32 10 84 22 18",
    "sg:postcode":"1390",
    "sg:province":"Brabant Wallon",
    "wof:name":"De Maere H",
    "wof:placetype":"venue"
},
  "geometry": {"coordinates":[4.6743907928,50.7513961792],"type":"Point"}
}