{
  "type": "Feature",
  "properties": {
    "addr:full":"Vrijheidsstraat 27 Aalst Oost-Vlaanderen 9300",
    "addr:housenumber":"27",
    "addr:postcode":"9300",
    "addr:street":"Vrijheidsstraat",
    "iso:country":"BE",
    "sg:address":"Vrijheidsstraat 27",
    "sg:city":"Aalst",
    "sg:classifiers":[
        {
            "category":"Shopping",
            "subcategory":"Bicycles & Sporting Goods",
            "type":"Retail Goods"
        }
    ],
    "sg:phone":"+32 53 21 69 15",
    "sg:postcode":"9300",
    "sg:province":"Oost-Vlaanderen",
    "sg:tags":[
        "article",
        "de",
        "sport",
        "camping"
    ],
    "wof:name":"Penne Sport",
    "wof:placetype":"venue"
},
  "geometry": {"coordinates":[4.0346360207,50.9405136108],"type":"Point"}
}