{
  "type": "Feature",
  "properties": {
    "iso:country":"BE",
    "sg:address":"Route De Ramillies 46",
    "sg:city":"Eghezee",
    "sg:orig_category":"Artsen and specialisten",
    "sg:phone":"+32 81 81 16 56",
    "sg:postcode":"5310",
    "sg:province":"Namur",
    "wof:name":"Jean Thiran",
    "wof:placetype":"venue"
},
  "geometry": {"coordinates":[4.9137129784,50.5982437134],"type":"Point"}
}