{
  "type": "Feature",
  "properties": {
    "iso:country":"BE",
    "sg:address":"300",
    "sg:city":"Menenstraat 8560 Wevelgem",
    "sg:classifiers":[
        {
            "category":"Manufacturing",
            "subcategory":"Rubber & Plastics",
            "type":"Manufacturing & Wholesale Goods"
        }
    ],
    "sg:phone":"+32 56 41 12 04",
    "sg:postcode":"300",
    "wof:name":"Unigom",
    "wof:placetype":"venue"
},
  "geometry": {"coordinates":[3.1508100033,50.8016738892],"type":"Point"}
}