{
  "type": "Feature",
  "properties": {
    "iso:country":"BE",
    "sg:address":"Grenadiersstraat 11",
    "sg:city":"Roeselare",
    "sg:orig_category":"Meubelzaken, woning- and keukeninrichting",
    "sg:phone":"+32 51 20 84 48",
    "sg:postcode":"8800",
    "sg:province":"West-Vlaanderen",
    "wof:name":"Mistral",
    "wof:placetype":"venue"
},
  "geometry": {"coordinates":[3.141712904,50.9240837097],"type":"Point"}
}