{
  "type": "Feature",
  "properties": {
    "iso:country":"BE",
    "sg:address":"Blasiusstraat 52",
    "sg:city":"Poperinge",
    "sg:orig_category":"Groententeelt",
    "sg:phone":"+32 57 30 17 57",
    "sg:postcode":"8972",
    "sg:province":"West-Vlaanderen",
    "wof:name":"Hardeman J",
    "wof:placetype":"venue"
},
  "geometry": {"coordinates":[2.6800539494,50.9000396729],"type":"Point"}
}