{
  "type": "Feature",
  "properties": {
    "addr:full":"Rue Du Smohain 5 Lasne (ohain) Brabant Wallon 1380",
    "addr:housenumber":"5",
    "addr:postcode":"1380",
    "addr:street":"Rue Du Smohain;Wallon",
    "iso:country":"BE",
    "sg:address":"Rue Du Smohain 5",
    "sg:city":"Lasne (ohain)",
    "sg:classifiers":[
        {
            "category":"Professional",
            "subcategory":"Management & Consulting",
            "type":"Services"
        }
    ],
    "sg:phone":"+32 2 633 43 13",
    "sg:postcode":"1380",
    "sg:province":"Brabant Wallon",
    "sg:tags":[
        "consultant"
    ],
    "wof:name":"Sealord Consulting Group",
    "wof:placetype":"venue"
},
  "geometry": {"coordinates":[4.4828081131,50.6981735229],"type":"Point"}
}