{
  "type": "Feature",
  "properties": {
    "iso:country":"BE",
    "sg:address":"Avenue Fernand Charlot 21",
    "sg:city":"Jodoigne",
    "sg:orig_category":"Kinderopvang",
    "sg:phone":"+32 10 81 21 98",
    "sg:postcode":"1370",
    "sg:province":"Brabant Wallon",
    "wof:name":"Aide Et Soins \u00c0 Domicile",
    "wof:placetype":"venue"
},
  "geometry": {"coordinates":[4.8706002235,50.7225494385],"type":"Point"}
}