{
  "type": "Feature",
  "properties": {
    "iso:country":"BE",
    "sg:address":"Avenue Du Luxembourg 44",
    "sg:city":"Li\u00c8ge",
    "sg:orig_category":"M\u00e9decins and sp\u00e9cialistes",
    "sg:phone":"+32 4 343 29 45",
    "sg:postcode":"4020",
    "sg:province":"Li\u00e8ge",
    "wof:name":"Louis Verlinden",
    "wof:placetype":"venue"
},
  "geometry": {"coordinates":[5.5853428841,50.6223182678],"type":"Point"}
}