{
  "type": "Feature",
  "properties": {
    "iso:country":"BE",
    "sg:address":"Champ Des Fleurs 7",
    "sg:city":"Wezembeek-oppem/wezembeek-oppem",
    "sg:orig_category":"Organisations and associations. Cours de danse. Cr\u00e8ches and garderies d'enfants",
    "sg:phone":"+32 2 731 11 96",
    "sg:postcode":"1970",
    "sg:province":"Vlaams-Brabant",
    "wof:name":"Toboggan",
    "wof:placetype":"venue"
},
  "geometry": {"coordinates":[4.471116066,50.8425521851],"type":"Point"}
}