{
  "type": "Feature",
  "properties": {
    "addr:full":"Route Provinciale 52 Tournai (mourcourt) Hainaut 7543",
    "addr:housenumber":"52",
    "addr:postcode":"7543",
    "addr:street":"Route Provinciale",
    "iso:country":"BE",
    "sg:address":"Route Provinciale 52",
    "sg:city":"Tournai (mourcourt)",
    "sg:classifiers":[
        {
            "category":"Health Services",
            "subcategory":"Health Practitioner",
            "type":"Services"
        }
    ],
    "sg:phone":"+32 69 34 60 60",
    "sg:postcode":"7543",
    "sg:province":"Hainaut",
    "sg:tags":[
        "physiotherapist"
    ],
    "wof:name":"Emare Abel",
    "wof:placetype":"venue"
},
  "geometry": {"coordinates":[3.4253220558,50.6464691162],"type":"Point"}
}