{
  "type": "Feature",
  "properties": {
    "addr:full":"Rotenbergplatz 18 Eupen Li\u00e8ge 4700",
    "addr:housenumber":"18",
    "addr:postcode":"4700",
    "addr:street":"Rotenbergplatz",
    "iso:country":"BE",
    "sg:address":"Rotenbergplatz 18",
    "sg:city":"Eupen",
    "sg:classifiers":[
        {
            "category":"Manufacturing",
            "subcategory":"Metals",
            "type":"Manufacturing & Wholesale Goods"
        }
    ],
    "sg:phone":"+32 87 55 34 44",
    "sg:postcode":"4700",
    "sg:province":"Li\u00e8ge",
    "sg:tags":[
        "ironwork"
    ],
    "wof:name":"Frank",
    "wof:placetype":"venue"
},
  "geometry": {"coordinates":[6.0269298553,50.6270904541],"type":"Point"}
}