{
  "type": "Feature",
  "properties": {
    "addr:full":"Rue Saint-jean 12 Jodoigne Brabant Wallon 1370",
    "addr:postcode":"12;1370",
    "addr:street":"Rue Saint-Jean",
    "iso:country":"BE",
    "sg:address":"Rue Saint-jean 12",
    "sg:city":"Jodoigne",
    "sg:classifiers":[
        {
            "category":"Restaurant",
            "type":"Food & Drink"
        }
    ],
    "sg:phone":"+32 10 81 48 72",
    "sg:postcode":"1370",
    "sg:province":"Brabant Wallon",
    "wof:name":"D\u00c9lifrance",
    "wof:placetype":"venue"
},
  "geometry": {"coordinates":[4.8702530861,50.7248344421],"type":"Point"}
}