{
  "type": "Feature",
  "properties": {
    "addr:full":"Kortrijkstraat 157 Ingelmunster West-Vlaanderen 8770",
    "addr:housenumber":"157",
    "addr:postcode":"8770",
    "addr:street":"Kortrijkstraat",
    "iso:country":"BE",
    "sg:address":"Kortrijkstraat 157",
    "sg:city":"Ingelmunster",
    "sg:orig_category":"Sportclubs",
    "sg:phone":"+32 51 30 03 34",
    "sg:postcode":"8770",
    "sg:province":"West-Vlaanderen",
    "wof:name":"La Macchina Vecchia",
    "wof:placetype":"venue"
},
  "geometry": {"coordinates":[3.2659239769,50.900138855],"type":"Point"}
}