{
  "type": "Feature",
  "properties": {
    "iso:country":"BE",
    "sg:address":"Mechelseweg 210",
    "sg:city":"Kapelle-op-den-bos",
    "sg:orig_category":"Centres de relaxation and bien-\u00eatre. Instituts de beaut\u00e9",
    "sg:phone":"+32 15 71 00 76",
    "sg:postcode":"1880",
    "sg:province":"Vlaams-Brabant",
    "wof:name":"Instituut Sofie",
    "wof:placetype":"venue"
},
  "geometry": {"coordinates":[4.3631482124,51.0119056702],"type":"Point"}
}