{
  "type": "Feature",
  "properties": {
    "addr:full":"Rue Gu\u00e9rin 28 Boussu Hainaut 7300",
    "addr:housenumber":"28",
    "addr:postcode":"7300",
    "addr:street":"Rue Gue\u0301Rin",
    "iso:country":"BE",
    "sg:address":"Rue Gu\u00e9rin 28",
    "sg:city":"Boussu",
    "sg:classifiers":[
        {
            "category":"Personal",
            "subcategory":"Beauty Salon",
            "type":"Services"
        }
    ],
    "sg:phone":"+32 65 78 28 68",
    "sg:postcode":"7300",
    "sg:province":"Hainaut",
    "sg:tags":[
        "lady",
        "-",
        "hairdressing"
    ],
    "wof:name":"Carole (coiffure)",
    "wof:placetype":"venue"
},
  "geometry": {"coordinates":[3.7963900566,50.4329147339],"type":"Point"}
}