{
  "type": "Feature",
  "properties": {
    "addr:full":"Viide-olympiadelaan 118 Antwerpen Antwerpen 2020",
    "addr:housenumber":"118",
    "addr:postcode":"2020",
    "iso:country":"BE",
    "sg:address":"Viide-olympiadelaan 118",
    "sg:city":"Antwerpen",
    "sg:orig_category":"M\u00e9decins and sp\u00e9cialistes",
    "sg:phone":"+32 3 216 34 02",
    "sg:postcode":"2020",
    "sg:province":"Antwerpen",
    "wof:name":"M. Van Hooff",
    "wof:placetype":"venue"
},
  "geometry": {"coordinates":[4.3836522102,51.1833953857],"type":"Point"}
}