{
  "type": "Feature",
  "properties": {
    "addr:full":"Chauss\u00c9e De Verviers 147 Theux Li\u00e8ge 4910",
    "addr:housenumber":"147",
    "addr:postcode":"4910",
    "addr:street":"Chausse\u0301E De Verviers",
    "iso:country":"BE",
    "sg:address":"Chauss\u00c9e De Verviers 147",
    "sg:city":"Theux",
    "sg:orig_category":"Diverse organisaties and verenigingen",
    "sg:phone":"+32 87 54 16 23",
    "sg:postcode":"4910",
    "sg:province":"Li\u00e8ge",
    "wof:name":"Klinger-consultant & Environnement",
    "wof:placetype":"venue"
},
  "geometry": {"coordinates":[5.8322100639,50.5451202393],"type":"Point"}
}