{
  "type": "Feature",
  "properties": {
    "addr:full":"Chapelle Des Anges 30 Thimister-clermont Li\u00e8ge 4890",
    "addr:housenumber":"30",
    "addr:postcode":"4890",
    "addr:street":"Thimister-Clermont Lie\u0300Ge",
    "iso:country":"BE",
    "sg:address":"Chapelle Des Anges 30",
    "sg:city":"Thimister-clermont",
    "sg:orig_category":"Fruitteelt",
    "sg:phone":"+32 87 68 63 07",
    "sg:postcode":"4890",
    "sg:province":"Li\u00e8ge",
    "wof:name":"Michel Hensen",
    "wof:placetype":"venue"
},
  "geometry": {"coordinates":[5.8634610176,50.6745033264],"type":"Point"}
}