{
  "type": "Feature",
  "properties": {
    "iso:country":"BE",
    "sg:address":"Rue De Streel 209",
    "sg:city":"Fexhe-le-haut-clocher",
    "sg:orig_category":"Eleveurs de bovins",
    "sg:phone":"+32 4 250 10 42",
    "sg:postcode":"4347",
    "sg:province":"Li\u00e8ge",
    "wof:name":"Jerome Roberti",
    "wof:placetype":"venue"
},
  "geometry": {"coordinates":[5.3914542198,50.6754837036],"type":"Point"}
}