{
  "type": "Feature",
  "properties": {
    "addr:full":"Route De Fosses Fosses-la-ville Namur 5070",
    "addr:postcode":"5070",
    "addr:street":"Route De Fosses",
    "iso:country":"BE",
    "sg:address":"Route De Fosses",
    "sg:city":"Fosses-la-ville",
    "sg:orig_category":"R\u00e9cup\u00e9ration de mati\u00e8res m\u00e9talliques recyclables and d\u00e9molisseurs de voitures. D\u00e9taillants en pi\u00e8ces",
    "sg:phone":"+32 71 71 31 95",
    "sg:postcode":"5070",
    "sg:province":"Namur",
    "wof:name":"Rondeaux",
    "wof:placetype":"venue"
},
  "geometry": {"coordinates":[4.6512451172,50.4221954346],"type":"Point"}
}