{
  "type": "Feature",
  "properties": {
    "iso:country":"BE",
    "sg:address":"Rue Keyenveld 39",
    "sg:city":"Bruxelles (ixelles)",
    "sg:classifiers":[
        {
            "category":"Communications",
            "subcategory":"Film & Video Production",
            "type":"Services"
        }
    ],
    "sg:phone":"+32 2 512 94 21",
    "sg:postcode":"1050",
    "sg:province":"Bruxelles-Capitale",
    "sg:tags":[
        "producer",
        "realizators"
    ],
    "wof:name":"Blue Art",
    "wof:placetype":"venue"
},
  "geometry": {"coordinates":[4.3609399796,50.8349494934],"type":"Point"}
}