{
  "type": "Feature",
  "properties": {
    "iso:country":"BE",
    "sg:address":"Kolonel Begaultlaan 15",
    "sg:city":"Leuven (wilsele)",
    "sg:classifiers":[
        {
            "category":"Arena",
            "subcategory":"Sports Club",
            "type":"Entertainment"
        }
    ],
    "sg:phone":"+32 16 23 57 68",
    "sg:postcode":"3012",
    "sg:province":"Vlaams-Brabant",
    "wof:name":"Sportopolis Squash & Fitness Centrum De Vaart",
    "wof:placetype":"venue"
},
  "geometry": {"coordinates":[4.7059540749,50.8914337158],"type":"Point"}
}