{
  "type": "Feature",
  "properties": {
    "iso:country":"BE",
    "sg:address":"Bd Industriel 3",
    "sg:city":"Comines",
    "sg:classifiers":[
        {
            "category":"Manufacturing",
            "subcategory":"Textiles",
            "type":"Manufacturing & Wholesale Goods"
        }
    ],
    "sg:phone":"+32 56 56 06 70",
    "sg:postcode":"7780",
    "sg:province":"Hainaut",
    "sg:tags":[
        "linen",
        "clothing",
        "fabric"
    ],
    "wof:name":"Ideal Fibres Et Fabrics Komen Sa",
    "wof:placetype":"venue"
},
  "geometry": {"coordinates":[3.0157558918,50.7767868042],"type":"Point"}
}