{
  "type": "Feature",
  "properties": {
    "iso:country":"BE",
    "sg:address":"Kopkapelstraat 1",
    "sg:city":"Lokeren",
    "sg:orig_category":"Artsen and specialisten",
    "sg:phone":"+32 9 348 69 28",
    "sg:postcode":"9160",
    "sg:province":"Oost-Vlaanderen",
    "wof:name":"Hilde D'hondt",
    "wof:placetype":"venue"
},
  "geometry": {"coordinates":[3.999022007,51.1151733398],"type":"Point"}
}