{
  "type": "Feature",
  "properties": {
    "iso:country":"BE",
    "sg:address":"Torhoutsesteenweg 40",
    "sg:city":"Zedelgem",
    "sg:orig_category":"Installation de menuiserie en bois and plastique",
    "sg:phone":"+32 50 82 30 84",
    "sg:postcode":"8210",
    "sg:province":"West-Vlaanderen",
    "wof:name":"Van Houcke Achiel",
    "wof:placetype":"venue"
},
  "geometry": {"coordinates":[3.1576468945,51.1365127563],"type":"Point"}
}