{
  "type": "Feature",
  "properties": {
    "addr:full":"Ninoofsesteenweg 142 Lennik (sint-kwintens-lennik) Vlaams-Brabant 1750",
    "addr:housenumber":"142",
    "addr:postcode":"1750",
    "addr:street":"Ninoofsesteenweg",
    "iso:country":"BE",
    "sg:address":"Ninoofsesteenweg 142",
    "sg:city":"Lennik (sint-kwintens-lennik)",
    "sg:classifiers":[
        {
            "category":"Home & Garden",
            "subcategory":"Hardware",
            "type":"Retail Goods"
        }
    ],
    "sg:phone":"+32 2 582 21 49",
    "sg:postcode":"1750",
    "sg:province":"Vlaams-Brabant",
    "sg:tags":[
        "machine",
        "horticultural"
    ],
    "wof:name":"Van Den Bossche",
    "wof:placetype":"venue"
},
  "geometry": {"coordinates":[4.1412091255,50.8345603943],"type":"Point"}
}