{
  "type": "Feature",
  "properties": {
    "iso:country":"BE",
    "sg:address":"Burgemeester Maenhautstraat 75",
    "sg:city":"Merelbeke",
    "sg:classifiers":[
        {
            "category":"Health Services",
            "subcategory":"Doctor",
            "type":"Services"
        }
    ],
    "sg:phone":"+32 9 232 06 88",
    "sg:postcode":"9820",
    "sg:province":"Oost-Vlaanderen",
    "sg:tags":[
        "medicinephysicians",
        "surgeon"
    ],
    "wof:name":"De Vits Anne",
    "wof:placetype":"venue"
},
  "geometry": {"coordinates":[3.7663600445,50.9861373901],"type":"Point"}
}