{
  "type": "Feature",
  "properties": {
    "iso:country":"BE",
    "sg:address":"Rue Notre Dame De Gr\u00e2ces 31",
    "sg:city":"Marche-en-famenne",
    "sg:classifiers":[
        {
            "category":"Wholesale",
            "subcategory":"Scrap",
            "type":"Manufacturing & Wholesale Goods"
        }
    ],
    "sg:phone":"+32 84 31 15 08",
    "sg:postcode":"6900",
    "sg:province":"Luxembourg",
    "sg:tags":[
        "metal"
    ],
    "wof:name":"Prestat Ets",
    "wof:placetype":"venue"
},
  "geometry": {"coordinates":[5.3422398567,50.230304718],"type":"Point"}
}