{
  "type": "Feature",
  "properties": {
    "addr:full":"Sint-maartensplein 1ba Wervik West-Vlaanderen 8940",
    "addr:housenumber":"1ba",
    "addr:postcode":"8940",
    "addr:street":"Sint-Maartensplein",
    "iso:country":"BE",
    "sg:address":"Sint-maartensplein 1ba",
    "sg:city":"Wervik",
    "sg:orig_category":"Banken and kredietinstellingen",
    "sg:phone":"+32 56 31 35 23",
    "sg:postcode":"8940",
    "sg:province":"West-Vlaanderen",
    "wof:name":"Nagelmackers",
    "wof:placetype":"venue"
},
  "geometry": {"coordinates":[3.0439720154,50.7781715393],"type":"Point"}
}