{
  "type": "Feature",
  "properties": {
    "addr:full":"Wijdouwbeekstraat 11 Alveringem West-Vlaanderen 8690",
    "addr:housenumber":"11",
    "addr:postcode":"8690",
    "addr:street":"Wijdouwbeekstraat",
    "iso:country":"BE",
    "sg:address":"Wijdouwbeekstraat 11",
    "sg:city":"Alveringem",
    "sg:orig_category":"Eleveurs and marchands de porcs. Eleveurs de bovins",
    "sg:phone":"+32 58 29 95 70",
    "sg:postcode":"8690",
    "sg:province":"West-Vlaanderen",
    "wof:name":"Godfried Coene",
    "wof:placetype":"venue"
},
  "geometry": {"coordinates":[2.6854040623,51.0159797668],"type":"Point"}
}