{
  "type": "Feature",
  "properties": {
    "addr:full":"Rue Des Croisons 1 Mont-de-l'enclus (amougies) Hainaut 7750",
    "addr:housenumber":"1",
    "addr:postcode":"7750",
    "addr:street":"Rue Des Croisons;Amougies Hainaut",
    "iso:country":"BE",
    "sg:address":"Rue Des Croisons 1",
    "sg:city":"Mont-de-l'enclus (amougies)",
    "sg:classifiers":[
        {
            "category":"Shopping",
            "subcategory":"Books",
            "type":"Retail Goods"
        }
    ],
    "sg:phone":"+32 69 76 84 91",
    "sg:postcode":"7750",
    "sg:province":"Hainaut",
    "sg:tags":[
        "bookseller"
    ],
    "wof:name":"Mory L",
    "wof:placetype":"venue"
},
  "geometry": {"coordinates":[5.0023469925,50.3222923279],"type":"Point"}
}