{
  "type": "Feature",
  "properties": {
    "addr:full":"Sint-jorisstraat 2 Izegem West-Vlaanderen 8870",
    "addr:housenumber":"2",
    "addr:postcode":"8870",
    "addr:street":"Sint-Jorisstraat",
    "iso:country":"BE",
    "sg:address":"Sint-jorisstraat 2",
    "sg:city":"Izegem",
    "sg:classifiers":[
        {
            "category":"Farming",
            "subcategory":"Fish & Marine Products",
            "type":"Manufacturing & Wholesale Goods"
        }
    ],
    "sg:phone":"+32 51 31 89 41",
    "sg:postcode":"8870",
    "sg:province":"West-Vlaanderen",
    "sg:tags":[
        "retail",
        "-",
        "shellfish"
    ],
    "wof:name":"'t Vissershuis",
    "wof:placetype":"venue"
},
  "geometry": {"coordinates":[3.2083330154,50.9147644043],"type":"Point"}
}