{
  "type": "Feature",
  "properties": {
    "addr:full":"Roeselaarsestraat 46 Izegem West-Vlaanderen 8870",
    "addr:housenumber":"46",
    "addr:postcode":"8870",
    "addr:street":"Roeselaarsestraat",
    "iso:country":"BE",
    "sg:address":"Roeselaarsestraat 46",
    "sg:city":"Izegem",
    "sg:classifiers":[
        {
            "category":"Recreation",
            "subcategory":"Dog Park",
            "type":"Entertainment"
        }
    ],
    "sg:phone":"+32 51 30 22 50",
    "sg:postcode":"8870",
    "sg:province":"West-Vlaanderen",
    "sg:tags":[
        "dame",
        "lingerie",
        "v\u00eatements",
        "pour",
        "sous-v\u00eatements"
    ],
    "wof:name":"Antoinette Lady Shop",
    "wof:placetype":"venue"
},
  "geometry": {"coordinates":[3.2118151188,50.918598175],"type":"Point"}
}