{
  "type": "Feature",
  "properties": {
    "iso:country":"BE",
    "sg:address":"Rue Potaarde 114",
    "sg:city":"Bruxelles (berchem-sainte-agathe)",
    "sg:orig_category":"Non-Classified Establishments",
    "sg:phone":"+32 2 465 35 59",
    "sg:postcode":"1082",
    "sg:province":"Bruxelles-Capitale",
    "wof:name":"Lamot Erol",
    "wof:placetype":"venue"
},
  "geometry": {"coordinates":[4.2823929787,50.8637123108],"type":"Point"}
}