{
  "type": "Feature",
  "properties": {
    "addr:full":"Clemenceaustraat 20 Sint-katelijne-waver Antwerpen 2860",
    "addr:housenumber":"20",
    "addr:postcode":"2860",
    "addr:street":"Clemenceaustraat",
    "iso:country":"BE",
    "sg:address":"Clemenceaustraat 20",
    "sg:city":"Sint-katelijne-waver",
    "sg:orig_category":"Kapsalons",
    "sg:phone":"+32 15 20 53 07",
    "sg:postcode":"2860",
    "sg:province":"Antwerpen",
    "wof:name":"Christiane Wijnants",
    "wof:placetype":"venue"
},
  "geometry": {"coordinates":[4.488629818,51.0621414185],"type":"Point"}
}