{
  "type": "Feature",
  "properties": {
    "addr:full":"Rue Du Marais 41 Pont-\u00e0-celles (buzet) Hainaut 6230",
    "addr:housenumber":"41",
    "addr:postcode":"6230",
    "addr:street":"Rue Du Marais",
    "iso:country":"BE",
    "sg:address":"Rue Du Marais 41",
    "sg:city":"Pont-\u00e0-celles (buzet)",
    "sg:orig_category":"Non-Classified Establishments",
    "sg:phone":"+32 71 84 59 08",
    "sg:postcode":"6230",
    "sg:province":"Hainaut",
    "wof:name":"Info Txt",
    "wof:placetype":"venue"
},
  "geometry": {"coordinates":[4.3692169189,50.5372772217],"type":"Point"}
}