{
  "type": "Feature",
  "properties": {
    "addr:full":"Rue De Namur 107 Fernelmont (pontillas) Namur 5380",
    "addr:housenumber":"107",
    "addr:postcode":"5380",
    "addr:street":"Rue De Namur",
    "iso:country":"BE",
    "sg:address":"Rue De Namur 107",
    "sg:city":"Fernelmont (pontillas)",
    "sg:classifiers":[
        {
            "category":"Industrial Area",
            "type":"Public Place"
        }
    ],
    "sg:phone":"+32 81 83 41 16",
    "sg:postcode":"5380",
    "sg:province":"Namur",
    "sg:tags":[
        "-",
        "lighting"
    ],
    "wof:name":"Dupelec Sprl",
    "wof:placetype":"venue"
},
  "geometry": {"coordinates":[4.9861078262,50.5531463623],"type":"Point"}
}