{
  "type": "Feature",
  "properties": {
    "addr:full":"Smeendijk 65 Boechout Antwerpen 2530",
    "addr:housenumber":"65",
    "addr:postcode":"2530",
    "addr:street":"Smeendijk",
    "iso:country":"BE",
    "sg:address":"Smeendijk 65",
    "sg:city":"Boechout",
    "sg:classifiers":[
        {
            "category":"Wholesale",
            "subcategory":"Plants",
            "type":"Manufacturing & Wholesale Goods"
        }
    ],
    "sg:phone":"+32 3 455 06 41",
    "sg:postcode":"2530",
    "sg:province":"Antwerpen",
    "sg:tags":[
        "whol",
        "flower",
        "-",
        "grower"
    ],
    "wof:name":"De Deckers F",
    "wof:placetype":"venue"
},
  "geometry": {"coordinates":[4.5260639191,51.1638298035],"type":"Point"}
}