{
  "type": "Feature",
  "properties": {
    "addr:full":"Sint-rembertlaan 25 Torhout West-Vlaanderen 8820",
    "addr:housenumber":"25",
    "addr:postcode":"8820",
    "addr:street":"Sint-Rembertlaan",
    "iso:country":"BE",
    "sg:address":"Sint-rembertlaan 25",
    "sg:city":"Torhout",
    "sg:classifiers":[
        {
            "category":"Building & Trades",
            "subcategory":"Construction",
            "type":"Services"
        }
    ],
    "sg:phone":"+32 50 22 04 86",
    "sg:postcode":"8820",
    "sg:province":"West-Vlaanderen",
    "sg:tags":[
        "installation",
        "-",
        "central",
        "heating"
    ],
    "wof:name":"Vandecasteele J",
    "wof:placetype":"venue"
},
  "geometry": {"coordinates":[3.0942869186,51.0691719055],"type":"Point"}
}