{
  "type": "Feature",
  "properties": {
    "addr:full":"Pullaar 177 Puurs Antwerpen 2870",
    "addr:housenumber":"177",
    "addr:postcode":"2870",
    "addr:street":"Pullaar",
    "iso:country":"BE",
    "sg:address":"Pullaar 177",
    "sg:city":"Puurs",
    "sg:orig_category":"Paramedische behandelingen",
    "sg:phone":"+32 3 886 34 67",
    "sg:postcode":"2870",
    "sg:province":"Antwerpen",
    "wof:name":"R. Dielkens",
    "wof:placetype":"venue"
},
  "geometry": {"coordinates":[4.3258609772,51.0658683777],"type":"Point"}
}