{
  "type": "Feature",
  "properties": {
    "iso:country":"BE",
    "sg:address":"Marktstraat 15",
    "sg:city":"Maldegem",
    "sg:orig_category":"Enseignement maternel and primaire",
    "sg:phone":"+32 50 71 81 68",
    "sg:postcode":"9990",
    "sg:province":"Oost-Vlaanderen",
    "wof:name":"Vrije Lagere School",
    "wof:placetype":"venue"
},
  "geometry": {"coordinates":[3.4455959797,51.2083282471],"type":"Point"}
}