{
  "type": "Feature",
  "properties": {
    "iso:country":"BE",
    "sg:address":"Galerijpad 2",
    "sg:city":"Zwalm (sint-maria-latem)",
    "sg:classifiers":[
        {
            "category":"Cafe",
            "type":"Food & Drink"
        }
    ],
    "sg:phone":"+32 55 49 94 05",
    "sg:postcode":"9630",
    "sg:province":"Oost-Vlaanderen",
    "sg:tags":[
        "snack-bars"
    ],
    "wof:name":"Ijzerkotmolen",
    "wof:placetype":"venue"
},
  "geometry": {"coordinates":[3.7138769627,50.8831863403],"type":"Point"}
}