{
  "type": "Feature",
  "properties": {
    "iso:country":"BE",
    "sg:address":"Enkestraat 57",
    "sg:city":"Kinrooi",
    "sg:orig_category":"Gespecialiseerde residenti\u00eble bouw",
    "sg:phone":"+32 89 70 12 77",
    "sg:postcode":"3640",
    "sg:province":"Limburg",
    "wof:name":"Tuindecor Neijens",
    "wof:placetype":"venue"
},
  "geometry": {"coordinates":[5.7252388,51.1781272888],"type":"Point"}
}