{
  "type": "Feature",
  "properties": {
    "addr:full":"Av. R. Vandendriessche 73 Sint-pieters-woluwe Bruxelles-Capitale 1150",
    "addr:housenumber":"73",
    "addr:postcode":"1150",
    "addr:street":"Av. R. Vandendriessche",
    "iso:country":"BE",
    "sg:address":"Av. R. Vandendriessche 73",
    "sg:city":"Sint-pieters-woluwe",
    "sg:orig_category":"S\u00e9lection de personnel and placement",
    "sg:phone":"+32 2 779 53 53",
    "sg:postcode":"1150",
    "sg:province":"Bruxelles-Capitale",
    "wof:name":"Carree, Biebuyck & Partn.",
    "wof:placetype":"venue"
},
  "geometry": {"coordinates":[4.4131579399,50.8326644897],"type":"Point"}
}