{
  "type": "Feature",
  "properties": {
    "addr:full":"Melkstraat 3 Halle Vlaams-Brabant 1500",
    "addr:housenumber":"3",
    "addr:postcode":"1500",
    "addr:street":"Melkstraat",
    "iso:country":"BE",
    "sg:address":"Melkstraat 3",
    "sg:city":"Halle",
    "sg:classifiers":[
        {
            "category":"Retail",
            "subcategory":"Funeral Services",
            "type":"Services"
        }
    ],
    "sg:phone":"+32 2 356 52 70",
    "sg:postcode":"1500",
    "sg:province":"Vlaams-Brabant",
    "sg:tags":[
        "director"
    ],
    "wof:name":"Trouchau J.p",
    "wof:placetype":"venue"
},
  "geometry": {"coordinates":[4.2370529175,50.7361106873],"type":"Point"}
}