{
  "type": "Feature",
  "properties": {
    "iso:country":"BE",
    "sg:address":"Kruisstraat 163",
    "sg:city":"Ronse",
    "sg:classifiers":[
        {
            "category":"Restaurant",
            "type":"Food & Drink"
        }
    ],
    "sg:phone":"+32 55 21 59 94",
    "sg:postcode":"9600",
    "sg:province":"Oost-Vlaanderen",
    "wof:name":"Mezza Luna",
    "wof:placetype":"venue"
},
  "geometry": {"coordinates":[3.5927050114,50.7540283203],"type":"Point"}
}