{
  "type": "Feature",
  "properties": {
    "iso:country":"BE",
    "sg:address":"Rue Alnoir 55b",
    "sg:city":"Jemeppe-sur-sambre",
    "sg:classifiers":[
        {
            "category":"Building & Trades",
            "subcategory":"Landscaping Services",
            "type":"Services"
        }
    ],
    "sg:phone":"+32 71 78 01 80",
    "sg:postcode":"5190",
    "sg:province":"Namur",
    "sg:tags":[
        "access",
        "pond",
        "laying-out",
        "-"
    ],
    "wof:name":"M C T",
    "wof:placetype":"venue"
},
  "geometry": {"coordinates":[4.6558637619,50.4714241028],"type":"Point"}
}