{
  "type": "Feature",
  "properties": {
    "iso:country":"BE",
    "sg:address":"Avenue Louis Bertrand 18",
    "sg:city":"Schaarbeek/schaerbeek",
    "sg:orig_category":"Mat\u00e9riel m\u00e9dical and orthop\u00e9dique and proth\u00e8ses Fab",
    "sg:phone":"+32 2 241 27 63",
    "sg:postcode":"1030",
    "sg:province":"Bruxelles-Capitale",
    "wof:name":"Ch. Pruzan",
    "wof:placetype":"venue"
},
  "geometry": {"coordinates":[4.3747210503,50.8640861511],"type":"Point"}
}