{
  "type": "Feature",
  "properties": {
    "addr:full":"Rue Veydt 82 Bruxelles (ixelles) Bruxelles-Capitale 1050",
    "addr:housenumber":"82",
    "addr:postcode":"1050",
    "addr:street":"Rue Veydt",
    "iso:country":"BE",
    "sg:address":"Rue Veydt 82",
    "sg:city":"Bruxelles (ixelles)",
    "sg:classifiers":[
        {
            "category":"Personal",
            "subcategory":"Beauty Salon",
            "type":"Services"
        }
    ],
    "sg:phone":"+32 2 534 99 92",
    "sg:postcode":"1050",
    "sg:province":"Bruxelles-Capitale",
    "wof:name":"Alexandra Perl",
    "wof:placetype":"venue"
},
  "geometry": {"coordinates":[4.3594961166,50.828289032],"type":"Point"}
}