{
  "type": "Feature",
  "properties": {
    "addr:full":"Rue De Bomer\u00e9e 183 Montigny-le-tilleul Hainaut 6110",
    "addr:housenumber":"183",
    "addr:postcode":"6110",
    "addr:street":"Rue De Bomere\u0301E",
    "iso:country":"BE",
    "sg:address":"Rue De Bomer\u00e9e 183",
    "sg:city":"Montigny-le-tilleul",
    "sg:classifiers":[
        {
            "category":"Retail",
            "subcategory":"Auto Repair",
            "type":"Services"
        }
    ],
    "sg:phone":"+32 71 51 79 37",
    "sg:postcode":"6110",
    "sg:province":"Hainaut",
    "sg:tags":[
        "automobile-body"
    ],
    "wof:name":"Prince G",
    "wof:placetype":"venue"
},
  "geometry": {"coordinates":[4.3841671944,50.3718605042],"type":"Point"}
}