{
  "type": "Feature",
  "properties": {
    "iso:country":"BE",
    "sg:address":"Rue Des Richots 1",
    "sg:city":"Hamois (natoye)",
    "sg:classifiers":[
        {
            "category":"Farming",
            "subcategory":"Livestock Farm",
            "type":"Manufacturing & Wholesale Goods"
        }
    ],
    "sg:phone":"+32 83 65 54 78",
    "sg:postcode":"5360",
    "sg:province":"Namur",
    "sg:tags":[
        "buyer"
    ],
    "wof:name":"Busar A",
    "wof:placetype":"venue"
},
  "geometry": {"coordinates":[5.0509591103,50.3544616699],"type":"Point"}
}