{
  "type": "Feature",
  "properties": {
    "iso:country":"BE",
    "sg:address":"Grand'rue 17",
    "sg:city":"Walcourt (somz\u00e9e)",
    "sg:classifiers":[
        {
            "category":"Professional",
            "subcategory":"Testing Lab",
            "type":"Services"
        }
    ],
    "sg:phone":"+32 71 21 48 46",
    "sg:postcode":"5651",
    "sg:province":"Namur",
    "sg:tags":[
        "chemist"
    ],
    "wof:name":"Squelard J",
    "wof:placetype":"venue"
},
  "geometry": {"coordinates":[4.4332799911,50.2857818604],"type":"Point"}
}