{
  "type": "Feature",
  "properties": {
    "iso:country":"BE",
    "sg:address":"Baarledorpstraat 6",
    "sg:city":"Gent",
    "sg:orig_category":"Travaux de pl\u00e2trage",
    "sg:phone":"+32 9 282 44 93",
    "sg:postcode":"9031",
    "sg:province":"Oost-Vlaanderen",
    "wof:name":"Daniel Coppens",
    "wof:placetype":"venue"
},
  "geometry": {"coordinates":[3.620290041,51.0372390747],"type":"Point"}
}