{
  "type": "Feature",
  "properties": {
    "addr:full":"Leopoldplein 14 Box 4 Hasselt Limburg 3500",
    "addr:housenumber":"14;4",
    "addr:postcode":"3500",
    "addr:street":"Leopoldplein;Box",
    "iso:country":"BE",
    "sg:address":"Leopoldplein 14 Box 4",
    "sg:city":"Hasselt",
    "sg:classifiers":[
        {
            "category":"Health Services",
            "subcategory":"Dentist",
            "type":"Services"
        }
    ],
    "sg:phone":"+32 11 22 32 31",
    "sg:postcode":"3500",
    "sg:province":"Limburg",
    "wof:name":"Van Enis Francis",
    "wof:placetype":"venue"
},
  "geometry": {"coordinates":[5.3352088928,50.9274024963],"type":"Point"}
}