{
  "type": "Feature",
  "properties": {
    "iso:country":"BE",
    "sg:address":"Rue Courbelette 114",
    "sg:city":"Quaregnon",
    "sg:classifiers":[
        {
            "category":"Professional",
            "subcategory":"Accounting & Tax Preparation",
            "type":"Services"
        }
    ],
    "sg:phone":"+32 65 78 03 81",
    "sg:postcode":"7390",
    "sg:province":"Hainaut",
    "sg:tags":[
        "accountant"
    ],
    "wof:name":"Jean Duez",
    "wof:placetype":"venue"
},
  "geometry": {"coordinates":[3.8589379787,50.4463882446],"type":"Point"}
}