{
  "type": "Feature",
  "properties": {
    "iso:country":"BE",
    "sg:address":"Rue Emile Strimelle 24",
    "sg:city":"Charleroi",
    "sg:orig_category":"Sportclubs",
    "sg:phone":"+32 71 35 89 70",
    "sg:postcode":"6040",
    "sg:province":"Hainaut",
    "wof:name":"V.c. Jumet",
    "wof:placetype":"venue"
},
  "geometry": {"coordinates":[4.4185261726,50.4348182678],"type":"Point"}
}