{
  "type": "Feature",
  "properties": {
    "addr:full":"Rue Sous L'eau 58 Li\u00e8ge 1 (li\u00e8ge 2) Li\u00e8ge 4020",
    "addr:housenumber":"58;1;2",
    "addr:postcode":"4020",
    "addr:street":"Rue Sous L'Eau",
    "iso:country":"BE",
    "sg:address":"Rue Sous L'eau 58",
    "sg:city":"Li\u00e8ge 1 (li\u00e8ge 2)",
    "sg:classifiers":[
        {
            "category":"Health Services",
            "subcategory":"Health Practitioner",
            "type":"Services"
        }
    ],
    "sg:phone":"+32 4 343 11 50",
    "sg:postcode":"4020",
    "sg:province":"Li\u00e8ge",
    "sg:tags":[
        "physiotherapist"
    ],
    "wof:name":"Gatsinzi Charles",
    "wof:placetype":"venue"
},
  "geometry": {"coordinates":[5.590929985,50.6390724182],"type":"Point"}
}