{
  "type": "Feature",
  "properties": {
    "addr:full":"Provincialeweg 4 Sint-amands Antwerpen 2890",
    "addr:housenumber":"4",
    "addr:postcode":"2890",
    "addr:street":"Provincialeweg",
    "iso:country":"BE",
    "sg:address":"Provincialeweg 4",
    "sg:city":"Sint-amands",
    "sg:classifiers":[
        {
            "category":"Retail",
            "subcategory":"Auto Repair",
            "type":"Services"
        }
    ],
    "sg:phone":"+32 52 33 52 56",
    "sg:postcode":"2890",
    "sg:province":"Antwerpen",
    "sg:tags":[
        "garage"
    ],
    "wof:name":"Faes G",
    "wof:placetype":"venue"
},
  "geometry": {"coordinates":[4.2076401711,51.0348091125],"type":"Point"}
}