{
  "type": "Feature",
  "properties": {
    "iso:country":"BE",
    "sg:address":"Boulevard Saint-michel 47",
    "sg:city":"Bruxelles (etterbeek)",
    "sg:classifiers":[
        {
            "category":"Manufacturing",
            "subcategory":"Metals",
            "type":"Manufacturing & Wholesale Goods"
        }
    ],
    "sg:phone":"+32 2 755 00 50",
    "sg:postcode":"1040",
    "sg:province":"Bruxelles-Capitale",
    "sg:tags":[
        "alloy",
        "aluminium"
    ],
    "wof:name":"As Benelux",
    "wof:placetype":"venue"
},
  "geometry": {"coordinates":[4.4057440758,50.8347663879],"type":"Point"}
}