{
  "type": "Feature",
  "properties": {
    "addr:full":"Herenthoutseweg 81 Herentals Antwerpen 2200",
    "addr:housenumber":"81",
    "addr:postcode":"2200",
    "addr:street":"Herenthoutseweg",
    "iso:country":"BE",
    "sg:address":"Herenthoutseweg 81",
    "sg:city":"Herentals",
    "sg:classifiers":[
        {
            "category":"Health Services",
            "subcategory":"Health Practitioner",
            "type":"Services"
        }
    ],
    "sg:phone":"+32 14 21 28 57",
    "sg:postcode":"2200",
    "sg:province":"Antwerpen",
    "sg:tags":[
        "physiotherapist"
    ],
    "wof:name":"Maes Tom",
    "wof:placetype":"venue"
},
  "geometry": {"coordinates":[4.8325800896,51.1716117859],"type":"Point"}
}