{
  "type": "Feature",
  "properties": {
    "addr:full":"Avenue Ch\u00c2teau De Walzin 10ab36 Ukkel/uccle Bruxelles-Capitale 1180",
    "addr:postcode":"1180",
    "addr:street":"Avenue Cha\u0302Teau De Walzin 10Ab36",
    "iso:country":"BE",
    "sg:address":"Avenue Ch\u00c2teau De Walzin 10ab36",
    "sg:city":"Ukkel/uccle",
    "sg:orig_category":"Agences immobili\u00e8res. Evaluation and estimation de biens immobiliers. Administration d'immeubles",
    "sg:phone":"+32 2 343 65 70",
    "sg:postcode":"1180",
    "sg:province":"Bruxelles-Capitale",
    "wof:name":"Cabinet Carlier",
    "wof:placetype":"venue"
},
  "geometry": {"coordinates":[4.3483548164,50.809009552],"type":"Point"}
}