{
  "type": "Feature",
  "properties": {
    "addr:full":"Rue Eug\u00e8ne Vandenhoff 86 Li\u00e8ge 1 (grivegn\u00e9e) Li\u00e8ge 4030",
    "addr:housenumber":"86;1",
    "addr:postcode":"4030",
    "addr:street":"Rue Euge\u0300Ne Vandenhoff",
    "iso:country":"BE",
    "sg:address":"Rue Eug\u00e8ne Vandenhoff 86",
    "sg:city":"Li\u00e8ge 1 (grivegn\u00e9e)",
    "sg:classifiers":[
        {
            "category":"Bars & Pubs",
            "type":"Food & Drink"
        }
    ],
    "sg:phone":"+32 4 342 59 45",
    "sg:postcode":"4030",
    "sg:province":"Li\u00e8ge",
    "sg:tags":[
        "tavern"
    ],
    "wof:name":"Time (le)",
    "wof:placetype":"venue"
},
  "geometry": {"coordinates":[5.6027140617,50.6303520203],"type":"Point"}
}