{
  "type": "Feature",
  "properties": {
    "iso:country":"BE",
    "sg:address":"Zammelseweg 183",
    "sg:city":"Geel",
    "sg:orig_category":"Enseignement maternel and primaire",
    "sg:phone":"+32 14 54 48 80",
    "sg:postcode":"2440",
    "sg:province":"Antwerpen",
    "wof:name":"Stedelijke Kleuterschool",
    "wof:placetype":"venue"
},
  "geometry": {"coordinates":[4.9504637718,51.0996665955],"type":"Point"}
}