{
  "type": "Feature",
  "properties": {
    "addr:full":"Ganzenpoelstraat 31 Maasmechelen (leut) Limburg 3630",
    "addr:housenumber":"31",
    "addr:postcode":"3630",
    "addr:street":"Ganzenpoelstraat",
    "iso:country":"BE",
    "sg:address":"Ganzenpoelstraat 31",
    "sg:city":"Maasmechelen (leut)",
    "sg:classifiers":[
        {
            "category":"Home & Garden",
            "subcategory":"Kitchen Supply",
            "type":"Retail Goods"
        }
    ],
    "sg:phone":"+32 89 79 35 25",
    "sg:postcode":"3630",
    "sg:province":"Limburg",
    "sg:tags":[
        "installation"
    ],
    "wof:name":"Mesterom Keukens",
    "wof:placetype":"venue"
},
  "geometry": {"coordinates":[5.6961350441,50.963848114],"type":"Point"}
}