{
  "type": "Feature",
  "properties": {
    "iso:country":"BE",
    "sg:address":"Watersniplaan 1",
    "sg:city":"Brecht",
    "sg:classifiers":[
        {
            "category":"Wholesale",
            "subcategory":"Plants",
            "type":"Manufacturing & Wholesale Goods"
        }
    ],
    "sg:phone":"+32 3 636 40 73",
    "sg:postcode":"2960",
    "sg:province":"Antwerpen",
    "sg:tags":[
        "whol",
        "flower",
        "-",
        "grower"
    ],
    "wof:name":"Van Der Lans Bvba",
    "wof:placetype":"venue"
},
  "geometry": {"coordinates":[4.5642461777,51.308971405],"type":"Point"}
}