{
  "type": "Feature",
  "properties": {
    "addr:full":"Rue Du Pot D'or 15 Liege Li\u00e8ge 4000",
    "addr:housenumber":"15",
    "addr:postcode":"4000",
    "addr:street":"Rue Du Pot D'Or",
    "iso:country":"BE",
    "sg:address":"Rue Du Pot D'or 15",
    "sg:city":"Liege",
    "sg:orig_category":"Schoonheidssalons",
    "sg:phone":"+32 4 222 43 12",
    "sg:postcode":"4000",
    "sg:province":"Li\u00e8ge",
    "wof:name":"Just Nails",
    "wof:placetype":"venue"
},
  "geometry": {"coordinates":[5.5848197937,50.6475486755],"type":"Point"}
}