{
  "type": "Feature",
  "properties": {
    "iso:country":"BE",
    "sg:address":"Chauss\u00e9e Brunehaut 280",
    "sg:city":"Juprelle (villers-saint-sim\u00e9on)",
    "sg:classifiers":[
        {
            "category":"Professional",
            "subcategory":"Engineering",
            "type":"Services"
        }
    ],
    "sg:phone":"+32 4 289 00 12",
    "sg:postcode":"4453",
    "sg:province":"Li\u00e8ge",
    "sg:tags":[
        "precision"
    ],
    "wof:name":"Atelier Th\u00e9o Boveroux Sa",
    "wof:placetype":"venue"
},
  "geometry": {"coordinates":[5.5448598862,50.7069206238],"type":"Point"}
}