{
  "type": "Feature",
  "properties": {
    "iso:country":"BE",
    "sg:address":"Coupure Links 455",
    "sg:city":"Gent",
    "sg:classifiers":[
        {
            "category":"Wholesale",
            "subcategory":"Medical Equipment & Supplies",
            "type":"Manufacturing & Wholesale Goods"
        }
    ],
    "sg:phone":"+32 475 56 50 36",
    "sg:postcode":"9000",
    "sg:province":"Oost-Vlaanderen",
    "sg:tags":[
        "instrument",
        "apparatus"
    ],
    "wof:name":"Vanderhaeghen V",
    "wof:placetype":"venue"
},
  "geometry": {"coordinates":[3.7103590965,51.0499267578],"type":"Point"}
}