{
  "type": "Feature",
  "properties": {
    "iso:country":"BE",
    "sg:address":"Blauwhondstraat 3",
    "sg:city":"Mechelen",
    "sg:orig_category":"V\u00eatements",
    "sg:phone":"+32 15 21 96 23",
    "sg:postcode":"2800",
    "sg:province":"Antwerpen",
    "wof:name":"Avenues",
    "wof:placetype":"venue"
},
  "geometry": {"coordinates":[4.4795751572,51.0271186829],"type":"Point"}
}