{
  "type": "Feature",
  "properties": {
    "addr:full":"Nieuwpoortstraat 47 Knokke-heist West-Vlaanderen 8300",
    "addr:housenumber":"47",
    "addr:postcode":"8300",
    "addr:street":"Nieuwpoortstraat",
    "iso:country":"BE",
    "sg:address":"Nieuwpoortstraat 47",
    "sg:city":"Knokke-heist",
    "sg:classifiers":[
        {
            "category":"Personal",
            "subcategory":"Beauty Salon",
            "type":"Services"
        }
    ],
    "sg:phone":"+32 50 61 18 05",
    "sg:postcode":"8300",
    "sg:province":"West-Vlaanderen",
    "sg:tags":[
        "de",
        "coiffure"
    ],
    "wof:name":"Coiffure John",
    "wof:placetype":"venue"
},
  "geometry": {"coordinates":[3.287694931,51.3467254639],"type":"Point"}
}