{
  "type": "Feature",
  "properties": {
    "addr:full":"Rue Du Bailli 35 Bruxelles (ixelles) Bruxelles-Capitale 1050",
    "addr:housenumber":"35",
    "addr:postcode":"1050",
    "addr:street":"Rue Du Bailli",
    "iso:country":"BE",
    "sg:address":"Rue Du Bailli 35",
    "sg:city":"Bruxelles (ixelles)",
    "sg:orig_category":"Ice-cream parlours",
    "sg:phone":"+32 2 647 51 44",
    "sg:postcode":"1050",
    "sg:province":"Bruxelles-Capitale",
    "wof:name":"Framboisier Dor\u00e9 (le)",
    "wof:placetype":"venue"
},
  "geometry": {"coordinates":[4.3616580963,50.8266029358],"type":"Point"}
}