{
  "type": "Feature",
  "properties": {
    "addr:full":"Schaluin 49 Aarschot Vlaams-Brabant 3200",
    "addr:housenumber":"49",
    "addr:postcode":"3200",
    "addr:street":"Schaluin",
    "iso:country":"BE",
    "sg:address":"Schaluin 49",
    "sg:city":"Aarschot",
    "sg:orig_category":"Kapsalons",
    "sg:phone":"+32 16 56 66 74",
    "sg:postcode":"3200",
    "sg:province":"Vlaams-Brabant",
    "wof:name":"Jeannine Van Craen",
    "wof:placetype":"venue"
},
  "geometry": {"coordinates":[4.8410210609,50.9896354675],"type":"Point"}
}