{
  "type": "Feature",
  "properties": {
    "addr:full":"Sint-jansstraat 183 Essen Antwerpen 2910",
    "addr:housenumber":"183",
    "addr:postcode":"2910",
    "addr:street":"Sint-Jansstraat",
    "iso:country":"BE",
    "sg:address":"Sint-jansstraat 183",
    "sg:city":"Essen",
    "sg:orig_category":"Installation \u00e9lectrique r\u00e9sidentielle",
    "sg:phone":"+32 3 677 22 81",
    "sg:postcode":"2910",
    "sg:province":"Antwerpen",
    "wof:name":"Electro Brosens-van Dyck",
    "wof:placetype":"venue"
},
  "geometry": {"coordinates":[4.4769611359,51.4241752625],"type":"Point"}
}