{
  "type": "Feature",
  "properties": {
    "addr:full":"De Heuvels 36 Brasschaat Antwerpen 2930",
    "addr:housenumber":"36",
    "addr:postcode":"2930",
    "addr:street":"De Heuvels",
    "iso:country":"BE",
    "sg:address":"De Heuvels 36",
    "sg:city":"Brasschaat",
    "sg:orig_category":"Reclamebureaus",
    "sg:phone":"+32 3 651 64 39",
    "sg:postcode":"2930",
    "sg:province":"Antwerpen",
    "wof:name":"Werner Van Osta",
    "wof:placetype":"venue"
},
  "geometry": {"coordinates":[4.5063209534,51.2866783142],"type":"Point"}
}