{
  "type": "Feature",
  "properties": {
    "addr:full":"Groenenborgerlaan 15 Antwerpen (wilrijk) Antwerpen 2610",
    "addr:housenumber":"15",
    "addr:postcode":"2610",
    "addr:street":"Groenenborgerlaan;Antwerpen",
    "iso:country":"BE",
    "sg:address":"Groenenborgerlaan 15",
    "sg:city":"Antwerpen (wilrijk)",
    "sg:classifiers":[
        {
            "category":"Professional",
            "subcategory":"Computer Services",
            "type":"Services"
        }
    ],
    "sg:phone":"+32 495 38 51 91",
    "sg:postcode":"2610",
    "sg:province":"Antwerpen",
    "sg:tags":[
        "-",
        "processing",
        "data"
    ],
    "wof:name":"T.c. Company Bvba",
    "wof:placetype":"venue"
},
  "geometry": {"coordinates":[4.3946051598,51.1691131592],"type":"Point"}
}