{
  "type": "Feature",
  "properties": {
    "addr:full":"Biezenstraat 46 Erpe-mere Oost-Vlaanderen 9420",
    "addr:housenumber":"46",
    "addr:postcode":"9420",
    "addr:street":"Biezenstraat",
    "iso:country":"BE",
    "sg:address":"Biezenstraat 46",
    "sg:city":"Erpe-mere",
    "sg:orig_category":"Avocats and conseillers juridiques",
    "sg:phone":"+32 53 62 82 40",
    "sg:postcode":"9420",
    "sg:province":"Oost-Vlaanderen",
    "wof:name":"Lieve Moereels",
    "wof:placetype":"venue"
},
  "geometry": {"coordinates":[3.9209799767,50.9070053101],"type":"Point"}
}