{
  "type": "Feature",
  "properties": {
    "iso:country":"BE",
    "sg:address":"Stationsstraat 271",
    "sg:city":"Dilbeek",
    "sg:classifiers":[
        {
            "category":"Education",
            "subcategory":"School",
            "type":"Public Place"
        }
    ],
    "sg:phone":"+32 2 466 20 36",
    "sg:postcode":"1700",
    "sg:province":"Vlaams-Brabant",
    "sg:tags":[
        "primary"
    ],
    "wof:name":"Savio",
    "wof:placetype":"venue"
},
  "geometry": {"coordinates":[4.2457132339,50.8640327454],"type":"Point"}
}