{
  "type": "Feature",
  "properties": {
    "addr:full":"Mande-saint-etienne 918 Bertogne Luxembourg 6688",
    "addr:housenumber":"918",
    "addr:postcode":"6688",
    "iso:country":"BE",
    "sg:address":"Mande-saint-etienne 918",
    "sg:city":"Bertogne",
    "sg:orig_category":"Eleveurs de bovins",
    "sg:phone":"+32 61 21 14 38",
    "sg:postcode":"6688",
    "sg:province":"Luxembourg",
    "wof:name":"Jean Goosse",
    "wof:placetype":"venue"
},
  "geometry": {"coordinates":[5.6400618553,50.0166015625],"type":"Point"}
}