{
  "type": "Feature",
  "properties": {
    "addr:full":"Steenweg Op Sevendonk 45 Oud-turnhout Antwerpen 2360",
    "addr:housenumber":"45",
    "addr:postcode":"2360",
    "addr:street":"Steenweg Op Sevendonk",
    "iso:country":"BE",
    "sg:address":"Steenweg Op Sevendonk 45",
    "sg:city":"Oud-turnhout",
    "sg:classifiers":[
        {
            "category":"Personal",
            "subcategory":"Beauty Salon",
            "type":"Services"
        }
    ],
    "sg:phone":"+32 14 45 29 18",
    "sg:postcode":"2360",
    "sg:province":"Antwerpen",
    "sg:tags":[
        "lady",
        "-",
        "hairdressing"
    ],
    "wof:name":"Bijou",
    "wof:placetype":"venue"
},
  "geometry": {"coordinates":[4.9801530838,51.3151016235],"type":"Point"}
}