{
  "type": "Feature",
  "properties": {
    "addr:full":"Place De L'hotel De Ville 2 Eupen Li\u00e8ge 4700",
    "addr:housenumber":"2",
    "addr:postcode":"4700",
    "addr:street":"Place De L'Hotel De Ville",
    "iso:country":"BE",
    "sg:address":"Place De L'hotel De Ville 2",
    "sg:city":"Eupen",
    "sg:classifiers":[
        {
            "category":"Restaurant",
            "type":"Food & Drink"
        }
    ],
    "sg:phone":"+32 87 55 69 13",
    "sg:postcode":"4700",
    "sg:province":"Li\u00e8ge",
    "wof:name":"Brasserie Sain-vincent",
    "wof:placetype":"venue"
},
  "geometry": {"coordinates":[6.1348800659,50.5989990234],"type":"Point"}
}