{
  "type": "Feature",
  "properties": {
    "iso:country":"BE",
    "sg:address":"Groot Burkeldreef 1",
    "sg:city":"Maldegem",
    "sg:orig_category":"Rundveehouders",
    "sg:phone":"+32 50 71 71 96",
    "sg:postcode":"9990",
    "sg:province":"Oost-Vlaanderen",
    "wof:name":"Norbert Fransoo",
    "wof:placetype":"venue"
},
  "geometry": {"coordinates":[3.4065599442,51.1740493774],"type":"Point"}
}