{
  "type": "Feature",
  "properties": {
    "addr:full":"Franseliniestraat 8 Aarschot (langdorp) Vlaams-Brabant 3201",
    "addr:housenumber":"8",
    "addr:postcode":"3201",
    "addr:street":"Franseliniestraat",
    "iso:country":"BE",
    "sg:address":"Franseliniestraat 8",
    "sg:city":"Aarschot (langdorp)",
    "sg:classifiers":[
        {
            "category":"Building & Trades",
            "subcategory":"Electrical",
            "type":"Services"
        }
    ],
    "sg:phone":"+32 16 56 78 95",
    "sg:postcode":"3201",
    "sg:province":"Vlaams-Brabant",
    "sg:tags":[
        "electric",
        "-",
        "housewiring",
        "contractor"
    ],
    "wof:name":"Thiels P",
    "wof:placetype":"venue"
},
  "geometry": {"coordinates":[4.8545432091,50.9884109497],"type":"Point"}
}