{
  "type": "Feature",
  "properties": {
    "addr:full":"Rue De La Planquette 34 Colfontaine (wasmes) Hainaut 7340",
    "addr:housenumber":"34",
    "addr:postcode":"7340",
    "addr:street":"Rue De La Planquette",
    "iso:country":"BE",
    "sg:address":"Rue De La Planquette 34",
    "sg:city":"Colfontaine (wasmes)",
    "sg:classifiers":[
        {
            "category":"Building & Trades",
            "subcategory":"Plumbing",
            "type":"Services"
        }
    ],
    "sg:phone":"+32 65 67 25 00",
    "sg:postcode":"7340",
    "sg:province":"Hainaut",
    "sg:tags":[
        "repair",
        "mainten",
        "-",
        "central",
        "heating"
    ],
    "wof:name":"Abrassart Y",
    "wof:placetype":"venue"
},
  "geometry": {"coordinates":[3.8468821049,50.4174499512],"type":"Point"}
}