{
  "type": "Feature",
  "properties": {
    "addr:full":"Route De Diekirch 371 Arlon Luxembourg 6700",
    "addr:housenumber":"371",
    "addr:postcode":"6700",
    "addr:street":"Route De Diekirch",
    "iso:country":"BE",
    "sg:address":"Route De Diekirch 371",
    "sg:city":"Arlon",
    "sg:classifiers":[
        {
            "category":"Cafe",
            "type":"Food & Drink"
        }
    ],
    "sg:phone":"+32 63 22 54 59",
    "sg:postcode":"6700",
    "sg:province":"Luxembourg",
    "sg:tags":[
        "caf\u00e9s"
    ],
    "wof:name":"Jean-pierre Koob",
    "wof:placetype":"venue"
},
  "geometry": {"coordinates":[5.8174500465,49.6897201538],"type":"Point"}
}