{
  "type": "Feature",
  "properties": {
    "addr:full":"Lozenhoekstraat 43 Keerbergen Vlaams-Brabant 3140",
    "addr:housenumber":"43",
    "addr:postcode":"3140",
    "addr:street":"Lozenhoekstraat",
    "iso:country":"BE",
    "sg:address":"Lozenhoekstraat 43",
    "sg:city":"Keerbergen",
    "sg:classifiers":[
        {
            "category":"Professional",
            "subcategory":"Printing & Photocopies",
            "type":"Services"
        }
    ],
    "sg:phone":"+32 15 23 01 69",
    "sg:postcode":"3140",
    "sg:province":"Vlaams-Brabant",
    "sg:tags":[
        "occasional",
        "-"
    ],
    "wof:name":"Crea + Bvba",
    "wof:placetype":"venue"
},
  "geometry": {"coordinates":[4.7004289627,51.0134887695],"type":"Point"}
}