{
  "type": "Feature",
  "properties": {
    "iso:country":"BE",
    "sg:address":"Rue Du Bailli 4",
    "sg:city":"Elsene/ixelles",
    "sg:orig_category":"Pain, p\u00e2tisseries and confiseries",
    "sg:phone":"+32 2 648 62 18",
    "sg:postcode":"1050",
    "sg:province":"Bruxelles-Capitale",
    "wof:name":"Teddy L.",
    "wof:placetype":"venue"
},
  "geometry": {"coordinates":[4.3620100021,50.8265914917],"type":"Point"}
}