{
  "type": "Feature",
  "properties": {
    "iso:country":"BE",
    "sg:address":"Rue Des Roches 22",
    "sg:city":"Comblain-au-pont",
    "sg:classifiers":[
        {
            "category":"Real Estate",
            "subcategory":"Architect",
            "type":"Services"
        }
    ],
    "sg:phone":"+32 4 369 21 08",
    "sg:postcode":"4170",
    "sg:province":"Li\u00e8ge",
    "wof:name":"Glaude J",
    "wof:placetype":"venue"
},
  "geometry": {"coordinates":[5.5781359673,50.4785614014],"type":"Point"}
}