{
  "type": "Feature",
  "properties": {
    "iso:country":"BE",
    "sg:address":"Risquons-toutsteenweg 375",
    "sg:city":"Moeskroen/mouscron",
    "sg:classifiers":[
        {
            "category":"Communications",
            "subcategory":"Television Station",
            "type":"Services"
        }
    ],
    "sg:phone":"+32 56 84 67 86",
    "sg:postcode":"7700",
    "sg:province":"Hainaut",
    "sg:tags":[
        "video",
        "audio",
        "verhuur"
    ],
    "wof:name":"Alberto Storari",
    "wof:placetype":"venue"
},
  "geometry": {"coordinates":[3.2323200703,50.7400932312],"type":"Point"}
}