{
  "type": "Feature",
  "properties": {
    "iso:country":"BE",
    "sg:address":"Iepersestraat 142",
    "sg:city":"Kortrijk",
    "sg:orig_category":"Ergotherapists",
    "sg:phone":"+32 56 37 16 28",
    "sg:postcode":"8500",
    "sg:province":"West-Vlaanderen",
    "wof:name":"De Smedt J",
    "wof:placetype":"venue"
},
  "geometry": {"coordinates":[3.2697210312,50.842628479],"type":"Point"}
}