{
  "type": "Feature",
  "properties": {
    "iso:country":"BE",
    "sg:address":"President Kennedypark 29ba",
    "sg:city":"Kortrijk",
    "sg:orig_category":"Diverse bedrijfsbeheeradviesbureaus Verzekeringsmakelaars and experts",
    "sg:phone":"+32 56 20 08 19",
    "sg:postcode":"8500",
    "sg:province":"West-Vlaanderen",
    "wof:name":"Verkoral Consulting",
    "wof:placetype":"venue"
},
  "geometry": {"coordinates":[3.277641058,50.8052406311],"type":"Point"}
}