{
  "type": "Feature",
  "properties": {
    "addr:full":"Binnenweg 24 Kinrooi Limburg 3640",
    "addr:housenumber":"24",
    "addr:postcode":"3640",
    "addr:street":"Binnenweg",
    "iso:country":"BE",
    "sg:address":"Binnenweg 24",
    "sg:city":"Kinrooi",
    "sg:classifiers":[
        {
            "category":"Structure",
            "subcategory":"Building",
            "type":"Public Place"
        }
    ],
    "sg:phone":"+32 496 91 15 16",
    "sg:postcode":"3640",
    "sg:province":"Limburg",
    "sg:tags":[
        "door"
    ],
    "wof:name":"Maggen Val\u00e8re",
    "wof:placetype":"venue"
},
  "geometry": {"coordinates":[5.7270159721,51.1482315063],"type":"Point"}
}