{
  "type": "Feature",
  "properties": {
    "addr:full":"Koningin Elisabethlaan 78 Sint-niklaas Oost-Vlaanderen 9100",
    "addr:housenumber":"78",
    "addr:postcode":"9100",
    "addr:street":"Koningin Elisabethlaan",
    "iso:country":"BE",
    "sg:address":"Koningin Elisabethlaan 78",
    "sg:city":"Sint-niklaas",
    "sg:orig_category":"Administration d'immeubles",
    "sg:phone":"+32 3 776 14 35",
    "sg:postcode":"9100",
    "sg:province":"Oost-Vlaanderen",
    "wof:name":"Guido Van Assche",
    "wof:placetype":"venue"
},
  "geometry": {"coordinates":[4.1561441422,51.1703491211],"type":"Point"}
}