{
  "type": "Feature",
  "properties": {
    "addr:full":"Engels Plein 17 Leuven Vlaams-Brabant 3000",
    "addr:housenumber":"17",
    "addr:postcode":"3000",
    "addr:street":"Engels Plein",
    "iso:country":"BE",
    "sg:address":"Engels Plein 17",
    "sg:city":"Leuven",
    "sg:orig_category":"Sport- and kampeermateriaal Sportclubs",
    "sg:phone":"+32 16 29 44 48",
    "sg:postcode":"3000",
    "sg:province":"Vlaams-Brabant",
    "wof:name":"Buds",
    "wof:placetype":"venue"
},
  "geometry": {"coordinates":[4.701818943,50.8883094788],"type":"Point"}
}