{
  "type": "Feature",
  "properties": {
    "addr:full":"Honzebroekstraat 83 Roeselare West-Vlaanderen 8800",
    "addr:housenumber":"83",
    "addr:postcode":"8800",
    "addr:street":"Honzebroekstraat",
    "iso:country":"BE",
    "sg:address":"Honzebroekstraat 83",
    "sg:city":"Roeselare",
    "sg:classifiers":[
        {
            "category":"Freight",
            "type":"Transportation"
        }
    ],
    "sg:phone":"+32 51 20 84 29",
    "sg:postcode":"8800",
    "sg:province":"West-Vlaanderen",
    "sg:tags":[
        "express",
        "transport"
    ],
    "wof:name":"Courier- En Expresdienst Verstraete",
    "wof:placetype":"venue"
},
  "geometry": {"coordinates":[3.1124579906,50.9639968872],"type":"Point"}
}