{
  "type": "Feature",
  "properties": {
    "addr:full":"Avenue De La For\u00eat 6 Bruxelles (ixelles) Bruxelles-Capitale 1050",
    "addr:housenumber":"6",
    "addr:postcode":"1050",
    "addr:street":"Avenue De La Fore\u0302T",
    "iso:country":"BE",
    "sg:address":"Avenue De La For\u00eat 6",
    "sg:city":"Bruxelles (ixelles)",
    "sg:classifiers":[
        {
            "category":"Professional",
            "subcategory":"Computer Services",
            "type":"Services"
        }
    ],
    "sg:phone":"+32 2 679 00 80",
    "sg:postcode":"1050",
    "sg:province":"Bruxelles-Capitale",
    "sg:tags":[
        "network"
    ],
    "wof:name":"C.m.s. Benelux",
    "wof:placetype":"venue"
},
  "geometry": {"coordinates":[4.3915309906,50.8022232056],"type":"Point"}
}