{
  "type": "Feature",
  "properties": {
    "iso:country":"BE",
    "sg:address":"Pontbrouckstraat 4",
    "sg:city":"Dentergem",
    "sg:classifiers":[
        {
            "category":"Farming",
            "subcategory":"Farm & Veterinary Services",
            "type":"Manufacturing & Wholesale Goods"
        }
    ],
    "sg:phone":"+32 51 63 32 09",
    "sg:postcode":"8720",
    "sg:province":"West-Vlaanderen",
    "sg:tags":[
        "agricultural",
        "contractor"
    ],
    "wof:name":"Demarez F",
    "wof:placetype":"venue"
},
  "geometry": {"coordinates":[3.4113109112,50.9688682556],"type":"Point"}
}