{
  "type": "Feature",
  "properties": {
    "iso:country":"BE",
    "sg:address":"Place Albert 1er 26",
    "sg:city":"Thuin",
    "sg:orig_category":"Enseignement maternel and primaire",
    "sg:phone":"+32 71 59 14 65",
    "sg:postcode":"6530",
    "sg:province":"Hainaut",
    "wof:name":"Ecole Primaire Libre",
    "wof:placetype":"venue"
},
  "geometry": {"coordinates":[4.2869858742,50.339389801],"type":"Point"}
}