{
  "type": "Feature",
  "properties": {
    "addr:full":"Hogeweg 7 Asse Vlaams-Brabant 1730",
    "addr:housenumber":"7",
    "addr:postcode":"1730",
    "addr:street":"Hogeweg",
    "iso:country":"BE",
    "sg:address":"Hogeweg 7",
    "sg:city":"Asse",
    "sg:classifiers":[
        {
            "category":"Professional",
            "subcategory":"Engineering",
            "type":"Services"
        }
    ],
    "sg:phone":"+32 2 453 06 09",
    "sg:postcode":"1730",
    "sg:province":"Vlaams-Brabant",
    "sg:tags":[
        "civil",
        "offices-"
    ],
    "wof:name":"Aska Engineering Bvba",
    "wof:placetype":"venue"
},
  "geometry": {"coordinates":[4.1587238312,50.9060173035],"type":"Point"}
}