{
  "type": "Feature",
  "properties": {
    "iso:country":"BE",
    "sg:address":"Markt 57b3",
    "sg:city":"Deinze",
    "sg:classifiers":[
        {
            "category":"Arena",
            "subcategory":"Sports Club",
            "type":"Entertainment"
        }
    ],
    "sg:phone":"+32 9 380 26 85",
    "sg:postcode":"9800",
    "sg:province":"Oost-Vlaanderen",
    "sg:tags":[
        "de"
    ],
    "wof:name":"T.c. Witte Kaproenen",
    "wof:placetype":"venue"
},
  "geometry": {"coordinates":[3.5262520313,50.9853858948],"type":"Point"}
}