{
  "type": "Feature",
  "properties": {
    "iso:country":"BE",
    "sg:address":"Berkenhoekstraat 2",
    "sg:city":"Sint-katelijne-waver (onze-lieve-vrouw-waver)",
    "sg:classifiers":[
        {
            "category":"Banks & Credit Unions",
            "subcategory":"Investment Brokerage",
            "type":"Services"
        }
    ],
    "sg:phone":"+32 15 75 25 75",
    "sg:postcode":"2861",
    "sg:province":"Antwerpen",
    "sg:tags":[
        "detection",
        "gas"
    ],
    "wof:name":"Elmaco Nv",
    "wof:placetype":"venue"
},
  "geometry": {"coordinates":[4.568734169,51.0550041199],"type":"Point"}
}