{
  "type": "Feature",
  "properties": {
    "iso:country":"BE",
    "sg:address":"Laagstraat 38",
    "sg:city":"Temse",
    "sg:classifiers":[
        {
            "category":"Home & Garden",
            "subcategory":"Home Furnishings",
            "type":"Retail Goods"
        }
    ],
    "sg:phone":"+32 3 771 09 90",
    "sg:postcode":"9140",
    "sg:province":"Oost-Vlaanderen",
    "sg:tags":[
        "fitting",
        "furniture"
    ],
    "wof:name":"Roelens Nv",
    "wof:placetype":"venue"
},
  "geometry": {"coordinates":[4.1925110817,51.1414031982],"type":"Point"}
}