{
  "type": "Feature",
  "properties": {
    "iso:country":"BE",
    "sg:address":"Rue De La Station 88",
    "sg:city":"Paliseul",
    "sg:orig_category":"Auto-\u00e9coles",
    "sg:phone":"+32 61 23 01 70",
    "sg:postcode":"6850",
    "sg:province":"Luxembourg",
    "wof:name":"Auto-ecole Ardennes",
    "wof:placetype":"venue"
},
  "geometry": {"coordinates":[5.1209101677,49.8969726562],"type":"Point"}
}