{
  "type": "Feature",
  "properties": {
    "addr:full":"Brakelstraat 93 Zottegem Oost-Vlaanderen 9620",
    "addr:housenumber":"93",
    "addr:postcode":"9620",
    "addr:street":"Brakelstraat",
    "iso:country":"BE",
    "sg:address":"Brakelstraat 93",
    "sg:city":"Zottegem",
    "sg:classifiers":[
        {
            "category":"Insurance",
            "subcategory":"Insurance Agent",
            "type":"Services"
        }
    ],
    "sg:phone":"+32 9 360 68 76",
    "sg:postcode":"9620",
    "sg:province":"Oost-Vlaanderen",
    "sg:tags":[
        "verzekeringsmakelaars",
        "expert"
    ],
    "wof:name":"Euro-assur",
    "wof:placetype":"venue"
},
  "geometry": {"coordinates":[3.8112111092,50.871181488],"type":"Point"}
}