{
  "type": "Feature",
  "properties": {
    "iso:country":"BE",
    "sg:address":"32",
    "sg:city":"Rue Edouard Dinot 5590 Ciney",
    "sg:classifiers":[
        {
            "category":"Health Services",
            "subcategory":"Medical Lab",
            "type":"Services"
        }
    ],
    "sg:phone":"+32 83 23 12 43",
    "sg:postcode":"32",
    "sg:tags":[
        "chemical",
        "pharmaceutical",
        "pharmacy"
    ],
    "wof:name":"L'economie Populaire De Ciney Scrl",
    "wof:placetype":"venue"
},
  "geometry": {"coordinates":[5.0995402336,50.294128418],"type":"Point"}
}