{
  "type": "Feature",
  "properties": {
    "addr:full":"Lindestraat 5 Erpe-mere (erondegem) Oost-Vlaanderen 9420",
    "addr:housenumber":"5",
    "addr:postcode":"9420",
    "addr:street":"Lindestraat",
    "iso:country":"BE",
    "sg:address":"Lindestraat 5",
    "sg:city":"Erpe-mere (erondegem)",
    "sg:classifiers":[
        {
            "category":"Professional",
            "subcategory":"Computer Services",
            "type":"Services"
        }
    ],
    "sg:phone":"+32 53 80 53 67",
    "sg:postcode":"9420",
    "sg:province":"Oost-Vlaanderen",
    "sg:tags":[
        "-",
        "processing",
        "data",
        "software"
    ],
    "wof:name":"Geers H",
    "wof:placetype":"venue"
},
  "geometry": {"coordinates":[3.9441180229,50.9458885193],"type":"Point"}
}