{
  "type": "Feature",
  "properties": {
    "addr:full":"Zonienwoudlaan 50b294 Sint-genesius-rode/rhode-saint-genese Vlaams-Brabant 1640",
    "addr:housenumber":"50b294",
    "addr:postcode":"1640",
    "addr:street":"Zonienwoudlaan",
    "iso:country":"BE",
    "sg:address":"Zonienwoudlaan 50b294",
    "sg:city":"Sint-genesius-rode/rhode-saint-genese",
    "sg:orig_category":"Artsen and specialisten",
    "sg:phone":"+32 2 358 49 38",
    "sg:postcode":"1640",
    "sg:province":"Vlaams-Brabant",
    "wof:name":"Roger Vandekerckhove",
    "wof:placetype":"venue"
},
  "geometry": {"coordinates":[4.3411049843,50.7413482666],"type":"Point"}
}