{
  "type": "Feature",
  "properties": {
    "iso:country":"BE",
    "sg:address":"Rue Des Communes 3",
    "sg:city":"Sombreffe",
    "sg:orig_category":"Artistes ind\u00e9pendants",
    "sg:phone":"+32 71 87 67 40",
    "sg:postcode":"5140",
    "sg:province":"Namur",
    "wof:name":"Francoise Deltour",
    "wof:placetype":"venue"
},
  "geometry": {"coordinates":[4.5895180702,50.5626602173],"type":"Point"}
}