{
  "type": "Feature",
  "properties": {
    "iso:country":"BE",
    "sg:address":"Sartlaan 22",
    "sg:city":"Oostende",
    "sg:classifiers":[
        {
            "category":"Freight",
            "type":"Transportation"
        }
    ],
    "sg:phone":"+32 59 70 41 76",
    "sg:postcode":"8400",
    "sg:province":"West-Vlaanderen",
    "sg:tags":[
        "-",
        "refrigerated",
        "transport"
    ],
    "wof:name":"Jodec Bvba",
    "wof:placetype":"venue"
},
  "geometry": {"coordinates":[2.9126999378,51.2312583923],"type":"Point"}
}