{
  "type": "Feature",
  "properties": {
    "addr:full":"Rue Du Chgteau De Broich 42 Plombieres/plombieres Li\u00e8ge 4850",
    "addr:housenumber":"42",
    "addr:postcode":"4850",
    "addr:street":"Rue Du Chgteau De Broich",
    "iso:country":"BE",
    "sg:address":"Rue Du Chgteau De Broich 42",
    "sg:city":"Plombieres/plombieres",
    "sg:orig_category":"Eleveurs de bovins. Eleveurs and marchands de porcs",
    "sg:phone":"+32 87 78 52 65",
    "sg:postcode":"4850",
    "sg:province":"Li\u00e8ge",
    "wof:name":"Felix Xhonneux",
    "wof:placetype":"venue"
},
  "geometry": {"coordinates":[5.9626002312,50.7068138123],"type":"Point"}
}