{
  "type": "Feature",
  "properties": {
    "addr:full":"Molenstraat 7 Oud-heverlee Vlaams-Brabant 3051",
    "addr:housenumber":"7",
    "addr:postcode":"3051",
    "addr:street":"Molenstraat",
    "iso:country":"BE",
    "sg:address":"Molenstraat 7",
    "sg:city":"Oud-heverlee",
    "sg:classifiers":[
        {
            "category":"Arena",
            "subcategory":"Sports Club",
            "type":"Entertainment"
        }
    ],
    "sg:phone":"+32 16 47 22 66",
    "sg:postcode":"3051",
    "sg:province":"Vlaams-Brabant",
    "sg:tags":[
        "de"
    ],
    "wof:name":"V.c. Wevok St.joris-weert",
    "wof:placetype":"venue"
},
  "geometry": {"coordinates":[4.6530051231,50.8019828796],"type":"Point"}
}