{
  "type": "Feature",
  "properties": {
    "addr:full":"Beekstraat 105 Lokeren Oost-Vlaanderen 9160",
    "addr:housenumber":"105",
    "addr:postcode":"9160",
    "addr:street":"Beekstraat",
    "iso:country":"BE",
    "sg:address":"Beekstraat 105",
    "sg:city":"Lokeren",
    "sg:classifiers":[
        {
            "category":"Restaurant",
            "type":"Food & Drink"
        }
    ],
    "sg:phone":"+32 9 348 90 55",
    "sg:postcode":"9160",
    "sg:province":"Oost-Vlaanderen",
    "wof:name":"Greco Palace",
    "wof:placetype":"venue"
},
  "geometry": {"coordinates":[4.004005909,51.0953483582],"type":"Point"}
}