{
  "type": "Feature",
  "properties": {
    "iso:country":"BE",
    "sg:address":"Retiesebaan 54",
    "sg:city":"Kasterlee",
    "sg:classifiers":[
        {
            "category":"Insurance",
            "subcategory":"Insurance Agent",
            "type":"Services"
        }
    ],
    "sg:phone":"+32 14 85 23 90",
    "sg:postcode":"2460",
    "sg:province":"Antwerpen",
    "sg:tags":[
        "broker"
    ],
    "wof:name":"Helsen Verzekeringen Nv",
    "wof:placetype":"venue"
},
  "geometry": {"coordinates":[4.9735660553,51.2415542603],"type":"Point"}
}