{
  "type": "Feature",
  "properties": {
    "addr:full":"Rue Epinette 9 Tournai Hainaut 7520",
    "addr:housenumber":"9",
    "addr:postcode":"7520",
    "addr:street":"Rue Epinette",
    "iso:country":"BE",
    "sg:address":"Rue Epinette 9",
    "sg:city":"Tournai",
    "sg:orig_category":"Rundveehouders",
    "sg:phone":"+32 69 84 60 32",
    "sg:postcode":"7520",
    "sg:province":"Hainaut",
    "wof:name":"Leon Lefebvre",
    "wof:placetype":"venue"
},
  "geometry": {"coordinates":[3.3915419579,50.6100196838],"type":"Point"}
}