{
  "type": "Feature",
  "properties": {
    "addr:full":"Monseigneur Koningsstraat 30 Maaseik Limburg 3680",
    "addr:housenumber":"30",
    "addr:postcode":"3680",
    "addr:street":"Monseigneur Koningsstraat",
    "iso:country":"BE",
    "sg:address":"Monseigneur Koningsstraat 30",
    "sg:city":"Maaseik",
    "sg:classifiers":[
        {
            "category":"Professional",
            "subcategory":"Management & Consulting",
            "type":"Services"
        }
    ],
    "sg:phone":"+32 89 56 35 75",
    "sg:postcode":"3680",
    "sg:province":"Limburg",
    "sg:tags":[
        "consultant"
    ],
    "wof:name":"Jos Poell Belgi\u00eb Bvba",
    "wof:placetype":"venue"
},
  "geometry": {"coordinates":[5.7951607704,51.0954322815],"type":"Point"}
}