{
  "type": "Feature",
  "properties": {
    "iso:country":"BE",
    "sg:address":"12-13 Casinoplein",
    "sg:city":"Blankenberge",
    "sg:classifiers":[
        {
            "category":"Travel",
            "subcategory":"Hotels & Motels",
            "type":"Entertainment"
        }
    ],
    "sg:phone":"+32 50 41 93 76",
    "sg:postcode":"8370",
    "sg:province":"West-Vlaanderen",
    "sg:tags":[
        "hotels",
        "business",
        "restaurant"
    ],
    "wof:name":"Van Hee Nancy M.",
    "wof:placetype":"venue"
},
  "geometry": {"coordinates":[3.1288330555,51.3158988953],"type":"Point"}
}