{
  "type": "Feature",
  "properties": {
    "addr:full":"Avenue Moli\u00c8re 309 Ukkel/uccle Bruxelles-Capitale 1180",
    "addr:housenumber":"309",
    "addr:postcode":"1180",
    "addr:street":"Avenue Molie\u0300Re;/",
    "iso:country":"BE",
    "sg:address":"Avenue Moli\u00c8re 309",
    "sg:city":"Ukkel/uccle",
    "sg:orig_category":"M\u00e9decins and sp\u00e9cialistes",
    "sg:phone":"+32 2 343 75 04",
    "sg:postcode":"1180",
    "sg:province":"Bruxelles-Capitale",
    "wof:name":"A. Vokaer",
    "wof:placetype":"venue"
},
  "geometry": {"coordinates":[4.3578882217,50.8153305054],"type":"Point"}
}