{
  "type": "Feature",
  "properties": {
    "iso:country":"BE",
    "sg:address":"Befferstraat 35",
    "sg:city":"Mechelen",
    "sg:classifiers":[
        {
            "category":"Personal",
            "subcategory":"Barber",
            "type":"Services"
        }
    ],
    "sg:phone":"+32 15 20 32 53",
    "sg:postcode":"2800",
    "sg:province":"Antwerpen",
    "sg:tags":[
        "gentleman",
        "salon",
        "-",
        "hairdressing"
    ],
    "wof:name":"Rich'hair",
    "wof:placetype":"venue"
},
  "geometry": {"coordinates":[4.4825677872,51.0285720825],"type":"Point"}
}