{
  "type": "Feature",
  "properties": {
    "iso:country":"BE",
    "sg:address":"Hepperstraat 25",
    "sg:city":"Maaseik",
    "sg:classifiers":[
        {
            "category":"Health Services",
            "subcategory":"Dentist",
            "type":"Services"
        }
    ],
    "sg:phone":"+32 89 56 73 04",
    "sg:postcode":"3680",
    "sg:province":"Limburg",
    "wof:name":"Ruttens L",
    "wof:placetype":"venue"
},
  "geometry": {"coordinates":[5.791082859,51.0929756165],"type":"Point"}
}