{
  "type": "Feature",
  "properties": {
    "iso:country":"BE",
    "sg:address":"Bloemistenstraat 21",
    "sg:city":"Gent",
    "sg:classifiers":[
        {
            "category":"Cafe",
            "type":"Food & Drink"
        }
    ],
    "sg:phone":"+32 9 228 64 93",
    "sg:postcode":"9040",
    "sg:province":"Oost-Vlaanderen",
    "sg:tags":[
        "caf\u00e9s"
    ],
    "wof:name":"Caf\u00c9 Hulstenboom",
    "wof:placetype":"venue"
},
  "geometry": {"coordinates":[3.751830101,51.0624313354],"type":"Point"}
}