{
  "type": "Feature",
  "properties": {
    "addr:full":"Eiland 4 Beernem West-Vlaanderen 8730",
    "addr:housenumber":"4",
    "addr:postcode":"8730",
    "addr:street":"Eiland",
    "iso:country":"BE",
    "sg:address":"Eiland 4",
    "sg:city":"Beernem",
    "sg:orig_category":"Herstelling and restauratie van meubelen Kapsalons",
    "sg:phone":"+32 50 79 08 24",
    "sg:postcode":"8730",
    "sg:province":"West-Vlaanderen",
    "wof:name":"Nicole De Graeve",
    "wof:placetype":"venue"
},
  "geometry": {"coordinates":[3.374229908,51.1329917908],"type":"Point"}
}