{
  "type": "Feature",
  "properties": {
    "iso:country":"BE",
    "sg:address":"Marktplein 49",
    "sg:city":"Sint-lievens-houtem",
    "sg:orig_category":"Herenkledingzaken Lingerie and ondergoed",
    "sg:phone":"+32 53 62 82 90",
    "sg:postcode":"9520",
    "sg:province":"Oost-Vlaanderen",
    "wof:name":"Huis Chouette",
    "wof:placetype":"venue"
},
  "geometry": {"coordinates":[3.8552849293,50.9203681946],"type":"Point"}
}