{
  "type": "Feature",
  "properties": {
    "addr:full":"Grand-place 12 Ecaussinnes Hainaut 7190",
    "addr:housenumber":"12",
    "addr:postcode":"7190",
    "addr:street":"Grand-Place;Hainaut",
    "iso:country":"BE",
    "sg:address":"Grand-place 12",
    "sg:city":"Ecaussinnes",
    "sg:orig_category":"Agences immobili\u00e8res. G\u00e9om\u00e8tres. Evaluation and estimation de biens immobiliers",
    "sg:phone":"+32 67 48 53 23",
    "sg:postcode":"7190",
    "sg:province":"Hainaut",
    "wof:name":"Bureau Offim",
    "wof:placetype":"venue"
},
  "geometry": {"coordinates":[4.1756110191,50.5696411133],"type":"Point"}
}