{
  "type": "Feature",
  "properties": {
    "addr:full":"Boulevard Joseph Tirou 68 Charleroi Hainaut 6000",
    "addr:housenumber":"68",
    "addr:postcode":"6000",
    "addr:street":"Boulevard Joseph Tirou;Hainaut",
    "iso:country":"BE",
    "sg:address":"Boulevard Joseph Tirou 68",
    "sg:city":"Charleroi",
    "sg:orig_category":"Studios photographiques. Caf\u00e9s",
    "sg:phone":"+32 71 30 30 44",
    "sg:postcode":"6000",
    "sg:province":"Hainaut",
    "wof:name":"Coqsd\u00b4ausse",
    "wof:placetype":"venue"
},
  "geometry": {"coordinates":[4.4431219101,50.4076690674],"type":"Point"}
}