{
  "type": "Feature",
  "properties": {
    "iso:country":"BE",
    "sg:address":"Houtmarkt 26",
    "sg:city":"Aalst",
    "sg:classifiers":[
        {
            "category":"Bars & Pubs",
            "type":"Food & Drink"
        }
    ],
    "sg:phone":"+32 53 77 46 40",
    "sg:postcode":"9300",
    "sg:province":"Oost-Vlaanderen",
    "wof:name":"Carnaby Marc",
    "wof:placetype":"venue"
},
  "geometry": {"coordinates":[4.0431637764,50.9346847534],"type":"Point"}
}