{
  "type": "Feature",
  "properties": {
    "iso:country":"BE",
    "sg:address":"Kapelstraat 16",
    "sg:city":"Wuustwezel",
    "sg:orig_category":"Geschenken and souvenirs Kantoormateriaal Krantenwinkels Rookartikelen",
    "sg:phone":"+32 3 669 80 17",
    "sg:postcode":"2990",
    "sg:province":"Antwerpen",
    "wof:name":"De Griffel",
    "wof:placetype":"venue"
},
  "geometry": {"coordinates":[4.6452999115,51.3994789124],"type":"Point"}
}