{
  "type": "Feature",
  "properties": {
    "addr:full":"D'helst 18 Lebbeke Oost-Vlaanderen 9280",
    "addr:housenumber":"18",
    "addr:postcode":"9280",
    "addr:street":"D'Helst",
    "iso:country":"BE",
    "sg:address":"D'helst 18",
    "sg:city":"Lebbeke",
    "sg:classifiers":[
        {
            "category":"Retail",
            "subcategory":"Auto Repair",
            "type":"Services"
        }
    ],
    "sg:phone":"+32 52 41 43 00",
    "sg:postcode":"9280",
    "sg:province":"Oost-Vlaanderen",
    "sg:tags":[
        "garage"
    ],
    "wof:name":"Auto Service Courtmans Nv",
    "wof:placetype":"venue"
},
  "geometry": {"coordinates":[4.1370420456,50.985244751],"type":"Point"}
}