{
  "type": "Feature",
  "properties": {
    "iso:country":"BE",
    "sg:address":"Rue Du Bout De La Haut 275",
    "sg:city":"Quaregnon",
    "sg:orig_category":"Installation de menuiserie en bois and plastique. Construction de maisons",
    "sg:phone":"+32 65 67 25 52",
    "sg:postcode":"7390",
    "sg:province":"Hainaut",
    "wof:name":"Jem Construct",
    "wof:placetype":"venue"
},
  "geometry": {"coordinates":[3.8707149029,50.418094635],"type":"Point"}
}