{
  "type": "Feature",
  "properties": {
    "iso:country":"BE",
    "sg:address":"Reigerslaan 5",
    "sg:city":"Kruibeke (bazel)",
    "sg:classifiers":[
        {
            "category":"Professional",
            "subcategory":"Management & Consulting",
            "type":"Services"
        }
    ],
    "sg:phone":"+32 3 774 32 62",
    "sg:postcode":"9150",
    "sg:province":"Oost-Vlaanderen",
    "sg:tags":[
        "consultant"
    ],
    "wof:name":"Baco",
    "wof:placetype":"venue"
},
  "geometry": {"coordinates":[4.3028388023,51.1476860046],"type":"Point"}
}