{
  "type": "Feature",
  "properties": {
    "addr:full":"Rue Du Fort 101-1 Soumagne (cerexhe-heuseux) Li\u00e8ge 4632",
    "addr:postcode":"101-1;4632",
    "addr:street":"Rue Du Fort",
    "iso:country":"BE",
    "sg:address":"Rue Du Fort 101-1",
    "sg:city":"Soumagne (cerexhe-heuseux)",
    "sg:classifiers":[
        {
            "category":"Autos & Motor Vehicles",
            "subcategory":"Auto Supplies",
            "type":"Retail Goods"
        }
    ],
    "sg:phone":"+32 4 377 23 47",
    "sg:postcode":"4632",
    "sg:province":"Li\u00e8ge",
    "sg:tags":[
        "access",
        "automobile",
        "part",
        "-"
    ],
    "wof:name":"B.t.l. Sprl",
    "wof:placetype":"venue"
},
  "geometry": {"coordinates":[5.7182321548,50.6437606812],"type":"Point"}
}