{
  "type": "Feature",
  "properties": {
    "iso:country":"BE",
    "sg:address":"Rue Albert I 5",
    "sg:city":"P\u00e9ruwelz",
    "sg:classifiers":[
        {
            "category":"Travel",
            "subcategory":"Travel Agent",
            "type":"Entertainment"
        }
    ],
    "sg:phone":"+32 69 77 65 01",
    "sg:postcode":"7600",
    "sg:province":"Hainaut",
    "sg:tags":[
        "agency"
    ],
    "wof:name":"Euro Voyages",
    "wof:placetype":"venue"
},
  "geometry": {"coordinates":[3.5908999443,50.508140564],"type":"Point"}
}