{
  "type": "Feature",
  "properties": {
    "iso:country":"BE",
    "sg:address":"Rue De Marcinelle 28",
    "sg:city":"Charleroi",
    "sg:classifiers":[
        {
            "category":"Travel",
            "subcategory":"Hotels & Motels",
            "type":"Entertainment"
        }
    ],
    "sg:phone":"+32 71 33 09 25",
    "sg:postcode":"6000",
    "sg:province":"Hainaut",
    "sg:tags":[
        "supply",
        "hotels",
        "catering"
    ],
    "wof:name":"Socowal Sc",
    "wof:placetype":"venue"
},
  "geometry": {"coordinates":[4.4436488152,50.4070091248],"type":"Point"}
}