{
  "type": "Feature",
  "properties": {
    "addr:full":"Karrestraat 40 Sint-lambrechts-woluwe/woluwe-saint-lambert Bruxelles-Capitale 1200",
    "addr:housenumber":"40",
    "addr:postcode":"1200",
    "addr:street":"Karrestraat",
    "iso:country":"BE",
    "sg:address":"Karrestraat 40",
    "sg:city":"Sint-lambrechts-woluwe/woluwe-saint-lambert",
    "sg:orig_category":"Musea and historische gebouwen",
    "sg:phone":"+32 2 761 27 57",
    "sg:postcode":"1200",
    "sg:province":"Bruxelles-Capitale",
    "wof:name":"Gemeentemuseum/mus\u00c9e Communal",
    "wof:placetype":"venue"
},
  "geometry": {"coordinates":[4.4226469994,50.8508110046],"type":"Point"}
}