{
  "type": "Feature",
  "properties": {
    "iso:country":"BE",
    "sg:address":"Zuidstraat 37",
    "sg:city":"Veurne",
    "sg:orig_category":"GROENTEN AND FRUIT Zuivelproducten",
    "sg:phone":"+32 58 31 18 47",
    "sg:postcode":"8630",
    "sg:province":"West-Vlaanderen",
    "wof:name":"De Kaashoeve",
    "wof:placetype":"venue"
},
  "geometry": {"coordinates":[2.6621661186,51.0698432922],"type":"Point"}
}