{
  "type": "Feature",
  "properties": {
    "addr:full":"Terjodenstraat 30 Denderleeuw (welle) Oost-Vlaanderen 9473",
    "addr:housenumber":"30",
    "addr:postcode":"9473",
    "addr:street":"Terjodenstraat",
    "iso:country":"BE",
    "sg:address":"Terjodenstraat 30",
    "sg:city":"Denderleeuw (welle)",
    "sg:classifiers":[
        {
            "category":"Home & Garden",
            "subcategory":"Hardware",
            "type":"Retail Goods"
        }
    ],
    "sg:phone":"+32 53 68 54 64",
    "sg:postcode":"9473",
    "sg:province":"Oost-Vlaanderen",
    "sg:tags":[
        "fixing",
        "material"
    ],
    "wof:name":"Bat Products Belgium Nv",
    "wof:placetype":"venue"
},
  "geometry": {"coordinates":[4.0419998169,50.904750824],"type":"Point"}
}