{
  "type": "Feature",
  "properties": {
    "addr:full":"Hagenbroek-noord 27 Lier Antwerpen 2500",
    "addr:housenumber":"27",
    "addr:postcode":"2500",
    "addr:street":"Hagenbroek-Noord",
    "iso:country":"BE",
    "sg:address":"Hagenbroek-noord 27",
    "sg:city":"Lier",
    "sg:orig_category":"Rundveehouders",
    "sg:phone":"+32 3 488 49 13",
    "sg:postcode":"2500",
    "sg:province":"Antwerpen",
    "wof:name":"Peeters Frans En Wim",
    "wof:placetype":"venue"
},
  "geometry": {"coordinates":[4.57462883,51.1456489563],"type":"Point"}
}