{
  "type": "Feature",
  "properties": {
    "iso:country":"BE",
    "sg:address":"Place De La Libert\u00c9 9",
    "sg:city":"Frasnes-lez-anvaing",
    "sg:orig_category":"Artsen and specialisten",
    "sg:phone":"+32 69 86 62 00",
    "sg:postcode":"7911",
    "sg:province":"Hainaut",
    "wof:name":"G. Fievet",
    "wof:placetype":"venue"
},
  "geometry": {"coordinates":[3.6193790436,50.6697120667],"type":"Point"}
}