{
  "type": "Feature",
  "properties": {
    "iso:country":"BE",
    "sg:address":"Augustuslaan 6/1",
    "sg:city":"Wetteren",
    "sg:orig_category":"Plomberie, chauffage and installations sanitaires",
    "sg:phone":"+32 9 366 11 91",
    "sg:postcode":"9230",
    "sg:province":"Oost-Vlaanderen",
    "wof:name":"Staelens Philip",
    "wof:placetype":"venue"
},
  "geometry": {"coordinates":[3.8951859474,51.0080986023],"type":"Point"}
}