{
  "type": "Feature",
  "properties": {
    "addr:full":"Boulevard Mairaux 36 La Louvi\u00e8re Hainaut 7100",
    "addr:housenumber":"36",
    "addr:postcode":"7100",
    "addr:street":"Boulevard Mairaux",
    "iso:country":"BE",
    "sg:address":"Boulevard Mairaux 36",
    "sg:city":"La Louvi\u00e8re",
    "sg:classifiers":[
        {
            "category":"Health Services",
            "subcategory":"Health Practitioner",
            "type":"Services"
        }
    ],
    "sg:phone":"+32 64 28 34 55",
    "sg:postcode":"7100",
    "sg:province":"Hainaut",
    "sg:tags":[
        "physiotherapist"
    ],
    "wof:name":"Mees I",
    "wof:placetype":"venue"
},
  "geometry": {"coordinates":[4.1874909401,50.4782829285],"type":"Point"}
}