{
  "type": "Feature",
  "properties": {
    "addr:full":"Brusselsesteenweg 7 Vilvoorde Vlaams-Brabant 1800",
    "addr:housenumber":"7",
    "addr:postcode":"1800",
    "addr:street":"Brusselsesteenweg",
    "iso:country":"BE",
    "sg:address":"Brusselsesteenweg 7",
    "sg:city":"Vilvoorde",
    "sg:classifiers":[
        {
            "category":"Real Estate",
            "subcategory":"Architect",
            "type":"Services"
        }
    ],
    "sg:phone":"+32 2 251 26 55",
    "sg:postcode":"1800",
    "sg:province":"Vlaams-Brabant",
    "wof:name":"Vyverman K",
    "wof:placetype":"venue"
},
  "geometry": {"coordinates":[4.4173798561,50.9244918823],"type":"Point"}
}