{
  "type": "Feature",
  "properties": {
    "iso:country":"BE",
    "sg:address":"Biesweg 43",
    "sg:city":"Lanaken (gellik)",
    "sg:classifiers":[
        {
            "category":"Health Services",
            "subcategory":"Health Practitioner",
            "type":"Services"
        }
    ],
    "sg:phone":"+32 89 72 13 20",
    "sg:postcode":"3620",
    "sg:province":"Limburg",
    "sg:tags":[
        "physiotherapist"
    ],
    "wof:name":"Van Gompel Patrick",
    "wof:placetype":"venue"
},
  "geometry": {"coordinates":[5.606716156,50.8874549866],"type":"Point"}
}