{
  "type": "Feature",
  "properties": {
    "addr:full":"Tramstationsstraat 30 Diksmuide West-Vlaanderen 8600",
    "addr:housenumber":"30",
    "addr:postcode":"8600",
    "addr:street":"Tramstationsstraat",
    "iso:country":"BE",
    "sg:address":"Tramstationsstraat 30",
    "sg:city":"Diksmuide",
    "sg:orig_category":"Traitements param\u00e9dicaux",
    "sg:phone":"+32 51 50 10 70",
    "sg:postcode":"8600",
    "sg:province":"West-Vlaanderen",
    "wof:name":"L. Vanden Auweele",
    "wof:placetype":"venue"
},
  "geometry": {"coordinates":[2.8657801151,51.0334663391],"type":"Point"}
}