{
  "type": "Feature",
  "properties": {
    "iso:country":"BE",
    "sg:address":"Rue Du Trieu 1",
    "sg:city":"Mons",
    "sg:orig_category":"Plomberie, chauffage and installations sanitaires",
    "sg:phone":"+32 65 35 32 88",
    "sg:postcode":"7000",
    "sg:province":"Hainaut",
    "wof:name":"Lucien Bruyere",
    "wof:placetype":"venue"
},
  "geometry": {"coordinates":[3.9454200268,50.4419898987],"type":"Point"}
}