{
  "type": "Feature",
  "properties": {
    "addr:full":"Rue Emile Cuvelier 31 Namur Namur 5000",
    "addr:housenumber":"31",
    "addr:postcode":"5000",
    "addr:street":"Rue Emile Cuvelier",
    "iso:country":"BE",
    "sg:address":"Rue Emile Cuvelier 31",
    "sg:city":"Namur",
    "sg:classifiers":[
        {
            "category":"Shopping",
            "subcategory":"Crafts & Fabrics",
            "type":"Retail Goods"
        }
    ],
    "sg:phone":"+32 81 22 32 65",
    "sg:postcode":"5000",
    "sg:province":"Namur",
    "sg:tags":[
        "graphic",
        "art",
        "supply",
        "-",
        "painting",
        "drawing"
    ],
    "wof:name":"Photoplan Imprim\u00e9 Sa",
    "wof:placetype":"venue"
},
  "geometry": {"coordinates":[4.8667578697,50.4643630981],"type":"Point"}
}