{
  "type": "Feature",
  "properties": {
    "addr:full":"Rue Des Ecoles 61 Limbourg Li\u00e8ge 4830",
    "addr:housenumber":"61",
    "addr:postcode":"4830",
    "addr:street":"Rue Des Ecoles",
    "iso:country":"BE",
    "sg:address":"Rue Des Ecoles 61",
    "sg:city":"Limbourg",
    "sg:orig_category":"Kapsalons",
    "sg:phone":"+32 87 76 27 32",
    "sg:postcode":"4830",
    "sg:province":"Li\u00e8ge",
    "wof:name":"Coiffure Patricia",
    "wof:placetype":"venue"
},
  "geometry": {"coordinates":[5.9407401085,50.6112518311],"type":"Point"}
}