{
  "type": "Feature",
  "properties": {
    "iso:country":"BE",
    "sg:address":"Universitaire Campus",
    "sg:city":"Diepenbeek",
    "sg:classifiers":[
        {
            "category":"Social Services",
            "type":"Services"
        }
    ],
    "sg:phone":"+32 11 23 31 45",
    "sg:postcode":"3590",
    "sg:province":"Limburg",
    "wof:name":"Limburgs Kankerfonds Vzw",
    "wof:placetype":"venue"
},
  "geometry": {"coordinates":[5.3969478607,50.9298744202],"type":"Point"}
}