{
  "type": "Feature",
  "properties": {
    "iso:country":"BE",
    "sg:address":"Chauss\u00c9e De Waterloo 91",
    "sg:city":"Namur",
    "sg:orig_category":"Boekhouders",
    "sg:phone":"+32 81 73 67 24",
    "sg:postcode":"5000",
    "sg:province":"Namur",
    "wof:name":"Robert De Meulenaer",
    "wof:placetype":"venue"
},
  "geometry": {"coordinates":[4.8480701447,50.4720611572],"type":"Point"}
}