{
  "type": "Feature",
  "properties": {
    "iso:country":"BE",
    "sg:address":"Leeuwerikenlaan 25",
    "sg:city":"Wemmel/wemmel",
    "sg:orig_category":"Fotografen and fotostudio's",
    "sg:phone":"+32 2 460 73 99",
    "sg:postcode":"1780",
    "sg:province":"Vlaams-Brabant",
    "wof:name":"Studio Blizzard",
    "wof:placetype":"venue"
},
  "geometry": {"coordinates":[4.315759182,50.9229049683],"type":"Point"}
}