{
  "type": "Feature",
  "properties": {
    "addr:full":"Avenue Fernand Golenvaux 25 Namur Namur 5000",
    "addr:housenumber":"25",
    "addr:postcode":"5000",
    "addr:street":"Avenue Fernand Golenvaux",
    "iso:country":"BE",
    "sg:address":"Avenue Fernand Golenvaux 25",
    "sg:city":"Namur",
    "sg:orig_category":"Action sociale avec h\u00e9bergement",
    "sg:phone":"+32 81 25 36 08",
    "sg:postcode":"5000",
    "sg:province":"Namur",
    "wof:name":"C.i.a.s.",
    "wof:placetype":"venue"
},
  "geometry": {"coordinates":[4.8693227768,50.4625549316],"type":"Point"}
}