{
  "type": "Feature",
  "properties": {
    "addr:full":"Sint-franciscusplein 14 Antwerpen (merksem) Antwerpen 2170",
    "addr:housenumber":"14",
    "addr:postcode":"2170",
    "addr:street":"Sint-Franciscusplein",
    "iso:country":"BE",
    "sg:address":"Sint-franciscusplein 14",
    "sg:city":"Antwerpen (merksem)",
    "sg:classifiers":[
        {
            "category":"Personal",
            "subcategory":"Beauty Salon",
            "type":"Services"
        }
    ],
    "sg:phone":"+32 3 645 78 13",
    "sg:postcode":"2170",
    "sg:province":"Antwerpen",
    "sg:tags":[
        "lady",
        "-",
        "hairdressing"
    ],
    "wof:name":"Yvonne",
    "wof:placetype":"venue"
},
  "geometry": {"coordinates":[4.4505147934,51.246723175],"type":"Point"}
}