{
  "type": "Feature",
  "properties": {
    "addr:full":"Baeckelmansstraat 28 Willebroek Antwerpen 2830",
    "addr:housenumber":"28",
    "addr:postcode":"2830",
    "addr:street":"Baeckelmansstraat",
    "iso:country":"BE",
    "sg:address":"Baeckelmansstraat 28",
    "sg:city":"Willebroek",
    "sg:orig_category":"Banques and organismes de cr\u00e9dit",
    "sg:phone":"+32 3 886 89 21",
    "sg:postcode":"2830",
    "sg:province":"Antwerpen",
    "wof:name":"Ippa",
    "wof:placetype":"venue"
},
  "geometry": {"coordinates":[4.3559780121,51.0347595215],"type":"Point"}
}