{
  "type": "Feature",
  "properties": {
    "addr:full":"Bouwelsesteenweg 281 Nijlen Antwerpen 2560",
    "addr:housenumber":"281",
    "addr:postcode":"2560",
    "addr:street":"Bouwelsesteenweg",
    "iso:country":"BE",
    "sg:address":"Bouwelsesteenweg 281",
    "sg:city":"Nijlen",
    "sg:classifiers":[
        {
            "category":"Bars & Pubs",
            "type":"Food & Drink"
        }
    ],
    "sg:phone":"+32 3 411 01 64",
    "sg:postcode":"2560",
    "sg:province":"Antwerpen",
    "wof:name":"Happy Few (the)",
    "wof:placetype":"venue"
},
  "geometry": {"coordinates":[4.6988730431,51.1644706726],"type":"Point"}
}