{
  "type": "Feature",
  "properties": {
    "iso:country":"BE",
    "sg:address":"Av. Franklin Roosevelt 48",
    "sg:city":"Vise",
    "sg:classifiers":[
        {
            "category":"Autos & Motor Vehicles",
            "subcategory":"Fuel & Gas Station",
            "type":"Retail Goods"
        }
    ],
    "sg:phone":"+32 4 379 53 74",
    "sg:postcode":"4600",
    "sg:province":"Li\u00e8ge",
    "sg:tags":[
        "stations-service",
        "carburants"
    ],
    "wof:name":"Texaco",
    "wof:placetype":"venue"
},
  "geometry": {"coordinates":[5.6845741272,50.737537384],"type":"Point"}
}