{
  "type": "Feature",
  "properties": {
    "iso:country":"BE",
    "sg:address":"Basiliekvoorplein 1",
    "sg:city":"Ganshoren/ganshoren",
    "sg:orig_category":"Radioproductie and uitzendingen",
    "sg:phone":"+32 2 424 23 46",
    "sg:postcode":"1083",
    "sg:province":"Bruxelles-Capitale",
    "wof:name":"Radio Spes",
    "wof:placetype":"venue"
},
  "geometry": {"coordinates":[4.3149781227,50.8677444458],"type":"Point"}
}