{
  "type": "Feature",
  "properties": {
    "iso:country":"BE",
    "sg:address":"Rue De Seron 8",
    "sg:city":"Fernelmont (hemptinne)",
    "sg:classifiers":[
        {
            "category":"Health Services",
            "subcategory":"Doctor",
            "type":"Services"
        }
    ],
    "sg:phone":"+32 81 85 50 90",
    "sg:postcode":"5380",
    "sg:province":"Namur",
    "sg:tags":[
        "medicinephysicians",
        "surgeon"
    ],
    "wof:name":"Coppens J-p",
    "wof:placetype":"venue"
},
  "geometry": {"coordinates":[4.9861078262,50.5531463623],"type":"Point"}
}