{
  "type": "Feature",
  "properties": {
    "iso:country":"BE",
    "sg:address":"Grootstraat 172",
    "sg:city":"Alken",
    "sg:classifiers":[
        {
            "category":"Home & Garden",
            "subcategory":"Building Materials",
            "type":"Retail Goods"
        }
    ],
    "sg:phone":"+32 11 31 24 80",
    "sg:postcode":"3570",
    "sg:province":"Limburg",
    "sg:tags":[
        "granite",
        "stone",
        "natural",
        "marble"
    ],
    "wof:name":"Grumaco Bvba",
    "wof:placetype":"venue"
},
  "geometry": {"coordinates":[5.3350257874,50.8800773621],"type":"Point"}
}