{
  "type": "Feature",
  "properties": {
    "iso:country":"BE",
    "sg:address":"Rue De Sart-lez-moulin 79",
    "sg:city":"Courcelles",
    "sg:orig_category":"D\u00e9chets and d\u00e9bris D\u00e9taillants en pi\u00e8ces and accessoires de voitures. Stations-service and carburant",
    "sg:phone":"+32 71 45 33 80",
    "sg:postcode":"6180",
    "sg:province":"Hainaut",
    "wof:name":"Q8",
    "wof:placetype":"venue"
},
  "geometry": {"coordinates":[4.35891819,50.44008255],"type":"Point"}
}