{
  "type": "Feature",
  "properties": {
    "addr:full":"Zomerweg 25 Lendelede West-Vlaanderen 8860",
    "addr:housenumber":"25",
    "addr:postcode":"8860",
    "addr:street":"Zomerweg",
    "iso:country":"BE",
    "sg:address":"Zomerweg 25",
    "sg:city":"Lendelede",
    "sg:orig_category":"Plaatsen van vloer- and muurbekleding Schilders",
    "sg:phone":"+32 51 31 88 53",
    "sg:postcode":"8860",
    "sg:province":"West-Vlaanderen",
    "wof:name":"Walter Verhaeghe",
    "wof:placetype":"venue"
},
  "geometry": {"coordinates":[3.2521619797,50.8877639771],"type":"Point"}
}