{
  "type": "Feature",
  "properties": {
    "addr:full":"Tienne Piertense 14 Mettet Namur 5640",
    "addr:housenumber":"14",
    "addr:postcode":"5640",
    "iso:country":"BE",
    "sg:address":"Tienne Piertense 14",
    "sg:city":"Mettet",
    "sg:classifiers":[
        {
            "category":"Wholesale",
            "subcategory":"Scrap",
            "type":"Manufacturing & Wholesale Goods"
        }
    ],
    "sg:phone":"+32 71 72 60 91",
    "sg:postcode":"5640",
    "sg:province":"Namur",
    "sg:tags":[
        "metal"
    ],
    "wof:name":"Bouchat E",
    "wof:placetype":"venue"
},
  "geometry": {"coordinates":[4.6474399567,50.3342781067],"type":"Point"}
}