{
  "type": "Feature",
  "properties": {
    "iso:country":"BE",
    "sg:address":"Excelsiorlaan 14",
    "sg:city":"Zaventem",
    "sg:classifiers":[
        {
            "category":"Manufacturing",
            "subcategory":"Furniture",
            "type":"Manufacturing & Wholesale Goods"
        }
    ],
    "sg:phone":"+32 2 725 02 40",
    "sg:postcode":"1930",
    "sg:province":"Vlaams-Brabant",
    "sg:tags":[
        "workshop"
    ],
    "wof:name":"Ssi Schafer Nv-sa",
    "wof:placetype":"venue"
},
  "geometry": {"coordinates":[4.4584970474,50.8843727112],"type":"Point"}
}