{
  "type": "Feature",
  "properties": {
    "addr:full":"Molenbergstr 10 Antwerpen Antwerpen 2000",
    "addr:housenumber":"10",
    "addr:postcode":"2000",
    "addr:street":"Molenbergstr",
    "iso:country":"BE",
    "sg:address":"Molenbergstr 10",
    "sg:city":"Antwerpen",
    "sg:classifiers":[
        {
            "category":"Manufacturing",
            "subcategory":"Metals",
            "type":"Manufacturing & Wholesale Goods"
        }
    ],
    "sg:phone":"+32 3 225 20 80",
    "sg:postcode":"2000",
    "sg:province":"Antwerpen",
    "sg:tags":[
        "metallurgy",
        "metalworking"
    ],
    "wof:name":"Hamann International Nv",
    "wof:placetype":"venue"
},
  "geometry": {"coordinates":[4.4155521393,51.2200737],"type":"Point"}
}