{
  "type": "Feature",
  "properties": {
    "iso:country":"BE",
    "sg:address":"Kouterweg 45",
    "sg:city":"Roeselare",
    "sg:classifiers":[
        {
            "category":"Military Area",
            "subcategory":"Air Force Base",
            "type":"Public Place"
        }
    ],
    "sg:phone":"+32 51 20 93 56",
    "sg:postcode":"8800",
    "sg:province":"West-Vlaanderen",
    "sg:tags":[
        "water",
        "treatment"
    ],
    "wof:name":"Vanacker Johan Bvba",
    "wof:placetype":"venue"
},
  "geometry": {"coordinates":[3.1381680965,50.9727554321],"type":"Point"}
}