{
  "type": "Feature",
  "properties": {
    "addr:full":"Maria Hendriklaan 15 De Haan West-Vlaanderen 8420",
    "addr:housenumber":"15",
    "addr:postcode":"8420",
    "addr:street":"Maria Hendriklaan",
    "iso:country":"BE",
    "sg:address":"Maria Hendriklaan 15",
    "sg:city":"De Haan",
    "sg:orig_category":"Alternatieve geneeskunde",
    "sg:phone":"+32 59 23 77 88",
    "sg:postcode":"8420",
    "sg:province":"West-Vlaanderen",
    "wof:name":"Dokter Moureau Pierre",
    "wof:placetype":"venue"
},
  "geometry": {"coordinates":[3.0328381062,51.275970459],"type":"Point"}
}