{
  "type": "Feature",
  "properties": {
    "iso:country":"BE",
    "sg:address":"Rue Des Combattants 16",
    "sg:city":"Esneux",
    "sg:orig_category":"Pharmaciens",
    "sg:phone":"+32 4 380 10 03",
    "sg:postcode":"4130",
    "sg:province":"Li\u00e8ge",
    "wof:name":"V. Degive",
    "wof:placetype":"venue"
},
  "geometry": {"coordinates":[5.5676460266,50.5356292725],"type":"Point"}
}