{
  "type": "Feature",
  "properties": {
    "iso:country":"BE",
    "sg:address":"Rue Fond Du Village 15",
    "sg:city":"Incourt",
    "sg:orig_category":"Benzinestations and brandstoffen",
    "sg:phone":"+32 10 84 12 24",
    "sg:postcode":"1315",
    "sg:province":"Brabant Wallon",
    "wof:name":"Chaparal",
    "wof:placetype":"venue"
},
  "geometry": {"coordinates":[4.799115181,50.6915283203],"type":"Point"}
}