{
  "type": "Feature",
  "properties": {
    "addr:full":"Beekstraat 43 Lokeren Oost-Vlaanderen 9160",
    "addr:housenumber":"43",
    "addr:postcode":"9160",
    "addr:street":"Beekstraat",
    "iso:country":"BE",
    "sg:address":"Beekstraat 43",
    "sg:city":"Lokeren",
    "sg:classifiers":[
        {
            "category":"Arena",
            "subcategory":"Sports Club",
            "type":"Entertainment"
        }
    ],
    "sg:phone":"+32 9 348 34 06",
    "sg:postcode":"9160",
    "sg:province":"Oost-Vlaanderen",
    "sg:tags":[
        "de"
    ],
    "wof:name":"Voor Geest En Lichaam Lokeren",
    "wof:placetype":"venue"
},
  "geometry": {"coordinates":[3.9989850521,51.0956726074],"type":"Point"}
}