{
  "type": "Feature",
  "properties": {
    "addr:full":"Chauss\u00c9e De Wavre 1543 Bruxelles Bruxelles-Capitale 1160",
    "addr:postcode":"1543;1160",
    "addr:street":"Chausse\u0301E De Wavre",
    "iso:country":"BE",
    "sg:address":"Chauss\u00c9e De Wavre 1543",
    "sg:city":"Bruxelles",
    "sg:classifiers":[
        {
            "category":"Restaurant",
            "type":"Food & Drink"
        }
    ],
    "sg:phone":"+32 477 37 19 02",
    "sg:postcode":"1160",
    "sg:province":"Bruxelles-Capitale",
    "wof:name":"Tof & Tondu",
    "wof:placetype":"venue"
},
  "geometry": {"coordinates":[4.4182009697,50.8180084229],"type":"Point"}
}