{
  "type": "Feature",
  "properties": {
    "addr:full":"Rue De Saint-remy 29 Vis\u00e9 (argenteau) Li\u00e8ge 4601",
    "addr:housenumber":"29",
    "addr:postcode":"4601",
    "addr:street":"Rue De Saint-Remy;Argenteau",
    "iso:country":"BE",
    "sg:address":"Rue De Saint-remy 29",
    "sg:city":"Vis\u00e9 (argenteau)",
    "sg:classifiers":[
        {
            "category":"Real Estate",
            "subcategory":"Architect",
            "type":"Services"
        }
    ],
    "sg:phone":"+32 497 36 65 17",
    "sg:postcode":"4601",
    "sg:province":"Li\u00e8ge",
    "wof:name":"Smets A",
    "wof:placetype":"venue"
},
  "geometry": {"coordinates":[5.6965341568,50.6967697144],"type":"Point"}
}