{
  "type": "Feature",
  "properties": {
    "iso:country":"BE",
    "sg:address":"Schuurstraat 59",
    "sg:city":"Gent",
    "sg:orig_category":"Brood, gebak and snoepgoed",
    "sg:phone":"+32 9 238 36 88",
    "sg:postcode":"9040",
    "sg:province":"Oost-Vlaanderen",
    "wof:name":"Patisserie Tijdgat",
    "wof:placetype":"venue"
},
  "geometry": {"coordinates":[3.7770578861,51.0725479126],"type":"Point"}
}