{
  "type": "Feature",
  "properties": {
    "iso:country":"BE",
    "sg:address":"Bodegemstraat 7",
    "sg:city":"Dilbeek",
    "sg:orig_category":"Meubelzaken, woning- and keukeninrichting",
    "sg:phone":"+32 2 569 74 43",
    "sg:postcode":"1701",
    "sg:province":"Vlaams-Brabant",
    "wof:name":"La Maison D\u00b4art Oriental",
    "wof:placetype":"venue"
},
  "geometry": {"coordinates":[4.2410960197,50.8426246643],"type":"Point"}
}