{
  "type": "Feature",
  "properties": {
    "iso:country":"BE",
    "sg:address":"Heirbaan 204",
    "sg:city":"Dendermonde",
    "sg:classifiers":[
        {
            "category":"Personal",
            "subcategory":"Beauty Salon",
            "type":"Services"
        }
    ],
    "sg:phone":"+32 52 22 14 89",
    "sg:postcode":"9200",
    "sg:province":"Oost-Vlaanderen",
    "sg:tags":[
        "de",
        "coiffure"
    ],
    "wof:name":"Kapsalon Maureen",
    "wof:placetype":"venue"
},
  "geometry": {"coordinates":[4.1173210144,51.0113639832],"type":"Point"}
}