{
  "type": "Feature",
  "properties": {
    "addr:full":"Chauss\u00e9e De Waterloo 368 Bruxelles (saint-gilles) Bruxelles-Capitale 1060",
    "addr:housenumber":"368",
    "addr:postcode":"1060",
    "addr:street":"Chausse\u0301E De Waterloo",
    "iso:country":"BE",
    "sg:address":"Chauss\u00e9e De Waterloo 368",
    "sg:city":"Bruxelles (saint-gilles)",
    "sg:classifiers":[
        {
            "category":"Shopping",
            "subcategory":"Books",
            "type":"Retail Goods"
        }
    ],
    "sg:phone":"+32 2 534 68 20",
    "sg:postcode":"1060",
    "sg:province":"Bruxelles-Capitale",
    "sg:tags":[
        "antiquarian",
        "trade"
    ],
    "wof:name":"Images",
    "wof:placetype":"venue"
},
  "geometry": {"coordinates":[4.3516860008,50.8238601685],"type":"Point"}
}