{
  "type": "Feature",
  "properties": {
    "addr:full":"Molenveld 99 Zemst Vlaams-Brabant 1982",
    "addr:housenumber":"99",
    "addr:postcode":"1982",
    "addr:street":"Molenveld;Vlaams-Brabant",
    "iso:country":"BE",
    "sg:address":"Molenveld 99",
    "sg:city":"Zemst",
    "sg:orig_category":"Woningbouw",
    "sg:phone":"+32 15 61 54 31",
    "sg:postcode":"1982",
    "sg:province":"Vlaams-Brabant",
    "wof:name":"Gerard Desmet",
    "wof:placetype":"venue"
},
  "geometry": {"coordinates":[4.5095601082,50.9623985291],"type":"Point"}
}