{
  "type": "Feature",
  "properties": {
    "iso:country":"BE",
    "sg:address":"Schuttershofstraat 25",
    "sg:city":"Niel",
    "sg:orig_category":"Sportclubs",
    "sg:phone":"+32 3 844 94 08",
    "sg:postcode":"2845",
    "sg:province":"Antwerpen",
    "wof:name":"J.c. Samurai Terhagen",
    "wof:placetype":"venue"
},
  "geometry": {"coordinates":[4.3240251541,51.1076049805],"type":"Point"}
}