{
  "type": "Feature",
  "properties": {
    "iso:country":"BE",
    "sg:address":"Rue De L'arbal\u00e8te 6",
    "sg:city":"Tournai",
    "sg:classifiers":[
        {
            "category":"Bars & Pubs",
            "type":"Food & Drink"
        }
    ],
    "sg:phone":"+32 69 84 12 51",
    "sg:postcode":"7500",
    "sg:province":"Hainaut",
    "wof:name":"Hangar Caf\u00e9",
    "wof:placetype":"venue"
},
  "geometry": {"coordinates":[3.3892519474,50.608253479],"type":"Point"}
}