{
  "type": "Feature",
  "properties": {
    "addr:full":"Fabiolalaan 25 Menen West-Vlaanderen 8930",
    "addr:housenumber":"25",
    "addr:postcode":"8930",
    "addr:street":"Fabiolalaan",
    "iso:country":"BE",
    "sg:address":"Fabiolalaan 25",
    "sg:city":"Menen",
    "sg:orig_category":"Artsen and specialisten",
    "sg:phone":"+32 56 51 18 16",
    "sg:postcode":"8930",
    "sg:province":"West-Vlaanderen",
    "wof:name":"Jan Lezy",
    "wof:placetype":"venue"
},
  "geometry": {"coordinates":[3.1250829697,50.7943687439],"type":"Point"}
}