{
  "type": "Feature",
  "properties": {
    "addr:full":"Abeelplein 6 Borgloon Limburg 3840",
    "addr:housenumber":"6",
    "addr:postcode":"3840",
    "addr:street":"Abeelplein",
    "iso:country":"BE",
    "sg:address":"Abeelplein 6",
    "sg:city":"Borgloon",
    "sg:orig_category":"Artiesten and kunstenaars",
    "sg:phone":"+32 12 67 14 53",
    "sg:postcode":"3840",
    "sg:province":"Limburg",
    "wof:name":"H. Verboven",
    "wof:placetype":"venue"
},
  "geometry": {"coordinates":[5.3431549072,50.802646637],"type":"Point"}
}