{
  "type": "Feature",
  "properties": {
    "iso:country":"BE",
    "sg:address":"Brandstraat 97",
    "sg:city":"Buggenhout",
    "sg:orig_category":"Rundveehouders Varkenskwekers",
    "sg:phone":"+32 52 33 24 12",
    "sg:postcode":"9255",
    "sg:province":"Oost-Vlaanderen",
    "wof:name":"Marc De Bock",
    "wof:placetype":"venue"
},
  "geometry": {"coordinates":[4.1620821953,51.0112800598],"type":"Point"}
}