{
  "type": "Feature",
  "properties": {
    "addr:full":"Chauss\u00c9e De Waterloo 720 Uccle (bruxelles) Bruxelles-Capitale 1180",
    "addr:housenumber":"720",
    "addr:postcode":"1180",
    "addr:street":"Chausse\u0301E De Waterloo",
    "iso:country":"BE",
    "sg:address":"Chauss\u00c9e De Waterloo 720",
    "sg:city":"Uccle (bruxelles)",
    "sg:orig_category":"Opticiens",
    "sg:phone":"+32 2 648 64 19",
    "sg:postcode":"1180",
    "sg:province":"Bruxelles-Capitale",
    "wof:name":"Pearle Vision Center",
    "wof:placetype":"venue"
},
  "geometry": {"coordinates":[4.3674201965,50.8152999878],"type":"Point"}
}