{
  "type": "Feature",
  "properties": {
    "addr:full":"Rue Du Roton 90b Charleroi Hainaut 6000",
    "addr:housenumber":"90b",
    "addr:postcode":"6000",
    "addr:street":"Rue Du Roton;Hainaut",
    "iso:country":"BE",
    "sg:address":"Rue Du Roton 90b",
    "sg:city":"Charleroi",
    "sg:classifiers":[
        {
            "category":"Social Services",
            "type":"Services"
        }
    ],
    "sg:phone":"+32 71 30 53 61",
    "sg:postcode":"6000",
    "sg:province":"Hainaut",
    "wof:name":"Broucheterre (la) Asbl",
    "wof:placetype":"venue"
},
  "geometry": {"coordinates":[4.4451260567,50.4213104248],"type":"Point"}
}