{
  "type": "Feature",
  "properties": {
    "iso:country":"BE",
    "sg:address":"Venneheideweg 5a",
    "sg:city":"Aarschot (langdorp)",
    "sg:classifiers":[
        {
            "category":"Building & Trades",
            "subcategory":"Plumbing",
            "type":"Services"
        }
    ],
    "sg:phone":"+32 16 56 56 81",
    "sg:postcode":"3201",
    "sg:province":"Vlaams-Brabant",
    "sg:tags":[
        "contractor"
    ],
    "wof:name":"Verbiest C Dakwerken Bvba",
    "wof:placetype":"venue"
},
  "geometry": {"coordinates":[4.8671808243,51.0107803345],"type":"Point"}
}