{
  "type": "Feature",
  "properties": {
    "iso:country":"BE",
    "sg:address":"Chemin Des Tombelles 11",
    "sg:city":"Court-saint-etienne",
    "sg:orig_category":"Artsen and specialisten",
    "sg:phone":"+32 10 61 13 19",
    "sg:postcode":"1490",
    "sg:province":"Brabant Wallon",
    "wof:name":"H. Vincke",
    "wof:placetype":"venue"
},
  "geometry": {"coordinates":[4.5328688622,50.6187286377],"type":"Point"}
}