{
  "type": "Feature",
  "properties": {
    "iso:country":"BE",
    "sg:address":"Bld De La Sauveni\u00c8re 33",
    "sg:city":"Li\u00c8ge",
    "sg:orig_category":"Editeurs de revues and p\u00e9riodiques. Editeurs de journaux",
    "sg:phone":"+32 4 223 59 55",
    "sg:postcode":"4000",
    "sg:province":"Li\u00e8ge",
    "wof:name":"F\u00c9d. Education Physique",
    "wof:placetype":"venue"
},
  "geometry": {"coordinates":[5.5683479309,50.6440124512],"type":"Point"}
}