{
  "type": "Feature",
  "properties": {
    "iso:country":"BE",
    "sg:address":"Juniorslaan 112",
    "sg:city":"Mechelen",
    "sg:orig_category":"Art and fournitures artistiques",
    "sg:phone":"+32 15 71 47 05",
    "sg:postcode":"2811",
    "sg:province":"Antwerpen",
    "wof:name":"Frederic Lefebvre",
    "wof:placetype":"venue"
},
  "geometry": {"coordinates":[4.3902621269,51.0312271118],"type":"Point"}
}