{
  "type": "Feature",
  "properties": {
    "iso:country":"BE",
    "sg:address":"Croix De Bon Air 1",
    "sg:city":"Beaumont",
    "sg:orig_category":"Eleveurs de bovins",
    "sg:phone":"+32 71 58 93 72",
    "sg:postcode":"6500",
    "sg:province":"Hainaut",
    "wof:name":"Guy Werry",
    "wof:placetype":"venue"
},
  "geometry": {"coordinates":[4.2709059715,50.2385292053],"type":"Point"}
}