{
  "type": "Feature",
  "properties": {
    "addr:full":"Kapellekesweg 82 Tielt-winge Vlaams-Brabant 3391",
    "addr:housenumber":"82",
    "addr:postcode":"3391",
    "addr:street":"Kapellekesweg",
    "iso:country":"BE",
    "sg:address":"Kapellekesweg 82",
    "sg:city":"Tielt-winge",
    "sg:orig_category":"R\u00e9parations d'horloges, montres and bijoux. Bijouteries and horlogeries. Opticiens",
    "sg:phone":"+32 16 64 08 14",
    "sg:postcode":"3391",
    "sg:province":"Vlaams-Brabant",
    "wof:name":"C Van Goidsenhoven",
    "wof:placetype":"venue"
},
  "geometry": {"coordinates":[4.9195890427,50.8959732056],"type":"Point"}
}