{
  "type": "Feature",
  "properties": {
    "addr:full":"Van Praetlei 54 Antwerpen Antwerpen 2170",
    "addr:housenumber":"54",
    "addr:postcode":"2170",
    "addr:street":"Van Praetlei",
    "iso:country":"BE",
    "sg:address":"Van Praetlei 54",
    "sg:city":"Antwerpen",
    "sg:orig_category":"Activit\u00e9s diverses d'imprimerie",
    "sg:phone":"+32 3 644 35 11",
    "sg:postcode":"2170",
    "sg:province":"Antwerpen",
    "wof:name":"Katrien Bruyninckx",
    "wof:placetype":"venue"
},
  "geometry": {"coordinates":[4.457652092,51.2506980896],"type":"Point"}
}