{
  "type": "Feature",
  "properties": {
    "addr:full":"Leenstraat 61 Gavere (vurste) Oost-Vlaanderen 9890",
    "addr:housenumber":"61",
    "addr:postcode":"9890",
    "addr:street":"Leenstraat",
    "iso:country":"BE",
    "sg:address":"Leenstraat 61",
    "sg:city":"Gavere (vurste)",
    "sg:classifiers":[
        {
            "category":"Building & Trades",
            "subcategory":"Electrical",
            "type":"Services"
        }
    ],
    "sg:phone":"+32 9 384 25 51",
    "sg:postcode":"9890",
    "sg:province":"Oost-Vlaanderen",
    "sg:tags":[
        "-",
        "electric",
        "contractor"
    ],
    "wof:name":"De Mulder Bvba",
    "wof:placetype":"venue"
},
  "geometry": {"coordinates":[3.6823821068,50.9484062195],"type":"Point"}
}