{
  "type": "Feature",
  "properties": {
    "iso:country":"BE",
    "sg:address":"Rue De La Madeleine 5a",
    "sg:city":"Bruxelles",
    "sg:classifiers":[
        {
            "category":"Shopping",
            "subcategory":"Clothing, Apparel, & Fashions",
            "type":"Retail Goods"
        }
    ],
    "sg:phone":"+32 2 511 99 16",
    "sg:postcode":"1000",
    "sg:province":"Bruxelles-Capitale",
    "sg:tags":[
        "lady",
        "clothing",
        "-"
    ],
    "wof:name":"Lux'maille Boutique",
    "wof:placetype":"venue"
},
  "geometry": {"coordinates":[4.3547039032,50.8460350037],"type":"Point"}
}