{
  "type": "Feature",
  "properties": {
    "addr:full":"Westerlosesteenweg 50 Herselt Antwerpen 2230",
    "addr:housenumber":"50",
    "addr:postcode":"2230",
    "addr:street":"Westerlosesteenweg",
    "iso:country":"BE",
    "sg:address":"Westerlosesteenweg 50",
    "sg:city":"Herselt",
    "sg:orig_category":"Rundveehouders",
    "sg:phone":"+32 14 54 70 08",
    "sg:postcode":"2230",
    "sg:province":"Antwerpen",
    "wof:name":"Jozef Celen",
    "wof:placetype":"venue"
},
  "geometry": {"coordinates":[4.8886389732,51.062702179],"type":"Point"}
}