{
  "type": "Feature",
  "properties": {
    "addr:full":"Onderbergen 25 Gent Oost-Vlaanderen 9000",
    "addr:housenumber":"25",
    "addr:postcode":"9000",
    "addr:street":"Onderbergen;Oost-Vlaanderen",
    "iso:country":"BE",
    "sg:address":"Onderbergen 25",
    "sg:city":"Gent",
    "sg:classifiers":[
        {
            "category":"Restaurant",
            "type":"Food & Drink"
        }
    ],
    "sg:phone":"+32 9 224 04 58",
    "sg:postcode":"9000",
    "sg:province":"Oost-Vlaanderen",
    "wof:name":"Mineral",
    "wof:placetype":"venue"
},
  "geometry": {"coordinates":[3.7199389935,51.0517807007],"type":"Point"}
}