{
  "type": "Feature",
  "properties": {
    "addr:full":"Route De Neufchateau 551 Arlon Luxembourg 6700",
    "addr:housenumber":"551",
    "addr:postcode":"6700",
    "addr:street":"Route De Neufchateau",
    "iso:country":"BE",
    "sg:address":"Route De Neufchateau 551",
    "sg:city":"Arlon",
    "sg:orig_category":"Metaalafval, schrootrecyclage and sloperijen Onderdelen and accessoires voor auto's Voertuigen",
    "sg:phone":"+32 63 22 11 13",
    "sg:postcode":"6700",
    "sg:province":"Luxembourg",
    "wof:name":"Pougin",
    "wof:placetype":"venue"
},
  "geometry": {"coordinates":[5.8042387962,49.689666748],"type":"Point"}
}