{
  "type": "Feature",
  "properties": {
    "iso:country":"BE",
    "sg:address":"Antwerpsestraat 201",
    "sg:city":"Mortsel",
    "sg:orig_category":"Meubelzaken, woning- and keukeninrichting",
    "sg:phone":"+32 3 449 90 47",
    "sg:postcode":"2640",
    "sg:province":"Antwerpen",
    "wof:name":"Rustwel",
    "wof:placetype":"venue"
},
  "geometry": {"coordinates":[4.4385957718,51.1752090454],"type":"Point"}
}