{
  "type": "Feature",
  "properties": {
    "addr:full":"Avenue Monplaisir 77-89 Bruxelles (schaerbeek) Bruxelles-Capitale 1030",
    "addr:housenumber":"77-89",
    "addr:postcode":"1030",
    "addr:street":"Avenue Monplaisir",
    "iso:country":"BE",
    "sg:address":"Avenue Monplaisir 77-89",
    "sg:city":"Bruxelles (schaerbeek)",
    "sg:classifiers":[
        {
            "category":"Home & Garden",
            "subcategory":"Hardware",
            "type":"Retail Goods"
        }
    ],
    "sg:phone":"+32 2 216 50 40",
    "sg:postcode":"1030",
    "sg:province":"Bruxelles-Capitale",
    "sg:tags":[
        "equipment",
        "woodworking",
        "machinery"
    ],
    "wof:name":"C.i.m.a. Sa",
    "wof:placetype":"venue"
},
  "geometry": {"coordinates":[4.3778948784,50.8768424988],"type":"Point"}
}