{
  "type": "Feature",
  "properties": {
    "iso:country":"BE",
    "sg:address":"Gravenlaan 11 Box 1",
    "sg:city":"Heusden-zolder (zolder)",
    "sg:classifiers":[
        {
            "category":"Professional",
            "subcategory":"Computer Services",
            "type":"Services"
        }
    ],
    "sg:phone":"+32 11 53 62 08",
    "sg:postcode":"3550",
    "sg:province":"Limburg",
    "sg:tags":[
        "-",
        "processing",
        "data",
        "software"
    ],
    "wof:name":"Infaco Bvba",
    "wof:placetype":"venue"
},
  "geometry": {"coordinates":[5.2744178772,51.0162315369],"type":"Point"}
}