{
  "type": "Feature",
  "properties": {
    "addr:full":"Rue Des Battes 4 Vis\u00c9 Li\u00e8ge 4600",
    "addr:housenumber":"4",
    "addr:postcode":"4600",
    "addr:street":"Rue Des Battes",
    "iso:country":"BE",
    "sg:address":"Rue Des Battes 4",
    "sg:city":"Vis\u00c9",
    "sg:orig_category":"Installation de menuiserie m\u00e9tallique",
    "sg:phone":"+32 4 379 38 34",
    "sg:postcode":"4600",
    "sg:province":"Li\u00e8ge",
    "wof:name":"Zanet",
    "wof:placetype":"venue"
},
  "geometry": {"coordinates":[5.6956510544,50.777256012],"type":"Point"}
}