{
  "type": "Feature",
  "properties": {
    "addr:full":"Diepestraat 3 Ardooie West-Vlaanderen 8850",
    "addr:housenumber":"3",
    "addr:postcode":"8850",
    "addr:street":"Diepestraat",
    "iso:country":"BE",
    "sg:address":"Diepestraat 3",
    "sg:city":"Ardooie",
    "sg:orig_category":"Rundveehouders Varkenskwekers",
    "sg:phone":"+32 51 74 81 90",
    "sg:postcode":"8850",
    "sg:province":"West-Vlaanderen",
    "wof:name":"Eric Defour",
    "wof:placetype":"venue"
},
  "geometry": {"coordinates":[3.2201180458,50.9881744385],"type":"Point"}
}