{
  "type": "Feature",
  "properties": {
    "addr:full":"Rue Longue 15bc Tournai Hainaut 7522",
    "addr:postcode":"15bc;7522",
    "addr:street":"Rue Longue;Hainaut",
    "iso:country":"BE",
    "sg:address":"Rue Longue 15bc",
    "sg:city":"Tournai",
    "sg:orig_category":"Entretien and r\u00e9parations de voitures",
    "sg:phone":"+32 69 84 60 66",
    "sg:postcode":"7522",
    "sg:province":"Hainaut",
    "wof:name":"Jacques Foret",
    "wof:placetype":"venue"
},
  "geometry": {"coordinates":[3.3041040897,50.5743484497],"type":"Point"}
}