{
  "type": "Feature",
  "properties": {
    "addr:full":"Rue De La Station 11 Wavre (limal) Brabant Wallon 1300",
    "addr:housenumber":"11",
    "addr:postcode":"1300",
    "addr:street":"Rue De La Station;Wallon",
    "iso:country":"BE",
    "sg:address":"Rue De La Station 11",
    "sg:city":"Wavre (limal)",
    "sg:orig_category":"Autombile concessionaires",
    "sg:phone":"+32 10 41 52 27",
    "sg:postcode":"1300",
    "sg:province":"Brabant Wallon",
    "wof:name":"Gar P Denis",
    "wof:placetype":"venue"
},
  "geometry": {"coordinates":[4.5736579895,50.6932563782],"type":"Point"}
}