{
  "type": "Feature",
  "properties": {
    "iso:country":"BE",
    "sg:address":"Aartselaarstraat 88",
    "sg:city":"Antwerpen",
    "sg:orig_category":"Meubles D\u00e9taillants, Am\u00e9nagement de B\u00e2timents et de Cuisines",
    "sg:phone":"+32 3 828 44 53",
    "sg:postcode":"2660",
    "sg:province":"Antwerpen",
    "wof:name":"Zetelgigant",
    "wof:placetype":"venue"
},
  "geometry": {"coordinates":[4.3397898674,51.1732788086],"type":"Point"}
}