{
  "type": "Feature",
  "properties": {
    "iso:country":"BE",
    "sg:address":"Neerwegstraat 15",
    "sg:city":"Herzele",
    "sg:orig_category":"Woningbouw",
    "sg:phone":"+32 53 62 23 22",
    "sg:postcode":"9550",
    "sg:province":"Oost-Vlaanderen",
    "wof:name":"Otte Julien",
    "wof:placetype":"venue"
},
  "geometry": {"coordinates":[3.9230480194,50.8709449768],"type":"Point"}
}