{
  "type": "Feature",
  "properties": {
    "iso:country":"BE",
    "sg:address":"7190",
    "sg:city":"Ecaussinnes",
    "sg:orig_category":"Pharmaciens",
    "sg:phone":"+32 900 10 500",
    "sg:postcode":"7190",
    "sg:province":"Hainaut",
    "wof:name":"Pharmacies De Garde",
    "wof:placetype":"venue"
},
  "geometry": {"coordinates":[4.1744699478,50.5608901978],"type":"Point"}
}