{
  "type": "Feature",
  "properties": {
    "iso:country":"BE",
    "sg:address":"Waterloose Steenweg 966",
    "sg:city":"Ukkel/uccle",
    "sg:orig_category":"Diverse zakelijke dienstverlening",
    "sg:phone":"+32 2 375 71 89",
    "sg:postcode":"1180",
    "sg:province":"Bruxelles-Capitale",
    "wof:name":"Bureau Mati\u00c8re Grise",
    "wof:placetype":"venue"
},
  "geometry": {"coordinates":[4.3732762337,50.8019142151],"type":"Point"}
}