{
  "type": "Feature",
  "properties": {
    "addr:full":"Theodoor Van Rijswijckplaats 4 Antwerpen Antwerpen 2000",
    "addr:housenumber":"4",
    "addr:postcode":"2000",
    "addr:street":"Theodoor Van Rijswijckplaats",
    "iso:country":"BE",
    "sg:address":"Theodoor Van Rijswijckplaats 4",
    "sg:city":"Antwerpen",
    "sg:classifiers":[
        {
            "category":"Education",
            "subcategory":"School",
            "type":"Public Place"
        }
    ],
    "sg:phone":"+32 3 232 25 70",
    "sg:postcode":"2000",
    "sg:province":"Antwerpen",
    "sg:tags":[
        "secondary"
    ],
    "wof:name":"Instituut Sint-paulus",
    "wof:placetype":"venue"
},
  "geometry": {"coordinates":[4.4001951218,51.2166671753],"type":"Point"}
}