{
  "type": "Feature",
  "properties": {
    "addr:full":"Frans Beirenslaan 2ba Borsbeek Antwerpen 2150",
    "addr:housenumber":"2ba",
    "addr:postcode":"2150",
    "addr:street":"Frans Beirenslaan",
    "iso:country":"BE",
    "sg:address":"Frans Beirenslaan 2ba",
    "sg:city":"Borsbeek",
    "sg:orig_category":"Enseignement artistique",
    "sg:phone":"+32 3 321 22 66",
    "sg:postcode":"2150",
    "sg:province":"Antwerpen",
    "wof:name":"Kunstschool Academia",
    "wof:placetype":"venue"
},
  "geometry": {"coordinates":[4.4750800133,51.1883468628],"type":"Point"}
}