{
  "type": "Feature",
  "properties": {
    "addr:full":"Rue Perkiets 1 Baelen Li\u00e8ge 4837",
    "addr:housenumber":"1",
    "addr:postcode":"4837",
    "addr:street":"Rue Perkiets",
    "iso:country":"BE",
    "sg:address":"Rue Perkiets 1",
    "sg:city":"Baelen",
    "sg:classifiers":[
        {
            "category":"Fast Food",
            "type":"Food & Drink"
        }
    ],
    "sg:phone":"+32 87 55 68 43",
    "sg:postcode":"4837",
    "sg:province":"Li\u00e8ge",
    "sg:tags":[
        "meeneem",
        "restaurant"
    ],
    "wof:name":"Friterie Au Chalet",
    "wof:placetype":"venue"
},
  "geometry": {"coordinates":[5.9988899231,50.6101608276],"type":"Point"}
}