{
  "type": "Feature",
  "properties": {
    "addr:full":"Rue De Fraire 31 Anhee Namur 5537",
    "addr:housenumber":"31",
    "addr:postcode":"5537",
    "addr:street":"Rue De Fraire;Namur",
    "iso:country":"BE",
    "sg:address":"Rue De Fraire 31",
    "sg:city":"Anhee",
    "sg:orig_category":"Rundveehouders",
    "sg:phone":"+32 71 79 92 62",
    "sg:postcode":"5537",
    "sg:province":"Namur",
    "wof:name":"Didier Rossomme",
    "wof:placetype":"venue"
},
  "geometry": {"coordinates":[4.7868418694,50.331993103],"type":"Point"}
}