{
  "type": "Feature",
  "properties": {
    "iso:country":"BE",
    "sg:address":"Mechelsesteenweg 102",
    "sg:city":"Kontich",
    "sg:classifiers":[
        {
            "category":"Shopping",
            "subcategory":"Gifts & Souvenirs",
            "type":"Retail Goods"
        }
    ],
    "sg:phone":"+32 3 457 66 68",
    "sg:postcode":"2550",
    "sg:province":"Antwerpen",
    "sg:tags":[
        "-"
    ],
    "wof:name":"Oooeps",
    "wof:placetype":"venue"
},
  "geometry": {"coordinates":[4.4461407661,51.1314926147],"type":"Point"}
}