{
  "type": "Feature",
  "properties": {
    "iso:country":"BE",
    "sg:address":"Hedekensdriesstraat 37",
    "sg:city":"Kruishoutem",
    "sg:orig_category":"Plaatsen van vloer- and muurbekleding Schilders",
    "sg:phone":"+32 9 383 74 51",
    "sg:postcode":"9770",
    "sg:province":"Oost-Vlaanderen",
    "wof:name":"Jan Verzelen",
    "wof:placetype":"venue"
},
  "geometry": {"coordinates":[3.5214979649,50.9040985107],"type":"Point"}
}