{
  "type": "Feature",
  "properties": {
    "addr:full":"Spanjestraat 10 Sint-gillis/saint-gilles Bruxelles-Capitale 1060",
    "addr:housenumber":"10",
    "addr:postcode":"1060",
    "addr:street":"Spanjestraat",
    "iso:country":"BE",
    "sg:address":"Spanjestraat 10",
    "sg:city":"Sint-gillis/saint-gilles",
    "sg:orig_category":"Film-, tv- and videoproductie",
    "sg:phone":"+32 2 539 00 41",
    "sg:postcode":"1060",
    "sg:province":"Bruxelles-Capitale",
    "wof:name":"Films Lyda",
    "wof:placetype":"venue"
},
  "geometry": {"coordinates":[4.3491020203,50.8264541626],"type":"Point"}
}