{
  "type": "Feature",
  "properties": {
    "addr:full":"Rue Des Hauts Tiennes 167 Braine L'alleud (braine-l'alleud) Brabant Wallon 1420",
    "addr:housenumber":"167",
    "addr:postcode":"1420",
    "addr:street":"Rue Des Hauts Tiennes",
    "iso:country":"BE",
    "sg:address":"Rue Des Hauts Tiennes 167",
    "sg:city":"Braine L'alleud (braine-l'alleud)",
    "sg:classifiers":[
        {
            "category":"Building & Trades",
            "subcategory":"Plumbing",
            "type":"Services"
        }
    ],
    "sg:phone":"+32 2 385 12 45",
    "sg:postcode":"1420",
    "sg:province":"Brabant Wallon",
    "sg:tags":[
        "contractor"
    ],
    "wof:name":"Plombi-zinc Sprl",
    "wof:placetype":"venue"
},
  "geometry": {"coordinates":[-0.8637679815,47.4133300781],"type":"Point"}
}