{
  "type": "Feature",
  "properties": {
    "iso:country":"BE",
    "sg:address":"Industrieweg 13",
    "sg:city":"Grobbendonk",
    "sg:orig_category":"Goederenvervoer over de weg Vrachtvervoer",
    "sg:phone":"+32 14 50 01 01",
    "sg:postcode":"2280",
    "sg:province":"Antwerpen",
    "wof:name":"Fracht International",
    "wof:placetype":"venue"
},
  "geometry": {"coordinates":[4.758866787,51.1772613525],"type":"Point"}
}