{
  "type": "Feature",
  "properties": {
    "iso:country":"BE",
    "sg:address":"Bosstraat 103",
    "sg:city":"Ternat (sint-katherina-lombeek)",
    "sg:classifiers":[
        {
            "category":"Retail",
            "subcategory":"Auto Rental",
            "type":"Services"
        }
    ],
    "sg:phone":"+32 53 64 58 64",
    "sg:postcode":"1742",
    "sg:province":"Vlaams-Brabant",
    "sg:tags":[
        "machine",
        "plasticizing"
    ],
    "wof:name":"Bindomatic Bvba",
    "wof:placetype":"venue"
},
  "geometry": {"coordinates":[4.1308679581,50.8752861023],"type":"Point"}
}