{
  "type": "Feature",
  "properties": {
    "addr:full":"Bierbeekstraat 116b11 Leuven Vlaams-Brabant 3001",
    "addr:housenumber":"116b11",
    "addr:postcode":"3001",
    "addr:street":"Bierbeekstraat",
    "iso:country":"BE",
    "sg:address":"Bierbeekstraat 116b11",
    "sg:city":"Leuven",
    "sg:classifiers":[
        {
            "category":"Taxi",
            "type":"Transportation"
        }
    ],
    "sg:phone":"+32 16 29 16 16",
    "sg:postcode":"3001",
    "sg:province":"Vlaams-Brabant",
    "sg:tags":[
        "taxi's"
    ],
    "wof:name":"Taxi Alex",
    "wof:placetype":"venue"
},
  "geometry": {"coordinates":[4.7175607681,50.871219635],"type":"Point"}
}