{
  "type": "Feature",
  "properties": {
    "iso:country":"BE",
    "sg:address":"Rue De Rochamps 13",
    "sg:city":"Rochefort (han-sur-lesse)",
    "sg:classifiers":[
        {
            "category":"Building & Trades",
            "subcategory":"Electrical",
            "type":"Services"
        }
    ],
    "sg:phone":"+32 84 37 77 61",
    "sg:postcode":"5580",
    "sg:province":"Namur",
    "sg:tags":[
        "electric",
        "-",
        "housewiring",
        "contractor"
    ],
    "wof:name":"Laroche E (ets)",
    "wof:placetype":"venue"
},
  "geometry": {"coordinates":[5.2231431007,50.1608505249],"type":"Point"}
}