{
  "type": "Feature",
  "properties": {
    "iso:country":"BE",
    "sg:address":"Kerkstraat 109",
    "sg:city":"Anzegem",
    "sg:orig_category":"Cr\u00e9dits divers",
    "sg:postcode":"8570",
    "sg:province":"West-Vlaanderen",
    "wof:name":"Bancontac-mister Cash",
    "wof:placetype":"venue"
},
  "geometry": {"coordinates":[3.4744749069,50.8382034302],"type":"Point"}
}