{
  "type": "Feature",
  "properties": {
    "iso:country":"BE",
    "sg:address":"Pettendonk 9b2",
    "sg:city":"Lier",
    "sg:orig_category":"Medische apparatuur, orthopedische artikelen and prothesen Fab",
    "sg:phone":"+32 3 489 19 83",
    "sg:postcode":"2500",
    "sg:province":"Antwerpen",
    "wof:name":"Dinkels Dental Labo",
    "wof:placetype":"venue"
},
  "geometry": {"coordinates":[4.578576088,51.1277275085],"type":"Point"}
}