{
  "type": "Feature",
  "properties": {
    "iso:country":"BE",
    "sg:address":"Hoog-lachenen 60",
    "sg:city":"Lier",
    "sg:orig_category":"Producteurs de l\u00e9gumes. Eleveurs and marchands de porcs. Eleveurs de bovins",
    "sg:phone":"+32 3 480 83 05",
    "sg:postcode":"2500",
    "sg:province":"Antwerpen",
    "wof:name":"Paul Van Dessel",
    "wof:placetype":"venue"
},
  "geometry": {"coordinates":[4.5124201775,51.1194953918],"type":"Point"}
}