{
  "type": "Feature",
  "properties": {
    "addr:full":"Rue Joseph Wauters 62 Quevaucamps Hainaut 7972",
    "addr:housenumber":"62",
    "addr:postcode":"7972",
    "addr:street":"Rue Joseph Wauters",
    "iso:country":"BE",
    "sg:address":"Rue Joseph Wauters 62",
    "sg:city":"Quevaucamps",
    "sg:orig_category":"Fleurs and plantes",
    "sg:phone":"+32 69 57 65 20",
    "sg:postcode":"7972",
    "sg:province":"Hainaut",
    "wof:name":"Lilyflowers",
    "wof:placetype":"venue"
},
  "geometry": {"coordinates":[3.683932066,50.5245285034],"type":"Point"}
}