{
  "type": "Feature",
  "properties": {
    "addr:full":"Zes Septemberstraat 86 Lummen Limburg 3560",
    "addr:housenumber":"86",
    "addr:postcode":"3560",
    "addr:street":"Zes Septemberstraat",
    "iso:country":"BE",
    "sg:address":"Zes Septemberstraat 86",
    "sg:city":"Lummen",
    "sg:orig_category":"Woningbouw",
    "sg:phone":"+32 11 43 31 42",
    "sg:postcode":"3560",
    "sg:province":"Limburg",
    "wof:name":"Theo Reynkens",
    "wof:placetype":"venue"
},
  "geometry": {"coordinates":[5.2031288147,51.0069465637],"type":"Point"}
}