{
  "type": "Feature",
  "properties": {
    "iso:country":"BE",
    "sg:address":"Neremweg 92",
    "sg:city":"Tongeren",
    "sg:orig_category":"D\u00e9m\u00e9nagements",
    "sg:phone":"+32 12 23 54 79",
    "sg:postcode":"3700",
    "sg:province":"Limburg",
    "wof:name":"Smullenberghs",
    "wof:placetype":"venue"
},
  "geometry": {"coordinates":[5.47544384,50.7745475769],"type":"Point"}
}