{
  "type": "Feature",
  "properties": {
    "addr:full":"Place Albert-ier 13 Nivelles Brabant Wallon 1400",
    "addr:housenumber":"13",
    "addr:postcode":"1400",
    "addr:street":"Place Albert-Ier",
    "iso:country":"BE",
    "sg:address":"Place Albert-ier 13",
    "sg:city":"Nivelles",
    "sg:orig_category":"Avocats and conseillers juridiques",
    "sg:phone":"+32 67 21 79 95",
    "sg:postcode":"1400",
    "sg:province":"Brabant Wallon",
    "wof:name":"A.f. Brasselle",
    "wof:placetype":"venue"
},
  "geometry": {"coordinates":[4.3224987984,50.5977478027],"type":"Point"}
}