{
  "type": "Feature",
  "properties": {
    "addr:full":"Kraanlei 37 Gent Oost-Vlaanderen 9000",
    "addr:housenumber":"37",
    "addr:postcode":"9000",
    "addr:street":"Kraanlei;Oost-Vlaanderen",
    "iso:country":"BE",
    "sg:address":"Kraanlei 37",
    "sg:city":"Gent",
    "sg:classifiers":[
        {
            "category":"Real Estate",
            "subcategory":"Surveying",
            "type":"Services"
        }
    ],
    "sg:phone":"+32 9 224 03 24",
    "sg:postcode":"9000",
    "sg:province":"Oost-Vlaanderen",
    "sg:tags":[
        "surveyor",
        "land"
    ],
    "wof:name":"De Moor H",
    "wof:placetype":"venue"
},
  "geometry": {"coordinates":[3.7226979733,51.0571136475],"type":"Point"}
}