{
  "type": "Feature",
  "properties": {
    "addr:full":"D'herbouvillekaai 103 Antwerpen Antwerpen 2020",
    "addr:housenumber":"103",
    "addr:postcode":"2020",
    "iso:country":"BE",
    "sg:address":"D'herbouvillekaai 103",
    "sg:city":"Antwerpen",
    "sg:orig_category":"Agences d'exp\u00e9dition",
    "sg:phone":"+32 3 238 54 48",
    "sg:postcode":"2020",
    "sg:province":"Antwerpen",
    "wof:name":"Belgische Potgrondfederatie",
    "wof:placetype":"venue"
},
  "geometry": {"coordinates":[4.3540649414,51.1982765198],"type":"Point"}
}