{
  "type": "Feature",
  "properties": {
    "addr:full":"Sint-michielskaai 40 Antwerpen Antwerpen 2000",
    "addr:housenumber":"40",
    "addr:postcode":"2000",
    "addr:street":"Sint-Michielskaai",
    "iso:country":"BE",
    "sg:address":"Sint-michielskaai 40",
    "sg:city":"Antwerpen",
    "sg:orig_category":"Promoteurs immobiliers. Agences immobili\u00e8res",
    "sg:phone":"+32 3 248 24 72",
    "sg:postcode":"2000",
    "sg:province":"Antwerpen",
    "wof:name":"Himmos",
    "wof:placetype":"venue"
},
  "geometry": {"coordinates":[4.3912100792,51.2134208679],"type":"Point"}
}