{
  "type": "Feature",
  "properties": {
    "iso:country":"BE",
    "sg:address":"Waversebaan 323",
    "sg:city":"Leuven",
    "sg:orig_category":"Grossistes divers",
    "sg:phone":"+32 16 40 56 61",
    "sg:postcode":"3001",
    "sg:province":"Vlaams-Brabant",
    "wof:name":"World Wide Promotion",
    "wof:placetype":"venue"
},
  "geometry": {"coordinates":[4.6758618355,50.8517913818],"type":"Point"}
}