{
  "type": "Feature",
  "properties": {
    "addr:full":"Ruiseleedsesteenweg 55 Tielt West-Vlaanderen 8700",
    "addr:housenumber":"55",
    "addr:postcode":"8700",
    "addr:street":"Ruiseleedsesteenweg",
    "iso:country":"BE",
    "sg:address":"Ruiseleedsesteenweg 55",
    "sg:city":"Tielt",
    "sg:classifiers":[
        {
            "category":"Building & Trades",
            "subcategory":"Pest Control",
            "type":"Services"
        }
    ],
    "sg:phone":"+32 51 40 31 42",
    "sg:postcode":"8700",
    "sg:province":"West-Vlaanderen",
    "sg:tags":[
        "disinfectant",
        "insecticide"
    ],
    "wof:name":"Disaghor Nv",
    "wof:placetype":"venue"
},
  "geometry": {"coordinates":[3.3631711006,51.0121154785],"type":"Point"}
}