{
  "type": "Feature",
  "properties": {
    "addr:full":"Rue L\u00c9onard De Vinci 32 Brussel/bruxelles Bruxelles-Capitale 1000",
    "addr:housenumber":"32",
    "addr:postcode":"1000",
    "addr:street":"Rue Le\u0301Onard De Vinci;/",
    "iso:country":"BE",
    "sg:address":"Rue L\u00c9onard De Vinci 32",
    "sg:city":"Brussel/bruxelles",
    "sg:orig_category":"Diverse grafische activiteiten Secretariaatsdiensten",
    "sg:phone":"+32 2 733 53 88",
    "sg:postcode":"1000",
    "sg:province":"Bruxelles-Capitale",
    "wof:name":"D-click",
    "wof:placetype":"venue"
},
  "geometry": {"coordinates":[4.3908119202,50.8448753357],"type":"Point"}
}