{
  "type": "Feature",
  "properties": {
    "addr:full":"Vossenlaan 29 Tervuren Vlaams-Brabant 3080",
    "addr:housenumber":"29",
    "addr:postcode":"3080",
    "addr:street":"Vossenlaan",
    "iso:country":"BE",
    "sg:address":"Vossenlaan 29",
    "sg:city":"Tervuren",
    "sg:orig_category":"M\u00e9decines alternatives",
    "sg:phone":"+32 2 767 49 02",
    "sg:postcode":"3080",
    "sg:province":"Vlaams-Brabant",
    "wof:name":"Karin Hansen",
    "wof:placetype":"venue"
},
  "geometry": {"coordinates":[4.5125141144,50.8173332214],"type":"Point"}
}