{
  "type": "Feature",
  "properties": {
    "addr:full":"Molderdijk 130 Mol Antwerpen 2400",
    "addr:housenumber":"130",
    "addr:postcode":"2400",
    "addr:street":"Molderdijk",
    "iso:country":"BE",
    "sg:address":"Molderdijk 130",
    "sg:city":"Mol",
    "sg:classifiers":[
        {
            "category":"Communications",
            "subcategory":"Newspaper",
            "type":"Services"
        }
    ],
    "sg:phone":"+32 14 34 79 11",
    "sg:postcode":"2400",
    "sg:province":"Antwerpen",
    "sg:tags":[
        "paper",
        "local",
        "free"
    ],
    "wof:name":"Zoeklicht (het)",
    "wof:placetype":"venue"
},
  "geometry": {"coordinates":[5.1281528473,51.1777877808],"type":"Point"}
}