{
  "type": "Feature",
  "properties": {
    "addr:full":"Rue Saint-eutrope 11 Paliseul Luxembourg 6850",
    "addr:housenumber":"11",
    "addr:postcode":"6850",
    "addr:street":"Rue Saint-Eutrope",
    "iso:country":"BE",
    "sg:address":"Rue Saint-eutrope 11",
    "sg:city":"Paliseul",
    "sg:classifiers":[
        {
            "category":"Insurance",
            "subcategory":"Insurance Agent",
            "type":"Services"
        }
    ],
    "sg:phone":"+32 61 53 44 71",
    "sg:postcode":"6850",
    "sg:province":"Luxembourg",
    "sg:tags":[
        "verzekeringsmakelaars",
        "expert"
    ],
    "wof:name":"Labbe",
    "wof:placetype":"venue"
},
  "geometry": {"coordinates":[5.1337518692,49.9037780762],"type":"Point"}
}