{
  "type": "Feature",
  "properties": {
    "iso:country":"BE",
    "sg:address":"Meiboomlaan 14",
    "sg:city":"Roeselare",
    "sg:orig_category":"Projectontwikkelaars Woningbouw",
    "sg:phone":"+32 51 20 66 01",
    "sg:postcode":"8800",
    "sg:province":"West-Vlaanderen",
    "wof:name":"R.i.m.",
    "wof:placetype":"venue"
},
  "geometry": {"coordinates":[3.1199929714,50.9355201721],"type":"Point"}
}