{
  "type": "Feature",
  "properties": {
    "addr:full":"Avenue Du Parc 91 Vorst/forest Bruxelles-Capitale 1190",
    "addr:housenumber":"91",
    "addr:postcode":"1190",
    "addr:street":"Avenue Du Parc;/ Forest",
    "iso:country":"BE",
    "sg:address":"Avenue Du Parc 91",
    "sg:city":"Vorst/forest",
    "sg:orig_category":"Biblioth\u00e8ques and archives publiques",
    "sg:phone":"+32 2 538 00 78",
    "sg:postcode":"1190",
    "sg:province":"Bruxelles-Capitale",
    "wof:name":"Grp Media Library",
    "wof:placetype":"venue"
},
  "geometry": {"coordinates":[4.3386111259,50.8253974915],"type":"Point"}
}