{
  "type": "Feature",
  "properties": {
    "iso:country":"BE",
    "sg:address":"Quartier De La Bruy\u00c8re 40",
    "sg:city":"Beloeil",
    "sg:orig_category":"Sportclubs",
    "sg:phone":"+32 495 24 15 91",
    "sg:postcode":"7971",
    "sg:province":"Hainaut",
    "wof:name":"T.c. Central Park",
    "wof:placetype":"venue"
},
  "geometry": {"coordinates":[3.6646900177,50.5214385986],"type":"Point"}
}