{
  "type": "Feature",
  "properties": {
    "addr:full":"Rue De L'esplanade 58 Sprimont Li\u00e8ge 4141",
    "addr:housenumber":"58",
    "addr:postcode":"4141",
    "addr:street":"Rue De L'Esplanade",
    "iso:country":"BE",
    "sg:address":"Rue De L'esplanade 58",
    "sg:city":"Sprimont",
    "sg:classifiers":[
        {
            "category":"Restaurant",
            "type":"Food & Drink"
        }
    ],
    "sg:phone":"+32 4 360 84 99",
    "sg:postcode":"4141",
    "sg:province":"Li\u00e8ge",
    "wof:name":"Restaurant De La Source",
    "wof:placetype":"venue"
},
  "geometry": {"coordinates":[5.739525795,50.5378112793],"type":"Point"}
}