{
  "type": "Feature",
  "properties": {
    "addr:full":"Corbillon 6 Thimister-clermont Li\u00e8ge 4890",
    "addr:housenumber":"6",
    "addr:postcode":"4890",
    "addr:street":"Corbillon",
    "iso:country":"BE",
    "sg:address":"Corbillon 6",
    "sg:city":"Thimister-clermont",
    "sg:orig_category":"Rundveehouders",
    "sg:phone":"+32 87 68 65 04",
    "sg:postcode":"4890",
    "sg:province":"Li\u00e8ge",
    "wof:name":"Leopold Demez",
    "wof:placetype":"venue"
},
  "geometry": {"coordinates":[5.8702888489,50.6755104065],"type":"Point"}
}