{
  "type": "Feature",
  "properties": {
    "iso:country":"BE",
    "sg:address":"Rue De Montigny 106",
    "sg:city":"Charleroi (grand)",
    "sg:orig_category":"Krantenwinkels Rookartikelen",
    "sg:phone":"+32 71 33 05 23",
    "sg:postcode":"6000",
    "sg:province":"Hainaut",
    "wof:name":"Bosquetville",
    "wof:placetype":"venue"
},
  "geometry": {"coordinates":[4.4484992027,50.406879425],"type":"Point"}
}