{
  "type": "Feature",
  "properties": {
    "iso:country":"BE",
    "sg:address":"Knorrebosstraat 15",
    "sg:city":"Meulebeke",
    "sg:orig_category":"Fruitteelt",
    "sg:phone":"+32 51 48 75 52",
    "sg:postcode":"8760",
    "sg:province":"West-Vlaanderen",
    "wof:name":"Noel Demeester",
    "wof:placetype":"venue"
},
  "geometry": {"coordinates":[3.2880349159,50.9229125977],"type":"Point"}
}