{
  "type": "Feature",
  "properties": {
    "iso:country":"BE",
    "sg:address":"Pulsebaan 48 Box 6",
    "sg:city":"Zandhoven (pulderbos)",
    "sg:classifiers":[
        {
            "category":"Manufacturing",
            "subcategory":"Motor Vehicles & Parts",
            "type":"Manufacturing & Wholesale Goods"
        }
    ],
    "sg:phone":"+32 3 464 02 22",
    "sg:postcode":"2242",
    "sg:province":"Antwerpen",
    "sg:tags":[
        "machine",
        "-",
        "indivisible",
        "transport"
    ],
    "wof:name":"Pauls Convoy Service",
    "wof:placetype":"venue"
},
  "geometry": {"coordinates":[4.6946258545,51.2126274109],"type":"Point"}
}