{
  "type": "Feature",
  "properties": {
    "addr:full":"Geelsebaan 21 Kasterlee Antwerpen 2460",
    "addr:housenumber":"21",
    "addr:postcode":"2460",
    "addr:street":"Geelsebaan",
    "iso:country":"BE",
    "sg:address":"Geelsebaan 21",
    "sg:city":"Kasterlee",
    "sg:orig_category":"Ice-cream parlours",
    "sg:phone":"+32 14 85 01 42",
    "sg:postcode":"2460",
    "sg:province":"Antwerpen",
    "wof:name":"Ijsmanneke",
    "wof:placetype":"venue"
},
  "geometry": {"coordinates":[4.9685640335,51.2391014099],"type":"Point"}
}