{
  "type": "Feature",
  "properties": {
    "addr:full":"Rue De L'institut 1 Estaimpuis Hainaut 7730",
    "addr:housenumber":"1",
    "addr:postcode":"7730",
    "addr:street":"Rue De L'Institut;Hainaut",
    "iso:country":"BE",
    "sg:address":"Rue De L'institut 1",
    "sg:city":"Estaimpuis",
    "sg:orig_category":"Maisons de repos and r\u00e9sidences",
    "sg:phone":"+32 69 35 23 00",
    "sg:postcode":"7730",
    "sg:province":"Hainaut",
    "wof:name":"Institut St.joseph",
    "wof:placetype":"venue"
},
  "geometry": {"coordinates":[3.2657980919,50.6665115356],"type":"Point"}
}