{
  "type": "Feature",
  "properties": {
    "addr:full":"Avenue D'auderghem 96 Bruxelles (etterbeek) Bruxelles-Capitale 1040",
    "addr:housenumber":"96",
    "addr:postcode":"1040",
    "addr:street":"Avenue D'Auderghem",
    "iso:country":"BE",
    "sg:address":"Avenue D'auderghem 96",
    "sg:city":"Bruxelles (etterbeek)",
    "sg:classifiers":[
        {
            "category":"Professional",
            "subcategory":"Lawyer & Legal Services",
            "type":"Services"
        }
    ],
    "sg:phone":"+32 2 736 00 19",
    "sg:postcode":"1040",
    "sg:province":"Bruxelles-Capitale",
    "sg:tags":[
        "notary"
    ],
    "wof:name":"Van Dyck R",
    "wof:placetype":"venue"
},
  "geometry": {"coordinates":[4.3863921165,50.8380889893],"type":"Point"}
}