{
  "type": "Feature",
  "properties": {
    "iso:country":"BE",
    "sg:address":"Avenue Eug\u00e8ne Demolder 24",
    "sg:city":"Bruxelles (schaerbeek)",
    "sg:classifiers":[
        {
            "category":"Professional",
            "subcategory":"Management & Consulting",
            "type":"Services"
        }
    ],
    "sg:phone":"+32 2 245 75 20",
    "sg:postcode":"1030",
    "sg:province":"Bruxelles-Capitale",
    "sg:tags":[
        "consultant",
        "promotion",
        "-",
        "sale"
    ],
    "wof:name":"Action Line Communication",
    "wof:placetype":"venue"
},
  "geometry": {"coordinates":[4.3774280548,50.8720092773],"type":"Point"}
}