{
  "type": "Feature",
  "properties": {
    "addr:full":"Boezingsestraat 80 Ieper West-Vlaanderen 8906",
    "addr:housenumber":"80",
    "addr:postcode":"8906",
    "addr:street":"Boezingsestraat",
    "iso:country":"BE",
    "sg:address":"Boezingsestraat 80",
    "sg:city":"Ieper",
    "sg:orig_category":"Varkenskwekers",
    "sg:phone":"+32 57 42 25 22",
    "sg:postcode":"8906",
    "sg:province":"West-Vlaanderen",
    "wof:name":"Frans Stragier",
    "wof:placetype":"venue"
},
  "geometry": {"coordinates":[2.8317990303,50.887878418],"type":"Point"}
}