{
  "type": "Feature",
  "properties": {
    "addr:full":"Place Albert Ier 14b15 Anderlues Hainaut 6150",
    "addr:housenumber":"14b15",
    "addr:postcode":"6150",
    "addr:street":"Place Albert Ier",
    "iso:country":"BE",
    "sg:address":"Place Albert Ier 14b15",
    "sg:city":"Anderlues",
    "sg:orig_category":"Banques and organismes de cr\u00e9dit",
    "sg:phone":"+32 71 52 50 91",
    "sg:postcode":"6150",
    "sg:province":"Hainaut",
    "wof:name":"Fortis",
    "wof:placetype":"venue"
},
  "geometry": {"coordinates":[4.2701258659,50.4071731567],"type":"Point"}
}