{
  "type": "Feature",
  "properties": {
    "addr:full":"Energieweg 7 Malle Antwerpen 2390",
    "addr:housenumber":"7",
    "addr:postcode":"2390",
    "addr:street":"Energieweg",
    "iso:country":"BE",
    "sg:address":"Energieweg 7",
    "sg:city":"Malle",
    "sg:orig_category":"Maatkleding Fab",
    "sg:phone":"+32 3 312 45 75",
    "sg:postcode":"2390",
    "sg:province":"Antwerpen",
    "wof:name":"Livs",
    "wof:placetype":"venue"
},
  "geometry": {"coordinates":[4.7154631615,51.2937736511],"type":"Point"}
}