{
  "type": "Feature",
  "properties": {
    "addr:full":"Betlehem 94 Menen West-Vlaanderen 8930",
    "addr:housenumber":"94",
    "addr:postcode":"8930",
    "addr:street":"Betlehem",
    "iso:country":"BE",
    "sg:address":"Betlehem 94",
    "sg:city":"Menen",
    "sg:orig_category":"Herstellingen and onderhoud van auto's Voertuigen",
    "sg:phone":"+32 56 51 38 10",
    "sg:postcode":"8930",
    "sg:province":"West-Vlaanderen",
    "wof:name":"Gino Dekeyser",
    "wof:placetype":"venue"
},
  "geometry": {"coordinates":[3.0969159603,50.7921829224],"type":"Point"}
}