{
  "type": "Feature",
  "properties": {
    "iso:country":"BE",
    "sg:address":"Chauss\u00c9e De Bascoup 35",
    "sg:city":"Anderlues",
    "sg:orig_category":"Jeux de hasard. Caf\u00e9s",
    "sg:phone":"+32 71 52 20 60",
    "sg:postcode":"6150",
    "sg:province":"Hainaut",
    "wof:name":"Caf\u00c9 Le Feu De Bois",
    "wof:placetype":"venue"
},
  "geometry": {"coordinates":[4.2834620476,50.4083709717],"type":"Point"}
}