{
  "type": "Feature",
  "properties": {
    "iso:country":"BE",
    "sg:address":"Rue De Chefa\u00cfd 11",
    "sg:city":"Huy",
    "sg:orig_category":"Herstellingen and onderhoud van auto's",
    "sg:phone":"+32 85 23 01 82",
    "sg:postcode":"4500",
    "sg:province":"Li\u00e8ge",
    "wof:name":"Patrice Libois",
    "wof:placetype":"venue"
},
  "geometry": {"coordinates":[5.1815419197,50.4848632812],"type":"Point"}
}