{
  "type": "Feature",
  "properties": {
    "iso:country":"BE",
    "sg:address":"Rue De La Bruy\u00c8re 250",
    "sg:city":"Charleroi",
    "sg:orig_category":"Dakwerken Industri\u00eble and commerci\u00eble bouw Plaatsen van vloer- and muurbekleding Woningbouw",
    "sg:phone":"+32 71 36 12 20",
    "sg:postcode":"6001",
    "sg:province":"Hainaut",
    "wof:name":"Druez",
    "wof:placetype":"venue"
},
  "geometry": {"coordinates":[4.4305019379,50.3739700317],"type":"Point"}
}