{
  "type": "Feature",
  "properties": {
    "iso:country":"BE",
    "sg:address":"Chauss\u00c9e De Waterloo 1366",
    "sg:city":"Ukkel/uccle",
    "sg:orig_category":"Bijoux Fab. Bijouteries and horlogeries",
    "sg:phone":"+32 2 374 22 08",
    "sg:postcode":"1180",
    "sg:province":"Bruxelles-Capitale",
    "wof:name":"Maison Anselot",
    "wof:placetype":"venue"
},
  "geometry": {"coordinates":[4.3753170967,50.7889022827],"type":"Point"}
}