{
  "type": "Feature",
  "properties": {
    "addr:full":"Pijpersveldstraat 9 Hasselt Limburg 3500",
    "addr:housenumber":"9",
    "addr:postcode":"3500",
    "addr:street":"Pijpersveldstraat",
    "iso:country":"BE",
    "sg:address":"Pijpersveldstraat 9",
    "sg:city":"Hasselt",
    "sg:orig_category":"Bloemen and planten",
    "sg:phone":"+32 11 24 10 02",
    "sg:postcode":"3500",
    "sg:province":"Limburg",
    "wof:name":"'t Bloementuiltje",
    "wof:placetype":"venue"
},
  "geometry": {"coordinates":[5.3831858635,50.9440422058],"type":"Point"}
}