{
  "type": "Feature",
  "properties": {
    "addr:full":"Schraaienstraat 63 Nazareth Oost-Vlaanderen 9810",
    "addr:housenumber":"63",
    "addr:postcode":"9810",
    "addr:street":"Schraaienstraat",
    "iso:country":"BE",
    "sg:address":"Schraaienstraat 63",
    "sg:city":"Nazareth",
    "sg:classifiers":[
        {
            "category":"Professional",
            "type":"Services"
        }
    ],
    "sg:phone":"+32 9 228 43 51",
    "sg:postcode":"9810",
    "sg:province":"Oost-Vlaanderen",
    "sg:tags":[
        "auction",
        "room"
    ],
    "wof:name":"Ogiers Bvba",
    "wof:placetype":"venue"
},
  "geometry": {"coordinates":[3.6185851097,50.9489707947],"type":"Point"}
}