{
  "type": "Feature",
  "properties": {
    "iso:country":"BE",
    "sg:address":"Schoolstraat 18",
    "sg:city":"Torhout",
    "sg:orig_category":"Slagers",
    "sg:phone":"+32 50 21 68 27",
    "sg:postcode":"8820",
    "sg:province":"West-Vlaanderen",
    "wof:name":"H. Vandewaetere",
    "wof:placetype":"venue"
},
  "geometry": {"coordinates":[3.0601139069,51.0910377502],"type":"Point"}
}