{
  "type": "Feature",
  "properties": {
    "addr:full":"Arsenaalstraat 45 Asse Vlaams-Brabant 1730",
    "addr:housenumber":"45",
    "addr:postcode":"1730",
    "addr:street":"Arsenaalstraat",
    "iso:country":"BE",
    "sg:address":"Arsenaalstraat 45",
    "sg:city":"Asse",
    "sg:orig_category":"Traitements param\u00e9dicaux",
    "sg:phone":"+32 2 452 22 85",
    "sg:postcode":"1730",
    "sg:province":"Vlaams-Brabant",
    "wof:name":"Vermandere",
    "wof:placetype":"venue"
},
  "geometry": {"coordinates":[4.1991510391,50.9091911316],"type":"Point"}
}