{
  "type": "Feature",
  "properties": {
    "iso:country":"BE",
    "sg:address":"Passage Linthout 3",
    "sg:city":"Bruxelles (woluwe-saint-lambert)",
    "sg:classifiers":[
        {
            "category":"Shopping",
            "subcategory":"Clothing, Apparel, & Fashions",
            "type":"Retail Goods"
        }
    ],
    "sg:phone":"+32 2 735 10 16",
    "sg:postcode":"1200",
    "sg:province":"Bruxelles-Capitale",
    "sg:tags":[
        "boutique"
    ],
    "wof:name":"Trafalgar",
    "wof:placetype":"venue"
},
  "geometry": {"coordinates":[4.4022312164,50.8408699036],"type":"Point"}
}