{
  "type": "Feature",
  "properties": {
    "addr:full":"Rue Willmotte Duport 13 Huy Li\u00e8ge 4500",
    "addr:housenumber":"13",
    "addr:postcode":"4500",
    "addr:street":"Rue Willmotte Duport",
    "iso:country":"BE",
    "sg:address":"Rue Willmotte Duport 13",
    "sg:city":"Huy",
    "sg:orig_category":"Architectes",
    "sg:phone":"+32 85 23 51 47",
    "sg:postcode":"4500",
    "sg:province":"Li\u00e8ge",
    "wof:name":"Sanglan Jean Pierre",
    "wof:placetype":"venue"
},
  "geometry": {"coordinates":[5.2444448471,50.5224990845],"type":"Point"}
}