{
  "type": "Feature",
  "properties": {
    "addr:full":"Kerspelstraat 26 Leuven (heverlee) Vlaams-Brabant 3001",
    "addr:housenumber":"26",
    "addr:postcode":"3001",
    "addr:street":"Kerspelstraat",
    "iso:country":"BE",
    "sg:address":"Kerspelstraat 26",
    "sg:city":"Leuven (heverlee)",
    "sg:classifiers":[
        {
            "category":"Professional",
            "subcategory":"Management & Consulting",
            "type":"Services"
        }
    ],
    "sg:phone":"+32 16 40 17 93",
    "sg:postcode":"3001",
    "sg:province":"Vlaams-Brabant",
    "sg:tags":[
        "-",
        "processing",
        "data",
        "consultant"
    ],
    "wof:name":"Levintelligence Bvba",
    "wof:placetype":"venue"
},
  "geometry": {"coordinates":[4.7060141563,50.8595085144],"type":"Point"}
}