{
  "type": "Feature",
  "properties": {
    "addr:full":"Rue Joseph Wauters 15 Tubize Brabant Wallon 1480",
    "addr:housenumber":"15",
    "addr:postcode":"1480",
    "addr:street":"Rue Joseph Wauters;Wallon",
    "iso:country":"BE",
    "sg:address":"Rue Joseph Wauters 15",
    "sg:city":"Tubize",
    "sg:orig_category":"Sportclubs",
    "sg:phone":"+32 2 355 84 21",
    "sg:postcode":"1480",
    "sg:province":"Brabant Wallon",
    "wof:name":"Plume D'argent",
    "wof:placetype":"venue"
},
  "geometry": {"coordinates":[4.1582660675,50.705329895],"type":"Point"}
}