{
  "type": "Feature",
  "properties": {
    "iso:country":"BE",
    "sg:address":"Avenue Reine Astrid 236",
    "sg:city":"Spa",
    "sg:classifiers":[
        {
            "category":"Shopping",
            "subcategory":"Bridal",
            "type":"Retail Goods"
        }
    ],
    "sg:phone":"+32 87 79 52 52",
    "sg:postcode":"4900",
    "sg:province":"Li\u00e8ge",
    "sg:tags":[
        "list",
        "-",
        "present",
        "wedding"
    ],
    "wof:name":"Cr\u00e9dence (la)",
    "wof:placetype":"venue"
},
  "geometry": {"coordinates":[5.8451862335,50.4897346497],"type":"Point"}
}