{
  "type": "Feature",
  "properties": {
    "addr:full":"Wilgenbroekstraat 60 Oostkamp West-Vlaanderen 8020",
    "addr:housenumber":"60",
    "addr:postcode":"8020",
    "addr:street":"Wilgenbroekstraat",
    "iso:country":"BE",
    "sg:address":"Wilgenbroekstraat 60",
    "sg:city":"Oostkamp",
    "sg:orig_category":"Fleurs and plantes",
    "sg:phone":"+32 50 38 76 83",
    "sg:postcode":"8020",
    "sg:province":"West-Vlaanderen",
    "wof:name":"Huis Vergote & Co",
    "wof:placetype":"venue"
},
  "geometry": {"coordinates":[3.2288808823,51.1717948914],"type":"Point"}
}