{
  "type": "Feature",
  "properties": {
    "iso:country":"BE",
    "sg:address":"Avenue Reine Astrid 26",
    "sg:city":"Waremme",
    "sg:orig_category":"Baby- and kinderkleding",
    "sg:phone":"+32 19 54 64 79",
    "sg:postcode":"4300",
    "sg:province":"Li\u00e8ge",
    "wof:name":"Mini Maxi Mod",
    "wof:placetype":"venue"
},
  "geometry": {"coordinates":[5.2511239052,50.6953659058],"type":"Point"}
}