{
  "type": "Feature",
  "properties": {
    "addr:full":"Zwevegemsestraat 65 Kortrijk West-Vlaanderen 8500",
    "addr:housenumber":"65",
    "addr:postcode":"8500",
    "addr:street":"Zwevegemsestraat",
    "iso:country":"BE",
    "sg:address":"Zwevegemsestraat 65",
    "sg:city":"Kortrijk",
    "sg:orig_category":"RESTAURANTS: SALLES DE CONF\u00c9RENCES AND DE R\u00c9CEPTIONS",
    "sg:phone":"+32 56 21 19 33",
    "sg:postcode":"8500",
    "sg:province":"West-Vlaanderen",
    "wof:name":"De Open Haard",
    "wof:placetype":"venue"
},
  "geometry": {"coordinates":[3.2738959789,50.824016571],"type":"Point"}
}