{
  "type": "Feature",
  "properties": {
    "iso:country":"BE",
    "sg:address":"B\u00fcllinger Strasse 231",
    "sg:city":"Amel",
    "sg:classifiers":[
        {
            "category":"Bars & Pubs",
            "type":"Food & Drink"
        }
    ],
    "sg:phone":"+32 80 34 90 35",
    "sg:postcode":"4770",
    "sg:province":"Li\u00e8ge",
    "wof:name":"Caf\u00e9-friture Peters",
    "wof:placetype":"venue"
},
  "geometry": {"coordinates":[6.1712818146,50.3494033813],"type":"Point"}
}