{
  "type": "Feature",
  "properties": {
    "addr:full":"Sint-amandstraat 20 Gent Oost-Vlaanderen 9000",
    "addr:housenumber":"20",
    "addr:postcode":"9000",
    "addr:street":"Sint-Amandstraat;Oost-Vlaanderen",
    "iso:country":"BE",
    "sg:address":"Sint-amandstraat 20",
    "sg:city":"Gent",
    "sg:classifiers":[
        {
            "category":"Professional",
            "subcategory":"Accounting & Tax Preparation",
            "type":"Services"
        }
    ],
    "sg:phone":"+32 9 223 37 91",
    "sg:postcode":"9000",
    "sg:province":"Oost-Vlaanderen",
    "sg:tags":[
        "bookkeeper"
    ],
    "wof:name":"Batimenta",
    "wof:placetype":"venue"
},
  "geometry": {"coordinates":[3.7244079113,51.0435943604],"type":"Point"}
}