{
  "type": "Feature",
  "properties": {
    "addr:full":"Zwartlandstraat 3 Hulshout Antwerpen 2235",
    "addr:housenumber":"3",
    "addr:postcode":"2235",
    "addr:street":"Zwartlandstraat",
    "iso:country":"BE",
    "sg:address":"Zwartlandstraat 3",
    "sg:city":"Hulshout",
    "sg:orig_category":"Pain, p\u00e2tisseries and confiseries",
    "sg:phone":"+32 15 22 07 60",
    "sg:postcode":"2235",
    "sg:province":"Antwerpen",
    "wof:name":"Bakkerij Van Oosterwyck",
    "wof:placetype":"venue"
},
  "geometry": {"coordinates":[4.7961101532,51.0794372559],"type":"Point"}
}