{
  "type": "Feature",
  "properties": {
    "addr:full":"Pauwstraat 15 Beveren (melsele) Oost-Vlaanderen 9120",
    "addr:housenumber":"15",
    "addr:postcode":"9120",
    "addr:street":"Pauwstraat",
    "iso:country":"BE",
    "sg:address":"Pauwstraat 15",
    "sg:city":"Beveren (melsele)",
    "sg:classifiers":[
        {
            "category":"Building & Trades",
            "subcategory":"Construction",
            "type":"Services"
        }
    ],
    "sg:phone":"+32 3 775 38 14",
    "sg:postcode":"9120",
    "sg:province":"Oost-Vlaanderen",
    "sg:tags":[
        "installation",
        "-",
        "central",
        "heating"
    ],
    "wof:name":"Van Hove Peter Bvba",
    "wof:placetype":"venue"
},
  "geometry": {"coordinates":[4.2838020325,51.2138252258],"type":"Point"}
}