{
  "type": "Feature",
  "properties": {
    "addr:full":"Transportcent.lar Blok M 60 Menen West-Vlaanderen 8930",
    "addr:housenumber":"60",
    "addr:postcode":"8930",
    "addr:street":"Blok M",
    "iso:country":"BE",
    "sg:address":"Transportcent.lar Blok M 60",
    "sg:city":"Menen",
    "sg:orig_category":"Beheer van reclamemedia",
    "sg:phone":"+32 56 41 74 88",
    "sg:postcode":"8930",
    "sg:province":"West-Vlaanderen",
    "wof:name":"Vlaamse Distributiemij",
    "wof:placetype":"venue"
},
  "geometry": {"coordinates":[3.1209149361,50.7961845398],"type":"Point"}
}