{
  "type": "Feature",
  "properties": {
    "iso:country":"BE",
    "sg:address":"Rue Lucien Foss\u00e9prez 41",
    "sg:city":"Profondeville (bois-de-villers)",
    "sg:classifiers":[
        {
            "category":"Health Services",
            "subcategory":"Health Practitioner",
            "type":"Services"
        }
    ],
    "sg:phone":"+32 81 43 32 61",
    "sg:postcode":"5170",
    "sg:province":"Namur",
    "sg:tags":[
        "physiotherapist"
    ],
    "wof:name":"Melin Isabelle",
    "wof:placetype":"venue"
},
  "geometry": {"coordinates":[4.8109412193,50.3872528076],"type":"Point"}
}