{
  "type": "Feature",
  "properties": {
    "addr:full":"Hoogstraat 1bb Meise Vlaams-Brabant 1861",
    "addr:housenumber":"1bb",
    "addr:postcode":"1861",
    "addr:street":"Hoogstraat",
    "iso:country":"BE",
    "sg:address":"Hoogstraat 1bb",
    "sg:city":"Meise",
    "sg:orig_category":"Banken and kredietinstellingen",
    "sg:phone":"+32 2 269 19 92",
    "sg:postcode":"1861",
    "sg:province":"Vlaams-Brabant",
    "wof:name":"Fortis",
    "wof:placetype":"venue"
},
  "geometry": {"coordinates":[4.3095240593,50.9509773254],"type":"Point"}
}