{
  "type": "Feature",
  "properties": {
    "addr:full":"Herentalsstraat 15 Turnhout Antwerpen 2300",
    "addr:housenumber":"15",
    "addr:postcode":"2300",
    "addr:street":"Herentalsstraat",
    "iso:country":"BE",
    "sg:address":"Herentalsstraat 15",
    "sg:city":"Turnhout",
    "sg:orig_category":"Blanchisserie, Nettoyage \u00e0 Sec and Salons-Lavoirs. Blanchisseries and teintureries",
    "sg:phone":"+32 14 41 33 60",
    "sg:postcode":"2300",
    "sg:province":"Antwerpen",
    "wof:name":"Quick Shop",
    "wof:placetype":"venue"
},
  "geometry": {"coordinates":[4.9494848251,51.3218727112],"type":"Point"}
}