{
  "type": "Feature",
  "properties": {
    "addr:full":"Rue Walth\u00c8re Jamar 113 Ans Li\u00e8ge 4430",
    "addr:housenumber":"113",
    "addr:postcode":"4430",
    "addr:street":"Rue Walthe\u0300Re Jamar",
    "iso:country":"BE",
    "sg:address":"Rue Walth\u00c8re Jamar 113",
    "sg:city":"Ans",
    "sg:orig_category":"Entretien and r\u00e9parations de voitures",
    "sg:phone":"+32 4 225 15 94",
    "sg:postcode":"4430",
    "sg:province":"Li\u00e8ge",
    "wof:name":"Umberto Piazza",
    "wof:placetype":"venue"
},
  "geometry": {"coordinates":[5.5415320396,50.6519355774],"type":"Point"}
}