{
  "type": "Feature",
  "properties": {
    "iso:country":"BE",
    "sg:address":"D\u00b4haenestraat 3",
    "sg:city":"Destelbergen",
    "sg:orig_category":"Plaatsen van vloer- and muurbekleding Schilders",
    "sg:phone":"+32 9 252 46 48",
    "sg:postcode":"9070",
    "sg:province":"Oost-Vlaanderen",
    "wof:name":"A.s.d. Schilderwerken",
    "wof:placetype":"venue"
},
  "geometry": {"coordinates":[3.8083438873,51.0034103394],"type":"Point"}
}