{
  "type": "Feature",
  "properties": {
    "iso:country":"BE",
    "sg:address":"Rue De La Dr\u00c8ve 10",
    "sg:city":"Neupre",
    "sg:orig_category":"Herstelling horloges and juwelen",
    "sg:phone":"+32 4 371 39 36",
    "sg:postcode":"4121",
    "sg:province":"Li\u00e8ge",
    "wof:name":"L' Horlogerie Li\u00c9geoise",
    "wof:placetype":"venue"
},
  "geometry": {"coordinates":[5.4852070808,50.5446090698],"type":"Point"}
}