{
  "type": "Feature",
  "properties": {
    "addr:full":"Eikhof 12 Lint Antwerpen 2547",
    "addr:housenumber":"12",
    "addr:postcode":"2547",
    "addr:street":"Eikhof",
    "iso:country":"BE",
    "sg:address":"Eikhof 12",
    "sg:city":"Lint",
    "sg:orig_category":"D\u00e9m\u00e9nagements",
    "sg:phone":"+32 3 455 26 02",
    "sg:postcode":"2547",
    "sg:province":"Antwerpen",
    "wof:name":"Arn Beunen",
    "wof:placetype":"venue"
},
  "geometry": {"coordinates":[4.4910101891,51.1262397766],"type":"Point"}
}