{
  "type": "Feature",
  "properties": {
    "iso:country":"BE",
    "sg:address":"Grote Baan 56",
    "sg:city":"Lovendegem",
    "sg:orig_category":"Herstellingen and onderhoud van auto's Voertuigen",
    "sg:phone":"+32 9 372 44 99",
    "sg:postcode":"9920",
    "sg:province":"Oost-Vlaanderen",
    "wof:name":"Garage Crivaco",
    "wof:placetype":"venue"
},
  "geometry": {"coordinates":[3.6395509243,51.0969924927],"type":"Point"}
}