{
  "type": "Feature",
  "properties": {
    "addr:full":"Chauss\u00e9e D'alsemberg 385 Bruxelles (uccle) Bruxelles-Capitale 1180",
    "addr:housenumber":"385",
    "addr:postcode":"1180",
    "addr:street":"Chausse\u0301E D'Alsemberg",
    "iso:country":"BE",
    "sg:address":"Chauss\u00e9e D'alsemberg 385",
    "sg:city":"Bruxelles (uccle)",
    "sg:classifiers":[
        {
            "category":"Home & Garden",
            "subcategory":"Furniture",
            "type":"Retail Goods"
        }
    ],
    "sg:phone":"+32 2 347 28 86",
    "sg:postcode":"1180",
    "sg:province":"Bruxelles-Capitale",
    "sg:tags":[
        "bamboo",
        "cane",
        "wickerwork"
    ],
    "wof:name":"Verlinden (maison) Sprl",
    "wof:placetype":"venue"
},
  "geometry": {"coordinates":[4.3391962051,50.8147583008],"type":"Point"}
}