{
  "type": "Feature",
  "properties": {
    "iso:country":"BE",
    "sg:address":"Robert Schumanstraat 2a",
    "sg:city":"Tielt",
    "sg:classifiers":[
        {
            "category":"Health Services",
            "subcategory":"Doctor",
            "type":"Services"
        }
    ],
    "sg:phone":"+32 51 40 52 36",
    "sg:postcode":"8700",
    "sg:province":"West-Vlaanderen",
    "sg:tags":[
        "medicinephysicians",
        "surgeon"
    ],
    "wof:name":"Cuypers Hans",
    "wof:placetype":"venue"
},
  "geometry": {"coordinates":[3.3387110233,51.0003814697],"type":"Point"}
}