{
  "type": "Feature",
  "properties": {
    "addr:full":"Rue Provinciale 51bb Herstal Li\u00e8ge 4042",
    "addr:postcode":"4042",
    "addr:street":"Rue Provinciale 51Bb",
    "iso:country":"BE",
    "sg:address":"Rue Provinciale 51bb",
    "sg:city":"Herstal",
    "sg:orig_category":"Slagers",
    "sg:phone":"+32 4 278 51 19",
    "sg:postcode":"4042",
    "sg:province":"Li\u00e8ge",
    "wof:name":"J. Mathus",
    "wof:placetype":"venue"
},
  "geometry": {"coordinates":[5.5627551079,50.6930389404],"type":"Point"}
}