{
  "type": "Feature",
  "properties": {
    "addr:full":"R\u00e9sidence Des Agasses 73 Mons (fl\u00e9nu) Hainaut 7012",
    "addr:housenumber":"73",
    "addr:postcode":"7012",
    "addr:street":"Re\u0301Sidence Des Agasses",
    "iso:country":"BE",
    "sg:address":"R\u00e9sidence Des Agasses 73",
    "sg:city":"Mons (fl\u00e9nu)",
    "sg:classifiers":[
        {
            "category":"Personal",
            "subcategory":"Beauty Salon",
            "type":"Services"
        }
    ],
    "sg:phone":"+32 65 88 43 17",
    "sg:postcode":"7012",
    "sg:province":"Hainaut",
    "sg:tags":[
        "lady",
        "-",
        "hairdressing"
    ],
    "wof:name":"Sylvie Coiffure",
    "wof:placetype":"venue"
},
  "geometry": {"coordinates":[3.8894600868,50.4481964111],"type":"Point"}
}