{
  "type": "Feature",
  "properties": {
    "addr:full":"Akkerstraat 9-15 Temse Oost-Vlaanderen 9140",
    "addr:housenumber":"9-15",
    "addr:postcode":"9140",
    "addr:street":"Akkerstraat",
    "iso:country":"BE",
    "sg:address":"Akkerstraat 9-15",
    "sg:city":"Temse",
    "sg:orig_category":"Bagage and lederwaren Schoenen",
    "sg:phone":"+32 3 771 05 35",
    "sg:postcode":"9140",
    "sg:province":"Oost-Vlaanderen",
    "wof:name":"Peeters",
    "wof:placetype":"venue"
},
  "geometry": {"coordinates":[4.2139558792,51.1250305176],"type":"Point"}
}