{
  "type": "Feature",
  "properties": {
    "addr:full":"Sterrestraat 11 Koekelare West-Vlaanderen 8680",
    "addr:housenumber":"11",
    "addr:postcode":"8680",
    "addr:street":"Sterrestraat",
    "iso:country":"BE",
    "sg:address":"Sterrestraat 11",
    "sg:city":"Koekelare",
    "sg:orig_category":"S\u00e9curit\u00e9 sociale",
    "sg:phone":"+32 51 58 15 01",
    "sg:postcode":"8680",
    "sg:province":"West-Vlaanderen",
    "wof:name":"Socialistische Mutualiteit",
    "wof:placetype":"venue"
},
  "geometry": {"coordinates":[2.9731869698,51.088760376],"type":"Point"}
}