{
  "type": "Feature",
  "properties": {
    "addr:full":"Kouterweg 78 Izegem West-Vlaanderen 8870",
    "addr:housenumber":"78",
    "addr:postcode":"8870",
    "addr:street":"Kouterweg",
    "iso:country":"BE",
    "sg:address":"Kouterweg 78",
    "sg:city":"Izegem",
    "sg:classifiers":[
        {
            "category":"Personal",
            "subcategory":"Beauty Salon",
            "type":"Services"
        }
    ],
    "sg:phone":"+32 51 31 68 47",
    "sg:postcode":"8870",
    "sg:province":"West-Vlaanderen",
    "sg:tags":[
        "lady",
        "-",
        "hairdressing"
    ],
    "wof:name":"Avanti",
    "wof:placetype":"venue"
},
  "geometry": {"coordinates":[3.2217350006,50.9248886108],"type":"Point"}
}