{
  "type": "Feature",
  "properties": {
    "iso:country":"BE",
    "sg:address":"Avenue Reine Astrid 12",
    "sg:city":"Ottignies-louvain-la-neuve",
    "sg:orig_category":"Sportclubs",
    "sg:phone":"+32 10 41 12 21",
    "sg:postcode":"1340",
    "sg:province":"Brabant Wallon",
    "wof:name":"D.s.t Ottignies",
    "wof:placetype":"venue"
},
  "geometry": {"coordinates":[4.5700750351,50.6664543152],"type":"Point"}
}