{
  "type": "Feature",
  "properties": {
    "addr:full":"Steenweg 52 As Limburg 3665",
    "addr:housenumber":"52",
    "addr:postcode":"3665",
    "addr:street":"Steenweg",
    "iso:country":"BE",
    "sg:address":"Steenweg 52",
    "sg:city":"As",
    "sg:orig_category":"Brood, gebak and snoepgoed",
    "sg:phone":"+32 89 65 70 38",
    "sg:postcode":"3665",
    "sg:province":"Limburg",
    "wof:name":"Bakk. Scheepers-van Herck",
    "wof:placetype":"venue"
},
  "geometry": {"coordinates":[5.5777478218,51.0013046265],"type":"Point"}
}