{
  "type": "Feature",
  "properties": {
    "iso:country":"BE",
    "sg:address":"Rue Du Geer 5",
    "sg:city":"Oreye",
    "sg:orig_category":"Dierenartsen",
    "sg:phone":"+32 19 67 77 52",
    "sg:postcode":"4360",
    "sg:province":"Li\u00e8ge",
    "wof:name":"Alain Desiron",
    "wof:placetype":"venue"
},
  "geometry": {"coordinates":[5.3285598755,50.7179718018],"type":"Point"}
}