{
  "type": "Feature",
  "properties": {
    "iso:country":"BE",
    "sg:address":"Rue F\u00e9tis 9",
    "sg:city":"Dinant",
    "sg:classifiers":[
        {
            "category":"Autos & Motor Vehicles",
            "subcategory":"Auto Supplies",
            "type":"Retail Goods"
        }
    ],
    "sg:phone":"+32 82 22 55 90",
    "sg:postcode":"5500",
    "sg:province":"Namur",
    "sg:tags":[
        "automobile",
        "-",
        "radio"
    ],
    "wof:name":"Summum Car",
    "wof:placetype":"venue"
},
  "geometry": {"coordinates":[4.9033107758,50.2668609619],"type":"Point"}
}