{
  "type": "Feature",
  "properties": {
    "iso:country":"BE",
    "sg:address":"Beukendreef 9",
    "sg:city":"Zandhoven",
    "sg:orig_category":"Installation de menuiserie m\u00e9tallique. Installation de menuiserie en bois and plastique. Installatio",
    "sg:phone":"+32 3 484 62 11",
    "sg:postcode":"2243",
    "sg:province":"Antwerpen",
    "wof:name":"Alc Automatisatie",
    "wof:placetype":"venue"
},
  "geometry": {"coordinates":[4.6855788231,51.1971588135],"type":"Point"}
}