{
  "type": "Feature",
  "properties": {
    "iso:country":"BE",
    "sg:address":"Rue De Saupont 31",
    "sg:city":"Bertrix",
    "sg:classifiers":[
        {
            "category":"Social Services",
            "type":"Services"
        }
    ],
    "sg:phone":"+32 61 41 63 80",
    "sg:postcode":"6880",
    "sg:province":"Luxembourg",
    "wof:name":"Habitations Prot\u00e9g\u00e9es",
    "wof:placetype":"venue"
},
  "geometry": {"coordinates":[5.2696318626,49.8535995483],"type":"Point"}
}