{
  "type": "Feature",
  "properties": {
    "addr:full":"Zeelaan 261 Koksijde West-Vlaanderen 8670",
    "addr:housenumber":"261",
    "addr:postcode":"8670",
    "addr:street":"Zeelaan",
    "iso:country":"BE",
    "sg:address":"Zeelaan 261",
    "sg:city":"Koksijde",
    "sg:classifiers":[
        {
            "category":"Farming",
            "subcategory":"Fish & Marine Products",
            "type":"Manufacturing & Wholesale Goods"
        }
    ],
    "sg:phone":"+32 58 52 40 92",
    "sg:postcode":"8670",
    "sg:province":"West-Vlaanderen",
    "sg:tags":[
        "retail",
        "-",
        "shellfish"
    ],
    "wof:name":"Saumon D'or",
    "wof:placetype":"venue"
},
  "geometry": {"coordinates":[2.6367630959,51.117149353],"type":"Point"}
}