{
  "type": "Feature",
  "properties": {
    "iso:country":"BE",
    "sg:address":"Jan Frans Willemsstraat 63",
    "sg:city":"Lommel",
    "sg:orig_category":"Pain, p\u00e2tisseries and confiseries",
    "sg:phone":"+32 11 54 00 26",
    "sg:postcode":"3920",
    "sg:province":"Limburg",
    "wof:name":"'t Bakkerswinkeltje",
    "wof:placetype":"venue"
},
  "geometry": {"coordinates":[5.2820248604,51.2283287048],"type":"Point"}
}