{
  "type": "Feature",
  "properties": {
    "iso:country":"BE",
    "sg:address":"6687",
    "sg:city":"Bertogne",
    "sg:classifiers":[
        {
            "category":"Sports & Exercise",
            "subcategory":"Sports Center",
            "type":"Entertainment"
        }
    ],
    "sg:phone":"+32 61 21 34 83",
    "sg:postcode":"6687",
    "sg:province":"Luxembourg",
    "sg:tags":[
        "terrain",
        "hors",
        "de",
        "installation",
        "sportifs"
    ],
    "wof:name":"Piste les Montagnais",
    "wof:placetype":"venue"
},
  "geometry": {"coordinates":[5.6810898781,50.0912513733],"type":"Point"}
}