{
  "type": "Feature",
  "properties": {
    "iso:country":"BE",
    "sg:address":"Rue Maurice Burlet 7",
    "sg:city":"Pont-a-celles",
    "sg:orig_category":"Installation de menuiserie en bois and plastique",
    "sg:phone":"+32 71 84 29 35",
    "sg:postcode":"6238",
    "sg:province":"Hainaut",
    "wof:name":"Michel Tournay",
    "wof:placetype":"venue"
},
  "geometry": {"coordinates":[4.4248380661,50.5133399963],"type":"Point"}
}