{
  "type": "Feature",
  "properties": {
    "iso:country":"BE",
    "sg:address":"Diestersteenweg 77",
    "sg:city":"Leopoldsburg",
    "sg:classifiers":[
        {
            "category":"Education",
            "subcategory":"Special Training",
            "type":"Public Place"
        }
    ],
    "sg:phone":"+32 11 34 61 45",
    "sg:postcode":"3970",
    "sg:province":"Limburg",
    "sg:tags":[
        "professional"
    ],
    "wof:name":"C.b.o. De Poort",
    "wof:placetype":"venue"
},
  "geometry": {"coordinates":[5.2486510277,51.1143379211],"type":"Point"}
}