{
  "type": "Feature",
  "properties": {
    "iso:country":"BE",
    "sg:address":"Koetsiersweg 65",
    "sg:city":"Lubbeek (linden)",
    "sg:classifiers":[
        {
            "category":"Professional",
            "subcategory":"Art Services",
            "type":"Services"
        }
    ],
    "sg:phone":"+32 16 25 53 91",
    "sg:postcode":"3210",
    "sg:province":"Vlaams-Brabant",
    "sg:tags":[
        "graphic",
        "designer"
    ],
    "wof:name":"Did Decort Image Design",
    "wof:placetype":"venue"
},
  "geometry": {"coordinates":[4.7564902306,50.9006576538],"type":"Point"}
}