{
  "type": "Feature",
  "properties": {
    "iso:country":"BE",
    "sg:address":"Rue Des H\u00eatres 29",
    "sg:city":"Linkebeek",
    "sg:classifiers":[
        {
            "category":"Building & Trades",
            "subcategory":"Equipment Rental",
            "type":"Services"
        }
    ],
    "sg:phone":"+32 2 381 01 17",
    "sg:postcode":"1630",
    "sg:province":"Vlaams-Brabant",
    "sg:tags":[
        "sound",
        "-",
        "system"
    ],
    "wof:name":"Blinder",
    "wof:placetype":"venue"
},
  "geometry": {"coordinates":[4.3256959915,50.770866394],"type":"Point"}
}