{
  "type": "Feature",
  "properties": {
    "addr:full":"Rue De Namur 191 Ch\u00e2telet Hainaut 6200",
    "addr:housenumber":"191",
    "addr:postcode":"6200",
    "addr:street":"Rue De Namur",
    "iso:country":"BE",
    "sg:address":"Rue De Namur 191",
    "sg:city":"Ch\u00e2telet",
    "sg:classifiers":[
        {
            "category":"Retail",
            "subcategory":"Auto Repair",
            "type":"Services"
        }
    ],
    "sg:phone":"+32 71 38 17 11",
    "sg:postcode":"6200",
    "sg:province":"Hainaut",
    "sg:tags":[
        "garage"
    ],
    "wof:name":"Businaro E",
    "wof:placetype":"venue"
},
  "geometry": {"coordinates":[4.5369000435,50.3978462219],"type":"Point"}
}