{
  "type": "Feature",
  "properties": {
    "addr:full":"Winninglaan 3 Temse Oost-Vlaanderen 9140",
    "addr:housenumber":"3",
    "addr:postcode":"9140",
    "addr:street":"Winninglaan",
    "iso:country":"BE",
    "sg:address":"Winninglaan 3",
    "sg:city":"Temse",
    "sg:orig_category":"Catalogues de vente par correspondance",
    "sg:phone":"+32 3 710 82 01",
    "sg:postcode":"9140",
    "sg:province":"Oost-Vlaanderen",
    "wof:name":"D.m.d.",
    "wof:placetype":"venue"
},
  "geometry": {"coordinates":[4.1934452057,51.1354446411],"type":"Point"}
}