{
  "type": "Feature",
  "properties": {
    "iso:country":"BE",
    "sg:address":"Rue Des Arquebusiers 41",
    "sg:city":"Mons",
    "sg:classifiers":[
        {
            "category":"Building & Trades",
            "subcategory":"Electrical",
            "type":"Services"
        }
    ],
    "sg:phone":"+32 65 31 32 35",
    "sg:postcode":"7000",
    "sg:province":"Hainaut",
    "sg:tags":[
        "electric",
        "-",
        "housewiring",
        "contractor"
    ],
    "wof:name":"Rosi\u00e8re J.",
    "wof:placetype":"venue"
},
  "geometry": {"coordinates":[3.9501600266,50.447101593],"type":"Point"}
}