{
  "type": "Feature",
  "properties": {
    "iso:country":"BE",
    "sg:address":"Guldendelle 14",
    "sg:city":"Zaventem",
    "sg:orig_category":"Fruitteelt Groententeelt",
    "sg:phone":"+32 2 759 87 75",
    "sg:postcode":"1930",
    "sg:province":"Vlaams-Brabant",
    "wof:name":"Jean Wauters",
    "wof:placetype":"venue"
},
  "geometry": {"coordinates":[4.5095739365,50.8824806213],"type":"Point"}
}