{
  "type": "Feature",
  "properties": {
    "addr:full":"Battelsestw 455d Mechelen Antwerpen 2800",
    "addr:housenumber":"455d",
    "addr:postcode":"2800",
    "addr:street":"Battelsestw",
    "iso:country":"BE",
    "sg:address":"Battelsestw 455d",
    "sg:city":"Mechelen",
    "sg:classifiers":[
        {
            "category":"Manufacturing",
            "subcategory":"Chemicals & Compounds",
            "type":"Manufacturing & Wholesale Goods"
        }
    ],
    "sg:phone":"+32 15 28 67 67",
    "sg:postcode":"2800",
    "sg:province":"Antwerpen",
    "sg:tags":[
        "pharmaceutical",
        "chemistry",
        "-",
        "by-product"
    ],
    "wof:name":"Ashland Belgium Bvba",
    "wof:placetype":"venue"
},
  "geometry": {"coordinates":[4.450094223,51.0380706787],"type":"Point"}
}