{
  "type": "Feature",
  "properties": {
    "addr:full":"Rue Hom\u00e8re 24 Bruxelles (anderlecht) Bruxelles-Capitale 1070",
    "addr:housenumber":"24",
    "addr:postcode":"1070",
    "addr:street":"Rue Home\u0300Re",
    "iso:country":"BE",
    "sg:address":"Rue Hom\u00e8re 24",
    "sg:city":"Bruxelles (anderlecht)",
    "sg:classifiers":[
        {
            "category":"Personal",
            "subcategory":"Beauty Salon",
            "type":"Services"
        }
    ],
    "sg:phone":"+32 2 522 26 17",
    "sg:postcode":"1070",
    "sg:province":"Bruxelles-Capitale",
    "sg:tags":[
        "lady",
        "-",
        "hairdressing"
    ],
    "wof:name":"Hubert Micheline",
    "wof:placetype":"venue"
},
  "geometry": {"coordinates":[4.2869668007,50.8439254761],"type":"Point"}
}