{
  "type": "Feature",
  "properties": {
    "addr:full":"Place Du Martyr 21 Box 7 Verviers Li\u00e8ge 4800",
    "addr:housenumber":"21;7",
    "addr:postcode":"4800",
    "addr:street":"Place Du Martyr;Box",
    "iso:country":"BE",
    "sg:address":"Place Du Martyr 21 Box 7",
    "sg:city":"Verviers",
    "sg:classifiers":[
        {
            "category":"Real Estate",
            "subcategory":"Real Estate Services",
            "type":"Services"
        }
    ],
    "sg:phone":"+32 87 46 03 30",
    "sg:postcode":"4800",
    "sg:province":"Li\u00e8ge",
    "wof:name":"Phija",
    "wof:placetype":"venue"
},
  "geometry": {"coordinates":[5.8607740402,50.5931396484],"type":"Point"}
}