{
  "type": "Feature",
  "properties": {
    "addr:full":"Avenue Albert I 35 Fosses-la-ville Namur 5070",
    "addr:housenumber":"35",
    "addr:postcode":"5070",
    "addr:street":"Avenue Albert I",
    "iso:country":"BE",
    "sg:address":"Avenue Albert I 35",
    "sg:city":"Fosses-la-ville",
    "sg:classifiers":[
        {
            "category":"Professional",
            "subcategory":"Lawyer & Legal Services",
            "type":"Services"
        }
    ],
    "sg:phone":"+32 71 71 28 68",
    "sg:postcode":"5070",
    "sg:province":"Namur",
    "wof:name":"Crappe Caroline",
    "wof:placetype":"venue"
},
  "geometry": {"coordinates":[4.6922039986,50.3941421509],"type":"Point"}
}