{
  "type": "Feature",
  "properties": {
    "addr:full":"Place Du Nouveau March\u00e9 Aux Grains 24 Bruxelles Bruxelles-Capitale 1000",
    "addr:housenumber":"24",
    "addr:postcode":"1000",
    "addr:street":"Place Du Nouveau Marche\u0301 Aux Grains",
    "iso:country":"BE",
    "sg:address":"Place Du Nouveau March\u00e9 Aux Grains 24",
    "sg:city":"Bruxelles",
    "sg:classifiers":[
        {
            "category":"Education",
            "subcategory":"School",
            "type":"Public Place"
        }
    ],
    "sg:postcode":"1000",
    "sg:province":"Bruxelles-Capitale",
    "sg:tags":[
        "secondary"
    ],
    "wof:name":"Institut De Mot-couvreur",
    "wof:placetype":"venue"
},
  "geometry": {"coordinates":[4.3440790176,50.8504714966],"type":"Point"}
}