{
  "type": "Feature",
  "properties": {
    "addr:full":"Brogelerweg 117 Bocholt Limburg 3950",
    "addr:housenumber":"117",
    "addr:postcode":"3950",
    "addr:street":"Brogelerweg",
    "iso:country":"BE",
    "sg:address":"Brogelerweg 117",
    "sg:city":"Bocholt",
    "sg:classifiers":[
        {
            "category":"Animal Shelter",
            "type":"Public Place"
        }
    ],
    "sg:phone":"+32 89 47 13 40",
    "sg:postcode":"3950",
    "sg:province":"Limburg",
    "sg:tags":[
        "construction",
        "installation",
        "stable"
    ],
    "wof:name":"Hendrix R Bvba",
    "wof:placetype":"venue"
},
  "geometry": {"coordinates":[5.5535202026,51.1706161499],"type":"Point"}
}