{
  "type": "Feature",
  "properties": {
    "iso:country":"BE",
    "sg:address":"Papenbroekstraat 156",
    "sg:city":"Diest",
    "sg:classifiers":[
        {
            "category":"Food & Beverages",
            "subcategory":"Meat & Fish",
            "type":"Retail Goods"
        }
    ],
    "sg:phone":"+32 13 31 26 83",
    "sg:postcode":"3290",
    "sg:province":"Vlaams-Brabant",
    "sg:tags":[
        "vi",
        "zeevruchten"
    ],
    "wof:name":"Ingrid Collin",
    "wof:placetype":"venue"
},
  "geometry": {"coordinates":[5.0606198311,50.9738388062],"type":"Point"}
}