{
  "type": "Feature",
  "properties": {
    "addr:full":"Tisseltstraat 52 Kapelle-op-den-bos Vlaams-Brabant 1880",
    "addr:housenumber":"52",
    "addr:postcode":"1880",
    "addr:street":"Tisseltstraat",
    "iso:country":"BE",
    "sg:address":"Tisseltstraat 52",
    "sg:city":"Kapelle-op-den-bos",
    "sg:orig_category":"Herstellingen and onderhoud van auto's",
    "sg:phone":"+32 15 71 26 70",
    "sg:postcode":"1880",
    "sg:province":"Vlaams-Brabant",
    "wof:name":"Valere Van Praet",
    "wof:placetype":"venue"
},
  "geometry": {"coordinates":[4.3379979134,51.0212135315],"type":"Point"}
}