{
  "type": "Feature",
  "properties": {
    "iso:country":"BE",
    "sg:address":"Nieuwrodese Steenweg 113",
    "sg:city":"Aarschot",
    "sg:orig_category":"R\u00e9parations and entretien de motos. Motos",
    "sg:phone":"+32 16 56 67 93",
    "sg:postcode":"3200",
    "sg:province":"Vlaams-Brabant",
    "wof:name":"Dirk Steenwerckers",
    "wof:placetype":"venue"
},
  "geometry": {"coordinates":[4.8351597786,50.9700813293],"type":"Point"}
}