{
  "type": "Feature",
  "properties": {
    "iso:country":"BE",
    "sg:address":"Emiel Clauslaan 37",
    "sg:city":"Deinze",
    "sg:orig_category":"Antiquit\u00e9s",
    "sg:phone":"+32 9 386 99 09",
    "sg:postcode":"9800",
    "sg:province":"Oost-Vlaanderen",
    "wof:name":"Antiek De Kouter",
    "wof:placetype":"venue"
},
  "geometry": {"coordinates":[3.5274240971,50.9844474792],"type":"Point"}
}