{
  "type": "Feature",
  "properties": {
    "addr:full":"Avenue Van Crombrugghe 82 Bruxelles (woluwe-saint-pierre) Bruxelles-Capitale 1150",
    "addr:housenumber":"82",
    "addr:postcode":"1150",
    "addr:street":"Avenue Van Crombrugghe",
    "iso:country":"BE",
    "sg:address":"Avenue Van Crombrugghe 82",
    "sg:city":"Bruxelles (woluwe-saint-pierre)",
    "sg:classifiers":[
        {
            "category":"Professional",
            "subcategory":"Management & Consulting",
            "type":"Services"
        }
    ],
    "sg:phone":"+32 2 771 00 06",
    "sg:postcode":"1150",
    "sg:province":"Bruxelles-Capitale",
    "sg:tags":[
        "tax-consultants"
    ],
    "wof:name":"Tributum Soci\u00e9t\u00e9 Professionnelle De Conseils Fiscaux",
    "wof:placetype":"venue"
},
  "geometry": {"coordinates":[4.4598751068,50.828163147],"type":"Point"}
}