{
  "type": "Feature",
  "properties": {
    "addr:full":"Rue Jolly 141 Bruxelles (schaerbeek) Bruxelles-Capitale 1030",
    "addr:housenumber":"141",
    "addr:postcode":"1030",
    "addr:street":"Rue Jolly",
    "iso:country":"BE",
    "sg:address":"Rue Jolly 141",
    "sg:city":"Bruxelles (schaerbeek)",
    "sg:classifiers":[
        {
            "category":"Real Estate",
            "subcategory":"Real Estate Services",
            "type":"Services"
        }
    ],
    "sg:phone":"+32 2 201 00 02",
    "sg:postcode":"1030",
    "sg:province":"Bruxelles-Capitale",
    "wof:name":"Groep Coenen Businessflats",
    "wof:placetype":"venue"
},
  "geometry": {"coordinates":[4.3605332375,50.8663825989],"type":"Point"}
}