{
  "type": "Feature",
  "properties": {
    "iso:country":"BE",
    "sg:address":"Van De Wervelaan 38",
    "sg:city":"Schilde",
    "sg:orig_category":"Agences maritimes",
    "sg:phone":"+32 3 384 12 28",
    "sg:postcode":"2970",
    "sg:province":"Antwerpen",
    "wof:name":"Etienne Van Rooy",
    "wof:placetype":"venue"
},
  "geometry": {"coordinates":[4.5768499374,51.23487854],"type":"Point"}
}