{
  "type": "Feature",
  "properties": {
    "iso:country":"BE",
    "sg:address":"Rue Am\u00c9ricaine 95",
    "sg:city":"Elsene",
    "sg:orig_category":"Agences d'exp\u00e9dition",
    "sg:phone":"+32 2 648 21 91",
    "sg:postcode":"1050",
    "sg:province":"Bruxelles-Capitale",
    "wof:name":"Sagd",
    "wof:placetype":"venue"
},
  "geometry": {"coordinates":[4.3591928482,50.8230400085],"type":"Point"}
}