{
  "type": "Feature",
  "properties": {
    "iso:country":"BE",
    "sg:address":"Gijmelsesteenweg 417",
    "sg:city":"Aarschot",
    "sg:orig_category":"Benzinestations and brandstoffen HUISBRANDOLIE",
    "sg:phone":"+32 16 56 18 85",
    "sg:postcode":"3201",
    "sg:province":"Vlaams-Brabant",
    "wof:name":"Fa. Schoovaerts",
    "wof:placetype":"venue"
},
  "geometry": {"coordinates":[4.8683137894,51.0120353699],"type":"Point"}
}