{
  "type": "Feature",
  "properties": {
    "addr:full":"Draaiweg 14 Kortrijk (aalbeke) West-Vlaanderen 8511",
    "addr:housenumber":"14",
    "addr:postcode":"8511",
    "addr:street":"Draaiweg",
    "iso:country":"BE",
    "sg:address":"Draaiweg 14",
    "sg:city":"Kortrijk (aalbeke)",
    "sg:classifiers":[
        {
            "category":"Communications",
            "type":"Services"
        }
    ],
    "sg:phone":"+32 56 40 34 87",
    "sg:postcode":"8511",
    "sg:province":"West-Vlaanderen",
    "sg:tags":[
        "translator"
    ],
    "wof:name":"Accent",
    "wof:placetype":"venue"
},
  "geometry": {"coordinates":[3.23508811,50.7710266113],"type":"Point"}
}