{
  "type": "Feature",
  "properties": {
    "addr:full":"Bollestraat 49 Hooglede (gits) West-Vlaanderen 8830",
    "addr:housenumber":"49",
    "addr:postcode":"8830",
    "addr:street":"Bollestraat",
    "iso:country":"BE",
    "sg:address":"Bollestraat 49",
    "sg:city":"Hooglede (gits)",
    "sg:classifiers":[
        {
            "category":"Food & Beverages",
            "subcategory":"Groceries & Convenience Stores",
            "type":"Retail Goods"
        }
    ],
    "sg:phone":"+32 51 24 23 25",
    "sg:postcode":"8830",
    "sg:province":"West-Vlaanderen",
    "sg:tags":[
        "baker",
        "-",
        "ingredient"
    ],
    "wof:name":"Deli-deco Bvba",
    "wof:placetype":"venue"
},
  "geometry": {"coordinates":[3.1199090481,50.9829216003],"type":"Point"}
}