{
  "type": "Feature",
  "properties": {
    "iso:country":"BE",
    "sg:address":"Industriepark 43",
    "sg:city":"Beernem",
    "sg:classifiers":[
        {
            "category":"Professional",
            "subcategory":"Accounting & Tax Preparation",
            "type":"Services"
        }
    ],
    "sg:phone":"+32 50 79 14 89",
    "sg:postcode":"8730",
    "sg:province":"West-Vlaanderen",
    "sg:tags":[
        "bookkeeper"
    ],
    "wof:name":"Van Den Bulke K",
    "wof:placetype":"venue"
},
  "geometry": {"coordinates":[3.3465409279,51.1245689392],"type":"Point"}
}