{
  "type": "Feature",
  "properties": {
    "addr:full":"Kolonel Dusartplein 21 Hasselt Limburg 3500",
    "addr:housenumber":"21",
    "addr:postcode":"3500",
    "addr:street":"Kolonel Dusartplein",
    "iso:country":"BE",
    "sg:address":"Kolonel Dusartplein 21",
    "sg:city":"Hasselt",
    "sg:classifiers":[
        {
            "category":"Real Estate",
            "subcategory":"Real Estate Services",
            "type":"Services"
        }
    ],
    "sg:phone":"+32 11 27 35 20",
    "sg:postcode":"3500",
    "sg:province":"Limburg",
    "wof:name":"Vdv-van Der Veken Nv",
    "wof:placetype":"venue"
},
  "geometry": {"coordinates":[5.3447508812,50.9314575195],"type":"Point"}
}