{
  "type": "Feature",
  "properties": {
    "addr:full":"Knokkestraat 33 Lokeren Oost-Vlaanderen 9160",
    "addr:housenumber":"33",
    "addr:postcode":"9160",
    "addr:street":"Knokkestraat",
    "iso:country":"BE",
    "sg:address":"Knokkestraat 33",
    "sg:city":"Lokeren",
    "sg:classifiers":[
        {
            "category":"Professional",
            "subcategory":"Lawyer & Legal Services",
            "type":"Services"
        }
    ],
    "sg:phone":"+32 9 348 41 26",
    "sg:postcode":"9160",
    "sg:province":"Oost-Vlaanderen",
    "wof:name":"Haentjens J",
    "wof:placetype":"venue"
},
  "geometry": {"coordinates":[3.9956729412,51.1037139893],"type":"Point"}
}