{
  "type": "Feature",
  "properties": {
    "iso:country":"BE",
    "sg:address":"Rue Du Montys 25a",
    "sg:city":"Tinlot (soheit-tinlot)",
    "sg:classifiers":[
        {
            "category":"Structure",
            "subcategory":"Building",
            "type":"Public Place"
        }
    ],
    "sg:phone":"+32 85 51 16 93",
    "sg:postcode":"4557",
    "sg:province":"Li\u00e8ge",
    "sg:tags":[
        "door"
    ],
    "wof:name":"Demoitie G",
    "wof:placetype":"venue"
},
  "geometry": {"coordinates":[5.3869037628,50.4721298218],"type":"Point"}
}