{
  "type": "Feature",
  "properties": {
    "addr:full":"Kleine Pathoekeweg 51 Brugge West-Vlaanderen 8000",
    "addr:housenumber":"51",
    "addr:postcode":"8000",
    "addr:street":"Kleine Pathoekeweg",
    "iso:country":"BE",
    "sg:address":"Kleine Pathoekeweg 51",
    "sg:city":"Brugge",
    "sg:orig_category":"Recyclage de mati\u00e8res non m\u00e9talliques. Ramassage and traitement des d\u00e9chets m\u00e9nagers",
    "sg:phone":"+32 50 31 47 88",
    "sg:postcode":"8000",
    "sg:province":"West-Vlaanderen",
    "wof:name":"Watco West",
    "wof:placetype":"venue"
},
  "geometry": {"coordinates":[3.2089130878,51.2493743896],"type":"Point"}
}