{
  "type": "Feature",
  "properties": {
    "addr:full":"Stationsstraat 10 Eeklo Oost-Vlaanderen 9900",
    "addr:housenumber":"10",
    "addr:postcode":"9900",
    "addr:street":"Stationsstraat",
    "iso:country":"BE",
    "sg:address":"Stationsstraat 10",
    "sg:city":"Eeklo",
    "sg:classifiers":[
        {
            "category":"Real Estate",
            "subcategory":"Real Estate Services",
            "type":"Services"
        }
    ],
    "sg:phone":"+32 9 377 23 40",
    "sg:postcode":"9900",
    "sg:province":"Oost-Vlaanderen",
    "wof:name":"Clincke",
    "wof:placetype":"venue"
},
  "geometry": {"coordinates":[3.5734839439,51.1815032959],"type":"Point"}
}