{
  "type": "Feature",
  "properties": {
    "addr:full":"Rue Basse Voie 44 Verviers (stembert) Li\u00e8ge 4801",
    "addr:housenumber":"44",
    "addr:postcode":"4801",
    "addr:street":"Rue Basse Voie",
    "iso:country":"BE",
    "sg:address":"Rue Basse Voie 44",
    "sg:city":"Verviers (stembert)",
    "sg:classifiers":[
        {
            "category":"Building & Trades",
            "subcategory":"Plumbing",
            "type":"Services"
        }
    ],
    "sg:phone":"+32 87 22 62 72",
    "sg:postcode":"4801",
    "sg:province":"Li\u00e8ge",
    "sg:tags":[
        "contractor"
    ],
    "wof:name":"Hennen G",
    "wof:placetype":"venue"
},
  "geometry": {"coordinates":[5.8997402191,50.5801849365],"type":"Point"}
}