{
  "type": "Feature",
  "properties": {
    "iso:country":"BE",
    "sg:address":"Rue Roi Albert 72",
    "sg:city":"Seraing",
    "sg:orig_category":"Charpentes and menuiseries Fab. Installation de menuiserie en bois and plastique",
    "sg:phone":"+32 4 337 20 01",
    "sg:postcode":"4102",
    "sg:province":"Li\u00e8ge",
    "wof:name":"Maurits Christiaens",
    "wof:placetype":"venue"
},
  "geometry": {"coordinates":[5.5369801521,50.6004142761],"type":"Point"}
}