{
  "type": "Feature",
  "properties": {
    "addr:full":"Groenstraat 135 Boutersem Vlaams-Brabant 3370",
    "addr:housenumber":"135",
    "addr:postcode":"3370",
    "addr:street":"Groenstraat",
    "iso:country":"BE",
    "sg:address":"Groenstraat 135",
    "sg:city":"Boutersem",
    "sg:orig_category":"Epiceries",
    "sg:phone":"+32 16 73 33 23",
    "sg:postcode":"3370",
    "sg:province":"Vlaams-Brabant",
    "wof:name":"F. Francois",
    "wof:placetype":"venue"
},
  "geometry": {"coordinates":[4.8624968529,50.8369636536],"type":"Point"}
}