{
  "type": "Feature",
  "properties": {
    "addr:full":"Gentseweg 625 Waregem West-Vlaanderen 8790",
    "addr:housenumber":"625",
    "addr:postcode":"8790",
    "addr:street":"Gentseweg",
    "iso:country":"BE",
    "sg:address":"Gentseweg 625",
    "sg:city":"Waregem",
    "sg:orig_category":"Grands magasins",
    "sg:phone":"+32 14382",
    "sg:postcode":"8790",
    "sg:province":"West-Vlaanderen",
    "wof:name":"Lidl",
    "wof:placetype":"venue"
},
  "geometry": {"coordinates":[3.4046909809,50.9011917114],"type":"Point"}
}