{
  "type": "Feature",
  "properties": {
    "addr:full":"Faubourg-saint-germain 87 Couvin Namur 5660",
    "addr:housenumber":"87",
    "addr:postcode":"5660",
    "addr:street":"Faubourg-Saint-Germain",
    "iso:country":"BE",
    "sg:address":"Faubourg-saint-germain 87",
    "sg:city":"Couvin",
    "sg:orig_category":"Boekhouders",
    "sg:phone":"+32 60 34 54 43",
    "sg:postcode":"5660",
    "sg:province":"Namur",
    "wof:name":"Margaret Migalska",
    "wof:placetype":"venue"
},
  "geometry": {"coordinates":[4.493929863,50.0523834229],"type":"Point"}
}