{
  "type": "Feature",
  "properties": {
    "iso:country":"BE",
    "sg:address":"Koekamerstraat 50",
    "sg:city":"Maarkedal",
    "sg:orig_category":"Eleveurs de bovins",
    "sg:phone":"+32 55 21 20 09",
    "sg:postcode":"9688",
    "sg:province":"Oost-Vlaanderen",
    "wof:name":"Devriendt R. & B.",
    "wof:placetype":"venue"
},
  "geometry": {"coordinates":[3.6697239876,50.7719116211],"type":"Point"}
}