{
  "type": "Feature",
  "properties": {
    "iso:country":"BE",
    "sg:address":"Derbystraat 243",
    "sg:city":"Gent (sint-denijs-westrem - Afsnee)",
    "sg:classifiers":[
        {
            "category":"Communications",
            "subcategory":"News Services",
            "type":"Services"
        }
    ],
    "sg:phone":"+32 9 242 84 40",
    "sg:postcode":"9051",
    "sg:province":"Oost-Vlaanderen",
    "sg:tags":[
        "illustrator"
    ],
    "wof:name":"Sgs Documentation Services",
    "wof:placetype":"venue"
},
  "geometry": {"coordinates":[3.6973369122,51.0233650208],"type":"Point"}
}