{
  "type": "Feature",
  "properties": {
    "iso:country":"BE",
    "sg:address":"Rue De Longchamps 3",
    "sg:city":"Gedinne",
    "sg:orig_category":"Eleveurs de bovins",
    "sg:phone":"+32 61 58 70 85",
    "sg:postcode":"5575",
    "sg:province":"Namur",
    "wof:name":"Leopold Baijot",
    "wof:placetype":"venue"
},
  "geometry": {"coordinates":[4.9097981453,49.9356002808],"type":"Point"}
}