{
  "type": "Feature",
  "properties": {
    "iso:country":"BE",
    "sg:address":"Reepstraat 148",
    "sg:city":"Sint-gillis-waas",
    "sg:orig_category":"Gespecialiseerde residenti\u00eble bouw",
    "sg:phone":"+32 3 707 09 18",
    "sg:postcode":"9170",
    "sg:province":"Oost-Vlaanderen",
    "wof:name":"Chapewerken Badas",
    "wof:placetype":"venue"
},
  "geometry": {"coordinates":[4.1000127792,51.2273406982],"type":"Point"}
}