{
  "type": "Feature",
  "properties": {
    "addr:full":"Rue Oscar Genot 50 Namur Namur 5020",
    "addr:housenumber":"50",
    "addr:postcode":"5020",
    "addr:street":"Rue Oscar Genot",
    "iso:country":"BE",
    "sg:address":"Rue Oscar Genot 50",
    "sg:city":"Namur",
    "sg:orig_category":"Ordinateurs and \u00e9quipement informatique",
    "sg:phone":"+32 81 73 70 28",
    "sg:postcode":"5020",
    "sg:province":"Namur",
    "wof:name":"Flag 2000",
    "wof:placetype":"venue"
},
  "geometry": {"coordinates":[4.8254971504,50.4563331604],"type":"Point"}
}