{
  "type": "Feature",
  "properties": {
    "iso:country":"BE",
    "sg:address":"Rue De Namur 11",
    "sg:city":"Nivelles",
    "sg:classifiers":[
        {
            "category":"Professional",
            "subcategory":"Art Services",
            "type":"Services"
        }
    ],
    "sg:phone":"+32 67 22 19 16",
    "sg:postcode":"1400",
    "sg:province":"Brabant Wallon",
    "sg:tags":[
        "photographer"
    ],
    "wof:name":"Action Shop Telecom",
    "wof:placetype":"venue"
},
  "geometry": {"coordinates":[4.325135231,50.5980453491],"type":"Point"}
}