{
  "type": "Feature",
  "properties": {
    "iso:country":"BE",
    "sg:address":"Rozendaalstraat 3",
    "sg:city":"Ieper",
    "sg:classifiers":[
        {
            "category":"Airport",
            "subcategory":"International",
            "type":"Transportation"
        }
    ],
    "sg:phone":"+32 57 20 08 71",
    "sg:postcode":"8900",
    "sg:province":"West-Vlaanderen",
    "sg:tags":[
        "-",
        "transport"
    ],
    "wof:name":"Lemahieu H",
    "wof:placetype":"venue"
},
  "geometry": {"coordinates":[2.8831319809,50.8745422363],"type":"Point"}
}