{
  "type": "Feature",
  "properties": {
    "iso:country":"BE",
    "sg:address":"Rue Pr\u00c9 D'awans 4",
    "sg:city":"Vise",
    "sg:classifiers":[
        {
            "category":"Cafe",
            "type":"Food & Drink"
        }
    ],
    "sg:phone":"+32 4 379 68 00",
    "sg:postcode":"4601",
    "sg:province":"Li\u00e8ge",
    "sg:tags":[
        "caf\u00e9s"
    ],
    "wof:name":"Caf\u00c9 Pourquoi Pas",
    "wof:placetype":"venue"
},
  "geometry": {"coordinates":[5.6820588112,50.7034683228],"type":"Point"}
}