{
  "type": "Feature",
  "properties": {
    "iso:country":"BE",
    "sg:address":"Vieux-chemin-de-jupille 29",
    "sg:city":"Beyne-heusay",
    "sg:orig_category":"Installation de menuiserie m\u00e9tallique",
    "sg:phone":"+32 4 358 10 02",
    "sg:postcode":"4610",
    "sg:province":"Li\u00e8ge",
    "wof:name":"L.p.r.",
    "wof:placetype":"venue"
},
  "geometry": {"coordinates":[5.6523370743,50.6240844727],"type":"Point"}
}