{
  "type": "Feature",
  "properties": {
    "iso:country":"BE",
    "sg:address":"Woestendorp 45",
    "sg:city":"Vleteren",
    "sg:orig_category":"Banken and kredietinstellingen",
    "sg:phone":"+32 57 42 21 82",
    "sg:postcode":"8640",
    "sg:province":"West-Vlaanderen",
    "wof:name":"Landbouwkrediet",
    "wof:placetype":"venue"
},
  "geometry": {"coordinates":[2.7882969379,50.9014053345],"type":"Point"}
}