{
  "type": "Feature",
  "properties": {
    "addr:full":"Quai Des Mat\u00e9riaux 13 Bruxelles Bruxelles-Capitale 1000",
    "addr:housenumber":"13",
    "addr:postcode":"1000",
    "addr:street":"Quai Des Mate\u0301Riaux",
    "iso:country":"BE",
    "sg:address":"Quai Des Mat\u00e9riaux 13",
    "sg:city":"Bruxelles",
    "sg:classifiers":[
        {
            "category":"Manufacturing",
            "subcategory":"Printing",
            "type":"Manufacturing & Wholesale Goods"
        }
    ],
    "sg:phone":"+32 2 426 22 00",
    "sg:postcode":"1000",
    "sg:province":"Bruxelles-Capitale",
    "sg:tags":[
        "paper",
        "waste"
    ],
    "wof:name":"Gerec-gemat",
    "wof:placetype":"venue"
},
  "geometry": {"coordinates":[4.3509712219,50.8645248413],"type":"Point"}
}