{
  "type": "Feature",
  "properties": {
    "addr:full":"Gistelsteenweg 140 Jabbeke West-Vlaanderen 8490",
    "addr:housenumber":"140",
    "addr:postcode":"8490",
    "addr:street":"Gistelsteenweg",
    "iso:country":"BE",
    "sg:address":"Gistelsteenweg 140",
    "sg:city":"Jabbeke",
    "sg:orig_category":"Herstellingswinkels voor diverse persoonlijke and huishoudartikelen Wasserijen, Reiniging and Droogk",
    "sg:phone":"+32 50 39 10 18",
    "sg:postcode":"8490",
    "sg:province":"West-Vlaanderen",
    "wof:name":"Decoster P.",
    "wof:placetype":"venue"
},
  "geometry": {"coordinates":[3.1105320454,51.1793174744],"type":"Point"}
}