{
  "type": "Feature",
  "properties": {
    "iso:country":"BE",
    "sg:address":"Rue Du Pont 5",
    "sg:city":"Anhee",
    "sg:orig_category":"Jardinage",
    "sg:phone":"+32 82 61 20 29",
    "sg:postcode":"5537",
    "sg:province":"Namur",
    "wof:name":"Etienne Jaumot",
    "wof:placetype":"venue"
},
  "geometry": {"coordinates":[4.8940820694,50.302154541],"type":"Point"}
}