{
  "type": "Feature",
  "properties": {
    "iso:country":"BE",
    "sg:address":"Rue De La Mazerine 41",
    "sg:city":"La Hulpe",
    "sg:classifiers":[
        {
            "category":"Professional",
            "subcategory":"Lawyer & Legal Services",
            "type":"Services"
        }
    ],
    "sg:phone":"+32 2 652 46 31",
    "sg:postcode":"1310",
    "sg:province":"Brabant Wallon",
    "wof:name":"Delcroix Pol",
    "wof:placetype":"venue"
},
  "geometry": {"coordinates":[4.4924879074,50.7307701111],"type":"Point"}
}