{
  "type": "Feature",
  "properties": {
    "addr:full":"Stationstraat 19 Sint-gillis-waas Oost-Vlaanderen 9170",
    "addr:housenumber":"19",
    "addr:postcode":"9170",
    "addr:street":"Stationstraat",
    "iso:country":"BE",
    "sg:address":"Stationstraat 19",
    "sg:city":"Sint-gillis-waas",
    "sg:orig_category":"Chaussures. Maroquinerie and articles de voyage",
    "sg:phone":"+32 3 707 19 33",
    "sg:postcode":"9170",
    "sg:province":"Oost-Vlaanderen",
    "wof:name":"Brantano",
    "wof:placetype":"venue"
},
  "geometry": {"coordinates":[4.121737957,51.2193908691],"type":"Point"}
}