{
  "type": "Feature",
  "properties": {
    "addr:full":"6560 Erquelinnes (groot) Hainaut 6560",
    "addr:postcode":"6560;6560",
    "addr:street":"Groot Hainaut",
    "iso:country":"BE",
    "sg:address":"6560",
    "sg:city":"Erquelinnes (groot)",
    "sg:orig_category":"Pharmaciens",
    "sg:phone":"+32 900 10 500",
    "sg:postcode":"6560",
    "sg:province":"Hainaut",
    "wof:name":"Pharmacies De Garde",
    "wof:placetype":"venue"
},
  "geometry": {"coordinates":[4.1253848076,50.3106536865],"type":"Point"}
}