{
  "type": "Feature",
  "properties": {
    "addr:full":"Tamme Kastanjebomenlaan 14 Moeskroen/mouscron Hainaut 7711",
    "addr:housenumber":"14",
    "addr:postcode":"7711",
    "addr:street":"Tamme Kastanjebomenlaan",
    "iso:country":"BE",
    "sg:address":"Tamme Kastanjebomenlaan 14",
    "sg:city":"Moeskroen/mouscron",
    "sg:orig_category":"Artsen and specialisten",
    "sg:phone":"+32 56 48 72 75",
    "sg:postcode":"7711",
    "sg:province":"Hainaut",
    "wof:name":"P. Vandestrate",
    "wof:placetype":"venue"
},
  "geometry": {"coordinates":[3.2672290802,50.7371482849],"type":"Point"}
}