{
  "type": "Feature",
  "properties": {
    "addr:full":"Herentalsebaan 41 Ranst Antwerpen 2520",
    "addr:housenumber":"41",
    "addr:postcode":"2520",
    "addr:street":"Herentalsebaan",
    "iso:country":"BE",
    "sg:address":"Herentalsebaan 41",
    "sg:city":"Ranst",
    "sg:classifiers":[
        {
            "category":"Home & Garden",
            "subcategory":"Home Furnishings",
            "type":"Retail Goods"
        }
    ],
    "sg:phone":"+32 3 475 01 40",
    "sg:postcode":"2520",
    "sg:province":"Antwerpen",
    "sg:tags":[
        "interior",
        "decoration"
    ],
    "wof:name":"Grenen Atelier ('t)",
    "wof:placetype":"venue"
},
  "geometry": {"coordinates":[4.5479540825,51.1841545105],"type":"Point"}
}