{
  "type": "Feature",
  "properties": {
    "iso:country":"BE",
    "sg:address":"Luikerveld 61",
    "sg:city":"Sint-lievens-houtem",
    "sg:orig_category":"Woningbouw",
    "sg:phone":"+32 53 62 41 42",
    "sg:postcode":"9520",
    "sg:province":"Oost-Vlaanderen",
    "wof:name":"Neuten",
    "wof:placetype":"venue"
},
  "geometry": {"coordinates":[3.9039459229,50.9420814514],"type":"Point"}
}