{
  "type": "Feature",
  "properties": {
    "iso:country":"BE",
    "sg:address":"Schippersweg 19",
    "sg:city":"Hombeek",
    "sg:classifiers":[
        {
            "category":"Manufacturing",
            "subcategory":"Rubber & Plastics",
            "type":"Manufacturing & Wholesale Goods"
        }
    ],
    "sg:phone":"+32 15 41 60 60",
    "sg:postcode":"2811",
    "sg:province":"Antwerpen",
    "wof:name":"Wase Autobanden Service Nv",
    "wof:placetype":"venue"
},
  "geometry": {"coordinates":[4.4367799759,51.0136795044],"type":"Point"}
}