{
  "type": "Feature",
  "properties": {
    "addr:full":"Rue Grand'ville 5 Verviers (ensival) Li\u00e8ge 4800",
    "addr:housenumber":"5",
    "addr:postcode":"4800",
    "addr:street":"Rue Grand'Ville",
    "iso:country":"BE",
    "sg:address":"Rue Grand'ville 5",
    "sg:city":"Verviers (ensival)",
    "sg:classifiers":[
        {
            "category":"Health Services",
            "subcategory":"Health Practitioner",
            "type":"Services"
        }
    ],
    "sg:phone":"+32 87 46 25 35",
    "sg:postcode":"4800",
    "sg:province":"Li\u00e8ge",
    "sg:tags":[
        "physiotherapist"
    ],
    "wof:name":"Hannon Pascal",
    "wof:placetype":"venue"
},
  "geometry": {"coordinates":[5.842634201,50.5815086365],"type":"Point"}
}