{
  "type": "Feature",
  "properties": {
    "iso:country":"BE",
    "sg:address":"Diebeke 7",
    "sg:city":"Geraardsbergen",
    "sg:classifiers":[
        {
            "category":"Health Services",
            "subcategory":"Medical Lab",
            "type":"Services"
        }
    ],
    "sg:phone":"+32 64 22 13 29",
    "sg:postcode":"9500",
    "sg:province":"Oost-Vlaanderen",
    "sg:tags":[
        "chemical",
        "pharmaceutical",
        "pharmacy"
    ],
    "wof:name":"Office Tarification Moyenne Belgique",
    "wof:placetype":"venue"
},
  "geometry": {"coordinates":[4.1868062019,50.4790725708],"type":"Point"}
}