{
  "type": "Feature",
  "properties": {
    "iso:country":"BE",
    "sg:address":"Rue De Nicoles 12bd",
    "sg:city":"Boussu",
    "sg:orig_category":"Elektrische installaties voor woningen",
    "sg:phone":"+32 65 77 97 56",
    "sg:postcode":"7301",
    "sg:province":"Hainaut",
    "wof:name":"I.p.e.l.",
    "wof:placetype":"venue"
},
  "geometry": {"coordinates":[3.8257451057,50.4362258911],"type":"Point"}
}