{
  "type": "Feature",
  "properties": {
    "addr:full":"Gentsesteenweg 285 Aalst Oost-Vlaanderen 9300",
    "addr:housenumber":"285",
    "addr:postcode":"9300",
    "addr:street":"Gentsesteenweg",
    "iso:country":"BE",
    "sg:address":"Gentsesteenweg 285",
    "sg:city":"Aalst",
    "sg:orig_category":"Journaux. Stations-service and carburants",
    "sg:phone":"+32 53 21 26 16",
    "sg:postcode":"9300",
    "sg:province":"Oost-Vlaanderen",
    "wof:name":"Esso",
    "wof:placetype":"venue"
},
  "geometry": {"coordinates":[4.0049591064,50.9413070679],"type":"Point"}
}