{
  "type": "Feature",
  "properties": {
    "iso:country":"BE",
    "sg:address":"Wolvenhofstraat 4",
    "sg:city":"Izegem",
    "sg:orig_category":"Pluimveekwekers",
    "sg:phone":"+32 51 30 19 85",
    "sg:postcode":"8870",
    "sg:province":"West-Vlaanderen",
    "wof:name":"Danny Vandevelde",
    "wof:placetype":"venue"
},
  "geometry": {"coordinates":[3.1904931068,50.9053230286],"type":"Point"}
}