{
  "type": "Feature",
  "properties": {
    "addr:full":"De Korenbloem 51 Laakdal Antwerpen 2430",
    "addr:housenumber":"51",
    "addr:postcode":"2430",
    "addr:street":"De Korenbloem",
    "iso:country":"BE",
    "sg:address":"De Korenbloem 51",
    "sg:city":"Laakdal",
    "sg:classifiers":[
        {
            "category":"Personal",
            "subcategory":"Beauty Salon",
            "type":"Services"
        }
    ],
    "sg:phone":"+32 13 66 33 63",
    "sg:postcode":"2430",
    "sg:province":"Antwerpen",
    "sg:tags":[
        "de",
        "coiffure"
    ],
    "wof:name":"Jozef Buntjens",
    "wof:placetype":"venue"
},
  "geometry": {"coordinates":[5.0267047882,51.0820236206],"type":"Point"}
}