{
  "type": "Feature",
  "properties": {
    "addr:full":"Prattenborgplein 28 Scherpenheuvel-zichem (scherpenheuvel) Vlaams-Brabant 3270",
    "addr:housenumber":"28",
    "addr:postcode":"3270",
    "addr:street":"Prattenborgplein",
    "iso:country":"BE",
    "sg:address":"Prattenborgplein 28",
    "sg:city":"Scherpenheuvel-zichem (scherpenheuvel)",
    "sg:classifiers":[
        {
            "category":"Banks & Credit Unions",
            "subcategory":"Investment Brokerage",
            "type":"Services"
        }
    ],
    "sg:phone":"+32 13 77 53 63",
    "sg:postcode":"3270",
    "sg:province":"Vlaams-Brabant",
    "sg:tags":[
        "printing",
        "-"
    ],
    "wof:name":"Studio Print",
    "wof:placetype":"venue"
},
  "geometry": {"coordinates":[4.9784708023,50.9784164429],"type":"Point"}
}