{
  "type": "Feature",
  "properties": {
    "iso:country":"BE",
    "sg:address":"Amb. Zone De Waerde 2073",
    "sg:city":"Zonhoven",
    "sg:orig_category":"Immobili\u00ebnkantoren Industri\u00eble and commerci\u00eble bouw Installatie van houten of kunststof schrijnwerk ",
    "sg:phone":"+32 11 81 43 92",
    "sg:postcode":"3520",
    "sg:province":"Limburg",
    "wof:name":"Welkenhuyzen-bielen",
    "wof:placetype":"venue"
},
  "geometry": {"coordinates":[5.3849549294,51.00182724],"type":"Point"}
}