{
  "type": "Feature",
  "properties": {
    "addr:full":"Frans Broeckaertlaan 51 Berlare (overmere) Oost-Vlaanderen 9290",
    "addr:housenumber":"51",
    "addr:postcode":"9290",
    "addr:street":"Frans Broeckaertlaan",
    "iso:country":"BE",
    "sg:address":"Frans Broeckaertlaan 51",
    "sg:city":"Berlare (overmere)",
    "sg:classifiers":[
        {
            "category":"Health Services",
            "subcategory":"Nursing And Care Facility",
            "type":"Services"
        }
    ],
    "sg:phone":"+32 9 367 95 52",
    "sg:postcode":"9290",
    "sg:province":"Oost-Vlaanderen",
    "sg:tags":[
        "home"
    ],
    "wof:name":"Walraevens C",
    "wof:placetype":"venue"
},
  "geometry": {"coordinates":[3.9745619297,51.0481643677],"type":"Point"}
}