{
  "type": "Feature",
  "properties": {
    "iso:country":"BE",
    "sg:address":"Rue De Libin 33",
    "sg:city":"Libin",
    "sg:orig_category":"RESTAURANTS: H\u00d4TELS",
    "sg:phone":"+32 61 61 18 28",
    "sg:postcode":"6890",
    "sg:province":"Luxembourg",
    "wof:name":"Le Relais",
    "wof:placetype":"venue"
},
  "geometry": {"coordinates":[5.2592887878,50.0063934326],"type":"Point"}
}