{
  "type": "Feature",
  "properties": {
    "iso:country":"BE",
    "sg:address":"Steenweg Op Mol 128",
    "sg:city":"Oud-turnhout",
    "sg:orig_category":"Meubles D\u00e9taillants, Am\u00e9nagement de B\u00e2timents et de Cuisines. Cuisines and Equipements de Cuisines. ",
    "sg:phone":"+32 14 46 29 30",
    "sg:postcode":"2360",
    "sg:province":"Antwerpen",
    "wof:name":"Lommelen N.v.",
    "wof:placetype":"venue"
},
  "geometry": {"coordinates":[4.9910650253,51.3132743835],"type":"Point"}
}