{
  "type": "Feature",
  "properties": {
    "addr:full":"Rue Voie Michel 117 Durbuy (barvaux-sur-ourthe) Luxembourg 6940",
    "addr:housenumber":"117",
    "addr:postcode":"6940",
    "addr:street":"Rue Voie Michel",
    "iso:country":"BE",
    "sg:address":"Rue Voie Michel 117",
    "sg:city":"Durbuy (barvaux-sur-ourthe)",
    "sg:classifiers":[
        {
            "category":"Health Services",
            "subcategory":"Doctor",
            "type":"Services"
        }
    ],
    "sg:phone":"+32 86 21 36 10",
    "sg:postcode":"6940",
    "sg:province":"Luxembourg",
    "sg:tags":[
        "medicinephysicians",
        "surgeon"
    ],
    "wof:name":"Dony E",
    "wof:placetype":"venue"
},
  "geometry": {"coordinates":[5.4543361664,50.3515777588],"type":"Point"}
}