{
  "type": "Feature",
  "properties": {
    "iso:country":"BE",
    "sg:address":"Menensesteenweg 305",
    "sg:city":"Wervik",
    "sg:orig_category":"Biocontrol Agents",
    "sg:phone":"+32 56 30 03 00",
    "sg:postcode":"8940",
    "sg:province":"West-Vlaanderen",
    "wof:name":"Sanac Nv",
    "wof:placetype":"venue"
},
  "geometry": {"coordinates":[3.0900549889,50.7815818787],"type":"Point"}
}