{
  "type": "Feature",
  "properties": {
    "addr:full":"Sportlaan 34 Beringen (koersel) Limburg 3582",
    "addr:housenumber":"34",
    "addr:postcode":"3582",
    "addr:street":"Sportlaan",
    "iso:country":"BE",
    "sg:address":"Sportlaan 34",
    "sg:city":"Beringen (koersel)",
    "sg:classifiers":[
        {
            "category":"Health Services",
            "subcategory":"Health Practitioner",
            "type":"Services"
        }
    ],
    "sg:phone":"+32 11 42 83 53",
    "sg:postcode":"3582",
    "sg:province":"Limburg",
    "sg:tags":[
        "physiotherapist"
    ],
    "wof:name":"Bosmans Luc",
    "wof:placetype":"venue"
},
  "geometry": {"coordinates":[5.2708749771,51.0595359802],"type":"Point"}
}