{
  "type": "Feature",
  "properties": {
    "addr:full":"Rue Coenraets 66 Bruxelles Bruxelles-Capitale 1060",
    "addr:housenumber":"66",
    "addr:postcode":"1060",
    "addr:street":"Rue Coenraets",
    "iso:country":"BE",
    "sg:address":"Rue Coenraets 66",
    "sg:city":"Bruxelles",
    "sg:classifiers":[
        {
            "category":"Manufacturing",
            "subcategory":"Chemicals & Compounds",
            "type":"Manufacturing & Wholesale Goods"
        }
    ],
    "sg:phone":"+32 2 535 06 77",
    "sg:postcode":"1060",
    "sg:province":"Bruxelles-Capitale",
    "sg:tags":[
        "pharmaceutical",
        "chemistry"
    ],
    "wof:name":"Centre Du Libre Examen De Bruxelles",
    "wof:placetype":"venue"
},
  "geometry": {"coordinates":[4.3381090164,50.8319206238],"type":"Point"}
}