{
  "type": "Feature",
  "properties": {
    "addr:full":"Pont D'ile 44 Li\u00c8ge Li\u00e8ge 4000",
    "addr:housenumber":"44",
    "addr:postcode":"4000",
    "addr:street":"Pont D'Ile",
    "iso:country":"BE",
    "sg:address":"Pont D'ile 44",
    "sg:city":"Li\u00c8ge",
    "sg:orig_category":"Baby- and kinderkleding Dameskledingzaken Herenkledingzaken",
    "sg:phone":"+32 4 222 02 59",
    "sg:postcode":"4000",
    "sg:province":"Li\u00e8ge",
    "wof:name":"Peek & Cloppenburg ( P&c)",
    "wof:placetype":"venue"
},
  "geometry": {"coordinates":[5.57102108,50.6424598694],"type":"Point"}
}