{
  "type": "Feature",
  "properties": {
    "addr:full":"Chauss\u00c9e Victor Lampe 85 Lessines Hainaut 7866",
    "addr:housenumber":"85",
    "addr:postcode":"7866",
    "addr:street":"Chausse\u0301E Victor Lampe;Hainaut",
    "iso:country":"BE",
    "sg:address":"Chauss\u00c9e Victor Lampe 85",
    "sg:city":"Lessines",
    "sg:orig_category":"Apotheken",
    "sg:phone":"+32 68 33 24 68",
    "sg:postcode":"7866",
    "sg:province":"Hainaut",
    "wof:name":"Andr\u00c9e Dubuisson",
    "wof:placetype":"venue"
},
  "geometry": {"coordinates":[3.8587861061,50.6850891113],"type":"Point"}
}