{
  "type": "Feature",
  "properties": {
    "addr:full":"Rue Justin Sauvenier 27 Bl\u00e9gny (barchon) Li\u00e8ge 4671",
    "addr:housenumber":"27",
    "addr:postcode":"4671",
    "addr:street":"Rue Justin Sauvenier;Barchon",
    "iso:country":"BE",
    "sg:address":"Rue Justin Sauvenier 27",
    "sg:city":"Bl\u00e9gny (barchon)",
    "sg:classifiers":[
        {
            "category":"Freight",
            "type":"Transportation"
        }
    ],
    "sg:phone":"+32 4 247 49 00",
    "sg:postcode":"4671",
    "sg:province":"Li\u00e8ge",
    "sg:tags":[
        "-",
        "transport"
    ],
    "wof:name":"Brm Sa",
    "wof:placetype":"venue"
},
  "geometry": {"coordinates":[5.7040228844,50.6691017151],"type":"Point"}
}