{
  "type": "Feature",
  "properties": {
    "iso:country":"BE",
    "sg:address":"Aisomont 44",
    "sg:city":"Trois-ponts",
    "sg:orig_category":"Rundveehouders",
    "sg:phone":"+32 80 86 24 59",
    "sg:postcode":"4980",
    "sg:province":"Li\u00e8ge",
    "wof:name":"Monique Mathieu",
    "wof:placetype":"venue"
},
  "geometry": {"coordinates":[5.8710570335,50.3724403381],"type":"Point"}
}