{
  "type": "Feature",
  "properties": {
    "iso:country":"BE",
    "sg:address":"Mercatorstraat 168 Box 1",
    "sg:city":"Sint-niklaas",
    "sg:orig_category":"Non-Classified Establishments",
    "sg:phone":"+32 3 776 23 53",
    "sg:postcode":"9100",
    "sg:province":"Oost-Vlaanderen",
    "wof:name":"Recta",
    "wof:placetype":"venue"
},
  "geometry": {"coordinates":[4.1512708664,51.1686096191],"type":"Point"}
}