{
  "type": "Feature",
  "properties": {
    "iso:country":"BE",
    "sg:address":"Klapdorp 35",
    "sg:city":"Antwerpen",
    "sg:orig_category":"Artiesten and kunstenaars",
    "sg:phone":"+32 3 232 23 80",
    "sg:postcode":"2000",
    "sg:province":"Antwerpen",
    "wof:name":"Lemaire",
    "wof:placetype":"venue"
},
  "geometry": {"coordinates":[4.4039559364,51.2242736816],"type":"Point"}
}