{
  "type": "Feature",
  "properties": {
    "addr:full":"Veldstraat 66 Beerse Antwerpen 2340",
    "addr:housenumber":"66",
    "addr:postcode":"2340",
    "addr:street":"Veldstraat",
    "iso:country":"BE",
    "sg:address":"Veldstraat 66",
    "sg:city":"Beerse",
    "sg:classifiers":[
        {
            "category":"Health Services",
            "subcategory":"Doctor",
            "type":"Services"
        }
    ],
    "sg:phone":"+32 14 61 63 47",
    "sg:postcode":"2340",
    "sg:province":"Antwerpen",
    "sg:tags":[
        "medicinephysicians",
        "surgeon"
    ],
    "wof:name":"Bronckaers M",
    "wof:placetype":"venue"
},
  "geometry": {"coordinates":[4.8694930077,51.3274421692],"type":"Point"}
}