{
  "type": "Feature",
  "properties": {
    "addr:full":"Compogne 481 Bertogne Luxembourg 6687",
    "addr:housenumber":"481",
    "addr:postcode":"6687",
    "addr:street":"Compogne",
    "iso:country":"BE",
    "sg:address":"Compogne 481",
    "sg:city":"Bertogne",
    "sg:orig_category":"Eleveurs de bovins",
    "sg:phone":"+32 61 21 19 70",
    "sg:postcode":"6687",
    "sg:province":"Luxembourg",
    "wof:name":"Lhermitte Justin-vincent",
    "wof:placetype":"venue"
},
  "geometry": {"coordinates":[5.7058339119,50.0801010132],"type":"Point"}
}