{
  "type": "Feature",
  "properties": {
    "addr:full":"Schouterveldstraat 34 Hasselt Limburg 3511",
    "addr:housenumber":"34",
    "addr:postcode":"3511",
    "addr:street":"Schouterveldstraat",
    "iso:country":"BE",
    "sg:address":"Schouterveldstraat 34",
    "sg:city":"Hasselt",
    "sg:orig_category":"Experts-comptables",
    "sg:phone":"+32 11 25 10 83",
    "sg:postcode":"3511",
    "sg:province":"Limburg",
    "wof:name":"Ferdinand Genne",
    "wof:placetype":"venue"
},
  "geometry": {"coordinates":[5.3034238815,50.9432487488],"type":"Point"}
}