{
  "type": "Feature",
  "properties": {
    "iso:country":"BE",
    "sg:address":"Rue De La Cure 1",
    "sg:city":"Manage (bellecourt)",
    "sg:classifiers":[
        {
            "category":"Real Estate",
            "subcategory":"Architect",
            "type":"Services"
        }
    ],
    "sg:phone":"+32 64 55 75 09",
    "sg:postcode":"7170",
    "sg:province":"Hainaut",
    "wof:name":"Soupart J-p",
    "wof:placetype":"venue"
},
  "geometry": {"coordinates":[4.253235817,50.4841651917],"type":"Point"}
}