{
  "type": "Feature",
  "properties": {
    "iso:country":"BE",
    "sg:address":"Kleistraat 7",
    "sg:city":"Maarkedal (etikhove)",
    "sg:classifiers":[
        {
            "category":"Building & Trades",
            "subcategory":"Landscaping Services",
            "type":"Services"
        }
    ],
    "sg:phone":"+32 55 21 26 39",
    "sg:postcode":"9680",
    "sg:province":"Oost-Vlaanderen",
    "sg:tags":[
        "slaughterer"
    ],
    "wof:name":"Marist K",
    "wof:placetype":"venue"
},
  "geometry": {"coordinates":[3.6321439743,50.7910652161],"type":"Point"}
}