{
  "type": "Feature",
  "properties": {
    "addr:full":"Acacialaan 1 Waasmunster Oost-Vlaanderen 9250",
    "addr:housenumber":"1",
    "addr:postcode":"9250",
    "addr:street":"Acacialaan",
    "iso:country":"BE",
    "sg:address":"Acacialaan 1",
    "sg:city":"Waasmunster",
    "sg:classifiers":[
        {
            "category":"Fast Food",
            "type":"Food & Drink"
        }
    ],
    "sg:phone":"+32 52 46 17 68",
    "sg:postcode":"9250",
    "sg:province":"Oost-Vlaanderen",
    "sg:tags":[
        "\u00c0",
        "emporter",
        "restaurants"
    ],
    "wof:name":"Frituur 't Paardje",
    "wof:placetype":"venue"
},
  "geometry": {"coordinates":[4.0866799355,51.1148643494],"type":"Point"}
}