{
  "type": "Feature",
  "properties": {
    "addr:full":"Vennestraat 254 Genk Limburg 3600",
    "addr:housenumber":"254",
    "addr:postcode":"3600",
    "addr:street":"Vennestraat",
    "iso:country":"BE",
    "sg:address":"Vennestraat 254",
    "sg:city":"Genk",
    "sg:orig_category":"Entretien and r\u00e9parations de voitures",
    "sg:phone":"+32 89 35 12 82",
    "sg:postcode":"3600",
    "sg:province":"Limburg",
    "wof:name":"Jean Truyen",
    "wof:placetype":"venue"
},
  "geometry": {"coordinates":[5.4808831215,50.9668731689],"type":"Point"}
}