{
  "type": "Feature",
  "properties": {
    "iso:country":"BE",
    "sg:address":"Grand Rue 95",
    "sg:city":"Sivry-rance",
    "sg:orig_category":"Banken and kredietinstellingen",
    "sg:phone":"+32 60 41 10 01",
    "sg:postcode":"6470",
    "sg:province":"Hainaut",
    "wof:name":"Fortis",
    "wof:placetype":"venue"
},
  "geometry": {"coordinates":[4.2756710052,50.1424446106],"type":"Point"}
}