{
  "type": "Feature",
  "properties": {
    "addr:full":"August Van Landeghemplein 8 Willebroek Antwerpen 2830",
    "addr:housenumber":"8",
    "addr:postcode":"2830",
    "addr:street":"August;Landeghemplein",
    "iso:country":"BE",
    "sg:address":"August Van Landeghemplein 8",
    "sg:city":"Willebroek",
    "sg:classifiers":[
        {
            "category":"Bars & Pubs",
            "type":"Food & Drink"
        }
    ],
    "sg:phone":"+32 3 886 78 39",
    "sg:postcode":"2830",
    "sg:province":"Antwerpen",
    "wof:name":"Knock Palace",
    "wof:placetype":"venue"
},
  "geometry": {"coordinates":[4.3598780632,51.0603065491],"type":"Point"}
}