{
  "type": "Feature",
  "properties": {
    "iso:country":"BE",
    "sg:address":"Hille 169e",
    "sg:city":"Wingene (zwevezele)",
    "sg:classifiers":[
        {
            "category":"Professional",
            "subcategory":"Management & Consulting",
            "type":"Services"
        }
    ],
    "sg:phone":"+32 51 61 16 47",
    "sg:postcode":"8750",
    "sg:province":"West-Vlaanderen",
    "sg:tags":[
        "consultant"
    ],
    "wof:name":"T.o.p. Consultants Bvba",
    "wof:placetype":"venue"
},
  "geometry": {"coordinates":[3.2266900539,51.0430870056],"type":"Point"}
}