{
  "type": "Feature",
  "properties": {
    "addr:full":"Rue De La Gare 26 Eghez\u00e9e Namur 5310",
    "addr:housenumber":"26",
    "addr:postcode":"5310",
    "addr:street":"Rue De La Gare;Namur",
    "iso:country":"BE",
    "sg:address":"Rue De La Gare 26",
    "sg:city":"Eghez\u00e9e",
    "sg:classifiers":[
        {
            "category":"Health Services",
            "subcategory":"Health Practitioner",
            "type":"Services"
        }
    ],
    "sg:phone":"+32 81 81 22 23",
    "sg:postcode":"5310",
    "sg:province":"Namur",
    "sg:tags":[
        "physiotherapist"
    ],
    "wof:name":"Burlet Pascal",
    "wof:placetype":"venue"
},
  "geometry": {"coordinates":[4.9105148315,50.5951538086],"type":"Point"}
}