{
  "type": "Feature",
  "properties": {
    "iso:country":"BE",
    "sg:address":"Rue Fontiane Au Biez 200",
    "sg:city":"Verviers",
    "sg:orig_category":"DIVERSE RECREATIEVE ACTIVITEITEN",
    "sg:phone":"+32 87 22 40 60",
    "sg:postcode":"4802",
    "sg:province":"Li\u00e8ge",
    "wof:name":"Plaine De Jeux Deru",
    "wof:placetype":"venue"
},
  "geometry": {"coordinates":[5.8864498138,50.5757904053],"type":"Point"}
}