{
  "type": "Feature",
  "properties": {
    "iso:country":"BE",
    "sg:address":"Koninklijke Sinte Mariastraat 103",
    "sg:city":"Brussel/bruxelles",
    "sg:orig_category":"Production de films, t\u00e9l\u00e9films and vid\u00e9os",
    "sg:phone":"+32 2 215 12 74",
    "sg:postcode":"1030",
    "sg:province":"Bruxelles-Capitale",
    "wof:name":"Rouffaer",
    "wof:placetype":"venue"
},
  "geometry": {"coordinates":[4.37038517,50.862323761],"type":"Point"}
}