{
  "type": "Feature",
  "properties": {
    "addr:full":"Hertogstraat 147 Leuven (heverlee) Vlaams-Brabant 3001",
    "addr:housenumber":"147",
    "addr:postcode":"3001",
    "addr:street":"Hertogstraat",
    "iso:country":"BE",
    "sg:address":"Hertogstraat 147",
    "sg:city":"Leuven (heverlee)",
    "sg:classifiers":[
        {
            "category":"Professional",
            "subcategory":"Management & Consulting",
            "type":"Services"
        }
    ],
    "sg:phone":"+32 16 40 67 99",
    "sg:postcode":"3001",
    "sg:province":"Vlaams-Brabant",
    "sg:tags":[
        "consultant"
    ],
    "wof:name":"Rouin Ghislain Bvba",
    "wof:placetype":"venue"
},
  "geometry": {"coordinates":[4.6994662285,50.8597373962],"type":"Point"}
}