{
  "type": "Feature",
  "properties": {
    "addr:full":"Gasthuisstraat 14b Kontich (waarloos) Antwerpen 2550",
    "addr:housenumber":"14b",
    "addr:postcode":"2550",
    "addr:street":"Gasthuisstraat",
    "iso:country":"BE",
    "sg:address":"Gasthuisstraat 14b",
    "sg:city":"Kontich (waarloos)",
    "sg:classifiers":[
        {
            "category":"Home & Garden",
            "subcategory":"Garden Supply",
            "type":"Retail Goods"
        }
    ],
    "sg:phone":"+32 15 31 73 80",
    "sg:postcode":"2550",
    "sg:province":"Antwerpen",
    "sg:tags":[
        "gardening"
    ],
    "wof:name":"B.i.p",
    "wof:placetype":"venue"
},
  "geometry": {"coordinates":[4.4658050537,51.1031913757],"type":"Point"}
}