{
  "type": "Feature",
  "properties": {
    "iso:country":"BE",
    "sg:address":"Kuipenstraat 17",
    "sg:city":"Oostkamp",
    "sg:orig_category":"Eleveurs and marchands de porcs. Eleveurs de bovins",
    "sg:phone":"+32 50 82 64 93",
    "sg:postcode":"8020",
    "sg:province":"West-Vlaanderen",
    "wof:name":"Rudy Perquy",
    "wof:placetype":"venue"
},
  "geometry": {"coordinates":[3.1987740993,51.1391105652],"type":"Point"}
}