{
  "type": "Feature",
  "properties": {
    "addr:full":"Lod. Lavkistraat 3 Heers Limburg 3870",
    "addr:housenumber":"3",
    "addr:postcode":"3870",
    "addr:street":"Lavkistraat",
    "iso:country":"BE",
    "sg:address":"Lod. Lavkistraat 3",
    "sg:city":"Heers",
    "sg:orig_category":"Banques and organismes de cr\u00e9dit",
    "sg:phone":"+32 12 74 19 11",
    "sg:postcode":"3870",
    "sg:province":"Limburg",
    "wof:name":"Citibank",
    "wof:placetype":"venue"
},
  "geometry": {"coordinates":[5.3562932014,50.7725143433],"type":"Point"}
}