{
  "type": "Feature",
  "properties": {
    "iso:country":"BE",
    "sg:address":"Galileistraat 1",
    "sg:city":"Diksmuide",
    "sg:orig_category":"Rundveehouders",
    "sg:phone":"+32 51 50 10 45",
    "sg:postcode":"8600",
    "sg:province":"West-Vlaanderen",
    "wof:name":"Roland Depuydt",
    "wof:placetype":"venue"
},
  "geometry": {"coordinates":[2.8642399311,51.0380401611],"type":"Point"}
}