{
  "type": "Feature",
  "properties": {
    "addr:full":"Breughelpark 5-50 Asse (zellik) Vlaams-Brabant 1731",
    "addr:housenumber":"5-50",
    "addr:postcode":"1731",
    "addr:street":"Breughelpark",
    "iso:country":"BE",
    "sg:address":"Breughelpark 5-50",
    "sg:city":"Asse (zellik)",
    "sg:classifiers":[
        {
            "category":"Personal",
            "subcategory":"Beauty Salon",
            "type":"Services"
        }
    ],
    "sg:phone":"+32 2 466 21 77",
    "sg:postcode":"1731",
    "sg:province":"Vlaams-Brabant",
    "sg:tags":[
        "lady",
        "-",
        "hairdressing"
    ],
    "wof:name":"Singel R",
    "wof:placetype":"venue"
},
  "geometry": {"coordinates":[4.2721309662,50.8836250305],"type":"Point"}
}