{
  "type": "Feature",
  "properties": {
    "iso:country":"BE",
    "sg:address":"Hochstrasse 93",
    "sg:city":"Eupen",
    "sg:classifiers":[
        {
            "category":"Government",
            "subcategory":"Fire Station",
            "type":"Public Place"
        }
    ],
    "sg:phone":"+32 87 56 02 96",
    "sg:postcode":"4700",
    "sg:province":"Li\u00e8ge",
    "sg:tags":[
        "detection",
        "installation",
        "material",
        "-"
    ],
    "wof:name":"Secur Sa",
    "wof:placetype":"venue"
},
  "geometry": {"coordinates":[6.0168709755,50.6359405518],"type":"Point"}
}