{
  "type": "Feature",
  "properties": {
    "addr:full":"Stationsstraat 27 Kampenhout Vlaams-Brabant 1910",
    "addr:housenumber":"27",
    "addr:postcode":"1910",
    "addr:street":"Stationsstraat",
    "iso:country":"BE",
    "sg:address":"Stationsstraat 27",
    "sg:city":"Kampenhout",
    "sg:classifiers":[
        {
            "category":"Building & Trades",
            "subcategory":"Pest Control",
            "type":"Services"
        }
    ],
    "sg:phone":"+32 16 65 56 89",
    "sg:postcode":"1910",
    "sg:province":"Vlaams-Brabant",
    "sg:tags":[
        "painting",
        "contractor"
    ],
    "wof:name":"Willems H",
    "wof:placetype":"venue"
},
  "geometry": {"coordinates":[4.5556149483,50.9408111572],"type":"Point"}
}