{
  "type": "Feature",
  "properties": {
    "iso:country":"BE",
    "sg:address":"Bandam 7",
    "sg:city":"Kaprijke",
    "sg:orig_category":"Serres and speciale beglazing",
    "sg:phone":"+32 9 379 07 70",
    "sg:postcode":"9970",
    "sg:province":"Oost-Vlaanderen",
    "wof:name":"Fa. Gama Glas",
    "wof:placetype":"venue"
},
  "geometry": {"coordinates":[3.617675066,51.2182540894],"type":"Point"}
}