{
  "type": "Feature",
  "properties": {
    "iso:country":"BE",
    "sg:address":"Europark-oost 2",
    "sg:city":"Sint-niklaas",
    "sg:orig_category":"Meubelen, niet-elektrische huishoudapparaten and vloerbekleding Gh",
    "sg:phone":"+32 3 780 94 94",
    "sg:postcode":"9100",
    "sg:province":"Oost-Vlaanderen",
    "wof:name":"P.t.s.",
    "wof:placetype":"venue"
},
  "geometry": {"coordinates":[4.1709909439,51.1624984741],"type":"Point"}
}