{
  "type": "Feature",
  "properties": {
    "iso:country":"BE",
    "sg:address":"Aarschotsesteenweg 377",
    "sg:city":"Leuven (wilsele)",
    "sg:classifiers":[
        {
            "category":"Home & Garden",
            "subcategory":"Carpets & Floor Coverings",
            "type":"Retail Goods"
        }
    ],
    "sg:phone":"+32 16 82 53 67",
    "sg:postcode":"3012",
    "sg:province":"Vlaams-Brabant",
    "sg:tags":[
        "layer",
        "mosaicists"
    ],
    "wof:name":"Peeters R",
    "wof:placetype":"venue"
},
  "geometry": {"coordinates":[4.7195367813,50.9216842651],"type":"Point"}
}