{
  "type": "Feature",
  "properties": {
    "addr:full":"Fran\u00c7ois Blauweweg 1 Lichtervelde West-Vlaanderen 8810",
    "addr:housenumber":"1",
    "addr:postcode":"8810",
    "addr:street":"Franc\u0327Ois Blauweweg",
    "iso:country":"BE",
    "sg:address":"Fran\u00c7ois Blauweweg 1",
    "sg:city":"Lichtervelde",
    "sg:orig_category":"Eleveurs and marchands de porcs. Eleveurs de bovins",
    "sg:phone":"+32 51 72 20 61",
    "sg:postcode":"8810",
    "sg:province":"West-Vlaanderen",
    "wof:name":"Wilfried Lievens",
    "wof:placetype":"venue"
},
  "geometry": {"coordinates":[3.1437659264,51.0077438354],"type":"Point"}
}