{
  "type": "Feature",
  "properties": {
    "iso:country":"BE",
    "sg:address":"Ossenmarkt 2",
    "sg:city":"Antwerpen-centrum",
    "sg:classifiers":[
        {
            "category":"Professional",
            "subcategory":"Computer Services",
            "type":"Services"
        }
    ],
    "sg:phone":"+32 3 232 09 76",
    "sg:postcode":"2000",
    "sg:province":"Antwerpen",
    "sg:tags":[
        "microsoft"
    ],
    "wof:name":"Think Tank",
    "wof:placetype":"venue"
},
  "geometry": {"coordinates":[4.4135479927,51.2222175598],"type":"Point"}
}