{
  "type": "Feature",
  "properties": {
    "iso:country":"BE",
    "sg:address":"Rue Sart Haut 77",
    "sg:city":"Les Bons Villers",
    "sg:orig_category":"Tuinen",
    "sg:phone":"+32 71 84 69 51",
    "sg:postcode":"6210",
    "sg:province":"Hainaut",
    "wof:name":"Sarfa",
    "wof:placetype":"venue"
},
  "geometry": {"coordinates":[4.3933429718,50.5531044006],"type":"Point"}
}