{
  "type": "Feature",
  "properties": {
    "addr:full":"Rue Du Lombard 25 Namur Namur 5000",
    "addr:housenumber":"25",
    "addr:postcode":"5000",
    "addr:street":"Rue Du Lombard",
    "iso:country":"BE",
    "sg:address":"Rue Du Lombard 25",
    "sg:city":"Namur",
    "sg:classifiers":[
        {
            "category":"Cafe",
            "type":"Food & Drink"
        }
    ],
    "sg:phone":"+32 81 22 28 12",
    "sg:postcode":"5000",
    "sg:province":"Namur",
    "sg:tags":[
        "snack-bars"
    ],
    "wof:name":"Panix",
    "wof:placetype":"venue"
},
  "geometry": {"coordinates":[4.8698382378,50.4639015198],"type":"Point"}
}