{
  "type": "Feature",
  "properties": {
    "iso:country":"BE",
    "sg:address":"Chauss\u00e9e De Namur 75",
    "sg:city":"Beauvechain (hamme-mille)",
    "sg:classifiers":[
        {
            "category":"Health Services",
            "subcategory":"Doctor",
            "type":"Services"
        }
    ],
    "sg:phone":"+32 10 86 63 50",
    "sg:postcode":"1320",
    "sg:province":"Brabant Wallon",
    "sg:tags":[
        "medicinephysicians",
        "surgeon"
    ],
    "wof:name":"Brichard C",
    "wof:placetype":"venue"
},
  "geometry": {"coordinates":[4.7250652313,50.7716293335],"type":"Point"}
}