{
  "type": "Feature",
  "properties": {
    "addr:full":"Neerzijstraat 109 Genk Limburg 3600",
    "addr:housenumber":"109",
    "addr:postcode":"3600",
    "addr:street":"Neerzijstraat",
    "iso:country":"BE",
    "sg:address":"Neerzijstraat 109",
    "sg:city":"Genk",
    "sg:classifiers":[
        {
            "category":"Farming",
            "subcategory":"Crops",
            "type":"Manufacturing & Wholesale Goods"
        }
    ],
    "sg:phone":"+32 89 71 12 40",
    "sg:postcode":"3600",
    "sg:province":"Limburg",
    "sg:tags":[
        "vegetable",
        "fruit",
        "agriculture",
        "livestock"
    ],
    "wof:name":"Dhr J Olaerts",
    "wof:placetype":"venue"
},
  "geometry": {"coordinates":[5.5402917862,50.976272583],"type":"Point"}
}