{
  "type": "Feature",
  "properties": {
    "addr:full":"Dorp 7ba Lille Antwerpen 2275",
    "addr:housenumber":"7ba",
    "addr:postcode":"2275",
    "addr:street":"Dorp",
    "iso:country":"BE",
    "sg:address":"Dorp 7ba",
    "sg:city":"Lille",
    "sg:classifiers":[
        {
            "category":"Food & Beverages",
            "subcategory":"Fruits & Vegetables",
            "type":"Retail Goods"
        }
    ],
    "sg:phone":"+32 14 88 28 08",
    "sg:postcode":"2275",
    "sg:province":"Antwerpen",
    "sg:tags":[
        "groenten"
    ],
    "wof:name":"Huis De Ley",
    "wof:placetype":"venue"
},
  "geometry": {"coordinates":[4.8357129097,51.2267341614],"type":"Point"}
}