{
  "type": "Feature",
  "properties": {
    "iso:country":"BE",
    "sg:address":"107",
    "sg:city":"Kuurnsesteenweg 8500 Kortrijk",
    "sg:classifiers":[
        {
            "category":"Autos & Motor Vehicles",
            "subcategory":"Automobile Sales",
            "type":"Retail Goods"
        }
    ],
    "sg:phone":"+32 56 35 10 00",
    "sg:postcode":"107",
    "sg:tags":[
        "equipment",
        "motor-cars",
        "transport"
    ],
    "wof:name":"Garage Vandecasteele Nv",
    "wof:placetype":"venue"
},
  "geometry": {"coordinates":[3.2716600895,50.8433761597],"type":"Point"}
}