{
  "type": "Feature",
  "properties": {
    "iso:country":"BE",
    "sg:address":"Rue Haut Baty 74",
    "sg:city":"Sambreville (arsimont)",
    "sg:classifiers":[
        {
            "category":"Personal",
            "subcategory":"Beauty Salon",
            "type":"Services"
        }
    ],
    "sg:phone":"+32 71 74 13 37",
    "sg:postcode":"5060",
    "sg:province":"Namur",
    "sg:tags":[
        "lady",
        "-",
        "hairdressing"
    ],
    "wof:name":"Lotfi S",
    "wof:placetype":"venue"
},
  "geometry": {"coordinates":[4.647480011,50.4248504639],"type":"Point"}
}