{
  "type": "Feature",
  "properties": {
    "iso:country":"BE",
    "sg:address":"Steenweg Deinze 11a",
    "sg:city":"Nazareth",
    "sg:classifiers":[
        {
            "category":"Building & Trades",
            "subcategory":"Cleaning & Sanitation",
            "type":"Services"
        }
    ],
    "sg:phone":"+32 9 380 00 53",
    "sg:postcode":"9810",
    "sg:province":"Oost-Vlaanderen",
    "sg:tags":[
        "blast"
    ],
    "wof:name":"Van Overberghe J",
    "wof:placetype":"venue"
},
  "geometry": {"coordinates":[3.5676860809,50.9517974854],"type":"Point"}
}