{
  "type": "Feature",
  "properties": {
    "addr:full":"Avenue Franklin Roosevelt 23a Vis\u00e9 Li\u00e8ge 4600",
    "addr:housenumber":"23a",
    "addr:postcode":"4600",
    "addr:street":"Avenue Franklin Roosevelt",
    "iso:country":"BE",
    "sg:address":"Avenue Franklin Roosevelt 23a",
    "sg:city":"Vis\u00e9",
    "sg:classifiers":[
        {
            "category":"Professional",
            "subcategory":"Testing Lab",
            "type":"Services"
        }
    ],
    "sg:phone":"+32 4 379 11 43",
    "sg:postcode":"4600",
    "sg:province":"Li\u00e8ge",
    "sg:tags":[
        "chemist"
    ],
    "wof:name":"Linotte F",
    "wof:placetype":"venue"
},
  "geometry": {"coordinates":[5.6860098839,50.7373275757],"type":"Point"}
}