{
  "type": "Feature",
  "properties": {
    "iso:country":"BE",
    "sg:address":"Keienveldstraat 11",
    "sg:city":"Elsene/ixelles",
    "sg:orig_category":"Diverse zakelijke dienstverlening Organisatie van beurzen, congressen and tentoonstellingen",
    "sg:phone":"+32 2 512 09 07",
    "sg:postcode":"1050",
    "sg:province":"Bruxelles-Capitale",
    "wof:name":"D. Signe",
    "wof:placetype":"venue"
},
  "geometry": {"coordinates":[4.3602180481,50.8356056213],"type":"Point"}
}