{
  "type": "Feature",
  "properties": {
    "addr:full":"Grote Pieter Potstraat 18 Antwerpen Antwerpen 2000",
    "addr:housenumber":"18",
    "addr:postcode":"2000",
    "addr:street":"Grote Pieter Potstraat",
    "iso:country":"BE",
    "sg:address":"Grote Pieter Potstraat 18",
    "sg:city":"Antwerpen",
    "sg:classifiers":[
        {
            "category":"Bars & Pubs",
            "type":"Food & Drink"
        }
    ],
    "sg:phone":"+32 3 234 03 69",
    "sg:postcode":"2000",
    "sg:province":"Antwerpen",
    "wof:name":"Katshuis ('t)",
    "wof:placetype":"venue"
},
  "geometry": {"coordinates":[4.39686203,51.2201690674],"type":"Point"}
}