{
  "type": "Feature",
  "properties": {
    "iso:country":"BE",
    "sg:address":"Blarenberglaan A23",
    "sg:city":"Mechelen",
    "sg:classifiers":[
        {
            "category":"Utilities",
            "subcategory":"Electric",
            "type":"Services"
        }
    ],
    "sg:phone":"+32 15 28 10 10",
    "sg:postcode":"2800",
    "sg:province":"Antwerpen",
    "sg:tags":[
        "drive"
    ],
    "wof:name":"Leroy-somer Belgium",
    "wof:placetype":"venue"
},
  "geometry": {"coordinates":[4.4854397774,51.0289268494],"type":"Point"}
}