{
  "type": "Feature",
  "properties": {
    "addr:full":"Alfons Gossetlaan 13 Groot-bijgaarden Vlaams-Brabant 1702",
    "addr:housenumber":"13",
    "addr:postcode":"1702",
    "addr:street":"Alfons Gossetlaan",
    "iso:country":"BE",
    "sg:address":"Alfons Gossetlaan 13",
    "sg:city":"Groot-bijgaarden",
    "sg:classifiers":[
        {
            "category":"Utilities",
            "subcategory":"Mobile Phone",
            "type":"Services"
        }
    ],
    "sg:phone":"+32 2 467 28 62",
    "sg:postcode":"1702",
    "sg:province":"Vlaams-Brabant",
    "sg:tags":[
        "article",
        "promotional"
    ],
    "wof:name":"Bugi",
    "wof:placetype":"venue"
},
  "geometry": {"coordinates":[4.2776641846,50.8726348877],"type":"Point"}
}