{
  "type": "Feature",
  "properties": {
    "addr:full":"Waversebaan 183 Oud-heverlee Vlaams-Brabant 3050",
    "addr:housenumber":"183",
    "addr:postcode":"3050",
    "addr:street":"Waversebaan",
    "iso:country":"BE",
    "sg:address":"Waversebaan 183",
    "sg:city":"Oud-heverlee",
    "sg:orig_category":"Paramedische behandelingen Rusthuizen and serviceflats",
    "sg:phone":"+32 16 47 25 91",
    "sg:postcode":"3050",
    "sg:province":"Vlaams-Brabant",
    "wof:name":"Bonhomme",
    "wof:placetype":"venue"
},
  "geometry": {"coordinates":[4.6520848274,50.8172340393],"type":"Point"}
}