{
  "type": "Feature",
  "properties": {
    "iso:country":"BE",
    "sg:address":"Avenue Orban 4",
    "sg:city":"Sint-pieters-woluwe/woluwe-saint-pierre",
    "sg:orig_category":"Pharmaciens",
    "sg:phone":"+32 2 770 13 15",
    "sg:postcode":"1150",
    "sg:province":"Bruxelles-Capitale",
    "wof:name":"Pharmacie Le Marinel",
    "wof:placetype":"venue"
},
  "geometry": {"coordinates":[4.4516801834,50.8314247131],"type":"Point"}
}