{
  "type": "Feature",
  "properties": {
    "iso:country":"BE",
    "sg:address":"Rue De Mangombroux 1",
    "sg:city":"Verviers",
    "sg:orig_category":"Apotheken",
    "sg:phone":"+32 87 33 17 36",
    "sg:postcode":"4800",
    "sg:province":"Li\u00e8ge",
    "wof:name":"Pharmacie Populaire",
    "wof:placetype":"venue"
},
  "geometry": {"coordinates":[5.8701601028,50.5891494751],"type":"Point"}
}