{
  "type": "Feature",
  "properties": {
    "addr:full":"Rue Du Babinay 2a Bertrix (orgeo) Luxembourg 6880",
    "addr:housenumber":"2a",
    "addr:postcode":"6880",
    "addr:street":"Rue Du Babinay",
    "iso:country":"BE",
    "sg:address":"Rue Du Babinay 2a",
    "sg:city":"Bertrix (orgeo)",
    "sg:classifiers":[
        {
            "category":"Mining & Drilling",
            "type":"Manufacturing & Wholesale Goods"
        }
    ],
    "sg:phone":"+32 61 41 64 00",
    "sg:postcode":"6880",
    "sg:province":"Luxembourg",
    "sg:tags":[
        "quarry"
    ],
    "wof:name":"Ardoisi\u00e8res D'herbeumont Sa",
    "wof:placetype":"venue"
},
  "geometry": {"coordinates":[5.2587828636,49.8120079041],"type":"Point"}
}