{
  "type": "Feature",
  "properties": {
    "addr:full":"Garestalaan 19 Leuven (kessel-lo) Vlaams-Brabant 3010",
    "addr:housenumber":"19",
    "addr:postcode":"3010",
    "addr:street":"Garestalaan",
    "iso:country":"BE",
    "sg:address":"Garestalaan 19",
    "sg:city":"Leuven (kessel-lo)",
    "sg:classifiers":[
        {
            "category":"Health Services",
            "subcategory":"Health Practitioner",
            "type":"Services"
        }
    ],
    "sg:phone":"+32 16 25 54 56",
    "sg:postcode":"3010",
    "sg:province":"Vlaams-Brabant",
    "sg:tags":[
        "physiotherapist"
    ],
    "wof:name":"Van Hooydonck F",
    "wof:placetype":"venue"
},
  "geometry": {"coordinates":[4.7304501534,50.889755249],"type":"Point"}
}