{
  "type": "Feature",
  "properties": {
    "addr:full":"Centrumstraat 78 Zulte Oost-Vlaanderen 9870",
    "addr:housenumber":"78",
    "addr:postcode":"9870",
    "addr:street":"Centrumstraat",
    "iso:country":"BE",
    "sg:address":"Centrumstraat 78",
    "sg:city":"Zulte",
    "sg:orig_category":"Articles m\u00e9talliques ouvr\u00e9s divers Fab",
    "sg:phone":"+32 9 388 94 08",
    "sg:postcode":"9870",
    "sg:province":"Oost-Vlaanderen",
    "wof:name":"Vanden Weghe Didier",
    "wof:placetype":"venue"
},
  "geometry": {"coordinates":[3.4697210789,50.9317741394],"type":"Point"}
}