{
  "type": "Feature",
  "properties": {
    "addr:full":"Grote Markt 51 Zelzate Oost-Vlaanderen 9060",
    "addr:housenumber":"51",
    "addr:postcode":"9060",
    "addr:street":"Grote Markt",
    "iso:country":"BE",
    "sg:address":"Grote Markt 51",
    "sg:city":"Zelzate",
    "sg:orig_category":"Studios photographiques",
    "sg:phone":"+32 9 344 63 82",
    "sg:postcode":"9060",
    "sg:province":"Oost-Vlaanderen",
    "wof:name":"Studio Vergauwe",
    "wof:placetype":"venue"
},
  "geometry": {"coordinates":[3.8110470772,51.2009391785],"type":"Point"}
}