{
  "type": "Feature",
  "properties": {
    "addr:full":"Eisenhowerlaan 3 Bonheiden Antwerpen 2820",
    "addr:housenumber":"3",
    "addr:postcode":"2820",
    "addr:street":"Eisenhowerlaan",
    "iso:country":"BE",
    "sg:address":"Eisenhowerlaan 3",
    "sg:city":"Bonheiden",
    "sg:classifiers":[
        {
            "category":"Utilities",
            "subcategory":"Natural Gas",
            "type":"Services"
        }
    ],
    "sg:phone":"+32 15 25 36 61",
    "sg:postcode":"2820",
    "sg:province":"Antwerpen",
    "sg:tags":[
        "welding"
    ],
    "wof:name":"De Groodt Lasbedrijf Bvba",
    "wof:placetype":"venue"
},
  "geometry": {"coordinates":[4.5571269989,51.0223693848],"type":"Point"}
}