{
  "type": "Feature",
  "properties": {
    "addr:full":"Rue De Menin 155 Moeskroen/mouscron Hainaut 7700",
    "addr:housenumber":"155",
    "addr:postcode":"7700",
    "addr:street":"Rue De Menin",
    "iso:country":"BE",
    "sg:address":"Rue De Menin 155",
    "sg:city":"Moeskroen/mouscron",
    "sg:orig_category":"Plomberie, chauffage and installations sanitaires. Entretien et r\u00e9parations de v\u00e9hicules \u00e0 domicile.",
    "sg:phone":"+32 56 84 12 78",
    "sg:postcode":"7700",
    "sg:province":"Hainaut",
    "wof:name":"S.o.s. D\u00c9pannage",
    "wof:placetype":"venue"
},
  "geometry": {"coordinates":[3.2323200703,50.7400932312],"type":"Point"}
}