{
  "type": "Feature",
  "properties": {
    "iso:country":"BE",
    "sg:address":"Burg-reuland 110",
    "sg:city":"Burg-reuland/burg-reuland",
    "sg:orig_category":"Boucheries",
    "sg:phone":"+32 80 32 90 76",
    "sg:postcode":"4790",
    "sg:province":"Li\u00e8ge",
    "wof:name":"Metzgerei Mayeres",
    "wof:placetype":"venue"
},
  "geometry": {"coordinates":[6.1348290443,50.1950302124],"type":"Point"}
}