{
  "type": "Feature",
  "properties": {
    "addr:full":"Langestraat 59 Kampenhout Vlaams-Brabant 1910",
    "addr:housenumber":"59",
    "addr:postcode":"1910",
    "addr:street":"Langestraat",
    "iso:country":"BE",
    "sg:address":"Langestraat 59",
    "sg:city":"Kampenhout",
    "sg:orig_category":"Installatie van houten of kunststof schrijnwerk",
    "sg:phone":"+32 16 65 77 76",
    "sg:postcode":"1910",
    "sg:province":"Vlaams-Brabant",
    "wof:name":"Patrick Breugelmans",
    "wof:placetype":"venue"
},
  "geometry": {"coordinates":[4.5564918518,50.9592666626],"type":"Point"}
}