{
  "type": "Feature",
  "properties": {
    "addr:full":"Meigemheidestraat 20 Beersel Vlaams-Brabant 1652",
    "addr:housenumber":"20",
    "addr:postcode":"1652",
    "addr:street":"Meigemheidestraat",
    "iso:country":"BE",
    "sg:address":"Meigemheidestraat 20",
    "sg:city":"Beersel",
    "sg:orig_category":"Bois Gr. Jardinage. Combustibles. Quincailleries",
    "sg:phone":"+32 2 380 33 43",
    "sg:postcode":"1652",
    "sg:province":"Vlaams-Brabant",
    "wof:name":"Van Hellemont",
    "wof:placetype":"venue"
},
  "geometry": {"coordinates":[4.308619976,50.7546806335],"type":"Point"}
}