{
  "type": "Feature",
  "properties": {
    "iso:country":"BE",
    "sg:address":"Ambachtstraat 12",
    "sg:city":"Torhout",
    "sg:orig_category":"Installatie van houten of kunststof schrijnwerk",
    "sg:phone":"+32 50 22 27 54",
    "sg:postcode":"8820",
    "sg:province":"West-Vlaanderen",
    "wof:name":"Anvro",
    "wof:placetype":"venue"
},
  "geometry": {"coordinates":[3.1073539257,51.0776405334],"type":"Point"}
}