{
  "type": "Feature",
  "properties": {
    "iso:country":"BE",
    "sg:address":"Anspachlaan 57",
    "sg:city":"Brussel/bruxelles",
    "sg:orig_category":"Dameskledingzaken",
    "sg:phone":"+32 2 223 33 91",
    "sg:postcode":"1000",
    "sg:province":"Bruxelles-Capitale",
    "wof:name":"Andromeda",
    "wof:placetype":"venue"
},
  "geometry": {"coordinates":[4.3503241539,50.8492240906],"type":"Point"}
}