{
  "type": "Feature",
  "properties": {
    "iso:country":"BE",
    "sg:address":"Beatrijslaan 26",
    "sg:city":"Rotselaar",
    "sg:classifiers":[
        {
            "category":"Landmark",
            "subcategory":"Tourist Attraction",
            "type":"Public Place"
        }
    ],
    "sg:phone":"+32 16 44 68 60",
    "sg:postcode":"3110",
    "sg:province":"Vlaams-Brabant",
    "sg:tags":[
        "tower-clocks",
        "bell-foundries"
    ],
    "wof:name":"Klokkengieterij J Sergeys",
    "wof:placetype":"venue"
},
  "geometry": {"coordinates":[4.7566800117,50.9568328857],"type":"Point"}
}