{
  "type": "Feature",
  "properties": {
    "addr:full":"Rue De La Moinerie 2 Verviers (petit-rechain) Li\u00e8ge 4800",
    "addr:housenumber":"2",
    "addr:postcode":"4800",
    "addr:street":"Rue De La Moinerie",
    "iso:country":"BE",
    "sg:address":"Rue De La Moinerie 2",
    "sg:city":"Verviers (petit-rechain)",
    "sg:classifiers":[
        {
            "category":"Shopping",
            "subcategory":"Books",
            "type":"Retail Goods"
        }
    ],
    "sg:phone":"+32 87 31 17 30",
    "sg:postcode":"4800",
    "sg:province":"Li\u00e8ge",
    "sg:tags":[
        "bookseller"
    ],
    "wof:name":"Bonni",
    "wof:placetype":"venue"
},
  "geometry": {"coordinates":[5.8578181267,50.5891189575],"type":"Point"}
}