{
  "type": "Feature",
  "properties": {
    "iso:country":"BE",
    "sg:address":"Mechelsesteenweg 113a",
    "sg:city":"Sint-katelijne-waver",
    "sg:classifiers":[
        {
            "category":"Professional",
            "subcategory":"Computer Services",
            "type":"Services"
        }
    ],
    "sg:phone":"+32 15 56 03 70",
    "sg:postcode":"2860",
    "sg:province":"Antwerpen",
    "sg:tags":[
        "network"
    ],
    "wof:name":"Commswitch Nv",
    "wof:placetype":"venue"
},
  "geometry": {"coordinates":[4.5256118774,51.0581207275],"type":"Point"}
}