{
  "type": "Feature",
  "properties": {
    "iso:country":"BE",
    "sg:address":"Salphen 7",
    "sg:city":"Malle",
    "sg:orig_category":"Rundveehouders",
    "sg:phone":"+32 3 312 03 17",
    "sg:postcode":"2390",
    "sg:province":"Antwerpen",
    "wof:name":"Roger Van Tichelen",
    "wof:placetype":"venue"
},
  "geometry": {"coordinates":[4.7419390678,51.292766571],"type":"Point"}
}