{
  "type": "Feature",
  "properties": {
    "iso:country":"BE",
    "sg:address":"Rue E. Vandervelde",
    "sg:city":"Vaux-sous-chevremont",
    "sg:orig_category":"Royal Canin. Animaux domestiques and accessoires",
    "sg:phone":"+32 4 365 46 55",
    "sg:postcode":"4051",
    "sg:province":"Li\u00e8ge",
    "wof:name":"M.potvliege",
    "wof:placetype":"venue"
},
  "geometry": {"coordinates":[5.629650116,50.6044692993],"type":"Point"}
}