{
  "type": "Feature",
  "properties": {
    "addr:full":"Achttiende - Oogstwal 37b1 Tongeren Limburg 3700",
    "addr:housenumber":"37b1",
    "addr:postcode":"3700",
    "addr:street":"Oogstwal",
    "iso:country":"BE",
    "sg:address":"Achttiende - Oogstwal 37b1",
    "sg:city":"Tongeren",
    "sg:orig_category":"Avocats and conseillers juridiques",
    "sg:phone":"+32 12 23 01 37",
    "sg:postcode":"3700",
    "sg:province":"Limburg",
    "wof:name":"Alda Romain",
    "wof:placetype":"venue"
},
  "geometry": {"coordinates":[5.4694180489,50.7848205566],"type":"Point"}
}