{
  "type": "Feature",
  "properties": {
    "addr:full":"Rue Simonis 60 Elsene/ixelles Bruxelles-Capitale 1050",
    "addr:housenumber":"60",
    "addr:postcode":"1050",
    "addr:street":"Rue Simonis",
    "iso:country":"BE",
    "sg:address":"Rue Simonis 60",
    "sg:city":"Elsene/ixelles",
    "sg:orig_category":"Antiquit\u00e9s. Biens d'occasion",
    "sg:phone":"+32 2 647 32 71",
    "sg:postcode":"1050",
    "sg:province":"Bruxelles-Capitale",
    "wof:name":"Ivoire & Chagrin",
    "wof:placetype":"venue"
},
  "geometry": {"coordinates":[4.3602838516,50.8256416321],"type":"Point"}
}