{
  "type": "Feature",
  "properties": {
    "addr:full":"Barth\u00c9l\u00c9mylaan 20 Brussel/bruxelles Bruxelles-Capitale 1000",
    "addr:housenumber":"20",
    "addr:postcode":"1000",
    "addr:street":"Barthe\u0301Le\u0301Mylaan;/",
    "iso:country":"BE",
    "sg:address":"Barth\u00c9l\u00c9mylaan 20",
    "sg:city":"Brussel/bruxelles",
    "sg:orig_category":"Zalen voor culturele evenementen",
    "sg:phone":"+32 2 511 84 44",
    "sg:postcode":"1000",
    "sg:province":"Bruxelles-Capitale",
    "wof:name":"Galerie Windoows",
    "wof:placetype":"venue"
},
  "geometry": {"coordinates":[4.3406271935,50.8520126343],"type":"Point"}
}