{
  "type": "Feature",
  "properties": {
    "addr:full":"Grote Markt 7 Brussel/bruxelles Bruxelles-Capitale 1000",
    "addr:housenumber":"7",
    "addr:postcode":"1000",
    "addr:street":"Grote Markt;/",
    "iso:country":"BE",
    "sg:address":"Grote Markt 7",
    "sg:city":"Brussel/bruxelles",
    "sg:orig_category":"Diverse kredietdiensten",
    "sg:postcode":"1000",
    "sg:province":"Bruxelles-Capitale",
    "wof:name":"Bancontact-mister Cash",
    "wof:placetype":"venue"
},
  "geometry": {"coordinates":[4.3517889977,50.8469848633],"type":"Point"}
}