{
  "type": "Feature",
  "properties": {
    "iso:country":"BE",
    "sg:address":"Holdestraat 12ba",
    "sg:city":"Ardooie",
    "sg:classifiers":[
        {
            "category":"Taxi",
            "type":"Transportation"
        }
    ],
    "sg:phone":"+32 475 24 50 27",
    "sg:postcode":"8851",
    "sg:province":"West-Vlaanderen",
    "sg:tags":[
        "sp\u00e9ciaux"
    ],
    "wof:name":"Huur Een Stuur",
    "wof:placetype":"venue"
},
  "geometry": {"coordinates":[3.2009699345,51.0057411194],"type":"Point"}
}