{
  "type": "Feature",
  "properties": {
    "addr:full":"Hoornstraat 58 Damme West-Vlaanderen 8340",
    "addr:housenumber":"58",
    "addr:postcode":"8340",
    "addr:street":"Hoornstraat",
    "iso:country":"BE",
    "sg:address":"Hoornstraat 58",
    "sg:city":"Damme",
    "sg:orig_category":"Kapsalons",
    "sg:phone":"+32 50 50 17 50",
    "sg:postcode":"8340",
    "sg:province":"West-Vlaanderen",
    "wof:name":"Coiffure Capelli",
    "wof:placetype":"venue"
},
  "geometry": {"coordinates":[3.2815999985,51.2513160706],"type":"Point"}
}