{
  "type": "Feature",
  "properties": {
    "iso:country":"BE",
    "sg:address":"Diksmuidseweg 301ba",
    "sg:city":"Ieper",
    "sg:orig_category":"V\u00e9t\u00e9rinaires",
    "sg:phone":"+32 57 42 27 70",
    "sg:postcode":"8904",
    "sg:province":"West-Vlaanderen",
    "wof:name":"Marc Boussemaere",
    "wof:placetype":"venue"
},
  "geometry": {"coordinates":[2.8661680222,50.8872108459],"type":"Point"}
}