{
  "type": "Feature",
  "properties": {
    "addr:full":"Rue De L'eglise Saint-martin 138-140 Bruxelles (ganshoren) Bruxelles-Capitale 1083",
    "addr:postcode":"138-140;1083",
    "addr:street":"Rue De L'Eglise Saint-Martin",
    "iso:country":"BE",
    "sg:address":"Rue De L'eglise Saint-martin 138-140",
    "sg:city":"Bruxelles (ganshoren)",
    "sg:classifiers":[
        {
            "category":"Fast Food",
            "type":"Food & Drink"
        }
    ],
    "sg:phone":"+32 2 428 68 14",
    "sg:postcode":"1083",
    "sg:province":"Bruxelles-Capitale",
    "sg:tags":[
        "fried",
        "stand",
        "potato"
    ],
    "wof:name":"Friterie-restaur Le Ganshoren",
    "wof:placetype":"venue"
},
  "geometry": {"coordinates":[4.3133888245,50.873298645],"type":"Point"}
}