{
  "type": "Feature",
  "properties": {
    "addr:full":"Kauwentijnestraat 42 Lichtervelde West-Vlaanderen 8810",
    "addr:housenumber":"42",
    "addr:postcode":"8810",
    "addr:street":"Kauwentijnestraat",
    "iso:country":"BE",
    "sg:address":"Kauwentijnestraat 42",
    "sg:city":"Lichtervelde",
    "sg:orig_category":"R\u00e9alisation de programmes and logiciels. Ordinateurs and \u00e9quipement informatique",
    "sg:phone":"+32 51 72 66 55",
    "sg:postcode":"8810",
    "sg:province":"West-Vlaanderen",
    "wof:name":"Adg Soft",
    "wof:placetype":"venue"
},
  "geometry": {"coordinates":[3.1497709751,51.0280036926],"type":"Point"}
}