{
  "type": "Feature",
  "properties": {
    "addr:full":"Rue De L\u00b4ile Aux Corbeaux 51 Liege Li\u00e8ge 4000",
    "addr:housenumber":"51",
    "addr:postcode":"4000",
    "addr:street":"Rue De L\u00b4Ile Aux Corbeaux",
    "iso:country":"BE",
    "sg:address":"Rue De L\u00b4ile Aux Corbeaux 51",
    "sg:city":"Liege",
    "sg:orig_category":"Bouwmaterialen Gh Vloer- and muurbekleding",
    "sg:phone":"+32 4 252 95 91",
    "sg:postcode":"4000",
    "sg:province":"Li\u00e8ge",
    "wof:name":"Rossi Et Fils",
    "wof:placetype":"venue"
},
  "geometry": {"coordinates":[5.5541877747,50.6088485718],"type":"Point"}
}