{
  "type": "Feature",
  "properties": {
    "iso:country":"BE",
    "sg:address":"Bredabaan 156",
    "sg:city":"Brasschaat",
    "sg:classifiers":[
        {
            "category":"Fast Food",
            "type":"Food & Drink"
        }
    ],
    "sg:phone":"+32 3 653 05 12",
    "sg:postcode":"2930",
    "sg:province":"Antwerpen",
    "sg:tags":[
        "meeneem",
        "restaurant"
    ],
    "wof:name":"La Dolce Pitta",
    "wof:placetype":"venue"
},
  "geometry": {"coordinates":[4.4853291512,51.2867507935],"type":"Point"}
}