{
  "type": "Feature",
  "properties": {
    "iso:country":"BE",
    "sg:address":"Leegstraat 93",
    "sg:city":"Oostrozebeke",
    "sg:classifiers":[
        {
            "category":"Personal",
            "subcategory":"Beauty Salon",
            "type":"Services"
        }
    ],
    "sg:phone":"+32 56 66 76 24",
    "sg:postcode":"8780",
    "sg:province":"West-Vlaanderen",
    "sg:tags":[
        "lady",
        "-",
        "hairdressing"
    ],
    "wof:name":"Roos",
    "wof:placetype":"venue"
},
  "geometry": {"coordinates":[3.3180480003,50.917514801],"type":"Point"}
}