{
  "type": "Feature",
  "properties": {
    "addr:full":"Winkelomstraat 10 Bilzen Limburg 3740",
    "addr:housenumber":"10",
    "addr:postcode":"3740",
    "addr:street":"Winkelomstraat",
    "iso:country":"BE",
    "sg:address":"Winkelomstraat 10",
    "sg:city":"Bilzen",
    "sg:orig_category":"Enseignement maternel and primaire",
    "sg:phone":"+32 89 41 66 89",
    "sg:postcode":"3740",
    "sg:province":"Limburg",
    "wof:name":"Vrije Lagere School",
    "wof:placetype":"venue"
},
  "geometry": {"coordinates":[5.5768251419,50.874786377],"type":"Point"}
}