{
  "type": "Feature",
  "properties": {
    "addr:full":"Groenstraat 9 Heist-op-den-berg Antwerpen 2221",
    "addr:housenumber":"9",
    "addr:postcode":"2221",
    "addr:street":"Groenstraat",
    "iso:country":"BE",
    "sg:address":"Groenstraat 9",
    "sg:city":"Heist-op-den-berg",
    "sg:orig_category":"Kapsalons",
    "sg:phone":"+32 15 22 22 64",
    "sg:postcode":"2221",
    "sg:province":"Antwerpen",
    "wof:name":"Haarmode",
    "wof:placetype":"venue"
},
  "geometry": {"coordinates":[4.7739758492,51.0512428284],"type":"Point"}
}