{
  "type": "Feature",
  "properties": {
    "iso:country":"BE",
    "sg:address":"Karel De Goedelaan 13",
    "sg:city":"Torhout",
    "sg:classifiers":[
        {
            "category":"Health Services",
            "subcategory":"Health Practitioner",
            "type":"Services"
        }
    ],
    "sg:phone":"+32 50 21 76 80",
    "sg:postcode":"8820",
    "sg:province":"West-Vlaanderen",
    "sg:tags":[
        "physiotherapist"
    ],
    "wof:name":"Vandevijvere Jan",
    "wof:placetype":"venue"
},
  "geometry": {"coordinates":[3.0988368988,51.0690116882],"type":"Point"}
}