{
  "type": "Feature",
  "properties": {
    "iso:country":"BE",
    "sg:address":"Rue De Thiaumont 45",
    "sg:city":"Arlon",
    "sg:orig_category":"Sportclubs",
    "sg:phone":"+32 63 22 10 63",
    "sg:postcode":"6700",
    "sg:province":"Luxembourg",
    "wof:name":"U. Lorraine A.",
    "wof:placetype":"venue"
},
  "geometry": {"coordinates":[5.7433199883,49.703037262],"type":"Point"}
}