{
  "type": "Feature",
  "properties": {
    "addr:full":"Rogierlaan 278 Schaarbeek/schaerbeek Bruxelles-Capitale 1030",
    "addr:housenumber":"278",
    "addr:postcode":"1030",
    "addr:street":"Rogierlaan",
    "iso:country":"BE",
    "sg:address":"Rogierlaan 278",
    "sg:city":"Schaarbeek/schaerbeek",
    "sg:orig_category":"Plaatsen van vloer- and muurbekleding Pleisterwerk Schilders",
    "sg:phone":"+32 2 216 46 12",
    "sg:postcode":"1030",
    "sg:province":"Bruxelles-Capitale",
    "wof:name":"New House",
    "wof:placetype":"venue"
},
  "geometry": {"coordinates":[4.3892259598,50.8570480347],"type":"Point"}
}