{
  "type": "Feature",
  "properties": {
    "iso:country":"BE",
    "sg:address":"Brusselsestraat 4",
    "sg:city":"Leuven",
    "sg:orig_category":"Brood, gebak and snoepgoed",
    "sg:phone":"+32 16 20 41 43",
    "sg:postcode":"3000",
    "sg:province":"Vlaams-Brabant",
    "wof:name":"Panos",
    "wof:placetype":"venue"
},
  "geometry": {"coordinates":[4.7001051903,50.8793983459],"type":"Point"}
}