{
  "type": "Feature",
  "properties": {
    "iso:country":"BE",
    "sg:address":"Strandlaan 208",
    "sg:city":"Koksijde",
    "sg:classifiers":[
        {
            "category":"Health Services",
            "subcategory":"Health Practitioner",
            "type":"Services"
        }
    ],
    "sg:phone":"+32 58 51 58 24",
    "sg:postcode":"8670",
    "sg:province":"West-Vlaanderen",
    "sg:tags":[
        "physiotherapist"
    ],
    "wof:name":"Soenen Charlotte",
    "wof:placetype":"venue"
},
  "geometry": {"coordinates":[2.6142530441,51.1078910828],"type":"Point"}
}