{
  "type": "Feature",
  "properties": {
    "iso:country":"BE",
    "sg:address":"Kerkstraat 29b2",
    "sg:city":"Lummen",
    "sg:classifiers":[
        {
            "category":"Insurance",
            "subcategory":"Life Insurance",
            "type":"Services"
        }
    ],
    "sg:phone":"+32 13 52 10 05",
    "sg:postcode":"3560",
    "sg:province":"Limburg",
    "sg:tags":[
        "assurance"
    ],
    "wof:name":"L. Alenus",
    "wof:placetype":"venue"
},
  "geometry": {"coordinates":[5.1882109642,50.9855957031],"type":"Point"}
}