{
  "type": "Feature",
  "properties": {
    "addr:full":"Rue Des Cenelles 13 Verviers (petit-rechain) Li\u00e8ge 4800",
    "addr:housenumber":"13",
    "addr:postcode":"4800",
    "addr:street":"Rue Des Cenelles",
    "iso:country":"BE",
    "sg:address":"Rue Des Cenelles 13",
    "sg:city":"Verviers (petit-rechain)",
    "sg:classifiers":[
        {
            "category":"Professional",
            "subcategory":"Management & Consulting",
            "type":"Services"
        }
    ],
    "sg:phone":"+32 87 35 53 53",
    "sg:postcode":"4800",
    "sg:province":"Li\u00e8ge",
    "sg:tags":[
        "consultant"
    ],
    "wof:name":"Elan Consulting Sprl",
    "wof:placetype":"venue"
},
  "geometry": {"coordinates":[5.8594508171,50.5917663574],"type":"Point"}
}