{
  "type": "Feature",
  "properties": {
    "iso:country":"BE",
    "sg:address":"Nieuwstraat 8",
    "sg:city":"Glabbeek",
    "sg:orig_category":"Industri\u00eble and commerci\u00eble bouw Woningbouw",
    "sg:phone":"+32 16 77 08 89",
    "sg:postcode":"3380",
    "sg:province":"Vlaams-Brabant",
    "wof:name":"Efor",
    "wof:placetype":"venue"
},
  "geometry": {"coordinates":[4.9492759705,50.8734130859],"type":"Point"}
}