{
  "type": "Feature",
  "properties": {
    "addr:full":"Liersesteenweg 360 Mechelen Antwerpen 2800",
    "addr:housenumber":"360",
    "addr:postcode":"2800",
    "addr:street":"Liersesteenweg",
    "iso:country":"BE",
    "sg:address":"Liersesteenweg 360",
    "sg:city":"Mechelen",
    "sg:orig_category":"Jardinage",
    "sg:phone":"+32 15 20 96 19",
    "sg:postcode":"2800",
    "sg:province":"Antwerpen",
    "wof:name":"Vds",
    "wof:placetype":"venue"
},
  "geometry": {"coordinates":[4.4778847694,51.044670105],"type":"Point"}
}