{
  "type": "Feature",
  "properties": {
    "iso:country":"BE",
    "sg:address":"Rue Des Anglais 28",
    "sg:city":"Li\u00e8ge 1",
    "sg:classifiers":[
        {
            "category":"Professional",
            "subcategory":"Credit Reporting & Collection",
            "type":"Services"
        }
    ],
    "sg:phone":"+32 4 222 28 87",
    "sg:postcode":"4000",
    "sg:province":"Li\u00e8ge",
    "sg:tags":[
        "bailiff"
    ],
    "wof:name":"De Fooz F",
    "wof:placetype":"venue"
},
  "geometry": {"coordinates":[5.5687789917,50.6476287842],"type":"Point"}
}