{
  "type": "Feature",
  "properties": {
    "iso:country":"BE",
    "sg:address":"Pastorijstraat",
    "sg:city":"Kapelle-op-den-bos",
    "sg:orig_category":"Sportclubs",
    "sg:phone":"+32 15 71 33 19",
    "sg:postcode":"1880",
    "sg:province":"Vlaams-Brabant",
    "wof:name":"Aikido Club Shizen",
    "wof:placetype":"venue"
},
  "geometry": {"coordinates":[4.3561248779,51.0136795044],"type":"Point"}
}