{
  "type": "Feature",
  "properties": {
    "iso:country":"BE",
    "sg:address":"Klapperstraat 117",
    "sg:city":"Beveren (beveren-waas)",
    "sg:classifiers":[
        {
            "category":"Health Services",
            "subcategory":"Doctor",
            "type":"Services"
        }
    ],
    "sg:phone":"+32 3 775 03 19",
    "sg:postcode":"9120",
    "sg:province":"Oost-Vlaanderen",
    "sg:tags":[
        "medicinephysicians",
        "surgeon"
    ],
    "wof:name":"Beeldens Inge",
    "wof:placetype":"venue"
},
  "geometry": {"coordinates":[4.2452149391,51.2125549316],"type":"Point"}
}