{
  "type": "Feature",
  "properties": {
    "addr:full":"Rue De Fooz 153 Fexhe-le-haut-clocher Li\u00e8ge 4347",
    "addr:housenumber":"153",
    "addr:postcode":"4347",
    "addr:street":"Rue De Fooz;Fexhe-Le-Haut-Clocher Lie\u0300Ge",
    "iso:country":"BE",
    "sg:address":"Rue De Fooz 153",
    "sg:city":"Fexhe-le-haut-clocher",
    "sg:orig_category":"Agences de presse",
    "sg:phone":"+32 4 250 48 38",
    "sg:postcode":"4347",
    "sg:province":"Li\u00e8ge",
    "wof:name":"Jean-michel Crespin",
    "wof:placetype":"venue"
},
  "geometry": {"coordinates":[5.3996062279,50.6656455994],"type":"Point"}
}