{
  "type": "Feature",
  "properties": {
    "addr:full":"Lange Lozanastraat 142 Antwerpen Antwerpen 2018",
    "addr:housenumber":"142",
    "addr:postcode":"2018",
    "addr:street":"Lange Lozanastraat",
    "iso:country":"BE",
    "sg:address":"Lange Lozanastraat 142",
    "sg:city":"Antwerpen",
    "sg:orig_category":"Diverse opleidingen and onderwijs",
    "sg:phone":"+32 3 242 03 60",
    "sg:postcode":"2018",
    "sg:province":"Antwerpen",
    "wof:name":"Quest For Knowledge",
    "wof:placetype":"venue"
},
  "geometry": {"coordinates":[4.4147148132,51.2068824768],"type":"Point"}
}