{
  "type": "Feature",
  "properties": {
    "iso:country":"BE",
    "sg:address":"Strijbeekseweg 15",
    "sg:city":"Hoogstraten",
    "sg:classifiers":[
        {
            "category":"Cafe",
            "type":"Food & Drink"
        }
    ],
    "sg:phone":"+32 3 315 00 32",
    "sg:postcode":"2328",
    "sg:province":"Antwerpen",
    "sg:tags":[
        "caf\u00e9s"
    ],
    "wof:name":"Handelsondern. Goossen",
    "wof:placetype":"venue"
},
  "geometry": {"coordinates":[4.8041949272,51.4741134644],"type":"Point"}
}