{
  "type": "Feature",
  "properties": {
    "iso:country":"BE",
    "sg:address":"Rue Floris 62",
    "sg:city":"Schaarbeek/schaerbeek",
    "sg:orig_category":"V\u00eatements",
    "sg:phone":"+32 2 242 06 73",
    "sg:postcode":"1030",
    "sg:province":"Bruxelles-Capitale",
    "wof:name":"Herman Van Dorsselaer",
    "wof:placetype":"venue"
},
  "geometry": {"coordinates":[4.3708820343,50.8685264587],"type":"Point"}
}