{
  "type": "Feature",
  "properties": {
    "iso:country":"BE",
    "sg:address":"Rue De Dinant",
    "sg:city":"Rochefort",
    "sg:classifiers":[
        {
            "category":"Food & Beverages",
            "subcategory":"Supermarket",
            "type":"Retail Goods"
        }
    ],
    "sg:phone":"+32 84 21 02 75",
    "sg:postcode":"5580",
    "sg:province":"Namur",
    "sg:tags":[
        "department",
        "store"
    ],
    "wof:name":"Pasquasy",
    "wof:placetype":"venue"
},
  "geometry": {"coordinates":[5.2067451477,50.1670837402],"type":"Point"}
}