{
  "type": "Feature",
  "properties": {
    "iso:country":"BE",
    "sg:address":"Pauwstraat 138",
    "sg:city":"Lochristi",
    "sg:classifiers":[
        {
            "category":"Professional",
            "subcategory":"Management & Consulting",
            "type":"Services"
        }
    ],
    "sg:phone":"+32 9 356 69 66",
    "sg:postcode":"9080",
    "sg:province":"Oost-Vlaanderen",
    "sg:tags":[
        "-",
        "engineering",
        "electrical",
        "consultant"
    ],
    "wof:name":"Haco",
    "wof:placetype":"venue"
},
  "geometry": {"coordinates":[3.8601911068,51.0938568115],"type":"Point"}
}