{
  "type": "Feature",
  "properties": {
    "iso:country":"BE",
    "sg:address":"Rue Des Combattants 137",
    "sg:city":"La Hulpe",
    "sg:orig_category":"M\u00e9decins and sp\u00e9cialistes",
    "sg:phone":"+32 2 652 25 72",
    "sg:postcode":"1310",
    "sg:province":"Brabant Wallon",
    "wof:name":"Christian Boes",
    "wof:placetype":"venue"
},
  "geometry": {"coordinates":[4.4843320847,50.7305030823],"type":"Point"}
}