{
  "type": "Feature",
  "properties": {
    "addr:full":"Rue L\u00c9on Duray 61 La Louviere Hainaut 7110",
    "addr:housenumber":"61",
    "addr:postcode":"7110",
    "addr:street":"Rue Le\u0301On Duray",
    "iso:country":"BE",
    "sg:address":"Rue L\u00c9on Duray 61",
    "sg:city":"La Louviere",
    "sg:orig_category":"Meubles D\u00e9taillants, Am\u00e9nagement de B\u00e2timents et de Cuisines",
    "sg:phone":"+32 64 22 86 75",
    "sg:postcode":"7110",
    "sg:province":"Hainaut",
    "wof:name":"Louise Deridder",
    "wof:placetype":"venue"
},
  "geometry": {"coordinates":[4.1565041542,50.4851989746],"type":"Point"}
}