{
  "type": "Feature",
  "properties": {
    "addr:full":"Blaesstraat 191 Brussel/bruxelles Bruxelles-Capitale 1000",
    "addr:housenumber":"191",
    "addr:postcode":"1000",
    "addr:street":"Blaesstraat;/",
    "iso:country":"BE",
    "sg:address":"Blaesstraat 191",
    "sg:city":"Brussel/bruxelles",
    "sg:classifiers":[
        {
            "category":"Cafe",
            "type":"Food & Drink"
        }
    ],
    "sg:phone":"+32 2 513 10 73",
    "sg:postcode":"1000",
    "sg:province":"Bruxelles-Capitale",
    "sg:tags":[
        "caf\u00e9s"
    ],
    "wof:name":"Caf\u00c9 Mi\u00c8res",
    "wof:placetype":"venue"
},
  "geometry": {"coordinates":[4.3450231552,50.8361129761],"type":"Point"}
}