{
  "type": "Feature",
  "properties": {
    "addr:full":"Route De La Hesbaye 131b2 Eghez\u00c9e Namur 5310",
    "addr:housenumber":"131b2",
    "addr:postcode":"5310",
    "addr:street":"Route De La Hesbaye",
    "iso:country":"BE",
    "sg:address":"Route De La Hesbaye 131b2",
    "sg:city":"Eghez\u00c9e",
    "sg:orig_category":"Fleurs and plantes",
    "sg:phone":"+32 81 81 15 51",
    "sg:postcode":"5310",
    "sg:province":"Namur",
    "wof:name":"Pauline Fleurs",
    "wof:placetype":"venue"
},
  "geometry": {"coordinates":[4.9108800888,50.6137123108],"type":"Point"}
}