{
  "type": "Feature",
  "properties": {
    "iso:country":"BE",
    "sg:address":"Raatshovenstraat 2",
    "sg:city":"Landen",
    "sg:classifiers":[
        {
            "category":"Building & Trades",
            "subcategory":"Plumbing",
            "type":"Services"
        }
    ],
    "sg:phone":"+32 11 88 01 00",
    "sg:postcode":"3400",
    "sg:province":"Vlaams-Brabant",
    "sg:tags":[
        "cast-iron",
        "pipeline",
        "casting",
        "pressure"
    ],
    "wof:name":"Saint-gobin Pipe Systems Nv",
    "wof:placetype":"venue"
},
  "geometry": {"coordinates":[5.0768480301,50.7471885681],"type":"Point"}
}