{
  "type": "Feature",
  "properties": {
    "addr:full":"Rue Obecq 14 Waterloo Brabant Wallon 1410",
    "addr:housenumber":"14",
    "addr:postcode":"1410",
    "addr:street":"Rue Obecq",
    "iso:country":"BE",
    "sg:address":"Rue Obecq 14",
    "sg:city":"Waterloo",
    "sg:classifiers":[
        {
            "category":"Manufacturing",
            "subcategory":"Building Materials",
            "type":"Manufacturing & Wholesale Goods"
        }
    ],
    "sg:phone":"+32 2 354 89 11",
    "sg:postcode":"1410",
    "sg:province":"Brabant Wallon",
    "sg:tags":[
        "fixture",
        "store"
    ],
    "wof:name":"C.g.c. Sprl",
    "wof:placetype":"venue"
},
  "geometry": {"coordinates":[4.4040298462,50.7002563477],"type":"Point"}
}