{
  "type": "Feature",
  "properties": {
    "addr:full":"Rue Hazette 25 Chaudfontaine Li\u00e8ge 4053",
    "addr:housenumber":"25",
    "addr:postcode":"4053",
    "addr:street":"Rue Hazette",
    "iso:country":"BE",
    "sg:address":"Rue Hazette 25",
    "sg:city":"Chaudfontaine",
    "sg:orig_category":"Paramedische behandelingen",
    "sg:phone":"+32 4 367 13 39",
    "sg:postcode":"4053",
    "sg:province":"Li\u00e8ge",
    "wof:name":"D. Nyssen",
    "wof:placetype":"venue"
},
  "geometry": {"coordinates":[5.6072449684,50.5865592957],"type":"Point"}
}