{
  "type": "Feature",
  "properties": {
    "addr:full":"Rue Joseph Bens 39 Bruxelles (uccle) Bruxelles-Capitale 1180",
    "addr:housenumber":"39",
    "addr:postcode":"1180",
    "addr:street":"Rue Joseph Bens",
    "iso:country":"BE",
    "sg:address":"Rue Joseph Bens 39",
    "sg:city":"Bruxelles (uccle)",
    "sg:classifiers":[
        {
            "category":"Professional",
            "subcategory":"Management & Consulting",
            "type":"Services"
        }
    ],
    "sg:phone":"+32 2 343 42 64",
    "sg:postcode":"1180",
    "sg:province":"Bruxelles-Capitale",
    "sg:tags":[
        "consultant",
        "agency",
        "advertising"
    ],
    "wof:name":"Didier Gernay Conseil Sprl",
    "wof:placetype":"venue"
},
  "geometry": {"coordinates":[4.3350658417,50.8075904846],"type":"Point"}
}