{
  "type": "Feature",
  "properties": {
    "iso:country":"BE",
    "sg:address":"Camiel Vereeckelaan 1",
    "sg:city":"Deerlijk",
    "sg:orig_category":"Pain, p\u00e2tisseries and confiseries",
    "sg:phone":"+32 56 77 87 30",
    "sg:postcode":"8540",
    "sg:province":"West-Vlaanderen",
    "wof:name":"Pascal Windels",
    "wof:placetype":"venue"
},
  "geometry": {"coordinates":[3.3747990131,50.8226509094],"type":"Point"}
}