{
  "type": "Feature",
  "properties": {
    "iso:country":"BE",
    "sg:address":"Rue Du G\u00c9n\u00c9ral De Gaulle 149",
    "sg:city":"Courcelles",
    "sg:orig_category":"Installation de menuiserie en bois and plastique",
    "sg:phone":"+32 71 45 45 10",
    "sg:postcode":"6180",
    "sg:province":"Hainaut",
    "wof:name":"Eric Lefevre",
    "wof:placetype":"venue"
},
  "geometry": {"coordinates":[4.3821201324,50.4541397095],"type":"Point"}
}