{
  "type": "Feature",
  "properties": {
    "iso:country":"BE",
    "sg:address":"Massau 30",
    "sg:city":"Pepinster",
    "sg:classifiers":[
        {
            "category":"Health Services",
            "subcategory":"Health Practitioner",
            "type":"Services"
        }
    ],
    "sg:phone":"+32 87 46 91 34",
    "sg:postcode":"4860",
    "sg:province":"Li\u00e8ge",
    "sg:tags":[
        "physiotherapist"
    ],
    "wof:name":"Marique Alain",
    "wof:placetype":"venue"
},
  "geometry": {"coordinates":[5.8023509979,50.5696907043],"type":"Point"}
}