{
  "type": "Feature",
  "properties": {
    "iso:country":"BE",
    "sg:address":"Het Moer 5",
    "sg:city":"Heist-op-den-berg (booischot)",
    "sg:classifiers":[
        {
            "category":"Professional",
            "subcategory":"Accounting & Tax Preparation",
            "type":"Services"
        }
    ],
    "sg:phone":"+32 15 22 33 73",
    "sg:postcode":"2221",
    "sg:province":"Antwerpen",
    "sg:tags":[
        "bookkeeper"
    ],
    "wof:name":"D.c.l. Boekhoudkantoor Bvba",
    "wof:placetype":"venue"
},
  "geometry": {"coordinates":[4.7594060898,51.0350036621],"type":"Point"}
}