{
  "type": "Feature",
  "properties": {
    "iso:country":"BE",
    "sg:address":"Samelstraat 44",
    "sg:city":"Sint-gillis-waas",
    "sg:orig_category":"G\u00e9nie hydraulique",
    "sg:phone":"+32 3 770 69 40",
    "sg:postcode":"9170",
    "sg:province":"Oost-Vlaanderen",
    "wof:name":"De Roeck-teugels",
    "wof:placetype":"venue"
},
  "geometry": {"coordinates":[4.1378078461,51.2203788757],"type":"Point"}
}