{
  "type": "Feature",
  "properties": {
    "iso:country":"BE",
    "sg:address":"Rue Faftu 14a",
    "sg:city":"Nandrin",
    "sg:classifiers":[
        {
            "category":"Building & Trades",
            "subcategory":"Landscaping Services",
            "type":"Services"
        }
    ],
    "sg:phone":"+32 85 51 28 39",
    "sg:postcode":"4550",
    "sg:province":"Li\u00e8ge",
    "sg:tags":[
        "forestry"
    ],
    "wof:name":"Evelette M",
    "wof:placetype":"venue"
},
  "geometry": {"coordinates":[5.4396390915,50.5025291443],"type":"Point"}
}