{
  "type": "Feature",
  "properties": {
    "addr:full":"Av. Du Prince H\u00c9ritier 178 Sint-lambrechts-woluwe/woluwe-saint-lambert Bruxelles-Capitale 1200",
    "addr:housenumber":"178",
    "addr:postcode":"1200",
    "addr:street":"Av. Du Prince He\u0301Ritier",
    "iso:country":"BE",
    "sg:address":"Av. Du Prince H\u00c9ritier 178",
    "sg:city":"Sint-lambrechts-woluwe/woluwe-saint-lambert",
    "sg:orig_category":"Traitements param\u00e9dicaux. Instituts de beaut\u00e9",
    "sg:phone":"+32 2 736 82 69",
    "sg:postcode":"1200",
    "sg:province":"Bruxelles-Capitale",
    "wof:name":"Brillens",
    "wof:placetype":"venue"
},
  "geometry": {"coordinates":[4.4089221954,50.8465538025],"type":"Point"}
}