{
  "type": "Feature",
  "properties": {
    "iso:country":"BE",
    "sg:address":"Hoogledestraat 122",
    "sg:city":"Kortemark",
    "sg:classifiers":[
        {
            "category":"Autos & Motor Vehicles",
            "subcategory":"Auto Supplies",
            "type":"Retail Goods"
        }
    ],
    "sg:phone":"+32 51 57 05 77",
    "sg:postcode":"8610",
    "sg:province":"West-Vlaanderen",
    "sg:tags":[
        "semi-trailers",
        "industrial",
        "-",
        "trailer"
    ],
    "wof:name":"Lambrecht Nv",
    "wof:placetype":"venue"
},
  "geometry": {"coordinates":[3.0515100956,51.009059906],"type":"Point"}
}