{
  "type": "Feature",
  "properties": {
    "iso:country":"BE",
    "sg:address":"Avenue Des Platanes 12",
    "sg:city":"Li\u00c8ge",
    "sg:orig_category":"Artsen and specialisten",
    "sg:phone":"+32 4 253 59 00",
    "sg:postcode":"4000",
    "sg:province":"Li\u00e8ge",
    "wof:name":"Mich\u00c8le Thys",
    "wof:placetype":"venue"
},
  "geometry": {"coordinates":[5.561647892,50.6175193787],"type":"Point"}
}