{
  "type": "Feature",
  "properties": {
    "addr:full":"Avenue Des Jardins 33 Bruxelles (schaerbeek) Bruxelles-Capitale 1030",
    "addr:housenumber":"33",
    "addr:postcode":"1030",
    "addr:street":"Avenue Des Jardins",
    "iso:country":"BE",
    "sg:address":"Avenue Des Jardins 33",
    "sg:city":"Bruxelles (schaerbeek)",
    "sg:classifiers":[
        {
            "category":"Communications",
            "subcategory":"Film & Video Production",
            "type":"Services"
        }
    ],
    "sg:phone":"+32 2 726 89 19",
    "sg:postcode":"1030",
    "sg:province":"Bruxelles-Capitale",
    "sg:tags":[
        "realisation",
        "-"
    ],
    "wof:name":"I T P",
    "wof:placetype":"venue"
},
  "geometry": {"coordinates":[4.3992910385,50.8602104187],"type":"Point"}
}