{
  "type": "Feature",
  "properties": {
    "addr:full":"Zuidstraat 41b4b Roeselare West-Vlaanderen 8800",
    "addr:housenumber":"41b4b",
    "addr:postcode":"8800",
    "addr:street":"Zuidstraat",
    "iso:country":"BE",
    "sg:address":"Zuidstraat 41b4b",
    "sg:city":"Roeselare",
    "sg:orig_category":"Activit\u00e9s diverses d'imprimerie",
    "sg:phone":"+32 51 25 09 86",
    "sg:postcode":"8800",
    "sg:province":"West-Vlaanderen",
    "wof:name":"Bert Bartsoen",
    "wof:placetype":"venue"
},
  "geometry": {"coordinates":[3.1247150898,50.9422912598],"type":"Point"}
}