{
  "type": "Feature",
  "properties": {
    "addr:full":"Rue De Lahaut 10a Nassogne Luxembourg 6950",
    "addr:housenumber":"10a",
    "addr:postcode":"6950",
    "addr:street":"Rue De Lahaut",
    "iso:country":"BE",
    "sg:address":"Rue De Lahaut 10a",
    "sg:city":"Nassogne",
    "sg:orig_category":"Notarissen",
    "sg:phone":"+32 84 21 07 13",
    "sg:postcode":"6950",
    "sg:province":"Luxembourg",
    "wof:name":"E. Poncelet",
    "wof:placetype":"venue"
},
  "geometry": {"coordinates":[5.343752861,50.1281814575],"type":"Point"}
}