{
  "type": "Feature",
  "properties": {
    "iso:country":"BE",
    "sg:address":"Wayenborgstr 8",
    "sg:city":"Mechelen",
    "sg:classifiers":[
        {
            "category":"Manufacturing",
            "subcategory":"Tools & Machinery",
            "type":"Manufacturing & Wholesale Goods"
        }
    ],
    "sg:phone":"+32 15 20 22 55",
    "sg:postcode":"2800",
    "sg:province":"Antwerpen",
    "sg:tags":[
        "equipment",
        "measurement",
        "-",
        "precision",
        "instrument"
    ],
    "wof:name":"Biomedic Belgium Nv",
    "wof:placetype":"venue"
},
  "geometry": {"coordinates":[4.4426760674,51.0497131348],"type":"Point"}
}