{
  "type": "Feature",
  "properties": {
    "addr:full":"Kleemputte 15 Maldegem Oost-Vlaanderen 9991",
    "addr:housenumber":"15",
    "addr:postcode":"9991",
    "addr:street":"Kleemputte",
    "iso:country":"BE",
    "sg:address":"Kleemputte 15",
    "sg:city":"Maldegem",
    "sg:orig_category":"Bijouteries and horlogeries",
    "sg:phone":"+32 9 377 55 88",
    "sg:postcode":"9991",
    "sg:province":"Oost-Vlaanderen",
    "wof:name":"Jan Page",
    "wof:placetype":"venue"
},
  "geometry": {"coordinates":[3.5043609142,51.1809997559],"type":"Point"}
}