{
  "type": "Feature",
  "properties": {
    "addr:full":"Rue Du Progr\u00c8s 50 Bievre Namur 5555",
    "addr:housenumber":"50",
    "addr:postcode":"5555",
    "addr:street":"Rue Du Progre\u0300S",
    "iso:country":"BE",
    "sg:address":"Rue Du Progr\u00c8s 50",
    "sg:city":"Bievre",
    "sg:orig_category":"Rev\u00eatements pour sols and murs. Peinture",
    "sg:phone":"+32 61 51 10 80",
    "sg:postcode":"5555",
    "sg:province":"Namur",
    "wof:name":"Jaumotte Et Fils",
    "wof:placetype":"venue"
},
  "geometry": {"coordinates":[5.048789978,49.938331604],"type":"Point"}
}