{
  "type": "Feature",
  "properties": {
    "addr:full":"Boulevard Charles Van Pree 11 Nevele Brabant Wallon 1400",
    "addr:housenumber":"11",
    "addr:postcode":"1400",
    "addr:street":"Boulevard Charles Van Pree",
    "iso:country":"BE",
    "sg:address":"Boulevard Charles Van Pree 11",
    "sg:city":"Nevele",
    "sg:classifiers":[
        {
            "category":"Social Services",
            "subcategory":"Retirement Home",
            "type":"Services"
        }
    ],
    "sg:phone":"+32 67 21 30 55",
    "sg:postcode":"1400",
    "sg:province":"Brabant Wallon",
    "sg:tags":[
        "compagnies",
        "vie",
        "assurance",
        "habitation"
    ],
    "wof:name":"Romain Moutone",
    "wof:placetype":"venue"
},
  "geometry": {"coordinates":[4.328851223,50.5973358154],"type":"Point"}
}