{
  "type": "Feature",
  "properties": {
    "addr:full":"J. Coosemansstraat 9 Bruxelles Bruxelles-Capitale 1030",
    "addr:housenumber":"9",
    "addr:postcode":"1030",
    "addr:street":"J. Coosemansstraat",
    "iso:country":"BE",
    "sg:address":"J. Coosemansstraat 9",
    "sg:city":"Bruxelles",
    "sg:orig_category":"Sportclubs",
    "sg:phone":"+32 2 733 62 64",
    "sg:postcode":"1030",
    "sg:province":"Bruxelles-Capitale",
    "wof:name":"Aikido Met Ki",
    "wof:placetype":"venue"
},
  "geometry": {"coordinates":[4.3867092133,50.8537864685],"type":"Point"}
}