{
  "type": "Feature",
  "properties": {
    "addr:full":"Chauss\u00e9e De Mons 697-699 Bruxelles (anderlecht) Bruxelles-Capitale 1070",
    "addr:postcode":"697-699;1070",
    "addr:street":"Chausse\u0301E De Mons",
    "iso:country":"BE",
    "sg:address":"Chauss\u00e9e De Mons 697-699",
    "sg:city":"Bruxelles (anderlecht)",
    "sg:classifiers":[
        {
            "category":"Utilities",
            "subcategory":"Refuse",
            "type":"Services"
        }
    ],
    "sg:phone":"+32 2 344 77 44",
    "sg:postcode":"1070",
    "sg:province":"Bruxelles-Capitale",
    "sg:tags":[
        "removal"
    ],
    "wof:name":"Potiez-deman",
    "wof:placetype":"venue"
},
  "geometry": {"coordinates":[4.3085021973,50.8306007385],"type":"Point"}
}