{
  "type": "Feature",
  "properties": {
    "iso:country":"BE",
    "sg:address":"Spoorwegstraat 16-18",
    "sg:city":"Halen (zelem)",
    "sg:classifiers":[
        {
            "category":"Health Services",
            "subcategory":"Health Practitioner",
            "type":"Services"
        }
    ],
    "sg:phone":"+32 13 44 13 02",
    "sg:postcode":"3545",
    "sg:province":"Limburg",
    "sg:tags":[
        "physiotherapist"
    ],
    "wof:name":"Vanhaeren Marcel",
    "wof:placetype":"venue"
},
  "geometry": {"coordinates":[5.1213498116,50.9786987305],"type":"Point"}
}