{
  "type": "Feature",
  "properties": {
    "iso:country":"BE",
    "sg:address":"Rue G\u00e9n\u00e9raux Cuvelier 3",
    "sg:city":"Florenville",
    "sg:classifiers":[
        {
            "category":"Bakery",
            "type":"Food & Drink"
        }
    ],
    "sg:phone":"+32 61 31 12 13",
    "sg:postcode":"6820",
    "sg:province":"Luxembourg",
    "sg:tags":[
        "confectioner",
        "baker"
    ],
    "wof:name":"Henrotte G Ets",
    "wof:placetype":"venue"
},
  "geometry": {"coordinates":[5.3121480942,49.6979026794],"type":"Point"}
}