{
  "type": "Feature",
  "properties": {
    "addr:full":"Mulk 120 Hamont-achel Limburg 3930",
    "addr:housenumber":"120",
    "addr:postcode":"3930",
    "addr:street":"Mulk",
    "iso:country":"BE",
    "sg:address":"Mulk 120",
    "sg:city":"Hamont-achel",
    "sg:orig_category":"Rundveehouders",
    "sg:phone":"+32 11 44 69 80",
    "sg:postcode":"3930",
    "sg:province":"Limburg",
    "wof:name":"Maria Janssen",
    "wof:placetype":"venue"
},
  "geometry": {"coordinates":[5.5450549126,51.2511863708],"type":"Point"}
}