{
  "type": "Feature",
  "properties": {
    "iso:country":"BE",
    "sg:address":"Onkerzelestraat 54",
    "sg:city":"Geraardsbergen",
    "sg:orig_category":"M\u00e9decins and sp\u00e9cialistes",
    "sg:phone":"+32 54 42 16 92",
    "sg:postcode":"9500",
    "sg:province":"Oost-Vlaanderen",
    "wof:name":"I. Vanholme",
    "wof:placetype":"venue"
},
  "geometry": {"coordinates":[3.8943850994,50.7744750977],"type":"Point"}
}