{
  "type": "Feature",
  "properties": {
    "iso:country":"BE",
    "sg:address":"Rue Du Centre 53",
    "sg:city":"Ciney",
    "sg:classifiers":[
        {
            "category":"Professional",
            "subcategory":"Art Services",
            "type":"Services"
        }
    ],
    "sg:phone":"+32 83 21 15 52",
    "sg:postcode":"5590",
    "sg:province":"Namur",
    "sg:tags":[
        "picture",
        "framer"
    ],
    "wof:name":"Laloux Encadrement",
    "wof:placetype":"venue"
},
  "geometry": {"coordinates":[5.1015877724,50.2964706421],"type":"Point"}
}