{
  "type": "Feature",
  "properties": {
    "iso:country":"BE",
    "sg:address":"Leopoldwal 6",
    "sg:city":"Tongeren",
    "sg:orig_category":"Advocaten and juridische adviseurs",
    "sg:phone":"+32 12 23 03 31",
    "sg:postcode":"3700",
    "sg:province":"Limburg",
    "wof:name":"Kris Huysmans",
    "wof:placetype":"venue"
},
  "geometry": {"coordinates":[5.4711828232,50.7827453613],"type":"Point"}
}