{
  "type": "Feature",
  "properties": {
    "iso:country":"BE",
    "sg:address":"Hinnenboomstraat 15",
    "sg:city":"Hoogstraten",
    "sg:orig_category":"Binnenhuisarchitecten",
    "sg:phone":"+32 3 314 93 07",
    "sg:postcode":"2320",
    "sg:province":"Antwerpen",
    "wof:name":"H. Lippens",
    "wof:placetype":"venue"
},
  "geometry": {"coordinates":[4.7242717743,51.410736084],"type":"Point"}
}