{
  "type": "Feature",
  "properties": {
    "addr:full":"Damendreef Oud-heverlee (haasrode) Vlaams-Brabant 3053",
    "addr:postcode":"3053",
    "addr:street":"Vlaams-Brabant",
    "iso:country":"BE",
    "sg:address":"Damendreef",
    "sg:city":"Oud-heverlee (haasrode)",
    "sg:classifiers":[
        {
            "category":"Retail",
            "subcategory":"Animal Services",
            "type":"Services"
        }
    ],
    "sg:phone":"+32 16 44 52 71",
    "sg:postcode":"3053",
    "sg:province":"Vlaams-Brabant",
    "sg:tags":[
        "training",
        "dog"
    ],
    "wof:name":"Pavlon-leuven",
    "wof:placetype":"venue"
},
  "geometry": {"coordinates":[4.7275500298,50.8341712952],"type":"Point"}
}