{
  "type": "Feature",
  "properties": {
    "iso:country":"BE",
    "sg:address":"Place Josse Goffin 19ba",
    "sg:city":"Tubize",
    "sg:orig_category":"Benzinestations and brandstoffen",
    "sg:phone":"+32 2 355 07 79",
    "sg:postcode":"1480",
    "sg:province":"Brabant Wallon",
    "wof:name":"Al Qudus",
    "wof:placetype":"venue"
},
  "geometry": {"coordinates":[4.2213959694,50.6893234253],"type":"Point"}
}