{
  "type": "Feature",
  "properties": {
    "addr:full":"Chauss\u00e9e De Wavre 150 Gembloux-sur-orneau (gembloux) Namur 5030",
    "addr:housenumber":"150",
    "addr:postcode":"5030",
    "addr:street":"Chausse\u0301E De Wavre;Namur",
    "iso:country":"BE",
    "sg:address":"Chauss\u00e9e De Wavre 150",
    "sg:city":"Gembloux-sur-orneau (gembloux)",
    "sg:classifiers":[
        {
            "category":"Farming",
            "subcategory":"Farm & Veterinary Services",
            "type":"Manufacturing & Wholesale Goods"
        }
    ],
    "sg:phone":"+32 81 61 40 12",
    "sg:postcode":"5030",
    "sg:province":"Namur",
    "sg:tags":[
        "agricultural",
        "contractor"
    ],
    "wof:name":"Capagri Scrl",
    "wof:placetype":"venue"
},
  "geometry": {"coordinates":[4.684928894,50.5821304321],"type":"Point"}
}