{
  "type": "Feature",
  "properties": {
    "iso:country":"BE",
    "sg:address":"Muizenvenstraat 5",
    "sg:city":"Turnhout",
    "sg:classifiers":[
        {
            "category":"Manufacturing",
            "subcategory":"Printing",
            "type":"Manufacturing & Wholesale Goods"
        }
    ],
    "sg:phone":"+32 14 42 27 26",
    "sg:postcode":"2300",
    "sg:province":"Antwerpen",
    "sg:tags":[
        "publishing"
    ],
    "wof:name":"Drukkerij Matthys - Beccu Bvba",
    "wof:placetype":"venue"
},
  "geometry": {"coordinates":[4.9220671654,51.3063735962],"type":"Point"}
}