{
  "type": "Feature",
  "properties": {
    "iso:country":"BE",
    "sg:address":"Bakkereel 24",
    "sg:city":"Ronse/renaix",
    "sg:orig_category":"Slagers",
    "sg:phone":"+32 55 20 71 25",
    "sg:postcode":"9600",
    "sg:province":"Oost-Vlaanderen",
    "wof:name":"Dirk De Roose",
    "wof:placetype":"venue"
},
  "geometry": {"coordinates":[3.5717060566,50.7434692383],"type":"Point"}
}