{
  "type": "Feature",
  "properties": {
    "iso:country":"BE",
    "sg:address":"Maleveld 48",
    "sg:city":"Brugge (sint-kruis)",
    "sg:orig_category":"Non-Classified Establishments",
    "sg:phone":"+32 50 37 04 12",
    "sg:postcode":"8310",
    "sg:province":"West-Vlaanderen",
    "wof:name":"Lamote-pieters R",
    "wof:placetype":"venue"
},
  "geometry": {"coordinates":[3.2796599865,51.2128486633],"type":"Point"}
}