{
  "type": "Feature",
  "properties": {
    "iso:country":"BE",
    "sg:address":"Voie De Li\u00c8ge 31",
    "sg:city":"Soumagne",
    "sg:orig_category":"Software ontwikkeling and ontwerp",
    "sg:phone":"+32 4 342 30 06",
    "sg:postcode":"4630",
    "sg:province":"Li\u00e8ge",
    "wof:name":"Twenty - Twenty Belgium",
    "wof:placetype":"venue"
},
  "geometry": {"coordinates":[5.71920681,50.6152763367],"type":"Point"}
}