{
  "type": "Feature",
  "properties": {
    "addr:full":"Rue Des Quatre Fils Aymon 17a Lessines Hainaut 7860",
    "addr:housenumber":"17a",
    "addr:postcode":"7860",
    "addr:street":"Rue Des Quatre Fils Aymon;Hainaut",
    "iso:country":"BE",
    "sg:address":"Rue Des Quatre Fils Aymon 17a",
    "sg:city":"Lessines",
    "sg:orig_category":"Activit\u00e9s r\u00e9cr\u00e9atives diverses",
    "sg:phone":"+32 68 33 44 91",
    "sg:postcode":"7860",
    "sg:province":"Hainaut",
    "wof:name":"L'echiquier Lessinois",
    "wof:placetype":"venue"
},
  "geometry": {"coordinates":[3.8343150616,50.7125053406],"type":"Point"}
}