{
  "type": "Feature",
  "properties": {
    "addr:full":"Heysellaan 22 Vilvoorde Vlaams-Brabant 1800",
    "addr:housenumber":"22",
    "addr:postcode":"1800",
    "addr:street":"Heysellaan",
    "iso:country":"BE",
    "sg:address":"Heysellaan 22",
    "sg:city":"Vilvoorde",
    "sg:classifiers":[
        {
            "category":"Health Services",
            "subcategory":"Health Practitioner",
            "type":"Services"
        }
    ],
    "sg:phone":"+32 2 267 11 53",
    "sg:postcode":"1800",
    "sg:province":"Vlaams-Brabant",
    "sg:tags":[
        "physiotherapist"
    ],
    "wof:name":"Emmerechts L",
    "wof:placetype":"venue"
},
  "geometry": {"coordinates":[4.3684902191,50.9004173279],"type":"Point"}
}