{
  "type": "Feature",
  "properties": {
    "addr:full":"Rue Du Tige 96 Herstal Li\u00e8ge 4040",
    "addr:housenumber":"96",
    "addr:postcode":"4040",
    "addr:street":"Rue Du Tige",
    "iso:country":"BE",
    "sg:address":"Rue Du Tige 96",
    "sg:city":"Herstal",
    "sg:orig_category":"Installation de menuiserie m\u00e9tallique. Installation \u00e9lectrique r\u00e9sidentielle",
    "sg:phone":"+32 4 240 21 08",
    "sg:postcode":"4040",
    "sg:province":"Li\u00e8ge",
    "wof:name":"Henri Dejardin",
    "wof:placetype":"venue"
},
  "geometry": {"coordinates":[5.6362709999,50.6717910767],"type":"Point"}
}