{
  "type": "Feature",
  "properties": {
    "addr:full":"Sint-jozefsstraat 12 Knokke-heist West-Vlaanderen 8301",
    "addr:housenumber":"12",
    "addr:postcode":"8301",
    "addr:street":"Sint-Jozefsstraat",
    "iso:country":"BE",
    "sg:address":"Sint-jozefsstraat 12",
    "sg:city":"Knokke-heist",
    "sg:orig_category":"Banques and organismes de cr\u00e9dit",
    "sg:phone":"+32 50 51 22 83",
    "sg:postcode":"8301",
    "sg:province":"West-Vlaanderen",
    "wof:name":"Citibank",
    "wof:placetype":"venue"
},
  "geometry": {"coordinates":[3.2639000416,51.3396911621],"type":"Point"}
}