{
  "type": "Feature",
  "properties": {
    "iso:country":"BE",
    "sg:address":"Provinciestraat 131-133",
    "sg:city":"Antwerpen",
    "sg:classifiers":[
        {
            "category":"Autos & Motor Vehicles",
            "subcategory":"Auto Supplies",
            "type":"Retail Goods"
        }
    ],
    "sg:phone":"+32 3 236 50 79",
    "sg:postcode":"2018",
    "sg:province":"Antwerpen",
    "sg:tags":[
        "access",
        "automobile",
        "part",
        "-"
    ],
    "wof:name":"Aydin",
    "wof:placetype":"venue"
},
  "geometry": {"coordinates":[4.4261579514,51.213596344],"type":"Point"}
}