{
  "type": "Feature",
  "properties": {
    "iso:country":"BE",
    "sg:address":"Ten Akkerdreef 83",
    "sg:city":"Kortrijk",
    "sg:classifiers":[
        {
            "category":"Health Services",
            "subcategory":"Health Practitioner",
            "type":"Services"
        }
    ],
    "sg:phone":"+32 56 20 08 51",
    "sg:postcode":"8500",
    "sg:province":"West-Vlaanderen",
    "sg:tags":[
        "physiotherapist"
    ],
    "wof:name":"Braems P",
    "wof:placetype":"venue"
},
  "geometry": {"coordinates":[3.2770040035,50.8206748962],"type":"Point"}
}