{
  "type": "Feature",
  "properties": {
    "addr:full":"Rue Des Buissons 46 Li\u00c8ge Li\u00e8ge 4000",
    "addr:housenumber":"46",
    "addr:postcode":"4000",
    "addr:street":"Rue Des Buissons",
    "iso:country":"BE",
    "sg:address":"Rue Des Buissons 46",
    "sg:city":"Li\u00c8ge",
    "sg:classifiers":[
        {
            "category":"Communications",
            "subcategory":"Television Station",
            "type":"Services"
        }
    ],
    "sg:phone":"+32 4 224 02 92",
    "sg:postcode":"4000",
    "sg:province":"Li\u00e8ge",
    "sg:tags":[
        "video",
        "audio",
        "verhuur"
    ],
    "wof:name":"Val\u00c9rie Coune",
    "wof:placetype":"venue"
},
  "geometry": {"coordinates":[5.5664200783,50.6521148682],"type":"Point"}
}