{
  "type": "Feature",
  "properties": {
    "addr:full":"Rue De La Presse 21 Brussel/bruxelles Bruxelles-Capitale 1000",
    "addr:housenumber":"21",
    "addr:postcode":"1000",
    "addr:street":"Rue De La;/",
    "iso:country":"BE",
    "sg:address":"Rue De La Presse 21",
    "sg:city":"Brussel/bruxelles",
    "sg:classifiers":[
        {
            "category":"Fast Food",
            "type":"Food & Drink"
        }
    ],
    "sg:phone":"+32 2 217 38 31",
    "sg:postcode":"1000",
    "sg:province":"Bruxelles-Capitale",
    "sg:tags":[
        "\u00c0",
        "restaurants",
        "emporter",
        "restaurant"
    ],
    "wof:name":"Astrid Chez Pierrot",
    "wof:placetype":"venue"
},
  "geometry": {"coordinates":[4.3665452003,50.8488426208],"type":"Point"}
}