{
  "type": "Feature",
  "properties": {
    "iso:country":"BE",
    "sg:address":"Voie Des Sauvages M\u00cal\u00c9es 34",
    "sg:city":"Bl\u00c9gny",
    "sg:orig_category":"Architectes",
    "sg:phone":"+32 4 370 66 73",
    "sg:postcode":"4671",
    "sg:province":"Li\u00e8ge",
    "wof:name":"Michel Mackowiak",
    "wof:placetype":"venue"
},
  "geometry": {"coordinates":[5.6737599373,50.6458282471],"type":"Point"}
}