{
  "type": "Feature",
  "properties": {
    "addr:full":"Goorbaan 43 Herselt Antwerpen 2230",
    "addr:housenumber":"43",
    "addr:postcode":"2230",
    "addr:street":"Goorbaan",
    "iso:country":"BE",
    "sg:address":"Goorbaan 43",
    "sg:city":"Herselt",
    "sg:classifiers":[
        {
            "category":"Home & Garden",
            "subcategory":"Kitchen Supply",
            "type":"Retail Goods"
        }
    ],
    "sg:phone":"+32 14 54 62 45",
    "sg:postcode":"2230",
    "sg:province":"Antwerpen",
    "sg:tags":[
        "installation"
    ],
    "wof:name":"Maes-mans Bvba",
    "wof:placetype":"venue"
},
  "geometry": {"coordinates":[4.9193601608,51.048160553],"type":"Point"}
}