{
  "type": "Feature",
  "properties": {
    "iso:country":"BE",
    "sg:address":"Grijspeerdstraat 57",
    "sg:city":"Hooglede (gits)",
    "sg:classifiers":[
        {
            "category":"Home & Garden",
            "subcategory":"Carpets & Floor Coverings",
            "type":"Retail Goods"
        }
    ],
    "sg:phone":"+32 478 42 00 09",
    "sg:postcode":"8830",
    "sg:province":"West-Vlaanderen",
    "sg:tags":[
        "tile"
    ],
    "wof:name":"Decoster K",
    "wof:placetype":"venue"
},
  "geometry": {"coordinates":[3.0935070515,51.0007476807],"type":"Point"}
}