{
  "type": "Feature",
  "properties": {
    "iso:country":"BE",
    "sg:address":"Eduard Arsenstraat 95",
    "sg:city":"Mortsel",
    "sg:orig_category":"Cr\u00e8ches and garderies d'enfants",
    "sg:phone":"+32 3 449 63 14",
    "sg:postcode":"2640",
    "sg:province":"Antwerpen",
    "wof:name":"Nougatine",
    "wof:placetype":"venue"
},
  "geometry": {"coordinates":[4.4437479973,51.1705703735],"type":"Point"}
}