{
  "type": "Feature",
  "properties": {
    "addr:full":"Eikhof 20 Heusden-zolder (zolder) Limburg 3550",
    "addr:housenumber":"20",
    "addr:postcode":"3550",
    "addr:street":"Eikhof",
    "iso:country":"BE",
    "sg:address":"Eikhof 20",
    "sg:city":"Heusden-zolder (zolder)",
    "sg:classifiers":[
        {
            "category":"Communications",
            "subcategory":"News Services",
            "type":"Services"
        }
    ],
    "sg:phone":"+32 11 53 30 63",
    "sg:postcode":"3550",
    "sg:province":"Limburg",
    "sg:tags":[
        "illustrator"
    ],
    "wof:name":"Bob Karikatuuranimatie",
    "wof:placetype":"venue"
},
  "geometry": {"coordinates":[5.277618885,51.0153846741],"type":"Point"}
}