{
  "type": "Feature",
  "properties": {
    "iso:country":"BE",
    "sg:address":"Kortrijkstraat 248",
    "sg:city":"Menen",
    "sg:orig_category":"Fabrication and montage de mobilier. Mat\u00e9riel pour plomberie and chauffage Mat\u00e9riaux de construction",
    "sg:phone":"+32 56 51 36 51",
    "sg:postcode":"8930",
    "sg:province":"West-Vlaanderen",
    "wof:name":"Dupont",
    "wof:placetype":"venue"
},
  "geometry": {"coordinates":[3.1305088997,50.7981987],"type":"Point"}
}