{
  "type": "Feature",
  "properties": {
    "addr:full":"Diestsestraat 94 Leuven Vlaams-Brabant 3000",
    "addr:housenumber":"94",
    "addr:postcode":"3000",
    "addr:street":"Diestsestraat",
    "iso:country":"BE",
    "sg:address":"Diestsestraat 94",
    "sg:city":"Leuven",
    "sg:orig_category":"Brood, gebak and snoepgoed",
    "sg:phone":"+32 16 20 30 29",
    "sg:postcode":"3000",
    "sg:province":"Vlaams-Brabant",
    "wof:name":"Boutique D\u00c9lifrance",
    "wof:placetype":"venue"
},
  "geometry": {"coordinates":[4.7074899673,50.8806381226],"type":"Point"}
}