{
  "type": "Feature",
  "properties": {
    "iso:country":"BE",
    "sg:address":"Turnhousebaan 370",
    "sg:city":"Schilde",
    "sg:classifiers":[
        {
            "category":"Restaurant",
            "type":"Food & Drink"
        }
    ],
    "sg:phone":"+32 3 385 92 97",
    "sg:postcode":"2970",
    "sg:province":"Antwerpen",
    "wof:name":"Le Caveau",
    "wof:placetype":"venue"
},
  "geometry": {"coordinates":[4.5878062248,51.2425384521],"type":"Point"}
}