{
  "type": "Feature",
  "properties": {
    "addr:full":"Ontmijnersstraat 1 Blankenberge West-Vlaanderen 8370",
    "addr:housenumber":"1",
    "addr:postcode":"8370",
    "addr:street":"Ontmijnersstraat",
    "iso:country":"BE",
    "sg:address":"Ontmijnersstraat 1",
    "sg:city":"Blankenberge",
    "sg:classifiers":[
        {
            "category":"Shopping",
            "subcategory":"Florist",
            "type":"Retail Goods"
        }
    ],
    "sg:phone":"+32 50 41 96 55",
    "sg:postcode":"8370",
    "sg:province":"West-Vlaanderen",
    "wof:name":"Iris",
    "wof:placetype":"venue"
},
  "geometry": {"coordinates":[3.1316111088,51.3120307922],"type":"Point"}
}