{
  "type": "Feature",
  "properties": {
    "addr:full":"Rue De La Poire D'or 16 Mons (cuesmes) Hainaut 7033",
    "addr:housenumber":"16",
    "addr:postcode":"7033",
    "addr:street":"Rue De La Poire D'Or",
    "iso:country":"BE",
    "sg:address":"Rue De La Poire D'or 16",
    "sg:city":"Mons (cuesmes)",
    "sg:classifiers":[
        {
            "category":"Insurance",
            "subcategory":"Insurance Agent",
            "type":"Services"
        }
    ],
    "sg:phone":"+32 65 40 11 74",
    "sg:postcode":"7033",
    "sg:province":"Hainaut",
    "sg:tags":[
        "broker"
    ],
    "wof:name":"Cuesmes-assur",
    "wof:placetype":"venue"
},
  "geometry": {"coordinates":[3.9233601093,50.4335708618],"type":"Point"}
}