{
  "type": "Feature",
  "properties": {
    "iso:country":"BE",
    "sg:address":"Mimosasstraat 46",
    "sg:city":"Schaarbeek/schaerbeek",
    "sg:orig_category":"Architecten",
    "sg:phone":"+32 2 245 66 05",
    "sg:postcode":"1030",
    "sg:province":"Bruxelles-Capitale",
    "wof:name":"Bernard Kirsch",
    "wof:placetype":"venue"
},
  "geometry": {"coordinates":[4.3884720802,50.8638420105],"type":"Point"}
}