{
  "type": "Feature",
  "properties": {
    "iso:country":"BE",
    "sg:address":"Rue Du Zodiaque 16",
    "sg:city":"Bruxelles (forest)",
    "sg:classifiers":[
        {
            "category":"Professional",
            "type":"Services"
        }
    ],
    "sg:phone":"+32 2 345 28 60",
    "sg:postcode":"1190",
    "sg:province":"Bruxelles-Capitale",
    "sg:tags":[
        "entertainer"
    ],
    "wof:name":"Dujardin X",
    "wof:placetype":"venue"
},
  "geometry": {"coordinates":[4.3451957703,50.8173751831],"type":"Point"}
}