{
  "type": "Feature",
  "properties": {
    "iso:country":"BE",
    "sg:address":"Rue Adolphe P\u00e9cher 1",
    "sg:city":"Mons",
    "sg:classifiers":[
        {
            "category":"Professional",
            "type":"Services"
        }
    ],
    "sg:phone":"+32 65 31 66 81",
    "sg:postcode":"7000",
    "sg:province":"Hainaut",
    "sg:tags":[
        "auction",
        "room"
    ],
    "wof:name":"Troc Land",
    "wof:placetype":"venue"
},
  "geometry": {"coordinates":[3.9443700314,50.449420929],"type":"Point"}
}