{
  "type": "Feature",
  "properties": {
    "addr:full":"Rue Fond-pirette 128 Li\u00e8ge 1 Li\u00e8ge 4000",
    "addr:housenumber":"128;1",
    "addr:postcode":"4000",
    "addr:street":"Rue Fond-Pirette",
    "iso:country":"BE",
    "sg:address":"Rue Fond-pirette 128",
    "sg:city":"Li\u00e8ge 1",
    "sg:classifiers":[
        {
            "category":"Retail",
            "subcategory":"Auto Repair",
            "type":"Services"
        }
    ],
    "sg:phone":"+32 4 226 19 64",
    "sg:postcode":"4000",
    "sg:province":"Li\u00e8ge",
    "sg:tags":[
        "garage"
    ],
    "wof:name":"Spallina",
    "wof:placetype":"venue"
},
  "geometry": {"coordinates":[5.5689811707,50.6507034302],"type":"Point"}
}