{
  "type": "Feature",
  "properties": {
    "addr:full":"Voie De L\u00b4ardenne 139 Chaudfontaine Li\u00e8ge 4053",
    "addr:housenumber":"139",
    "addr:postcode":"4053",
    "addr:street":"Voie De L\u00b4Ardenne",
    "iso:country":"BE",
    "sg:address":"Voie De L\u00b4ardenne 139",
    "sg:city":"Chaudfontaine",
    "sg:orig_category":"Assurances. Evaluation and estimation de biens immobiliers",
    "sg:phone":"+32 4 368 68 50",
    "sg:postcode":"4053",
    "sg:province":"Li\u00e8ge",
    "wof:name":"Sud Services",
    "wof:placetype":"venue"
},
  "geometry": {"coordinates":[5.6115179062,50.5872268677],"type":"Point"}
}