{
  "type": "Feature",
  "properties": {
    "iso:country":"BE",
    "sg:address":"Avenue Moli\u00c8re 43",
    "sg:city":"Waver",
    "sg:orig_category":"Diverse bedrijfsbeheeradviesbureaus",
    "sg:phone":"+32 10 22 56 12",
    "sg:postcode":"1300",
    "sg:province":"Brabant Wallon",
    "wof:name":"Proconsult",
    "wof:placetype":"venue"
},
  "geometry": {"coordinates":[4.6347308159,50.707233429],"type":"Point"}
}