{
  "type": "Feature",
  "properties": {
    "iso:country":"BE",
    "sg:address":"Mechelsesteenweg 366",
    "sg:city":"Herent",
    "sg:orig_category":"Royal Canin. Animaux domestiques and accessoires",
    "sg:phone":"+32 16 23 19 96",
    "sg:postcode":"3020",
    "sg:province":"Vlaams-Brabant",
    "wof:name":"Missoul",
    "wof:placetype":"venue"
},
  "geometry": {"coordinates":[4.6744499207,50.9034194946],"type":"Point"}
}