{
  "type": "Feature",
  "properties": {
    "addr:full":"Grote Baan 39 Lovendegem Oost-Vlaanderen 9920",
    "addr:housenumber":"39",
    "addr:postcode":"9920",
    "addr:street":"Grote Baan",
    "iso:country":"BE",
    "sg:address":"Grote Baan 39",
    "sg:city":"Lovendegem",
    "sg:orig_category":"Elektrische installaties voor woningen Huishoudapparaten, televisies and radio's Loodgieterij, verwa",
    "sg:phone":"+32 9 372 72 72",
    "sg:postcode":"9920",
    "sg:province":"Oost-Vlaanderen",
    "wof:name":"Elektrotechniek",
    "wof:placetype":"venue"
},
  "geometry": {"coordinates":[3.6412479877,51.0953140259],"type":"Point"}
}