{
  "type": "Feature",
  "properties": {
    "iso:country":"BE",
    "sg:address":"Kwakkelstraat 151",
    "sg:city":"Turnhout",
    "sg:orig_category":"Mat\u00e9riel de T\u00e9l\u00e9communication. D\u00e9taillants en pi\u00e8ces and accessoires de voitures",
    "sg:phone":"+32 14 41 02 88",
    "sg:postcode":"2300",
    "sg:province":"Antwerpen",
    "wof:name":"Ataf Car Electronics",
    "wof:placetype":"venue"
},
  "geometry": {"coordinates":[4.9575948715,51.3159103394],"type":"Point"}
}