{
  "type": "Feature",
  "properties": {
    "addr:full":"Steenweg Deinze 125a Nazareth Oost-Vlaanderen 9810",
    "addr:housenumber":"125a",
    "addr:postcode":"9810",
    "addr:street":"Steenweg Deinze",
    "iso:country":"BE",
    "sg:address":"Steenweg Deinze 125a",
    "sg:city":"Nazareth",
    "sg:classifiers":[
        {
            "category":"Personal",
            "subcategory":"Beauty Salon",
            "type":"Services"
        }
    ],
    "sg:phone":"+32 9 384 40 37",
    "sg:postcode":"9810",
    "sg:province":"Oost-Vlaanderen",
    "wof:name":"Oliebos M",
    "wof:placetype":"venue"
},
  "geometry": {"coordinates":[3.591573,50.942489624],"type":"Point"}
}