{
  "type": "Feature",
  "properties": {
    "iso:country":"BE",
    "sg:address":"Rue Du Beau-moulin 14",
    "sg:city":"Ch\u00c2telet",
    "sg:orig_category":"Medische apparatuur, orthopedische artikelen and prothesen Fab",
    "sg:phone":"+32 71 38 44 04",
    "sg:postcode":"6200",
    "sg:province":"Hainaut",
    "wof:name":"Jean-jacques Zandavalli",
    "wof:placetype":"venue"
},
  "geometry": {"coordinates":[4.5161700249,50.4019737244],"type":"Point"}
}