{
  "type": "Feature",
  "properties": {
    "addr:full":"Plaatsstraat 31 Galmaarden (tollembeek) Vlaams-Brabant 1570",
    "addr:housenumber":"31",
    "addr:postcode":"1570",
    "addr:street":"Plaatsstraat",
    "iso:country":"BE",
    "sg:address":"Plaatsstraat 31",
    "sg:city":"Galmaarden (tollembeek)",
    "sg:classifiers":[
        {
            "category":"Personal",
            "subcategory":"Beauty Salon",
            "type":"Services"
        }
    ],
    "sg:phone":"+32 54 58 02 00",
    "sg:postcode":"1570",
    "sg:province":"Vlaams-Brabant",
    "sg:tags":[
        "lady",
        "-",
        "hairdressing"
    ],
    "wof:name":"Knip En Krul Mireille",
    "wof:placetype":"venue"
},
  "geometry": {"coordinates":[4.0036978722,50.7423400879],"type":"Point"}
}