{
  "type": "Feature",
  "properties": {
    "addr:full":"Galerie Kennedy Rixensart Brabant Wallon 1330",
    "addr:postcode":"1330",
    "addr:street":"Brabant Wallon",
    "iso:country":"BE",
    "sg:address":"Galerie Kennedy",
    "sg:city":"Rixensart",
    "sg:classifiers":[
        {
            "category":"Cafe",
            "type":"Food & Drink"
        }
    ],
    "sg:phone":"+32 2 653 48 27",
    "sg:postcode":"1330",
    "sg:province":"Brabant Wallon",
    "sg:tags":[
        "snack-bars"
    ],
    "wof:name":"Panth\u00e8re Rose (la)",
    "wof:placetype":"venue"
},
  "geometry": {"coordinates":[4.5209498405,50.7110290527],"type":"Point"}
}