{
  "type": "Feature",
  "properties": {
    "iso:country":"BE",
    "sg:address":"Heierveld 46",
    "sg:city":"Asse",
    "sg:orig_category":"M\u00e9decins and sp\u00e9cialistes",
    "sg:phone":"+32 2 452 60 25",
    "sg:postcode":"1730",
    "sg:province":"Vlaams-Brabant",
    "wof:name":"Tony Peeters",
    "wof:placetype":"venue"
},
  "geometry": {"coordinates":[4.2326469421,50.9062538147],"type":"Point"}
}