{
  "type": "Feature",
  "properties": {
    "iso:country":"BE",
    "sg:address":"Sint-kristoffelstraat 14",
    "sg:city":"Brugge (assebroek)",
    "sg:classifiers":[
        {
            "category":"Building & Trades",
            "subcategory":"Construction",
            "type":"Services"
        }
    ],
    "sg:phone":"+32 50 37 20 58",
    "sg:postcode":"8310",
    "sg:province":"West-Vlaanderen",
    "sg:tags":[
        "carpenter"
    ],
    "wof:name":"Bonte G",
    "wof:placetype":"venue"
},
  "geometry": {"coordinates":[3.2497739792,51.2025184631],"type":"Point"}
}