{
  "type": "Feature",
  "properties": {
    "addr:full":"Ottogracht 51 Gent Oost-Vlaanderen 9000",
    "addr:housenumber":"51",
    "addr:postcode":"9000",
    "addr:street":"Ottogracht;Oost-Vlaanderen",
    "iso:country":"BE",
    "sg:address":"Ottogracht 51",
    "sg:city":"Gent",
    "sg:classifiers":[
        {
            "category":"Shopping",
            "subcategory":"Bicycles & Sporting Goods",
            "type":"Retail Goods"
        }
    ],
    "sg:phone":"+32 9 223 57 47",
    "sg:postcode":"9000",
    "sg:province":"Oost-Vlaanderen",
    "sg:tags":[
        "tyre"
    ],
    "wof:name":"Gentse Bandencentrale",
    "wof:placetype":"venue"
},
  "geometry": {"coordinates":[3.7268259525,51.0587387085],"type":"Point"}
}