{
  "type": "Feature",
  "properties": {
    "iso:country":"BE",
    "sg:address":"Rue De L'ecole 13",
    "sg:city":"Houffalize",
    "sg:orig_category":"Enseignement maternel and primaire",
    "sg:phone":"+32 61 28 93 59",
    "sg:postcode":"6666",
    "sg:province":"Luxembourg",
    "wof:name":"Ecole Fond. Communale",
    "wof:placetype":"venue"
},
  "geometry": {"coordinates":[5.7190799713,50.1673698425],"type":"Point"}
}