{
  "type": "Feature",
  "properties": {
    "addr:full":"Kapelstraat 12 Hechtel-eksel Limburg 3941",
    "addr:housenumber":"12",
    "addr:postcode":"3941",
    "addr:street":"Kapelstraat",
    "iso:country":"BE",
    "sg:address":"Kapelstraat 12",
    "sg:city":"Hechtel-eksel",
    "sg:orig_category":"Dansscholen",
    "sg:phone":"+32 11 73 10 88",
    "sg:postcode":"3941",
    "sg:province":"Limburg",
    "wof:name":"Dansliga Sportfederatie",
    "wof:placetype":"venue"
},
  "geometry": {"coordinates":[5.3937678337,51.1521987915],"type":"Point"}
}