{
  "type": "Feature",
  "properties": {
    "addr:full":"Avenue Charles Quint 46 Ganshoren Bruxelles-Capitale 1083",
    "addr:housenumber":"46",
    "addr:postcode":"1083",
    "addr:street":"Avenue Charles Quint",
    "iso:country":"BE",
    "sg:address":"Avenue Charles Quint 46",
    "sg:city":"Ganshoren",
    "sg:classifiers":[
        {
            "category":"Fast Food",
            "type":"Food & Drink"
        }
    ],
    "sg:phone":"+32 2 420 76 80",
    "sg:postcode":"1083",
    "sg:province":"Bruxelles-Capitale",
    "sg:tags":[
        "\u00c0",
        "restaurants",
        "emporter",
        "restaurant"
    ],
    "wof:name":"Le Grand Alexandre",
    "wof:placetype":"venue"
},
  "geometry": {"coordinates":[4.3121538162,50.868598938],"type":"Point"}
}