{
  "type": "Feature",
  "properties": {
    "iso:country":"BE",
    "sg:address":"Maria Theresiastraat 59",
    "sg:city":"Oostende",
    "sg:classifiers":[
        {
            "category":"Cafe",
            "type":"Food & Drink"
        }
    ],
    "sg:phone":"+32 59 70 24 48",
    "sg:postcode":"8400",
    "sg:province":"West-Vlaanderen",
    "sg:tags":[
        "caf\u00e9s"
    ],
    "wof:name":"Roger Vanhoecke",
    "wof:placetype":"venue"
},
  "geometry": {"coordinates":[2.9047551155,51.2249298096],"type":"Point"}
}