{
  "type": "Feature",
  "properties": {
    "iso:country":"BE",
    "sg:address":"Ieperstraat 15c",
    "sg:city":"Wevelgem (moorsele)",
    "sg:classifiers":[
        {
            "category":"Home & Garden",
            "subcategory":"Building Materials",
            "type":"Retail Goods"
        }
    ],
    "sg:phone":"+32 56 42 65 09",
    "sg:postcode":"8560",
    "sg:province":"West-Vlaanderen",
    "sg:tags":[
        "veranda"
    ],
    "wof:name":"Perdu",
    "wof:placetype":"venue"
},
  "geometry": {"coordinates":[3.2126309872,50.8359298706],"type":"Point"}
}