{
  "type": "Feature",
  "properties": {
    "iso:country":"BE",
    "sg:address":"Ossebilkstraat 44",
    "sg:city":"Zedelgem (aartrijke)",
    "sg:classifiers":[
        {
            "category":"Home & Garden",
            "subcategory":"Garden Supply",
            "type":"Retail Goods"
        }
    ],
    "sg:phone":"+32 50 20 87 93",
    "sg:postcode":"8211",
    "sg:province":"West-Vlaanderen",
    "wof:name":"Simaey-onraedt",
    "wof:placetype":"venue"
},
  "geometry": {"coordinates":[3.0889649391,51.1200408936],"type":"Point"}
}