{
  "type": "Feature",
  "properties": {
    "iso:country":"BE",
    "sg:address":"Rijkendalstraat 50",
    "sg:city":"Grimbergen (strombeek-bever)",
    "sg:classifiers":[
        {
            "category":"Banks & Credit Unions",
            "subcategory":"Investment Brokerage",
            "type":"Services"
        }
    ],
    "sg:phone":"+32 2 267 13 04",
    "sg:postcode":"1853",
    "sg:province":"Vlaams-Brabant",
    "sg:tags":[
        "repair",
        "-",
        "installation",
        "sanitary",
        "article"
    ],
    "wof:name":"Vanderhulst F",
    "wof:placetype":"venue"
},
  "geometry": {"coordinates":[4.3572540283,50.9064788818],"type":"Point"}
}