{
  "type": "Feature",
  "properties": {
    "addr:full":"Rue Mont Leville 58b60 Colfontaine Hainaut 7340",
    "addr:housenumber":"58b60",
    "addr:postcode":"7340",
    "addr:street":"Rue Mont",
    "iso:country":"BE",
    "sg:address":"Rue Mont Leville 58b60",
    "sg:city":"Colfontaine",
    "sg:orig_category":"HERSTELLING ELEKTRISCHE HUISHOUDAPPARATEN Huishoudapparaten, televisies and radio's",
    "sg:phone":"+32 65 78 50 88",
    "sg:postcode":"7340",
    "sg:province":"Hainaut",
    "wof:name":"Ets. Gevenois",
    "wof:placetype":"venue"
},
  "geometry": {"coordinates":[3.8422889709,50.4196014404],"type":"Point"}
}