{
  "type": "Feature",
  "properties": {
    "iso:country":"BE",
    "sg:address":"Rue De La Station 42",
    "sg:city":"Bl\u00e9gny (trembleur)",
    "sg:orig_category":"Autombile concessionaires",
    "sg:phone":"+32 4 387 41 08",
    "sg:postcode":"4670",
    "sg:province":"Li\u00e8ge",
    "wof:name":"Ets Thomassin Sprl",
    "wof:placetype":"venue"
},
  "geometry": {"coordinates":[5.7242379189,50.6755943298],"type":"Point"}
}