{
  "type": "Feature",
  "properties": {
    "addr:full":"Ave. Ch.woeste 156 Brussel-jette Bruxelles-Capitale 1090",
    "addr:housenumber":"156",
    "addr:postcode":"1090",
    "addr:street":"Ave.;Brussel-Jette",
    "iso:country":"BE",
    "sg:address":"Ave. Ch.woeste 156",
    "sg:city":"Brussel-jette",
    "sg:classifiers":[
        {
            "category":"Building & Trades",
            "subcategory":"Construction",
            "type":"Services"
        }
    ],
    "sg:phone":"+32 2 421 78 78",
    "sg:postcode":"1090",
    "sg:province":"Bruxelles-Capitale",
    "sg:tags":[
        "siemens",
        "fujitsu"
    ],
    "wof:name":"Dwesab Engineering",
    "wof:placetype":"venue"
},
  "geometry": {"coordinates":[4.3341321945,50.8740959167],"type":"Point"}
}