{
  "type": "Feature",
  "properties": {
    "iso:country":"BE",
    "sg:address":"Chauss\u00e9e De Philippeville 11",
    "sg:city":"Couvin (mariembourg)",
    "sg:classifiers":[
        {
            "category":"Bars & Pubs",
            "type":"Food & Drink"
        }
    ],
    "sg:phone":"+32 60 31 31 16",
    "sg:postcode":"5660",
    "sg:province":"Namur",
    "sg:tags":[
        "tavern"
    ],
    "wof:name":"La Houblonni\u00e8re",
    "wof:placetype":"venue"
},
  "geometry": {"coordinates":[4.5098872185,50.0972061157],"type":"Point"}
}