{
  "type": "Feature",
  "properties": {
    "iso:country":"BE",
    "sg:address":"Rue Jean Vinois 18",
    "sg:city":"Ellezelles",
    "sg:orig_category":"Huisdieren and benodigdheden Sport- and kampeermateriaal",
    "sg:phone":"+32 68 54 37 14",
    "sg:postcode":"7890",
    "sg:province":"Hainaut",
    "wof:name":"Palais Oiseaux Et P\u00cache",
    "wof:placetype":"venue"
},
  "geometry": {"coordinates":[3.6812040806,50.7330589294],"type":"Point"}
}