{
  "type": "Feature",
  "properties": {
    "addr:full":"Hooiwege 12 Evergem Oost-Vlaanderen 9940",
    "addr:housenumber":"12",
    "addr:postcode":"9940",
    "addr:street":"Hooiwege;Oost-Vlaanderen",
    "iso:country":"BE",
    "sg:address":"Hooiwege 12",
    "sg:city":"Evergem",
    "sg:orig_category":"Bloemen and planten Bloemen and planten Gh",
    "sg:phone":"+32 9 357 35 59",
    "sg:postcode":"9940",
    "sg:province":"Oost-Vlaanderen",
    "wof:name":"Erik De Somviele",
    "wof:placetype":"venue"
},
  "geometry": {"coordinates":[3.6787250042,51.1386528015],"type":"Point"}
}