{
  "type": "Feature",
  "properties": {
    "iso:country":"BE",
    "sg:address":"Berthoutstraat 45",
    "sg:city":"Boechout (vremde)",
    "sg:classifiers":[
        {
            "category":"Home & Garden",
            "subcategory":"Building Materials",
            "type":"Retail Goods"
        }
    ],
    "sg:phone":"+32 3 455 95 56",
    "sg:postcode":"2531",
    "sg:province":"Antwerpen",
    "sg:tags":[
        "insect",
        "screen"
    ],
    "wof:name":"Vliegske ('t)",
    "wof:placetype":"venue"
},
  "geometry": {"coordinates":[4.5286989212,51.1737174988],"type":"Point"}
}