{
  "type": "Feature",
  "properties": {
    "iso:country":"BE",
    "sg:address":"Chauss\u00c9e Romaine 147",
    "sg:city":"Gembloux",
    "sg:orig_category":"Biens d'occasion",
    "sg:phone":"+32 81 61 12 11",
    "sg:postcode":"5030",
    "sg:province":"Namur",
    "wof:name":"Brocanteur Collignon",
    "wof:placetype":"venue"
},
  "geometry": {"coordinates":[4.6849861145,50.579284668],"type":"Point"}
}