{
  "type": "Feature",
  "properties": {
    "addr:full":"Elyzeese Velden 12 Gent Oost-Vlaanderen 9000",
    "addr:housenumber":"12",
    "addr:postcode":"9000",
    "addr:street":"Elyzeese Velden;Oost-Vlaanderen",
    "iso:country":"BE",
    "sg:address":"Elyzeese Velden 12",
    "sg:city":"Gent",
    "sg:orig_category":"Fotografen and fotostudio's",
    "sg:phone":"+32 9 233 53 57",
    "sg:postcode":"9000",
    "sg:province":"Oost-Vlaanderen",
    "wof:name":"Anne Deknock",
    "wof:placetype":"venue"
},
  "geometry": {"coordinates":[3.7048420906,51.0617599487],"type":"Point"}
}