{
  "type": "Feature",
  "properties": {
    "addr:full":"Gustave Latinislaan 125ba Schaarbeek/schaerbeek Bruxelles-Capitale 1030",
    "addr:postcode":"1030",
    "addr:street":"Gustave Latinislaan 125Ba",
    "iso:country":"BE",
    "sg:address":"Gustave Latinislaan 125ba",
    "sg:city":"Schaarbeek/schaerbeek",
    "sg:orig_category":"Boekhouders",
    "sg:phone":"+32 2 245 45 06",
    "sg:postcode":"1030",
    "sg:province":"Bruxelles-Capitale",
    "wof:name":"Pascale Broden",
    "wof:placetype":"venue"
},
  "geometry": {"coordinates":[4.3903861046,50.8637619019],"type":"Point"}
}