{
  "type": "Feature",
  "properties": {
    "iso:country":"BE",
    "sg:address":"Resedaslaan 19",
    "sg:city":"Koksijde",
    "sg:orig_category":"Artistes ind\u00e9pendants",
    "sg:phone":"+32 58 51 72 00",
    "sg:postcode":"8670",
    "sg:province":"West-Vlaanderen",
    "wof:name":"Yves Boullet",
    "wof:placetype":"venue"
},
  "geometry": {"coordinates":[2.6271150112,51.1083488464],"type":"Point"}
}