{
  "type": "Feature",
  "properties": {
    "addr:full":"Kerkstraat 6 De Haan West-Vlaanderen 8420",
    "addr:housenumber":"6",
    "addr:postcode":"8420",
    "addr:street":"Kerkstraat",
    "iso:country":"BE",
    "sg:address":"Kerkstraat 6",
    "sg:city":"De Haan",
    "sg:classifiers":[
        {
            "category":"Restaurant",
            "type":"Food & Drink"
        }
    ],
    "sg:phone":"+32 50 41 19 09",
    "sg:postcode":"8420",
    "sg:province":"West-Vlaanderen",
    "wof:name":"Rita",
    "wof:placetype":"venue"
},
  "geometry": {"coordinates":[3.0796089172,51.3009986877],"type":"Point"}
}