{
  "type": "Feature",
  "properties": {
    "iso:country":"BE",
    "sg:address":"Oneux 123",
    "sg:city":"Comblain-au-pont",
    "sg:orig_category":"Eleveurs de bovins",
    "sg:phone":"+32 4 369 13 05",
    "sg:postcode":"4170",
    "sg:province":"Li\u00e8ge",
    "wof:name":"Lemmens Martin & Andree",
    "wof:placetype":"venue"
},
  "geometry": {"coordinates":[5.5984921455,50.4738082886],"type":"Point"}
}