{
  "type": "Feature",
  "properties": {
    "iso:country":"BE",
    "sg:address":"Place Communale 1",
    "sg:city":"La Bruy\u00e8re (rhisnes)",
    "sg:classifiers":[
        {
            "category":"Health Services",
            "subcategory":"Nursing And Care Facility",
            "type":"Services"
        }
    ],
    "sg:phone":"+32 81 56 05 34",
    "sg:postcode":"5080",
    "sg:province":"Namur",
    "sg:tags":[
        "home"
    ],
    "wof:name":"Warnimont Jacqueline",
    "wof:placetype":"venue"
},
  "geometry": {"coordinates":[4.8040151596,50.5057487488],"type":"Point"}
}