{
  "type": "Feature",
  "properties": {
    "addr:full":"Chemin De Reumont 46 Namur Namur 5020",
    "addr:housenumber":"46",
    "addr:postcode":"5020",
    "addr:street":"Chemin De Reumont",
    "iso:country":"BE",
    "sg:address":"Chemin De Reumont 46",
    "sg:city":"Namur",
    "sg:orig_category":"Activit\u00e9s diverses d'imprimerie",
    "sg:phone":"+32 81 45 01 73",
    "sg:postcode":"5020",
    "sg:province":"Namur",
    "wof:name":"F. Clabots",
    "wof:placetype":"venue"
},
  "geometry": {"coordinates":[4.8123531342,50.4317092896],"type":"Point"}
}