{
  "type": "Feature",
  "properties": {
    "addr:full":"Rue Bosquet 58 Sint-gillis/saint-gilles Bruxelles-Capitale 1060",
    "addr:housenumber":"58",
    "addr:postcode":"1060",
    "addr:street":"Rue Bosquet",
    "iso:country":"BE",
    "sg:address":"Rue Bosquet 58",
    "sg:city":"Sint-gillis/saint-gilles",
    "sg:classifiers":[
        {
            "category":"Restaurant",
            "type":"Food & Drink"
        }
    ],
    "sg:phone":"+32 2 537 48 16",
    "sg:postcode":"1060",
    "sg:province":"Bruxelles-Capitale",
    "wof:name":"La Rusticana",
    "wof:placetype":"venue"
},
  "geometry": {"coordinates":[4.3530569077,50.833442688],"type":"Point"}
}