{
  "type": "Feature",
  "properties": {
    "iso:country":"BE",
    "sg:address":"Albert I Laan 201",
    "sg:city":"Nieuwpoort",
    "sg:orig_category":"Slagers",
    "sg:phone":"+32 58 23 32 30",
    "sg:postcode":"8620",
    "sg:province":"West-Vlaanderen",
    "wof:name":"Christophe Blanckaert",
    "wof:placetype":"venue"
},
  "geometry": {"coordinates":[2.7167000771,51.1486816406],"type":"Point"}
}