{
  "type": "Feature",
  "properties": {
    "iso:country":"BE",
    "sg:address":"Livinus Walravenslaan 9",
    "sg:city":"Dilbeek",
    "sg:classifiers":[
        {
            "category":"Professional",
            "subcategory":"Accounting & Tax Preparation",
            "type":"Services"
        }
    ],
    "sg:phone":"+32 2 567 90 70",
    "sg:postcode":"1700",
    "sg:province":"Vlaams-Brabant",
    "sg:tags":[
        "accountant"
    ],
    "wof:name":"Nguyen Thi Khanh T",
    "wof:placetype":"venue"
},
  "geometry": {"coordinates":[4.2774868011,50.8442497253],"type":"Point"}
}