{
  "type": "Feature",
  "properties": {
    "iso:country":"BE",
    "sg:address":"Parklaan",
    "sg:city":"Sint-niklaas (groot)",
    "sg:orig_category":"Tijdelijke werkgelegenheid and uitzendkantoren",
    "sg:phone":"+32 3 777 06 43",
    "sg:postcode":"9100",
    "sg:province":"Oost-Vlaanderen",
    "wof:name":"Tulikivi - Ago Interim",
    "wof:placetype":"venue"
},
  "geometry": {"coordinates":[4.1472501755,51.1605949402],"type":"Point"}
}