{
  "type": "Feature",
  "properties": {
    "addr:full":"Rue Des Fran\u00e7ais 15 Charleroi (dampremy) Hainaut 6020",
    "addr:housenumber":"15",
    "addr:postcode":"6020",
    "addr:street":"Rue Des Franc\u0327Ais",
    "iso:country":"BE",
    "sg:address":"Rue Des Fran\u00e7ais 15",
    "sg:city":"Charleroi (dampremy)",
    "sg:classifiers":[
        {
            "category":"Food & Beverages",
            "subcategory":"Groceries & Convenience Stores",
            "type":"Retail Goods"
        }
    ],
    "sg:phone":"+32 71 32 74 01",
    "sg:postcode":"6020",
    "sg:province":"Hainaut",
    "sg:tags":[
        "grocer"
    ],
    "wof:name":"Ori\u00ebnt",
    "wof:placetype":"venue"
},
  "geometry": {"coordinates":[4.4389820099,50.4219932556],"type":"Point"}
}