{
  "type": "Feature",
  "properties": {
    "addr:full":"Oude Diestersebaan 95 Lommel Limburg 3920",
    "addr:housenumber":"95",
    "addr:postcode":"3920",
    "addr:street":"Oude Diestersebaan",
    "iso:country":"BE",
    "sg:address":"Oude Diestersebaan 95",
    "sg:city":"Lommel",
    "sg:classifiers":[
        {
            "category":"Communications",
            "subcategory":"Television Station",
            "type":"Services"
        }
    ],
    "sg:phone":"+32 477 57 52 52",
    "sg:postcode":"3920",
    "sg:province":"Limburg",
    "sg:tags":[
        "antenna"
    ],
    "wof:name":"All-sat Kerremans",
    "wof:placetype":"venue"
},
  "geometry": {"coordinates":[5.3127179146,51.2010765076],"type":"Point"}
}