{
  "type": "Feature",
  "properties": {
    "addr:full":"Rue De Reckem 22 Mouscron Hainaut 7700",
    "addr:housenumber":"22",
    "addr:postcode":"7700",
    "addr:street":"Rue De Reckem",
    "iso:country":"BE",
    "sg:address":"Rue De Reckem 22",
    "sg:city":"Mouscron",
    "sg:classifiers":[
        {
            "category":"Manufacturing",
            "subcategory":"Metals",
            "type":"Manufacturing & Wholesale Goods"
        }
    ],
    "sg:phone":"+32 56 33 27 80",
    "sg:postcode":"7700",
    "sg:province":"Hainaut",
    "sg:tags":[
        "ornamental",
        "work",
        "-"
    ],
    "wof:name":"Theuninck L",
    "wof:placetype":"venue"
},
  "geometry": {"coordinates":[3.197067976,50.7523803711],"type":"Point"}
}