{
  "type": "Feature",
  "properties": {
    "addr:full":"Rue Albert De Latour 46 Schaarbeek/schaerbeek Bruxelles-Capitale 1030",
    "addr:housenumber":"46",
    "addr:postcode":"1030",
    "addr:street":"Rue Albert De Latour",
    "iso:country":"BE",
    "sg:address":"Rue Albert De Latour 46",
    "sg:city":"Schaarbeek/schaerbeek",
    "sg:orig_category":"M\u00e9decins and sp\u00e9cialistes",
    "sg:phone":"+32 2 241 85 48",
    "sg:postcode":"1030",
    "sg:province":"Bruxelles-Capitale",
    "wof:name":"Vincenzo Ettore Buscemi",
    "wof:placetype":"venue"
},
  "geometry": {"coordinates":[4.3812041283,50.8556442261],"type":"Point"}
}