{
  "type": "Feature",
  "properties": {
    "addr:full":"Sint-pieterskaai 71-75 Brugge West-Vlaanderen 8000",
    "addr:postcode":"71-75;8000",
    "addr:street":"Sint-Pieterskaai",
    "iso:country":"BE",
    "sg:address":"Sint-pieterskaai 71-75",
    "sg:city":"Brugge",
    "sg:orig_category":"Verhuisdiensten",
    "sg:phone":"+32 50 44 61 60",
    "sg:postcode":"8000",
    "sg:province":"West-Vlaanderen",
    "wof:name":"Shurgard Self-storage",
    "wof:placetype":"venue"
},
  "geometry": {"coordinates":[3.2246630192,51.2227668762],"type":"Point"}
}