{
  "type": "Feature",
  "properties": {
    "addr:full":"Halledorp 142 Zoersel Antwerpen 2980",
    "addr:housenumber":"142",
    "addr:postcode":"2980",
    "addr:street":"Halledorp",
    "iso:country":"BE",
    "sg:address":"Halledorp 142",
    "sg:city":"Zoersel",
    "sg:classifiers":[
        {
            "category":"Restaurant",
            "type":"Food & Drink"
        }
    ],
    "sg:phone":"+32 3 385 85 00",
    "sg:postcode":"2980",
    "sg:province":"Antwerpen",
    "wof:name":"'t Open Vuur",
    "wof:placetype":"venue"
},
  "geometry": {"coordinates":[4.6403970718,51.2406158447],"type":"Point"}
}