{
  "type": "Feature",
  "properties": {
    "addr:full":"Avelgemstraat 234 Zwevegem West-Vlaanderen 8550",
    "addr:housenumber":"234",
    "addr:postcode":"8550",
    "addr:street":"Avelgemstraat",
    "iso:country":"BE",
    "sg:address":"Avelgemstraat 234",
    "sg:city":"Zwevegem",
    "sg:orig_category":"Pharmaciens",
    "sg:phone":"+32 56 75 76 33",
    "sg:postcode":"8550",
    "sg:province":"West-Vlaanderen",
    "wof:name":"Rita Vercruysse",
    "wof:placetype":"venue"
},
  "geometry": {"coordinates":[3.3479480743,50.8013420105],"type":"Point"}
}