{
  "type": "Feature",
  "properties": {
    "iso:country":"BE",
    "sg:address":"Kapellestraat 55",
    "sg:city":"Evergem",
    "sg:classifiers":[
        {
            "category":"Real Estate",
            "subcategory":"Real Estate Services",
            "type":"Services"
        }
    ],
    "sg:phone":"+32 9 253 85 19",
    "sg:postcode":"9940",
    "sg:province":"Oost-Vlaanderen",
    "wof:name":"Immo Vercruysse",
    "wof:placetype":"venue"
},
  "geometry": {"coordinates":[3.7103869915,51.1121902466],"type":"Point"}
}