{
  "type": "Feature",
  "properties": {
    "addr:full":"Baksveld 24 Westerlo Antwerpen 2260",
    "addr:housenumber":"24",
    "addr:postcode":"2260",
    "addr:street":"Baksveld",
    "iso:country":"BE",
    "sg:address":"Baksveld 24",
    "sg:city":"Westerlo",
    "sg:orig_category":"Schoonheidssalons",
    "sg:phone":"+32 14 54 47 20",
    "sg:postcode":"2260",
    "sg:province":"Antwerpen",
    "wof:name":"Natuurverzorgingsinstituut Inge",
    "wof:placetype":"venue"
},
  "geometry": {"coordinates":[4.9170160294,51.0925521851],"type":"Point"}
}