{
  "type": "Feature",
  "properties": {
    "addr:full":"Industrielaan 24 Overpelt Limburg 3900",
    "addr:housenumber":"24",
    "addr:postcode":"3900",
    "addr:street":"Industrielaan",
    "iso:country":"BE",
    "sg:address":"Industrielaan 24",
    "sg:city":"Overpelt",
    "sg:classifiers":[
        {
            "category":"Utilities",
            "subcategory":"Natural Gas",
            "type":"Services"
        }
    ],
    "sg:phone":"+32 11 64 23 84",
    "sg:postcode":"3900",
    "sg:province":"Limburg",
    "sg:tags":[
        "aerosol"
    ],
    "wof:name":"Aerotrim Nv",
    "wof:placetype":"venue"
},
  "geometry": {"coordinates":[5.3663301468,51.2180252075],"type":"Point"}
}