{
  "type": "Feature",
  "properties": {
    "addr:full":"Parklaan 70b12 Sint-niklaas Oost-Vlaanderen 9100",
    "addr:housenumber":"70b12",
    "addr:postcode":"9100",
    "addr:street":"Parklaan",
    "iso:country":"BE",
    "sg:address":"Parklaan 70b12",
    "sg:city":"Sint-niklaas",
    "sg:orig_category":"Production de films, t\u00e9l\u00e9films and vid\u00e9os",
    "sg:phone":"+32 3 766 48 00",
    "sg:postcode":"9100",
    "sg:province":"Oost-Vlaanderen",
    "wof:name":"Vdm Vid\u00c9o",
    "wof:placetype":"venue"
},
  "geometry": {"coordinates":[4.151638031,51.1585350037],"type":"Point"}
}