{
  "type": "Feature",
  "properties": {
    "iso:country":"BE",
    "sg:address":"Rue Du Hocquet 18",
    "sg:city":"La Louvi\u00e8re",
    "sg:classifiers":[
        {
            "category":"Personal",
            "subcategory":"Beauty Salon",
            "type":"Services"
        }
    ],
    "sg:phone":"+32 64 22 93 55",
    "sg:postcode":"7100",
    "sg:province":"Hainaut",
    "sg:tags":[
        "lady",
        "-",
        "hairdressing"
    ],
    "wof:name":"Coiffure Gino",
    "wof:placetype":"venue"
},
  "geometry": {"coordinates":[4.183098793,50.48204422],"type":"Point"}
}