{
  "type": "Feature",
  "properties": {
    "iso:country":"BE",
    "sg:address":"P Van Cauwelaertstraat 121",
    "sg:city":"Ternat",
    "sg:orig_category":"Promoteurs immobiliers. Agences immobili\u00e8res. Construction de maisons",
    "sg:phone":"+32 2 582 25 26",
    "sg:postcode":"1740",
    "sg:province":"Vlaams-Brabant",
    "wof:name":"Lievens",
    "wof:placetype":"venue"
},
  "geometry": {"coordinates":[4.1736860275,50.8647232056],"type":"Point"}
}