{
  "type": "Feature",
  "properties": {
    "addr:full":"Rue Edouard Binam\u00c9 60 Profondeville Namur 5170",
    "addr:housenumber":"60",
    "addr:postcode":"5170",
    "addr:street":"Rue Edouard Biname\u0301",
    "iso:country":"BE",
    "sg:address":"Rue Edouard Binam\u00c9 60",
    "sg:city":"Profondeville",
    "sg:classifiers":[
        {
            "category":"Insurance",
            "subcategory":"Life Insurance",
            "type":"Services"
        }
    ],
    "sg:phone":"+32 81 43 38 78",
    "sg:postcode":"5170",
    "sg:province":"Namur",
    "sg:tags":[
        "assurance"
    ],
    "wof:name":"Ren\u00c9 Baufays",
    "wof:placetype":"venue"
},
  "geometry": {"coordinates":[4.8336658478,50.4069099426],"type":"Point"}
}