{
  "type": "Feature",
  "properties": {
    "addr:full":"Nieuwpoortsesteenweg 579 Oostende West-Vlaanderen 8400",
    "addr:housenumber":"579",
    "addr:postcode":"8400",
    "addr:street":"Nieuwpoortsesteenweg",
    "iso:country":"BE",
    "sg:address":"Nieuwpoortsesteenweg 579",
    "sg:city":"Oostende",
    "sg:classifiers":[
        {
            "category":"Shopping",
            "subcategory":"Optician",
            "type":"Retail Goods"
        }
    ],
    "sg:phone":"+32 59 50 74 10",
    "sg:postcode":"8400",
    "sg:province":"West-Vlaanderen",
    "sg:tags":[
        "-"
    ],
    "wof:name":"Germonprez Optiek",
    "wof:placetype":"venue"
},
  "geometry": {"coordinates":[2.8883399963,51.2153282166],"type":"Point"}
}