{
  "type": "Feature",
  "properties": {
    "addr:full":"Chauss\u00c9e De Bruxelles 610 Waterloo Brabant Wallon 1410",
    "addr:housenumber":"610",
    "addr:postcode":"1410",
    "addr:street":"Chausse\u0301E De Bruxelles",
    "iso:country":"BE",
    "sg:address":"Chauss\u00c9e De Bruxelles 610",
    "sg:city":"Waterloo",
    "sg:orig_category":"Afvalwaterverwerking and ontstoppingsdiensten",
    "sg:phone":"+32 2 354 73 60",
    "sg:postcode":"1410",
    "sg:province":"Brabant Wallon",
    "wof:name":"Debosschere & Fils",
    "wof:placetype":"venue"
},
  "geometry": {"coordinates":[4.4020819664,50.6988105774],"type":"Point"}
}