{
  "type": "Feature",
  "properties": {
    "addr:full":"5590 Ciney Namur 5590",
    "addr:postcode":"5590;5590",
    "iso:country":"BE",
    "sg:address":"5590",
    "sg:city":"Ciney",
    "sg:orig_category":"Produits chimiques Gr",
    "sg:phone":"+32 83 21 40 02",
    "sg:postcode":"5590",
    "sg:province":"Namur",
    "wof:name":"Aquapro",
    "wof:placetype":"venue"
},
  "geometry": {"coordinates":[5.1022520065,50.297088623],"type":"Point"}
}