{
  "type": "Feature",
  "properties": {
    "addr:full":"Monacoplein 9b Oostende West-Vlaanderen 8400",
    "addr:housenumber":"9b",
    "addr:postcode":"8400",
    "addr:street":"Monacoplein",
    "iso:country":"BE",
    "sg:address":"Monacoplein 9b",
    "sg:city":"Oostende",
    "sg:classifiers":[
        {
            "category":"Bars & Pubs",
            "type":"Food & Drink"
        }
    ],
    "sg:phone":"+32 59 70 32 51",
    "sg:postcode":"8400",
    "sg:province":"West-Vlaanderen",
    "sg:tags":[
        "tavern"
    ],
    "wof:name":"Pichet",
    "wof:placetype":"venue"
},
  "geometry": {"coordinates":[2.9125471115,51.2313194275],"type":"Point"}
}