{
  "type": "Feature",
  "properties": {
    "addr:full":"St. Lievenslaan 35 Gent Oost-Vlaanderen 9000",
    "addr:housenumber":"35",
    "addr:postcode":"9000",
    "addr:street":"St. Lievenslaan;Oost-Vlaanderen",
    "iso:country":"BE",
    "sg:address":"St. Lievenslaan 35",
    "sg:city":"Gent",
    "sg:orig_category":"Epiceries",
    "sg:postcode":"9000",
    "sg:province":"Oost-Vlaanderen",
    "wof:name":"Automatische Muurwinkel",
    "wof:placetype":"venue"
},
  "geometry": {"coordinates":[3.7337429523,51.038520813],"type":"Point"}
}