{
  "type": "Feature",
  "properties": {
    "iso:country":"BE",
    "sg:address":"Schotelven 17",
    "sg:city":"Arendonk",
    "sg:orig_category":"Quincailleries. Caravanes and remorques",
    "sg:phone":"+32 14 67 01 09",
    "sg:postcode":"2370",
    "sg:province":"Antwerpen",
    "wof:name":"Aanhangwagencentrale",
    "wof:placetype":"venue"
},
  "geometry": {"coordinates":[5.0657200813,51.3155899048],"type":"Point"}
}