{
  "type": "Feature",
  "properties": {
    "iso:country":"BE",
    "sg:address":"Edward Stuckensstraat 94",
    "sg:city":"Evere",
    "sg:orig_category":"Dakwerken Installatie van houten of kunststof schrijnwerk",
    "sg:phone":"+32 2 245 09 50",
    "sg:postcode":"1140",
    "sg:province":"Bruxelles-Capitale",
    "wof:name":"Durabel",
    "wof:placetype":"venue"
},
  "geometry": {"coordinates":[4.3971681595,50.8758544922],"type":"Point"}
}