{
  "type": "Feature",
  "properties": {
    "addr:full":"Hoogstraat 126 Sint-pieters-leeuw Vlaams-Brabant 1600",
    "addr:housenumber":"126",
    "addr:postcode":"1600",
    "addr:street":"Hoogstraat",
    "iso:country":"BE",
    "sg:address":"Hoogstraat 126",
    "sg:city":"Sint-pieters-leeuw",
    "sg:orig_category":"Koerierbedrijven",
    "sg:phone":"+32 2 331 32 32",
    "sg:postcode":"1600",
    "sg:province":"Vlaams-Brabant",
    "wof:name":"Courier Management Group",
    "wof:placetype":"venue"
},
  "geometry": {"coordinates":[4.2277522087,50.7835578918],"type":"Point"}
}