{
  "type": "Feature",
  "properties": {
    "addr:full":"Avenue Des Cerisiers 72 Jemeppe-sur-sambre Namur 5190",
    "addr:housenumber":"72",
    "addr:postcode":"5190",
    "addr:street":"Avenue Des Cerisiers",
    "iso:country":"BE",
    "sg:address":"Avenue Des Cerisiers 72",
    "sg:city":"Jemeppe-sur-sambre",
    "sg:orig_category":"R\u00e9paration and restauration de meubles",
    "sg:phone":"+32 71 78 48 86",
    "sg:postcode":"5190",
    "sg:province":"Namur",
    "wof:name":"Francis Brosteaux",
    "wof:placetype":"venue"
},
  "geometry": {"coordinates":[4.6624188423,50.4731826782],"type":"Point"}
}