{
  "type": "Feature",
  "properties": {
    "iso:country":"BE",
    "sg:address":"Kerkstraat 169b2",
    "sg:city":"Blankenberge",
    "sg:classifiers":[
        {
            "category":"Cafe",
            "type":"Food & Drink"
        }
    ],
    "sg:phone":"+32 50 41 30 16",
    "sg:postcode":"8370",
    "sg:province":"West-Vlaanderen",
    "sg:tags":[
        "caf\u00e9s"
    ],
    "wof:name":"Caf\u00c9 De Landdijk",
    "wof:placetype":"venue"
},
  "geometry": {"coordinates":[3.1340370178,51.3109664917],"type":"Point"}
}