{
  "type": "Feature",
  "properties": {
    "iso:country":"BE",
    "sg:address":"Kapellei 268",
    "sg:city":"Zoersel (halle)",
    "sg:classifiers":[
        {
            "category":"Home & Garden",
            "subcategory":"Building Materials",
            "type":"Retail Goods"
        }
    ],
    "sg:phone":"+32 3 385 01 21",
    "sg:postcode":"2980",
    "sg:province":"Antwerpen",
    "sg:tags":[
        "wall",
        "cupboard"
    ],
    "wof:name":"Dyckmans G & Zn",
    "wof:placetype":"venue"
},
  "geometry": {"coordinates":[4.6149830818,51.2531967163],"type":"Point"}
}