{
  "type": "Feature",
  "properties": {
    "iso:country":"BE",
    "sg:address":"Vaartstraat 55",
    "sg:city":"Veurne",
    "sg:orig_category":"Rundveehouders",
    "sg:phone":"+32 58 31 17 44",
    "sg:postcode":"8630",
    "sg:province":"West-Vlaanderen",
    "wof:name":"Gilbert Lowagie",
    "wof:placetype":"venue"
},
  "geometry": {"coordinates":[2.6757080555,51.0612030029],"type":"Point"}
}