{
  "type": "Feature",
  "properties": {
    "addr:full":"Rue Saint Gilles 242 Li\u00c8ge Li\u00e8ge 4000",
    "addr:housenumber":"242",
    "addr:postcode":"4000",
    "addr:street":"Rue Saint Gilles",
    "iso:country":"BE",
    "sg:address":"Rue Saint Gilles 242",
    "sg:city":"Li\u00c8ge",
    "sg:classifiers":[
        {
            "category":"Personal",
            "subcategory":"Beauty Salon",
            "type":"Services"
        }
    ],
    "sg:phone":"+32 4 223 62 19",
    "sg:postcode":"4000",
    "sg:province":"Li\u00e8ge",
    "sg:tags":[
        "de",
        "coiffure"
    ],
    "wof:name":"Coiffure Georges-antoine",
    "wof:placetype":"venue"
},
  "geometry": {"coordinates":[5.5613012314,50.6374130249],"type":"Point"}
}