{
  "type": "Feature",
  "properties": {
    "iso:country":"BE",
    "sg:address":"Boulevard Pasteur 15",
    "sg:city":"Seraing",
    "sg:classifiers":[
        {
            "category":"Autos & Motor Vehicles",
            "subcategory":"Automobile Sales",
            "type":"Retail Goods"
        }
    ],
    "sg:phone":"+32 4 337 65 00",
    "sg:postcode":"4100",
    "sg:province":"Li\u00e8ge",
    "sg:tags":[
        "car",
        "used",
        "-"
    ],
    "wof:name":"Delbecq Sprl",
    "wof:placetype":"venue"
},
  "geometry": {"coordinates":[5.4971671104,50.591091156],"type":"Point"}
}