{
  "type": "Feature",
  "properties": {
    "addr:full":"Leopoldstraat 21 Antwerpen Antwerpen 2000",
    "addr:housenumber":"21",
    "addr:postcode":"2000",
    "addr:street":"Leopoldstraat",
    "iso:country":"BE",
    "sg:address":"Leopoldstraat 21",
    "sg:city":"Antwerpen",
    "sg:orig_category":"Articles de sport, camping and jouets Articles de camping and de sport",
    "sg:phone":"+32 3 226 05 49",
    "sg:postcode":"2000",
    "sg:province":"Antwerpen",
    "wof:name":"Kampeerder",
    "wof:placetype":"venue"
},
  "geometry": {"coordinates":[4.4070038795,51.2149772644],"type":"Point"}
}