{
  "type": "Feature",
  "properties": {
    "addr:full":"Cit\u00c9 Jean Rolland 37 Saint-ghislain Hainaut 7330",
    "addr:housenumber":"37",
    "addr:postcode":"7330",
    "addr:street":"Cite\u0301 Jean Rolland;Hainaut",
    "iso:country":"BE",
    "sg:address":"Cit\u00c9 Jean Rolland 37",
    "sg:city":"Saint-ghislain",
    "sg:orig_category":"Enseignement maternel and primaire",
    "sg:phone":"+32 65 77 01 93",
    "sg:postcode":"7330",
    "sg:province":"Hainaut",
    "wof:name":"Ecole Matern. Communale",
    "wof:placetype":"venue"
},
  "geometry": {"coordinates":[3.8141889572,50.4474754333],"type":"Point"}
}