{
  "type": "Feature",
  "properties": {
    "iso:country":"BE",
    "sg:address":"Beverststraat 70",
    "sg:city":"Genk",
    "sg:classifiers":[
        {
            "category":"Building & Trades",
            "subcategory":"Construction",
            "type":"Services"
        }
    ],
    "sg:phone":"+32 89 81 19 28",
    "sg:postcode":"3600",
    "sg:province":"Limburg",
    "sg:tags":[
        "installation",
        "-",
        "central",
        "heating"
    ],
    "wof:name":"Vanroy P",
    "wof:placetype":"venue"
},
  "geometry": {"coordinates":[5.4879097939,50.9293785095],"type":"Point"}
}