{
  "type": "Feature",
  "properties": {
    "addr:full":"Tongersesteenweg 212 Borgloon Limburg 3840",
    "addr:housenumber":"212",
    "addr:postcode":"3840",
    "addr:street":"Tongersesteenweg",
    "iso:country":"BE",
    "sg:address":"Tongersesteenweg 212",
    "sg:city":"Borgloon",
    "sg:orig_category":"Eleveurs de bovins",
    "sg:phone":"+32 12 74 72 18",
    "sg:postcode":"3840",
    "sg:province":"Limburg",
    "wof:name":"Jules Sampermans",
    "wof:placetype":"venue"
},
  "geometry": {"coordinates":[5.3611898422,50.798210144],"type":"Point"}
}