{
  "type": "Feature",
  "properties": {
    "addr:full":"Elewijtsesteenweg 134 Zemst (eppegem) Vlaams-Brabant 1980",
    "addr:housenumber":"134",
    "addr:postcode":"1980",
    "addr:street":"Elewijtsesteenweg",
    "iso:country":"BE",
    "sg:address":"Elewijtsesteenweg 134",
    "sg:city":"Zemst (eppegem)",
    "sg:classifiers":[
        {
            "category":"Building & Trades",
            "subcategory":"Landscaping Services",
            "type":"Services"
        }
    ],
    "sg:phone":"+32 15 62 18 91",
    "sg:postcode":"1980",
    "sg:province":"Vlaams-Brabant",
    "sg:tags":[
        "gardening",
        "garden",
        "maintenance"
    ],
    "wof:name":"Vermeylen V",
    "wof:placetype":"venue"
},
  "geometry": {"coordinates":[4.4668631554,50.9602279663],"type":"Point"}
}