{
  "type": "Feature",
  "properties": {
    "addr:full":"Grand'rue 43 / 45 Mons Hainaut 7000",
    "addr:housenumber":"43 / 45",
    "addr:postcode":"7000",
    "addr:street":"Grand'Rue;Hainaut",
    "iso:country":"BE",
    "sg:address":"Grand'rue 43 / 45",
    "sg:city":"Mons",
    "sg:orig_category":"V\u00eatements pour Dames. V\u00eatements pour b\u00e9b\u00e9s and enfants. V\u00eatements pour Hommes",
    "sg:phone":"+32 65 31 23 46",
    "sg:postcode":"7000",
    "sg:province":"Hainaut",
    "wof:name":"C&a",
    "wof:placetype":"venue"
},
  "geometry": {"coordinates":[3.952878952,50.4551277161],"type":"Point"}
}