{
  "type": "Feature",
  "properties": {
    "iso:country":"BE",
    "sg:address":"Waterstraat 7",
    "sg:city":"Geel",
    "sg:orig_category":"M\u00e9decins and sp\u00e9cialistes",
    "sg:phone":"+32 14 58 87 22",
    "sg:postcode":"2440",
    "sg:province":"Antwerpen",
    "wof:name":"J. Verschooten",
    "wof:placetype":"venue"
},
  "geometry": {"coordinates":[4.9875011444,51.1569862366],"type":"Point"}
}