{
  "type": "Feature",
  "properties": {
    "addr:full":"Boulevard Sylvain Dupuis 238 Anderlecht/anderlecht Bruxelles-Capitale 1070",
    "addr:housenumber":"238",
    "addr:postcode":"1070",
    "addr:street":"Boulevard Sylvain Dupuis",
    "iso:country":"BE",
    "sg:address":"Boulevard Sylvain Dupuis 238",
    "sg:city":"Anderlecht/anderlecht",
    "sg:classifiers":[
        {
            "category":"Cafe",
            "type":"Food & Drink"
        }
    ],
    "sg:phone":"+32 2 523 45 17",
    "sg:postcode":"1070",
    "sg:province":"Bruxelles-Capitale",
    "sg:tags":[
        "caf\u00e9s"
    ],
    "wof:name":"Theodoros Tzionas",
    "wof:placetype":"venue"
},
  "geometry": {"coordinates":[4.2939810753,50.8369865417],"type":"Point"}
}