{
  "type": "Feature",
  "properties": {
    "addr:full":"Kasteelstraat 10 Sint-truiden Limburg 3800",
    "addr:housenumber":"10",
    "addr:postcode":"3800",
    "addr:street":"Kasteelstraat",
    "iso:country":"BE",
    "sg:address":"Kasteelstraat 10",
    "sg:city":"Sint-truiden",
    "sg:orig_category":"Installation de menuiserie m\u00e9tallique. Installation de menuiserie en bois and plastique",
    "sg:phone":"+32 11 68 17 67",
    "sg:postcode":"3800",
    "sg:province":"Limburg",
    "wof:name":"Bamps Roger - Lacroix",
    "wof:placetype":"venue"
},
  "geometry": {"coordinates":[5.2440662384,50.8286209106],"type":"Point"}
}