{
  "type": "Feature",
  "properties": {
    "addr:full":"Place Saint-jacques 2 Huy Li\u00e8ge 4500",
    "addr:housenumber":"2",
    "addr:postcode":"4500",
    "addr:street":"Place Saint-Jacques",
    "iso:country":"BE",
    "sg:address":"Place Saint-jacques 2",
    "sg:city":"Huy",
    "sg:classifiers":[
        {
            "category":"Real Estate",
            "subcategory":"Developer",
            "type":"Services"
        }
    ],
    "sg:phone":"+32 85 25 34 93",
    "sg:postcode":"4500",
    "sg:province":"Li\u00e8ge",
    "sg:tags":[
        "project"
    ],
    "wof:name":"Prologe",
    "wof:placetype":"venue"
},
  "geometry": {"coordinates":[5.2554321289,50.5236816406],"type":"Point"}
}