{
  "type": "Feature",
  "properties": {
    "addr:full":"Rue Des Mara\u00eechers 90 Li\u00e8ge 1 (li\u00e8ge 2) Li\u00e8ge 4020",
    "addr:housenumber":"90;1;2",
    "addr:postcode":"4020",
    "addr:street":"Rue Des Marai\u0302Chers",
    "iso:country":"BE",
    "sg:address":"Rue Des Mara\u00eechers 90",
    "sg:city":"Li\u00e8ge 1 (li\u00e8ge 2)",
    "sg:classifiers":[
        {
            "category":"Professional",
            "subcategory":"Testing Lab",
            "type":"Services"
        }
    ],
    "sg:phone":"+32 4 343 33 14",
    "sg:postcode":"4020",
    "sg:province":"Li\u00e8ge",
    "sg:tags":[
        "chemist"
    ],
    "wof:name":"Bomans L",
    "wof:placetype":"venue"
},
  "geometry": {"coordinates":[5.594438076,50.63879776],"type":"Point"}
}