{
  "type": "Feature",
  "properties": {
    "addr:full":"Thier Saint-leonard 184 Grace-hollogne Li\u00e8ge 4460",
    "addr:housenumber":"184",
    "addr:postcode":"4460",
    "addr:street":"Thier Saint-Leonard",
    "iso:country":"BE",
    "sg:address":"Thier Saint-leonard 184",
    "sg:city":"Grace-hollogne",
    "sg:orig_category":"Plomberie, chauffage and installations sanitaires",
    "sg:phone":"+32 4 233 10 22",
    "sg:postcode":"4460",
    "sg:province":"Li\u00e8ge",
    "wof:name":"Bruno Lucchesse",
    "wof:placetype":"venue"
},
  "geometry": {"coordinates":[5.4656100273,50.6291542053],"type":"Point"}
}