{
  "type": "Feature",
  "properties": {
    "iso:country":"BE",
    "sg:address":"Rue Tranquille 9",
    "sg:city":"Marche-en-famenne",
    "sg:orig_category":"Rundveehouders",
    "sg:phone":"+32 84 31 17 86",
    "sg:postcode":"6900",
    "sg:province":"Luxembourg",
    "wof:name":"Collet Rene Et Denise",
    "wof:placetype":"venue"
},
  "geometry": {"coordinates":[5.3266940117,50.2265510559],"type":"Point"}
}