{
  "type": "Feature",
  "properties": {
    "addr:full":"Hovenstraat 2a Hasselt Limburg 3500",
    "addr:housenumber":"2a",
    "addr:postcode":"3500",
    "addr:street":"Hovenstraat",
    "iso:country":"BE",
    "sg:address":"Hovenstraat 2a",
    "sg:city":"Hasselt",
    "sg:classifiers":[
        {
            "category":"Real Estate",
            "subcategory":"Architect",
            "type":"Services"
        }
    ],
    "sg:phone":"+32 11 26 19 66",
    "sg:postcode":"3500",
    "sg:province":"Limburg",
    "wof:name":"Jaspers V",
    "wof:placetype":"venue"
},
  "geometry": {"coordinates":[5.340089798,50.9348716736],"type":"Point"}
}