{
  "type": "Feature",
  "properties": {
    "addr:full":"Avenue Winston Churchill 77 Box 6 Bruxelles (uccle) Bruxelles-Capitale 1180",
    "addr:housenumber":"77;6",
    "addr:postcode":"1180",
    "addr:street":"Avenue Winston Churchill;Box",
    "iso:country":"BE",
    "sg:address":"Avenue Winston Churchill 77 Box 6",
    "sg:city":"Bruxelles (uccle)",
    "sg:classifiers":[
        {
            "category":"Professional",
            "subcategory":"Lawyer & Legal Services",
            "type":"Services"
        }
    ],
    "sg:phone":"+32 2 344 77 29",
    "sg:postcode":"1180",
    "sg:province":"Bruxelles-Capitale",
    "wof:name":"Byl Danielle",
    "wof:placetype":"venue"
},
  "geometry": {"coordinates":[4.3541240692,50.8114204407],"type":"Point"}
}