{
  "type": "Feature",
  "properties": {
    "iso:country":"BE",
    "sg:address":"Viergatenstraat 41",
    "sg:city":"Gooik",
    "sg:orig_category":"Magasins sp\u00e9cialis\u00e9s. Quincailleries",
    "sg:phone":"+32 54 56 70 82",
    "sg:postcode":"1755",
    "sg:province":"Vlaams-Brabant",
    "wof:name":"Guido De Greef",
    "wof:placetype":"venue"
},
  "geometry": {"coordinates":[4.0609698296,50.7646408081],"type":"Point"}
}