{
  "type": "Feature",
  "properties": {
    "addr:full":"Avenue Auguste Rodin 53 Elsene/ixelles Bruxelles-Capitale 1050",
    "addr:housenumber":"53",
    "addr:postcode":"1050",
    "addr:street":"Avenue Auguste Rodin",
    "iso:country":"BE",
    "sg:address":"Avenue Auguste Rodin 53",
    "sg:city":"Elsene/ixelles",
    "sg:orig_category":"M\u00e9decins and sp\u00e9cialistes",
    "sg:phone":"+32 2 640 06 00",
    "sg:postcode":"1050",
    "sg:province":"Bruxelles-Capitale",
    "wof:name":"S\u00c9bastien Renoy",
    "wof:placetype":"venue"
},
  "geometry": {"coordinates":[4.3787088394,50.8268432617],"type":"Point"}
}