{
  "type": "Feature",
  "properties": {
    "addr:full":"Rue Du Flosse 4a Libramont-chevigny (recogne) Luxembourg 6800",
    "addr:housenumber":"4a",
    "addr:postcode":"6800",
    "addr:street":"Rue Du Flosse",
    "iso:country":"BE",
    "sg:address":"Rue Du Flosse 4a",
    "sg:city":"Libramont-chevigny (recogne)",
    "sg:classifiers":[
        {
            "category":"Home & Garden",
            "subcategory":"Home Furnishings",
            "type":"Retail Goods"
        }
    ],
    "sg:phone":"+32 61 23 25 75",
    "sg:postcode":"6800",
    "sg:province":"Luxembourg",
    "sg:tags":[
        "interior",
        "decoration"
    ],
    "wof:name":"Max D\u00e9co Libramont Sprl",
    "wof:placetype":"venue"
},
  "geometry": {"coordinates":[5.3678350449,49.9124565125],"type":"Point"}
}