{
  "type": "Feature",
  "properties": {
    "addr:full":"Lekedorpsstraat 50 Diksmuide West-Vlaanderen 8600",
    "addr:housenumber":"50",
    "addr:postcode":"8600",
    "addr:street":"Lekedorpsstraat",
    "iso:country":"BE",
    "sg:address":"Lekedorpsstraat 50",
    "sg:city":"Diksmuide",
    "sg:orig_category":"Catering and organisation de f\u00eates. Boucheries. Alimentation sp\u00e9cialis\u00e9e",
    "sg:phone":"+32 51 50 17 40",
    "sg:postcode":"8600",
    "sg:province":"West-Vlaanderen",
    "wof:name":"Beenhouwerij Antoon & Co",
    "wof:placetype":"venue"
},
  "geometry": {"coordinates":[2.8657801151,51.0334663391],"type":"Point"}
}