{
  "type": "Feature",
  "properties": {
    "addr:full":"Steenweg Op Aalst 1074 Aalst Oost-Vlaanderen 9308",
    "addr:housenumber":"1074",
    "addr:postcode":"9308",
    "addr:street":"Steenweg Op Aalst",
    "iso:country":"BE",
    "sg:address":"Steenweg Op Aalst 1074",
    "sg:city":"Aalst",
    "sg:orig_category":"Farmaceutische producten Gh",
    "sg:phone":"+32 53 78 16 32",
    "sg:postcode":"9308",
    "sg:province":"Oost-Vlaanderen",
    "wof:name":"Medishop Lievens",
    "wof:placetype":"venue"
},
  "geometry": {"coordinates":[4.0347590446,50.9603500366],"type":"Point"}
}