{
  "type": "Feature",
  "properties": {
    "addr:full":"Klein Laarstraat 19 Heist-op-den-berg Antwerpen 2220",
    "addr:housenumber":"19",
    "addr:postcode":"2220",
    "addr:street":"Klein Laarstraat",
    "iso:country":"BE",
    "sg:address":"Klein Laarstraat 19",
    "sg:city":"Heist-op-den-berg",
    "sg:orig_category":"Sportclubs",
    "sg:phone":"+32 15 24 85 11",
    "sg:postcode":"2220",
    "sg:province":"Antwerpen",
    "wof:name":"De Ware Vrienden",
    "wof:placetype":"venue"
},
  "geometry": {"coordinates":[4.7472338676,51.0685157776],"type":"Point"}
}