{
  "type": "Feature",
  "properties": {
    "iso:country":"BE",
    "sg:address":"Staatsbaan 19-21",
    "sg:city":"Lanaken",
    "sg:orig_category":"Ice-cream parlours",
    "sg:phone":"+32 89 73 27 00",
    "sg:postcode":"3620",
    "sg:province":"Limburg",
    "wof:name":"Dali",
    "wof:placetype":"venue"
},
  "geometry": {"coordinates":[5.6798000336,50.9070396423],"type":"Point"}
}