{
  "type": "Feature",
  "properties": {
    "iso:country":"BE",
    "sg:address":"Rue De La Fronti\u00c8re 105",
    "sg:city":"Dour",
    "sg:orig_category":"Installation de menuiserie en bois and plastique",
    "sg:phone":"+32 65 65 26 22",
    "sg:postcode":"7370",
    "sg:province":"Hainaut",
    "wof:name":"Gilbert Cordier",
    "wof:placetype":"venue"
},
  "geometry": {"coordinates":[3.8096129894,50.3710975647],"type":"Point"}
}