{
  "type": "Feature",
  "properties": {
    "addr:full":"Markt 32 Deinze Oost-Vlaanderen 9800",
    "addr:housenumber":"32",
    "addr:postcode":"9800",
    "addr:street":"Markt",
    "iso:country":"BE",
    "sg:address":"Markt 32",
    "sg:city":"Deinze",
    "sg:orig_category":"RESTAURANTS: CAF\u00c9S",
    "sg:phone":"+32 9 386 12 26",
    "sg:postcode":"9800",
    "sg:province":"Oost-Vlaanderen",
    "wof:name":"Taverne Palace",
    "wof:placetype":"venue"
},
  "geometry": {"coordinates":[3.5267219543,50.9836921692],"type":"Point"}
}