{
  "type": "Feature",
  "properties": {
    "addr:full":"Robert Dansaertlaan 100 Dilbeek (groot - Bijgaarden) Vlaams-Brabant 1702",
    "addr:housenumber":"100;1702",
    "addr:street":"Robert Dansaertlaan;Groot Bijgaarden Vlaams-Brabant",
    "iso:country":"BE",
    "sg:address":"Robert Dansaertlaan 100",
    "sg:city":"Dilbeek (groot - Bijgaarden)",
    "sg:classifiers":[
        {
            "category":"Building & Trades",
            "subcategory":"Cleaning & Sanitation",
            "type":"Services"
        }
    ],
    "sg:phone":"+32 2 466 26 23",
    "sg:postcode":"1702",
    "sg:province":"Vlaams-Brabant",
    "sg:tags":[
        "blast"
    ],
    "wof:name":"Lostermans & Le Brun Bvba",
    "wof:placetype":"venue"
},
  "geometry": {"coordinates":[4.2716088295,50.866973877],"type":"Point"}
}