{
  "type": "Feature",
  "properties": {
    "iso:country":"BE",
    "sg:address":"Rue Neuve 3",
    "sg:city":"Fosses-la-ville",
    "sg:orig_category":"V\u00e9hicules automobiles. Stations-service and carburants. Entretien and r\u00e9parations de voitures",
    "sg:phone":"+32 71 71 20 18",
    "sg:postcode":"5070",
    "sg:province":"Namur",
    "wof:name":"G.m.v. Vandevandel",
    "wof:placetype":"venue"
},
  "geometry": {"coordinates":[4.6838088036,50.3831520081],"type":"Point"}
}