{
  "type": "Feature",
  "properties": {
    "addr:full":"Charlottalei 34b5 Antwerpen Antwerpen 2018",
    "addr:housenumber":"34b5",
    "addr:postcode":"2018",
    "addr:street":"Charlottalei",
    "iso:country":"BE",
    "sg:address":"Charlottalei 34b5",
    "sg:city":"Antwerpen",
    "sg:orig_category":"Beheer onroerend goed",
    "sg:phone":"+32 3 230 17 08",
    "sg:postcode":"2018",
    "sg:province":"Antwerpen",
    "wof:name":"J. Rombouts",
    "wof:placetype":"venue"
},
  "geometry": {"coordinates":[4.4183549881,51.2085342407],"type":"Point"}
}