{
  "type": "Feature",
  "properties": {
    "iso:country":"BE",
    "sg:address":"Zaveldriesstraat 28",
    "sg:city":"Genk",
    "sg:orig_category":"Zalen voor culturele evenementen",
    "sg:phone":"+32 89 84 54 17",
    "sg:postcode":"3600",
    "sg:province":"Limburg",
    "wof:name":"Young Gallery",
    "wof:placetype":"venue"
},
  "geometry": {"coordinates":[5.4975981712,51.0055885315],"type":"Point"}
}