{
  "type": "Feature",
  "properties": {
    "iso:country":"BE",
    "sg:address":"Avenue Albert Giraud 4 Box 13",
    "sg:city":"Bruxelles (schaerbeek)",
    "sg:classifiers":[
        {
            "category":"Shopping",
            "subcategory":"Clothing, Apparel, & Fashions",
            "type":"Retail Goods"
        }
    ],
    "sg:phone":"+32 2 215 06 71",
    "sg:postcode":"1030",
    "sg:province":"Bruxelles-Capitale",
    "sg:tags":[
        "-",
        "clothing",
        "child"
    ],
    "wof:name":"Ley & Co Sprl",
    "wof:placetype":"venue"
},
  "geometry": {"coordinates":[4.3773818016,50.8738365173],"type":"Point"}
}