{
  "type": "Feature",
  "properties": {
    "addr:full":"Avenue De L'hippodrome 128 Elsene/ixelles Bruxelles-Capitale 1050",
    "addr:housenumber":"128",
    "addr:postcode":"1050",
    "addr:street":"Avenue De L'Hippodrome",
    "iso:country":"BE",
    "sg:address":"Avenue De L'hippodrome 128",
    "sg:city":"Elsene/ixelles",
    "sg:classifiers":[
        {
            "category":"Fast Food",
            "type":"Food & Drink"
        }
    ],
    "sg:phone":"+32 2 649 79 77",
    "sg:postcode":"1050",
    "sg:province":"Bruxelles-Capitale",
    "sg:tags":[
        "\u00c0",
        "emporter",
        "restaurants"
    ],
    "wof:name":"Tsui",
    "wof:placetype":"venue"
},
  "geometry": {"coordinates":[4.3769440651,50.8208122253],"type":"Point"}
}