{
  "type": "Feature",
  "properties": {
    "iso:country":"BE",
    "sg:address":"Provinciebaan 91",
    "sg:city":"Dikkelvenne",
    "sg:orig_category":"Dakwerken",
    "sg:phone":"+32 9 362 23 38",
    "sg:postcode":"9890",
    "sg:province":"Oost-Vlaanderen",
    "wof:name":"Yves Rouquart",
    "wof:placetype":"venue"
},
  "geometry": {"coordinates":[3.7284929752,50.9186325073],"type":"Point"}
}