{
  "type": "Feature",
  "properties": {
    "iso:country":"BE",
    "sg:address":"'s Gravenstraat 100",
    "sg:city":"Nazareth",
    "sg:classifiers":[
        {
            "category":"Bars & Pubs",
            "type":"Food & Drink"
        }
    ],
    "sg:phone":"+32 9 385 45 99",
    "sg:postcode":"9810",
    "sg:province":"Oost-Vlaanderen",
    "wof:name":"Vliegend Paard",
    "wof:placetype":"venue"
},
  "geometry": {"coordinates":[3.5945150852,50.9573097229],"type":"Point"}
}