{
  "type": "Feature",
  "properties": {
    "iso:country":"BE",
    "sg:address":"Herkerstraat 10",
    "sg:city":"Hasselt",
    "sg:orig_category":"Installation \u00e9lectrique r\u00e9sidentielle. Installation \u00e9lectrique industrielle",
    "sg:phone":"+32 11 28 37 91",
    "sg:postcode":"3500",
    "sg:province":"Limburg",
    "wof:name":"Therm En Elektr Montage",
    "wof:placetype":"venue"
},
  "geometry": {"coordinates":[5.3260068893,50.9430122375],"type":"Point"}
}