{
  "type": "Feature",
  "properties": {
    "addr:full":"Place De Bois-de-lessines 32 Lessines Hainaut 7866",
    "addr:housenumber":"32",
    "addr:postcode":"7866",
    "addr:street":"Place De Bois-De-Lessines;Hainaut",
    "iso:country":"BE",
    "sg:address":"Place De Bois-de-lessines 32",
    "sg:city":"Lessines",
    "sg:orig_category":"Rev\u00eatements pour sols and murs. Peinture",
    "sg:phone":"+32 68 33 32 88",
    "sg:postcode":"7866",
    "sg:province":"Hainaut",
    "wof:name":"Fabrice Barbe",
    "wof:placetype":"venue"
},
  "geometry": {"coordinates":[3.889662981,50.6975479126],"type":"Point"}
}