{
  "type": "Feature",
  "properties": {
    "addr:full":"Rue Du Christ 59 Mouscron Hainaut 7700",
    "addr:housenumber":"59",
    "addr:postcode":"7700",
    "addr:street":"Rue Du Christ",
    "iso:country":"BE",
    "sg:address":"Rue Du Christ 59",
    "sg:city":"Mouscron",
    "sg:classifiers":[
        {
            "category":"Food & Beverages",
            "subcategory":"Groceries & Convenience Stores",
            "type":"Retail Goods"
        }
    ],
    "sg:phone":"+32 56 33 35 43",
    "sg:postcode":"7700",
    "sg:province":"Hainaut",
    "sg:tags":[
        "grocer"
    ],
    "wof:name":"Petruzzi Product",
    "wof:placetype":"venue"
},
  "geometry": {"coordinates":[3.2072720528,50.7439002991],"type":"Point"}
}