{
  "type": "Feature",
  "properties": {
    "iso:country":"BE",
    "sg:address":"Rue Du Ch\u00eane 1a",
    "sg:city":"Frasnes-lez-anvaing (herquegies)",
    "sg:classifiers":[
        {
            "category":"Home & Garden",
            "subcategory":"Carpets & Floor Coverings",
            "type":"Retail Goods"
        }
    ],
    "sg:phone":"+32 69 86 69 29",
    "sg:postcode":"7911",
    "sg:province":"Hainaut",
    "sg:tags":[
        "tile"
    ],
    "wof:name":"Delbecq & Cie Sprl",
    "wof:placetype":"venue"
},
  "geometry": {"coordinates":[3.579531908,50.638469696],"type":"Point"}
}