{
  "type": "Feature",
  "properties": {
    "iso:country":"BE",
    "sg:address":"Futselstraat 8",
    "sg:city":"Wingene",
    "sg:orig_category":"Meubles D\u00e9taillants, Am\u00e9nagement de B\u00e2timents et de Cuisines. Rev\u00eatements pour sols and murs. Peintu",
    "sg:phone":"+32 51 65 50 70",
    "sg:postcode":"8750",
    "sg:province":"West-Vlaanderen",
    "wof:name":"Lauwers-van Parys",
    "wof:placetype":"venue"
},
  "geometry": {"coordinates":[3.2779328823,51.0588989258],"type":"Point"}
}