{
  "type": "Feature",
  "properties": {
    "addr:full":"Gistelsesteenweg 62 Oostende West-Vlaanderen 8400",
    "addr:housenumber":"62",
    "addr:postcode":"8400",
    "addr:street":"Gistelsesteenweg",
    "iso:country":"BE",
    "sg:address":"Gistelsesteenweg 62",
    "sg:city":"Oostende",
    "sg:classifiers":[
        {
            "category":"Government",
            "subcategory":"Post Office",
            "type":"Public Place"
        }
    ],
    "sg:phone":"+32 59 50 36 42",
    "sg:postcode":"8400",
    "sg:province":"West-Vlaanderen",
    "sg:tags":[
        "whol",
        "set",
        "-",
        "cutlery"
    ],
    "wof:name":"Vicarr\u00e9 Bvba",
    "wof:placetype":"venue"
},
  "geometry": {"coordinates":[2.9266300201,51.2150115967],"type":"Point"}
}