{
  "type": "Feature",
  "properties": {
    "addr:full":"Grote Doelstraat 1a Bonheiden Antwerpen 2820",
    "addr:housenumber":"1a",
    "addr:postcode":"2820",
    "addr:street":"Grote Doelstraat",
    "iso:country":"BE",
    "sg:address":"Grote Doelstraat 1a",
    "sg:city":"Bonheiden",
    "sg:classifiers":[
        {
            "category":"Bars & Pubs",
            "type":"Food & Drink"
        }
    ],
    "sg:phone":"+32 475 38 37 93",
    "sg:postcode":"2820",
    "sg:province":"Antwerpen",
    "sg:tags":[
        "tavern"
    ],
    "wof:name":"Berentrode",
    "wof:placetype":"venue"
},
  "geometry": {"coordinates":[4.556139946,51.0260696411],"type":"Point"}
}