{
  "type": "Feature",
  "properties": {
    "addr:full":"Gossetlaan 26 Groot-bijgaarden Vlaams-Brabant 1702",
    "addr:housenumber":"26",
    "addr:postcode":"1702",
    "addr:street":"Gossetlaan",
    "iso:country":"BE",
    "sg:address":"Gossetlaan 26",
    "sg:city":"Groot-bijgaarden",
    "sg:classifiers":[
        {
            "category":"Shopping",
            "subcategory":"Computers & Home Electronics",
            "type":"Retail Goods"
        }
    ],
    "sg:phone":"+32 2 467 27 76",
    "sg:postcode":"1702",
    "sg:province":"Vlaams-Brabant",
    "sg:tags":[
        "computerapparatuur",
        "microsoft"
    ],
    "wof:name":"Communication Technologies",
    "wof:placetype":"venue"
},
  "geometry": {"coordinates":[4.277818203,50.87292099],"type":"Point"}
}