{
  "type": "Feature",
  "properties": {
    "iso:country":"BE",
    "sg:address":"Lakenweversstraat 52",
    "sg:city":"Elsene/ixelles",
    "sg:orig_category":"Artsen and specialisten",
    "sg:phone":"+32 2 503 16 68",
    "sg:postcode":"1050",
    "sg:province":"Bruxelles-Capitale",
    "wof:name":"Laurence Cobin",
    "wof:placetype":"venue"
},
  "geometry": {"coordinates":[4.3600068092,50.8347930908],"type":"Point"}
}