{
  "type": "Feature",
  "properties": {
    "addr:full":"Kattestraat 35 Heist-op-den-berg Antwerpen 2220",
    "addr:housenumber":"35",
    "addr:postcode":"2220",
    "addr:street":"Kattestraat",
    "iso:country":"BE",
    "sg:address":"Kattestraat 35",
    "sg:city":"Heist-op-den-berg",
    "sg:classifiers":[
        {
            "category":"Cafe",
            "type":"Food & Drink"
        }
    ],
    "sg:phone":"+32 15 24 90 46",
    "sg:postcode":"2220",
    "sg:province":"Antwerpen",
    "sg:tags":[
        "caf\u00e9s"
    ],
    "wof:name":"Caf\u00c9 De Kes",
    "wof:placetype":"venue"
},
  "geometry": {"coordinates":[4.718184948,51.0754470825],"type":"Point"}
}