{
  "type": "Feature",
  "properties": {
    "addr:full":"Haag 155 Mol Antwerpen 2400",
    "addr:housenumber":"155",
    "addr:postcode":"2400",
    "addr:street":"Haag",
    "iso:country":"BE",
    "sg:address":"Haag 155",
    "sg:city":"Mol",
    "sg:orig_category":"Afvalwaterverwerking and ontstoppingsdiensten",
    "sg:phone":"+32 14 31 39 44",
    "sg:postcode":"2400",
    "sg:province":"Antwerpen",
    "wof:name":"Heho",
    "wof:placetype":"venue"
},
  "geometry": {"coordinates":[5.0672588348,51.1813545227],"type":"Point"}
}