{
  "type": "Feature",
  "properties": {
    "addr:full":"Place Cockerill 18 Li\u00e8ge 1 Li\u00e8ge 4000",
    "addr:housenumber":"18;1",
    "addr:postcode":"4000",
    "addr:street":"Place Cockerill",
    "iso:country":"BE",
    "sg:address":"Place Cockerill 18",
    "sg:city":"Li\u00e8ge 1",
    "sg:classifiers":[
        {
            "category":"Food & Beverages",
            "subcategory":"Specialty",
            "type":"Retail Goods"
        }
    ],
    "sg:phone":"+32 4 221 21 64",
    "sg:postcode":"4000",
    "sg:province":"Li\u00e8ge",
    "sg:tags":[
        "health",
        "dietary",
        "-",
        "biological"
    ],
    "wof:name":"Al Binete",
    "wof:placetype":"venue"
},
  "geometry": {"coordinates":[5.5749101639,50.6413269043],"type":"Point"}
}