{
  "type": "Feature",
  "properties": {
    "iso:country":"BE",
    "sg:address":"Brusselsesteenweg 434",
    "sg:city":"Melle",
    "sg:orig_category":"Boissons",
    "sg:phone":"+32 9 252 14 38",
    "sg:postcode":"9090",
    "sg:province":"Oost-Vlaanderen",
    "wof:name":"Guy De Roover",
    "wof:placetype":"venue"
},
  "geometry": {"coordinates":[3.8284881115,50.9921188354],"type":"Point"}
}