{
  "type": "Feature",
  "properties": {
    "iso:country":"BE",
    "sg:address":"Diepenbekerweg 65 Box 2",
    "sg:city":"Hasselt",
    "sg:classifiers":[
        {
            "category":"Professional",
            "subcategory":"Research",
            "type":"Services"
        }
    ],
    "sg:phone":"+32 11 30 13 56",
    "sg:postcode":"3500",
    "sg:province":"Limburg",
    "sg:tags":[
        "actuary"
    ],
    "wof:name":"Daenen - Van Havermaet Employee Benefits Nv",
    "wof:placetype":"venue"
},
  "geometry": {"coordinates":[5.3699798584,50.923122406],"type":"Point"}
}