{
  "type": "Feature",
  "properties": {
    "addr:full":"A. Fastenaekelslaan 24 Koksijde West-Vlaanderen 8670",
    "addr:housenumber":"24",
    "addr:postcode":"8670",
    "addr:street":"Fastenaekelslaan",
    "iso:country":"BE",
    "sg:address":"A. Fastenaekelslaan 24",
    "sg:city":"Koksijde",
    "sg:classifiers":[
        {
            "category":"Arena",
            "subcategory":"Sports Club",
            "type":"Entertainment"
        }
    ],
    "sg:phone":"+32 58 52 14 01",
    "sg:postcode":"8670",
    "sg:province":"West-Vlaanderen",
    "sg:tags":[
        "de"
    ],
    "wof:name":"Aikido Traditionnel Ko Budo",
    "wof:placetype":"venue"
},
  "geometry": {"coordinates":[2.639977932,51.112411499],"type":"Point"}
}