{
  "type": "Feature",
  "properties": {
    "addr:full":"Route De Namur 9 Fleurus (wanferc\u00e9e-baulet) Hainaut 6224",
    "addr:housenumber":"9",
    "addr:postcode":"6224",
    "addr:street":"Route De Namur",
    "iso:country":"BE",
    "sg:address":"Route De Namur 9",
    "sg:city":"Fleurus (wanferc\u00e9e-baulet)",
    "sg:classifiers":[
        {
            "category":"Professional",
            "subcategory":"Printing & Photocopies",
            "type":"Services"
        }
    ],
    "sg:phone":"+32 71 81 23 92",
    "sg:postcode":"6224",
    "sg:province":"Hainaut",
    "sg:tags":[
        "engraving"
    ],
    "wof:name":"Logograph Sa",
    "wof:placetype":"venue"
},
  "geometry": {"coordinates":[4.5866918564,50.4606056213],"type":"Point"}
}