{
  "type": "Feature",
  "properties": {
    "addr:full":"Tweede Carabinierslaan 111 Lanaken Limburg 3620",
    "addr:housenumber":"111",
    "addr:postcode":"3620",
    "addr:street":"Tweede Carabinierslaan",
    "iso:country":"BE",
    "sg:address":"Tweede Carabinierslaan 111",
    "sg:city":"Lanaken",
    "sg:orig_category":"Woningbouw",
    "sg:phone":"+32 89 71 62 84",
    "sg:postcode":"3620",
    "sg:province":"Limburg",
    "wof:name":"Brems",
    "wof:placetype":"venue"
},
  "geometry": {"coordinates":[5.6551351547,50.8912277222],"type":"Point"}
}