{
  "type": "Feature",
  "properties": {
    "iso:country":"BE",
    "sg:address":"Sint-annastraat 5",
    "sg:city":"Merelbeke",
    "sg:orig_category":"Geschenken and souvenirs Meubelzaken, woning- and keukeninrichting Verlichting and huishoudartikelen",
    "sg:phone":"+32 9 362 53 61",
    "sg:postcode":"9820",
    "sg:province":"Oost-Vlaanderen",
    "wof:name":"Pontzeele Interieur",
    "wof:placetype":"venue"
},
  "geometry": {"coordinates":[3.7531120777,50.9635620117],"type":"Point"}
}