{
  "type": "Feature",
  "properties": {
    "iso:country":"BE",
    "sg:address":"Avenue De Roodebeek 117",
    "sg:city":"Schaarbeek/schaerbeek",
    "sg:orig_category":"Entretien and r\u00e9parations de voitures",
    "sg:phone":"+32 2 733 56 08",
    "sg:postcode":"1030",
    "sg:province":"Bruxelles-Capitale",
    "wof:name":"Garage Latrech",
    "wof:placetype":"venue"
},
  "geometry": {"coordinates":[4.4002461433,50.8483810425],"type":"Point"}
}