{
  "type": "Feature",
  "properties": {
    "addr:full":"Waterkasteelstraat 17 Bilzen (beverst) Limburg 3740",
    "addr:housenumber":"17",
    "addr:postcode":"3740",
    "addr:street":"Waterkasteelstraat",
    "iso:country":"BE",
    "sg:address":"Waterkasteelstraat 17",
    "sg:city":"Bilzen (beverst)",
    "sg:classifiers":[
        {
            "category":"Health Services",
            "subcategory":"Health Practitioner",
            "type":"Services"
        }
    ],
    "sg:phone":"+32 89 41 25 82",
    "sg:postcode":"3740",
    "sg:province":"Limburg",
    "sg:tags":[
        "therapist",
        "speech"
    ],
    "wof:name":"Palmers S",
    "wof:placetype":"venue"
},
  "geometry": {"coordinates":[5.4802150726,50.9029388428],"type":"Point"}
}