{
  "type": "Feature",
  "properties": {
    "iso:country":"BE",
    "sg:address":"Boulevard De L'europe 7",
    "sg:city":"Braine L'alleud (braine-l'alleud)",
    "sg:classifiers":[
        {
            "category":"Community Center",
            "type":"Public Place"
        }
    ],
    "sg:phone":"+32 2 387 53 11",
    "sg:postcode":"1420",
    "sg:province":"Brabant Wallon",
    "sg:tags":[
        "medical"
    ],
    "wof:name":"Centre Param\u00e9dical Riva Bella",
    "wof:placetype":"venue"
},
  "geometry": {"coordinates":[7.8578400612,52.9761810303],"type":"Point"}
}