{
  "type": "Feature",
  "properties": {
    "addr:full":"Grote Vreunte 54 Kortenaken Vlaams-Brabant 3473",
    "addr:housenumber":"54",
    "addr:postcode":"3473",
    "addr:street":"Grote Vreunte",
    "iso:country":"BE",
    "sg:address":"Grote Vreunte 54",
    "sg:city":"Kortenaken",
    "sg:classifiers":[
        {
            "category":"Cafe",
            "type":"Food & Drink"
        }
    ],
    "sg:phone":"+32 16 77 76 32",
    "sg:postcode":"3473",
    "sg:province":"Vlaams-Brabant",
    "sg:tags":[
        "caf\u00e9s"
    ],
    "wof:name":"Robert Marcoen",
    "wof:placetype":"venue"
},
  "geometry": {"coordinates":[5.0049848557,50.9137802124],"type":"Point"}
}