{
  "type": "Feature",
  "properties": {
    "iso:country":"BE",
    "sg:address":"Brechtsebaan 459c",
    "sg:city":"Schoten",
    "sg:classifiers":[
        {
            "category":"Autos & Motor Vehicles",
            "subcategory":"Auto Supplies",
            "type":"Retail Goods"
        }
    ],
    "sg:phone":"+32 3 653 47 30",
    "sg:postcode":"2900",
    "sg:province":"Antwerpen",
    "sg:tags":[
        "automobile",
        "alarm",
        "-",
        "system"
    ],
    "wof:name":"Acs-all Car Systems",
    "wof:placetype":"venue"
},
  "geometry": {"coordinates":[4.5279550552,51.2804412842],"type":"Point"}
}