{
  "type": "Feature",
  "properties": {
    "iso:country":"BE",
    "sg:address":"Rue Van Hamm\u00e9e 60",
    "sg:city":"Bruxelles (schaerbeek)",
    "sg:classifiers":[
        {
            "category":"Communications",
            "subcategory":"Film & Video Production",
            "type":"Services"
        }
    ],
    "sg:phone":"+32 2 215 34 73",
    "sg:postcode":"1030",
    "sg:province":"Bruxelles-Capitale",
    "sg:tags":[
        "movie",
        "maker"
    ],
    "wof:name":"Mertens P",
    "wof:placetype":"venue"
},
  "geometry": {"coordinates":[4.381128788,50.8564834595],"type":"Point"}
}