{
  "type": "Feature",
  "properties": {
    "iso:country":"BE",
    "sg:address":"Vanderkinderestraat 295",
    "sg:city":"Ukkel/uccle",
    "sg:orig_category":"Binnenhuisarchitecten",
    "sg:phone":"+32 2 345 77 63",
    "sg:postcode":"1180",
    "sg:province":"Bruxelles-Capitale",
    "wof:name":"M. Boudry",
    "wof:placetype":"venue"
},
  "geometry": {"coordinates":[4.3553738594,50.8140335083],"type":"Point"}
}