{
  "type": "Feature",
  "properties": {
    "iso:country":"BE",
    "sg:address":"Koningin Astridlaan 29",
    "sg:city":"Brugge",
    "sg:orig_category":"Banknote, Coin, Coin-Rolls, Chip And Money Changers",
    "sg:phone":"+32 50 55 12 06",
    "sg:postcode":"8000",
    "sg:province":"West-Vlaanderen",
    "wof:name":"Travelex Belgium Nv",
    "wof:placetype":"venue"
},
  "geometry": {"coordinates":[3.2487030029,51.1999588013],"type":"Point"}
}