{
  "type": "Feature",
  "properties": {
    "addr:full":"Hendrik Serruyslaan 42 Oostende West-Vlaanderen 8400",
    "addr:housenumber":"42",
    "addr:postcode":"8400",
    "addr:street":"Serruyslaan",
    "iso:country":"BE",
    "sg:address":"Hendrik Serruyslaan 42",
    "sg:city":"Oostende",
    "sg:orig_category":"Services divers aux entreprises. Agences immobili\u00e8res",
    "sg:phone":"+32 59 70 70 10",
    "sg:postcode":"8400",
    "sg:province":"West-Vlaanderen",
    "wof:name":"J.e.v. Eeckhout",
    "wof:placetype":"venue"
},
  "geometry": {"coordinates":[2.9171819687,51.2287521362],"type":"Point"}
}