{
  "type": "Feature",
  "properties": {
    "addr:full":"Bessemerstraat 15 Lanaken Limburg 3620",
    "addr:housenumber":"15",
    "addr:postcode":"3620",
    "addr:street":"Bessemerstraat",
    "iso:country":"BE",
    "sg:address":"Bessemerstraat 15",
    "sg:city":"Lanaken",
    "sg:orig_category":"Banques and organismes de cr\u00e9dit",
    "sg:phone":"+32 89 71 69 70",
    "sg:postcode":"3620",
    "sg:province":"Limburg",
    "wof:name":"Kbc",
    "wof:placetype":"venue"
},
  "geometry": {"coordinates":[5.6507310867,50.8898658752],"type":"Point"}
}