{
  "type": "Feature",
  "properties": {
    "iso:country":"BE",
    "sg:address":"Vredestraat 54",
    "sg:city":"Wervik",
    "sg:orig_category":"Artsen and specialisten",
    "sg:phone":"+32 56 31 33 23",
    "sg:postcode":"8940",
    "sg:province":"West-Vlaanderen",
    "wof:name":"Koen Titeca",
    "wof:placetype":"venue"
},
  "geometry": {"coordinates":[3.0491080284,50.7855644226],"type":"Point"}
}