{
  "type": "Feature",
  "properties": {
    "iso:country":"BE",
    "sg:address":"Rue Vaussalle 3",
    "sg:city":"Andenne (nam\u00eache)",
    "sg:classifiers":[
        {
            "category":"Organizations",
            "subcategory":"Community Association",
            "type":"Services"
        }
    ],
    "sg:phone":"+32 81 58 12 43",
    "sg:postcode":"5300",
    "sg:province":"Namur",
    "sg:tags":[
        "cultural"
    ],
    "wof:name":"Foyer Culturel Jules Bodard",
    "wof:placetype":"venue"
},
  "geometry": {"coordinates":[4.9944500923,50.4715805054],"type":"Point"}
}