{
  "type": "Feature",
  "properties": {
    "iso:country":"BE",
    "sg:address":"Rue De La Gare 14",
    "sg:city":"Waimes",
    "sg:orig_category":"Vakantiehuizen",
    "sg:phone":"+32 80 67 80 29",
    "sg:postcode":"4950",
    "sg:province":"Li\u00e8ge",
    "wof:name":"E.grosjean",
    "wof:placetype":"venue"
},
  "geometry": {"coordinates":[6.1144528389,50.4136581421],"type":"Point"}
}