{
  "type": "Feature",
  "properties": {
    "addr:full":"Koerselsebaan 16 Heusden-zolder Limburg 3550",
    "addr:housenumber":"16",
    "addr:postcode":"3550",
    "addr:street":"Koerselsebaan",
    "iso:country":"BE",
    "sg:address":"Koerselsebaan 16",
    "sg:city":"Heusden-zolder",
    "sg:orig_category":"Biens d'occasion. Eclairage et \u00e9quipements du foyer",
    "sg:phone":"+32 11 42 18 05",
    "sg:postcode":"3550",
    "sg:province":"Limburg",
    "wof:name":"Oxfam Wereldwinkel",
    "wof:placetype":"venue"
},
  "geometry": {"coordinates":[5.2823438644,51.0345993042],"type":"Point"}
}