{
  "type": "Feature",
  "properties": {
    "addr:full":"Rue Du Chalet 38 Aywaille Li\u00e8ge 4920",
    "addr:housenumber":"38",
    "addr:postcode":"4920",
    "addr:street":"Rue Du Chalet",
    "iso:country":"BE",
    "sg:address":"Rue Du Chalet 38",
    "sg:city":"Aywaille",
    "sg:classifiers":[
        {
            "category":"Retail",
            "subcategory":"Repair Shop",
            "type":"Services"
        }
    ],
    "sg:phone":"+32 4 384 64 88",
    "sg:postcode":"4920",
    "sg:province":"Li\u00e8ge",
    "sg:tags":[
        "denture"
    ],
    "wof:name":"Bertrand F Dentsply",
    "wof:placetype":"venue"
},
  "geometry": {"coordinates":[5.678355217,50.4700584412],"type":"Point"}
}