{
  "type": "Feature",
  "properties": {
    "iso:country":"BE",
    "sg:address":"Plantinkaai 24-26",
    "sg:city":"Antwerpen",
    "sg:orig_category":"Agences immobili\u00e8res",
    "sg:phone":"+32 3 233 33 00",
    "sg:postcode":"2000",
    "sg:province":"Antwerpen",
    "wof:name":"Amber Vastgoed",
    "wof:placetype":"venue"
},
  "geometry": {"coordinates":[4.3941421509,51.2167816162],"type":"Point"}
}