{
  "type": "Feature",
  "properties": {
    "iso:country":"BE",
    "sg:address":"Henry Dunantlaan 7",
    "sg:city":"Evere/evere",
    "sg:orig_category":"Artsen and specialisten",
    "sg:phone":"+32 2 705 26 32",
    "sg:postcode":"1140",
    "sg:province":"Bruxelles-Capitale",
    "wof:name":"M. Detemmerman",
    "wof:placetype":"venue"
},
  "geometry": {"coordinates":[4.4065651894,50.8613700867],"type":"Point"}
}