{
  "type": "Feature",
  "properties": {
    "addr:full":"Steenweg Op Meerhout 42 Laakdal Antwerpen 2430",
    "addr:housenumber":"42",
    "addr:postcode":"2430",
    "addr:street":"Steenweg Op Meerhout",
    "iso:country":"BE",
    "sg:address":"Steenweg Op Meerhout 42",
    "sg:city":"Laakdal",
    "sg:classifiers":[
        {
            "category":"Building & Trades",
            "subcategory":"Construction",
            "type":"Services"
        }
    ],
    "sg:phone":"+32 14 86 66 05",
    "sg:postcode":"2430",
    "sg:province":"Antwerpen",
    "sg:tags":[
        "machine",
        "hiring"
    ],
    "wof:name":"Couwenberghs",
    "wof:placetype":"venue"
},
  "geometry": {"coordinates":[5.01790905,51.1094245911],"type":"Point"}
}