{
  "type": "Feature",
  "properties": {
    "iso:country":"BE",
    "sg:address":"Brabantstraat 130",
    "sg:city":"Schaarbeek/schaerbeek",
    "sg:orig_category":"Kruideniers Verlichting and huishoudartikelen",
    "sg:phone":"+32 2 219 22 46",
    "sg:postcode":"1030",
    "sg:province":"Bruxelles-Capitale",
    "wof:name":"Maison M.c. Negoce",
    "wof:placetype":"venue"
},
  "geometry": {"coordinates":[4.3627848625,50.8597183228],"type":"Point"}
}