{
  "type": "Feature",
  "properties": {
    "addr:full":"Kluizenhof 27 Sint-gillis-waas Oost-Vlaanderen 9170",
    "addr:housenumber":"27",
    "addr:postcode":"9170",
    "addr:street":"Kluizenhof",
    "iso:country":"BE",
    "sg:address":"Kluizenhof 27",
    "sg:city":"Sint-gillis-waas",
    "sg:classifiers":[
        {
            "category":"Home & Garden",
            "subcategory":"Building Materials",
            "type":"Retail Goods"
        }
    ],
    "sg:phone":"+32 3 727 12 50",
    "sg:postcode":"9170",
    "sg:province":"Oost-Vlaanderen",
    "sg:tags":[
        "house"
    ],
    "wof:name":"Vetrabo Bvba",
    "wof:placetype":"venue"
},
  "geometry": {"coordinates":[4.0916900635,51.2286758423],"type":"Point"}
}