{
  "type": "Feature",
  "properties": {
    "addr:full":"Chauss\u00e9e De Ramioul 298 Fl\u00e9malle (ivoz-ramet) Li\u00e8ge 4400",
    "addr:housenumber":"298",
    "addr:postcode":"4400",
    "addr:street":"Chausse\u0301E De Ramioul;Ivoz-Ramet",
    "iso:country":"BE",
    "sg:address":"Chauss\u00e9e De Ramioul 298",
    "sg:city":"Fl\u00e9malle (ivoz-ramet)",
    "sg:classifiers":[
        {
            "category":"Building & Trades",
            "subcategory":"Cleaning & Sanitation",
            "type":"Services"
        }
    ],
    "sg:phone":"+32 4 273 01 13",
    "sg:postcode":"4400",
    "sg:province":"Li\u00e8ge",
    "sg:tags":[
        "sweep",
        "chimney"
    ],
    "wof:name":"Socothermic Sprl",
    "wof:placetype":"venue"
},
  "geometry": {"coordinates":[5.4576430321,50.5693130493],"type":"Point"}
}