{
  "type": "Feature",
  "properties": {
    "addr:full":"Keibergstraat 146 Torhout West-Vlaanderen 8820",
    "addr:housenumber":"146",
    "addr:postcode":"8820",
    "addr:street":"Keibergstraat",
    "iso:country":"BE",
    "sg:address":"Keibergstraat 146",
    "sg:city":"Torhout",
    "sg:orig_category":"Voertuigen",
    "sg:phone":"+32 50 21 28 60",
    "sg:postcode":"8820",
    "sg:province":"West-Vlaanderen",
    "wof:name":"Garage Muylaert",
    "wof:placetype":"venue"
},
  "geometry": {"coordinates":[3.1200690269,51.0803146362],"type":"Point"}
}