{
  "type": "Feature",
  "properties": {
    "addr:full":"Leuvensesteenweg 88 Diest Vlaams-Brabant 3290",
    "addr:housenumber":"88",
    "addr:postcode":"3290",
    "addr:street":"Leuvensesteenweg",
    "iso:country":"BE",
    "sg:address":"Leuvensesteenweg 88",
    "sg:city":"Diest",
    "sg:classifiers":[
        {
            "category":"Freight",
            "type":"Transportation"
        }
    ],
    "sg:phone":"+32 13 77 73 94",
    "sg:postcode":"3290",
    "sg:province":"Vlaams-Brabant",
    "sg:tags":[
        "-",
        "transport"
    ],
    "wof:name":"Feditrans Bvba",
    "wof:placetype":"venue"
},
  "geometry": {"coordinates":[5.0439658165,50.9771080017],"type":"Point"}
}