{
  "type": "Feature",
  "properties": {
    "iso:country":"BE",
    "sg:address":"Brusselsestraat 100",
    "sg:city":"Geraardsbergen",
    "sg:orig_category":"Editeurs de livres. Enregistrements sonores",
    "sg:phone":"+32 54 41 74 55",
    "sg:postcode":"9500",
    "sg:province":"Oost-Vlaanderen",
    "wof:name":"Mm-recording Studio",
    "wof:placetype":"venue"
},
  "geometry": {"coordinates":[3.8843801022,50.7716445923],"type":"Point"}
}