{
  "type": "Feature",
  "properties": {
    "iso:country":"BE",
    "sg:address":"Oude Gistelseweg 18",
    "sg:city":"Oudenburg (westkerke)",
    "sg:classifiers":[
        {
            "category":"Ice Cream",
            "type":"Food & Drink"
        }
    ],
    "sg:phone":"+32 59 26 78 88",
    "sg:postcode":"8460",
    "sg:province":"West-Vlaanderen",
    "wof:name":"Lijsterbes (de)",
    "wof:placetype":"venue"
},
  "geometry": {"coordinates":[3.0026469231,51.1671485901],"type":"Point"}
}