{
  "type": "Feature",
  "properties": {
    "iso:country":"BE",
    "sg:address":"Boomgaardstraat 348",
    "sg:city":"Antwerpen (berchem)",
    "sg:classifiers":[
        {
            "category":"Building & Trades",
            "subcategory":"Equipment Rental",
            "type":"Services"
        }
    ],
    "sg:phone":"+32 475 22 45 41",
    "sg:postcode":"2600",
    "sg:province":"Antwerpen",
    "sg:tags":[
        "sound",
        "-",
        "system"
    ],
    "wof:name":"Soundcheck",
    "wof:placetype":"venue"
},
  "geometry": {"coordinates":[4.4306030273,51.2001724243],"type":"Point"}
}