{
  "type": "Feature",
  "properties": {
    "addr:full":"Rue Nestor Bouillon 16 Somme-leuze Namur 5377",
    "addr:housenumber":"16",
    "addr:postcode":"5377",
    "addr:street":"Rue Nestor Bouillon",
    "iso:country":"BE",
    "sg:address":"Rue Nestor Bouillon 16",
    "sg:city":"Somme-leuze",
    "sg:orig_category":"Architectes",
    "sg:phone":"+32 86 32 33 20",
    "sg:postcode":"5377",
    "sg:province":"Namur",
    "wof:name":"Pirlet Caroline",
    "wof:placetype":"venue"
},
  "geometry": {"coordinates":[5.2521657944,50.2727966309],"type":"Point"}
}