{
  "type": "Feature",
  "properties": {
    "iso:country":"BE",
    "sg:address":"Eugeen Verelstlei 59",
    "sg:city":"Borsbeek",
    "sg:orig_category":"Installation \u00e9lectrique r\u00e9sidentielle",
    "sg:phone":"+32 3 366 58 11",
    "sg:postcode":"2150",
    "sg:province":"Antwerpen",
    "wof:name":"Elektrotechniek Antwerpen",
    "wof:placetype":"venue"
},
  "geometry": {"coordinates":[4.4936170578,51.1971054077],"type":"Point"}
}