{
  "type": "Feature",
  "properties": {
    "addr:full":"Kapellestraat 34 Evergem Oost-Vlaanderen 9940",
    "addr:housenumber":"34",
    "addr:postcode":"9940",
    "addr:street":"Kapellestraat;Oost-Vlaanderen",
    "iso:country":"BE",
    "sg:address":"Kapellestraat 34",
    "sg:city":"Evergem",
    "sg:orig_category":"Medische apparatuur, orthopedische artikelen and prothesen Fab",
    "sg:phone":"+32 9 253 90 83",
    "sg:postcode":"9940",
    "sg:province":"Oost-Vlaanderen",
    "wof:name":"Bart Van Acker",
    "wof:placetype":"venue"
},
  "geometry": {"coordinates":[3.7103528976,51.1109809875],"type":"Point"}
}