{
  "type": "Feature",
  "properties": {
    "iso:country":"BE",
    "sg:address":"Zwijvegemstraat 10",
    "sg:city":"Mechelen",
    "sg:orig_category":"Waterzuivering",
    "sg:phone":"+32 15 41 59 87",
    "sg:postcode":"2812",
    "sg:province":"Antwerpen",
    "wof:name":"H & V Chemicals",
    "wof:placetype":"venue"
},
  "geometry": {"coordinates":[4.5012907982,51.009979248],"type":"Point"}
}