{
  "type": "Feature",
  "properties": {
    "addr:full":"Chateau De Sclassin Soiron Li\u00e8ge 4861",
    "addr:postcode":"4861",
    "iso:country":"BE",
    "sg:address":"Chateau De Sclassin",
    "sg:city":"Soiron",
    "sg:classifiers":[
        {
            "category":"Health Services",
            "subcategory":"Doctor",
            "type":"Services"
        }
    ],
    "sg:phone":"+32 87 46 15 70",
    "sg:postcode":"4861",
    "sg:province":"Li\u00e8ge",
    "sg:tags":[
        "medicinephysicians",
        "surgeon"
    ],
    "wof:name":"Crielaard J M",
    "wof:placetype":"venue"
},
  "geometry": {"coordinates":[5.7906870842,50.5916099548],"type":"Point"}
}