{
  "type": "Feature",
  "properties": {
    "iso:country":"BE",
    "sg:address":"Bankloopstraat 15",
    "sg:city":"Olen",
    "sg:orig_category":"Sportclubs",
    "sg:phone":"+32 14 21 35 36",
    "sg:postcode":"2250",
    "sg:province":"Antwerpen",
    "wof:name":"K.a.m.c. Herentals",
    "wof:placetype":"venue"
},
  "geometry": {"coordinates":[4.9067811966,51.1847953796],"type":"Point"}
}