{
  "type": "Feature",
  "properties": {
    "iso:country":"BE",
    "sg:address":"Rubensstraat 30",
    "sg:city":"Turnhout",
    "sg:classifiers":[
        {
            "category":"Health Services",
            "subcategory":"Doctor",
            "type":"Services"
        }
    ],
    "sg:phone":"+32 14 72 42 72",
    "sg:postcode":"2300",
    "sg:province":"Antwerpen",
    "sg:tags":[
        "medicinephysicians",
        "surgeon"
    ],
    "wof:name":"Hofkens Peter",
    "wof:placetype":"venue"
},
  "geometry": {"coordinates":[4.944606781,51.3183670044],"type":"Point"}
}