{
  "type": "Feature",
  "properties": {
    "addr:full":"Rue Ravenstein 3 Bruxelles Bruxelles-Capitale 1000",
    "addr:housenumber":"3",
    "addr:postcode":"1000",
    "addr:street":"Rue Ravenstein",
    "iso:country":"BE",
    "sg:address":"Rue Ravenstein 3",
    "sg:city":"Bruxelles",
    "sg:classifiers":[
        {
            "category":"Communications",
            "type":"Services"
        }
    ],
    "sg:phone":"+32 2 513 09 15",
    "sg:postcode":"1000",
    "sg:province":"Bruxelles-Capitale",
    "sg:tags":[
        "translator"
    ],
    "wof:name":"Chambre Belge Des Traducteurs, Interpr\u00eates Et Philologues",
    "wof:placetype":"venue"
},
  "geometry": {"coordinates":[4.3588218689,50.8437767029],"type":"Point"}
}