{
  "type": "Feature",
  "properties": {
    "addr:full":"Chauss\u00e9e De Waterloo 63 Bruxelles (saint-gilles) Bruxelles-Capitale 1060",
    "addr:housenumber":"63",
    "addr:postcode":"1060",
    "addr:street":"Chausse\u0301E De Waterloo",
    "iso:country":"BE",
    "sg:address":"Chauss\u00e9e De Waterloo 63",
    "sg:city":"Bruxelles (saint-gilles)",
    "sg:classifiers":[
        {
            "category":"Tea Room",
            "subcategory":"None",
            "type":"Food & Drink"
        }
    ],
    "sg:phone":"+32 2 537 35 55",
    "sg:postcode":"1060",
    "sg:province":"Bruxelles-Capitale",
    "wof:name":"Gaufre Dor\u00e9e (la) Sprl",
    "wof:placetype":"venue"
},
  "geometry": {"coordinates":[4.3442702293,50.8300743103],"type":"Point"}
}