{
  "type": "Feature",
  "properties": {
    "iso:country":"BE",
    "sg:address":"Pastoor Bellonstraat",
    "sg:city":"Leuven",
    "sg:classifiers":[
        {
            "category":"Fast Food",
            "type":"Food & Drink"
        }
    ],
    "sg:phone":"+32 16 44 37 00",
    "sg:postcode":"3018",
    "sg:province":"Vlaams-Brabant",
    "sg:tags":[
        "meeneem",
        "restaurant"
    ],
    "wof:name":"Frituur Ymeria",
    "wof:placetype":"venue"
},
  "geometry": {"coordinates":[4.7051901817,50.9264450073],"type":"Point"}
}