{
  "type": "Feature",
  "properties": {
    "iso:country":"BE",
    "sg:address":"Nijverheidslaan 9a",
    "sg:city":"Anzegem (vichte)",
    "sg:classifiers":[
        {
            "category":"Home & Garden",
            "subcategory":"Building Materials",
            "type":"Retail Goods"
        }
    ],
    "sg:phone":"+32 56 77 36 08",
    "sg:postcode":"8570",
    "sg:province":"West-Vlaanderen",
    "sg:tags":[
        "veranda"
    ],
    "wof:name":"Lloyd Hamilton",
    "wof:placetype":"venue"
},
  "geometry": {"coordinates":[3.3910589218,50.8303222656],"type":"Point"}
}