{
  "type": "Feature",
  "properties": {
    "addr:full":"3020 Herent (groot) Vlaams-Brabant 3020",
    "addr:postcode":"3020;3020",
    "addr:street":"Groot Vlaams-Brabant",
    "iso:country":"BE",
    "sg:address":"3020",
    "sg:city":"Herent (groot)",
    "sg:orig_category":"Pharmaciens",
    "sg:phone":"+32 900 10 500",
    "sg:postcode":"3020",
    "sg:province":"Vlaams-Brabant",
    "wof:name":"Pharmacies De Garde",
    "wof:placetype":"venue"
},
  "geometry": {"coordinates":[4.6749200821,50.9079055786],"type":"Point"}
}