{
  "type": "Feature",
  "properties": {
    "addr:full":"Rue De Rametenne 1 Rochefort Namur 5580",
    "addr:housenumber":"1",
    "addr:postcode":"5580",
    "addr:street":"Rue De Rametenne",
    "iso:country":"BE",
    "sg:address":"Rue De Rametenne 1",
    "sg:city":"Rochefort",
    "sg:orig_category":"Herstellingen and onderhoud van auto's",
    "sg:phone":"+32 84 21 11 47",
    "sg:postcode":"5580",
    "sg:province":"Namur",
    "wof:name":"Garage A. Leroy-delhaye",
    "wof:placetype":"venue"
},
  "geometry": {"coordinates":[5.2530698776,50.1241569519],"type":"Point"}
}