{
  "type": "Feature",
  "properties": {
    "addr:full":"Rue Walth\u00c8re Jamar 169-171 Ans Li\u00e8ge 4430",
    "addr:postcode":"169-171;4430",
    "addr:street":"Rue Walthe\u0300Re Jamar",
    "iso:country":"BE",
    "sg:address":"Rue Walth\u00c8re Jamar 169-171",
    "sg:city":"Ans",
    "sg:orig_category":"RESTAURANTS: SALLES DE CONF\u00c9RENCES AND DE R\u00c9CEPTIONS",
    "sg:phone":"+32 4 226 43 46",
    "sg:postcode":"4430",
    "sg:province":"Li\u00e8ge",
    "wof:name":"Le Marguerite",
    "wof:placetype":"venue"
},
  "geometry": {"coordinates":[5.5388040543,50.6528587341],"type":"Point"}
}