{
  "type": "Feature",
  "properties": {
    "addr:full":"Sint-jansplein 63 Antwerpen Antwerpen 2060",
    "addr:housenumber":"63",
    "addr:postcode":"2060",
    "addr:street":"Sint-Jansplein",
    "iso:country":"BE",
    "sg:address":"Sint-jansplein 63",
    "sg:city":"Antwerpen",
    "sg:orig_category":"V\u00e9t\u00e9rinaires",
    "sg:phone":"+32 3 233 23 33",
    "sg:postcode":"2060",
    "sg:province":"Antwerpen",
    "wof:name":"Dierenkliniek St.jan",
    "wof:placetype":"venue"
},
  "geometry": {"coordinates":[4.4173088074,51.2260856628],"type":"Point"}
}