{
  "type": "Feature",
  "properties": {
    "addr:full":"J.p. Minckelersstraat 65 Leuven Vlaams-Brabant 3000",
    "addr:housenumber":"65",
    "addr:postcode":"3000",
    "addr:street":"J.P. Minckelersstraat",
    "iso:country":"BE",
    "sg:address":"J.p. Minckelersstraat 65",
    "sg:city":"Leuven",
    "sg:orig_category":"Non-Classified Establishments",
    "sg:phone":"+32 16 22 98 25",
    "sg:postcode":"3000",
    "sg:province":"Vlaams-Brabant",
    "wof:name":"Drafcon Nv",
    "wof:placetype":"venue"
},
  "geometry": {"coordinates":[4.7041130066,50.8847465515],"type":"Point"}
}