{
  "type": "Feature",
  "properties": {
    "addr:full":"Provincieweg 233 Herzele Oost-Vlaanderen 9550",
    "addr:housenumber":"233",
    "addr:postcode":"9550",
    "addr:street":"Provincieweg;Oost-Vlaanderen",
    "iso:country":"BE",
    "sg:address":"Provincieweg 233",
    "sg:city":"Herzele",
    "sg:orig_category":"Banken and kredietinstellingen",
    "sg:phone":"+32 53 62 25 22",
    "sg:postcode":"9550",
    "sg:province":"Oost-Vlaanderen",
    "wof:name":"Centea",
    "wof:placetype":"venue"
},
  "geometry": {"coordinates":[3.8797619343,50.9000320435],"type":"Point"}
}