{
  "type": "Feature",
  "properties": {
    "iso:country":"BE",
    "sg:address":"Oude Leestsebaan 58",
    "sg:city":"Mechelen",
    "sg:classifiers":[
        {
            "category":"Shopping",
            "subcategory":"Musical Instruments",
            "type":"Retail Goods"
        }
    ],
    "sg:phone":"+32 15 27 03 22",
    "sg:postcode":"2800",
    "sg:province":"Antwerpen",
    "sg:tags":[
        "-"
    ],
    "wof:name":"Christiaens Francis Muziekatelier",
    "wof:placetype":"venue"
},
  "geometry": {"coordinates":[4.4421601295,51.0368652344],"type":"Point"}
}