{
  "type": "Feature",
  "properties": {
    "addr:full":"Steenweg Op Gierle 150 Turnhout Antwerpen 2300",
    "addr:housenumber":"150",
    "addr:postcode":"2300",
    "addr:street":"Steenweg Op Gierle",
    "iso:country":"BE",
    "sg:address":"Steenweg Op Gierle 150",
    "sg:city":"Turnhout",
    "sg:orig_category":"Stations-service and carburants. Entretien and r\u00e9parations de voitures",
    "sg:phone":"+32 14 41 12 41",
    "sg:postcode":"2300",
    "sg:province":"Antwerpen",
    "wof:name":"Garage Delsard V.",
    "wof:placetype":"venue"
},
  "geometry": {"coordinates":[4.9276409149,51.3142814636],"type":"Point"}
}