{
  "type": "Feature",
  "properties": {
    "iso:country":"BE",
    "sg:address":"Oudenaardsestraat 70-72",
    "sg:city":"Harelbeke",
    "sg:classifiers":[
        {
            "category":"Home & Garden",
            "subcategory":"Carpets & Floor Coverings",
            "type":"Retail Goods"
        }
    ],
    "sg:phone":"+32 56 77 83 33",
    "sg:postcode":"8530",
    "sg:province":"West-Vlaanderen",
    "sg:tags":[
        "houses",
        "shed"
    ],
    "wof:name":"Verhaeghe Chalets En Sauna Nv",
    "wof:placetype":"venue"
},
  "geometry": {"coordinates":[3.3406350613,50.8361549377],"type":"Point"}
}