{
  "type": "Feature",
  "properties": {
    "addr:full":"Brugstraat 61 Unit 9b Turnhout Antwerpen 2300",
    "addr:housenumber":"61 unit 9b",
    "addr:postcode":"2300",
    "addr:street":"Brugstraat",
    "iso:country":"BE",
    "sg:address":"Brugstraat 61 Unit 9b",
    "sg:city":"Turnhout",
    "sg:classifiers":[
        {
            "category":"Utilities",
            "subcategory":"Cable",
            "type":"Services"
        }
    ],
    "sg:phone":"+32 14 43 64 43",
    "sg:postcode":"2300",
    "sg:province":"Antwerpen",
    "sg:tags":[
        "accessory"
    ],
    "wof:name":"Lapp Benelux Bv",
    "wof:placetype":"venue"
},
  "geometry": {"coordinates":[4.9502749443,51.3175506592],"type":"Point"}
}