{
  "type": "Feature",
  "properties": {
    "iso:country":"BE",
    "sg:address":"Hoogstraat 293",
    "sg:city":"As",
    "sg:classifiers":[
        {
            "category":"Wholesale",
            "subcategory":"Construction Materials",
            "type":"Manufacturing & Wholesale Goods"
        }
    ],
    "sg:phone":"+32 89 65 97 56",
    "sg:postcode":"3665",
    "sg:province":"Limburg",
    "sg:tags":[
        "elevator"
    ],
    "wof:name":"Liften Pareyn",
    "wof:placetype":"venue"
},
  "geometry": {"coordinates":[5.5937099457,51.0107917786],"type":"Point"}
}