{
  "type": "Feature",
  "properties": {
    "addr:full":"Rue Des Sorbiers 35 Verviers Li\u00e8ge 4800",
    "addr:housenumber":"35",
    "addr:postcode":"4800",
    "addr:street":"Rue Des Sorbiers",
    "iso:country":"BE",
    "sg:address":"Rue Des Sorbiers 35",
    "sg:city":"Verviers",
    "sg:classifiers":[
        {
            "category":"Personal",
            "subcategory":"Beauty Salon",
            "type":"Services"
        }
    ],
    "sg:phone":"+32 87 22 51 74",
    "sg:postcode":"4800",
    "sg:province":"Li\u00e8ge",
    "wof:name":"Centre D'esth\u00e9tique Les Sorbiers",
    "wof:placetype":"venue"
},
  "geometry": {"coordinates":[5.8962922096,50.5687599182],"type":"Point"}
}