{
  "type": "Feature",
  "properties": {
    "addr:full":"Trilpopulierenlaan 2 Sint-genesius-rode/rhode-saint-genese Vlaams-Brabant 1640",
    "addr:housenumber":"2",
    "addr:postcode":"1640",
    "addr:street":"Trilpopulierenlaan",
    "iso:country":"BE",
    "sg:address":"Trilpopulierenlaan 2",
    "sg:city":"Sint-genesius-rode/rhode-saint-genese",
    "sg:orig_category":"Brood, gebak and snoepgoed",
    "sg:phone":"+32 2 358 27 09",
    "sg:postcode":"1640",
    "sg:province":"Vlaams-Brabant",
    "wof:name":"Boul. Lonbois De Richelle",
    "wof:placetype":"venue"
},
  "geometry": {"coordinates":[4.3810319901,50.7575569153],"type":"Point"}
}