{
  "type": "Feature",
  "properties": {
    "iso:country":"BE",
    "sg:address":"Meiboomlaan 28",
    "sg:city":"Tremelo",
    "sg:classifiers":[
        {
            "category":"Professional",
            "subcategory":"Management & Consulting",
            "type":"Services"
        }
    ],
    "sg:phone":"+32 16 53 92 50",
    "sg:postcode":"3120",
    "sg:province":"Vlaams-Brabant",
    "sg:tags":[
        "-",
        "processing",
        "data",
        "consultant"
    ],
    "wof:name":"Mindshare Consulting Bvba",
    "wof:placetype":"venue"
},
  "geometry": {"coordinates":[4.7293329239,51.0084381104],"type":"Point"}
}