{
  "type": "Feature",
  "properties": {
    "addr:full":"Lippenslaan 86 Knokke-heist West-Vlaanderen 8300",
    "addr:housenumber":"86",
    "addr:postcode":"8300",
    "addr:street":"Lippenslaan",
    "iso:country":"BE",
    "sg:address":"Lippenslaan 86",
    "sg:city":"Knokke-heist",
    "sg:orig_category":"Pain, p\u00e2tisseries and confiseries",
    "sg:phone":"+32 50 62 55 43",
    "sg:postcode":"8300",
    "sg:province":"West-Vlaanderen",
    "wof:name":"Chocolaterie Truffy",
    "wof:placetype":"venue"
},
  "geometry": {"coordinates":[3.288310051,51.34425354],"type":"Point"}
}