{
  "type": "Feature",
  "properties": {
    "iso:country":"BE",
    "sg:address":"Bellegemstraat 42",
    "sg:city":"Zwevegem",
    "sg:orig_category":"Non-Classified Establishments",
    "sg:phone":"+32 56 75 48 02",
    "sg:postcode":"8550",
    "sg:province":"West-Vlaanderen",
    "wof:name":"V.l.s. Bvba",
    "wof:placetype":"venue"
},
  "geometry": {"coordinates":[3.3381319046,50.7997131348],"type":"Point"}
}