{
  "type": "Feature",
  "properties": {
    "addr:full":"Monnikenhofstraat 318 Antwerpen Antwerpen 2040",
    "addr:housenumber":"318",
    "addr:postcode":"2040",
    "addr:street":"Monnikenhofstraat",
    "iso:country":"BE",
    "sg:address":"Monnikenhofstraat 318",
    "sg:city":"Antwerpen",
    "sg:classifiers":[
        {
            "category":"Arts & Performance",
            "subcategory":"Music",
            "type":"Entertainment"
        }
    ],
    "sg:phone":"+32 476 36 06 30",
    "sg:postcode":"2040",
    "sg:province":"Antwerpen",
    "sg:tags":[
        "disc-jockeys"
    ],
    "wof:name":"Atmosphere",
    "wof:placetype":"venue"
},
  "geometry": {"coordinates":[4.3317799568,51.3528785706],"type":"Point"}
}