{
  "type": "Feature",
  "properties": {
    "iso:country":"BE",
    "sg:address":"Helleketelweg 5",
    "sg:city":"Poperinge",
    "sg:orig_category":"Installation \u00e9lectrique r\u00e9sidentielle",
    "sg:phone":"+32 57 33 55 89",
    "sg:postcode":"8970",
    "sg:province":"West-Vlaanderen",
    "wof:name":"Dirk Devooght",
    "wof:placetype":"venue"
},
  "geometry": {"coordinates":[2.669328928,50.8388366699],"type":"Point"}
}