{
  "type": "Feature",
  "properties": {
    "addr:full":"Petronellahof 17 Lanaken (rekem) Limburg 3621",
    "addr:housenumber":"17",
    "addr:postcode":"3621",
    "addr:street":"Petronellahof",
    "iso:country":"BE",
    "sg:address":"Petronellahof 17",
    "sg:city":"Lanaken (rekem)",
    "sg:classifiers":[
        {
            "category":"Real Estate",
            "subcategory":"Surveying",
            "type":"Services"
        }
    ],
    "sg:phone":"+32 89 71 69 24",
    "sg:postcode":"3621",
    "sg:province":"Limburg",
    "sg:tags":[
        "surveyor",
        "land"
    ],
    "wof:name":"Straetemans J",
    "wof:placetype":"venue"
},
  "geometry": {"coordinates":[5.6867160797,50.9177017212],"type":"Point"}
}