{
  "type": "Feature",
  "properties": {
    "addr:full":"Vijversstraat 25-29 Hasselt Limburg 3500",
    "addr:postcode":"25-29;3500",
    "addr:street":"Vijversstraat",
    "iso:country":"BE",
    "sg:address":"Vijversstraat 25-29",
    "sg:city":"Hasselt",
    "sg:classifiers":[
        {
            "category":"Real Estate",
            "subcategory":"Architect",
            "type":"Services"
        }
    ],
    "sg:phone":"+32 11 21 19 84",
    "sg:postcode":"3500",
    "sg:province":"Limburg",
    "wof:name":"Kuyken J",
    "wof:placetype":"venue"
},
  "geometry": {"coordinates":[5.3535490036,50.9636077881],"type":"Point"}
}