{
  "type": "Feature",
  "properties": {
    "iso:country":"BE",
    "sg:address":"Oostendestraat 54",
    "sg:city":"Torhout",
    "sg:orig_category":"Newspapers, magazines, periodicals - Distribution",
    "sg:phone":"+32 50 21 46 26",
    "sg:postcode":"8820",
    "sg:province":"West-Vlaanderen",
    "wof:name":"De Kiosk",
    "wof:placetype":"venue"
},
  "geometry": {"coordinates":[3.0975289345,51.065662384],"type":"Point"}
}