{
  "type": "Feature",
  "properties": {
    "addr:full":"Avenue De L\u00b4equinoxe 59 Sint-lambrechts-woluwe/woluwe-saint-lambert Bruxelles-Capitale 1200",
    "addr:housenumber":"59",
    "addr:postcode":"1200",
    "addr:street":"Avenue De L\u00b4Equinoxe",
    "iso:country":"BE",
    "sg:address":"Avenue De L\u00b4equinoxe 59",
    "sg:city":"Sint-lambrechts-woluwe/woluwe-saint-lambert",
    "sg:orig_category":"Experts-comptables",
    "sg:phone":"+32 2 762 20 44",
    "sg:postcode":"1200",
    "sg:province":"Bruxelles-Capitale",
    "wof:name":"Luc Ginsbach",
    "wof:placetype":"venue"
},
  "geometry": {"coordinates":[4.4196529388,50.8479690552],"type":"Point"}
}