{
  "type": "Feature",
  "properties": {
    "addr:full":"Felix D'hoopstraat 115 Tielt West-Vlaanderen 8700",
    "addr:housenumber":"115",
    "addr:postcode":"8700",
    "addr:street":"D'Hoopstraat",
    "iso:country":"BE",
    "sg:address":"Felix D'hoopstraat 115",
    "sg:city":"Tielt",
    "sg:classifiers":[
        {
            "category":"Food & Beverages",
            "subcategory":"Meat & Fish",
            "type":"Retail Goods"
        }
    ],
    "sg:phone":"+32 51 40 12 93",
    "sg:postcode":"8700",
    "sg:province":"West-Vlaanderen",
    "sg:tags":[
        "-",
        "livestock"
    ],
    "wof:name":"Lambrecht Nv",
    "wof:placetype":"venue"
},
  "geometry": {"coordinates":[3.3459730148,50.9976158142],"type":"Point"}
}