{
  "type": "Feature",
  "properties": {
    "iso:country":"BE",
    "sg:address":"Rue Saint-eloi",
    "sg:city":"Morlanwelz",
    "sg:orig_category":"Activit\u00e9s r\u00e9cr\u00e9atives diverses",
    "sg:phone":"+32 64 45 15 44",
    "sg:postcode":"7141",
    "sg:province":"Hainaut",
    "wof:name":"Cercle D'echecs De Carni\u00c8res",
    "wof:placetype":"venue"
},
  "geometry": {"coordinates":[4.2337818146,50.446056366],"type":"Point"}
}