{
  "type": "Feature",
  "properties": {
    "addr:full":"Bijstierstraat 17 Brakel Oost-Vlaanderen 9660",
    "addr:housenumber":"17",
    "addr:postcode":"9660",
    "addr:street":"Bijstierstraat",
    "iso:country":"BE",
    "sg:address":"Bijstierstraat 17",
    "sg:city":"Brakel",
    "sg:orig_category":"Epiceries",
    "sg:phone":"+32 55 42 13 07",
    "sg:postcode":"9660",
    "sg:province":"Oost-Vlaanderen",
    "wof:name":"Victor Harboort",
    "wof:placetype":"venue"
},
  "geometry": {"coordinates":[3.7527599335,50.8204994202],"type":"Point"}
}