{
  "type": "Feature",
  "properties": {
    "iso:country":"BE",
    "sg:address":"Rue Fond-des-vaulx 96",
    "sg:city":"Wellin",
    "sg:orig_category":"Location d'articles de sport, de sport nautique and de camping",
    "sg:phone":"+32 84 38 91 09",
    "sg:postcode":"6920",
    "sg:province":"Luxembourg",
    "wof:name":"H\u00d4te-lesse",
    "wof:placetype":"venue"
},
  "geometry": {"coordinates":[5.1152620316,50.0879859924],"type":"Point"}
}