{
  "type": "Feature",
  "properties": {
    "iso:country":"BE",
    "sg:address":"Nederkouter 147",
    "sg:city":"Gent",
    "sg:classifiers":[
        {
            "category":"Shopping",
            "subcategory":"Jewelry",
            "type":"Retail Goods"
        }
    ],
    "sg:phone":"+32 9 223 83 41",
    "sg:postcode":"9000",
    "sg:province":"Oost-Vlaanderen",
    "sg:tags":[
        "-",
        "imitation"
    ],
    "wof:name":"Basse Terres",
    "wof:placetype":"venue"
},
  "geometry": {"coordinates":[3.7221000195,51.04637146],"type":"Point"}
}