{
  "type": "Feature",
  "properties": {
    "iso:country":"BE",
    "sg:address":"Gistelsesteenweg 22",
    "sg:city":"Brugge",
    "sg:orig_category":"V\u00eatements pour Hommes",
    "sg:phone":"+32 50 33 31 27",
    "sg:postcode":"8000",
    "sg:province":"West-Vlaanderen",
    "wof:name":"Knapp-targa",
    "wof:placetype":"venue"
},
  "geometry": {"coordinates":[3.224891901,51.213924408],"type":"Point"}
}