{
  "type": "Feature",
  "properties": {
    "iso:country":"BE",
    "sg:address":"Grand\u00b4place 33",
    "sg:city":"Chimay",
    "sg:orig_category":"Beautyfarms, relaxatie and lichamelijk welzijn Cosmetica and toiletartikelen Schoonheidssalons",
    "sg:phone":"+32 60 21 26 66",
    "sg:postcode":"6460",
    "sg:province":"Hainaut",
    "wof:name":"Au Parfum Des Sens",
    "wof:placetype":"venue"
},
  "geometry": {"coordinates":[4.3149280548,50.0490455627],"type":"Point"}
}