{
  "type": "Feature",
  "properties": {
    "addr:full":"Avenue De La Clairi\u00c8re 5 Brussel/bruxelles Bruxelles-Capitale 1000",
    "addr:housenumber":"5",
    "addr:postcode":"1000",
    "addr:street":"Avenue De La Clairie\u0300Re;/",
    "iso:country":"BE",
    "sg:address":"Avenue De La Clairi\u00c8re 5",
    "sg:city":"Brussel/bruxelles",
    "sg:orig_category":"Agences de publicit\u00e9",
    "sg:phone":"+32 2 377 96 52",
    "sg:postcode":"1000",
    "sg:province":"Bruxelles-Capitale",
    "wof:name":"Equip Publicity",
    "wof:placetype":"venue"
},
  "geometry": {"coordinates":[4.3743491173,50.8052825928],"type":"Point"}
}