{
  "type": "Feature",
  "properties": {
    "iso:country":"BE",
    "sg:address":"Avenue De Messidor 203",
    "sg:city":"Bruxelles (uccle)",
    "sg:classifiers":[
        {
            "category":"Travel",
            "subcategory":"Travel Agent",
            "type":"Entertainment"
        }
    ],
    "sg:phone":"+32 2 343 65 18",
    "sg:postcode":"1180",
    "sg:province":"Bruxelles-Capitale",
    "sg:tags":[
        "agency"
    ],
    "wof:name":"Let's Go Travel Sprl",
    "wof:placetype":"venue"
},
  "geometry": {"coordinates":[4.3456578255,50.8102111816],"type":"Point"}
}