{
  "type": "Feature",
  "properties": {
    "addr:full":"Nati\u00cbnlaan 195 Knokke-heist West-Vlaanderen 8300",
    "addr:housenumber":"195",
    "addr:postcode":"8300",
    "addr:street":"Natie\u0308Nlaan",
    "iso:country":"BE",
    "sg:address":"Nati\u00cbnlaan 195",
    "sg:city":"Knokke-heist",
    "sg:orig_category":"D\u00e9taillants en pi\u00e8ces and accessoires de voitures",
    "sg:phone":"+32 50 60 87 76",
    "sg:postcode":"8300",
    "sg:province":"West-Vlaanderen",
    "wof:name":"Knokse Bandencentrale",
    "wof:placetype":"venue"
},
  "geometry": {"coordinates":[3.2890501022,51.3361816406],"type":"Point"}
}