{
  "type": "Feature",
  "properties": {
    "iso:country":"BE",
    "sg:address":"Kortemarkstraat 110",
    "sg:city":"Lichtervelde",
    "sg:orig_category":"Travaux d'isolation",
    "sg:phone":"+32 51 72 60 88",
    "sg:postcode":"8810",
    "sg:province":"West-Vlaanderen",
    "wof:name":"R.n.i.",
    "wof:placetype":"venue"
},
  "geometry": {"coordinates":[3.1134469509,51.0238952637],"type":"Point"}
}