{
  "type": "Feature",
  "properties": {
    "addr:full":"Chauss\u00c9e De Louvain 542 Schaarbeek/schaerbeek Bruxelles-Capitale 1030",
    "addr:housenumber":"542",
    "addr:postcode":"1030",
    "addr:street":"Chausse\u0301E De Louvain",
    "iso:country":"BE",
    "sg:address":"Chauss\u00c9e De Louvain 542",
    "sg:city":"Schaarbeek/schaerbeek",
    "sg:orig_category":"Agences immobili\u00e8res",
    "sg:phone":"+32 2 734 55 92",
    "sg:postcode":"1030",
    "sg:province":"Bruxelles-Capitale",
    "wof:name":"Imry Belge",
    "wof:placetype":"venue"
},
  "geometry": {"coordinates":[4.3949232101,50.8540267944],"type":"Point"}
}