{
  "type": "Feature",
  "properties": {
    "iso:country":"BE",
    "sg:address":"Jacob De Meyerstraat 26",
    "sg:city":"Blankenberge",
    "sg:orig_category":"Centres de relaxation and bien-\u00eatre",
    "sg:phone":"+32 50 42 69 96",
    "sg:postcode":"8370",
    "sg:province":"West-Vlaanderen",
    "wof:name":"Freija Vzw",
    "wof:placetype":"venue"
},
  "geometry": {"coordinates":[3.123773098,51.3112487793],"type":"Point"}
}