{
  "type": "Feature",
  "properties": {
    "iso:country":"BE",
    "sg:address":"Prins-bischopssingel 73",
    "sg:city":"Hasselt (groot)",
    "sg:classifiers":[
        {
            "category":"Insurance",
            "subcategory":"Life Insurance",
            "type":"Services"
        }
    ],
    "sg:phone":"+32 11 28 21 11",
    "sg:postcode":"3500",
    "sg:province":"Limburg",
    "sg:tags":[
        "assurance"
    ],
    "wof:name":"Omob",
    "wof:placetype":"venue"
},
  "geometry": {"coordinates":[5.3294811249,50.9163703918],"type":"Point"}
}