{
  "type": "Feature",
  "properties": {
    "iso:country":"BE",
    "sg:address":"Rue De Mons 35",
    "sg:city":"Braine-le-comte",
    "sg:classifiers":[
        {
            "category":"Fast Food",
            "type":"Food & Drink"
        }
    ],
    "sg:phone":"+32 67 84 22 92",
    "sg:postcode":"7090",
    "sg:province":"Hainaut",
    "sg:tags":[
        "fried",
        "stand",
        "potato"
    ],
    "wof:name":"David (chez)",
    "wof:placetype":"venue"
},
  "geometry": {"coordinates":[4.1347022057,50.6093292236],"type":"Point"}
}