{
  "type": "Feature",
  "properties": {
    "addr:full":"Rue Rogier 42 Namur Namur 5000",
    "addr:housenumber":"42",
    "addr:postcode":"5000",
    "addr:street":"Rue Rogier",
    "iso:country":"BE",
    "sg:address":"Rue Rogier 42",
    "sg:city":"Namur",
    "sg:orig_category":"Services pour animaux domestiques",
    "sg:phone":"+32 81 22 97 49",
    "sg:postcode":"5000",
    "sg:province":"Namur",
    "wof:name":"Le Petit Prince",
    "wof:placetype":"venue"
},
  "geometry": {"coordinates":[4.8674521446,50.4673881531],"type":"Point"}
}