{
  "type": "Feature",
  "properties": {
    "iso:country":"BE",
    "sg:address":"Chee De Charleroi 20",
    "sg:city":"Montigny",
    "sg:classifiers":[
        {
            "category":"Banks & Credit Unions",
            "subcategory":"Bank",
            "type":"Services"
        }
    ],
    "sg:phone":"+32 60 31 27 54",
    "sg:postcode":"6080",
    "wof:name":"Cr\u00e9dit Communal",
    "wof:placetype":"venue"
},
  "geometry": {"coordinates":[4.4439110756,50.4085693359],"type":"Point"}
}