{
  "type": "Feature",
  "properties": {
    "addr:full":"Sinjorendreef 58 Zoersel Antwerpen 2980",
    "addr:housenumber":"58",
    "addr:postcode":"2980",
    "addr:street":"Sinjorendreef",
    "iso:country":"BE",
    "sg:address":"Sinjorendreef 58",
    "sg:city":"Zoersel",
    "sg:orig_category":"Forge, Moulage and Profilage des M\u00e9taux",
    "sg:phone":"+32 3 383 32 14",
    "sg:postcode":"2980",
    "sg:province":"Antwerpen",
    "wof:name":"Vervloet Kristof",
    "wof:placetype":"venue"
},
  "geometry": {"coordinates":[4.6615319252,51.2611923218],"type":"Point"}
}