{
  "type": "Feature",
  "properties": {
    "iso:country":"BE",
    "sg:address":"Oude Zak 10",
    "sg:city":"Brugge",
    "sg:classifiers":[
        {
            "category":"Health Services",
            "subcategory":"Dentist",
            "type":"Services"
        }
    ],
    "sg:phone":"+32 50 33 39 65",
    "sg:postcode":"8000",
    "sg:province":"West-Vlaanderen",
    "wof:name":"Decaluw\u00e9 M",
    "wof:placetype":"venue"
},
  "geometry": {"coordinates":[3.219630003,51.2113761902],"type":"Point"}
}