{
  "type": "Feature",
  "properties": {
    "iso:country":"BE",
    "sg:address":"Louis Lepoutrelaan 37",
    "sg:city":"Elsene/ixelles",
    "sg:orig_category":"Artsen and specialisten",
    "sg:phone":"+32 2 345 38 48",
    "sg:postcode":"1050",
    "sg:province":"Bruxelles-Capitale",
    "wof:name":"C. Sohie",
    "wof:placetype":"venue"
},
  "geometry": {"coordinates":[4.3579831123,50.8194885254],"type":"Point"}
}