{
  "type": "Feature",
  "properties": {
    "addr:full":"Assenedestraat 17 Evergem (ertvelde) Oost-Vlaanderen 9940",
    "addr:housenumber":"17",
    "addr:postcode":"9940",
    "addr:street":"Assenedestraat;Ertvelde Oost-Vlaanderen",
    "iso:country":"BE",
    "sg:address":"Assenedestraat 17",
    "sg:city":"Evergem (ertvelde)",
    "sg:classifiers":[
        {
            "category":"Animal Shelter",
            "type":"Public Place"
        }
    ],
    "sg:phone":"+32 9 343 09 99",
    "sg:postcode":"9940",
    "sg:province":"Oost-Vlaanderen",
    "sg:tags":[
        "construction",
        "installation",
        "stable"
    ],
    "wof:name":"Metaalconstructie De Vos M",
    "wof:placetype":"venue"
},
  "geometry": {"coordinates":[3.7802278996,51.1830940247],"type":"Point"}
}