{
  "type": "Feature",
  "properties": {
    "addr:full":"Eernegemweg 147 Jabbeke West-Vlaanderen 8490",
    "addr:housenumber":"147",
    "addr:postcode":"8490",
    "iso:country":"BE",
    "sg:address":"Eernegemweg 147",
    "sg:city":"Jabbeke",
    "sg:orig_category":"Rundveehouders",
    "sg:phone":"+32 50 81 36 84",
    "sg:postcode":"8490",
    "sg:province":"West-Vlaanderen",
    "wof:name":"Andr\u00c9 Lagast",
    "wof:placetype":"venue"
},
  "geometry": {"coordinates":[3.1033239365,51.1630783081],"type":"Point"}
}