{
  "type": "Feature",
  "properties": {
    "addr:full":"Beersebaan 1 Lille Antwerpen 2275",
    "addr:housenumber":"1",
    "addr:postcode":"2275",
    "addr:street":"Beersebaan",
    "iso:country":"BE",
    "sg:address":"Beersebaan 1",
    "sg:city":"Lille",
    "sg:orig_category":"Banken and kredietinstellingen",
    "sg:phone":"+32 14 55 75 83",
    "sg:postcode":"2275",
    "sg:province":"Antwerpen",
    "wof:name":"Fortis",
    "wof:placetype":"venue"
},
  "geometry": {"coordinates":[4.8672528267,51.2683258057],"type":"Point"}
}