{
  "type": "Feature",
  "properties": {
    "iso:country":"BE",
    "sg:address":"De Vunt 7",
    "sg:city":"Holsbeek",
    "sg:classifiers":[
        {
            "category":"Government",
            "subcategory":"Post Office",
            "type":"Public Place"
        }
    ],
    "sg:phone":"+32 16 44 42 28",
    "sg:postcode":"3220",
    "sg:province":"Vlaams-Brabant",
    "sg:tags":[
        "traffic",
        "sign"
    ],
    "wof:name":"Publiway B.v.b.a.",
    "wof:placetype":"venue"
},
  "geometry": {"coordinates":[4.7167978287,50.9123573303],"type":"Point"}
}