{
  "type": "Feature",
  "properties": {
    "iso:country":"BE",
    "sg:address":"Rue De La Gare 24",
    "sg:city":"La Roche-en-ardenne",
    "sg:orig_category":"Notaires",
    "sg:phone":"+32 84 41 11 07",
    "sg:postcode":"6980",
    "sg:province":"Luxembourg",
    "wof:name":"Jean-philippe De Limbourg",
    "wof:placetype":"venue"
},
  "geometry": {"coordinates":[5.5754470825,50.1859779358],"type":"Point"}
}