{
  "type": "Feature",
  "properties": {
    "addr:full":"Westover 11 Alveringem West-Vlaanderen 8690",
    "addr:housenumber":"11",
    "addr:postcode":"8690",
    "addr:street":"Westover",
    "iso:country":"BE",
    "sg:address":"Westover 11",
    "sg:city":"Alveringem",
    "sg:orig_category":"Vakantiehuizen",
    "sg:phone":"+32 58 28 81 44",
    "sg:postcode":"8690",
    "sg:province":"West-Vlaanderen",
    "wof:name":"Westkanterhoeve",
    "wof:placetype":"venue"
},
  "geometry": {"coordinates":[2.7250640392,51.0154533386],"type":"Point"}
}