{
  "type": "Feature",
  "properties": {
    "addr:full":"Rue De La Bruy\u00e8re 90 Seraing Li\u00e8ge 4100",
    "addr:housenumber":"90",
    "addr:postcode":"4100",
    "addr:street":"Rue De La Bruye\u0300Re",
    "iso:country":"BE",
    "sg:address":"Rue De La Bruy\u00e8re 90",
    "sg:city":"Seraing",
    "sg:classifiers":[
        {
            "category":"Professional",
            "subcategory":"Art Services",
            "type":"Services"
        }
    ],
    "sg:phone":"+32 496 05 48 56",
    "sg:postcode":"4100",
    "sg:province":"Li\u00e8ge",
    "sg:tags":[
        "graphic",
        "designer"
    ],
    "wof:name":"No\u00e9 O",
    "wof:placetype":"venue"
},
  "geometry": {"coordinates":[5.5097532272,50.5832214355],"type":"Point"}
}