{
  "type": "Feature",
  "properties": {
    "iso:country":"BE",
    "sg:address":"Rue Z\u00c9phirin Fontaine 120",
    "sg:city":"Binche",
    "sg:orig_category":"Boucheries",
    "sg:phone":"+32 64 33 23 77",
    "sg:postcode":"7130",
    "sg:province":"Hainaut",
    "wof:name":"Gilbert Vandenhende",
    "wof:placetype":"venue"
},
  "geometry": {"coordinates":[4.2024831772,50.4118652344],"type":"Point"}
}