{
  "type": "Feature",
  "properties": {
    "iso:country":"BE",
    "sg:address":"Oude Gentweg 77",
    "sg:city":"Torhout",
    "sg:orig_category":"Installatie van houten of kunststof schrijnwerk",
    "sg:phone":"+32 50 21 45 05",
    "sg:postcode":"8820",
    "sg:province":"West-Vlaanderen",
    "wof:name":"Daniel Willem",
    "wof:placetype":"venue"
},
  "geometry": {"coordinates":[3.1131410599,51.0823402405],"type":"Point"}
}