{
  "type": "Feature",
  "properties": {
    "addr:full":"Schriekstraat 50 Heist-op-den-berg Antwerpen 2223",
    "addr:housenumber":"50",
    "addr:postcode":"2223",
    "addr:street":"Schriekstraat",
    "iso:country":"BE",
    "sg:address":"Schriekstraat 50",
    "sg:city":"Heist-op-den-berg",
    "sg:orig_category":"Slagers",
    "sg:phone":"+32 15 23 40 44",
    "sg:postcode":"2223",
    "sg:province":"Antwerpen",
    "wof:name":"Kippenshop",
    "wof:placetype":"venue"
},
  "geometry": {"coordinates":[4.6935648918,51.0282707214],"type":"Point"}
}