{
  "type": "Feature",
  "properties": {
    "addr:full":"Oude Antwerpsebaan 29 Mechelen Antwerpen 2800",
    "addr:housenumber":"29",
    "addr:postcode":"2800",
    "addr:street":"Oude Antwerpsebaan",
    "iso:country":"BE",
    "sg:address":"Oude Antwerpsebaan 29",
    "sg:city":"Mechelen",
    "sg:orig_category":"HERSTELLING ELEKTRISCHE HUISHOUDAPPARATEN",
    "sg:phone":"+32 15 20 16 44",
    "sg:postcode":"2800",
    "sg:province":"Antwerpen",
    "wof:name":"Jozef Serrien",
    "wof:placetype":"venue"
},
  "geometry": {"coordinates":[4.4699311256,51.0405921936],"type":"Point"}
}