{
  "type": "Feature",
  "properties": {
    "iso:country":"BE",
    "sg:address":"11e Rue 0",
    "sg:city":"Saint-ghislain",
    "sg:orig_category":"Kinderopvang",
    "sg:phone":"+32 65 77 85 41",
    "sg:postcode":"7330",
    "sg:province":"Hainaut",
    "wof:name":"Cr\u00c8che La Bambinade",
    "wof:placetype":"venue"
},
  "geometry": {"coordinates":[3.816534996,50.446849823],"type":"Point"}
}