{
  "type": "Feature",
  "properties": {
    "addr:full":"Groenedreef 19 Kruishoutem Oost-Vlaanderen 9770",
    "addr:housenumber":"19",
    "addr:postcode":"9770",
    "addr:street":"Groenedreef",
    "iso:country":"BE",
    "sg:address":"Groenedreef 19",
    "sg:city":"Kruishoutem",
    "sg:classifiers":[
        {
            "category":"Communications",
            "subcategory":"Film & Video Production",
            "type":"Services"
        }
    ],
    "sg:phone":"+32 9 338 12 11",
    "sg:postcode":"9770",
    "sg:province":"Oost-Vlaanderen",
    "sg:tags":[
        "agricultural"
    ],
    "wof:name":"Polyweave Division Of Beaulieu Real Nv",
    "wof:placetype":"venue"
},
  "geometry": {"coordinates":[3.5181879997,50.9074325562],"type":"Point"}
}