{
  "type": "Feature",
  "properties": {
    "iso:country":"BE",
    "sg:address":"Kouter 35",
    "sg:city":"Lokeren",
    "sg:orig_category":"Openbare veiligheid",
    "sg:phone":"+32 9 348 10 13",
    "sg:postcode":"9160",
    "sg:province":"Oost-Vlaanderen",
    "wof:name":"Federale Politie",
    "wof:placetype":"venue"
},
  "geometry": {"coordinates":[3.9835588932,51.1002998352],"type":"Point"}
}