{
  "type": "Feature",
  "properties": {
    "iso:country":"BE",
    "sg:address":"Kortrijksesteenweg 592",
    "sg:city":"Gent",
    "sg:orig_category":"Opticiens",
    "sg:phone":"+32 9 222 88 70",
    "sg:postcode":"9000",
    "sg:province":"Oost-Vlaanderen",
    "wof:name":"Trioptic",
    "wof:placetype":"venue"
},
  "geometry": {"coordinates":[3.7133278847,51.0315322876],"type":"Point"}
}