{
  "type": "Feature",
  "properties": {
    "iso:country":"BE",
    "sg:address":"Jan Zonder Vreesln 8",
    "sg:city":"Oudenaarde",
    "sg:classifiers":[
        {
            "category":"Travel",
            "subcategory":"Hotels & Motels",
            "type":"Entertainment"
        }
    ],
    "sg:phone":"+32 55 31 89 88",
    "sg:postcode":"9700",
    "sg:province":"Oost-Vlaanderen",
    "sg:tags":[
        "hotels",
        "business",
        "restaurant"
    ],
    "wof:name":"Hotel Restaurant De Rantere Bvba",
    "wof:placetype":"venue"
},
  "geometry": {"coordinates":[3.606069088,50.8412742615],"type":"Point"}
}