{
  "type": "Feature",
  "properties": {
    "iso:country":"BE",
    "sg:address":"Bosquetiastraat 4",
    "sg:city":"Koksijde",
    "sg:orig_category":"MEUBELONTWERP AND -INSTALLATIE Meubelzaken, woning- and keukeninrichting",
    "sg:phone":"+32 58 51 15 70",
    "sg:postcode":"8670",
    "sg:province":"West-Vlaanderen",
    "wof:name":"Godfried Luca",
    "wof:placetype":"venue"
},
  "geometry": {"coordinates":[2.6372170448,51.1160583496],"type":"Point"}
}