{
  "type": "Feature",
  "properties": {
    "iso:country":"BE",
    "sg:address":"Stapelstraat 55",
    "sg:city":"Sint-truiden",
    "sg:classifiers":[
        {
            "category":"Professional",
            "subcategory":"Testing Lab",
            "type":"Services"
        }
    ],
    "sg:phone":"+32 11 68 75 45",
    "sg:postcode":"3800",
    "sg:province":"Limburg",
    "sg:tags":[
        "chemist"
    ],
    "wof:name":"Schalenbourg G",
    "wof:placetype":"venue"
},
  "geometry": {"coordinates":[5.1823267937,50.8152770996],"type":"Point"}
}