{
  "type": "Feature",
  "properties": {
    "iso:country":"BE",
    "sg:address":"Groenspechtlaan 32",
    "sg:city":"Sint-genesius-rode/rhode-saint-genese",
    "sg:classifiers":[
        {
            "category":"Professional",
            "subcategory":"Accounting & Tax Preparation",
            "type":"Services"
        }
    ],
    "sg:phone":"+32 2 358 17 35",
    "sg:postcode":"1640",
    "sg:province":"Vlaams-Brabant",
    "sg:tags":[
        "accountant"
    ],
    "wof:name":"Yves Echement",
    "wof:placetype":"venue"
},
  "geometry": {"coordinates":[4.3649501801,50.772518158],"type":"Point"}
}