{
  "type": "Feature",
  "properties": {
    "iso:country":"BE",
    "sg:address":"De Waterwilgen 2",
    "sg:city":"Brugge",
    "sg:orig_category":"Medische apparatuur, orthopedische artikelen and prothesen Fab",
    "sg:phone":"+32 50 37 29 70",
    "sg:postcode":"8310",
    "sg:province":"West-Vlaanderen",
    "wof:name":"Katrien Biesemans",
    "wof:placetype":"venue"
},
  "geometry": {"coordinates":[3.2451839447,51.2150764465],"type":"Point"}
}