{
  "type": "Feature",
  "properties": {
    "iso:country":"BE",
    "sg:address":"Gen.geneesheer Deracheln 60",
    "sg:city":"Elsene/ixelles",
    "sg:orig_category":"Advocaten and juridische adviseurs",
    "sg:phone":"+32 2 646 23 93",
    "sg:postcode":"1050",
    "sg:province":"Bruxelles-Capitale",
    "wof:name":"P. Deldaele",
    "wof:placetype":"venue"
},
  "geometry": {"coordinates":[4.3871188164,50.8159446716],"type":"Point"}
}