{
  "type": "Feature",
  "properties": {
    "iso:country":"BE",
    "sg:address":"Grensstraat 20",
    "sg:city":"Sint-gillis-waas",
    "sg:orig_category":"Pain, p\u00e2tisseries and confiseries",
    "sg:phone":"+32 3 773 42 43",
    "sg:postcode":"9170",
    "sg:province":"Oost-Vlaanderen",
    "wof:name":"Bakkerij Rottier F. & D.",
    "wof:placetype":"venue"
},
  "geometry": {"coordinates":[4.1642661095,51.291053772],"type":"Point"}
}