{
  "type": "Feature",
  "properties": {
    "iso:country":"BE",
    "sg:address":"Chauss\u00c9e De Fleurus 90ba",
    "sg:city":"Charleroi",
    "sg:orig_category":"Eleveurs de bovins",
    "sg:phone":"+32 71 35 03 13",
    "sg:postcode":"6041",
    "sg:province":"Hainaut",
    "wof:name":"Jean Le Hardy De Beaulieu",
    "wof:placetype":"venue"
},
  "geometry": {"coordinates":[4.4728951454,50.440486908],"type":"Point"}
}