{
  "type": "Feature",
  "properties": {
    "addr:full":"Maastrichterstraat 4 Hasselt Limburg 3500",
    "addr:housenumber":"4",
    "addr:postcode":"3500",
    "addr:street":"Maastrichterstraat",
    "iso:country":"BE",
    "sg:address":"Maastrichterstraat 4",
    "sg:city":"Hasselt",
    "sg:orig_category":"Souvenirs and objets artisanaux",
    "sg:phone":"+32 11 22 65 86",
    "sg:postcode":"3500",
    "sg:province":"Limburg",
    "wof:name":"Huis Sibelle",
    "wof:placetype":"venue"
},
  "geometry": {"coordinates":[5.3381619453,50.9293556213],"type":"Point"}
}