{
  "type": "Feature",
  "properties": {
    "addr:full":"Engelstraat 81 Ichtegem West-Vlaanderen 8480",
    "addr:housenumber":"81",
    "addr:postcode":"8480",
    "addr:street":"Engelstraat",
    "iso:country":"BE",
    "sg:address":"Engelstraat 81",
    "sg:city":"Ichtegem",
    "sg:classifiers":[
        {
            "category":"Health Services",
            "subcategory":"Dentist",
            "type":"Services"
        }
    ],
    "sg:phone":"+32 51 58 02 71",
    "sg:postcode":"8480",
    "sg:province":"West-Vlaanderen",
    "wof:name":"Wildemauwe Linda",
    "wof:placetype":"venue"
},
  "geometry": {"coordinates":[3.0175569057,51.0940933228],"type":"Point"}
}