{
  "type": "Feature",
  "properties": {
    "iso:country":"BE",
    "sg:address":"Route De Ch\u00e2telet 251",
    "sg:city":"Charleroi (couillet)",
    "sg:classifiers":[
        {
            "category":"Professional",
            "subcategory":"Testing Lab",
            "type":"Services"
        }
    ],
    "sg:phone":"+32 71 36 29 44",
    "sg:postcode":"6010",
    "sg:province":"Hainaut",
    "sg:tags":[
        "chemist"
    ],
    "wof:name":"Dubuc N",
    "wof:placetype":"venue"
},
  "geometry": {"coordinates":[4.4647688866,50.3921966553],"type":"Point"}
}