{
  "type": "Feature",
  "properties": {
    "addr:full":"Stationspln 11 Geraardsbergen Oost-Vlaanderen 9500",
    "addr:housenumber":"11",
    "addr:postcode":"9500",
    "addr:street":"Stationspln",
    "iso:country":"BE",
    "sg:address":"Stationspln 11",
    "sg:city":"Geraardsbergen",
    "sg:classifiers":[
        {
            "category":"Banks & Credit Unions",
            "subcategory":"Bank",
            "type":"Services"
        }
    ],
    "sg:phone":"+32 54 41 11 23",
    "sg:postcode":"9500",
    "sg:province":"Oost-Vlaanderen",
    "wof:name":"Krediet Nuverheid",
    "wof:placetype":"venue"
},
  "geometry": {"coordinates":[3.8744499683,50.7705078125],"type":"Point"}
}