{
  "type": "Feature",
  "properties": {
    "iso:country":"BE",
    "sg:address":"Rue Boursoit 15",
    "sg:city":"Onhaye",
    "sg:orig_category":"Bouwwerktuigen Gh Verhuur bouwmachines",
    "sg:phone":"+32 82 22 47 44",
    "sg:postcode":"5524",
    "sg:province":"Namur",
    "wof:name":"Christy",
    "wof:placetype":"venue"
},
  "geometry": {"coordinates":[4.8166332245,50.2447891235],"type":"Point"}
}