{
  "type": "Feature",
  "properties": {
    "addr:full":"Hemelrijkstraat 2 Gingelom Limburg 3891",
    "addr:housenumber":"2",
    "addr:postcode":"3891",
    "addr:street":"Hemelrijkstraat",
    "iso:country":"BE",
    "sg:address":"Hemelrijkstraat 2",
    "sg:city":"Gingelom",
    "sg:orig_category":"Bloemen and planten Gh",
    "sg:phone":"+32 11 83 13 64",
    "sg:postcode":"3891",
    "sg:province":"Limburg",
    "wof:name":"Franse Handelskwekerij",
    "wof:placetype":"venue"
},
  "geometry": {"coordinates":[5.1799378395,50.7381629944],"type":"Point"}
}