{
  "type": "Feature",
  "properties": {
    "addr:full":"Rue De Montigny 30 Charleroi Hainaut 6000",
    "addr:housenumber":"30",
    "addr:postcode":"6000",
    "addr:street":"Rue De Montigny;Hainaut",
    "iso:country":"BE",
    "sg:address":"Rue De Montigny 30",
    "sg:city":"Charleroi",
    "sg:classifiers":[
        {
            "category":"Personal",
            "subcategory":"Tattoo Parlor",
            "type":"Services"
        }
    ],
    "sg:phone":"+32 71 61 36 00",
    "sg:postcode":"6000",
    "sg:province":"Hainaut",
    "sg:tags":[
        "tattooists"
    ],
    "wof:name":"Bob Tattoo & Piercing",
    "wof:placetype":"venue"
},
  "geometry": {"coordinates":[4.4442820549,50.4085197449],"type":"Point"}
}