{
  "type": "Feature",
  "properties": {
    "iso:country":"BE",
    "sg:address":"Opperstraat 182",
    "sg:city":"Liedekerke",
    "sg:classifiers":[
        {
            "category":"Bars & Pubs",
            "type":"Food & Drink"
        }
    ],
    "sg:phone":"+32 53 67 04 95",
    "sg:postcode":"1770",
    "sg:province":"Vlaams-Brabant",
    "wof:name":"Sportcaf\u00e9 ('t)",
    "wof:placetype":"venue"
},
  "geometry": {"coordinates":[4.0929951668,50.8684997559],"type":"Point"}
}