{
  "type": "Feature",
  "properties": {
    "iso:country":"BE",
    "sg:address":"Achterheidestraat 28",
    "sg:city":"Tessenderlo",
    "sg:orig_category":"Woningbouw",
    "sg:phone":"+32 13 77 82 28",
    "sg:postcode":"3980",
    "sg:province":"Limburg",
    "wof:name":"Paul Brems",
    "wof:placetype":"venue"
},
  "geometry": {"coordinates":[5.0875849724,51.0672340393],"type":"Point"}
}