{
  "type": "Feature",
  "properties": {
    "addr:full":"Rue De La Fraternit\u00c9 14 Chapelle-lez-herlaimont Hainaut 7160",
    "addr:housenumber":"14",
    "addr:postcode":"7160",
    "addr:street":"Rue De La Fraternite\u0301",
    "iso:country":"BE",
    "sg:address":"Rue De La Fraternit\u00c9 14",
    "sg:city":"Chapelle-lez-herlaimont",
    "sg:orig_category":"Woningbouw",
    "sg:phone":"+32 64 45 85 26",
    "sg:postcode":"7160",
    "sg:province":"Hainaut",
    "wof:name":"G.fulco",
    "wof:placetype":"venue"
},
  "geometry": {"coordinates":[4.2924289703,50.4958992004],"type":"Point"}
}