{
  "type": "Feature",
  "properties": {
    "iso:country":"BE",
    "sg:address":"Kleine Dam 33",
    "sg:city":"Lokeren",
    "sg:classifiers":[
        {
            "category":"Health Services",
            "subcategory":"Health Practitioner",
            "type":"Services"
        }
    ],
    "sg:phone":"+32 9 349 17 60",
    "sg:postcode":"9160",
    "sg:province":"Oost-Vlaanderen",
    "sg:tags":[
        "physiotherapist"
    ],
    "wof:name":"Saeys Bart - Van Moeseke Veronique",
    "wof:placetype":"venue"
},
  "geometry": {"coordinates":[3.9832859039,51.1022109985],"type":"Point"}
}