{
  "type": "Feature",
  "properties": {
    "iso:country":"BE",
    "sg:address":"Meilaan 11",
    "sg:city":"Sint-lambrechts-woluwe/woluwe-saint-lambert",
    "sg:orig_category":"Dierenartsen",
    "sg:phone":"+32 2 772 65 50",
    "sg:postcode":"1200",
    "sg:province":"Bruxelles-Capitale",
    "wof:name":"Fr\u00c9d\u00c9ric Lewinson",
    "wof:placetype":"venue"
},
  "geometry": {"coordinates":[4.4238982201,50.8481826782],"type":"Point"}
}