{
  "type": "Feature",
  "properties": {
    "addr:full":"Dr\u00e8ve Des Agaves 7 Bruxelles (anderlecht) Bruxelles-Capitale 1070",
    "addr:housenumber":"7",
    "addr:postcode":"1070",
    "addr:street":"Dre\u0300Ve Des Agaves",
    "iso:country":"BE",
    "sg:address":"Dr\u00e8ve Des Agaves 7",
    "sg:city":"Bruxelles (anderlecht)",
    "sg:classifiers":[
        {
            "category":"Health Services",
            "subcategory":"Doctor",
            "type":"Services"
        }
    ],
    "sg:phone":"+32 2 522 23 38",
    "sg:postcode":"1070",
    "sg:province":"Bruxelles-Capitale",
    "sg:tags":[
        "medicinephysicians",
        "surgeon"
    ],
    "wof:name":"Desmet Albert",
    "wof:placetype":"venue"
},
  "geometry": {"coordinates":[4.2855029106,50.8338928223],"type":"Point"}
}