{
  "type": "Feature",
  "properties": {
    "addr:full":"Haachtsesteenweg 1896 Brussel/bruxelles Bruxelles-Capitale 1130",
    "addr:postcode":"1896;/ bruxelles;1130",
    "addr:street":"Haachtsesteenweg",
    "iso:country":"BE",
    "sg:address":"Haachtsesteenweg 1896",
    "sg:city":"Brussel/bruxelles",
    "sg:orig_category":"Diverse bouwafwerking and reiniging Loodgieterij, verwarming and sanitaire installaties",
    "sg:phone":"+32 2 705 12 78",
    "sg:postcode":"1130",
    "sg:province":"Bruxelles-Capitale",
    "wof:name":"F.y.s. Et Fr\u00c8res",
    "wof:placetype":"venue"
},
  "geometry": {"coordinates":[4.4263339043,50.8899116516],"type":"Point"}
}