{
  "type": "Feature",
  "properties": {
    "iso:country":"BE",
    "sg:address":"Kaulillerdorp 25",
    "sg:city":"Bocholt",
    "sg:classifiers":[
        {
            "category":"Cafe",
            "type":"Food & Drink"
        }
    ],
    "sg:phone":"+32 11 62 14 82",
    "sg:postcode":"3950",
    "sg:province":"Limburg",
    "sg:tags":[
        "caf\u00e9s"
    ],
    "wof:name":"Desire Reynders",
    "wof:placetype":"venue"
},
  "geometry": {"coordinates":[5.5167970657,51.1898651123],"type":"Point"}
}