{
  "type": "Feature",
  "properties": {
    "iso:country":"BE",
    "sg:address":"Rue Du Trieu 23",
    "sg:city":"Mont-de-l\u00b4enclus",
    "sg:orig_category":"Ordinateurs and \u00e9quipement informatique",
    "sg:phone":"+32 69 76 91 11",
    "sg:postcode":"7750",
    "sg:province":"Hainaut",
    "wof:name":"Mc Tec",
    "wof:placetype":"venue"
},
  "geometry": {"coordinates":[3.5288848877,50.7585525513],"type":"Point"}
}