{
  "type": "Feature",
  "properties": {
    "addr:full":"Borgerhoutsedijk 55 Mol Antwerpen 2400",
    "addr:housenumber":"55",
    "addr:postcode":"2400",
    "addr:street":"Borgerhoutsedijk",
    "iso:country":"BE",
    "sg:address":"Borgerhoutsedijk 55",
    "sg:city":"Mol",
    "sg:orig_category":"D\u00e9taillants en pi\u00e8ces and accessoires de voitures. Entretien and r\u00e9parations de voitures. V\u00e9hicules ",
    "sg:phone":"+32 14 31 56 74",
    "sg:postcode":"2400",
    "sg:province":"Antwerpen",
    "wof:name":"Autobedrijf L. Thijs Mol N.v.",
    "wof:placetype":"venue"
},
  "geometry": {"coordinates":[5.1074409485,51.1768608093],"type":"Point"}
}