{
  "type": "Feature",
  "properties": {
    "addr:full":"Stationsplein 17 Denderleeuw Oost-Vlaanderen 9470",
    "addr:housenumber":"17",
    "addr:postcode":"9470",
    "addr:street":"Stationsplein",
    "iso:country":"BE",
    "sg:address":"Stationsplein 17",
    "sg:city":"Denderleeuw",
    "sg:orig_category":"Chaussures",
    "sg:phone":"+32 53 66 36 60",
    "sg:postcode":"9470",
    "sg:province":"Oost-Vlaanderen",
    "wof:name":"Asics Benelux",
    "wof:placetype":"venue"
},
  "geometry": {"coordinates":[4.0716509819,50.8924026489],"type":"Point"}
}