{
  "type": "Feature",
  "properties": {
    "addr:full":"Rue De La Margelle 3 Ottignies-louvain-la-neuve Brabant Wallon 1341",
    "addr:housenumber":"3",
    "addr:postcode":"1341",
    "addr:street":"Rue De La Margelle",
    "iso:country":"BE",
    "sg:address":"Rue De La Margelle 3",
    "sg:city":"Ottignies-louvain-la-neuve",
    "sg:orig_category":"Elektrische installaties voor woningen",
    "sg:phone":"+32 10 61 41 22",
    "sg:postcode":"1341",
    "sg:province":"Brabant Wallon",
    "wof:name":"Pro Safe",
    "wof:placetype":"venue"
},
  "geometry": {"coordinates":[4.5627598763,50.6583099365],"type":"Point"}
}