{
  "type": "Feature",
  "properties": {
    "addr:full":"Schouwvegersstraat 20 Antwerpen Antwerpen 2040",
    "addr:housenumber":"20",
    "addr:postcode":"2040",
    "addr:street":"Schouwvegersstraat",
    "iso:country":"BE",
    "sg:address":"Schouwvegersstraat 20",
    "sg:city":"Antwerpen",
    "sg:classifiers":[
        {
            "category":"Building & Trades",
            "subcategory":"Plumbing",
            "type":"Services"
        }
    ],
    "sg:phone":"+32 3 568 98 98",
    "sg:postcode":"2040",
    "sg:province":"Antwerpen",
    "sg:tags":[
        "contractor"
    ],
    "wof:name":"Verhaegen J",
    "wof:placetype":"venue"
},
  "geometry": {"coordinates":[4.3207101822,51.3409500122],"type":"Point"}
}