{
  "type": "Feature",
  "properties": {
    "addr:full":"Energielaan 14 Kapellen Antwerpen 2950",
    "addr:housenumber":"14",
    "addr:postcode":"2950",
    "addr:street":"Energielaan",
    "iso:country":"BE",
    "sg:address":"Energielaan 14",
    "sg:city":"Kapellen",
    "sg:orig_category":"Non-Classified Establishments",
    "sg:phone":"+32 3 620 20 70",
    "sg:postcode":"2950",
    "sg:province":"Antwerpen",
    "wof:name":"Delafaille Chocolatier Nv",
    "wof:placetype":"venue"
},
  "geometry": {"coordinates":[4.5022139549,51.3554763794],"type":"Point"}
}