{
  "type": "Feature",
  "properties": {
    "addr:full":"Bd Lambermont 111 Bruxelles Bruxelles-Capitale 1030",
    "addr:housenumber":"111",
    "addr:postcode":"1030",
    "addr:street":"Bd Lambermont",
    "iso:country":"BE",
    "sg:address":"Bd Lambermont 111",
    "sg:city":"Bruxelles",
    "sg:classifiers":[
        {
            "category":"Manufacturing",
            "subcategory":"Rubber & Plastics",
            "type":"Manufacturing & Wholesale Goods"
        }
    ],
    "sg:phone":"+32 2 241 86 48",
    "sg:postcode":"1030",
    "sg:province":"Bruxelles-Capitale",
    "wof:name":"Inolit Belgium Bvba",
    "wof:placetype":"venue"
},
  "geometry": {"coordinates":[4.3804879189,50.8715438843],"type":"Point"}
}