{
  "type": "Feature",
  "properties": {
    "addr:full":"Mercatorstraat 42 Antwerpen Antwerpen 2018",
    "addr:housenumber":"42",
    "addr:postcode":"2018",
    "addr:street":"Mercatorstraat",
    "iso:country":"BE",
    "sg:address":"Mercatorstraat 42",
    "sg:city":"Antwerpen",
    "sg:orig_category":"Produits interm\u00e9diaires Gr",
    "sg:phone":"+32 3 239 00 90",
    "sg:postcode":"2018",
    "sg:province":"Antwerpen",
    "wof:name":"Hirsh Geldzahler",
    "wof:placetype":"venue"
},
  "geometry": {"coordinates":[4.4230799675,51.2087173462],"type":"Point"}
}