{
  "type": "Feature",
  "properties": {
    "addr:full":"Rue Du Cerf 81 Rixensart (genval) Brabant Wallon 1332",
    "addr:housenumber":"81",
    "addr:postcode":"1332",
    "addr:street":"Rue Du Cerf",
    "iso:country":"BE",
    "sg:address":"Rue Du Cerf 81",
    "sg:city":"Rixensart (genval)",
    "sg:classifiers":[
        {
            "category":"Shopping",
            "subcategory":"Crafts & Fabrics",
            "type":"Retail Goods"
        }
    ],
    "sg:phone":"+32 2 653 92 67",
    "sg:postcode":"1332",
    "sg:province":"Brabant Wallon",
    "sg:tags":[
        "paints",
        "varnish",
        "-",
        "lacquers",
        "enamel"
    ],
    "wof:name":"Genval D\u00e9cor Sprl",
    "wof:placetype":"venue"
},
  "geometry": {"coordinates":[4.5090050697,50.7290802002],"type":"Point"}
}