{
  "type": "Feature",
  "properties": {
    "addr:full":"Rue Des Saules 78 Huy Li\u00e8ge 4500",
    "addr:housenumber":"78",
    "addr:postcode":"4500",
    "addr:street":"Rue Des Saules",
    "iso:country":"BE",
    "sg:address":"Rue Des Saules 78",
    "sg:city":"Huy",
    "sg:orig_category":"Magasins de r\u00e9parations d'articles personnels et m\u00e9nagers divers",
    "sg:phone":"+32 85 23 04 44",
    "sg:postcode":"4500",
    "sg:province":"Li\u00e8ge",
    "wof:name":"Maison Le D\u00c9 \u00c0 Coudre",
    "wof:placetype":"venue"
},
  "geometry": {"coordinates":[5.2548570633,50.5332756042],"type":"Point"}
}