{
  "type": "Feature",
  "properties": {
    "addr:full":"Neervenweg 115 Wuustwezel Antwerpen 2990",
    "addr:housenumber":"115",
    "addr:postcode":"2990",
    "addr:street":"Neervenweg",
    "iso:country":"BE",
    "sg:address":"Neervenweg 115",
    "sg:city":"Wuustwezel",
    "sg:orig_category":"Rundveehouders",
    "sg:phone":"+32 3 669 84 09",
    "sg:postcode":"2990",
    "sg:province":"Antwerpen",
    "wof:name":"Marc Cools",
    "wof:placetype":"venue"
},
  "geometry": {"coordinates":[4.6345992088,51.3875465393],"type":"Point"}
}