{
  "type": "Feature",
  "properties": {
    "iso:country":"BE",
    "sg:address":"Rue De La Houssi\u00e8re 1",
    "sg:city":"Mons",
    "sg:classifiers":[
        {
            "category":"Bars & Pubs",
            "type":"Food & Drink"
        }
    ],
    "sg:phone":"+32 65 35 11 42",
    "sg:postcode":"7000",
    "sg:province":"Hainaut",
    "wof:name":"Bon Vieux Temps (au)",
    "wof:placetype":"venue"
},
  "geometry": {"coordinates":[3.945086956,50.4534606934],"type":"Point"}
}