{
  "type": "Feature",
  "properties": {
    "addr:full":"Bergensesteenweg 32 Lot Vlaams-Brabant 1651",
    "addr:housenumber":"32;1651",
    "addr:street":"Bergensesteenweg;Vlaams-Brabant",
    "iso:country":"BE",
    "sg:address":"Bergensesteenweg 32",
    "sg:city":"Lot",
    "sg:classifiers":[
        {
            "category":"Banks & Credit Unions",
            "subcategory":"Investment Brokerage",
            "type":"Services"
        }
    ],
    "sg:phone":"+32 2 334 87 00",
    "sg:postcode":"1651",
    "sg:province":"Vlaams-Brabant",
    "sg:tags":[
        "roofing",
        "sealing",
        "roll",
        "roof",
        "bitumen"
    ],
    "wof:name":"Derbigum - Imperbel Group Sa/nv",
    "wof:placetype":"venue"
},
  "geometry": {"coordinates":[4.2724809647,50.761013031],"type":"Point"}
}