{
  "type": "Feature",
  "properties": {
    "iso:country":"BE",
    "sg:address":"Bosquetstraat 73",
    "sg:city":"Sint-gillis/saint-gilles",
    "sg:orig_category":"Diverse organisaties and verenigingen",
    "sg:phone":"+32 2 534 48 82",
    "sg:postcode":"1060",
    "sg:province":"Bruxelles-Capitale",
    "wof:name":"Chantiers Jeunes",
    "wof:placetype":"venue"
},
  "geometry": {"coordinates":[4.3520717621,50.8338165283],"type":"Point"}
}