{
  "type": "Feature",
  "properties": {
    "iso:country":"BE",
    "sg:address":"Felix Boviestraat 34",
    "sg:city":"Elsene/ixelles",
    "sg:orig_category":"Artsen and specialisten",
    "sg:phone":"+32 2 646 06 74",
    "sg:postcode":"1050",
    "sg:province":"Bruxelles-Capitale",
    "wof:name":"Beno\u00cet Dechene",
    "wof:placetype":"venue"
},
  "geometry": {"coordinates":[4.3763160706,50.8270645142],"type":"Point"}
}