{
  "type": "Feature",
  "properties": {
    "addr:full":"Wingensesteenweg 81 Tielt West-Vlaanderen 8700",
    "addr:housenumber":"81",
    "addr:postcode":"8700",
    "addr:street":"Wingensesteenweg",
    "iso:country":"BE",
    "sg:address":"Wingensesteenweg 81",
    "sg:city":"Tielt",
    "sg:orig_category":"Eleveurs and marchands de porcs",
    "sg:phone":"+32 51 40 04 02",
    "sg:postcode":"8700",
    "sg:province":"West-Vlaanderen",
    "wof:name":"Johny De Roo",
    "wof:placetype":"venue"
},
  "geometry": {"coordinates":[3.3107259274,51.0188751221],"type":"Point"}
}