{
  "type": "Feature",
  "properties": {
    "iso:country":"BE",
    "sg:address":"Rue De Jeumont 5bd",
    "sg:city":"Estinnes",
    "sg:orig_category":"Kapsalons",
    "sg:phone":"+32 64 77 17 61",
    "sg:postcode":"7120",
    "sg:province":"Hainaut",
    "wof:name":"M-th Longo",
    "wof:placetype":"venue"
},
  "geometry": {"coordinates":[4.1242389679,50.3512878418],"type":"Point"}
}