{
  "type": "Feature",
  "properties": {
    "addr:full":"Rue De Mons 17 Tubize Brabant Wallon 1480",
    "addr:housenumber":"17",
    "addr:postcode":"1480",
    "addr:street":"Rue De Mons;Wallon",
    "iso:country":"BE",
    "sg:address":"Rue De Mons 17",
    "sg:city":"Tubize",
    "sg:orig_category":"Computers and computerapparatuur Microsoft Onderhoud van kantoor- and computeruitrusting",
    "sg:phone":"+32 2 355 61 66",
    "sg:postcode":"1480",
    "sg:province":"Brabant Wallon",
    "wof:name":"Ordigestion",
    "wof:placetype":"venue"
},
  "geometry": {"coordinates":[4.2040419579,50.6922187805],"type":"Point"}
}