{
  "type": "Feature",
  "properties": {
    "addr:full":"Rue Jules Stracmans 2 Manage (fayt-lez-manage) Hainaut 7170",
    "addr:housenumber":"2",
    "addr:postcode":"7170",
    "addr:street":"Rue Jules Stracmans",
    "iso:country":"BE",
    "sg:address":"Rue Jules Stracmans 2",
    "sg:city":"Manage (fayt-lez-manage)",
    "sg:classifiers":[
        {
            "category":"Health Services",
            "subcategory":"Doctor",
            "type":"Services"
        }
    ],
    "sg:phone":"+32 64 55 56 17",
    "sg:postcode":"7170",
    "sg:province":"Hainaut",
    "sg:tags":[
        "medicinephysicians",
        "surgeon"
    ],
    "wof:name":"Hertsens J",
    "wof:placetype":"venue"
},
  "geometry": {"coordinates":[4.2327899933,50.5008239746],"type":"Point"}
}