{
  "type": "Feature",
  "properties": {
    "iso:country":"BE",
    "sg:address":"Rue Jos\u00c9phine Rauscent 79",
    "sg:city":"Wavre",
    "sg:orig_category":"Loodgieterij, verwarming and sanitaire installaties",
    "sg:phone":"+32 10 41 29 37",
    "sg:postcode":"1300",
    "sg:province":"Brabant Wallon",
    "wof:name":"Patrick Nys",
    "wof:placetype":"venue"
},
  "geometry": {"coordinates":[4.6116552353,50.7134132385],"type":"Point"}
}