{
  "type": "Feature",
  "properties": {
    "addr:full":"Raamstraat 10 Begijnendijk Vlaams-Brabant 3130",
    "addr:housenumber":"10",
    "addr:postcode":"3130",
    "addr:street":"Raamstraat",
    "iso:country":"BE",
    "sg:address":"Raamstraat 10",
    "sg:city":"Begijnendijk",
    "sg:orig_category":"Woningbouw",
    "sg:phone":"+32 16 53 55 57",
    "sg:postcode":"3130",
    "sg:province":"Vlaams-Brabant",
    "wof:name":"De Winter Luc",
    "wof:placetype":"venue"
},
  "geometry": {"coordinates":[4.7883629799,51.0160293579],"type":"Point"}
}