{
  "type": "Feature",
  "properties": {
    "iso:country":"BE",
    "sg:address":"Dellaertsdreef 9b",
    "sg:city":"Evergem",
    "sg:orig_category":"Mat\u00e9riaux de construction Gr",
    "sg:phone":"+32 9 357 20 14",
    "sg:postcode":"9940",
    "sg:province":"Oost-Vlaanderen",
    "wof:name":"Van Beneden",
    "wof:placetype":"venue"
},
  "geometry": {"coordinates":[3.6747200489,51.1325721741],"type":"Point"}
}