{
  "type": "Feature",
  "properties": {
    "addr:full":"Molenstraat 21 Oostkamp West-Vlaanderen 8020",
    "addr:housenumber":"21",
    "addr:postcode":"8020",
    "addr:street":"Molenstraat",
    "iso:country":"BE",
    "sg:address":"Molenstraat 21",
    "sg:city":"Oostkamp",
    "sg:orig_category":"Woningbouw",
    "sg:phone":"+32 50 82 68 96",
    "sg:postcode":"8020",
    "sg:province":"West-Vlaanderen",
    "wof:name":"Paul Vandendorpe",
    "wof:placetype":"venue"
},
  "geometry": {"coordinates":[3.2286250591,51.1522827148],"type":"Point"}
}