{
  "type": "Feature",
  "properties": {
    "addr:full":"Itali\u00eblei 66 Antwerpen Antwerpen 2000",
    "addr:housenumber":"66",
    "addr:postcode":"2000",
    "addr:street":"Italie\u0308Lei",
    "iso:country":"BE",
    "sg:address":"Itali\u00eblei 66",
    "sg:city":"Antwerpen",
    "sg:orig_category":"Miscellaneous Products",
    "sg:phone":"+32 3 224 05 60",
    "sg:postcode":"2000",
    "sg:province":"Antwerpen",
    "wof:name":"Urals Ara",
    "wof:placetype":"venue"
},
  "geometry": {"coordinates":[4.4151439667,51.2233886719],"type":"Point"}
}