{
  "type": "Feature",
  "properties": {
    "addr:full":"Rue Du Gavre 9 Spiere-helkijn/espierres-helchin West-Vlaanderen 8587",
    "addr:housenumber":"9",
    "addr:postcode":"8587",
    "addr:street":"Rue Du Gavre",
    "iso:country":"BE",
    "sg:address":"Rue Du Gavre 9",
    "sg:city":"Spiere-helkijn/espierres-helchin",
    "sg:orig_category":"Eleveurs de bovins. Eleveurs and marchands de porcs",
    "sg:phone":"+32 56 45 53 29",
    "sg:postcode":"8587",
    "sg:province":"West-Vlaanderen",
    "wof:name":"Desauw/noel Desauw",
    "wof:placetype":"venue"
},
  "geometry": {"coordinates":[3.370265007,50.7356185913],"type":"Point"}
}