{
  "type": "Feature",
  "properties": {
    "addr:full":"Vliegveld Wevelgem West-Vlaanderen 8560",
    "addr:postcode":"8560",
    "iso:country":"BE",
    "sg:address":"Vliegveld",
    "sg:city":"Wevelgem",
    "sg:classifiers":[
        {
            "category":"Home & Garden",
            "subcategory":"Building Materials",
            "type":"Retail Goods"
        }
    ],
    "sg:phone":"+32 56 42 07 20",
    "sg:postcode":"8560",
    "sg:province":"West-Vlaanderen",
    "sg:tags":[
        "shutter"
    ],
    "wof:name":"Profilex",
    "wof:placetype":"venue"
},
  "geometry": {"coordinates":[3.2057549953,50.8186912537],"type":"Point"}
}