{
  "type": "Feature",
  "properties": {
    "addr:full":"Veldstraat 47 De Panne West-Vlaanderen 8660",
    "addr:housenumber":"47",
    "addr:postcode":"8660",
    "addr:street":"Veldstraat",
    "iso:country":"BE",
    "sg:address":"Veldstraat 47",
    "sg:city":"De Panne",
    "sg:orig_category":"Installation \u00e9lectrique r\u00e9sidentielle. Installation \u00e9lectrique industrielle",
    "sg:phone":"+32 58 41 52 44",
    "sg:postcode":"8660",
    "sg:province":"West-Vlaanderen",
    "wof:name":"Rudi Vanderheyde",
    "wof:placetype":"venue"
},
  "geometry": {"coordinates":[2.5897340775,51.0709228516],"type":"Point"}
}