{
  "type": "Feature",
  "properties": {
    "iso:country":"BE",
    "sg:address":"Oude Beestenmarkt 10",
    "sg:city":"Gent",
    "sg:classifiers":[
        {
            "category":"Shopping",
            "subcategory":"Bicycles & Sporting Goods",
            "type":"Retail Goods"
        }
    ],
    "sg:phone":"+32 9 225 25 41",
    "sg:postcode":"9000",
    "sg:province":"Oost-Vlaanderen",
    "sg:tags":[
        "article",
        "de",
        "sport",
        "camping"
    ],
    "wof:name":"Mario's Golfcentrum",
    "wof:placetype":"venue"
},
  "geometry": {"coordinates":[3.7316329479,51.0545921326],"type":"Point"}
}