{
  "type": "Feature",
  "properties": {
    "addr:full":"Grand'rue 11 Lessines Hainaut 7860",
    "addr:housenumber":"11",
    "addr:postcode":"7860",
    "addr:street":"Grand'Rue;Hainaut",
    "iso:country":"BE",
    "sg:address":"Grand'rue 11",
    "sg:city":"Lessines",
    "sg:classifiers":[
        {
            "category":"Personal",
            "subcategory":"Beauty Salon",
            "type":"Services"
        }
    ],
    "sg:phone":"+32 68 33 29 07",
    "sg:postcode":"7860",
    "sg:province":"Hainaut",
    "sg:tags":[
        "lady",
        "-",
        "hairdressing"
    ],
    "wof:name":"Bernard (coiffure)",
    "wof:placetype":"venue"
},
  "geometry": {"coordinates":[3.8290889263,50.7124633789],"type":"Point"}
}