{
  "type": "Feature",
  "properties": {
    "iso:country":"BE",
    "sg:address":"Butschovestraat 29",
    "sg:city":"Glabbeek (attenrode)",
    "sg:classifiers":[
        {
            "category":"Building & Trades",
            "subcategory":"Pest Control",
            "type":"Services"
        }
    ],
    "sg:phone":"+32 16 77 05 78",
    "sg:postcode":"3384",
    "sg:province":"Vlaams-Brabant",
    "sg:tags":[
        "painting",
        "contractor"
    ],
    "wof:name":"Id Schilderwerken",
    "wof:placetype":"venue"
},
  "geometry": {"coordinates":[4.9141421318,50.8666801453],"type":"Point"}
}