{
  "type": "Feature",
  "properties": {
    "addr:full":"Geraardsbergsestraat 59 Aalst Oost-Vlaanderen 9300",
    "addr:housenumber":"59",
    "addr:postcode":"9300",
    "addr:street":"Geraardsbergsestraat",
    "iso:country":"BE",
    "sg:address":"Geraardsbergsestraat 59",
    "sg:city":"Aalst",
    "sg:orig_category":"Sportclubs",
    "sg:phone":"+32 53 21 34 18",
    "sg:postcode":"9300",
    "sg:province":"Oost-Vlaanderen",
    "wof:name":"Kon. Turnkring Aalst",
    "wof:placetype":"venue"
},
  "geometry": {"coordinates":[4.0363287926,50.9328651428],"type":"Point"}
}