{
  "type": "Feature",
  "properties": {
    "iso:country":"BE",
    "sg:address":"Ramselsesteenweg 2a",
    "sg:city":"Hulshout (westmeerbeek)",
    "sg:classifiers":[
        {
            "category":"Manufacturing",
            "subcategory":"Metals",
            "type":"Manufacturing & Wholesale Goods"
        }
    ],
    "sg:phone":"+32 16 69 43 21",
    "sg:postcode":"2235",
    "sg:province":"Antwerpen",
    "sg:tags":[
        "ironwork"
    ],
    "wof:name":"Stetec",
    "wof:placetype":"venue"
},
  "geometry": {"coordinates":[4.8345332146,51.0598983765],"type":"Point"}
}