{
  "type": "Feature",
  "properties": {
    "iso:country":"BE",
    "sg:address":"Kerkhofweg 41b1",
    "sg:city":"Turnhout",
    "sg:classifiers":[
        {
            "category":"Insurance",
            "subcategory":"Insurance Agent",
            "type":"Services"
        }
    ],
    "sg:phone":"+32 14 41 38 24",
    "sg:postcode":"2300",
    "sg:province":"Antwerpen",
    "sg:tags":[
        "verzekeringsmakelaars",
        "expert"
    ],
    "wof:name":"Bureau Smeyers & Jacobs",
    "wof:placetype":"venue"
},
  "geometry": {"coordinates":[4.9595031738,51.3179092407],"type":"Point"}
}