{
  "type": "Feature",
  "properties": {
    "iso:country":"BE",
    "sg:address":"Klein-hulststraat 90",
    "sg:city":"Sint-niklaas",
    "sg:orig_category":"Epiceries",
    "sg:phone":"+32 3 776 13 75",
    "sg:postcode":"9100",
    "sg:province":"Oost-Vlaanderen",
    "wof:name":"Huis Daniella",
    "wof:placetype":"venue"
},
  "geometry": {"coordinates":[4.1509289742,51.1675453186],"type":"Point"}
}