{
  "type": "Feature",
  "properties": {
    "addr:full":"Rue D\u00b4hatrival 173a Libin Luxembourg 6890",
    "addr:housenumber":"173a",
    "addr:postcode":"6890",
    "addr:street":"Rue D\u00b4Hatrival",
    "iso:country":"BE",
    "sg:address":"Rue D\u00b4hatrival 173a",
    "sg:city":"Libin",
    "sg:orig_category":"Sportcentra Sportterreinen and installaties behalve sportcentra",
    "sg:phone":"+32 61 65 80 83",
    "sg:postcode":"6890",
    "sg:province":"Luxembourg",
    "wof:name":"Complexe Sportif",
    "wof:placetype":"venue"
},
  "geometry": {"coordinates":[5.265458107,49.9834785461],"type":"Point"}
}