{
  "type": "Feature",
  "properties": {
    "addr:full":"Rue Des Colonies 11 Brussel/bruxelles Bruxelles-Capitale 1000",
    "addr:housenumber":"11",
    "addr:postcode":"1000",
    "addr:street":"Rue Des Colonies;/",
    "iso:country":"BE",
    "sg:address":"Rue Des Colonies 11",
    "sg:city":"Brussel/bruxelles",
    "sg:orig_category":"Avocats and conseillers juridiques",
    "sg:phone":"+32 2 500 15 00",
    "sg:postcode":"1000",
    "sg:province":"Bruxelles-Capitale",
    "wof:name":"Jean-louis Berra",
    "wof:placetype":"venue"
},
  "geometry": {"coordinates":[4.3596301079,50.8464279175],"type":"Point"}
}