{
  "type": "Feature",
  "properties": {
    "iso:country":"BE",
    "sg:address":"Pintestraat 18",
    "sg:city":"De Pinte",
    "sg:orig_category":"M\u00e9decins and sp\u00e9cialistes",
    "sg:phone":"+32 9 282 53 06",
    "sg:postcode":"9840",
    "sg:province":"Oost-Vlaanderen",
    "wof:name":"Kristof Vandekerckhove",
    "wof:placetype":"venue"
},
  "geometry": {"coordinates":[3.6482450962,50.9911575317],"type":"Point"}
}