{
  "type": "Feature",
  "properties": {
    "iso:country":"BE",
    "sg:address":"Rue Joseph Wauters 2",
    "sg:city":"Verviers",
    "sg:classifiers":[
        {
            "category":"Shopping",
            "subcategory":"Florist",
            "type":"Retail Goods"
        }
    ],
    "sg:phone":"+32 87 22 32 34",
    "sg:postcode":"4800",
    "sg:province":"Li\u00e8ge",
    "wof:name":"Heusyflor",
    "wof:placetype":"venue"
},
  "geometry": {"coordinates":[5.8691711426,50.582901001],"type":"Point"}
}