{
  "type": "Feature",
  "properties": {
    "addr:full":"Grensstraat 234 Kapellen Antwerpen 2950",
    "addr:housenumber":"234",
    "addr:postcode":"2950",
    "addr:street":"Grensstraat",
    "iso:country":"BE",
    "sg:address":"Grensstraat 234",
    "sg:city":"Kapellen",
    "sg:classifiers":[
        {
            "category":"Arena",
            "subcategory":"Sports Club",
            "type":"Entertainment"
        }
    ],
    "sg:phone":"+32 3 665 40 07",
    "sg:postcode":"2950",
    "sg:province":"Antwerpen",
    "sg:tags":[
        "de"
    ],
    "wof:name":"Kando Technique",
    "wof:placetype":"venue"
},
  "geometry": {"coordinates":[4.4203090668,51.3618736267],"type":"Point"}
}