{
  "type": "Feature",
  "properties": {
    "iso:country":"BE",
    "sg:address":"Rue Du Onze Novembre 9",
    "sg:city":"Mons",
    "sg:orig_category":"Avocats and conseillers juridiques",
    "sg:phone":"+32 65 34 76 56",
    "sg:postcode":"7000",
    "sg:province":"Hainaut",
    "wof:name":"Fran\u00c7ois Daout",
    "wof:placetype":"venue"
},
  "geometry": {"coordinates":[3.9508779049,50.4560317993],"type":"Point"}
}