{
  "type": "Feature",
  "properties": {
    "addr:full":"Den Bremt 45 Herent Vlaams-Brabant 3020",
    "addr:housenumber":"45",
    "addr:postcode":"3020",
    "addr:street":"Den Bremt",
    "iso:country":"BE",
    "sg:address":"Den Bremt 45",
    "sg:city":"Herent",
    "sg:classifiers":[
        {
            "category":"Professional",
            "subcategory":"Art Services",
            "type":"Services"
        }
    ],
    "sg:phone":"+32 16 22 98 42",
    "sg:postcode":"3020",
    "sg:province":"Vlaams-Brabant",
    "sg:tags":[
        "interior",
        "designer"
    ],
    "wof:name":"Krea-line",
    "wof:placetype":"venue"
},
  "geometry": {"coordinates":[4.6619830132,50.9040679932],"type":"Point"}
}