{
  "type": "Feature",
  "properties": {
    "addr:full":"Rue Saint-luc 46 Namur (bouge) Namur 5004",
    "addr:housenumber":"46",
    "addr:postcode":"5004",
    "addr:street":"Rue Saint-Luc",
    "iso:country":"BE",
    "sg:address":"Rue Saint-luc 46",
    "sg:city":"Namur (bouge)",
    "sg:classifiers":[
        {
            "category":"Health Services",
            "subcategory":"Dentist",
            "type":"Services"
        }
    ],
    "sg:phone":"+32 81 21 02 65",
    "sg:postcode":"5004",
    "sg:province":"Namur",
    "wof:name":"Gatot J",
    "wof:placetype":"venue"
},
  "geometry": {"coordinates":[4.8834710121,50.4766311646],"type":"Point"}
}