{
  "type": "Feature",
  "properties": {
    "iso:country":"BE",
    "sg:address":"Rue De Mons 91",
    "sg:city":"Tubize",
    "sg:orig_category":"Pain, p\u00e2tisseries and confiseries",
    "sg:phone":"+32 2 355 61 69",
    "sg:postcode":"1480",
    "sg:province":"Brabant Wallon",
    "wof:name":"Jacques Demol",
    "wof:placetype":"venue"
},
  "geometry": {"coordinates":[4.2021141052,50.6901855469],"type":"Point"}
}