{
  "type": "Feature",
  "properties": {
    "iso:country":"BE",
    "sg:address":"Plantinlaan 66",
    "sg:city":"Stabroek",
    "sg:classifiers":[
        {
            "category":"Insurance",
            "subcategory":"Life Insurance",
            "type":"Services"
        }
    ],
    "sg:phone":"+32 3 664 69 24",
    "sg:postcode":"2940",
    "sg:province":"Antwerpen",
    "sg:tags":[
        "assurance"
    ],
    "wof:name":"A. Vennincx",
    "wof:placetype":"venue"
},
  "geometry": {"coordinates":[4.3899140358,51.3480491638],"type":"Point"}
}