{
  "type": "Feature",
  "properties": {
    "addr:full":"V. Coppensstraat 4 Sint-gillis-waas Oost-Vlaanderen 9170",
    "addr:housenumber":"4",
    "addr:postcode":"9170",
    "addr:street":"V. Coppensstraat",
    "iso:country":"BE",
    "sg:address":"V. Coppensstraat 4",
    "sg:city":"Sint-gillis-waas",
    "sg:orig_category":"Slagers",
    "sg:phone":"+32 3 770 77 91",
    "sg:postcode":"9170",
    "sg:province":"Oost-Vlaanderen",
    "wof:name":"Ronan Raes",
    "wof:placetype":"venue"
},
  "geometry": {"coordinates":[4.1235289574,51.2163848877],"type":"Point"}
}