{
  "type": "Feature",
  "properties": {
    "iso:country":"BE",
    "sg:address":"Leemstraat 45",
    "sg:city":"Lochristi (zaffelare)",
    "sg:classifiers":[
        {
            "category":"Real Estate",
            "subcategory":"Architect",
            "type":"Services"
        }
    ],
    "sg:phone":"+32 9 356 73 63",
    "sg:postcode":"9080",
    "sg:province":"Oost-Vlaanderen",
    "wof:name":"Verschueren W",
    "wof:placetype":"venue"
},
  "geometry": {"coordinates":[3.8800430298,51.129901886],"type":"Point"}
}