{
  "type": "Feature",
  "properties": {
    "iso:country":"BE",
    "sg:address":"Vall\u00e9e Du Hoyoux 75",
    "sg:city":"Modave (vierset-barse)",
    "sg:classifiers":[
        {
            "category":"Professional",
            "subcategory":"Management & Consulting",
            "type":"Services"
        }
    ],
    "sg:phone":"+32 85 23 25 91",
    "sg:postcode":"4577",
    "sg:province":"Li\u00e8ge",
    "sg:tags":[
        "consultant"
    ],
    "wof:name":"Fidumo Sprl",
    "wof:placetype":"venue"
},
  "geometry": {"coordinates":[5.2582731247,50.4883041382],"type":"Point"}
}