{
  "type": "Feature",
  "properties": {
    "addr:full":"Ninoofsesteenweg 22 Haaltert (denderhoutem) Oost-Vlaanderen 9450",
    "addr:housenumber":"22",
    "addr:postcode":"9450",
    "addr:street":"Ninoofsesteenweg",
    "iso:country":"BE",
    "sg:address":"Ninoofsesteenweg 22",
    "sg:city":"Haaltert (denderhoutem)",
    "sg:classifiers":[
        {
            "category":"Retail",
            "subcategory":"Event Space",
            "type":"Services"
        }
    ],
    "sg:phone":"+32 54 32 18 55",
    "sg:postcode":"9450",
    "sg:province":"Oost-Vlaanderen",
    "sg:tags":[
        "rental",
        "-",
        "hall"
    ],
    "wof:name":"Pennelekker (de)",
    "wof:placetype":"venue"
},
  "geometry": {"coordinates":[4.0181331635,50.8673286438],"type":"Point"}
}