{
  "type": "Feature",
  "properties": {
    "iso:country":"BE",
    "sg:address":"Toekomststraat 10",
    "sg:city":"Zaventem",
    "sg:classifiers":[
        {
            "category":"Health Services",
            "subcategory":"Medical Lab",
            "type":"Services"
        }
    ],
    "sg:phone":"+32 2 720 33 93",
    "sg:postcode":"1930",
    "sg:province":"Vlaams-Brabant",
    "sg:tags":[
        "implant"
    ],
    "wof:name":"Ams Benelux B.v.b.a.",
    "wof:placetype":"venue"
},
  "geometry": {"coordinates":[4.4658999443,50.8919906616],"type":"Point"}
}