{
  "type": "Feature",
  "properties": {
    "iso:country":"BE",
    "sg:address":"Rue Des Fours-a-chauxmazy. 1",
    "sg:city":"Mazy",
    "sg:classifiers":[
        {
            "category":"Utilities",
            "subcategory":"Natural Gas",
            "type":"Services"
        }
    ],
    "sg:phone":"+32 81 63 32 49",
    "sg:postcode":"5032",
    "sg:province":"Namur",
    "sg:tags":[
        "block",
        "chimney"
    ],
    "wof:name":"Compagnie Du Bois D'anthisnes S.a.",
    "wof:placetype":"venue"
},
  "geometry": {"coordinates":[4.6786160469,50.5174217224],"type":"Point"}
}