{
  "type": "Feature",
  "properties": {
    "addr:full":"Kapelsesteenweg 479 Antwerpen (ekeren) Antwerpen 2180",
    "addr:housenumber":"479",
    "addr:postcode":"2180",
    "addr:street":"Kapelsesteenweg",
    "iso:country":"BE",
    "sg:address":"Kapelsesteenweg 479",
    "sg:city":"Antwerpen (ekeren)",
    "sg:classifiers":[
        {
            "category":"Health Services",
            "subcategory":"Dentist",
            "type":"Services"
        }
    ],
    "sg:phone":"+32 3 665 16 94",
    "sg:postcode":"2180",
    "sg:province":"Antwerpen",
    "wof:name":"Roes L",
    "wof:placetype":"venue"
},
  "geometry": {"coordinates":[4.4586000443,51.2716217041],"type":"Point"}
}