{
  "type": "Feature",
  "properties": {
    "addr:full":"Zandpoortvest 43 Mechelen Antwerpen 2800",
    "addr:housenumber":"43",
    "addr:postcode":"2800",
    "addr:street":"Zandpoortvest",
    "iso:country":"BE",
    "sg:address":"Zandpoortvest 43",
    "sg:city":"Mechelen",
    "sg:classifiers":[
        {
            "category":"Tea Room",
            "subcategory":"None",
            "type":"Food & Drink"
        }
    ],
    "sg:phone":"+32 15 33 13 77",
    "sg:postcode":"2800",
    "sg:province":"Antwerpen",
    "wof:name":"Alikizo",
    "wof:placetype":"venue"
},
  "geometry": {"coordinates":[4.4876561165,51.0240974426],"type":"Point"}
}