{
  "type": "Feature",
  "properties": {
    "iso:country":"BE",
    "sg:address":"Rue Konkel 87",
    "sg:city":"Bruxelles (woluwe-saint-pierre)",
    "sg:classifiers":[
        {
            "category":"Social Services",
            "type":"Services"
        }
    ],
    "sg:phone":"+32 2 772 73 36",
    "sg:postcode":"1150",
    "sg:province":"Bruxelles-Capitale",
    "wof:name":"Ethologia",
    "wof:placetype":"venue"
},
  "geometry": {"coordinates":[4.4403209686,50.8375358582],"type":"Point"}
}