{
  "type": "Feature",
  "properties": {
    "iso:country":"BE",
    "sg:address":"Kleine Ommegangweg 4",
    "sg:city":"Erpe-mere",
    "sg:orig_category":"Sportclubs",
    "sg:phone":"+32 53 80 58 91",
    "sg:postcode":"9420",
    "sg:province":"Oost-Vlaanderen",
    "wof:name":"T.c. Sportina",
    "wof:placetype":"venue"
},
  "geometry": {"coordinates":[3.9676449299,50.9200401306],"type":"Point"}
}