{
  "type": "Feature",
  "properties": {
    "addr:full":"Stationsstraat 41 Eeklo Oost-Vlaanderen 9900",
    "addr:housenumber":"41",
    "addr:postcode":"9900",
    "addr:street":"Stationsstraat",
    "iso:country":"BE",
    "sg:address":"Stationsstraat 41",
    "sg:city":"Eeklo",
    "sg:classifiers":[
        {
            "category":"Insurance",
            "subcategory":"Life Insurance",
            "type":"Services"
        }
    ],
    "sg:phone":"+32 9 376 91 11",
    "sg:postcode":"9900",
    "sg:province":"Oost-Vlaanderen",
    "sg:tags":[
        "assurance"
    ],
    "wof:name":"P&v",
    "wof:placetype":"venue"
},
  "geometry": {"coordinates":[3.5695610046,51.183265686],"type":"Point"}
}