{
  "type": "Feature",
  "properties": {
    "iso:country":"BE",
    "sg:address":"Driemasterstr 58",
    "sg:city":"Gent",
    "sg:classifiers":[
        {
            "category":"Professional",
            "subcategory":"Engineering",
            "type":"Services"
        }
    ],
    "sg:phone":"+32 9 258 23 52",
    "sg:postcode":"9000",
    "sg:province":"Oost-Vlaanderen",
    "sg:tags":[
        "machine",
        "-",
        "mechanical"
    ],
    "wof:name":"V I C Systems Europe Nv",
    "wof:placetype":"venue"
},
  "geometry": {"coordinates":[3.7223849297,51.0870246887],"type":"Point"}
}