{
  "type": "Feature",
  "properties": {
    "iso:country":"BE",
    "sg:address":"Op De Bekker 18",
    "sg:city":"Dilsen-stokkem (dilsen)",
    "sg:classifiers":[
        {
            "category":"Personal",
            "subcategory":"Beauty Salon",
            "type":"Services"
        }
    ],
    "sg:phone":"+32 89 79 29 26",
    "sg:postcode":"3650",
    "sg:province":"Limburg",
    "wof:name":"Lisette",
    "wof:placetype":"venue"
},
  "geometry": {"coordinates":[5.7100830078,51.0365447998],"type":"Point"}
}