{
  "type": "Feature",
  "properties": {
    "addr:full":"Rue Du Mill\u00c9naire 8 Chiny Luxembourg 6810",
    "addr:housenumber":"8",
    "addr:postcode":"6810",
    "addr:street":"Rue Du Mille\u0301Naire",
    "iso:country":"BE",
    "sg:address":"Rue Du Mill\u00c9naire 8",
    "sg:city":"Chiny",
    "sg:orig_category":"Epiceries",
    "sg:phone":"+32 61 31 15 65",
    "sg:postcode":"6810",
    "sg:province":"Luxembourg",
    "wof:name":"Spar",
    "wof:placetype":"venue"
},
  "geometry": {"coordinates":[5.3411459923,49.7388000488],"type":"Point"}
}