{
  "type": "Feature",
  "properties": {
    "addr:full":"Rue Xhenorie 0 Dison Li\u00e8ge 4821",
    "addr:housenumber":"0",
    "addr:postcode":"4821",
    "addr:street":"Rue Xhenorie",
    "iso:country":"BE",
    "sg:address":"Rue Xhenorie 0",
    "sg:city":"Dison",
    "sg:orig_category":"Gespecialiseerde niet-residenti\u00eble bouw",
    "sg:phone":"+32 87 35 19 13",
    "sg:postcode":"4821",
    "sg:province":"Li\u00e8ge",
    "wof:name":"M\u00c9tal Construct",
    "wof:placetype":"venue"
},
  "geometry": {"coordinates":[5.881280899,50.6143875122],"type":"Point"}
}