{
  "type": "Feature",
  "properties": {
    "addr:full":"Beringenbaan 63 Diest Vlaams-Brabant 3290",
    "addr:housenumber":"63",
    "addr:postcode":"3290",
    "addr:street":"Beringenbaan",
    "iso:country":"BE",
    "sg:address":"Beringenbaan 63",
    "sg:city":"Diest",
    "sg:orig_category":"Producteurs de l\u00e9gumes",
    "sg:phone":"+32 13 32 77 68",
    "sg:postcode":"3290",
    "sg:province":"Vlaams-Brabant",
    "wof:name":"Bogaerts R. & H.",
    "wof:placetype":"venue"
},
  "geometry": {"coordinates":[5.1506748199,51.0259399414],"type":"Point"}
}