{
  "type": "Feature",
  "properties": {
    "iso:country":"BE",
    "sg:address":"Lijsterstraat 52",
    "sg:city":"Zulte",
    "sg:classifiers":[
        {
            "category":"Retail",
            "subcategory":"Funeral Services",
            "type":"Services"
        }
    ],
    "sg:phone":"+32 9 388 79 21",
    "sg:postcode":"9870",
    "sg:province":"Oost-Vlaanderen",
    "sg:tags":[
        "director"
    ],
    "wof:name":"Van De Vijver D & P",
    "wof:placetype":"venue"
},
  "geometry": {"coordinates":[3.4537699223,50.922618866],"type":"Point"}
}