{
  "type": "Feature",
  "properties": {
    "addr:full":"Ringlaan 14 Zandhoven Antwerpen 2240",
    "addr:housenumber":"14",
    "addr:postcode":"2240",
    "addr:street":"Ringlaan",
    "iso:country":"BE",
    "sg:address":"Ringlaan 14",
    "sg:city":"Zandhoven",
    "sg:classifiers":[
        {
            "category":"Autos & Motor Vehicles",
            "subcategory":"Automobile Sales",
            "type":"Retail Goods"
        }
    ],
    "sg:phone":"+32 3 484 39 59",
    "sg:postcode":"2240",
    "sg:province":"Antwerpen",
    "sg:tags":[
        "car",
        "used",
        "-"
    ],
    "wof:name":"Devroede Car Business",
    "wof:placetype":"venue"
},
  "geometry": {"coordinates":[4.654569149,51.2079772949],"type":"Point"}
}