{
  "type": "Feature",
  "properties": {
    "addr:full":"Parelsbergstraat 21 Diest Vlaams-Brabant 3290",
    "addr:housenumber":"21",
    "addr:postcode":"3290",
    "addr:street":"Parelsbergstraat",
    "iso:country":"BE",
    "sg:address":"Parelsbergstraat 21",
    "sg:city":"Diest",
    "sg:orig_category":"Mat\u00e9riel m\u00e9dical and orthop\u00e9dique and proth\u00e8ses Fab",
    "sg:phone":"+32 13 31 20 66",
    "sg:postcode":"3290",
    "sg:province":"Vlaams-Brabant",
    "wof:name":"Labo Fabre",
    "wof:placetype":"venue"
},
  "geometry": {"coordinates":[5.0637922287,50.973072052],"type":"Point"}
}