{
  "type": "Feature",
  "properties": {
    "addr:full":"Chauss\u00c9e D'alsemberg 137 Braine-l'alleud Brabant Wallon 1420",
    "addr:housenumber":"137",
    "addr:postcode":"1420",
    "addr:street":"Chausse\u0301E D'Alsemberg",
    "iso:country":"BE",
    "sg:address":"Chauss\u00c9e D'alsemberg 137",
    "sg:city":"Braine-l'alleud",
    "sg:orig_category":"Eleveurs de bovins",
    "sg:phone":"+32 2 384 45 76",
    "sg:postcode":"1420",
    "sg:province":"Brabant Wallon",
    "wof:name":"Willy Baligant",
    "wof:placetype":"venue"
},
  "geometry": {"coordinates":[-0.7711730003,47.3931159973],"type":"Point"}
}