{
  "type": "Feature",
  "properties": {
    "addr:full":"Keyserlei 2 Antwerpen Antwerpen 2000",
    "addr:housenumber":"2",
    "addr:postcode":"2000",
    "addr:street":"Keyserlei",
    "iso:country":"BE",
    "sg:address":"Keyserlei 2",
    "sg:city":"Antwerpen",
    "sg:orig_category":"Syst\u00e8mes de t\u00e9l\u00e9communications. The Phone House",
    "sg:phone":"+32 3 222 90 30",
    "sg:postcode":"2000",
    "sg:province":"Antwerpen",
    "wof:name":"The Phone House",
    "wof:placetype":"venue"
},
  "geometry": {"coordinates":[4.4157719612,51.2178421021],"type":"Point"}
}