{
  "type": "Feature",
  "properties": {
    "addr:full":"Avenue De La Croix De Bourgogne 38 Waterloo Brabant Wallon 1410",
    "addr:housenumber":"38",
    "addr:postcode":"1410",
    "addr:street":"Avenue De La Croix De Bourgogne",
    "iso:country":"BE",
    "sg:address":"Avenue De La Croix De Bourgogne 38",
    "sg:city":"Waterloo",
    "sg:classifiers":[
        {
            "category":"Health Services",
            "subcategory":"Doctor",
            "type":"Services"
        }
    ],
    "sg:phone":"+32 2 384 58 03",
    "sg:postcode":"1410",
    "sg:province":"Brabant Wallon",
    "sg:tags":[
        "medicinephysicians",
        "surgeon"
    ],
    "wof:name":"Bettendorf M",
    "wof:placetype":"venue"
},
  "geometry": {"coordinates":[4.3980112076,50.6968078613],"type":"Point"}
}