{
  "type": "Feature",
  "properties": {
    "iso:country":"BE",
    "sg:address":"Place De L'orneau 23",
    "sg:city":"Gembloux",
    "sg:orig_category":"Industri\u00eble wasserijen and droogkuis",
    "sg:phone":"+32 81 61 18 12",
    "sg:postcode":"5030",
    "sg:province":"Namur",
    "wof:name":"Tout \u00c0 Sec",
    "wof:placetype":"venue"
},
  "geometry": {"coordinates":[4.6921272278,50.5607681274],"type":"Point"}
}