{
  "type": "Feature",
  "properties": {
    "iso:country":"BE",
    "sg:address":"Av De L'ind\u00e9pendance 33",
    "sg:city":"Wandre",
    "sg:classifiers":[
        {
            "category":"Food Court",
            "type":"Food & Drink"
        }
    ],
    "sg:phone":"+32 4 227 92 92",
    "sg:postcode":"4020",
    "sg:province":"Li\u00e8ge",
    "sg:tags":[
        "product",
        "related"
    ],
    "wof:name":"Boissons Jms Sa",
    "wof:placetype":"venue"
},
  "geometry": {"coordinates":[5.581829071,50.6424331665],"type":"Point"}
}