{
  "type": "Feature",
  "properties": {
    "addr:full":"Peter Benoitlaan 121 Gent (gentbrugge) Oost-Vlaanderen 9050",
    "addr:housenumber":"121",
    "addr:postcode":"9050",
    "addr:street":"Peter Benoitlaan",
    "iso:country":"BE",
    "sg:address":"Peter Benoitlaan 121",
    "sg:city":"Gent (gentbrugge)",
    "sg:classifiers":[
        {
            "category":"Professional",
            "subcategory":"Computer Services",
            "type":"Services"
        }
    ],
    "sg:phone":"+32 9 329 59 28",
    "sg:postcode":"9050",
    "sg:province":"Oost-Vlaanderen",
    "sg:tags":[
        "-",
        "processing",
        "data"
    ],
    "wof:name":"Dtservice",
    "wof:placetype":"venue"
},
  "geometry": {"coordinates":[3.7608940601,51.0283851624],"type":"Point"}
}