{
  "type": "Feature",
  "properties": {
    "iso:country":"BE",
    "sg:address":"Holstraat 69",
    "sg:city":"Waregem",
    "sg:orig_category":"Fietsen",
    "sg:phone":"+32 56 60 11 59",
    "sg:postcode":"8790",
    "sg:province":"West-Vlaanderen",
    "wof:name":"Huis Snoeck",
    "wof:placetype":"venue"
},
  "geometry": {"coordinates":[3.4374890327,50.8841209412],"type":"Point"}
}