{
  "type": "Feature",
  "properties": {
    "iso:country":"BE",
    "sg:address":"Rue Nicolas Fossoul 54",
    "sg:city":"Boncelles",
    "sg:orig_category":"Services de s\u00e9curit\u00e9 and entreprises de gardiennage",
    "sg:phone":"+32 4 221 01 95",
    "sg:postcode":"4100",
    "sg:province":"Li\u00e8ge",
    "wof:name":"Hallgard S\u00c9curity",
    "wof:placetype":"venue"
},
  "geometry": {"coordinates":[5.5424160957,50.5746459961],"type":"Point"}
}