{
  "type": "Feature",
  "properties": {
    "addr:full":"Brusselsesteenweg 154 Aalst Oost-Vlaanderen 9300",
    "addr:housenumber":"154",
    "addr:postcode":"9300",
    "addr:street":"Brusselsesteenweg",
    "iso:country":"BE",
    "sg:address":"Brusselsesteenweg 154",
    "sg:city":"Aalst",
    "sg:orig_category":"Meubles D\u00e9taillants, Am\u00e9nagement de B\u00e2timents et de Cuisines. Eclairage et \u00e9quipements du foyer",
    "sg:phone":"+32 53 78 92 57",
    "sg:postcode":"9300",
    "sg:province":"Oost-Vlaanderen",
    "wof:name":"Krea Woondecoratie",
    "wof:placetype":"venue"
},
  "geometry": {"coordinates":[4.0650458336,50.9293136597],"type":"Point"}
}