{
  "type": "Feature",
  "properties": {
    "iso:country":"BE",
    "sg:address":"Nukkerstraat 38",
    "sg:city":"Bredene",
    "sg:orig_category":"Pain, p\u00e2tisseries and confiseries",
    "sg:phone":"+32 59 32 33 26",
    "sg:postcode":"8450",
    "sg:province":"West-Vlaanderen",
    "wof:name":"Danny Annys",
    "wof:placetype":"venue"
},
  "geometry": {"coordinates":[2.9580490589,51.2220153809],"type":"Point"}
}