{
  "type": "Feature",
  "properties": {
    "addr:full":"Rue Des Ecureuils 29 Rochefort Namur 5580",
    "addr:housenumber":"29",
    "addr:postcode":"5580",
    "addr:street":"Rue Des Ecureuils",
    "iso:country":"BE",
    "sg:address":"Rue Des Ecureuils 29",
    "sg:city":"Rochefort",
    "sg:orig_category":"Entretien and r\u00e9parations de voitures",
    "sg:phone":"+32 84 21 12 48",
    "sg:postcode":"5580",
    "sg:province":"Namur",
    "wof:name":"Garage Picard F.",
    "wof:placetype":"venue"
},
  "geometry": {"coordinates":[5.2165141106,50.1487464905],"type":"Point"}
}