{
  "type": "Feature",
  "properties": {
    "addr:full":"Ternesselei 21 Wommelgem Antwerpen 2160",
    "addr:housenumber":"21",
    "addr:postcode":"2160",
    "addr:street":"Ternesselei",
    "iso:country":"BE",
    "sg:address":"Ternesselei 21",
    "sg:city":"Wommelgem",
    "sg:classifiers":[
        {
            "category":"Building & Trades",
            "subcategory":"Construction",
            "type":"Services"
        }
    ],
    "sg:phone":"+32 3 354 57 72",
    "sg:postcode":"2160",
    "sg:province":"Antwerpen",
    "sg:tags":[
        "work",
        "waterproofing"
    ],
    "wof:name":"Versmissen Willy Bvba",
    "wof:placetype":"venue"
},
  "geometry": {"coordinates":[4.5156002045,51.2057495117],"type":"Point"}
}