{
  "type": "Feature",
  "properties": {
    "addr:full":"Buisson-la-fleur 111 Verlaine Li\u00e8ge 4537",
    "addr:housenumber":"111",
    "addr:postcode":"4537",
    "addr:street":"Verlaine Lie\u0300Ge",
    "iso:country":"BE",
    "sg:address":"Buisson-la-fleur 111",
    "sg:city":"Verlaine",
    "sg:classifiers":[
        {
            "category":"Health Services",
            "subcategory":"Dentist",
            "type":"Services"
        }
    ],
    "sg:phone":"+32 4 259 64 16",
    "sg:postcode":"4537",
    "sg:province":"Li\u00e8ge",
    "wof:name":"Bernard J-l",
    "wof:placetype":"venue"
},
  "geometry": {"coordinates":[5.3099579811,50.6109237671],"type":"Point"}
}