{
  "type": "Feature",
  "properties": {
    "addr:full":"Proenhofstraat 28 Tongeren Limburg 3700",
    "addr:housenumber":"28",
    "addr:postcode":"3700",
    "addr:street":"Proenhofstraat",
    "iso:country":"BE",
    "sg:address":"Proenhofstraat 28",
    "sg:city":"Tongeren",
    "sg:orig_category":"Forge, Moulage and Profilage des M\u00e9taux",
    "sg:phone":"+32 12 39 27 19",
    "sg:postcode":"3700",
    "sg:province":"Limburg",
    "wof:name":"Bellefroid",
    "wof:placetype":"venue"
},
  "geometry": {"coordinates":[5.4636240005,50.7807197571],"type":"Point"}
}