{
  "type": "Feature",
  "properties": {
    "addr:full":"Poststraat 26 Halle Vlaams-Brabant 1500",
    "addr:housenumber":"26",
    "addr:postcode":"1500",
    "addr:street":"Poststraat",
    "iso:country":"BE",
    "sg:address":"Poststraat 26",
    "sg:city":"Halle",
    "sg:classifiers":[
        {
            "category":"Shopping",
            "subcategory":"Stationery & Office Supplies",
            "type":"Retail Goods"
        }
    ],
    "sg:phone":"+32 2 361 36 86",
    "sg:postcode":"1500",
    "sg:province":"Vlaams-Brabant",
    "sg:tags":[
        "machine",
        "repair",
        "mainten",
        "-"
    ],
    "wof:name":"Marcelis",
    "wof:placetype":"venue"
},
  "geometry": {"coordinates":[4.2325768471,50.7335891724],"type":"Point"}
}