{
  "type": "Feature",
  "properties": {
    "addr:full":"Parklaan 15 Zaventem Vlaams-Brabant 1930",
    "addr:housenumber":"15",
    "addr:postcode":"1930",
    "addr:street":"Parklaan",
    "iso:country":"BE",
    "sg:address":"Parklaan 15",
    "sg:city":"Zaventem",
    "sg:classifiers":[
        {
            "category":"Bars & Pubs",
            "type":"Food & Drink"
        }
    ],
    "sg:phone":"+32 2 725 60 95",
    "sg:postcode":"1930",
    "sg:province":"Vlaams-Brabant",
    "sg:tags":[
        "tavern"
    ],
    "wof:name":"Van Dijckhof",
    "wof:placetype":"venue"
},
  "geometry": {"coordinates":[4.4745898247,50.8813934326],"type":"Point"}
}