{
  "type": "Feature",
  "properties": {
    "addr:full":"Marmotlaan 55 Wezembeek-oppem Vlaams-Brabant 1970",
    "addr:housenumber":"55",
    "addr:postcode":"1970",
    "addr:street":"Marmotlaan",
    "iso:country":"BE",
    "sg:address":"Marmotlaan 55",
    "sg:city":"Wezembeek-oppem",
    "sg:orig_category":"Beheer onroerend goed Landmeters and schatters",
    "sg:phone":"+32 2 784 20 90",
    "sg:postcode":"1970",
    "sg:province":"Vlaams-Brabant",
    "wof:name":"J.v. Consult",
    "wof:placetype":"venue"
},
  "geometry": {"coordinates":[4.4974098206,50.8359031677],"type":"Point"}
}