{
  "type": "Feature",
  "properties": {
    "addr:full":"Rue De Dampremy 10 Charleroi Hainaut 6000",
    "addr:housenumber":"10",
    "addr:postcode":"6000",
    "addr:street":"Rue De Dampremy;Hainaut",
    "iso:country":"BE",
    "sg:address":"Rue De Dampremy 10",
    "sg:city":"Charleroi",
    "sg:classifiers":[
        {
            "category":"Shopping",
            "subcategory":"Bridal",
            "type":"Retail Goods"
        }
    ],
    "sg:phone":"+32 71 30 30 01",
    "sg:postcode":"6000",
    "sg:province":"Hainaut",
    "sg:tags":[
        "list",
        "-",
        "present",
        "wedding"
    ],
    "wof:name":"Encore Et Encore",
    "wof:placetype":"venue"
},
  "geometry": {"coordinates":[4.442073822,50.4086761475],"type":"Point"}
}