{
  "type": "Feature",
  "properties": {
    "iso:country":"BE",
    "sg:address":"Heideveld 54b",
    "sg:city":"Beersel (huizingen)",
    "sg:classifiers":[
        {
            "category":"Transit Center",
            "subcategory":"Passenger",
            "type":"Transportation"
        }
    ],
    "sg:phone":"+32 2 356 96 27",
    "sg:postcode":"1654",
    "sg:province":"Vlaams-Brabant",
    "sg:tags":[
        "sand",
        "gravel"
    ],
    "wof:name":"Amacro Nv",
    "wof:placetype":"venue"
},
  "geometry": {"coordinates":[4.2618050575,50.7551078796],"type":"Point"}
}