{
  "type": "Feature",
  "properties": {
    "addr:full":"Avenue Du G\u00c9n\u00c9ral-patton 237 Arlon Luxembourg 6700",
    "addr:housenumber":"237",
    "addr:postcode":"6700",
    "addr:street":"Avenue Du Ge\u0301Ne\u0301Ral-Patton",
    "iso:country":"BE",
    "sg:address":"Avenue Du G\u00c9n\u00c9ral-patton 237",
    "sg:city":"Arlon",
    "sg:classifiers":[
        {
            "category":"Health Services",
            "subcategory":"Nursing And Care Facility",
            "type":"Services"
        }
    ],
    "sg:phone":"+32 63 21 55 11",
    "sg:postcode":"6700",
    "sg:province":"Luxembourg",
    "sg:tags":[
        "public"
    ],
    "wof:name":"Telelux",
    "wof:placetype":"venue"
},
  "geometry": {"coordinates":[5.8180251122,49.6718025208],"type":"Point"}
}