{
  "type": "Feature",
  "properties": {
    "addr:full":"Halveweg 24 Zonhoven Limburg 3520",
    "addr:housenumber":"24",
    "addr:postcode":"3520",
    "addr:street":"Halveweg",
    "iso:country":"BE",
    "sg:address":"Halveweg 24",
    "sg:city":"Zonhoven",
    "sg:classifiers":[
        {
            "category":"Food & Beverages",
            "subcategory":"Fruits & Vegetables",
            "type":"Retail Goods"
        }
    ],
    "sg:phone":"+32 11 81 89 13",
    "sg:postcode":"3520",
    "sg:province":"Limburg",
    "sg:tags":[
        "-"
    ],
    "wof:name":"Pompolino/vanoirbeek Wendy",
    "wof:placetype":"venue"
},
  "geometry": {"coordinates":[5.3445081711,50.9924163818],"type":"Point"}
}