{
  "type": "Feature",
  "properties": {
    "iso:country":"BE",
    "sg:address":"Oostremstraat 2a",
    "sg:city":"Laarne",
    "sg:classifiers":[
        {
            "category":"Professional",
            "subcategory":"Computer Services",
            "type":"Services"
        }
    ],
    "sg:phone":"+32 9 368 08 71",
    "sg:postcode":"9270",
    "sg:province":"Oost-Vlaanderen",
    "sg:tags":[
        "-",
        "processing",
        "data",
        "software"
    ],
    "wof:name":"R S D",
    "wof:placetype":"venue"
},
  "geometry": {"coordinates":[3.8545749187,51.0323829651],"type":"Point"}
}