{
  "type": "Feature",
  "properties": {
    "addr:full":"De Nefstraat 49 Lille (gierle) Antwerpen 2275",
    "addr:housenumber":"49",
    "addr:postcode":"2275",
    "addr:street":"De Nefstraat",
    "iso:country":"BE",
    "sg:address":"De Nefstraat 49",
    "sg:city":"Lille (gierle)",
    "sg:classifiers":[
        {
            "category":"Home & Garden",
            "subcategory":"Household Appliances",
            "type":"Retail Goods"
        }
    ],
    "sg:phone":"+32 14 55 68 43",
    "sg:postcode":"2275",
    "sg:province":"Antwerpen",
    "sg:tags":[
        "repair",
        "mainten",
        "-",
        "electric"
    ],
    "wof:name":"Puus Bvba",
    "wof:placetype":"venue"
},
  "geometry": {"coordinates":[4.8707318306,51.269947052],"type":"Point"}
}