{
  "type": "Feature",
  "properties": {
    "addr:full":"Jakob Jordaensstraat 9 Gent Oost-Vlaanderen 9000",
    "addr:housenumber":"9",
    "addr:postcode":"9000",
    "addr:street":"Jakob Jordaensstraat;Oost-Vlaanderen",
    "iso:country":"BE",
    "sg:address":"Jakob Jordaensstraat 9",
    "sg:city":"Gent",
    "sg:classifiers":[
        {
            "category":"Home & Garden",
            "subcategory":"Building Materials",
            "type":"Retail Goods"
        }
    ],
    "sg:phone":"+32 477 30 77 16",
    "sg:postcode":"9000",
    "sg:province":"Oost-Vlaanderen",
    "sg:tags":[
        "water",
        "heater"
    ],
    "wof:name":"A Mouton-gent",
    "wof:placetype":"venue"
},
  "geometry": {"coordinates":[3.7225999832,51.0427207947],"type":"Point"}
}