{
  "type": "Feature",
  "properties": {
    "iso:country":"BE",
    "sg:address":"Baliestraat 5",
    "sg:city":"Kortrijk (marke)",
    "sg:orig_category":"Non-Classified Establishments",
    "sg:phone":"+32 56 22 99 05",
    "sg:postcode":"8510",
    "sg:province":"West-Vlaanderen",
    "wof:name":"Mdr Nv",
    "wof:placetype":"venue"
},
  "geometry": {"coordinates":[3.2440929413,50.8078155518],"type":"Point"}
}