{
  "type": "Feature",
  "properties": {
    "iso:country":"BE",
    "sg:address":"Sent De La Fermette 28",
    "sg:city":"Court-saint-etienne",
    "sg:orig_category":"Tuinen",
    "sg:phone":"+32 10 61 34 20",
    "sg:postcode":"1490",
    "sg:province":"Brabant Wallon",
    "wof:name":"Cantillon & Fils",
    "wof:placetype":"venue"
},
  "geometry": {"coordinates":[4.5297598839,50.6488990784],"type":"Point"}
}