{
  "type": "Feature",
  "properties": {
    "addr:full":"Rue De Sclaigneau 645 Andenne Namur 5300",
    "addr:housenumber":"645",
    "addr:postcode":"5300",
    "addr:street":"Rue De Sclaigneau",
    "iso:country":"BE",
    "sg:address":"Rue De Sclaigneau 645",
    "sg:city":"Andenne",
    "sg:orig_category":"Kapsalons",
    "sg:phone":"+32 81 58 81 32",
    "sg:postcode":"5300",
    "sg:province":"Namur",
    "wof:name":"Anne-marie Evrard",
    "wof:placetype":"venue"
},
  "geometry": {"coordinates":[5.0089511871,50.495677948],"type":"Point"}
}