{
  "type": "Feature",
  "properties": {
    "addr:full":"Oeverstraat 84 Temse Oost-Vlaanderen 9140",
    "addr:housenumber":"84",
    "addr:postcode":"9140",
    "addr:street":"Oeverstraat",
    "iso:country":"BE",
    "sg:address":"Oeverstraat 84",
    "sg:city":"Temse",
    "sg:orig_category":"V\u00eatements",
    "sg:phone":"+32 3 771 56 80",
    "sg:postcode":"9140",
    "sg:province":"Oost-Vlaanderen",
    "wof:name":"Belcon",
    "wof:placetype":"venue"
},
  "geometry": {"coordinates":[4.2082629204,51.1255950928],"type":"Point"}
}