{
  "type": "Feature",
  "properties": {
    "iso:country":"BE",
    "sg:address":"Koksijdeweg 24",
    "sg:city":"De Panne",
    "sg:orig_category":"Installation \u00e9lectrique r\u00e9sidentielle",
    "sg:phone":"+32 58 42 15 35",
    "sg:postcode":"8660",
    "sg:province":"West-Vlaanderen",
    "wof:name":"Christophe Vanhove",
    "wof:placetype":"venue"
},
  "geometry": {"coordinates":[2.6133439541,51.0946922302],"type":"Point"}
}