{
  "type": "Feature",
  "properties": {
    "iso:country":"BE",
    "sg:address":"Perseweide 13",
    "sg:city":"Ieper (zillebeke)",
    "sg:classifiers":[
        {
            "category":"Building & Trades",
            "subcategory":"Electrical",
            "type":"Services"
        }
    ],
    "sg:phone":"+32 57 20 95 29",
    "sg:postcode":"8902",
    "sg:province":"West-Vlaanderen",
    "sg:tags":[
        "electric",
        "-",
        "housewiring",
        "contractor"
    ],
    "wof:name":"Vandeskelde L",
    "wof:placetype":"venue"
},
  "geometry": {"coordinates":[2.9215049744,50.8332176208],"type":"Point"}
}