{
  "type": "Feature",
  "properties": {
    "addr:full":"Boulevard L\u00c9opold Iii 96 Peruwelz Hainaut 7600",
    "addr:housenumber":"96",
    "addr:postcode":"7600",
    "addr:street":"Boulevard Le\u0301Opold Iii;Hainaut",
    "iso:country":"BE",
    "sg:address":"Boulevard L\u00c9opold Iii 96",
    "sg:city":"Peruwelz",
    "sg:classifiers":[
        {
            "category":"Professional",
            "subcategory":"Accounting & Tax Preparation",
            "type":"Services"
        }
    ],
    "sg:phone":"+32 69 77 32 66",
    "sg:postcode":"7600",
    "sg:province":"Hainaut",
    "sg:tags":[
        "accountant"
    ],
    "wof:name":"Jean-marie Noulet",
    "wof:placetype":"venue"
},
  "geometry": {"coordinates":[3.5963230133,50.5041427612],"type":"Point"}
}