{
  "type": "Feature",
  "properties": {
    "addr:full":"Kortestraat 4 Lichtervelde West-Vlaanderen 8810",
    "addr:housenumber":"4",
    "addr:postcode":"8810",
    "addr:street":"Kortestraat",
    "iso:country":"BE",
    "sg:address":"Kortestraat 4",
    "sg:city":"Lichtervelde",
    "sg:orig_category":"Lampes and appareils \u00e9lectriques Fab. Travaux d\u00b4installation divers",
    "sg:phone":"+32 51 72 40 91",
    "sg:postcode":"8810",
    "sg:province":"West-Vlaanderen",
    "wof:name":"Neon Jean",
    "wof:placetype":"venue"
},
  "geometry": {"coordinates":[3.1426839828,51.0208702087],"type":"Point"}
}