{
  "type": "Feature",
  "properties": {
    "iso:country":"BE",
    "sg:address":"Nekkersputstraat 106",
    "sg:city":"Gent",
    "sg:classifiers":[
        {
            "category":"Building & Trades",
            "subcategory":"Landscaping Services",
            "type":"Services"
        }
    ],
    "sg:phone":"+32 9 226 68 40",
    "sg:postcode":"9000",
    "sg:province":"Oost-Vlaanderen",
    "sg:tags":[
        "access",
        "pond",
        "laying-out",
        "-"
    ],
    "wof:name":"Amf Marine Cv",
    "wof:placetype":"venue"
},
  "geometry": {"coordinates":[3.6909880638,51.060459137],"type":"Point"}
}