{
  "type": "Feature",
  "properties": {
    "addr:full":"Chauss\u00c9e De Bruxelles 440 Doornik Hainaut 7500",
    "addr:housenumber":"440",
    "addr:postcode":"7500",
    "addr:street":"Chausse\u0301E De Bruxelles;Hainaut",
    "iso:country":"BE",
    "sg:address":"Chauss\u00c9e De Bruxelles 440",
    "sg:city":"Doornik",
    "sg:orig_category":"Autokeuringen",
    "sg:phone":"+32 69 22 24 45",
    "sg:postcode":"7500",
    "sg:province":"Hainaut",
    "wof:name":"Contr\u00d4le Technique Automobile",
    "wof:placetype":"venue"
},
  "geometry": {"coordinates":[3.4388380051,50.6009788513],"type":"Point"}
}