{
  "type": "Feature",
  "properties": {
    "iso:country":"BE",
    "sg:address":"Boondaalsesteenweg 460",
    "sg:city":"Elsene/ixelles",
    "sg:orig_category":"Kapsalons",
    "sg:phone":"+32 2 648 59 75",
    "sg:postcode":"1050",
    "sg:province":"Bruxelles-Capitale",
    "wof:name":"Coiffure Charly",
    "wof:placetype":"venue"
},
  "geometry": {"coordinates":[4.3895430565,50.8164482117],"type":"Point"}
}