{
  "type": "Feature",
  "properties": {
    "iso:country":"BE",
    "sg:address":"Avenue De La D\u00c9livrance 121",
    "sg:city":"Moeskroen/mouscron",
    "sg:orig_category":"Charpentes and couvertures",
    "sg:phone":"+32 56 48 87 45",
    "sg:postcode":"7711",
    "sg:province":"Hainaut",
    "wof:name":"Emile Talon",
    "wof:placetype":"venue"
},
  "geometry": {"coordinates":[3.301213026,50.7187805176],"type":"Point"}
}