{
  "type": "Feature",
  "properties": {
    "addr:full":"Rue De Huy 28 Hannut Li\u00e8ge 4280",
    "addr:housenumber":"28",
    "addr:postcode":"4280",
    "addr:street":"Rue De Huy",
    "iso:country":"BE",
    "sg:address":"Rue De Huy 28",
    "sg:city":"Hannut",
    "sg:classifiers":[
        {
            "category":"Education",
            "subcategory":"School",
            "type":"Public Place"
        }
    ],
    "sg:phone":"+32 19 51 32 83",
    "sg:postcode":"4280",
    "sg:province":"Li\u00e8ge",
    "sg:tags":[
        "secondary"
    ],
    "wof:name":"Institut D'enseignement Sp\u00e9cial Secondaire De La Communaut\u00e9 Fran\u00e7aise",
    "wof:placetype":"venue"
},
  "geometry": {"coordinates":[5.0882940292,50.6662445068],"type":"Point"}
}