{
  "type": "Feature",
  "properties": {
    "iso:country":"BE",
    "sg:address":"Breidelstraat 4",
    "sg:city":"Brugge",
    "sg:orig_category":"Non-Classified Establishments",
    "sg:phone":"+32 50 34 87 43",
    "sg:postcode":"8000",
    "sg:province":"West-Vlaanderen",
    "wof:name":"Lace Art Gallery",
    "wof:placetype":"venue"
},
  "geometry": {"coordinates":[3.2252349854,51.2083740234],"type":"Point"}
}