{
  "type": "Feature",
  "properties": {
    "iso:country":"BE",
    "sg:address":"Schuttersstraat 19",
    "sg:city":"Lommel",
    "sg:orig_category":"Elektrische installaties voor woningen",
    "sg:phone":"+32 11 55 35 70",
    "sg:postcode":"3920",
    "sg:province":"Limburg",
    "wof:name":"Johan Hesemans",
    "wof:placetype":"venue"
},
  "geometry": {"coordinates":[5.3142838478,51.2140846252],"type":"Point"}
}