{
  "type": "Feature",
  "properties": {
    "addr:full":"Rostijnestraat 16 Gent (desteldonk) Oost-Vlaanderen 9042",
    "addr:housenumber":"16",
    "addr:postcode":"9042",
    "addr:street":"Rostijnestraat",
    "iso:country":"BE",
    "sg:address":"Rostijnestraat 16",
    "sg:city":"Gent (desteldonk)",
    "sg:classifiers":[
        {
            "category":"Farming",
            "subcategory":"Nursery",
            "type":"Manufacturing & Wholesale Goods"
        }
    ],
    "sg:phone":"+32 9 355 74 25",
    "sg:postcode":"9042",
    "sg:province":"Oost-Vlaanderen",
    "sg:tags":[
        "horticultural",
        "automation"
    ],
    "wof:name":"Van Eeckhoute R & Zn",
    "wof:placetype":"venue"
},
  "geometry": {"coordinates":[3.7816700935,51.1223831177],"type":"Point"}
}