{
  "type": "Feature",
  "properties": {
    "iso:country":"BE",
    "sg:address":"Lange Breestraat 14",
    "sg:city":"Lebbeke",
    "sg:orig_category":"Groenten and fruit Gh",
    "sg:phone":"+32 52 35 58 11",
    "sg:postcode":"9280",
    "sg:province":"Oost-Vlaanderen",
    "wof:name":"Hendrik Jansegers",
    "wof:placetype":"venue"
},
  "geometry": {"coordinates":[4.1476869583,50.976436615],"type":"Point"}
}