{
  "type": "Feature",
  "properties": {
    "addr:full":"Kapelstraat 27 Kalmthout Antwerpen 2920",
    "addr:housenumber":"27",
    "addr:postcode":"2920",
    "addr:street":"Kapelstraat",
    "iso:country":"BE",
    "sg:address":"Kapelstraat 27",
    "sg:city":"Kalmthout",
    "sg:classifiers":[
        {
            "category":"Building & Trades",
            "subcategory":"Landscaping Services",
            "type":"Services"
        }
    ],
    "sg:phone":"+32 495 87 95 84",
    "sg:postcode":"2920",
    "sg:province":"Antwerpen",
    "sg:tags":[
        "gardening",
        "garden",
        "maintenance"
    ],
    "wof:name":"Art Vert Bvba",
    "wof:placetype":"venue"
},
  "geometry": {"coordinates":[4.5083432198,51.4030799866],"type":"Point"}
}