{
  "type": "Feature",
  "properties": {
    "addr:full":"Domaine Sart Tilman Li\u00e8ge 1 (tonne) Li\u00e8ge 4000",
    "addr:postcode":"4000",
    "addr:street":"Tonne",
    "iso:country":"BE",
    "sg:address":"Domaine Sart Tilman",
    "sg:city":"Li\u00e8ge 1 (tonne)",
    "sg:classifiers":[
        {
            "category":"Health Services",
            "subcategory":"Dentist",
            "type":"Services"
        }
    ],
    "sg:phone":"+32 4 366 71 11",
    "sg:postcode":"4000",
    "sg:province":"Li\u00e8ge",
    "sg:tags":[
        "dental",
        "clinic"
    ],
    "wof:name":"C.h.u. De Liege",
    "wof:placetype":"venue"
},
  "geometry": {"coordinates":[5.5749769211,50.5722961426],"type":"Point"}
}