{
  "type": "Feature",
  "properties": {
    "iso:country":"BE",
    "sg:address":"Diksmuidseweg 301a",
    "sg:city":"Ieper (boezinge)",
    "sg:classifiers":[
        {
            "category":"Retail",
            "subcategory":"Veterinary Services",
            "type":"Services"
        }
    ],
    "sg:phone":"+32 57 42 27 70",
    "sg:postcode":"8904",
    "sg:province":"West-Vlaanderen",
    "sg:tags":[
        "veterinarian"
    ],
    "wof:name":"Boussemaere M",
    "wof:placetype":"venue"
},
  "geometry": {"coordinates":[2.8661680222,50.8872108459],"type":"Point"}
}