{
  "type": "Feature",
  "properties": {
    "addr:full":"Willem Coosemansstraat 105b3 Leuven Vlaams-Brabant 3010",
    "addr:housenumber":"105b3",
    "addr:postcode":"3010",
    "addr:street":"Willem Coosemansstraat",
    "iso:country":"BE",
    "sg:address":"Willem Coosemansstraat 105b3",
    "sg:city":"Leuven",
    "sg:orig_category":"Secr\u00e9tariats",
    "sg:phone":"+32 16 35 00 34",
    "sg:postcode":"3010",
    "sg:province":"Vlaams-Brabant",
    "wof:name":"Alibee A'linea",
    "wof:placetype":"venue"
},
  "geometry": {"coordinates":[4.7304501534,50.889755249],"type":"Point"}
}