{
  "type": "Feature",
  "properties": {
    "addr:full":"Dorpsstraat 87 Knokke-heist West-Vlaanderen 8300",
    "addr:housenumber":"87",
    "addr:postcode":"8300",
    "addr:street":"Dorpsstraat",
    "iso:country":"BE",
    "sg:address":"Dorpsstraat 87",
    "sg:city":"Knokke-heist",
    "sg:orig_category":"Epiceries",
    "sg:phone":"+32 50 61 55 96",
    "sg:postcode":"8300",
    "sg:province":"West-Vlaanderen",
    "wof:name":"Spar",
    "wof:placetype":"venue"
},
  "geometry": {"coordinates":[3.287694931,51.3467254639],"type":"Point"}
}