{
  "type": "Feature",
  "properties": {
    "iso:country":"BE",
    "sg:address":"Avenue Fran\u00c7oise 9",
    "sg:city":"Rixensart",
    "sg:orig_category":"Instituts pour adultes moins valides",
    "sg:phone":"+32 2 653 27 38",
    "sg:postcode":"1330",
    "sg:province":"Brabant Wallon",
    "wof:name":"Foyer De L'amit\u00c9",
    "wof:placetype":"venue"
},
  "geometry": {"coordinates":[4.5261697769,50.7086448669],"type":"Point"}
}