{
  "type": "Feature",
  "properties": {
    "iso:country":"BE",
    "sg:address":"Kiliaanstraat 25",
    "sg:city":"Duffel",
    "sg:classifiers":[
        {
            "category":"Shopping",
            "subcategory":"Baby Store",
            "type":"Retail Goods"
        }
    ],
    "sg:phone":"+32 15 31 00 26",
    "sg:postcode":"2570",
    "sg:province":"Antwerpen",
    "sg:tags":[
        "-",
        "accessory"
    ],
    "wof:name":"Bubbels",
    "wof:placetype":"venue"
},
  "geometry": {"coordinates":[4.5033721924,51.095085144],"type":"Point"}
}