{
  "type": "Feature",
  "properties": {
    "iso:country":"BE",
    "sg:address":"L\u00c9on Bekaertlaan 24",
    "sg:city":"Aalter",
    "sg:classifiers":[
        {
            "category":"Shopping",
            "subcategory":"Computers & Home Electronics",
            "type":"Retail Goods"
        }
    ],
    "sg:phone":"+32 9 325 75 50",
    "sg:postcode":"9880",
    "sg:province":"Oost-Vlaanderen",
    "sg:tags":[
        "siemens",
        "fujitsu",
        "computerapparatuur"
    ],
    "wof:name":"Promatic-b",
    "wof:placetype":"venue"
},
  "geometry": {"coordinates":[3.4500050545,51.1015892029],"type":"Point"}
}