{
  "type": "Feature",
  "properties": {
    "iso:country":"BE",
    "sg:address":"Belgi\u00eblei 149 Box 7",
    "sg:city":"Antwerpen",
    "sg:classifiers":[
        {
            "category":"Personal",
            "subcategory":"Psychics & Astrologers",
            "type":"Services"
        }
    ],
    "sg:phone":"+32 3 230 75 11",
    "sg:postcode":"2018",
    "sg:province":"Antwerpen",
    "sg:tags":[
        "astrology"
    ],
    "wof:name":"Vlaams Astrologisch Genootschap Vzw",
    "wof:placetype":"venue"
},
  "geometry": {"coordinates":[4.4159817696,51.2039642334],"type":"Point"}
}