{
  "type": "Feature",
  "properties": {
    "iso:country":"BE",
    "sg:address":"Leiepark 5",
    "sg:city":"Sint-martens-latem",
    "sg:orig_category":"Installation de menuiserie en bois and plastique",
    "sg:phone":"+32 9 367 88 93",
    "sg:postcode":"9831",
    "sg:province":"Oost-Vlaanderen",
    "wof:name":"Fermall",
    "wof:placetype":"venue"
},
  "geometry": {"coordinates":[3.6034889221,51.0003471375],"type":"Point"}
}