{
  "type": "Feature",
  "properties": {
    "addr:full":"Aardstraat 10 Nijlen (kessel) Antwerpen 2560",
    "addr:housenumber":"10",
    "addr:postcode":"2560",
    "addr:street":"Aardstraat",
    "iso:country":"BE",
    "sg:address":"Aardstraat 10",
    "sg:city":"Nijlen (kessel)",
    "sg:classifiers":[
        {
            "category":"Professional",
            "subcategory":"Art Services",
            "type":"Services"
        }
    ],
    "sg:phone":"+32 3 489 11 85",
    "sg:postcode":"2560",
    "sg:province":"Antwerpen",
    "sg:tags":[
        "children's",
        "animation"
    ],
    "wof:name":"Klei-tof",
    "wof:placetype":"venue"
},
  "geometry": {"coordinates":[4.6163978577,51.1530838013],"type":"Point"}
}