{
  "type": "Feature",
  "properties": {
    "iso:country":"BE",
    "sg:address":"Rue De Maestricht 95",
    "sg:city":"Vis\u00c9",
    "sg:orig_category":"Isolatiewerk",
    "sg:phone":"+32 4 379 04 14",
    "sg:postcode":"4600",
    "sg:province":"Li\u00e8ge",
    "wof:name":"Ors",
    "wof:placetype":"venue"
},
  "geometry": {"coordinates":[5.7037072182,50.7469139099],"type":"Point"}
}