{
  "type": "Feature",
  "properties": {
    "addr:full":"Reinaertgalerij 34 Sint-niklaas Oost-Vlaanderen 9100",
    "addr:housenumber":"34",
    "addr:postcode":"9100",
    "addr:street":"Reinaertgalerij",
    "iso:country":"BE",
    "sg:address":"Reinaertgalerij 34",
    "sg:city":"Sint-niklaas",
    "sg:classifiers":[
        {
            "category":"Personal",
            "subcategory":"Beauty Salon",
            "type":"Services"
        }
    ],
    "sg:phone":"+32 3 776 04 44",
    "sg:postcode":"9100",
    "sg:province":"Oost-Vlaanderen",
    "sg:tags":[
        "lady",
        "-",
        "hairdressing"
    ],
    "wof:name":"Mario",
    "wof:placetype":"venue"
},
  "geometry": {"coordinates":[4.1517419815,51.1501731873],"type":"Point"}
}