{
  "type": "Feature",
  "properties": {
    "iso:country":"BE",
    "sg:address":"Rue D'h\u00c9rinnes 21",
    "sg:city":"Edingen/enghien",
    "sg:orig_category":"Opticiens",
    "sg:phone":"+32 2 395 34 75",
    "sg:postcode":"7850",
    "sg:province":"Hainaut",
    "wof:name":"Maison Maesen",
    "wof:placetype":"venue"
},
  "geometry": {"coordinates":[4.0391249657,50.6943321228],"type":"Point"}
}