{
  "type": "Feature",
  "properties": {
    "addr:full":"Albert I Laan 27 Veurne West-Vlaanderen 8630",
    "addr:housenumber":"27",
    "addr:postcode":"8630",
    "addr:street":"Albert I Laan",
    "iso:country":"BE",
    "sg:address":"Albert I Laan 27",
    "sg:city":"Veurne",
    "sg:classifiers":[
        {
            "category":"Home & Garden",
            "subcategory":"Garden Supply",
            "type":"Retail Goods"
        }
    ],
    "sg:phone":"+32 58 31 38 92",
    "sg:postcode":"8630",
    "sg:province":"West-Vlaanderen",
    "sg:tags":[
        "machine",
        "agricultural",
        "-"
    ],
    "wof:name":"Gouwy J",
    "wof:placetype":"venue"
},
  "geometry": {"coordinates":[2.6814169884,51.0647087097],"type":"Point"}
}