{
  "type": "Feature",
  "properties": {
    "addr:full":"Westbroekstraat 60 Houthulst West-Vlaanderen 8650",
    "addr:housenumber":"60",
    "addr:postcode":"8650",
    "addr:street":"Westbroekstraat",
    "iso:country":"BE",
    "sg:address":"Westbroekstraat 60",
    "sg:city":"Houthulst",
    "sg:orig_category":"Banques and organismes de cr\u00e9dit",
    "sg:phone":"+32 51 54 46 16",
    "sg:postcode":"8650",
    "sg:province":"West-Vlaanderen",
    "wof:name":"Landbouwkrediet",
    "wof:placetype":"venue"
},
  "geometry": {"coordinates":[2.9509439468,50.9778862],"type":"Point"}
}