{
  "type": "Feature",
  "properties": {
    "iso:country":"BE",
    "sg:address":"Meersbloem Melden 20",
    "sg:city":"Oudenaarde (melden)",
    "sg:classifiers":[
        {
            "category":"Home & Garden",
            "subcategory":"Carpets & Floor Coverings",
            "type":"Retail Goods"
        }
    ],
    "sg:phone":"+32 55 33 59 11",
    "sg:postcode":"9700",
    "sg:province":"Oost-Vlaanderen",
    "sg:tags":[
        "industrial",
        "-"
    ],
    "wof:name":"Gilleman",
    "wof:placetype":"venue"
},
  "geometry": {"coordinates":[3.57385993,50.8169593811],"type":"Point"}
}