{
  "type": "Feature",
  "properties": {
    "addr:full":"Battelsesteenweg 455b Mechelen Antwerpen 2800",
    "addr:housenumber":"455b",
    "addr:postcode":"2800",
    "addr:street":"Battelsesteenweg",
    "iso:country":"BE",
    "sg:address":"Battelsesteenweg 455b",
    "sg:city":"Mechelen",
    "sg:orig_category":"Bedrijvencentra and kantoordiensten Secretariaatsdiensten Vertalers and tolken",
    "sg:phone":"+32 15 27 15 85",
    "sg:postcode":"2800",
    "sg:province":"Antwerpen",
    "wof:name":"Business Service Taminiau",
    "wof:placetype":"venue"
},
  "geometry": {"coordinates":[4.450094223,51.0380706787],"type":"Point"}
}