{
  "type": "Feature",
  "properties": {
    "addr:full":"Rue Des Ecoliers 18 Li\u00c8ge Li\u00e8ge 4020",
    "addr:housenumber":"18",
    "addr:postcode":"4020",
    "addr:street":"Rue Des Ecoliers",
    "iso:country":"BE",
    "sg:address":"Rue Des Ecoliers 18",
    "sg:city":"Li\u00c8ge",
    "sg:classifiers":[
        {
            "category":"Fast Food",
            "type":"Food & Drink"
        }
    ],
    "sg:phone":"+32 4 343 50 30",
    "sg:postcode":"4020",
    "sg:province":"Li\u00e8ge",
    "sg:tags":[
        "\u00c0",
        "emporter",
        "restaurants"
    ],
    "wof:name":"Friterie Chez Tonio",
    "wof:placetype":"venue"
},
  "geometry": {"coordinates":[5.5820841789,50.6435241699],"type":"Point"}
}