{
  "type": "Feature",
  "properties": {
    "addr:full":"Prinshoeveweg 142 Antwerpen (ekeren) Antwerpen 2180",
    "addr:housenumber":"142",
    "addr:postcode":"2180",
    "addr:street":"Prinshoeveweg",
    "iso:country":"BE",
    "sg:address":"Prinshoeveweg 142",
    "sg:city":"Antwerpen (ekeren)",
    "sg:classifiers":[
        {
            "category":"Shopping",
            "subcategory":"Jewelry",
            "type":"Retail Goods"
        }
    ],
    "sg:phone":"+32 3 647 27 86",
    "sg:postcode":"2180",
    "sg:province":"Antwerpen",
    "sg:tags":[
        "-",
        "imitation"
    ],
    "wof:name":"Regnier M",
    "wof:placetype":"venue"
},
  "geometry": {"coordinates":[4.4182572365,51.2778625488],"type":"Point"}
}