{
  "type": "Feature",
  "properties": {
    "addr:full":"Stationsstraat 255 Dilbeek Vlaams-Brabant 1700",
    "addr:housenumber":"255",
    "addr:postcode":"1700",
    "addr:street":"Stationsstraat",
    "iso:country":"BE",
    "sg:address":"Stationsstraat 255",
    "sg:city":"Dilbeek",
    "sg:orig_category":"M\u00e9decins and sp\u00e9cialistes",
    "sg:phone":"+32 2 466 03 09",
    "sg:postcode":"1700",
    "sg:province":"Vlaams-Brabant",
    "wof:name":"Eric Genie",
    "wof:placetype":"venue"
},
  "geometry": {"coordinates":[4.2459387779,50.8630371094],"type":"Point"}
}