{
  "type": "Feature",
  "properties": {
    "addr:full":"New-orleansstraat 449 Gent Oost-Vlaanderen 9000",
    "addr:housenumber":"449",
    "addr:postcode":"9000",
    "addr:street":"Oost-Vlaanderen",
    "iso:country":"BE",
    "sg:address":"New-orleansstraat 449",
    "sg:city":"Gent",
    "sg:orig_category":"Dakwerken Loodgieterij, verwarming and sanitaire installaties",
    "sg:phone":"+32 9 251 60 14",
    "sg:postcode":"9000",
    "sg:province":"Oost-Vlaanderen",
    "wof:name":"Julien Bove",
    "wof:placetype":"venue"
},
  "geometry": {"coordinates":[3.7300789356,51.0850372314],"type":"Point"}
}