{
  "type": "Feature",
  "properties": {
    "addr:full":"Rue Du Travail 16 Grace-hollogne Li\u00e8ge 4460",
    "addr:housenumber":"16",
    "addr:postcode":"4460",
    "addr:street":"Rue Du Travail",
    "iso:country":"BE",
    "sg:address":"Rue Du Travail 16",
    "sg:city":"Grace-hollogne",
    "sg:orig_category":"Games and entertainment Horticulture Miscellaneous Products",
    "sg:phone":"+32 4 239 97 10",
    "sg:postcode":"4460",
    "sg:province":"Li\u00e8ge",
    "wof:name":"Ets Guy Lambert Sa",
    "wof:placetype":"venue"
},
  "geometry": {"coordinates":[5.4996809959,50.6573448181],"type":"Point"}
}