{
  "type": "Feature",
  "properties": {
    "iso:country":"BE",
    "sg:address":"Chem.bois De Steenkerque 12ba",
    "sg:city":"Soignies",
    "sg:orig_category":"Eleveurs and marchands de porcs",
    "sg:phone":"+32 67 33 58 95",
    "sg:postcode":"7060",
    "sg:province":"Hainaut",
    "wof:name":"Guy Duquene",
    "wof:placetype":"venue"
},
  "geometry": {"coordinates":[4.0729470253,50.580821991],"type":"Point"}
}