{
  "type": "Feature",
  "properties": {
    "iso:country":"BE",
    "sg:address":"Av De Nerviens 9-31",
    "sg:city":"Bruxelles",
    "sg:classifiers":[
        {
            "category":"Banks & Credit Unions",
            "subcategory":"Financial Services",
            "type":"Services"
        }
    ],
    "sg:phone":"+32 2 504 82 11",
    "sg:postcode":"1040",
    "sg:province":"Bruxelles-Capitale",
    "sg:tags":[
        "banking",
        "finance",
        "insurance"
    ],
    "wof:name":"Secura Belgian Re",
    "wof:placetype":"venue"
},
  "geometry": {"coordinates":[4.3859539032,50.8393325806],"type":"Point"}
}