{
  "type": "Feature",
  "properties": {
    "addr:full":"Avenue Brugmann 235 Bruxelles (ixelles) Bruxelles-Capitale 1050",
    "addr:housenumber":"235",
    "addr:postcode":"1050",
    "addr:street":"Avenue Brugmann",
    "iso:country":"BE",
    "sg:address":"Avenue Brugmann 235",
    "sg:city":"Bruxelles (ixelles)",
    "sg:classifiers":[
        {
            "category":"Professional",
            "subcategory":"Computer Services",
            "type":"Services"
        }
    ],
    "sg:phone":"+32 2 340 49 60",
    "sg:postcode":"1050",
    "sg:province":"Bruxelles-Capitale",
    "sg:tags":[
        "webdesign",
        "-",
        "internet"
    ],
    "wof:name":"Cyberia",
    "wof:placetype":"venue"
},
  "geometry": {"coordinates":[4.348154068,50.8143882751],"type":"Point"}
}