{
  "type": "Feature",
  "properties": {
    "addr:full":"Rue Au Bois 358 Sint-pieters-woluwe/woluwe-sai Bruxelles-Capitale 1150",
    "addr:housenumber":"358",
    "addr:postcode":"1150",
    "addr:street":"Rue Au Bois",
    "iso:country":"BE",
    "sg:address":"Rue Au Bois 358",
    "sg:city":"Sint-pieters-woluwe/woluwe-sai",
    "sg:classifiers":[
        {
            "category":"Restaurant",
            "type":"Food & Drink"
        }
    ],
    "sg:phone":"+32 2 770 91 38",
    "sg:postcode":"1150",
    "sg:province":"Bruxelles-Capitale",
    "wof:name":"Resto Resto ( La Carrosserie )",
    "wof:placetype":"venue"
},
  "geometry": {"coordinates":[4.4542069435,50.8300552368],"type":"Point"}
}