{
  "type": "Feature",
  "properties": {
    "addr:full":"Rue Fond Du Mar\u00e9chal 10 Suarl\u00e9e Namur 5020",
    "addr:housenumber":"10",
    "addr:postcode":"5020",
    "addr:street":"Rue Fond Du Mare\u0301Chal",
    "iso:country":"BE",
    "sg:address":"Rue Fond Du Mar\u00e9chal 10",
    "sg:city":"Suarl\u00e9e",
    "sg:classifiers":[
        {
            "category":"Health Services",
            "subcategory":"Medical Lab",
            "type":"Services"
        }
    ],
    "sg:phone":"+32 81 24 51 32",
    "sg:postcode":"5020",
    "sg:province":"Namur",
    "sg:tags":[
        "chemical",
        "pharmaceutical",
        "pharmacy"
    ],
    "wof:name":"Cophana Sa",
    "wof:placetype":"venue"
},
  "geometry": {"coordinates":[4.7909049988,50.4916954041],"type":"Point"}
}