{
  "type": "Feature",
  "properties": {
    "addr:full":"Rue De Vise 273 Li\u00c8ge Li\u00e8ge 4020",
    "addr:housenumber":"273",
    "addr:postcode":"4020",
    "addr:street":"Rue De Vise",
    "iso:country":"BE",
    "sg:address":"Rue De Vise 273",
    "sg:city":"Li\u00c8ge",
    "sg:orig_category":"Industri\u00eble wasserijen and droogkuis",
    "sg:phone":"+32 4 362 90 30",
    "sg:postcode":"4020",
    "sg:province":"Li\u00e8ge",
    "wof:name":"Salon-lavoir Charlemagne",
    "wof:placetype":"venue"
},
  "geometry": {"coordinates":[5.6334052086,50.6482315063],"type":"Point"}
}