{
  "type": "Feature",
  "properties": {
    "iso:country":"BE",
    "sg:address":"Huidevetterslaan 33",
    "sg:city":"Hasselt",
    "sg:orig_category":"Charpentes and couvertures. Plomberie, chauffage and installations sanitaires",
    "sg:phone":"+32 11 27 46 11",
    "sg:postcode":"3500",
    "sg:province":"Limburg",
    "wof:name":"Eurodak",
    "wof:placetype":"venue"
},
  "geometry": {"coordinates":[5.3249378204,50.9202423096],"type":"Point"}
}