{
  "type": "Feature",
  "properties": {
    "addr:full":"Rue Montreuil Sous Bois 80 Mons Hainaut 7022",
    "addr:housenumber":"80",
    "addr:postcode":"7022",
    "addr:street":"Rue Montreuil Sous Bois;Hainaut",
    "iso:country":"BE",
    "sg:address":"Rue Montreuil Sous Bois 80",
    "sg:city":"Mons",
    "sg:orig_category":"Artsen and specialisten",
    "sg:phone":"+32 65 35 20 48",
    "sg:postcode":"7022",
    "sg:province":"Hainaut",
    "wof:name":"Andr\u00c9 Bernard",
    "wof:placetype":"venue"
},
  "geometry": {"coordinates":[3.9568500519,50.4404716492],"type":"Point"}
}