{
  "type": "Feature",
  "properties": {
    "addr:full":"Rue De Miaucourt 51 Courcelles Hainaut 6180",
    "addr:housenumber":"51",
    "addr:postcode":"6180",
    "addr:street":"Rue De Miaucourt",
    "iso:country":"BE",
    "sg:address":"Rue De Miaucourt 51",
    "sg:city":"Courcelles",
    "sg:orig_category":"M\u00e9decins and sp\u00e9cialistes",
    "sg:phone":"+32 71 45 45 70",
    "sg:postcode":"6180",
    "sg:province":"Hainaut",
    "wof:name":"Sabine Maghe",
    "wof:placetype":"venue"
},
  "geometry": {"coordinates":[4.3860602379,50.45911026],"type":"Point"}
}