{
  "type": "Feature",
  "properties": {
    "addr:full":"Avenue Du Tram 29-7 Kraainem Vlaams-Brabant 1950",
    "addr:housenumber":"29-7",
    "addr:postcode":"1950",
    "addr:street":"Avenue Du Tram",
    "iso:country":"BE",
    "sg:address":"Avenue Du Tram 29-7",
    "sg:city":"Kraainem",
    "sg:classifiers":[
        {
            "category":"Health Services",
            "subcategory":"Medical Lab",
            "type":"Services"
        }
    ],
    "sg:phone":"+32 2 725 89 11",
    "sg:postcode":"1950",
    "sg:province":"Vlaams-Brabant",
    "sg:tags":[
        "laboratory",
        "dental"
    ],
    "wof:name":"Dental Partners",
    "wof:placetype":"venue"
},
  "geometry": {"coordinates":[4.4498357773,50.8654670715],"type":"Point"}
}