{
  "type": "Feature",
  "properties": {
    "addr:full":"Rue Du Tchaurnia 2 Houyet (mesnil-saint-blaise) Namur 5560",
    "addr:housenumber":"2",
    "addr:postcode":"5560",
    "addr:street":"Rue Du Tchaurnia",
    "iso:country":"BE",
    "sg:address":"Rue Du Tchaurnia 2",
    "sg:city":"Houyet (mesnil-saint-blaise)",
    "sg:classifiers":[
        {
            "category":"Social Services",
            "type":"Services"
        }
    ],
    "sg:phone":"+32 82 74 40 73",
    "sg:postcode":"5560",
    "sg:province":"Namur",
    "sg:tags":[
        "handicapped",
        "-"
    ],
    "wof:name":"Aide Mesniloise Aux Handicap\u00e9s Asbl",
    "wof:placetype":"venue"
},
  "geometry": {"coordinates":[4.8924050331,50.1668701172],"type":"Point"}
}