{
  "type": "Feature",
  "properties": {
    "iso:country":"BE",
    "sg:address":"Putsebaan 6",
    "sg:city":"Keerbergen",
    "sg:classifiers":[
        {
            "category":"Real Estate",
            "subcategory":"Real Estate Services",
            "type":"Services"
        }
    ],
    "sg:phone":"+32 15 51 45 40",
    "sg:postcode":"3140",
    "sg:province":"Vlaams-Brabant",
    "wof:name":"Immo Margriet Bvba",
    "wof:placetype":"venue"
},
  "geometry": {"coordinates":[4.6279420853,51.0046615601],"type":"Point"}
}