{
  "type": "Feature",
  "properties": {
    "addr:full":"Geuzestraat 28 Knesselare Oost-Vlaanderen 9910",
    "addr:housenumber":"28",
    "addr:postcode":"9910",
    "addr:street":"Geuzestraat;Oost-Vlaanderen",
    "iso:country":"BE",
    "sg:address":"Geuzestraat 28",
    "sg:city":"Knesselare",
    "sg:classifiers":[
        {
            "category":"Real Estate",
            "subcategory":"Developer",
            "type":"Services"
        }
    ],
    "sg:phone":"+32 9 374 27 91",
    "sg:postcode":"9910",
    "sg:province":"Oost-Vlaanderen",
    "sg:tags":[
        "project"
    ],
    "wof:name":"Immesoete P",
    "wof:placetype":"venue"
},
  "geometry": {"coordinates":[3.4109840393,51.1510047913],"type":"Point"}
}