{
  "type": "Feature",
  "properties": {
    "iso:country":"BE",
    "sg:address":"Bilzerstraat 27",
    "sg:city":"Hoeselt",
    "sg:orig_category":"Eleveurs de bovins. Eleveurs and marchands de porcs",
    "sg:phone":"+32 89 41 16 78",
    "sg:postcode":"3730",
    "sg:province":"Limburg",
    "wof:name":"Jozef Bollen",
    "wof:placetype":"venue"
},
  "geometry": {"coordinates":[5.4885220528,50.8684387207],"type":"Point"}
}