{
  "type": "Feature",
  "properties": {
    "addr:full":"Rue De L'auflette 196 Mons (cuesmes) Hainaut 7033",
    "addr:housenumber":"196",
    "addr:postcode":"7033",
    "addr:street":"Rue De L'Auflette",
    "iso:country":"BE",
    "sg:address":"Rue De L'auflette 196",
    "sg:city":"Mons (cuesmes)",
    "sg:classifiers":[
        {
            "category":"Building & Trades",
            "subcategory":"Pest Control",
            "type":"Services"
        }
    ],
    "sg:phone":"+32 475 49 19 28",
    "sg:postcode":"7033",
    "sg:province":"Hainaut",
    "sg:tags":[
        "painting",
        "contractor"
    ],
    "wof:name":"Dan & Dan Sprl",
    "wof:placetype":"venue"
},
  "geometry": {"coordinates":[3.9070448875,50.4437332153],"type":"Point"}
}