{
  "type": "Feature",
  "properties": {
    "addr:full":"Centraleweg 14 Nijlen Antwerpen 2560",
    "addr:housenumber":"14",
    "addr:postcode":"2560",
    "addr:street":"Centraleweg",
    "iso:country":"BE",
    "sg:address":"Centraleweg 14",
    "sg:city":"Nijlen",
    "sg:orig_category":"Editeurs de revues and p\u00e9riodiques. Editeurs de journaux",
    "sg:phone":"+32 3 481 89 58",
    "sg:postcode":"2560",
    "sg:province":"Antwerpen",
    "wof:name":"Uitgeverij Kontakt '96",
    "wof:placetype":"venue"
},
  "geometry": {"coordinates":[4.7038030624,51.1656951904],"type":"Point"}
}