{
  "type": "Feature",
  "properties": {
    "iso:country":"BE",
    "sg:address":"Donderberg 27",
    "sg:city":"Brussel/bruxelles",
    "sg:orig_category":"M\u00e9decins and sp\u00e9cialistes",
    "sg:phone":"+32 2 268 08 68",
    "sg:postcode":"1120",
    "sg:province":"Bruxelles-Capitale",
    "wof:name":"Michel Van Hassel",
    "wof:placetype":"venue"
},
  "geometry": {"coordinates":[4.3758602142,50.8955116272],"type":"Point"}
}