{
  "type": "Feature",
  "properties": {
    "addr:full":"Lindelei 163 Hemiksem Antwerpen 2620",
    "addr:housenumber":"163",
    "addr:postcode":"2620",
    "addr:street":"Lindelei",
    "iso:country":"BE",
    "sg:address":"Lindelei 163",
    "sg:city":"Hemiksem",
    "sg:classifiers":[
        {
            "category":"Cafe",
            "type":"Food & Drink"
        }
    ],
    "sg:phone":"+32 3 887 56 59",
    "sg:postcode":"2620",
    "sg:province":"Antwerpen",
    "sg:tags":[
        "caf\u00e9s"
    ],
    "wof:name":"Caf\u00c9 't Wit Peerdje",
    "wof:placetype":"venue"
},
  "geometry": {"coordinates":[4.3434720039,51.1463127136],"type":"Point"}
}