{
  "type": "Feature",
  "properties": {
    "iso:country":"BE",
    "sg:address":"Emile Vanderveldelaan 47",
    "sg:city":"Niel",
    "sg:classifiers":[
        {
            "category":"Bakery",
            "type":"Food & Drink"
        }
    ],
    "sg:phone":"+32 3 888 07 73",
    "sg:postcode":"2845",
    "sg:province":"Antwerpen",
    "sg:tags":[
        "confectioner",
        "baker"
    ],
    "wof:name":"De Klok",
    "wof:placetype":"venue"
},
  "geometry": {"coordinates":[4.3289890289,51.1065979004],"type":"Point"}
}