{
  "type": "Feature",
  "properties": {
    "iso:country":"BE",
    "sg:address":"Rue Max Tannier 25-27",
    "sg:city":"Heron",
    "sg:orig_category":"Fleurs and plantes. Jardinage. Pisciculture",
    "sg:phone":"+32 85 71 15 42",
    "sg:postcode":"4218",
    "sg:province":"Li\u00e8ge",
    "wof:name":"Les Eaux Du Vieux Manoir",
    "wof:placetype":"venue"
},
  "geometry": {"coordinates":[5.1180567741,50.5211601257],"type":"Point"}
}