{
  "type": "Feature",
  "properties": {
    "addr:full":"Ohiostraat 192 Oudenaarde Oost-Vlaanderen 9700",
    "addr:housenumber":"192",
    "addr:postcode":"9700",
    "addr:street":"Ohiostraat",
    "iso:country":"BE",
    "sg:address":"Ohiostraat 192",
    "sg:city":"Oudenaarde",
    "sg:orig_category":"Epiceries",
    "sg:phone":"+32 55 31 24 93",
    "sg:postcode":"9700",
    "sg:province":"Oost-Vlaanderen",
    "wof:name":"Hedwige Vandendaele",
    "wof:placetype":"venue"
},
  "geometry": {"coordinates":[3.6224429607,50.870136261],"type":"Point"}
}