{
  "type": "Feature",
  "properties": {
    "addr:full":"Stationsstraat 100 Waregem West-Vlaanderen 8790",
    "addr:housenumber":"100",
    "addr:postcode":"8790",
    "addr:street":"Stationsstraat",
    "iso:country":"BE",
    "sg:address":"Stationsstraat 100",
    "sg:city":"Waregem",
    "sg:orig_category":"Banques and organismes de cr\u00e9dit",
    "sg:phone":"+32 56 60 43 43",
    "sg:postcode":"8790",
    "sg:province":"West-Vlaanderen",
    "wof:name":"Fortis",
    "wof:placetype":"venue"
},
  "geometry": {"coordinates":[3.4290161133,50.8904876709],"type":"Point"}
}