{
  "type": "Feature",
  "properties": {
    "addr:full":"Grand Trieu 2a Estaimpuis (estaimbourg) Hainaut 7730",
    "addr:housenumber":"2a",
    "addr:postcode":"7730",
    "addr:street":"Trieu",
    "iso:country":"BE",
    "sg:address":"Grand Trieu 2a",
    "sg:city":"Estaimpuis (estaimbourg)",
    "sg:classifiers":[
        {
            "category":"Home & Garden",
            "subcategory":"Hardware",
            "type":"Retail Goods"
        }
    ],
    "sg:phone":"+32 69 55 61 26",
    "sg:postcode":"7730",
    "sg:province":"Hainaut",
    "sg:tags":[
        "-"
    ],
    "wof:name":"Hubaut J-m",
    "wof:placetype":"venue"
},
  "geometry": {"coordinates":[3.3093140125,50.6801719666],"type":"Point"}
}