{
  "type": "Feature",
  "properties": {
    "iso:country":"BE",
    "sg:address":"Grote Dweersstraat 48",
    "sg:city":"Temse",
    "sg:orig_category":"Drukkerijen and copyshops Kantoormateriaal Gh",
    "sg:phone":"+32 3 711 18 20",
    "sg:postcode":"9140",
    "sg:province":"Oost-Vlaanderen",
    "wof:name":"Plottek",
    "wof:placetype":"venue"
},
  "geometry": {"coordinates":[4.2010068893,51.1339836121],"type":"Point"}
}