{
  "type": "Feature",
  "properties": {
    "iso:country":"BE",
    "sg:address":"Meikapelstraat 17",
    "sg:city":"Lendelede",
    "sg:classifiers":[
        {
            "category":"Professional",
            "subcategory":"Art Services",
            "type":"Services"
        }
    ],
    "sg:phone":"+32 51 30 46 93",
    "sg:postcode":"8860",
    "sg:province":"West-Vlaanderen",
    "sg:tags":[
        "photographer"
    ],
    "wof:name":"Vancoillie J",
    "wof:placetype":"venue"
},
  "geometry": {"coordinates":[3.2456350327,50.892490387],"type":"Point"}
}