{
  "type": "Feature",
  "properties": {
    "addr:full":"Oude Gentweg 30 De Pinte Oost-Vlaanderen 9840",
    "addr:housenumber":"30",
    "addr:postcode":"9840",
    "addr:street":"Oude Gentweg",
    "iso:country":"BE",
    "sg:address":"Oude Gentweg 30",
    "sg:city":"De Pinte",
    "sg:classifiers":[
        {
            "category":"Professional",
            "subcategory":"Accounting & Tax Preparation",
            "type":"Services"
        }
    ],
    "sg:phone":"+32 9 282 59 44",
    "sg:postcode":"9840",
    "sg:province":"Oost-Vlaanderen",
    "sg:tags":[
        "accountant"
    ],
    "wof:name":"Pique G",
    "wof:placetype":"venue"
},
  "geometry": {"coordinates":[3.6627678871,51.0019302368],"type":"Point"}
}