{
  "type": "Feature",
  "properties": {
    "addr:full":"D'aspremont Lyndenlaan 1 Lanaken Limburg 3621",
    "addr:housenumber":"1",
    "addr:postcode":"3621",
    "addr:street":"Lyndenlaan",
    "iso:country":"BE",
    "sg:address":"D'aspremont Lyndenlaan 1",
    "sg:city":"Lanaken",
    "sg:orig_category":"Enseignement maternel and primaire",
    "sg:phone":"+32 89 71 54 15",
    "sg:postcode":"3621",
    "sg:province":"Limburg",
    "wof:name":"B.s.g.o. Ter Linden",
    "wof:placetype":"venue"
},
  "geometry": {"coordinates":[5.690969944,50.9229660034],"type":"Point"}
}