{
  "type": "Feature",
  "properties": {
    "addr:full":"Rue Du Calvaire 114 Li\u00c8ge Li\u00e8ge 4000",
    "addr:housenumber":"114",
    "addr:postcode":"4000",
    "addr:street":"Rue Du Calvaire",
    "iso:country":"BE",
    "sg:address":"Rue Du Calvaire 114",
    "sg:city":"Li\u00c8ge",
    "sg:orig_category":"Sportclubs",
    "sg:phone":"+32 4 252 01 99",
    "sg:postcode":"4000",
    "sg:province":"Li\u00e8ge",
    "wof:name":"V.c. Rocourt",
    "wof:placetype":"venue"
},
  "geometry": {"coordinates":[5.5509471893,50.6385612488],"type":"Point"}
}