{
  "type": "Feature",
  "properties": {
    "iso:country":"BE",
    "sg:address":"Rue De Petit-axhe 40",
    "sg:city":"Waremme",
    "sg:orig_category":"Rev\u00eatements pour sols and murs. Peinture",
    "sg:phone":"+32 19 32 22 34",
    "sg:postcode":"4300",
    "sg:province":"Li\u00e8ge",
    "wof:name":"Eric Gastelblum",
    "wof:placetype":"venue"
},
  "geometry": {"coordinates":[5.2334799767,50.6839790344],"type":"Point"}
}