{
  "type": "Feature",
  "properties": {
    "iso:country":"BE",
    "sg:address":"Waterloose Steenweg 1512",
    "sg:city":"Ukkel/uccle",
    "sg:orig_category":"DIVERSE RECREATIEVE ACTIVITEITEN Sportterreinen and installaties behalve sportcentra",
    "sg:phone":"+32 2 374 84 49",
    "sg:postcode":"1180",
    "sg:province":"Bruxelles-Capitale",
    "wof:name":"Pom Pom Poney",
    "wof:placetype":"venue"
},
  "geometry": {"coordinates":[4.3828048706,50.7666282654],"type":"Point"}
}