{
  "type": "Feature",
  "properties": {
    "iso:country":"BE",
    "sg:address":"Rue De La Maison-forte 7",
    "sg:city":"Bastogne",
    "sg:classifiers":[
        {
            "category":"Cafe",
            "type":"Food & Drink"
        }
    ],
    "sg:phone":"+32 61 21 73 27",
    "sg:postcode":"6600",
    "sg:province":"Luxembourg",
    "sg:tags":[
        "caf\u00e9s"
    ],
    "wof:name":"Caf\u00c9 Le Crossman",
    "wof:placetype":"venue"
},
  "geometry": {"coordinates":[5.7188339233,50.0075836182],"type":"Point"}
}