{
  "type": "Feature",
  "properties": {
    "addr:full":"Gottemstraat 4 Dentergem West-Vlaanderen 8720",
    "addr:housenumber":"4",
    "addr:postcode":"8720",
    "addr:street":"Gottemstraat",
    "iso:country":"BE",
    "sg:address":"Gottemstraat 4",
    "sg:city":"Dentergem",
    "sg:orig_category":"Slagers",
    "sg:phone":"+32 51 63 63 19",
    "sg:postcode":"8720",
    "sg:province":"West-Vlaanderen",
    "wof:name":"Nico De Witte",
    "wof:placetype":"venue"
},
  "geometry": {"coordinates":[3.4224600792,50.9646682739],"type":"Point"}
}