{
  "type": "Feature",
  "properties": {
    "addr:full":"Av. Gouvern. E. Cornez 2b23 Mons Hainaut 7000",
    "addr:housenumber":"2b23",
    "addr:postcode":"7000",
    "addr:street":"Av. Gouvern. E. Cornez;Hainaut",
    "iso:country":"BE",
    "sg:address":"Av. Gouvern. E. Cornez 2b23",
    "sg:city":"Mons",
    "sg:orig_category":"Artsen and specialisten",
    "sg:phone":"+32 65 34 97 07",
    "sg:postcode":"7000",
    "sg:province":"Hainaut",
    "wof:name":"Yves Streulens",
    "wof:placetype":"venue"
},
  "geometry": {"coordinates":[3.9627249241,50.4453430176],"type":"Point"}
}