{
  "type": "Feature",
  "properties": {
    "addr:full":"Industriepark De Bruwaan 45 Oudenaarde Oost-Vlaanderen 9700",
    "addr:housenumber":"45",
    "addr:postcode":"9700",
    "addr:street":"Industriepark;Bruwaan",
    "iso:country":"BE",
    "sg:address":"Industriepark De Bruwaan 45",
    "sg:city":"Oudenaarde",
    "sg:orig_category":"Clothing accessories Fabrics Printing Textiles and Clothing",
    "sg:phone":"+32 55 31 13 45",
    "sg:postcode":"9700",
    "sg:province":"Oost-Vlaanderen",
    "wof:name":"Aarova",
    "wof:placetype":"venue"
},
  "geometry": {"coordinates":[3.6044800282,50.869430542],"type":"Point"}
}