{
  "type": "Feature",
  "properties": {
    "iso:country":"BE",
    "sg:address":"Reedijk 56",
    "sg:city":"Merchtem",
    "sg:classifiers":[
        {
            "category":"Personal",
            "subcategory":"Beauty Salon",
            "type":"Services"
        }
    ],
    "sg:phone":"+32 495 47 58 15",
    "sg:postcode":"1785",
    "sg:province":"Vlaams-Brabant",
    "wof:name":"Nail's Factory",
    "wof:placetype":"venue"
},
  "geometry": {"coordinates":[4.2328429222,50.9593734741],"type":"Point"}
}