{
  "type": "Feature",
  "properties": {
    "addr:full":"Rue De Mianoye 33 Yvoir Namur 5530",
    "addr:housenumber":"33",
    "addr:postcode":"5530",
    "addr:street":"Rue De Mianoye",
    "iso:country":"BE",
    "sg:address":"Rue De Mianoye 33",
    "sg:city":"Yvoir",
    "sg:classifiers":[
        {
            "category":"Social Services",
            "subcategory":"Job Training",
            "type":"Services"
        }
    ],
    "sg:phone":"+32 83 69 91 63",
    "sg:postcode":"5530",
    "sg:province":"Namur",
    "sg:tags":[
        "de",
        "terrain",
        "camping"
    ],
    "wof:name":"Camping Pommier Rustique",
    "wof:placetype":"venue"
},
  "geometry": {"coordinates":[4.9860610962,50.338809967],"type":"Point"}
}