{
  "type": "Feature",
  "properties": {
    "iso:country":"BE",
    "sg:address":"Avenue Emile Van Becelaere 50",
    "sg:city":"Bruxelles (watermael-boitsfort)",
    "sg:classifiers":[
        {
            "category":"Communications",
            "subcategory":"Film & Video Production",
            "type":"Services"
        }
    ],
    "sg:phone":"+32 2 672 41 99",
    "sg:postcode":"1170",
    "sg:province":"Bruxelles-Capitale",
    "sg:tags":[
        "movie",
        "maker"
    ],
    "wof:name":"A. Punto Sprl",
    "wof:placetype":"venue"
},
  "geometry": {"coordinates":[4.4046978951,50.8007545471],"type":"Point"}
}