{
  "type": "Feature",
  "properties": {
    "iso:country":"BE",
    "sg:address":"Heiveld 13",
    "sg:city":"Aartselaar",
    "sg:classifiers":[
        {
            "category":"Arena",
            "subcategory":"Sports Club",
            "type":"Entertainment"
        }
    ],
    "sg:phone":"+32 3 887 04 36",
    "sg:postcode":"2630",
    "sg:province":"Antwerpen",
    "sg:tags":[
        "de"
    ],
    "wof:name":"Kaisho",
    "wof:placetype":"venue"
},
  "geometry": {"coordinates":[4.3888049126,51.1425056458],"type":"Point"}
}