{
  "type": "Feature",
  "properties": {
    "addr:full":"Rue Des Teinturiers 10-12 Bruxelles Bruxelles-Capitale 1000",
    "addr:postcode":"10-12;1000",
    "addr:street":"Rue Des Teinturiers",
    "iso:country":"BE",
    "sg:address":"Rue Des Teinturiers 10-12",
    "sg:city":"Bruxelles",
    "sg:classifiers":[
        {
            "category":"Shopping",
            "subcategory":"Shoes",
            "type":"Retail Goods"
        }
    ],
    "sg:phone":"+32 2 513 34 99",
    "sg:postcode":"1000",
    "sg:province":"Bruxelles-Capitale",
    "sg:tags":[
        "slipper",
        "-"
    ],
    "wof:name":"Paradis De La Babouche",
    "wof:placetype":"venue"
},
  "geometry": {"coordinates":[4.3484311104,50.8463630676],"type":"Point"}
}