{
  "type": "Feature",
  "properties": {
    "iso:country":"BE",
    "sg:address":"Avenue Du Douaire 68",
    "sg:city":"Ottignies-louvain-la-neuve (ottignies)",
    "sg:classifiers":[
        {
            "category":"Personal",
            "subcategory":"Beauty Salon",
            "type":"Services"
        }
    ],
    "sg:phone":"+32 10 43 93 00",
    "sg:postcode":"1340",
    "sg:province":"Brabant Wallon",
    "wof:name":"Temps Pour Soi (au)",
    "wof:placetype":"venue"
},
  "geometry": {"coordinates":[4.5672249794,50.6636390686],"type":"Point"}
}