{
  "type": "Feature",
  "properties": {
    "iso:country":"BE",
    "sg:address":"Rue Du Vent Val 35b",
    "sg:city":"Le Roeulx (ville-sur-haine)",
    "sg:classifiers":[
        {
            "category":"Health Services",
            "subcategory":"Nursing And Care Facility",
            "type":"Services"
        }
    ],
    "sg:phone":"+32 64 67 77 34",
    "sg:postcode":"7070",
    "sg:province":"Hainaut",
    "sg:tags":[
        "home"
    ],
    "wof:name":"Debouver J-p",
    "wof:placetype":"venue"
},
  "geometry": {"coordinates":[4.0637450218,50.5008468628],"type":"Point"}
}