{
  "type": "Feature",
  "properties": {
    "addr:full":"Raymond Pelgrims De Bigardlaan 101 Dilbeek (groot - Bijgaarden) Vlaams-Brabant 1702",
    "addr:housenumber":"101;1702",
    "addr:street":"Bigardlaan;Groot Bijgaarden Vlaams-Brabant",
    "iso:country":"BE",
    "sg:address":"Raymond Pelgrims De Bigardlaan 101",
    "sg:city":"Dilbeek (groot - Bijgaarden)",
    "sg:classifiers":[
        {
            "category":"Freight",
            "type":"Transportation"
        }
    ],
    "sg:phone":"+32 2 463 51 51",
    "sg:postcode":"1702",
    "sg:province":"Vlaams-Brabant",
    "sg:tags":[
        "-",
        "transport"
    ],
    "wof:name":"Benelux Trans Nv",
    "wof:placetype":"venue"
},
  "geometry": {"coordinates":[4.2628970146,50.8712081909],"type":"Point"}
}