{
  "type": "Feature",
  "properties": {
    "addr:full":"Rue D'anderlues 22 Thuin Hainaut 6530",
    "addr:housenumber":"22",
    "addr:postcode":"6530",
    "addr:street":"Rue D'Anderlues",
    "iso:country":"BE",
    "sg:address":"Rue D'anderlues 22",
    "sg:city":"Thuin",
    "sg:classifiers":[
        {
            "category":"Building & Trades",
            "subcategory":"Plumbing",
            "type":"Services"
        }
    ],
    "sg:phone":"+32 71 59 00 26",
    "sg:postcode":"6530",
    "sg:province":"Hainaut",
    "sg:tags":[
        "contractor"
    ],
    "wof:name":"Piraux-vanadenhove Sprl",
    "wof:placetype":"venue"
},
  "geometry": {"coordinates":[4.2886519432,50.3444824219],"type":"Point"}
}