{
  "type": "Feature",
  "properties": {
    "iso:country":"BE",
    "sg:address":"Deinsesteenweg 52",
    "sg:city":"Kruishoutem",
    "sg:orig_category":"Rundveehouders",
    "sg:phone":"+32 9 383 50 52",
    "sg:postcode":"9770",
    "sg:province":"Oost-Vlaanderen",
    "wof:name":"Amede Claus",
    "wof:placetype":"venue"
},
  "geometry": {"coordinates":[3.5304811001,50.9188690186],"type":"Point"}
}