{
  "type": "Feature",
  "properties": {
    "iso:country":"BE",
    "sg:address":"Brusselstraat 33",
    "sg:city":"Edingen/enghien",
    "sg:orig_category":"Maatkleding Fab",
    "sg:phone":"+32 2 395 68 75",
    "sg:postcode":"7850",
    "sg:province":"Hainaut",
    "wof:name":"Jacques Bourleau",
    "wof:placetype":"venue"
},
  "geometry": {"coordinates":[4.0405921936,50.6939697266],"type":"Point"}
}