{
  "type": "Feature",
  "properties": {
    "addr:full":"Place Emile-de-lalieux 20 Nivelles Brabant Wallon 1400",
    "addr:housenumber":"20",
    "addr:postcode":"1400",
    "addr:street":"Place Emile-De-Lalieux",
    "iso:country":"BE",
    "sg:address":"Place Emile-de-lalieux 20",
    "sg:city":"Nivelles",
    "sg:orig_category":"Blanchisseries and teintureries",
    "sg:phone":"+32 67 21 88 38",
    "sg:postcode":"1400",
    "sg:province":"Brabant Wallon",
    "wof:name":"Nettoyage \u00c0 Sec La Comete",
    "wof:placetype":"venue"
},
  "geometry": {"coordinates":[4.328192234,50.5981292725],"type":"Point"}
}