{
  "type": "Feature",
  "properties": {
    "iso:country":"BE",
    "sg:address":"Place D'ollignies 2",
    "sg:city":"Lessines",
    "sg:orig_category":"Kansspelen",
    "sg:phone":"+32 68 33 94 58",
    "sg:postcode":"7866",
    "sg:province":"Hainaut",
    "wof:name":"Angence Hippique Dumoulin",
    "wof:placetype":"venue"
},
  "geometry": {"coordinates":[3.8862140179,50.6955604553],"type":"Point"}
}