{
  "type": "Feature",
  "properties": {
    "addr:full":"Rue De L\u00b4ancienne Gare Libramont Luxembourg 6800",
    "addr:postcode":"6800",
    "addr:street":"Rue De L\u00b4Ancienne Gare",
    "iso:country":"BE",
    "sg:address":"Rue De L\u00b4ancienne Gare",
    "sg:city":"Libramont",
    "sg:classifiers":[
        {
            "category":"Bars & Pubs",
            "subcategory":"Oxygen Bar",
            "type":"Food & Drink"
        }
    ],
    "sg:phone":"+32 61 22 41 01",
    "sg:postcode":"6800",
    "sg:province":"Luxembourg",
    "sg:tags":[
        "animaux",
        "gr",
        "aliment",
        "canin",
        "royal",
        "pour",
        "c\u00e9r\u00e9ales"
    ],
    "wof:name":"Aliments Guillaume",
    "wof:placetype":"venue"
},
  "geometry": {"coordinates":[5.3777279854,49.9189224243],"type":"Point"}
}