{
  "type": "Feature",
  "properties": {
    "addr:full":"Coupure 916 Gent Oost-Vlaanderen 9000",
    "addr:housenumber":"916",
    "addr:postcode":"9000",
    "addr:street":"Coupure;Oost-Vlaanderen",
    "iso:country":"BE",
    "sg:address":"Coupure 916",
    "sg:city":"Gent",
    "sg:classifiers":[
        {
            "category":"Health Services",
            "subcategory":"Dentist",
            "type":"Services"
        }
    ],
    "sg:phone":"+32 9 233 54 87",
    "sg:postcode":"9000",
    "sg:province":"Oost-Vlaanderen",
    "wof:name":"Baetens Philippe",
    "wof:placetype":"venue"
},
  "geometry": {"coordinates":[3.7091939449,51.0560646057],"type":"Point"}
}