{
  "type": "Feature",
  "properties": {
    "iso:country":"BE",
    "sg:address":"Veeweidestraat 4",
    "sg:city":"Anderlecht",
    "sg:orig_category":"Slagers",
    "sg:phone":"+32 2 524 19 22",
    "sg:postcode":"1070",
    "sg:province":"Bruxelles-Capitale",
    "wof:name":"Declerck-cloetens",
    "wof:placetype":"venue"
},
  "geometry": {"coordinates":[4.3021249771,50.8209533691],"type":"Point"}
}