{
  "type": "Feature",
  "properties": {
    "addr:full":"Dr\u00e8ve Du Ch\u00e2teau 18-2 Linkebeek Vlaams-Brabant 1630",
    "addr:housenumber":"18-2",
    "addr:postcode":"1630",
    "addr:street":"Dre\u0300Ve Du Cha\u0302Teau",
    "iso:country":"BE",
    "sg:address":"Dr\u00e8ve Du Ch\u00e2teau 18-2",
    "sg:city":"Linkebeek",
    "sg:classifiers":[
        {
            "category":"Communications",
            "subcategory":"Film & Video Production",
            "type":"Services"
        }
    ],
    "sg:phone":"+32 2 345 45 41",
    "sg:postcode":"1630",
    "sg:province":"Vlaams-Brabant",
    "sg:tags":[
        "sound",
        "recording",
        "studio"
    ],
    "wof:name":"Polfliet D",
    "wof:placetype":"venue"
},
  "geometry": {"coordinates":[4.336687088,50.7704734802],"type":"Point"}
}