{
  "type": "Feature",
  "properties": {
    "iso:country":"BE",
    "sg:address":"Montjoielaan 228",
    "sg:city":"Ukkel/uccle",
    "sg:orig_category":"Postkantoren Verzekeringsmakelaars and experts",
    "sg:phone":"+32 2 344 05 13",
    "sg:postcode":"1180",
    "sg:province":"Bruxelles-Capitale",
    "wof:name":"De Post",
    "wof:placetype":"venue"
},
  "geometry": {"coordinates":[4.3544588089,50.8111877441],"type":"Point"}
}