{
  "type": "Feature",
  "properties": {
    "addr:full":"Diksmuidsesteenweg 274 Box 6 Roeselare West-Vlaanderen 8800",
    "addr:housenumber":"274;6",
    "addr:postcode":"8800",
    "addr:street":"Diksmuidsesteenweg;Box",
    "iso:country":"BE",
    "sg:address":"Diksmuidsesteenweg 274 Box 6",
    "sg:city":"Roeselare",
    "sg:classifiers":[
        {
            "category":"Health Services",
            "subcategory":"Nursing And Care Facility",
            "type":"Services"
        }
    ],
    "sg:phone":"+32 476 61 09 81",
    "sg:postcode":"8800",
    "sg:province":"West-Vlaanderen",
    "sg:tags":[
        "home"
    ],
    "wof:name":"Deceuninck N",
    "wof:placetype":"venue"
},
  "geometry": {"coordinates":[3.1097180843,50.9480133057],"type":"Point"}
}