{
  "type": "Feature",
  "properties": {
    "addr:full":"Rue Du G\u00c9n\u00c9ral De Gaulle 8 Courcelles Hainaut 6180",
    "addr:housenumber":"8",
    "addr:postcode":"6180",
    "addr:street":"Rue Du Ge\u0301Ne\u0301Ral De Gaulle",
    "iso:country":"BE",
    "sg:address":"Rue Du G\u00c9n\u00c9ral De Gaulle 8",
    "sg:city":"Courcelles",
    "sg:classifiers":[
        {
            "category":"Cafe",
            "type":"Food & Drink"
        }
    ],
    "sg:phone":"+32 71 45 12 25",
    "sg:postcode":"6180",
    "sg:province":"Hainaut",
    "sg:tags":[
        "caf\u00e9s"
    ],
    "wof:name":"Caf\u00c9 L'entonoir",
    "wof:placetype":"venue"
},
  "geometry": {"coordinates":[4.3800258636,50.4591026306],"type":"Point"}
}