{
  "type": "Feature",
  "properties": {
    "addr:full":"Leo Baekelandstraat 7 Kapellen (mariaburg) Antwerpen 2950",
    "addr:housenumber":"7",
    "addr:postcode":"2950",
    "addr:street":"Leo Baekelandstraat",
    "iso:country":"BE",
    "sg:address":"Leo Baekelandstraat 7",
    "sg:city":"Kapellen (mariaburg)",
    "sg:classifiers":[
        {
            "category":"Home & Garden",
            "subcategory":"Carpets & Floor Coverings",
            "type":"Retail Goods"
        }
    ],
    "sg:phone":"+32 3 660 14 14",
    "sg:postcode":"2950",
    "sg:province":"Antwerpen",
    "sg:tags":[
        "heating"
    ],
    "wof:name":"Sanitair De Winter",
    "wof:placetype":"venue"
},
  "geometry": {"coordinates":[4.4349379539,51.2986450195],"type":"Point"}
}