{
  "type": "Feature",
  "properties": {
    "iso:country":"BE",
    "sg:address":"Chauss\u00c9e De Tongres 329",
    "sg:city":"Li\u00c8ge",
    "sg:classifiers":[
        {
            "category":"Personal",
            "subcategory":"Beauty Salon",
            "type":"Services"
        }
    ],
    "sg:phone":"+32 4 246 35 70",
    "sg:postcode":"4000",
    "sg:province":"Li\u00e8ge",
    "sg:tags":[
        "de",
        "coiffure"
    ],
    "wof:name":"Coiffure Miceli J. & Fils",
    "wof:placetype":"venue"
},
  "geometry": {"coordinates":[5.547290802,50.6735458374],"type":"Point"}
}