{
  "type": "Feature",
  "properties": {
    "addr:full":"Rue Des D\u00c9port\u00c9s 73 Verviers Li\u00e8ge 4800",
    "addr:housenumber":"73",
    "addr:postcode":"4800",
    "addr:street":"Rue Des De\u0301Porte\u0301S",
    "iso:country":"BE",
    "sg:address":"Rue Des D\u00c9port\u00c9s 73",
    "sg:city":"Verviers",
    "sg:orig_category":"Huishoudapparaten, televisies and radio's",
    "sg:phone":"+32 87 22 42 16",
    "sg:postcode":"4800",
    "sg:province":"Li\u00e8ge",
    "wof:name":"Louis Nullens",
    "wof:placetype":"venue"
},
  "geometry": {"coordinates":[5.8516011238,50.5837135315],"type":"Point"}
}