{
  "type": "Feature",
  "properties": {
    "iso:country":"BE",
    "sg:address":"Melkerijstraat 1",
    "sg:city":"Berlare",
    "sg:classifiers":[
        {
            "category":"Cafe",
            "type":"Food & Drink"
        }
    ],
    "sg:phone":"+32 52 42 72 59",
    "sg:postcode":"9290",
    "sg:province":"Oost-Vlaanderen",
    "sg:tags":[
        "caf\u00e9s"
    ],
    "wof:name":"Caf\u00c9 't Smisken",
    "wof:placetype":"venue"
},
  "geometry": {"coordinates":[4.0065197945,51.0204391479],"type":"Point"}
}