{
  "type": "Feature",
  "properties": {
    "addr:full":"Rue Burenville 136 Li\u00e8ge 1 Li\u00e8ge 4000",
    "addr:housenumber":"136;1",
    "addr:postcode":"4000",
    "addr:street":"Rue Burenville",
    "iso:country":"BE",
    "sg:address":"Rue Burenville 136",
    "sg:city":"Li\u00e8ge 1",
    "sg:classifiers":[
        {
            "category":"Home & Garden",
            "subcategory":"Home Furnishings",
            "type":"Retail Goods"
        }
    ],
    "sg:phone":"+32 4 226 62 20",
    "sg:postcode":"4000",
    "sg:province":"Li\u00e8ge",
    "sg:tags":[
        "-",
        "furniture"
    ],
    "wof:name":"My-way Trading Sa",
    "wof:placetype":"venue"
},
  "geometry": {"coordinates":[5.5404009819,50.639289856],"type":"Point"}
}