{
  "type": "Feature",
  "properties": {
    "iso:country":"BE",
    "sg:address":"Kaaskerkestraat 56a",
    "sg:city":"Diksmuide",
    "sg:classifiers":[
        {
            "category":"Home & Garden",
            "subcategory":"Household Appliances",
            "type":"Retail Goods"
        }
    ],
    "sg:phone":"+32 51 50 40 37",
    "sg:postcode":"8600",
    "sg:province":"West-Vlaanderen",
    "sg:tags":[
        "repair",
        "mainten",
        "-",
        "electric"
    ],
    "wof:name":"Dellobel D",
    "wof:placetype":"venue"
},
  "geometry": {"coordinates":[2.8271460533,51.0384979248],"type":"Point"}
}