{
  "type": "Feature",
  "properties": {
    "addr:full":"Avenue De La Porall\u00e9e 55 Aywaille (sougn\u00e9-remouchamps) Li\u00e8ge 4920",
    "addr:housenumber":"55",
    "addr:postcode":"4920",
    "addr:street":"Avenue De La Poralle\u0301E;Sougne\u0301-Remouchamps",
    "iso:country":"BE",
    "sg:address":"Avenue De La Porall\u00e9e 55",
    "sg:city":"Aywaille (sougn\u00e9-remouchamps)",
    "sg:classifiers":[
        {
            "category":"Farming",
            "subcategory":"Livestock Farm",
            "type":"Manufacturing & Wholesale Goods"
        }
    ],
    "sg:phone":"+32 4 384 74 66",
    "sg:postcode":"4920",
    "sg:province":"Li\u00e8ge",
    "sg:tags":[
        "breeding"
    ],
    "wof:name":"Gilrex",
    "wof:placetype":"venue"
},
  "geometry": {"coordinates":[5.6782069206,50.4738540649],"type":"Point"}
}