{
  "type": "Feature",
  "properties": {
    "addr:full":"Vlinderstraat 2 Waregem West-Vlaanderen 8792",
    "addr:housenumber":"2",
    "addr:postcode":"8792",
    "addr:street":"Vlinderstraat",
    "iso:country":"BE",
    "sg:address":"Vlinderstraat 2",
    "sg:city":"Waregem",
    "sg:orig_category":"Installatie van houten of kunststof schrijnwerk",
    "sg:phone":"+32 56 72 58 55",
    "sg:postcode":"8792",
    "sg:province":"West-Vlaanderen",
    "wof:name":"Claude Meerschaert",
    "wof:placetype":"venue"
},
  "geometry": {"coordinates":[3.3676218987,50.8861694336],"type":"Point"}
}