{
  "type": "Feature",
  "properties": {
    "iso:country":"BE",
    "sg:address":"Onze-lieve-vrouwlaan 26",
    "sg:city":"Duffel",
    "sg:orig_category":"M\u00e9decins and sp\u00e9cialistes",
    "sg:phone":"+32 15 31 12 55",
    "sg:postcode":"2570",
    "sg:province":"Antwerpen",
    "wof:name":"L. Verhavert",
    "wof:placetype":"venue"
},
  "geometry": {"coordinates":[4.5093531609,51.0932197571],"type":"Point"}
}