{
  "type": "Feature",
  "properties": {
    "addr:full":"Molenstraat 15a Grimbergen (beigem) Vlaams-Brabant 1852",
    "addr:housenumber":"15a",
    "addr:postcode":"1852",
    "addr:street":"Molenstraat",
    "iso:country":"BE",
    "sg:address":"Molenstraat 15a",
    "sg:city":"Grimbergen (beigem)",
    "sg:classifiers":[
        {
            "category":"Bars & Pubs",
            "type":"Food & Drink"
        }
    ],
    "sg:phone":"+32 2 269 13 39",
    "sg:postcode":"1852",
    "sg:province":"Vlaams-Brabant",
    "wof:name":"Duivelshoek",
    "wof:placetype":"venue"
},
  "geometry": {"coordinates":[4.367123127,50.9574432373],"type":"Point"}
}