{
  "type": "Feature",
  "properties": {
    "addr:full":"Boulevard Fr\u00e8re-orban 1a Li\u00e8ge 1 Li\u00e8ge 4000",
    "addr:housenumber":"1a;1",
    "addr:postcode":"4000",
    "addr:street":"Boulevard Fre\u0300Re-Orban",
    "iso:country":"BE",
    "sg:address":"Boulevard Fr\u00e8re-orban 1a",
    "sg:city":"Li\u00e8ge 1",
    "sg:classifiers":[
        {
            "category":"Real Estate",
            "subcategory":"Real Estate Services",
            "type":"Services"
        }
    ],
    "sg:phone":"+32 4 223 38 20",
    "sg:postcode":"4000",
    "sg:province":"Li\u00e8ge",
    "wof:name":"C.i.b.-wallonie",
    "wof:placetype":"venue"
},
  "geometry": {"coordinates":[5.5722818375,50.6358222961],"type":"Point"}
}