{
  "type": "Feature",
  "properties": {
    "iso:country":"BE",
    "sg:address":"Antwerpse Steenweg 91",
    "sg:city":"Lochristi",
    "sg:classifiers":[
        {
            "category":"Manufacturing",
            "subcategory":"Furniture",
            "type":"Manufacturing & Wholesale Goods"
        }
    ],
    "sg:phone":"+32 9 355 65 01",
    "sg:postcode":"9080",
    "sg:province":"Oost-Vlaanderen",
    "sg:tags":[
        "design",
        "-"
    ],
    "wof:name":"Vandella Lochristi",
    "wof:placetype":"venue"
},
  "geometry": {"coordinates":[3.8083980083,51.088394165],"type":"Point"}
}