{
  "type": "Feature",
  "properties": {
    "addr:full":"Stoofstraat 4 Brugge West-Vlaanderen 8000",
    "addr:housenumber":"4",
    "addr:postcode":"8000",
    "addr:street":"Stoofstraat",
    "iso:country":"BE",
    "sg:address":"Stoofstraat 4",
    "sg:city":"Brugge",
    "sg:classifiers":[
        {
            "category":"Food & Beverages",
            "subcategory":"Chocolate",
            "type":"Retail Goods"
        }
    ],
    "sg:phone":"+32 50 34 25 56",
    "sg:postcode":"8000",
    "sg:province":"West-Vlaanderen",
    "sg:tags":[
        "confectionery",
        "-"
    ],
    "wof:name":"Tsjokoreeto",
    "wof:placetype":"venue"
},
  "geometry": {"coordinates":[3.2245569229,51.2034072876],"type":"Point"}
}