{
  "type": "Feature",
  "properties": {
    "iso:country":"BE",
    "sg:address":"Albert I-laan 7",
    "sg:city":"Langemark-poelkapelle (langemark)",
    "sg:classifiers":[
        {
            "category":"Building & Trades",
            "subcategory":"Cleaning & Sanitation",
            "type":"Services"
        }
    ],
    "sg:phone":"+32 57 48 96 89",
    "sg:postcode":"8920",
    "sg:province":"West-Vlaanderen",
    "sg:tags":[
        "fa\u00e7ade",
        "maintenance"
    ],
    "wof:name":"Desodt R",
    "wof:placetype":"venue"
},
  "geometry": {"coordinates":[2.919770956,50.9132423401],"type":"Point"}
}