{
  "type": "Feature",
  "properties": {
    "iso:country":"BE",
    "sg:address":"Rue Dupre 117-123",
    "sg:city":"Bruxelles",
    "sg:classifiers":[
        {
            "category":"Home & Garden",
            "subcategory":"Furniture",
            "type":"Retail Goods"
        }
    ],
    "sg:phone":"+32 2 479 11 17",
    "sg:postcode":"1090",
    "sg:province":"Bruxelles-Capitale",
    "sg:tags":[
        "designer"
    ],
    "wof:name":"Actualine S.a.",
    "wof:placetype":"venue"
},
  "geometry": {"coordinates":[4.3256568909,50.88098526],"type":"Point"}
}