{
  "type": "Feature",
  "properties": {
    "iso:country":"BE",
    "sg:address":"Emile Van Becelaerelaan 27",
    "sg:city":"Watermaal-bosvoorde/watermael-boitsfort",
    "sg:orig_category":"Immobili\u00ebnkantoren",
    "sg:phone":"+32 2 768 26 86",
    "sg:postcode":"1170",
    "sg:province":"Bruxelles-Capitale",
    "wof:name":"T. & C. Real Estate Ltd",
    "wof:placetype":"venue"
},
  "geometry": {"coordinates":[4.4060931206,50.7994728088],"type":"Point"}
}