{
  "type": "Feature",
  "properties": {
    "iso:country":"BE",
    "sg:address":"Edm. De Coussemakerstr. 31",
    "sg:city":"Antwerpen",
    "sg:orig_category":"Artiesten and kunstenaars",
    "sg:phone":"+32 3 219 06 80",
    "sg:postcode":"2050",
    "sg:province":"Antwerpen",
    "wof:name":"Kurt Vergult",
    "wof:placetype":"venue"
},
  "geometry": {"coordinates":[4.3742499352,51.2175788879],"type":"Point"}
}