{
  "type": "Feature",
  "properties": {
    "addr:full":"Alfred Verweeplein 17 Knokke-heist West-Vlaanderen 8300",
    "addr:housenumber":"17",
    "addr:postcode":"8300",
    "addr:street":"Knokke-Heist West-Vlaanderen",
    "iso:country":"BE",
    "sg:address":"Alfred Verweeplein 17",
    "sg:city":"Knokke-heist",
    "sg:orig_category":"V\u00eatements pour b\u00e9b\u00e9s and enfants",
    "sg:phone":"+32 50 60 22 63",
    "sg:postcode":"8300",
    "sg:province":"West-Vlaanderen",
    "wof:name":"Benjamin",
    "wof:placetype":"venue"
},
  "geometry": {"coordinates":[3.2880349159,51.3430671692],"type":"Point"}
}