{
  "type": "Feature",
  "properties": {
    "iso:country":"BE",
    "sg:address":"Handzamestraat 3",
    "sg:city":"Kortemark",
    "sg:classifiers":[
        {
            "category":"Shopping",
            "subcategory":"Clothing, Apparel, & Fashions",
            "type":"Retail Goods"
        }
    ],
    "sg:phone":"+32 51 56 81 79",
    "sg:postcode":"8610",
    "sg:province":"West-Vlaanderen",
    "sg:tags":[
        "-",
        "clothing",
        "child"
    ],
    "wof:name":"Bambilini",
    "wof:placetype":"venue"
},
  "geometry": {"coordinates":[3.0408840179,51.0284767151],"type":"Point"}
}