{
  "type": "Feature",
  "properties": {
    "addr:full":"Pieter Van Den Bemdenlaan 107 Edegem Antwerpen 2650",
    "addr:housenumber":"107",
    "addr:postcode":"2650",
    "addr:street":"Pieter Van Den Bemdenlaan",
    "iso:country":"BE",
    "sg:address":"Pieter Van Den Bemdenlaan 107",
    "sg:city":"Edegem",
    "sg:classifiers":[
        {
            "category":"Manufacturing",
            "subcategory":"Glass & Minerals",
            "type":"Manufacturing & Wholesale Goods"
        }
    ],
    "sg:phone":"+32 3 440 89 87",
    "sg:postcode":"2650",
    "sg:province":"Antwerpen",
    "sg:tags":[
        "precious",
        "stone"
    ],
    "wof:name":"Mineralogische Kring Antwerpen Vzw",
    "wof:placetype":"venue"
},
  "geometry": {"coordinates":[4.4175901413,51.1618804932],"type":"Point"}
}