{
  "type": "Feature",
  "properties": {
    "iso:country":"BE",
    "sg:address":"Budastraat 30",
    "sg:city":"Kortrijk",
    "sg:classifiers":[
        {
            "category":"Health Services",
            "subcategory":"Nursing And Care Facility",
            "type":"Services"
        }
    ],
    "sg:phone":"+32 56 20 10 63",
    "sg:postcode":"8500",
    "sg:province":"West-Vlaanderen",
    "sg:tags":[
        "home",
        "rest"
    ],
    "wof:name":"Woon En Zorg H. Hart Vzw",
    "wof:placetype":"venue"
},
  "geometry": {"coordinates":[3.2634210587,50.8306541443],"type":"Point"}
}