{
  "type": "Feature",
  "properties": {
    "addr:full":"Rue Des Mimosas 39 Bruxelles (schaerbeek) Bruxelles-Capitale 1030",
    "addr:housenumber":"39",
    "addr:postcode":"1030",
    "addr:street":"Rue Des Mimosas",
    "iso:country":"BE",
    "sg:address":"Rue Des Mimosas 39",
    "sg:city":"Bruxelles (schaerbeek)",
    "sg:classifiers":[
        {
            "category":"Professional",
            "subcategory":"Art Services",
            "type":"Services"
        }
    ],
    "sg:phone":"+32 2 241 11 06",
    "sg:postcode":"1030",
    "sg:province":"Bruxelles-Capitale",
    "sg:tags":[
        "photographer"
    ],
    "wof:name":"Carr\u00e9 P",
    "wof:placetype":"venue"
},
  "geometry": {"coordinates":[4.3874559402,50.8643379211],"type":"Point"}
}