{
  "type": "Feature",
  "properties": {
    "iso:country":"BE",
    "sg:address":"Rue Saint-martin 50",
    "sg:city":"Namur",
    "sg:orig_category":"Artistes ind\u00e9pendants",
    "sg:phone":"+32 81 22 30 44",
    "sg:postcode":"5000",
    "sg:province":"Namur",
    "wof:name":"Louis Londot",
    "wof:placetype":"venue"
},
  "geometry": {"coordinates":[4.8604249954,50.454875946],"type":"Point"}
}