{
  "type": "Feature",
  "properties": {
    "iso:country":"BE",
    "sg:address":"Les Rouges Eaux 8",
    "sg:city":"Herbeumont",
    "sg:orig_category":"Pensions de famille",
    "sg:phone":"+32 61 41 16 46",
    "sg:postcode":"6887",
    "sg:province":"Luxembourg",
    "wof:name":"Englebert-zondacq",
    "wof:placetype":"venue"
},
  "geometry": {"coordinates":[5.3271870613,49.8223228455],"type":"Point"}
}