{
  "type": "Feature",
  "properties": {
    "addr:full":"Rue Des H\u00e9ros 48 Loncin Li\u00e8ge 4431",
    "addr:housenumber":"48",
    "addr:postcode":"4431",
    "addr:street":"Rue Des He\u0301Ros",
    "iso:country":"BE",
    "sg:address":"Rue Des H\u00e9ros 48",
    "sg:city":"Loncin",
    "sg:classifiers":[
        {
            "category":"Manufacturing",
            "subcategory":"Glass & Minerals",
            "type":"Manufacturing & Wholesale Goods"
        }
    ],
    "sg:phone":"+32 4 263 75 38",
    "sg:postcode":"4431",
    "sg:province":"Li\u00e8ge",
    "sg:tags":[
        "building",
        "material"
    ],
    "wof:name":"Dhr Philippe Tomson",
    "wof:placetype":"venue"
},
  "geometry": {"coordinates":[5.504119873,50.6656188965],"type":"Point"}
}