{
  "type": "Feature",
  "properties": {
    "iso:country":"BE",
    "sg:address":"Rue Jan Van Ruusbroeck 81",
    "sg:city":"Bruxelles (evere)",
    "sg:classifiers":[
        {
            "category":"Building & Trades",
            "subcategory":"Pest Control",
            "type":"Services"
        }
    ],
    "sg:phone":"+32 2 215 86 52",
    "sg:postcode":"1140",
    "sg:province":"Bruxelles-Capitale",
    "sg:tags":[
        "painting",
        "contractor"
    ],
    "wof:name":"Brusselman Jacques",
    "wof:placetype":"venue"
},
  "geometry": {"coordinates":[4.4024448395,50.870464325],"type":"Point"}
}