{
  "type": "Feature",
  "properties": {
    "addr:full":"Fabriekstraat 99 Bocholt Limburg 3950",
    "addr:housenumber":"99",
    "addr:postcode":"3950",
    "addr:street":"Fabriekstraat",
    "iso:country":"BE",
    "sg:address":"Fabriekstraat 99",
    "sg:city":"Bocholt",
    "sg:orig_category":"Trailers, Special-Purpose",
    "sg:phone":"+32 11 44 61 14",
    "sg:postcode":"3950",
    "sg:province":"Limburg",
    "wof:name":"Helpo Aanhangwagens Gewone Comm. Venn.",
    "wof:placetype":"venue"
},
  "geometry": {"coordinates":[5.5230622292,51.1949195862],"type":"Point"}
}