{
  "type": "Feature",
  "properties": {
    "iso:country":"BE",
    "sg:address":"Avenue Androm\u00c8de 23b16",
    "sg:city":"Sint-lambrechts-woluwe/woluwe-saint-lambert",
    "sg:orig_category":"Traitements param\u00e9dicaux",
    "sg:phone":"+32 2 762 35 20",
    "sg:postcode":"1200",
    "sg:province":"Bruxelles-Capitale",
    "wof:name":"Hernalsteen",
    "wof:placetype":"venue"
},
  "geometry": {"coordinates":[4.4252758026,50.8531074524],"type":"Point"}
}