{
  "type": "Feature",
  "properties": {
    "iso:country":"BE",
    "sg:address":"Rue Carli 1",
    "sg:city":"Evere/evere",
    "sg:orig_category":"Librairies",
    "sg:phone":"+32 2 240 92 00",
    "sg:postcode":"1140",
    "sg:province":"Bruxelles-Capitale",
    "wof:name":"Artis Historia",
    "wof:placetype":"venue"
},
  "geometry": {"coordinates":[4.392411232,50.8793334961],"type":"Point"}
}