{
  "type": "Feature",
  "properties": {
    "iso:country":"BE",
    "sg:address":"Loofblommestraat 67",
    "sg:city":"Gent (sint-denijs-westrem - Afsnee)",
    "sg:classifiers":[
        {
            "category":"Real Estate",
            "subcategory":"Surveying",
            "type":"Services"
        }
    ],
    "sg:phone":"+32 9 245 52 69",
    "sg:postcode":"9051",
    "sg:province":"Oost-Vlaanderen",
    "sg:tags":[
        "lettering",
        "letter"
    ],
    "wof:name":"Beautiful",
    "wof:placetype":"venue"
},
  "geometry": {"coordinates":[3.6687800884,51.0224609375],"type":"Point"}
}