{
  "type": "Feature",
  "properties": {
    "addr:full":"Beselarestraat 257 Zonnebeke (beselare) West-Vlaanderen 8980",
    "addr:housenumber":"257",
    "addr:postcode":"8980",
    "addr:street":"Beselarestraat",
    "iso:country":"BE",
    "sg:address":"Beselarestraat 257",
    "sg:city":"Zonnebeke (beselare)",
    "sg:classifiers":[
        {
            "category":"Bakery",
            "type":"Food & Drink"
        }
    ],
    "sg:phone":"+32 57 46 65 61",
    "sg:postcode":"8980",
    "sg:province":"West-Vlaanderen",
    "sg:tags":[
        "confectioner",
        "baker"
    ],
    "wof:name":"Sioen R",
    "wof:placetype":"venue"
},
  "geometry": {"coordinates":[3.0097019672,50.8606758118],"type":"Point"}
}