{
  "type": "Feature",
  "properties": {
    "iso:country":"BE",
    "sg:address":"Hayenhoek 121",
    "sg:city":"Neerpelt",
    "sg:classifiers":[
        {
            "category":"Bakery",
            "type":"Food & Drink"
        }
    ],
    "sg:phone":"+32 11 64 04 04",
    "sg:postcode":"3910",
    "sg:province":"Limburg",
    "sg:tags":[
        "confectioner",
        "baker"
    ],
    "wof:name":"De Vaan R Pellens",
    "wof:placetype":"venue"
},
  "geometry": {"coordinates":[5.437871933,51.244846344],"type":"Point"}
}