{
  "type": "Feature",
  "properties": {
    "iso:country":"BE",
    "sg:address":"Gal. Carmes",
    "sg:city":"Wavre",
    "sg:orig_category":"Verplichte sociale verzekeringen Verzekeringsmakelaars and experts",
    "sg:phone":"+32 10 22 92 89",
    "sg:postcode":"1300",
    "sg:province":"Brabant Wallon",
    "wof:name":"Securex",
    "wof:placetype":"venue"
},
  "geometry": {"coordinates":[4.6076688766,50.7151184082],"type":"Point"}
}