{
  "type": "Feature",
  "properties": {
    "iso:country":"BE",
    "sg:address":"Rue Stappers 13",
    "sg:city":"Li\u00c8ge",
    "sg:orig_category":"Medische apparatuur, orthopedische artikelen and prothesen Fab",
    "sg:phone":"+32 4 343 71 72",
    "sg:postcode":"4020",
    "sg:province":"Li\u00e8ge",
    "wof:name":"Alain Bronne",
    "wof:placetype":"venue"
},
  "geometry": {"coordinates":[5.5918440819,50.6206054688],"type":"Point"}
}