{
  "type": "Feature",
  "properties": {
    "addr:full":"Gentpoortstraat 13 Brugge West-Vlaanderen 8000",
    "addr:housenumber":"13",
    "addr:postcode":"8000",
    "addr:street":"Gentpoortstraat",
    "iso:country":"BE",
    "sg:address":"Gentpoortstraat 13",
    "sg:city":"Brugge",
    "sg:orig_category":"Newspapers, magazines, periodicals - Distribution",
    "sg:phone":"+32 50 33 29 43",
    "sg:postcode":"8000",
    "sg:province":"West-Vlaanderen",
    "wof:name":"Madeleintje ('t)",
    "wof:placetype":"venue"
},
  "geometry": {"coordinates":[3.2322950363,51.2040481567],"type":"Point"}
}