{
  "type": "Feature",
  "properties": {
    "iso:country":"BE",
    "sg:address":"Bierbeekstraat 93",
    "sg:city":"Bierbeek (korbeek-lo)",
    "sg:classifiers":[
        {
            "category":"Health Services",
            "subcategory":"Doctor",
            "type":"Services"
        }
    ],
    "sg:phone":"+32 16 46 10 04",
    "sg:postcode":"3360",
    "sg:province":"Vlaams-Brabant",
    "sg:tags":[
        "medicinephysicians",
        "surgeon"
    ],
    "wof:name":"Hoet J J",
    "wof:placetype":"venue"
},
  "geometry": {"coordinates":[4.7615442276,50.8573188782],"type":"Point"}
}