{
  "type": "Feature",
  "properties": {
    "iso:country":"BE",
    "sg:address":"Baronielaan 49",
    "sg:city":"Izegem",
    "sg:orig_category":"HUISBRANDOLIE Hout and afgeleiden Gh IJzerwaren, bouw- and verfmaterialen",
    "sg:phone":"+32 51 31 65 01",
    "sg:postcode":"8870",
    "sg:province":"West-Vlaanderen",
    "wof:name":"Desabois",
    "wof:placetype":"venue"
},
  "geometry": {"coordinates":[3.2211680412,50.9104614258],"type":"Point"}
}