{
  "type": "Feature",
  "properties": {
    "iso:country":"BE",
    "sg:address":"Esmoreitlaan 3b",
    "sg:city":"Antwerpen",
    "sg:classifiers":[
        {
            "category":"Professional",
            "subcategory":"Management & Consulting",
            "type":"Services"
        }
    ],
    "sg:phone":"+32 3 219 44 28",
    "sg:postcode":"2050",
    "sg:province":"Antwerpen",
    "sg:tags":[
        "consultant",
        "promotion",
        "-",
        "sale"
    ],
    "wof:name":"Creaprojects",
    "wof:placetype":"venue"
},
  "geometry": {"coordinates":[4.3846740723,51.233253479],"type":"Point"}
}