{
  "type": "Feature",
  "properties": {
    "addr:full":"Avenue Paul Pastur 93 Charleroi (mont-sur-marchienne) Hainaut 6032",
    "addr:housenumber":"93",
    "addr:postcode":"6032",
    "addr:street":"Avenue Paul Pastur",
    "iso:country":"BE",
    "sg:address":"Avenue Paul Pastur 93",
    "sg:city":"Charleroi (mont-sur-marchienne)",
    "sg:classifiers":[
        {
            "category":"Health Services",
            "subcategory":"Dentist",
            "type":"Services"
        }
    ],
    "sg:phone":"+32 71 36 56 70",
    "sg:postcode":"6032",
    "sg:province":"Hainaut",
    "wof:name":"Copp\u00e9e Bernard",
    "wof:placetype":"venue"
},
  "geometry": {"coordinates":[4.4083981514,50.3904953003],"type":"Point"}
}