{
  "type": "Feature",
  "properties": {
    "iso:country":"BE",
    "sg:address":"Rue De Beloeil 65",
    "sg:city":"Saint-ghislain (sirault)",
    "sg:classifiers":[
        {
            "category":"Health Services",
            "subcategory":"Health Practitioner",
            "type":"Services"
        }
    ],
    "sg:phone":"+32 69 84 89 00",
    "sg:postcode":"7332",
    "sg:province":"Hainaut",
    "sg:tags":[
        "physiotherapist"
    ],
    "wof:name":"Pratte Val\u00e9rie",
    "wof:placetype":"venue"
},
  "geometry": {"coordinates":[3.786839962,50.5054969788],"type":"Point"}
}