{
  "type": "Feature",
  "properties": {
    "addr:full":"Rue De Wand 168 Brussel/bruxelles Bruxelles-Capitale 1020",
    "addr:housenumber":"168",
    "addr:postcode":"1020",
    "addr:street":"Rue De Wand;/",
    "iso:country":"BE",
    "sg:address":"Rue De Wand 168",
    "sg:city":"Brussel/bruxelles",
    "sg:orig_category":"Mat\u00e9riaux de construction Gr",
    "sg:phone":"+32 2 262 08 06",
    "sg:postcode":"1020",
    "sg:province":"Bruxelles-Capitale",
    "wof:name":"Fourneau",
    "wof:placetype":"venue"
},
  "geometry": {"coordinates":[4.3603720665,50.9010238647],"type":"Point"}
}