{
  "type": "Feature",
  "properties": {
    "addr:full":"Nieuwe Kerkstraat 27 Kruibeke Oost-Vlaanderen 9150",
    "addr:housenumber":"27",
    "addr:postcode":"9150",
    "addr:street":"Nieuwe Kerkstraat",
    "iso:country":"BE",
    "sg:address":"Nieuwe Kerkstraat 27",
    "sg:city":"Kruibeke",
    "sg:orig_category":"Rev\u00eatements de sols and murs",
    "sg:phone":"+32 3 774 05 68",
    "sg:postcode":"9150",
    "sg:province":"Oost-Vlaanderen",
    "wof:name":"Dirk De Jonghe",
    "wof:placetype":"venue"
},
  "geometry": {"coordinates":[4.3112778664,51.1740150452],"type":"Point"}
}