{
  "type": "Feature",
  "properties": {
    "iso:country":"BE",
    "sg:address":"Kleine Geeststraat 26",
    "sg:city":"Zaventem",
    "sg:orig_category":"Landmeters",
    "sg:phone":"+32 2 731 26 80",
    "sg:postcode":"1933",
    "sg:province":"Vlaams-Brabant",
    "wof:name":"Rene Verhaeghe",
    "wof:placetype":"venue"
},
  "geometry": {"coordinates":[4.5121002197,50.8614044189],"type":"Point"}
}