{
  "type": "Feature",
  "properties": {
    "iso:country":"BE",
    "sg:address":"Vezerlaan 1-1",
    "sg:city":"Herk-de-stad",
    "sg:classifiers":[
        {
            "category":"Professional",
            "subcategory":"Lawyer & Legal Services",
            "type":"Services"
        }
    ],
    "sg:phone":"+32 13 55 31 84",
    "sg:postcode":"3540",
    "sg:province":"Limburg",
    "wof:name":"Raskin T & Gruyters B Advocatenkantoor",
    "wof:placetype":"venue"
},
  "geometry": {"coordinates":[5.1692562103,50.9422073364],"type":"Point"}
}