{
  "type": "Feature",
  "properties": {
    "iso:country":"BE",
    "sg:address":"Baeckelmanstr. 52",
    "sg:city":"Tisselt",
    "sg:classifiers":[
        {
            "category":"Professional",
            "subcategory":"Engineering",
            "type":"Services"
        }
    ],
    "sg:phone":"+32 3 886 01 59",
    "sg:postcode":"2830",
    "sg:province":"Antwerpen",
    "sg:tags":[
        "machine",
        "-",
        "mechanical"
    ],
    "wof:name":"Inarti Nv",
    "wof:placetype":"venue"
},
  "geometry": {"coordinates":[4.3538122177,51.0353927612],"type":"Point"}
}