{
  "type": "Feature",
  "properties": {
    "iso:country":"BE",
    "sg:address":"Rechtestraat 25",
    "sg:city":"Lille (grand)",
    "sg:orig_category":"Herstellingen and onderhoud van auto's Herstellingen motorfietsen",
    "sg:phone":"+32 14 88 20 44",
    "sg:postcode":"2275",
    "sg:province":"Antwerpen",
    "wof:name":"Schoenen Van Tendeloo",
    "wof:placetype":"venue"
},
  "geometry": {"coordinates":[4.8236098289,51.2395515442],"type":"Point"}
}