{
  "type": "Feature",
  "properties": {
    "iso:country":"BE",
    "sg:address":"Rue De Tournai 46",
    "sg:city":"Pecq",
    "sg:classifiers":[
        {
            "category":"Food & Beverages",
            "subcategory":"Chocolate",
            "type":"Retail Goods"
        }
    ],
    "sg:phone":"+32 69 45 65 95",
    "sg:postcode":"7740",
    "sg:province":"Hainaut",
    "sg:tags":[
        "confectionery",
        "-"
    ],
    "wof:name":"Chocolat (maison Du)",
    "wof:placetype":"venue"
},
  "geometry": {"coordinates":[3.3391199112,50.6832733154],"type":"Point"}
}