{
  "type": "Feature",
  "properties": {
    "iso:country":"BE",
    "sg:address":"Grietestraat 6",
    "sg:city":"Lichtervelde",
    "sg:orig_category":"Editeurs de journaux. Editeurs de revues and p\u00e9riodiques",
    "sg:phone":"+32 51 72 23 71",
    "sg:postcode":"8810",
    "sg:province":"West-Vlaanderen",
    "wof:name":"Aeroscript",
    "wof:placetype":"venue"
},
  "geometry": {"coordinates":[3.154088974,51.0586357117],"type":"Point"}
}