{
  "type": "Feature",
  "properties": {
    "addr:full":"Schomstraat 8 Heusden-zolder Limburg 3550",
    "addr:housenumber":"8",
    "addr:postcode":"3550",
    "addr:street":"Schomstraat",
    "iso:country":"BE",
    "sg:address":"Schomstraat 8",
    "sg:city":"Heusden-zolder",
    "sg:orig_category":"Cr\u00e8ches and garderies d'enfants. Auberges de jeunesse and refuges",
    "sg:phone":"+32 11 45 12 25",
    "sg:postcode":"3550",
    "sg:province":"Limburg",
    "wof:name":"Het Heem",
    "wof:placetype":"venue"
},
  "geometry": {"coordinates":[5.3139648438,51.0231018066],"type":"Point"}
}