{
  "type": "Feature",
  "properties": {
    "addr:full":"Rue Souverain-pont 47 Li\u00c8ge Li\u00e8ge 4000",
    "addr:housenumber":"47",
    "addr:postcode":"4000",
    "addr:street":"Rue Souverain-Pont",
    "iso:country":"BE",
    "sg:address":"Rue Souverain-pont 47",
    "sg:city":"Li\u00c8ge",
    "sg:orig_category":"Epiceries",
    "sg:phone":"+32 4 221 25 08",
    "sg:postcode":"4000",
    "sg:province":"Li\u00e8ge",
    "wof:name":"Many Mode",
    "wof:placetype":"venue"
},
  "geometry": {"coordinates":[5.5760030746,50.6432609558],"type":"Point"}
}