{
  "type": "Feature",
  "properties": {
    "iso:country":"BE",
    "sg:address":"Sint-pietersweg 29",
    "sg:city":"Kortrijk",
    "sg:classifiers":[
        {
            "category":"Insurance",
            "subcategory":"Life Insurance",
            "type":"Services"
        }
    ],
    "sg:phone":"+32 56 21 33 62",
    "sg:postcode":"8510",
    "sg:province":"West-Vlaanderen",
    "sg:tags":[
        "assurance"
    ],
    "wof:name":"Covenas",
    "wof:placetype":"venue"
},
  "geometry": {"coordinates":[3.2836470604,50.7794075012],"type":"Point"}
}