{
  "type": "Feature",
  "properties": {
    "addr:full":"Rue Al\u00b4copette 9 Marche-en-famenne Luxembourg 6900",
    "addr:housenumber":"9",
    "addr:postcode":"6900",
    "addr:street":"Rue Al\u00b4Copette",
    "iso:country":"BE",
    "sg:address":"Rue Al\u00b4copette 9",
    "sg:city":"Marche-en-famenne",
    "sg:orig_category":"Elektrische installaties voor woningen",
    "sg:phone":"+32 84 31 51 28",
    "sg:postcode":"6900",
    "sg:province":"Luxembourg",
    "wof:name":"Jonathan De Ceulaer",
    "wof:placetype":"venue"
},
  "geometry": {"coordinates":[5.3430151939,50.2273483276],"type":"Point"}
}