{
  "type": "Feature",
  "properties": {
    "iso:country":"BE",
    "sg:address":"Marktstraat 98",
    "sg:city":"Harelbeke",
    "sg:orig_category":"Activit\u00e9s d\u00b4action sociale sans h\u00e9bergement",
    "sg:phone":"+32 56 73 34 50",
    "sg:postcode":"8530",
    "sg:province":"West-Vlaanderen",
    "wof:name":"Jip",
    "wof:placetype":"venue"
},
  "geometry": {"coordinates":[3.3079319,50.854763031],"type":"Point"}
}