{
  "type": "Feature",
  "properties": {
    "iso:country":"BE",
    "sg:address":"Avenue Jean Sobieski 30",
    "sg:city":"Brussel/bruxelles",
    "sg:orig_category":"Maisons de repos and r\u00e9sidences",
    "sg:phone":"+32 2 479 15 44",
    "sg:postcode":"1020",
    "sg:province":"Bruxelles-Capitale",
    "wof:name":"R\u00c9sidence Parc Royal",
    "wof:placetype":"venue"
},
  "geometry": {"coordinates":[4.3444690704,50.8883247375],"type":"Point"}
}