{
  "type": "Feature",
  "properties": {
    "addr:full":"Smidsestraat 8b4 Rotselaar Vlaams-Brabant 3110",
    "addr:housenumber":"8b4",
    "addr:postcode":"3110",
    "addr:street":"Smidsestraat",
    "iso:country":"BE",
    "sg:address":"Smidsestraat 8b4",
    "sg:city":"Rotselaar",
    "sg:classifiers":[
        {
            "category":"Arena",
            "subcategory":"Sports Club",
            "type":"Entertainment"
        }
    ],
    "sg:phone":"+32 16 44 93 56",
    "sg:postcode":"3110",
    "sg:province":"Vlaams-Brabant",
    "sg:tags":[
        "de"
    ],
    "wof:name":"M.v.c. Smash Wilsele",
    "wof:placetype":"venue"
},
  "geometry": {"coordinates":[4.7094449997,50.9508056641],"type":"Point"}
}