{
  "type": "Feature",
  "properties": {
    "iso:country":"BE",
    "sg:address":"Rue Joseph Wettinck 7",
    "sg:city":"Seraing (jemeppe-sur-meuse)",
    "sg:classifiers":[
        {
            "category":"Banks & Credit Unions",
            "subcategory":"Investment Brokerage",
            "type":"Services"
        }
    ],
    "sg:phone":"+32 4 233 93 98",
    "sg:postcode":"4101",
    "sg:province":"Li\u00e8ge",
    "sg:tags":[
        "printing",
        "-"
    ],
    "wof:name":"Grandry C",
    "wof:placetype":"venue"
},
  "geometry": {"coordinates":[5.5032248497,50.6157951355],"type":"Point"}
}