{
  "type": "Feature",
  "properties": {
    "iso:country":"BE",
    "sg:address":"Legeweg 201",
    "sg:city":"Brugge",
    "sg:orig_category":"Instituts pour enfants en difficult\u00e9. Orphelinats",
    "sg:phone":"+32 50 31 58 55",
    "sg:postcode":"8200",
    "sg:province":"West-Vlaanderen",
    "wof:name":"Zingende Sparren",
    "wof:placetype":"venue"
},
  "geometry": {"coordinates":[3.1957600117,51.2053184509],"type":"Point"}
}