{
  "type": "Feature",
  "properties": {
    "iso:country":"BE",
    "sg:address":"Hermesstraat 3",
    "sg:city":"Zaventem",
    "sg:orig_category":"Location de voitures",
    "sg:phone":"+32 2 725 10 40",
    "sg:postcode":"1930",
    "sg:province":"Vlaams-Brabant",
    "wof:name":"Keddy",
    "wof:placetype":"venue"
},
  "geometry": {"coordinates":[4.5032601357,50.875213623],"type":"Point"}
}