{
  "type": "Feature",
  "properties": {
    "iso:country":"BE",
    "sg:address":"Laageind 19",
    "sg:city":"Stabroek",
    "sg:classifiers":[
        {
            "category":"Education",
            "subcategory":"School",
            "type":"Public Place"
        }
    ],
    "sg:phone":"+32 3 561 05 00",
    "sg:postcode":"2940",
    "sg:province":"Antwerpen",
    "sg:tags":[
        "secondary"
    ],
    "wof:name":"Provinciaal Instituut Pito Stabroek",
    "wof:placetype":"venue"
},
  "geometry": {"coordinates":[4.3606472015,51.32995224],"type":"Point"}
}