{
  "type": "Feature",
  "properties": {
    "addr:full":"Chauss\u00e9e De Bruxelles 360 Ath (meslin - L'ev\u00eaque) Hainaut 7822",
    "addr:housenumber":"360;meslin",
    "addr:postcode":"7822",
    "addr:street":"Chausse\u0301E De Bruxelles;\u0302Que Hainaut",
    "iso:country":"BE",
    "sg:address":"Chauss\u00e9e De Bruxelles 360",
    "sg:city":"Ath (meslin - L'ev\u00eaque)",
    "sg:orig_category":"Non-Classified Establishments",
    "sg:phone":"+32 68 28 42 80",
    "sg:postcode":"7822",
    "sg:province":"Hainaut",
    "wof:name":"Lekien (ets)",
    "wof:placetype":"venue"
},
  "geometry": {"coordinates":[3.8858850002,50.6560249329],"type":"Point"}
}