{
  "type": "Feature",
  "properties": {
    "addr:full":"Jean Wellensstraat 9 Sint-pieters-woluwe/woluwe-saint-pierre Bruxelles-Capitale 1150",
    "addr:housenumber":"9",
    "addr:postcode":"1150",
    "addr:street":"Jean Wellensstraat;/",
    "iso:country":"BE",
    "sg:address":"Jean Wellensstraat 9",
    "sg:city":"Sint-pieters-woluwe/woluwe-saint-pierre",
    "sg:orig_category":"Bloemen and planten",
    "sg:phone":"+32 2 771 31 20",
    "sg:postcode":"1150",
    "sg:province":"Bruxelles-Capitale",
    "wof:name":"Vreven",
    "wof:placetype":"venue"
},
  "geometry": {"coordinates":[4.4305000305,50.8357925415],"type":"Point"}
}