{
  "type": "Feature",
  "properties": {
    "addr:full":"Kleinrees 74 Kasterlee Antwerpen 2460",
    "addr:housenumber":"74",
    "addr:postcode":"2460",
    "addr:street":"Kleinrees",
    "iso:country":"BE",
    "sg:address":"Kleinrees 74",
    "sg:city":"Kasterlee",
    "sg:classifiers":[
        {
            "category":"Health Services",
            "subcategory":"Doctor",
            "type":"Services"
        }
    ],
    "sg:phone":"+32 14 85 02 67",
    "sg:postcode":"2460",
    "sg:province":"Antwerpen",
    "sg:tags":[
        "medicinephysicians",
        "surgeon"
    ],
    "wof:name":"Buytaert Anton",
    "wof:placetype":"venue"
},
  "geometry": {"coordinates":[4.9603409767,51.2648925781],"type":"Point"}
}