{
  "type": "Feature",
  "properties": {
    "addr:full":"Rue D'egypte 24 Les Bons Villers Hainaut 6210",
    "addr:housenumber":"24",
    "addr:postcode":"6210",
    "addr:street":"Rue D'Egypte",
    "iso:country":"BE",
    "sg:address":"Rue D'egypte 24",
    "sg:city":"Les Bons Villers",
    "sg:orig_category":"Activit\u00e9s diverses d'imprimerie",
    "sg:phone":"+32 71 84 73 11",
    "sg:postcode":"6210",
    "sg:province":"Hainaut",
    "wof:name":"Christiane Philippart",
    "wof:placetype":"venue"
},
  "geometry": {"coordinates":[4.4182667732,50.5398216248],"type":"Point"}
}