{
  "type": "Feature",
  "properties": {
    "addr:full":"Place Eug\u00e8ne Keym 43 B 27 Bruxelles Bruxelles-Capitale 1170",
    "addr:housenumber":"43 b 27",
    "addr:postcode":"1170",
    "addr:street":"Place Euge\u0300Ne Keym",
    "iso:country":"BE",
    "sg:address":"Place Eug\u00e8ne Keym 43 B 27",
    "sg:city":"Bruxelles",
    "sg:classifiers":[
        {
            "category":"Manufacturing",
            "subcategory":"Chemicals & Compounds",
            "type":"Manufacturing & Wholesale Goods"
        }
    ],
    "sg:phone":"+32 2 674 23 11",
    "sg:postcode":"1170",
    "sg:province":"Bruxelles-Capitale",
    "sg:tags":[
        "pharmaceutical",
        "chemistry"
    ],
    "wof:name":"Omya Benelux Sa",
    "wof:placetype":"venue"
},
  "geometry": {"coordinates":[4.4029331207,50.8091659546],"type":"Point"}
}