{
  "type": "Feature",
  "properties": {
    "addr:full":"Chaussee De Mons 1445 Bruxelles Bruxelles-Capitale 1070",
    "addr:postcode":"1445;1070",
    "addr:street":"Chaussee De Mons",
    "iso:country":"BE",
    "sg:address":"Chaussee De Mons 1445",
    "sg:city":"Bruxelles",
    "sg:classifiers":[
        {
            "category":"Autos & Motor Vehicles",
            "subcategory":"Auto Supplies",
            "type":"Retail Goods"
        }
    ],
    "sg:phone":"+32 2 524 11 10",
    "sg:postcode":"1070",
    "sg:province":"Bruxelles-Capitale",
    "sg:tags":[
        "body",
        "car",
        "truck",
        "trailer",
        "superstructure"
    ],
    "wof:name":"M\u00e9canique Bruxelloise Distribution Automobile S.a.",
    "wof:placetype":"venue"
},
  "geometry": {"coordinates":[4.2891302109,50.8100318909],"type":"Point"}
}