{
  "type": "Feature",
  "properties": {
    "addr:full":"Rue Grande 102 Dour Hainaut 7370",
    "addr:housenumber":"102",
    "addr:postcode":"7370",
    "addr:street":"Rue Grande;Hainaut",
    "iso:country":"BE",
    "sg:address":"Rue Grande 102",
    "sg:city":"Dour",
    "sg:classifiers":[
        {
            "category":"Shopping",
            "subcategory":"Optician",
            "type":"Retail Goods"
        }
    ],
    "sg:phone":"+32 65 65 51 92",
    "sg:postcode":"7370",
    "sg:province":"Hainaut",
    "sg:tags":[
        "-"
    ],
    "wof:name":"Krys",
    "wof:placetype":"venue"
},
  "geometry": {"coordinates":[3.7820301056,50.3998756409],"type":"Point"}
}