{
  "type": "Feature",
  "properties": {
    "addr:full":"Rue Spintay 111 Verviers Li\u00e8ge 4800",
    "addr:housenumber":"111",
    "addr:postcode":"4800",
    "addr:street":"Rue Spintay",
    "iso:country":"BE",
    "sg:address":"Rue Spintay 111",
    "sg:city":"Verviers",
    "sg:classifiers":[
        {
            "category":"Personal",
            "subcategory":"Beauty Salon",
            "type":"Services"
        }
    ],
    "sg:phone":"+32 87 33 79 46",
    "sg:postcode":"4800",
    "sg:province":"Li\u00e8ge",
    "sg:tags":[
        "lady",
        "-",
        "hairdressing"
    ],
    "wof:name":"Horsch-aveni\u00e8re",
    "wof:placetype":"venue"
},
  "geometry": {"coordinates":[5.8594508171,50.5917663574],"type":"Point"}
}