{
  "type": "Feature",
  "properties": {
    "iso:country":"BE",
    "sg:address":"Verlorenkost 10",
    "sg:city":"Heusden-zolder",
    "sg:orig_category":"Woningbouw",
    "sg:phone":"+32 11 53 64 38",
    "sg:postcode":"3550",
    "sg:province":"Limburg",
    "wof:name":"Bsg",
    "wof:placetype":"venue"
},
  "geometry": {"coordinates":[5.3294491768,51.0206451416],"type":"Point"}
}