{
  "type": "Feature",
  "properties": {
    "iso:country":"BE",
    "sg:address":"Hoogweg 30",
    "sg:city":"Kluisbergen (ruien)",
    "sg:classifiers":[
        {
            "category":"Personal",
            "subcategory":"Beauty Salon",
            "type":"Services"
        }
    ],
    "sg:phone":"+32 55 38 63 57",
    "sg:postcode":"9690",
    "sg:province":"Oost-Vlaanderen",
    "sg:tags":[
        "lady",
        "-",
        "hairdressing"
    ],
    "wof:name":"Eveline",
    "wof:placetype":"venue"
},
  "geometry": {"coordinates":[3.4931020737,50.7706871033],"type":"Point"}
}