{
  "type": "Feature",
  "properties": {
    "addr:full":"Molenstraat 36 Blankenberge West-Vlaanderen 8370",
    "addr:housenumber":"36",
    "addr:postcode":"8370",
    "addr:street":"Molenstraat",
    "iso:country":"BE",
    "sg:address":"Molenstraat 36",
    "sg:city":"Blankenberge",
    "sg:orig_category":"Bloemen and planten",
    "sg:phone":"+32 50 41 41 64",
    "sg:postcode":"8370",
    "sg:province":"West-Vlaanderen",
    "wof:name":"Ikebana",
    "wof:placetype":"venue"
},
  "geometry": {"coordinates":[3.1292080879,51.3147125244],"type":"Point"}
}