{
  "type": "Feature",
  "properties": {
    "iso:country":"BE",
    "sg:address":"Wegvoeringsstraat 10",
    "sg:city":"Geraardsbergen",
    "sg:orig_category":"Algemeen secundair onderwijs",
    "sg:phone":"+32 54 41 31 37",
    "sg:postcode":"9500",
    "sg:province":"Oost-Vlaanderen",
    "wof:name":"Middenschool",
    "wof:placetype":"venue"
},
  "geometry": {"coordinates":[3.8779540062,50.7722358704],"type":"Point"}
}