{
  "type": "Feature",
  "properties": {
    "addr:full":"Rue Du Corsal 54 Chastre Brabant Wallon 1450",
    "addr:housenumber":"54",
    "addr:postcode":"1450",
    "addr:street":"Rue Du Corsal",
    "iso:country":"BE",
    "sg:address":"Rue Du Corsal 54",
    "sg:city":"Chastre",
    "sg:orig_category":"Plomberie, chauffage and installations sanitaires",
    "sg:phone":"+32 78 71 91 09",
    "sg:postcode":"1450",
    "sg:province":"Brabant Wallon",
    "wof:name":"Dethy",
    "wof:placetype":"venue"
},
  "geometry": {"coordinates":[4.636452198,50.6085243225],"type":"Point"}
}