{
  "type": "Feature",
  "properties": {
    "addr:full":"Bredestraat 167 Gent Oost-Vlaanderen 9041",
    "addr:housenumber":"167",
    "addr:postcode":"9041",
    "addr:street":"Bredestraat;Oost-Vlaanderen",
    "iso:country":"BE",
    "sg:address":"Bredestraat 167",
    "sg:city":"Gent",
    "sg:orig_category":"Epiceries",
    "sg:phone":"+32 9 251 14 98",
    "sg:postcode":"9041",
    "sg:province":"Oost-Vlaanderen",
    "wof:name":"Ria Bracke",
    "wof:placetype":"venue"
},
  "geometry": {"coordinates":[3.7770750523,51.104927063],"type":"Point"}
}