{
  "type": "Feature",
  "properties": {
    "addr:full":"Rue De Li\u00c8ge 3 Houffalize Luxembourg 6660",
    "addr:housenumber":"3",
    "addr:postcode":"6660",
    "addr:street":"Rue De Lie\u0300Ge",
    "iso:country":"BE",
    "sg:address":"Rue De Li\u00c8ge 3",
    "sg:city":"Houffalize",
    "sg:orig_category":"Pharmaciens",
    "sg:phone":"+32 61 28 80 24",
    "sg:postcode":"6660",
    "sg:province":"Luxembourg",
    "wof:name":"L. Gilson",
    "wof:placetype":"venue"
},
  "geometry": {"coordinates":[5.7905731201,50.1326980591],"type":"Point"}
}