{
  "type": "Feature",
  "properties": {
    "iso:country":"BE",
    "sg:address":"Middaglijnstraat 100",
    "sg:city":"Sint-joost-ten-node/saint-josse-ten-noode",
    "sg:orig_category":"Ziekenhuizen and zorginstellingen Ziekenvervoer",
    "sg:phone":"+32 2 225 91 11",
    "sg:postcode":"1210",
    "sg:province":"Bruxelles-Capitale",
    "wof:name":"Clinique St.etienne",
    "wof:placetype":"venue"
},
  "geometry": {"coordinates":[4.3689761162,50.8559417725],"type":"Point"}
}