{
  "type": "Feature",
  "properties": {
    "iso:country":"BE",
    "sg:address":"Waterstraat 21",
    "sg:city":"Tessenderlo",
    "sg:orig_category":"Plaatsen van vloer- and muurbekleding Schilders",
    "sg:phone":"+32 13 67 53 26",
    "sg:postcode":"3980",
    "sg:province":"Limburg",
    "wof:name":"Decofas",
    "wof:placetype":"venue"
},
  "geometry": {"coordinates":[5.1234698296,51.0630378723],"type":"Point"}
}