{
  "type": "Feature",
  "properties": {
    "iso:country":"BE",
    "sg:address":"Gernechamps 20",
    "sg:city":"Lierneux",
    "sg:orig_category":"Rundveehouders",
    "sg:phone":"+32 80 31 94 05",
    "sg:postcode":"4990",
    "sg:province":"Li\u00e8ge",
    "wof:name":"Edouard Lesenfants",
    "wof:placetype":"venue"
},
  "geometry": {"coordinates":[5.8251228333,50.290802002],"type":"Point"}
}