{
  "type": "Feature",
  "properties": {
    "addr:full":"Avenue Des Erables 79 Waterloo Brabant Wallon 1410",
    "addr:housenumber":"79",
    "addr:postcode":"1410",
    "addr:street":"Avenue Des Erables",
    "iso:country":"BE",
    "sg:address":"Avenue Des Erables 79",
    "sg:city":"Waterloo",
    "sg:orig_category":"Meubles Fab",
    "sg:phone":"+32 2 354 65 64",
    "sg:postcode":"1410",
    "sg:province":"Brabant Wallon",
    "wof:name":"Move Cuisimeuble",
    "wof:placetype":"venue"
},
  "geometry": {"coordinates":[4.4091658592,50.7234458923],"type":"Point"}
}