{
  "type": "Feature",
  "properties": {
    "iso:country":"BE",
    "sg:address":"Plaatsnijdersstraat 2",
    "sg:city":"Antwerpen",
    "sg:classifiers":[
        {
            "category":"Museum",
            "type":"Entertainment"
        }
    ],
    "sg:phone":"+32 3 238 78 09",
    "sg:postcode":"2000",
    "sg:province":"Antwerpen",
    "wof:name":"Kon Museum Vr Schone Kunsten",
    "wof:placetype":"venue"
},
  "geometry": {"coordinates":[4.3964338303,51.2081069946],"type":"Point"}
}