{
  "type": "Feature",
  "properties": {
    "addr:full":"Kloetstraat 5 Beveren Oost-Vlaanderen 9120",
    "addr:housenumber":"5",
    "addr:postcode":"9120",
    "addr:street":"Kloetstraat",
    "iso:country":"BE",
    "sg:address":"Kloetstraat 5",
    "sg:city":"Beveren",
    "sg:classifiers":[
        {
            "category":"Utilities",
            "subcategory":"Fuel Oil & Lpg",
            "type":"Services"
        }
    ],
    "sg:phone":"+32 3 775 70 27",
    "sg:postcode":"9120",
    "sg:province":"Oost-Vlaanderen",
    "sg:tags":[
        "stations-service",
        "combustible",
        "carburants"
    ],
    "wof:name":"Rudi Felix",
    "wof:placetype":"venue"
},
  "geometry": {"coordinates":[4.2885971069,51.2306671143],"type":"Point"}
}