{
  "type": "Feature",
  "properties": {
    "addr:full":"2 Pladysstraat Deerlijk West-Vlaanderen 8540",
    "addr:housenumber":"2",
    "addr:postcode":"8540",
    "addr:street":"Pladysstraat",
    "iso:country":"BE",
    "sg:address":"2 Pladysstraat",
    "sg:city":"Deerlijk",
    "sg:classifiers":[
        {
            "category":"Shopping",
            "subcategory":"Crafts & Fabrics",
            "type":"Retail Goods"
        }
    ],
    "sg:phone":"+32 56 35 02 06",
    "sg:postcode":"8540",
    "sg:province":"West-Vlaanderen",
    "sg:tags":[
        "textile",
        "linen",
        "clothing"
    ],
    "wof:name":"Bruvatex-sagaert & Speyer Nv",
    "wof:placetype":"venue"
},
  "geometry": {"coordinates":[3.3609399796,50.8295936584],"type":"Point"}
}