{
  "type": "Feature",
  "properties": {
    "iso:country":"BE",
    "sg:address":"Ichtegemstraat 95ba",
    "sg:city":"Kortemark",
    "sg:classifiers":[
        {
            "category":"Restaurant",
            "type":"Food & Drink"
        }
    ],
    "sg:phone":"+32 51 56 78 32",
    "sg:postcode":"8610",
    "sg:province":"West-Vlaanderen",
    "wof:name":"Tearoom Hispano",
    "wof:placetype":"venue"
},
  "geometry": {"coordinates":[3.0353109837,51.0430412292],"type":"Point"}
}