{
  "type": "Feature",
  "properties": {
    "iso:country":"BE",
    "sg:address":"Rue Adolphe Bastin 23",
    "sg:city":"Namur",
    "sg:classifiers":[
        {
            "category":"Building & Trades",
            "subcategory":"Equipment Rental",
            "type":"Services"
        }
    ],
    "sg:phone":"+32 81 26 15 95",
    "sg:postcode":"5000",
    "sg:province":"Namur",
    "sg:tags":[
        "lighting",
        "-",
        "fixture"
    ],
    "wof:name":"Mega Productions Objectif Plus Sprl",
    "wof:placetype":"venue"
},
  "geometry": {"coordinates":[4.863781929,50.4708557129],"type":"Point"}
}