{
  "type": "Feature",
  "properties": {
    "iso:country":"BE",
    "sg:address":"Provincieweg 287-289",
    "sg:city":"Herzele",
    "sg:classifiers":[
        {
            "category":"Retail",
            "subcategory":"Auto Repair",
            "type":"Services"
        }
    ],
    "sg:phone":"+32 53 62 23 28",
    "sg:postcode":"9550",
    "sg:province":"Oost-Vlaanderen",
    "sg:tags":[
        "garage"
    ],
    "wof:name":"Van Bellinghen P",
    "wof:placetype":"venue"
},
  "geometry": {"coordinates":[3.8787400723,50.8998908997],"type":"Point"}
}