{
  "type": "Feature",
  "properties": {
    "iso:country":"BE",
    "sg:address":"Route Du Viroin 21",
    "sg:city":"Doische (gimn\u00e9e)",
    "sg:classifiers":[
        {
            "category":"Wholesale",
            "subcategory":"Machinery & Supplies",
            "type":"Manufacturing & Wholesale Goods"
        }
    ],
    "sg:phone":"+32 82 67 83 39",
    "sg:postcode":"5680",
    "sg:province":"Namur",
    "sg:tags":[
        "retail",
        "-",
        "electric"
    ],
    "wof:name":"Guislain A",
    "wof:placetype":"venue"
},
  "geometry": {"coordinates":[4.7260651588,50.131439209],"type":"Point"}
}