{
  "type": "Feature",
  "properties": {
    "addr:full":"Langemunt 21 Erpe-mere Oost-Vlaanderen 9420",
    "addr:housenumber":"21",
    "addr:postcode":"9420",
    "addr:street":"Langemunt",
    "iso:country":"BE",
    "sg:address":"Langemunt 21",
    "sg:city":"Erpe-mere",
    "sg:orig_category":"Banken and kredietinstellingen",
    "sg:phone":"+32 53 63 12 14",
    "sg:postcode":"9420",
    "sg:province":"Oost-Vlaanderen",
    "wof:name":"Van Impe-van Sande",
    "wof:placetype":"venue"
},
  "geometry": {"coordinates":[3.9404630661,50.8929100037],"type":"Point"}
}