{
  "type": "Feature",
  "properties": {
    "iso:country":"BE",
    "sg:address":"Rue Du Wez 10",
    "sg:city":"Vaux-sur-sure",
    "sg:orig_category":"Artsen and specialisten",
    "sg:phone":"+32 61 25 59 17",
    "sg:postcode":"6640",
    "sg:province":"Luxembourg",
    "wof:name":"Anne Staumont",
    "wof:placetype":"venue"
},
  "geometry": {"coordinates":[5.5664978027,49.9096183777],"type":"Point"}
}