{
  "type": "Feature",
  "properties": {
    "iso:country":"BE",
    "sg:address":"Roodebeeksteenweg 392",
    "sg:city":"Sint-lambrechts-woluwe/woluwe-saint-lambert",
    "sg:orig_category":"Artsen and specialisten",
    "sg:phone":"+32 2 771 92 47",
    "sg:postcode":"1200",
    "sg:province":"Bruxelles-Capitale",
    "wof:name":"P. Marchand",
    "wof:placetype":"venue"
},
  "geometry": {"coordinates":[4.4198560715,50.8498687744],"type":"Point"}
}