{
  "type": "Feature",
  "properties": {
    "addr:full":"Joseph Smeetslaan 13 Maasmechelen Limburg 3630",
    "addr:housenumber":"13",
    "addr:postcode":"3630",
    "addr:street":"Joseph Smeetslaan",
    "iso:country":"BE",
    "sg:address":"Joseph Smeetslaan 13",
    "sg:city":"Maasmechelen",
    "sg:classifiers":[
        {
            "category":"Insurance",
            "subcategory":"Life Insurance",
            "type":"Services"
        }
    ],
    "sg:phone":"+32 89 76 46 88",
    "sg:postcode":"3630",
    "sg:province":"Limburg",
    "sg:tags":[
        "assurance"
    ],
    "wof:name":"Group Belver",
    "wof:placetype":"venue"
},
  "geometry": {"coordinates":[5.6942148209,50.9648933411],"type":"Point"}
}