{
  "type": "Feature",
  "properties": {
    "iso:country":"BE",
    "sg:address":"Dr\u00e8ve Du Bonheur 37",
    "sg:city":"Bruxelles (woluwe-saint-pierre)",
    "sg:classifiers":[
        {
            "category":"Health Services",
            "subcategory":"Nursing And Care Facility",
            "type":"Services"
        }
    ],
    "sg:phone":"+32 2 772 36 70",
    "sg:postcode":"1150",
    "sg:province":"Bruxelles-Capitale",
    "sg:tags":[
        "handwriting",
        "-",
        "expert"
    ],
    "wof:name":"Silvestri",
    "wof:placetype":"venue"
},
  "geometry": {"coordinates":[4.4654388428,50.8441123962],"type":"Point"}
}