{
  "type": "Feature",
  "properties": {
    "addr:full":"Beernemstraat 65 Wingene West-Vlaanderen 8750",
    "addr:housenumber":"65",
    "addr:postcode":"8750",
    "addr:street":"Beernemstraat",
    "iso:country":"BE",
    "sg:address":"Beernemstraat 65",
    "sg:city":"Wingene",
    "sg:classifiers":[
        {
            "category":"Professional",
            "subcategory":"Engineering",
            "type":"Services"
        }
    ],
    "sg:postcode":"8750",
    "sg:province":"West-Vlaanderen",
    "sg:tags":[
        "workshop"
    ],
    "wof:name":"Mcm Bvba",
    "wof:placetype":"venue"
},
  "geometry": {"coordinates":[3.2779769897,51.0628547668],"type":"Point"}
}