{
  "type": "Feature",
  "properties": {
    "addr:full":"G. Gezellelaan 59 Heusden-zolder Limburg 3550",
    "addr:housenumber":"59",
    "addr:postcode":"3550",
    "addr:street":"G. Gezellelaan",
    "iso:country":"BE",
    "sg:address":"G. Gezellelaan 59",
    "sg:city":"Heusden-zolder",
    "sg:orig_category":"Studios photographiques. Equipement photographique",
    "sg:phone":"+32 11 42 05 07",
    "sg:postcode":"3550",
    "sg:province":"Limburg",
    "wof:name":"Foto Paul Reynders",
    "wof:placetype":"venue"
},
  "geometry": {"coordinates":[5.2766890526,51.0308380127],"type":"Point"}
}