{
  "type": "Feature",
  "properties": {
    "addr:full":"Van Craenenbroeckstraat 67 Beveren Oost-Vlaanderen 9120",
    "addr:housenumber":"67",
    "addr:postcode":"9120",
    "addr:street":"Craenenbroeckstraat",
    "iso:country":"BE",
    "sg:address":"Van Craenenbroeckstraat 67",
    "sg:city":"Beveren",
    "sg:classifiers":[
        {
            "category":"Cafe",
            "type":"Food & Drink"
        }
    ],
    "sg:phone":"+32 3 775 19 95",
    "sg:postcode":"9120",
    "sg:province":"Oost-Vlaanderen",
    "sg:tags":[
        "caf\u00e9s"
    ],
    "wof:name":"Davy Buys",
    "wof:placetype":"venue"
},
  "geometry": {"coordinates":[4.2511582375,51.2217445374],"type":"Point"}
}