{
  "type": "Feature",
  "properties": {
    "addr:full":"Rue Du Pot-d\u00b4or 14 Li\u00c8ge Li\u00e8ge 4000",
    "addr:housenumber":"14",
    "addr:postcode":"4000",
    "addr:street":"Rue Du Pot-D\u00b4Or",
    "iso:country":"BE",
    "sg:address":"Rue Du Pot-d\u00b4or 14",
    "sg:city":"Li\u00c8ge",
    "sg:classifiers":[
        {
            "category":"Shopping",
            "subcategory":"Clothing, Apparel, & Fashions",
            "type":"Retail Goods"
        }
    ],
    "sg:phone":"+32 4 221 07 67",
    "sg:postcode":"4000",
    "sg:province":"Li\u00e8ge",
    "sg:tags":[
        "v\u00eatements",
        "pour",
        "dame"
    ],
    "wof:name":"Caroline Biss",
    "wof:placetype":"venue"
},
  "geometry": {"coordinates":[5.5700669289,50.6419677734],"type":"Point"}
}