{
  "type": "Feature",
  "properties": {
    "iso:country":"BE",
    "sg:address":"Holsteenweg 28",
    "sg:city":"Zonhoven",
    "sg:classifiers":[
        {
            "category":"Restaurant",
            "type":"Food & Drink"
        }
    ],
    "sg:phone":"+32 11 81 50 86",
    "sg:postcode":"3520",
    "sg:province":"Limburg",
    "wof:name":"Holsteenhoeve",
    "wof:placetype":"venue"
},
  "geometry": {"coordinates":[5.4163079262,50.9960479736],"type":"Point"}
}