{
  "type": "Feature",
  "properties": {
    "addr:full":"Kasteellaan 487 Gent Oost-Vlaanderen 9000",
    "addr:housenumber":"487",
    "addr:postcode":"9000",
    "addr:street":"Kasteellaan;Oost-Vlaanderen",
    "iso:country":"BE",
    "sg:address":"Kasteellaan 487",
    "sg:city":"Gent",
    "sg:orig_category":"Solar protection - Inside",
    "sg:phone":"+32 9 233 75 02",
    "sg:postcode":"9000",
    "sg:province":"Oost-Vlaanderen",
    "wof:name":"D'sign",
    "wof:placetype":"venue"
},
  "geometry": {"coordinates":[3.7385380268,51.0560798645],"type":"Point"}
}