{
  "type": "Feature",
  "properties": {
    "addr:full":"Torkonjestraat 52 Kortrijk West-Vlaanderen 8510",
    "addr:housenumber":"52",
    "addr:postcode":"8510",
    "addr:street":"Torkonjestraat",
    "iso:country":"BE",
    "sg:address":"Torkonjestraat 52",
    "sg:city":"Kortrijk",
    "sg:classifiers":[
        {
            "category":"Cafe",
            "type":"Food & Drink"
        }
    ],
    "sg:phone":"+32 56 25 64 17",
    "sg:postcode":"8510",
    "sg:province":"West-Vlaanderen",
    "sg:tags":[
        "caf\u00e9s"
    ],
    "wof:name":"Caf\u00c9 D\u00d4me",
    "wof:placetype":"venue"
},
  "geometry": {"coordinates":[3.2398290634,50.7935371399],"type":"Point"}
}