{
  "type": "Feature",
  "properties": {
    "iso:country":"BE",
    "sg:address":"Tweede Koninginstraat 31",
    "sg:city":"Ukkel/uccle",
    "sg:orig_category":"Elektrische installaties voor woningen",
    "sg:phone":"+32 2 343 14 39",
    "sg:postcode":"1180",
    "sg:province":"Bruxelles-Capitale",
    "wof:name":"Electricit\u00c9 Pierre Fr\u00c8res",
    "wof:placetype":"venue"
},
  "geometry": {"coordinates":[4.3413767815,50.8127174377],"type":"Point"}
}