{
  "type": "Feature",
  "properties": {
    "iso:country":"BE",
    "sg:address":"Magdalena Vermeeschlaan 29",
    "sg:city":"Hove",
    "sg:classifiers":[
        {
            "category":"Transit Center",
            "subcategory":"Freight",
            "type":"Transportation"
        }
    ],
    "sg:phone":"+32 3 454 22 21",
    "sg:postcode":"2540",
    "sg:province":"Antwerpen",
    "sg:tags":[
        "import",
        "export",
        "-"
    ],
    "wof:name":"Europea Trade Nv",
    "wof:placetype":"venue"
},
  "geometry": {"coordinates":[4.4815001488,51.1440010071],"type":"Point"}
}