{
  "type": "Feature",
  "properties": {
    "iso:country":"BE",
    "sg:address":"Kapittel 27a",
    "sg:city":"Brakel (michelbeke)",
    "sg:orig_category":"Non-Classified Establishments",
    "sg:phone":"+32 55 42 59 36",
    "sg:postcode":"9660",
    "sg:province":"Oost-Vlaanderen",
    "wof:name":"Ann Couture",
    "wof:placetype":"venue"
},
  "geometry": {"coordinates":[3.7813620567,50.8296394348],"type":"Point"}
}