{
  "type": "Feature",
  "properties": {
    "addr:full":"Aarschotsesteenweg 478 Leuven Vlaams-Brabant 3012",
    "addr:housenumber":"478",
    "addr:postcode":"3012",
    "addr:street":"Aarschotsesteenweg",
    "iso:country":"BE",
    "sg:address":"Aarschotsesteenweg 478",
    "sg:city":"Leuven",
    "sg:orig_category":"MEUBELONTWERP AND -INSTALLATIE Meubelzaken, woning- and keukeninrichting",
    "sg:phone":"+32 16 44 98 30",
    "sg:postcode":"3012",
    "sg:province":"Vlaams-Brabant",
    "wof:name":"Dreco",
    "wof:placetype":"venue"
},
  "geometry": {"coordinates":[4.717730999,50.9175834656],"type":"Point"}
}