{
  "type": "Feature",
  "properties": {
    "addr:full":"Rue De La Station 51 Perwez Brabant Wallon 1360",
    "addr:housenumber":"51",
    "addr:postcode":"1360",
    "addr:street":"Rue De La Station",
    "iso:country":"BE",
    "sg:address":"Rue De La Station 51",
    "sg:city":"Perwez",
    "sg:orig_category":"Banques and organismes de cr\u00e9dit",
    "sg:phone":"+32 81 65 50 88",
    "sg:postcode":"1360",
    "sg:province":"Brabant Wallon",
    "wof:name":"Bbl",
    "wof:placetype":"venue"
},
  "geometry": {"coordinates":[4.8118891716,50.6249580383],"type":"Point"}
}