{
  "type": "Feature",
  "properties": {
    "iso:country":"BE",
    "sg:address":"Rue Auguste Farcy 14",
    "sg:city":"Thuin",
    "sg:orig_category":"Sportclubs Sportterreinen and installaties behalve sportcentra",
    "sg:phone":"+32 71 51 12 65",
    "sg:postcode":"6534",
    "sg:province":"Hainaut",
    "wof:name":"F.c. Tuniques Bleues",
    "wof:placetype":"venue"
},
  "geometry": {"coordinates":[4.3539199829,50.3455810547],"type":"Point"}
}