{
  "type": "Feature",
  "properties": {
    "addr:full":"Route Des Fagnes 2 Ferri\u00c8res Li\u00e8ge 4190",
    "addr:housenumber":"2",
    "addr:postcode":"4190",
    "addr:street":"Route Des Fagnes",
    "iso:country":"BE",
    "sg:address":"Route Des Fagnes 2",
    "sg:city":"Ferri\u00c8res",
    "sg:classifiers":[
        {
            "category":"Travel",
            "subcategory":"Hotels & Motels",
            "type":"Entertainment"
        }
    ],
    "sg:phone":"+32 86 40 03 35",
    "sg:postcode":"4190",
    "sg:province":"Li\u00e8ge",
    "sg:tags":[
        "restaurant"
    ],
    "wof:name":"Hotel Le Coq D'or",
    "wof:placetype":"venue"
},
  "geometry": {"coordinates":[5.5850372314,50.413734436],"type":"Point"}
}