{
  "type": "Feature",
  "properties": {
    "addr:full":"Rue Du Charreau 22 Gedinne Namur 5575",
    "addr:housenumber":"22",
    "addr:postcode":"5575",
    "addr:street":"Rue Du Charreau",
    "iso:country":"BE",
    "sg:address":"Rue Du Charreau 22",
    "sg:city":"Gedinne",
    "sg:orig_category":"Traitements param\u00e9dicaux",
    "sg:phone":"+32 61 58 83 64",
    "sg:postcode":"5575",
    "sg:province":"Namur",
    "wof:name":"Eric Cunin",
    "wof:placetype":"venue"
},
  "geometry": {"coordinates":[4.9494428635,49.9387550354],"type":"Point"}
}