{
  "type": "Feature",
  "properties": {
    "iso:country":"BE",
    "sg:address":"All\u00e9e Des Tilleuls 19",
    "sg:city":"Wemmel",
    "sg:classifiers":[
        {
            "category":"Professional",
            "subcategory":"Management & Consulting",
            "type":"Services"
        }
    ],
    "sg:phone":"+32 2 460 42 41",
    "sg:postcode":"1780",
    "sg:province":"Vlaams-Brabant",
    "sg:tags":[
        "consultant"
    ],
    "wof:name":"H.v. Management Bvba",
    "wof:placetype":"venue"
},
  "geometry": {"coordinates":[4.3147821426,50.9175643921],"type":"Point"}
}