{
  "type": "Feature",
  "properties": {
    "addr:full":"Square Marie-louise 33 Box 2 Bruxelles Bruxelles-Capitale 1000",
    "addr:housenumber":"33;2",
    "addr:postcode":"1000",
    "addr:street":"Square Marie-Louise;Box",
    "iso:country":"BE",
    "sg:address":"Square Marie-louise 33 Box 2",
    "sg:city":"Bruxelles",
    "sg:classifiers":[
        {
            "category":"Professional",
            "subcategory":"Engineering",
            "type":"Services"
        }
    ],
    "sg:phone":"+32 2 230 02 24",
    "sg:postcode":"1000",
    "sg:province":"Bruxelles-Capitale",
    "sg:tags":[
        "-"
    ],
    "wof:name":"Population And Social Policy",
    "wof:placetype":"venue"
},
  "geometry": {"coordinates":[4.3785800934,50.8479232788],"type":"Point"}
}