{
  "type": "Feature",
  "properties": {
    "addr:full":"Rue Joseph Wauters 72 Waremme Li\u00e8ge 4300",
    "addr:housenumber":"72",
    "addr:postcode":"4300",
    "addr:street":"Rue Joseph Wauters",
    "iso:country":"BE",
    "sg:address":"Rue Joseph Wauters 72",
    "sg:city":"Waremme",
    "sg:orig_category":"Chaussures",
    "sg:phone":"+32 19 32 50 23",
    "sg:postcode":"4300",
    "sg:province":"Li\u00e8ge",
    "wof:name":"Avance",
    "wof:placetype":"venue"
},
  "geometry": {"coordinates":[5.2530059814,50.6960144043],"type":"Point"}
}