{
  "type": "Feature",
  "properties": {
    "addr:full":"Onze-lieve-vrouwekerkhof 11 Mechelen Antwerpen 2800",
    "addr:housenumber":"11",
    "addr:postcode":"2800",
    "addr:street":"Onze-Lieve-Vrouwekerkhof",
    "iso:country":"BE",
    "sg:address":"Onze-lieve-vrouwekerkhof 11",
    "sg:city":"Mechelen",
    "sg:classifiers":[
        {
            "category":"Health Services",
            "subcategory":"Nursing And Care Facility",
            "type":"Services"
        }
    ],
    "sg:phone":"+32 15 43 04 99",
    "sg:postcode":"2800",
    "sg:province":"Antwerpen",
    "sg:tags":[
        "home",
        "rest"
    ],
    "wof:name":"Milsenhof",
    "wof:placetype":"venue"
},
  "geometry": {"coordinates":[4.477935791,51.0229072571],"type":"Point"}
}