{
  "type": "Feature",
  "properties": {
    "iso:country":"BE",
    "sg:address":"Zandstraat 138",
    "sg:city":"Zoersel",
    "sg:classifiers":[
        {
            "category":"Personal",
            "subcategory":"Beauty Salon",
            "type":"Services"
        }
    ],
    "sg:phone":"+32 3 311 63 21",
    "sg:postcode":"2980",
    "sg:province":"Antwerpen",
    "sg:tags":[
        "lady",
        "-",
        "hairdressing"
    ],
    "wof:name":"Ann",
    "wof:placetype":"venue"
},
  "geometry": {"coordinates":[4.7105851173,51.2586402893],"type":"Point"}
}