{
  "type": "Feature",
  "properties": {
    "addr:full":"Hulstbaan 4 Sint-niklaas Oost-Vlaanderen 9112",
    "addr:housenumber":"4",
    "addr:postcode":"9112",
    "addr:street":"Hulstbaan",
    "iso:country":"BE",
    "sg:address":"Hulstbaan 4",
    "sg:city":"Sint-niklaas",
    "sg:orig_category":"Epiceries",
    "sg:phone":"+32 3 772 34 14",
    "sg:postcode":"9112",
    "sg:province":"Oost-Vlaanderen",
    "wof:name":"Brasoli",
    "wof:placetype":"venue"
},
  "geometry": {"coordinates":[4.0429382324,51.1548805237],"type":"Point"}
}