{
  "type": "Feature",
  "properties": {
    "addr:full":"Place De La Victoire 4 Ch\u00c2telet Hainaut 6200",
    "addr:housenumber":"4",
    "addr:postcode":"6200",
    "addr:street":"Place De La Victoire",
    "iso:country":"BE",
    "sg:address":"Place De La Victoire 4",
    "sg:city":"Ch\u00c2telet",
    "sg:orig_category":"Huisdieren and benodigdheden",
    "sg:phone":"+32 71 38 20 03",
    "sg:postcode":"6200",
    "sg:province":"Hainaut",
    "wof:name":"Aqua-hobby",
    "wof:placetype":"venue"
},
  "geometry": {"coordinates":[4.5179800987,50.4041481018],"type":"Point"}
}