{
  "type": "Feature",
  "properties": {
    "addr:full":"Melleveldstraat 23 Hoeselt Limburg 3730",
    "addr:housenumber":"23",
    "addr:postcode":"3730",
    "addr:street":"Melleveldstraat",
    "iso:country":"BE",
    "sg:address":"Melleveldstraat 23",
    "sg:city":"Hoeselt",
    "sg:classifiers":[
        {
            "category":"Professional",
            "subcategory":"Accounting & Tax Preparation",
            "type":"Services"
        }
    ],
    "sg:phone":"+32 89 41 69 52",
    "sg:postcode":"3730",
    "sg:province":"Limburg",
    "sg:tags":[
        "bookkeeper"
    ],
    "wof:name":"Hermans G",
    "wof:placetype":"venue"
},
  "geometry": {"coordinates":[5.4773049355,50.8699111938],"type":"Point"}
}