{
  "type": "Feature",
  "properties": {
    "addr:full":"Chemin D' Havr\u00c9 62 Mons Hainaut 7030",
    "addr:housenumber":"62",
    "addr:postcode":"7030",
    "addr:street":"Chemin D ' Havre\u0301;Hainaut",
    "iso:country":"BE",
    "sg:address":"Chemin D' Havr\u00c9 62",
    "sg:city":"Mons",
    "sg:orig_category":"Verhuur bouwmachines Verhuur doe-het-zelf materiaal",
    "sg:phone":"+32 65 34 83 67",
    "sg:postcode":"7030",
    "sg:province":"Hainaut",
    "wof:name":"Laurent Colart",
    "wof:placetype":"venue"
},
  "geometry": {"coordinates":[4.0229377747,50.4433403015],"type":"Point"}
}