{
  "type": "Feature",
  "properties": {
    "addr:full":"Koornbloemstraat 3 Anzegem West-Vlaanderen 8570",
    "addr:housenumber":"3",
    "addr:postcode":"8570",
    "addr:street":"Koornbloemstraat",
    "iso:country":"BE",
    "sg:address":"Koornbloemstraat 3",
    "sg:city":"Anzegem",
    "sg:orig_category":"Elektrische installaties voor woningen",
    "sg:phone":"+32 56 77 64 58",
    "sg:postcode":"8570",
    "sg:province":"West-Vlaanderen",
    "wof:name":"Patrick Luyckx",
    "wof:placetype":"venue"
},
  "geometry": {"coordinates":[3.4141619205,50.8371925354],"type":"Point"}
}