{
  "type": "Feature",
  "properties": {
    "addr:full":"Avenue Reine Astrid 131 Spa Li\u00e8ge 4900",
    "addr:housenumber":"131",
    "addr:postcode":"4900",
    "addr:street":"Avenue Reine Astrid",
    "iso:country":"BE",
    "sg:address":"Avenue Reine Astrid 131",
    "sg:city":"Spa",
    "sg:orig_category":"Artsen and specialisten",
    "sg:phone":"+32 87 77 41 61",
    "sg:postcode":"4900",
    "sg:province":"Li\u00e8ge",
    "wof:name":"Violette Jastrzebska",
    "wof:placetype":"venue"
},
  "geometry": {"coordinates":[5.8512539864,50.4909057617],"type":"Point"}
}