{
  "type": "Feature",
  "properties": {
    "iso:country":"BE",
    "sg:address":"Rue Marchovelette 19",
    "sg:city":"Namur",
    "sg:orig_category":"Rev\u00eatements de sols and murs. Rev\u00eatements pour sols and murs. Peinture",
    "sg:phone":"+32 81 22 28 21",
    "sg:postcode":"5000",
    "sg:province":"Namur",
    "wof:name":"Ets. Balaine",
    "wof:placetype":"venue"
},
  "geometry": {"coordinates":[4.8668961525,50.4626197815],"type":"Point"}
}