{
  "type": "Feature",
  "properties": {
    "iso:country":"BE",
    "sg:address":"Thier De Limbourg 58",
    "sg:city":"Limbourg",
    "sg:orig_category":"Belastingconsulenten Boekhouders Diverse juridische dienstverlening",
    "sg:phone":"+32 87 76 48 76",
    "sg:postcode":"4830",
    "sg:province":"Li\u00e8ge",
    "wof:name":"Arlette Lalemant",
    "wof:placetype":"venue"
},
  "geometry": {"coordinates":[5.9405407906,50.6134910583],"type":"Point"}
}