{
  "type": "Feature",
  "properties": {
    "addr:full":"Rue De Tamines 4 Fleurus Hainaut 6224",
    "addr:housenumber":"4",
    "addr:postcode":"6224",
    "addr:street":"Rue De Tamines",
    "iso:country":"BE",
    "sg:address":"Rue De Tamines 4",
    "sg:city":"Fleurus",
    "sg:orig_category":"Woningbouw",
    "sg:phone":"+32 71 81 77 04",
    "sg:postcode":"6224",
    "sg:province":"Hainaut",
    "wof:name":"Andrea Veneziano",
    "wof:placetype":"venue"
},
  "geometry": {"coordinates":[4.5866770744,50.4697227478],"type":"Point"}
}