{
  "type": "Feature",
  "properties": {
    "addr:full":"Niepkerkestraat 56 Heuvelland West-Vlaanderen 8950",
    "addr:housenumber":"56",
    "addr:postcode":"8950",
    "addr:street":"Niepkerkestraat",
    "iso:country":"BE",
    "sg:address":"Niepkerkestraat 56",
    "sg:city":"Heuvelland",
    "sg:orig_category":"Rundveehouders Varkenskwekers",
    "sg:phone":"+32 57 44 48 05",
    "sg:postcode":"8950",
    "sg:province":"West-Vlaanderen",
    "wof:name":"Michel Bacquart",
    "wof:placetype":"venue"
},
  "geometry": {"coordinates":[2.8319270611,50.7363815308],"type":"Point"}
}