{
  "type": "Feature",
  "properties": {
    "iso:country":"BE",
    "sg:address":"Hezewijk 37a",
    "sg:city":"Olen",
    "sg:classifiers":[
        {
            "category":"Food & Beverages",
            "subcategory":"Fruits & Vegetables",
            "type":"Retail Goods"
        }
    ],
    "sg:phone":"+32 14 26 33 62",
    "sg:postcode":"2250",
    "sg:province":"Antwerpen",
    "sg:tags":[
        "-"
    ],
    "wof:name":"Punthoef (de):bij Sabine",
    "wof:placetype":"venue"
},
  "geometry": {"coordinates":[4.8454141617,51.1485786438],"type":"Point"}
}