{
  "type": "Feature",
  "properties": {
    "addr:full":"Winnerstraat 12 Hechtel-eksel (eksel) Limburg 3941",
    "addr:housenumber":"12",
    "addr:postcode":"3941",
    "addr:street":"Winnerstraat",
    "iso:country":"BE",
    "sg:address":"Winnerstraat 12",
    "sg:city":"Hechtel-eksel (eksel)",
    "sg:classifiers":[
        {
            "category":"Community Center",
            "subcategory":"Youth",
            "type":"Public Place"
        }
    ],
    "sg:phone":"+32 11 73 47 86",
    "sg:postcode":"3941",
    "sg:province":"Limburg",
    "sg:tags":[
        "club"
    ],
    "wof:name":"Kamphoeve De Winner",
    "wof:placetype":"venue"
},
  "geometry": {"coordinates":[5.394862175,51.1539764404],"type":"Point"}
}