{
  "type": "Feature",
  "properties": {
    "iso:country":"BE",
    "sg:address":"Armand Segerslei 75",
    "sg:city":"Mortsel",
    "sg:orig_category":"Etalage- and showroomontwerpers",
    "sg:phone":"+32 3 448 36 57",
    "sg:postcode":"2640",
    "sg:province":"Antwerpen",
    "wof:name":"Luc Matthys",
    "wof:placetype":"venue"
},
  "geometry": {"coordinates":[4.4452991486,51.1705322266],"type":"Point"}
}