{
  "type": "Feature",
  "properties": {
    "addr:full":"Industrielaan 16-20 Ternat Vlaams-Brabant 1740",
    "addr:postcode":"16-20;1740",
    "addr:street":"Industrielaan",
    "iso:country":"BE",
    "sg:address":"Industrielaan 16-20",
    "sg:city":"Ternat",
    "sg:classifiers":[
        {
            "category":"Freight",
            "type":"Transportation"
        }
    ],
    "sg:phone":"+32 2 583 50 25",
    "sg:postcode":"1740",
    "sg:province":"Vlaams-Brabant",
    "sg:tags":[
        "-",
        "transport"
    ],
    "wof:name":"Tms-transport Management Services",
    "wof:placetype":"venue"
},
  "geometry": {"coordinates":[4.1788921356,50.8861808777],"type":"Point"}
}