{
  "type": "Feature",
  "properties": {
    "addr:full":"Edingseweg 138 Geraardsbergen Oost-Vlaanderen 9500",
    "addr:housenumber":"138",
    "addr:postcode":"9500",
    "addr:street":"Edingseweg",
    "iso:country":"BE",
    "sg:address":"Edingseweg 138",
    "sg:city":"Geraardsbergen",
    "sg:orig_category":"Entretien and r\u00e9parations de voitures",
    "sg:phone":"+32 54 41 68 98",
    "sg:postcode":"9500",
    "sg:province":"Oost-Vlaanderen",
    "wof:name":"Michel Richez",
    "wof:placetype":"venue"
},
  "geometry": {"coordinates":[3.8971400261,50.7698707581],"type":"Point"}
}