{
  "type": "Feature",
  "properties": {
    "addr:full":"Bakkerstraat 84 Zele Oost-Vlaanderen 9240",
    "addr:housenumber":"84",
    "addr:postcode":"9240",
    "addr:street":"Bakkerstraat",
    "iso:country":"BE",
    "sg:address":"Bakkerstraat 84",
    "sg:city":"Zele",
    "sg:orig_category":"P\u00e9pini\u00e9ristes. Articles de jardin. Fleurs and plantes",
    "sg:phone":"+32 52 44 41 07",
    "sg:postcode":"9240",
    "sg:province":"Oost-Vlaanderen",
    "wof:name":"Verheggen",
    "wof:placetype":"venue"
},
  "geometry": {"coordinates":[4.0619440079,51.0694541931],"type":"Point"}
}