{
  "type": "Feature",
  "properties": {
    "addr:full":"Zonnelaan 19 Meise Vlaams-Brabant 1860",
    "addr:housenumber":"19",
    "addr:postcode":"1860",
    "addr:street":"Zonnelaan",
    "iso:country":"BE",
    "sg:address":"Zonnelaan 19",
    "sg:city":"Meise",
    "sg:classifiers":[
        {
            "category":"Real Estate",
            "subcategory":"Architect",
            "type":"Services"
        }
    ],
    "sg:phone":"+32 2 270 05 59",
    "sg:postcode":"1860",
    "sg:province":"Vlaams-Brabant",
    "wof:name":"Mallefait C",
    "wof:placetype":"venue"
},
  "geometry": {"coordinates":[4.3232197762,50.9425849915],"type":"Point"}
}