{
  "type": "Feature",
  "properties": {
    "addr:full":"Kapellekensweg 65 Rotselaar Vlaams-Brabant 3111",
    "addr:housenumber":"65",
    "addr:postcode":"3111",
    "addr:street":"Kapellekensweg",
    "iso:country":"BE",
    "sg:address":"Kapellekensweg 65",
    "sg:city":"Rotselaar",
    "sg:orig_category":"Catering and organisatie van feesten",
    "sg:phone":"+32 16 58 33 50",
    "sg:postcode":"3111",
    "sg:province":"Vlaams-Brabant",
    "wof:name":"Christel Daman",
    "wof:placetype":"venue"
},
  "geometry": {"coordinates":[4.7642397881,50.9479446411],"type":"Point"}
}