{
  "type": "Feature",
  "properties": {
    "addr:full":"Haagdoornlaan 52 Kapellen Antwerpen 2950",
    "addr:housenumber":"52",
    "addr:postcode":"2950",
    "addr:street":"Haagdoornlaan",
    "iso:country":"BE",
    "sg:address":"Haagdoornlaan 52",
    "sg:city":"Kapellen",
    "sg:orig_category":"Experts-comptables",
    "sg:phone":"+32 3 665 17 76",
    "sg:postcode":"2950",
    "sg:province":"Antwerpen",
    "wof:name":"Guido Eulaers",
    "wof:placetype":"venue"
},
  "geometry": {"coordinates":[4.4360699654,51.324634552],"type":"Point"}
}