{
  "type": "Feature",
  "properties": {
    "addr:full":"Boulevard Ernest M\u00e9lot 9-12 Namur Namur 5000",
    "addr:housenumber":"9-12",
    "addr:postcode":"5000",
    "addr:street":"Boulevard Ernest Me\u0301Lot",
    "iso:country":"BE",
    "sg:address":"Boulevard Ernest M\u00e9lot 9-12",
    "sg:city":"Namur",
    "sg:classifiers":[
        {
            "category":"Communications",
            "subcategory":"Radio Station",
            "type":"Services"
        }
    ],
    "sg:phone":"+32 81 22 26 22",
    "sg:postcode":"5000",
    "sg:province":"Namur",
    "sg:tags":[
        "local"
    ],
    "wof:name":"Radio Nostalgie",
    "wof:placetype":"venue"
},
  "geometry": {"coordinates":[4.8609027863,50.4681129456],"type":"Point"}
}