{
  "type": "Feature",
  "properties": {
    "iso:country":"BE",
    "sg:address":"Keibosstraat 19",
    "sg:city":"Tielt",
    "sg:orig_category":"Rundveehouders Varkenskwekers",
    "sg:phone":"+32 51 63 39 27",
    "sg:postcode":"8700",
    "sg:province":"West-Vlaanderen",
    "wof:name":"Joris De Poorter",
    "wof:placetype":"venue"
},
  "geometry": {"coordinates":[3.406181097,50.9836235046],"type":"Point"}
}