{
  "type": "Feature",
  "properties": {
    "addr:full":"Stationlei 71 Vilvoorde Vlaams-Brabant 1800",
    "addr:housenumber":"71",
    "addr:postcode":"1800",
    "addr:street":"Stationlei",
    "iso:country":"BE",
    "sg:address":"Stationlei 71",
    "sg:city":"Vilvoorde",
    "sg:orig_category":"Non-Classified Establishments",
    "sg:phone":"+32 2 251 52 97",
    "sg:postcode":"1800",
    "sg:province":"Vlaams-Brabant",
    "wof:name":"Lisine Epstein Cosmetics Nv",
    "wof:placetype":"venue"
},
  "geometry": {"coordinates":[4.4311637878,50.9251556396],"type":"Point"}
}