{
  "type": "Feature",
  "properties": {
    "iso:country":"BE",
    "sg:address":"Klottenbergstraat 11",
    "sg:city":"Zoutleeuw",
    "sg:orig_category":"Eleveurs and marchands de porcs. Eleveurs de bovins",
    "sg:phone":"+32 11 58 76 04",
    "sg:postcode":"3440",
    "sg:province":"Vlaams-Brabant",
    "wof:name":"Emiel Willems",
    "wof:placetype":"venue"
},
  "geometry": {"coordinates":[5.0626392365,50.8677215576],"type":"Point"}
}