{
  "type": "Feature",
  "properties": {
    "iso:country":"BE",
    "sg:address":"Molenheide 6",
    "sg:city":"Wijnegem",
    "sg:orig_category":"M\u00e9decins and sp\u00e9cialistes",
    "sg:phone":"+32 3 354 00 38",
    "sg:postcode":"2110",
    "sg:province":"Antwerpen",
    "wof:name":"Ingrid Vissenberg",
    "wof:placetype":"venue"
},
  "geometry": {"coordinates":[4.5486040115,51.2257003784],"type":"Point"}
}