{
  "type": "Feature",
  "properties": {
    "addr:full":"Gansstraat 3 Zingem (huise) Oost-Vlaanderen 9750",
    "addr:housenumber":"3",
    "addr:postcode":"9750",
    "addr:street":"Gansstraat;Oost-Vlaanderen",
    "iso:country":"BE",
    "sg:address":"Gansstraat 3",
    "sg:city":"Zingem (huise)",
    "sg:classifiers":[
        {
            "category":"Personal",
            "subcategory":"Beauty Salon",
            "type":"Services"
        }
    ],
    "sg:phone":"+32 9 383 64 57",
    "sg:postcode":"9750",
    "sg:province":"Oost-Vlaanderen",
    "sg:tags":[
        "lady",
        "-",
        "hairdressing"
    ],
    "wof:name":"Claudine",
    "wof:placetype":"venue"
},
  "geometry": {"coordinates":[3.5814990997,50.9063568115],"type":"Point"}
}