{
  "type": "Feature",
  "properties": {
    "iso:country":"BE",
    "sg:address":"Avenue Du Panth\u00c9on 33b8",
    "sg:city":"Koekelberg",
    "sg:orig_category":"Avocats and conseillers juridiques",
    "sg:phone":"+32 2 415 85 45",
    "sg:postcode":"1081",
    "sg:province":"Bruxelles-Capitale",
    "wof:name":"Aim\u00c9 Kilolo Musamba Lubemba",
    "wof:placetype":"venue"
},
  "geometry": {"coordinates":[4.3225941658,50.8642044067],"type":"Point"}
}