{
  "type": "Feature",
  "properties": {
    "addr:full":"Gasstraat 21 Lommel Limburg 3920",
    "addr:housenumber":"21",
    "addr:postcode":"3920",
    "addr:street":"Gasstraat",
    "iso:country":"BE",
    "sg:address":"Gasstraat 21",
    "sg:city":"Lommel",
    "sg:classifiers":[
        {
            "category":"Health Services",
            "subcategory":"Health Practitioner",
            "type":"Services"
        }
    ],
    "sg:phone":"+32 11 54 08 10",
    "sg:postcode":"3920",
    "sg:province":"Limburg",
    "sg:tags":[
        "physiotherapist"
    ],
    "wof:name":"Bergmans Annemie",
    "wof:placetype":"venue"
},
  "geometry": {"coordinates":[5.3051848412,51.232131958],"type":"Point"}
}