{
  "type": "Feature",
  "properties": {
    "addr:full":"Rue Du M\u00c9ridien 32 Sint-joost-ten-node/saint-josse-ten-noode Bruxelles-Capitale 1210",
    "addr:housenumber":"32",
    "addr:postcode":"1210",
    "addr:street":"Rue Du Me\u0301Ridien",
    "iso:country":"BE",
    "sg:address":"Rue Du M\u00c9ridien 32",
    "sg:city":"Sint-joost-ten-node/saint-josse-ten-noode",
    "sg:orig_category":"Agences de publicit\u00e9",
    "sg:phone":"+32 2 217 48 61",
    "sg:postcode":"1210",
    "sg:province":"Bruxelles-Capitale",
    "wof:name":"Bureau Jordens",
    "wof:placetype":"venue"
},
  "geometry": {"coordinates":[4.3691601753,50.8539390564],"type":"Point"}
}