{
  "type": "Feature",
  "properties": {
    "addr:full":"Beverhoutsveldstraat 11 Beernem (oedelem) West-Vlaanderen 8730",
    "addr:housenumber":"11",
    "addr:postcode":"8730",
    "addr:street":"Beverhoutsveldstraat",
    "iso:country":"BE",
    "sg:address":"Beverhoutsveldstraat 11",
    "sg:city":"Beernem (oedelem)",
    "sg:classifiers":[
        {
            "category":"Landmark",
            "subcategory":"Fountain",
            "type":"Public Place"
        }
    ],
    "sg:phone":"+32 50 35 13 24",
    "sg:postcode":"8730",
    "sg:province":"West-Vlaanderen",
    "sg:tags":[
        "spring"
    ],
    "wof:name":"Vandermoere Bvba",
    "wof:placetype":"venue"
},
  "geometry": {"coordinates":[3.3034980297,51.1802101135],"type":"Point"}
}