{
  "type": "Feature",
  "properties": {
    "iso:country":"BE",
    "sg:address":"Rue Nihar 2",
    "sg:city":"Seraing",
    "sg:orig_category":"Rev\u00eatements pour sols and murs. Peinture",
    "sg:phone":"+32 4 231 21 96",
    "sg:postcode":"4101",
    "sg:province":"Li\u00e8ge",
    "wof:name":"D\u00c9cors Muraux",
    "wof:placetype":"venue"
},
  "geometry": {"coordinates":[5.5024080276,50.6135444641],"type":"Point"}
}