{
  "type": "Feature",
  "properties": {
    "iso:country":"BE",
    "sg:address":"Rue Du Midi 130",
    "sg:city":"Brussel/bruxelles",
    "sg:orig_category":"Timbres, monnaies and troph\u00e9es",
    "sg:phone":"+32 2 511 36 66",
    "sg:postcode":"1000",
    "sg:province":"Bruxelles-Capitale",
    "wof:name":"Roland De Groote",
    "wof:placetype":"venue"
},
  "geometry": {"coordinates":[4.3481178284,50.8444709778],"type":"Point"}
}