{
  "type": "Feature",
  "properties": {
    "addr:full":"Rue Du Bois De Samme 11 Braine-le-chateau Brabant Wallon 1440",
    "addr:housenumber":"11",
    "addr:postcode":"1440",
    "addr:street":"Rue Du Bois De Samme;Brabant Wallon",
    "iso:country":"BE",
    "sg:address":"Rue Du Bois De Samme 11",
    "sg:city":"Braine-le-chateau",
    "sg:orig_category":"Artsen and specialisten",
    "sg:phone":"+32 2 366 35 30",
    "sg:postcode":"1440",
    "sg:province":"Brabant Wallon",
    "wof:name":"N. Duhamel",
    "wof:placetype":"venue"
},
  "geometry": {"coordinates":[4.288465023,50.6661682129],"type":"Point"}
}