{
  "type": "Feature",
  "properties": {
    "addr:full":"Place Marie-jos\u00e9 6 Bruxelles (ixelles) Bruxelles-Capitale 1050",
    "addr:housenumber":"6",
    "addr:postcode":"1050",
    "addr:street":"Place Marie-Jose\u0301",
    "iso:country":"BE",
    "sg:address":"Place Marie-jos\u00e9 6",
    "sg:city":"Bruxelles (ixelles)",
    "sg:classifiers":[
        {
            "category":"Health Services",
            "subcategory":"Health Practitioner",
            "type":"Services"
        }
    ],
    "sg:phone":"+32 2 640 27 88",
    "sg:postcode":"1050",
    "sg:province":"Bruxelles-Capitale",
    "sg:tags":[
        "physiotherapist"
    ],
    "wof:name":"Lenoir A",
    "wof:placetype":"venue"
},
  "geometry": {"coordinates":[4.3875060081,50.8063049316],"type":"Point"}
}