{
  "type": "Feature",
  "properties": {
    "iso:country":"BE",
    "sg:address":"Rue Wery 91",
    "sg:city":"Elsene/ixelles",
    "sg:orig_category":"Studios photographiques",
    "sg:phone":"+32 2 648 25 47",
    "sg:postcode":"1050",
    "sg:province":"Bruxelles-Capitale",
    "wof:name":"Collin Ph.",
    "wof:placetype":"venue"
},
  "geometry": {"coordinates":[4.3756809235,50.8294906616],"type":"Point"}
}