{
  "type": "Feature",
  "properties": {
    "iso:country":"BE",
    "sg:address":"Gasstraat 3",
    "sg:city":"Middelkerke",
    "sg:orig_category":"Sportclubs",
    "sg:phone":"+32 59 31 01 29",
    "sg:postcode":"8430",
    "sg:province":"West-Vlaanderen",
    "wof:name":"B.c. Flandria Oostende",
    "wof:placetype":"venue"
},
  "geometry": {"coordinates":[2.8221559525,51.1846466064],"type":"Point"}
}