{
  "type": "Feature",
  "properties": {
    "iso:country":"BE",
    "sg:address":"Bo\u00eete Postale 287",
    "sg:city":"Tournai",
    "sg:classifiers":[
        {
            "category":"Shopping",
            "subcategory":"Beauty & Cosmetics",
            "type":"Retail Goods"
        }
    ],
    "sg:phone":"+32 70 22 28 24",
    "sg:postcode":"7500",
    "sg:province":"Hainaut",
    "sg:tags":[
        "-",
        "perfumery"
    ],
    "wof:name":"Daniel Jouvance",
    "wof:placetype":"venue"
},
  "geometry": {"coordinates":[3.3867199421,50.606098175],"type":"Point"}
}