{
  "type": "Feature",
  "properties": {
    "addr:full":"Rue Aux Fleurs 30-32 Brussel/bruxelles Bruxelles-Capitale 1000",
    "addr:postcode":"30-32;/ bruxelles;1000",
    "addr:street":"Rue Aux Fleurs",
    "iso:country":"BE",
    "sg:address":"Rue Aux Fleurs 30-32",
    "sg:city":"Brussel/bruxelles",
    "sg:orig_category":"Secr\u00e9tariats sociaux",
    "sg:phone":"+32 2 229 10 20",
    "sg:postcode":"1000",
    "sg:province":"Bruxelles-Capitale",
    "wof:name":"Assurances Sociales Conf\u00c9d\u00c9r\u00c9es",
    "wof:placetype":"venue"
},
  "geometry": {"coordinates":[4.3527951241,50.853263855],"type":"Point"}
}