{
  "type": "Feature",
  "properties": {
    "iso:country":"BE",
    "sg:address":"Terbeemden 43",
    "sg:city":"Tessenderlo",
    "sg:orig_category":"Sportclubs",
    "sg:phone":"+32 13 66 58 22",
    "sg:postcode":"3980",
    "sg:province":"Limburg",
    "wof:name":"Jong-rap & Kranig",
    "wof:placetype":"venue"
},
  "geometry": {"coordinates":[5.1372890472,51.0695075989],"type":"Point"}
}