{
  "type": "Feature",
  "properties": {
    "iso:country":"BE",
    "sg:address":"Rue Marianne 30",
    "sg:city":"Ukkel/uccle",
    "sg:orig_category":"Cr\u00e8ches and garderies d'enfants",
    "sg:phone":"+32 2 344 98 82",
    "sg:postcode":"1180",
    "sg:province":"Bruxelles-Capitale",
    "wof:name":"Touclet",
    "wof:placetype":"venue"
},
  "geometry": {"coordinates":[4.35272789,50.8130912781],"type":"Point"}
}