{
  "type": "Feature",
  "properties": {
    "addr:full":"Kwadeplasstraat 44ba Linter Vlaams-Brabant 3350",
    "addr:housenumber":"44ba",
    "addr:postcode":"3350",
    "addr:street":"Kwadeplasstraat;Vlaams-Brabant",
    "iso:country":"BE",
    "sg:address":"Kwadeplasstraat 44ba",
    "sg:city":"Linter",
    "sg:orig_category":"Advocaten and juridische adviseurs",
    "sg:phone":"+32 11 78 30 83",
    "sg:postcode":"3350",
    "sg:province":"Vlaams-Brabant",
    "wof:name":"Kristien Spiritus",
    "wof:placetype":"venue"
},
  "geometry": {"coordinates":[5.0643911362,50.8061676025],"type":"Point"}
}