{
  "type": "Feature",
  "properties": {
    "addr:full":"Rue Radache 104 Sambreville Namur 5060",
    "addr:housenumber":"104",
    "addr:postcode":"5060",
    "addr:street":"Rue Radache",
    "iso:country":"BE",
    "sg:address":"Rue Radache 104",
    "sg:city":"Sambreville",
    "sg:orig_category":"Avocats and conseillers juridiques",
    "sg:phone":"+32 71 77 38 21",
    "sg:postcode":"5060",
    "sg:province":"Namur",
    "wof:name":"J. Boxus",
    "wof:placetype":"venue"
},
  "geometry": {"coordinates":[4.6285200119,50.4448738098],"type":"Point"}
}