{
  "type": "Feature",
  "properties": {
    "addr:full":"Nindsebaan 47 Keerbergen Vlaams-Brabant 3140",
    "addr:housenumber":"47",
    "addr:postcode":"3140",
    "addr:street":"Nindsebaan",
    "iso:country":"BE",
    "sg:address":"Nindsebaan 47",
    "sg:city":"Keerbergen",
    "sg:orig_category":"Agences de presse",
    "sg:phone":"+32 15 73 01 10",
    "sg:postcode":"3140",
    "sg:province":"Vlaams-Brabant",
    "wof:name":"Gaby Feyaerts",
    "wof:placetype":"venue"
},
  "geometry": {"coordinates":[4.6600937843,50.9959754944],"type":"Point"}
}