{
  "type": "Feature",
  "properties": {
    "addr:full":"Rue Du Moulin 25 Rixensart Brabant Wallon 1330",
    "addr:housenumber":"25",
    "addr:postcode":"1330",
    "addr:street":"Rue Du Moulin;Wallon",
    "iso:country":"BE",
    "sg:address":"Rue Du Moulin 25",
    "sg:city":"Rixensart",
    "sg:classifiers":[
        {
            "category":"Building & Trades",
            "subcategory":"Pest Control",
            "type":"Services"
        }
    ],
    "sg:phone":"+32 2 653 42 60",
    "sg:postcode":"1330",
    "sg:province":"Brabant Wallon",
    "sg:tags":[
        "painting",
        "contractor"
    ],
    "wof:name":"Daubr\u00e9 P",
    "wof:placetype":"venue"
},
  "geometry": {"coordinates":[4.5102829933,50.7133140564],"type":"Point"}
}