{
  "type": "Feature",
  "properties": {
    "iso:country":"BE",
    "sg:address":"Lange Munte 51",
    "sg:city":"Oosterzele",
    "sg:orig_category":"Agences d'exp\u00e9dition",
    "sg:phone":"+32 9 362 31 62",
    "sg:postcode":"9860",
    "sg:province":"Oost-Vlaanderen",
    "wof:name":"R\u00c9bell",
    "wof:placetype":"venue"
},
  "geometry": {"coordinates":[3.7625000477,50.9229393005],"type":"Point"}
}