{
  "type": "Feature",
  "properties": {
    "iso:country":"BE",
    "sg:address":"Naamsesteenweg 112",
    "sg:city":"Leuven",
    "sg:orig_category":"Banques and organismes de cr\u00e9dit",
    "sg:phone":"+32 16 22 54 59",
    "sg:postcode":"3001",
    "sg:province":"Vlaams-Brabant",
    "wof:name":"Bacob",
    "wof:placetype":"venue"
},
  "geometry": {"coordinates":[4.6958441734,50.865486145],"type":"Point"}
}