{
  "type": "Feature",
  "properties": {
    "addr:full":"Kerkstraat 13 De Haan West-Vlaanderen 8420",
    "addr:housenumber":"13",
    "addr:postcode":"8420",
    "addr:street":"Kerkstraat",
    "iso:country":"BE",
    "sg:address":"Kerkstraat 13",
    "sg:city":"De Haan",
    "sg:orig_category":"Schoenen",
    "sg:phone":"+32 50 41 23 66",
    "sg:postcode":"8420",
    "sg:province":"West-Vlaanderen",
    "wof:name":"Stefaan De Vos",
    "wof:placetype":"venue"
},
  "geometry": {"coordinates":[3.079447031,51.3006706238],"type":"Point"}
}