{
  "type": "Feature",
  "properties": {
    "iso:country":"BE",
    "sg:address":"Boulevard De Waterloo 48",
    "sg:city":"Bruxelles",
    "sg:classifiers":[
        {
            "category":"Shopping",
            "subcategory":"Shoes",
            "type":"Retail Goods"
        }
    ],
    "sg:phone":"+32 2 511 61 80",
    "sg:postcode":"1000",
    "sg:province":"Bruxelles-Capitale",
    "sg:tags":[
        "slipper",
        "-"
    ],
    "wof:name":"Ferramoro Sa",
    "wof:placetype":"venue"
},
  "geometry": {"coordinates":[4.3567528725,50.8369445801],"type":"Point"}
}