{
  "type": "Feature",
  "properties": {
    "addr:full":"Kloosterstraat 4 Bilzen Limburg 3740",
    "addr:housenumber":"4",
    "addr:postcode":"3740",
    "addr:street":"Kloosterstraat",
    "iso:country":"BE",
    "sg:address":"Kloosterstraat 4",
    "sg:city":"Bilzen",
    "sg:orig_category":"Bloemen and planten",
    "sg:phone":"+32 89 41 71 03",
    "sg:postcode":"3740",
    "sg:province":"Limburg",
    "wof:name":"Ogenlust Bloembinderij",
    "wof:placetype":"venue"
},
  "geometry": {"coordinates":[5.5181808472,50.8711738586],"type":"Point"}
}