{
  "type": "Feature",
  "properties": {
    "addr:full":"Rue Houlteau 3 Herve (chaineux) Li\u00e8ge 4650",
    "addr:housenumber":"3",
    "addr:postcode":"4650",
    "addr:street":"Rue Houlteau",
    "iso:country":"BE",
    "sg:address":"Rue Houlteau 3",
    "sg:city":"Herve (chaineux)",
    "sg:classifiers":[
        {
            "category":"Wholesale",
            "subcategory":"Painting Supplies",
            "type":"Manufacturing & Wholesale Goods"
        }
    ],
    "sg:phone":"+32 87 44 67 03",
    "sg:postcode":"4650",
    "sg:province":"Li\u00e8ge",
    "sg:tags":[
        "industrial",
        "-"
    ],
    "wof:name":"Renson P",
    "wof:placetype":"venue"
},
  "geometry": {"coordinates":[5.8576021194,50.6312675476],"type":"Point"}
}