{
  "type": "Feature",
  "properties": {
    "addr:full":"Isidoor Van Beverenstraat 57 Dilbeek (groot - Bijgaarden) Vlaams-Brabant 1702",
    "addr:housenumber":"57;1702",
    "addr:street":"Isidoor Van Beverenstraat;Groot Bijgaarden Vlaams-Brabant",
    "iso:country":"BE",
    "sg:address":"Isidoor Van Beverenstraat 57",
    "sg:city":"Dilbeek (groot - Bijgaarden)",
    "sg:classifiers":[
        {
            "category":"Retail",
            "subcategory":"Animal Services",
            "type":"Services"
        }
    ],
    "sg:phone":"+32 2 521 75 23",
    "sg:postcode":"1702",
    "sg:province":"Vlaams-Brabant",
    "sg:tags":[
        "training",
        "dog"
    ],
    "wof:name":"Centre Canin-molenhof",
    "wof:placetype":"venue"
},
  "geometry": {"coordinates":[4.2628970146,50.8712081909],"type":"Point"}
}