{
  "type": "Feature",
  "properties": {
    "iso:country":"BE",
    "sg:address":"Avenue De L\u00b4informatique 9b",
    "sg:city":"Alleur",
    "sg:classifiers":[
        {
            "category":"Professional",
            "subcategory":"Computer Services",
            "type":"Services"
        }
    ],
    "sg:phone":"+32 4 239 91 50",
    "sg:postcode":"4432",
    "sg:province":"Li\u00e8ge",
    "sg:tags":[
        "microsoft"
    ],
    "wof:name":"Nsi",
    "wof:placetype":"venue"
},
  "geometry": {"coordinates":[5.5307478905,50.6737976074],"type":"Point"}
}