{
  "type": "Feature",
  "properties": {
    "addr:full":"Rue Saint-jean 11 Tournai Hainaut 7500",
    "addr:housenumber":"11",
    "addr:postcode":"7500",
    "addr:street":"Rue Saint-Jean",
    "iso:country":"BE",
    "sg:address":"Rue Saint-jean 11",
    "sg:city":"Tournai",
    "sg:orig_category":"Journaux. Tabac",
    "sg:phone":"+32 69 21 55 60",
    "sg:postcode":"7500",
    "sg:province":"Hainaut",
    "wof:name":"Librairie St-jean",
    "wof:placetype":"venue"
},
  "geometry": {"coordinates":[3.3978888988,50.6051139832],"type":"Point"}
}