{
  "type": "Feature",
  "properties": {
    "addr:full":"Eikenlaan 41 Wommelgem Antwerpen 2160",
    "addr:housenumber":"41",
    "addr:postcode":"2160",
    "addr:street":"Eikenlaan",
    "iso:country":"BE",
    "sg:address":"Eikenlaan 41",
    "sg:city":"Wommelgem",
    "sg:classifiers":[
        {
            "category":"Arena",
            "subcategory":"Sports Club",
            "type":"Entertainment"
        }
    ],
    "sg:phone":"+32 3 354 03 27",
    "sg:postcode":"2160",
    "sg:province":"Antwerpen",
    "sg:tags":[
        "de"
    ],
    "wof:name":"Chung Gun",
    "wof:placetype":"venue"
},
  "geometry": {"coordinates":[4.5281682014,51.2017021179],"type":"Point"}
}