{
  "type": "Feature",
  "properties": {
    "iso:country":"BE",
    "sg:address":"Rue Du Vivier 80",
    "sg:city":"Bastogne",
    "sg:classifiers":[
        {
            "category":"Banks & Credit Unions",
            "subcategory":"Bank",
            "type":"Services"
        }
    ],
    "sg:phone":"+32 62 21 54 01",
    "sg:postcode":"6650",
    "wof:name":"Caisse Nationale De, Cr\u00e9dit Professionnel",
    "wof:placetype":"venue"
},
  "geometry": {"coordinates":[5.7155008316,50.0006446838],"type":"Point"}
}