{
  "type": "Feature",
  "properties": {
    "iso:country":"BE",
    "sg:address":"Edingsesteenweg 392",
    "sg:city":"Ninove (denderwindeke)",
    "sg:classifiers":[
        {
            "category":"Shopping",
            "subcategory":"Clothing, Apparel, & Fashions",
            "type":"Retail Goods"
        }
    ],
    "sg:phone":"+32 54 33 44 45",
    "sg:postcode":"9400",
    "sg:province":"Oost-Vlaanderen",
    "sg:tags":[
        "boutique"
    ],
    "wof:name":"Pin-up Mode",
    "wof:placetype":"venue"
},
  "geometry": {"coordinates":[4.025370121,50.7972488403],"type":"Point"}
}