{
  "type": "Feature",
  "properties": {
    "addr:full":"Thomas Van Loostraat 59 Oostende West-Vlaanderen 8400",
    "addr:housenumber":"59",
    "addr:postcode":"8400",
    "addr:street":"Thomas Van Loostraat",
    "iso:country":"BE",
    "sg:address":"Thomas Van Loostraat 59",
    "sg:city":"Oostende",
    "sg:orig_category":"Opticiens",
    "sg:phone":"+32 59 32 39 91",
    "sg:postcode":"8400",
    "sg:province":"West-Vlaanderen",
    "wof:name":"Vancoppenolle Brillen",
    "wof:placetype":"venue"
},
  "geometry": {"coordinates":[2.9442689419,51.2303009033],"type":"Point"}
}