{
  "type": "Feature",
  "properties": {
    "iso:country":"BE",
    "sg:address":"Rue Blaes 49",
    "sg:city":"Brussel/bruxelles",
    "sg:orig_category":"Biens d'occasion",
    "sg:phone":"+32 2 512 12 99",
    "sg:postcode":"1000",
    "sg:province":"Bruxelles-Capitale",
    "wof:name":"Antik-blaes",
    "wof:placetype":"venue"
},
  "geometry": {"coordinates":[4.3496279716,50.8401107788],"type":"Point"}
}