{
  "type": "Feature",
  "properties": {
    "iso:country":"BE",
    "sg:address":"Roeselaarsestraat 55",
    "sg:city":"Moorslede",
    "sg:orig_category":"Rookartikelen",
    "sg:phone":"+32 51 77 70 82",
    "sg:postcode":"8890",
    "sg:province":"West-Vlaanderen",
    "wof:name":"Luc Beernaert",
    "wof:placetype":"venue"
},
  "geometry": {"coordinates":[3.0633049011,50.8931236267],"type":"Point"}
}