{
  "type": "Feature",
  "properties": {
    "addr:full":"Roodborstjestraat 8 Watermaal-bosvoorde/watermael-boitsfort Bruxelles-Capitale 1170",
    "addr:housenumber":"8",
    "addr:postcode":"1170",
    "addr:street":"Roodborstjestraat",
    "iso:country":"BE",
    "sg:address":"Roodborstjestraat 8",
    "sg:city":"Watermaal-bosvoorde/watermael-boitsfort",
    "sg:orig_category":"Organisatie van beurzen, congressen and tentoonstellingen Software ontwikkeling and ontwerp",
    "sg:phone":"+32 2 672 82 22",
    "sg:postcode":"1170",
    "sg:province":"Bruxelles-Capitale",
    "wof:name":"M.h.m. International",
    "wof:placetype":"venue"
},
  "geometry": {"coordinates":[4.4227838516,50.7904548645],"type":"Point"}
}