{
  "type": "Feature",
  "properties": {
    "addr:full":"Chauss\u00c9e D'alsemberg 962 Ukkel/uccle Bruxelles-Capitale 1180",
    "addr:housenumber":"962",
    "addr:postcode":"1180",
    "addr:street":"Chausse\u0301E D'Alsemberg;/",
    "iso:country":"BE",
    "sg:address":"Chauss\u00c9e D'alsemberg 962",
    "sg:city":"Ukkel/uccle",
    "sg:orig_category":"Benzinestations and brandstoffen",
    "sg:phone":"+32 2 376 81 15",
    "sg:postcode":"1180",
    "sg:province":"Bruxelles-Capitale",
    "wof:name":"Fina",
    "wof:placetype":"venue"
},
  "geometry": {"coordinates":[4.3336949348,50.7929534912],"type":"Point"}
}