{
  "type": "Feature",
  "properties": {
    "iso:country":"BE",
    "sg:address":"Picardstraat 68",
    "sg:city":"Sint-jans-molenbeek",
    "sg:orig_category":"Quincailleries",
    "sg:phone":"+32 2 428 71 28",
    "sg:postcode":"1080",
    "sg:province":"Bruxelles-Capitale",
    "wof:name":"Van Waasdijk",
    "wof:placetype":"venue"
},
  "geometry": {"coordinates":[4.3452410698,50.8635368347],"type":"Point"}
}