{
  "type": "Feature",
  "properties": {
    "iso:country":"BE",
    "sg:address":"Grote Peperstraat 16",
    "sg:city":"Sint-niklaas",
    "sg:classifiers":[
        {
            "category":"Education",
            "subcategory":"School",
            "type":"Public Place"
        }
    ],
    "sg:phone":"+32 3 760 41 20",
    "sg:postcode":"9100",
    "sg:province":"Oost-Vlaanderen",
    "sg:tags":[
        "secondary"
    ],
    "wof:name":"Instituut Berkenboom Humaniora",
    "wof:placetype":"venue"
},
  "geometry": {"coordinates":[4.1426649094,51.1633987427],"type":"Point"}
}