{
  "type": "Feature",
  "properties": {
    "addr:full":"Rue De La Liaison 28 Sint-lambrechts-woluwe/woluwe-saint-lambert Bruxelles-Capitale 1200",
    "addr:housenumber":"28",
    "addr:postcode":"1200",
    "addr:street":"Rue De La Liaison",
    "iso:country":"BE",
    "sg:address":"Rue De La Liaison 28",
    "sg:city":"Sint-lambrechts-woluwe/woluwe-saint-lambert",
    "sg:orig_category":"Administration d'immeubles",
    "sg:phone":"+32 2 771 56 64",
    "sg:postcode":"1200",
    "sg:province":"Bruxelles-Capitale",
    "wof:name":"Immo Colin",
    "wof:placetype":"venue"
},
  "geometry": {"coordinates":[4.4236149788,50.8441886902],"type":"Point"}
}