{
  "type": "Feature",
  "properties": {
    "addr:full":"Holeindestraat 19 Laarne Oost-Vlaanderen 9270",
    "addr:housenumber":"19",
    "addr:postcode":"9270",
    "addr:street":"Holeindestraat",
    "iso:country":"BE",
    "sg:address":"Holeindestraat 19",
    "sg:city":"Laarne",
    "sg:orig_category":"Paardenfokkers",
    "sg:phone":"+32 9 367 81 35",
    "sg:postcode":"9270",
    "sg:province":"Oost-Vlaanderen",
    "wof:name":"Stal Trojaan",
    "wof:placetype":"venue"
},
  "geometry": {"coordinates":[3.8879539967,51.0515480042],"type":"Point"}
}