{
  "type": "Feature",
  "properties": {
    "addr:full":"Hoogstraat 45 Bierbeek Vlaams-Brabant 3360",
    "addr:housenumber":"45",
    "addr:postcode":"3360",
    "addr:street":"Hoogstraat",
    "iso:country":"BE",
    "sg:address":"Hoogstraat 45",
    "sg:city":"Bierbeek",
    "sg:orig_category":"M\u00e9decins and sp\u00e9cialistes",
    "sg:phone":"+32 16 46 11 99",
    "sg:postcode":"3360",
    "sg:province":"Vlaams-Brabant",
    "wof:name":"G. De Brabander",
    "wof:placetype":"venue"
},
  "geometry": {"coordinates":[4.7499198914,50.8310813904],"type":"Point"}
}