{
  "type": "Feature",
  "properties": {
    "addr:full":"Langemarkstraat 51 Zonnebeke West-Vlaanderen 8980",
    "addr:housenumber":"51",
    "addr:postcode":"8980",
    "addr:street":"Langemarkstraat",
    "iso:country":"BE",
    "sg:address":"Langemarkstraat 51",
    "sg:city":"Zonnebeke",
    "sg:classifiers":[
        {
            "category":"Autos & Motor Vehicles",
            "subcategory":"Automobile Sales",
            "type":"Retail Goods"
        }
    ],
    "sg:phone":"+32 51 77 88 30",
    "sg:postcode":"8980",
    "sg:province":"West-Vlaanderen",
    "sg:tags":[
        "car",
        "used",
        "-"
    ],
    "wof:name":"Vanbesien Cv",
    "wof:placetype":"venue"
},
  "geometry": {"coordinates":[2.98320508,50.8754310608],"type":"Point"}
}