{
  "type": "Feature",
  "properties": {
    "iso:country":"BE",
    "sg:address":"Grand'rue 49",
    "sg:city":"Mont-saint-guibert",
    "sg:orig_category":"V\u00e9t\u00e9rinaires",
    "sg:phone":"+32 10 65 53 96",
    "sg:postcode":"1435",
    "sg:province":"Brabant Wallon",
    "wof:name":"Michel Debilderling",
    "wof:placetype":"venue"
},
  "geometry": {"coordinates":[4.6107521057,50.6339874268],"type":"Point"}
}