{
  "type": "Feature",
  "properties": {
    "addr:full":"Terkamerenstraat 33 Sint-pieters-woluwe/woluwe-saint-pierre Bruxelles-Capitale 1150",
    "addr:housenumber":"33",
    "addr:postcode":"1150",
    "addr:street":"Terkamerenstraat;/",
    "iso:country":"BE",
    "sg:address":"Terkamerenstraat 33",
    "sg:city":"Sint-pieters-woluwe/woluwe-saint-pierre",
    "sg:orig_category":"Advocaten and juridische adviseurs",
    "sg:phone":"+32 2 770 54 32",
    "sg:postcode":"1150",
    "sg:province":"Bruxelles-Capitale",
    "wof:name":"J.p. Willems",
    "wof:placetype":"venue"
},
  "geometry": {"coordinates":[4.4290819168,50.839176178],"type":"Point"}
}