{
  "type": "Feature",
  "properties": {
    "iso:country":"BE",
    "sg:address":"Stationsstraat 6",
    "sg:city":"Duffel",
    "sg:classifiers":[
        {
            "category":"Education",
            "subcategory":"School",
            "type":"Public Place"
        }
    ],
    "sg:phone":"+32 15 30 38 17",
    "sg:postcode":"2570",
    "sg:province":"Antwerpen",
    "sg:tags":[
        "secondary"
    ],
    "wof:name":"St-norbertusinstituut Aso-tso-bso",
    "wof:placetype":"venue"
},
  "geometry": {"coordinates":[4.4991440773,51.092300415],"type":"Point"}
}