{
  "type": "Feature",
  "properties": {
    "addr:full":"Route De Neufch\u00e2teau 475 Arlon (heinsch) Luxembourg 6700",
    "addr:housenumber":"475",
    "addr:postcode":"6700",
    "addr:street":"Route De Neufcha\u0302Teau",
    "iso:country":"BE",
    "sg:address":"Route De Neufch\u00e2teau 475",
    "sg:city":"Arlon (heinsch)",
    "sg:classifiers":[
        {
            "category":"Health Services",
            "subcategory":"Doctor",
            "type":"Services"
        }
    ],
    "sg:phone":"+32 63 22 38 09",
    "sg:postcode":"6700",
    "sg:province":"Luxembourg",
    "sg:tags":[
        "medicinephysicians",
        "surgeon"
    ],
    "wof:name":"Heintz Genevi\u00e8ve",
    "wof:placetype":"venue"
},
  "geometry": {"coordinates":[5.8042387962,49.689666748],"type":"Point"}
}