{
  "type": "Feature",
  "properties": {
    "addr:full":"Wolvertemsesteenweg 20ba Merchtem Vlaams-Brabant 1785",
    "addr:housenumber":"20ba",
    "addr:postcode":"1785",
    "addr:street":"Wolvertemsesteenweg",
    "iso:country":"BE",
    "sg:address":"Wolvertemsesteenweg 20ba",
    "sg:city":"Merchtem",
    "sg:classifiers":[
        {
            "category":"Food & Beverages",
            "subcategory":"Meat & Fish",
            "type":"Retail Goods"
        }
    ],
    "sg:phone":"+32 52 37 23 68",
    "sg:postcode":"1785",
    "sg:province":"Vlaams-Brabant",
    "sg:tags":[
        "vi",
        "zeevruchten"
    ],
    "wof:name":"Alfons Van Den Bossche",
    "wof:placetype":"venue"
},
  "geometry": {"coordinates":[4.2385020256,50.9601554871],"type":"Point"}
}