{
  "type": "Feature",
  "properties": {
    "addr:full":"Tervuursevest 13 Heverlee Vlaams-Brabant 3001",
    "addr:housenumber":"13",
    "addr:postcode":"3001",
    "addr:street":"Tervuursevest",
    "iso:country":"BE",
    "sg:address":"Tervuursevest 13",
    "sg:city":"Heverlee",
    "sg:orig_category":"Imprimeries and copyshops",
    "sg:phone":"+32 16 29 53 93",
    "sg:postcode":"3001",
    "sg:province":"Vlaams-Brabant",
    "wof:name":"Color Image",
    "wof:placetype":"venue"
},
  "geometry": {"coordinates":[4.6826858521,50.8765830994],"type":"Point"}
}