{
  "type": "Feature",
  "properties": {
    "addr:full":"Schoolstraat 51 Lokeren Oost-Vlaanderen 9160",
    "addr:housenumber":"51",
    "addr:postcode":"9160",
    "addr:street":"Schoolstraat",
    "iso:country":"BE",
    "sg:address":"Schoolstraat 51",
    "sg:city":"Lokeren",
    "sg:classifiers":[
        {
            "category":"Social Services",
            "type":"Services"
        }
    ],
    "sg:phone":"+32 9 348 82 99",
    "sg:postcode":"9160",
    "sg:province":"Oost-Vlaanderen",
    "wof:name":"Lokerse Integratiedienst",
    "wof:placetype":"venue"
},
  "geometry": {"coordinates":[3.9893488884,51.1020507812],"type":"Point"}
}