{
  "type": "Feature",
  "properties": {
    "iso:country":"BE",
    "sg:address":"Sallemeulekouter 44",
    "sg:city":"Merelbeke",
    "sg:classifiers":[
        {
            "category":"Professional",
            "subcategory":"Accounting & Tax Preparation",
            "type":"Services"
        }
    ],
    "sg:phone":"+32 9 363 83 83",
    "sg:postcode":"9820",
    "sg:province":"Oost-Vlaanderen",
    "sg:tags":[
        "bookkeeper"
    ],
    "wof:name":"Marbon Bvba",
    "wof:placetype":"venue"
},
  "geometry": {"coordinates":[3.7341880798,50.9757881165],"type":"Point"}
}