{
  "type": "Feature",
  "properties": {
    "addr:full":"Avenue De Burlet 4 Nivelles Brabant Wallon 1400",
    "addr:housenumber":"4",
    "addr:postcode":"1400",
    "addr:street":"Avenue De Burlet",
    "iso:country":"BE",
    "sg:address":"Avenue De Burlet 4",
    "sg:city":"Nivelles",
    "sg:orig_category":"Gevangenissen and strafinrichtingen",
    "sg:phone":"+32 67 89 51 00",
    "sg:postcode":"1400",
    "sg:province":"Brabant Wallon",
    "wof:name":"Prison",
    "wof:placetype":"venue"
},
  "geometry": {"coordinates":[4.3336901665,50.6016654968],"type":"Point"}
}