{
  "type": "Feature",
  "properties": {
    "iso:country":"BE",
    "sg:address":"Faubourg De Charleroi 15",
    "sg:city":"Nivelles",
    "sg:classifiers":[
        {
            "category":"Professional",
            "subcategory":"Credit Reporting & Collection",
            "type":"Services"
        }
    ],
    "sg:phone":"+32 67 84 20 84",
    "sg:postcode":"1400",
    "sg:province":"Brabant Wallon",
    "sg:tags":[
        "bailiff"
    ],
    "wof:name":"Cuisenaire M (mme)",
    "wof:placetype":"venue"
},
  "geometry": {"coordinates":[4.3271870613,50.5939559937],"type":"Point"}
}