{
  "type": "Feature",
  "properties": {
    "addr:full":"Mollekot 8 Sint-laureins Oost-Vlaanderen 9988",
    "addr:housenumber":"8",
    "addr:postcode":"9988",
    "addr:street":"Mollekot",
    "iso:country":"BE",
    "sg:address":"Mollekot 8",
    "sg:city":"Sint-laureins",
    "sg:orig_category":"Fruits and l\u00e9gumes Eleveurs de bovins",
    "sg:phone":"+32 9 379 83 02",
    "sg:postcode":"9988",
    "sg:province":"Oost-Vlaanderen",
    "wof:name":"Guido Pauwels",
    "wof:placetype":"venue"
},
  "geometry": {"coordinates":[3.6349630356,51.2857818604],"type":"Point"}
}