{
  "type": "Feature",
  "properties": {
    "addr:full":"Plateau De La Gare 39 Tubize Brabant Wallon 1480",
    "addr:housenumber":"39",
    "addr:postcode":"1480",
    "addr:street":"Plateau De La Gare;Wallon",
    "iso:country":"BE",
    "sg:address":"Plateau De La Gare 39",
    "sg:city":"Tubize",
    "sg:classifiers":[
        {
            "category":"Fast Food",
            "type":"Food & Drink"
        }
    ],
    "sg:phone":"+32 2 355 01 14",
    "sg:postcode":"1480",
    "sg:province":"Brabant Wallon",
    "sg:tags":[
        "meeneem",
        "restaurant"
    ],
    "wof:name":"Orient Express",
    "wof:placetype":"venue"
},
  "geometry": {"coordinates":[4.2049789429,50.6923332214],"type":"Point"}
}