{
  "type": "Feature",
  "properties": {
    "iso:country":"BE",
    "sg:address":"Grand\u00b4route 13",
    "sg:city":"Mont-saint-guibert",
    "sg:orig_category":"Diensten voor huisdieren",
    "sg:phone":"+32 10 65 06 75",
    "sg:postcode":"1435",
    "sg:province":"Brabant Wallon",
    "wof:name":"Toilettage Happy Dog",
    "wof:placetype":"venue"
},
  "geometry": {"coordinates":[4.6117048264,50.6352119446],"type":"Point"}
}