{
  "type": "Feature",
  "properties": {
    "iso:country":"BE",
    "sg:address":"Meir 58",
    "sg:city":"Buggenhout",
    "sg:classifiers":[
        {
            "category":"Health Services",
            "subcategory":"Health Practitioner",
            "type":"Services"
        }
    ],
    "sg:phone":"+32 52 35 00 66",
    "sg:postcode":"9255",
    "sg:province":"Oost-Vlaanderen",
    "sg:tags":[
        "physiotherapist"
    ],
    "wof:name":"Moonen M",
    "wof:placetype":"venue"
},
  "geometry": {"coordinates":[4.1833429337,50.9963493347],"type":"Point"}
}