{
  "type": "Feature",
  "properties": {
    "addr:full":"Hoogveld 53 Westerlo Antwerpen 2260",
    "addr:housenumber":"53",
    "addr:postcode":"2260",
    "addr:street":"Hoogveld",
    "iso:country":"BE",
    "sg:address":"Hoogveld 53",
    "sg:city":"Westerlo",
    "sg:orig_category":"Airconditioning and ventilatie Elektrische installaties voor woningen Loodgieterij, verwarming and s",
    "sg:phone":"+32 14 26 76 50",
    "sg:postcode":"2260",
    "sg:province":"Antwerpen",
    "wof:name":"Van Springel Technics",
    "wof:placetype":"venue"
},
  "geometry": {"coordinates":[4.8589057922,51.1306266785],"type":"Point"}
}