{
  "type": "Feature",
  "properties": {
    "addr:full":"Korte Gasthuisstraat 30 Antwerpen Antwerpen 2000",
    "addr:housenumber":"30",
    "addr:postcode":"2000",
    "addr:street":"Korte Gasthuisstraat",
    "iso:country":"BE",
    "sg:address":"Korte Gasthuisstraat 30",
    "sg:city":"Antwerpen",
    "sg:orig_category":"Bloemen and planten",
    "sg:phone":"+32 3 232 16 74",
    "sg:postcode":"2000",
    "sg:province":"Antwerpen",
    "wof:name":"Verhoogen",
    "wof:placetype":"venue"
},
  "geometry": {"coordinates":[4.4041857719,51.2167282104],"type":"Point"}
}