{
  "type": "Feature",
  "properties": {
    "addr:full":"Pl Bracquegnies La Louviere Hainaut 7110",
    "addr:postcode":"7110",
    "addr:street":"Pl Bracquegnies",
    "iso:country":"BE",
    "sg:address":"Pl Bracquegnies",
    "sg:city":"La Louviere",
    "sg:orig_category":"Enseignement maternel and primaire",
    "sg:phone":"+32 64 66 34 87",
    "sg:postcode":"7110",
    "sg:province":"Hainaut",
    "wof:name":"Ecole Fond. Communale",
    "wof:placetype":"venue"
},
  "geometry": {"coordinates":[4.1505050659,50.4826698303],"type":"Point"}
}