{
  "type": "Feature",
  "properties": {
    "addr:full":"Dikberd 29 Herentals Antwerpen 2200",
    "addr:housenumber":"29",
    "addr:postcode":"2200",
    "addr:street":"Dikberd",
    "iso:country":"BE",
    "sg:address":"Dikberd 29",
    "sg:city":"Herentals",
    "sg:orig_category":"Sportterreinen and installaties behalve sportcentra",
    "sg:phone":"+32 14 21 23 46",
    "sg:postcode":"2200",
    "sg:province":"Antwerpen",
    "wof:name":"Rawhide Ranch",
    "wof:placetype":"venue"
},
  "geometry": {"coordinates":[4.8518300056,51.1643600464],"type":"Point"}
}