{
  "type": "Feature",
  "properties": {
    "addr:full":"Tijmlaan 10 Waregem West-Vlaanderen 8790",
    "addr:housenumber":"10",
    "addr:postcode":"8790",
    "addr:street":"Tijmlaan",
    "iso:country":"BE",
    "sg:address":"Tijmlaan 10",
    "sg:city":"Waregem",
    "sg:orig_category":"Banken and kredietinstellingen",
    "sg:phone":"+32 56 60 42 29",
    "sg:postcode":"8790",
    "sg:province":"West-Vlaanderen",
    "wof:name":"Ippa",
    "wof:placetype":"venue"
},
  "geometry": {"coordinates":[3.4155709743,50.8933830261],"type":"Point"}
}