{
  "type": "Feature",
  "properties": {
    "iso:country":"BE",
    "sg:address":"Ieperstr 34",
    "sg:city":"Roeselare",
    "sg:classifiers":[
        {
            "category":"Banks & Credit Unions",
            "subcategory":"Bank",
            "type":"Services"
        }
    ],
    "sg:phone":"+32 51 20 56 70",
    "sg:postcode":"8800",
    "sg:province":"West-Vlaanderen",
    "wof:name":"Aslk-cger Bank",
    "wof:placetype":"venue"
},
  "geometry": {"coordinates":[3.1225600243,50.9424209595],"type":"Point"}
}