{
  "type": "Feature",
  "properties": {
    "iso:country":"BE",
    "sg:address":"Place Colignon 12",
    "sg:city":"Schaarbeek/schaerbeek",
    "sg:orig_category":"M\u00e9decins and sp\u00e9cialistes",
    "sg:phone":"+32 2 242 80 40",
    "sg:postcode":"1030",
    "sg:province":"Bruxelles-Capitale",
    "wof:name":"Polyclinique Schaerbeek",
    "wof:placetype":"venue"
},
  "geometry": {"coordinates":[4.3737211227,50.8669281006],"type":"Point"}
}