{
  "type": "Feature",
  "properties": {
    "iso:country":"BE",
    "sg:address":"Marktstraat 16",
    "sg:city":"Nieuwpoort",
    "sg:classifiers":[
        {
            "category":"Professional",
            "subcategory":"Credit Reporting & Collection",
            "type":"Services"
        }
    ],
    "sg:phone":"+32 58 23 44 10",
    "sg:postcode":"8620",
    "sg:province":"West-Vlaanderen",
    "sg:tags":[
        "bailiff"
    ],
    "wof:name":"Priem W",
    "wof:placetype":"venue"
},
  "geometry": {"coordinates":[2.7522859573,51.1315040588],"type":"Point"}
}