{
  "type": "Feature",
  "properties": {
    "iso:country":"BE",
    "sg:address":"Blaesstraat 158",
    "sg:city":"Brussel/bruxelles",
    "sg:classifiers":[
        {
            "category":"Shopping",
            "subcategory":"Clothing, Apparel, & Fashions",
            "type":"Retail Goods"
        }
    ],
    "sg:phone":"+32 2 513 36 48",
    "sg:postcode":"1000",
    "sg:province":"Bruxelles-Capitale",
    "sg:tags":[
        "ondergoed",
        "lingerie"
    ],
    "wof:name":"Patricia Shop",
    "wof:placetype":"venue"
},
  "geometry": {"coordinates":[4.3473291397,50.8375701904],"type":"Point"}
}