{
  "type": "Feature",
  "properties": {
    "iso:country":"BE",
    "sg:address":"Rue Roger Salengro 38",
    "sg:city":"Mouscron",
    "sg:classifiers":[
        {
            "category":"Wholesale",
            "subcategory":"Wine & Distilled Alcoholic Beverages",
            "type":"Manufacturing & Wholesale Goods"
        }
    ],
    "sg:phone":"+32 56 33 05 68",
    "sg:postcode":"7700",
    "sg:province":"Hainaut",
    "sg:tags":[
        "whol",
        "-",
        "spirit",
        "mfg"
    ],
    "wof:name":"Malfait M",
    "wof:placetype":"venue"
},
  "geometry": {"coordinates":[3.207834959,50.7468261719],"type":"Point"}
}