{
  "type": "Feature",
  "properties": {
    "addr:full":"Scheutlaan 231 Anderlecht Bruxelles-Capitale 1070",
    "addr:housenumber":"231",
    "addr:postcode":"1070",
    "addr:street":"Scheutlaan",
    "iso:country":"BE",
    "sg:address":"Scheutlaan 231",
    "sg:city":"Anderlecht",
    "sg:orig_category":"Benzinestations and brandstoffen Herstellingen and onderhoud van auto's Voertuigen",
    "sg:phone":"+32 2 523 13 69",
    "sg:postcode":"1070",
    "sg:province":"Bruxelles-Capitale",
    "wof:name":"Garage Donckerwolke/donckerwolke",
    "wof:placetype":"venue"
},
  "geometry": {"coordinates":[4.308825016,50.8473434448],"type":"Point"}
}