{
  "type": "Feature",
  "properties": {
    "addr:full":"Henri Bernard De Tracylaan 43 Gent (oostakker) Oost-Vlaanderen 9041",
    "addr:housenumber":"43",
    "addr:postcode":"9041",
    "addr:street":"Henri Bernard De Tracylaan",
    "iso:country":"BE",
    "sg:address":"Henri Bernard De Tracylaan 43",
    "sg:city":"Gent (oostakker)",
    "sg:classifiers":[
        {
            "category":"Real Estate",
            "subcategory":"Real Estate Services",
            "type":"Services"
        }
    ],
    "sg:phone":"+32 475 60 21 55",
    "sg:postcode":"9041",
    "sg:province":"Oost-Vlaanderen",
    "wof:name":"Intelect Bvba",
    "wof:placetype":"venue"
},
  "geometry": {"coordinates":[3.7644729614,51.0944824219],"type":"Point"}
}