{
  "type": "Feature",
  "properties": {
    "iso:country":"BE",
    "sg:address":"Korenbloemstraat 25",
    "sg:city":"Torhout",
    "sg:orig_category":"Sportclubs",
    "sg:phone":"+32 50 21 30 70",
    "sg:postcode":"8820",
    "sg:province":"West-Vlaanderen",
    "wof:name":"W.c. Rozeveldvrienden",
    "wof:placetype":"venue"
},
  "geometry": {"coordinates":[3.130685091,51.0818939209],"type":"Point"}
}