{
  "type": "Feature",
  "properties": {
    "iso:country":"BE",
    "sg:address":"Chemin \u00e0 Baraques 27g",
    "sg:city":"Mons",
    "sg:classifiers":[
        {
            "category":"Real Estate",
            "subcategory":"Architect",
            "type":"Services"
        }
    ],
    "sg:phone":"+32 65 31 59 63",
    "sg:postcode":"7000",
    "sg:province":"Hainaut",
    "wof:name":"De Meyer M",
    "wof:placetype":"venue"
},
  "geometry": {"coordinates":[3.9950840473,50.4496192932],"type":"Point"}
}