{
  "type": "Feature",
  "properties": {
    "addr:full":"Stationsstraat 55 Sint-niklaas Oost-Vlaanderen 9100",
    "addr:housenumber":"55",
    "addr:postcode":"9100",
    "addr:street":"Stationsstraat",
    "iso:country":"BE",
    "sg:address":"Stationsstraat 55",
    "sg:city":"Sint-niklaas",
    "sg:classifiers":[
        {
            "category":"Government",
            "subcategory":"Fire Station",
            "type":"Public Place"
        }
    ],
    "sg:phone":"+32 3 777 72 47",
    "sg:postcode":"9100",
    "sg:province":"Oost-Vlaanderen",
    "sg:tags":[
        "packard",
        "nec",
        "bell"
    ],
    "wof:name":"Photo-hall Sint-niklaas",
    "wof:placetype":"venue"
},
  "geometry": {"coordinates":[4.1419620514,51.1667480469],"type":"Point"}
}