{
  "type": "Feature",
  "properties": {
    "addr:full":"Avenue De Criel 3 Havelange Namur 5370",
    "addr:housenumber":"3",
    "addr:postcode":"5370",
    "addr:street":"Avenue De Criel",
    "iso:country":"BE",
    "sg:address":"Avenue De Criel 3",
    "sg:city":"Havelange",
    "sg:orig_category":"Artsen and specialisten",
    "sg:phone":"+32 83 63 34 48",
    "sg:postcode":"5370",
    "sg:province":"Namur",
    "wof:name":"Philippe Danthine",
    "wof:placetype":"venue"
},
  "geometry": {"coordinates":[5.2346038818,50.3864212036],"type":"Point"}
}