{
  "type": "Feature",
  "properties": {
    "addr:full":"Bruggestraat 132 Torhout West-Vlaanderen 8820",
    "addr:housenumber":"132",
    "addr:postcode":"8820",
    "addr:street":"Bruggestraat",
    "iso:country":"BE",
    "sg:address":"Bruggestraat 132",
    "sg:city":"Torhout",
    "sg:orig_category":"Huisvuilophaling and -verwerking",
    "sg:phone":"+32 50 22 17 33",
    "sg:postcode":"8820",
    "sg:province":"West-Vlaanderen",
    "wof:name":"Silvamo",
    "wof:placetype":"venue"
},
  "geometry": {"coordinates":[3.1131100655,51.079208374],"type":"Point"}
}