{
  "type": "Feature",
  "properties": {
    "iso:country":"BE",
    "sg:address":"Rue Du Papillon 97",
    "sg:city":"Seraing",
    "sg:orig_category":"Pharmaciens",
    "sg:phone":"+32 4 338 80 13",
    "sg:postcode":"4100",
    "sg:province":"Li\u00e8ge",
    "wof:name":"Pharmacie D\u00c9om",
    "wof:placetype":"venue"
},
  "geometry": {"coordinates":[5.5170798302,50.6023445129],"type":"Point"}
}