{
  "type": "Feature",
  "properties": {
    "addr:full":"Jules Peurquaetstraat 1 Oostende West-Vlaanderen 8400",
    "addr:housenumber":"1",
    "addr:postcode":"8400",
    "addr:street":"Peurquaetstraat",
    "iso:country":"BE",
    "sg:address":"Jules Peurquaetstraat 1",
    "sg:city":"Oostende",
    "sg:orig_category":"Immobili\u00ebnkantoren Verzekeringsmakelaars and experts",
    "sg:phone":"+32 59 50 39 59",
    "sg:postcode":"8400",
    "sg:province":"West-Vlaanderen",
    "wof:name":"Immo Novac",
    "wof:placetype":"venue"
},
  "geometry": {"coordinates":[2.9100821018,51.226524353],"type":"Point"}
}