{
  "type": "Feature",
  "properties": {
    "iso:country":"BE",
    "sg:address":"Veilinglaan 18",
    "sg:city":"Meise (wolvertem)",
    "sg:classifiers":[
        {
            "category":"Retail",
            "subcategory":"Auto Repair",
            "type":"Services"
        }
    ],
    "sg:phone":"+32 2 269 35 45",
    "sg:postcode":"1861",
    "sg:province":"Vlaams-Brabant",
    "sg:tags":[
        "automobile",
        "servic",
        "electrical",
        "-"
    ],
    "wof:name":"Sergoyne Bvba",
    "wof:placetype":"venue"
},
  "geometry": {"coordinates":[4.3038630486,50.9566116333],"type":"Point"}
}