{
  "type": "Feature",
  "properties": {
    "addr:full":"Rue Du Christ 73 Mouscron Hainaut 7700",
    "addr:housenumber":"73",
    "addr:postcode":"7700",
    "addr:street":"Rue Du Christ",
    "iso:country":"BE",
    "sg:address":"Rue Du Christ 73",
    "sg:city":"Mouscron",
    "sg:classifiers":[
        {
            "category":"Personal",
            "subcategory":"Beauty Salon",
            "type":"Services"
        }
    ],
    "sg:phone":"+32 56 84 09 08",
    "sg:postcode":"7700",
    "sg:province":"Hainaut",
    "sg:tags":[
        "lady",
        "-",
        "hairdressing"
    ],
    "wof:name":"Coste",
    "wof:placetype":"venue"
},
  "geometry": {"coordinates":[3.206897974,50.7438430786],"type":"Point"}
}