{
  "type": "Feature",
  "properties": {
    "addr:full":"Dageraadlaanplein 29 Antwerpen Antwerpen 2000",
    "addr:housenumber":"29",
    "addr:postcode":"2000",
    "addr:street":"Dageraadlaanplein",
    "iso:country":"BE",
    "sg:address":"Dageraadlaanplein 29",
    "sg:city":"Antwerpen",
    "sg:classifiers":[
        {
            "category":"Shopping",
            "subcategory":"Gifts & Souvenirs",
            "type":"Retail Goods"
        }
    ],
    "sg:phone":"+32 3 239 14 63",
    "sg:postcode":"2000",
    "sg:province":"Antwerpen",
    "sg:tags":[
        "geschenken"
    ],
    "wof:name":"Aters E",
    "wof:placetype":"venue"
},
  "geometry": {"coordinates":[4.3974518776,51.2216911316],"type":"Point"}
}