{
  "type": "Feature",
  "properties": {
    "iso:country":"BE",
    "sg:address":"Cuylitsstraat 119",
    "sg:city":"Antwerpen",
    "sg:classifiers":[
        {
            "category":"Real Estate",
            "subcategory":"Real Estate Services",
            "type":"Services"
        }
    ],
    "sg:phone":"+32 3 260 69 80",
    "sg:postcode":"2018",
    "sg:province":"Antwerpen",
    "wof:name":"Home-planning",
    "wof:placetype":"venue"
},
  "geometry": {"coordinates":[4.3899102211,51.2039604187],"type":"Point"}
}