{
  "type": "Feature",
  "properties": {
    "addr:full":"Westrozebekestraat 67 Staden West-Vlaanderen 8840",
    "addr:housenumber":"67",
    "addr:postcode":"8840",
    "addr:street":"Westrozebekestraat",
    "iso:country":"BE",
    "sg:address":"Westrozebekestraat 67",
    "sg:city":"Staden",
    "sg:orig_category":"Rev\u00eatements de sols and murs",
    "sg:phone":"+32 51 22 89 79",
    "sg:postcode":"8840",
    "sg:province":"West-Vlaanderen",
    "wof:name":"Wybaillie Steen-en Marmerbedrijf",
    "wof:placetype":"venue"
},
  "geometry": {"coordinates":[3.0495119095,50.9429244995],"type":"Point"}
}