{
  "type": "Feature",
  "properties": {
    "addr:full":"Ouwegemstraat 65 Belgium Oost-Vlaanderen 9750",
    "addr:housenumber":"65",
    "addr:postcode":"9750",
    "addr:street":"Ouwegemstraat;Oost-Vlaanderen",
    "iso:country":"BE",
    "sg:address":"Ouwegemstraat 65",
    "sg:city":"Belgium",
    "sg:orig_category":"Machines and mat\u00e9riel de bureau Fournitures de bureau. Syst\u00e8mes de t\u00e9l\u00e9communications. Ordinateurs a",
    "sg:phone":"+32 9 384 46 55",
    "sg:postcode":"9750",
    "sg:province":"Oost-Vlaanderen",
    "wof:name":"Geurs Office Equipment",
    "wof:placetype":"venue"
},
  "geometry": {"coordinates":[3.5980210304,50.9188423157],"type":"Point"}
}