{
  "type": "Feature",
  "properties": {
    "addr:full":"Hoogstraat 9 Mechelen Antwerpen 2800",
    "addr:housenumber":"9",
    "addr:postcode":"2800",
    "addr:street":"Hoogstraat",
    "iso:country":"BE",
    "sg:address":"Hoogstraat 9",
    "sg:city":"Mechelen",
    "sg:orig_category":"Agences d\u00b4interim and personnel temporaire",
    "sg:phone":"+32 15 41 82 92",
    "sg:postcode":"2800",
    "sg:province":"Antwerpen",
    "wof:name":"Action Interim",
    "wof:placetype":"venue"
},
  "geometry": {"coordinates":[4.4786200523,51.0240097046],"type":"Point"}
}