{
  "type": "Feature",
  "properties": {
    "iso:country":"BE",
    "sg:address":"Bld Emile Schevenels 17",
    "sg:city":"Lessines",
    "sg:orig_category":"V\u00e9t\u00e9rinaires",
    "sg:phone":"+32 68 33 86 17",
    "sg:postcode":"7860",
    "sg:province":"Hainaut",
    "wof:name":"Patrice Vermeulen",
    "wof:placetype":"venue"
},
  "geometry": {"coordinates":[3.8249149323,50.711315155],"type":"Point"}
}