{
  "type": "Feature",
  "properties": {
    "addr:full":"Koningsstraat 197 Sint-joost-ten-node/saint-josse-ten-noode Bruxelles-Capitale 1210",
    "addr:housenumber":"197",
    "addr:postcode":"1210",
    "addr:street":"Koningsstraat;Sint-Joost-Ten-Node /",
    "iso:country":"BE",
    "sg:address":"Koningsstraat 197",
    "sg:city":"Sint-joost-ten-node/saint-josse-ten-noode",
    "sg:orig_category":"Kapsalons",
    "sg:phone":"+32 2 217 12 09",
    "sg:postcode":"1210",
    "sg:province":"Bruxelles-Capitale",
    "wof:name":"Coiffure Royale",
    "wof:placetype":"venue"
},
  "geometry": {"coordinates":[4.3666501045,50.8549041748],"type":"Point"}
}