{
  "type": "Feature",
  "properties": {
    "addr:full":"Spechtenstraat 14 Hechtel-eksel (hechtel) Limburg 3940",
    "addr:housenumber":"14",
    "addr:postcode":"3940",
    "addr:street":"Spechtenstraat",
    "iso:country":"BE",
    "sg:address":"Spechtenstraat 14",
    "sg:city":"Hechtel-eksel (hechtel)",
    "sg:classifiers":[
        {
            "category":"Building & Trades",
            "subcategory":"Equipment Rental",
            "type":"Services"
        }
    ],
    "sg:phone":"+32 11 66 77 24",
    "sg:postcode":"3940",
    "sg:province":"Limburg",
    "sg:tags":[
        "use",
        "apparatus",
        "tool",
        "-",
        "professional",
        "machines"
    ],
    "wof:name":"Cleanmat Belgium",
    "wof:placetype":"venue"
},
  "geometry": {"coordinates":[5.364795208,51.1255340576],"type":"Point"}
}