{
  "type": "Feature",
  "properties": {
    "addr:full":"Lepelstraat 2 Vorselaar Antwerpen 2290",
    "addr:housenumber":"2",
    "addr:postcode":"2290",
    "addr:street":"Lepelstraat",
    "iso:country":"BE",
    "sg:address":"Lepelstraat 2",
    "sg:city":"Vorselaar",
    "sg:orig_category":"Hoger onderwijs",
    "sg:phone":"+32 14 50 93 11",
    "sg:postcode":"2290",
    "sg:province":"Antwerpen",
    "wof:name":"K.h.k.-kard. Van Roey",
    "wof:placetype":"venue"
},
  "geometry": {"coordinates":[4.7727069855,51.2011070251],"type":"Point"}
}