{
  "type": "Feature",
  "properties": {
    "iso:country":"BE",
    "sg:address":"Doornzelestraat 29",
    "sg:city":"Lochristi",
    "sg:orig_category":"Bloemen and planten Gh",
    "sg:phone":"+32 9 355 65 81",
    "sg:postcode":"9080",
    "sg:province":"Oost-Vlaanderen",
    "wof:name":"De Schoenmacker",
    "wof:placetype":"venue"
},
  "geometry": {"coordinates":[3.8147580624,51.1155891418],"type":"Point"}
}