{
  "type": "Feature",
  "properties": {
    "iso:country":"BE",
    "sg:address":"Tiensestraat 199",
    "sg:city":"Leuven",
    "sg:classifiers":[
        {
            "category":"Arena",
            "subcategory":"Sports Club",
            "type":"Entertainment"
        }
    ],
    "sg:phone":"+32 16 29 36 96",
    "sg:postcode":"3000",
    "sg:province":"Vlaams-Brabant",
    "wof:name":"Kungfu Wushu",
    "wof:placetype":"venue"
},
  "geometry": {"coordinates":[4.7117037773,50.874584198],"type":"Point"}
}