{
  "type": "Feature",
  "properties": {
    "iso:country":"BE",
    "sg:address":"Rue De La P\u00cacherie 40",
    "sg:city":"Ukkel/uccle",
    "sg:classifiers":[
        {
            "category":"Restaurant",
            "type":"Food & Drink"
        }
    ],
    "sg:phone":"+32 2 375 07 67",
    "sg:postcode":"1180",
    "sg:province":"Bruxelles-Capitale",
    "wof:name":"Casse-noisette",
    "wof:placetype":"venue"
},
  "geometry": {"coordinates":[4.360147953,50.793926239],"type":"Point"}
}