{
  "type": "Feature",
  "properties": {
    "iso:country":"BE",
    "sg:address":"Konijnestraat 130",
    "sg:city":"Sint-pieters-leeuw",
    "sg:orig_category":"Producteurs de fruits",
    "sg:phone":"+32 2 569 11 55",
    "sg:postcode":"1602",
    "sg:province":"Vlaams-Brabant",
    "wof:name":"Line Stock",
    "wof:placetype":"venue"
},
  "geometry": {"coordinates":[4.2164268494,50.8074264526],"type":"Point"}
}