{
  "type": "Feature",
  "properties": {
    "iso:country":"BE",
    "sg:address":"Molenstraat 10-12",
    "sg:city":"Zomergem",
    "sg:orig_category":"Quincailleries. Installation de menuiserie en bois and plastique. Fabrication and montage de mobilie",
    "sg:phone":"+32 9 372 72 45",
    "sg:postcode":"9930",
    "sg:province":"Oost-Vlaanderen",
    "wof:name":"De Bruyne",
    "wof:placetype":"venue"
},
  "geometry": {"coordinates":[3.5576078892,51.1120605469],"type":"Point"}
}