{
  "type": "Feature",
  "properties": {
    "iso:country":"BE",
    "sg:address":"Frumont 7",
    "sg:city":"Onhaye",
    "sg:orig_category":"M\u00e9decins and sp\u00e9cialistes",
    "sg:phone":"+32 82 64 47 36",
    "sg:postcode":"5520",
    "sg:province":"Namur",
    "wof:name":"T. Mathelart",
    "wof:placetype":"venue"
},
  "geometry": {"coordinates":[4.8431158066,50.2382202148],"type":"Point"}
}