{
  "type": "Feature",
  "properties": {
    "addr:full":"Rootenstraat 11 Genk Limburg 3600",
    "addr:housenumber":"11",
    "addr:postcode":"3600",
    "addr:street":"Rootenstraat",
    "iso:country":"BE",
    "sg:address":"Rootenstraat 11",
    "sg:city":"Genk",
    "sg:orig_category":"V\u00eatements de mariage and c\u00e9r\u00e9monies",
    "sg:phone":"+32 89 36 29 65",
    "sg:postcode":"3600",
    "sg:province":"Limburg",
    "wof:name":"Lieben Bruids- & Feestkleding",
    "wof:placetype":"venue"
},
  "geometry": {"coordinates":[5.5028338432,50.9652481079],"type":"Point"}
}