{
  "type": "Feature",
  "properties": {
    "addr:full":"Rue Spintay 41 Verviers Li\u00e8ge 4800",
    "addr:housenumber":"41",
    "addr:postcode":"4800",
    "addr:street":"Rue Spintay",
    "iso:country":"BE",
    "sg:address":"Rue Spintay 41",
    "sg:city":"Verviers",
    "sg:classifiers":[
        {
            "category":"Shopping",
            "subcategory":"Books",
            "type":"Retail Goods"
        }
    ],
    "sg:phone":"+32 87 33 15 16",
    "sg:postcode":"4800",
    "sg:province":"Li\u00e8ge",
    "sg:tags":[
        "diary",
        "note-books"
    ],
    "wof:name":"Plumhans G Ets",
    "wof:placetype":"venue"
},
  "geometry": {"coordinates":[5.8594508171,50.5917663574],"type":"Point"}
}