{
  "type": "Feature",
  "properties": {
    "addr:full":"Dorpsstraat 41 Horebeke Oost-Vlaanderen 9667",
    "addr:housenumber":"41",
    "addr:postcode":"9667",
    "addr:street":"Dorpsstraat",
    "iso:country":"BE",
    "sg:address":"Dorpsstraat 41",
    "sg:city":"Horebeke",
    "sg:orig_category":"Pain, p\u00e2tisseries and confiseries",
    "sg:phone":"+32 55 45 68 32",
    "sg:postcode":"9667",
    "sg:province":"Oost-Vlaanderen",
    "wof:name":"Bakkerij Philip",
    "wof:placetype":"venue"
},
  "geometry": {"coordinates":[3.6865611076,50.8370552063],"type":"Point"}
}