{
  "type": "Feature",
  "properties": {
    "iso:country":"BE",
    "sg:address":"Meulebekestraat 95",
    "sg:city":"Pittem",
    "sg:orig_category":"Elektrische installaties voor woningen",
    "sg:phone":"+32 51 46 43 28",
    "sg:postcode":"8740",
    "sg:province":"West-Vlaanderen",
    "wof:name":"Elektro Decadt Rik",
    "wof:placetype":"venue"
},
  "geometry": {"coordinates":[3.2685830593,50.981754303],"type":"Point"}
}