{
  "type": "Feature",
  "properties": {
    "addr:full":"Rue Des Martyrs 13 Arlon Luxembourg 6700",
    "addr:housenumber":"13",
    "addr:postcode":"6700",
    "addr:street":"Rue Des Martyrs",
    "iso:country":"BE",
    "sg:address":"Rue Des Martyrs 13",
    "sg:city":"Arlon",
    "sg:orig_category":"Mus\u00e9es and patrimoine culturel",
    "sg:phone":"+32 63 22 61 92",
    "sg:postcode":"6700",
    "sg:province":"Luxembourg",
    "wof:name":"Mus\u00c9e Luxembourgeois",
    "wof:placetype":"venue"
},
  "geometry": {"coordinates":[5.8108949661,49.6839790344],"type":"Point"}
}