{
  "type": "Feature",
  "properties": {
    "addr:full":"Kapelstraat 46a Wuustwezel (loenhout) Antwerpen 2990",
    "addr:housenumber":"46a",
    "addr:postcode":"2990",
    "addr:street":"Kapelstraat",
    "iso:country":"BE",
    "sg:address":"Kapelstraat 46a",
    "sg:city":"Wuustwezel (loenhout)",
    "sg:classifiers":[
        {
            "category":"Shopping",
            "subcategory":"Clothing, Apparel, & Fashions",
            "type":"Retail Goods"
        }
    ],
    "sg:phone":"+32 3 669 62 30",
    "sg:postcode":"2990",
    "sg:province":"Antwerpen",
    "sg:tags":[
        "-",
        "clothing",
        "child"
    ],
    "wof:name":"Sjapooke",
    "wof:placetype":"venue"
},
  "geometry": {"coordinates":[4.6468629837,51.3999900818],"type":"Point"}
}