{
  "type": "Feature",
  "properties": {
    "iso:country":"BE",
    "sg:address":"Markt 10",
    "sg:city":"Kasterlee",
    "sg:classifiers":[
        {
            "category":"Fast Food",
            "type":"Food & Drink"
        }
    ],
    "sg:phone":"+32 14 85 05 89",
    "sg:postcode":"2460",
    "sg:province":"Antwerpen",
    "sg:tags":[
        "\u00c0",
        "emporter",
        "restaurants"
    ],
    "wof:name":"Intro",
    "wof:placetype":"venue"
},
  "geometry": {"coordinates":[4.9682798386,51.2408676147],"type":"Point"}
}