{
  "type": "Feature",
  "properties": {
    "addr:full":"Holven 89 Balen Antwerpen 2490",
    "addr:housenumber":"89",
    "addr:postcode":"2490",
    "addr:street":"Holven",
    "iso:country":"BE",
    "sg:address":"Holven 89",
    "sg:city":"Balen",
    "sg:orig_category":"Schoonmaakbedrijven and ongediertebestrijding",
    "sg:phone":"+32 14 82 80 68",
    "sg:postcode":"2490",
    "sg:province":"Antwerpen",
    "wof:name":"Van Moeseke",
    "wof:placetype":"venue"
},
  "geometry": {"coordinates":[5.1566381454,51.1620483398],"type":"Point"}
}