{
  "type": "Feature",
  "properties": {
    "iso:country":"BE",
    "sg:address":"Rue Du Poivre 28",
    "sg:city":"Renaix",
    "sg:classifiers":[
        {
            "category":"Bakery",
            "type":"Food & Drink"
        }
    ],
    "sg:phone":"+32 55 21 13 86",
    "sg:postcode":"9600",
    "sg:province":"Oost-Vlaanderen",
    "sg:tags":[
        "confectioner",
        "baker"
    ],
    "wof:name":"Vannieuwenhuyse F",
    "wof:placetype":"venue"
},
  "geometry": {"coordinates":[3.6008930206,50.7471466064],"type":"Point"}
}