{
  "type": "Feature",
  "properties": {
    "addr:full":"Oudergemselaan 291 Etterbeek Bruxelles-Capitale 1040",
    "addr:housenumber":"291",
    "addr:postcode":"1040",
    "addr:street":"Oudergemselaan",
    "iso:country":"BE",
    "sg:address":"Oudergemselaan 291",
    "sg:city":"Etterbeek",
    "sg:orig_category":"Dakwerken Loodgieterij, verwarming and sanitaire installaties Plaatsen van vloer- and muurbekleding ",
    "sg:phone":"+32 2 646 76 27",
    "sg:postcode":"1040",
    "sg:province":"Bruxelles-Capitale",
    "wof:name":"D. Sintobin",
    "wof:placetype":"venue"
},
  "geometry": {"coordinates":[4.3893179893,50.8316688538],"type":"Point"}
}