{
  "type": "Feature",
  "properties": {
    "iso:country":"BE",
    "sg:address":"Sentier Baribant 3",
    "sg:city":"Fernelmont",
    "sg:orig_category":"Woningbouw",
    "sg:phone":"+32 81 21 46 90",
    "sg:postcode":"5380",
    "sg:province":"Namur",
    "wof:name":"Didier Swinnen",
    "wof:placetype":"venue"
},
  "geometry": {"coordinates":[4.940513134,50.5204238892],"type":"Point"}
}