{
  "type": "Feature",
  "properties": {
    "iso:country":"BE",
    "sg:address":"Chauss\u00c9e De Waterloo 190",
    "sg:city":"Saint-gilles",
    "sg:orig_category":"Epiceries",
    "sg:phone":"+32 2 538 89 51",
    "sg:postcode":"1060",
    "sg:province":"Bruxelles-Capitale",
    "wof:name":"Night Shops Balal",
    "wof:placetype":"venue"
},
  "geometry": {"coordinates":[4.3445987701,50.8272514343],"type":"Point"}
}