{
  "type": "Feature",
  "properties": {
    "iso:country":"BE",
    "sg:address":"Avenue H. Conscience 24",
    "sg:city":"Evere",
    "sg:orig_category":"Vertalers and tolken",
    "sg:phone":"+32 2 215 93 74",
    "sg:postcode":"1140",
    "sg:province":"Bruxelles-Capitale",
    "wof:name":"Federova O. Cbtip/bkvtf",
    "wof:placetype":"venue"
},
  "geometry": {"coordinates":[4.3981580734,50.8668479919],"type":"Point"}
}