{
  "type": "Feature",
  "properties": {
    "addr:full":"Zeeweg 38 Jabbeke West-Vlaanderen 8490",
    "addr:housenumber":"38",
    "addr:postcode":"8490",
    "addr:street":"Zeeweg",
    "iso:country":"BE",
    "sg:address":"Zeeweg 38",
    "sg:city":"Jabbeke",
    "sg:orig_category":"Artsen and specialisten",
    "sg:phone":"+32 50 31 60 58",
    "sg:postcode":"8490",
    "sg:province":"West-Vlaanderen",
    "wof:name":"Philip Van Canneyt",
    "wof:placetype":"venue"
},
  "geometry": {"coordinates":[3.1535420418,51.1857528687],"type":"Point"}
}