{
  "type": "Feature",
  "properties": {
    "addr:full":"Franslaan 172 Nieuwpoort West-Vlaanderen 8620",
    "addr:housenumber":"172",
    "addr:postcode":"8620",
    "addr:street":"Franslaan",
    "iso:country":"BE",
    "sg:address":"Franslaan 172",
    "sg:city":"Nieuwpoort",
    "sg:classifiers":[
        {
            "category":"Personal",
            "subcategory":"Beauty Salon",
            "type":"Services"
        }
    ],
    "sg:phone":"+32 58 23 97 42",
    "sg:postcode":"8620",
    "sg:province":"West-Vlaanderen",
    "sg:tags":[
        "de",
        "coiffure"
    ],
    "wof:name":"Coiffure Lady N",
    "wof:placetype":"venue"
},
  "geometry": {"coordinates":[2.7067079544,51.1433105469],"type":"Point"}
}