{
  "type": "Feature",
  "properties": {
    "addr:full":"Hulgenrodestraat 57 Borsbeek Antwerpen 2150",
    "addr:housenumber":"57",
    "addr:postcode":"2150",
    "addr:street":"Hulgenrodestraat",
    "iso:country":"BE",
    "sg:address":"Hulgenrodestraat 57",
    "sg:city":"Borsbeek",
    "sg:orig_category":"Ordinateurs and \u00e9quipement informatique. Entretien and r\u00e9parations de machines de bureau and ordinat",
    "sg:phone":"+32 3 322 70 78",
    "sg:postcode":"2150",
    "sg:province":"Antwerpen",
    "wof:name":"New-media",
    "wof:placetype":"venue"
},
  "geometry": {"coordinates":[4.4948182106,51.1916122437],"type":"Point"}
}