{
  "type": "Feature",
  "properties": {
    "addr:full":"Rue De L'yser 3 Ronse/renaix Oost-Vlaanderen 9600",
    "addr:housenumber":"3",
    "addr:postcode":"9600",
    "addr:street":"Rue De L'Yser",
    "iso:country":"BE",
    "sg:address":"Rue De L'yser 3",
    "sg:city":"Ronse/renaix",
    "sg:classifiers":[
        {
            "category":"Cafe",
            "type":"Food & Drink"
        }
    ],
    "sg:phone":"+32 55 20 82 43",
    "sg:postcode":"9600",
    "sg:province":"Oost-Vlaanderen",
    "sg:tags":[
        "caf\u00e9s"
    ],
    "wof:name":"Jean-marie Bufkens",
    "wof:placetype":"venue"
},
  "geometry": {"coordinates":[3.6029059887,50.7429351807],"type":"Point"}
}