{
  "type": "Feature",
  "properties": {
    "addr:full":"Keiberg 95 Zwevegem 8552",
    "addr:housenumber":"95",
    "addr:postcode":"8552",
    "addr:street":"Keiberg",
    "iso:country":"BE",
    "sg:address":"Keiberg 95",
    "sg:city":"Zwevegem",
    "sg:orig_category":"Bloemen and planten Gh Groententeelt",
    "sg:phone":"+32 56 64 70 02",
    "sg:postcode":"8552",
    "wof:name":"Cottenier",
    "wof:placetype":"venue"
},
  "geometry": {"coordinates":[3.3771378994,50.7896118164],"type":"Point"}
}