{
  "type": "Feature",
  "properties": {
    "addr:full":"Chauss\u00e9e De Nivelles 6 Gembloux-sur-orneau (mazy) Namur 5032",
    "addr:housenumber":"6",
    "addr:postcode":"5032",
    "addr:street":"Chausse\u0301E De Nivelles;Mazy",
    "iso:country":"BE",
    "sg:address":"Chauss\u00e9e De Nivelles 6",
    "sg:city":"Gembloux-sur-orneau (mazy)",
    "sg:classifiers":[
        {
            "category":"Personal",
            "subcategory":"Beauty Salon",
            "type":"Services"
        }
    ],
    "sg:phone":"+32 81 63 44 49",
    "sg:postcode":"5032",
    "sg:province":"Namur",
    "sg:tags":[
        "lady",
        "-",
        "hairdressing"
    ],
    "wof:name":"Catherine D (coiffure)",
    "wof:placetype":"venue"
},
  "geometry": {"coordinates":[4.6769509315,50.5117645264],"type":"Point"}
}