{
  "type": "Feature",
  "properties": {
    "iso:country":"BE",
    "sg:address":"Serbosstraat 1ba",
    "sg:city":"Dendermonde",
    "sg:orig_category":"Journaux. Tabac",
    "sg:phone":"+32 52 22 57 22",
    "sg:postcode":"9200",
    "sg:province":"Oost-Vlaanderen",
    "wof:name":"'t Krantje",
    "wof:placetype":"venue"
},
  "geometry": {"coordinates":[4.0926232338,51.0183372498],"type":"Point"}
}