{
  "type": "Feature",
  "properties": {
    "iso:country":"BE",
    "sg:address":"Rue Georges Theys 4",
    "sg:city":"Pont-a-celles",
    "sg:orig_category":"Landmeters",
    "sg:phone":"+32 71 84 29 62",
    "sg:postcode":"6238",
    "sg:province":"Hainaut",
    "wof:name":"Jean Wery",
    "wof:placetype":"venue"
},
  "geometry": {"coordinates":[4.3911180496,50.5093994141],"type":"Point"}
}