{
  "type": "Feature",
  "properties": {
    "iso:country":"BE",
    "sg:address":"Rue De Washington 141",
    "sg:city":"Elsene/ixelles",
    "sg:orig_category":"R\u00e9paration and restauration de meubles",
    "sg:phone":"+32 2 345 60 71",
    "sg:postcode":"1050",
    "sg:province":"Bruxelles-Capitale",
    "wof:name":"Boon F.",
    "wof:placetype":"venue"
},
  "geometry": {"coordinates":[4.3628559113,50.8207244873],"type":"Point"}
}