{
  "type": "Feature",
  "properties": {
    "iso:country":"BE",
    "sg:address":"Eikelenweg 106",
    "sg:city":"Lanaken",
    "sg:classifiers":[
        {
            "category":"Retail",
            "subcategory":"Animal Services",
            "type":"Services"
        }
    ],
    "sg:phone":"+32 89 71 70 60",
    "sg:postcode":"3620",
    "sg:province":"Limburg",
    "sg:tags":[
        "grooming",
        "-",
        "dog"
    ],
    "wof:name":"Hunneke ('t)",
    "wof:placetype":"venue"
},
  "geometry": {"coordinates":[5.6313719749,50.8946113586],"type":"Point"}
}