{
  "type": "Feature",
  "properties": {
    "addr:full":"Rue De Hodebierge 1 Jodoigne Brabant Wallon 1370",
    "addr:housenumber":"1",
    "addr:postcode":"1370",
    "addr:street":"Rue De Hodebierge",
    "iso:country":"BE",
    "sg:address":"Rue De Hodebierge 1",
    "sg:city":"Jodoigne",
    "sg:orig_category":"M\u00e9decins and sp\u00e9cialistes",
    "sg:phone":"+32 10 81 16 45",
    "sg:postcode":"1370",
    "sg:province":"Brabant Wallon",
    "wof:name":"Anita Mortelmans",
    "wof:placetype":"venue"
},
  "geometry": {"coordinates":[4.8679351807,50.7248001099],"type":"Point"}
}