{
  "type": "Feature",
  "properties": {
    "iso:country":"BE",
    "sg:address":"Rue Emile Vandervelde 105",
    "sg:city":"Courcelles (souvret)",
    "sg:classifiers":[
        {
            "category":"Health Services",
            "subcategory":"Health Practitioner",
            "type":"Services"
        }
    ],
    "sg:phone":"+32 71 45 76 19",
    "sg:postcode":"6182",
    "sg:province":"Hainaut",
    "sg:tags":[
        "physiotherapist"
    ],
    "wof:name":"Ghislain-mahieu Fran\u00e7oise",
    "wof:placetype":"venue"
},
  "geometry": {"coordinates":[4.3558578491,50.4444389343],"type":"Point"}
}