{
  "type": "Feature",
  "properties": {
    "iso:country":"BE",
    "sg:address":"Meenselstraat 77",
    "sg:city":"Lubbeek (binkom)",
    "sg:classifiers":[
        {
            "category":"Retail",
            "subcategory":"Auto Repair",
            "type":"Services"
        }
    ],
    "sg:phone":"+32 16 63 53 31",
    "sg:postcode":"3211",
    "sg:province":"Vlaams-Brabant",
    "sg:tags":[
        "garage"
    ],
    "wof:name":"Vanhellemont",
    "wof:placetype":"venue"
},
  "geometry": {"coordinates":[4.8989281654,50.8808441162],"type":"Point"}
}