{
  "type": "Feature",
  "properties": {
    "addr:full":"Bisschopslaan 12 Beerse Antwerpen 2340",
    "addr:housenumber":"12",
    "addr:postcode":"2340",
    "addr:street":"Bisschopslaan",
    "iso:country":"BE",
    "sg:address":"Bisschopslaan 12",
    "sg:city":"Beerse",
    "sg:classifiers":[
        {
            "category":"Professional",
            "subcategory":"Lawyer & Legal Services",
            "type":"Services"
        }
    ],
    "sg:phone":"+32 14 61 12 44",
    "sg:postcode":"2340",
    "sg:province":"Antwerpen",
    "sg:tags":[
        "notary"
    ],
    "wof:name":"Van Roosbroeck J",
    "wof:placetype":"venue"
},
  "geometry": {"coordinates":[4.8551468849,51.3185424805],"type":"Point"}
}