{
  "type": "Feature",
  "properties": {
    "iso:country":"BE",
    "sg:address":"Rue Du Village 111",
    "sg:city":"Sint-genesius-rode/rhode-saint-genese",
    "sg:classifiers":[
        {
            "category":"Personal",
            "subcategory":"Beauty Salon",
            "type":"Services"
        }
    ],
    "sg:phone":"+32 2 380 57 86",
    "sg:postcode":"1640",
    "sg:province":"Vlaams-Brabant",
    "sg:tags":[
        "de",
        "coiffure"
    ],
    "wof:name":"Robert Degelas",
    "wof:placetype":"venue"
},
  "geometry": {"coordinates":[4.3455400467,50.7459487915],"type":"Point"}
}