{
  "type": "Feature",
  "properties": {
    "iso:country":"BE",
    "sg:address":"Statiestraat 13",
    "sg:city":"Nijlen",
    "sg:orig_category":"Diverse organisaties and verenigingen",
    "sg:phone":"+32 3 411 19 88",
    "sg:postcode":"2560",
    "sg:province":"Antwerpen",
    "wof:name":"Jeugdhuis Kroenkel",
    "wof:placetype":"venue"
},
  "geometry": {"coordinates":[4.6679201126,51.1600456238],"type":"Point"}
}