{
  "type": "Feature",
  "properties": {
    "iso:country":"BE",
    "sg:address":"Rue Montavaux 155",
    "sg:city":"Frameries",
    "sg:classifiers":[
        {
            "category":"Wholesale",
            "subcategory":"Tobacco Products",
            "type":"Manufacturing & Wholesale Goods"
        }
    ],
    "sg:phone":"+32 65 66 29 00",
    "sg:postcode":"7080",
    "sg:province":"Hainaut",
    "sg:tags":[
        "pharmaceutical",
        "food",
        "cosmetic",
        "related",
        "chemical",
        "grain",
        "cereal"
    ],
    "wof:name":"Universal Pharma Sa",
    "wof:placetype":"venue"
},
  "geometry": {"coordinates":[3.9116399288,50.4075508118],"type":"Point"}
}