{
  "type": "Feature",
  "properties": {
    "addr:full":"Dorpstraat 43 Glabbeek (kapellen) Vlaams-Brabant 3381",
    "addr:housenumber":"43",
    "addr:postcode":"3381",
    "addr:street":"Dorpstraat",
    "iso:country":"BE",
    "sg:address":"Dorpstraat 43",
    "sg:city":"Glabbeek (kapellen)",
    "sg:classifiers":[
        {
            "category":"Retail",
            "subcategory":"Auto Repair",
            "type":"Services"
        }
    ],
    "sg:phone":"+32 16 77 75 58",
    "sg:postcode":"3381",
    "sg:province":"Vlaams-Brabant",
    "sg:tags":[
        "automobile-body"
    ],
    "wof:name":"Autoschade Veulemans",
    "wof:placetype":"venue"
},
  "geometry": {"coordinates":[4.953417778,50.886428833],"type":"Point"}
}