{
  "type": "Feature",
  "properties": {
    "addr:full":"Rue Louvrex 83 Li\u00e8ge 1 Li\u00e8ge 4000",
    "addr:housenumber":"83;1",
    "addr:postcode":"4000",
    "addr:street":"Rue Louvrex",
    "iso:country":"BE",
    "sg:address":"Rue Louvrex 83",
    "sg:city":"Li\u00e8ge 1",
    "sg:classifiers":[
        {
            "category":"Professional",
            "subcategory":"Management & Consulting",
            "type":"Services"
        }
    ],
    "sg:phone":"+32 4 222 48 82",
    "sg:postcode":"4000",
    "sg:province":"Li\u00e8ge",
    "sg:tags":[
        "consultant",
        "agency",
        "advertising"
    ],
    "wof:name":"Linea Gellura Design",
    "wof:placetype":"venue"
},
  "geometry": {"coordinates":[5.5643520355,50.6342353821],"type":"Point"}
}