{
  "type": "Feature",
  "properties": {
    "addr:full":"Rubenslaan 16 Leopoldsburg Limburg 3970",
    "addr:housenumber":"16",
    "addr:postcode":"3970",
    "addr:street":"Rubenslaan",
    "iso:country":"BE",
    "sg:address":"Rubenslaan 16",
    "sg:city":"Leopoldsburg",
    "sg:orig_category":"Sportclubs",
    "sg:phone":"+32 11 34 62 80",
    "sg:postcode":"3970",
    "sg:province":"Limburg",
    "wof:name":"Zwemclub De Merel",
    "wof:placetype":"venue"
},
  "geometry": {"coordinates":[5.2640199661,51.1179618835],"type":"Point"}
}