{
  "type": "Feature",
  "properties": {
    "addr:full":"Steinroth 52 Eupen Li\u00e8ge 4700",
    "addr:housenumber":"52",
    "addr:postcode":"4700",
    "addr:street":"Steinroth",
    "iso:country":"BE",
    "sg:address":"Steinroth 52",
    "sg:city":"Eupen",
    "sg:classifiers":[
        {
            "category":"Shopping",
            "subcategory":"Hobbies, Toys, & Games",
            "type":"Retail Goods"
        }
    ],
    "sg:phone":"+32 87 55 31 01",
    "sg:postcode":"4700",
    "sg:province":"Li\u00e8ge",
    "sg:tags":[
        "product",
        "miscellaneous",
        "entertainment"
    ],
    "wof:name":"Krafft W Sprl",
    "wof:placetype":"venue"
},
  "geometry": {"coordinates":[6.0217981339,50.6242637634],"type":"Point"}
}