{
  "type": "Feature",
  "properties": {
    "addr:full":"Bruggesteenweg 116 Hooglede West-Vlaanderen 8830",
    "addr:housenumber":"116",
    "addr:postcode":"8830",
    "addr:street":"Bruggesteenweg",
    "iso:country":"BE",
    "sg:address":"Bruggesteenweg 116",
    "sg:city":"Hooglede",
    "sg:classifiers":[
        {
            "category":"Restaurant",
            "type":"Food & Drink"
        }
    ],
    "sg:phone":"+32 51 22 70 07",
    "sg:postcode":"8830",
    "sg:province":"West-Vlaanderen",
    "sg:tags":[
        "caf\u00e9s",
        "h\u00f4tels"
    ],
    "wof:name":"Hotel Land Van Belofte",
    "wof:placetype":"venue"
},
  "geometry": {"coordinates":[3.0945260525,50.9826507568],"type":"Point"}
}