{
  "type": "Feature",
  "properties": {
    "iso:country":"BE",
    "sg:address":"Rue Du Village 12",
    "sg:city":"Tinlot",
    "sg:orig_category":"Architecten",
    "sg:phone":"+32 85 41 21 50",
    "sg:postcode":"4557",
    "sg:province":"Li\u00e8ge",
    "wof:name":"Sabine Dupont",
    "wof:placetype":"venue"
},
  "geometry": {"coordinates":[5.331223011,50.4661140442],"type":"Point"}
}