{
  "type": "Feature",
  "properties": {
    "iso:country":"BE",
    "sg:address":"Stationsstraat 109",
    "sg:city":"Hamont-achel (hamont)",
    "sg:classifiers":[
        {
            "category":"Shopping",
            "subcategory":"Clothing, Apparel, & Fashions",
            "type":"Retail Goods"
        }
    ],
    "sg:phone":"+32 11 44 74 23",
    "sg:postcode":"3930",
    "sg:province":"Limburg",
    "sg:tags":[
        "boutique"
    ],
    "wof:name":"Ribelle",
    "wof:placetype":"venue"
},
  "geometry": {"coordinates":[5.5450549126,51.2511863708],"type":"Point"}
}