{
  "type": "Feature",
  "properties": {
    "addr:full":"Boulevard De L'yser 13b1 Charleroi Hainaut 6000",
    "addr:housenumber":"13b1",
    "addr:postcode":"6000",
    "addr:street":"Boulevard De L'Yser;Hainaut",
    "iso:country":"BE",
    "sg:address":"Boulevard De L'yser 13b1",
    "sg:city":"Charleroi",
    "sg:orig_category":"Advocaten and juridische adviseurs",
    "sg:phone":"+32 71 32 83 69",
    "sg:postcode":"6000",
    "sg:province":"Hainaut",
    "wof:name":"A. Ureel",
    "wof:placetype":"venue"
},
  "geometry": {"coordinates":[4.4426779747,50.4100341797],"type":"Point"}
}