{
  "type": "Feature",
  "properties": {
    "addr:full":"Rue Des Awirs 111 Flemalle Li\u00e8ge 4400",
    "addr:housenumber":"111",
    "addr:postcode":"4400",
    "addr:street":"Rue Des Awirs",
    "iso:country":"BE",
    "sg:address":"Rue Des Awirs 111",
    "sg:city":"Flemalle",
    "sg:classifiers":[
        {
            "category":"Personal",
            "subcategory":"Beauty Salon",
            "type":"Services"
        }
    ],
    "sg:phone":"+32 4 275 30 62",
    "sg:postcode":"4400",
    "sg:province":"Li\u00e8ge",
    "sg:tags":[
        "de",
        "coiffure"
    ],
    "wof:name":"Coiffure Jacques",
    "wof:placetype":"venue"
},
  "geometry": {"coordinates":[5.3892731667,50.6146774292],"type":"Point"}
}