{
  "type": "Feature",
  "properties": {
    "addr:full":"Dendermondsesteenweg 241 Gent Oost-Vlaanderen 9040",
    "addr:housenumber":"241",
    "addr:postcode":"9040",
    "addr:street":"Dendermondsesteenweg;Oost-Vlaanderen",
    "iso:country":"BE",
    "sg:address":"Dendermondsesteenweg 241",
    "sg:city":"Gent",
    "sg:orig_category":"Blanchisseries and teintureries",
    "sg:phone":"+32 9 228 28 26",
    "sg:postcode":"9040",
    "sg:province":"Oost-Vlaanderen",
    "wof:name":"De Schop",
    "wof:placetype":"venue"
},
  "geometry": {"coordinates":[3.7483348846,51.0527153015],"type":"Point"}
}