{
  "type": "Feature",
  "properties": {
    "iso:country":"BE",
    "sg:address":"Putstraat 47",
    "sg:city":"Tongeren",
    "sg:classifiers":[
        {
            "category":"Personal",
            "subcategory":"Beauty Salon",
            "type":"Services"
        }
    ],
    "sg:phone":"+32 12 23 38 48",
    "sg:postcode":"3700",
    "sg:province":"Limburg",
    "sg:tags":[
        "lady",
        "-",
        "hairdressing"
    ],
    "wof:name":"Ernots Coiffure Bvba",
    "wof:placetype":"venue"
},
  "geometry": {"coordinates":[5.460832119,50.7785682678],"type":"Point"}
}