{
  "type": "Feature",
  "properties": {
    "addr:full":"Wittenweg 14 Plombi\u00c8res Li\u00e8ge 4851",
    "addr:housenumber":"14",
    "addr:postcode":"4851",
    "addr:street":"Wittenweg",
    "iso:country":"BE",
    "sg:address":"Wittenweg 14",
    "sg:city":"Plombi\u00c8res",
    "sg:orig_category":"Boekhouders",
    "sg:phone":"+32 87 78 59 88",
    "sg:postcode":"4851",
    "sg:province":"Li\u00e8ge",
    "wof:name":"Nicole Alofs",
    "wof:placetype":"venue"
},
  "geometry": {"coordinates":[5.9952659607,50.7457046509],"type":"Point"}
}