{
  "type": "Feature",
  "properties": {
    "iso:country":"BE",
    "sg:address":"Westernieuwweg 84",
    "sg:city":"Jabbeke",
    "sg:orig_category":"Transports routiers de marchandises",
    "sg:phone":"+32 50 39 50 56",
    "sg:postcode":"8490",
    "sg:province":"West-Vlaanderen",
    "wof:name":"Taffeiren G",
    "wof:placetype":"venue"
},
  "geometry": {"coordinates":[3.1320478916,51.2074432373],"type":"Point"}
}