{
  "type": "Feature",
  "properties": {
    "addr:full":"Blauwstraat 14 Boom Antwerpen 2850",
    "addr:housenumber":"14",
    "addr:postcode":"2850",
    "addr:street":"Blauwstraat",
    "iso:country":"BE",
    "sg:address":"Blauwstraat 14",
    "sg:city":"Boom",
    "sg:orig_category":"Agences immobili\u00e8res",
    "sg:phone":"+32 3 844 84 64",
    "sg:postcode":"2850",
    "sg:province":"Antwerpen",
    "wof:name":"Immo-casco",
    "wof:placetype":"venue"
},
  "geometry": {"coordinates":[4.3667721748,51.0861473083],"type":"Point"}
}