{
  "type": "Feature",
  "properties": {
    "iso:country":"BE",
    "sg:address":"Zwaarveld 26",
    "sg:city":"Hamme",
    "sg:classifiers":[
        {
            "category":"Professional",
            "type":"Services"
        }
    ],
    "sg:phone":"+32 52 47 87 11",
    "sg:postcode":"9220",
    "sg:province":"Oost-Vlaanderen",
    "sg:tags":[
        "transport",
        "road"
    ],
    "wof:name":"Transport Coulier Nv",
    "wof:placetype":"venue"
},
  "geometry": {"coordinates":[4.1325058937,51.07472229],"type":"Point"}
}