{
  "type": "Feature",
  "properties": {
    "iso:country":"BE",
    "sg:address":"Otegemstraat 45",
    "sg:city":"Zwevegem",
    "sg:classifiers":[
        {
            "category":"Real Estate",
            "subcategory":"Real Estate Services",
            "type":"Services"
        }
    ],
    "sg:phone":"+32 56 75 57 47",
    "sg:postcode":"8550",
    "sg:province":"West-Vlaanderen",
    "wof:name":"Era Becue",
    "wof:placetype":"venue"
},
  "geometry": {"coordinates":[3.3369750977,50.8129920959],"type":"Point"}
}