{
  "type": "Feature",
  "properties": {
    "addr:full":"Rue De La Haie 30 Wavre Brabant Wallon 1301",
    "addr:housenumber":"30;1301",
    "addr:street":"Rue De La Haie",
    "iso:country":"BE",
    "sg:address":"Rue De La Haie 30",
    "sg:city":"Wavre",
    "sg:orig_category":"Tuinen",
    "sg:phone":"+32 10 41 12 95",
    "sg:postcode":"1301",
    "sg:province":"Brabant Wallon",
    "wof:name":"Ecotaille",
    "wof:placetype":"venue"
},
  "geometry": {"coordinates":[4.579185009,50.7087783813],"type":"Point"}
}