{
  "type": "Feature",
  "properties": {
    "addr:full":"Ispralaan 10 Mol Antwerpen 2400",
    "addr:housenumber":"10",
    "addr:postcode":"2400",
    "addr:street":"Ispralaan",
    "iso:country":"BE",
    "sg:address":"Ispralaan 10",
    "sg:city":"Mol",
    "sg:orig_category":"Diverse organisaties and verenigingen",
    "sg:phone":"+32 14 31 55 40",
    "sg:postcode":"2400",
    "sg:province":"Antwerpen",
    "wof:name":"J.a. 't Spinnekotteke",
    "wof:placetype":"venue"
},
  "geometry": {"coordinates":[5.0470228195,51.1928100586],"type":"Point"}
}