{
  "type": "Feature",
  "properties": {
    "addr:full":"Rue De L'egalit\u00e9 26 Quaregnon Hainaut 7390",
    "addr:housenumber":"26",
    "addr:postcode":"7390",
    "addr:street":"Rue De L'Egalite \u0301",
    "iso:country":"BE",
    "sg:address":"Rue De L'egalit\u00e9 26",
    "sg:city":"Quaregnon",
    "sg:classifiers":[
        {
            "category":"Professional",
            "subcategory":"Lawyer & Legal Services",
            "type":"Services"
        }
    ],
    "sg:phone":"+32 65 80 30 67",
    "sg:postcode":"7390",
    "sg:province":"Hainaut",
    "wof:name":"Descamps Etienne",
    "wof:placetype":"venue"
},
  "geometry": {"coordinates":[3.8638679981,50.4409370422],"type":"Point"}
}