{
  "type": "Feature",
  "properties": {
    "iso:country":"BE",
    "sg:address":"Kasteeldreef 40",
    "sg:city":"Schoten",
    "sg:classifiers":[
        {
            "category":"Bars & Pubs",
            "type":"Food & Drink"
        }
    ],
    "sg:phone":"+32 3 658 44 26",
    "sg:postcode":"2900",
    "sg:province":"Antwerpen",
    "sg:tags":[
        "tavern"
    ],
    "wof:name":"De Riddershoeve",
    "wof:placetype":"venue"
},
  "geometry": {"coordinates":[4.4900069237,51.2458763123],"type":"Point"}
}