{
  "type": "Feature",
  "properties": {
    "iso:country":"BE",
    "sg:address":"Hospicestraat-ter Moere 15",
    "sg:city":"Moerbeke",
    "sg:orig_category":"Maisons de repos and r\u00e9sidences",
    "sg:phone":"+32 9 346 55 43",
    "sg:postcode":"9180",
    "sg:province":"Oost-Vlaanderen",
    "wof:name":"Rusthuis Herfstvrede",
    "wof:placetype":"venue"
},
  "geometry": {"coordinates":[3.9448320866,51.1744003296],"type":"Point"}
}