{
  "type": "Feature",
  "properties": {
    "addr:full":"Avenue Florida 39 Waterloo Brabant Wallon 1410",
    "addr:housenumber":"39",
    "addr:postcode":"1410",
    "addr:street":"Avenue Florida",
    "iso:country":"BE",
    "sg:address":"Avenue Florida 39",
    "sg:city":"Waterloo",
    "sg:orig_category":"Sportclubs",
    "sg:phone":"+32 2 354 45 30",
    "sg:postcode":"1410",
    "sg:province":"Brabant Wallon",
    "wof:name":"Lion Waterloo A.",
    "wof:placetype":"venue"
},
  "geometry": {"coordinates":[4.3859300613,50.723941803],"type":"Point"}
}