{
  "type": "Feature",
  "properties": {
    "addr:full":"Mollekot 54 Sint-laureins Oost-Vlaanderen 9988",
    "addr:housenumber":"54",
    "addr:postcode":"9988",
    "addr:street":"Mollekot",
    "iso:country":"BE",
    "sg:address":"Mollekot 54",
    "sg:city":"Sint-laureins",
    "sg:orig_category":"Groenten and fruit Gh",
    "sg:phone":"+32 9 379 84 20",
    "sg:postcode":"9988",
    "sg:province":"Oost-Vlaanderen",
    "wof:name":"Van Zele E. En K.",
    "wof:placetype":"venue"
},
  "geometry": {"coordinates":[3.6261999607,51.2758598328],"type":"Point"}
}