{
  "type": "Feature",
  "properties": {
    "iso:country":"BE",
    "sg:address":"Sint-remigiusstraat 2",
    "sg:city":"Pittem",
    "sg:classifiers":[
        {
            "category":"Utilities",
            "subcategory":"Telephone",
            "type":"Services"
        }
    ],
    "sg:phone":"+32 51 46 43 52",
    "sg:postcode":"8740",
    "sg:province":"West-Vlaanderen",
    "sg:tags":[
        "addressing",
        "mailing"
    ],
    "wof:name":"Buro Devan-dejaeghere",
    "wof:placetype":"venue"
},
  "geometry": {"coordinates":[3.2529320717,50.9960441589],"type":"Point"}
}