{
  "type": "Feature",
  "properties": {
    "iso:country":"BE",
    "sg:address":"Kerkstraat 24",
    "sg:city":"Avelgem",
    "sg:orig_category":"Pharmaciens",
    "sg:phone":"+32 56 64 41 06",
    "sg:postcode":"8580",
    "sg:province":"West-Vlaanderen",
    "wof:name":"Apoth. Vantieghem-bollen",
    "wof:placetype":"venue"
},
  "geometry": {"coordinates":[3.4457790852,50.7757072449],"type":"Point"}
}