{
  "type": "Feature",
  "properties": {
    "addr:full":"Rue Ma Campagne 32 Waterloo Brabant Wallon 1410",
    "addr:housenumber":"32",
    "addr:postcode":"1410",
    "addr:street":"Rue Ma Campagne",
    "iso:country":"BE",
    "sg:address":"Rue Ma Campagne 32",
    "sg:city":"Waterloo",
    "sg:orig_category":"Boekhouders",
    "sg:phone":"+32 2 353 01 67",
    "sg:postcode":"1410",
    "sg:province":"Brabant Wallon",
    "wof:name":"Hubert Van Akelyen",
    "wof:placetype":"venue"
},
  "geometry": {"coordinates":[4.3822879791,50.706489563],"type":"Point"}
}