{
  "type": "Feature",
  "properties": {
    "iso:country":"BE",
    "sg:address":"Rue De La Rivi\u00c8re 23",
    "sg:city":"Habay",
    "sg:orig_category":"Enseignement maternel and primaire",
    "sg:phone":"+32 63 41 11 43",
    "sg:postcode":"6724",
    "sg:province":"Luxembourg",
    "wof:name":"Ecole Fond. Communale",
    "wof:placetype":"venue"
},
  "geometry": {"coordinates":[5.5597100258,49.7180557251],"type":"Point"}
}