{
  "type": "Feature",
  "properties": {
    "iso:country":"BE",
    "sg:address":"Rue Grihanster 21",
    "sg:city":"Trooz (nessonvaux)",
    "sg:classifiers":[
        {
            "category":"Real Estate",
            "subcategory":"Surveying",
            "type":"Services"
        }
    ],
    "sg:phone":"+32 87 26 80 27",
    "sg:postcode":"4870",
    "sg:province":"Li\u00e8ge",
    "sg:tags":[
        "surveyor",
        "land"
    ],
    "wof:name":"Laszlo A",
    "wof:placetype":"venue"
},
  "geometry": {"coordinates":[5.6734352112,50.5785331726],"type":"Point"}
}