{
  "type": "Feature",
  "properties": {
    "iso:country":"BE",
    "sg:address":"Edmond Thieffrylaan 100",
    "sg:city":"Mortsel",
    "sg:orig_category":"Boekhouders",
    "sg:phone":"+32 3 440 86 56",
    "sg:postcode":"2640",
    "sg:province":"Antwerpen",
    "wof:name":"Peter Minne",
    "wof:placetype":"venue"
},
  "geometry": {"coordinates":[4.4495620728,51.1663780212],"type":"Point"}
}