{
  "type": "Feature",
  "properties": {
    "addr:full":"Ijzerlaan 56 Diksmuide West-Vlaanderen 8600",
    "addr:housenumber":"56",
    "addr:postcode":"8600",
    "addr:street":"Ijzerlaan",
    "iso:country":"BE",
    "sg:address":"Ijzerlaan 56",
    "sg:city":"Diksmuide",
    "sg:classifiers":[
        {
            "category":"Health Services",
            "subcategory":"Dentist",
            "type":"Services"
        }
    ],
    "sg:phone":"+32 51 50 42 84",
    "sg:postcode":"8600",
    "sg:province":"West-Vlaanderen",
    "wof:name":"Bouquillon Heidi",
    "wof:placetype":"venue"
},
  "geometry": {"coordinates":[2.8570580482,51.0328483582],"type":"Point"}
}