{
  "type": "Feature",
  "properties": {
    "iso:country":"BE",
    "sg:address":"Brugse Steenweg 58",
    "sg:city":"Veurne",
    "sg:orig_category":"Apotheken",
    "sg:phone":"+32 58 31 33 86",
    "sg:postcode":"8630",
    "sg:province":"West-Vlaanderen",
    "wof:name":"Monique Van Acker",
    "wof:placetype":"venue"
},
  "geometry": {"coordinates":[2.6733920574,51.0771408081],"type":"Point"}
}