{
  "type": "Feature",
  "properties": {
    "addr:full":"Rue Du Monument 28 Esneux Li\u00e8ge 4130",
    "addr:housenumber":"28",
    "addr:postcode":"4130",
    "addr:street":"Rue Du Monument",
    "iso:country":"BE",
    "sg:address":"Rue Du Monument 28",
    "sg:city":"Esneux",
    "sg:classifiers":[
        {
            "category":"Professional",
            "subcategory":"Computer Services",
            "type":"Services"
        }
    ],
    "sg:phone":"+32 4 380 06 10",
    "sg:postcode":"4130",
    "sg:province":"Li\u00e8ge",
    "sg:tags":[
        "-",
        "processing",
        "data"
    ],
    "wof:name":"Micro Digit Sprl",
    "wof:placetype":"venue"
},
  "geometry": {"coordinates":[5.5660500526,50.5334205627],"type":"Point"}
}