{
  "type": "Feature",
  "properties": {
    "iso:country":"BE",
    "sg:address":"Rue Chevrefeuille 2",
    "sg:city":"Marcinelle",
    "sg:classifiers":[
        {
            "category":"Shopping",
            "subcategory":"Computers & Home Electronics",
            "type":"Retail Goods"
        }
    ],
    "sg:phone":"+32 71 47 63 03",
    "sg:postcode":"6001",
    "sg:province":"Hainaut",
    "sg:tags":[
        "siemens",
        "fujitsu",
        "computerapparatuur"
    ],
    "wof:name":"M.a.d.i.",
    "wof:placetype":"venue"
},
  "geometry": {"coordinates":[4.4408211708,50.3876953125],"type":"Point"}
}