{
  "type": "Feature",
  "properties": {
    "iso:country":"BE",
    "sg:address":"Onafhankelijkheidslaan 42",
    "sg:city":"Gent",
    "sg:orig_category":"Artsen and specialisten",
    "sg:phone":"+32 9 245 15 20",
    "sg:postcode":"9000",
    "sg:province":"Oost-Vlaanderen",
    "wof:name":"Bart Lafaut",
    "wof:placetype":"venue"
},
  "geometry": {"coordinates":[3.7152900696,51.0323982239],"type":"Point"}
}