{
  "type": "Feature",
  "properties": {
    "addr:full":"Dorpsstraat 17 Londerzeel Vlaams-Brabant 1840",
    "addr:housenumber":"17",
    "addr:postcode":"1840",
    "addr:street":"Dorpsstraat",
    "iso:country":"BE",
    "sg:address":"Dorpsstraat 17",
    "sg:city":"Londerzeel",
    "sg:classifiers":[
        {
            "category":"Banks & Credit Unions",
            "subcategory":"Investment Brokerage",
            "type":"Services"
        }
    ],
    "sg:phone":"+32 52 30 90 21",
    "sg:postcode":"1840",
    "sg:province":"Vlaams-Brabant",
    "sg:tags":[
        "fence"
    ],
    "wof:name":"Cauwenbergh Bvba",
    "wof:placetype":"venue"
},
  "geometry": {"coordinates":[4.3026199341,51.0034484863],"type":"Point"}
}