{
  "type": "Feature",
  "properties": {
    "iso:country":"BE",
    "sg:address":"Landwaartslaan 66",
    "sg:city":"Genk",
    "sg:classifiers":[
        {
            "category":"Personal",
            "subcategory":"Beauty Salon",
            "type":"Services"
        }
    ],
    "sg:phone":"+32 473 49 81 42",
    "sg:postcode":"3600",
    "sg:province":"Limburg",
    "sg:tags":[
        "product",
        "-",
        "apparatus"
    ],
    "wof:name":"Nail Creation",
    "wof:placetype":"venue"
},
  "geometry": {"coordinates":[5.4494419098,50.9671897888],"type":"Point"}
}