{
  "type": "Feature",
  "properties": {
    "addr:full":"Rue De Dave 54 Namur Namur 5100",
    "addr:housenumber":"54",
    "addr:postcode":"5100",
    "addr:street":"Rue De Dave",
    "iso:country":"BE",
    "sg:address":"Rue De Dave 54",
    "sg:city":"Namur",
    "sg:orig_category":"Deurwaarders",
    "sg:phone":"+32 81 30 04 58",
    "sg:postcode":"5100",
    "sg:province":"Namur",
    "wof:name":"Andr\u00c9 De Suray",
    "wof:placetype":"venue"
},
  "geometry": {"coordinates":[4.8713750839,50.4566345215],"type":"Point"}
}