{
  "type": "Feature",
  "properties": {
    "addr:full":"Ninoofsesteenweg 37-39 Lennik (sint-martens-lennik) Vlaams-Brabant 1750",
    "addr:housenumber":"37-39",
    "addr:postcode":"1750",
    "addr:street":"Ninoofsesteenweg",
    "iso:country":"BE",
    "sg:address":"Ninoofsesteenweg 37-39",
    "sg:city":"Lennik (sint-martens-lennik)",
    "sg:orig_category":"Non-Classified Establishments",
    "sg:phone":"+32 2 582 70 92",
    "sg:postcode":"1750",
    "sg:province":"Vlaams-Brabant",
    "wof:name":"William",
    "wof:placetype":"venue"
},
  "geometry": {"coordinates":[4.1499218941,50.8353309631],"type":"Point"}
}