{
  "type": "Feature",
  "properties": {
    "iso:country":"BE",
    "sg:address":"Rue Valduc 229",
    "sg:city":"Bruxelles (auderghem)",
    "sg:classifiers":[
        {
            "category":"Bakery",
            "type":"Food & Drink"
        }
    ],
    "sg:phone":"+32 2 672 43 73",
    "sg:postcode":"1160",
    "sg:province":"Bruxelles-Capitale",
    "sg:tags":[
        "confectioner",
        "baker"
    ],
    "wof:name":"Desmet",
    "wof:placetype":"venue"
},
  "geometry": {"coordinates":[4.4127001762,50.8206443787],"type":"Point"}
}