{
  "type": "Feature",
  "properties": {
    "addr:full":"Lepelstraat 17 Sint-truiden Limburg 3800",
    "addr:housenumber":"17",
    "addr:postcode":"3800",
    "addr:street":"Lepelstraat",
    "iso:country":"BE",
    "sg:address":"Lepelstraat 17",
    "sg:city":"Sint-truiden",
    "sg:classifiers":[
        {
            "category":"Quarry",
            "type":"Physical Feature"
        }
    ],
    "sg:phone":"+32 11 68 30 28",
    "sg:postcode":"3800",
    "sg:province":"Limburg",
    "sg:tags":[
        "granite",
        "work",
        "marble"
    ],
    "wof:name":"Haesen P",
    "wof:placetype":"venue"
},
  "geometry": {"coordinates":[5.18481493,50.8112068176],"type":"Point"}
}