{
  "type": "Feature",
  "properties": {
    "addr:full":"Kesseldallaan 95b403 Leuven Vlaams-Brabant 3010",
    "addr:housenumber":"95b403",
    "addr:postcode":"3010",
    "addr:street":"Kesseldallaan",
    "iso:country":"BE",
    "sg:address":"Kesseldallaan 95b403",
    "sg:city":"Leuven",
    "sg:orig_category":"M\u00e9decins and sp\u00e9cialistes",
    "sg:phone":"+32 16 25 08 63",
    "sg:postcode":"3010",
    "sg:province":"Vlaams-Brabant",
    "wof:name":"Michel Craninx",
    "wof:placetype":"venue"
},
  "geometry": {"coordinates":[4.7304501534,50.889755249],"type":"Point"}
}