{
  "type": "Feature",
  "properties": {
    "addr:full":"Avenue Des Glycines 10 Schaarbeek/schaerbeek Bruxelles-Capitale 1030",
    "addr:housenumber":"10",
    "addr:postcode":"1030",
    "addr:street":"Avenue Des Glycines",
    "iso:country":"BE",
    "sg:address":"Avenue Des Glycines 10",
    "sg:city":"Schaarbeek/schaerbeek",
    "sg:orig_category":"M\u00e9decins and sp\u00e9cialistes",
    "sg:phone":"+32 2 241 41 40",
    "sg:postcode":"1030",
    "sg:province":"Bruxelles-Capitale",
    "wof:name":"Arthur Lardinois",
    "wof:placetype":"venue"
},
  "geometry": {"coordinates":[4.3864078522,50.8662796021],"type":"Point"}
}