{
  "type": "Feature",
  "properties": {
    "addr:full":"Bergstraat 99 Kampenhout Vlaams-Brabant 1910",
    "addr:housenumber":"99",
    "addr:postcode":"1910",
    "addr:street":"Bergstraat",
    "iso:country":"BE",
    "sg:address":"Bergstraat 99",
    "sg:city":"Kampenhout",
    "sg:orig_category":"Reclamebureaus",
    "sg:phone":"+32 16 65 03 03",
    "sg:postcode":"1910",
    "sg:province":"Vlaams-Brabant",
    "wof:name":"Content & Concept",
    "wof:placetype":"venue"
},
  "geometry": {"coordinates":[4.543697834,50.9304733276],"type":"Point"}
}