{
  "type": "Feature",
  "properties": {
    "addr:full":"Rue Lesbroussart 17 Bruxelles (ixelles) Bruxelles-Capitale 1050",
    "addr:housenumber":"17",
    "addr:postcode":"1050",
    "addr:street":"Rue Lesbroussart",
    "iso:country":"BE",
    "sg:address":"Rue Lesbroussart 17",
    "sg:city":"Bruxelles (ixelles)",
    "sg:classifiers":[
        {
            "category":"Personal",
            "subcategory":"Beauty Salon",
            "type":"Services"
        }
    ],
    "sg:phone":"+32 2 644 22 48",
    "sg:postcode":"1050",
    "sg:province":"Bruxelles-Capitale",
    "wof:name":"Ruby's Nail Art",
    "wof:placetype":"venue"
},
  "geometry": {"coordinates":[4.3704061508,50.8279342651],"type":"Point"}
}