{
  "type": "Feature",
  "properties": {
    "addr:full":"J. Minckelersstraat 76 Leuven Vlaams-Brabant 3000",
    "addr:housenumber":"76",
    "addr:postcode":"3000",
    "addr:street":"J. Minckelersstraat",
    "iso:country":"BE",
    "sg:address":"J. Minckelersstraat 76",
    "sg:city":"Leuven",
    "sg:orig_category":"Biljart- and snookerzalen Sportclubs",
    "sg:phone":"+32 16 22 06 02",
    "sg:postcode":"3000",
    "sg:province":"Vlaams-Brabant",
    "wof:name":"The Pocket",
    "wof:placetype":"venue"
},
  "geometry": {"coordinates":[4.7062358856,50.8834152222],"type":"Point"}
}