{
  "type": "Feature",
  "properties": {
    "addr:full":"Rue Des Combattants 39 Braine-l\u00b4alleud Brabant Wallon 1421",
    "addr:housenumber":"39;1421",
    "addr:street":"Rue Des Combattants;Brabant Wallon",
    "iso:country":"BE",
    "sg:address":"Rue Des Combattants 39",
    "sg:city":"Braine-l\u00b4alleud",
    "sg:orig_category":"Apotheken",
    "sg:phone":"+32 2 384 29 57",
    "sg:postcode":"1421",
    "sg:province":"Brabant Wallon",
    "wof:name":"Williame-poulaert",
    "wof:placetype":"venue"
},
  "geometry": {"coordinates":[4.3464999199,50.6640548706],"type":"Point"}
}