{
  "type": "Feature",
  "properties": {
    "addr:full":"Nederkouter 49 Gent Oost-Vlaanderen 9000",
    "addr:housenumber":"49",
    "addr:postcode":"9000",
    "addr:street":"Nederkouter;Oost-Vlaanderen",
    "iso:country":"BE",
    "sg:address":"Nederkouter 49",
    "sg:city":"Gent",
    "sg:orig_category":"Huishoudapparaten, televisies and radio's",
    "sg:phone":"+32 9 225 39 64",
    "sg:postcode":"9000",
    "sg:province":"Oost-Vlaanderen",
    "wof:name":"S & M Security",
    "wof:placetype":"venue"
},
  "geometry": {"coordinates":[3.7217888832,51.0476455688],"type":"Point"}
}