{
  "type": "Feature",
  "properties": {
    "iso:country":"BE",
    "sg:address":"Bieshof 5",
    "sg:city":"Hoogstraten",
    "sg:orig_category":"Varkenskwekers",
    "sg:phone":"+32 3 315 41 06",
    "sg:postcode":"2321",
    "sg:province":"Antwerpen",
    "wof:name":"Jan Van Den Broeck",
    "wof:placetype":"venue"
},
  "geometry": {"coordinates":[4.7296638489,51.4680137634],"type":"Point"}
}