{
  "type": "Feature",
  "properties": {
    "addr:full":"Boulevard Du R\u00e9gent 8 Bruxelles Bruxelles-Capitale 1000",
    "addr:housenumber":"8",
    "addr:postcode":"1000",
    "addr:street":"Boulevard Du Re\u0301Gent",
    "iso:country":"BE",
    "sg:address":"Boulevard Du R\u00e9gent 8",
    "sg:city":"Bruxelles",
    "sg:classifiers":[
        {
            "category":"Autos & Motor Vehicles",
            "subcategory":"Fuel & Gas Station",
            "type":"Retail Goods"
        }
    ],
    "sg:phone":"+32 71 66 20 11",
    "sg:postcode":"1000",
    "sg:province":"Bruxelles-Capitale",
    "sg:tags":[
        "electricity",
        "supply"
    ],
    "wof:name":"Electrabel",
    "wof:placetype":"venue"
},
  "geometry": {"coordinates":[4.363492012,50.8398208618],"type":"Point"}
}