{
  "type": "Feature",
  "properties": {
    "addr:full":"Wallerode 5a Sankt Vith (wallerode) Li\u00e8ge 4780",
    "addr:housenumber":"5a",
    "addr:postcode":"4780",
    "addr:street":"Wallerode",
    "iso:country":"BE",
    "sg:address":"Wallerode 5a",
    "sg:city":"Sankt Vith (wallerode)",
    "sg:classifiers":[
        {
            "category":"Building & Trades",
            "subcategory":"Landscaping Services",
            "type":"Services"
        }
    ],
    "sg:postcode":"4780",
    "sg:province":"Li\u00e8ge",
    "sg:tags":[
        "gardening",
        "garden",
        "maintenance"
    ],
    "wof:name":"Green Art Hgar Sarl",
    "wof:placetype":"venue"
},
  "geometry": {"coordinates":[6.1256680489,50.2810821533],"type":"Point"}
}