{
  "type": "Feature",
  "properties": {
    "iso:country":"BE",
    "sg:address":"Collegelaan 14b1",
    "sg:city":"Genk",
    "sg:orig_category":"Boekhouders",
    "sg:phone":"+32 89 30 78 40",
    "sg:postcode":"3600",
    "sg:province":"Limburg",
    "wof:name":"Pascal Meyers",
    "wof:placetype":"venue"
},
  "geometry": {"coordinates":[5.5199980736,50.9756584167],"type":"Point"}
}