{
  "type": "Feature",
  "properties": {
    "iso:country":"BE",
    "sg:address":"Dellenstrasse 12",
    "sg:city":"B\u00fctgenbach (elsenborn)",
    "sg:classifiers":[
        {
            "category":"Travel",
            "subcategory":"Hotels & Motels",
            "type":"Entertainment"
        }
    ],
    "sg:phone":"+32 80 44 61 49",
    "sg:postcode":"4750",
    "sg:province":"Li\u00e8ge",
    "wof:name":"Printemps (au)",
    "wof:placetype":"venue"
},
  "geometry": {"coordinates":[6.2043948174,50.4263038635],"type":"Point"}
}