{
  "type": "Feature",
  "properties": {
    "addr:full":"Barelstraat 155 Bornem Antwerpen 2880",
    "addr:housenumber":"155",
    "addr:postcode":"2880",
    "addr:street":"Barelstraat",
    "iso:country":"BE",
    "sg:address":"Barelstraat 155",
    "sg:city":"Bornem",
    "sg:classifiers":[
        {
            "category":"Insurance",
            "subcategory":"Life Insurance",
            "type":"Services"
        }
    ],
    "sg:phone":"+32 3 889 21 12",
    "sg:postcode":"2880",
    "sg:province":"Antwerpen",
    "sg:tags":[
        "assurance"
    ],
    "wof:name":"Hertog",
    "wof:placetype":"venue"
},
  "geometry": {"coordinates":[4.2328782082,51.0898399353],"type":"Point"}
}