{
  "type": "Feature",
  "properties": {
    "iso:country":"BE",
    "sg:address":"Sooi Willemsplein 1b2",
    "sg:city":"Neerpelt",
    "sg:orig_category":"M\u00e9decins and sp\u00e9cialistes",
    "sg:phone":"+32 11 80 31 99",
    "sg:postcode":"3910",
    "sg:province":"Limburg",
    "wof:name":"Consultatiebur.jonge Kind",
    "wof:placetype":"venue"
},
  "geometry": {"coordinates":[5.4322748184,51.2293624878],"type":"Point"}
}