{
  "type": "Feature",
  "properties": {
    "iso:country":"BE",
    "sg:address":"Oleanderstraat 22",
    "sg:city":"Wevelgem",
    "sg:classifiers":[
        {
            "category":"Health Services",
            "subcategory":"Dentist",
            "type":"Services"
        }
    ],
    "sg:phone":"+32 56 41 51 11",
    "sg:postcode":"8560",
    "sg:province":"West-Vlaanderen",
    "wof:name":"Deprez J",
    "wof:placetype":"venue"
},
  "geometry": {"coordinates":[3.1758930683,50.8169021606],"type":"Point"}
}