{
  "type": "Feature",
  "properties": {
    "addr:full":"Schoonderbeukenweg 71 Aarschot (rillaar) Vlaams-Brabant 3202",
    "addr:housenumber":"71",
    "addr:postcode":"3202",
    "addr:street":"Schoonderbeukenweg",
    "iso:country":"BE",
    "sg:address":"Schoonderbeukenweg 71",
    "sg:city":"Aarschot (rillaar)",
    "sg:classifiers":[
        {
            "category":"Ice Cream",
            "type":"Food & Drink"
        }
    ],
    "sg:phone":"+32 16 50 07 69",
    "sg:postcode":"3202",
    "sg:province":"Vlaams-Brabant",
    "wof:name":"Ding-dong",
    "wof:placetype":"venue"
},
  "geometry": {"coordinates":[4.9044370651,50.9731369019],"type":"Point"}
}