{
  "type": "Feature",
  "properties": {
    "addr:full":"Diestsesteenweg 373 Leuven Vlaams-Brabant 3010",
    "addr:housenumber":"373",
    "addr:postcode":"3010",
    "addr:street":"Diestsesteenweg",
    "iso:country":"BE",
    "sg:address":"Diestsesteenweg 373",
    "sg:city":"Leuven",
    "sg:orig_category":"Fleurs and plantes",
    "sg:phone":"+32 16 26 13 14",
    "sg:postcode":"3010",
    "sg:province":"Vlaams-Brabant",
    "wof:name":"Bloemenstudio",
    "wof:placetype":"venue"
},
  "geometry": {"coordinates":[4.7304501534,50.889755249],"type":"Point"}
}