{
  "type": "Feature",
  "properties": {
    "addr:full":"Hoogstraat 31 Beersel Vlaams-Brabant 1650",
    "addr:housenumber":"31",
    "addr:postcode":"1650",
    "addr:street":"Hoogstraat",
    "iso:country":"BE",
    "sg:address":"Hoogstraat 31",
    "sg:city":"Beersel",
    "sg:orig_category":"Artistes ind\u00e9pendants",
    "sg:phone":"+32 2 331 07 17",
    "sg:postcode":"1650",
    "sg:province":"Vlaams-Brabant",
    "wof:name":"Hilde Van Sumere",
    "wof:placetype":"venue"
},
  "geometry": {"coordinates":[4.3109917641,50.765411377],"type":"Point"}
}