{
  "type": "Feature",
  "properties": {
    "addr:full":"Avenue L\u00c9opold Iii 109 Wezembeek-oppem Vlaams-Brabant 1970",
    "addr:housenumber":"109",
    "addr:postcode":"1970",
    "addr:street":"Avenue Le\u0301Opold Iii",
    "iso:country":"BE",
    "sg:address":"Avenue L\u00c9opold Iii 109",
    "sg:city":"Wezembeek-oppem",
    "sg:orig_category":"Maisons de repos and r\u00e9sidences",
    "sg:phone":"+32 2 767 71 70",
    "sg:postcode":"1970",
    "sg:province":"Vlaams-Brabant",
    "wof:name":"Home Aurora",
    "wof:placetype":"venue"
},
  "geometry": {"coordinates":[4.5044441223,50.8419036865],"type":"Point"}
}