{
  "type": "Feature",
  "properties": {
    "iso:country":"BE",
    "sg:address":"Sint-ursmurasstraat 9",
    "sg:city":"Brakel",
    "sg:orig_category":"Installation \u00e9lectrique industrielle",
    "sg:phone":"+32 55 45 52 62",
    "sg:postcode":"9660",
    "sg:province":"Oost-Vlaanderen",
    "wof:name":"Protelek",
    "wof:placetype":"venue"
},
  "geometry": {"coordinates":[3.7147290707,50.8200378418],"type":"Point"}
}