{
  "type": "Feature",
  "properties": {
    "iso:country":"BE",
    "sg:address":"Rue Bois-mayette 39",
    "sg:city":"Li\u00c8ge",
    "sg:orig_category":"Epiceries",
    "sg:phone":"+32 4 253 26 48",
    "sg:postcode":"4000",
    "sg:province":"Li\u00e8ge",
    "wof:name":"Francine Weron",
    "wof:placetype":"venue"
},
  "geometry": {"coordinates":[5.5433688164,50.6335487366],"type":"Point"}
}