{
  "type": "Feature",
  "properties": {
    "iso:country":"BE",
    "sg:address":"Broelstr 98",
    "sg:city":"Harelbeke",
    "sg:classifiers":[
        {
            "category":"Professional",
            "subcategory":"Engineering",
            "type":"Services"
        }
    ],
    "sg:phone":"+32 56 71 03 21",
    "sg:postcode":"8530",
    "sg:province":"West-Vlaanderen",
    "sg:tags":[
        "machine",
        "-",
        "mechanical"
    ],
    "wof:name":"Dkr Refrigerations Nv",
    "wof:placetype":"venue"
},
  "geometry": {"coordinates":[3.3091568947,50.8630638123],"type":"Point"}
}