{
  "type": "Feature",
  "properties": {
    "iso:country":"BE",
    "sg:address":"Manestraat 61",
    "sg:city":"Herk-de-stad",
    "sg:orig_category":"Rev\u00eatements pour sols and murs. Construction de maisons",
    "sg:phone":"+32 13 55 51 79",
    "sg:postcode":"3540",
    "sg:province":"Limburg",
    "wof:name":"Jamar - Reynders",
    "wof:placetype":"venue"
},
  "geometry": {"coordinates":[5.1871180534,50.9513473511],"type":"Point"}
}