{
  "type": "Feature",
  "properties": {
    "addr:full":"Lamme Quiche-erf 19 Halle Vlaams-Brabant 1500",
    "addr:housenumber":"19",
    "addr:postcode":"1500",
    "iso:country":"BE",
    "sg:address":"Lamme Quiche-erf 19",
    "sg:city":"Halle",
    "sg:classifiers":[
        {
            "category":"Professional",
            "subcategory":"Management & Consulting",
            "type":"Services"
        }
    ],
    "sg:phone":"+32 2 360 17 40",
    "sg:postcode":"1500",
    "sg:province":"Vlaams-Brabant",
    "sg:tags":[
        "consultant",
        "agency",
        "advertising"
    ],
    "wof:name":"Gifts & Products",
    "wof:placetype":"venue"
},
  "geometry": {"coordinates":[4.2258210182,50.7414627075],"type":"Point"}
}