{
  "type": "Feature",
  "properties": {
    "addr:full":"Denderstraat 34 Aalst Oost-Vlaanderen 9300",
    "addr:housenumber":"34",
    "addr:postcode":"9300",
    "addr:street":"Denderstraat",
    "iso:country":"BE",
    "sg:address":"Denderstraat 34",
    "sg:city":"Aalst",
    "sg:classifiers":[
        {
            "category":"Cafe",
            "type":"Food & Drink"
        }
    ],
    "sg:phone":"+32 53 21 21 84",
    "sg:postcode":"9300",
    "sg:province":"Oost-Vlaanderen",
    "sg:tags":[
        "caf\u00e9s"
    ],
    "wof:name":"Caf\u00c9 Tramhalte",
    "wof:placetype":"venue"
},
  "geometry": {"coordinates":[4.0362439156,50.9433174133],"type":"Point"}
}