{
  "type": "Feature",
  "properties": {
    "iso:country":"BE",
    "sg:address":"Brusselsesteenweg 2",
    "sg:city":"Mechelen",
    "sg:orig_category":"Salles de conf\u00e9rences and de r\u00e9ceptions. Salles de conf\u00e9rences and de r\u00e9ceptions. H\u00f4tels",
    "sg:phone":"+32 15 42 25 35",
    "sg:postcode":"2800",
    "sg:province":"Antwerpen",
    "wof:name":"Gulden Anker",
    "wof:placetype":"venue"
},
  "geometry": {"coordinates":[4.471601963,51.0208358765],"type":"Point"}
}