{
  "type": "Feature",
  "properties": {
    "iso:country":"BE",
    "sg:address":"Comberg 30a",
    "sg:city":"Voeren",
    "sg:orig_category":"Vakantiehuizen",
    "sg:phone":"+32 4 381 08 08",
    "sg:postcode":"3790",
    "sg:province":"Limburg",
    "wof:name":"De Mot",
    "wof:placetype":"venue"
},
  "geometry": {"coordinates":[5.8114318848,50.75050354],"type":"Point"}
}