{
  "type": "Feature",
  "properties": {
    "iso:country":"BE",
    "sg:address":"Guido Gezellestraat 12b",
    "sg:city":"Aartselaar",
    "sg:orig_category":"Advocaten and juridische adviseurs",
    "sg:phone":"+32 475 45 78 14",
    "sg:postcode":"2630",
    "sg:province":"Antwerpen",
    "wof:name":"Advokatenkantoor Van Loo & Partners",
    "wof:placetype":"venue"
},
  "geometry": {"coordinates":[4.3863620758,51.1346855164],"type":"Point"}
}