{
  "type": "Feature",
  "properties": {
    "iso:country":"BE",
    "sg:address":"Schrieksebaan 146",
    "sg:city":"Keerbergen",
    "sg:orig_category":"M\u00e9decins and sp\u00e9cialistes",
    "sg:phone":"+32 15 23 63 00",
    "sg:postcode":"3140",
    "sg:province":"Vlaams-Brabant",
    "wof:name":"Roger Jaeken",
    "wof:placetype":"venue"
},
  "geometry": {"coordinates":[4.678604126,51.0160865784],"type":"Point"}
}