{
  "type": "Feature",
  "properties": {
    "addr:full":"Avenue Du Douaire 2 Ottignies-louvain-la-neuve Brabant Wallon 1340",
    "addr:housenumber":"2",
    "addr:postcode":"1340",
    "addr:street":"Avenue Du Douaire",
    "iso:country":"BE",
    "sg:address":"Avenue Du Douaire 2",
    "sg:city":"Ottignies-louvain-la-neuve",
    "sg:orig_category":"Diverse kredietdiensten",
    "sg:postcode":"1340",
    "sg:province":"Brabant Wallon",
    "wof:name":"Bancontact-mister Cash",
    "wof:placetype":"venue"
},
  "geometry": {"coordinates":[4.5672249794,50.6636390686],"type":"Point"}
}