{
  "type": "Feature",
  "properties": {
    "addr:full":"Neerstraat 39 Zwalm Oost-Vlaanderen 9636",
    "addr:housenumber":"39",
    "addr:postcode":"9636",
    "addr:street":"Neerstraat;Oost-Vlaanderen",
    "iso:country":"BE",
    "sg:address":"Neerstraat 39",
    "sg:city":"Zwalm",
    "sg:classifiers":[
        {
            "category":"Restaurant",
            "type":"Food & Drink"
        }
    ],
    "sg:phone":"+32 55 49 85 29",
    "sg:postcode":"9636",
    "sg:province":"Oost-Vlaanderen",
    "wof:name":"'t Kapelleke",
    "wof:placetype":"venue"
},
  "geometry": {"coordinates":[3.6923160553,50.8860931396],"type":"Point"}
}