{
  "type": "Feature",
  "properties": {
    "addr:full":"Pr\u00e9 Michotte 4 Stavelot Li\u00e8ge 4970",
    "addr:housenumber":"4",
    "addr:postcode":"4970",
    "addr:street":"Pre\u0301 Michotte",
    "iso:country":"BE",
    "sg:address":"Pr\u00e9 Michotte 4",
    "sg:city":"Stavelot",
    "sg:classifiers":[
        {
            "category":"Wholesale",
            "subcategory":"Machinery & Supplies",
            "type":"Manufacturing & Wholesale Goods"
        }
    ],
    "sg:phone":"+32 80 86 28 56",
    "sg:postcode":"4970",
    "sg:province":"Li\u00e8ge",
    "sg:tags":[
        "water",
        "pump",
        "-"
    ],
    "wof:name":"Sepult Sprl",
    "wof:placetype":"venue"
},
  "geometry": {"coordinates":[5.924489975,50.392364502],"type":"Point"}
}