{
  "type": "Feature",
  "properties": {
    "addr:full":"Meibloemstraat 96 Gent Oost-Vlaanderen 9000",
    "addr:housenumber":"96",
    "addr:postcode":"9000",
    "addr:street":"Meibloemstraat;Oost-Vlaanderen",
    "iso:country":"BE",
    "sg:address":"Meibloemstraat 96",
    "sg:city":"Gent",
    "sg:classifiers":[
        {
            "category":"Social Services",
            "type":"Services"
        }
    ],
    "sg:phone":"+32 9 227 58 24",
    "sg:postcode":"9000",
    "sg:province":"Oost-Vlaanderen",
    "wof:name":"Transithuis",
    "wof:placetype":"venue"
},
  "geometry": {"coordinates":[3.6960470676,51.0599136353],"type":"Point"}
}