{
  "type": "Feature",
  "properties": {
    "addr:full":"Kruispad 32 Oud-turnhout Antwerpen 2360",
    "addr:housenumber":"32",
    "addr:postcode":"2360",
    "addr:street":"Kruispad",
    "iso:country":"BE",
    "sg:address":"Kruispad 32",
    "sg:city":"Oud-turnhout",
    "sg:orig_category":"Instituts de beaut\u00e9",
    "sg:phone":"+32 14 45 13 13",
    "sg:postcode":"2360",
    "sg:province":"Antwerpen",
    "wof:name":"Studio Mieke Van Breukelen",
    "wof:placetype":"venue"
},
  "geometry": {"coordinates":[4.9940481186,51.31980896],"type":"Point"}
}