{
  "type": "Feature",
  "properties": {
    "iso:country":"BE",
    "sg:address":"Emile Bossaertlaan 43",
    "sg:city":"Koekelberg/koekelberg",
    "sg:orig_category":"Advocaten and juridische adviseurs",
    "sg:phone":"+32 2 414 25 78",
    "sg:postcode":"1081",
    "sg:province":"Bruxelles-Capitale",
    "wof:name":"David Sprecher",
    "wof:placetype":"venue"
},
  "geometry": {"coordinates":[4.318215847,50.8636436462],"type":"Point"}
}