{
  "type": "Feature",
  "properties": {
    "iso:country":"BE",
    "sg:address":"Nederbroekstraat 6",
    "sg:city":"Destelbergen",
    "sg:orig_category":"Paramedische behandelingen",
    "sg:phone":"+32 9 252 33 00",
    "sg:postcode":"9070",
    "sg:province":"Oost-Vlaanderen",
    "wof:name":"E. Roggeman",
    "wof:placetype":"venue"
},
  "geometry": {"coordinates":[3.8111350536,51.0182952881],"type":"Point"}
}