{
  "type": "Feature",
  "properties": {
    "iso:country":"BE",
    "sg:address":"Hoog Bavegemstraat 8a",
    "sg:city":"Sint-lievens-houtem (bavegem)",
    "sg:classifiers":[
        {
            "category":"Bakery",
            "type":"Food & Drink"
        }
    ],
    "sg:phone":"+32 9 362 51 21",
    "sg:postcode":"9520",
    "sg:province":"Oost-Vlaanderen",
    "sg:tags":[
        "confectioner",
        "baker"
    ],
    "wof:name":"D'haemers G",
    "wof:placetype":"venue"
},
  "geometry": {"coordinates":[3.8600320816,50.9448051453],"type":"Point"}
}