{
  "type": "Feature",
  "properties": {
    "iso:country":"BE",
    "sg:address":"R. Cl\u00e9ment Ader 12",
    "sg:city":"Gosselies",
    "sg:classifiers":[
        {
            "category":"Professional",
            "subcategory":"Computer Services",
            "type":"Services"
        }
    ],
    "sg:phone":"+32 71 25 80 80",
    "sg:postcode":"6041",
    "sg:province":"Hainaut",
    "sg:tags":[
        "information",
        "technology",
        "software"
    ],
    "wof:name":"Selligent Sa Corporate Offices",
    "wof:placetype":"venue"
},
  "geometry": {"coordinates":[4.4639048576,50.4718856812],"type":"Point"}
}