{
  "type": "Feature",
  "properties": {
    "iso:country":"BE",
    "sg:address":"Vrijdagmarkt 65",
    "sg:city":"Gent",
    "sg:orig_category":"Schoenen",
    "sg:phone":"+32 9 223 98 51",
    "sg:postcode":"9000",
    "sg:province":"Oost-Vlaanderen",
    "wof:name":"Soldi",
    "wof:placetype":"venue"
},
  "geometry": {"coordinates":[3.7248969078,51.0567512512],"type":"Point"}
}