{
  "type": "Feature",
  "properties": {
    "addr:full":"Erasme Ruelensvest 111 Leuven (heverlee) Vlaams-Brabant 3001",
    "addr:housenumber":"111",
    "addr:postcode":"3001",
    "addr:street":"Erasme Ruelensvest",
    "iso:country":"BE",
    "sg:address":"Erasme Ruelensvest 111",
    "sg:city":"Leuven (heverlee)",
    "sg:classifiers":[
        {
            "category":"Real Estate",
            "subcategory":"Architect",
            "type":"Services"
        }
    ],
    "sg:phone":"+32 16 22 45 39",
    "sg:postcode":"3001",
    "sg:province":"Vlaams-Brabant",
    "wof:name":"De Neuter G",
    "wof:placetype":"venue"
},
  "geometry": {"coordinates":[4.7048969269,50.8681297302],"type":"Point"}
}