{
  "type": "Feature",
  "properties": {
    "addr:full":"Place De Riva-bella 12b32 Braine-l\u00b4alleud Brabant Wallon 1420",
    "addr:housenumber":"12b32",
    "addr:postcode":"1420",
    "addr:street":"Place De Riva-Bella;Brabant Wallon",
    "iso:country":"BE",
    "sg:address":"Place De Riva-bella 12b32",
    "sg:city":"Braine-l\u00b4alleud",
    "sg:orig_category":"Advocaten and juridische adviseurs",
    "sg:phone":"+32 2 384 71 46",
    "sg:postcode":"1420",
    "sg:province":"Brabant Wallon",
    "wof:name":"Aude Schepens",
    "wof:placetype":"venue"
},
  "geometry": {"coordinates":[4.3709449768,50.6845207214],"type":"Point"}
}