{
  "type": "Feature",
  "properties": {
    "iso:country":"BE",
    "sg:address":"Parc Ind.-ch\u00c9e De Wavre 28",
    "sg:city":"Perwez",
    "sg:orig_category":"Location de voitures",
    "sg:phone":"+32 81 65 94 23",
    "sg:postcode":"1360",
    "sg:province":"Brabant Wallon",
    "wof:name":"A.t.p. Rent A Car",
    "wof:placetype":"venue"
},
  "geometry": {"coordinates":[4.8067750931,50.6271057129],"type":"Point"}
}