{
  "type": "Feature",
  "properties": {
    "addr:full":"Chauss\u00c9e De Helmet 294 Bruxelles Bruxelles-Capitale 1030",
    "addr:housenumber":"294",
    "addr:postcode":"1030",
    "addr:street":"Chausse\u0301E De Helmet",
    "iso:country":"BE",
    "sg:address":"Chauss\u00c9e De Helmet 294",
    "sg:city":"Bruxelles",
    "sg:orig_category":"Articles m\u00e9talliques ouvr\u00e9s divers Fab. Composition and photogravure",
    "sg:phone":"+32 2 241 04 33",
    "sg:postcode":"1030",
    "sg:province":"Bruxelles-Capitale",
    "wof:name":"Geirnaert",
    "wof:placetype":"venue"
},
  "geometry": {"coordinates":[4.3890500069,50.874710083],"type":"Point"}
}