{
  "type": "Feature",
  "properties": {
    "addr:full":"Zone Plantis Des Aisements Momignies Hainaut 6590",
    "addr:postcode":"6590",
    "addr:street":"Hainaut",
    "iso:country":"BE",
    "sg:address":"Zone Plantis Des Aisements",
    "sg:city":"Momignies",
    "sg:classifiers":[
        {
            "category":"Shopping",
            "subcategory":"Bicycles & Sporting Goods",
            "type":"Retail Goods"
        }
    ],
    "sg:phone":"+32 60 51 41 51",
    "sg:postcode":"6590",
    "sg:province":"Hainaut",
    "sg:tags":[
        "tyre"
    ],
    "wof:name":"P.c. Pneus",
    "wof:placetype":"venue"
},
  "geometry": {"coordinates":[4.1657729149,50.02967453],"type":"Point"}
}