{
  "type": "Feature",
  "properties": {
    "addr:full":"Ieperstuk 15 Kortrijk West-Vlaanderen 8501",
    "addr:housenumber":"15",
    "addr:postcode":"8501",
    "addr:street":"Ieperstuk",
    "iso:country":"BE",
    "sg:address":"Ieperstuk 15",
    "sg:city":"Kortrijk",
    "sg:orig_category":"Verlichting and huishoudartikelen",
    "sg:phone":"+32 56 35 92 59",
    "sg:postcode":"8501",
    "sg:province":"West-Vlaanderen",
    "wof:name":"Interieur Ontwerp",
    "wof:placetype":"venue"
},
  "geometry": {"coordinates":[3.2326331139,50.8358268738],"type":"Point"}
}