{
  "type": "Feature",
  "properties": {
    "addr:full":"Apostelstraat 20 Antwerpen Antwerpen 2000",
    "addr:housenumber":"20",
    "addr:postcode":"2000",
    "addr:street":"Apostelstraat",
    "iso:country":"BE",
    "sg:address":"Apostelstraat 20",
    "sg:city":"Antwerpen",
    "sg:classifiers":[
        {
            "category":"Social Services",
            "type":"Services"
        }
    ],
    "sg:phone":"+32 3 227 12 24",
    "sg:postcode":"2000",
    "sg:province":"Antwerpen",
    "wof:name":"Riskant",
    "wof:placetype":"venue"
},
  "geometry": {"coordinates":[4.4129981995,51.2196311951],"type":"Point"}
}