{
  "type": "Feature",
  "properties": {
    "addr:full":"Rue Van Soust 277 Bruxelles (anderlecht) Bruxelles-Capitale 1070",
    "addr:housenumber":"277",
    "addr:postcode":"1070",
    "addr:street":"Rue Van Soust",
    "iso:country":"BE",
    "sg:address":"Rue Van Soust 277",
    "sg:city":"Bruxelles (anderlecht)",
    "sg:classifiers":[
        {
            "category":"Professional",
            "subcategory":"Printing & Photocopies",
            "type":"Services"
        }
    ],
    "sg:phone":"+32 2 508 16 00",
    "sg:postcode":"1070",
    "sg:province":"Bruxelles-Capitale",
    "sg:tags":[
        "digital"
    ],
    "wof:name":"D.p.i. Sprl",
    "wof:placetype":"venue"
},
  "geometry": {"coordinates":[4.3013458252,50.846622467],"type":"Point"}
}