{
  "type": "Feature",
  "properties": {
    "iso:country":"BE",
    "sg:address":"Tuinwijk 66",
    "sg:city":"Rumst",
    "sg:orig_category":"Epiceries",
    "sg:phone":"+32 3 888 78 12",
    "sg:postcode":"2840",
    "sg:province":"Antwerpen",
    "wof:name":"Supermarkten V & C",
    "wof:placetype":"venue"
},
  "geometry": {"coordinates":[4.426112175,51.0803413391],"type":"Point"}
}