{
  "type": "Feature",
  "properties": {
    "addr:full":"Avenue Du Centenaire 21 Mons (hyon) Hainaut 7022",
    "addr:housenumber":"21",
    "addr:postcode":"7022",
    "addr:street":"Avenue Du Centenaire",
    "iso:country":"BE",
    "sg:address":"Avenue Du Centenaire 21",
    "sg:city":"Mons (hyon)",
    "sg:classifiers":[
        {
            "category":"Insurance",
            "subcategory":"Insurance Agent",
            "type":"Services"
        }
    ],
    "sg:phone":"+32 65 87 48 75",
    "sg:postcode":"7022",
    "sg:province":"Hainaut",
    "sg:tags":[
        "broker"
    ],
    "wof:name":"Lescot P",
    "wof:placetype":"venue"
},
  "geometry": {"coordinates":[3.9547119141,50.4391136169],"type":"Point"}
}