{
  "type": "Feature",
  "properties": {
    "addr:full":"Kamerijkstraat 6 Gent Oost-Vlaanderen 9041",
    "addr:housenumber":"6",
    "addr:postcode":"9041",
    "addr:street":"Kamerijkstraat;Oost-Vlaanderen",
    "iso:country":"BE",
    "sg:address":"Kamerijkstraat 6",
    "sg:city":"Gent",
    "sg:classifiers":[
        {
            "category":"Government",
            "subcategory":"Department Of Motor Vehicles",
            "type":"Public Place"
        }
    ],
    "sg:phone":"+32 9 251 09 47",
    "sg:postcode":"9041",
    "sg:province":"Oost-Vlaanderen",
    "sg:tags":[
        "tractor"
    ],
    "wof:name":"Ldh-trans",
    "wof:placetype":"venue"
},
  "geometry": {"coordinates":[3.7781629562,51.0982093811],"type":"Point"}
}