{
  "type": "Feature",
  "properties": {
    "iso:country":"BE",
    "sg:address":"Ardooisesteenweg 39",
    "sg:city":"Roeselare",
    "sg:orig_category":"Instituts pour enfants en difficult\u00e9. Orphelinats",
    "sg:phone":"+32 51 20 15 58",
    "sg:postcode":"8800",
    "sg:province":"West-Vlaanderen",
    "wof:name":"Dagcentrum De Trompet",
    "wof:placetype":"venue"
},
  "geometry": {"coordinates":[3.1322119236,50.9495620728],"type":"Point"}
}