{
  "type": "Feature",
  "properties": {
    "iso:country":"BE",
    "sg:address":"Reeweg 51",
    "sg:city":"Genk",
    "sg:orig_category":"M\u00e9decins and sp\u00e9cialistes",
    "sg:phone":"+32 89 36 16 90",
    "sg:postcode":"3600",
    "sg:province":"Limburg",
    "wof:name":"Constantinus Politis",
    "wof:placetype":"venue"
},
  "geometry": {"coordinates":[5.5169258118,50.9493293762],"type":"Point"}
}