{
  "type": "Feature",
  "properties": {
    "iso:country":"BE",
    "sg:address":"Rue De Fleurus 28",
    "sg:city":"Sambreville (moignel\u00e9e)",
    "sg:classifiers":[
        {
            "category":"Real Estate",
            "subcategory":"Surveying",
            "type":"Services"
        }
    ],
    "sg:phone":"+32 71 76 03 66",
    "sg:postcode":"5060",
    "sg:province":"Namur",
    "sg:tags":[
        "lettering",
        "letter"
    ],
    "wof:name":"Plgs Design Sa",
    "wof:placetype":"venue"
},
  "geometry": {"coordinates":[4.58913517,50.4399147034],"type":"Point"}
}