{
  "type": "Feature",
  "properties": {
    "iso:country":"BE",
    "sg:address":"Desir\u00c9 Delcroixstraat 5",
    "sg:city":"Deinze",
    "sg:classifiers":[
        {
            "category":"Arena",
            "subcategory":"Sports Club",
            "type":"Entertainment"
        }
    ],
    "sg:phone":"+32 9 386 09 16",
    "sg:postcode":"9800",
    "sg:province":"Oost-Vlaanderen",
    "sg:tags":[
        "de"
    ],
    "wof:name":"Deinze Yacht Club",
    "wof:placetype":"venue"
},
  "geometry": {"coordinates":[3.5390050411,50.9851379395],"type":"Point"}
}