{
  "type": "Feature",
  "properties": {
    "iso:country":"BE",
    "sg:address":"August Vermeylenstraat 6",
    "sg:city":"Oostende",
    "sg:orig_category":"Voertuigen",
    "sg:phone":"+32 59 50 69 72",
    "sg:postcode":"8400",
    "sg:province":"West-Vlaanderen",
    "wof:name":"Mano Vanhove",
    "wof:placetype":"venue"
},
  "geometry": {"coordinates":[2.927560091,51.216999054],"type":"Point"}
}