{
  "type": "Feature",
  "properties": {
    "addr:full":"Hoverheide 34 Hove Antwerpen 2540",
    "addr:housenumber":"34",
    "addr:postcode":"2540",
    "addr:street":"Hoverheide",
    "iso:country":"BE",
    "sg:address":"Hoverheide 34",
    "sg:city":"Hove",
    "sg:classifiers":[
        {
            "category":"Professional",
            "subcategory":"Management & Consulting",
            "type":"Services"
        }
    ],
    "sg:phone":"+32 3 455 17 78",
    "sg:postcode":"2540",
    "sg:province":"Antwerpen",
    "sg:tags":[
        "tax-consultants"
    ],
    "wof:name":"Verstraeten E",
    "wof:placetype":"venue"
},
  "geometry": {"coordinates":[4.4602031708,51.159122467],"type":"Point"}
}