{
  "type": "Feature",
  "properties": {
    "addr:full":"Dorpsstraat 47 Bilzen Limburg 3740",
    "addr:housenumber":"47",
    "addr:postcode":"3740",
    "addr:street":"Dorpsstraat",
    "iso:country":"BE",
    "sg:address":"Dorpsstraat 47",
    "sg:city":"Bilzen",
    "sg:orig_category":"Banques and organismes de cr\u00e9dit",
    "sg:phone":"+32 89 50 26 92",
    "sg:postcode":"3740",
    "sg:province":"Limburg",
    "wof:name":"Ippa",
    "wof:placetype":"venue"
},
  "geometry": {"coordinates":[5.5750641823,50.8739967346],"type":"Point"}
}