{
  "type": "Feature",
  "properties": {
    "iso:country":"BE",
    "sg:address":"Kerkstraat 98ba",
    "sg:city":"Sint-pieters-woluwe/woluwe-saint-pierre",
    "sg:orig_category":"Dameskledingzaken",
    "sg:phone":"+32 2 772 86 15",
    "sg:postcode":"1150",
    "sg:province":"Bruxelles-Capitale",
    "wof:name":"Boutique Laurence",
    "wof:placetype":"venue"
},
  "geometry": {"coordinates":[4.4640359879,50.840675354],"type":"Point"}
}