{
  "type": "Feature",
  "properties": {
    "iso:country":"BE",
    "sg:address":"Heirbaan 196",
    "sg:city":"Hamme",
    "sg:orig_category":"Installation de menuiserie en bois and plastique. Installation de menuiserie m\u00e9tallique",
    "sg:phone":"+32 52 47 13 84",
    "sg:postcode":"9220",
    "sg:province":"Oost-Vlaanderen",
    "wof:name":"Daniel Waegeman",
    "wof:placetype":"venue"
},
  "geometry": {"coordinates":[4.0920262337,51.0770645142],"type":"Point"}
}