{
  "type": "Feature",
  "properties": {
    "iso:country":"BE",
    "sg:address":"Mandellaan 93",
    "sg:city":"Roeselare",
    "sg:orig_category":"Epiceries",
    "sg:phone":"+32 51 20 27 21",
    "sg:postcode":"8800",
    "sg:province":"West-Vlaanderen",
    "wof:name":"'t Hoekske",
    "wof:placetype":"venue"
},
  "geometry": {"coordinates":[3.1354210377,50.9543876648],"type":"Point"}
}