{
  "type": "Feature",
  "properties": {
    "iso:country":"BE",
    "sg:address":"Avenue Albertine 30",
    "sg:city":"Rixensart",
    "sg:classifiers":[
        {
            "category":"Health Services",
            "subcategory":"Health Practitioner",
            "type":"Services"
        }
    ],
    "sg:phone":"+32 2 653 70 25",
    "sg:postcode":"1330",
    "sg:province":"Brabant Wallon",
    "sg:tags":[
        "physiotherapist"
    ],
    "wof:name":"Van Der Schueren Frederic",
    "wof:placetype":"venue"
},
  "geometry": {"coordinates":[4.5368680954,50.707244873],"type":"Point"}
}