{
  "type": "Feature",
  "properties": {
    "iso:country":"BE",
    "sg:address":"Avenue De La Lib\u00c9ration 82",
    "sg:city":"Couvin",
    "sg:orig_category":"Installation de menuiserie m\u00e9tallique. Installation de menuiserie en bois and plastique. Constructio",
    "sg:phone":"+32 60 34 59 79",
    "sg:postcode":"5660",
    "sg:province":"Namur",
    "wof:name":"Euro-dif-bel",
    "wof:placetype":"venue"
},
  "geometry": {"coordinates":[4.4854960442,50.05493927],"type":"Point"}
}