{
  "type": "Feature",
  "properties": {
    "iso:country":"BE",
    "sg:address":"Slagmeersenstraat 67",
    "sg:city":"Izegem",
    "sg:classifiers":[
        {
            "category":"Real Estate",
            "subcategory":"Architect",
            "type":"Services"
        }
    ],
    "sg:phone":"+32 51 30 08 86",
    "sg:postcode":"8870",
    "sg:province":"West-Vlaanderen",
    "wof:name":"Blieck S",
    "wof:placetype":"venue"
},
  "geometry": {"coordinates":[3.2245500088,50.9137992859],"type":"Point"}
}