{
  "type": "Feature",
  "properties": {
    "addr:full":"Westkapellestraat 39 Knokke-heist West-Vlaanderen 8301",
    "addr:housenumber":"39",
    "addr:postcode":"8301",
    "addr:street":"Westkapellestraat",
    "iso:country":"BE",
    "sg:address":"Westkapellestraat 39",
    "sg:city":"Knokke-heist",
    "sg:orig_category":"Woningbouw",
    "sg:phone":"+32 50 51 26 98",
    "sg:postcode":"8301",
    "sg:province":"West-Vlaanderen",
    "wof:name":"Willy Bostyn",
    "wof:placetype":"venue"
},
  "geometry": {"coordinates":[3.2554140091,51.3313560486],"type":"Point"}
}