{
  "type": "Feature",
  "properties": {
    "iso:country":"BE",
    "sg:address":"Kloosterstraat 5",
    "sg:city":"Heist-op-den-berg",
    "sg:orig_category":"Algemeen secundair onderwijs Technisch and beroeps secundair onderwijs",
    "sg:phone":"+32 15 24 16 36",
    "sg:postcode":"2220",
    "sg:province":"Antwerpen",
    "wof:name":"Heilig Hart-bovenbouw 1",
    "wof:placetype":"venue"
},
  "geometry": {"coordinates":[4.7313017845,51.0761299133],"type":"Point"}
}