{
  "type": "Feature",
  "properties": {
    "iso:country":"BE",
    "sg:address":"Briekhoekstraat 3",
    "sg:city":"Moorslede",
    "sg:orig_category":"Solar protection - Inside",
    "sg:phone":"+32 51 20 26 31",
    "sg:postcode":"8890",
    "sg:province":"West-Vlaanderen",
    "wof:name":"Soliflex Bvba",
    "wof:placetype":"venue"
},
  "geometry": {"coordinates":[3.082365036,50.8874893188],"type":"Point"}
}