{
  "type": "Feature",
  "properties": {
    "addr:full":"Reikemstraat 17bc Herent Vlaams-Brabant 3020",
    "addr:housenumber":"17bc",
    "addr:postcode":"3020",
    "addr:street":"Reikemstraat",
    "iso:country":"BE",
    "sg:address":"Reikemstraat 17bc",
    "sg:city":"Herent",
    "sg:orig_category":"Dranken",
    "sg:phone":"+32 16 49 03 30",
    "sg:postcode":"3020",
    "sg:province":"Vlaams-Brabant",
    "wof:name":"Alcimex",
    "wof:placetype":"venue"
},
  "geometry": {"coordinates":[4.6749200821,50.9079055786],"type":"Point"}
}