{
  "type": "Feature",
  "properties": {
    "iso:country":"BE",
    "sg:address":"Kloosteraprilstraat 1",
    "sg:city":"Assenede",
    "sg:orig_category":"Zuivelproducten",
    "sg:phone":"+32 9 344 60 23",
    "sg:postcode":"9960",
    "sg:province":"Oost-Vlaanderen",
    "wof:name":"Medard De Vuyst",
    "wof:placetype":"venue"
},
  "geometry": {"coordinates":[3.7658851147,51.2214202881],"type":"Point"}
}