{
  "type": "Feature",
  "properties": {
    "addr:full":"Rue B\u00c9ribou 4 Verviers Li\u00e8ge 4800",
    "addr:housenumber":"4",
    "addr:postcode":"4800",
    "addr:street":"Rue Be\u0301Ribou",
    "iso:country":"BE",
    "sg:address":"Rue B\u00c9ribou 4",
    "sg:city":"Verviers",
    "sg:orig_category":"Produits chimiques Gr",
    "sg:phone":"+32 87 33 61 21",
    "sg:postcode":"4800",
    "sg:province":"Li\u00e8ge",
    "wof:name":"Westbroek Lanolin Company",
    "wof:placetype":"venue"
},
  "geometry": {"coordinates":[5.8463191986,50.5946235657],"type":"Point"}
}