{
  "type": "Feature",
  "properties": {
    "iso:country":"BE",
    "sg:address":"Leuvensesteenweg 80",
    "sg:city":"Kortenberg",
    "sg:classifiers":[
        {
            "category":"Utilities",
            "subcategory":"Natural Gas",
            "type":"Services"
        }
    ],
    "sg:phone":"+32 2 759 85 64",
    "sg:postcode":"3070",
    "sg:province":"Vlaams-Brabant",
    "sg:tags":[
        "hide",
        "skin"
    ],
    "wof:name":"Stolz Bvba",
    "wof:placetype":"venue"
},
  "geometry": {"coordinates":[4.5287852287,50.8839530945],"type":"Point"}
}