{
  "type": "Feature",
  "properties": {
    "addr:full":"Windmolenlaan 46 Zaventem (sterrebeek) Vlaams-Brabant 1933",
    "addr:housenumber":"46",
    "addr:postcode":"1933",
    "addr:street":"Windmolenlaan",
    "iso:country":"BE",
    "sg:address":"Windmolenlaan 46",
    "sg:city":"Zaventem (sterrebeek)",
    "sg:classifiers":[
        {
            "category":"Real Estate",
            "subcategory":"Architect",
            "type":"Services"
        }
    ],
    "sg:phone":"+32 2 731 95 09",
    "sg:postcode":"1933",
    "sg:province":"Vlaams-Brabant",
    "wof:name":"Ceuppens M",
    "wof:placetype":"venue"
},
  "geometry": {"coordinates":[4.5108280182,50.8654632568],"type":"Point"}
}