{
  "type": "Feature",
  "properties": {
    "iso:country":"BE",
    "sg:address":"Limburgerweg 6",
    "sg:city":"Eupen/eupen",
    "sg:classifiers":[
        {
            "category":"Wholesale",
            "subcategory":"Farm Supplies",
            "type":"Manufacturing & Wholesale Goods"
        }
    ],
    "sg:phone":"+32 87 74 44 57",
    "sg:postcode":"4700",
    "sg:province":"Li\u00e8ge",
    "sg:tags":[
        "machine",
        "agricoles",
        "mat\u00e9riel",
        "gr"
    ],
    "wof:name":"Peters Maschinenbau Eupen",
    "wof:placetype":"venue"
},
  "geometry": {"coordinates":[6.0299119949,50.6229782104],"type":"Point"}
}