{
  "type": "Feature",
  "properties": {
    "iso:country":"BE",
    "sg:address":"Schoolstraat 3",
    "sg:city":"Kapelle-op-den-bos",
    "sg:orig_category":"Pharmaciens",
    "sg:phone":"+32 15 71 11 69",
    "sg:postcode":"1880",
    "sg:province":"Vlaams-Brabant",
    "wof:name":"Vemaco",
    "wof:placetype":"venue"
},
  "geometry": {"coordinates":[4.360461235,51.0119056702],"type":"Point"}
}