{
  "type": "Feature",
  "properties": {
    "addr:full":"Chemin D'amelgem 1 Wemmel/wemmel Vlaams-Brabant 1780",
    "addr:housenumber":"1",
    "addr:postcode":"1780",
    "addr:street":"Chemin D'Amelgem",
    "iso:country":"BE",
    "sg:address":"Chemin D'amelgem 1",
    "sg:city":"Wemmel/wemmel",
    "sg:orig_category":"M\u00e9decins and sp\u00e9cialistes",
    "sg:phone":"+32 2 461 26 93",
    "sg:postcode":"1780",
    "sg:province":"Vlaams-Brabant",
    "wof:name":"A. De Coninck",
    "wof:placetype":"venue"
},
  "geometry": {"coordinates":[4.317109108,50.9208221436],"type":"Point"}
}