{
  "type": "Feature",
  "properties": {
    "iso:country":"BE",
    "sg:address":"Warandestraat 4",
    "sg:city":"Ravels",
    "sg:orig_category":"Woningbouw",
    "sg:phone":"+32 14 65 03 45",
    "sg:postcode":"2380",
    "sg:province":"Antwerpen",
    "wof:name":"Rijkers Patrick",
    "wof:placetype":"venue"
},
  "geometry": {"coordinates":[5.0120849609,51.3734664917],"type":"Point"}
}