{
  "type": "Feature",
  "properties": {
    "iso:country":"BE",
    "sg:address":"Langestraat 15",
    "sg:city":"Lebbeke",
    "sg:orig_category":"Groententeelt",
    "sg:phone":"+32 52 41 15 65",
    "sg:postcode":"9280",
    "sg:province":"Oost-Vlaanderen",
    "wof:name":"Theofiel De Kinder",
    "wof:placetype":"venue"
},
  "geometry": {"coordinates":[4.1481070518,51.0004920959],"type":"Point"}
}