{
  "type": "Feature",
  "properties": {
    "addr:full":"Elleboogstraat 16 Mechelen Antwerpen 2811",
    "addr:housenumber":"16",
    "addr:postcode":"2811",
    "addr:street":"Elleboogstraat",
    "iso:country":"BE",
    "sg:address":"Elleboogstraat 16",
    "sg:city":"Mechelen",
    "sg:orig_category":"Installation de menuiserie en bois and plastique",
    "sg:phone":"+32 15 21 82 80",
    "sg:postcode":"2811",
    "sg:province":"Antwerpen",
    "wof:name":"De Hondt-diddens",
    "wof:placetype":"venue"
},
  "geometry": {"coordinates":[4.4074540138,51.028968811],"type":"Point"}
}