{
  "type": "Feature",
  "properties": {
    "addr:full":"Rue Joseph Dufrane 2 Frameries Hainaut 7080",
    "addr:housenumber":"2",
    "addr:postcode":"7080",
    "addr:street":"Rue Joseph Dufrane",
    "iso:country":"BE",
    "sg:address":"Rue Joseph Dufrane 2",
    "sg:city":"Frameries",
    "sg:orig_category":"Pharmaciens",
    "sg:phone":"+32 65 67 11 28",
    "sg:postcode":"7080",
    "sg:province":"Hainaut",
    "wof:name":"Philippe Maroquin",
    "wof:placetype":"venue"
},
  "geometry": {"coordinates":[3.8933029175,50.4071922302],"type":"Point"}
}