{
  "type": "Feature",
  "properties": {
    "iso:country":"BE",
    "sg:address":"Diestsestraat 31",
    "sg:city":"Kortenaken",
    "sg:orig_category":"Fruitteelt",
    "sg:phone":"+32 11 58 78 32",
    "sg:postcode":"3470",
    "sg:province":"Vlaams-Brabant",
    "wof:name":"Herman Spapen",
    "wof:placetype":"venue"
},
  "geometry": {"coordinates":[5.0615720749,50.9134521484],"type":"Point"}
}