{
  "type": "Feature",
  "properties": {
    "iso:country":"BE",
    "sg:address":"Dokter Eduard Moreauxlaan 65",
    "sg:city":"Oostende",
    "sg:classifiers":[
        {
            "category":"Home & Garden",
            "subcategory":"Home Furnishings",
            "type":"Retail Goods"
        }
    ],
    "sg:phone":"+32 59 32 08 92",
    "sg:postcode":"8400",
    "sg:province":"West-Vlaanderen",
    "sg:tags":[
        "curtain",
        "-",
        "fixture"
    ],
    "wof:name":"Deco Rosseel Nv",
    "wof:placetype":"venue"
},
  "geometry": {"coordinates":[2.941865921,51.224445343],"type":"Point"}
}