{
  "type": "Feature",
  "properties": {
    "iso:country":"BE",
    "sg:address":"Pekelharing 2",
    "sg:city":"Gent",
    "sg:classifiers":[
        {
            "category":"Health Services",
            "subcategory":"Health Practitioner",
            "type":"Services"
        }
    ],
    "sg:phone":"+32 9 225 68 10",
    "sg:postcode":"9000",
    "sg:province":"Oost-Vlaanderen",
    "sg:tags":[
        "psychologist"
    ],
    "wof:name":"De Man A",
    "wof:placetype":"venue"
},
  "geometry": {"coordinates":[3.7195529938,51.049030304],"type":"Point"}
}