{
  "type": "Feature",
  "properties": {
    "iso:country":"BE",
    "sg:address":"Ten Bogaerdeplein 5",
    "sg:city":"Edegem",
    "sg:classifiers":[
        {
            "category":"Retail",
            "subcategory":"Veterinary Services",
            "type":"Services"
        }
    ],
    "sg:phone":"+32 3 440 70 56",
    "sg:postcode":"2650",
    "sg:province":"Antwerpen",
    "sg:tags":[
        "veterinarian"
    ],
    "wof:name":"Feyen L",
    "wof:placetype":"venue"
},
  "geometry": {"coordinates":[4.4245271683,51.163230896],"type":"Point"}
}