{
  "type": "Feature",
  "properties": {
    "iso:country":"BE",
    "sg:address":"Avenue De La Sapini\u00c8re 32",
    "sg:city":"Rixensart",
    "sg:orig_category":"Loodgieterij, verwarming and sanitaire installaties",
    "sg:phone":"+32 2 653 75 41",
    "sg:postcode":"1331",
    "sg:province":"Brabant Wallon",
    "wof:name":"Henri Sackenprez",
    "wof:placetype":"venue"
},
  "geometry": {"coordinates":[4.5406479836,50.735042572],"type":"Point"}
}