{
  "type": "Feature",
  "properties": {
    "iso:country":"BE",
    "sg:address":"Rue C\u00c9sar Despretz 14",
    "sg:city":"Lessines",
    "sg:classifiers":[
        {
            "category":"Restaurant",
            "type":"Food & Drink"
        }
    ],
    "sg:phone":"+32 68 33 67 82",
    "sg:postcode":"7860",
    "sg:province":"Hainaut",
    "wof:name":"Le Dauphin",
    "wof:placetype":"venue"
},
  "geometry": {"coordinates":[3.8285050392,50.7120246887],"type":"Point"}
}