{
  "type": "Feature",
  "properties": {
    "addr:full":"Sint-jobsesteenweg 666 Ukkel/uccle Bruxelles-Capitale 1180",
    "addr:housenumber":"666",
    "addr:postcode":"1180",
    "addr:street":"Sint-Jobsesteenweg;/",
    "iso:country":"BE",
    "sg:address":"Sint-jobsesteenweg 666",
    "sg:city":"Ukkel/uccle",
    "sg:orig_category":"Drukkerijen and copyshops",
    "sg:phone":"+32 2 375 23 69",
    "sg:postcode":"1180",
    "sg:province":"Bruxelles-Capitale",
    "wof:name":"Paperland",
    "wof:placetype":"venue"
},
  "geometry": {"coordinates":[4.3646950722,50.7946014404],"type":"Point"}
}