{
  "type": "Feature",
  "properties": {
    "iso:country":"BE",
    "sg:address":"Rue P\u00e8re Cambier 17",
    "sg:city":"Namur",
    "sg:classifiers":[
        {
            "category":"Sports & Exercise",
            "subcategory":"Climbing Gym",
            "type":"Entertainment"
        }
    ],
    "sg:phone":"+32 81 74 03 07",
    "sg:postcode":"5000",
    "sg:province":"Namur",
    "sg:tags":[
        "water",
        "article"
    ],
    "wof:name":"Neree Sprlu",
    "wof:placetype":"venue"
},
  "geometry": {"coordinates":[4.8515849113,50.4673194885],"type":"Point"}
}