{
  "type": "Feature",
  "properties": {
    "iso:country":"BE",
    "sg:address":"Stastionsstraat 55",
    "sg:city":"Waasmunster",
    "sg:classifiers":[
        {
            "category":"Personal",
            "subcategory":"Beauty Salon",
            "type":"Services"
        }
    ],
    "sg:phone":"+32 52 46 20 46",
    "sg:postcode":"9250",
    "sg:province":"Oost-Vlaanderen",
    "sg:tags":[
        "de",
        "coiffure"
    ],
    "wof:name":"Caresse",
    "wof:placetype":"venue"
},
  "geometry": {"coordinates":[4.0877051353,51.1107292175],"type":"Point"}
}