{
  "type": "Feature",
  "properties": {
    "iso:country":"BE",
    "sg:address":"Avenue Des Courtils 33",
    "sg:city":"Oupeye",
    "sg:orig_category":"Onderdelen and accessoires voor auto's",
    "sg:phone":"+32 4 379 10 14",
    "sg:postcode":"4684",
    "sg:province":"Li\u00e8ge",
    "wof:name":"Autoval",
    "wof:placetype":"venue"
},
  "geometry": {"coordinates":[5.6676812172,50.7285575867],"type":"Point"}
}