{
  "type": "Feature",
  "properties": {
    "addr:full":"Herenbaan-oost 64a Houthalen-helchteren Limburg 3530",
    "addr:housenumber":"64a",
    "addr:postcode":"3530",
    "addr:street":"Herenbaan-Oost",
    "iso:country":"BE",
    "sg:address":"Herenbaan-oost 64a",
    "sg:city":"Houthalen-helchteren",
    "sg:orig_category":"Verlichting and huishoudartikelen",
    "sg:phone":"+32 11 52 52 38",
    "sg:postcode":"3530",
    "sg:province":"Limburg",
    "wof:name":"Gilissen G Dekor",
    "wof:placetype":"venue"
},
  "geometry": {"coordinates":[5.3719201088,51.0310020447],"type":"Point"}
}