{
  "type": "Feature",
  "properties": {
    "iso:country":"BE",
    "sg:address":"Place Lucien Molitor 2",
    "sg:city":"Oupeye",
    "sg:orig_category":"Apotheken",
    "sg:phone":"+32 4 379 17 24",
    "sg:postcode":"4681",
    "sg:province":"Li\u00e8ge",
    "wof:name":"Nicole Michel",
    "wof:placetype":"venue"
},
  "geometry": {"coordinates":[5.6798892021,50.7113418579],"type":"Point"}
}