{
  "type": "Feature",
  "properties": {
    "iso:country":"BE",
    "sg:address":"Rue Le Lorrain 6-8",
    "sg:city":"Bruxelles (molenbeek-saint-jean)",
    "sg:classifiers":[
        {
            "category":"Wholesale",
            "subcategory":"Scrap",
            "type":"Manufacturing & Wholesale Goods"
        }
    ],
    "sg:phone":"+32 2 420 67 13",
    "sg:postcode":"1080",
    "sg:province":"Bruxelles-Capitale",
    "sg:tags":[
        "metal"
    ],
    "wof:name":"Brum\u00e9tal",
    "wof:placetype":"venue"
},
  "geometry": {"coordinates":[4.3464927673,50.8624572754],"type":"Point"}
}