{
  "type": "Feature",
  "properties": {
    "iso:country":"BE",
    "sg:address":"Rue De Bouvy 7b5",
    "sg:city":"La Louviere",
    "sg:orig_category":"Agences de voyages",
    "sg:phone":"+32 64 26 24 55",
    "sg:postcode":"7100",
    "sg:province":"Hainaut",
    "wof:name":"Echanges Linguistiques",
    "wof:placetype":"venue"
},
  "geometry": {"coordinates":[4.1865592003,50.4743728638],"type":"Point"}
}