{
  "type": "Feature",
  "properties": {
    "addr:full":"Berkenlaan 44 Kasterlee Antwerpen 2460",
    "addr:housenumber":"44",
    "addr:postcode":"2460",
    "addr:street":"Berkenlaan",
    "iso:country":"BE",
    "sg:address":"Berkenlaan 44",
    "sg:city":"Kasterlee",
    "sg:classifiers":[
        {
            "category":"Communications",
            "subcategory":"Radio Station",
            "type":"Services"
        }
    ],
    "sg:phone":"+32 14 85 32 63",
    "sg:postcode":"2460",
    "sg:province":"Antwerpen",
    "sg:tags":[
        "medium",
        "broker"
    ],
    "wof:name":"Multi Media Management Bvba",
    "wof:placetype":"venue"
},
  "geometry": {"coordinates":[4.978181839,51.2372932434],"type":"Point"}
}