{
  "type": "Feature",
  "properties": {
    "addr:full":"Sint-bernardsstraat 25 Boechout (vremde) Antwerpen 2531",
    "addr:housenumber":"25",
    "addr:postcode":"2531",
    "addr:street":"Sint-Bernardsstraat",
    "iso:country":"BE",
    "sg:address":"Sint-bernardsstraat 25",
    "sg:city":"Boechout (vremde)",
    "sg:classifiers":[
        {
            "category":"Industrial Area",
            "type":"Public Place"
        }
    ],
    "sg:phone":"+32 3 475 91 69",
    "sg:postcode":"2531",
    "sg:province":"Antwerpen",
    "sg:tags":[
        "-",
        "lighting"
    ],
    "wof:name":"Crolux",
    "wof:placetype":"venue"
},
  "geometry": {"coordinates":[4.5446271896,51.1759490967],"type":"Point"}
}