{
  "type": "Feature",
  "properties": {
    "iso:country":"BE",
    "sg:address":"Barend Van Orleystraat 8",
    "sg:city":"Kortrijk",
    "sg:orig_category":"Artsen and specialisten",
    "sg:phone":"+32 56 20 34 53",
    "sg:postcode":"8510",
    "sg:province":"West-Vlaanderen",
    "wof:name":"Marc Busschaert",
    "wof:placetype":"venue"
},
  "geometry": {"coordinates":[3.2580549717,50.8038215637],"type":"Point"}
}