{
  "type": "Feature",
  "properties": {
    "iso:country":"BE",
    "sg:address":"Route De Hannut 530",
    "sg:city":"Namur",
    "sg:orig_category":"Alimentation sp\u00e9cialis\u00e9e. Catering and organisation de f\u00eates. Boucheries",
    "sg:phone":"+32 81 21 09 50",
    "sg:postcode":"5024",
    "sg:province":"Namur",
    "wof:name":"La Cote \u00c0 L'os",
    "wof:placetype":"venue"
},
  "geometry": {"coordinates":[4.9563660622,50.5052680969],"type":"Point"}
}