{
  "type": "Feature",
  "properties": {
    "addr:full":"Kardinaal Mercierstraat 10 Knokke-heist West-Vlaanderen 8301",
    "addr:housenumber":"10",
    "addr:postcode":"8301",
    "addr:street":"Kardinaal Mercierstraat",
    "iso:country":"BE",
    "sg:address":"Kardinaal Mercierstraat 10",
    "sg:city":"Knokke-heist",
    "sg:classifiers":[
        {
            "category":"Restaurant",
            "type":"Food & Drink"
        }
    ],
    "sg:phone":"+32 50 51 56 79",
    "sg:postcode":"8301",
    "sg:province":"West-Vlaanderen",
    "wof:name":"Caroline",
    "wof:placetype":"venue"
},
  "geometry": {"coordinates":[3.2639000416,51.3396911621],"type":"Point"}
}