{
  "type": "Feature",
  "properties": {
    "addr:full":"Place Albert-ier 7 Nivelles Brabant Wallon 1400",
    "addr:housenumber":"7",
    "addr:postcode":"1400",
    "addr:street":"Place Albert-Ier",
    "iso:country":"BE",
    "sg:address":"Place Albert-ier 7",
    "sg:city":"Nivelles",
    "sg:orig_category":"Banken and kredietinstellingen",
    "sg:phone":"+32 67 21 37 93",
    "sg:postcode":"1400",
    "sg:province":"Brabant Wallon",
    "wof:name":"Bbl",
    "wof:placetype":"venue"
},
  "geometry": {"coordinates":[4.3224568367,50.5976676941],"type":"Point"}
}