{
  "type": "Feature",
  "properties": {
    "addr:full":"Rue Des Cortils 9 Namur Namur 5101",
    "addr:housenumber":"9",
    "addr:postcode":"5101",
    "addr:street":"Rue Des Cortils",
    "iso:country":"BE",
    "sg:address":"Rue Des Cortils 9",
    "sg:city":"Namur",
    "sg:orig_category":"Rundveehouders",
    "sg:phone":"+32 81 30 68 23",
    "sg:postcode":"5101",
    "sg:province":"Namur",
    "wof:name":"Jean-pierre Rase",
    "wof:placetype":"venue"
},
  "geometry": {"coordinates":[4.9024009705,50.4496536255],"type":"Point"}
}