{
  "type": "Feature",
  "properties": {
    "addr:full":"Rue Louis Bierin 1 Pepinster Li\u00e8ge 4860",
    "addr:housenumber":"1",
    "addr:postcode":"4860",
    "addr:street":"Rue Louis Bierin",
    "iso:country":"BE",
    "sg:address":"Rue Louis Bierin 1",
    "sg:city":"Pepinster",
    "sg:orig_category":"Loodgieterij, verwarming and sanitaire installaties",
    "sg:phone":"+32 87 46 89 05",
    "sg:postcode":"4860",
    "sg:province":"Li\u00e8ge",
    "wof:name":"J-l Constant",
    "wof:placetype":"venue"
},
  "geometry": {"coordinates":[5.7970728874,50.5706710815],"type":"Point"}
}