{
  "type": "Feature",
  "properties": {
    "iso:country":"BE",
    "sg:address":"Rue Colette 5",
    "sg:city":"Tournai (blandain - Hertain)",
    "sg:classifiers":[
        {
            "category":"Retail",
            "subcategory":"Veterinary Services",
            "type":"Services"
        }
    ],
    "sg:phone":"+32 69 66 77 88",
    "sg:postcode":"7522",
    "sg:province":"Hainaut",
    "sg:tags":[
        "veterinarian"
    ],
    "wof:name":"Boonaert O",
    "wof:placetype":"venue"
},
  "geometry": {"coordinates":[3.2996730804,50.6228637695],"type":"Point"}
}