{
  "type": "Feature",
  "properties": {
    "iso:country":"BE",
    "sg:address":"Rue Neuve 20",
    "sg:city":"Charleroi",
    "sg:classifiers":[
        {
            "category":"Communications",
            "subcategory":"Film & Video Production",
            "type":"Services"
        }
    ],
    "sg:phone":"+32 71 30 43 63",
    "sg:postcode":"6000",
    "sg:province":"Hainaut",
    "sg:tags":[
        "cassette",
        "retail",
        "-",
        "tape"
    ],
    "wof:name":"Video 58",
    "wof:placetype":"venue"
},
  "geometry": {"coordinates":[4.4445309639,50.4127311707],"type":"Point"}
}