{
  "type": "Feature",
  "properties": {
    "addr:full":"Sint-gillislaan 39 Dendermonde Oost-Vlaanderen 9200",
    "addr:housenumber":"39",
    "addr:postcode":"9200",
    "addr:street":"Sint-Gillislaan;Oost-Vlaanderen",
    "iso:country":"BE",
    "sg:address":"Sint-gillislaan 39",
    "sg:city":"Dendermonde",
    "sg:classifiers":[
        {
            "category":"Health Services",
            "subcategory":"Health Practitioner",
            "type":"Services"
        }
    ],
    "sg:phone":"+32 52 21 43 33",
    "sg:postcode":"9200",
    "sg:province":"Oost-Vlaanderen",
    "sg:tags":[
        "therapist",
        "speech"
    ],
    "wof:name":"Blondia Fabienne",
    "wof:placetype":"venue"
},
  "geometry": {"coordinates":[4.1077861786,51.0219573975],"type":"Point"}
}