{
  "type": "Feature",
  "properties": {
    "addr:full":"Oosteindestraat 23 Evergem Oost-Vlaanderen 9940",
    "addr:housenumber":"23",
    "addr:postcode":"9940",
    "addr:street":"Oosteindestraat;Oost-Vlaanderen",
    "iso:country":"BE",
    "sg:address":"Oosteindestraat 23",
    "sg:city":"Evergem",
    "sg:orig_category":"Entretien and r\u00e9parations de voitures",
    "sg:phone":"+32 9 253 07 41",
    "sg:postcode":"9940",
    "sg:province":"Oost-Vlaanderen",
    "wof:name":"Carrosserie Tuytschaever",
    "wof:placetype":"venue"
},
  "geometry": {"coordinates":[3.6665349007,51.1021728516],"type":"Point"}
}