{
  "type": "Feature",
  "properties": {
    "addr:full":"Ridder Van Ranstlei 22 Mortsel Antwerpen 2640",
    "addr:housenumber":"22",
    "addr:postcode":"2640",
    "addr:street":"Ridder Van Ranstlei",
    "iso:country":"BE",
    "sg:address":"Ridder Van Ranstlei 22",
    "sg:city":"Mortsel",
    "sg:orig_category":"Eclairage et \u00e9quipements du foyer. Souvenirs and objets artisanaux",
    "sg:phone":"+32 3 449 98 93",
    "sg:postcode":"2640",
    "sg:province":"Antwerpen",
    "wof:name":"Huis Donum",
    "wof:placetype":"venue"
},
  "geometry": {"coordinates":[4.4396438599,51.1742362976],"type":"Point"}
}