{
  "type": "Feature",
  "properties": {
    "addr:full":"Oudstrijderslaan 16 Ledegem West-Vlaanderen 8880",
    "addr:housenumber":"16",
    "addr:postcode":"8880",
    "addr:street":"Oudstrijderslaan",
    "iso:country":"BE",
    "sg:address":"Oudstrijderslaan 16",
    "sg:city":"Ledegem",
    "sg:orig_category":"Sportclubs Sportterreinen and installaties behalve sportcentra",
    "sg:phone":"+32 56 50 02 19",
    "sg:postcode":"8880",
    "sg:province":"West-Vlaanderen",
    "wof:name":"K. St.eloois-winkel Sport",
    "wof:placetype":"venue"
},
  "geometry": {"coordinates":[3.1841669083,50.8739395142],"type":"Point"}
}