{
  "type": "Feature",
  "properties": {
    "iso:country":"BE",
    "sg:address":"Jupiterlaan 57b2",
    "sg:city":"Vorst/forest",
    "sg:orig_category":"Woningbouw",
    "sg:phone":"+32 2 345 31 88",
    "sg:postcode":"1190",
    "sg:province":"Bruxelles-Capitale",
    "wof:name":"Viki",
    "wof:placetype":"venue"
},
  "geometry": {"coordinates":[4.3340959549,50.8167762756],"type":"Point"}
}