{
  "type": "Feature",
  "properties": {
    "addr:full":"Kerkstraat 65 Diest Vlaams-Brabant 3290",
    "addr:housenumber":"65",
    "addr:postcode":"3290",
    "addr:street":"Kerkstraat",
    "iso:country":"BE",
    "sg:address":"Kerkstraat 65",
    "sg:city":"Diest",
    "sg:orig_category":"Groententeelt",
    "sg:phone":"+32 13 31 35 23",
    "sg:postcode":"3290",
    "sg:province":"Vlaams-Brabant",
    "wof:name":"Fa. All-champ",
    "wof:placetype":"venue"
},
  "geometry": {"coordinates":[5.0821838379,51.0047187805],"type":"Point"}
}