{
  "type": "Feature",
  "properties": {
    "addr:full":"Waterloose Steenweg 236 Sint-gillis/saint-gilles Bruxelles-Capitale 1060",
    "addr:housenumber":"236",
    "addr:postcode":"1060",
    "addr:street":"Waterloose Steenweg",
    "iso:country":"BE",
    "sg:address":"Waterloose Steenweg 236",
    "sg:city":"Sint-gillis/saint-gilles",
    "sg:orig_category":"Juwelen and horloges",
    "sg:phone":"+32 2 538 47 27",
    "sg:postcode":"1060",
    "sg:province":"Bruxelles-Capitale",
    "wof:name":"Ren\u00c9 Corbeaux",
    "wof:placetype":"venue"
},
  "geometry": {"coordinates":[4.3464407921,50.8262290955],"type":"Point"}
}