{
  "type": "Feature",
  "properties": {
    "addr:full":"Onderwijsstraat 2 Halle Vlaams-Brabant 1500",
    "addr:housenumber":"2",
    "addr:postcode":"1500",
    "addr:street":"Onderwijsstraat",
    "iso:country":"BE",
    "sg:address":"Onderwijsstraat 2",
    "sg:city":"Halle",
    "sg:classifiers":[
        {
            "category":"Education",
            "subcategory":"School",
            "type":"Public Place"
        }
    ],
    "sg:phone":"+32 2 356 85 74",
    "sg:postcode":"1500",
    "sg:province":"Vlaams-Brabant",
    "sg:tags":[
        "secondary"
    ],
    "wof:name":"Meiboom (de)",
    "wof:placetype":"venue"
},
  "geometry": {"coordinates":[4.2368221283,50.7379226685],"type":"Point"}
}