{
  "type": "Feature",
  "properties": {
    "addr:full":"Chauss\u00e9e De Mons 158 Bruxelles (anderlecht) Bruxelles-Capitale 1070",
    "addr:housenumber":"158",
    "addr:postcode":"1070",
    "addr:street":"Chausse\u0301E De Mons",
    "iso:country":"BE",
    "sg:address":"Chauss\u00e9e De Mons 158",
    "sg:city":"Bruxelles (anderlecht)",
    "sg:classifiers":[
        {
            "category":"Bakery",
            "type":"Food & Drink"
        }
    ],
    "sg:phone":"+32 2 521 81 87",
    "sg:postcode":"1070",
    "sg:province":"Bruxelles-Capitale",
    "sg:tags":[
        "confectioner",
        "baker"
    ],
    "wof:name":"Hajaa",
    "wof:placetype":"venue"
},
  "geometry": {"coordinates":[4.3307681084,50.842048645],"type":"Point"}
}