{
  "type": "Feature",
  "properties": {
    "addr:full":"Rue Richard 11 Engis Li\u00e8ge 4480",
    "addr:housenumber":"11",
    "addr:postcode":"4480",
    "addr:street":"Rue Richard",
    "iso:country":"BE",
    "sg:address":"Rue Richard 11",
    "sg:city":"Engis",
    "sg:orig_category":"Assurances. Bureaux de poste",
    "sg:phone":"+32 4 275 11 00",
    "sg:postcode":"4480",
    "sg:province":"Li\u00e8ge",
    "wof:name":"La Poste",
    "wof:placetype":"venue"
},
  "geometry": {"coordinates":[5.4048480988,50.5820808411],"type":"Point"}
}