{
  "type": "Feature",
  "properties": {
    "addr:full":"Grensstraat 67 Keerbergen Vlaams-Brabant 3140",
    "addr:housenumber":"67",
    "addr:postcode":"3140",
    "addr:street":"Grensstraat",
    "iso:country":"BE",
    "sg:address":"Grensstraat 67",
    "sg:city":"Keerbergen",
    "sg:orig_category":"Groententeelt",
    "sg:phone":"+32 15 23 36 32",
    "sg:postcode":"3140",
    "sg:province":"Vlaams-Brabant",
    "wof:name":"Edmond De Weerdt",
    "wof:placetype":"venue"
},
  "geometry": {"coordinates":[4.6530861855,51.0196533203],"type":"Point"}
}