{
  "type": "Feature",
  "properties": {
    "iso:country":"BE",
    "sg:address":"Klein Overlaar 22",
    "sg:city":"Hoegaarden",
    "sg:classifiers":[
        {
            "category":"Food & Beverages",
            "subcategory":"Fruits & Vegetables",
            "type":"Retail Goods"
        }
    ],
    "sg:phone":"+32 16 76 67 45",
    "sg:postcode":"3320",
    "sg:province":"Vlaams-Brabant",
    "sg:tags":[
        "grain",
        "product",
        "dairy",
        "cereal",
        "related"
    ],
    "wof:name":"Supefra Nv",
    "wof:placetype":"venue"
},
  "geometry": {"coordinates":[4.8964071274,50.780128479],"type":"Point"}
}