{
  "type": "Feature",
  "properties": {
    "iso:country":"BE",
    "sg:address":"Mons. De Haernestraat 24",
    "sg:city":"Ieper",
    "sg:classifiers":[
        {
            "category":"Restaurant",
            "type":"Food & Drink"
        }
    ],
    "sg:phone":"+32 57 20 63 45",
    "sg:postcode":"8900",
    "sg:province":"West-Vlaanderen",
    "sg:tags":[
        "caf\u00e9s"
    ],
    "wof:name":"Taverne Happy Days",
    "wof:placetype":"venue"
},
  "geometry": {"coordinates":[2.8854050636,50.8483314514],"type":"Point"}
}