{
  "type": "Feature",
  "properties": {
    "iso:country":"BE",
    "sg:address":"Ter Lindenstraat 65",
    "sg:city":"Waregem",
    "sg:orig_category":"Goederenvervoer over de weg Verhuur bouwmachines",
    "sg:phone":"+32 56 71 70 38",
    "sg:postcode":"8792",
    "sg:province":"West-Vlaanderen",
    "wof:name":"Avet Transport",
    "wof:placetype":"venue"
},
  "geometry": {"coordinates":[3.3538620472,50.8920249939],"type":"Point"}
}