{
  "type": "Feature",
  "properties": {
    "addr:full":"Staatsbaan 239a Zulte Oost-Vlaanderen 9870",
    "addr:housenumber":"239a",
    "addr:postcode":"9870",
    "addr:street":"Staatsbaan",
    "iso:country":"BE",
    "sg:address":"Staatsbaan 239a",
    "sg:city":"Zulte",
    "sg:classifiers":[
        {
            "category":"Retail",
            "subcategory":"Auto Repair",
            "type":"Services"
        }
    ],
    "sg:phone":"+32 9 388 82 07",
    "sg:postcode":"9870",
    "sg:province":"Oost-Vlaanderen",
    "sg:tags":[
        "garage"
    ],
    "wof:name":"Leieauto's Bvba",
    "wof:placetype":"venue"
},
  "geometry": {"coordinates":[3.4384579659,50.9181442261],"type":"Point"}
}