{
  "type": "Feature",
  "properties": {
    "iso:country":"BE",
    "sg:address":"Toekomststraat 22",
    "sg:city":"Sint-truiden",
    "sg:classifiers":[
        {
            "category":"Government",
            "subcategory":"Office",
            "type":"Public Place"
        }
    ],
    "sg:phone":"+32 11 67 28 51",
    "sg:postcode":"3800",
    "sg:province":"Limburg",
    "sg:tags":[
        "environmental",
        "contro",
        "pollution"
    ],
    "wof:name":"Enviro Engineering Bvba",
    "wof:placetype":"venue"
},
  "geometry": {"coordinates":[5.1797032356,50.8178634644],"type":"Point"}
}