{
  "type": "Feature",
  "properties": {
    "iso:country":"BE",
    "sg:address":"Rue Robert Willame 163",
    "sg:city":"Chimay",
    "sg:orig_category":"Sportterreinen and installaties behalve sportcentra",
    "sg:phone":"+32 60 21 46 47",
    "sg:postcode":"6464",
    "sg:province":"Hainaut",
    "wof:name":"Man\u00c8ge Les Galopins",
    "wof:placetype":"venue"
},
  "geometry": {"coordinates":[4.3236589432,50.0240592957],"type":"Point"}
}