{
  "type": "Feature",
  "properties": {
    "addr:full":"Chauss\u00e9e De Mons 49 Ath Hainaut 7800",
    "addr:housenumber":"49",
    "addr:postcode":"7800",
    "addr:street":"Chausse\u0301E De Mons",
    "iso:country":"BE",
    "sg:address":"Chauss\u00e9e De Mons 49",
    "sg:city":"Ath",
    "sg:classifiers":[
        {
            "category":"Bars & Pubs",
            "type":"Food & Drink"
        }
    ],
    "sg:phone":"+32 68 28 40 91",
    "sg:postcode":"7800",
    "sg:province":"Hainaut",
    "wof:name":"Faubourg (le)",
    "wof:placetype":"venue"
},
  "geometry": {"coordinates":[3.7728960514,50.6253471375],"type":"Point"}
}