{
  "type": "Feature",
  "properties": {
    "addr:full":"Rue Puissant 72 Charleroi Hainaut 6040",
    "addr:housenumber":"72",
    "addr:postcode":"6040",
    "addr:street":"Rue Puissant;Hainaut",
    "iso:country":"BE",
    "sg:address":"Rue Puissant 72",
    "sg:city":"Charleroi",
    "sg:orig_category":"Enseignement maternel and primaire",
    "sg:phone":"+32 71 34 27 70",
    "sg:postcode":"6040",
    "sg:province":"Hainaut",
    "wof:name":"Ecole Fondamentale Libre",
    "wof:placetype":"venue"
},
  "geometry": {"coordinates":[4.4337358475,50.4384841919],"type":"Point"}
}