{
  "type": "Feature",
  "properties": {
    "addr:full":"Zandstraat 1 Heist-op-den-berg Antwerpen 2223",
    "addr:housenumber":"1",
    "addr:postcode":"2223",
    "addr:street":"Zandstraat",
    "iso:country":"BE",
    "sg:address":"Zandstraat 1",
    "sg:city":"Heist-op-den-berg",
    "sg:orig_category":"Huishoudapparaten, televisies and radio's Winkelinrichting and handelsuitrusting Gh",
    "sg:phone":"+32 15 23 39 23",
    "sg:postcode":"2223",
    "sg:province":"Antwerpen",
    "wof:name":"Willy Buelens",
    "wof:placetype":"venue"
},
  "geometry": {"coordinates":[4.710419178,51.0128059387],"type":"Point"}
}