{
  "type": "Feature",
  "properties": {
    "addr:full":"Denderoordstraat 45 Geraardsbergen (overboelare) Oost-Vlaanderen 9500",
    "addr:housenumber":"45",
    "addr:postcode":"9500",
    "addr:street":"Denderoordstraat",
    "iso:country":"BE",
    "sg:address":"Denderoordstraat 45",
    "sg:city":"Geraardsbergen (overboelare)",
    "sg:classifiers":[
        {
            "category":"Professional",
            "subcategory":"Engineering",
            "type":"Services"
        }
    ],
    "sg:phone":"+32 54 41 67 52",
    "sg:postcode":"9500",
    "sg:province":"Oost-Vlaanderen",
    "sg:tags":[
        "-"
    ],
    "wof:name":"Cabes Bvba",
    "wof:placetype":"venue"
},
  "geometry": {"coordinates":[3.8702309132,50.752658844],"type":"Point"}
}