{
  "type": "Feature",
  "properties": {
    "iso:country":"BE",
    "sg:address":"Waterloose Steenweg 690b44",
    "sg:city":"Ukkel/uccle",
    "sg:orig_category":"Textiel",
    "sg:phone":"+32 2 647 67 97",
    "sg:postcode":"1180",
    "sg:province":"Bruxelles-Capitale",
    "wof:name":"The Coat Inn",
    "wof:placetype":"venue"
},
  "geometry": {"coordinates":[4.3669700623,50.8161582947],"type":"Point"}
}