{
  "type": "Feature",
  "properties": {
    "iso:country":"BE",
    "sg:address":"Heirbaan 142",
    "sg:city":"Zwijndrecht",
    "sg:orig_category":"Pain, p\u00e2tisseries and confiseries",
    "sg:phone":"+32 3 252 72 08",
    "sg:postcode":"2070",
    "sg:province":"Antwerpen",
    "wof:name":"Van Herck Chris",
    "wof:placetype":"venue"
},
  "geometry": {"coordinates":[4.333106041,51.1994361877],"type":"Point"}
}