{
  "type": "Feature",
  "properties": {
    "addr:full":"Maesstraat 82 Elsene/ixelles Bruxelles-Capitale 1050",
    "addr:housenumber":"82",
    "addr:postcode":"1050",
    "addr:street":"Maesstraat",
    "iso:country":"BE",
    "sg:address":"Maesstraat 82",
    "sg:city":"Elsene/ixelles",
    "sg:orig_category":"Reclamebureaus",
    "sg:phone":"+32 2 648 55 82",
    "sg:postcode":"1050",
    "sg:province":"Bruxelles-Capitale",
    "wof:name":"Creative Bank",
    "wof:placetype":"venue"
},
  "geometry": {"coordinates":[4.3725690842,50.8309631348],"type":"Point"}
}