{
  "type": "Feature",
  "properties": {
    "addr:full":"Strijdersstraat 44 Edegem Antwerpen 2650",
    "addr:housenumber":"44",
    "addr:postcode":"2650",
    "addr:street":"Strijdersstraat",
    "iso:country":"BE",
    "sg:address":"Strijdersstraat 44",
    "sg:city":"Edegem",
    "sg:classifiers":[
        {
            "category":"Bars & Pubs",
            "type":"Food & Drink"
        }
    ],
    "sg:phone":"+32 3 458 10 72",
    "sg:postcode":"2650",
    "sg:province":"Antwerpen",
    "wof:name":"Pagadder",
    "wof:placetype":"venue"
},
  "geometry": {"coordinates":[4.4441728592,51.1575737],"type":"Point"}
}