{
  "type": "Feature",
  "properties": {
    "addr:full":"Rue Floribert 7 Chaudfontaine Li\u00e8ge 4050",
    "addr:housenumber":"7",
    "addr:postcode":"4050",
    "addr:street":"Rue Floribert",
    "iso:country":"BE",
    "sg:address":"Rue Floribert 7",
    "sg:city":"Chaudfontaine",
    "sg:orig_category":"Ordinateurs and \u00e9quipement informatique",
    "sg:phone":"+32 4 368 73 67",
    "sg:postcode":"4050",
    "sg:province":"Li\u00e8ge",
    "wof:name":"Ordicam",
    "wof:placetype":"venue"
},
  "geometry": {"coordinates":[5.6334319115,50.5822906494],"type":"Point"}
}