{
  "type": "Feature",
  "properties": {
    "addr:full":"Rue Valduc 352 Oudergem/auderghem Bruxelles-Capitale 1160",
    "addr:housenumber":"352",
    "addr:postcode":"1160",
    "addr:street":"Rue Valduc;/",
    "iso:country":"BE",
    "sg:address":"Rue Valduc 352",
    "sg:city":"Oudergem/auderghem",
    "sg:orig_category":"R\u00e9alisation de programmes and logiciels",
    "sg:phone":"+32 2 675 64 19",
    "sg:postcode":"1160",
    "sg:province":"Bruxelles-Capitale",
    "wof:name":"Mulog",
    "wof:placetype":"venue"
},
  "geometry": {"coordinates":[4.4101200104,50.8209609985],"type":"Point"}
}