{
  "type": "Feature",
  "properties": {
    "addr:full":"Veugelberg 25 Bekkevoort Vlaams-Brabant 3460",
    "addr:housenumber":"25",
    "addr:postcode":"3460",
    "addr:street":"Veugelberg",
    "iso:country":"BE",
    "sg:address":"Veugelberg 25",
    "sg:city":"Bekkevoort",
    "sg:orig_category":"Installation \u00e9lectrique r\u00e9sidentielle",
    "sg:phone":"+32 13 78 35 13",
    "sg:postcode":"3460",
    "sg:province":"Vlaams-Brabant",
    "wof:name":"E.a.d.b.",
    "wof:placetype":"venue"
},
  "geometry": {"coordinates":[4.9415121078,50.9605751038],"type":"Point"}
}