{
  "type": "Feature",
  "properties": {
    "iso:country":"BE",
    "sg:address":"Chemin De Papignies 3c",
    "sg:city":"Lessines",
    "sg:classifiers":[
        {
            "category":"Building & Trades",
            "subcategory":"Cleaning & Sanitation",
            "type":"Services"
        }
    ],
    "sg:phone":"+32 68 33 62 06",
    "sg:postcode":"7860",
    "sg:province":"Hainaut",
    "sg:tags":[
        "janitor"
    ],
    "wof:name":"Lessines Clean-transparence",
    "wof:placetype":"venue"
},
  "geometry": {"coordinates":[3.828166008,50.707157135],"type":"Point"}
}