{
  "type": "Feature",
  "properties": {
    "iso:country":"BE",
    "sg:address":"Rue Grande 43",
    "sg:city":"Saint-ghislain",
    "sg:orig_category":"Banken and kredietinstellingen",
    "sg:phone":"+32 65 78 58 64",
    "sg:postcode":"7330",
    "sg:province":"Hainaut",
    "wof:name":"Dexia",
    "wof:placetype":"venue"
},
  "geometry": {"coordinates":[3.820456028,50.4460144043],"type":"Point"}
}