{
  "type": "Feature",
  "properties": {
    "addr:full":"Hoofdstraat 54 Sankt Vith Li\u00e8ge 4780",
    "addr:housenumber":"54",
    "addr:postcode":"4780",
    "addr:street":"Hoofdstraat",
    "iso:country":"BE",
    "sg:address":"Hoofdstraat 54",
    "sg:city":"Sankt Vith",
    "sg:orig_category":"Activit\u00e9s d\u00b4action sociale sans h\u00e9bergement",
    "sg:phone":"+32 80 28 00 20",
    "sg:postcode":"4780",
    "sg:province":"Li\u00e8ge",
    "wof:name":"Infor Jeunes",
    "wof:placetype":"venue"
},
  "geometry": {"coordinates":[6.1256680489,50.2810821533],"type":"Point"}
}