{
  "type": "Feature",
  "properties": {
    "addr:full":"Place De La Station 5 Namur Namur 5000",
    "addr:housenumber":"5",
    "addr:postcode":"5000",
    "addr:street":"Place De La Station",
    "iso:country":"BE",
    "sg:address":"Place De La Station 5",
    "sg:city":"Namur",
    "sg:classifiers":[
        {
            "category":"Restaurant",
            "type":"Food & Drink"
        }
    ],
    "sg:phone":"+32 81 22 58 96",
    "sg:postcode":"5000",
    "sg:province":"Namur",
    "wof:name":"Lunch Garden",
    "wof:placetype":"venue"
},
  "geometry": {"coordinates":[4.8636450768,50.468208313],"type":"Point"}
}