{
  "type": "Feature",
  "properties": {
    "addr:full":"Avenue De La R\u00c9sistance 268 Soumagne Li\u00e8ge 4630",
    "addr:housenumber":"268",
    "addr:postcode":"4630",
    "addr:street":"Avenue De La Re\u0301Sistance",
    "iso:country":"BE",
    "sg:address":"Avenue De La R\u00c9sistance 268",
    "sg:city":"Soumagne",
    "sg:orig_category":"HERSTELLING ELEKTRISCHE HUISHOUDAPPARATEN Huishoudapparaten, televisies and radio's",
    "sg:phone":"+32 4 377 40 70",
    "sg:postcode":"4630",
    "sg:province":"Li\u00e8ge",
    "wof:name":"Audiac",
    "wof:placetype":"venue"
},
  "geometry": {"coordinates":[5.7358818054,50.6314811707],"type":"Point"}
}