{
  "type": "Feature",
  "properties": {
    "addr:full":"Rue De Maire 9bb Tournai Hainaut 7503",
    "addr:housenumber":"9bb",
    "addr:postcode":"7503",
    "addr:street":"Rue De Maire",
    "iso:country":"BE",
    "sg:address":"Rue De Maire 9bb",
    "sg:city":"Tournai",
    "sg:orig_category":"Herstellingen and onderhoud van auto's Voertuigen",
    "sg:phone":"+32 69 22 49 21",
    "sg:postcode":"7503",
    "sg:province":"Hainaut",
    "wof:name":"Carrosserie Lendasse",
    "wof:placetype":"venue"
},
  "geometry": {"coordinates":[3.3702540398,50.6244087219],"type":"Point"}
}