{
  "type": "Feature",
  "properties": {
    "addr:full":"Rue Edith Cavell 32 Bruxelles (uccle) Bruxelles-Capitale 1180",
    "addr:housenumber":"32",
    "addr:postcode":"1180",
    "addr:street":"Rue Edith Cavell",
    "iso:country":"BE",
    "sg:address":"Rue Edith Cavell 32",
    "sg:city":"Bruxelles (uccle)",
    "sg:classifiers":[
        {
            "category":"Health Services",
            "subcategory":"Hospital",
            "type":"Services"
        }
    ],
    "sg:postcode":"1180",
    "sg:province":"Bruxelles-Capitale",
    "wof:name":"Chirec",
    "wof:placetype":"venue"
},
  "geometry": {"coordinates":[4.3565921783,50.8137283325],"type":"Point"}
}