{
  "type": "Feature",
  "properties": {
    "iso:country":"BE",
    "sg:address":"Rue De L'ile 6",
    "sg:city":"Esneux",
    "sg:orig_category":"Tuinen",
    "sg:phone":"+32 4 380 04 02",
    "sg:postcode":"4130",
    "sg:province":"Li\u00e8ge",
    "wof:name":"Fish M\u00c9dical",
    "wof:placetype":"venue"
},
  "geometry": {"coordinates":[5.5633020401,50.5501060486],"type":"Point"}
}