{
  "type": "Feature",
  "properties": {
    "addr:full":"Avenue De L'atlantique 124 Sint-pieters-woluwe/woluwe-saint-pierre Bruxelles-Capitale 1150",
    "addr:housenumber":"124",
    "addr:postcode":"1150",
    "addr:street":"Avenue De L'Atlantique;/",
    "iso:country":"BE",
    "sg:address":"Avenue De L'atlantique 124",
    "sg:city":"Sint-pieters-woluwe/woluwe-saint-pierre",
    "sg:orig_category":"Eclairage et \u00e9quipements du foyer. Antiquit\u00e9s",
    "sg:phone":"+32 2 771 71 25",
    "sg:postcode":"1150",
    "sg:province":"Bruxelles-Capitale",
    "wof:name":"Chris'ann",
    "wof:placetype":"venue"
},
  "geometry": {"coordinates":[4.418653965,50.8280181885],"type":"Point"}
}