{
  "type": "Feature",
  "properties": {
    "addr:full":"Herderstr 4-6 Tielt West-Vlaanderen 8700",
    "addr:housenumber":"4-6",
    "addr:postcode":"8700",
    "addr:street":"Herderstr",
    "iso:country":"BE",
    "sg:address":"Herderstr 4-6",
    "sg:city":"Tielt",
    "sg:classifiers":[
        {
            "category":"Manufacturing",
            "subcategory":"Rubber & Plastics",
            "type":"Manufacturing & Wholesale Goods"
        }
    ],
    "sg:phone":"+32 51 40 38 06",
    "sg:postcode":"8700",
    "sg:province":"West-Vlaanderen",
    "wof:name":"Vulkoprin Nv",
    "wof:placetype":"venue"
},
  "geometry": {"coordinates":[3.3322899342,50.9813308716],"type":"Point"}
}