{
  "type": "Feature",
  "properties": {
    "addr:full":"Stationsstraat 12 Gistel West-Vlaanderen 8470",
    "addr:housenumber":"12",
    "addr:postcode":"8470",
    "addr:street":"Stationsstraat",
    "iso:country":"BE",
    "sg:address":"Stationsstraat 12",
    "sg:city":"Gistel",
    "sg:classifiers":[
        {
            "category":"Shopping",
            "subcategory":"Jewelry",
            "type":"Retail Goods"
        }
    ],
    "sg:phone":"+32 59 27 82 63",
    "sg:postcode":"8470",
    "sg:province":"West-Vlaanderen",
    "sg:tags":[
        "jeweller",
        "-"
    ],
    "wof:name":"Casselman K",
    "wof:placetype":"venue"
},
  "geometry": {"coordinates":[2.9662399292,51.1561012268],"type":"Point"}
}