{
  "type": "Feature",
  "properties": {
    "addr:full":"Trade Mart 312-313 Bruxelles Bruxelles-Capitale 1020",
    "addr:housenumber":"312-313",
    "addr:postcode":"1020",
    "iso:country":"BE",
    "sg:address":"Trade Mart 312-313",
    "sg:city":"Bruxelles",
    "sg:classifiers":[
        {
            "category":"Wholesale",
            "subcategory":"Furniture",
            "type":"Manufacturing & Wholesale Goods"
        }
    ],
    "sg:phone":"+32 2 479 43 22",
    "sg:postcode":"1020",
    "sg:province":"Bruxelles-Capitale",
    "sg:tags":[
        "-",
        "collectivities"
    ],
    "wof:name":"Mathy By Bols",
    "wof:placetype":"venue"
},
  "geometry": {"coordinates":[4.3462300301,50.8855514526],"type":"Point"}
}