{
  "type": "Feature",
  "properties": {
    "iso:country":"BE",
    "sg:address":"Place Sommeleville 32",
    "sg:city":"Verviers",
    "sg:classifiers":[
        {
            "category":"Building & Trades",
            "subcategory":"Pest Control",
            "type":"Services"
        }
    ],
    "sg:phone":"+32 87 35 28 70",
    "sg:postcode":"4800",
    "sg:province":"Li\u00e8ge",
    "sg:tags":[
        "machine",
        "vending"
    ],
    "wof:name":"B.c.w.",
    "wof:placetype":"venue"
},
  "geometry": {"coordinates":[5.8724150658,50.5946884155],"type":"Point"}
}