{
  "type": "Feature",
  "properties": {
    "iso:country":"BE",
    "sg:address":"Avenue Des Combattants 81",
    "sg:city":"Rixensart",
    "sg:orig_category":"Boekhouders",
    "sg:phone":"+32 2 653 48 94",
    "sg:postcode":"1332",
    "sg:province":"Brabant Wallon",
    "wof:name":"Koester-stevens G.",
    "wof:placetype":"venue"
},
  "geometry": {"coordinates":[4.5030241013,50.7190551758],"type":"Point"}
}