{
  "type": "Feature",
  "properties": {
    "addr:full":"Veldstraat 12 Wetteren Oost-Vlaanderen 9230",
    "addr:housenumber":"12",
    "addr:postcode":"9230",
    "addr:street":"Veldstraat",
    "iso:country":"BE",
    "sg:address":"Veldstraat 12",
    "sg:city":"Wetteren",
    "sg:classifiers":[
        {
            "category":"Professional",
            "subcategory":"Management & Consulting",
            "type":"Services"
        }
    ],
    "sg:phone":"+32 9 366 35 78",
    "sg:postcode":"9230",
    "sg:province":"Oost-Vlaanderen",
    "sg:tags":[
        "consultant"
    ],
    "wof:name":"M M Consult",
    "wof:placetype":"venue"
},
  "geometry": {"coordinates":[3.8762469292,51.0124816895],"type":"Point"}
}