{
  "type": "Feature",
  "properties": {
    "iso:country":"BE",
    "sg:address":"Klaverbladstraat 2bb",
    "sg:city":"Lummen",
    "sg:orig_category":"Metaalbehandeling and -bekleding",
    "sg:phone":"+32 13 53 17 77",
    "sg:postcode":"3560",
    "sg:province":"Limburg",
    "wof:name":"L & D-jet-techniek",
    "wof:placetype":"venue"
},
  "geometry": {"coordinates":[5.2286858559,50.9948654175],"type":"Point"}
}