{
  "type": "Feature",
  "properties": {
    "addr:full":"Rue Des P\u00e2turages 2 Tournai Hainaut 7500",
    "addr:housenumber":"2",
    "addr:postcode":"7500",
    "addr:street":"Rue Des Pa\u0302Turages",
    "iso:country":"BE",
    "sg:address":"Rue Des P\u00e2turages 2",
    "sg:city":"Tournai",
    "sg:classifiers":[
        {
            "category":"Personal",
            "subcategory":"Beauty Salon",
            "type":"Services"
        }
    ],
    "sg:phone":"+32 69 22 28 23",
    "sg:postcode":"7500",
    "sg:province":"Hainaut",
    "sg:tags":[
        "lady",
        "-",
        "hairdressing"
    ],
    "wof:name":"Jacqueline (coiffure)",
    "wof:placetype":"venue"
},
  "geometry": {"coordinates":[3.4095189571,50.6141319275],"type":"Point"}
}