{
  "type": "Feature",
  "properties": {
    "addr:full":"Avenue Blonden 26 Li\u00c8ge Li\u00e8ge 4000",
    "addr:housenumber":"26",
    "addr:postcode":"4000",
    "addr:street":"Avenue Blonden",
    "iso:country":"BE",
    "sg:address":"Avenue Blonden 26",
    "sg:city":"Li\u00c8ge",
    "sg:orig_category":"Hypermarkten",
    "sg:phone":"+32 4 254 56 11",
    "sg:postcode":"4000",
    "sg:province":"Li\u00e8ge",
    "wof:name":"Super G.b.",
    "wof:placetype":"venue"
},
  "geometry": {"coordinates":[5.5699501038,50.6289787292],"type":"Point"}
}