{
  "type": "Feature",
  "properties": {
    "iso:country":"BE",
    "sg:address":"Maria Van Bourgondi\u00eblaan 36",
    "sg:city":"Torhout",
    "sg:classifiers":[
        {
            "category":"Professional",
            "subcategory":"Lawyer & Legal Services",
            "type":"Services"
        }
    ],
    "sg:phone":"+32 50 21 27 59",
    "sg:postcode":"8820",
    "sg:province":"West-Vlaanderen",
    "wof:name":"Legein K",
    "wof:placetype":"venue"
},
  "geometry": {"coordinates":[3.0976428986,51.068447113],"type":"Point"}
}