{
  "type": "Feature",
  "properties": {
    "addr:full":"Lepelstraat 77a Brakel (michelbeke) Oost-Vlaanderen 9660",
    "addr:housenumber":"77a",
    "addr:postcode":"9660",
    "addr:street":"Lepelstraat",
    "iso:country":"BE",
    "sg:address":"Lepelstraat 77a",
    "sg:city":"Brakel (michelbeke)",
    "sg:classifiers":[
        {
            "category":"Banks & Credit Unions",
            "subcategory":"Bank",
            "type":"Services"
        }
    ],
    "sg:phone":"+32 55 42 39 40",
    "sg:postcode":"9660",
    "sg:province":"Oost-Vlaanderen",
    "wof:name":"Argenta",
    "wof:placetype":"venue"
},
  "geometry": {"coordinates":[3.7642250061,50.8031082153],"type":"Point"}
}