{
  "type": "Feature",
  "properties": {
    "addr:full":"Rue Des Tisserands 40 Braine-l'alleud Brabant Wallon 1420",
    "addr:housenumber":"40",
    "addr:postcode":"1420",
    "addr:street":"Rue Des Tisserands",
    "iso:country":"BE",
    "sg:address":"Rue Des Tisserands 40",
    "sg:city":"Braine-l'alleud",
    "sg:classifiers":[
        {
            "category":"Personal",
            "subcategory":"Beauty Salon",
            "type":"Services"
        }
    ],
    "sg:phone":"+32 2 387 24 05",
    "sg:postcode":"1420",
    "sg:province":"Brabant Wallon",
    "sg:tags":[
        "de",
        "coiffure"
    ],
    "wof:name":"Atmosp'hair",
    "wof:placetype":"venue"
},
  "geometry": {"coordinates":[-75.60595703120001,37.7877616882],"type":"Point"}
}