{
  "type": "Feature",
  "properties": {
    "iso:country":"BE",
    "sg:address":"Verkensstraat 29a",
    "sg:city":"Heist-op-den-berg (hallaar)",
    "sg:classifiers":[
        {
            "category":"Shopping",
            "subcategory":"Florist",
            "type":"Retail Goods"
        }
    ],
    "sg:phone":"+32 15 22 68 96",
    "sg:postcode":"2220",
    "sg:province":"Antwerpen",
    "wof:name":"Van Eccelpoel Bvba",
    "wof:placetype":"venue"
},
  "geometry": {"coordinates":[4.7254419327,51.0897293091],"type":"Point"}
}