{
  "type": "Feature",
  "properties": {
    "addr:full":"Grand'rue 46 Peruwelz Hainaut 7608",
    "addr:housenumber":"46",
    "addr:postcode":"7608",
    "addr:street":"Grand'Rue;Hainaut",
    "iso:country":"BE",
    "sg:address":"Grand'rue 46",
    "sg:city":"Peruwelz",
    "sg:orig_category":"Eleveurs de bovins",
    "sg:phone":"+32 69 77 25 25",
    "sg:postcode":"7608",
    "sg:province":"Hainaut",
    "wof:name":"Yves Vandenberghe",
    "wof:placetype":"venue"
},
  "geometry": {"coordinates":[3.5258259773,50.525680542],"type":"Point"}
}