{
  "type": "Feature",
  "properties": {
    "addr:full":"Sint-katelijnestraat 42 Brussel/bruxelles Bruxelles-Capitale 1000",
    "addr:housenumber":"42",
    "addr:postcode":"1000",
    "addr:street":"Sint-Katelijnestraat;/",
    "iso:country":"BE",
    "sg:address":"Sint-katelijnestraat 42",
    "sg:city":"Brussel/bruxelles",
    "sg:classifiers":[
        {
            "category":"Cafe",
            "type":"Food & Drink"
        }
    ],
    "sg:phone":"+32 2 513 42 49",
    "sg:postcode":"1000",
    "sg:province":"Bruxelles-Capitale",
    "sg:tags":[
        "caf\u00e9s"
    ],
    "wof:name":"Caf\u00c9 Zinneke",
    "wof:placetype":"venue"
},
  "geometry": {"coordinates":[4.3481869698,50.8504867554],"type":"Point"}
}