{
  "type": "Feature",
  "properties": {
    "addr:full":"Kreupelstraat 6 Zwevegem West-Vlaanderen 8550",
    "addr:housenumber":"6",
    "addr:postcode":"8550",
    "addr:street":"Kreupelstraat",
    "iso:country":"BE",
    "sg:address":"Kreupelstraat 6",
    "sg:city":"Zwevegem",
    "sg:classifiers":[
        {
            "category":"Insurance",
            "subcategory":"Life Insurance",
            "type":"Services"
        }
    ],
    "sg:phone":"+32 56 75 60 30",
    "sg:postcode":"8550",
    "sg:province":"West-Vlaanderen",
    "sg:tags":[
        "assurance"
    ],
    "wof:name":"Verzekeringen Remmerie",
    "wof:placetype":"venue"
},
  "geometry": {"coordinates":[3.3289411068,50.7936592102],"type":"Point"}
}