{
  "type": "Feature",
  "properties": {
    "addr:full":"Rue De La Limite 12/14 Liege Li\u00e8ge 4020",
    "addr:housenumber":"12 / 14",
    "addr:postcode":"4020",
    "addr:street":"Rue De La Limite",
    "iso:country":"BE",
    "sg:address":"Rue De La Limite 12/14",
    "sg:city":"Liege",
    "sg:orig_category":"Mat\u00e9riaux de construction Gr",
    "sg:phone":"+32 4 343 17 23",
    "sg:postcode":"4020",
    "sg:province":"Li\u00e8ge",
    "wof:name":"Eymael F.",
    "wof:placetype":"venue"
},
  "geometry": {"coordinates":[5.5873098373,50.630241394],"type":"Point"}
}