{
  "type": "Feature",
  "properties": {
    "iso:country":"BE",
    "sg:address":"Rue De Hachy 22",
    "sg:city":"Arlon",
    "sg:orig_category":"Electrom\u00e9nager, t\u00e9l\u00e9visions and radios",
    "sg:phone":"+32 63 22 49 14",
    "sg:postcode":"6700",
    "sg:province":"Luxembourg",
    "wof:name":"Ets. Theis Fils",
    "wof:placetype":"venue"
},
  "geometry": {"coordinates":[5.6952409744,49.6929931641],"type":"Point"}
}