{
  "type": "Feature",
  "properties": {
    "iso:country":"BE",
    "sg:address":"Rue Du Gazom\u00e8tre 32",
    "sg:city":"Pont-\u00e0-celles",
    "sg:classifiers":[
        {
            "category":"Home & Garden",
            "subcategory":"Carpets & Floor Coverings",
            "type":"Retail Goods"
        }
    ],
    "sg:phone":"+32 71 84 65 28",
    "sg:postcode":"6230",
    "sg:province":"Hainaut",
    "sg:tags":[
        "layer",
        "mosaicists"
    ],
    "wof:name":"Slot D",
    "wof:placetype":"venue"
},
  "geometry": {"coordinates":[4.372179985,50.507900238],"type":"Point"}
}