{
  "type": "Feature",
  "properties": {
    "iso:country":"BE",
    "sg:address":"Gaaipersstraat 1",
    "sg:city":"Roeselare",
    "sg:orig_category":"Kapsalons Schoonheidssalons",
    "sg:phone":"+32 51 20 86 51",
    "sg:postcode":"8800",
    "sg:province":"West-Vlaanderen",
    "wof:name":"Coiffure Charme",
    "wof:placetype":"venue"
},
  "geometry": {"coordinates":[3.1199100018,50.9504623413],"type":"Point"}
}