{
  "type": "Feature",
  "properties": {
    "iso:country":"BE",
    "sg:address":"Avenue Des Casernes 26",
    "sg:city":"Bruxelles (etterbeek)",
    "sg:classifiers":[
        {
            "category":"Shopping",
            "subcategory":"Optician",
            "type":"Retail Goods"
        }
    ],
    "sg:phone":"+32 2 647 82 95",
    "sg:postcode":"1040",
    "sg:province":"Bruxelles-Capitale",
    "sg:tags":[
        "-"
    ],
    "wof:name":"Michel Optique",
    "wof:placetype":"venue"
},
  "geometry": {"coordinates":[4.3906240463,50.8292694092],"type":"Point"}
}