{
  "type": "Feature",
  "properties": {
    "addr:full":"Sint-niklaasstraat 44 Gent Oost-Vlaanderen 9000",
    "addr:housenumber":"44",
    "addr:postcode":"9000",
    "addr:street":"Sint-Niklaasstraat;Oost-Vlaanderen",
    "iso:country":"BE",
    "sg:address":"Sint-niklaasstraat 44",
    "sg:city":"Gent",
    "sg:classifiers":[
        {
            "category":"Shopping",
            "subcategory":"Antiques",
            "type":"Retail Goods"
        }
    ],
    "sg:phone":"+32 9 223 37 89",
    "sg:postcode":"9000",
    "sg:province":"Oost-Vlaanderen",
    "wof:name":"Art & Antiques Steinfeld",
    "wof:placetype":"venue"
},
  "geometry": {"coordinates":[3.7228229046,51.0528182983],"type":"Point"}
}