{
  "type": "Feature",
  "properties": {
    "addr:full":"Rue De Herve 479 Li\u00e8ge 1 (grivegn\u00e9e) Li\u00e8ge 4030",
    "addr:housenumber":"479;1",
    "addr:postcode":"4030",
    "addr:street":"Rue De Herve",
    "iso:country":"BE",
    "sg:address":"Rue De Herve 479",
    "sg:city":"Li\u00e8ge 1 (grivegn\u00e9e)",
    "sg:classifiers":[
        {
            "category":"Health Services",
            "subcategory":"Doctor",
            "type":"Services"
        }
    ],
    "sg:phone":"+32 4 367 78 28",
    "sg:postcode":"4030",
    "sg:province":"Li\u00e8ge",
    "sg:tags":[
        "medicinephysicians",
        "surgeon"
    ],
    "wof:name":"Kreusch Bernard",
    "wof:placetype":"venue"
},
  "geometry": {"coordinates":[5.6213440895,50.6287841797],"type":"Point"}
}