{
  "type": "Feature",
  "properties": {
    "iso:country":"BE",
    "sg:address":"Rue Du Moulin 17a",
    "sg:city":"Hannut",
    "sg:classifiers":[
        {
            "category":"Retail",
            "subcategory":"Auto Repair",
            "type":"Services"
        }
    ],
    "sg:phone":"+32 19 51 08 39",
    "sg:postcode":"4280",
    "sg:province":"Li\u00e8ge",
    "sg:tags":[
        "garage"
    ],
    "wof:name":"Polleunus M",
    "wof:placetype":"venue"
},
  "geometry": {"coordinates":[5.0673069954,50.6768455505],"type":"Point"}
}