{
  "type": "Feature",
  "properties": {
    "iso:country":"BE",
    "sg:address":"Lange Nieuwstraat 29b6",
    "sg:city":"Antwerpen",
    "sg:orig_category":"Antiek",
    "sg:phone":"+32 3 231 88 50",
    "sg:postcode":"2000",
    "sg:province":"Antwerpen",
    "wof:name":"Stradanus",
    "wof:placetype":"venue"
},
  "geometry": {"coordinates":[4.4076700211,51.2199516296],"type":"Point"}
}