{
  "type": "Feature",
  "properties": {
    "addr:full":"Geldenaaksebaan 71 Leuven (heverlee) Vlaams-Brabant 3001",
    "addr:housenumber":"71",
    "addr:postcode":"3001",
    "addr:street":"Geldenaaksebaan",
    "iso:country":"BE",
    "sg:address":"Geldenaaksebaan 71",
    "sg:city":"Leuven (heverlee)",
    "sg:classifiers":[
        {
            "category":"Real Estate",
            "subcategory":"Architect",
            "type":"Services"
        }
    ],
    "sg:phone":"+32 16 40 37 35",
    "sg:postcode":"3001",
    "sg:province":"Vlaams-Brabant",
    "wof:name":"Dens C",
    "wof:placetype":"venue"
},
  "geometry": {"coordinates":[4.7114930153,50.864276886],"type":"Point"}
}