{
  "type": "Feature",
  "properties": {
    "addr:full":"Ottergemsesteenweg 13 Gent Oost-Vlaanderen 9000",
    "addr:housenumber":"13",
    "addr:postcode":"9000",
    "addr:street":"Ottergemsesteenweg;Oost-Vlaanderen",
    "iso:country":"BE",
    "sg:address":"Ottergemsesteenweg 13",
    "sg:city":"Gent",
    "sg:classifiers":[
        {
            "category":"Cafe",
            "type":"Food & Drink"
        }
    ],
    "sg:phone":"+32 9 242 00 71",
    "sg:postcode":"9000",
    "sg:province":"Oost-Vlaanderen",
    "sg:tags":[
        "caf\u00e9s"
    ],
    "wof:name":"Caf\u00c9 Pepsi Pool",
    "wof:placetype":"venue"
},
  "geometry": {"coordinates":[3.7272069454,51.0372123718],"type":"Point"}
}