{
  "type": "Feature",
  "properties": {
    "iso:country":"BE",
    "sg:address":"Rue Lieutenant Freddy Wampach 1",
    "sg:city":"Bruxelles (woluwe-saint-lambert)",
    "sg:orig_category":"Mayonnaise - Mfg.& Whol",
    "sg:phone":"+32 2 771 81 92",
    "sg:postcode":"1200",
    "sg:province":"Bruxelles-Capitale",
    "wof:name":"Copa",
    "wof:placetype":"venue"
},
  "geometry": {"coordinates":[4.4172468185,50.8439102173],"type":"Point"}
}