{
  "type": "Feature",
  "properties": {
    "addr:full":"Wielsbekestraat 21 Oostrozebeke West-Vlaanderen 8780",
    "addr:housenumber":"21",
    "addr:postcode":"8780",
    "addr:street":"Wielsbekestraat",
    "iso:country":"BE",
    "sg:address":"Wielsbekestraat 21",
    "sg:city":"Oostrozebeke",
    "sg:orig_category":"Enseignement maternel and primaire",
    "sg:phone":"+32 56 66 80 60",
    "sg:postcode":"8780",
    "sg:province":"West-Vlaanderen",
    "wof:name":"Vrije Basisschool",
    "wof:placetype":"venue"
},
  "geometry": {"coordinates":[3.3383231163,50.9210090637],"type":"Point"}
}