{
  "type": "Feature",
  "properties": {
    "addr:full":"Route De La Baraque Michel 39 Malmedy Li\u00e8ge 4960",
    "addr:housenumber":"39",
    "addr:postcode":"4960",
    "addr:street":"Route De La Baraque Michel",
    "iso:country":"BE",
    "sg:address":"Route De La Baraque Michel 39",
    "sg:city":"Malmedy",
    "sg:orig_category":"Maisons de vacances",
    "sg:phone":"+32 80 33 05 00",
    "sg:postcode":"4960",
    "sg:province":"Li\u00e8ge",
    "wof:name":"J.quetsch",
    "wof:placetype":"venue"
},
  "geometry": {"coordinates":[6.0561552048,50.4617729187],"type":"Point"}
}