{
  "type": "Feature",
  "properties": {
    "addr:full":"Rue Irma Fi\u00e9vez 122 Mons (havr\u00e9) Hainaut 7021",
    "addr:housenumber":"122",
    "addr:postcode":"7021",
    "addr:street":"Rue Irma Fie\u0301Vez",
    "iso:country":"BE",
    "sg:address":"Rue Irma Fi\u00e9vez 122",
    "sg:city":"Mons (havr\u00e9)",
    "sg:classifiers":[
        {
            "category":"Health Services",
            "subcategory":"Doctor",
            "type":"Services"
        }
    ],
    "sg:phone":"+32 65 87 33 91",
    "sg:postcode":"7021",
    "sg:province":"Hainaut",
    "sg:tags":[
        "medicinephysicians",
        "surgeon"
    ],
    "wof:name":"Glineur F",
    "wof:placetype":"venue"
},
  "geometry": {"coordinates":[4.0456829071,50.4640655518],"type":"Point"}
}