{
  "type": "Feature",
  "properties": {
    "iso:country":"BE",
    "sg:address":"Rue Mauvinage 81",
    "sg:city":"Silly",
    "sg:classifiers":[
        {
            "category":"Professional",
            "subcategory":"Management & Consulting",
            "type":"Services"
        }
    ],
    "sg:phone":"+32 68 56 85 22",
    "sg:postcode":"7830",
    "sg:province":"Hainaut",
    "sg:tags":[
        "-",
        "processing",
        "data",
        "consultant"
    ],
    "wof:name":"Hanart",
    "wof:placetype":"venue"
},
  "geometry": {"coordinates":[3.9339520931,50.6344413757],"type":"Point"}
}