{
  "type": "Feature",
  "properties": {
    "addr:full":"Rue Du Moulin 55bb Gembloux Namur 5030",
    "addr:housenumber":"55bb",
    "addr:postcode":"5030",
    "addr:street":"Rue Du Moulin;Namur",
    "iso:country":"BE",
    "sg:address":"Rue Du Moulin 55bb",
    "sg:city":"Gembloux",
    "sg:orig_category":"Zalen voor culturele evenementen",
    "sg:phone":"+32 81 61 38 38",
    "sg:postcode":"5030",
    "sg:province":"Namur",
    "wof:name":"Foyer Culturel",
    "wof:placetype":"venue"
},
  "geometry": {"coordinates":[4.6932969093,50.5632209778],"type":"Point"}
}