{
  "type": "Feature",
  "properties": {
    "iso:country":"BE",
    "sg:address":"Kloosterstraat 47",
    "sg:city":"Gierle",
    "sg:orig_category":"Pain, p\u00e2tisseries and confiseries",
    "sg:phone":"+32 14 55 75 75",
    "sg:postcode":"2275",
    "sg:province":"Antwerpen",
    "wof:name":"Bakkerij Piedfort-vervoort",
    "wof:placetype":"venue"
},
  "geometry": {"coordinates":[4.8645701408,51.2649307251],"type":"Point"}
}