{
  "type": "Feature",
  "properties": {
    "addr:full":"Auguste Reyerslaan 15b9 Schaarbeek/schaerbeek Bruxelles-Capitale 1030",
    "addr:housenumber":"15b9",
    "addr:postcode":"1030",
    "addr:street":"Auguste Reyerslaan",
    "iso:country":"BE",
    "sg:address":"Auguste Reyerslaan 15b9",
    "sg:city":"Schaarbeek/schaerbeek",
    "sg:orig_category":"Krantenuitgeverijen Tijdschriftenuitgeverijen",
    "sg:phone":"+32 2 735 95 05",
    "sg:postcode":"1030",
    "sg:province":"Bruxelles-Capitale",
    "wof:name":"Sebastien Delmee",
    "wof:placetype":"venue"
},
  "geometry": {"coordinates":[4.3990879059,50.8538093567],"type":"Point"}
}