{
  "type": "Feature",
  "properties": {
    "addr:full":"Rozendreef 5 Kalmthout Antwerpen 2920",
    "addr:housenumber":"5",
    "addr:postcode":"2920",
    "addr:street":"Rozendreef",
    "iso:country":"BE",
    "sg:address":"Rozendreef 5",
    "sg:city":"Kalmthout",
    "sg:orig_category":"Diverse bedrijfsbeheeradviesbureaus",
    "sg:phone":"+32 3 666 20 71",
    "sg:postcode":"2920",
    "sg:province":"Antwerpen",
    "wof:name":"Finaudit",
    "wof:placetype":"venue"
},
  "geometry": {"coordinates":[4.4575071335,51.3779792786],"type":"Point"}
}