{
  "type": "Feature",
  "properties": {
    "iso:country":"BE",
    "sg:address":"Liersesteenweg 374",
    "sg:city":"Mechelen",
    "sg:classifiers":[
        {
            "category":"Autos & Motor Vehicles",
            "subcategory":"Automobile Sales",
            "type":"Retail Goods"
        }
    ],
    "sg:phone":"+32 15 20 13 65",
    "sg:postcode":"2800",
    "sg:province":"Antwerpen",
    "sg:tags":[
        "car",
        "used",
        "-"
    ],
    "wof:name":"De Ven",
    "wof:placetype":"venue"
},
  "geometry": {"coordinates":[4.4786391258,51.0461006165],"type":"Point"}
}