{
  "type": "Feature",
  "properties": {
    "iso:country":"BE",
    "sg:address":"Heerle 62",
    "sg:city":"Hoogstraten (meerle)",
    "sg:classifiers":[
        {
            "category":"Home & Garden",
            "subcategory":"Kitchen Supply",
            "type":"Retail Goods"
        }
    ],
    "sg:phone":"+32 3 315 05 91",
    "sg:postcode":"2328",
    "sg:province":"Antwerpen",
    "sg:tags":[
        "range"
    ],
    "wof:name":"Nobel Fornuizen",
    "wof:placetype":"venue"
},
  "geometry": {"coordinates":[4.8041949272,51.4741134644],"type":"Point"}
}