{
  "type": "Feature",
  "properties": {
    "iso:country":"BE",
    "sg:address":"Rue De Grande Bretagne 3",
    "sg:city":"Frameries",
    "sg:classifiers":[
        {
            "category":"Health Services",
            "subcategory":"Health Practitioner",
            "type":"Services"
        }
    ],
    "sg:phone":"+32 65 66 11 31",
    "sg:postcode":"7080",
    "sg:province":"Hainaut",
    "sg:tags":[
        "therapist",
        "speech"
    ],
    "wof:name":"Dernoncourt Marie-ange",
    "wof:placetype":"venue"
},
  "geometry": {"coordinates":[3.8963279724,50.4114532471],"type":"Point"}
}