{
  "type": "Feature",
  "properties": {
    "addr:full":"Kanaalkaai 3520 Bree Limburg 3960",
    "addr:postcode":"3520;3960",
    "addr:street":"Kanaalkaai",
    "iso:country":"BE",
    "sg:address":"Kanaalkaai 3520",
    "sg:city":"Bree",
    "sg:classifiers":[
        {
            "category":"Animal Shelter",
            "type":"Public Place"
        }
    ],
    "sg:phone":"+32 89 46 72 35",
    "sg:postcode":"3960",
    "sg:province":"Limburg",
    "sg:tags":[
        "construction",
        "installation",
        "stable"
    ],
    "wof:name":"Luke Bvba",
    "wof:placetype":"venue"
},
  "geometry": {"coordinates":[5.6193089485,51.1415977478],"type":"Point"}
}