{
  "type": "Feature",
  "properties": {
    "addr:full":"Kerkstraat 43 Hamme Oost-Vlaanderen 9220",
    "addr:housenumber":"43",
    "addr:postcode":"9220",
    "addr:street":"Kerkstraat",
    "iso:country":"BE",
    "sg:address":"Kerkstraat 43",
    "sg:city":"Hamme",
    "sg:classifiers":[
        {
            "category":"Banks & Credit Unions",
            "subcategory":"Investment Brokerage",
            "type":"Services"
        }
    ],
    "sg:phone":"+32 52 47 31 73",
    "sg:postcode":"9220",
    "sg:province":"Oost-Vlaanderen",
    "sg:tags":[
        "printing",
        "-"
    ],
    "wof:name":"Vermeire-boel Bvba",
    "wof:placetype":"venue"
},
  "geometry": {"coordinates":[4.1346120834,51.0983123779],"type":"Point"}
}