{
  "type": "Feature",
  "properties": {
    "addr:full":"Appelstraat 6a Tielt (aarsele) West-Vlaanderen 8700",
    "addr:housenumber":"6a",
    "addr:postcode":"8700",
    "addr:street":"Appelstraat",
    "iso:country":"BE",
    "sg:address":"Appelstraat 6a",
    "sg:city":"Tielt (aarsele)",
    "sg:classifiers":[
        {
            "category":"Professional",
            "subcategory":"Management & Consulting",
            "type":"Services"
        }
    ],
    "sg:phone":"+32 51 63 47 56",
    "sg:postcode":"8700",
    "sg:province":"West-Vlaanderen",
    "sg:tags":[
        "tax-consultants"
    ],
    "wof:name":"Peck D",
    "wof:placetype":"venue"
},
  "geometry": {"coordinates":[3.4129340649,50.9840736389],"type":"Point"}
}