{
  "type": "Feature",
  "properties": {
    "iso:country":"BE",
    "sg:address":"Chauss\u00c9e De Charleroi 13",
    "sg:city":"Lasne",
    "sg:orig_category":"Producteurs de l\u00e9gumes",
    "sg:phone":"+32 2 384 33 54",
    "sg:postcode":"1380",
    "sg:province":"Brabant Wallon",
    "wof:name":"Philippe Dewulf",
    "wof:placetype":"venue"
},
  "geometry": {"coordinates":[4.4136500359,50.6623802185],"type":"Point"}
}