{
  "type": "Feature",
  "properties": {
    "addr:full":"Schoolstraat 55 Ravels Antwerpen 2381",
    "addr:housenumber":"55",
    "addr:postcode":"2381",
    "addr:street":"Schoolstraat",
    "iso:country":"BE",
    "sg:address":"Schoolstraat 55",
    "sg:city":"Ravels",
    "sg:classifiers":[
        {
            "category":"Arena",
            "subcategory":"Sports Club",
            "type":"Entertainment"
        }
    ],
    "sg:phone":"+32 14 65 97 93",
    "sg:postcode":"2381",
    "sg:province":"Antwerpen",
    "sg:tags":[
        "de"
    ],
    "wof:name":"Volleybalclub Power-ravels",
    "wof:placetype":"venue"
},
  "geometry": {"coordinates":[5.006374836,51.4099845886],"type":"Point"}
}