{
  "type": "Feature",
  "properties": {
    "addr:full":"Kalmthoutsesteenweg 380 Kalmthout Antwerpen 2920",
    "addr:housenumber":"380",
    "addr:postcode":"2920",
    "addr:street":"Kalmthoutsesteenweg",
    "iso:country":"BE",
    "sg:address":"Kalmthoutsesteenweg 380",
    "sg:city":"Kalmthout",
    "sg:orig_category":"M\u00e9decins and sp\u00e9cialistes",
    "sg:phone":"+32 3 666 76 12",
    "sg:postcode":"2920",
    "sg:province":"Antwerpen",
    "wof:name":"J. Raskin",
    "wof:placetype":"venue"
},
  "geometry": {"coordinates":[4.5042061806,51.3971557617],"type":"Point"}
}