{
  "type": "Feature",
  "properties": {
    "iso:country":"BE",
    "sg:address":"Maurits Noestraat 65",
    "sg:city":"Oud-heverlee",
    "sg:orig_category":"Elektrische installaties voor woningen Huishoudapparaten, televisies and radio's Industri\u00eble elektri",
    "sg:phone":"+32 16 40 21 99",
    "sg:postcode":"3054",
    "sg:province":"Vlaams-Brabant",
    "wof:name":"Vanopdenbosch",
    "wof:placetype":"venue"
},
  "geometry": {"coordinates":[4.6755261421,50.8242492676],"type":"Point"}
}