{
  "type": "Feature",
  "properties": {
    "addr:full":"Oostendesteenweg 262 Ichtegem (eernegem) West-Vlaanderen 8480",
    "addr:housenumber":"262",
    "addr:postcode":"8480",
    "addr:street":"Oostendesteenweg",
    "iso:country":"BE",
    "sg:address":"Oostendesteenweg 262",
    "sg:city":"Ichtegem (eernegem)",
    "sg:classifiers":[
        {
            "category":"Shopping",
            "subcategory":"Clothing, Apparel, & Fashions",
            "type":"Retail Goods"
        }
    ],
    "sg:phone":"+32 59 25 12 55",
    "sg:postcode":"8480",
    "sg:province":"West-Vlaanderen",
    "sg:tags":[
        "underwear",
        "lingerie",
        "-"
    ],
    "wof:name":"Female Touch - Eroboetiek",
    "wof:placetype":"venue"
},
  "geometry": {"coordinates":[3.0132501125,51.1129493713],"type":"Point"}
}