{
  "type": "Feature",
  "properties": {
    "addr:full":"Lambertusstraat 18 Borgloon Limburg 3840",
    "addr:housenumber":"18",
    "addr:postcode":"3840",
    "addr:street":"Lambertusstraat",
    "iso:country":"BE",
    "sg:address":"Lambertusstraat 18",
    "sg:city":"Borgloon",
    "sg:orig_category":"Herstellingen and onderhoud van auto's",
    "sg:phone":"+32 12 74 40 44",
    "sg:postcode":"3840",
    "sg:province":"Limburg",
    "wof:name":"Benedictus Putzeys",
    "wof:placetype":"venue"
},
  "geometry": {"coordinates":[5.332174778,50.8020362854],"type":"Point"}
}