{
  "type": "Feature",
  "properties": {
    "iso:country":"BE",
    "sg:address":"Krokuslaan 36",
    "sg:city":"Kasterlee (lichtaart)",
    "sg:classifiers":[
        {
            "category":"Health Services",
            "subcategory":"Health Practitioner",
            "type":"Services"
        }
    ],
    "sg:phone":"+32 14 55 35 72",
    "sg:postcode":"2460",
    "sg:province":"Antwerpen",
    "sg:tags":[
        "physiotherapist"
    ],
    "wof:name":"Van Doninck Mieke",
    "wof:placetype":"venue"
},
  "geometry": {"coordinates":[4.9671049118,51.2406616211],"type":"Point"}
}