{
  "type": "Feature",
  "properties": {
    "addr:full":"Groenestraat 52 Alveringem West-Vlaanderen 8691",
    "addr:housenumber":"52",
    "addr:postcode":"8691",
    "addr:street":"Groenestraat",
    "iso:country":"BE",
    "sg:address":"Groenestraat 52",
    "sg:city":"Alveringem",
    "sg:orig_category":"Kapsalons",
    "sg:phone":"+32 58 29 96 88",
    "sg:postcode":"8691",
    "sg:province":"West-Vlaanderen",
    "wof:name":"Coiffure Rita",
    "wof:placetype":"venue"
},
  "geometry": {"coordinates":[2.6652519703,50.9701004028],"type":"Point"}
}