{
  "type": "Feature",
  "properties": {
    "addr:full":"Gaverstraat 35a Geraardsbergen Oost-Vlaanderen 9500",
    "addr:housenumber":"35a",
    "addr:postcode":"9500",
    "addr:street":"Gaverstraat",
    "iso:country":"BE",
    "sg:address":"Gaverstraat 35a",
    "sg:city":"Geraardsbergen",
    "sg:orig_category":"Goederenvervoer over de weg",
    "sg:phone":"+32 54 41 21 82",
    "sg:postcode":"9500",
    "sg:province":"Oost-Vlaanderen",
    "wof:name":"Luc Coesens",
    "wof:placetype":"venue"
},
  "geometry": {"coordinates":[3.8796401024,50.7635993958],"type":"Point"}
}