{
  "type": "Feature",
  "properties": {
    "addr:full":"Peulisstraat 37 Putte Antwerpen 2580",
    "addr:housenumber":"37",
    "addr:postcode":"2580",
    "addr:street":"Peulisstraat",
    "iso:country":"BE",
    "sg:address":"Peulisstraat 37",
    "sg:city":"Putte",
    "sg:classifiers":[
        {
            "category":"Insurance",
            "subcategory":"Insurance Agent",
            "type":"Services"
        }
    ],
    "sg:phone":"+32 15 75 52 61",
    "sg:postcode":"2580",
    "sg:province":"Antwerpen",
    "sg:tags":[
        "verzekeringsmakelaars",
        "expert"
    ],
    "wof:name":"C. Hens",
    "wof:placetype":"venue"
},
  "geometry": {"coordinates":[4.5884327888,51.0382461548],"type":"Point"}
}