{
  "type": "Feature",
  "properties": {
    "addr:full":"Ardooisesteenweg 242 Roeselare West-Vlaanderen 8800",
    "addr:housenumber":"242",
    "addr:postcode":"8800",
    "addr:street":"Ardooisesteenweg",
    "iso:country":"BE",
    "sg:address":"Ardooisesteenweg 242",
    "sg:city":"Roeselare",
    "sg:orig_category":"Goederenvervoer over de weg",
    "sg:phone":"+32 51 24 10 20",
    "sg:postcode":"8800",
    "sg:province":"West-Vlaanderen",
    "wof:name":"Tanghe Snelvervoer",
    "wof:placetype":"venue"
},
  "geometry": {"coordinates":[3.1632399559,50.9480514526],"type":"Point"}
}