{
  "type": "Feature",
  "properties": {
    "addr:full":"Turnhoutsebaan 209 Schilde Antwerpen 2970",
    "addr:housenumber":"209",
    "addr:postcode":"2970",
    "addr:street":"Turnhoutsebaan",
    "iso:country":"BE",
    "sg:address":"Turnhoutsebaan 209",
    "sg:city":"Schilde",
    "sg:orig_category":"M\u00e9decines alternatives",
    "sg:phone":"+32 3 384 27 62",
    "sg:postcode":"2970",
    "sg:province":"Antwerpen",
    "wof:name":"Aertgeerts",
    "wof:placetype":"venue"
},
  "geometry": {"coordinates":[4.5847268105,51.2415618896],"type":"Point"}
}