{
  "type": "Feature",
  "properties": {
    "addr:full":"Alsembergse Steenweg 1049 Ukkel/uccle Bruxelles-Capitale 1180",
    "addr:housenumber":"1049",
    "addr:postcode":"1180",
    "addr:street":"Alsembergse Steenweg;/",
    "iso:country":"BE",
    "sg:address":"Alsembergse Steenweg 1049",
    "sg:city":"Ukkel/uccle",
    "sg:orig_category":"Paramedische behandelingen",
    "sg:phone":"+32 2 332 12 20",
    "sg:postcode":"1180",
    "sg:province":"Bruxelles-Capitale",
    "wof:name":"Ivanka Cankov",
    "wof:placetype":"venue"
},
  "geometry": {"coordinates":[4.3328580856,50.7923355103],"type":"Point"}
}