{
  "type": "Feature",
  "properties": {
    "addr:full":"Nevelstraat 23 Kuurne West-Vlaanderen 8520",
    "addr:housenumber":"23",
    "addr:postcode":"8520",
    "addr:street":"Nevelstraat",
    "iso:country":"BE",
    "sg:address":"Nevelstraat 23",
    "sg:city":"Kuurne",
    "sg:orig_category":"Film-, tv- and videoproductie",
    "sg:phone":"+32 56 72 91 79",
    "sg:postcode":"8520",
    "sg:province":"West-Vlaanderen",
    "wof:name":"Franky Dermaut",
    "wof:placetype":"venue"
},
  "geometry": {"coordinates":[3.2891869545,50.8597106934],"type":"Point"}
}