{
  "type": "Feature",
  "properties": {
    "addr:full":"Antwerpenplein 13-15 Gent Oost-Vlaanderen 9000",
    "addr:housenumber":"13-15",
    "addr:postcode":"9000",
    "addr:street":"Antwerpenplein;Oost-Vlaanderen",
    "iso:country":"BE",
    "sg:address":"Antwerpenplein 13-15",
    "sg:city":"Gent",
    "sg:classifiers":[
        {
            "category":"Professional",
            "subcategory":"Lawyer & Legal Services",
            "type":"Services"
        }
    ],
    "sg:phone":"+32 9 228 30 57",
    "sg:postcode":"9000",
    "sg:province":"Oost-Vlaanderen",
    "wof:name":"De Roeck Arnold",
    "wof:placetype":"venue"
},
  "geometry": {"coordinates":[3.741050005,51.0567779541],"type":"Point"}
}