{
  "type": "Feature",
  "properties": {
    "addr:full":"Boulevard Adolphe Max 115 Bruxelles Bruxelles-Capitale 1000",
    "addr:housenumber":"115",
    "addr:postcode":"1000",
    "addr:street":"Boulevard Adolphe Max",
    "iso:country":"BE",
    "sg:address":"Boulevard Adolphe Max 115",
    "sg:city":"Bruxelles",
    "sg:classifiers":[
        {
            "category":"Communications",
            "subcategory":"Film & Video Production",
            "type":"Services"
        }
    ],
    "sg:phone":"+32 2 219 86 77",
    "sg:postcode":"1000",
    "sg:province":"Bruxelles-Capitale",
    "sg:tags":[
        "hiring",
        "-"
    ],
    "wof:name":"Pink Store",
    "wof:placetype":"venue"
},
  "geometry": {"coordinates":[4.3570351601,50.8545188904],"type":"Point"}
}