{
  "type": "Feature",
  "properties": {
    "addr:full":"Rue Des Dames-blanches 3 La Bruyere Namur 5080",
    "addr:housenumber":"3",
    "addr:postcode":"5080",
    "addr:street":"Rue Des Dames-Blanches;La Bruyere",
    "iso:country":"BE",
    "sg:address":"Rue Des Dames-blanches 3",
    "sg:city":"La Bruyere",
    "sg:orig_category":"Enseignement maternel and primaire",
    "sg:phone":"+32 81 56 79 59",
    "sg:postcode":"5080",
    "sg:province":"Namur",
    "wof:name":"Ecole Fond. Communale",
    "wof:placetype":"venue"
},
  "geometry": {"coordinates":[4.8022260666,50.5055618286],"type":"Point"}
}