{
  "type": "Feature",
  "properties": {
    "addr:full":"Jan Bethunehof 10 Kortrijk West-Vlaanderen 8500",
    "addr:housenumber":"10",
    "addr:postcode":"8500",
    "iso:country":"BE",
    "sg:address":"Jan Bethunehof 10",
    "sg:city":"Kortrijk",
    "sg:orig_category":"Loodgieterij, verwarming and sanitaire installaties",
    "sg:phone":"+32 56 22 38 61",
    "sg:postcode":"8500",
    "sg:province":"West-Vlaanderen",
    "wof:name":"Georges Vansteenkiste",
    "wof:placetype":"venue"
},
  "geometry": {"coordinates":[3.2531189919,50.8221702576],"type":"Point"}
}