{
  "type": "Feature",
  "properties": {
    "iso:country":"BE",
    "sg:address":"Rue Arthur Regniers 10",
    "sg:city":"Lobbes",
    "sg:classifiers":[
        {
            "category":"Arena",
            "subcategory":"Sports Club",
            "type":"Entertainment"
        }
    ],
    "sg:phone":"+32 71 59 27 65",
    "sg:postcode":"6543",
    "sg:province":"Hainaut",
    "sg:tags":[
        "terrain",
        "hors",
        "de",
        "installation",
        "sportifs"
    ],
    "wof:name":"U.s. Merbesars",
    "wof:placetype":"venue"
},
  "geometry": {"coordinates":[4.2123970985,50.3539810181],"type":"Point"}
}