{
  "type": "Feature",
  "properties": {
    "addr:full":"Lorkenlaan 13 Malle Antwerpen 2390",
    "addr:housenumber":"13",
    "addr:postcode":"2390",
    "addr:street":"Lorkenlaan",
    "iso:country":"BE",
    "sg:address":"Lorkenlaan 13",
    "sg:city":"Malle",
    "sg:orig_category":"Software ontwikkeling and ontwerp",
    "sg:phone":"+32 3 309 02 28",
    "sg:postcode":"2390",
    "sg:province":"Antwerpen",
    "wof:name":"Y.l.s.",
    "wof:placetype":"venue"
},
  "geometry": {"coordinates":[4.7631540298,51.2971305847],"type":"Point"}
}