{
  "type": "Feature",
  "properties": {
    "addr:full":"Rue Vandenboogaerde 33 Bruxelles (molenbeek-saint-jean) Bruxelles-Capitale 1080",
    "addr:housenumber":"33",
    "addr:postcode":"1080",
    "addr:street":"Rue Vandenboogaerde",
    "iso:country":"BE",
    "sg:address":"Rue Vandenboogaerde 33",
    "sg:city":"Bruxelles (molenbeek-saint-jean)",
    "sg:classifiers":[
        {
            "category":"Building & Trades",
            "subcategory":"Cleaning & Sanitation",
            "type":"Services"
        }
    ],
    "sg:phone":"+32 2 426 29 67",
    "sg:postcode":"1080",
    "sg:province":"Bruxelles-Capitale",
    "sg:tags":[
        "janitor"
    ],
    "wof:name":"Wery Fr\u00e8res",
    "wof:placetype":"venue"
},
  "geometry": {"coordinates":[4.3397369385,50.8617172241],"type":"Point"}
}