{
  "type": "Feature",
  "properties": {
    "iso:country":"BE",
    "sg:address":"Ninoofsesteenweg 69a",
    "sg:city":"Haaltert (denderhoutem)",
    "sg:classifiers":[
        {
            "category":"Structure",
            "subcategory":"Office Building",
            "type":"Public Place"
        }
    ],
    "sg:phone":"+32 54 34 34 71",
    "sg:postcode":"9450",
    "sg:province":"Oost-Vlaanderen",
    "sg:tags":[
        "drawing"
    ],
    "wof:name":"Gp-design",
    "wof:placetype":"venue"
},
  "geometry": {"coordinates":[4.0213551521,50.8616714478],"type":"Point"}
}