{
  "type": "Feature",
  "properties": {
    "addr:full":"Bergstraat 42a Heist-op-den-berg Antwerpen 2220",
    "addr:housenumber":"42a",
    "addr:postcode":"2220",
    "addr:street":"Bergstraat",
    "iso:country":"BE",
    "sg:address":"Bergstraat 42a",
    "sg:city":"Heist-op-den-berg",
    "sg:classifiers":[
        {
            "category":"Tea Room",
            "subcategory":"None",
            "type":"Food & Drink"
        }
    ],
    "sg:phone":"+32 15 24 34 84",
    "sg:postcode":"2220",
    "sg:province":"Antwerpen",
    "wof:name":"Karreeke ('t)",
    "wof:placetype":"venue"
},
  "geometry": {"coordinates":[4.722618103,51.076133728],"type":"Point"}
}