{
  "type": "Feature",
  "properties": {
    "iso:country":"BE",
    "sg:address":"Meyerveldstraat 44",
    "sg:city":"Aarschot",
    "sg:orig_category":"Plomberie, chauffage and installations sanitaires",
    "sg:phone":"+32 16 50 22 70",
    "sg:postcode":"3202",
    "sg:province":"Vlaams-Brabant",
    "wof:name":"Jacobs Verwarming",
    "wof:placetype":"venue"
},
  "geometry": {"coordinates":[4.8715472221,50.9817810059],"type":"Point"}
}