{
  "type": "Feature",
  "properties": {
    "iso:country":"BE",
    "sg:address":"Drieselstraat 16",
    "sg:city":"Gent",
    "sg:orig_category":"Paramedische behandelingen",
    "sg:phone":"+32 9 251 25 53",
    "sg:postcode":"9041",
    "sg:province":"Oost-Vlaanderen",
    "wof:name":"L. Blomme",
    "wof:placetype":"venue"
},
  "geometry": {"coordinates":[3.7774760723,51.0975570679],"type":"Point"}
}