{
  "type": "Feature",
  "properties": {
    "addr:full":"Bochtlaan 12 Genk Limburg 3600",
    "addr:housenumber":"12",
    "addr:postcode":"3600",
    "addr:street":"Bochtlaan",
    "iso:country":"BE",
    "sg:address":"Bochtlaan 12",
    "sg:city":"Genk",
    "sg:classifiers":[
        {
            "category":"Insurance",
            "subcategory":"Insurance Agent",
            "type":"Services"
        }
    ],
    "sg:phone":"+32 89 36 29 48",
    "sg:postcode":"3600",
    "sg:province":"Limburg",
    "sg:tags":[
        "broker"
    ],
    "wof:name":"Duwel R & Partners Vof",
    "wof:placetype":"venue"
},
  "geometry": {"coordinates":[5.5022702217,50.9666023254],"type":"Point"}
}