{
  "type": "Feature",
  "properties": {
    "iso:country":"BE",
    "sg:address":"Rue D'ypres 14",
    "sg:city":"Komen-waasten/comines-warneton",
    "sg:orig_category":"Assurances. Bureaux de poste",
    "sg:phone":"+32 56 55 52 43",
    "sg:postcode":"7784",
    "sg:province":"Hainaut",
    "wof:name":"La Poste",
    "wof:placetype":"venue"
},
  "geometry": {"coordinates":[2.948497057,50.753490448],"type":"Point"}
}