{
  "type": "Feature",
  "properties": {
    "addr:full":"Broekstraat 4 Zaventem Vlaams-Brabant 1932",
    "addr:housenumber":"4",
    "addr:postcode":"1932",
    "addr:street":"Broekstraat",
    "iso:country":"BE",
    "sg:address":"Broekstraat 4",
    "sg:city":"Zaventem",
    "sg:orig_category":"M\u00e9decins and sp\u00e9cialistes",
    "sg:phone":"+32 2 720 40 42",
    "sg:postcode":"1932",
    "sg:province":"Vlaams-Brabant",
    "wof:name":"Paul Vercammen",
    "wof:placetype":"venue"
},
  "geometry": {"coordinates":[4.4511919022,50.8700523376],"type":"Point"}
}