{
  "type": "Feature",
  "properties": {
    "iso:country":"BE",
    "sg:address":"Arendonckstraat 6",
    "sg:city":"Mechelen",
    "sg:orig_category":"DIVERSE RECREATIEVE ACTIVITEITEN",
    "sg:phone":"+32 15 20 03 90",
    "sg:postcode":"2800",
    "sg:province":"Antwerpen",
    "wof:name":"K.v.b.p. Mechelen",
    "wof:placetype":"venue"
},
  "geometry": {"coordinates":[4.4809331894,51.0370254517],"type":"Point"}
}