{
  "type": "Feature",
  "properties": {
    "addr:full":"Distellaan 59 Oostende West-Vlaanderen 8400",
    "addr:housenumber":"59",
    "addr:postcode":"8400",
    "addr:street":"Distellaan",
    "iso:country":"BE",
    "sg:address":"Distellaan 59",
    "sg:city":"Oostende",
    "sg:orig_category":"Loodgieterij, verwarming and sanitaire installaties",
    "sg:phone":"+32 59 70 18 50",
    "sg:postcode":"8400",
    "sg:province":"West-Vlaanderen",
    "wof:name":"Dominique Cornillie",
    "wof:placetype":"venue"
},
  "geometry": {"coordinates":[2.9126999378,51.2312583923],"type":"Point"}
}