{
  "type": "Feature",
  "properties": {
    "iso:country":"BE",
    "sg:address":"Berlaarsestraat 1",
    "sg:city":"Lier",
    "sg:classifiers":[
        {
            "category":"Landmark",
            "subcategory":"Fountain",
            "type":"Public Place"
        }
    ],
    "sg:phone":"+32 3 489 09 91",
    "sg:postcode":"2500",
    "sg:province":"Antwerpen",
    "sg:tags":[
        "spring"
    ],
    "wof:name":"Tevema Nv",
    "wof:placetype":"venue"
},
  "geometry": {"coordinates":[4.5751280785,51.1303710938],"type":"Point"}
}