{
  "type": "Feature",
  "properties": {
    "addr:full":"Ganzenberg 51 Hamme Oost-Vlaanderen 9220",
    "addr:housenumber":"51",
    "addr:postcode":"9220",
    "addr:street":"Ganzenberg",
    "iso:country":"BE",
    "sg:address":"Ganzenberg 51",
    "sg:city":"Hamme",
    "sg:orig_category":"Epiceries",
    "sg:phone":"+32 52 48 33 92",
    "sg:postcode":"9220",
    "sg:province":"Oost-Vlaanderen",
    "wof:name":"Supermarkt",
    "wof:placetype":"venue"
},
  "geometry": {"coordinates":[4.1637411118,51.0474052429],"type":"Point"}
}