{
  "type": "Feature",
  "properties": {
    "addr:full":"1700 Dilbeek (groot) Vlaams-Brabant 1700",
    "addr:postcode":"1700;1700",
    "addr:street":"Groot Vlaams-Brabant",
    "iso:country":"BE",
    "sg:address":"1700",
    "sg:city":"Dilbeek (groot)",
    "sg:orig_category":"Pharmaciens",
    "sg:phone":"+32 900 10 500",
    "sg:postcode":"1700",
    "sg:province":"Vlaams-Brabant",
    "wof:name":"Pharmacies De Garde",
    "wof:placetype":"venue"
},
  "geometry": {"coordinates":[4.2624697685,50.8459358215],"type":"Point"}
}