{
  "type": "Feature",
  "properties": {
    "iso:country":"BE",
    "sg:address":"Quai Du Halage 56",
    "sg:city":"Vise",
    "sg:classifiers":[
        {
            "category":"Wholesale",
            "subcategory":"Sporting Goods",
            "type":"Manufacturing & Wholesale Goods"
        }
    ],
    "sg:phone":"+32 4 379 23 80",
    "sg:postcode":"4600",
    "sg:province":"Li\u00e8ge",
    "sg:tags":[
        "sport-",
        "kampeermateriaal"
    ],
    "wof:name":"Maison Chez Jos\u00c9",
    "wof:placetype":"venue"
},
  "geometry": {"coordinates":[5.6872119904,50.7416763306],"type":"Point"}
}