{
  "type": "Feature",
  "properties": {
    "addr:full":"Stationsstraat 86 Heusden-zolder Limburg 3550",
    "addr:housenumber":"86",
    "addr:postcode":"3550",
    "addr:street":"Stationsstraat",
    "iso:country":"BE",
    "sg:address":"Stationsstraat 86",
    "sg:city":"Heusden-zolder",
    "sg:orig_category":"Electrom\u00e9nager, t\u00e9l\u00e9visions and radios. Installation \u00e9lectrique r\u00e9sidentielle. R\u00e9parations d'apparei",
    "sg:phone":"+32 11 57 13 18",
    "sg:postcode":"3550",
    "sg:province":"Limburg",
    "wof:name":"Alfons Hoydonckx",
    "wof:placetype":"venue"
},
  "geometry": {"coordinates":[5.3305850029,51.0347747803],"type":"Point"}
}