{
  "type": "Feature",
  "properties": {
    "addr:full":"Place Jules Francq 30 Charleroi (jumet) Hainaut 6040",
    "addr:housenumber":"30",
    "addr:postcode":"6040",
    "addr:street":"Place Jules Francq",
    "iso:country":"BE",
    "sg:address":"Place Jules Francq 30",
    "sg:city":"Charleroi (jumet)",
    "sg:classifiers":[
        {
            "category":"Food & Beverages",
            "subcategory":"Groceries & Convenience Stores",
            "type":"Retail Goods"
        }
    ],
    "sg:phone":"+32 71 35 40 34",
    "sg:postcode":"6040",
    "sg:province":"Hainaut",
    "sg:tags":[
        "grocer"
    ],
    "wof:name":"Paradis Du Frais (au)",
    "wof:placetype":"venue"
},
  "geometry": {"coordinates":[4.4094371796,50.4447898865],"type":"Point"}
}