{
  "type": "Feature",
  "properties": {
    "addr:full":"Rue Ferrer 1 Saint-ghislain Hainaut 7331",
    "addr:housenumber":"1",
    "addr:postcode":"7331",
    "addr:street":"Rue Ferrer;Hainaut",
    "iso:country":"BE",
    "sg:address":"Rue Ferrer 1",
    "sg:city":"Saint-ghislain",
    "sg:orig_category":"Evaluation and estimation de biens immobiliers",
    "sg:phone":"+32 65 64 18 08",
    "sg:postcode":"7331",
    "sg:province":"Hainaut",
    "wof:name":"Immomeca",
    "wof:placetype":"venue"
},
  "geometry": {"coordinates":[3.8329670429,50.4846725464],"type":"Point"}
}