{
  "type": "Feature",
  "properties": {
    "iso:country":"BE",
    "sg:address":"Rue Paulin Ladeuze 6/101",
    "sg:city":"Louvain-la-neuve",
    "sg:classifiers":[
        {
            "category":"Bus Stop",
            "subcategory":"None",
            "type":"Transportation"
        }
    ],
    "sg:phone":"+32 10 45 55 19",
    "sg:postcode":"1348",
    "sg:province":"Brabant Wallon",
    "sg:tags":[
        "autoclave"
    ],
    "wof:name":"Litech S.a.",
    "wof:placetype":"venue"
},
  "geometry": {"coordinates":[4.6118431091,50.6701660156],"type":"Point"}
}