{
  "type": "Feature",
  "properties": {
    "addr:full":"Rue Du Vilcran 13 Gembloux Namur 5031",
    "addr:housenumber":"13",
    "addr:postcode":"5031",
    "addr:street":"Rue Du Vilcran;Namur",
    "iso:country":"BE",
    "sg:address":"Rue Du Vilcran 13",
    "sg:city":"Gembloux",
    "sg:orig_category":"Studios photographiques",
    "sg:phone":"+32 81 64 06 97",
    "sg:postcode":"5031",
    "sg:province":"Namur",
    "wof:name":"Patrick Guillou",
    "wof:placetype":"venue"
},
  "geometry": {"coordinates":[4.7731018066,50.5849876404],"type":"Point"}
}