{
  "type": "Feature",
  "properties": {
    "addr:full":"Rue Fran\u00c7ois Lef\u00c8bvre 2 Liege Li\u00e8ge 4000",
    "addr:housenumber":"2",
    "addr:postcode":"4000",
    "addr:street":"Rue Franc\u0327Ois Lefe\u0300Bvre",
    "iso:country":"BE",
    "sg:address":"Rue Fran\u00c7ois Lef\u00c8bvre 2",
    "sg:city":"Liege",
    "sg:orig_category":"HUISBRANDOLIE",
    "sg:phone":"+32 4 246 01 11",
    "sg:postcode":"4000",
    "sg:province":"Li\u00e8ge",
    "wof:name":"Anthraco-vignette",
    "wof:placetype":"venue"
},
  "geometry": {"coordinates":[5.5512690544,50.6856269836],"type":"Point"}
}