{
  "type": "Feature",
  "properties": {
    "iso:country":"BE",
    "sg:address":"Rue De Mons 91",
    "sg:city":"Estinnes (estinnes-au-val)",
    "sg:classifiers":[
        {
            "category":"Health Services",
            "subcategory":"Health Practitioner",
            "type":"Services"
        }
    ],
    "sg:phone":"+32 65 87 23 60",
    "sg:postcode":"7120",
    "sg:province":"Hainaut",
    "sg:tags":[
        "physiotherapist"
    ],
    "wof:name":"Barbier S\u00e9bastien",
    "wof:placetype":"venue"
},
  "geometry": {"coordinates":[4.0695858002,50.4291992188],"type":"Point"}
}