{
  "type": "Feature",
  "properties": {
    "addr:full":"Vekestraat 34 Antwerpen Antwerpen 2000",
    "addr:housenumber":"34",
    "addr:postcode":"2000",
    "addr:street":"Vekestraat",
    "iso:country":"BE",
    "sg:address":"Vekestraat 34",
    "sg:city":"Antwerpen",
    "sg:orig_category":"Salles de conf\u00e9rences and de r\u00e9ceptions",
    "sg:phone":"+32 3 233 38 78",
    "sg:postcode":"2000",
    "sg:province":"Antwerpen",
    "wof:name":"Bleekhof",
    "wof:placetype":"venue"
},
  "geometry": {"coordinates":[4.4112520218,51.2236022949],"type":"Point"}
}