{
  "type": "Feature",
  "properties": {
    "iso:country":"BE",
    "sg:address":"Haachtsestw 162b",
    "sg:city":"Steenokkerzeel",
    "sg:orig_category":"Electrom\u00e9nager, t\u00e9l\u00e9visions and radios. R\u00e9parations d'appareils \u00e9lectrom\u00e9nagers",
    "sg:phone":"+32 2 751 41 81",
    "sg:postcode":"1820",
    "sg:province":"Vlaams-Brabant",
    "wof:name":"Gias",
    "wof:placetype":"venue"
},
  "geometry": {"coordinates":[4.4942522049,50.916267395],"type":"Point"}
}