{
  "type": "Feature",
  "properties": {
    "iso:country":"BE",
    "sg:address":"Paul Parmentierlaan 77",
    "sg:city":"Knokke-heist (knokke)",
    "sg:classifiers":[
        {
            "category":"Bars & Pubs",
            "type":"Food & Drink"
        }
    ],
    "sg:phone":"+32 50 60 24 29",
    "sg:postcode":"8300",
    "sg:province":"West-Vlaanderen",
    "wof:name":"Monico",
    "wof:placetype":"venue"
},
  "geometry": {"coordinates":[3.2855439186,51.3442993164],"type":"Point"}
}