{
  "type": "Feature",
  "properties": {
    "addr:full":"Plachettes 10 Flobecq Hainaut 7880",
    "addr:housenumber":"10",
    "addr:postcode":"7880",
    "addr:street":"Plachettes;Hainaut",
    "iso:country":"BE",
    "sg:address":"Plachettes 10",
    "sg:city":"Flobecq",
    "sg:classifiers":[
        {
            "category":"Health Services",
            "subcategory":"Health Practitioner",
            "type":"Services"
        }
    ],
    "sg:phone":"+32 68 44 79 15",
    "sg:postcode":"7880",
    "sg:province":"Hainaut",
    "sg:tags":[
        "physiotherapist"
    ],
    "wof:name":"Desmet Cl. Azaire",
    "wof:placetype":"venue"
},
  "geometry": {"coordinates":[3.7352039814,50.7506332397],"type":"Point"}
}