{
  "type": "Feature",
  "properties": {
    "addr:full":"Rue Sylvain Guyaux 68 La Louviere Hainaut 7100",
    "addr:housenumber":"68",
    "addr:postcode":"7100",
    "addr:street":"Rue Sylvain Guyaux",
    "iso:country":"BE",
    "sg:address":"Rue Sylvain Guyaux 68",
    "sg:city":"La Louviere",
    "sg:orig_category":"D\u00e9taillants en pi\u00e8ces and accessoires de voitures",
    "sg:phone":"+32 64 26 69 46",
    "sg:postcode":"7100",
    "sg:province":"Hainaut",
    "wof:name":"Speedy Belgium",
    "wof:placetype":"venue"
},
  "geometry": {"coordinates":[4.1831450462,50.4758796692],"type":"Point"}
}