{
  "type": "Feature",
  "properties": {
    "addr:full":"Avenue Wanderpepen 31 Binche Hainaut 7130",
    "addr:housenumber":"31",
    "addr:postcode":"7130",
    "addr:street":"Avenue Wanderpepen",
    "iso:country":"BE",
    "sg:address":"Avenue Wanderpepen 31",
    "sg:city":"Binche",
    "sg:orig_category":"Schoenen",
    "sg:phone":"+32 64 33 29 91",
    "sg:postcode":"7130",
    "sg:province":"Hainaut",
    "wof:name":"Maison Nathalie",
    "wof:placetype":"venue"
},
  "geometry": {"coordinates":[4.1685090065,50.4119720459],"type":"Point"}
}