{
  "type": "Feature",
  "properties": {
    "iso:country":"BE",
    "sg:address":"Geelsebaan 64",
    "sg:city":"Kasterlee",
    "sg:orig_category":"Supermarkten",
    "sg:postcode":"2460",
    "sg:province":"Antwerpen",
    "wof:name":"Aldi",
    "wof:placetype":"venue"
},
  "geometry": {"coordinates":[4.9700307846,51.2365455627],"type":"Point"}
}