{
  "type": "Feature",
  "properties": {
    "addr:full":"Veldekensstraat 14 Lebbeke Oost-Vlaanderen 9280",
    "addr:housenumber":"14",
    "addr:postcode":"9280",
    "addr:street":"Veldekensstraat",
    "iso:country":"BE",
    "sg:address":"Veldekensstraat 14",
    "sg:city":"Lebbeke",
    "sg:orig_category":"Paramedische behandelingen",
    "sg:phone":"+32 52 41 31 41",
    "sg:postcode":"9280",
    "sg:province":"Oost-Vlaanderen",
    "wof:name":"M.t. Nissens",
    "wof:placetype":"venue"
},
  "geometry": {"coordinates":[4.130109787,50.9946098328],"type":"Point"}
}