{
  "type": "Feature",
  "properties": {
    "addr:full":"Rue Des Pr\u00c9s-pirotte 8 Bievre Namur 5555",
    "addr:housenumber":"8",
    "addr:postcode":"5555",
    "addr:street":"Rue Des Pre\u0301S-Pirotte",
    "iso:country":"BE",
    "sg:address":"Rue Des Pr\u00c9s-pirotte 8",
    "sg:city":"Bievre",
    "sg:orig_category":"Loodgieterij, verwarming and sanitaire installaties",
    "sg:phone":"+32 61 53 45 64",
    "sg:postcode":"5555",
    "sg:province":"Namur",
    "wof:name":"Alain Sabeau",
    "wof:placetype":"venue"
},
  "geometry": {"coordinates":[5.0866141319,49.9197692871],"type":"Point"}
}