{
  "type": "Feature",
  "properties": {
    "iso:country":"BE",
    "sg:address":"Rue Des Beaux-arts 4",
    "sg:city":"Li\u00c8ge",
    "sg:orig_category":"Biblioth\u00e8ques and archives publiques",
    "sg:phone":"+32 4 253 45 32",
    "sg:postcode":"4000",
    "sg:province":"Li\u00e8ge",
    "wof:name":"Ludoth\u00c8que Le Tourbillon",
    "wof:placetype":"venue"
},
  "geometry": {"coordinates":[5.5506358147,50.6087760925],"type":"Point"}
}