{
  "type": "Feature",
  "properties": {
    "addr:full":"Vinkenlaan 34 Sint-niklaas Oost-Vlaanderen 9100",
    "addr:housenumber":"34",
    "addr:postcode":"9100",
    "addr:street":"Vinkenlaan",
    "iso:country":"BE",
    "sg:address":"Vinkenlaan 34",
    "sg:city":"Sint-niklaas",
    "sg:classifiers":[
        {
            "category":"Real Estate",
            "subcategory":"Architect",
            "type":"Services"
        }
    ],
    "sg:phone":"+32 3 777 02 99",
    "sg:postcode":"9100",
    "sg:province":"Oost-Vlaanderen",
    "wof:name":"Pycke R",
    "wof:placetype":"venue"
},
  "geometry": {"coordinates":[4.1373519897,51.1785697937],"type":"Point"}
}