{
  "type": "Feature",
  "properties": {
    "addr:full":"Dijlestraat 10 Oud-heverlee Vlaams-Brabant 3051",
    "addr:housenumber":"10",
    "addr:postcode":"3051",
    "addr:street":"Dijlestraat",
    "iso:country":"BE",
    "sg:address":"Dijlestraat 10",
    "sg:city":"Oud-heverlee",
    "sg:orig_category":"Fruits and l\u00e9gumes. Producteurs de fruits",
    "sg:phone":"+32 16 47 27 81",
    "sg:postcode":"3051",
    "sg:province":"Vlaams-Brabant",
    "wof:name":"Appelfabriek",
    "wof:placetype":"venue"
},
  "geometry": {"coordinates":[4.6423788071,50.8033103943],"type":"Point"}
}