{
  "type": "Feature",
  "properties": {
    "addr:full":"Gachardstraat 51 Elsene/ixelles Bruxelles-Capitale 1050",
    "addr:housenumber":"51",
    "addr:postcode":"1050",
    "addr:street":"Gachardstraat",
    "iso:country":"BE",
    "sg:address":"Gachardstraat 51",
    "sg:city":"Elsene/ixelles",
    "sg:orig_category":"Artsen and specialisten Ziekenhuizen and zorginstellingen",
    "sg:phone":"+32 2 648 22 91",
    "sg:postcode":"1050",
    "sg:province":"Bruxelles-Capitale",
    "wof:name":"Centre M\u00c9dical Gachard",
    "wof:placetype":"venue"
},
  "geometry": {"coordinates":[4.3680357933,50.8263092041],"type":"Point"}
}