{
  "type": "Feature",
  "properties": {
    "addr:full":"Wezembeekstraat 2 Zaventem Vlaams-Brabant 1930",
    "addr:housenumber":"2",
    "addr:postcode":"1930",
    "addr:street":"Wezembeekstraat",
    "iso:country":"BE",
    "sg:address":"Wezembeekstraat 2",
    "sg:city":"Zaventem",
    "sg:orig_category":"Order And Operational Data Acquisition Services",
    "sg:phone":"+32 2 306 86 96",
    "sg:postcode":"1930",
    "sg:province":"Vlaams-Brabant",
    "wof:name":"Bluebackup Belgium Nv",
    "wof:placetype":"venue"
},
  "geometry": {"coordinates":[4.4765658379,50.8712806702],"type":"Point"}
}