{
  "type": "Feature",
  "properties": {
    "addr:full":"Grote Markt 8 Veurne West-Vlaanderen 8630",
    "addr:housenumber":"8",
    "addr:postcode":"8630",
    "addr:street":"Grote Markt",
    "iso:country":"BE",
    "sg:address":"Grote Markt 8",
    "sg:city":"Veurne",
    "sg:classifiers":[
        {
            "category":"Cafe",
            "type":"Food & Drink"
        }
    ],
    "sg:phone":"+32 58 31 18 20",
    "sg:postcode":"8630",
    "sg:province":"West-Vlaanderen",
    "sg:tags":[
        "caf\u00e9s"
    ],
    "wof:name":"Caf\u00c9 De Kroon",
    "wof:placetype":"venue"
},
  "geometry": {"coordinates":[2.6628000736,51.072479248],"type":"Point"}
}