{
  "type": "Feature",
  "properties": {
    "iso:country":"BE",
    "sg:address":"Koepoortkaai 29",
    "sg:city":"Gent",
    "sg:orig_category":"Artsen and specialisten",
    "sg:phone":"+32 9 227 34 59",
    "sg:postcode":"9000",
    "sg:province":"Oost-Vlaanderen",
    "wof:name":"Luc Jordaens",
    "wof:placetype":"venue"
},
  "geometry": {"coordinates":[3.7342460155,51.0523948669],"type":"Point"}
}