{
  "type": "Feature",
  "properties": {
    "iso:country":"BE",
    "sg:address":"Kamstraat 9",
    "sg:city":"Herzele",
    "sg:orig_category":"Eleveurs de bovins",
    "sg:phone":"+32 54 50 05 12",
    "sg:postcode":"9550",
    "sg:province":"Oost-Vlaanderen",
    "wof:name":"Paul Van Der Taelen",
    "wof:placetype":"venue"
},
  "geometry": {"coordinates":[3.9399869442,50.8627929688],"type":"Point"}
}