{
  "type": "Feature",
  "properties": {
    "addr:full":"Vleminkstraat 39 Aarschot Vlaams-Brabant 3201",
    "addr:housenumber":"39",
    "addr:postcode":"3201",
    "addr:street":"Vleminkstraat",
    "iso:country":"BE",
    "sg:address":"Vleminkstraat 39",
    "sg:city":"Aarschot",
    "sg:classifiers":[
        {
            "category":"Fast Food",
            "type":"Food & Drink"
        }
    ],
    "sg:phone":"+32 16 57 06 78",
    "sg:postcode":"3201",
    "sg:province":"Vlaams-Brabant",
    "sg:tags":[
        "\u00c0",
        "emporter",
        "restaurants"
    ],
    "wof:name":"Frituur Bij Arlette",
    "wof:placetype":"venue"
},
  "geometry": {"coordinates":[4.8770709038,51.0153274536],"type":"Point"}
}