{
  "type": "Feature",
  "properties": {
    "iso:country":"BE",
    "sg:address":"Boomsestraat 45",
    "sg:city":"Niel",
    "sg:classifiers":[
        {
            "category":"Personal",
            "subcategory":"Piercing",
            "type":"Services"
        }
    ],
    "sg:phone":"+32 3 844 66 89",
    "sg:postcode":"2845",
    "sg:province":"Antwerpen",
    "sg:tags":[
        "piercings",
        "tatouages"
    ],
    "wof:name":"Tattoo Theo",
    "wof:placetype":"venue"
},
  "geometry": {"coordinates":[4.3330750465,51.1038246155],"type":"Point"}
}