{
  "type": "Feature",
  "properties": {
    "addr:full":"Dek Bernardstraat 16 Maasmechelen Limburg 3630",
    "addr:housenumber":"16",
    "addr:postcode":"3630",
    "addr:street":"Dek Bernardstraat",
    "iso:country":"BE",
    "sg:address":"Dek Bernardstraat 16",
    "sg:city":"Maasmechelen",
    "sg:orig_category":"Diverse bedrijfsbeheeradviesbureaus",
    "sg:phone":"+32 89 77 11 22",
    "sg:postcode":"3630",
    "sg:province":"Limburg",
    "wof:name":"Management & Organisation",
    "wof:placetype":"venue"
},
  "geometry": {"coordinates":[5.6996078491,50.9609451294],"type":"Point"}
}