{
  "type": "Feature",
  "properties": {
    "addr:full":"Kerselaarstraat 6 Hoegaarden Vlaams-Brabant 3320",
    "addr:housenumber":"6",
    "addr:postcode":"3320",
    "addr:street":"Kerselaarstraat",
    "iso:country":"BE",
    "sg:address":"Kerselaarstraat 6",
    "sg:city":"Hoegaarden",
    "sg:orig_category":"Epiceries",
    "sg:phone":"+32 16 76 63 44",
    "sg:postcode":"3320",
    "sg:province":"Vlaams-Brabant",
    "wof:name":"M. Devos",
    "wof:placetype":"venue"
},
  "geometry": {"coordinates":[4.8358998299,50.7897872925],"type":"Point"}
}