{
  "type": "Feature",
  "properties": {
    "addr:full":"F. Van Cauwenberghstraat 14 Lier Antwerpen 2500",
    "addr:housenumber":"14",
    "addr:postcode":"2500",
    "addr:street":"F. Van Cauwenberghstraat",
    "iso:country":"BE",
    "sg:address":"F. Van Cauwenberghstraat 14",
    "sg:city":"Lier",
    "sg:orig_category":"Musea and historische gebouwen",
    "sg:phone":"+32 3 491 13 96",
    "sg:postcode":"2500",
    "sg:province":"Antwerpen",
    "wof:name":"Museum Wuyts-van Campen",
    "wof:placetype":"venue"
},
  "geometry": {"coordinates":[4.5674061775,51.1315498352],"type":"Point"}
}