{
  "type": "Feature",
  "properties": {
    "addr:full":"Chemin Froide Fontaine 1 Soignies Hainaut 7060",
    "addr:housenumber":"1",
    "addr:postcode":"7060",
    "addr:street":"Chemin Froide Fontaine",
    "iso:country":"BE",
    "sg:address":"Chemin Froide Fontaine 1",
    "sg:city":"Soignies",
    "sg:orig_category":"Eleveurs de bovins",
    "sg:phone":"+32 67 33 23 04",
    "sg:postcode":"7060",
    "sg:province":"Hainaut",
    "wof:name":"Charles Motte",
    "wof:placetype":"venue"
},
  "geometry": {"coordinates":[4.0724000931,50.5779037476],"type":"Point"}
}