{
  "type": "Feature",
  "properties": {
    "iso:country":"BE",
    "sg:address":"Corneel Vissenaekenspln 12",
    "sg:city":"Begijnendijk",
    "sg:orig_category":"Distilleries. Vins Fab. Boissons",
    "sg:phone":"+32 16 56 65 29",
    "sg:postcode":"3130",
    "sg:province":"Vlaams-Brabant",
    "wof:name":"Victor De Gent",
    "wof:placetype":"venue"
},
  "geometry": {"coordinates":[4.7838859558,50.9858551025],"type":"Point"}
}