{
  "type": "Feature",
  "properties": {
    "addr:full":"Francisco Ferrerlaan 216 Gent Oost-Vlaanderen 9000",
    "addr:housenumber":"216",
    "addr:postcode":"9000",
    "addr:street":"Francisco Ferrerlaan;Oost-Vlaanderen",
    "iso:country":"BE",
    "sg:address":"Francisco Ferrerlaan 216",
    "sg:city":"Gent",
    "sg:orig_category":"Banques and organismes de cr\u00e9dit",
    "sg:phone":"+32 9 227 78 33",
    "sg:postcode":"9000",
    "sg:province":"Oost-Vlaanderen",
    "wof:name":"Dexia",
    "wof:placetype":"venue"
},
  "geometry": {"coordinates":[3.704969883,51.0708198547],"type":"Point"}
}