{
  "type": "Feature",
  "properties": {
    "iso:country":"BE",
    "sg:address":"Rue La Chapelle 10",
    "sg:city":"Baelen",
    "sg:classifiers":[
        {
            "category":"Arena",
            "subcategory":"Sports Club",
            "type":"Entertainment"
        }
    ],
    "sg:phone":"+32 87 89 01 73",
    "sg:postcode":"4837",
    "sg:province":"Li\u00e8ge",
    "sg:tags":[
        "de"
    ],
    "wof:name":"J.b.m-v.b.c Baelen",
    "wof:placetype":"venue"
},
  "geometry": {"coordinates":[5.9654121399,50.6418609619],"type":"Point"}
}