{
  "type": "Feature",
  "properties": {
    "iso:country":"BE",
    "sg:address":"Hondschootebaan 11",
    "sg:city":"Veurne",
    "sg:orig_category":"Rundveehouders Varkenskwekers",
    "sg:phone":"+32 58 29 94 00",
    "sg:postcode":"8630",
    "sg:province":"West-Vlaanderen",
    "wof:name":"Werner Vandecasserie",
    "wof:placetype":"venue"
},
  "geometry": {"coordinates":[2.6073000431,50.9987106323],"type":"Point"}
}