{
  "type": "Feature",
  "properties": {
    "addr:full":"Paradijsstraat 134 Menen West-Vlaanderen 8930",
    "addr:housenumber":"134",
    "addr:postcode":"8930",
    "addr:street":"Paradijsstraat",
    "iso:country":"BE",
    "sg:address":"Paradijsstraat 134",
    "sg:city":"Menen",
    "sg:orig_category":"Artsen and specialisten",
    "sg:phone":"+32 56 41 60 77",
    "sg:postcode":"8930",
    "sg:province":"West-Vlaanderen",
    "wof:name":"Marc Mullebrouck",
    "wof:placetype":"venue"
},
  "geometry": {"coordinates":[3.1782300472,50.7618370056],"type":"Point"}
}