{
  "type": "Feature",
  "properties": {
    "addr:full":"Rue Paul-reuter 61 Arlon Luxembourg 6700",
    "addr:housenumber":"61",
    "addr:postcode":"6700",
    "addr:street":"Rue Paul-Reuter",
    "iso:country":"BE",
    "sg:address":"Rue Paul-reuter 61",
    "sg:city":"Arlon",
    "sg:orig_category":"Brood, gebak and snoepgoed",
    "sg:phone":"+32 63 22 43 86",
    "sg:postcode":"6700",
    "sg:province":"Luxembourg",
    "wof:name":"Au Fournil St-jean",
    "wof:placetype":"venue"
},
  "geometry": {"coordinates":[5.8187198639,49.6841316223],"type":"Point"}
}