{
  "type": "Feature",
  "properties": {
    "iso:country":"BE",
    "sg:address":"Joris Van Oostenrijkstraat 70",
    "sg:city":"Hasselt (kuringen)",
    "sg:classifiers":[
        {
            "category":"Fast Food",
            "type":"Food & Drink"
        }
    ],
    "sg:phone":"+32 11 87 35 45",
    "sg:postcode":"3511",
    "sg:province":"Limburg",
    "sg:tags":[
        "fried",
        "stand",
        "potato"
    ],
    "wof:name":"Hiro-snack",
    "wof:placetype":"venue"
},
  "geometry": {"coordinates":[5.3056077957,50.9436912537],"type":"Point"}
}