{
  "type": "Feature",
  "properties": {
    "addr:full":"Molendreef 3 De Haan West-Vlaanderen 8421",
    "addr:housenumber":"3",
    "addr:postcode":"8421",
    "addr:street":"Molendreef",
    "iso:country":"BE",
    "sg:address":"Molendreef 3",
    "sg:city":"De Haan",
    "sg:classifiers":[
        {
            "category":"Banks & Credit Unions",
            "subcategory":"Investment Brokerage",
            "type":"Services"
        }
    ],
    "sg:phone":"+32 59 23 33 20",
    "sg:postcode":"8421",
    "sg:province":"West-Vlaanderen",
    "sg:tags":[
        "pension"
    ],
    "wof:name":"Depree Yvonne",
    "wof:placetype":"venue"
},
  "geometry": {"coordinates":[3.0391368866,51.2713737488],"type":"Point"}
}