{
  "type": "Feature",
  "properties": {
    "iso:country":"BE",
    "sg:address":"Alkenstraat 34",
    "sg:city":"Hasselt",
    "sg:orig_category":"Brood, gebak and snoepgoed",
    "sg:phone":"+32 11 31 23 51",
    "sg:postcode":"3512",
    "sg:province":"Limburg",
    "wof:name":"Bakkerij Dupont",
    "wof:placetype":"venue"
},
  "geometry": {"coordinates":[5.2482180595,50.9159965515],"type":"Point"}
}