{
  "type": "Feature",
  "properties": {
    "iso:country":"BE",
    "sg:address":"Rue Garde-dieu 24",
    "sg:city":"Li\u00c8ge",
    "sg:orig_category":"Advocaten and juridische adviseurs",
    "sg:phone":"+32 4 349 02 00",
    "sg:postcode":"4031",
    "sg:province":"Li\u00e8ge",
    "wof:name":"Cora Counerotte",
    "wof:placetype":"venue"
},
  "geometry": {"coordinates":[5.5847802162,50.6193161011],"type":"Point"}
}