{
  "type": "Feature",
  "properties": {
    "iso:country":"BE",
    "sg:address":"Husseveldestraat 70",
    "sg:city":"Laarne",
    "sg:orig_category":"Charpentes and couvertures",
    "sg:phone":"+32 9 367 00 08",
    "sg:postcode":"9270",
    "sg:province":"Oost-Vlaanderen",
    "wof:name":"Geert Krick",
    "wof:placetype":"venue"
},
  "geometry": {"coordinates":[3.9117760658,51.0654716492],"type":"Point"}
}