{
  "type": "Feature",
  "properties": {
    "addr:full":"Martelaarslaan 305 Gent Oost-Vlaanderen 9000",
    "addr:housenumber":"305",
    "addr:postcode":"9000",
    "addr:street":"Martelaarslaan;Oost-Vlaanderen",
    "iso:country":"BE",
    "sg:address":"Martelaarslaan 305",
    "sg:city":"Gent",
    "sg:classifiers":[
        {
            "category":"Insurance",
            "subcategory":"Insurance Agent",
            "type":"Services"
        }
    ],
    "sg:phone":"+32 9 240 00 00",
    "sg:postcode":"9000",
    "sg:province":"Oost-Vlaanderen",
    "sg:tags":[
        "broker"
    ],
    "wof:name":"Allia Nv",
    "wof:placetype":"venue"
},
  "geometry": {"coordinates":[3.7101979256,51.0472946167],"type":"Point"}
}