{
  "type": "Feature",
  "properties": {
    "addr:full":"Sans Soucistraat 60 Elsene/ixelles Bruxelles-Capitale 1050",
    "addr:housenumber":"60",
    "addr:postcode":"1050",
    "addr:street":"Sans Soucistraat",
    "iso:country":"BE",
    "sg:address":"Sans Soucistraat 60",
    "sg:city":"Elsene/ixelles",
    "sg:orig_category":"Artsen and specialisten",
    "sg:phone":"+32 2 513 11 50",
    "sg:postcode":"1050",
    "sg:province":"Bruxelles-Capitale",
    "wof:name":"Philippe Laskar",
    "wof:placetype":"venue"
},
  "geometry": {"coordinates":[4.3700780869,50.8339920044],"type":"Point"}
}