{
  "type": "Feature",
  "properties": {
    "iso:country":"BE",
    "sg:address":"Meerskant 30",
    "sg:city":"Lebbeke",
    "sg:orig_category":"Articles non-alimentaires",
    "sg:phone":"+32 52 41 53 93",
    "sg:postcode":"9280",
    "sg:province":"Oost-Vlaanderen",
    "wof:name":"Dream Company",
    "wof:placetype":"venue"
},
  "geometry": {"coordinates":[4.0894141197,50.997756958],"type":"Point"}
}