{
  "type": "Feature",
  "properties": {
    "iso:country":"BE",
    "sg:address":"Geertruimoerstraat 27",
    "sg:city":"Tremelo (baal)",
    "sg:classifiers":[
        {
            "category":"Manufacturing",
            "subcategory":"Tools & Machinery",
            "type":"Manufacturing & Wholesale Goods"
        }
    ],
    "sg:phone":"+32 16 53 26 30",
    "sg:postcode":"3128",
    "sg:province":"Vlaams-Brabant",
    "sg:tags":[
        "-"
    ],
    "wof:name":"Icc-widia",
    "wof:placetype":"venue"
},
  "geometry": {"coordinates":[4.7410359383,51.01222229],"type":"Point"}
}