{
  "type": "Feature",
  "properties": {
    "iso:country":"BE",
    "sg:address":"Karel Serweytensstraat 4",
    "sg:city":"Brugge",
    "sg:orig_category":"Decoratieve kunst and kunstbenodigdheden",
    "sg:phone":"+32 50 31 47 90",
    "sg:postcode":"8000",
    "sg:province":"West-Vlaanderen",
    "wof:name":"Francoise Alleyn",
    "wof:placetype":"venue"
},
  "geometry": {"coordinates":[3.2034950256,51.2168159485],"type":"Point"}
}