{
  "type": "Feature",
  "properties": {
    "iso:country":"BE",
    "sg:address":"Rue Baziles 2",
    "sg:city":"Bl\u00e9gny (trembleur)",
    "sg:classifiers":[
        {
            "category":"Professional",
            "subcategory":"Engineering",
            "type":"Services"
        }
    ],
    "sg:phone":"+32 4 387 64 41",
    "sg:postcode":"4670",
    "sg:province":"Li\u00e8ge",
    "sg:tags":[
        "industrial",
        "-",
        "automation"
    ],
    "wof:name":"Bartholom\u00e9 Automatisme Sprl",
    "wof:placetype":"venue"
},
  "geometry": {"coordinates":[5.7255001068,50.6765937805],"type":"Point"}
}