{
  "type": "Feature",
  "properties": {
    "addr:full":"Avenue Des Tritons 31 Box 2 Bruxelles (watermael-boitsfort) Bruxelles-Capitale 1170",
    "addr:housenumber":"31;2",
    "addr:postcode":"1170",
    "addr:street":"Avenue Des Tritons;Box",
    "iso:country":"BE",
    "sg:address":"Avenue Des Tritons 31 Box 2",
    "sg:city":"Bruxelles (watermael-boitsfort)",
    "sg:classifiers":[
        {
            "category":"Insurance",
            "subcategory":"Insurance Agent",
            "type":"Services"
        }
    ],
    "sg:phone":"+32 2 673 52 20",
    "sg:postcode":"1170",
    "sg:province":"Bruxelles-Capitale",
    "sg:tags":[
        "broker"
    ],
    "wof:name":"Van Dessel Gilbert",
    "wof:placetype":"venue"
},
  "geometry": {"coordinates":[4.4160151482,50.8058776855],"type":"Point"}
}