{
  "type": "Feature",
  "properties": {
    "addr:full":"Ijzerenleen 4-6 Mechelen Antwerpen 2800",
    "addr:housenumber":"4-6",
    "addr:postcode":"2800",
    "addr:street":"Ijzerenleen",
    "iso:country":"BE",
    "sg:address":"Ijzerenleen 4-6",
    "sg:city":"Mechelen",
    "sg:classifiers":[
        {
            "category":"Building & Trades",
            "subcategory":"Construction",
            "type":"Services"
        }
    ],
    "sg:phone":"+32 15 20 45 43",
    "sg:postcode":"2800",
    "sg:province":"Antwerpen",
    "sg:tags":[
        "tapestry"
    ],
    "wof:name":"Van Caster Etn",
    "wof:placetype":"venue"
},
  "geometry": {"coordinates":[4.4788198471,51.0272293091],"type":"Point"}
}