{
  "type": "Feature",
  "properties": {
    "iso:country":"BE",
    "sg:address":"Rue Albert I",
    "sg:city":"La Louviere",
    "sg:orig_category":"Industri\u00eble wasserijen and droogkuis",
    "sg:phone":"+32 64 22 66 22",
    "sg:postcode":"7100",
    "sg:province":"Hainaut",
    "wof:name":"Boland",
    "wof:placetype":"venue"
},
  "geometry": {"coordinates":[4.1874508858,50.4768066406],"type":"Point"}
}