{
  "type": "Feature",
  "properties": {
    "addr:full":"Hezewijk 37ba Olen Antwerpen 2250",
    "addr:housenumber":"37ba",
    "addr:postcode":"2250",
    "addr:street":"Hezewijk",
    "iso:country":"BE",
    "sg:address":"Hezewijk 37ba",
    "sg:city":"Olen",
    "sg:classifiers":[
        {
            "category":"Food & Beverages",
            "subcategory":"Fruits & Vegetables",
            "type":"Retail Goods"
        }
    ],
    "sg:phone":"+32 14 26 33 62",
    "sg:postcode":"2250",
    "sg:province":"Antwerpen",
    "sg:tags":[
        "groenten"
    ],
    "wof:name":"De Punthoef",
    "wof:placetype":"venue"
},
  "geometry": {"coordinates":[4.8454141617,51.1485786438],"type":"Point"}
}