{
  "type": "Feature",
  "properties": {
    "addr:full":"Kwabrugstraat 19 Kortrijk West-Vlaanderen 8510",
    "addr:housenumber":"19",
    "addr:postcode":"8510",
    "addr:street":"Kwabrugstraat",
    "iso:country":"BE",
    "sg:address":"Kwabrugstraat 19",
    "sg:city":"Kortrijk",
    "sg:orig_category":"Passagiersvervoer over de weg Reisbureaus",
    "sg:phone":"+32 56 22 37 17",
    "sg:postcode":"8510",
    "sg:province":"West-Vlaanderen",
    "wof:name":"Demuynck-vansteelandt",
    "wof:placetype":"venue"
},
  "geometry": {"coordinates":[3.2788519859,50.7750358582],"type":"Point"}
}