{
  "type": "Feature",
  "properties": {
    "addr:full":"Hogeweg 12 Sint-truiden (ordingen) Limburg 3800",
    "addr:housenumber":"12",
    "addr:postcode":"3800",
    "addr:street":"Hogeweg",
    "iso:country":"BE",
    "sg:address":"Hogeweg 12",
    "sg:city":"Sint-truiden (ordingen)",
    "sg:classifiers":[
        {
            "category":"Building & Trades",
            "subcategory":"Locksmith",
            "type":"Services"
        }
    ],
    "sg:phone":"+32 11 68 52 18",
    "sg:postcode":"3800",
    "sg:province":"Limburg",
    "sg:tags":[
        "material",
        "road"
    ],
    "wof:name":"Somers G",
    "wof:placetype":"venue"
},
  "geometry": {"coordinates":[5.1863641739,50.8153343201],"type":"Point"}
}