{
  "type": "Feature",
  "properties": {
    "addr:full":"Industrieweg Noord 1114 Opglabbeek Limburg 3660",
    "addr:housenumber":"1114",
    "addr:postcode":"3660",
    "addr:street":"Industrieweg Noord",
    "iso:country":"BE",
    "sg:address":"Industrieweg Noord 1114",
    "sg:city":"Opglabbeek",
    "sg:classifiers":[
        {
            "category":"Autos & Motor Vehicles",
            "subcategory":"Auto Supplies",
            "type":"Retail Goods"
        }
    ],
    "sg:phone":"+32 89 81 98 10",
    "sg:postcode":"3660",
    "sg:province":"Limburg",
    "sg:tags":[
        "access",
        "automobile",
        "part",
        "-"
    ],
    "wof:name":"Autoservice Elmech",
    "wof:placetype":"venue"
},
  "geometry": {"coordinates":[5.5357408524,51.0351409912],"type":"Point"}
}