{
  "type": "Feature",
  "properties": {
    "iso:country":"BE",
    "sg:address":"Rue D'anderlues 1",
    "sg:city":"Binche (leval-trahegnies)",
    "sg:classifiers":[
        {
            "category":"Restaurant",
            "type":"Food & Drink"
        }
    ],
    "sg:phone":"+32 64 31 09 09",
    "sg:postcode":"7134",
    "sg:province":"Hainaut",
    "sg:tags":[
        "industrial",
        "kitchen",
        "catering"
    ],
    "wof:name":"Ital Sprl",
    "wof:placetype":"venue"
},
  "geometry": {"coordinates":[4.2221341133,50.4237632751],"type":"Point"}
}