{
  "type": "Feature",
  "properties": {
    "iso:country":"BE",
    "sg:address":"Egelvoortstraat 15",
    "sg:city":"Schilde",
    "sg:orig_category":"Instituts de beaut\u00e9",
    "sg:phone":"+32 3 385 82 17",
    "sg:postcode":"2970",
    "sg:province":"Antwerpen",
    "wof:name":"Kristel Verhoeven",
    "wof:placetype":"venue"
},
  "geometry": {"coordinates":[4.5923981667,51.2387123108],"type":"Point"}
}