{
  "type": "Feature",
  "properties": {
    "addr:full":"Antwerpsestraat 43 Lier Antwerpen 2500",
    "addr:housenumber":"43",
    "addr:postcode":"2500",
    "addr:street":"Antwerpsestraat",
    "iso:country":"BE",
    "sg:address":"Antwerpsestraat 43",
    "sg:city":"Lier",
    "sg:classifiers":[
        {
            "category":"Shopping",
            "subcategory":"Clothing, Apparel, & Fashions",
            "type":"Retail Goods"
        }
    ],
    "sg:phone":"+32 3 488 31 09",
    "sg:postcode":"2500",
    "sg:province":"Antwerpen",
    "sg:tags":[
        "v\u00eatements",
        "pour",
        "dame"
    ],
    "wof:name":"Huis Coquet",
    "wof:placetype":"venue"
},
  "geometry": {"coordinates":[4.5680770874,51.132774353],"type":"Point"}
}