{
  "type": "Feature",
  "properties": {
    "addr:full":"Rue Lahaut 21 Donceel (jeneffe) Li\u00e8ge 4357",
    "addr:housenumber":"21",
    "addr:postcode":"4357",
    "addr:street":"Rue Lahaut;Jeneffe",
    "iso:country":"BE",
    "sg:address":"Rue Lahaut 21",
    "sg:city":"Donceel (jeneffe)",
    "sg:classifiers":[
        {
            "category":"Professional",
            "subcategory":"Accounting & Tax Preparation",
            "type":"Services"
        }
    ],
    "sg:phone":"+32 4 250 39 29",
    "sg:postcode":"4357",
    "sg:province":"Li\u00e8ge",
    "sg:tags":[
        "bookkeeper"
    ],
    "wof:name":"Roly Ch",
    "wof:placetype":"venue"
},
  "geometry": {"coordinates":[5.3534631729,50.6491851807],"type":"Point"}
}