{
  "type": "Feature",
  "properties": {
    "iso:country":"BE",
    "sg:address":"Handelslei 96",
    "sg:city":"Zoersel",
    "sg:classifiers":[
        {
            "category":"Fast Food",
            "type":"Food & Drink"
        }
    ],
    "sg:phone":"+32 3 385 07 69",
    "sg:postcode":"2980",
    "sg:province":"Antwerpen",
    "sg:tags":[
        "meeneem",
        "restaurant"
    ],
    "wof:name":"Kam Po",
    "wof:placetype":"venue"
},
  "geometry": {"coordinates":[4.6484470367,51.2730941772],"type":"Point"}
}