{
  "type": "Feature",
  "properties": {
    "iso:country":"BE",
    "sg:address":"Avenue Franklin Roosevelt 104",
    "sg:city":"Rixensart",
    "sg:orig_category":"Non-Classified Establishments",
    "sg:phone":"+32 2 654 15 14",
    "sg:postcode":"1330",
    "sg:province":"Brabant Wallon",
    "wof:name":"Hutrade Sprl",
    "wof:placetype":"venue"
},
  "geometry": {"coordinates":[4.516040802,50.7213096619],"type":"Point"}
}