{
  "type": "Feature",
  "properties": {
    "iso:country":"BE",
    "sg:address":"Torhoutsesteenweg 283b1",
    "sg:city":"Brugge",
    "sg:orig_category":"Textiel Verlichting and huishoudartikelen",
    "sg:phone":"+32 50 39 00 47",
    "sg:postcode":"8200",
    "sg:province":"West-Vlaanderen",
    "wof:name":"Artline Woondecoratie",
    "wof:placetype":"venue"
},
  "geometry": {"coordinates":[3.1989500523,51.1945343018],"type":"Point"}
}