{
  "type": "Feature",
  "properties": {
    "iso:country":"BE",
    "sg:address":"Chauss\u00e9e De Louvain 480-484",
    "sg:city":"Namur (bouge)",
    "sg:classifiers":[
        {
            "category":"Professional",
            "subcategory":"Business Services",
            "type":"Services"
        }
    ],
    "sg:phone":"+32 81 21 52 00",
    "sg:postcode":"5004",
    "sg:province":"Namur",
    "sg:tags":[
        "firm"
    ],
    "wof:name":"Burogest Sa",
    "wof:placetype":"venue"
},
  "geometry": {"coordinates":[4.8893108368,50.4850463867],"type":"Point"}
}