{
  "type": "Feature",
  "properties": {
    "iso:country":"BE",
    "sg:address":"Varkensmarkt 50b2",
    "sg:city":"Diepenbeek",
    "sg:orig_category":"Banques and organismes de cr\u00e9dit",
    "sg:phone":"+32 11 33 40 20",
    "sg:postcode":"3590",
    "sg:province":"Limburg",
    "wof:name":"Bank Van Limburg",
    "wof:placetype":"venue"
},
  "geometry": {"coordinates":[5.4173002243,50.9069404602],"type":"Point"}
}