{
  "type": "Feature",
  "properties": {
    "iso:country":"BE",
    "sg:address":"Rootstraat 53",
    "sg:city":"Tervuren (duisburg)",
    "sg:classifiers":[
        {
            "category":"Banks & Credit Unions",
            "subcategory":"Investment Brokerage",
            "type":"Services"
        }
    ],
    "sg:phone":"+32 2 767 88 84",
    "sg:postcode":"3080",
    "sg:province":"Vlaams-Brabant",
    "sg:tags":[
        "machine",
        "soil",
        "drilling",
        "equipment"
    ],
    "wof:name":"L.b.s.m. Benelux",
    "wof:placetype":"venue"
},
  "geometry": {"coordinates":[4.5132598877,50.8243637085],"type":"Point"}
}