{
  "type": "Feature",
  "properties": {
    "addr:full":"Avenue Du Grand Cortil 13 Chaudfontaine (embourg) Li\u00e8ge 4053",
    "addr:housenumber":"13",
    "addr:postcode":"4053",
    "addr:street":"Avenue Du Grand Cortil",
    "iso:country":"BE",
    "sg:address":"Avenue Du Grand Cortil 13",
    "sg:city":"Chaudfontaine (embourg)",
    "sg:classifiers":[
        {
            "category":"Health Services",
            "subcategory":"Health Practitioner",
            "type":"Services"
        }
    ],
    "sg:phone":"+32 4 365 80 14",
    "sg:postcode":"4053",
    "sg:province":"Li\u00e8ge",
    "sg:tags":[
        "physiotherapist"
    ],
    "wof:name":"Curtz M",
    "wof:placetype":"venue"
},
  "geometry": {"coordinates":[5.6081418991,50.5862312317],"type":"Point"}
}