{
  "type": "Feature",
  "properties": {
    "addr:full":"Brusselsesteenweg 341 Herent Vlaams-Brabant 3020",
    "addr:housenumber":"341",
    "addr:postcode":"3020",
    "addr:street":"Brusselsesteenweg",
    "iso:country":"BE",
    "sg:address":"Brusselsesteenweg 341",
    "sg:city":"Herent",
    "sg:orig_category":"Belastingconsulenten Diverse juridische dienstverlening",
    "sg:phone":"+32 16 49 92 22",
    "sg:postcode":"3020",
    "sg:province":"Vlaams-Brabant",
    "wof:name":"Bur.buyse-de Vlieger & Co",
    "wof:placetype":"venue"
},
  "geometry": {"coordinates":[4.6591420174,50.888584137],"type":"Point"}
}