{
  "type": "Feature",
  "properties": {
    "iso:country":"BE",
    "sg:address":"Beverbeek 15",
    "sg:city":"Hamont-achel",
    "sg:orig_category":"Rundveehouders",
    "sg:phone":"+32 11 44 54 68",
    "sg:postcode":"3930",
    "sg:province":"Limburg",
    "wof:name":"Jan Broekx",
    "wof:placetype":"venue"
},
  "geometry": {"coordinates":[5.5450549126,51.2511863708],"type":"Point"}
}