{
  "type": "Feature",
  "properties": {
    "addr:full":"Rue General Tombeur 18-20 Bruxelles Bruxelles-Capitale 1040",
    "addr:housenumber":"18-20",
    "addr:postcode":"1040",
    "addr:street":"Rue General Tombeur",
    "iso:country":"BE",
    "sg:address":"Rue General Tombeur 18-20",
    "sg:city":"Bruxelles",
    "sg:orig_category":"Extra-Large Photos",
    "sg:phone":"+32 2 735 33 05",
    "sg:postcode":"1040",
    "sg:province":"Bruxelles-Capitale",
    "wof:name":"Sadocolor S.p.r.l.",
    "wof:placetype":"venue"
},
  "geometry": {"coordinates":[4.3962521553,50.8362846375],"type":"Point"}
}