{
  "type": "Feature",
  "properties": {
    "addr:full":"Avenue Coghen 120 Bruxelles (uccle) Bruxelles-Capitale 1180",
    "addr:housenumber":"120",
    "addr:postcode":"1180",
    "addr:street":"Avenue Coghen",
    "iso:country":"BE",
    "sg:address":"Avenue Coghen 120",
    "sg:city":"Bruxelles (uccle)",
    "sg:classifiers":[
        {
            "category":"Real Estate",
            "subcategory":"Architect",
            "type":"Services"
        }
    ],
    "sg:phone":"+32 2 346 49 15",
    "sg:postcode":"1180",
    "sg:province":"Bruxelles-Capitale",
    "wof:name":"Closson Ph",
    "wof:placetype":"venue"
},
  "geometry": {"coordinates":[4.3403282166,50.8103294373],"type":"Point"}
}