{
  "type": "Feature",
  "properties": {
    "iso:country":"BE",
    "sg:address":"Sinaaistraat 40",
    "sg:city":"Lokeren",
    "sg:orig_category":"Mat\u00e9riel m\u00e9dical and orthop\u00e9dique and proth\u00e8ses Fab",
    "sg:phone":"+32 9 348 32 08",
    "sg:postcode":"9160",
    "sg:province":"Oost-Vlaanderen",
    "wof:name":"Geert Slabbaert",
    "wof:placetype":"venue"
},
  "geometry": {"coordinates":[4.0089859962,51.1272354126],"type":"Point"}
}