{
  "type": "Feature",
  "properties": {
    "addr:full":"Hogerstraat 25 Kinrooi Limburg 3640",
    "addr:housenumber":"25",
    "addr:postcode":"3640",
    "addr:street":"Hogerstraat",
    "iso:country":"BE",
    "sg:address":"Hogerstraat 25",
    "sg:city":"Kinrooi",
    "sg:orig_category":"HUISBRANDOLIE",
    "sg:phone":"+32 89 70 11 34",
    "sg:postcode":"3640",
    "sg:province":"Limburg",
    "wof:name":"Maria Vrinssen",
    "wof:placetype":"venue"
},
  "geometry": {"coordinates":[5.737197876,51.176486969],"type":"Point"}
}