{
  "type": "Feature",
  "properties": {
    "addr:full":"Vaartstraat 64 Leuven Vlaams-Brabant 3000",
    "addr:housenumber":"64",
    "addr:postcode":"3000",
    "addr:street":"Vaartstraat",
    "iso:country":"BE",
    "sg:address":"Vaartstraat 64",
    "sg:city":"Leuven",
    "sg:classifiers":[
        {
            "category":"Professional",
            "subcategory":"Lawyer & Legal Services",
            "type":"Services"
        }
    ],
    "sg:phone":"+32 16 31 01 31",
    "sg:postcode":"3000",
    "sg:province":"Vlaams-Brabant",
    "wof:name":"Simar Renaud",
    "wof:placetype":"venue"
},
  "geometry": {"coordinates":[4.7011451721,50.8839263916],"type":"Point"}
}