{
  "type": "Feature",
  "properties": {
    "addr:full":"Gareelmakersstraat 10 Bellegem West-Vlaanderen 8510",
    "addr:housenumber":"10",
    "addr:postcode":"8510",
    "addr:street":"Gareelmakersstraat",
    "iso:country":"BE",
    "sg:address":"Gareelmakersstraat 10",
    "sg:city":"Bellegem",
    "sg:orig_category":"Dakwerken Gespecialiseerde residenti\u00eble bouw",
    "sg:phone":"+32 56 20 31 77",
    "sg:postcode":"8510",
    "sg:province":"West-Vlaanderen",
    "wof:name":"Vanwael",
    "wof:placetype":"venue"
},
  "geometry": {"coordinates":[3.2849009037,50.7727661133],"type":"Point"}
}