{
  "type": "Feature",
  "properties": {
    "iso:country":"BE",
    "sg:address":"Industriepark Kolmen 38-2",
    "sg:city":"Alken",
    "sg:classifiers":[
        {
            "category":"Food & Beverages",
            "subcategory":"Specialty",
            "type":"Retail Goods"
        }
    ],
    "sg:phone":"+32 11 59 01 59",
    "sg:postcode":"3570",
    "sg:province":"Limburg",
    "sg:tags":[
        "sinking",
        "groundwater"
    ],
    "wof:name":"Gm Consulting",
    "wof:placetype":"venue"
},
  "geometry": {"coordinates":[5.294301033,50.8866691589],"type":"Point"}
}