{
  "type": "Feature",
  "properties": {
    "addr:full":"Dwarsstraat 1 Anzegem West-Vlaanderen 8570",
    "addr:housenumber":"1",
    "addr:postcode":"8570",
    "addr:street":"Dwarsstraat",
    "iso:country":"BE",
    "sg:address":"Dwarsstraat 1",
    "sg:city":"Anzegem",
    "sg:orig_category":"Ordinateurs and \u00e9quipement informatique",
    "sg:phone":"+32 56 68 91 09",
    "sg:postcode":"8570",
    "sg:province":"West-Vlaanderen",
    "wof:name":"D.l.x.",
    "wof:placetype":"venue"
},
  "geometry": {"coordinates":[3.5012390614,50.8283424377],"type":"Point"}
}