{
  "type": "Feature",
  "properties": {
    "addr:full":"Rue De La Tasseni\u00e8re 3 Dinant Namur 5500",
    "addr:housenumber":"3",
    "addr:postcode":"5500",
    "addr:street":"Rue De La Tassenie\u0300Re",
    "iso:country":"BE",
    "sg:address":"Rue De La Tasseni\u00e8re 3",
    "sg:city":"Dinant",
    "sg:classifiers":[
        {
            "category":"Insurance",
            "subcategory":"Insurance Agent",
            "type":"Services"
        }
    ],
    "sg:phone":"+32 82 21 30 31",
    "sg:postcode":"5500",
    "sg:province":"Namur",
    "sg:tags":[
        "broker"
    ],
    "wof:name":"Pigneur Ets",
    "wof:placetype":"venue"
},
  "geometry": {"coordinates":[4.8943891525,50.2349205017],"type":"Point"}
}