{
  "type": "Feature",
  "properties": {
    "addr:full":"Wolvertemsesteenweg 24 Merchtem Vlaams-Brabant 1785",
    "addr:housenumber":"24",
    "addr:postcode":"1785",
    "addr:street":"Wolvertemsesteenweg",
    "iso:country":"BE",
    "sg:address":"Wolvertemsesteenweg 24",
    "sg:city":"Merchtem",
    "sg:orig_category":"Groenten and fruit Gh",
    "sg:phone":"+32 52 37 07 59",
    "sg:postcode":"1785",
    "sg:province":"Vlaams-Brabant",
    "wof:name":"Jozef Kallaerts",
    "wof:placetype":"venue"
},
  "geometry": {"coordinates":[4.2387781143,50.960067749],"type":"Point"}
}