{
  "type": "Feature",
  "properties": {
    "addr:full":"Sint-annastraat 30 Overijse Vlaams-Brabant 3090",
    "addr:housenumber":"30",
    "addr:postcode":"3090",
    "addr:street":"Sint-Annastraat",
    "iso:country":"BE",
    "sg:address":"Sint-annastraat 30",
    "sg:city":"Overijse",
    "sg:orig_category":"Banken and kredietinstellingen",
    "sg:phone":"+32 2 687 51 23",
    "sg:postcode":"3090",
    "sg:province":"Vlaams-Brabant",
    "wof:name":"Citibank",
    "wof:placetype":"venue"
},
  "geometry": {"coordinates":[4.5182909966,50.7764892578],"type":"Point"}
}