{
  "type": "Feature",
  "properties": {
    "addr:full":"Stationsstraat 19 Linter (drieslinter) Vlaams-Brabant 3350",
    "addr:housenumber":"19",
    "addr:postcode":"3350",
    "addr:street":"Stationsstraat",
    "iso:country":"BE",
    "sg:address":"Stationsstraat 19",
    "sg:city":"Linter (drieslinter)",
    "sg:classifiers":[
        {
            "category":"Bars & Pubs",
            "type":"Food & Drink"
        }
    ],
    "sg:phone":"+32 11 78 19 42",
    "sg:postcode":"3350",
    "sg:province":"Vlaams-Brabant",
    "wof:name":"Stiers H",
    "wof:placetype":"venue"
},
  "geometry": {"coordinates":[5.0549149513,50.8459434509],"type":"Point"}
}