{
  "type": "Feature",
  "properties": {
    "addr:full":"Noorddoorgang 11 Brussel/bruxelles Bruxelles-Capitale 1000",
    "addr:housenumber":"11",
    "addr:postcode":"1000",
    "addr:street":"Noorddoorgang;/",
    "iso:country":"BE",
    "sg:address":"Noorddoorgang 11",
    "sg:city":"Brussel/bruxelles",
    "sg:orig_category":"Herstelling horloges and juwelen Juwelen and horloges",
    "sg:phone":"+32 2 217 77 88",
    "sg:postcode":"1000",
    "sg:province":"Bruxelles-Capitale",
    "wof:name":"Creations Halet",
    "wof:placetype":"venue"
},
  "geometry": {"coordinates":[4.3682951927,50.8486480713],"type":"Point"}
}