{
  "type": "Feature",
  "properties": {
    "addr:full":"Rue Fran\u00e7ois Hellinckx 13 Bruxelles (koekelberg) Bruxelles-Capitale 1081",
    "addr:housenumber":"13",
    "addr:postcode":"1081",
    "addr:street":"Rue Franc\u0327Ois Hellinckx",
    "iso:country":"BE",
    "sg:address":"Rue Fran\u00e7ois Hellinckx 13",
    "sg:city":"Bruxelles (koekelberg)",
    "sg:classifiers":[
        {
            "category":"Banks & Credit Unions",
            "subcategory":"Investment Brokerage",
            "type":"Services"
        }
    ],
    "sg:phone":"+32 2 411 47 60",
    "sg:postcode":"1081",
    "sg:province":"Bruxelles-Capitale",
    "sg:tags":[
        "printing",
        "-"
    ],
    "wof:name":"Roprint Nv",
    "wof:placetype":"venue"
},
  "geometry": {"coordinates":[4.3267769814,50.8575782776],"type":"Point"}
}