{
  "type": "Feature",
  "properties": {
    "addr:full":"Montegnet 2 Havelange Namur 5370",
    "addr:housenumber":"2",
    "addr:postcode":"5370",
    "addr:street":"Montegnet",
    "iso:country":"BE",
    "sg:address":"Montegnet 2",
    "sg:city":"Havelange",
    "sg:orig_category":"Sportclubs Sportterreinen and installaties behalve sportcentra",
    "sg:phone":"+32 83 63 38 69",
    "sg:postcode":"5370",
    "sg:province":"Namur",
    "wof:name":"R. Entente Flostoy F.c.",
    "wof:placetype":"venue"
},
  "geometry": {"coordinates":[5.1946878433,50.3891067505],"type":"Point"}
}