{
  "type": "Feature",
  "properties": {
    "iso:country":"BE",
    "sg:address":"Rue Saint-alphonse 20-22",
    "sg:city":"La Louvi\u00e8re (str\u00e9py-bracquegnies)",
    "sg:classifiers":[
        {
            "category":"Bars & Pubs",
            "type":"Food & Drink"
        }
    ],
    "sg:phone":"+32 64 66 48 82",
    "sg:postcode":"7110",
    "sg:province":"Hainaut",
    "wof:name":"Caf\u00e9 D'el Fosse",
    "wof:placetype":"venue"
},
  "geometry": {"coordinates":[4.129611969,50.4701576233],"type":"Point"}
}