{
  "type": "Feature",
  "properties": {
    "addr:full":"Pladijsstraat 307 Deerlijk West-Vlaanderen 8540",
    "addr:housenumber":"307",
    "addr:postcode":"8540",
    "addr:street":"Pladijsstraat",
    "iso:country":"BE",
    "sg:address":"Pladijsstraat 307",
    "sg:city":"Deerlijk",
    "sg:classifiers":[
        {
            "category":"Retail",
            "subcategory":"Veterinary Services",
            "type":"Services"
        }
    ],
    "sg:phone":"+32 56 77 76 77",
    "sg:postcode":"8540",
    "sg:province":"West-Vlaanderen",
    "sg:tags":[
        "veterinarian"
    ],
    "wof:name":"Goeminne S",
    "wof:placetype":"venue"
},
  "geometry": {"coordinates":[3.3760359287,50.8226089478],"type":"Point"}
}