{
  "type": "Feature",
  "properties": {
    "iso:country":"BE",
    "sg:address":"Poederstraat 2",
    "sg:city":"Arendonk",
    "sg:classifiers":[
        {
            "category":"Professional",
            "subcategory":"Management & Consulting",
            "type":"Services"
        }
    ],
    "sg:phone":"+32 14 67 88 76",
    "sg:postcode":"2370",
    "sg:province":"Antwerpen",
    "sg:tags":[
        "-",
        "processing",
        "data",
        "consultant"
    ],
    "wof:name":"Robric",
    "wof:placetype":"venue"
},
  "geometry": {"coordinates":[5.1110448837,51.3355751038],"type":"Point"}
}