{
  "type": "Feature",
  "properties": {
    "addr:full":"Hoenderstraat 61 Wetteren Oost-Vlaanderen 9230",
    "addr:housenumber":"61",
    "addr:postcode":"9230",
    "addr:street":"Hoenderstraat",
    "iso:country":"BE",
    "sg:address":"Hoenderstraat 61",
    "sg:city":"Wetteren",
    "sg:orig_category":"Boucheries",
    "sg:phone":"+32 9 369 08 76",
    "sg:postcode":"9230",
    "sg:province":"Oost-Vlaanderen",
    "wof:name":"Erwin Verliefde",
    "wof:placetype":"venue"
},
  "geometry": {"coordinates":[3.8831570148,51.0042724609],"type":"Point"}
}