{
  "type": "Feature",
  "properties": {
    "iso:country":"BE",
    "sg:address":"Rue Des Champs Fleuris 19",
    "sg:city":"Le Roeulx",
    "sg:classifiers":[
        {
            "category":"Health Services",
            "subcategory":"Health Practitioner",
            "type":"Services"
        }
    ],
    "sg:phone":"+32 64 67 30 62",
    "sg:postcode":"7070",
    "sg:province":"Hainaut",
    "sg:tags":[
        "physiotherapist"
    ],
    "wof:name":"Ladeuze G",
    "wof:placetype":"venue"
},
  "geometry": {"coordinates":[4.111787796,50.4962654114],"type":"Point"}
}