{
  "type": "Feature",
  "properties": {
    "addr:full":"Toevluchtweg 2 Nieuwpoort West-Vlaanderen 8620",
    "addr:housenumber":"2",
    "addr:postcode":"8620",
    "addr:street":"Toevluchtweg",
    "iso:country":"BE",
    "sg:address":"Toevluchtweg 2",
    "sg:city":"Nieuwpoort",
    "sg:classifiers":[
        {
            "category":"Food & Beverages",
            "subcategory":"Chocolate",
            "type":"Retail Goods"
        }
    ],
    "sg:phone":"+32 58 23 24 92",
    "sg:postcode":"8620",
    "sg:province":"West-Vlaanderen",
    "wof:name":"Diema's Boerenbrood B.v.b.a.",
    "wof:placetype":"venue"
},
  "geometry": {"coordinates":[2.761605978,51.1288948059],"type":"Point"}
}