{
  "type": "Feature",
  "properties": {
    "addr:full":"Avenue De Jette 364 Jette/jette Bruxelles-Capitale 1090",
    "addr:housenumber":"364",
    "addr:postcode":"1090",
    "addr:street":"Avenue De Jette",
    "iso:country":"BE",
    "sg:address":"Avenue De Jette 364",
    "sg:city":"Jette/jette",
    "sg:orig_category":"Entretien and r\u00e9parations de voitures. V\u00e9hicules automobiles",
    "sg:phone":"+32 2 425 14 88",
    "sg:postcode":"1090",
    "sg:province":"Bruxelles-Capitale",
    "wof:name":"Garage Autoformalit\u00c9s",
    "wof:placetype":"venue"
},
  "geometry": {"coordinates":[4.3215899467,50.8747711182],"type":"Point"}
}