{
  "type": "Feature",
  "properties": {
    "addr:full":"Eerselseweg 100 Mol Antwerpen 2400",
    "addr:housenumber":"100",
    "addr:postcode":"2400",
    "addr:street":"Eerselseweg",
    "iso:country":"BE",
    "sg:address":"Eerselseweg 100",
    "sg:city":"Mol",
    "sg:classifiers":[
        {
            "category":"Bars & Pubs",
            "subcategory":"Nightclub",
            "type":"Food & Drink"
        }
    ],
    "sg:phone":"+32 14 37 74 45",
    "sg:postcode":"2400",
    "sg:province":"Antwerpen",
    "sg:tags":[
        "nachtclubs",
        "dancing"
    ],
    "wof:name":"Discotheek Heidelicht",
    "wof:placetype":"venue"
},
  "geometry": {"coordinates":[5.2330508232,51.2995872498],"type":"Point"}
}