{
  "type": "Feature",
  "properties": {
    "addr:full":"Hoekstraat 26 Brecht Antwerpen 2960",
    "addr:housenumber":"26",
    "addr:postcode":"2960",
    "addr:street":"Hoekstraat",
    "iso:country":"BE",
    "sg:address":"Hoekstraat 26",
    "sg:city":"Brecht",
    "sg:orig_category":"Antiquit\u00e9s. Ramassage and traitement des d\u00e9chets m\u00e9nagers. Biens d'occasion. D\u00e9molition d\u00b4immeubles ",
    "sg:phone":"+32 3 313 95 13",
    "sg:postcode":"2960",
    "sg:province":"Antwerpen",
    "wof:name":"Snoeys Achille",
    "wof:placetype":"venue"
},
  "geometry": {"coordinates":[4.6193709373,51.3574562073],"type":"Point"}
}