{
  "type": "Feature",
  "properties": {
    "iso:country":"BE",
    "sg:address":"Kortrijksestraat 81",
    "sg:city":"Kuurne",
    "sg:classifiers":[
        {
            "category":"Cafe",
            "type":"Food & Drink"
        }
    ],
    "sg:phone":"+32 56 72 73 73",
    "sg:postcode":"8520",
    "sg:province":"West-Vlaanderen",
    "sg:tags":[
        "caf\u00e9s"
    ],
    "wof:name":"Kuurnse Watersportver.",
    "wof:placetype":"venue"
},
  "geometry": {"coordinates":[3.280039072,50.8474655151],"type":"Point"}
}