{
  "type": "Feature",
  "properties": {
    "addr:full":"Pieter Deswartelaan 8 Nieuwpoort West-Vlaanderen 8620",
    "addr:housenumber":"8",
    "addr:postcode":"8620",
    "addr:street":"Pieter Deswartelaan",
    "iso:country":"BE",
    "sg:address":"Pieter Deswartelaan 8",
    "sg:city":"Nieuwpoort",
    "sg:classifiers":[
        {
            "category":"Retail",
            "subcategory":"Repair Shop",
            "type":"Services"
        }
    ],
    "sg:phone":"+32 58 23 50 64",
    "sg:postcode":"8620",
    "sg:province":"West-Vlaanderen",
    "sg:tags":[
        "mainten",
        "-",
        "parquet"
    ],
    "wof:name":"Rossey Bvba",
    "wof:placetype":"venue"
},
  "geometry": {"coordinates":[2.7565500736,51.132724762],"type":"Point"}
}