{
  "type": "Feature",
  "properties": {
    "iso:country":"BE",
    "sg:address":"Rue Vert Vin\u00e2ve 89",
    "sg:city":"Gr\u00e2ce-hollogne (gr\u00e2ce-berleur)",
    "sg:orig_category":"Ice-cream parlours",
    "sg:phone":"+32 4 234 00 85",
    "sg:postcode":"4460",
    "sg:province":"Li\u00e8ge",
    "wof:name":"L\u00e9onard Glacier",
    "wof:placetype":"venue"
},
  "geometry": {"coordinates":[5.4991440773,50.6382904053],"type":"Point"}
}