{
  "type": "Feature",
  "properties": {
    "addr:full":"Kerkeneind 4 Kalmthout Antwerpen 2920",
    "addr:housenumber":"4",
    "addr:postcode":"2920",
    "addr:street":"Kerkeneind",
    "iso:country":"BE",
    "sg:address":"Kerkeneind 4",
    "sg:city":"Kalmthout",
    "sg:orig_category":"Banken and kredietinstellingen",
    "sg:phone":"+32 3 666 60 58",
    "sg:postcode":"2920",
    "sg:province":"Antwerpen",
    "wof:name":"Kbc",
    "wof:placetype":"venue"
},
  "geometry": {"coordinates":[4.4769778252,51.3846702576],"type":"Point"}
}