{
  "type": "Feature",
  "properties": {
    "iso:country":"BE",
    "sg:address":"Rue De Sas 81ba",
    "sg:city":"Saint-ghislain",
    "sg:orig_category":"Entretien and r\u00e9parations de voitures",
    "sg:phone":"+32 65 60 03 37",
    "sg:postcode":"7330",
    "sg:province":"Hainaut",
    "wof:name":"Garage Piscina",
    "wof:placetype":"venue"
},
  "geometry": {"coordinates":[3.8145000935,50.4494895935],"type":"Point"}
}