{
  "type": "Feature",
  "properties": {
    "iso:country":"BE",
    "sg:address":"Breendonkdorp 94",
    "sg:city":"Puurs",
    "sg:orig_category":"Enseignement maternel and primaire",
    "sg:phone":"+32 3 886 50 30",
    "sg:postcode":"2870",
    "sg:province":"Antwerpen",
    "wof:name":"Vrije Basisschool",
    "wof:placetype":"venue"
},
  "geometry": {"coordinates":[4.3259887695,51.0452651978],"type":"Point"}
}