{
  "type": "Feature",
  "properties": {
    "addr:full":"Turkeyenhoeklos 2 Nazareth Oost-Vlaanderen 9810",
    "addr:housenumber":"2",
    "addr:postcode":"9810",
    "addr:street":"Turkeyenhoeklos",
    "iso:country":"BE",
    "sg:address":"Turkeyenhoeklos 2",
    "sg:city":"Nazareth",
    "sg:orig_category":"Plomberie, chauffage and installations sanitaires",
    "sg:phone":"+32 9 384 20 42",
    "sg:postcode":"9810",
    "sg:province":"Oost-Vlaanderen",
    "wof:name":"Martin Dhondt",
    "wof:placetype":"venue"
},
  "geometry": {"coordinates":[3.5967800617,50.9596405029],"type":"Point"}
}