{
  "type": "Feature",
  "properties": {
    "iso:country":"BE",
    "sg:address":"Aarschotsebaan 75",
    "sg:city":"Kampenhout",
    "sg:classifiers":[
        {
            "category":"Insurance",
            "subcategory":"Insurance Agent",
            "type":"Services"
        }
    ],
    "sg:phone":"+32 16 65 18 92",
    "sg:postcode":"1910",
    "sg:province":"Vlaams-Brabant",
    "sg:tags":[
        "broker"
    ],
    "wof:name":"Van Steenweghen Bvba",
    "wof:placetype":"venue"
},
  "geometry": {"coordinates":[4.5828609467,50.9444999695],"type":"Point"}
}