{
  "type": "Feature",
  "properties": {
    "addr:full":"Jourdanplein 55 Etterbeek/etterbeek Bruxelles-Capitale 1040",
    "addr:housenumber":"55",
    "addr:postcode":"1040",
    "addr:street":"Jourdanplein",
    "iso:country":"BE",
    "sg:address":"Jourdanplein 55",
    "sg:city":"Etterbeek/etterbeek",
    "sg:orig_category":"Kruideniers Supermarkten",
    "sg:phone":"+32 2 231 08 95",
    "sg:postcode":"1040",
    "sg:province":"Bruxelles-Capitale",
    "wof:name":"Gb Contact",
    "wof:placetype":"venue"
},
  "geometry": {"coordinates":[4.3810777664,50.8370628357],"type":"Point"}
}