{
  "type": "Feature",
  "properties": {
    "addr:full":"Rue Louis-boumal 12 Li\u00c8ge Li\u00e8ge 4000",
    "addr:housenumber":"12",
    "addr:postcode":"4000",
    "addr:street":"Rue Louis-Boumal",
    "iso:country":"BE",
    "sg:address":"Rue Louis-boumal 12",
    "sg:city":"Li\u00c8ge",
    "sg:orig_category":"Kleding Maatkleding Fab",
    "sg:phone":"+32 4 252 50 70",
    "sg:postcode":"4000",
    "sg:province":"Li\u00e8ge",
    "wof:name":"Robert Weber",
    "wof:placetype":"venue"
},
  "geometry": {"coordinates":[5.5588722229,50.6336708069],"type":"Point"}
}