{
  "type": "Feature",
  "properties": {
    "addr:full":"Rue Basses-voies 127 Libin Luxembourg 6890",
    "addr:housenumber":"127",
    "addr:postcode":"6890",
    "addr:street":"Rue Basses-Voies",
    "iso:country":"BE",
    "sg:address":"Rue Basses-voies 127",
    "sg:city":"Libin",
    "sg:orig_category":"Eleveurs de bovins",
    "sg:phone":"+32 61 65 53 57",
    "sg:postcode":"6890",
    "sg:province":"Luxembourg",
    "wof:name":"Joseph Henry",
    "wof:placetype":"venue"
},
  "geometry": {"coordinates":[5.2605438232,49.9782409668],"type":"Point"}
}