{
  "type": "Feature",
  "properties": {
    "iso:country":"BE",
    "sg:address":"Chemin Du Trainage",
    "sg:city":"Hensies",
    "sg:classifiers":[
        {
            "category":"Utilities",
            "subcategory":"Refuse",
            "type":"Services"
        }
    ],
    "sg:phone":"+32 65 66 95 97",
    "sg:postcode":"7350",
    "sg:province":"Hainaut",
    "sg:tags":[
        "management",
        "waste"
    ],
    "wof:name":"Spaque",
    "wof:placetype":"venue"
},
  "geometry": {"coordinates":[3.6802139282,50.4439849854],"type":"Point"}
}