{
  "type": "Feature",
  "properties": {
    "addr:full":"Eeckbergstraat 62 Sint-gillis-waas Oost-Vlaanderen 9170",
    "addr:housenumber":"62",
    "addr:postcode":"9170",
    "addr:street":"Eeckbergstraat",
    "iso:country":"BE",
    "sg:address":"Eeckbergstraat 62",
    "sg:city":"Sint-gillis-waas",
    "sg:orig_category":"Transports routiers de marchandises",
    "sg:phone":"+32 3 770 50 31",
    "sg:postcode":"9170",
    "sg:province":"Oost-Vlaanderen",
    "wof:name":"Tack D",
    "wof:placetype":"venue"
},
  "geometry": {"coordinates":[4.1197018623,51.2397460938],"type":"Point"}
}