{
  "type": "Feature",
  "properties": {
    "iso:country":"BE",
    "sg:address":"Winterbeeklaan 37",
    "sg:city":"Genk",
    "sg:orig_category":"Transports routiers de marchandises",
    "sg:phone":"+32 89 30 61 43",
    "sg:postcode":"3600",
    "sg:province":"Limburg",
    "wof:name":"Transcoma",
    "wof:placetype":"venue"
},
  "geometry": {"coordinates":[5.4625849724,50.9400596619],"type":"Point"}
}