{
  "type": "Feature",
  "properties": {
    "addr:full":"Rondplein 11 Meise Vlaams-Brabant 1860",
    "addr:housenumber":"11",
    "addr:postcode":"1860",
    "addr:street":"Rondplein",
    "iso:country":"BE",
    "sg:address":"Rondplein 11",
    "sg:city":"Meise",
    "sg:classifiers":[
        {
            "category":"Autos & Motor Vehicles",
            "subcategory":"Fuel & Gas Station",
            "type":"Retail Goods"
        }
    ],
    "sg:phone":"+32 2 269 07 06",
    "sg:postcode":"1860",
    "sg:province":"Vlaams-Brabant",
    "wof:name":"Q8-lomme",
    "wof:placetype":"venue"
},
  "geometry": {"coordinates":[4.3299398422,50.9351844788],"type":"Point"}
}