{
  "type": "Feature",
  "properties": {
    "addr:full":"Bivak Berkendreef Neerpelt Limburg 3910",
    "addr:postcode":"3910",
    "addr:street":"Bivak Berkendreef",
    "iso:country":"BE",
    "sg:address":"Bivak Berkendreef",
    "sg:city":"Neerpelt",
    "sg:orig_category":"Activit\u00e9s r\u00e9cr\u00e9atives diverses",
    "sg:phone":"+32 11 64 46 31",
    "sg:postcode":"3910",
    "sg:province":"Limburg",
    "wof:name":"Scoutsrally",
    "wof:placetype":"venue"
},
  "geometry": {"coordinates":[5.4115958214,51.2319908142],"type":"Point"}
}