{
  "type": "Feature",
  "properties": {
    "iso:country":"BE",
    "sg:address":"Rue Catalogne 122",
    "sg:city":"Villers-la-ville",
    "sg:classifiers":[
        {
            "category":"Insurance",
            "subcategory":"Life Insurance",
            "type":"Services"
        }
    ],
    "sg:phone":"+32 71 87 98 94",
    "sg:postcode":"1495",
    "sg:province":"Brabant Wallon",
    "sg:tags":[
        "assurance"
    ],
    "wof:name":"M. Wattiaux",
    "wof:placetype":"venue"
},
  "geometry": {"coordinates":[4.530477047,50.5786132812],"type":"Point"}
}