{
  "type": "Feature",
  "properties": {
    "addr:full":"Hoogte Honderdplein 19 Vorst/forest Bruxelles-Capitale 1190",
    "addr:housenumber":"19",
    "addr:postcode":"1190",
    "addr:street":"Hoogte Honderdplein;/ Forest",
    "iso:country":"BE",
    "sg:address":"Hoogte Honderdplein 19",
    "sg:city":"Vorst/forest",
    "sg:orig_category":"Bloemen and planten",
    "sg:phone":"+32 2 343 53 56",
    "sg:postcode":"1190",
    "sg:province":"Bruxelles-Capitale",
    "wof:name":"Louise Fleurs",
    "wof:placetype":"venue"
},
  "geometry": {"coordinates":[4.3365540504,50.8170852661],"type":"Point"}
}