{
  "type": "Feature",
  "properties": {
    "addr:full":"Moerstraat 9 Kaprijke Oost-Vlaanderen 9970",
    "addr:housenumber":"9",
    "addr:postcode":"9970",
    "addr:street":"Moerstraat",
    "iso:country":"BE",
    "sg:address":"Moerstraat 9",
    "sg:city":"Kaprijke",
    "sg:orig_category":"Installatie van metalen schrijnwerk",
    "sg:phone":"+32 9 377 82 69",
    "sg:postcode":"9970",
    "sg:province":"Oost-Vlaanderen",
    "wof:name":"Du Puy Metaalconstructie",
    "wof:placetype":"venue"
},
  "geometry": {"coordinates":[3.5769100189,51.2193984985],"type":"Point"}
}