{
  "type": "Feature",
  "properties": {
    "iso:country":"BE",
    "sg:address":"Bld De La Sauveni\u00c8re 134",
    "sg:city":"Li\u00c8ge",
    "sg:orig_category":"M\u00e9decins and sp\u00e9cialistes. Centres sportifs",
    "sg:phone":"+32 4 367 17 40",
    "sg:postcode":"4000",
    "sg:province":"Li\u00e8ge",
    "wof:name":"Centre De Yoga Et Massage Asbl",
    "wof:placetype":"venue"
},
  "geometry": {"coordinates":[5.566411972,50.6417388916],"type":"Point"}
}