{
  "type": "Feature",
  "properties": {
    "addr:full":"Beveldorp 99 Nijlen Antwerpen 2560",
    "addr:housenumber":"99",
    "addr:postcode":"2560",
    "addr:street":"Beveldorp",
    "iso:country":"BE",
    "sg:address":"Beveldorp 99",
    "sg:city":"Nijlen",
    "sg:orig_category":"Huisdieren and benodigdheden",
    "sg:phone":"+32 3 411 12 08",
    "sg:postcode":"2560",
    "sg:province":"Antwerpen",
    "wof:name":"Cattery De Pallieter",
    "wof:placetype":"venue"
},
  "geometry": {"coordinates":[4.6839280128,51.1364326477],"type":"Point"}
}