{
  "type": "Feature",
  "properties": {
    "iso:country":"BE",
    "sg:address":"Eendenweg 5",
    "sg:city":"Lokeren (eksaarde)",
    "sg:classifiers":[
        {
            "category":"Personal",
            "subcategory":"Beauty Salon",
            "type":"Services"
        }
    ],
    "sg:phone":"+32 9 348 88 35",
    "sg:postcode":"9160",
    "sg:province":"Oost-Vlaanderen",
    "sg:tags":[
        "lady",
        "-",
        "hairdressing"
    ],
    "wof:name":"Eveline Kapster",
    "wof:placetype":"venue"
},
  "geometry": {"coordinates":[3.9864850044,51.1047401428],"type":"Point"}
}