{
  "type": "Feature",
  "properties": {
    "addr:full":"Place Aux Foires 22 Marche-en-famenne Luxembourg 6900",
    "addr:housenumber":"22",
    "addr:postcode":"6900",
    "addr:street":"Place Aux Foires",
    "iso:country":"BE",
    "sg:address":"Place Aux Foires 22",
    "sg:city":"Marche-en-famenne",
    "sg:classifiers":[
        {
            "category":"Bars & Pubs",
            "type":"Food & Drink"
        }
    ],
    "sg:phone":"+32 496 53 65 07",
    "sg:postcode":"6900",
    "sg:province":"Luxembourg",
    "wof:name":"Infiniment...songe (l')",
    "wof:placetype":"venue"
},
  "geometry": {"coordinates":[5.3450741768,50.2258338928],"type":"Point"}
}