{
  "type": "Feature",
  "properties": {
    "iso:country":"BE",
    "sg:address":"Voie Des Chars 64",
    "sg:city":"Chaudfontaine",
    "sg:orig_category":"Artsen and specialisten",
    "sg:phone":"+32 4 368 81 13",
    "sg:postcode":"4050",
    "sg:province":"Li\u00e8ge",
    "wof:name":"Alain Troisfontaines",
    "wof:placetype":"venue"
},
  "geometry": {"coordinates":[5.6360940933,50.5833282471],"type":"Point"}
}