{
  "type": "Feature",
  "properties": {
    "addr:full":"Wayenborgstraat 12 Mechelen Antwerpen 2800",
    "addr:housenumber":"12",
    "addr:postcode":"2800",
    "addr:street":"Wayenborgstraat",
    "iso:country":"BE",
    "sg:address":"Wayenborgstraat 12",
    "sg:city":"Mechelen",
    "sg:classifiers":[
        {
            "category":"Social Services",
            "subcategory":"Job Training",
            "type":"Services"
        }
    ],
    "sg:phone":"+32 15 21 09 75",
    "sg:postcode":"2800",
    "sg:province":"Antwerpen",
    "sg:tags":[
        "condiment",
        "spice"
    ],
    "wof:name":"Verstegen Specerijen Nv",
    "wof:placetype":"venue"
},
  "geometry": {"coordinates":[4.4428911209,51.0495643616],"type":"Point"}
}