{
  "type": "Feature",
  "properties": {
    "addr:full":"Westlaan 321 Heusden-zolder Limburg 3550",
    "addr:housenumber":"321",
    "addr:postcode":"3550",
    "addr:street":"Westlaan",
    "iso:country":"BE",
    "sg:address":"Westlaan 321",
    "sg:city":"Heusden-zolder",
    "sg:orig_category":"Industri\u00eble elektrische installaties",
    "sg:phone":"+32 13 53 18 90",
    "sg:postcode":"3550",
    "sg:province":"Limburg",
    "wof:name":"Lifttechnisch Bureau",
    "wof:placetype":"venue"
},
  "geometry": {"coordinates":[5.2378678322,50.9963912964],"type":"Point"}
}