{
  "type": "Feature",
  "properties": {
    "addr:full":"Roosterkensweg 33 Zonhoven Limburg 3520",
    "addr:housenumber":"33",
    "addr:postcode":"3520",
    "addr:street":"Roosterkensweg",
    "iso:country":"BE",
    "sg:address":"Roosterkensweg 33",
    "sg:city":"Zonhoven",
    "sg:orig_category":"Gespecialiseerde residenti\u00eble bouw",
    "sg:phone":"+32 11 81 88 34",
    "sg:postcode":"3520",
    "sg:province":"Limburg",
    "wof:name":"Freddy Jaspers",
    "wof:placetype":"venue"
},
  "geometry": {"coordinates":[5.3517489433,50.9953155518],"type":"Point"}
}