{
  "type": "Feature",
  "properties": {
    "addr:full":"Machelenbinnenweg 5 Deinze (petegem-aan-de-leie) Oost-Vlaanderen 9800",
    "addr:housenumber":"5",
    "addr:postcode":"9800",
    "addr:street":"Machelenbinnenweg;Oost-Vlaanderen",
    "iso:country":"BE",
    "sg:address":"Machelenbinnenweg 5",
    "sg:city":"Deinze (petegem-aan-de-leie)",
    "sg:classifiers":[
        {
            "category":"Community Center",
            "subcategory":"Social",
            "type":"Public Place"
        }
    ],
    "sg:phone":"+32 9 386 31 63",
    "sg:postcode":"9800",
    "sg:province":"Oost-Vlaanderen",
    "sg:tags":[
        "polishing",
        "abrasive",
        "compound"
    ],
    "wof:name":"Ufttools Bvba",
    "wof:placetype":"venue"
},
  "geometry": {"coordinates":[3.530174017,50.9863166809],"type":"Point"}
}