{
  "type": "Feature",
  "properties": {
    "iso:country":"BE",
    "sg:address":"Waterloose Steenweg 880",
    "sg:city":"Brussel/bruxelles",
    "sg:orig_category":"Werk and personeelsselectie",
    "sg:phone":"+32 2 375 89 33",
    "sg:postcode":"1000",
    "sg:province":"Bruxelles-Capitale",
    "wof:name":"Bureau Succes",
    "wof:placetype":"venue"
},
  "geometry": {"coordinates":[4.3721342087,50.8052902222],"type":"Point"}
}