{
  "type": "Feature",
  "properties": {
    "addr:full":"Rue De Tabora 13 Brussel/bruxelles Bruxelles-Capitale 1000",
    "addr:housenumber":"13",
    "addr:postcode":"1000",
    "addr:street":"Rue De Tabora;/",
    "iso:country":"BE",
    "sg:address":"Rue De Tabora 13",
    "sg:city":"Brussel/bruxelles",
    "sg:orig_category":"Equipement photographique. Studios photographiques",
    "sg:phone":"+32 2 512 73 32",
    "sg:postcode":"1000",
    "sg:province":"Bruxelles-Capitale",
    "wof:name":"River",
    "wof:placetype":"venue"
},
  "geometry": {"coordinates":[4.3512239456,50.8480491638],"type":"Point"}
}