{
  "type": "Feature",
  "properties": {
    "iso:country":"BE",
    "sg:address":"Rue Du Brochet 55",
    "sg:city":"Bruxelles (ixelles)",
    "sg:classifiers":[
        {
            "category":"Professional",
            "type":"Services"
        }
    ],
    "sg:phone":"+32 2 647 68 78",
    "sg:postcode":"1050",
    "sg:province":"Bruxelles-Capitale",
    "sg:tags":[
        "entertainer"
    ],
    "wof:name":"Un Oeuf Is Un Oeuf",
    "wof:placetype":"venue"
},
  "geometry": {"coordinates":[4.3811979294,50.8329429626],"type":"Point"}
}