{
  "type": "Feature",
  "properties": {
    "iso:country":"BE",
    "sg:address":"Ruddervoordestraat 143",
    "sg:city":"Torhout",
    "sg:orig_category":"Artistes ind\u00e9pendants",
    "sg:phone":"+32 50 21 37 80",
    "sg:postcode":"8820",
    "sg:province":"West-Vlaanderen",
    "wof:name":"Dwin Versmesse",
    "wof:placetype":"venue"
},
  "geometry": {"coordinates":[3.1187670231,51.0646400452],"type":"Point"}
}