{
  "type": "Feature",
  "properties": {
    "iso:country":"BE",
    "sg:address":"Groene Wandeling 11",
    "sg:city":"Waregem",
    "sg:classifiers":[
        {
            "category":"Sports & Exercise",
            "subcategory":"Gym",
            "type":"Entertainment"
        }
    ],
    "sg:phone":"+32 56 60 90 25",
    "sg:postcode":"8790",
    "sg:province":"West-Vlaanderen",
    "sg:tags":[
        "fitness"
    ],
    "wof:name":"Groene Wandeling",
    "wof:placetype":"venue"
},
  "geometry": {"coordinates":[3.4134230614,50.8876228333],"type":"Point"}
}