{
  "type": "Feature",
  "properties": {
    "addr:full":"Boomstraat 27 Bornem Antwerpen 2880",
    "addr:housenumber":"27",
    "addr:postcode":"2880",
    "addr:street":"Boomstraat",
    "iso:country":"BE",
    "sg:address":"Boomstraat 27",
    "sg:city":"Bornem",
    "sg:orig_category":"Brood, gebak and snoepgoed",
    "sg:phone":"+32 3 899 27 41",
    "sg:postcode":"2880",
    "sg:province":"Antwerpen",
    "wof:name":"Huis Deldiche",
    "wof:placetype":"venue"
},
  "geometry": {"coordinates":[4.2340011597,51.0985603333],"type":"Point"}
}