{
  "type": "Feature",
  "properties": {
    "iso:country":"BE",
    "sg:address":"Coenstraat 7",
    "sg:city":"Opwijk",
    "sg:orig_category":"Projectontwikkelaars",
    "sg:phone":"+32 52 35 69 51",
    "sg:postcode":"1745",
    "sg:province":"Vlaams-Brabant",
    "wof:name":"Jokebat",
    "wof:placetype":"venue"
},
  "geometry": {"coordinates":[4.1553649902,50.9718513489],"type":"Point"}
}