{
  "type": "Feature",
  "properties": {
    "addr:full":"Brusselsesteenweg 55 Tervuren Vlaams-Brabant 3080",
    "addr:housenumber":"55",
    "addr:postcode":"3080",
    "addr:street":"Brusselsesteenweg",
    "iso:country":"BE",
    "sg:address":"Brusselsesteenweg 55",
    "sg:city":"Tervuren",
    "sg:classifiers":[
        {
            "category":"Shopping",
            "subcategory":"Clothing, Apparel, & Fashions",
            "type":"Retail Goods"
        }
    ],
    "sg:phone":"+32 2 767 33 81",
    "sg:postcode":"3080",
    "sg:province":"Vlaams-Brabant",
    "sg:tags":[
        "underwear",
        "lingerie",
        "-"
    ],
    "wof:name":"Belladonna",
    "wof:placetype":"venue"
},
  "geometry": {"coordinates":[4.5096030235,50.8247718811],"type":"Point"}
}