{
  "type": "Feature",
  "properties": {
    "iso:country":"BE",
    "sg:address":"Keekstraat 1",
    "sg:city":"Kinrooi",
    "sg:orig_category":"Producteurs de l\u00e9gumes",
    "sg:phone":"+32 89 56 85 49",
    "sg:postcode":"3640",
    "sg:province":"Limburg",
    "wof:name":"Bernardus Van Wonderen",
    "wof:placetype":"venue"
},
  "geometry": {"coordinates":[5.7684102058,51.1307029724],"type":"Point"}
}