{
  "type": "Feature",
  "properties": {
    "addr:full":"Rue Strivay 30 Neupr\u00e9 (plainevaux) Li\u00e8ge 4122",
    "addr:housenumber":"30",
    "addr:postcode":"4122",
    "addr:street":"Rue Strivay;Plainevaux",
    "iso:country":"BE",
    "sg:address":"Rue Strivay 30",
    "sg:city":"Neupr\u00e9 (plainevaux)",
    "sg:classifiers":[
        {
            "category":"Professional",
            "subcategory":"Accounting & Tax Preparation",
            "type":"Services"
        }
    ],
    "sg:phone":"+32 4 380 54 75",
    "sg:postcode":"4122",
    "sg:province":"Li\u00e8ge",
    "sg:tags":[
        "bookkeeper"
    ],
    "wof:name":"Cogeco conseils Gestion Comptabilit\u00e9",
    "wof:placetype":"venue"
},
  "geometry": {"coordinates":[5.5326700211,50.5376091003],"type":"Point"}
}