{
  "type": "Feature",
  "properties": {
    "addr:full":"Provemseweg 90 B Poperinge West-Vlaanderen 8970",
    "addr:housenumber":"90 b",
    "addr:postcode":"8970",
    "addr:street":"Provemseweg",
    "iso:country":"BE",
    "sg:address":"Provemseweg 90 B",
    "sg:city":"Poperinge",
    "sg:orig_category":"Winkelinrichting and handelsuitrusting Gh",
    "sg:phone":"+32 57 33 40 07",
    "sg:postcode":"8970",
    "sg:province":"West-Vlaanderen",
    "wof:name":"Cobeltab",
    "wof:placetype":"venue"
},
  "geometry": {"coordinates":[2.6975450516,50.8601799011],"type":"Point"}
}