{
  "type": "Feature",
  "properties": {
    "addr:full":"Everaertsstraat 32 Antwerpen Antwerpen 2060",
    "addr:housenumber":"32",
    "addr:postcode":"2060",
    "addr:street":"Everaertsstraat",
    "iso:country":"BE",
    "sg:address":"Everaertsstraat 32",
    "sg:city":"Antwerpen",
    "sg:classifiers":[
        {
            "category":"Professional",
            "subcategory":"Advertising",
            "type":"Services"
        }
    ],
    "sg:phone":"+32 3 234 00 68",
    "sg:postcode":"2060",
    "sg:province":"Antwerpen",
    "sg:tags":[
        "studio"
    ],
    "wof:name":"Atoz Nv",
    "wof:placetype":"venue"
},
  "geometry": {"coordinates":[4.4234042168,51.2267723083],"type":"Point"}
}