{
  "type": "Feature",
  "properties": {
    "addr:full":"Waalstraat 91 Zulte Oost-Vlaanderen 9870",
    "addr:housenumber":"91",
    "addr:postcode":"9870",
    "addr:street":"Waalstraat",
    "iso:country":"BE",
    "sg:address":"Waalstraat 91",
    "sg:city":"Zulte",
    "sg:classifiers":[
        {
            "category":"Health Services",
            "subcategory":"Dentist",
            "type":"Services"
        }
    ],
    "sg:phone":"+32 9 388 72 45",
    "sg:postcode":"9870",
    "sg:province":"Oost-Vlaanderen",
    "wof:name":"Simoens Ignace",
    "wof:placetype":"venue"
},
  "geometry": {"coordinates":[3.4502220154,50.9198379517],"type":"Point"}
}