{
  "type": "Feature",
  "properties": {
    "addr:full":"Stationspln 21 Lokeren Oost-Vlaanderen 9100",
    "addr:housenumber":"21",
    "addr:postcode":"9100",
    "addr:street":"Stationspln",
    "iso:country":"BE",
    "sg:address":"Stationspln 21",
    "sg:city":"Lokeren",
    "sg:classifiers":[
        {
            "category":"Banks & Credit Unions",
            "subcategory":"Bank",
            "type":"Services"
        }
    ],
    "sg:phone":"+32 91484858",
    "sg:postcode":"9100",
    "sg:province":"Oost-Vlaanderen",
    "wof:name":"Aslk-cger Bank",
    "wof:placetype":"venue"
},
  "geometry": {"coordinates":[3.9887259007,51.1078643799],"type":"Point"}
}