{
  "type": "Feature",
  "properties": {
    "iso:country":"BE",
    "sg:address":"Vrijheid 144",
    "sg:city":"Hoogstraten",
    "sg:orig_category":"Herstelling leer and schoeisel",
    "sg:phone":"+32 3 314 36 70",
    "sg:postcode":"2320",
    "sg:province":"Antwerpen",
    "wof:name":"Quick Service",
    "wof:placetype":"venue"
},
  "geometry": {"coordinates":[4.7618479729,51.4028587341],"type":"Point"}
}