{
  "type": "Feature",
  "properties": {
    "iso:country":"BE",
    "sg:address":"Rue De La Hulpe 82a",
    "sg:city":"Rixensart (rosi\u00e8res)",
    "sg:orig_category":"Non-Classified Establishments",
    "sg:postcode":"1331",
    "sg:province":"Brabant Wallon",
    "wof:name":"Batavus (belgie)",
    "wof:placetype":"venue"
},
  "geometry": {"coordinates":[5.9290947914,52.9584503174],"type":"Point"}
}