{
  "type": "Feature",
  "properties": {
    "addr:full":"Selsaetentuinwijk 40 Wommelgem Antwerpen 2160",
    "addr:housenumber":"40",
    "addr:postcode":"2160",
    "addr:street":"Selsaetentuinwijk",
    "iso:country":"BE",
    "sg:address":"Selsaetentuinwijk 40",
    "sg:city":"Wommelgem",
    "sg:orig_category":"Verhuur kantoormateriaal",
    "sg:phone":"+32 3 354 37 48",
    "sg:postcode":"2160",
    "sg:province":"Antwerpen",
    "wof:name":"Antwerp Mobilophone Renting",
    "wof:placetype":"venue"
},
  "geometry": {"coordinates":[4.539121151,51.199508667],"type":"Point"}
}