{
  "type": "Feature",
  "properties": {
    "addr:full":"Waversebaan 222 Oud-heverlee Vlaams-Brabant 3050",
    "addr:housenumber":"222",
    "addr:postcode":"3050",
    "addr:street":"Waversebaan",
    "iso:country":"BE",
    "sg:address":"Waversebaan 222",
    "sg:city":"Oud-heverlee",
    "sg:classifiers":[
        {
            "category":"Banks & Credit Unions",
            "subcategory":"Investment Brokerage",
            "type":"Services"
        }
    ],
    "sg:phone":"+32 16 47 40 47",
    "sg:postcode":"3050",
    "sg:province":"Vlaams-Brabant",
    "sg:tags":[
        "fence"
    ],
    "wof:name":"Alba ('l)",
    "wof:placetype":"venue"
},
  "geometry": {"coordinates":[4.6559028625,50.8280563354],"type":"Point"}
}