{
  "type": "Feature",
  "properties": {
    "iso:country":"BE",
    "sg:address":"Plantinlaan 3ba",
    "sg:city":"Stabroek",
    "sg:orig_category":"Artsen and specialisten",
    "sg:phone":"+32 3 664 11 74",
    "sg:postcode":"2940",
    "sg:province":"Antwerpen",
    "wof:name":"W. Van Den Eede",
    "wof:placetype":"venue"
},
  "geometry": {"coordinates":[4.3916420937,51.3550872803],"type":"Point"}
}