{
  "type": "Feature",
  "properties": {
    "addr:full":"Vleurgatsesteenweg 154 Brussel/bruxelles Bruxelles-Capitale 1000",
    "addr:housenumber":"154",
    "addr:postcode":"1000",
    "addr:street":"Vleurgatsesteenweg;/",
    "iso:country":"BE",
    "sg:address":"Vleurgatsesteenweg 154",
    "sg:city":"Brussel/bruxelles",
    "sg:classifiers":[
        {
            "category":"Travel",
            "subcategory":"Hotels & Motels",
            "type":"Entertainment"
        }
    ],
    "sg:phone":"+32 2 648 53 30",
    "sg:postcode":"1000",
    "sg:province":"Bruxelles-Capitale",
    "sg:tags":[
        "restaurant"
    ],
    "wof:name":"H\u00d4tel Wellington",
    "wof:placetype":"venue"
},
  "geometry": {"coordinates":[4.3671760559,50.8226699829],"type":"Point"}
}