{
  "type": "Feature",
  "properties": {
    "iso:country":"BE",
    "sg:address":"Boulevard De L'europe 3",
    "sg:city":"Wavre (bierges)",
    "sg:classifiers":[
        {
            "category":"Retail",
            "subcategory":"Repair Shop",
            "type":"Services"
        }
    ],
    "sg:phone":"+32 10 22 47 43",
    "sg:postcode":"1301",
    "sg:province":"Brabant Wallon",
    "sg:tags":[
        "photographic",
        "equipment",
        "-",
        "accessory"
    ],
    "wof:name":"Wavre (bierges) Maxi Gb",
    "wof:placetype":"venue"
},
  "geometry": {"coordinates":[4.6100921631,50.7142791748],"type":"Point"}
}