{
  "type": "Feature",
  "properties": {
    "addr:full":"Rue Henri Stacquet 27 Bruxelles (schaerbeek) Bruxelles-Capitale 1030",
    "addr:housenumber":"27",
    "addr:postcode":"1030",
    "addr:street":"Rue Henri Stacquet",
    "iso:country":"BE",
    "sg:address":"Rue Henri Stacquet 27",
    "sg:city":"Bruxelles (schaerbeek)",
    "sg:classifiers":[
        {
            "category":"Health Services",
            "subcategory":"Health Practitioner",
            "type":"Services"
        }
    ],
    "sg:phone":"+32 2 732 63 73",
    "sg:postcode":"1030",
    "sg:province":"Bruxelles-Capitale",
    "sg:tags":[
        "physiotherapist"
    ],
    "wof:name":"Deversain V",
    "wof:placetype":"venue"
},
  "geometry": {"coordinates":[4.3889479637,50.8578262329],"type":"Point"}
}