{
  "type": "Feature",
  "properties": {
    "iso:country":"BE",
    "sg:address":"Weteringstraat 17",
    "sg:city":"Ravels",
    "sg:orig_category":"Schoonheidssalons",
    "sg:phone":"+32 14 65 61 78",
    "sg:postcode":"2380",
    "sg:province":"Antwerpen",
    "wof:name":"Pascale Lodewijks",
    "wof:placetype":"venue"
},
  "geometry": {"coordinates":[4.9951500893,51.368724823],"type":"Point"}
}