{
  "type": "Feature",
  "properties": {
    "addr:full":"Stift 2 Bree Limburg 3960",
    "addr:housenumber":"2",
    "addr:postcode":"3960",
    "addr:street":"Stift",
    "iso:country":"BE",
    "sg:address":"Stift 2",
    "sg:city":"Bree",
    "sg:classifiers":[
        {
            "category":"Community Center",
            "type":"Public Place"
        }
    ],
    "sg:phone":"+32 89 46 97 00",
    "sg:postcode":"3960",
    "sg:province":"Limburg",
    "sg:tags":[
        "medical"
    ],
    "wof:name":"Medisch Centrum Huisartsen Bree En Omgeving",
    "wof:placetype":"venue"
},
  "geometry": {"coordinates":[5.594894886,51.1430473328],"type":"Point"}
}