{
  "type": "Feature",
  "properties": {
    "addr:full":"Arnaud Fraiteurlaan 25 Elsene/ixelles Bruxelles-Capitale 1050",
    "addr:housenumber":"25",
    "addr:postcode":"1050",
    "addr:street":"Fraiteurlaan",
    "iso:country":"BE",
    "sg:address":"Arnaud Fraiteurlaan 25",
    "sg:city":"Elsene/ixelles",
    "sg:orig_category":"Benzinestations and brandstoffen",
    "sg:phone":"+32 2 639 91 11",
    "sg:postcode":"1050",
    "sg:province":"Bruxelles-Capitale",
    "wof:name":"Texaco",
    "wof:placetype":"venue"
},
  "geometry": {"coordinates":[4.3945398331,50.8175392151],"type":"Point"}
}