{
  "type": "Feature",
  "properties": {
    "iso:country":"BE",
    "sg:address":"Dennenbosstraat 1a",
    "sg:city":"Geetbets",
    "sg:classifiers":[
        {
            "category":"Professional",
            "subcategory":"Accounting & Tax Preparation",
            "type":"Services"
        }
    ],
    "sg:phone":"+32 11 58 80 51",
    "sg:postcode":"3450",
    "sg:province":"Vlaams-Brabant",
    "sg:tags":[
        "bookkeeper"
    ],
    "wof:name":"Cresens L",
    "wof:placetype":"venue"
},
  "geometry": {"coordinates":[5.0827741623,50.8819465637],"type":"Point"}
}