{
  "type": "Feature",
  "properties": {
    "iso:country":"BE",
    "sg:address":"Obusstraat 165",
    "sg:city":"Anderlecht",
    "sg:orig_category":"Non-Classified Establishments",
    "sg:phone":"+32 2 520 60 19",
    "sg:postcode":"1070",
    "sg:province":"Bruxelles-Capitale",
    "wof:name":"Spriet",
    "wof:placetype":"venue"
},
  "geometry": {"coordinates":[4.3060731888,50.8419494629],"type":"Point"}
}