{
  "type": "Feature",
  "properties": {
    "iso:country":"BE",
    "sg:address":"Leiestraat 93",
    "sg:city":"Zulte",
    "sg:orig_category":"Balie van Gent. Avocats and conseillers juridiques",
    "sg:phone":"+32 9 286 02 56",
    "sg:postcode":"9870",
    "sg:province":"Oost-Vlaanderen",
    "wof:name":"Claus Inge",
    "wof:placetype":"venue"
},
  "geometry": {"coordinates":[3.4412031174,50.9270133972],"type":"Point"}
}