{
  "type": "Feature",
  "properties": {
    "iso:country":"BE",
    "sg:address":"Eekhoornlaan 29",
    "sg:city":"Schilde ('s Gravenwezel)",
    "sg:classifiers":[
        {
            "category":"Professional",
            "subcategory":"Lawyer & Legal Services",
            "type":"Services"
        }
    ],
    "sg:phone":"+32 3 354 42 20",
    "sg:postcode":"2970",
    "sg:province":"Antwerpen",
    "wof:name":"Van Den Bogaert Hilde",
    "wof:placetype":"venue"
},
  "geometry": {"coordinates":[4.5549201965,51.2529182434],"type":"Point"}
}