{
  "type": "Feature",
  "properties": {
    "addr:full":"Place Verstappen 7 Charleroi (marchienne-au-pont) Hainaut 6030",
    "addr:housenumber":"7",
    "addr:postcode":"6030",
    "addr:street":"Place Verstappen",
    "iso:country":"BE",
    "sg:address":"Place Verstappen 7",
    "sg:city":"Charleroi (marchienne-au-pont)",
    "sg:classifiers":[
        {
            "category":"Shopping",
            "subcategory":"Crafts & Fabrics",
            "type":"Retail Goods"
        }
    ],
    "sg:phone":"+32 71 51 91 02",
    "sg:postcode":"6030",
    "sg:province":"Hainaut",
    "sg:tags":[
        "plant",
        "flower",
        "artificial"
    ],
    "wof:name":"Zone Verte",
    "wof:placetype":"venue"
},
  "geometry": {"coordinates":[4.3949289322,50.4065132141],"type":"Point"}
}