{
  "type": "Feature",
  "properties": {
    "iso:country":"BE",
    "sg:address":"Galerie Toison D\u00b4or",
    "sg:city":"Bruxelles-ixelles",
    "sg:orig_category":"Alimentation sp\u00e9cialis\u00e9e",
    "sg:phone":"+32 2 514 25 15",
    "sg:postcode":"1050",
    "sg:province":"Bruxelles-Capitale",
    "wof:name":"Dame Nature",
    "wof:placetype":"venue"
},
  "geometry": {"coordinates":[4.3944449425,50.8132514954],"type":"Point"}
}