{
  "type": "Feature",
  "properties": {
    "iso:country":"BE",
    "sg:address":"Voldersstraat 3",
    "sg:city":"Lochristi",
    "sg:orig_category":"Plantes and fleurs Gr",
    "sg:phone":"+32 9 355 68 48",
    "sg:postcode":"9080",
    "sg:province":"Oost-Vlaanderen",
    "wof:name":"Marchand A",
    "wof:placetype":"venue"
},
  "geometry": {"coordinates":[3.8952770233,51.0850219727],"type":"Point"}
}