{
  "type": "Feature",
  "properties": {
    "addr:full":"Huissegemstraat 14 Denderleeuw Oost-Vlaanderen 9470",
    "addr:housenumber":"14",
    "addr:postcode":"9470",
    "addr:street":"Huissegemstraat",
    "iso:country":"BE",
    "sg:address":"Huissegemstraat 14",
    "sg:city":"Denderleeuw",
    "sg:classifiers":[
        {
            "category":"Home & Garden",
            "subcategory":"Garden Supply",
            "type":"Retail Goods"
        }
    ],
    "sg:phone":"+32 53 66 11 51",
    "sg:postcode":"9470",
    "sg:province":"Oost-Vlaanderen",
    "sg:tags":[
        "seed",
        "-"
    ],
    "wof:name":"Tuinweelde Bvba",
    "wof:placetype":"venue"
},
  "geometry": {"coordinates":[4.0764260292,50.8749084473],"type":"Point"}
}