{
  "type": "Feature",
  "properties": {
    "iso:country":"BE",
    "sg:address":"Simonisstraat 31",
    "sg:city":"Elsene/ixelles",
    "sg:classifiers":[
        {
            "category":"Insurance",
            "subcategory":"Insurance Agent",
            "type":"Services"
        }
    ],
    "sg:phone":"+32 2 538 50 24",
    "sg:postcode":"1050",
    "sg:province":"Bruxelles-Capitale",
    "sg:tags":[
        "verzekeringsmakelaars",
        "expert"
    ],
    "wof:name":"Comara",
    "wof:placetype":"venue"
},
  "geometry": {"coordinates":[4.3585400581,50.8262214661],"type":"Point"}
}