{
  "type": "Feature",
  "properties": {
    "addr:full":"Eekstraat 317 Lokeren Oost-Vlaanderen 9160",
    "addr:housenumber":"317",
    "addr:postcode":"9160",
    "addr:street":"Eekstraat",
    "iso:country":"BE",
    "sg:address":"Eekstraat 317",
    "sg:city":"Lokeren",
    "sg:orig_category":"Huisvuilophaling and -verwerking Verhuur bouwmachines",
    "sg:phone":"+32 9 348 25 17",
    "sg:postcode":"9160",
    "sg:province":"Oost-Vlaanderen",
    "wof:name":"Containerdienst Mels",
    "wof:placetype":"venue"
},
  "geometry": {"coordinates":[3.9624669552,51.1004257202],"type":"Point"}
}