{
  "type": "Feature",
  "properties": {
    "addr:full":"Avenue Des Millepertuis 15 Anderlecht Bruxelles-Capitale 1070",
    "addr:housenumber":"15",
    "addr:postcode":"1070",
    "addr:street":"Avenue Des Millepertuis",
    "iso:country":"BE",
    "sg:address":"Avenue Des Millepertuis 15",
    "sg:city":"Anderlecht",
    "sg:classifiers":[
        {
            "category":"Insurance",
            "subcategory":"Life Insurance",
            "type":"Services"
        }
    ],
    "sg:phone":"+32 2 527 19 53",
    "sg:postcode":"1070",
    "sg:province":"Bruxelles-Capitale",
    "sg:tags":[
        "assurance"
    ],
    "wof:name":"Mathoux & Cie",
    "wof:placetype":"venue"
},
  "geometry": {"coordinates":[4.2833762169,50.8140411377],"type":"Point"}
}