{
  "type": "Feature",
  "properties": {
    "iso:country":"BE",
    "sg:address":"Brugmannlaan 229",
    "sg:city":"Elsene/ixelles",
    "sg:orig_category":"Kapsalons Schoonheidssalons",
    "sg:phone":"+32 2 347 24 88",
    "sg:postcode":"1050",
    "sg:province":"Bruxelles-Capitale",
    "wof:name":"Jacques Dessange",
    "wof:placetype":"venue"
},
  "geometry": {"coordinates":[4.348279953,50.81457901],"type":"Point"}
}