{
  "type": "Feature",
  "properties": {
    "addr:full":"Rue De Strichon 92 Villers-la-ville Brabant Wallon 1495",
    "addr:housenumber":"92",
    "addr:postcode":"1495",
    "addr:street":"Rue De Strichon",
    "iso:country":"BE",
    "sg:address":"Rue De Strichon 92",
    "sg:city":"Villers-la-ville",
    "sg:orig_category":"Meubles D\u00e9taillants, Am\u00e9nagement de B\u00e2timents et de Cuisines. Electrom\u00e9nager, t\u00e9l\u00e9visions and radios",
    "sg:phone":"+32 71 87 67 99",
    "sg:postcode":"1495",
    "sg:province":"Brabant Wallon",
    "wof:name":"Live Line",
    "wof:placetype":"venue"
},
  "geometry": {"coordinates":[4.5588498116,50.577960968],"type":"Point"}
}