{
  "type": "Feature",
  "properties": {
    "iso:country":"BE",
    "sg:address":"Kroonstraat 130",
    "sg:city":"Beringen",
    "sg:orig_category":"Gespecialiseerde residenti\u00eble bouw",
    "sg:phone":"+32 11 34 26 32",
    "sg:postcode":"3581",
    "sg:province":"Limburg",
    "wof:name":"Jan Houtmeyers",
    "wof:placetype":"venue"
},
  "geometry": {"coordinates":[5.2681798935,51.0915412903],"type":"Point"}
}