{
  "type": "Feature",
  "properties": {
    "iso:country":"BE",
    "sg:address":"Sint-janslaan 17",
    "sg:city":"Diepenbeek",
    "sg:orig_category":"R\u00e9parations d'appareils \u00e9lectrom\u00e9nagers. Electrom\u00e9nager, t\u00e9l\u00e9visions and radios",
    "sg:phone":"+32 11 32 13 29",
    "sg:postcode":"3590",
    "sg:province":"Limburg",
    "wof:name":"Radio En Electro Greven",
    "wof:placetype":"venue"
},
  "geometry": {"coordinates":[5.4201312065,50.9058876038],"type":"Point"}
}