{
  "type": "Feature",
  "properties": {
    "iso:country":"BE",
    "sg:address":"Avenue De L\u00b4et\u00c9 60",
    "sg:city":"Waterloo",
    "sg:orig_category":"Artsen and specialisten",
    "sg:phone":"+32 2 354 37 47",
    "sg:postcode":"1410",
    "sg:province":"Brabant Wallon",
    "wof:name":"S. Pakalin",
    "wof:placetype":"venue"
},
  "geometry": {"coordinates":[4.3916540146,50.7090034485],"type":"Point"}
}