{
  "type": "Feature",
  "properties": {
    "addr:full":"Rue Antoine Andr\u00e9 64 Wavre (limal) Brabant Wallon 1300",
    "addr:housenumber":"64",
    "addr:postcode":"1300",
    "addr:street":"Rue Antoine Andre\u0301;Wallon",
    "iso:country":"BE",
    "sg:address":"Rue Antoine Andr\u00e9 64",
    "sg:city":"Wavre (limal)",
    "sg:classifiers":[
        {
            "category":"Building & Trades",
            "subcategory":"Electrical",
            "type":"Services"
        }
    ],
    "sg:phone":"+32 475 83 68 46",
    "sg:postcode":"1300",
    "sg:province":"Brabant Wallon",
    "sg:tags":[
        "electric",
        "-",
        "housewiring",
        "contractor"
    ],
    "wof:name":"Marcotty H-p",
    "wof:placetype":"venue"
},
  "geometry": {"coordinates":[4.5901222229,50.68800354],"type":"Point"}
}