{
  "type": "Feature",
  "properties": {
    "iso:country":"BE",
    "sg:address":"Rue Des Volontaires 1",
    "sg:city":"Wavre",
    "sg:orig_category":"Dameskledingzaken Herenkledingzaken Kleding",
    "sg:phone":"+32 10 22 28 99",
    "sg:postcode":"1300",
    "sg:province":"Brabant Wallon",
    "wof:name":"Van Assche",
    "wof:placetype":"venue"
},
  "geometry": {"coordinates":[4.6066470146,50.7168121338],"type":"Point"}
}