{
  "type": "Feature",
  "properties": {
    "addr:full":"Chauss\u00c9e Brunehaut 364 Beloeil Hainaut 7972",
    "addr:housenumber":"364",
    "addr:postcode":"7972",
    "addr:street":"Chausse\u0301E Brunehaut",
    "iso:country":"BE",
    "sg:address":"Chauss\u00c9e Brunehaut 364",
    "sg:city":"Beloeil",
    "sg:orig_category":"Entretien and r\u00e9parations de voitures. V\u00e9hicules automobiles",
    "sg:phone":"+32 69 68 85 81",
    "sg:postcode":"7972",
    "sg:province":"Hainaut",
    "wof:name":"Garage Michel Ok-az",
    "wof:placetype":"venue"
},
  "geometry": {"coordinates":[3.6904549599,50.5526885986],"type":"Point"}
}