{
  "type": "Feature",
  "properties": {
    "addr:full":"K Verbruggenstraat 29 Puurs Antwerpen 2870",
    "addr:housenumber":"29",
    "addr:postcode":"2870",
    "addr:street":"K Verbruggenstraat",
    "iso:country":"BE",
    "sg:address":"K Verbruggenstraat 29",
    "sg:city":"Puurs",
    "sg:orig_category":"Installatie van houten of kunststof schrijnwerk Meubelzaken, woning- and keukeninrichting",
    "sg:phone":"+32 3 899 34 54",
    "sg:postcode":"2870",
    "sg:province":"Antwerpen",
    "wof:name":"Atlanten",
    "wof:placetype":"venue"
},
  "geometry": {"coordinates":[4.2987751961,51.0832862854],"type":"Point"}
}