{
  "type": "Feature",
  "properties": {
    "addr:full":"Rue De Mons 27a Charleroi Hainaut 6000",
    "addr:housenumber":"27a",
    "addr:postcode":"6000",
    "addr:street":"Rue De Mons;Hainaut",
    "iso:country":"BE",
    "sg:address":"Rue De Mons 27a",
    "sg:city":"Charleroi",
    "sg:classifiers":[
        {
            "category":"Retail",
            "subcategory":"Auto Repair",
            "type":"Services"
        }
    ],
    "sg:phone":"+32 71 32 27 00",
    "sg:postcode":"6000",
    "sg:province":"Hainaut",
    "sg:tags":[
        "garage"
    ],
    "wof:name":"Danieli",
    "wof:placetype":"venue"
},
  "geometry": {"coordinates":[4.43521595,50.4122314453],"type":"Point"}
}