{
  "type": "Feature",
  "properties": {
    "addr:full":"Avenue De Mai 138 Sint-lambrechts-woluwe/woluwe-saint-lambert Bruxelles-Capitale 1200",
    "addr:housenumber":"138;/",
    "addr:postcode":"1200",
    "addr:street":"Avenue De Mai;Sint-Lambrechts-Woluwe",
    "iso:country":"BE",
    "sg:address":"Avenue De Mai 138",
    "sg:city":"Sint-lambrechts-woluwe/woluwe-saint-lambert",
    "sg:orig_category":"Traitements param\u00e9dicaux",
    "sg:phone":"+32 2 770 00 35",
    "sg:postcode":"1200",
    "sg:province":"Bruxelles-Capitale",
    "wof:name":"Wit-gele Kruis/croix Jaune Et Blanche",
    "wof:placetype":"venue"
},
  "geometry": {"coordinates":[4.4179358482,50.8488578796],"type":"Point"}
}