{
  "type": "Feature",
  "properties": {
    "addr:full":"Poeldries 13 Zwevegem (moen) 8552",
    "addr:housenumber":"13",
    "addr:postcode":"8552",
    "addr:street":"Poeldries;Moen",
    "iso:country":"BE",
    "sg:address":"Poeldries 13",
    "sg:city":"Zwevegem (moen)",
    "sg:classifiers":[
        {
            "category":"Building & Trades",
            "subcategory":"Construction",
            "type":"Services"
        }
    ],
    "sg:phone":"+32 56 45 60 47",
    "sg:postcode":"8552",
    "sg:tags":[
        "stair"
    ],
    "wof:name":"Bossuyt S",
    "wof:placetype":"venue"
},
  "geometry": {"coordinates":[3.3932960033,50.7541809082],"type":"Point"}
}