{
  "type": "Feature",
  "properties": {
    "iso:country":"BE",
    "sg:address":"Nieuwenhovestraat 24",
    "sg:city":"Deerlijk",
    "sg:classifiers":[
        {
            "category":"Building & Trades",
            "subcategory":"Construction",
            "type":"Services"
        }
    ],
    "sg:phone":"+32 56 77 32 07",
    "sg:postcode":"8540",
    "sg:province":"West-Vlaanderen",
    "sg:tags":[
        "stair"
    ],
    "wof:name":"Travamec Bvba",
    "wof:placetype":"venue"
},
  "geometry": {"coordinates":[3.3916931152,50.859577179],"type":"Point"}
}