{
  "type": "Feature",
  "properties": {
    "iso:country":"BE",
    "sg:address":"Temsesteenweg 13",
    "sg:city":"Bornem",
    "sg:orig_category":"Elektrische installaties voor woningen",
    "sg:phone":"+32 3 889 86 50",
    "sg:postcode":"2880",
    "sg:province":"Antwerpen",
    "wof:name":"Marc Verhaeghen",
    "wof:placetype":"venue"
},
  "geometry": {"coordinates":[4.232363224,51.1025924683],"type":"Point"}
}