{
  "type": "Feature",
  "properties": {
    "addr:full":"Rue De La R\u00c9sistance 69 Saint-nicolas Li\u00e8ge 4420",
    "addr:housenumber":"69",
    "addr:postcode":"4420",
    "addr:street":"Rue De La Re\u0301Sistance",
    "iso:country":"BE",
    "sg:address":"Rue De La R\u00c9sistance 69",
    "sg:city":"Saint-nicolas",
    "sg:orig_category":"Kapsalons",
    "sg:phone":"+32 4 263 99 24",
    "sg:postcode":"4420",
    "sg:province":"Li\u00e8ge",
    "wof:name":"Claudio La Delfa",
    "wof:placetype":"venue"
},
  "geometry": {"coordinates":[5.5188441277,50.6401519775],"type":"Point"}
}