{
  "type": "Feature",
  "properties": {
    "iso:country":"BE",
    "sg:address":"23",
    "sg:city":"Rue Claessens 1020 Bruxelles",
    "sg:classifiers":[
        {
            "category":"Building & Trades",
            "subcategory":"Construction",
            "type":"Services"
        }
    ],
    "sg:phone":"+32 2 428 97 30",
    "sg:postcode":"23",
    "sg:tags":[
        "work",
        "public"
    ],
    "wof:name":"Antoniou Sa",
    "wof:placetype":"venue"
},
  "geometry": {"coordinates":[4.3565950394,50.8723564148],"type":"Point"}
}