{
  "type": "Feature",
  "properties": {
    "addr:full":"Gustaaf Schockaertstraat 2 Zottegem Oost-Vlaanderen 9620",
    "addr:housenumber":"2",
    "addr:postcode":"9620",
    "addr:street":"Gustaaf Schockaertstraat",
    "iso:country":"BE",
    "sg:address":"Gustaaf Schockaertstraat 2",
    "sg:city":"Zottegem",
    "sg:classifiers":[
        {
            "category":"Food & Beverages",
            "subcategory":"Specialty",
            "type":"Retail Goods"
        }
    ],
    "sg:phone":"+32 9 360 42 36",
    "sg:postcode":"9620",
    "sg:province":"Oost-Vlaanderen",
    "sg:tags":[
        "health",
        "dietary",
        "-",
        "biological"
    ],
    "wof:name":"Helianthus Bvba",
    "wof:placetype":"venue"
},
  "geometry": {"coordinates":[3.8117339611,50.8672447205],"type":"Point"}
}