{
  "type": "Feature",
  "properties": {
    "iso:country":"BE",
    "sg:address":"Roiseleux 1",
    "sg:city":"Thimister-clermont (thimister)",
    "sg:classifiers":[
        {
            "category":"Farming",
            "subcategory":"Livestock Farm",
            "type":"Manufacturing & Wholesale Goods"
        }
    ],
    "sg:phone":"+32 87 44 62 66",
    "sg:postcode":"4890",
    "sg:province":"Li\u00e8ge",
    "sg:tags":[
        "horse"
    ],
    "wof:name":"Baumans E",
    "wof:placetype":"venue"
},
  "geometry": {"coordinates":[5.8447608948,50.6689300537],"type":"Point"}
}