{
  "type": "Feature",
  "properties": {
    "iso:country":"BE",
    "sg:address":"Lammerdries 12",
    "sg:city":"Geel",
    "sg:classifiers":[
        {
            "category":"Utilities",
            "subcategory":"Natural Gas",
            "type":"Services"
        }
    ],
    "sg:phone":"+32 14 28 68 68",
    "sg:postcode":"2440",
    "sg:province":"Antwerpen",
    "sg:tags":[
        "industrial",
        "heating"
    ],
    "wof:name":"Bovema International Nv",
    "wof:placetype":"venue"
},
  "geometry": {"coordinates":[4.9223408699,51.1459121704],"type":"Point"}
}