{
  "type": "Feature",
  "properties": {
    "addr:full":"Avenue De Tercoigne 34 Bruxelles (watermael-boitsfort) Bruxelles-Capitale 1170",
    "addr:housenumber":"34",
    "addr:postcode":"1170",
    "addr:street":"Avenue De Tercoigne",
    "iso:country":"BE",
    "sg:address":"Avenue De Tercoigne 34",
    "sg:city":"Bruxelles (watermael-boitsfort)",
    "sg:classifiers":[
        {
            "category":"Real Estate",
            "subcategory":"Architect",
            "type":"Services"
        }
    ],
    "sg:phone":"+32 2 672 62 58",
    "sg:postcode":"1170",
    "sg:province":"Bruxelles-Capitale",
    "wof:name":"Fran\u00e7ois H",
    "wof:placetype":"venue"
},
  "geometry": {"coordinates":[4.4052047729,50.8143119812],"type":"Point"}
}