{
  "type": "Feature",
  "properties": {
    "iso:country":"BE",
    "sg:address":"Nieuwe Kassei 78",
    "sg:city":"Affligem (hekelgem)",
    "sg:classifiers":[
        {
            "category":"Social Services",
            "subcategory":"Job Training",
            "type":"Services"
        }
    ],
    "sg:phone":"+32 53 66 94 93",
    "sg:postcode":"1790",
    "sg:province":"Vlaams-Brabant",
    "sg:tags":[
        "coordinator",
        "safety"
    ],
    "wof:name":"Db Nv",
    "wof:placetype":"venue"
},
  "geometry": {"coordinates":[4.1141180992,50.920135498],"type":"Point"}
}