{
  "type": "Feature",
  "properties": {
    "iso:country":"BE",
    "sg:address":"Champ Des Fontaines 26",
    "sg:city":"Wavre (limal)",
    "sg:classifiers":[
        {
            "category":"Professional",
            "subcategory":"Advertising",
            "type":"Services"
        }
    ],
    "sg:phone":"+32 10 40 17 37",
    "sg:postcode":"1300",
    "sg:province":"Brabant Wallon",
    "sg:tags":[
        "bill",
        "-",
        "posting"
    ],
    "wof:name":"Renta Pub Sa",
    "wof:placetype":"venue"
},
  "geometry": {"coordinates":[4.6083898544,50.7136764526],"type":"Point"}
}