{
  "type": "Feature",
  "properties": {
    "addr:full":"Kruishoutemseweg 138 Waregem West-Vlaanderen 8790",
    "addr:housenumber":"138",
    "addr:postcode":"8790",
    "iso:country":"BE",
    "sg:address":"Kruishoutemseweg 138",
    "sg:city":"Waregem",
    "sg:classifiers":[
        {
            "category":"Food & Beverages",
            "subcategory":"Meat & Fish",
            "type":"Retail Goods"
        }
    ],
    "sg:phone":"+32 56 60 02 12",
    "sg:postcode":"8790",
    "sg:province":"West-Vlaanderen",
    "sg:tags":[
        "-",
        "livestock"
    ],
    "wof:name":"Paardevoeders Moerman Nv",
    "wof:placetype":"venue"
},
  "geometry": {"coordinates":[3.4696280956,50.8935317993],"type":"Point"}
}