{
  "type": "Feature",
  "properties": {
    "addr:full":"H Lebbestraat 93 Waregem West-Vlaanderen 8790",
    "addr:housenumber":"93",
    "addr:postcode":"8790",
    "addr:street":"Lebbestraat",
    "iso:country":"BE",
    "sg:address":"H Lebbestraat 93",
    "sg:city":"Waregem",
    "sg:orig_category":"Agences d'exp\u00e9dition",
    "sg:phone":"+32 56 61 26 90",
    "sg:postcode":"8790",
    "sg:province":"West-Vlaanderen",
    "wof:name":"Alpha Light",
    "wof:placetype":"venue"
},
  "geometry": {"coordinates":[3.4243168831,50.8800735474],"type":"Point"}
}