{
  "type": "Feature",
  "properties": {
    "addr:full":"Pennestraat 7 Ieper West-Vlaanderen 8900",
    "addr:housenumber":"7",
    "addr:postcode":"8900",
    "addr:street":"Pennestraat",
    "iso:country":"BE",
    "sg:address":"Pennestraat 7",
    "sg:city":"Ieper",
    "sg:orig_category":"Assembling, Disassembling",
    "sg:phone":"+32 57 20 83 94",
    "sg:postcode":"8900",
    "sg:province":"West-Vlaanderen",
    "wof:name":"Elca Nv",
    "wof:placetype":"venue"
},
  "geometry": {"coordinates":[2.890319109,50.8564300537],"type":"Point"}
}