{
  "type": "Feature",
  "properties": {
    "addr:full":"Chauss\u00c9e Du Roeulx 35 Mons Hainaut 7000",
    "addr:housenumber":"35",
    "addr:postcode":"7000",
    "addr:street":"Chausse\u0301E Du Roeulx;Hainaut",
    "iso:country":"BE",
    "sg:address":"Chauss\u00c9e Du Roeulx 35",
    "sg:city":"Mons",
    "sg:orig_category":"Plaatsen van vloer- and muurbekleding Schilders",
    "sg:phone":"+32 65 31 78 59",
    "sg:postcode":"7000",
    "sg:province":"Hainaut",
    "wof:name":"Jean-claude Hamende",
    "wof:placetype":"venue"
},
  "geometry": {"coordinates":[3.9677100182,50.4542541504],"type":"Point"}
}