{
  "type": "Feature",
  "properties": {
    "addr:full":"Fabriekstraat 18 Aarschot Vlaams-Brabant 3200",
    "addr:housenumber":"18",
    "addr:postcode":"3200",
    "addr:street":"Fabriekstraat",
    "iso:country":"BE",
    "sg:address":"Fabriekstraat 18",
    "sg:city":"Aarschot",
    "sg:orig_category":"M\u00e9decins and sp\u00e9cialistes",
    "sg:phone":"+32 16 57 28 98",
    "sg:postcode":"3200",
    "sg:province":"Vlaams-Brabant",
    "wof:name":"Axelle De Dycker",
    "wof:placetype":"venue"
},
  "geometry": {"coordinates":[4.8274621964,50.984336853],"type":"Point"}
}