{
  "type": "Feature",
  "properties": {
    "addr:full":"Diestsesteenweg 85 Tielt-winge Vlaams-Brabant 3390",
    "addr:housenumber":"85",
    "addr:postcode":"3390",
    "addr:street":"Diestsesteenweg",
    "iso:country":"BE",
    "sg:address":"Diestsesteenweg 85",
    "sg:city":"Tielt-winge",
    "sg:orig_category":"Mat\u00e9riel de contr\u00f4le des processus industriels Fab",
    "sg:phone":"+32 16 64 09 26",
    "sg:postcode":"3390",
    "sg:province":"Vlaams-Brabant",
    "wof:name":"Centrale Smeertechniek",
    "wof:placetype":"venue"
},
  "geometry": {"coordinates":[4.948029995,50.9374313354],"type":"Point"}
}