{
  "type": "Feature",
  "properties": {
    "iso:country":"BE",
    "sg:address":"Rue Du Coq 9",
    "sg:city":"Amay",
    "sg:orig_category":"Schoonheidssalons",
    "sg:phone":"+32 85 31 43 59",
    "sg:postcode":"4540",
    "sg:province":"Li\u00e8ge",
    "wof:name":"Brigitte Moineau",
    "wof:placetype":"venue"
},
  "geometry": {"coordinates":[5.3075499535,50.5510177612],"type":"Point"}
}