{
  "type": "Feature",
  "properties": {
    "iso:country":"BE",
    "sg:address":"Polderstraat 12",
    "sg:city":"Oud-heverlee (sint-joris-weert)",
    "sg:classifiers":[
        {
            "category":"Health Services",
            "subcategory":"Dentist",
            "type":"Services"
        }
    ],
    "sg:phone":"+32 16 47 16 44",
    "sg:postcode":"3051",
    "sg:province":"Vlaams-Brabant",
    "wof:name":"Draye J",
    "wof:placetype":"venue"
},
  "geometry": {"coordinates":[4.6534509659,50.7999076843],"type":"Point"}
}