{
  "type": "Feature",
  "properties": {
    "addr:full":"Rue Des Ursulines 1 Namur Namur 5000",
    "addr:housenumber":"1",
    "addr:postcode":"5000",
    "addr:street":"Rue Des Ursulines",
    "iso:country":"BE",
    "sg:address":"Rue Des Ursulines 1",
    "sg:city":"Namur",
    "sg:classifiers":[
        {
            "category":"Personal",
            "subcategory":"Beauty Salon",
            "type":"Services"
        }
    ],
    "sg:phone":"+32 81 22 81 51",
    "sg:postcode":"5000",
    "sg:province":"Namur",
    "wof:name":"Centre D'esthetique Ysara",
    "wof:placetype":"venue"
},
  "geometry": {"coordinates":[4.8615989685,50.4681282043],"type":"Point"}
}