{
  "type": "Feature",
  "properties": {
    "addr:full":"Leuerbroek 1070 Kinrooi Limburg 3640",
    "addr:postcode":"1070 kinrooi;3640",
    "iso:country":"BE",
    "sg:address":"Leuerbroek 1070",
    "sg:city":"Kinrooi",
    "sg:orig_category":"Metaalbehandeling and -bekleding",
    "sg:phone":"+32 89 70 36 01",
    "sg:postcode":"3640",
    "sg:province":"Limburg",
    "wof:name":"Ergon Maasland",
    "wof:placetype":"venue"
},
  "geometry": {"coordinates":[5.75147295,51.1375045776],"type":"Point"}
}