{
  "type": "Feature",
  "properties": {
    "iso:country":"BE",
    "sg:address":"Rue Des Roches 51",
    "sg:city":"Houyet",
    "sg:orig_category":"Villages de vacances",
    "sg:phone":"+32 82 66 66 54",
    "sg:postcode":"5563",
    "sg:province":"Namur",
    "wof:name":"Le Cheneau",
    "wof:placetype":"venue"
},
  "geometry": {"coordinates":[5.0250988007,50.1548995972],"type":"Point"}
}