{
  "type": "Feature",
  "properties": {
    "iso:country":"BE",
    "sg:address":"Rue Alexandre-daoust 41",
    "sg:city":"Dinant",
    "sg:orig_category":"Avocats and conseillers juridiques",
    "sg:phone":"+32 82 22 23 29",
    "sg:postcode":"5500",
    "sg:province":"Namur",
    "wof:name":"Pascal Vancraeynest",
    "wof:placetype":"venue"
},
  "geometry": {"coordinates":[4.9174518585,50.2524719238],"type":"Point"}
}