{
  "type": "Feature",
  "properties": {
    "iso:country":"BE",
    "sg:address":"Route De Rochefort 4",
    "sg:city":"Ciney",
    "sg:orig_category":"Boissons Caf\u00e9s",
    "sg:phone":"+32 83 22 03 44",
    "sg:postcode":"5590",
    "sg:province":"Namur",
    "wof:name":"Brasserie Demarche",
    "wof:placetype":"venue"
},
  "geometry": {"coordinates":[5.1574749947,50.255279541],"type":"Point"}
}