{
  "type": "Feature",
  "properties": {
    "addr:full":"Stationsstraat 286 Deerlijk West-Vlaanderen 8540",
    "addr:housenumber":"286",
    "addr:postcode":"8540",
    "addr:street":"Stationsstraat",
    "iso:country":"BE",
    "sg:address":"Stationsstraat 286",
    "sg:city":"Deerlijk",
    "sg:orig_category":"Meubelzaken, woning- and keukeninrichting",
    "sg:phone":"+32 56 77 55 45",
    "sg:postcode":"8540",
    "sg:province":"West-Vlaanderen",
    "wof:name":"Rova International",
    "wof:placetype":"venue"
},
  "geometry": {"coordinates":[3.349159956,50.8369026184],"type":"Point"}
}