{
  "type": "Feature",
  "properties": {
    "addr:full":"Rue Delb\u00c8que 37b2 Morlanwelz Hainaut 7140",
    "addr:housenumber":"37b2",
    "addr:postcode":"7140",
    "addr:street":"Rue Delbe\u0300Que",
    "iso:country":"BE",
    "sg:address":"Rue Delb\u00c8que 37b2",
    "sg:city":"Morlanwelz",
    "sg:orig_category":"Installation \u00e9lectrique r\u00e9sidentielle",
    "sg:phone":"+32 64 44 59 05",
    "sg:postcode":"7140",
    "sg:province":"Hainaut",
    "wof:name":"Giuseppe Ciuro",
    "wof:placetype":"venue"
},
  "geometry": {"coordinates":[4.2483000755,50.4520645142],"type":"Point"}
}