{
  "type": "Feature",
  "properties": {
    "addr:full":"De Valken 52 Arendonk Antwerpen 2370",
    "addr:housenumber":"52",
    "addr:postcode":"2370",
    "addr:street":"De Valken",
    "iso:country":"BE",
    "sg:address":"De Valken 52",
    "sg:city":"Arendonk",
    "sg:orig_category":"Banken and kredietinstellingen",
    "sg:phone":"+32 14 67 83 26",
    "sg:postcode":"2370",
    "sg:province":"Antwerpen",
    "wof:name":"Bbl",
    "wof:placetype":"venue"
},
  "geometry": {"coordinates":[5.0831851959,51.3202590942],"type":"Point"}
}