{
  "type": "Feature",
  "properties": {
    "iso:country":"BE",
    "sg:address":"Beverhoekstraat 15",
    "sg:city":"Kruishoutem",
    "sg:classifiers":[
        {
            "category":"Personal",
            "type":"Services"
        }
    ],
    "sg:phone":"+32 9 383 58 28",
    "sg:postcode":"9770",
    "sg:province":"Oost-Vlaanderen",
    "sg:tags":[
        "clothing",
        "men's",
        "tailor",
        "-"
    ],
    "wof:name":"De Bruyne A",
    "wof:placetype":"venue"
},
  "geometry": {"coordinates":[3.524089098,50.9081344604],"type":"Point"}
}