{
  "type": "Feature",
  "properties": {
    "addr:full":"Pourbusstraat 24 Antwerpen Antwerpen 2000",
    "addr:housenumber":"24",
    "addr:postcode":"2000",
    "addr:street":"Pourbusstraat",
    "iso:country":"BE",
    "sg:address":"Pourbusstraat 24",
    "sg:city":"Antwerpen",
    "sg:classifiers":[
        {
            "category":"Social Services",
            "type":"Services"
        }
    ],
    "sg:phone":"+32 3 248 07 09",
    "sg:postcode":"2000",
    "sg:province":"Antwerpen",
    "wof:name":"Consortium Schoolopbouwwerk Antwerpen Zuid Vzw",
    "wof:placetype":"venue"
},
  "geometry": {"coordinates":[4.3909788132,51.2084312439],"type":"Point"}
}