{
  "type": "Feature",
  "properties": {
    "addr:full":"46 Beringsesteenweg 3971 Leopoldsburg Heppe 46",
    "addr:housenumber":"46;46",
    "addr:postcode":"3971",
    "addr:street":"Beringsesteenweg;Heppe",
    "iso:country":"BE",
    "sg:address":"46",
    "sg:city":"Beringsesteenweg 3971 Leopoldsburg Heppe",
    "sg:classifiers":[
        {
            "category":"Professional",
            "subcategory":"Advertising",
            "type":"Services"
        }
    ],
    "sg:phone":"+32 11 40 16 56",
    "sg:postcode":"46",
    "sg:tags":[
        "communication",
        "medium"
    ],
    "wof:name":"Horemans Nv",
    "wof:placetype":"venue"
},
  "geometry": {"coordinates":[5.2278819084,51.1079216003],"type":"Point"}
}