{
  "type": "Feature",
  "properties": {
    "iso:country":"BE",
    "sg:address":"Rue Des Censes 3",
    "sg:city":"Froidchapelle (vergnies)",
    "sg:classifiers":[
        {
            "category":"Mining & Drilling",
            "type":"Manufacturing & Wholesale Goods"
        }
    ],
    "sg:phone":"+32 60 45 66 47",
    "sg:postcode":"6440",
    "sg:province":"Hainaut",
    "sg:tags":[
        "concrete",
        "reinforced",
        "sawing"
    ],
    "wof:name":"Perce B\u00e9ton",
    "wof:placetype":"venue"
},
  "geometry": {"coordinates":[4.3025350571,50.2000656128],"type":"Point"}
}