{
  "type": "Feature",
  "properties": {
    "addr:full":"Ringlaan 34b224 Kortrijk West-Vlaanderen 8500",
    "addr:housenumber":"34b224",
    "addr:postcode":"8500",
    "addr:street":"Ringlaan",
    "iso:country":"BE",
    "sg:address":"Ringlaan 34b224",
    "sg:city":"Kortrijk",
    "sg:classifiers":[
        {
            "category":"Shopping",
            "subcategory":"Clothing, Apparel, & Fashions",
            "type":"Retail Goods"
        }
    ],
    "sg:phone":"+32 56 37 18 05",
    "sg:postcode":"8500",
    "sg:province":"West-Vlaanderen",
    "sg:tags":[
        "lingerie",
        "sous-v\u00eatements"
    ],
    "wof:name":"Huis Per Tutti",
    "wof:placetype":"venue"
},
  "geometry": {"coordinates":[3.2646589279,50.8452682495],"type":"Point"}
}