{
  "type": "Feature",
  "properties": {
    "addr:full":"Klingedorp 9 Sint-gillis-waas Oost-Vlaanderen 9170",
    "addr:housenumber":"9",
    "addr:postcode":"9170",
    "addr:street":"Klingedorp",
    "iso:country":"BE",
    "sg:address":"Klingedorp 9",
    "sg:city":"Sint-gillis-waas",
    "sg:orig_category":"Advocaten and juridische adviseurs",
    "sg:phone":"+32 3 707 04 45",
    "sg:postcode":"9170",
    "sg:province":"Oost-Vlaanderen",
    "wof:name":"N. Huygels",
    "wof:placetype":"venue"
},
  "geometry": {"coordinates":[4.090405941,51.2565383911],"type":"Point"}
}