{
  "type": "Feature",
  "properties": {
    "iso:country":"BE",
    "sg:address":"Jozef Van Hovestraat 35",
    "sg:city":"Kraainem/kraainem",
    "sg:orig_category":"Plaatsen van vloer- and muurbekleding Schilders",
    "sg:phone":"+32 2 720 51 83",
    "sg:postcode":"1950",
    "sg:province":"Vlaams-Brabant",
    "wof:name":"Fe. Mendes Da Costa Cl.",
    "wof:placetype":"venue"
},
  "geometry": {"coordinates":[4.4529891014,50.8650474548],"type":"Point"}
}