{
  "type": "Feature",
  "properties": {
    "iso:country":"BE",
    "sg:address":"Vrijgeweidestraat 1",
    "sg:city":"Oostkamp",
    "sg:orig_category":"S\u00e9curit\u00e9 sociale. Biblioth\u00e8ques and archives publiques",
    "sg:phone":"+32 50 27 92 67",
    "sg:postcode":"8020",
    "sg:province":"West-Vlaanderen",
    "wof:name":"Christelijke Mutualiteit",
    "wof:placetype":"venue"
},
  "geometry": {"coordinates":[3.1717100143,51.0766601562],"type":"Point"}
}