{
  "type": "Feature",
  "properties": {
    "addr:full":"Rue De La Gare 32 Couvin Namur 5660",
    "addr:housenumber":"32",
    "addr:postcode":"5660",
    "addr:street":"Rue De La Gare",
    "iso:country":"BE",
    "sg:address":"Rue De La Gare 32",
    "sg:city":"Couvin",
    "sg:orig_category":"Kansspelen",
    "sg:phone":"+32 60 34 59 34",
    "sg:postcode":"5660",
    "sg:province":"Namur",
    "wof:name":"Ladbrokes",
    "wof:placetype":"venue"
},
  "geometry": {"coordinates":[4.4922919273,50.0551834106],"type":"Point"}
}