{
  "type": "Feature",
  "properties": {
    "addr:full":"Thomas Van Loostraat 56 Oostende West-Vlaanderen 8400",
    "addr:housenumber":"56",
    "addr:postcode":"8400",
    "addr:street":"Thomas Van Loostraat",
    "iso:country":"BE",
    "sg:address":"Thomas Van Loostraat 56",
    "sg:city":"Oostende",
    "sg:orig_category":"Enseignement maternel and primaire",
    "sg:phone":"+32 59 32 27 45",
    "sg:postcode":"8400",
    "sg:province":"West-Vlaanderen",
    "wof:name":"Stedelijke Basisschool",
    "wof:placetype":"venue"
},
  "geometry": {"coordinates":[2.9459459782,51.2300567627],"type":"Point"}
}