{
  "type": "Feature",
  "properties": {
    "addr:full":"Kasteeldreef 19 Oostkamp West-Vlaanderen 8020",
    "addr:housenumber":"19",
    "addr:postcode":"8020",
    "addr:street":"Kasteeldreef",
    "iso:country":"BE",
    "sg:address":"Kasteeldreef 19",
    "sg:city":"Oostkamp",
    "sg:orig_category":"Parfumeries",
    "sg:phone":"+32 50 27 53 02",
    "sg:postcode":"8020",
    "sg:province":"West-Vlaanderen",
    "wof:name":"Michiel Vanclooster",
    "wof:placetype":"venue"
},
  "geometry": {"coordinates":[3.27886796,51.1010322571],"type":"Point"}
}