{
  "type": "Feature",
  "properties": {
    "iso:country":"BE",
    "sg:address":"Avenue Du Fond Marie Monseu 58",
    "sg:city":"Rixensart",
    "sg:classifiers":[
        {
            "category":"Personal",
            "subcategory":"Beauty Salon",
            "type":"Services"
        }
    ],
    "sg:phone":"+32 2 654 06 97",
    "sg:postcode":"1330",
    "sg:province":"Brabant Wallon",
    "sg:tags":[
        "lady",
        "-",
        "hairdressing"
    ],
    "wof:name":"Bigoudou (le)",
    "wof:placetype":"venue"
},
  "geometry": {"coordinates":[4.5434322357,50.7078514099],"type":"Point"}
}