{
  "type": "Feature",
  "properties": {
    "addr:full":"Koolmijnlaan 518 Beringen Limburg 3581",
    "addr:housenumber":"518",
    "addr:postcode":"3581",
    "addr:street":"Koolmijnlaan",
    "iso:country":"BE",
    "sg:address":"Koolmijnlaan 518",
    "sg:city":"Beringen",
    "sg:orig_category":"Banques and organismes de cr\u00e9dit",
    "sg:phone":"+32 11 34 35 93",
    "sg:postcode":"3581",
    "sg:province":"Limburg",
    "wof:name":"Kbc",
    "wof:placetype":"venue"
},
  "geometry": {"coordinates":[5.2189002037,51.0863609314],"type":"Point"}
}