{
  "type": "Feature",
  "properties": {
    "iso:country":"BE",
    "sg:address":"Steenweg 140",
    "sg:city":"Lanaken (rekem)",
    "sg:classifiers":[
        {
            "category":"Sports & Exercise",
            "subcategory":"Climbing Gym",
            "type":"Entertainment"
        }
    ],
    "sg:phone":"+32 89 71 24 04",
    "sg:postcode":"3621",
    "sg:province":"Limburg",
    "sg:tags":[
        "water",
        "article"
    ],
    "wof:name":"Checked Flag",
    "wof:placetype":"venue"
},
  "geometry": {"coordinates":[5.6860489845,50.9225349426],"type":"Point"}
}