{
  "type": "Feature",
  "properties": {
    "iso:country":"BE",
    "sg:address":"Rue De Crupet 12",
    "sg:city":"Assesse",
    "sg:orig_category":"Rundveehouders",
    "sg:phone":"+32 83 65 58 11",
    "sg:postcode":"5330",
    "sg:province":"Namur",
    "wof:name":"Housiaux Philippe",
    "wof:placetype":"venue"
},
  "geometry": {"coordinates":[4.9750242233,50.3773612976],"type":"Point"}
}