{
  "type": "Feature",
  "properties": {
    "addr:full":"Prosper Van Raemdonkstraat 11 Beveren (beveren-waas) Oost-Vlaanderen 9120",
    "addr:housenumber":"11",
    "addr:postcode":"9120",
    "addr:street":"Prosper Van Raemdonkstraat;Oost-Vlaanderen",
    "iso:country":"BE",
    "sg:address":"Prosper Van Raemdonkstraat 11",
    "sg:city":"Beveren (beveren-waas)",
    "sg:classifiers":[
        {
            "category":"Organizations",
            "subcategory":"Professional Association",
            "type":"Services"
        }
    ],
    "sg:phone":"+32 479 25 96 29",
    "sg:postcode":"9120",
    "sg:province":"Oost-Vlaanderen",
    "sg:tags":[
        "artist",
        "make-up"
    ],
    "wof:name":"Akasha Arts",
    "wof:placetype":"venue"
},
  "geometry": {"coordinates":[4.2484178543,51.2160301208],"type":"Point"}
}