{
  "type": "Feature",
  "properties": {
    "iso:country":"BE",
    "sg:address":"Rue L\u00e9on Debelle 22",
    "sg:city":"Manage (bois-d'haine)",
    "sg:classifiers":[
        {
            "category":"Health Services",
            "subcategory":"Health Practitioner",
            "type":"Services"
        }
    ],
    "sg:phone":"+32 64 54 81 34",
    "sg:postcode":"7170",
    "sg:province":"Hainaut",
    "sg:tags":[
        "physiotherapist"
    ],
    "wof:name":"Chaidron P",
    "wof:placetype":"venue"
},
  "geometry": {"coordinates":[4.2099599838,50.494304657],"type":"Point"}
}