{
  "type": "Feature",
  "properties": {
    "iso:country":"BE",
    "sg:address":"Avenue Marius Renard 25ba",
    "sg:city":"Anderlecht",
    "sg:orig_category":"Banques and organismes de cr\u00e9dit",
    "sg:phone":"+32 2 523 80 20",
    "sg:postcode":"1070",
    "sg:province":"Bruxelles-Capitale",
    "wof:name":"Marius Finance",
    "wof:placetype":"venue"
},
  "geometry": {"coordinates":[4.2873687744,50.8268013],"type":"Point"}
}