{
  "type": "Feature",
  "properties": {
    "addr:full":"Akker 33 Zoersel Antwerpen 2980",
    "addr:housenumber":"33",
    "addr:postcode":"2980",
    "addr:street":"Akker",
    "iso:country":"BE",
    "sg:address":"Akker 33",
    "sg:city":"Zoersel",
    "sg:classifiers":[
        {
            "category":"Professional",
            "subcategory":"Business Services",
            "type":"Services"
        }
    ],
    "sg:phone":"+32 497 37 05 90",
    "sg:postcode":"2980",
    "sg:province":"Antwerpen",
    "sg:tags":[
        "firm"
    ],
    "wof:name":"Dinnammo",
    "wof:placetype":"venue"
},
  "geometry": {"coordinates":[4.713435173,51.269985199],"type":"Point"}
}