{
  "type": "Feature",
  "properties": {
    "iso:country":"BE",
    "sg:address":"Zeger Van Heulestraat 4",
    "sg:city":"Kortrijk (heule)",
    "sg:classifiers":[
        {
            "category":"Health Services",
            "subcategory":"Dentist",
            "type":"Services"
        }
    ],
    "sg:phone":"+32 56 35 37 53",
    "sg:postcode":"8501",
    "sg:province":"West-Vlaanderen",
    "wof:name":"Pareit Jean-pierre",
    "wof:placetype":"venue"
},
  "geometry": {"coordinates":[3.2358820438,50.8436088562],"type":"Point"}
}