{
  "type": "Feature",
  "properties": {
    "addr:full":"Rue De La Station 4 Leuze-en-hainaut Hainaut 7904",
    "addr:housenumber":"4",
    "addr:postcode":"7904",
    "addr:street":"Rue De La Station",
    "iso:country":"BE",
    "sg:address":"Rue De La Station 4",
    "sg:city":"Leuze-en-hainaut",
    "sg:orig_category":"Installatie van houten of kunststof schrijnwerk",
    "sg:phone":"+32 69 67 12 30",
    "sg:postcode":"7904",
    "sg:province":"Hainaut",
    "wof:name":"Rodolphe Labie",
    "wof:placetype":"venue"
},
  "geometry": {"coordinates":[3.6462659836,50.573764801],"type":"Point"}
}