{
  "type": "Feature",
  "properties": {
    "iso:country":"BE",
    "sg:address":"Kapel Ter Bede 51",
    "sg:city":"Kortrijk",
    "sg:orig_category":"Installatie van houten of kunststof schrijnwerk MEUBELONTWERP AND -INSTALLATIE Meubelzaken, woning- ",
    "sg:phone":"+32 56 21 22 88",
    "sg:postcode":"8500",
    "sg:province":"West-Vlaanderen",
    "wof:name":"Vandenborre Gebrs",
    "wof:placetype":"venue"
},
  "geometry": {"coordinates":[3.2928140163,50.8216552734],"type":"Point"}
}