{
  "type": "Feature",
  "properties": {
    "iso:country":"BE",
    "sg:address":"Avenue D'auderghem 300",
    "sg:city":"Etterbeek",
    "sg:orig_category":"Agences d'exp\u00e9dition",
    "sg:phone":"+32 2 648 40 64",
    "sg:postcode":"1040",
    "sg:province":"Bruxelles-Capitale",
    "wof:name":"Kenes International",
    "wof:placetype":"venue"
},
  "geometry": {"coordinates":[4.3896331787,50.831943512],"type":"Point"}
}