{
  "type": "Feature",
  "properties": {
    "addr:full":"Rue Samuel Manet 1 Le Roeulx (ville-sur-haine) Hainaut 7070",
    "addr:housenumber":"1",
    "addr:postcode":"7070",
    "addr:street":"Rue Samuel Manet",
    "iso:country":"BE",
    "sg:address":"Rue Samuel Manet 1",
    "sg:city":"Le Roeulx (ville-sur-haine)",
    "sg:classifiers":[
        {
            "category":"Building & Trades",
            "subcategory":"Electrical",
            "type":"Services"
        }
    ],
    "sg:phone":"+32 64 66 55 14",
    "sg:postcode":"7070",
    "sg:province":"Hainaut",
    "sg:tags":[
        "electric",
        "-",
        "housewiring",
        "contractor"
    ],
    "wof:name":"Lejeune M",
    "wof:placetype":"venue"
},
  "geometry": {"coordinates":[4.0544438362,50.4947357178],"type":"Point"}
}