{
  "type": "Feature",
  "properties": {
    "addr:full":"Boulevard G\u00c9n\u00c9ral Jacques 48 Elsene/ixelles Bruxelles-Capitale 1050",
    "addr:housenumber":"48",
    "addr:postcode":"1050",
    "addr:street":"Boulevard Ge\u0301Ne\u0301Ral Jacques",
    "iso:country":"BE",
    "sg:address":"Boulevard G\u00c9n\u00c9ral Jacques 48",
    "sg:city":"Elsene/ixelles",
    "sg:classifiers":[
        {
            "category":"Restaurant",
            "type":"Food & Drink"
        }
    ],
    "sg:phone":"+32 2 647 13 62",
    "sg:postcode":"1050",
    "sg:province":"Bruxelles-Capitale",
    "wof:name":"La Tourelle",
    "wof:placetype":"venue"
},
  "geometry": {"coordinates":[4.3790397644,50.8183059692],"type":"Point"}
}