{
  "type": "Feature",
  "properties": {
    "iso:country":"BE",
    "sg:address":"Rue Du Pensionnat 5",
    "sg:city":"Ath",
    "sg:orig_category":"Eleveurs de bovins",
    "sg:phone":"+32 68 28 38 18",
    "sg:postcode":"7803",
    "sg:province":"Hainaut",
    "wof:name":"Dominique Debleser",
    "wof:placetype":"venue"
},
  "geometry": {"coordinates":[3.7681910992,50.6463928223],"type":"Point"}
}