{
  "type": "Feature",
  "properties": {
    "iso:country":"BE",
    "sg:address":"Picardielaan 6",
    "sg:city":"Schilde",
    "sg:orig_category":"Instituts de beaut\u00e9",
    "sg:phone":"+32 3 384 04 06",
    "sg:postcode":"2970",
    "sg:province":"Antwerpen",
    "wof:name":"Instituut Bourbon",
    "wof:placetype":"venue"
},
  "geometry": {"coordinates":[4.5835499763,51.2428779602],"type":"Point"}
}