{
  "type": "Feature",
  "properties": {
    "iso:country":"BE",
    "sg:address":"Europalaan 27",
    "sg:city":"Hasselt",
    "sg:orig_category":"Mat\u00e9riel de T\u00e9l\u00e9communication",
    "sg:phone":"+32 11 23 37 84",
    "sg:postcode":"3500",
    "sg:province":"Limburg",
    "wof:name":"Gsm Car Center",
    "wof:placetype":"venue"
},
  "geometry": {"coordinates":[5.3445701599,50.9579696655],"type":"Point"}
}