{
  "type": "Feature",
  "properties": {
    "addr:full":"Prekelindenlaan 15 Sint-lambrechts-woluwe/woluwe-saint-lambert Bruxelles-Capitale 1200",
    "addr:housenumber":"15",
    "addr:postcode":"1200",
    "addr:street":"Prekelindenlaan",
    "iso:country":"BE",
    "sg:address":"Prekelindenlaan 15",
    "sg:city":"Sint-lambrechts-woluwe/woluwe-saint-lambert",
    "sg:orig_category":"Voertuigen",
    "sg:phone":"+32 2 735 74 26",
    "sg:postcode":"1200",
    "sg:province":"Bruxelles-Capitale",
    "wof:name":"Garage R De Leeuw/de Leeuw R.",
    "wof:placetype":"venue"
},
  "geometry": {"coordinates":[4.4105291367,50.8394546509],"type":"Point"}
}