{
  "type": "Feature",
  "properties": {
    "addr:full":"Chauss\u00e9e De Mons 19 Ath Hainaut 7800",
    "addr:housenumber":"19",
    "addr:postcode":"7800",
    "addr:street":"Chausse\u0301E De Mons",
    "iso:country":"BE",
    "sg:address":"Chauss\u00e9e De Mons 19",
    "sg:city":"Ath",
    "sg:classifiers":[
        {
            "category":"Health Services",
            "subcategory":"Dentist",
            "type":"Services"
        }
    ],
    "sg:phone":"+32 68 28 24 83",
    "sg:postcode":"7800",
    "sg:province":"Hainaut",
    "wof:name":"Michiels Martine",
    "wof:placetype":"venue"
},
  "geometry": {"coordinates":[3.7719891071,50.6258239746],"type":"Point"}
}