{
  "type": "Feature",
  "properties": {
    "addr:full":"Rue De La Vignette 187 Bruxelles (auderghem) Bruxelles-Capitale 1160",
    "addr:housenumber":"187",
    "addr:postcode":"1160",
    "addr:street":"Rue De La Vignette",
    "iso:country":"BE",
    "sg:address":"Rue De La Vignette 187",
    "sg:city":"Bruxelles (auderghem)",
    "sg:classifiers":[
        {
            "category":"Government",
            "subcategory":"Fire Station",
            "type":"Public Place"
        }
    ],
    "sg:phone":"+32 2 675 66 74",
    "sg:postcode":"1160",
    "sg:province":"Bruxelles-Capitale",
    "sg:tags":[
        "water",
        "restoration",
        "damage"
    ],
    "wof:name":"Brucco Sa",
    "wof:placetype":"venue"
},
  "geometry": {"coordinates":[4.4199399948,50.8146858215],"type":"Point"}
}