{
  "type": "Feature",
  "properties": {
    "iso:country":"BE",
    "sg:address":"Devoghelin 7",
    "sg:city":"Lennik",
    "sg:orig_category":"Mat\u00e9riel de T\u00e9l\u00e9communication",
    "sg:phone":"+32 2 532 11 11",
    "sg:postcode":"1750",
    "sg:province":"Vlaams-Brabant",
    "wof:name":"Vipcom",
    "wof:placetype":"venue"
},
  "geometry": {"coordinates":[4.154654026,50.8054275513],"type":"Point"}
}