{
  "type": "Feature",
  "properties": {
    "addr:full":"Rue Joseph Wauters 59 Verviers Li\u00e8ge 4800",
    "addr:housenumber":"59",
    "addr:postcode":"4800",
    "addr:street":"Rue Joseph Wauters",
    "iso:country":"BE",
    "sg:address":"Rue Joseph Wauters 59",
    "sg:city":"Verviers",
    "sg:classifiers":[
        {
            "category":"Retail",
            "subcategory":"Emissions Testing",
            "type":"Services"
        }
    ],
    "sg:phone":"+32 87 22 35 37",
    "sg:postcode":"4800",
    "sg:province":"Li\u00e8ge",
    "sg:tags":[
        "consulting",
        "iso"
    ],
    "wof:name":"Eurologistics S.p.r.l.",
    "wof:placetype":"venue"
},
  "geometry": {"coordinates":[5.8719577789,50.5826301575],"type":"Point"}
}