{
  "type": "Feature",
  "properties": {
    "addr:full":"Renaat Desmedtstraat 1 Staden West-Vlaanderen 8840",
    "addr:housenumber":"1",
    "addr:postcode":"8840",
    "addr:street":"Renaat Desmedtstraat",
    "iso:country":"BE",
    "sg:address":"Renaat Desmedtstraat 1",
    "sg:city":"Staden",
    "sg:orig_category":"Banken and kredietinstellingen",
    "sg:phone":"+32 51 70 15 93",
    "sg:postcode":"8840",
    "sg:province":"West-Vlaanderen",
    "wof:name":"Landbouwkrediet",
    "wof:placetype":"venue"
},
  "geometry": {"coordinates":[3.0206260681,50.9828681946],"type":"Point"}
}