{
  "type": "Feature",
  "properties": {
    "addr:full":"Industrieweg 6 Aartselaar Antwerpen 2630",
    "addr:housenumber":"6",
    "addr:postcode":"2630",
    "addr:street":"Industrieweg",
    "iso:country":"BE",
    "sg:address":"Industrieweg 6",
    "sg:city":"Aartselaar",
    "sg:classifiers":[
        {
            "category":"Shopping",
            "type":"Retail Goods"
        }
    ],
    "sg:phone":"+32 3 870 70 90",
    "sg:postcode":"2630",
    "sg:province":"Antwerpen",
    "sg:tags":[
        "product",
        "cleaning",
        "maintenance"
    ],
    "wof:name":"W.v.t. Industries",
    "wof:placetype":"venue"
},
  "geometry": {"coordinates":[4.3698167801,51.1291618347],"type":"Point"}
}