{
  "type": "Feature",
  "properties": {
    "iso:country":"BE",
    "sg:address":"Rue Constant Deraedt 26",
    "sg:city":"Wavre",
    "sg:classifiers":[
        {
            "category":"Fast Food",
            "type":"Food & Drink"
        }
    ],
    "sg:phone":"+32 10 24 27 29",
    "sg:postcode":"1300",
    "sg:province":"Brabant Wallon",
    "sg:tags":[
        "\u00c0",
        "emporter",
        "restaurants"
    ],
    "wof:name":"Restaurant Pyramide",
    "wof:placetype":"venue"
},
  "geometry": {"coordinates":[4.6110568047,50.7156181335],"type":"Point"}
}