{
  "type": "Feature",
  "properties": {
    "addr:full":"Place Albert Ier 28 Charleroi Hainaut 6061",
    "addr:housenumber":"28",
    "addr:postcode":"6061",
    "addr:street":"Place Albert Ier;Hainaut",
    "iso:country":"BE",
    "sg:address":"Place Albert Ier 28",
    "sg:city":"Charleroi",
    "sg:orig_category":"Brood, gebak and snoepgoed",
    "sg:phone":"+32 71 31 28 46",
    "sg:postcode":"6061",
    "sg:province":"Hainaut",
    "wof:name":"Ets. Christiaens & Fils",
    "wof:placetype":"venue"
},
  "geometry": {"coordinates":[4.4793200493,50.4008979797],"type":"Point"}
}