{
  "type": "Feature",
  "properties": {
    "addr:full":"Leuvensesteenweg 10 Vilvoorde Vlaams-Brabant 1800",
    "addr:housenumber":"10",
    "addr:postcode":"1800",
    "addr:street":"Leuvensesteenweg",
    "iso:country":"BE",
    "sg:address":"Leuvensesteenweg 10",
    "sg:city":"Vilvoorde",
    "sg:classifiers":[
        {
            "category":"Retail",
            "subcategory":"Repair Shop",
            "type":"Services"
        }
    ],
    "sg:phone":"+32 2 251 26 43",
    "sg:postcode":"1800",
    "sg:province":"Vlaams-Brabant",
    "sg:tags":[
        "-",
        "mainten",
        "watch",
        "clock"
    ],
    "wof:name":"Patyn",
    "wof:placetype":"venue"
},
  "geometry": {"coordinates":[4.4355998039,50.9279785156],"type":"Point"}
}