{
  "type": "Feature",
  "properties": {
    "addr:full":"Boulevard Emile De Laveleye 140 Li\u00e8ge 1 (li\u00e8ge 2) Li\u00e8ge 4020",
    "addr:housenumber":"140;1;2",
    "addr:postcode":"4020",
    "addr:street":"Boulevard Emile De Laveleye",
    "iso:country":"BE",
    "sg:address":"Boulevard Emile De Laveleye 140",
    "sg:city":"Li\u00e8ge 1 (li\u00e8ge 2)",
    "sg:classifiers":[
        {
            "category":"Professional",
            "subcategory":"Testing Lab",
            "type":"Services"
        }
    ],
    "sg:phone":"+32 4 342 02 30",
    "sg:postcode":"4020",
    "sg:province":"Li\u00e8ge",
    "sg:tags":[
        "chemist"
    ],
    "wof:name":"Nollet G",
    "wof:placetype":"venue"
},
  "geometry": {"coordinates":[5.5911440849,50.6191482544],"type":"Point"}
}