{
  "type": "Feature",
  "properties": {
    "addr:full":"Avenue De La Ch\u00eanaie 55 Bruxelles (uccle) Bruxelles-Capitale 1180",
    "addr:housenumber":"55",
    "addr:postcode":"1180",
    "addr:street":"Avenue De La Che\u0302Naie",
    "iso:country":"BE",
    "sg:address":"Avenue De La Ch\u00eanaie 55",
    "sg:city":"Bruxelles (uccle)",
    "sg:classifiers":[
        {
            "category":"Health Services",
            "subcategory":"Doctor",
            "type":"Services"
        }
    ],
    "sg:phone":"+32 2 374 47 64",
    "sg:postcode":"1180",
    "sg:province":"Bruxelles-Capitale",
    "sg:tags":[
        "medicinephysicians",
        "surgeon"
    ],
    "wof:name":"Bormans Jeannie",
    "wof:placetype":"venue"
},
  "geometry": {"coordinates":[4.3491802216,50.7906608582],"type":"Point"}
}