{
  "type": "Feature",
  "properties": {
    "iso:country":"BE",
    "sg:address":"Breugellaan 12",
    "sg:city":"Torhout",
    "sg:orig_category":"Entretien and r\u00e9parations de voitures",
    "sg:phone":"+32 50 22 11 42",
    "sg:postcode":"8820",
    "sg:province":"West-Vlaanderen",
    "wof:name":"Henk Sinnaeve",
    "wof:placetype":"venue"
},
  "geometry": {"coordinates":[3.1129059792,51.0700263977],"type":"Point"}
}