{
  "type": "Feature",
  "properties": {
    "iso:country":"BE",
    "sg:address":"Ch\u00c9e De La Lib\u00c9ration 9",
    "sg:city":"Mont-de-l'enclus",
    "sg:orig_category":"Maisons de repos and r\u00e9sidences",
    "sg:phone":"+32 69 45 48 97",
    "sg:postcode":"7750",
    "sg:province":"Hainaut",
    "wof:name":"Maison De Repos Emmaus",
    "wof:placetype":"venue"
},
  "geometry": {"coordinates":[2.6025109291,46.3370933533],"type":"Point"}
}