{
  "type": "Feature",
  "properties": {
    "iso:country":"BE",
    "sg:address":"Kortrijksestraat 41",
    "sg:city":"Harelbeke",
    "sg:classifiers":[
        {
            "category":"Fast Food",
            "type":"Food & Drink"
        }
    ],
    "sg:phone":"+32 56 72 71 46",
    "sg:postcode":"8530",
    "sg:province":"West-Vlaanderen",
    "sg:tags":[
        "\u00c0",
        "emporter",
        "restaurants"
    ],
    "wof:name":"Hong Kong Garden",
    "wof:placetype":"venue"
},
  "geometry": {"coordinates":[3.3064649105,50.8529815674],"type":"Point"}
}