{
  "type": "Feature",
  "properties": {
    "addr:full":"Rue Henri Bl\u00e8s 150 Namur Namur 5000",
    "addr:housenumber":"150",
    "addr:postcode":"5000",
    "addr:street":"Rue Henri Ble\u0300S",
    "iso:country":"BE",
    "sg:address":"Rue Henri Bl\u00e8s 150",
    "sg:city":"Namur",
    "sg:classifiers":[
        {
            "category":"Health Services",
            "subcategory":"Doctor",
            "type":"Services"
        }
    ],
    "sg:phone":"+32 81 73 61 52",
    "sg:postcode":"5000",
    "sg:province":"Namur",
    "sg:tags":[
        "medicinephysicians",
        "surgeon"
    ],
    "wof:name":"Dupuis Guy",
    "wof:placetype":"venue"
},
  "geometry": {"coordinates":[4.8407559395,50.4654273987],"type":"Point"}
}