{
  "type": "Feature",
  "properties": {
    "addr:full":"Stationsstraat 111 Beernem West-Vlaanderen 8730",
    "addr:housenumber":"111",
    "addr:postcode":"8730",
    "addr:street":"Stationsstraat",
    "iso:country":"BE",
    "sg:address":"Stationsstraat 111",
    "sg:city":"Beernem",
    "sg:classifiers":[
        {
            "category":"Professional",
            "subcategory":"Art Services",
            "type":"Services"
        }
    ],
    "sg:phone":"+32 50 79 09 70",
    "sg:postcode":"8730",
    "sg:province":"West-Vlaanderen",
    "sg:tags":[
        "photography",
        "reporting",
        "-"
    ],
    "wof:name":"Van Den Berghe Fotografie",
    "wof:placetype":"venue"
},
  "geometry": {"coordinates":[3.331058979,51.1302986145],"type":"Point"}
}