{
  "type": "Feature",
  "properties": {
    "addr:full":"Lanzerath 18 B\u00dcllingen/bullange Li\u00e8ge 4760",
    "addr:housenumber":"18",
    "addr:postcode":"4760",
    "addr:street":"Lanzerath",
    "iso:country":"BE",
    "sg:address":"Lanzerath 18",
    "sg:city":"B\u00dcllingen/bullange",
    "sg:orig_category":"Rundveehouders",
    "sg:phone":"+32 80 54 84 01",
    "sg:postcode":"4760",
    "sg:province":"Li\u00e8ge",
    "wof:name":"Haas",
    "wof:placetype":"venue"
},
  "geometry": {"coordinates":[6.3325719833,50.357170105],"type":"Point"}
}