{
  "type": "Feature",
  "properties": {
    "iso:country":"BE",
    "sg:address":"Voorstraat 6",
    "sg:city":"Kaprijke",
    "sg:orig_category":"S\u00e9curit\u00e9 sociale",
    "sg:phone":"+32 9 373 66 52",
    "sg:postcode":"9970",
    "sg:province":"Oost-Vlaanderen",
    "wof:name":"Christelijke Mutualiteit",
    "wof:placetype":"venue"
},
  "geometry": {"coordinates":[3.6157650948,51.2182235718],"type":"Point"}
}