{
  "type": "Feature",
  "properties": {
    "iso:country":"BE",
    "sg:address":"Boostraat 4",
    "sg:city":"Bertem",
    "sg:orig_category":"V\u00eatements",
    "sg:phone":"+32 16 48 01 06",
    "sg:postcode":"3060",
    "sg:province":"Vlaams-Brabant",
    "wof:name":"M & R Jeans",
    "wof:placetype":"venue"
},
  "geometry": {"coordinates":[4.6309361458,50.8663444519],"type":"Point"}
}