{
  "type": "Feature",
  "properties": {
    "iso:country":"BE",
    "sg:address":"Pr. Boudewijnlaan 152",
    "sg:city":"Edegem",
    "sg:orig_category":"Agences d'exp\u00e9dition",
    "sg:phone":"+32 3 457 69 25",
    "sg:postcode":"2650",
    "sg:province":"Antwerpen",
    "wof:name":"Indika",
    "wof:placetype":"venue"
},
  "geometry": {"coordinates":[4.4348869324,51.1487159729],"type":"Point"}
}