{
  "type": "Feature",
  "properties": {
    "addr:full":"Aragonialaan 6 Temse (steendorp) Oost-Vlaanderen 9140",
    "addr:housenumber":"6",
    "addr:postcode":"9140",
    "addr:street":"Aragonialaan",
    "iso:country":"BE",
    "sg:address":"Aragonialaan 6",
    "sg:city":"Temse (steendorp)",
    "sg:classifiers":[
        {
            "category":"Food & Beverages",
            "subcategory":"Groceries & Convenience Stores",
            "type":"Retail Goods"
        }
    ],
    "sg:phone":"+32 3 774 10 77",
    "sg:postcode":"9140",
    "sg:province":"Oost-Vlaanderen",
    "sg:tags":[
        "baker",
        "-",
        "ingredient"
    ],
    "wof:name":"Janssens-de Maeyer Bvba",
    "wof:placetype":"venue"
},
  "geometry": {"coordinates":[4.2703018188,51.1243591309],"type":"Point"}
}