{
  "type": "Feature",
  "properties": {
    "iso:country":"BE",
    "sg:address":"L\u00fctticher Strasse 242",
    "sg:city":"Kelmis",
    "sg:classifiers":[
        {
            "category":"Bars & Pubs",
            "type":"Food & Drink"
        }
    ],
    "sg:phone":"+32 87 65 78 38",
    "sg:postcode":"4720",
    "sg:province":"Li\u00e8ge",
    "wof:name":"Raskeller",
    "wof:placetype":"venue"
},
  "geometry": {"coordinates":[6.0129179955,50.7139778137],"type":"Point"}
}