{
  "type": "Feature",
  "properties": {
    "iso:country":"BE",
    "sg:address":"Route D'obourg 65",
    "sg:city":"Mons",
    "sg:orig_category":"Eleveurs de bovins",
    "sg:phone":"+32 65 36 23 02",
    "sg:postcode":"7000",
    "sg:province":"Hainaut",
    "wof:name":"Haliba C.i.a.",
    "wof:placetype":"venue"
},
  "geometry": {"coordinates":[3.9900619984,50.4595680237],"type":"Point"}
}