{
  "type": "Feature",
  "properties": {
    "iso:country":"BE",
    "sg:address":"Brouwersvliet 33",
    "sg:city":"Antwerpen",
    "sg:orig_category":"Sociale secretariaten",
    "sg:phone":"+32 3 221 97 11",
    "sg:postcode":"2000",
    "sg:province":"Antwerpen",
    "wof:name":"Compens.kas Bestaanszek.",
    "wof:placetype":"venue"
},
  "geometry": {"coordinates":[4.4038081169,51.2272186279],"type":"Point"}
}