{
  "type": "Feature",
  "properties": {
    "addr:full":"Rue Du Ry D'amour 20 Fleurus Hainaut 6220",
    "addr:housenumber":"20",
    "addr:postcode":"6220",
    "addr:street":"Rue Du Ry D'Amour",
    "iso:country":"BE",
    "sg:address":"Rue Du Ry D'amour 20",
    "sg:city":"Fleurus",
    "sg:classifiers":[
        {
            "category":"Professional",
            "subcategory":"Accounting & Tax Preparation",
            "type":"Services"
        }
    ],
    "sg:phone":"+32 71 81 53 61",
    "sg:postcode":"6220",
    "sg:province":"Hainaut",
    "sg:tags":[
        "accountant"
    ],
    "wof:name":"Michel Dejaiffe",
    "wof:placetype":"venue"
},
  "geometry": {"coordinates":[4.5602707863,50.4876937866],"type":"Point"}
}