{
  "type": "Feature",
  "properties": {
    "addr:full":"Rue Du Champ Du Loup 35 Lobbes Hainaut 6540",
    "addr:housenumber":"35",
    "addr:postcode":"6540",
    "addr:street":"Rue Du Champ Du Loup",
    "iso:country":"BE",
    "sg:address":"Rue Du Champ Du Loup 35",
    "sg:city":"Lobbes",
    "sg:orig_category":"Location d'appareils audio-visuels",
    "sg:phone":"+32 71 59 22 44",
    "sg:postcode":"6540",
    "sg:province":"Hainaut",
    "wof:name":"Light And Sound Developm.",
    "wof:placetype":"venue"
},
  "geometry": {"coordinates":[4.2788639069,50.3561935425],"type":"Point"}
}