{
  "type": "Feature",
  "properties": {
    "iso:country":"BE",
    "sg:address":"Klein Appelstraat 13",
    "sg:city":"Haacht",
    "sg:classifiers":[
        {
            "category":"Building & Trades",
            "subcategory":"Construction",
            "type":"Services"
        }
    ],
    "sg:phone":"+32 16 60 05 74",
    "sg:postcode":"3150",
    "sg:province":"Vlaams-Brabant",
    "sg:tags":[
        "stucco",
        "contractor"
    ],
    "wof:name":"Aannemer Bezettingswerken S&v Bvba",
    "wof:placetype":"venue"
},
  "geometry": {"coordinates":[4.6341409683,50.980556488],"type":"Point"}
}