{
  "type": "Feature",
  "properties": {
    "addr:full":"Noordstraat 5 Veurne West-Vlaanderen 8630",
    "addr:housenumber":"5",
    "addr:postcode":"8630",
    "addr:street":"Noordstraat",
    "iso:country":"BE",
    "sg:address":"Noordstraat 5",
    "sg:city":"Veurne",
    "sg:classifiers":[
        {
            "category":"Personal",
            "subcategory":"Beauty Salon",
            "type":"Services"
        }
    ],
    "sg:phone":"+32 58 31 31 26",
    "sg:postcode":"8630",
    "sg:province":"West-Vlaanderen",
    "sg:tags":[
        "de",
        "coiffure"
    ],
    "wof:name":"Coiffure Isabelle",
    "wof:placetype":"venue"
},
  "geometry": {"coordinates":[2.6626501083,51.0729904175],"type":"Point"}
}