{
  "type": "Feature",
  "properties": {
    "iso:country":"BE",
    "sg:address":"Brusselsesteenweg 28",
    "sg:city":"Mechelen",
    "sg:classifiers":[
        {
            "category":"Shopping",
            "subcategory":"Florist",
            "type":"Retail Goods"
        }
    ],
    "sg:phone":"+32 15 34 55 66",
    "sg:postcode":"2800",
    "sg:province":"Antwerpen",
    "wof:name":"Lisbet Riesterer",
    "wof:placetype":"venue"
},
  "geometry": {"coordinates":[4.4723892212,51.0199699402],"type":"Point"}
}