{
  "type": "Feature",
  "properties": {
    "iso:country":"BE",
    "sg:address":"Woestenstraat 29",
    "sg:city":"Vleteren",
    "sg:orig_category":"Eleveurs and marchands de porcs. Eleveurs de bovins",
    "sg:phone":"+32 57 40 01 08",
    "sg:postcode":"8640",
    "sg:province":"West-Vlaanderen",
    "wof:name":"Hubert Sampers",
    "wof:placetype":"venue"
},
  "geometry": {"coordinates":[2.7410759926,50.9289550781],"type":"Point"}
}