{
  "type": "Feature",
  "properties": {
    "addr:full":"Kouterstraat 8a Zottegem (elene - Oombergen) Oost-Vlaanderen 9620",
    "addr:housenumber":"8a",
    "addr:postcode":"9620",
    "addr:street":"Kouterstraat;Oost-Vlaanderen",
    "iso:country":"BE",
    "sg:address":"Kouterstraat 8a",
    "sg:city":"Zottegem (elene - Oombergen)",
    "sg:classifiers":[
        {
            "category":"Home & Garden",
            "subcategory":"Building Materials",
            "type":"Retail Goods"
        }
    ],
    "sg:phone":"+32 9 360 77 55",
    "sg:postcode":"9620",
    "sg:province":"Oost-Vlaanderen",
    "sg:tags":[
        "window"
    ],
    "wof:name":"Kegeda",
    "wof:placetype":"venue"
},
  "geometry": {"coordinates":[3.8112111092,50.871181488],"type":"Point"}
}