{
  "type": "Feature",
  "properties": {
    "iso:country":"BE",
    "sg:address":"Jan Tieboutstraat 9",
    "sg:city":"Asse",
    "sg:orig_category":"Loodgieterij, verwarming and sanitaire installaties",
    "sg:phone":"+32 2 463 19 34",
    "sg:postcode":"1731",
    "sg:province":"Vlaams-Brabant",
    "wof:name":"T Dejan En Cie",
    "wof:placetype":"venue"
},
  "geometry": {"coordinates":[4.2888469696,50.8748321533],"type":"Point"}
}