{
  "type": "Feature",
  "properties": {
    "iso:country":"BE",
    "sg:address":"Dorpstraat 6",
    "sg:city":"Huldenberg",
    "sg:orig_category":"G\u00e9om\u00e8tres",
    "sg:phone":"+32 16 47 37 61",
    "sg:postcode":"3040",
    "sg:province":"Vlaams-Brabant",
    "wof:name":"Jan Van Meerbeek",
    "wof:placetype":"venue"
},
  "geometry": {"coordinates":[4.6287150383,50.8188819885],"type":"Point"}
}