{
  "type": "Feature",
  "properties": {
    "iso:country":"BE",
    "sg:address":"Vogelsancklaan 270",
    "sg:city":"Zonhoven",
    "sg:classifiers":[
        {
            "category":"Banks & Credit Unions",
            "subcategory":"Investment Brokerage",
            "type":"Services"
        }
    ],
    "sg:phone":"+32 11 81 37 50",
    "sg:postcode":"3520",
    "sg:province":"Limburg",
    "sg:tags":[
        "fence"
    ],
    "wof:name":"Baeten W",
    "wof:placetype":"venue"
},
  "geometry": {"coordinates":[5.331474781,50.9995117188],"type":"Point"}
}