{
  "type": "Feature",
  "properties": {
    "addr:full":"Chauss\u00c9e De Charleroi 145 Gembloux Namur 5030",
    "addr:housenumber":"145",
    "addr:postcode":"5030",
    "addr:street":"Chausse\u0301E De Charleroi;Namur",
    "iso:country":"BE",
    "sg:address":"Chauss\u00c9e De Charleroi 145",
    "sg:city":"Gembloux",
    "sg:orig_category":"Clubs de sport. Installations and terrains de sport hors centres sportifs. Clubs de sport",
    "sg:phone":"+32 81 61 46 34",
    "sg:postcode":"5030",
    "sg:province":"Namur",
    "wof:name":"B.c. Le Leader",
    "wof:placetype":"venue"
},
  "geometry": {"coordinates":[4.6829199791,50.5614318848],"type":"Point"}
}