{
  "type": "Feature",
  "properties": {
    "addr:full":"Chauss\u00c9e De Charleroi 13-133 Beaumont Hainaut 6511",
    "addr:postcode":"13-133;6511",
    "addr:street":"Chausse\u0301E De Charleroi;Hainaut",
    "iso:country":"BE",
    "sg:address":"Chauss\u00c9e De Charleroi 13-133",
    "sg:city":"Beaumont",
    "sg:orig_category":"Voertuigen",
    "sg:phone":"+32 71 53 30 89",
    "sg:postcode":"6511",
    "sg:province":"Hainaut",
    "wof:name":"Garage Gillard",
    "wof:placetype":"venue"
},
  "geometry": {"coordinates":[4.2766609192,50.2640609741],"type":"Point"}
}