{
  "type": "Feature",
  "properties": {
    "addr:full":"Teschlaan 2 Box 1 Hasselt Limburg 3500",
    "addr:housenumber":"2;1",
    "addr:postcode":"3500",
    "addr:street":"Teschlaan;Box",
    "iso:country":"BE",
    "sg:address":"Teschlaan 2 Box 1",
    "sg:city":"Hasselt",
    "sg:classifiers":[
        {
            "category":"Professional",
            "subcategory":"Management & Consulting",
            "type":"Services"
        }
    ],
    "sg:phone":"+32 11 27 29 82",
    "sg:postcode":"3500",
    "sg:province":"Limburg",
    "sg:tags":[
        "tax-consultants"
    ],
    "wof:name":"Beusen F",
    "wof:placetype":"venue"
},
  "geometry": {"coordinates":[5.331401825,50.9202346802],"type":"Point"}
}