{
  "type": "Feature",
  "properties": {
    "iso:country":"BE",
    "sg:address":"Rue De Val-dieu 45",
    "sg:city":"Aubel",
    "sg:classifiers":[
        {
            "category":"Building & Trades",
            "subcategory":"Construction",
            "type":"Services"
        }
    ],
    "sg:phone":"+32 87 68 65 59",
    "sg:postcode":"4880",
    "sg:province":"Li\u00e8ge",
    "sg:tags":[
        "carpenter"
    ],
    "wof:name":"P\u00e9r\u00e9e J",
    "wof:placetype":"venue"
},
  "geometry": {"coordinates":[5.7995300293,50.7027397156],"type":"Point"}
}