{
  "type": "Feature",
  "properties": {
    "iso:country":"BE",
    "sg:address":"Pas 83",
    "sg:city":"Geel",
    "sg:orig_category":"Agences de voyages",
    "sg:phone":"+32 14 58 12 24",
    "sg:postcode":"2440",
    "sg:province":"Antwerpen",
    "wof:name":"Reizen Boschmans",
    "wof:placetype":"venue"
},
  "geometry": {"coordinates":[4.9892201424,51.1590270996],"type":"Point"}
}