{
  "type": "Feature",
  "properties": {
    "addr:full":"Brusselsesteenweg 701 Gent Oost-Vlaanderen 9050",
    "addr:housenumber":"701",
    "addr:postcode":"9050",
    "addr:street":"Brusselsesteenweg;Oost-Vlaanderen",
    "iso:country":"BE",
    "sg:address":"Brusselsesteenweg 701",
    "sg:city":"Gent",
    "sg:orig_category":"Antiquit\u00e9s",
    "sg:phone":"+32 9 329 50 28",
    "sg:postcode":"9050",
    "sg:province":"Oost-Vlaanderen",
    "wof:name":"Antiek Brocante Curiosia",
    "wof:placetype":"venue"
},
  "geometry": {"coordinates":[3.7656650543,51.0295600891],"type":"Point"}
}