{
  "type": "Feature",
  "properties": {
    "addr:full":"Avenue Houba De Strooper 696 Laeken Bruxelles-Capitale 1020",
    "addr:housenumber":"696",
    "addr:postcode":"1020",
    "addr:street":"Avenue Houba De Strooper",
    "iso:country":"BE",
    "sg:address":"Avenue Houba De Strooper 696",
    "sg:city":"Laeken",
    "sg:orig_category":"Plomberie, chauffage and installations sanitaires",
    "sg:phone":"+32 476 55 09 75",
    "sg:postcode":"1020",
    "sg:province":"Bruxelles-Capitale",
    "wof:name":"Van P\u00c9",
    "wof:placetype":"venue"
},
  "geometry": {"coordinates":[4.3282880783,50.896686554],"type":"Point"}
}