{
  "type": "Feature",
  "properties": {
    "iso:country":"BE",
    "sg:address":"Veldenbergstraat 27",
    "sg:city":"Merksplas",
    "sg:orig_category":"Schoonheidssalons",
    "sg:phone":"+32 14 63 55 58",
    "sg:postcode":"2330",
    "sg:province":"Antwerpen",
    "wof:name":"Pedicure Gaya",
    "wof:placetype":"venue"
},
  "geometry": {"coordinates":[4.8490319252,51.3616714478],"type":"Point"}
}