{
  "type": "Feature",
  "properties": {
    "iso:country":"BE",
    "sg:address":"Chauss\u00e9e Du Pont Du Sart 111",
    "sg:city":"La Louvi\u00e8re (houdeng-aimeries)",
    "sg:classifiers":[
        {
            "category":"Shopping",
            "subcategory":"Books",
            "type":"Retail Goods"
        }
    ],
    "sg:phone":"+32 64 26 70 06",
    "sg:postcode":"7110",
    "sg:province":"Hainaut",
    "sg:tags":[
        "bookseller"
    ],
    "wof:name":"Catalano C",
    "wof:placetype":"venue"
},
  "geometry": {"coordinates":[4.1505050659,50.4826698303],"type":"Point"}
}