{
  "type": "Feature",
  "properties": {
    "addr:full":"Langestraat 33b1 Blankenberge West-Vlaanderen 8370",
    "addr:housenumber":"33b1",
    "addr:postcode":"8370",
    "addr:street":"Langestraat",
    "iso:country":"BE",
    "sg:address":"Langestraat 33b1",
    "sg:city":"Blankenberge",
    "sg:classifiers":[
        {
            "category":"Food & Beverages",
            "subcategory":"Fruits & Vegetables",
            "type":"Retail Goods"
        }
    ],
    "sg:phone":"+32 50 42 66 23",
    "sg:postcode":"8370",
    "sg:province":"West-Vlaanderen",
    "sg:tags":[
        "groenten"
    ],
    "wof:name":"All Vitamine",
    "wof:placetype":"venue"
},
  "geometry": {"coordinates":[3.1283419132,51.3146858215],"type":"Point"}
}