{
  "type": "Feature",
  "properties": {
    "addr:full":"Grand'rue 128 Tintigny Luxembourg 6730",
    "addr:housenumber":"128",
    "addr:postcode":"6730",
    "addr:street":"Grand'Rue",
    "iso:country":"BE",
    "sg:address":"Grand'rue 128",
    "sg:city":"Tintigny",
    "sg:classifiers":[
        {
            "category":"Retail",
            "subcategory":"Auto Repair",
            "type":"Services"
        }
    ],
    "sg:phone":"+32 63 44 47 22",
    "sg:postcode":"6730",
    "sg:province":"Luxembourg",
    "sg:tags":[
        "automobile-body"
    ],
    "wof:name":"Orban Garage Sprl",
    "wof:placetype":"venue"
},
  "geometry": {"coordinates":[5.519217968,49.6826286316],"type":"Point"}
}