{
  "type": "Feature",
  "properties": {
    "iso:country":"BE",
    "sg:address":"Bellevuestraat 1",
    "sg:city":"Izegem",
    "sg:classifiers":[
        {
            "category":"Health Services",
            "subcategory":"Dentist",
            "type":"Services"
        }
    ],
    "sg:phone":"+32 51 30 57 61",
    "sg:postcode":"8870",
    "sg:province":"West-Vlaanderen",
    "wof:name":"Devolder J",
    "wof:placetype":"venue"
},
  "geometry": {"coordinates":[3.2062189579,50.9198951721],"type":"Point"}
}