{
  "type": "Feature",
  "properties": {
    "iso:country":"BE",
    "sg:address":"Veldstraat 39",
    "sg:city":"Balen",
    "sg:orig_category":"Pain, p\u00e2tisseries and confiseries",
    "sg:phone":"+32 14 30 04 05",
    "sg:postcode":"2491",
    "sg:province":"Antwerpen",
    "wof:name":"Henri Geys",
    "wof:placetype":"venue"
},
  "geometry": {"coordinates":[5.1540489197,51.1369819641],"type":"Point"}
}