{
  "type": "Feature",
  "properties": {
    "addr:full":"Rue Du Mus\u00e9e 1 Martelange Luxembourg 6630",
    "addr:housenumber":"1",
    "addr:postcode":"6630",
    "addr:street":"Rue Du Muse\u0301E",
    "iso:country":"BE",
    "sg:address":"Rue Du Mus\u00e9e 1",
    "sg:city":"Martelange",
    "sg:classifiers":[
        {
            "category":"Food & Beverages",
            "subcategory":"Groceries & Convenience Stores",
            "type":"Retail Goods"
        }
    ],
    "sg:phone":"+32 63 60 01 29",
    "sg:postcode":"6630",
    "sg:province":"Luxembourg",
    "sg:tags":[
        "grocer"
    ],
    "wof:name":"Zeippen J",
    "wof:placetype":"venue"
},
  "geometry": {"coordinates":[5.7381048203,49.8309936523],"type":"Point"}
}