{
  "type": "Feature",
  "properties": {
    "iso:country":"BE",
    "sg:address":"Stationsplein 9",
    "sg:city":"Zottegem",
    "sg:classifiers":[
        {
            "category":"Bars & Pubs",
            "type":"Food & Drink"
        }
    ],
    "sg:phone":"+32 9 360 00 12",
    "sg:postcode":"9620",
    "sg:province":"Oost-Vlaanderen",
    "wof:name":"Meileken",
    "wof:placetype":"venue"
},
  "geometry": {"coordinates":[3.8121409416,50.8690872192],"type":"Point"}
}