{
  "type": "Feature",
  "properties": {
    "addr:full":"Leopoldlei 36bc Heist-op-den-berg Antwerpen 2220",
    "addr:housenumber":"36bc",
    "addr:postcode":"2220",
    "addr:street":"Leopoldlei",
    "iso:country":"BE",
    "sg:address":"Leopoldlei 36bc",
    "sg:city":"Heist-op-den-berg",
    "sg:orig_category":"Foto-uitrusting Fotografen and fotostudio's",
    "sg:phone":"+32 15 24 91 92",
    "sg:postcode":"2220",
    "sg:province":"Antwerpen",
    "wof:name":"Jofoto",
    "wof:placetype":"venue"
},
  "geometry": {"coordinates":[4.7272701263,51.0778312683],"type":"Point"}
}