{
  "type": "Feature",
  "properties": {
    "addr:full":"Rue F\u00e9lix Chaumont 41 Herstal Li\u00e8ge 4040",
    "addr:housenumber":"41",
    "addr:postcode":"4040",
    "addr:street":"Rue Fe\u0301Lix Chaumont",
    "iso:country":"BE",
    "sg:address":"Rue F\u00e9lix Chaumont 41",
    "sg:city":"Herstal",
    "sg:classifiers":[
        {
            "category":"Retail",
            "subcategory":"Auto Repair",
            "type":"Services"
        }
    ],
    "sg:phone":"+32 4 264 41 22",
    "sg:postcode":"4040",
    "sg:province":"Li\u00e8ge",
    "sg:tags":[
        "automobile-body"
    ],
    "wof:name":"Carrosserie Alexandris A",
    "wof:placetype":"venue"
},
  "geometry": {"coordinates":[5.6224808693,50.663974762],"type":"Point"}
}