{
  "type": "Feature",
  "properties": {
    "addr:full":"Waversesteenweg 8 Hoeilaart Vlaams-Brabant 1560",
    "addr:housenumber":"8",
    "addr:postcode":"1560",
    "addr:street":"Waversesteenweg",
    "iso:country":"BE",
    "sg:address":"Waversesteenweg 8",
    "sg:city":"Hoeilaart",
    "sg:orig_category":"Kapsalons",
    "sg:phone":"+32 2 657 98 09",
    "sg:postcode":"1560",
    "sg:province":"Vlaams-Brabant",
    "wof:name":"New Style",
    "wof:placetype":"venue"
},
  "geometry": {"coordinates":[4.4759478569,50.7662963867],"type":"Point"}
}