{
  "type": "Feature",
  "properties": {
    "iso:country":"BE",
    "sg:address":"Kerkstraat 6",
    "sg:city":"Melle",
    "sg:classifiers":[
        {
            "category":"Deli",
            "type":"Food & Drink"
        }
    ],
    "sg:phone":"+32 9 252 38 31",
    "sg:postcode":"9090",
    "sg:province":"Oost-Vlaanderen",
    "sg:tags":[
        "delicatessen"
    ],
    "wof:name":"Pedro Delicatessen",
    "wof:placetype":"venue"
},
  "geometry": {"coordinates":[3.8009290695,51.0036849976],"type":"Point"}
}