{
  "type": "Feature",
  "properties": {
    "iso:country":"BE",
    "sg:address":"Burgemeester Bollenstr. 9b1",
    "sg:city":"Hasselt",
    "sg:orig_category":"M\u00e9decins and sp\u00e9cialistes",
    "sg:phone":"+32 11 22 25 11",
    "sg:postcode":"3500",
    "sg:province":"Limburg",
    "wof:name":"J. Verhelst",
    "wof:placetype":"venue"
},
  "geometry": {"coordinates":[5.3327870369,50.9317932129],"type":"Point"}
}