{
  "type": "Feature",
  "properties": {
    "iso:country":"BE",
    "sg:address":"Rue Louis Hymans 40b3",
    "sg:city":"Elsene/ixelles",
    "sg:orig_category":"M\u00e9decins and sp\u00e9cialistes",
    "sg:phone":"+32 2 346 61 69",
    "sg:postcode":"1050",
    "sg:province":"Bruxelles-Capitale",
    "wof:name":"Claude Haber",
    "wof:placetype":"venue"
},
  "geometry": {"coordinates":[4.3554649353,50.8171272278],"type":"Point"}
}