{
  "type": "Feature",
  "properties": {
    "iso:country":"BE",
    "sg:address":"Frans Oomsplein 1",
    "sg:city":"Hoevenen",
    "sg:orig_category":"Disneyland Paris. Agences de voyages",
    "sg:phone":"+32 3 605 32 72",
    "sg:postcode":"2940",
    "sg:province":"Antwerpen",
    "wof:name":"Stabroek Travel - Hoevens",
    "wof:placetype":"venue"
},
  "geometry": {"coordinates":[4.4049301147,51.3067092896],"type":"Point"}
}