{
  "type": "Feature",
  "properties": {
    "iso:country":"BE",
    "sg:address":"Galerie De La Porte De Namur 25",
    "sg:city":"Elsene",
    "sg:orig_category":"Magasins de r\u00e9parations d'articles personnels et m\u00e9nagers divers. V\u00eatements pour Dames",
    "sg:phone":"+32 2 512 55 81",
    "sg:postcode":"1050",
    "sg:province":"Bruxelles-Capitale",
    "wof:name":"Shireen's Boutique",
    "wof:placetype":"venue"
},
  "geometry": {"coordinates":[4.3627858162,50.8375511169],"type":"Point"}
}