{
  "type": "Feature",
  "properties": {
    "addr:full":"Rue De Binche 87 Quaregnon Hainaut 7390",
    "addr:housenumber":"87",
    "addr:postcode":"7390",
    "addr:street":"Rue De Binche",
    "iso:country":"BE",
    "sg:address":"Rue De Binche 87",
    "sg:city":"Quaregnon",
    "sg:classifiers":[
        {
            "category":"Building & Trades",
            "subcategory":"Construction",
            "type":"Services"
        }
    ],
    "sg:phone":"+32 65 88 67 04",
    "sg:postcode":"7390",
    "sg:province":"Hainaut",
    "sg:tags":[
        "installation",
        "-",
        "central",
        "heating"
    ],
    "wof:name":"Dieu G-l",
    "wof:placetype":"venue"
},
  "geometry": {"coordinates":[3.8709750175,50.4131355286],"type":"Point"}
}