{
  "type": "Feature",
  "properties": {
    "addr:full":"Avenue De La Marmotte 103 Wezembeek-oppem Vlaams-Brabant 1970",
    "addr:housenumber":"103",
    "addr:postcode":"1970",
    "addr:street":"Avenue De La Marmotte",
    "iso:country":"BE",
    "sg:address":"Avenue De La Marmotte 103",
    "sg:city":"Wezembeek-oppem",
    "sg:classifiers":[
        {
            "category":"Building & Trades",
            "subcategory":"Plumbing",
            "type":"Services"
        }
    ],
    "sg:phone":"+32 2 768 23 54",
    "sg:postcode":"1970",
    "sg:province":"Vlaams-Brabant",
    "sg:tags":[
        "repair",
        "mainten",
        "-",
        "central",
        "heating"
    ],
    "wof:name":"Vanbutsel C",
    "wof:placetype":"venue"
},
  "geometry": {"coordinates":[4.4974098206,50.8359031677],"type":"Point"}
}