{
  "type": "Feature",
  "properties": {
    "addr:full":"Eksaarde Dorp 72 Lokeren (eksaarde) Oost-Vlaanderen 9160",
    "addr:housenumber":"72",
    "addr:postcode":"9160",
    "addr:street":"Eksaarde Dorp;Lokeren Eksaarde Oost-Vlaanderen",
    "iso:country":"BE",
    "sg:address":"Eksaarde Dorp 72",
    "sg:city":"Lokeren (eksaarde)",
    "sg:classifiers":[
        {
            "category":"Building & Trades",
            "subcategory":"Electrical",
            "type":"Services"
        }
    ],
    "sg:phone":"+32 9 346 86 08",
    "sg:postcode":"9160",
    "sg:province":"Oost-Vlaanderen",
    "sg:tags":[
        "electric",
        "-",
        "housewiring",
        "contractor"
    ],
    "wof:name":"Puim\u00e9ge F Bvba",
    "wof:placetype":"venue"
},
  "geometry": {"coordinates":[3.9637329578,51.1203041077],"type":"Point"}
}