{
  "type": "Feature",
  "properties": {
    "iso:country":"BE",
    "sg:address":"Brusselsesteenweg 235b",
    "sg:city":"Lebbeke",
    "sg:classifiers":[
        {
            "category":"Autos & Motor Vehicles",
            "subcategory":"Fuel & Gas Station",
            "type":"Retail Goods"
        }
    ],
    "sg:phone":"+32 52 41 40 73",
    "sg:postcode":"9280",
    "sg:province":"Oost-Vlaanderen",
    "wof:name":"Buytaert B",
    "wof:placetype":"venue"
},
  "geometry": {"coordinates":[4.1384510994,50.9852828979],"type":"Point"}
}