{
  "type": "Feature",
  "properties": {
    "iso:country":"BE",
    "sg:address":"Kortrijkstraat 88",
    "sg:city":"Deinze",
    "sg:orig_category":"Catering and organisatie van feesten Fast food and meeneem restaurants Levering aan huis restaurants",
    "sg:phone":"+32 9 386 14 11",
    "sg:postcode":"9800",
    "sg:province":"Oost-Vlaanderen",
    "wof:name":"Carlo Taverne",
    "wof:placetype":"venue"
},
  "geometry": {"coordinates":[3.5274000168,50.9770240784],"type":"Point"}
}