{
  "type": "Feature",
  "properties": {
    "iso:country":"BE",
    "sg:address":"Rue Carl Jost 39",
    "sg:city":"Fl\u00e9ron (retinne)",
    "sg:classifiers":[
        {
            "category":"Building & Trades",
            "subcategory":"Plumbing",
            "type":"Services"
        }
    ],
    "sg:phone":"+32 4 358 77 84",
    "sg:postcode":"4621",
    "sg:province":"Li\u00e8ge",
    "sg:tags":[
        "repair",
        "mainten",
        "-",
        "central",
        "heating"
    ],
    "wof:name":"Ac Technique",
    "wof:placetype":"venue"
},
  "geometry": {"coordinates":[5.7078528404,50.6248207092],"type":"Point"}
}