{
  "type": "Feature",
  "properties": {
    "addr:full":"Waversesteenweg 1682 Brussel-auderghem Bruxelles-Capitale 1160",
    "addr:housenumber":"1682",
    "addr:postcode":"1160",
    "addr:street":"Waversesteenweg",
    "iso:country":"BE",
    "sg:address":"Waversesteenweg 1682",
    "sg:city":"Brussel-auderghem",
    "sg:classifiers":[
        {
            "category":"Retail",
            "subcategory":"Auto Rental",
            "type":"Services"
        }
    ],
    "sg:phone":"+32 2 660 15 39",
    "sg:postcode":"1160",
    "sg:province":"Bruxelles-Capitale",
    "sg:tags":[
        "mazda",
        "automobile",
        "v\u00e9hicules"
    ],
    "wof:name":"Car Technic S.a. Garage",
    "wof:placetype":"venue"
},
  "geometry": {"coordinates":[4.428647995,50.8161888123],"type":"Point"}
}