{
  "type": "Feature",
  "properties": {
    "iso:country":"BE",
    "sg:address":"Vissenheuvel 22",
    "sg:city":"Essen",
    "sg:classifiers":[
        {
            "category":"Building & Trades",
            "subcategory":"Cleaning & Sanitation",
            "type":"Services"
        }
    ],
    "sg:phone":"+32 3 667 35 94",
    "sg:postcode":"2910",
    "sg:province":"Antwerpen",
    "sg:tags":[
        "machine",
        "street",
        "maintenance"
    ],
    "wof:name":"Brosens (aannemersbedrijf)",
    "wof:placetype":"venue"
},
  "geometry": {"coordinates":[4.4914951324,51.440574646],"type":"Point"}
}