{
  "type": "Feature",
  "properties": {
    "iso:country":"BE",
    "sg:address":"Guido Gezellestraat 30",
    "sg:city":"Diest",
    "sg:orig_category":"Artsen and specialisten",
    "sg:phone":"+32 13 33 42 06",
    "sg:postcode":"3290",
    "sg:province":"Vlaams-Brabant",
    "wof:name":"Titia Swinnen",
    "wof:placetype":"venue"
},
  "geometry": {"coordinates":[5.053981781,50.9836654663],"type":"Point"}
}