{
  "type": "Feature",
  "properties": {
    "addr:full":"Eugenie Terlinckpl 17 Koksijde West-Vlaanderen 8670",
    "addr:housenumber":"17",
    "addr:postcode":"8670",
    "iso:country":"BE",
    "sg:address":"Eugenie Terlinckpl 17",
    "sg:city":"Koksijde",
    "sg:classifiers":[
        {
            "category":"Travel",
            "subcategory":"Hotels & Motels",
            "type":"Entertainment"
        }
    ],
    "sg:phone":"+32 58 52 00 00",
    "sg:postcode":"8670",
    "sg:province":"West-Vlaanderen",
    "sg:tags":[
        "hotels",
        "business",
        "restaurant"
    ],
    "wof:name":"Hotel Terlinck Koksijde Nv",
    "wof:placetype":"venue"
},
  "geometry": {"coordinates":[2.6336390972,51.1201629639],"type":"Point"}
}