{
  "type": "Feature",
  "properties": {
    "addr:full":"Dorpsstraat 67 Halen (zelem) Limburg 3545",
    "addr:housenumber":"67",
    "addr:postcode":"3545",
    "addr:street":"Dorpsstraat",
    "iso:country":"BE",
    "sg:address":"Dorpsstraat 67",
    "sg:city":"Halen (zelem)",
    "sg:classifiers":[
        {
            "category":"Health Services",
            "subcategory":"Health Practitioner",
            "type":"Services"
        }
    ],
    "sg:phone":"+32 13 44 10 59",
    "sg:postcode":"3545",
    "sg:province":"Limburg",
    "sg:tags":[
        "physiotherapist"
    ],
    "wof:name":"Boets Dirk",
    "wof:placetype":"venue"
},
  "geometry": {"coordinates":[5.1057472229,50.9776115417],"type":"Point"}
}