{
  "type": "Feature",
  "properties": {
    "iso:country":"BE",
    "sg:address":"Rue Des Trois Burettes 43",
    "sg:city":"Mont-saint-guibert",
    "sg:orig_category":"Ordinateurs and \u00e9quipement informatique",
    "sg:phone":"+32 10 65 07 15",
    "sg:postcode":"1435",
    "sg:province":"Brabant Wallon",
    "wof:name":"Control H",
    "wof:placetype":"venue"
},
  "geometry": {"coordinates":[4.6127200127,50.6451454163],"type":"Point"}
}