{
  "type": "Feature",
  "properties": {
    "addr:full":"Leiestraat 91 Kuurne West-Vlaanderen 8520",
    "addr:housenumber":"91",
    "addr:postcode":"8520",
    "addr:street":"Leiestraat",
    "iso:country":"BE",
    "sg:address":"Leiestraat 91",
    "sg:city":"Kuurne",
    "sg:classifiers":[
        {
            "category":"Insurance",
            "subcategory":"Life Insurance",
            "type":"Services"
        }
    ],
    "sg:phone":"+32 56 71 31 79",
    "sg:postcode":"8520",
    "sg:province":"West-Vlaanderen",
    "sg:tags":[
        "assurance"
    ],
    "wof:name":"Framas",
    "wof:placetype":"venue"
},
  "geometry": {"coordinates":[3.2888219357,50.8527946472],"type":"Point"}
}