{
  "type": "Feature",
  "properties": {
    "addr:full":"Rue De La Berwinne 5 Juprelle (lantin) Li\u00e8ge 4450",
    "addr:housenumber":"5",
    "addr:postcode":"4450",
    "addr:street":"Rue De La Berwinne;Lantin",
    "iso:country":"BE",
    "sg:address":"Rue De La Berwinne 5",
    "sg:city":"Juprelle (lantin)",
    "sg:classifiers":[
        {
            "category":"Building & Trades",
            "subcategory":"Construction",
            "type":"Services"
        }
    ],
    "sg:phone":"+32 4 263 04 83",
    "sg:postcode":"4450",
    "sg:province":"Li\u00e8ge",
    "sg:tags":[
        "stucco",
        "contractor"
    ],
    "wof:name":"Levenstond A",
    "wof:placetype":"venue"
},
  "geometry": {"coordinates":[5.5360121727,50.693321228],"type":"Point"}
}