{
  "type": "Feature",
  "properties": {
    "iso:country":"BE",
    "sg:address":"Schaberstraat 11",
    "sg:city":"Diepenbeek",
    "sg:orig_category":"Tuinen",
    "sg:phone":"+32 11 32 27 75",
    "sg:postcode":"3590",
    "sg:province":"Limburg",
    "wof:name":"Huismzns",
    "wof:placetype":"venue"
},
  "geometry": {"coordinates":[5.4192109108,50.920665741],"type":"Point"}
}