{
  "type": "Feature",
  "properties": {
    "addr:full":"Zuidlindestraat 18 Heuvelland (nieuwkerke) West-Vlaanderen 8950",
    "addr:housenumber":"18",
    "addr:postcode":"8950",
    "addr:street":"Zuidlindestraat",
    "iso:country":"BE",
    "sg:address":"Zuidlindestraat 18",
    "sg:city":"Heuvelland (nieuwkerke)",
    "sg:classifiers":[
        {
            "category":"Retail",
            "subcategory":"Event Space",
            "type":"Services"
        }
    ],
    "sg:phone":"+32 57 21 29 06",
    "sg:postcode":"8950",
    "sg:province":"West-Vlaanderen",
    "sg:tags":[
        "organisation"
    ],
    "wof:name":"Fland",
    "wof:placetype":"venue"
},
  "geometry": {"coordinates":[2.8485229015,50.7249832153],"type":"Point"}
}