{
  "type": "Feature",
  "properties": {
    "iso:country":"BE",
    "sg:address":"Dadizelestraat 5",
    "sg:city":"Wervik",
    "sg:orig_category":"Eleveurs de volaille",
    "sg:phone":"+32 56 51 45 39",
    "sg:postcode":"8940",
    "sg:province":"West-Vlaanderen",
    "wof:name":"Daniel Vanraes",
    "wof:placetype":"venue"
},
  "geometry": {"coordinates":[3.0860760212,50.8236083984],"type":"Point"}
}