{
  "type": "Feature",
  "properties": {
    "addr:full":"Rue Des Ecoles 8 Bastogne Luxembourg 6600",
    "addr:housenumber":"8",
    "addr:postcode":"6600",
    "addr:street":"Rue Des Ecoles",
    "iso:country":"BE",
    "sg:address":"Rue Des Ecoles 8",
    "sg:city":"Bastogne",
    "sg:classifiers":[
        {
            "category":"Education",
            "subcategory":"School",
            "type":"Public Place"
        }
    ],
    "sg:phone":"+32 61 21 22 14",
    "sg:postcode":"6600",
    "sg:province":"Luxembourg",
    "sg:tags":[
        "secondary"
    ],
    "wof:name":"Indse 1er Degr\u00e9 Asbl",
    "wof:placetype":"venue"
},
  "geometry": {"coordinates":[5.715681076,50.0023117065],"type":"Point"}
}