{
  "type": "Feature",
  "properties": {
    "addr:full":"Koninksemstraat 245 Tongeren Limburg 3700",
    "addr:housenumber":"245",
    "addr:postcode":"3700",
    "addr:street":"Koninksemstraat",
    "iso:country":"BE",
    "sg:address":"Koninksemstraat 245",
    "sg:city":"Tongeren",
    "sg:classifiers":[
        {
            "category":"Building & Trades",
            "subcategory":"Construction",
            "type":"Services"
        }
    ],
    "sg:phone":"+32 12 23 62 74",
    "sg:postcode":"3700",
    "sg:province":"Limburg",
    "sg:tags":[
        "carpenter"
    ],
    "wof:name":"Vandenbergh Jef & Kris Bvba",
    "wof:placetype":"venue"
},
  "geometry": {"coordinates":[5.451690197,50.7732810974],"type":"Point"}
}