{
  "type": "Feature",
  "properties": {
    "addr:full":"Avenue De L'atomium 347 Bruxelles Bruxelles-Capitale 1020",
    "addr:housenumber":"347",
    "addr:postcode":"1020",
    "addr:street":"Avenue De L'Atomium",
    "iso:country":"BE",
    "sg:address":"Avenue De L'atomium 347",
    "sg:city":"Bruxelles",
    "sg:orig_category":"Non-Classified Establishments",
    "sg:phone":"+32 2 479 77 47",
    "sg:postcode":"1020",
    "sg:province":"Bruxelles-Capitale",
    "wof:name":"Parastone Sprl",
    "wof:placetype":"venue"
},
  "geometry": {"coordinates":[4.3462300301,50.8855514526],"type":"Point"}
}