{
  "type": "Feature",
  "properties": {
    "addr:full":"Rue Modeste Carlier 64 Quaregnon Hainaut 7390",
    "addr:housenumber":"64",
    "addr:postcode":"7390",
    "addr:street":"Rue Modeste Carlier",
    "iso:country":"BE",
    "sg:address":"Rue Modeste Carlier 64",
    "sg:city":"Quaregnon",
    "sg:orig_category":"Artsen and specialisten",
    "sg:phone":"+32 65 79 45 01",
    "sg:postcode":"7390",
    "sg:province":"Hainaut",
    "wof:name":"Diane Vanderstukken",
    "wof:placetype":"venue"
},
  "geometry": {"coordinates":[3.86332798,50.4419517517],"type":"Point"}
}