{
  "type": "Feature",
  "properties": {
    "iso:country":"BE",
    "sg:address":"Rue Fran\u00e7ois Lapierre 28",
    "sg:city":"Fl\u00e9ron",
    "sg:classifiers":[
        {
            "category":"Health Services",
            "subcategory":"Health Practitioner",
            "type":"Services"
        }
    ],
    "sg:phone":"+32 4 358 63 44",
    "sg:postcode":"4620",
    "sg:province":"Li\u00e8ge",
    "sg:tags":[
        "physiotherapist"
    ],
    "wof:name":"Henvaux A-f",
    "wof:placetype":"venue"
},
  "geometry": {"coordinates":[5.6826400757,50.6181869507],"type":"Point"}
}