{
  "type": "Feature",
  "properties": {
    "iso:country":"BE",
    "sg:address":"Pont De Wiers 2",
    "sg:city":"P\u00e9ruwelz (wiers)",
    "sg:orig_category":"Rainwear",
    "sg:phone":"+32 69 77 27 70",
    "sg:postcode":"7608",
    "sg:province":"Hainaut",
    "wof:name":"Petit J-c",
    "wof:placetype":"venue"
},
  "geometry": {"coordinates":[3.5266089439,50.5254325867],"type":"Point"}
}