{
  "type": "Feature",
  "properties": {
    "addr:full":"Rue Du Paradis 45 Herstal Li\u00e8ge 4040",
    "addr:housenumber":"45",
    "addr:postcode":"4040",
    "addr:street":"Rue Du Paradis",
    "iso:country":"BE",
    "sg:address":"Rue Du Paradis 45",
    "sg:city":"Herstal",
    "sg:orig_category":"Sportclubs Sportterreinen and installaties behalve sportcentra",
    "sg:phone":"+32 4 240 31 28",
    "sg:postcode":"4040",
    "sg:province":"Li\u00e8ge",
    "wof:name":"F.c. R. Lorca Nord",
    "wof:placetype":"venue"
},
  "geometry": {"coordinates":[5.6186752319,50.6786766052],"type":"Point"}
}