{
  "type": "Feature",
  "properties": {
    "iso:country":"BE",
    "sg:address":"Lewastraat 1",
    "sg:city":"Zoutleeuw",
    "sg:orig_category":"Dakwerken Gespecialiseerde residenti\u00eble bouw",
    "sg:phone":"+32 11 78 21 02",
    "sg:postcode":"3440",
    "sg:province":"Vlaams-Brabant",
    "wof:name":"Mc Gevel- En Dakwerken",
    "wof:placetype":"venue"
},
  "geometry": {"coordinates":[5.1127300262,50.8301429749],"type":"Point"}
}