{
  "type": "Feature",
  "properties": {
    "addr:full":"Place De L'h\u00f4tel De Ville Chapelle-lez-herlaimont Hainaut 7160",
    "addr:postcode":"7160",
    "addr:street":"Place De L'Ho \u0302Tel De Ville;Hainaut",
    "iso:country":"BE",
    "sg:address":"Place De L'h\u00f4tel De Ville",
    "sg:city":"Chapelle-lez-herlaimont",
    "sg:classifiers":[
        {
            "category":"Organizations",
            "subcategory":"Community Association",
            "type":"Services"
        }
    ],
    "sg:phone":"+32 64 43 13 35",
    "sg:postcode":"7160",
    "sg:province":"Hainaut",
    "sg:tags":[
        "cultural"
    ],
    "wof:name":"Foyer Culturel D'herlaimont",
    "wof:placetype":"venue"
},
  "geometry": {"coordinates":[4.2810001373,50.4714698792],"type":"Point"}
}