{
  "type": "Feature",
  "properties": {
    "addr:full":"Rue As-pois 60 Tournai Hainaut 7500",
    "addr:housenumber":"60",
    "addr:postcode":"7500",
    "addr:street":"Rue As-Pois",
    "iso:country":"BE",
    "sg:address":"Rue As-pois 60",
    "sg:city":"Tournai",
    "sg:orig_category":"Installation de serres, double vitrage and fen\u00eatres",
    "sg:phone":"+32 69 22 23 16",
    "sg:postcode":"7500",
    "sg:province":"Hainaut",
    "wof:name":"Duvivier",
    "wof:placetype":"venue"
},
  "geometry": {"coordinates":[3.3839991093,50.6042633057],"type":"Point"}
}