{
  "type": "Feature",
  "properties": {
    "addr:full":"Astweg 4 Anzegem (ingooigem) West-Vlaanderen 8570",
    "addr:housenumber":"4",
    "addr:postcode":"8570",
    "addr:street":"Astweg",
    "iso:country":"BE",
    "sg:address":"Astweg 4",
    "sg:city":"Anzegem (ingooigem)",
    "sg:classifiers":[
        {
            "category":"Building & Trades",
            "subcategory":"Plumbing",
            "type":"Services"
        }
    ],
    "sg:phone":"+32 56 68 16 30",
    "sg:postcode":"8570",
    "sg:province":"West-Vlaanderen",
    "sg:tags":[
        "pipe",
        "drain",
        "unblocking"
    ],
    "wof:name":"Verbauwhede Bvba",
    "wof:placetype":"venue"
},
  "geometry": {"coordinates":[3.4478719234,50.8056335449],"type":"Point"}
}