{
  "type": "Feature",
  "properties": {
    "iso:country":"BE",
    "sg:address":"Markt 20",
    "sg:city":"Temse",
    "sg:orig_category":"M\u00e9decins and sp\u00e9cialistes",
    "sg:phone":"+32 3 771 04 11",
    "sg:postcode":"9140",
    "sg:province":"Oost-Vlaanderen",
    "wof:name":"Roger De Clerck",
    "wof:placetype":"venue"
},
  "geometry": {"coordinates":[4.2141361237,51.1236457825],"type":"Point"}
}