{
  "type": "Feature",
  "properties": {
    "iso:country":"BE",
    "sg:address":"Paradijzen 2",
    "sg:city":"Heist-op-den-berg",
    "sg:orig_category":"HERSTELLING ELEKTRISCHE HUISHOUDAPPARATEN Huishoudapparaten, televisies and radio's",
    "sg:phone":"+32 14 26 09 30",
    "sg:postcode":"2222",
    "sg:province":"Antwerpen",
    "wof:name":"Havermans Electro",
    "wof:placetype":"venue"
},
  "geometry": {"coordinates":[4.7292399406,51.1032218933],"type":"Point"}
}