{
  "type": "Feature",
  "properties": {
    "addr:full":"Hogebaan 2 Brecht Antwerpen 2960",
    "addr:housenumber":"2",
    "addr:postcode":"2960",
    "addr:street":"Hogebaan",
    "iso:country":"BE",
    "sg:address":"Hogebaan 2",
    "sg:city":"Brecht",
    "sg:orig_category":"Enseignement maternel and primaire",
    "sg:phone":"+32 3 666 12 29",
    "sg:postcode":"2960",
    "sg:province":"Antwerpen",
    "wof:name":"Vrije Bassischool",
    "wof:placetype":"venue"
},
  "geometry": {"coordinates":[4.5722842216,51.2981796265],"type":"Point"}
}