{
  "type": "Feature",
  "properties": {
    "iso:country":"BE",
    "sg:address":"Broekstraat 1c",
    "sg:city":"Herent (veltem-beisem)",
    "sg:classifiers":[
        {
            "category":"Professional",
            "subcategory":"Art Services",
            "type":"Services"
        }
    ],
    "sg:phone":"+32 16 49 00 77",
    "sg:postcode":"3020",
    "sg:province":"Vlaams-Brabant",
    "sg:tags":[
        "interior",
        "designer"
    ],
    "wof:name":"De Prins",
    "wof:placetype":"venue"
},
  "geometry": {"coordinates":[4.6749200821,50.9079055786],"type":"Point"}
}