{
  "type": "Feature",
  "properties": {
    "iso:country":"BE",
    "sg:address":"Wolvestraat 10",
    "sg:city":"Kortenberg",
    "sg:orig_category":"Boekhouders",
    "sg:postcode":"3078",
    "sg:province":"Vlaams-Brabant",
    "wof:name":"Leopold Rinchard",
    "wof:placetype":"venue"
},
  "geometry": {"coordinates":[4.5697798729,50.8790512085],"type":"Point"}
}