{
  "type": "Feature",
  "properties": {
    "addr:full":"Heikant 39 Arendonk Antwerpen 2370",
    "addr:housenumber":"39",
    "addr:postcode":"2370",
    "addr:street":"Heikant",
    "iso:country":"BE",
    "sg:address":"Heikant 39",
    "sg:city":"Arendonk",
    "sg:orig_category":"Royal Canin Tuinbenodigdheden",
    "sg:phone":"+32 14 67 70 30",
    "sg:postcode":"2370",
    "sg:province":"Antwerpen",
    "wof:name":"Smets Henri",
    "wof:placetype":"venue"
},
  "geometry": {"coordinates":[5.0795311928,51.3309593201],"type":"Point"}
}