{
  "type": "Feature",
  "properties": {
    "iso:country":"BE",
    "sg:address":"Panoramalaan 1",
    "sg:city":"Leuven",
    "sg:orig_category":"Fotografen and fotostudio's",
    "sg:phone":"+32 16 29 03 02",
    "sg:postcode":"3012",
    "sg:province":"Vlaams-Brabant",
    "wof:name":"Peter Verhaegen",
    "wof:placetype":"venue"
},
  "geometry": {"coordinates":[4.7038321495,50.8907279968],"type":"Point"}
}