{
  "type": "Feature",
  "properties": {
    "addr:full":"Lucasstraat 2 Staden West-Vlaanderen 8840",
    "addr:housenumber":"2",
    "addr:postcode":"8840",
    "addr:street":"Lucasstraat",
    "iso:country":"BE",
    "sg:address":"Lucasstraat 2",
    "sg:city":"Staden",
    "sg:orig_category":"Eleveurs de bovins",
    "sg:phone":"+32 51 70 21 77",
    "sg:postcode":"8840",
    "sg:province":"West-Vlaanderen",
    "wof:name":"Egfried Wyseur",
    "wof:placetype":"venue"
},
  "geometry": {"coordinates":[3.0104269981,50.9803314209],"type":"Point"}
}