{
  "type": "Feature",
  "properties": {
    "iso:country":"BE",
    "sg:address":"Wolvendreef 4",
    "sg:city":"Kortrijk",
    "sg:classifiers":[
        {
            "category":"Health Services",
            "subcategory":"Doctor",
            "type":"Services"
        }
    ],
    "sg:phone":"+32 56 32 55 12",
    "sg:postcode":"8500",
    "sg:province":"West-Vlaanderen",
    "sg:tags":[
        "medicinephysicians",
        "surgeon"
    ],
    "wof:name":"Colaert J",
    "wof:placetype":"venue"
},
  "geometry": {"coordinates":[3.2640790939,50.8129081726],"type":"Point"}
}