{
  "type": "Feature",
  "properties": {
    "addr:full":"Rue D'herchies 6 Jurbise (erbisoeul) Hainaut 7050",
    "addr:housenumber":"6",
    "addr:postcode":"7050",
    "addr:street":"Rue D'Herchies",
    "iso:country":"BE",
    "sg:address":"Rue D'herchies 6",
    "sg:city":"Jurbise (erbisoeul)",
    "sg:classifiers":[
        {
            "category":"Shopping",
            "subcategory":"Gifts & Souvenirs",
            "type":"Retail Goods"
        }
    ],
    "sg:phone":"+32 65 22 70 23",
    "sg:postcode":"7050",
    "sg:province":"Hainaut",
    "sg:tags":[
        "postcard",
        "picture",
        "greeting",
        "card"
    ],
    "wof:name":"Lotigier (maison)",
    "wof:placetype":"venue"
},
  "geometry": {"coordinates":[3.8844349384,50.5057296753],"type":"Point"}
}