{
  "type": "Feature",
  "properties": {
    "iso:country":"BE",
    "sg:address":"Luxemburghof 12",
    "sg:city":"Harelbeke",
    "sg:classifiers":[
        {
            "category":"Cafe",
            "type":"Food & Drink"
        }
    ],
    "sg:phone":"+32 56 72 70 88",
    "sg:postcode":"8530",
    "sg:province":"West-Vlaanderen",
    "sg:tags":[
        "caf\u00e9s"
    ],
    "wof:name":"Brigitte Vandenbogaerde",
    "wof:placetype":"venue"
},
  "geometry": {"coordinates":[3.3272230625,50.8563270569],"type":"Point"}
}