{
  "type": "Feature",
  "properties": {
    "addr:full":"Avenue Jeanne 33 Box 4 Bruxelles (ixelles) Bruxelles-Capitale 1050",
    "addr:housenumber":"33;4",
    "addr:postcode":"1050",
    "addr:street":"Avenue Jeanne;Box",
    "iso:country":"BE",
    "sg:address":"Avenue Jeanne 33 Box 4",
    "sg:city":"Bruxelles (ixelles)",
    "sg:classifiers":[
        {
            "category":"Professional",
            "subcategory":"Accounting & Tax Preparation",
            "type":"Services"
        }
    ],
    "sg:phone":"+32 2 649 68 88",
    "sg:postcode":"1050",
    "sg:province":"Bruxelles-Capitale",
    "sg:tags":[
        "bookkeeper"
    ],
    "wof:name":"Bureau B.c.a. Sc",
    "wof:placetype":"venue"
},
  "geometry": {"coordinates":[4.3786611557,50.8141937256],"type":"Point"}
}