{
  "type": "Feature",
  "properties": {
    "addr:full":"Brugsesteenweg 211 Kuurne West-Vlaanderen 8520",
    "addr:housenumber":"211",
    "addr:postcode":"8520",
    "addr:street":"Brugsesteenweg",
    "iso:country":"BE",
    "sg:address":"Brugsesteenweg 211",
    "sg:city":"Kuurne",
    "sg:classifiers":[
        {
            "category":"Personal",
            "subcategory":"Beauty Salon",
            "type":"Services"
        }
    ],
    "sg:phone":"+32 486 89 47 23",
    "sg:postcode":"8520",
    "sg:province":"West-Vlaanderen",
    "wof:name":"Image Nails",
    "wof:placetype":"venue"
},
  "geometry": {"coordinates":[3.2701590061,50.857421875],"type":"Point"}
}