{
  "type": "Feature",
  "properties": {
    "iso:country":"BE",
    "sg:address":"Route De Philippeville 301",
    "sg:city":"Charleroi (couillet)",
    "sg:classifiers":[
        {
            "category":"Retail",
            "subcategory":"Auto Repair",
            "type":"Services"
        }
    ],
    "sg:phone":"+32 71 36 35 35",
    "sg:postcode":"6010",
    "sg:province":"Hainaut",
    "sg:tags":[
        "garage"
    ],
    "wof:name":"Renault Sud Sa",
    "wof:placetype":"venue"
},
  "geometry": {"coordinates":[4.4642071724,50.3843574524],"type":"Point"}
}