{
  "type": "Feature",
  "properties": {
    "addr:full":"Schaafweg 2 Bornem Antwerpen 2880",
    "addr:housenumber":"2",
    "addr:postcode":"2880",
    "addr:street":"Schaafweg",
    "iso:country":"BE",
    "sg:address":"Schaafweg 2",
    "sg:city":"Bornem",
    "sg:orig_category":"Woningbouw",
    "sg:phone":"+32 3 889 68 61",
    "sg:postcode":"2880",
    "sg:province":"Antwerpen",
    "wof:name":"Alfons Van Den Heule",
    "wof:placetype":"venue"
},
  "geometry": {"coordinates":[4.1999077797,51.0779838562],"type":"Point"}
}