{
  "type": "Feature",
  "properties": {
    "iso:country":"BE",
    "sg:address":"Rodenbachlaan 24",
    "sg:city":"Meulebeke",
    "sg:classifiers":[
        {
            "category":"Cafe",
            "type":"Food & Drink"
        }
    ],
    "sg:phone":"+32 51 48 88 06",
    "sg:postcode":"8760",
    "sg:province":"West-Vlaanderen",
    "sg:tags":[
        "caf\u00e9s"
    ],
    "wof:name":"Roger Verbrugghe",
    "wof:placetype":"venue"
},
  "geometry": {"coordinates":[3.2903220654,50.939655304],"type":"Point"}
}