{
  "type": "Feature",
  "properties": {
    "addr:full":"Elsbroeken 5 Hoogstraten Antwerpen 2320",
    "addr:housenumber":"5",
    "addr:postcode":"2320",
    "addr:street":"Elsbroeken",
    "iso:country":"BE",
    "sg:address":"Elsbroeken 5",
    "sg:city":"Hoogstraten",
    "sg:orig_category":"D\u00e9chets and d\u00e9bris Gr",
    "sg:phone":"+32 3 314 76 01",
    "sg:postcode":"2320",
    "sg:province":"Antwerpen",
    "wof:name":"W Kapoen",
    "wof:placetype":"venue"
},
  "geometry": {"coordinates":[4.7654018402,51.3925590515],"type":"Point"}
}