{
  "type": "Feature",
  "properties": {
    "addr:full":"Miereberg 2 Haacht Vlaams-Brabant 3150",
    "addr:housenumber":"2",
    "addr:postcode":"3150",
    "addr:street":"Miereberg",
    "iso:country":"BE",
    "sg:address":"Miereberg 2",
    "sg:city":"Haacht",
    "sg:orig_category":"Editeurs de livres",
    "sg:phone":"+32 16 60 07 35",
    "sg:postcode":"3150",
    "sg:province":"Vlaams-Brabant",
    "wof:name":"Sonic Attack",
    "wof:placetype":"venue"
},
  "geometry": {"coordinates":[4.6306929588,50.981842041],"type":"Point"}
}