{
  "type": "Feature",
  "properties": {
    "addr:full":"Sint-rochusstraat 29 Halle Vlaams-Brabant 1500",
    "addr:housenumber":"29",
    "addr:postcode":"1500",
    "addr:street":"Sint-Rochusstraat",
    "iso:country":"BE",
    "sg:address":"Sint-rochusstraat 29",
    "sg:city":"Halle",
    "sg:classifiers":[
        {
            "category":"Recreation",
            "subcategory":"Dance Hall",
            "type":"Entertainment"
        }
    ],
    "sg:phone":"+32 2 360 03 28",
    "sg:postcode":"1500",
    "sg:province":"Vlaams-Brabant",
    "sg:tags":[
        "discotheque"
    ],
    "wof:name":"The Club",
    "wof:placetype":"venue"
},
  "geometry": {"coordinates":[4.239759922,50.7314834595],"type":"Point"}
}