{
  "type": "Feature",
  "properties": {
    "addr:full":"Boomgaardstraat 36 Maaseik Limburg 3680",
    "addr:housenumber":"36",
    "addr:postcode":"3680",
    "addr:street":"Boomgaardstraat",
    "iso:country":"BE",
    "sg:address":"Boomgaardstraat 36",
    "sg:city":"Maaseik",
    "sg:orig_category":"Kapsalons",
    "sg:phone":"+32 89 56 53 70",
    "sg:postcode":"3680",
    "sg:province":"Limburg",
    "wof:name":"E. Bertjens",
    "wof:placetype":"venue"
},
  "geometry": {"coordinates":[5.7876901627,51.0945396423],"type":"Point"}
}