{
  "type": "Feature",
  "properties": {
    "iso:country":"BE",
    "sg:address":"Bortierlaan 61",
    "sg:city":"De Panne",
    "sg:classifiers":[
        {
            "category":"Health Services",
            "subcategory":"Health Practitioner",
            "type":"Services"
        }
    ],
    "sg:phone":"+32 58 41 38 58",
    "sg:postcode":"8660",
    "sg:province":"West-Vlaanderen",
    "sg:tags":[
        "physiotherapist"
    ],
    "wof:name":"Seru Brigitte",
    "wof:placetype":"venue"
},
  "geometry": {"coordinates":[2.5837199688,51.0987892151],"type":"Point"}
}