{
  "type": "Feature",
  "properties": {
    "addr:full":"Rue Des Franchimontois 10 Dison Li\u00e8ge 4821",
    "addr:housenumber":"10",
    "addr:postcode":"4821",
    "addr:street":"Rue Des Franchimontois",
    "iso:country":"BE",
    "sg:address":"Rue Des Franchimontois 10",
    "sg:city":"Dison",
    "sg:orig_category":"Notarissen",
    "sg:phone":"+32 87 33 82 66",
    "sg:postcode":"4821",
    "sg:province":"Li\u00e8ge",
    "wof:name":"Beno\u00cet Jeangette",
    "wof:placetype":"venue"
},
  "geometry": {"coordinates":[5.8593540192,50.5985565186],"type":"Point"}
}