{
  "type": "Feature",
  "properties": {
    "iso:country":"BE",
    "sg:address":"Sint-denijsestraat 92",
    "sg:city":"Kortrijk",
    "sg:orig_category":"Blanchisseries and teintureries",
    "sg:phone":"+32 56 21 97 74",
    "sg:postcode":"8500",
    "sg:province":"West-Vlaanderen",
    "wof:name":"Wasserij St.denijs",
    "wof:placetype":"venue"
},
  "geometry": {"coordinates":[3.2725789547,50.8220672607],"type":"Point"}
}