{
  "type": "Feature",
  "properties": {
    "iso:country":"BE",
    "sg:address":"De Mattein 66",
    "sg:city":"Affligem",
    "sg:orig_category":"Dierenartsen",
    "sg:phone":"+32 53 68 17 29",
    "sg:postcode":"1790",
    "sg:province":"Vlaams-Brabant",
    "wof:name":"Regina Pladet",
    "wof:placetype":"venue"
},
  "geometry": {"coordinates":[4.1119170189,50.9199180603],"type":"Point"}
}