{
  "type": "Feature",
  "properties": {
    "addr:full":"Rue De Plainevaux 81b43 Seraing Li\u00e8ge 4100",
    "addr:housenumber":"81b43",
    "addr:postcode":"4100",
    "addr:street":"Rue De Plainevaux",
    "iso:country":"BE",
    "sg:address":"Rue De Plainevaux 81b43",
    "sg:city":"Seraing",
    "sg:orig_category":"Paramedische behandelingen",
    "sg:phone":"+32 4 336 27 39",
    "sg:postcode":"4100",
    "sg:province":"Li\u00e8ge",
    "wof:name":"A. Sartiaux",
    "wof:placetype":"venue"
},
  "geometry": {"coordinates":[5.5068049431,50.5843429565],"type":"Point"}
}