{
  "type": "Feature",
  "properties": {
    "addr:full":"Stationsstraat 2 Genk Limburg 3600",
    "addr:housenumber":"2",
    "addr:postcode":"3600",
    "addr:street":"Stationsstraat",
    "iso:country":"BE",
    "sg:address":"Stationsstraat 2",
    "sg:city":"Genk",
    "sg:orig_category":"Tijdelijke werkgelegenheid and uitzendkantoren",
    "sg:phone":"+32 89 32 95 75",
    "sg:postcode":"3600",
    "sg:province":"Limburg",
    "wof:name":"Unique Interim",
    "wof:placetype":"venue"
},
  "geometry": {"coordinates":[5.5001711845,50.9642105103],"type":"Point"}
}