{
  "type": "Feature",
  "properties": {
    "iso:country":"BE",
    "sg:address":"Rue Des Champs Du Bois 32",
    "sg:city":"Braine-l`alleud",
    "sg:orig_category":"Peinture. Rev\u00eatements pour sols and murs. Travaux de finition and nettoyage de b\u00e2timents. Eclairage ",
    "sg:phone":"+32 2 387 06 67",
    "sg:postcode":"1421",
    "sg:province":"Brabant Wallon",
    "wof:name":"Entreprise J.l. Senterre",
    "wof:placetype":"venue"
},
  "geometry": {"coordinates":[1.2029399872,47.4052200317],"type":"Point"}
}