{
  "type": "Feature",
  "properties": {
    "iso:country":"BE",
    "sg:address":"Nestor De Ti\u00c8restraat 127",
    "sg:city":"Oudenaarde",
    "sg:orig_category":"Opticiens",
    "sg:phone":"+32 55 30 27 92",
    "sg:postcode":"9700",
    "sg:province":"Oost-Vlaanderen",
    "wof:name":"Optiek Focus",
    "wof:placetype":"venue"
},
  "geometry": {"coordinates":[3.6184539795,50.86693573],"type":"Point"}
}