{
  "type": "Feature",
  "properties": {
    "addr:full":"Rue De Mont St.-guibert 17 Ottignies-louvain-la-neuve Brabant Wallon 1340",
    "addr:housenumber":"17",
    "addr:postcode":"1340",
    "addr:street":"Rue De Mont St.-Guibert",
    "iso:country":"BE",
    "sg:address":"Rue De Mont St.-guibert 17",
    "sg:city":"Ottignies-louvain-la-neuve",
    "sg:orig_category":"M\u00e9decins and sp\u00e9cialistes",
    "sg:phone":"+32 10 45 48 01",
    "sg:postcode":"1340",
    "sg:province":"Brabant Wallon",
    "wof:name":"Jacqueline Van Raemdonck",
    "wof:placetype":"venue"
},
  "geometry": {"coordinates":[4.5994539261,50.6659622192],"type":"Point"}
}