{
  "type": "Feature",
  "properties": {
    "addr:full":"Rue Marchand 12 La Louviere Hainaut 7110",
    "addr:housenumber":"12",
    "addr:postcode":"7110",
    "addr:street":"Rue Marchand",
    "iso:country":"BE",
    "sg:address":"Rue Marchand 12",
    "sg:city":"La Louviere",
    "sg:orig_category":"Pharmaciens",
    "sg:phone":"+32 64 66 20 16",
    "sg:postcode":"7110",
    "sg:province":"Hainaut",
    "wof:name":"Multipharma",
    "wof:placetype":"venue"
},
  "geometry": {"coordinates":[4.1505050659,50.4826698303],"type":"Point"}
}