{
  "type": "Feature",
  "properties": {
    "addr:full":"Rue Les Claines 29 Beauvechain Brabant Wallon 1320",
    "addr:housenumber":"29",
    "addr:postcode":"1320",
    "addr:street":"Rue Les Claines",
    "iso:country":"BE",
    "sg:address":"Rue Les Claines 29",
    "sg:city":"Beauvechain",
    "sg:orig_category":"Architecten",
    "sg:phone":"+32 10 86 70 58",
    "sg:postcode":"1320",
    "sg:province":"Brabant Wallon",
    "wof:name":"Jo\u00cbl Brunet",
    "wof:placetype":"venue"
},
  "geometry": {"coordinates":[4.7732748985,50.7803611755],"type":"Point"}
}