{
  "type": "Feature",
  "properties": {
    "addr:full":"Kapelsesteenweg 377-379 Anvers Antwerpen 2180",
    "addr:housenumber":"377-379",
    "addr:postcode":"2180",
    "addr:street":"Kapelsesteenweg",
    "iso:country":"BE",
    "sg:address":"Kapelsesteenweg 377-379",
    "sg:city":"Anvers",
    "sg:orig_category":"Rev\u00eatements de sols and murs",
    "sg:phone":"+32 3 644 74 73",
    "sg:postcode":"2180",
    "sg:province":"Antwerpen",
    "wof:name":"Serena Kurk",
    "wof:placetype":"venue"
},
  "geometry": {"coordinates":[4.4586000443,51.2716217041],"type":"Point"}
}