{
  "type": "Feature",
  "properties": {
    "addr:full":"Langendijkstraat 12 Zutendaal Limburg 3690",
    "addr:housenumber":"12",
    "addr:postcode":"3690",
    "addr:street":"Langendijkstraat",
    "iso:country":"BE",
    "sg:address":"Langendijkstraat 12",
    "sg:city":"Zutendaal",
    "sg:classifiers":[
        {
            "category":"Recreation",
            "subcategory":"Arcade",
            "type":"Entertainment"
        }
    ],
    "sg:phone":"+32 89 61 27 65",
    "sg:postcode":"3690",
    "sg:province":"Limburg",
    "sg:tags":[
        "machine",
        "amusement"
    ],
    "wof:name":"John Gille Co Nv/jgc",
    "wof:placetype":"venue"
},
  "geometry": {"coordinates":[5.5374999046,50.9201278687],"type":"Point"}
}