{
  "type": "Feature",
  "properties": {
    "iso:country":"BE",
    "sg:address":"Avenue Eiffel 3",
    "sg:city":"Wavre",
    "sg:classifiers":[
        {
            "category":"Professional",
            "subcategory":"Advertising",
            "type":"Services"
        }
    ],
    "sg:phone":"+32 10 84 52 19",
    "sg:postcode":"1300",
    "sg:province":"Brabant Wallon",
    "sg:tags":[
        "-",
        "three-dimensional"
    ],
    "wof:name":"Giant Sprl",
    "wof:placetype":"venue"
},
  "geometry": {"coordinates":[4.596558094,50.7371101379],"type":"Point"}
}