{
  "type": "Feature",
  "properties": {
    "addr:full":"Chauss\u00e9e De Bruxelles 58 Awans (hognoul) Li\u00e8ge 4342",
    "addr:housenumber":"58",
    "addr:postcode":"4342",
    "addr:street":"Chausse\u0301E De Bruxelles",
    "iso:country":"BE",
    "sg:address":"Chauss\u00e9e De Bruxelles 58",
    "sg:city":"Awans (hognoul)",
    "sg:classifiers":[
        {
            "category":"Autos & Motor Vehicles",
            "subcategory":"Fuel & Gas Station",
            "type":"Retail Goods"
        }
    ],
    "sg:phone":"+32 4 257 68 88",
    "sg:postcode":"4342",
    "sg:province":"Li\u00e8ge",
    "wof:name":"Truck Center Chez Viviane Sprl",
    "wof:placetype":"venue"
},
  "geometry": {"coordinates":[5.4754161835,50.6779823303],"type":"Point"}
}