{
  "type": "Feature",
  "properties": {
    "iso:country":"BE",
    "sg:address":"Stationsstraat 83",
    "sg:city":"Sint-niklaas",
    "sg:orig_category":"Warenhuizen",
    "sg:phone":"+32 3 760 09 10",
    "sg:postcode":"9100",
    "sg:province":"Oost-Vlaanderen",
    "wof:name":"Hema",
    "wof:placetype":"venue"
},
  "geometry": {"coordinates":[4.1422510147,51.1680145264],"type":"Point"}
}