{
  "type": "Feature",
  "properties": {
    "addr:full":"Rue Louis De Meuse 78 Herstal Li\u00e8ge 4040",
    "addr:housenumber":"78",
    "addr:postcode":"4040",
    "addr:street":"Rue Louis De Meuse",
    "iso:country":"BE",
    "sg:address":"Rue Louis De Meuse 78",
    "sg:city":"Herstal",
    "sg:orig_category":"Epiceries",
    "sg:phone":"+32 4 264 49 68",
    "sg:postcode":"4040",
    "sg:province":"Li\u00e8ge",
    "wof:name":"Spar Herstal",
    "wof:placetype":"venue"
},
  "geometry": {"coordinates":[5.6327848434,50.6771316528],"type":"Point"}
}