{
  "type": "Feature",
  "properties": {
    "addr:full":"Kruisekestraat 3 Zonnebeke West-Vlaanderen 8980",
    "addr:housenumber":"3",
    "addr:postcode":"8980",
    "addr:street":"Kruisekestraat",
    "iso:country":"BE",
    "sg:address":"Kruisekestraat 3",
    "sg:city":"Zonnebeke",
    "sg:orig_category":"Rundveehouders",
    "sg:phone":"+32 57 46 65 73",
    "sg:postcode":"8980",
    "sg:province":"West-Vlaanderen",
    "wof:name":"Michel Dehem",
    "wof:placetype":"venue"
},
  "geometry": {"coordinates":[2.9872550964,50.8730812073],"type":"Point"}
}