{
  "type": "Feature",
  "properties": {
    "addr:full":"Chauss\u00e9e De Haecht 1465 Bruxelles Bruxelles-Capitale 1130",
    "addr:housenumber":"1465",
    "addr:postcode":"1130",
    "addr:street":"Chausse\u0301E De Haecht",
    "iso:country":"BE",
    "sg:address":"Chauss\u00e9e De Haecht 1465",
    "sg:city":"Bruxelles",
    "sg:classifiers":[
        {
            "category":"Manufacturing",
            "subcategory":"Metals",
            "type":"Manufacturing & Wholesale Goods"
        }
    ],
    "sg:phone":"+32 2 240 18 40",
    "sg:postcode":"1130",
    "sg:province":"Bruxelles-Capitale",
    "sg:tags":[
        "steel",
        "high-quality",
        "-",
        "special"
    ],
    "wof:name":"Carpenter Technology Europe Sa",
    "wof:placetype":"venue"
},
  "geometry": {"coordinates":[4.4228749275,50.8864173889],"type":"Point"}
}