{
  "type": "Feature",
  "properties": {
    "iso:country":"BE",
    "sg:address":"Helzoldstraat 11",
    "sg:city":"Houthalen-helchteren",
    "sg:classifiers":[
        {
            "category":"Cafe",
            "type":"Food & Drink"
        }
    ],
    "sg:phone":"+32 11 60 52 93",
    "sg:postcode":"3530",
    "sg:province":"Limburg",
    "sg:tags":[
        "caf\u00e9s"
    ],
    "wof:name":"Ursula Labrenz",
    "wof:placetype":"venue"
},
  "geometry": {"coordinates":[5.3578147888,51.0458145142],"type":"Point"}
}