{
  "type": "Feature",
  "properties": {
    "addr:full":"Rue De Brocqueroy 29 Soignies (casteau) Hainaut 7061",
    "addr:housenumber":"29",
    "addr:postcode":"7061",
    "addr:street":"Rue De Brocqueroy",
    "iso:country":"BE",
    "sg:address":"Rue De Brocqueroy 29",
    "sg:city":"Soignies (casteau)",
    "sg:classifiers":[
        {
            "category":"Insurance",
            "subcategory":"Insurance Agent",
            "type":"Services"
        }
    ],
    "sg:phone":"+32 65 73 18 52",
    "sg:postcode":"7061",
    "sg:province":"Hainaut",
    "sg:tags":[
        "broker"
    ],
    "wof:name":"Flament-martinet Assurances",
    "wof:placetype":"venue"
},
  "geometry": {"coordinates":[4.0133500099,50.5159416199],"type":"Point"}
}