{
  "type": "Feature",
  "properties": {
    "iso:country":"BE",
    "sg:address":"Molsesteenweg 5",
    "sg:city":"Balen",
    "sg:classifiers":[
        {
            "category":"Cafe",
            "type":"Food & Drink"
        }
    ],
    "sg:phone":"+32 14 32 08 60",
    "sg:postcode":"2490",
    "sg:province":"Antwerpen",
    "sg:tags":[
        "caf\u00e9s"
    ],
    "wof:name":"Willem Wouters",
    "wof:placetype":"venue"
},
  "geometry": {"coordinates":[5.149711132,51.1726646423],"type":"Point"}
}