{
  "type": "Feature",
  "properties": {
    "iso:country":"BE",
    "sg:address":"Zwijnaardsesteenweg 736",
    "sg:city":"Gent",
    "sg:classifiers":[
        {
            "category":"Communications",
            "subcategory":"Film & Video Production",
            "type":"Services"
        }
    ],
    "sg:phone":"+32 9 221 53 32",
    "sg:postcode":"9000",
    "sg:province":"Oost-Vlaanderen",
    "sg:tags":[
        "hiring",
        "-"
    ],
    "wof:name":"Athena Video",
    "wof:placetype":"venue"
},
  "geometry": {"coordinates":[3.7198960781,51.0205726624],"type":"Point"}
}