{
  "type": "Feature",
  "properties": {
    "iso:country":"BE",
    "sg:address":"Brugseweg 269",
    "sg:city":"Langemark-poelkapelle (poelkapelle)",
    "sg:classifiers":[
        {
            "category":"Social Services",
            "subcategory":"Child Care",
            "type":"Services"
        }
    ],
    "sg:phone":"+32 57 48 63 01",
    "sg:postcode":"8920",
    "sg:province":"West-Vlaanderen",
    "sg:tags":[
        "baby",
        "nursery",
        "day",
        "sitting"
    ],
    "wof:name":"Boeleke",
    "wof:placetype":"venue"
},
  "geometry": {"coordinates":[2.9379899502,50.8924789429],"type":"Point"}
}