{
  "type": "Feature",
  "properties": {
    "addr:full":"Rue Mitoyenne 903 Welkenraedt/welkenraedt Li\u00e8ge 4840",
    "addr:housenumber":"903",
    "addr:postcode":"4840",
    "addr:street":"Rue Mitoyenne",
    "iso:country":"BE",
    "sg:address":"Rue Mitoyenne 903",
    "sg:city":"Welkenraedt/welkenraedt",
    "sg:orig_category":"D\u00e9taillants en pi\u00e8ces and accessoires de voitures. Stations-service and carburants. Pi\u00e8ces and acces",
    "sg:phone":"+32 87 89 95 95",
    "sg:postcode":"4840",
    "sg:province":"Li\u00e8ge",
    "wof:name":"Q8",
    "wof:placetype":"venue"
},
  "geometry": {"coordinates":[5.9796700478,50.6616210938],"type":"Point"}
}