{
  "type": "Feature",
  "properties": {
    "addr:full":"Rue De La Leche 36 Li\u00c8ge Li\u00e8ge 4020",
    "addr:housenumber":"36",
    "addr:postcode":"4020",
    "addr:street":"Rue De La Leche",
    "iso:country":"BE",
    "sg:address":"Rue De La Leche 36",
    "sg:city":"Li\u00c8ge",
    "sg:orig_category":"Diverse bouwafwerking and reiniging Gespecialiseerde residenti\u00eble bouw Industri\u00eble and commerci\u00eble b",
    "sg:phone":"+32 4 343 11 36",
    "sg:postcode":"4020",
    "sg:province":"Li\u00e8ge",
    "wof:name":"Entreprises Jean Moury",
    "wof:placetype":"venue"
},
  "geometry": {"coordinates":[5.6105599403,50.6436080933],"type":"Point"}
}