{
  "type": "Feature",
  "properties": {
    "addr:full":"Avenue Mascaux 3 Charleroi Hainaut 6001",
    "addr:housenumber":"3",
    "addr:postcode":"6001",
    "addr:street":"Avenue Mascaux;Hainaut",
    "iso:country":"BE",
    "sg:address":"Avenue Mascaux 3",
    "sg:city":"Charleroi",
    "sg:orig_category":"Animaux domestiques and accessoires",
    "sg:phone":"+32 71 43 14 51",
    "sg:postcode":"6001",
    "sg:province":"Hainaut",
    "wof:name":"Oisellerie Du Centre",
    "wof:placetype":"venue"
},
  "geometry": {"coordinates":[4.4477591515,50.3998031616],"type":"Point"}
}