{
  "type": "Feature",
  "properties": {
    "iso:country":"BE",
    "sg:address":"Rue Mont-saint-guibert 18",
    "sg:city":"Ottignies-louvain-la-neuve",
    "sg:orig_category":"Beautyfarms, relaxatie and lichamelijk welzijn Werk and personeelsselectie",
    "sg:phone":"+32 10 48 35 45",
    "sg:postcode":"1340",
    "sg:province":"Brabant Wallon",
    "wof:name":"Servais Et Chauvaux",
    "wof:placetype":"venue"
},
  "geometry": {"coordinates":[4.5993118286,50.6659393311],"type":"Point"}
}