{
  "type": "Feature",
  "properties": {
    "iso:country":"BE",
    "sg:address":"Provinciebaan 29",
    "sg:city":"Koekelare",
    "sg:orig_category":"R\u00e9parations \u00e0 domicile d'appareils \u00e9lectriques. R\u00e9parations d'appareils \u00e9lectrom\u00e9nagers",
    "sg:phone":"+32 51 58 03 65",
    "sg:postcode":"8680",
    "sg:province":"West-Vlaanderen",
    "wof:name":"Roland Eeckhout",
    "wof:placetype":"venue"
},
  "geometry": {"coordinates":[2.9472899437,51.0680198669],"type":"Point"}
}