{
  "type": "Feature",
  "properties": {
    "iso:country":"BE",
    "sg:address":"Rue De La Semois 33",
    "sg:city":"Bouillon (les Hayons)",
    "sg:classifiers":[
        {
            "category":"Utilities",
            "subcategory":"Telephone",
            "type":"Services"
        }
    ],
    "sg:phone":"+32 61 27 13 80",
    "sg:postcode":"6830",
    "sg:province":"Luxembourg",
    "sg:tags":[
        "-",
        "internet"
    ],
    "wof:name":"Grenadine Agence Web",
    "wof:placetype":"venue"
},
  "geometry": {"coordinates":[5.1458101273,49.8131904602],"type":"Point"}
}