{
  "type": "Feature",
  "properties": {
    "iso:country":"BE",
    "sg:address":"Kerelstraat 2",
    "sg:city":"Hooglede",
    "sg:orig_category":"Rev\u00eatements pour sols and murs",
    "sg:phone":"+32 51 22 39 36",
    "sg:postcode":"8830",
    "sg:province":"West-Vlaanderen",
    "wof:name":"Casteur-florisoone",
    "wof:placetype":"venue"
},
  "geometry": {"coordinates":[3.0881071091,50.9761772156],"type":"Point"}
}