{
  "type": "Feature",
  "properties": {
    "addr:full":"Chauss\u00c9e De Bruxelles 281 Waterloo (grand) Brabant Wallon 1410",
    "addr:housenumber":"281",
    "addr:postcode":"1410",
    "addr:street":"Chausse\u0301E De Bruxelles;Wallon",
    "iso:country":"BE",
    "sg:address":"Chauss\u00c9e De Bruxelles 281",
    "sg:city":"Waterloo (grand)",
    "sg:orig_category":"Rev\u00eatements de sols and murs. Quincailleries. Eclairage et \u00e9quipements du foyer. Textiles",
    "sg:phone":"+32 2 354 44 58",
    "sg:postcode":"1410",
    "sg:province":"Brabant Wallon",
    "wof:name":"Heytens",
    "wof:placetype":"venue"
},
  "geometry": {"coordinates":[4.4003047943,50.7127151489],"type":"Point"}
}