{
  "type": "Feature",
  "properties": {
    "addr:full":"Place Communale 1ba Walhain Brabant Wallon 1457",
    "addr:housenumber":"1457",
    "addr:street":"Place Communale 1Ba",
    "iso:country":"BE",
    "sg:address":"Place Communale 1ba",
    "sg:city":"Walhain",
    "sg:classifiers":[
        {
            "category":"Health Services",
            "subcategory":"Nursing And Care Facility",
            "type":"Services"
        }
    ],
    "sg:phone":"+32 10 65 86 68",
    "sg:postcode":"1457",
    "sg:province":"Brabant Wallon",
    "sg:tags":[
        "public"
    ],
    "wof:name":"C.p.a.s.",
    "wof:placetype":"venue"
},
  "geometry": {"coordinates":[4.6952910423,50.6182632446],"type":"Point"}
}