{
  "type": "Feature",
  "properties": {
    "addr:full":"Rue De Lurot 1 Mettet Namur 5640",
    "addr:housenumber":"1",
    "addr:postcode":"5640",
    "addr:street":"Rue De Lurot",
    "iso:country":"BE",
    "sg:address":"Rue De Lurot 1",
    "sg:city":"Mettet",
    "sg:classifiers":[
        {
            "category":"Banks & Credit Unions",
            "subcategory":"Bank",
            "type":"Services"
        }
    ],
    "sg:phone":"+32 60 72 86 60",
    "sg:postcode":"5640",
    "sg:province":"Namur",
    "wof:name":"Cr\u00e9dit Communal",
    "wof:placetype":"venue"
},
  "geometry": {"coordinates":[4.6580672264,50.3194046021],"type":"Point"}
}