{
  "type": "Feature",
  "properties": {
    "iso:country":"BE",
    "sg:address":"Mechelsesteenweg 20",
    "sg:city":"Kontich",
    "sg:classifiers":[
        {
            "category":"Professional",
            "subcategory":"Art Services",
            "type":"Services"
        }
    ],
    "sg:phone":"+32 3 458 50 42",
    "sg:postcode":"2550",
    "sg:province":"Antwerpen",
    "sg:tags":[
        "interior",
        "designer"
    ],
    "wof:name":"Arima Bvba",
    "wof:placetype":"venue"
},
  "geometry": {"coordinates":[4.4450159073,51.1341362],"type":"Point"}
}