{
  "type": "Feature",
  "properties": {
    "iso:country":"BE",
    "sg:address":"Pacificatielaan 35",
    "sg:city":"Gent",
    "sg:orig_category":"Openbare veiligheid",
    "sg:phone":"+32 9 243 50 50",
    "sg:postcode":"9000",
    "sg:province":"Oost-Vlaanderen",
    "wof:name":"Federale Politie/police F\u00c9d\u00c9rale",
    "wof:placetype":"venue"
},
  "geometry": {"coordinates":[3.7145600319,51.0279846191],"type":"Point"}
}