{
  "type": "Feature",
  "properties": {
    "iso:country":"BE",
    "sg:address":"Rue Couture 96",
    "sg:city":"Ham-sur-heure-nalinnes",
    "sg:orig_category":"Traitements param\u00e9dicaux",
    "sg:phone":"+32 71 21 78 80",
    "sg:postcode":"6120",
    "sg:province":"Hainaut",
    "wof:name":"Dico Service",
    "wof:placetype":"venue"
},
  "geometry": {"coordinates":[4.4570150375,50.3335762024],"type":"Point"}
}