{
  "type": "Feature",
  "properties": {
    "addr:full":"Rue Frantz Poussard 26 Verviers (petit-rechain) Li\u00e8ge 4800",
    "addr:housenumber":"26",
    "addr:postcode":"4800",
    "addr:street":"Rue Frantz Poussard",
    "iso:country":"BE",
    "sg:address":"Rue Frantz Poussard 26",
    "sg:city":"Verviers (petit-rechain)",
    "sg:classifiers":[
        {
            "category":"Building & Trades",
            "subcategory":"Landscaping Services",
            "type":"Services"
        }
    ],
    "sg:phone":"+32 87 35 12 87",
    "sg:postcode":"4800",
    "sg:province":"Li\u00e8ge",
    "sg:tags":[
        "handicraft"
    ],
    "wof:name":"Senteurs Artisanales (les)",
    "wof:placetype":"venue"
},
  "geometry": {"coordinates":[5.8286709785,50.6137504578],"type":"Point"}
}