{
  "type": "Feature",
  "properties": {
    "addr:full":"Rue Des Piges 223 Charleroi (monceau-sur-sambre) Hainaut 6031",
    "addr:housenumber":"223",
    "addr:postcode":"6031",
    "addr:street":"Rue Des Piges",
    "iso:country":"BE",
    "sg:address":"Rue Des Piges 223",
    "sg:city":"Charleroi (monceau-sur-sambre)",
    "sg:classifiers":[
        {
            "category":"Building & Trades",
            "subcategory":"Electrical",
            "type":"Services"
        }
    ],
    "sg:phone":"+32 477 30 14 48",
    "sg:postcode":"6031",
    "sg:province":"Hainaut",
    "sg:tags":[
        "electric",
        "-",
        "housewiring",
        "contractor"
    ],
    "wof:name":"Duquesnoy Patrick",
    "wof:placetype":"venue"
},
  "geometry": {"coordinates":[4.38022995,50.4121742249],"type":"Point"}
}