{
  "type": "Feature",
  "properties": {
    "iso:country":"BE",
    "sg:address":"Statiestraat 38a",
    "sg:city":"Wichelen",
    "sg:orig_category":"Aanleg van wegen, sportterreinen and vliegvelden Afbraak- and draineerwerken Bouwwerktuigen Gh Verhu",
    "sg:phone":"+32 52 42 20 73",
    "sg:postcode":"9260",
    "sg:province":"Oost-Vlaanderen",
    "wof:name":"Adegro",
    "wof:placetype":"venue"
},
  "geometry": {"coordinates":[3.9726839066,51.0060844421],"type":"Point"}
}