{
  "type": "Feature",
  "properties": {
    "iso:country":"BE",
    "sg:address":"Rue Des Cascades 3",
    "sg:city":"Antoing (maubray)",
    "sg:classifiers":[
        {
            "category":"Home & Garden",
            "subcategory":"Home Furnishings",
            "type":"Retail Goods"
        }
    ],
    "sg:phone":"+32 69 44 14 31",
    "sg:postcode":"7640",
    "sg:province":"Hainaut",
    "sg:tags":[
        "-",
        "freezer",
        "refrigerator"
    ],
    "wof:name":"Delecluse Marc Ets",
    "wof:placetype":"venue"
},
  "geometry": {"coordinates":[3.4798369408,50.5520133972],"type":"Point"}
}