{
  "type": "Feature",
  "properties": {
    "iso:country":"BE",
    "sg:address":"Nachtegaallaan 71",
    "sg:city":"Dilsen-stokkem",
    "sg:orig_category":"Entretien and r\u00e9parations de voitures",
    "sg:phone":"+32 89 86 63 34",
    "sg:postcode":"3650",
    "sg:province":"Limburg",
    "wof:name":"Franciscus Damoiseaux",
    "wof:placetype":"venue"
},
  "geometry": {"coordinates":[5.7180662155,51.0669212341],"type":"Point"}
}