{
  "type": "Feature",
  "properties": {
    "iso:country":"BE",
    "sg:address":"Gasthuisstraat 74 Box 1",
    "sg:city":"Turnhout",
    "sg:classifiers":[
        {
            "category":"Shopping",
            "subcategory":"Clothing, Apparel, & Fashions",
            "type":"Retail Goods"
        }
    ],
    "sg:phone":"+32 14 43 56 42",
    "sg:postcode":"2300",
    "sg:province":"Antwerpen",
    "sg:tags":[
        "-",
        "clothing",
        "child"
    ],
    "wof:name":"Villa Happ",
    "wof:placetype":"venue"
},
  "geometry": {"coordinates":[4.9435548782,51.322593689],"type":"Point"}
}