{
  "type": "Feature",
  "properties": {
    "iso:country":"BE",
    "sg:address":"Rue De Philippeville 113",
    "sg:city":"Ham-sur-heure-nalinnes (nalinnes)",
    "sg:classifiers":[
        {
            "category":"Home & Garden",
            "subcategory":"Kitchen Supply",
            "type":"Retail Goods"
        }
    ],
    "sg:phone":"+32 71 21 95 17",
    "sg:postcode":"6120",
    "sg:province":"Hainaut",
    "sg:tags":[
        "installation"
    ],
    "wof:name":"Ekips Concept",
    "wof:placetype":"venue"
},
  "geometry": {"coordinates":[4.475317955,50.3342208862],"type":"Point"}
}