{
  "type": "Feature",
  "properties": {
    "addr:full":"Avenue Du Centaure 16ba Sint-lambrechts-woluwe/woluwe-saint-lambert Bruxelles-Capitale 1200",
    "addr:housenumber":"16ba",
    "addr:postcode":"1200",
    "addr:street":"Avenue Du Centaure",
    "iso:country":"BE",
    "sg:address":"Avenue Du Centaure 16ba",
    "sg:city":"Sint-lambrechts-woluwe/woluwe-saint-lambert",
    "sg:orig_category":"Enseignement maternel and primaire",
    "sg:phone":"+32 2 761 28 89",
    "sg:postcode":"1200",
    "sg:province":"Bruxelles-Capitale",
    "wof:name":"Ecole Matern. Communale",
    "wof:placetype":"venue"
},
  "geometry": {"coordinates":[4.4147410393,50.852394104],"type":"Point"}
}