{
  "type": "Feature",
  "properties": {
    "addr:full":"Groothandelsmarkt 79 Antwerpen Antwerpen 2020",
    "addr:housenumber":"79",
    "addr:postcode":"2020",
    "addr:street":"Groothandelsmarkt",
    "iso:country":"BE",
    "sg:address":"Groothandelsmarkt 79",
    "sg:city":"Antwerpen",
    "sg:classifiers":[
        {
            "category":"Food & Beverages",
            "subcategory":"Fruits & Vegetables",
            "type":"Retail Goods"
        }
    ],
    "sg:phone":"+32 3 237 02 31",
    "sg:postcode":"2020",
    "sg:province":"Antwerpen",
    "sg:tags":[
        "-"
    ],
    "wof:name":"Vawi",
    "wof:placetype":"venue"
},
  "geometry": {"coordinates":[4.3810501099,51.1914710999],"type":"Point"}
}