{
  "type": "Feature",
  "properties": {
    "addr:full":"Rue Chemin Vert 15 Fontaine-l'ev\u00eaque (leernes) Hainaut 6142",
    "addr:housenumber":"15",
    "addr:postcode":"6142",
    "addr:street":"Rue Chemin Vert;Hainaut",
    "iso:country":"BE",
    "sg:address":"Rue Chemin Vert 15",
    "sg:city":"Fontaine-l'ev\u00eaque (leernes)",
    "sg:classifiers":[
        {
            "category":"Building & Trades",
            "subcategory":"Pest Control",
            "type":"Services"
        }
    ],
    "sg:phone":"+32 71 52 81 30",
    "sg:postcode":"6142",
    "sg:province":"Hainaut",
    "sg:tags":[
        "painting",
        "contractor"
    ],
    "wof:name":"Bortholozzi D",
    "wof:placetype":"venue"
},
  "geometry": {"coordinates":[-111.9644622803,46.2507972717],"type":"Point"}
}