{
  "type": "Feature",
  "properties": {
    "addr:full":"Rue De L\u00b4enseignement 49 Fontaine-l\u00b4ev\u00caque Hainaut 6140",
    "addr:housenumber":"49",
    "addr:postcode":"6140",
    "addr:street":"Rue De L\u00b4Enseignement;Hainaut",
    "iso:country":"BE",
    "sg:address":"Rue De L\u00b4enseignement 49",
    "sg:city":"Fontaine-l\u00b4ev\u00caque",
    "sg:orig_category":"S\u00e9lection de personnel and placement",
    "sg:phone":"+32 71 54 06 69",
    "sg:postcode":"6140",
    "sg:province":"Hainaut",
    "wof:name":"Ale Fontaine-l\u00b4ev\u00caque",
    "wof:placetype":"venue"
},
  "geometry": {"coordinates":[4.3208971024,50.4097747803],"type":"Point"}
}