{
  "type": "Feature",
  "properties": {
    "iso:country":"BE",
    "sg:address":"Brugsevaart 87",
    "sg:city":"Gent (mariakerke)",
    "sg:classifiers":[
        {
            "category":"Retail",
            "subcategory":"Auto Repair",
            "type":"Services"
        }
    ],
    "sg:phone":"+32 9 226 57 31",
    "sg:postcode":"9030",
    "sg:province":"Oost-Vlaanderen",
    "sg:tags":[
        "breakdown",
        "automobile",
        "-",
        "recovery"
    ],
    "wof:name":"Depannage Gilbert",
    "wof:placetype":"venue"
},
  "geometry": {"coordinates":[3.6747119427,51.0797805786],"type":"Point"}
}