{
  "type": "Feature",
  "properties": {
    "addr:full":"Route De Li\u00c8ge 7 Nandrin Li\u00e8ge 4550",
    "addr:housenumber":"7",
    "addr:postcode":"4550",
    "addr:street":"Route De Lie\u0300Ge",
    "iso:country":"BE",
    "sg:address":"Route De Li\u00c8ge 7",
    "sg:city":"Nandrin",
    "sg:orig_category":"Meubles D\u00e9taillants, Am\u00e9nagement de B\u00e2timents et de Cuisines",
    "sg:phone":"+32 4 371 49 45",
    "sg:postcode":"4550",
    "sg:province":"Li\u00e8ge",
    "wof:name":"Basic Meubles Sa",
    "wof:placetype":"venue"
},
  "geometry": {"coordinates":[5.4204249382,50.5065155029],"type":"Point"}
}