{
  "type": "Feature",
  "properties": {
    "iso:country":"BE",
    "sg:address":"Stalenstraat 107",
    "sg:city":"Genk",
    "sg:classifiers":[
        {
            "category":"Bars & Pubs",
            "type":"Food & Drink"
        }
    ],
    "sg:phone":"+32 89 84 28 26",
    "sg:postcode":"3600",
    "sg:province":"Limburg",
    "wof:name":"Webcaf\u00c9",
    "wof:placetype":"venue"
},
  "geometry": {"coordinates":[5.5198969841,50.9943847656],"type":"Point"}
}