{
  "type": "Feature",
  "properties": {
    "addr:full":"Rue De La Chauss\u00c9e 12 Mons Hainaut 7000",
    "addr:housenumber":"12",
    "addr:postcode":"7000",
    "addr:street":"Rue De La Chausse\u0301E;Hainaut",
    "iso:country":"BE",
    "sg:address":"Rue De La Chauss\u00c9e 12",
    "sg:city":"Mons",
    "sg:classifiers":[
        {
            "category":"Shopping",
            "subcategory":"Clothing, Apparel, & Fashions",
            "type":"Retail Goods"
        }
    ],
    "sg:phone":"+32 65 35 15 43",
    "sg:postcode":"7000",
    "sg:province":"Hainaut",
    "sg:tags":[
        "lingerie",
        "sous-v\u00eatements"
    ],
    "wof:name":"Damart",
    "wof:placetype":"venue"
},
  "geometry": {"coordinates":[3.9516510963,50.4535636902],"type":"Point"}
}