{
  "type": "Feature",
  "properties": {
    "iso:country":"BE",
    "sg:address":"Rijmsdam 28",
    "sg:city":"Gent",
    "sg:classifiers":[
        {
            "category":"Personal",
            "type":"Services"
        }
    ],
    "sg:phone":"+32 9 217 06 17",
    "sg:postcode":"9000",
    "sg:province":"Oost-Vlaanderen",
    "sg:tags":[
        "party",
        "planning"
    ],
    "wof:name":"Carpe Diem",
    "wof:placetype":"venue"
},
  "geometry": {"coordinates":[3.6845180988,51.067615509],"type":"Point"}
}