{
  "type": "Feature",
  "properties": {
    "addr:full":"Ganzendries 41 Erpe-mere (erondegem) Oost-Vlaanderen 9420",
    "addr:housenumber":"41",
    "addr:postcode":"9420",
    "addr:street":"Ganzendries",
    "iso:country":"BE",
    "sg:address":"Ganzendries 41",
    "sg:city":"Erpe-mere (erondegem)",
    "sg:classifiers":[
        {
            "category":"Personal",
            "subcategory":"Beauty Salon",
            "type":"Services"
        }
    ],
    "sg:phone":"+32 53 80 51 68",
    "sg:postcode":"9420",
    "sg:province":"Oost-Vlaanderen",
    "sg:tags":[
        "lady",
        "-",
        "hairdressing"
    ],
    "wof:name":"Lutgarde",
    "wof:placetype":"venue"
},
  "geometry": {"coordinates":[3.9493069649,50.9461784363],"type":"Point"}
}