{
  "type": "Feature",
  "properties": {
    "addr:full":"Napelsstraat 128 Antwerpen Antwerpen 2000",
    "addr:housenumber":"128",
    "addr:postcode":"2000",
    "addr:street":"Napelsstraat",
    "iso:country":"BE",
    "sg:address":"Napelsstraat 128",
    "sg:city":"Antwerpen",
    "sg:classifiers":[
        {
            "category":"Restaurant",
            "type":"Food & Drink"
        }
    ],
    "sg:phone":"+32 3 233 37 54",
    "sg:postcode":"2000",
    "sg:province":"Antwerpen",
    "sg:tags":[
        "caf\u00e9s"
    ],
    "wof:name":"Taverne Bacchus",
    "wof:placetype":"venue"
},
  "geometry": {"coordinates":[4.4111099243,51.2310600281],"type":"Point"}
}