{
  "type": "Feature",
  "properties": {
    "addr:full":"Cornelius Sneyssenslaan 13 Merelbeke Oost-Vlaanderen 9820",
    "addr:housenumber":"13",
    "addr:postcode":"9820",
    "addr:street":"Sneyssenslaan",
    "iso:country":"BE",
    "sg:address":"Cornelius Sneyssenslaan 13",
    "sg:city":"Merelbeke",
    "sg:orig_category":"Installation \u00e9lectrique industrielle",
    "sg:phone":"+32 475 50 22 80",
    "sg:postcode":"9820",
    "sg:province":"Oost-Vlaanderen",
    "wof:name":"Filip Hutsebaut",
    "wof:placetype":"venue"
},
  "geometry": {"coordinates":[3.7456190586,50.9888038635],"type":"Point"}
}