{
  "type": "Feature",
  "properties": {
    "addr:full":"Rue Gachard 52 Bruxelles (ixelles) Bruxelles-Capitale 1050",
    "addr:housenumber":"52",
    "addr:postcode":"1050",
    "addr:street":"Rue Gachard",
    "iso:country":"BE",
    "sg:address":"Rue Gachard 52",
    "sg:city":"Bruxelles (ixelles)",
    "sg:classifiers":[
        {
            "category":"Home & Garden",
            "subcategory":"Home Furnishings",
            "type":"Retail Goods"
        }
    ],
    "sg:phone":"+32 2 648 53 50",
    "sg:postcode":"1050",
    "sg:province":"Bruxelles-Capitale",
    "sg:tags":[
        "interior",
        "decoration"
    ],
    "wof:name":"Cr\u00e9ations Isabelle De Borchgrave",
    "wof:placetype":"venue"
},
  "geometry": {"coordinates":[4.3685998917,50.8263282776],"type":"Point"}
}