{
  "type": "Feature",
  "properties": {
    "iso:country":"BE",
    "sg:address":"Lostraat 144",
    "sg:city":"Roosdaal",
    "sg:orig_category":"Installation de menuiserie en bois and plastique",
    "sg:phone":"+32 54 33 77 62",
    "sg:postcode":"1760",
    "sg:province":"Vlaams-Brabant",
    "wof:name":"De Pauw",
    "wof:placetype":"venue"
},
  "geometry": {"coordinates":[4.1131629944,50.8431053162],"type":"Point"}
}