{
  "type": "Feature",
  "properties": {
    "iso:country":"BE",
    "sg:address":"Ankerstraat 106",
    "sg:city":"Sint-niklaas",
    "sg:orig_category":"V\u00eatements de mariage and c\u00e9r\u00e9monies. V\u00eatements sur mesure Fab. V\u00eatements",
    "sg:phone":"+32 3 776 37 35",
    "sg:postcode":"9100",
    "sg:province":"Oost-Vlaanderen",
    "wof:name":"Huis Pascal",
    "wof:placetype":"venue"
},
  "geometry": {"coordinates":[4.1475348473,51.1670608521],"type":"Point"}
}