{
  "type": "Feature",
  "properties": {
    "iso:country":"BE",
    "sg:address":"Leliestraat 10",
    "sg:city":"Geel",
    "sg:classifiers":[
        {
            "category":"Building & Trades",
            "subcategory":"Electrical",
            "type":"Services"
        }
    ],
    "sg:phone":"+32 14 59 05 08",
    "sg:postcode":"2440",
    "sg:province":"Antwerpen",
    "sg:tags":[
        "electric",
        "-",
        "housewiring",
        "contractor"
    ],
    "wof:name":"Van Eyndhoven E",
    "wof:placetype":"venue"
},
  "geometry": {"coordinates":[4.9748501778,51.1662063599],"type":"Point"}
}