{
  "type": "Feature",
  "properties": {
    "iso:country":"BE",
    "sg:address":"Vaartstraat 144",
    "sg:city":"Balen",
    "sg:classifiers":[
        {
            "category":"Retail",
            "subcategory":"Repair Shop",
            "type":"Services"
        }
    ],
    "sg:phone":"+32 14 81 63 33",
    "sg:postcode":"2490",
    "sg:province":"Antwerpen",
    "sg:tags":[
        "denture"
    ],
    "wof:name":"Van Ouytsel Bvba",
    "wof:placetype":"venue"
},
  "geometry": {"coordinates":[5.1556801796,51.1725845337],"type":"Point"}
}