{
  "type": "Feature",
  "properties": {
    "addr:full":"Heirweg 35 Kuurne West-Vlaanderen 8520",
    "addr:housenumber":"35",
    "addr:postcode":"8520",
    "addr:street":"Heirweg",
    "iso:country":"BE",
    "sg:address":"Heirweg 35",
    "sg:city":"Kuurne",
    "sg:classifiers":[
        {
            "category":"Utilities",
            "subcategory":"Electric",
            "type":"Services"
        }
    ],
    "sg:phone":"+32 56 37 33 90",
    "sg:postcode":"8520",
    "sg:province":"West-Vlaanderen",
    "sg:tags":[
        "generator"
    ],
    "wof:name":"Dirk Luyckx",
    "wof:placetype":"venue"
},
  "geometry": {"coordinates":[3.2649559975,50.854095459],"type":"Point"}
}