{
  "type": "Feature",
  "properties": {
    "addr:full":"Stichelgatstraat 11 Dilbeek Vlaams-Brabant 1700",
    "addr:housenumber":"11",
    "addr:postcode":"1700",
    "addr:street":"Stichelgatstraat",
    "iso:country":"BE",
    "sg:address":"Stichelgatstraat 11",
    "sg:city":"Dilbeek",
    "sg:orig_category":"Drogueries",
    "sg:phone":"+32 2 466 03 11",
    "sg:postcode":"1700",
    "sg:province":"Vlaams-Brabant",
    "wof:name":"Clar Decor",
    "wof:placetype":"venue"
},
  "geometry": {"coordinates":[4.2632598877,50.8624687195],"type":"Point"}
}