{
  "type": "Feature",
  "properties": {
    "iso:country":"BE",
    "sg:address":"Schoolstraat 8",
    "sg:city":"Zoutleeuw",
    "sg:orig_category":"Kapsalons",
    "sg:phone":"+32 11 58 73 79",
    "sg:postcode":"3440",
    "sg:province":"Vlaams-Brabant",
    "wof:name":"Coiffure Thomas",
    "wof:placetype":"venue"
},
  "geometry": {"coordinates":[5.0887379646,50.8639450073],"type":"Point"}
}