{
  "type": "Feature",
  "properties": {
    "iso:country":"BE",
    "sg:address":"Wondelgemstraat 202",
    "sg:city":"Gent-centrum",
    "sg:orig_category":"Randstad",
    "sg:phone":"+32 9 233 31 91",
    "sg:postcode":"9000",
    "sg:province":"Oost-Vlaanderen",
    "wof:name":"Randstad",
    "wof:placetype":"venue"
},
  "geometry": {"coordinates":[3.7093338966,51.064956665],"type":"Point"}
}