{
  "type": "Feature",
  "properties": {
    "addr:full":"Rue Des Ponts 4 Oupeye Li\u00e8ge 4684",
    "addr:housenumber":"4",
    "addr:postcode":"4684",
    "addr:street":"Rue Des Ponts",
    "iso:country":"BE",
    "sg:address":"Rue Des Ponts 4",
    "sg:city":"Oupeye",
    "sg:orig_category":"Kansspelen",
    "sg:phone":"+32 4 379 43 11",
    "sg:postcode":"4684",
    "sg:province":"Li\u00e8ge",
    "wof:name":"Tierc\u00c9 Franco Belge",
    "wof:placetype":"venue"
},
  "geometry": {"coordinates":[5.6670231819,50.7329864502],"type":"Point"}
}