{
  "type": "Feature",
  "properties": {
    "iso:country":"BE",
    "sg:address":"Blancefloerlaan 27",
    "sg:city":"Antwerpen",
    "sg:classifiers":[
        {
            "category":"Fast Food",
            "type":"Food & Drink"
        }
    ],
    "sg:phone":"+32 3 219 18 34",
    "sg:postcode":"2050",
    "sg:province":"Antwerpen",
    "sg:tags":[
        "\u00c0",
        "emporter",
        "restaurants"
    ],
    "wof:name":"Swans",
    "wof:placetype":"venue"
},
  "geometry": {"coordinates":[4.3840417862,51.2201194763],"type":"Point"}
}