{
  "type": "Feature",
  "properties": {
    "addr:full":"Oude Molenstraat 2 Drogenbos Vlaams-Brabant 1620",
    "addr:housenumber":"2",
    "addr:postcode":"1620",
    "addr:street":"Oude Molenstraat",
    "iso:country":"BE",
    "sg:address":"Oude Molenstraat 2",
    "sg:city":"Drogenbos",
    "sg:classifiers":[
        {
            "category":"Restaurant",
            "type":"Food & Drink"
        }
    ],
    "sg:phone":"+32 2 377 64 64",
    "sg:postcode":"1620",
    "sg:province":"Vlaams-Brabant",
    "sg:tags":[
        "caf\u00e9s"
    ],
    "wof:name":"Taverne La Cr\u00c8te",
    "wof:placetype":"venue"
},
  "geometry": {"coordinates":[4.3184118271,50.7902069092],"type":"Point"}
}