{
  "type": "Feature",
  "properties": {
    "addr:full":"Boulevard Audent 1 Charleroi Hainaut 6000",
    "addr:housenumber":"1",
    "addr:postcode":"6000",
    "addr:street":"Boulevard Audent;Hainaut",
    "iso:country":"BE",
    "sg:address":"Boulevard Audent 1",
    "sg:city":"Charleroi",
    "sg:orig_category":"Pharmaciens",
    "sg:phone":"+32 71 31 39 98",
    "sg:postcode":"6000",
    "sg:province":"Hainaut",
    "wof:name":"Multipharma",
    "wof:placetype":"venue"
},
  "geometry": {"coordinates":[4.4432458878,50.4102745056],"type":"Point"}
}