{
  "type": "Feature",
  "properties": {
    "iso:country":"BE",
    "sg:address":"Rue Hugo D'oignies 32",
    "sg:city":"Namur",
    "sg:orig_category":"Advocaten and juridische adviseurs",
    "sg:phone":"+32 81 30 14 00",
    "sg:postcode":"5100",
    "sg:province":"Namur",
    "wof:name":"Isabelle Zombek",
    "wof:placetype":"venue"
},
  "geometry": {"coordinates":[4.8658270836,50.4538421631],"type":"Point"}
}