{
  "type": "Feature",
  "properties": {
    "addr:full":"Kortrijksestr 443 Oostkamp West-Vlaanderen 8020",
    "addr:housenumber":"443",
    "addr:postcode":"8020",
    "iso:country":"BE",
    "sg:address":"Kortrijksestr 443",
    "sg:city":"Oostkamp",
    "sg:classifiers":[
        {
            "category":"Home & Garden",
            "subcategory":"Furniture",
            "type":"Retail Goods"
        }
    ],
    "sg:phone":"+32 50 79 90 80",
    "sg:postcode":"8020",
    "sg:province":"West-Vlaanderen",
    "sg:tags":[
        "household",
        "wood"
    ],
    "wof:name":"De Akker Nv",
    "wof:placetype":"venue"
},
  "geometry": {"coordinates":[3.2227499485,51.1264457703],"type":"Point"}
}