{
  "type": "Feature",
  "properties": {
    "iso:country":"BE",
    "sg:address":"Rue Saint-blaise 85",
    "sg:city":"Chatelet",
    "sg:orig_category":"Charpentes and couvertures",
    "sg:phone":"+32 71 39 43 96",
    "sg:postcode":"6200",
    "sg:province":"Hainaut",
    "wof:name":"Ets. Gillain",
    "wof:placetype":"venue"
},
  "geometry": {"coordinates":[4.5244550705,50.4016494751],"type":"Point"}
}