{
  "type": "Feature",
  "properties": {
    "addr:full":"Drieleienstraat 31 Gent Oost-Vlaanderen 9031",
    "addr:housenumber":"31",
    "addr:postcode":"9031",
    "addr:street":"Drieleienstraat;Oost-Vlaanderen",
    "iso:country":"BE",
    "sg:address":"Drieleienstraat 31",
    "sg:city":"Gent",
    "sg:orig_category":"Artiesten and kunstenaars",
    "sg:phone":"+32 9 227 44 90",
    "sg:postcode":"9031",
    "sg:province":"Oost-Vlaanderen",
    "wof:name":"Herman Blondeel",
    "wof:placetype":"venue"
},
  "geometry": {"coordinates":[3.6630249023,51.0503692627],"type":"Point"}
}