{
  "type": "Feature",
  "properties": {
    "addr:full":"Moorselbaan 448 Aalst Oost-Vlaanderen 9300",
    "addr:housenumber":"448",
    "addr:postcode":"9300",
    "addr:street":"Moorselbaan",
    "iso:country":"BE",
    "sg:address":"Moorselbaan 448",
    "sg:city":"Aalst",
    "sg:orig_category":"Autombile concessionaires",
    "sg:phone":"+32 53 77 42 13",
    "sg:postcode":"9300",
    "sg:province":"Oost-Vlaanderen",
    "wof:name":"Honda Center Van Gijsegem Nv",
    "wof:placetype":"venue"
},
  "geometry": {"coordinates":[4.0716547966,50.9452209473],"type":"Point"}
}