{
  "type": "Feature",
  "properties": {
    "addr:full":"August Petenlei 31 Antwerpen Antwerpen 2100",
    "addr:housenumber":"31",
    "addr:postcode":"2100",
    "iso:country":"BE",
    "sg:address":"August Petenlei 31",
    "sg:city":"Antwerpen",
    "sg:classifiers":[
        {
            "category":"Personal",
            "subcategory":"Beauty Salon",
            "type":"Services"
        }
    ],
    "sg:phone":"+32 3 366 37 37",
    "sg:postcode":"2100",
    "sg:province":"Antwerpen",
    "sg:tags":[
        "de",
        "coiffure"
    ],
    "wof:name":"Coiffure Sabina",
    "wof:placetype":"venue"
},
  "geometry": {"coordinates":[4.4586100578,51.2203941345],"type":"Point"}
}