{
  "type": "Feature",
  "properties": {
    "iso:country":"BE",
    "sg:address":"Hogeschuurstraat 1",
    "sg:city":"Staden",
    "sg:orig_category":"Eleveurs de bovins",
    "sg:phone":"+32 51 70 14 69",
    "sg:postcode":"8840",
    "sg:province":"West-Vlaanderen",
    "wof:name":"Julien Deleu",
    "wof:placetype":"venue"
},
  "geometry": {"coordinates":[3.0082950592,50.9784088135],"type":"Point"}
}