{
  "type": "Feature",
  "properties": {
    "addr:full":"Iepersestraat 123 Roeselare West-Vlaanderen 8800",
    "addr:housenumber":"123",
    "addr:postcode":"8800",
    "addr:street":"Iepersestraat",
    "iso:country":"BE",
    "sg:address":"Iepersestraat 123",
    "sg:city":"Roeselare",
    "sg:classifiers":[
        {
            "category":"Home & Garden",
            "subcategory":"Garden Supply",
            "type":"Retail Goods"
        }
    ],
    "sg:phone":"+32 51 20 04 80",
    "sg:postcode":"8800",
    "sg:province":"West-Vlaanderen",
    "sg:tags":[
        "machine",
        "agricultural",
        "-"
    ],
    "wof:name":"Vandenbroucke R",
    "wof:placetype":"venue"
},
  "geometry": {"coordinates":[3.1192979813,50.9411811829],"type":"Point"}
}