{
  "type": "Feature",
  "properties": {
    "addr:full":"Rue Quellin 42 Antwerpen Antwerpen 2018",
    "addr:housenumber":"42",
    "addr:postcode":"2018",
    "addr:street":"Rue Quellin",
    "iso:country":"BE",
    "sg:address":"Rue Quellin 42",
    "sg:city":"Antwerpen",
    "sg:orig_category":"Services de t\u00e9l\u00e9communications",
    "sg:phone":"+32 800 31 505",
    "sg:postcode":"2018",
    "sg:province":"Antwerpen",
    "wof:name":"Econophone Service Client\u00c8le",
    "wof:placetype":"venue"
},
  "geometry": {"coordinates":[4.4157891273,51.2158279419],"type":"Point"}
}