{
  "type": "Feature",
  "properties": {
    "iso:country":"BE",
    "sg:address":"Slangenstraat 52",
    "sg:city":"Lubbeek",
    "sg:orig_category":"Agences de relations publiques",
    "sg:phone":"+32 16 25 90 16",
    "sg:postcode":"3210",
    "sg:province":"Vlaams-Brabant",
    "wof:name":"Driesen Consult. & Train.",
    "wof:placetype":"venue"
},
  "geometry": {"coordinates":[4.7570781708,50.9026412964],"type":"Point"}
}