{
  "type": "Feature",
  "properties": {
    "addr:full":"Route Des Roches 29 Manhay (harre) Luxembourg 6960",
    "addr:housenumber":"29",
    "addr:postcode":"6960",
    "addr:street":"Route Des Roches",
    "iso:country":"BE",
    "sg:address":"Route Des Roches 29",
    "sg:city":"Manhay (harre)",
    "sg:classifiers":[
        {
            "category":"Manufacturing",
            "subcategory":"Metals",
            "type":"Manufacturing & Wholesale Goods"
        }
    ],
    "sg:phone":"+32 86 49 96 83",
    "sg:postcode":"6960",
    "sg:province":"Luxembourg",
    "sg:tags":[
        "ornamental",
        "work",
        "-"
    ],
    "wof:name":"Julien C M J",
    "wof:placetype":"venue"
},
  "geometry": {"coordinates":[5.5907120705,50.3490104675],"type":"Point"}
}