{
  "type": "Feature",
  "properties": {
    "iso:country":"BE",
    "sg:address":"Avenue Reine Elisabeth",
    "sg:city":"Andenne",
    "sg:orig_category":"Royal Canin. Fruits and l\u00e9gumes. Animaux domestiques and accessoires. Articles de jardin",
    "sg:phone":"+32 85 84 11 54",
    "sg:postcode":"5300",
    "sg:province":"Namur",
    "wof:name":"Tirtiaux",
    "wof:placetype":"venue"
},
  "geometry": {"coordinates":[5.0861411095,50.4911689758],"type":"Point"}
}