{
  "type": "Feature",
  "properties": {
    "addr:full":"Braamkasteelstraat 26 Gent Oost-Vlaanderen 9050",
    "addr:housenumber":"26",
    "addr:postcode":"9050",
    "addr:street":"Braamkasteelstraat;Oost-Vlaanderen",
    "iso:country":"BE",
    "sg:address":"Braamkasteelstraat 26",
    "sg:city":"Gent",
    "sg:orig_category":"Enseignement artistique",
    "sg:phone":"+32 9 230 21 21",
    "sg:postcode":"9050",
    "sg:province":"Oost-Vlaanderen",
    "wof:name":"Stedelijke Muziekacademie",
    "wof:placetype":"venue"
},
  "geometry": {"coordinates":[3.7629299164,51.0389213562],"type":"Point"}
}