{
  "type": "Feature",
  "properties": {
    "addr:full":"Rue De La Petite Guirlande 9 Mons Hainaut 7000",
    "addr:housenumber":"9",
    "addr:postcode":"7000",
    "addr:street":"Rue De La Petite Guirlande;Hainaut",
    "iso:country":"BE",
    "sg:address":"Rue De La Petite Guirlande 9",
    "sg:city":"Mons",
    "sg:classifiers":[
        {
            "category":"Shopping",
            "subcategory":"Computers & Home Electronics",
            "type":"Retail Goods"
        }
    ],
    "sg:phone":"+32 65 84 60 60",
    "sg:postcode":"7000",
    "sg:province":"Hainaut",
    "sg:tags":[
        "siemens",
        "fujitsu",
        "computerapparatuur"
    ],
    "wof:name":"Horizon 3000",
    "wof:placetype":"venue"
},
  "geometry": {"coordinates":[3.945720911,50.4511909485],"type":"Point"}
}