{
  "type": "Feature",
  "properties": {
    "addr:full":"Arthur Putzeysstraat 24 Hoegaarden Vlaams-Brabant 3320",
    "addr:housenumber":"24",
    "addr:postcode":"3320",
    "addr:street":"Arthur Putzeysstraat",
    "iso:country":"BE",
    "sg:address":"Arthur Putzeysstraat 24",
    "sg:city":"Hoegaarden",
    "sg:classifiers":[
        {
            "category":"Shopping",
            "subcategory":"Florist",
            "type":"Retail Goods"
        }
    ],
    "sg:phone":"+32 16 76 65 27",
    "sg:postcode":"3320",
    "sg:province":"Vlaams-Brabant",
    "wof:name":"Hugardiflor",
    "wof:placetype":"venue"
},
  "geometry": {"coordinates":[4.8885068893,50.7747955322],"type":"Point"}
}