{
  "type": "Feature",
  "properties": {
    "iso:country":"BE",
    "sg:address":"Rue De La Gare 55",
    "sg:city":"Bievre",
    "sg:orig_category":"Charpentes and couvertures. Constructions r\u00e9sidentielles sp\u00e9cifiques. Bois Gr",
    "sg:phone":"+32 61 51 18 85",
    "sg:postcode":"5555",
    "sg:province":"Namur",
    "wof:name":"Andre Gerard",
    "wof:placetype":"venue"
},
  "geometry": {"coordinates":[5.0344629288,49.9347572327],"type":"Point"}
}