{
  "type": "Feature",
  "properties": {
    "addr:full":"Stockeu 2 Stavelot Li\u00e8ge 4970",
    "addr:housenumber":"2",
    "addr:postcode":"4970",
    "addr:street":"Stockeu",
    "iso:country":"BE",
    "sg:address":"Stockeu 2",
    "sg:city":"Stavelot",
    "sg:orig_category":"Non-Classified Establishments",
    "sg:phone":"+32 80 89 20 20",
    "sg:postcode":"4970",
    "sg:province":"Li\u00e8ge",
    "wof:name":"Salaisons Des Blancs Moussis Sa",
    "wof:placetype":"venue"
},
  "geometry": {"coordinates":[5.932653904,50.3911018372],"type":"Point"}
}