{
  "type": "Feature",
  "properties": {
    "iso:country":"BE",
    "sg:address":"Boulevard Georges Deryck 96-98",
    "sg:city":"Tubize",
    "sg:classifiers":[
        {
            "category":"Building & Trades",
            "subcategory":"Landscaping Services",
            "type":"Services"
        }
    ],
    "sg:phone":"+32 2 355 77 91",
    "sg:postcode":"1480",
    "sg:province":"Brabant Wallon",
    "sg:tags":[
        "soil",
        "analysis"
    ],
    "wof:name":"M.s.a.",
    "wof:placetype":"venue"
},
  "geometry": {"coordinates":[4.2013688087,50.692199707],"type":"Point"}
}