{
  "type": "Feature",
  "properties": {
    "addr:full":"Rue De Magnee 108 Beyne-heusay Li\u00e8ge 4610",
    "addr:housenumber":"108",
    "addr:postcode":"4610",
    "addr:street":"Rue De Magnee",
    "iso:country":"BE",
    "sg:address":"Rue De Magnee 108",
    "sg:city":"Beyne-heusay",
    "sg:classifiers":[
        {
            "category":"Banks & Credit Unions",
            "subcategory":"Investment Brokerage",
            "type":"Services"
        }
    ],
    "sg:phone":"+32 4 358 85 75",
    "sg:postcode":"4610",
    "sg:province":"Li\u00e8ge",
    "sg:tags":[
        "control",
        "equipment",
        "switch",
        "automatic",
        "switching"
    ],
    "wof:name":"Guillaume - Teco S.a.",
    "wof:placetype":"venue"
},
  "geometry": {"coordinates":[5.6687507629,50.6151504517],"type":"Point"}
}