{
  "type": "Feature",
  "properties": {
    "iso:country":"BE",
    "sg:address":"Rue Du Couvent 8",
    "sg:city":"Walcourt",
    "sg:classifiers":[
        {
            "category":"Professional",
            "subcategory":"Accounting & Tax Preparation",
            "type":"Services"
        }
    ],
    "sg:phone":"+32 71 61 13 78",
    "sg:postcode":"5650",
    "sg:province":"Namur",
    "sg:tags":[
        "bookkeeper"
    ],
    "wof:name":"Pireaux P",
    "wof:placetype":"venue"
},
  "geometry": {"coordinates":[4.4306869507,50.2504768372],"type":"Point"}
}