{
  "type": "Feature",
  "properties": {
    "iso:country":"BE",
    "sg:address":"Route D' Arville 6",
    "sg:city":"Saint-hubert",
    "sg:orig_category":"Paramedische behandelingen",
    "sg:phone":"+32 61 61 24 12",
    "sg:postcode":"6870",
    "sg:province":"Luxembourg",
    "wof:name":"M. Guerisse",
    "wof:placetype":"venue"
},
  "geometry": {"coordinates":[5.3418259621,50.029209137],"type":"Point"}
}