{
  "type": "Feature",
  "properties": {
    "iso:country":"BE",
    "sg:address":"Heyveld 6",
    "sg:city":"Brakel (nederbrakel)",
    "sg:classifiers":[
        {
            "category":"Professional",
            "subcategory":"Management & Consulting",
            "type":"Services"
        }
    ],
    "sg:phone":"+32 55 42 03 78",
    "sg:postcode":"9660",
    "sg:province":"Oost-Vlaanderen",
    "sg:tags":[
        "-",
        "processing",
        "data",
        "consultant"
    ],
    "wof:name":"Bekasoft.com",
    "wof:placetype":"venue"
},
  "geometry": {"coordinates":[3.7875750065,50.8127288818],"type":"Point"}
}