{
  "type": "Feature",
  "properties": {
    "iso:country":"BE",
    "sg:address":"Karperstraat 204",
    "sg:city":"Gent",
    "sg:classifiers":[
        {
            "category":"Bakery",
            "type":"Food & Drink"
        }
    ],
    "sg:phone":"+32 9 233 25 27",
    "sg:postcode":"9000",
    "sg:province":"Oost-Vlaanderen",
    "sg:tags":[
        "confectioner",
        "baker"
    ],
    "wof:name":"Korenaar (de)",
    "wof:placetype":"venue"
},
  "geometry": {"coordinates":[3.7435688972,51.0453796387],"type":"Point"}
}