{
  "type": "Feature",
  "properties": {
    "addr:full":"Sluisvijverstraat 15a Ternat (sint-katherina-lombeek) Vlaams-Brabant 1742",
    "addr:housenumber":"15a",
    "addr:postcode":"1742",
    "addr:street":"Sluisvijverstraat",
    "iso:country":"BE",
    "sg:address":"Sluisvijverstraat 15a",
    "sg:city":"Ternat (sint-katherina-lombeek)",
    "sg:classifiers":[
        {
            "category":"Personal",
            "subcategory":"Beauty Salon",
            "type":"Services"
        }
    ],
    "sg:phone":"+32 53 66 27 54",
    "sg:postcode":"1742",
    "sg:province":"Vlaams-Brabant",
    "sg:tags":[
        "lady",
        "-",
        "hairdressing"
    ],
    "wof:name":"Christine",
    "wof:placetype":"venue"
},
  "geometry": {"coordinates":[4.1168651581,50.8819656372],"type":"Point"}
}