{
  "type": "Feature",
  "properties": {
    "addr:full":"Molhemstraat 35 Peer Limburg 3990",
    "addr:housenumber":"35",
    "addr:postcode":"3990",
    "addr:street":"Molhemstraat",
    "iso:country":"BE",
    "sg:address":"Molhemstraat 35",
    "sg:city":"Peer",
    "sg:orig_category":"Epiceries",
    "sg:phone":"+32 11 63 20 51",
    "sg:postcode":"3990",
    "sg:province":"Limburg",
    "wof:name":"Maria Daenen",
    "wof:placetype":"venue"
},
  "geometry": {"coordinates":[5.4379458427,51.1369132996],"type":"Point"}
}