{
  "type": "Feature",
  "properties": {
    "addr:full":"Weg Naar Bijloos 15 Houthalen-helchteren (houthalen) Limburg 3530",
    "addr:housenumber":"15",
    "addr:postcode":"3530",
    "addr:street":"Weg Naar Bijloos",
    "iso:country":"BE",
    "sg:address":"Weg Naar Bijloos 15",
    "sg:city":"Houthalen-helchteren (houthalen)",
    "sg:classifiers":[
        {
            "category":"Education",
            "subcategory":"Special Training",
            "type":"Public Place"
        }
    ],
    "sg:phone":"+32 11 72 69 60",
    "sg:postcode":"3530",
    "sg:province":"Limburg",
    "sg:tags":[
        "-",
        "processing",
        "data"
    ],
    "wof:name":"Boldimmo Nv",
    "wof:placetype":"venue"
},
  "geometry": {"coordinates":[5.4062252045,51.0304222107],"type":"Point"}
}