{
  "type": "Feature",
  "properties": {
    "addr:full":"Beekmolenstraat 7ba Beveren Oost-Vlaanderen 9120",
    "addr:postcode":"9120",
    "addr:street":"Beekmolenstraat;Oost-Vlaanderen",
    "iso:country":"BE",
    "sg:address":"Beekmolenstraat 7ba",
    "sg:city":"Beveren",
    "sg:orig_category":"Eleveurs de bovins. Eleveurs and marchands de porcs",
    "sg:phone":"+32 3 775 80 23",
    "sg:postcode":"9120",
    "sg:province":"Oost-Vlaanderen",
    "wof:name":"Herman Maes",
    "wof:placetype":"venue"
},
  "geometry": {"coordinates":[4.2878050804,51.2088356018],"type":"Point"}
}