{
  "type": "Feature",
  "properties": {
    "iso:country":"BE",
    "sg:address":"Alemstraat 21",
    "sg:city":"Kapelle-op-den-bos",
    "sg:orig_category":"Herstelling and restauratie van meubelen",
    "sg:phone":"+32 15 71 36 41",
    "sg:postcode":"1880",
    "sg:province":"Vlaams-Brabant",
    "wof:name":"Braeckmans",
    "wof:placetype":"venue"
},
  "geometry": {"coordinates":[4.3729457855,51.0260162354],"type":"Point"}
}