{
  "type": "Feature",
  "properties": {
    "addr:full":"Hulselstraat 40 Retie Antwerpen 2470",
    "addr:housenumber":"40",
    "addr:postcode":"2470",
    "addr:street":"Hulselstraat",
    "iso:country":"BE",
    "sg:address":"Hulselstraat 40",
    "sg:city":"Retie",
    "sg:orig_category":"Kapsalons Schoonheidssalons",
    "sg:phone":"+32 14 37 75 52",
    "sg:postcode":"2470",
    "sg:province":"Antwerpen",
    "wof:name":"Trenza",
    "wof:placetype":"venue"
},
  "geometry": {"coordinates":[5.1024899483,51.2717895508],"type":"Point"}
}