{
  "type": "Feature",
  "properties": {
    "iso:country":"BE",
    "sg:address":"Ingberthoeveweg 21",
    "sg:city":"Aartselaar",
    "sg:classifiers":[
        {
            "category":"Utilities",
            "subcategory":"Water",
            "type":"Services"
        }
    ],
    "sg:phone":"+32 3 450 45 02",
    "sg:postcode":"2630",
    "sg:province":"Antwerpen",
    "sg:tags":[
        "purification"
    ],
    "wof:name":"Aquaplus Nv",
    "wof:placetype":"venue"
},
  "geometry": {"coordinates":[4.3950300217,51.148979187],"type":"Point"}
}