{
  "type": "Feature",
  "properties": {
    "iso:country":"BE",
    "sg:address":"Chauss\u00c9e Romaine 31",
    "sg:city":"Vresse-sur-semois",
    "sg:classifiers":[
        {
            "category":"Restaurant",
            "type":"Food & Drink"
        }
    ],
    "sg:phone":"+32 61 50 00 16",
    "sg:postcode":"5550",
    "sg:province":"Namur",
    "wof:name":"Au Pique-nique",
    "wof:placetype":"venue"
},
  "geometry": {"coordinates":[4.9014167786,49.8657493591],"type":"Point"}
}