{
  "type": "Feature",
  "properties": {
    "iso:country":"BE",
    "sg:address":"Prof. Dr. Vital Celenplein 22",
    "sg:city":"Hulshout",
    "sg:orig_category":"Beveiligingsdiensten and bewakingsbedrijven Herstelling leer and schoeisel Herstellingswinkels voor ",
    "sg:phone":"+32 477 93 04 94",
    "sg:postcode":"2235",
    "sg:province":"Antwerpen",
    "wof:name":"Nico",
    "wof:placetype":"venue"
},
  "geometry": {"coordinates":[4.7884349823,51.0753211975],"type":"Point"}
}