{
  "type": "Feature",
  "properties": {
    "addr:full":"Gravin Elisabethlaan 2 Hoogstraten (groot) Antwerpen 2320",
    "addr:housenumber":"2",
    "addr:postcode":"2320",
    "addr:street":"Gravin Elisabethlaan;Groot Antwerpen",
    "iso:country":"BE",
    "sg:address":"Gravin Elisabethlaan 2",
    "sg:city":"Hoogstraten (groot)",
    "sg:orig_category":"Activit\u00e9s d\u00b4action sociale sans h\u00e9bergement",
    "sg:phone":"+32 3 314 57 19",
    "sg:postcode":"2320",
    "sg:province":"Antwerpen",
    "wof:name":"Clb",
    "wof:placetype":"venue"
},
  "geometry": {"coordinates":[4.7606010437,51.4007606506],"type":"Point"}
}