{
  "type": "Feature",
  "properties": {
    "iso:country":"BE",
    "sg:address":"Geraardsbergsestraat 130",
    "sg:city":"Dilbeek (schepdaal)",
    "sg:classifiers":[
        {
            "category":"Home & Garden",
            "subcategory":"Building Materials",
            "type":"Retail Goods"
        }
    ],
    "sg:phone":"+32 2 569 74 39",
    "sg:postcode":"1703",
    "sg:province":"Vlaams-Brabant",
    "sg:tags":[
        "house"
    ],
    "wof:name":"Wauters Tuinhuizen",
    "wof:placetype":"venue"
},
  "geometry": {"coordinates":[4.1904520988,50.8329658508],"type":"Point"}
}