{
  "type": "Feature",
  "properties": {
    "iso:country":"BE",
    "sg:address":"Avenue Albert Lancaster 92",
    "sg:city":"Ukkel/uccle",
    "sg:orig_category":"M\u00e9decins and sp\u00e9cialistes",
    "sg:phone":"+32 2 375 27 42",
    "sg:postcode":"1180",
    "sg:province":"Bruxelles-Capitale",
    "wof:name":"I. Renard",
    "wof:placetype":"venue"
},
  "geometry": {"coordinates":[4.3659420013,50.7970695496],"type":"Point"}
}