{
  "type": "Feature",
  "properties": {
    "addr:full":"Binsterweg 103 Eupen Li\u00e8ge 4700",
    "addr:housenumber":"103",
    "addr:postcode":"4700",
    "addr:street":"Binsterweg",
    "iso:country":"BE",
    "sg:address":"Binsterweg 103",
    "sg:city":"Eupen",
    "sg:classifiers":[
        {
            "category":"Professional",
            "subcategory":"Management & Consulting",
            "type":"Services"
        }
    ],
    "sg:phone":"+32 87 74 42 53",
    "sg:postcode":"4700",
    "sg:province":"Li\u00e8ge",
    "sg:tags":[
        "consultant"
    ],
    "wof:name":"Talleyrand Consulting Kamlah Helmut Ph.d",
    "wof:placetype":"venue"
},
  "geometry": {"coordinates":[6.0507521629,50.6137161255],"type":"Point"}
}