{
  "type": "Feature",
  "properties": {
    "addr:full":"Prins Albertlaan 30 Izegem West-Vlaanderen 8870",
    "addr:housenumber":"30",
    "addr:postcode":"8870",
    "addr:street":"Prins Albertlaan",
    "iso:country":"BE",
    "sg:address":"Prins Albertlaan 30",
    "sg:city":"Izegem",
    "sg:classifiers":[
        {
            "category":"Banks & Credit Unions",
            "subcategory":"Investment Brokerage",
            "type":"Services"
        }
    ],
    "sg:phone":"+32 51 30 00 38",
    "sg:postcode":"8870",
    "sg:province":"West-Vlaanderen",
    "sg:tags":[
        "-",
        "plastic"
    ],
    "wof:name":"J R Talonform Nv",
    "wof:placetype":"venue"
},
  "geometry": {"coordinates":[3.2053339481,50.9227142334],"type":"Point"}
}