{
  "type": "Feature",
  "properties": {
    "iso:country":"BE",
    "sg:address":"Rue Lambert 32",
    "sg:city":"Beaumont",
    "sg:orig_category":"Elektrische installaties voor woningen",
    "sg:phone":"+32 71 53 48 54",
    "sg:postcode":"6511",
    "sg:province":"Hainaut",
    "wof:name":"Fe. Patigny",
    "wof:placetype":"venue"
},
  "geometry": {"coordinates":[4.300055027,50.2779655457],"type":"Point"}
}