{
  "type": "Feature",
  "properties": {
    "addr:full":"Stationsstraat 72 Galmaarden Vlaams-Brabant 1570",
    "addr:housenumber":"72",
    "addr:postcode":"1570",
    "addr:street":"Stationsstraat",
    "iso:country":"BE",
    "sg:address":"Stationsstraat 72",
    "sg:city":"Galmaarden",
    "sg:orig_category":"Boucheries",
    "sg:phone":"+32 54 58 90 92",
    "sg:postcode":"1570",
    "sg:province":"Vlaams-Brabant",
    "wof:name":"Louis Souffriau",
    "wof:placetype":"venue"
},
  "geometry": {"coordinates":[3.9702219963,50.7466812134],"type":"Point"}
}