{
  "type": "Feature",
  "properties": {
    "iso:country":"BE",
    "sg:address":"Rue L\u00e9on Delacroix 12",
    "sg:city":"Bruxelles (anderlecht)",
    "sg:classifiers":[
        {
            "category":"Wholesale",
            "subcategory":"Meat",
            "type":"Manufacturing & Wholesale Goods"
        }
    ],
    "sg:phone":"+32 2 410 37 35",
    "sg:postcode":"1070",
    "sg:province":"Bruxelles-Capitale",
    "sg:tags":[
        "whol",
        "-"
    ],
    "wof:name":"Aelbrecht Bvba",
    "wof:placetype":"venue"
},
  "geometry": {"coordinates":[4.3294267654,50.8428153992],"type":"Point"}
}