{
  "type": "Feature",
  "properties": {
    "iso:country":"BE",
    "sg:address":"Jan De Donckerlaan 4",
    "sg:city":"Puurs",
    "sg:classifiers":[
        {
            "category":"Arena",
            "subcategory":"Sports Club",
            "type":"Entertainment"
        }
    ],
    "sg:phone":"+32 3 886 18 02",
    "sg:postcode":"2870",
    "sg:province":"Antwerpen",
    "sg:tags":[
        "de"
    ],
    "wof:name":"Acro Pro Gymnastics",
    "wof:placetype":"venue"
},
  "geometry": {"coordinates":[4.3243770599,51.0787353516],"type":"Point"}
}