{
  "type": "Feature",
  "properties": {
    "iso:country":"BE",
    "sg:address":"Ch.de Saint-ghislain 189",
    "sg:city":"Chievres",
    "sg:classifiers":[
        {
            "category":"Wholesale",
            "subcategory":"Farm Supplies",
            "type":"Manufacturing & Wholesale Goods"
        }
    ],
    "sg:phone":"+32 68 65 70 68",
    "sg:postcode":"7950",
    "sg:province":"Hainaut",
    "sg:tags":[
        "machine",
        "agricoles",
        "mat\u00e9riel",
        "gr"
    ],
    "wof:name":"Daniel Marginet",
    "wof:placetype":"venue"
},
  "geometry": {"coordinates":[3.8061699867,50.5644493103],"type":"Point"}
}