{
  "type": "Feature",
  "properties": {
    "iso:country":"BE",
    "sg:address":"Thiriarlaan 51",
    "sg:city":"Brussel/bruxelles",
    "sg:orig_category":"Kapsalons",
    "sg:phone":"+32 2 479 60 06",
    "sg:postcode":"1020",
    "sg:province":"Bruxelles-Capitale",
    "wof:name":"Coiffure Citronelle",
    "wof:placetype":"venue"
},
  "geometry": {"coordinates":[4.3273658752,50.8914871216],"type":"Point"}
}