{
  "type": "Feature",
  "properties": {
    "iso:country":"BE",
    "sg:address":"Crocqstraat 114",
    "sg:city":"Sint-lambrechts-woluwe/woluwe-saint-lambert",
    "sg:orig_category":"Sportclubs",
    "sg:phone":"+32 2 762 26 93",
    "sg:postcode":"1200",
    "sg:province":"Bruxelles-Capitale",
    "wof:name":"Toffe Jeugd Volley Zellik",
    "wof:placetype":"venue"
},
  "geometry": {"coordinates":[4.4203767776,50.8480224609],"type":"Point"}
}