{
  "type": "Feature",
  "properties": {
    "addr:full":"Wolverbosstraat 8 Mechelen Antwerpen 2800",
    "addr:housenumber":"8",
    "addr:postcode":"2800",
    "addr:street":"Wolverbosstraat",
    "iso:country":"BE",
    "sg:address":"Wolverbosstraat 8",
    "sg:city":"Mechelen",
    "sg:orig_category":"Slagers",
    "sg:phone":"+32 15 27 15 02",
    "sg:postcode":"2800",
    "sg:province":"Antwerpen",
    "wof:name":"Huis Maerevoet-v.d. Bulck",
    "wof:placetype":"venue"
},
  "geometry": {"coordinates":[4.4455709457,51.0417289734],"type":"Point"}
}