{
  "type": "Feature",
  "properties": {
    "iso:country":"BE",
    "sg:address":"Rue De La Gare 15",
    "sg:city":"Libramont-chevigny",
    "sg:orig_category":"Apotheken",
    "sg:phone":"+32 61 22 33 80",
    "sg:postcode":"6800",
    "sg:province":"Luxembourg",
    "wof:name":"E.p.c.",
    "wof:placetype":"venue"
},
  "geometry": {"coordinates":[5.3761348724,49.9199943542],"type":"Point"}
}