{
  "type": "Feature",
  "properties": {
    "addr:full":"Place Anneessens 13 Bruxelles Bruxelles-Capitale 1000",
    "addr:housenumber":"13",
    "addr:postcode":"1000",
    "addr:street":"Place Anneessens",
    "iso:country":"BE",
    "sg:address":"Place Anneessens 13",
    "sg:city":"Bruxelles",
    "sg:classifiers":[
        {
            "category":"Social Services",
            "type":"Services"
        }
    ],
    "sg:phone":"+32 2 502 70 79",
    "sg:postcode":"1000",
    "sg:province":"Bruxelles-Capitale",
    "wof:name":"Oxfam Solidarite-solidariteit",
    "wof:placetype":"venue"
},
  "geometry": {"coordinates":[4.3437981606,50.8442344666],"type":"Point"}
}