{
  "type": "Feature",
  "properties": {
    "addr:full":"Hollebekestraat 25 Heuvelland West-Vlaanderen 8953",
    "addr:housenumber":"25",
    "addr:postcode":"8953",
    "addr:street":"Hollebekestraat",
    "iso:country":"BE",
    "sg:address":"Hollebekestraat 25",
    "sg:city":"Heuvelland",
    "sg:orig_category":"Eleveurs de bovins",
    "sg:phone":"+32 57 20 74 17",
    "sg:postcode":"8953",
    "sg:province":"West-Vlaanderen",
    "wof:name":"Noel Barbez",
    "wof:placetype":"venue"
},
  "geometry": {"coordinates":[2.9202489853,50.7986412048],"type":"Point"}
}