{
  "type": "Feature",
  "properties": {
    "iso:country":"BE",
    "sg:address":"Kraaiendonk 5",
    "sg:city":"Sint-martens-latem",
    "sg:orig_category":"Artsen and specialisten",
    "sg:phone":"+32 9 281 15 70",
    "sg:postcode":"9830",
    "sg:province":"Oost-Vlaanderen",
    "wof:name":"Fran\u00c7oise Van Maele",
    "wof:placetype":"venue"
},
  "geometry": {"coordinates":[3.6363620758,51.0044326782],"type":"Point"}
}