{
  "type": "Feature",
  "properties": {
    "iso:country":"BE",
    "sg:address":"Boerenkrijglaan 37",
    "sg:city":"Westerlo",
    "sg:classifiers":[
        {
            "category":"Health Services",
            "subcategory":"Health Practitioner",
            "type":"Services"
        }
    ],
    "sg:phone":"+32 14 54 45 06",
    "sg:postcode":"2260",
    "sg:province":"Antwerpen",
    "sg:tags":[
        "physiotherapist"
    ],
    "wof:name":"Van De Poel Jozef",
    "wof:placetype":"venue"
},
  "geometry": {"coordinates":[4.9148740768,51.0883026123],"type":"Point"}
}