{
  "type": "Feature",
  "properties": {
    "addr:full":"Atealaan 17 Herentals Antwerpen 2200",
    "addr:housenumber":"17",
    "addr:postcode":"2200",
    "addr:street":"Atealaan",
    "iso:country":"BE",
    "sg:address":"Atealaan 17",
    "sg:city":"Herentals",
    "sg:classifiers":[
        {
            "category":"Professional",
            "subcategory":"Engineering",
            "type":"Services"
        }
    ],
    "sg:phone":"+32 14 23 13 71",
    "sg:postcode":"2200",
    "sg:province":"Antwerpen",
    "sg:tags":[
        "-"
    ],
    "wof:name":"Endesys Nv",
    "wof:placetype":"venue"
},
  "geometry": {"coordinates":[4.7880501747,51.1609992981],"type":"Point"}
}