{
  "type": "Feature",
  "properties": {
    "addr:full":"Hoge Bokstraat 196 Sint-niklaas Oost-Vlaanderen 9111",
    "addr:housenumber":"196",
    "addr:postcode":"9111",
    "addr:street":"Hoge Bokstraat",
    "iso:country":"BE",
    "sg:address":"Hoge Bokstraat 196",
    "sg:city":"Sint-niklaas",
    "sg:orig_category":"Afbraak- and draineerwerken Goederenvervoer over de weg",
    "sg:phone":"+32 3 776 34 63",
    "sg:postcode":"9111",
    "sg:province":"Oost-Vlaanderen",
    "wof:name":"Smet A. En R.",
    "wof:placetype":"venue"
},
  "geometry": {"coordinates":[4.1122832298,51.1680145264],"type":"Point"}
}