{
  "type": "Feature",
  "properties": {
    "iso:country":"BE",
    "sg:address":"Oude Vest 150",
    "sg:city":"Dendermonde",
    "sg:orig_category":"Protection civile",
    "sg:phone":"+32 52 21 76 77",
    "sg:postcode":"9200",
    "sg:province":"Oost-Vlaanderen",
    "wof:name":"Brandweerkazerne",
    "wof:placetype":"venue"
},
  "geometry": {"coordinates":[4.1044549942,51.0311393738],"type":"Point"}
}