{
  "type": "Feature",
  "properties": {
    "iso:country":"BE",
    "sg:address":"Rue Du Paquis 29",
    "sg:city":"Aubange (halanzy)",
    "sg:classifiers":[
        {
            "category":"Building & Trades",
            "subcategory":"Landscaping Services",
            "type":"Services"
        }
    ],
    "sg:phone":"+32 63 67 70 84",
    "sg:postcode":"6792",
    "sg:province":"Luxembourg",
    "sg:tags":[
        "moss",
        "removal"
    ],
    "wof:name":"Luxembourg Nettoyage",
    "wof:placetype":"venue"
},
  "geometry": {"coordinates":[5.741268158,49.5594177246],"type":"Point"}
}