{
  "type": "Feature",
  "properties": {
    "iso:country":"BE",
    "sg:address":"Ter Maelenbaan 2",
    "sg:city":"Schilde",
    "sg:orig_category":"Artsen and specialisten",
    "sg:phone":"+32 3 384 00 92",
    "sg:postcode":"2970",
    "sg:province":"Antwerpen",
    "wof:name":"Ludo J.m. Schuddinck",
    "wof:placetype":"venue"
},
  "geometry": {"coordinates":[4.5735301971,51.2339515686],"type":"Point"}
}