{
  "type": "Feature",
  "properties": {
    "iso:country":"BE",
    "sg:address":"Beneluxlaan 79",
    "sg:city":"Tielt",
    "sg:classifiers":[
        {
            "category":"Building & Trades",
            "subcategory":"Construction",
            "type":"Services"
        }
    ],
    "sg:phone":"+32 51 40 21 23",
    "sg:postcode":"8700",
    "sg:province":"West-Vlaanderen",
    "sg:tags":[
        "surveyor",
        "-"
    ],
    "wof:name":"Dornez Co\u00d6rdinatenbureau",
    "wof:placetype":"venue"
},
  "geometry": {"coordinates":[3.3390679359,51.0016479492],"type":"Point"}
}