{
  "type": "Feature",
  "properties": {
    "iso:country":"BE",
    "sg:address":"Brand 78",
    "sg:city":"Retie",
    "sg:classifiers":[
        {
            "category":"Sports & Exercise",
            "subcategory":"Sports Center",
            "type":"Entertainment"
        }
    ],
    "sg:phone":"+32 14 37 90 41",
    "sg:postcode":"2470",
    "sg:province":"Antwerpen",
    "sg:tags":[
        "installation",
        "sportifs",
        "camping",
        "de",
        "terrain",
        "hors"
    ],
    "wof:name":"Camping Berkenstrand",
    "wof:placetype":"venue"
},
  "geometry": {"coordinates":[5.1260547638,51.2761535645],"type":"Point"}
}