{
  "type": "Feature",
  "properties": {
    "iso:country":"BE",
    "sg:address":"Engelenweg 19",
    "sg:city":"Opglabbeek",
    "sg:orig_category":"Travaux de pl\u00e2trage. Rev\u00eatements de sols and murs",
    "sg:phone":"+32 89 85 41 08",
    "sg:postcode":"3660",
    "sg:province":"Limburg",
    "wof:name":"Fa. Segers J.",
    "wof:placetype":"venue"
},
  "geometry": {"coordinates":[5.5813407898,51.0478096008],"type":"Point"}
}