{
  "type": "Feature",
  "properties": {
    "iso:country":"BE",
    "sg:address":"Rue De La R\u00e9sistance 19",
    "sg:city":"Fl\u00e9malle (mons-lez-li\u00e8ge)",
    "sg:classifiers":[
        {
            "category":"Health Services",
            "subcategory":"Doctor",
            "type":"Services"
        }
    ],
    "sg:phone":"+32 4 250 40 07",
    "sg:postcode":"4400",
    "sg:province":"Li\u00e8ge",
    "sg:tags":[
        "medicinephysicians",
        "surgeon"
    ],
    "wof:name":"Graindorge Mireille",
    "wof:placetype":"venue"
},
  "geometry": {"coordinates":[5.4238052368,50.6165885925],"type":"Point"}
}