{
  "type": "Feature",
  "properties": {
    "addr:full":"Quai Godefroid-kurth 19-93 Li\u00e8ge 1 (li\u00e8ge 2) Li\u00e8ge 4020",
    "addr:housenumber":"2",
    "addr:postcode":"19-93;4020",
    "addr:street":"Quai Godefroid-Kurth;Lie\u0300Ge",
    "iso:country":"BE",
    "sg:address":"Quai Godefroid-kurth 19-93",
    "sg:city":"Li\u00e8ge 1 (li\u00e8ge 2)",
    "sg:classifiers":[
        {
            "category":"Building & Trades",
            "subcategory":"Plumbing",
            "type":"Services"
        }
    ],
    "sg:phone":"+32 4 342 08 78",
    "sg:postcode":"4020",
    "sg:province":"Li\u00e8ge",
    "sg:tags":[
        "pipe",
        "drain",
        "unblocking"
    ],
    "wof:name":"allo Plombier - O.wlogalski",
    "wof:placetype":"venue"
},
  "geometry": {"coordinates":[5.5886311531,50.6460418701],"type":"Point"}
}