{
  "type": "Feature",
  "properties": {
    "addr:full":"Keienberglaan 4 Grimbergen Vlaams-Brabant 1850",
    "addr:housenumber":"4",
    "addr:postcode":"1850",
    "addr:street":"Keienberglaan",
    "iso:country":"BE",
    "sg:address":"Keienberglaan 4",
    "sg:city":"Grimbergen",
    "sg:orig_category":"M\u00e9decins and sp\u00e9cialistes",
    "sg:phone":"+32 2 269 68 51",
    "sg:postcode":"1850",
    "sg:province":"Vlaams-Brabant",
    "wof:name":"D. Van Linthoudt",
    "wof:placetype":"venue"
},
  "geometry": {"coordinates":[4.3669848442,50.9360618591],"type":"Point"}
}