{
  "type": "Feature",
  "properties": {
    "iso:country":"BE",
    "sg:address":"Jan Leostraat 3",
    "sg:city":"Asse (zellik)",
    "sg:classifiers":[
        {
            "category":"Home & Garden",
            "subcategory":"Building Materials",
            "type":"Retail Goods"
        }
    ],
    "sg:phone":"+32 2 460 17 32",
    "sg:postcode":"1731",
    "sg:province":"Vlaams-Brabant",
    "sg:tags":[
        "shutter"
    ],
    "wof:name":"De Coster-van Mileghem Bvba",
    "wof:placetype":"venue"
},
  "geometry": {"coordinates":[4.2844090462,50.8908348083],"type":"Point"}
}