{
  "type": "Feature",
  "properties": {
    "iso:country":"BE",
    "sg:address":"Rietstraat 2",
    "sg:city":"Westerlo",
    "sg:classifiers":[
        {
            "category":"Health Services",
            "subcategory":"Health Practitioner",
            "type":"Services"
        }
    ],
    "sg:phone":"+32 14 26 76 83",
    "sg:postcode":"2260",
    "sg:province":"Antwerpen",
    "sg:tags":[
        "dietitian"
    ],
    "wof:name":"Dilli\u00ebn V",
    "wof:placetype":"venue"
},
  "geometry": {"coordinates":[4.9198942184,51.0880699158],"type":"Point"}
}