{
  "type": "Feature",
  "properties": {
    "addr:full":"Emiel Becquaertlaan 101 Mol Antwerpen 2400",
    "addr:housenumber":"101",
    "addr:postcode":"2400",
    "addr:street":"Emiel Becquaertlaan",
    "iso:country":"BE",
    "sg:address":"Emiel Becquaertlaan 101",
    "sg:city":"Mol",
    "sg:classifiers":[
        {
            "category":"Utilities",
            "subcategory":"Fuel Oil & Lpg",
            "type":"Services"
        }
    ],
    "sg:phone":"+32 14 31 29 99",
    "sg:postcode":"2400",
    "sg:province":"Antwerpen",
    "wof:name":"Altraco Nv",
    "wof:placetype":"venue"
},
  "geometry": {"coordinates":[5.102399826,51.2135047913],"type":"Point"}
}