{
  "type": "Feature",
  "properties": {
    "iso:country":"BE",
    "sg:address":"Marktstraat 5",
    "sg:city":"Genk",
    "sg:classifiers":[
        {
            "category":"Shopping",
            "subcategory":"Shoes",
            "type":"Retail Goods"
        }
    ],
    "sg:phone":"+32 89 35 28 52",
    "sg:postcode":"3600",
    "sg:province":"Limburg",
    "sg:tags":[
        "slipper",
        "-"
    ],
    "wof:name":"Dani\u00ebls B\u00f6gemann",
    "wof:placetype":"venue"
},
  "geometry": {"coordinates":[5.5008239746,50.9651298523],"type":"Point"}
}