{
  "type": "Feature",
  "properties": {
    "iso:country":"BE",
    "sg:address":"Olmenlaan 7",
    "sg:city":"Kasterlee",
    "sg:classifiers":[
        {
            "category":"Shopping Center",
            "type":"Public Place"
        }
    ],
    "sg:phone":"+32 14 55 56 95",
    "sg:postcode":"2460",
    "sg:province":"Antwerpen",
    "sg:tags":[
        "enseignement",
        "formation"
    ],
    "wof:name":"A.v.d.",
    "wof:placetype":"venue"
},
  "geometry": {"coordinates":[4.9016227722,51.2078285217],"type":"Point"}
}