{
  "type": "Feature",
  "properties": {
    "iso:country":"BE",
    "sg:address":"105",
    "sg:city":"Gilseinde 2380 Ravels",
    "sg:classifiers":[
        {
            "category":"Building & Trades",
            "subcategory":"Construction",
            "type":"Services"
        }
    ],
    "sg:phone":"+32 14 65 96 56",
    "sg:postcode":"105",
    "sg:tags":[
        "work",
        "public"
    ],
    "wof:name":"D.f.m. Milieu Verzorging Nv",
    "wof:placetype":"venue"
},
  "geometry": {"coordinates":[5.0098800659,51.3722572327],"type":"Point"}
}