{
  "type": "Feature",
  "properties": {
    "addr:full":"Rue Des Tanneries 17 Rochefort Namur 5580",
    "addr:housenumber":"17",
    "addr:postcode":"5580",
    "addr:street":"Rue Des Tanneries",
    "iso:country":"BE",
    "sg:address":"Rue Des Tanneries 17",
    "sg:city":"Rochefort",
    "sg:classifiers":[
        {
            "category":"Food & Beverages",
            "subcategory":"Supermarket",
            "type":"Retail Goods"
        }
    ],
    "sg:phone":"+32 84 21 09 00",
    "sg:postcode":"5580",
    "sg:province":"Namur",
    "sg:tags":[
        "department",
        "store"
    ],
    "wof:name":"Spar",
    "wof:placetype":"venue"
},
  "geometry": {"coordinates":[5.2190899849,50.1612281799],"type":"Point"}
}