{
  "type": "Feature",
  "properties": {
    "addr:full":"Jagersstraat 7 Ichtegem West-Vlaanderen 8480",
    "addr:housenumber":"7",
    "addr:postcode":"8480",
    "addr:street":"Jagersstraat",
    "iso:country":"BE",
    "sg:address":"Jagersstraat 7",
    "sg:city":"Ichtegem",
    "sg:orig_category":"Electrom\u00e9nager, t\u00e9l\u00e9visions and radios",
    "sg:phone":"+32 51 58 14 24",
    "sg:postcode":"8480",
    "sg:province":"West-Vlaanderen",
    "wof:name":"Goemaere Telecommunicatie",
    "wof:placetype":"venue"
},
  "geometry": {"coordinates":[3.0281829834,51.0754814148],"type":"Point"}
}