{
  "type": "Feature",
  "properties": {
    "iso:country":"BE",
    "sg:address":"Passerelstraat 6",
    "sg:city":"Hasselt",
    "sg:classifiers":[
        {
            "category":"Autos & Motor Vehicles",
            "subcategory":"Fuel & Gas Station",
            "type":"Retail Goods"
        }
    ],
    "sg:phone":"+32 475 23 72 79",
    "sg:postcode":"3500",
    "sg:province":"Limburg",
    "sg:tags":[
        "appliance",
        "mainten",
        "-"
    ],
    "wof:name":"Sani-scooter",
    "wof:placetype":"venue"
},
  "geometry": {"coordinates":[5.3319811821,50.9296836853],"type":"Point"}
}