{
  "type": "Feature",
  "properties": {
    "iso:country":"BE",
    "sg:address":"Herentalsesteenweg 58",
    "sg:city":"Herselt",
    "sg:classifiers":[
        {
            "category":"Autos & Motor Vehicles",
            "subcategory":"Fuel & Gas Station",
            "type":"Retail Goods"
        }
    ],
    "sg:phone":"+32 14 54 47 44",
    "sg:postcode":"2230",
    "sg:province":"Antwerpen",
    "wof:name":"Houtmeyrs Bvba",
    "wof:placetype":"venue"
},
  "geometry": {"coordinates":[4.8786249161,51.0705223083],"type":"Point"}
}