{
  "type": "Feature",
  "properties": {
    "iso:country":"BE",
    "sg:address":"Vierwinden 13",
    "sg:city":"Zaventem",
    "sg:classifiers":[
        {
            "category":"Education",
            "subcategory":"Special Training",
            "type":"Public Place"
        }
    ],
    "sg:phone":"+32 2 712 59 11",
    "sg:postcode":"1930",
    "sg:province":"Vlaams-Brabant",
    "sg:tags":[
        "professional"
    ],
    "wof:name":"Group 4 Total Security",
    "wof:placetype":"venue"
},
  "geometry": {"coordinates":[4.4886798859,50.8717918396],"type":"Point"}
}