{
  "type": "Feature",
  "properties": {
    "addr:full":"Waterloose Steenweg 550 Elsene/ixelles Bruxelles-Capitale 1050",
    "addr:housenumber":"550",
    "addr:postcode":"1050",
    "addr:street":"Waterloose Steenweg",
    "iso:country":"BE",
    "sg:address":"Waterloose Steenweg 550",
    "sg:city":"Elsene/ixelles",
    "sg:orig_category":"Dameskledingzaken",
    "sg:phone":"+32 2 344 14 25",
    "sg:postcode":"1050",
    "sg:province":"Bruxelles-Capitale",
    "wof:name":"Maison B\u00c9atrice",
    "wof:placetype":"venue"
},
  "geometry": {"coordinates":[4.3614020348,50.8194007874],"type":"Point"}
}