{
  "type": "Feature",
  "properties": {
    "addr:full":"Chauss\u00c9e D'asse 35 Edingen/enghien Hainaut 7850",
    "addr:housenumber":"35",
    "addr:postcode":"7850",
    "addr:street":"Chausse\u0301E D'Asse",
    "iso:country":"BE",
    "sg:address":"Chauss\u00c9e D'asse 35",
    "sg:city":"Edingen/enghien",
    "sg:orig_category":"RESTAURANTS: PRODUITS SURGEL\u00c9S GR",
    "sg:phone":"+32 2 395 95 60",
    "sg:postcode":"7850",
    "sg:province":"Hainaut",
    "wof:name":"De Smet",
    "wof:placetype":"venue"
},
  "geometry": {"coordinates":[4.0455379486,50.698474884],"type":"Point"}
}