{
  "type": "Feature",
  "properties": {
    "addr:full":"Naamsesteenweg 143b304 Sint-truiden Limburg 3800",
    "addr:housenumber":"143b304",
    "addr:postcode":"3800",
    "addr:street":"Naamsesteenweg",
    "iso:country":"BE",
    "sg:address":"Naamsesteenweg 143b304",
    "sg:city":"Sint-truiden",
    "sg:orig_category":"Agences de presse",
    "sg:phone":"+32 11 68 08 80",
    "sg:postcode":"3800",
    "sg:province":"Limburg",
    "wof:name":"Moniek Breesch",
    "wof:placetype":"venue"
},
  "geometry": {"coordinates":[5.1817040443,50.8092651367],"type":"Point"}
}