{
  "type": "Feature",
  "properties": {
    "iso:country":"BE",
    "sg:address":"Rue Du Centre 2",
    "sg:city":"Trois-ponts",
    "sg:orig_category":"Herstelling horloges and juwelen Juwelen and horloges",
    "sg:phone":"+32 80 68 46 34",
    "sg:postcode":"4980",
    "sg:province":"Li\u00e8ge",
    "wof:name":"Maison Franck",
    "wof:placetype":"venue"
},
  "geometry": {"coordinates":[5.8711371422,50.3722419739],"type":"Point"}
}