{
  "type": "Feature",
  "properties": {
    "addr:full":"Broeseinderdijk 145 Neerpelt Limburg 3910",
    "addr:housenumber":"145",
    "addr:postcode":"3910",
    "iso:country":"BE",
    "sg:address":"Broeseinderdijk 145",
    "sg:city":"Neerpelt",
    "sg:orig_category":"Rev\u00eatements pour sols and murs. Peinture",
    "sg:phone":"+32 11 64 03 41",
    "sg:postcode":"3910",
    "sg:province":"Limburg",
    "wof:name":"A.s.r.o.",
    "wof:placetype":"venue"
},
  "geometry": {"coordinates":[5.4246997833,51.2468910217],"type":"Point"}
}