{
  "type": "Feature",
  "properties": {
    "iso:country":"BE",
    "sg:address":"Promenade Du Val D'argent 11",
    "sg:city":"La Hulpe",
    "sg:orig_category":"Immobili\u00ebnkantoren Watersport-, Sport- and Kampeerbenodigdheden Verhuur",
    "sg:phone":"+32 2 351 08 88",
    "sg:postcode":"1310",
    "sg:province":"Brabant Wallon",
    "wof:name":"Alain Henry Vacances C\u00d4te Sud",
    "wof:placetype":"venue"
},
  "geometry": {"coordinates":[4.4410309792,50.7229347229],"type":"Point"}
}