{
  "type": "Feature",
  "properties": {
    "iso:country":"BE",
    "sg:address":"Avenue Brugmann 403",
    "sg:city":"Ukkel/uccle",
    "sg:orig_category":"Avocats and conseillers juridiques",
    "sg:phone":"+32 2 340 82 82",
    "sg:postcode":"1180",
    "sg:province":"Bruxelles-Capitale",
    "wof:name":"Marc Snoeck",
    "wof:placetype":"venue"
},
  "geometry": {"coordinates":[4.3440752029,50.8079032898],"type":"Point"}
}