{
  "type": "Feature",
  "properties": {
    "addr:full":"Appelstraat 20 Sint-truiden Limburg 3800",
    "addr:housenumber":"20",
    "addr:postcode":"3800",
    "addr:street":"Appelstraat",
    "iso:country":"BE",
    "sg:address":"Appelstraat 20",
    "sg:city":"Sint-truiden",
    "sg:orig_category":"Brood, gebak and snoepgoed",
    "sg:phone":"+32 11 69 16 03",
    "sg:postcode":"3800",
    "sg:province":"Limburg",
    "wof:name":"Dirk Janssen",
    "wof:placetype":"venue"
},
  "geometry": {"coordinates":[5.1730089188,50.8118782043],"type":"Point"}
}