{
  "type": "Feature",
  "properties": {
    "iso:country":"BE",
    "sg:address":"Rue De La Cale Seche 30",
    "sg:city":"Haccourt",
    "sg:classifiers":[
        {
            "category":"Building & Trades",
            "subcategory":"Construction",
            "type":"Services"
        }
    ],
    "sg:phone":"+32 4 379 22 52",
    "sg:postcode":"4684",
    "sg:province":"Li\u00e8ge",
    "sg:tags":[
        "cistern"
    ],
    "wof:name":"Scalco Petro Services S.p.r.l.",
    "wof:placetype":"venue"
},
  "geometry": {"coordinates":[5.6685199738,50.7374801636],"type":"Point"}
}