{
  "type": "Feature",
  "properties": {
    "addr:full":"Edingsesteenweg 10 Gooik Vlaams-Brabant 1755",
    "addr:housenumber":"10",
    "addr:postcode":"1755",
    "addr:street":"Edingsesteenweg",
    "iso:country":"BE",
    "sg:address":"Edingsesteenweg 10",
    "sg:city":"Gooik",
    "sg:classifiers":[
        {
            "category":"Professional",
            "subcategory":"Accounting & Tax Preparation",
            "type":"Services"
        }
    ],
    "sg:phone":"+32 2 532 03 05",
    "sg:postcode":"1755",
    "sg:province":"Vlaams-Brabant",
    "sg:tags":[
        "accountant"
    ],
    "wof:name":"De Meyst R",
    "wof:placetype":"venue"
},
  "geometry": {"coordinates":[4.129981041,50.8022155762],"type":"Point"}
}