{
  "type": "Feature",
  "properties": {
    "addr:full":"Winkelomseheide 120 Geel Antwerpen 2440",
    "addr:housenumber":"120",
    "addr:postcode":"2440",
    "addr:street":"Winkelomseheide",
    "iso:country":"BE",
    "sg:address":"Winkelomseheide 120",
    "sg:city":"Geel",
    "sg:orig_category":"Newspapers, magazines, periodicals - Distribution",
    "sg:phone":"+32 14 58 00 50",
    "sg:postcode":"2440",
    "sg:province":"Antwerpen",
    "wof:name":"Lezertje ('t)",
    "wof:placetype":"venue"
},
  "geometry": {"coordinates":[5.0106301308,51.1373100281],"type":"Point"}
}