{
  "type": "Feature",
  "properties": {
    "addr:full":"Avenue De France 197 Marche-en-famenne Luxembourg 6900",
    "addr:housenumber":"197",
    "addr:postcode":"6900",
    "addr:street":"Avenue De France",
    "iso:country":"BE",
    "sg:address":"Avenue De France 197",
    "sg:city":"Marche-en-famenne",
    "sg:classifiers":[
        {
            "category":"Banks & Credit Unions",
            "subcategory":"Investment Brokerage",
            "type":"Services"
        }
    ],
    "sg:phone":"+32 84 31 60 22",
    "sg:postcode":"6900",
    "sg:province":"Luxembourg",
    "sg:tags":[
        "repair",
        "-",
        "installation",
        "sanitary",
        "article"
    ],
    "wof:name":"Liegeois R\u00e9gis",
    "wof:placetype":"venue"
},
  "geometry": {"coordinates":[5.3261699677,50.2084693909],"type":"Point"}
}