{
  "type": "Feature",
  "properties": {
    "iso:country":"BE",
    "sg:address":"Mont 31",
    "sg:city":"Comblain-au-pont",
    "sg:orig_category":"Woningbouw",
    "sg:phone":"+32 4 369 28 40",
    "sg:postcode":"4170",
    "sg:province":"Li\u00e8ge",
    "wof:name":"Rudy Regimont",
    "wof:placetype":"venue"
},
  "geometry": {"coordinates":[5.5595397949,50.48412323],"type":"Point"}
}