{
  "type": "Feature",
  "properties": {
    "addr:full":"H. Consciencelaan 71 Waarschoot Oost-Vlaanderen 9950",
    "addr:housenumber":"71",
    "addr:postcode":"9950",
    "addr:street":"Consciencelaan",
    "iso:country":"BE",
    "sg:address":"H. Consciencelaan 71",
    "sg:city":"Waarschoot",
    "sg:orig_category":"Agences de publicit\u00e9. Articles m\u00e9talliques ouvr\u00e9s divers Fab. Composition and photogravure",
    "sg:phone":"+32 9 377 57 26",
    "sg:postcode":"9950",
    "sg:province":"Oost-Vlaanderen",
    "wof:name":"Pynaert",
    "wof:placetype":"venue"
},
  "geometry": {"coordinates":[3.6021389961,51.1427955627],"type":"Point"}
}