{
  "type": "Feature",
  "properties": {
    "iso:country":"BE",
    "sg:address":"Rue Edouard Remouchamps 23b",
    "sg:city":"Li\u00e8ge 1 (li\u00e8ge 2)",
    "sg:classifiers":[
        {
            "category":"Wholesale",
            "subcategory":"Construction Materials",
            "type":"Manufacturing & Wholesale Goods"
        }
    ],
    "sg:phone":"+32 4 349 97 57",
    "sg:postcode":"4020",
    "sg:province":"Li\u00e8ge",
    "sg:tags":[
        "elevator"
    ],
    "wof:name":"Piklift Sa",
    "wof:placetype":"venue"
},
  "geometry": {"coordinates":[5.5826048851,50.6342964172],"type":"Point"}
}