{
  "type": "Feature",
  "properties": {
    "iso:country":"BE",
    "sg:address":"Jonkersweg 7",
    "sg:city":"Maaseik",
    "sg:classifiers":[
        {
            "category":"Sports & Exercise",
            "subcategory":"Sports Center",
            "type":"Entertainment"
        }
    ],
    "sg:phone":"+32 89 86 86 41",
    "sg:postcode":"3680",
    "sg:province":"Limburg",
    "sg:tags":[
        "terrain",
        "hors",
        "de",
        "installation",
        "sportifs"
    ],
    "wof:name":"Jonkershof",
    "wof:placetype":"venue"
},
  "geometry": {"coordinates":[5.791285038,51.0954208374],"type":"Point"}
}