{
  "type": "Feature",
  "properties": {
    "addr:full":"Rue Du Fraity 16 Bernissart Hainaut 7320",
    "addr:housenumber":"16",
    "addr:postcode":"7320",
    "addr:street":"Rue Du Fraity",
    "iso:country":"BE",
    "sg:address":"Rue Du Fraity 16",
    "sg:city":"Bernissart",
    "sg:classifiers":[
        {
            "category":"Health Services",
            "subcategory":"Doctor",
            "type":"Services"
        }
    ],
    "sg:phone":"+32 69 57 93 24",
    "sg:postcode":"7320",
    "sg:province":"Hainaut",
    "sg:tags":[
        "medicinephysicians",
        "surgeon"
    ],
    "wof:name":"Dejaegher Daniel",
    "wof:placetype":"venue"
},
  "geometry": {"coordinates":[3.6570370197,50.4756546021],"type":"Point"}
}