{
  "type": "Feature",
  "properties": {
    "addr:full":"Weefbergstraat 57 Scherpenheuvel-zichem (averbode) Vlaams-Brabant 3271",
    "addr:housenumber":"57",
    "addr:postcode":"3271",
    "addr:street":"Weefbergstraat",
    "iso:country":"BE",
    "sg:address":"Weefbergstraat 57",
    "sg:city":"Scherpenheuvel-zichem (averbode)",
    "sg:classifiers":[
        {
            "category":"Insurance",
            "subcategory":"Insurance Agent",
            "type":"Services"
        }
    ],
    "sg:phone":"+32 13 77 58 31",
    "sg:postcode":"3271",
    "sg:province":"Vlaams-Brabant",
    "sg:tags":[
        "broker"
    ],
    "wof:name":"Claes P",
    "wof:placetype":"venue"
},
  "geometry": {"coordinates":[4.9869728088,51.0017662048],"type":"Point"}
}