{
  "type": "Feature",
  "properties": {
    "iso:country":"BE",
    "sg:address":"Hoge Bokstraat 167ba",
    "sg:city":"Sint-niklaas",
    "sg:orig_category":"Bouwmaterialen Gh MEUBELONTWERP AND -INSTALLATIE Plaatsen van vloer- and muurbekleding Woningbouw",
    "sg:phone":"+32 3 777 66 16",
    "sg:postcode":"9111",
    "sg:province":"Oost-Vlaanderen",
    "wof:name":"Wabomat",
    "wof:placetype":"venue"
},
  "geometry": {"coordinates":[4.1127071381,51.168056488],"type":"Point"}
}