{
  "type": "Feature",
  "properties": {
    "iso:country":"BE",
    "sg:address":"Volkensvoortstraat 33a",
    "sg:city":"Aarschot (langdorp)",
    "sg:classifiers":[
        {
            "category":"Professional",
            "subcategory":"Accounting & Tax Preparation",
            "type":"Services"
        }
    ],
    "sg:phone":"+32 13 77 27 52",
    "sg:postcode":"3201",
    "sg:province":"Vlaams-Brabant",
    "sg:tags":[
        "accountant"
    ],
    "wof:name":"Van Den Berckt W",
    "wof:placetype":"venue"
},
  "geometry": {"coordinates":[4.9143829346,51.0261802673],"type":"Point"}
}