{
  "type": "Feature",
  "properties": {
    "addr:full":"Hufengasse 39-41 Eupen Li\u00e8ge 4700",
    "addr:postcode":"39-41;4700",
    "addr:street":"Hufengasse",
    "iso:country":"BE",
    "sg:address":"Hufengasse 39-41",
    "sg:city":"Eupen",
    "sg:orig_category":"Fleurs and plantes",
    "sg:phone":"+32 87 74 41 77",
    "sg:postcode":"4700",
    "sg:province":"Li\u00e8ge",
    "wof:name":"Lowenzahn",
    "wof:placetype":"venue"
},
  "geometry": {"coordinates":[6.0292282104,50.6292724609],"type":"Point"}
}