{
  "type": "Feature",
  "properties": {
    "iso:country":"BE",
    "sg:address":"Kastanjestraat 26",
    "sg:city":"Vorst/forest",
    "sg:orig_category":"Artsen and specialisten",
    "sg:phone":"+32 2 344 86 54",
    "sg:postcode":"1190",
    "sg:province":"Bruxelles-Capitale",
    "wof:name":"Fran\u00c7ois Elens",
    "wof:placetype":"venue"
},
  "geometry": {"coordinates":[4.3269929886,50.8175430298],"type":"Point"}
}