{
  "type": "Feature",
  "properties": {
    "addr:full":"Rue D'irlande 50 Bruxelles (saint-gilles) Bruxelles-Capitale 1060",
    "addr:housenumber":"50",
    "addr:postcode":"1060",
    "addr:street":"Rue D'Irlande",
    "iso:country":"BE",
    "sg:address":"Rue D'irlande 50",
    "sg:city":"Bruxelles (saint-gilles)",
    "sg:classifiers":[
        {
            "category":"Professional",
            "subcategory":"Art Services",
            "type":"Services"
        }
    ],
    "sg:phone":"+32 2 538 33 77",
    "sg:postcode":"1060",
    "sg:province":"Bruxelles-Capitale",
    "sg:tags":[
        "children's",
        "animation"
    ],
    "wof:name":"Lecot A",
    "wof:placetype":"venue"
},
  "geometry": {"coordinates":[4.3517231941,50.8263130188],"type":"Point"}
}