{
  "type": "Feature",
  "properties": {
    "addr:full":"Karreweg 88 Kruishoutem Oost-Vlaanderen 9770",
    "addr:housenumber":"88",
    "addr:postcode":"9770",
    "addr:street":"Karreweg",
    "iso:country":"BE",
    "sg:address":"Karreweg 88",
    "sg:city":"Kruishoutem",
    "sg:orig_category":"Eleveurs and marchands de porcs",
    "sg:phone":"+32 9 388 89 55",
    "sg:postcode":"9770",
    "sg:province":"Oost-Vlaanderen",
    "wof:name":"Marc De Visschere",
    "wof:placetype":"venue"
},
  "geometry": {"coordinates":[3.5095551014,50.9339637756],"type":"Point"}
}