{
  "type": "Feature",
  "properties": {
    "iso:country":"BE",
    "sg:address":"Langevelde 28",
    "sg:city":"Zele",
    "sg:orig_category":"Rev\u00eatements pour sols and murs. Peinture",
    "sg:phone":"+32 52 45 12 16",
    "sg:postcode":"9240",
    "sg:province":"Oost-Vlaanderen",
    "wof:name":"Geert Thienpondt",
    "wof:placetype":"venue"
},
  "geometry": {"coordinates":[4.05940485,51.0738220215],"type":"Point"}
}