{
  "type": "Feature",
  "properties": {
    "addr:full":"Chauss\u00e9e De Namur 63 Wavre Brabant Wallon 1300",
    "addr:housenumber":"63;1300",
    "addr:street":"Chausse\u0301E De Namur",
    "iso:country":"BE",
    "sg:address":"Chauss\u00e9e De Namur 63",
    "sg:city":"Wavre",
    "sg:classifiers":[
        {
            "category":"Health Services",
            "subcategory":"Nursing And Care Facility",
            "type":"Services"
        }
    ],
    "sg:phone":"+32 10 22 60 66",
    "sg:postcode":"1300",
    "sg:province":"Brabant Wallon",
    "sg:tags":[
        "home",
        "rest"
    ],
    "wof:name":"R\u00e9sidence Des Mays",
    "wof:placetype":"venue"
},
  "geometry": {"coordinates":[4.6156730652,50.7054634094],"type":"Point"}
}