{
  "type": "Feature",
  "properties": {
    "addr:full":"Maalse Steenweg 149 Brugge (sint-kruis) West-Vlaanderen 8310",
    "addr:housenumber":"149",
    "addr:postcode":"8310",
    "addr:street":"Maalse Steenweg",
    "iso:country":"BE",
    "sg:address":"Maalse Steenweg 149",
    "sg:city":"Brugge (sint-kruis)",
    "sg:classifiers":[
        {
            "category":"Communications",
            "subcategory":"Film & Video Production",
            "type":"Services"
        }
    ],
    "sg:phone":"+32 50 79 27 07",
    "sg:postcode":"8310",
    "sg:province":"West-Vlaanderen",
    "sg:tags":[
        "multimedia",
        "-",
        "system"
    ],
    "wof:name":"Videowest Producties",
    "wof:placetype":"venue"
},
  "geometry": {"coordinates":[3.2497971058,51.2098655701],"type":"Point"}
}