{
  "type": "Feature",
  "properties": {
    "addr:full":"Aardappelstraat 2 Beernem West-Vlaanderen 8730",
    "addr:housenumber":"2",
    "addr:postcode":"8730",
    "addr:street":"Aardappelstraat",
    "iso:country":"BE",
    "sg:address":"Aardappelstraat 2",
    "sg:city":"Beernem",
    "sg:orig_category":"Gespecialiseerde residenti\u00eble bouw",
    "sg:phone":"+32 50 78 11 75",
    "sg:postcode":"8730",
    "sg:province":"West-Vlaanderen",
    "wof:name":"Patrick Corvelyn",
    "wof:placetype":"venue"
},
  "geometry": {"coordinates":[3.3401219845,51.1344032288],"type":"Point"}
}