{
  "type": "Feature",
  "properties": {
    "addr:full":"Industriepark Noord 25 Sint-niklaas Oost-Vlaanderen 9100",
    "addr:housenumber":"25",
    "addr:postcode":"9100",
    "addr:street":"Industriepark Noord",
    "iso:country":"BE",
    "sg:address":"Industriepark Noord 25",
    "sg:city":"Sint-niklaas",
    "sg:orig_category":"Non-Classified Establishments",
    "sg:phone":"+32 3 778 05 69",
    "sg:postcode":"9100",
    "sg:province":"Oost-Vlaanderen",
    "wof:name":"Wymeersch Breigoederen Nv",
    "wof:placetype":"venue"
},
  "geometry": {"coordinates":[4.1679039001,51.1473617554],"type":"Point"}
}