{
  "type": "Feature",
  "properties": {
    "addr:full":"Bevrijdingslaan 8-10 Tielt Oost-Vlaanderen 9800",
    "addr:housenumber":"8-10",
    "addr:postcode":"9800",
    "addr:street":"Bevrijdingslaan",
    "iso:country":"BE",
    "sg:address":"Bevrijdingslaan 8-10",
    "sg:city":"Tielt",
    "sg:orig_category":"Transports routiers de marchandises",
    "sg:phone":"+32 51 40 30 11",
    "sg:postcode":"9800",
    "sg:province":"Oost-Vlaanderen",
    "wof:name":"Dematra",
    "wof:placetype":"venue"
},
  "geometry": {"coordinates":[3.3525359631,50.9997901917],"type":"Point"}
}