{
  "type": "Feature",
  "properties": {
    "addr:full":"Rue Des Serpolets 18 Tournai Hainaut 7522",
    "addr:housenumber":"18",
    "addr:postcode":"7522",
    "addr:street":"Rue Des Serpolets",
    "iso:country":"BE",
    "sg:address":"Rue Des Serpolets 18",
    "sg:city":"Tournai",
    "sg:orig_category":"Installatie van houten of kunststof schrijnwerk",
    "sg:phone":"+32 69 21 51 21",
    "sg:postcode":"7522",
    "sg:province":"Hainaut",
    "wof:name":"Mondial Chassis",
    "wof:placetype":"venue"
},
  "geometry": {"coordinates":[3.3302209377,50.6105003357],"type":"Point"}
}