{
  "type": "Feature",
  "properties": {
    "addr:full":"Rue Des Bl\u00c9s 2 Waremme Li\u00e8ge 4300",
    "addr:housenumber":"2",
    "addr:postcode":"4300",
    "addr:street":"Rue Des Ble\u0301S",
    "iso:country":"BE",
    "sg:address":"Rue Des Bl\u00c9s 2",
    "sg:city":"Waremme",
    "sg:orig_category":"Artiesten and kunstenaars",
    "sg:phone":"+32 19 32 37 64",
    "sg:postcode":"4300",
    "sg:province":"Li\u00e8ge",
    "wof:name":"Ketelslegers",
    "wof:placetype":"venue"
},
  "geometry": {"coordinates":[5.2648191452,50.6964263916],"type":"Point"}
}