{
  "type": "Feature",
  "properties": {
    "iso:country":"BE",
    "sg:address":"Ossenwegstraat 74",
    "sg:city":"Zoutleeuw",
    "sg:classifiers":[
        {
            "category":"Professional",
            "subcategory":"Computer Services",
            "type":"Services"
        }
    ],
    "sg:phone":"+32 11 78 06 82",
    "sg:postcode":"3440",
    "sg:province":"Vlaams-Brabant",
    "sg:tags":[
        "-",
        "processing",
        "data"
    ],
    "wof:name":"D.v.s.",
    "wof:placetype":"venue"
},
  "geometry": {"coordinates":[5.1326317787,50.8470077515],"type":"Point"}
}