{
  "type": "Feature",
  "properties": {
    "addr:full":"Rijksweg 111 Harelbeke West-Vlaanderen 8531",
    "addr:housenumber":"111",
    "addr:postcode":"8531",
    "addr:street":"Rijksweg",
    "iso:country":"BE",
    "sg:address":"Rijksweg 111",
    "sg:city":"Harelbeke",
    "sg:orig_category":"Herstellingen and onderhoud van auto's",
    "sg:phone":"+32 56 71 40 23",
    "sg:postcode":"8531",
    "sg:province":"West-Vlaanderen",
    "wof:name":"Garage Vandekerckhove",
    "wof:placetype":"venue"
},
  "geometry": {"coordinates":[3.2879440784,50.8655204773],"type":"Point"}
}