{
  "type": "Feature",
  "properties": {
    "addr:full":"Burgemeester Lemmensstraat 13 Hamme (moerzeke) Oost-Vlaanderen 9220",
    "addr:housenumber":"13",
    "addr:postcode":"9220",
    "addr:street":"Burgemeester Lemmensstraat",
    "iso:country":"BE",
    "sg:address":"Burgemeester Lemmensstraat 13",
    "sg:city":"Hamme (moerzeke)",
    "sg:classifiers":[
        {
            "category":"Health Services",
            "subcategory":"Dentist",
            "type":"Services"
        }
    ],
    "sg:phone":"+32 52 47 60 61",
    "sg:postcode":"9220",
    "sg:province":"Oost-Vlaanderen",
    "wof:name":"Standaert Yannick",
    "wof:placetype":"venue"
},
  "geometry": {"coordinates":[4.1537079811,51.0640983582],"type":"Point"}
}