{
  "type": "Feature",
  "properties": {
    "iso:country":"BE",
    "sg:address":"Biesvijverstraat 6",
    "sg:city":"Oudenaarde",
    "sg:orig_category":"Eleveurs de bovins. Eleveurs and marchands de porcs",
    "sg:phone":"+32 55 31 12 45",
    "sg:postcode":"9700",
    "sg:province":"Oost-Vlaanderen",
    "wof:name":"Noel Lamon",
    "wof:placetype":"venue"
},
  "geometry": {"coordinates":[3.5734479427,50.8599243164],"type":"Point"}
}