{
  "type": "Feature",
  "properties": {
    "iso:country":"BE",
    "sg:address":"Route D\u00b4anderlues 197a",
    "sg:city":"Lobbes",
    "sg:orig_category":"Installation de menuiserie en bois and plastique",
    "sg:phone":"+32 71 52 84 58",
    "sg:postcode":"6540",
    "sg:province":"Hainaut",
    "wof:name":"Modern - Space Scr\u00c8ve",
    "wof:placetype":"venue"
},
  "geometry": {"coordinates":[4.2787070274,50.3828468323],"type":"Point"}
}