{
  "type": "Feature",
  "properties": {
    "iso:country":"BE",
    "sg:address":"Rue Du Pot-d\u00b4or 31",
    "sg:city":"Li\u00c8ge",
    "sg:orig_category":"Chaussures",
    "sg:phone":"+32 4 222 14 18",
    "sg:postcode":"4000",
    "sg:province":"Li\u00e8ge",
    "wof:name":"Zaza Chausse",
    "wof:placetype":"venue"
},
  "geometry": {"coordinates":[5.569683075,50.6414985657],"type":"Point"}
}