{
  "type": "Feature",
  "properties": {
    "addr:full":"Brugsesteenweg 192 Pittem West-Vlaanderen 8740",
    "addr:housenumber":"192",
    "addr:postcode":"8740",
    "addr:street":"Brugsesteenweg",
    "iso:country":"BE",
    "sg:address":"Brugsesteenweg 192",
    "sg:city":"Pittem",
    "sg:orig_category":"V\u00eatements",
    "sg:phone":"+32 51 46 64 73",
    "sg:postcode":"8740",
    "sg:province":"West-Vlaanderen",
    "wof:name":"Damtex",
    "wof:placetype":"venue"
},
  "geometry": {"coordinates":[3.2359199524,51.004699707],"type":"Point"}
}