{
  "type": "Feature",
  "properties": {
    "iso:country":"BE",
    "sg:address":"Lange Leemstraat 105",
    "sg:city":"Antwerpen",
    "sg:orig_category":"Kapsalons",
    "sg:phone":"+32 3 213 36 33",
    "sg:postcode":"2018",
    "sg:province":"Antwerpen",
    "wof:name":"Coiffure Lea",
    "wof:placetype":"venue"
},
  "geometry": {"coordinates":[4.4130129814,51.2081069946],"type":"Point"}
}