{
  "type": "Feature",
  "properties": {
    "addr:full":"Rue Petit Pige 17 Charleroi Hainaut 6000",
    "addr:housenumber":"17",
    "addr:postcode":"6000",
    "addr:street":"Rue Petit Pige;Hainaut",
    "iso:country":"BE",
    "sg:address":"Rue Petit Pige 17",
    "sg:city":"Charleroi",
    "sg:orig_category":"Installation \u00e9lectrique r\u00e9sidentielle",
    "sg:phone":"+32 71 42 19 74",
    "sg:postcode":"6000",
    "sg:province":"Hainaut",
    "wof:name":"Jean-yves Gany",
    "wof:placetype":"venue"
},
  "geometry": {"coordinates":[4.4537057877,50.4218177795],"type":"Point"}
}