{
  "type": "Feature",
  "properties": {
    "addr:full":"Jan De Paduwaplaats 19 Evere/evere Bruxelles-Capitale 1140",
    "addr:housenumber":"19",
    "addr:postcode":"1140",
    "addr:street":"Jan De Paduwaplaats",
    "iso:country":"BE",
    "sg:address":"Jan De Paduwaplaats 19",
    "sg:city":"Evere/evere",
    "sg:orig_category":"Herstelling leer and schoeisel",
    "sg:phone":"+32 2 726 91 41",
    "sg:postcode":"1140",
    "sg:province":"Bruxelles-Capitale",
    "wof:name":"Schoenmakerij Lambert",
    "wof:placetype":"venue"
},
  "geometry": {"coordinates":[4.4149699211,50.8589782715],"type":"Point"}
}