{
  "type": "Feature",
  "properties": {
    "iso:country":"BE",
    "sg:address":"Nieder Emmels 44",
    "sg:city":"Sankt Vith (crombach)",
    "sg:classifiers":[
        {
            "category":"Farming",
            "subcategory":"Livestock Farm",
            "type":"Manufacturing & Wholesale Goods"
        }
    ],
    "sg:phone":"+32 80 22 83 41",
    "sg:postcode":"4784",
    "sg:province":"Li\u00e8ge",
    "sg:tags":[
        "buyer"
    ],
    "wof:name":"Niessen J & Sohn",
    "wof:placetype":"venue"
},
  "geometry": {"coordinates":[6.1054711342,50.3023414612],"type":"Point"}
}