{
  "type": "Feature",
  "properties": {
    "iso:country":"BE",
    "sg:address":"Marktplein 8",
    "sg:city":"Wijnegem",
    "sg:classifiers":[
        {
            "category":"Bars & Pubs",
            "type":"Food & Drink"
        }
    ],
    "sg:phone":"+32 3 353 89 26",
    "sg:postcode":"2110",
    "sg:province":"Antwerpen",
    "sg:tags":[
        "tavern"
    ],
    "wof:name":"Vleminckhof",
    "wof:placetype":"venue"
},
  "geometry": {"coordinates":[4.52312994,51.2271614075],"type":"Point"}
}