{
  "type": "Feature",
  "properties": {
    "iso:country":"BE",
    "sg:address":"Natterveld 19",
    "sg:city":"Kinrooi",
    "sg:orig_category":"Traitements param\u00e9dicaux",
    "sg:phone":"+32 89 70 21 25",
    "sg:postcode":"3640",
    "sg:province":"Limburg",
    "wof:name":"Thuisverpleging Vera",
    "wof:placetype":"venue"
},
  "geometry": {"coordinates":[5.742620945,51.1413269043],"type":"Point"}
}