{
  "type": "Feature",
  "properties": {
    "addr:full":"Rue Gustave Defnet 84 Soumagne Li\u00e8ge 4630",
    "addr:housenumber":"84",
    "addr:postcode":"4630",
    "addr:street":"Rue Gustave Defnet",
    "iso:country":"BE",
    "sg:address":"Rue Gustave Defnet 84",
    "sg:city":"Soumagne",
    "sg:orig_category":"Beautyfarms, relaxatie and lichamelijk welzijn Schoonheidssalons",
    "sg:phone":"+32 4 377 57 76",
    "sg:postcode":"4630",
    "sg:province":"Li\u00e8ge",
    "wof:name":"Fabienne Thirion",
    "wof:placetype":"venue"
},
  "geometry": {"coordinates":[5.7519750595,50.6288986206],"type":"Point"}
}