{
  "type": "Feature",
  "properties": {
    "addr:full":"Houthalenseweg 109 Zonhoven Limburg 3520",
    "addr:housenumber":"109",
    "addr:postcode":"3520",
    "addr:street":"Zonhoven Limburg",
    "iso:country":"BE",
    "sg:address":"Houthalenseweg 109",
    "sg:city":"Zonhoven",
    "sg:classifiers":[
        {
            "category":"Health Services",
            "subcategory":"Health Practitioner",
            "type":"Services"
        }
    ],
    "sg:phone":"+32 11 81 35 25",
    "sg:postcode":"3520",
    "sg:province":"Limburg",
    "sg:tags":[
        "physiotherapist"
    ],
    "wof:name":"Melotte I",
    "wof:placetype":"venue"
},
  "geometry": {"coordinates":[5.3713607788,51.0037269592],"type":"Point"}
}