{
  "type": "Feature",
  "properties": {
    "addr:full":"Stationsstraat 1 Wevelgem West-Vlaanderen 8560",
    "addr:housenumber":"1",
    "addr:postcode":"8560",
    "addr:street":"Stationsstraat",
    "iso:country":"BE",
    "sg:address":"Stationsstraat 1",
    "sg:city":"Wevelgem",
    "sg:orig_category":"Transports ferroviaires",
    "sg:phone":"+32 56 26 34 25",
    "sg:postcode":"8560",
    "sg:province":"West-Vlaanderen",
    "wof:name":"Station Wevelgem",
    "wof:placetype":"venue"
},
  "geometry": {"coordinates":[3.1817269325,50.8106231689],"type":"Point"}
}