{
  "type": "Feature",
  "properties": {
    "iso:country":"BE",
    "sg:address":"Meerbeekstraat 113",
    "sg:city":"Brakel (nederbrakel)",
    "sg:classifiers":[
        {
            "category":"Bars & Pubs",
            "type":"Food & Drink"
        }
    ],
    "sg:phone":"+32 55 42 34 77",
    "sg:postcode":"9660",
    "sg:province":"Oost-Vlaanderen",
    "wof:name":"Viville G",
    "wof:placetype":"venue"
},
  "geometry": {"coordinates":[3.7531490326,50.8046455383],"type":"Point"}
}