{
  "type": "Feature",
  "properties": {
    "addr:full":"Duivekotestraat 13 Kortrijk (bissegem) West-Vlaanderen 8501",
    "addr:housenumber":"13",
    "addr:postcode":"8501",
    "addr:street":"Duivekotestraat",
    "iso:country":"BE",
    "sg:address":"Duivekotestraat 13",
    "sg:city":"Kortrijk (bissegem)",
    "sg:classifiers":[
        {
            "category":"Communications",
            "subcategory":"Television Station",
            "type":"Services"
        }
    ],
    "sg:phone":"+32 56 35 83 45",
    "sg:postcode":"8501",
    "sg:province":"West-Vlaanderen",
    "sg:tags":[
        "report",
        "video"
    ],
    "wof:name":"H.v.c.-video",
    "wof:placetype":"venue"
},
  "geometry": {"coordinates":[3.2268140316,50.8275604248],"type":"Point"}
}