{
  "type": "Feature",
  "properties": {
    "iso:country":"BE",
    "sg:address":"Avenue Gouverneur Bovesse 66",
    "sg:city":"Namur",
    "sg:orig_category":"V\u00e9hicules automobiles. Entretien and r\u00e9parations de voitures",
    "sg:phone":"+32 81 30 56 30",
    "sg:postcode":"5100",
    "sg:province":"Namur",
    "wof:name":"Garage Namuretoile",
    "wof:placetype":"venue"
},
  "geometry": {"coordinates":[4.8713750839,50.4566345215],"type":"Point"}
}