{
  "type": "Feature",
  "properties": {
    "addr:full":"Le Ban D'alle 4 Bouillon Luxembourg 6838",
    "addr:housenumber":"4",
    "addr:postcode":"6838",
    "addr:street":"D'Alle",
    "iso:country":"BE",
    "sg:address":"Le Ban D'alle 4",
    "sg:city":"Bouillon",
    "sg:orig_category":"Maisons de vacances",
    "sg:phone":"+32 61 46 77 57",
    "sg:postcode":"6838",
    "sg:province":"Luxembourg",
    "wof:name":"J.-m; Pierrot",
    "wof:placetype":"venue"
},
  "geometry": {"coordinates":[5.0093798637,49.7943191528],"type":"Point"}
}