{
  "type": "Feature",
  "properties": {
    "addr:full":"Hollandshof 3 Hamme Oost-Vlaanderen 9220",
    "addr:housenumber":"3",
    "addr:postcode":"9220",
    "addr:street":"Hollandshof",
    "iso:country":"BE",
    "sg:address":"Hollandshof 3",
    "sg:city":"Hamme",
    "sg:orig_category":"Pleisterwerk",
    "sg:phone":"+32 52 47 19 98",
    "sg:postcode":"9220",
    "sg:province":"Oost-Vlaanderen",
    "wof:name":"Jan Weyn",
    "wof:placetype":"venue"
},
  "geometry": {"coordinates":[4.0757188797,51.093536377],"type":"Point"}
}