{
  "type": "Feature",
  "properties": {
    "addr:full":"Rue De Florival 44b5 Grez-doiceau Brabant Wallon 1390",
    "addr:housenumber":"44b5",
    "addr:postcode":"1390",
    "addr:street":"Rue De Florival",
    "iso:country":"BE",
    "sg:address":"Rue De Florival 44b5",
    "sg:city":"Grez-doiceau",
    "sg:orig_category":"D\u00e9corateurs d'int\u00e9rieur",
    "sg:phone":"+32 10 84 55 12",
    "sg:postcode":"1390",
    "sg:province":"Brabant Wallon",
    "wof:name":"Grafico Spazi Architet.",
    "wof:placetype":"venue"
},
  "geometry": {"coordinates":[4.6663498878,50.7536773682],"type":"Point"}
}