{
  "type": "Feature",
  "properties": {
    "iso:country":"BE",
    "sg:address":"Antwerpsesteenweg 395",
    "sg:city":"Malle (westmalle)",
    "sg:classifiers":[
        {
            "category":"Health Services",
            "subcategory":"Health Practitioner",
            "type":"Services"
        }
    ],
    "sg:phone":"+32 3 311 66 96",
    "sg:postcode":"2390",
    "sg:province":"Antwerpen",
    "sg:tags":[
        "physiotherapist"
    ],
    "wof:name":"Ceusters Pierre",
    "wof:placetype":"venue"
},
  "geometry": {"coordinates":[4.679956913,51.2936210632],"type":"Point"}
}