{
  "type": "Feature",
  "properties": {
    "iso:country":"BE",
    "sg:address":"Oudstrijdersplaats 18",
    "sg:city":"Ninove",
    "sg:orig_category":"Artiesten and kunstenaars",
    "sg:phone":"+32 54 33 34 32",
    "sg:postcode":"9400",
    "sg:province":"Oost-Vlaanderen",
    "wof:name":"Agnes Walravens",
    "wof:placetype":"venue"
},
  "geometry": {"coordinates":[4.022810936,50.8352165222],"type":"Point"}
}