{
  "type": "Feature",
  "properties": {
    "iso:country":"BE",
    "sg:address":"Rue Champ Du Venerable 21",
    "sg:city":"Villers-la-ville",
    "sg:orig_category":"Producteurs de l\u00e9gumes",
    "sg:phone":"+32 71 87 53 15",
    "sg:postcode":"1495",
    "sg:province":"Brabant Wallon",
    "wof:name":"Daniel Lemoine",
    "wof:placetype":"venue"
},
  "geometry": {"coordinates":[4.5711708069,50.5859985352],"type":"Point"}
}