{
  "type": "Feature",
  "properties": {
    "iso:country":"BE",
    "sg:address":"Herckenrodestraat 51",
    "sg:city":"Heusden-zolder (zolder)",
    "sg:orig_category":"Cigarette Papers And Filtered Cigarette Tubes",
    "sg:phone":"+32 3 821 09 00",
    "sg:postcode":"3550",
    "sg:province":"Limburg",
    "wof:name":"Rizla Belgium Nv",
    "wof:placetype":"venue"
},
  "geometry": {"coordinates":[4.4059038162,51.1714172363],"type":"Point"}
}