{
  "type": "Feature",
  "properties": {
    "iso:country":"BE",
    "sg:address":"Driebeekstraat 22",
    "sg:city":"Gent",
    "sg:orig_category":"Sportcentra",
    "sg:phone":"+32 9 230 30 02",
    "sg:postcode":"9050",
    "sg:province":"Oost-Vlaanderen",
    "wof:name":"Sporthal Driebeek",
    "wof:placetype":"venue"
},
  "geometry": {"coordinates":[3.7686080933,51.0380554199],"type":"Point"}
}