{
  "type": "Feature",
  "properties": {
    "addr:full":"Korte Dijkstraat 25 Dendermonde Oost-Vlaanderen 9200",
    "addr:housenumber":"25",
    "addr:postcode":"9200",
    "addr:street":"Korte Dijkstraat;Oost-Vlaanderen",
    "iso:country":"BE",
    "sg:address":"Korte Dijkstraat 25",
    "sg:city":"Dendermonde",
    "sg:classifiers":[
        {
            "category":"Professional",
            "subcategory":"Testing Lab",
            "type":"Services"
        }
    ],
    "sg:phone":"+32 52 22 09 80",
    "sg:postcode":"9200",
    "sg:province":"Oost-Vlaanderen",
    "sg:tags":[
        "chemist"
    ],
    "wof:name":"De Loose I",
    "wof:placetype":"venue"
},
  "geometry": {"coordinates":[4.1017098427,51.0306930542],"type":"Point"}
}