{
  "type": "Feature",
  "properties": {
    "iso:country":"BE",
    "sg:address":"Aalstersestraat 75",
    "sg:city":"Lebbeke",
    "sg:orig_category":"Messageries",
    "sg:phone":"+32 53 70 86 93",
    "sg:postcode":"9280",
    "sg:province":"Oost-Vlaanderen",
    "wof:name":"Van Den Spiegel Ilse",
    "wof:placetype":"venue"
},
  "geometry": {"coordinates":[4.1099300385,50.987159729],"type":"Point"}
}