{
  "type": "Feature",
  "properties": {
    "iso:country":"BE",
    "sg:address":"Weldoenerslaan 10",
    "sg:city":"Maasmechelen",
    "sg:classifiers":[
        {
            "category":"Personal",
            "subcategory":"Beauty Salon",
            "type":"Services"
        }
    ],
    "sg:phone":"+32 89 76 17 20",
    "sg:postcode":"3630",
    "sg:province":"Limburg",
    "sg:tags":[
        "lady",
        "-",
        "hairdressing"
    ],
    "wof:name":"Vision Hair",
    "wof:placetype":"venue"
},
  "geometry": {"coordinates":[5.672478199,50.9771232605],"type":"Point"}
}