{
  "type": "Feature",
  "properties": {
    "addr:full":"Guldensporenstraat 8 Wevelgem West-Vlaanderen 8560",
    "addr:housenumber":"8",
    "addr:postcode":"8560",
    "addr:street":"Guldensporenstraat",
    "iso:country":"BE",
    "sg:address":"Guldensporenstraat 8",
    "sg:city":"Wevelgem",
    "sg:orig_category":"Kapsalons",
    "sg:phone":"+32 56 41 33 25",
    "sg:postcode":"8560",
    "sg:province":"West-Vlaanderen",
    "wof:name":"Coiffure Viviane",
    "wof:placetype":"venue"
},
  "geometry": {"coordinates":[3.1979351044,50.8125572205],"type":"Point"}
}