{
  "type": "Feature",
  "properties": {
    "addr:full":"Bretheistraat 148 Genk Limburg 3600",
    "addr:housenumber":"148",
    "addr:postcode":"3600",
    "addr:street":"Bretheistraat",
    "iso:country":"BE",
    "sg:address":"Bretheistraat 148",
    "sg:city":"Genk",
    "sg:classifiers":[
        {
            "category":"Health Services",
            "subcategory":"Doctor",
            "type":"Services"
        }
    ],
    "sg:phone":"+32 89 35 85 48",
    "sg:postcode":"3600",
    "sg:province":"Limburg",
    "sg:tags":[
        "medicinephysicians",
        "surgeon"
    ],
    "wof:name":"De Coninck Claire",
    "wof:placetype":"venue"
},
  "geometry": {"coordinates":[5.5158309937,50.9687652588],"type":"Point"}
}