{
  "type": "Feature",
  "properties": {
    "iso:country":"BE",
    "sg:address":"Kerkskendorp 26",
    "sg:city":"Haaltert",
    "sg:classifiers":[
        {
            "category":"Cafe",
            "type":"Food & Drink"
        }
    ],
    "sg:phone":"+32 53 83 68 37",
    "sg:postcode":"9451",
    "sg:province":"Oost-Vlaanderen",
    "sg:tags":[
        "caf\u00e9s"
    ],
    "wof:name":"Jenny Grootaers",
    "wof:placetype":"venue"
},
  "geometry": {"coordinates":[3.9882929325,50.8890571594],"type":"Point"}
}