{
  "type": "Feature",
  "properties": {
    "addr:full":"Riemsterweg 303 Bilzen Limburg 3740",
    "addr:housenumber":"303",
    "addr:postcode":"3740",
    "iso:country":"BE",
    "sg:address":"Riemsterweg 303",
    "sg:city":"Bilzen",
    "sg:orig_category":"Transports terrestres de voyageurs",
    "sg:phone":"+32 89 41 53 91",
    "sg:postcode":"3740",
    "sg:province":"Limburg",
    "wof:name":"De Morgenstond",
    "wof:placetype":"venue"
},
  "geometry": {"coordinates":[5.5292901993,50.8601989746],"type":"Point"}
}