{
  "type": "Feature",
  "properties": {
    "iso:country":"BE",
    "sg:address":"Rue De La Charite 6a",
    "sg:city":"Sint-joost-ten-node/saint-joss",
    "sg:orig_category":"Emballages en plastique Fab",
    "sg:phone":"+32 2 219 33 42",
    "sg:postcode":"1210",
    "sg:province":"Bruxelles-Capitale",
    "wof:name":"Incoplas",
    "wof:placetype":"venue"
},
  "geometry": {"coordinates":[4.3700170517,50.8488998413],"type":"Point"}
}