{
  "type": "Feature",
  "properties": {
    "addr:full":"Keiberg 18 Oosterzele Oost-Vlaanderen 9860",
    "addr:housenumber":"18",
    "addr:postcode":"9860",
    "addr:street":"Keiberg;Oost-Vlaanderen",
    "iso:country":"BE",
    "sg:address":"Keiberg 18",
    "sg:city":"Oosterzele",
    "sg:orig_category":"Studios photographiques",
    "sg:phone":"+32 9 362 76 53",
    "sg:postcode":"9860",
    "sg:province":"Oost-Vlaanderen",
    "wof:name":"Ronny Monsecour",
    "wof:placetype":"venue"
},
  "geometry": {"coordinates":[3.8097779751,50.9454574585],"type":"Point"}
}