{
  "type": "Feature",
  "properties": {
    "addr:full":"Rue Du Bourgmestre Henri Francotte 2 Dalhem Li\u00e8ge 4607",
    "addr:housenumber":"2",
    "addr:postcode":"4607",
    "addr:street":"Rue Du Bourgmestre Henri Francotte",
    "iso:country":"BE",
    "sg:address":"Rue Du Bourgmestre Henri Francotte 2",
    "sg:city":"Dalhem",
    "sg:classifiers":[
        {
            "category":"Fast Food",
            "type":"Food & Drink"
        }
    ],
    "sg:phone":"+32 4 374 02 41",
    "sg:postcode":"4607",
    "sg:province":"Li\u00e8ge",
    "sg:tags":[
        "fried",
        "stand",
        "potato"
    ],
    "wof:name":"Au Pied De Wichet",
    "wof:placetype":"venue"
},
  "geometry": {"coordinates":[5.7229170799,50.7136001587],"type":"Point"}
}