{
  "type": "Feature",
  "properties": {
    "addr:full":"Rue Des Ch\u00eanays 120a Wellin (chanly) Luxembourg 6921",
    "addr:housenumber":"120a",
    "addr:postcode":"6921",
    "addr:street":"Rue Des Che\u0302Nays",
    "iso:country":"BE",
    "sg:address":"Rue Des Ch\u00eanays 120a",
    "sg:city":"Wellin (chanly)",
    "sg:classifiers":[
        {
            "category":"Social Services",
            "subcategory":"Child Care",
            "type":"Services"
        }
    ],
    "sg:phone":"+32 84 38 85 21",
    "sg:postcode":"6921",
    "sg:province":"Luxembourg",
    "sg:tags":[
        "home"
    ],
    "wof:name":"Fermette (la)deprez-daisne Asbl",
    "wof:placetype":"venue"
},
  "geometry": {"coordinates":[5.154583931,50.0783538818],"type":"Point"}
}