{
  "type": "Feature",
  "properties": {
    "addr:full":"Rue Catherine Andr\u00c9 15 Malmedy Li\u00e8ge 4960",
    "addr:housenumber":"15",
    "addr:postcode":"4960",
    "addr:street":"Rue Catherine Andre\u0301",
    "iso:country":"BE",
    "sg:address":"Rue Catherine Andr\u00c9 15",
    "sg:city":"Malmedy",
    "sg:orig_category":"Architectes",
    "sg:phone":"+32 80 33 03 25",
    "sg:postcode":"4960",
    "sg:province":"Li\u00e8ge",
    "wof:name":"Delphine Heinen",
    "wof:placetype":"venue"
},
  "geometry": {"coordinates":[6.0256948471,50.424911499],"type":"Point"}
}