{
  "type": "Feature",
  "properties": {
    "addr:full":"Nieuwe Baan 84 Kruibeke (bazel) Oost-Vlaanderen 9150",
    "addr:housenumber":"84",
    "addr:postcode":"9150",
    "addr:street":"Nieuwe Baan",
    "iso:country":"BE",
    "sg:address":"Nieuwe Baan 84",
    "sg:city":"Kruibeke (bazel)",
    "sg:classifiers":[
        {
            "category":"Freight",
            "type":"Transportation"
        }
    ],
    "sg:phone":"+32 3 774 57 61",
    "sg:postcode":"9150",
    "sg:province":"Oost-Vlaanderen",
    "sg:tags":[
        "-",
        "transport"
    ],
    "wof:name":"Antwerp Trucking Corporation",
    "wof:placetype":"venue"
},
  "geometry": {"coordinates":[4.2830338478,51.135559082],"type":"Point"}
}