{
  "type": "Feature",
  "properties": {
    "addr:full":"Mannenberg 169 Scherpenheuvel-zichem Vlaams-Brabant 3270",
    "addr:housenumber":"169",
    "addr:postcode":"3270",
    "addr:street":"Mannenberg",
    "iso:country":"BE",
    "sg:address":"Mannenberg 169",
    "sg:city":"Scherpenheuvel-zichem",
    "sg:orig_category":"MEUBELONTWERP AND -INSTALLATIE",
    "sg:phone":"+32 13 77 44 07",
    "sg:postcode":"3270",
    "sg:province":"Vlaams-Brabant",
    "wof:name":"Practi Comfort",
    "wof:placetype":"venue"
},
  "geometry": {"coordinates":[4.9370942116,50.9775733948],"type":"Point"}
}