{
  "type": "Feature",
  "properties": {
    "iso:country":"BE",
    "sg:address":"Zuid-ossenaarstraat 6",
    "sg:city":"Alveringem",
    "sg:orig_category":"Rundveehouders Varkenskwekers",
    "sg:phone":"+32 58 28 86 13",
    "sg:postcode":"8690",
    "sg:province":"West-Vlaanderen",
    "wof:name":"Frans Vandenbroucke",
    "wof:placetype":"venue"
},
  "geometry": {"coordinates":[2.7389500141,51.0123596191],"type":"Point"}
}