{
  "type": "Feature",
  "properties": {
    "iso:country":"BE",
    "sg:address":"Rue Du Coquelet 24bd1",
    "sg:city":"Gembloux",
    "sg:orig_category":"Advocaten and juridische adviseurs",
    "sg:phone":"+32 81 61 06 81",
    "sg:postcode":"5030",
    "sg:province":"Namur",
    "wof:name":"G\u00c9rard Baudhuin",
    "wof:placetype":"venue"
},
  "geometry": {"coordinates":[4.6940989494,50.5667572021],"type":"Point"}
}