{
  "type": "Feature",
  "properties": {
    "addr:full":"Rue De La Vou\u00e9e Juetta 13b Vis\u00e9 (richelle) Li\u00e8ge 4600",
    "addr:housenumber":"13b",
    "addr:postcode":"4600",
    "addr:street":"Rue De La Voue\u0301E Juetta",
    "iso:country":"BE",
    "sg:address":"Rue De La Vou\u00e9e Juetta 13b",
    "sg:city":"Vis\u00e9 (richelle)",
    "sg:classifiers":[
        {
            "category":"Building & Trades",
            "subcategory":"Construction",
            "type":"Services"
        }
    ],
    "sg:phone":"+32 4 379 33 05",
    "sg:postcode":"4600",
    "sg:province":"Li\u00e8ge",
    "sg:tags":[
        "installation",
        "-",
        "central",
        "heating"
    ],
    "wof:name":"Caps Y",
    "wof:placetype":"venue"
},
  "geometry": {"coordinates":[5.6951770782,50.712223053],"type":"Point"}
}