{
  "type": "Feature",
  "properties": {
    "addr:full":"Tiensestraat 59 Leuven Vlaams-Brabant 3000",
    "addr:housenumber":"59",
    "addr:postcode":"3000",
    "addr:street":"Tiensestraat",
    "iso:country":"BE",
    "sg:address":"Tiensestraat 59",
    "sg:city":"Leuven",
    "sg:orig_category":"Blanchisseries and teintureries. Location de v\u00eatements, chaussures and textiles",
    "sg:phone":"+32 16 22 11 18",
    "sg:postcode":"3000",
    "sg:province":"Vlaams-Brabant",
    "wof:name":"Atomic",
    "wof:placetype":"venue"
},
  "geometry": {"coordinates":[4.7050571442,50.8772163391],"type":"Point"}
}