{
  "type": "Feature",
  "properties": {
    "iso:country":"BE",
    "sg:address":"Sint-lenaartseweg 24 Box 2",
    "sg:city":"Wuustwezel (loenhout)",
    "sg:classifiers":[
        {
            "category":"Building & Trades",
            "subcategory":"Landscaping Services",
            "type":"Services"
        }
    ],
    "sg:phone":"+32 3 669 52 42",
    "sg:postcode":"2990",
    "sg:province":"Antwerpen",
    "sg:tags":[
        "gardening",
        "garden",
        "maintenance"
    ],
    "wof:name":"Labyrint",
    "wof:placetype":"venue"
},
  "geometry": {"coordinates":[4.6489467621,51.3984642029],"type":"Point"}
}