{
  "type": "Feature",
  "properties": {
    "iso:country":"BE",
    "sg:address":"Battelsesteenweg 493bb",
    "sg:city":"Mechelen",
    "sg:orig_category":"Avocats and conseillers juridiques",
    "sg:phone":"+32 15 27 22 01",
    "sg:postcode":"2800",
    "sg:province":"Antwerpen",
    "wof:name":"Marc Hendrickx",
    "wof:placetype":"venue"
},
  "geometry": {"coordinates":[4.4493598938,51.0387191772],"type":"Point"}
}