{
  "type": "Feature",
  "properties": {
    "iso:country":"BE",
    "sg:address":"Veldenbergstraat 91",
    "sg:city":"Merksplas",
    "sg:classifiers":[
        {
            "category":"Sports & Exercise",
            "subcategory":"Sports Center",
            "type":"Entertainment"
        }
    ],
    "sg:phone":"+32 14 63 43 43",
    "sg:postcode":"2330",
    "sg:province":"Antwerpen",
    "sg:tags":[
        "installation",
        "sportifs",
        "camping",
        "de",
        "terrain",
        "hors"
    ],
    "wof:name":"Zwembad Molenzijdse Heide",
    "wof:placetype":"venue"
},
  "geometry": {"coordinates":[4.8392939568,51.3693275452],"type":"Point"}
}