{
  "type": "Feature",
  "properties": {
    "iso:country":"BE",
    "sg:address":"Rue Des Combattants 27",
    "sg:city":"Chaudfontaine",
    "sg:orig_category":"Artsen and specialisten",
    "sg:phone":"+32 4 367 21 07",
    "sg:postcode":"4051",
    "sg:province":"Li\u00e8ge",
    "wof:name":"Daniel Secco",
    "wof:placetype":"venue"
},
  "geometry": {"coordinates":[5.6325540543,50.6020927429],"type":"Point"}
}