{
  "type": "Feature",
  "properties": {
    "iso:country":"BE",
    "sg:address":"Aartrijksestraat 96",
    "sg:city":"Eernegem",
    "sg:orig_category":"Royal Canin. Services pour animaux domestiques",
    "sg:phone":"+32 59 29 06 07",
    "sg:postcode":"8480",
    "sg:province":"West-Vlaanderen",
    "wof:name":"Vanhaverbeke Kathy",
    "wof:placetype":"venue"
},
  "geometry": {"coordinates":[3.0310070515,51.1244392395],"type":"Point"}
}