{
  "type": "Feature",
  "properties": {
    "addr:full":"Rue Du Ch\u00e2telain 49 Bruxelles (ixelles) Bruxelles-Capitale 1050",
    "addr:housenumber":"49",
    "addr:postcode":"1050",
    "addr:street":"Rue Du Cha\u0302Telain",
    "iso:country":"BE",
    "sg:address":"Rue Du Ch\u00e2telain 49",
    "sg:city":"Bruxelles (ixelles)",
    "sg:classifiers":[
        {
            "category":"Utilities",
            "subcategory":"Telephone",
            "type":"Services"
        }
    ],
    "sg:phone":"+32 2 649 00 51",
    "sg:postcode":"1050",
    "sg:province":"Bruxelles-Capitale",
    "sg:tags":[
        "-",
        "internet"
    ],
    "wof:name":"Ubiquity Sa",
    "wof:placetype":"venue"
},
  "geometry": {"coordinates":[4.3618998528,50.8256263733],"type":"Point"}
}