{
  "type": "Feature",
  "properties": {
    "addr:full":"Vierschaarstraat 8 Kortrijk West-Vlaanderen 8500",
    "addr:housenumber":"8",
    "addr:postcode":"8500",
    "addr:street":"Vierschaarstraat",
    "iso:country":"BE",
    "sg:address":"Vierschaarstraat 8",
    "sg:city":"Kortrijk",
    "sg:classifiers":[
        {
            "category":"Home & Garden",
            "subcategory":"Carpets & Floor Coverings",
            "type":"Retail Goods"
        }
    ],
    "sg:phone":"+32 56 20 52 55",
    "sg:postcode":"8500",
    "sg:province":"West-Vlaanderen",
    "sg:tags":[
        "-"
    ],
    "wof:name":"Kordekor Nv",
    "wof:placetype":"venue"
},
  "geometry": {"coordinates":[3.2770810127,50.8215637207],"type":"Point"}
}