{
  "type": "Feature",
  "properties": {
    "addr:full":"Clemenceaustraat 124 Sint-katelijne-waver Antwerpen 2860",
    "addr:housenumber":"124",
    "addr:postcode":"2860",
    "addr:street":"Clemenceaustraat",
    "iso:country":"BE",
    "sg:address":"Clemenceaustraat 124",
    "sg:city":"Sint-katelijne-waver",
    "sg:orig_category":"Brood, gebak and snoepgoed",
    "sg:phone":"+32 15 21 87 90",
    "sg:postcode":"2860",
    "sg:province":"Antwerpen",
    "wof:name":"Bakkerij Peeters",
    "wof:placetype":"venue"
},
  "geometry": {"coordinates":[4.488629818,51.0621414185],"type":"Point"}
}