{
  "type": "Feature",
  "properties": {
    "iso:country":"BE",
    "sg:address":"Groenestraat 4",
    "sg:city":"Kruishoutem",
    "sg:orig_category":"Varkenskwekers",
    "sg:phone":"+32 9 383 64 78",
    "sg:postcode":"9770",
    "sg:province":"Oost-Vlaanderen",
    "wof:name":"Martin Haerinck",
    "wof:placetype":"venue"
},
  "geometry": {"coordinates":[3.5453650951,50.9053192139],"type":"Point"}
}