{
  "type": "Feature",
  "properties": {
    "addr:full":"Leo Baekelandstraat 7 Box 2 Kapellen (mariaburg) Antwerpen 2950",
    "addr:housenumber":"7;2",
    "addr:postcode":"2950",
    "addr:street":"Leo Baekelandstraat;Box",
    "iso:country":"BE",
    "sg:address":"Leo Baekelandstraat 7 Box 2",
    "sg:city":"Kapellen (mariaburg)",
    "sg:classifiers":[
        {
            "category":"Utilities",
            "subcategory":"Refuse",
            "type":"Services"
        }
    ],
    "sg:phone":"+32 3 666 47 77",
    "sg:postcode":"2950",
    "sg:province":"Antwerpen",
    "sg:tags":[
        "catering"
    ],
    "wof:name":"I S B Bvba",
    "wof:placetype":"venue"
},
  "geometry": {"coordinates":[4.4349379539,51.2986450195],"type":"Point"}
}