{
  "type": "Feature",
  "properties": {
    "iso:country":"BE",
    "sg:address":"Markt 88",
    "sg:city":"Berlaar",
    "sg:orig_category":"Slagers",
    "sg:phone":"+32 3 422 55 78",
    "sg:postcode":"2590",
    "sg:province":"Antwerpen",
    "wof:name":"De Kippenwinkel",
    "wof:placetype":"venue"
},
  "geometry": {"coordinates":[4.6615190506,51.1184997559],"type":"Point"}
}