{
  "type": "Feature",
  "properties": {
    "addr:full":"Cherra 62 Flemalle Li\u00e8ge 4400",
    "addr:housenumber":"62",
    "addr:postcode":"4400",
    "addr:street":"Cherra",
    "iso:country":"BE",
    "sg:address":"Cherra 62",
    "sg:city":"Flemalle",
    "sg:orig_category":"Boissons",
    "sg:phone":"+32 4 275 61 42",
    "sg:postcode":"4400",
    "sg:province":"Li\u00e8ge",
    "wof:name":"Jean Depireux",
    "wof:placetype":"venue"
},
  "geometry": {"coordinates":[5.4232401848,50.5832901001],"type":"Point"}
}