{
  "type": "Feature",
  "properties": {
    "addr:full":"Theo Andriesstraat 31 Puurs Antwerpen 2870",
    "addr:housenumber":"31",
    "addr:postcode":"2870",
    "addr:street":"Theo Andriesstraat",
    "iso:country":"BE",
    "sg:address":"Theo Andriesstraat 31",
    "sg:city":"Puurs",
    "sg:orig_category":"Boucheries",
    "sg:phone":"+32 3 889 60 36",
    "sg:postcode":"2870",
    "sg:province":"Antwerpen",
    "wof:name":"Cecilia Van De Ven",
    "wof:placetype":"venue"
},
  "geometry": {"coordinates":[4.2797031403,51.0547065735],"type":"Point"}
}