{
  "type": "Feature",
  "properties": {
    "iso:country":"BE",
    "sg:address":"Steenweg Op Oosthoven 267",
    "sg:city":"Turnhout",
    "sg:orig_category":"Meubelzaken, woning- and keukeninrichting",
    "sg:phone":"+32 14 42 09 20",
    "sg:postcode":"2300",
    "sg:province":"Antwerpen",
    "wof:name":"Meubelen Van De Lisdonk",
    "wof:placetype":"venue"
},
  "geometry": {"coordinates":[4.9622812271,51.3340301514],"type":"Point"}
}