{
  "type": "Feature",
  "properties": {
    "addr:full":"Oude Tramweg 19 Hoogstraten Antwerpen 2328",
    "addr:housenumber":"19",
    "addr:postcode":"2328",
    "addr:street":"Oude Tramweg",
    "iso:country":"BE",
    "sg:address":"Oude Tramweg 19",
    "sg:city":"Hoogstraten",
    "sg:orig_category":"Installatie van houten of kunststof schrijnwerk Installatie van metalen schrijnwerk",
    "sg:phone":"+32 3 315 04 05",
    "sg:postcode":"2328",
    "sg:province":"Antwerpen",
    "wof:name":"Luc Marijnissen",
    "wof:placetype":"venue"
},
  "geometry": {"coordinates":[4.7734627724,51.4939689636],"type":"Point"}
}