{
  "type": "Feature",
  "properties": {
    "iso:country":"BE",
    "sg:address":"Avenue De Copenhague 1",
    "sg:city":"Shape",
    "sg:classifiers":[
        {
            "category":"Retail",
            "subcategory":"Auto Repair",
            "type":"Services"
        }
    ],
    "sg:phone":"+32 65 34 85 93",
    "sg:postcode":"7010",
    "sg:tags":[
        "garage"
    ],
    "wof:name":"Shape Car City",
    "wof:placetype":"venue"
},
  "geometry": {"coordinates":[3.9827299118,50.5000114441],"type":"Point"}
}