{
  "type": "Feature",
  "properties": {
    "iso:country":"BE",
    "sg:address":"Zwarte Zusterslaan 1",
    "sg:city":"Maldegem",
    "sg:orig_category":"Enseignement maternel and primaire",
    "sg:phone":"+32 50 71 23 81",
    "sg:postcode":"9990",
    "sg:province":"Oost-Vlaanderen",
    "wof:name":"Vrije Basisschool",
    "wof:placetype":"venue"
},
  "geometry": {"coordinates":[3.4523251057,51.206401825],"type":"Point"}
}