{
  "type": "Feature",
  "properties": {
    "addr:full":"Kursaallaan 9 Koksijde West-Vlaanderen 8670",
    "addr:housenumber":"9",
    "addr:postcode":"8670",
    "addr:street":"Kursaallaan",
    "iso:country":"BE",
    "sg:address":"Kursaallaan 9",
    "sg:city":"Koksijde",
    "sg:orig_category":"Kapsalons",
    "sg:phone":"+32 58 51 76 85",
    "sg:postcode":"8670",
    "sg:province":"West-Vlaanderen",
    "wof:name":"Muriel",
    "wof:placetype":"venue"
},
  "geometry": {"coordinates":[2.6358749866,51.1176147461],"type":"Point"}
}