{
  "type": "Feature",
  "properties": {
    "iso:country":"BE",
    "sg:address":"Maastrichtersteenweg 129",
    "sg:city":"Maaseik",
    "sg:orig_category":"Location de voitures",
    "sg:phone":"+32 89 56 45 71",
    "sg:postcode":"3680",
    "sg:province":"Limburg",
    "wof:name":"Autoverhuur Bijnens",
    "wof:placetype":"venue"
},
  "geometry": {"coordinates":[5.7669019699,51.0890159607],"type":"Point"}
}