{
  "type": "Feature",
  "properties": {
    "addr:full":"Avenue De Kersbeek 234 Vorst/forest Bruxelles-Capitale 1190",
    "addr:housenumber":"234",
    "addr:postcode":"1190",
    "addr:street":"Avenue De Kersbeek;/ Forest",
    "iso:country":"BE",
    "sg:address":"Avenue De Kersbeek 234",
    "sg:city":"Vorst/forest",
    "sg:orig_category":"Plomberie, chauffage and installations sanitaires",
    "sg:phone":"+32 2 376 70 07",
    "sg:postcode":"1190",
    "sg:province":"Bruxelles-Capitale",
    "wof:name":"Saniflo",
    "wof:placetype":"venue"
},
  "geometry": {"coordinates":[4.3207278252,50.8023605347],"type":"Point"}
}