{
  "type": "Feature",
  "properties": {
    "addr:full":"Knokstraat 24 Ruiselede West-Vlaanderen 8755",
    "addr:housenumber":"24",
    "addr:postcode":"8755",
    "addr:street":"Knokstraat",
    "iso:country":"BE",
    "sg:address":"Knokstraat 24",
    "sg:city":"Ruiselede",
    "sg:orig_category":"Woningbouw",
    "sg:phone":"+32 51 68 80 32",
    "sg:postcode":"8755",
    "sg:province":"West-Vlaanderen",
    "wof:name":"Constant Vindevoghel",
    "wof:placetype":"venue"
},
  "geometry": {"coordinates":[3.381592989,51.047252655],"type":"Point"}
}