{
  "type": "Feature",
  "properties": {
    "iso:country":"BE",
    "sg:address":"Molenstraat 6",
    "sg:city":"Eeklo",
    "sg:classifiers":[
        {
            "category":"Professional",
            "subcategory":"Advertising",
            "type":"Services"
        }
    ],
    "sg:phone":"+32 58 31 27 02",
    "sg:postcode":"9900",
    "sg:province":"Oost-Vlaanderen",
    "sg:tags":[
        "article",
        "porcelain",
        "ceramic"
    ],
    "wof:name":"Ardies Import Nv",
    "wof:placetype":"venue"
},
  "geometry": {"coordinates":[2.6617588997,51.072681427],"type":"Point"}
}