{
  "type": "Feature",
  "properties": {
    "iso:country":"BE",
    "sg:address":"Rue De L'arsenal 104",
    "sg:city":"Luik (groot)",
    "sg:orig_category":"Production de spectacles. Artistes ind\u00e9pendants",
    "sg:phone":"+32 4 263 38 46",
    "sg:postcode":"4000",
    "sg:province":"Li\u00e8ge",
    "wof:name":"Twirling Waremmien",
    "wof:placetype":"venue"
},
  "geometry": {"coordinates":[5.5599050522,50.6777000427],"type":"Point"}
}