{
  "type": "Feature",
  "properties": {
    "iso:country":"BE",
    "sg:address":"Rue Baron Copp\u00e9e 96",
    "sg:city":"Libin (ochamps)",
    "sg:classifiers":[
        {
            "category":"Bars & Pubs",
            "type":"Food & Drink"
        }
    ],
    "sg:phone":"+32 61 22 39 20",
    "sg:postcode":"6890",
    "sg:province":"Luxembourg",
    "wof:name":"Riviera (la)",
    "wof:placetype":"venue"
},
  "geometry": {"coordinates":[5.2797989845,49.9244232178],"type":"Point"}
}