{
  "type": "Feature",
  "properties": {
    "addr:full":"Victoriastraat 37 Edegem Antwerpen 2650",
    "addr:housenumber":"37",
    "addr:postcode":"2650",
    "addr:street":"Victoriastraat",
    "iso:country":"BE",
    "sg:address":"Victoriastraat 37",
    "sg:city":"Edegem",
    "sg:classifiers":[
        {
            "category":"Professional",
            "subcategory":"Lawyer & Legal Services",
            "type":"Services"
        }
    ],
    "sg:phone":"+32 3 457 81 97",
    "sg:postcode":"2650",
    "sg:province":"Antwerpen",
    "wof:name":"Verhelst Wilfried",
    "wof:placetype":"venue"
},
  "geometry": {"coordinates":[4.4485239983,51.1524887085],"type":"Point"}
}