{
  "type": "Feature",
  "properties": {
    "addr:full":"Voie Des Fosses 33 Blegny Li\u00e8ge 4672",
    "addr:housenumber":"33",
    "addr:postcode":"4672",
    "addr:street":"Voie Des Fosses",
    "iso:country":"BE",
    "sg:address":"Voie Des Fosses 33",
    "sg:city":"Blegny",
    "sg:orig_category":"Artsen and specialisten",
    "sg:phone":"+32 4 387 50 75",
    "sg:postcode":"4672",
    "sg:province":"Li\u00e8ge",
    "wof:name":"Aline Bauduin",
    "wof:placetype":"venue"
},
  "geometry": {"coordinates":[5.7018008232,50.6961021423],"type":"Point"}
}