{
  "type": "Feature",
  "properties": {
    "addr:full":"Neerstalse Steenweg 16 Vorst/forest Bruxelles-Capitale 1190",
    "addr:housenumber":"16",
    "addr:postcode":"1190",
    "addr:street":"Neerstalse Steenweg;/ Forest",
    "iso:country":"BE",
    "sg:address":"Neerstalse Steenweg 16",
    "sg:city":"Vorst/forest",
    "sg:orig_category":"Kapsalons",
    "sg:phone":"+32 2 376 93 99",
    "sg:postcode":"1190",
    "sg:province":"Bruxelles-Capitale",
    "wof:name":"Michel Luyten",
    "wof:placetype":"venue"
},
  "geometry": {"coordinates":[4.3175849915,50.809261322],"type":"Point"}
}