{
  "type": "Feature",
  "properties": {
    "addr:full":"Godshuislaan 46 Roeselare West-Vlaanderen 8800",
    "addr:housenumber":"46",
    "addr:postcode":"8800",
    "addr:street":"Godshuislaan",
    "iso:country":"BE",
    "sg:address":"Godshuislaan 46",
    "sg:city":"Roeselare",
    "sg:classifiers":[
        {
            "category":"Health Services",
            "subcategory":"Doctor",
            "type":"Services"
        }
    ],
    "sg:phone":"+32 51 20 37 20",
    "sg:postcode":"8800",
    "sg:province":"West-Vlaanderen",
    "sg:tags":[
        "medicinephysicians",
        "surgeon"
    ],
    "wof:name":"Deckers T",
    "wof:placetype":"venue"
},
  "geometry": {"coordinates":[3.1245129108,50.9576873779],"type":"Point"}
}