{
  "type": "Feature",
  "properties": {
    "iso:country":"BE",
    "sg:address":"Ronchamps 52",
    "sg:city":"La Roche-en-ardenne (beausaint)",
    "sg:classifiers":[
        {
            "category":"Retail",
            "subcategory":"Auto Repair",
            "type":"Services"
        }
    ],
    "sg:phone":"+32 84 41 30 30",
    "sg:postcode":"6980",
    "sg:province":"Luxembourg",
    "sg:tags":[
        "automobile-body"
    ],
    "wof:name":"C.m.f. Car",
    "wof:placetype":"venue"
},
  "geometry": {"coordinates":[5.5757198334,50.1831130981],"type":"Point"}
}