{
  "type": "Feature",
  "properties": {
    "addr:full":"Avenue Des Sept Bonniers 13 Bruxelles (uccle) Bruxelles-Capitale 1180",
    "addr:housenumber":"13",
    "addr:postcode":"1180",
    "addr:street":"Avenue Des Sept Bonniers",
    "iso:country":"BE",
    "sg:address":"Avenue Des Sept Bonniers 13",
    "sg:city":"Bruxelles (uccle)",
    "sg:classifiers":[
        {
            "category":"Health Services",
            "subcategory":"Health Practitioner",
            "type":"Services"
        }
    ],
    "sg:phone":"+32 2 346 63 34",
    "sg:postcode":"1180",
    "sg:province":"Bruxelles-Capitale",
    "sg:tags":[
        "physiotherapist"
    ],
    "wof:name":"Denys Claudine",
    "wof:placetype":"venue"
},
  "geometry": {"coordinates":[4.3381390572,50.8136177063],"type":"Point"}
}