{
  "type": "Feature",
  "properties": {
    "iso:country":"BE",
    "sg:address":"Rue E Walschaerts 22",
    "sg:city":"Saint-gilles",
    "sg:orig_category":"Magasins sp\u00e9cialis\u00e9s. Quincailleries",
    "sg:phone":"+32 2 537 76 21",
    "sg:postcode":"1060",
    "sg:province":"Bruxelles-Capitale",
    "wof:name":"B'block",
    "wof:placetype":"venue"
},
  "geometry": {"coordinates":[4.3366751671,50.8265571594],"type":"Point"}
}