{
  "type": "Feature",
  "properties": {
    "iso:country":"BE",
    "sg:address":"D\u00c9sir\u00c9 Mercierlaan 114",
    "sg:city":"Gent",
    "sg:orig_category":"Medische apparatuur, orthopedische artikelen and prothesen Fab",
    "sg:phone":"+32 9 232 19 78",
    "sg:postcode":"9050",
    "sg:province":"Oost-Vlaanderen",
    "wof:name":"Labo Terryn",
    "wof:placetype":"venue"
},
  "geometry": {"coordinates":[3.7644500732,51.0246582031],"type":"Point"}
}