{
  "type": "Feature",
  "properties": {
    "iso:country":"BE",
    "sg:address":"Rue Hanoteau 81",
    "sg:city":"Sombreffe",
    "sg:classifiers":[
        {
            "category":"Sports & Exercise",
            "subcategory":"Sports Center",
            "type":"Entertainment"
        }
    ],
    "sg:phone":"+32 71 54 19 04",
    "sg:postcode":"5140",
    "sg:province":"Namur",
    "sg:tags":[
        "terrain",
        "hors",
        "de",
        "installation",
        "sportifs"
    ],
    "wof:name":"Etrier De Sombreffe",
    "wof:placetype":"venue"
},
  "geometry": {"coordinates":[4.6169080734,50.5338287354],"type":"Point"}
}