{
  "type": "Feature",
  "properties": {
    "iso:country":"BE",
    "sg:address":"Neerstraat 2",
    "sg:city":"Oud-turnhout",
    "sg:orig_category":"Brood, gebak and snoepgoed",
    "sg:phone":"+32 14 45 34 86",
    "sg:postcode":"2360",
    "sg:province":"Antwerpen",
    "wof:name":"Huis Cornelissen-meyers",
    "wof:placetype":"venue"
},
  "geometry": {"coordinates":[4.9818220139,51.3170623779],"type":"Point"}
}