{
  "type": "Feature",
  "properties": {
    "addr:full":"Rue De L\u00b4yser 407 Ans Li\u00e8ge 4430",
    "addr:housenumber":"407",
    "addr:postcode":"4430",
    "addr:street":"Rue De L\u00b4Yser",
    "iso:country":"BE",
    "sg:address":"Rue De L\u00b4yser 407",
    "sg:city":"Ans",
    "sg:orig_category":"Dameskledingzaken",
    "sg:phone":"+32 4 246 53 32",
    "sg:postcode":"4430",
    "sg:province":"Li\u00e8ge",
    "wof:name":"Maison Nat & Co",
    "wof:placetype":"venue"
},
  "geometry": {"coordinates":[5.5122160912,50.6637039185],"type":"Point"}
}