{
  "type": "Feature",
  "properties": {
    "addr:full":"Schatting 12 Zedelgem West-Vlaanderen 8210",
    "addr:housenumber":"12",
    "addr:postcode":"8210",
    "addr:street":"Schatting",
    "iso:country":"BE",
    "sg:address":"Schatting 12",
    "sg:city":"Zedelgem",
    "sg:classifiers":[
        {
            "category":"Military Area",
            "subcategory":"Air Force Base",
            "type":"Public Place"
        }
    ],
    "sg:phone":"+32 50 24 16 01",
    "sg:postcode":"8210",
    "sg:province":"West-Vlaanderen",
    "sg:tags":[
        "gear"
    ],
    "wof:name":"Van Poucke Mech Constr. Bvba",
    "wof:placetype":"venue"
},
  "geometry": {"coordinates":[3.144671917,51.1367263794],"type":"Point"}
}