{
  "type": "Feature",
  "properties": {
    "addr:full":"Rue Marie-christine 91 Bruxelles Bruxelles-Capitale 1020",
    "addr:housenumber":"91",
    "addr:postcode":"1020",
    "addr:street":"Rue Marie-Christine",
    "iso:country":"BE",
    "sg:address":"Rue Marie-christine 91",
    "sg:city":"Bruxelles",
    "sg:orig_category":"Video-Equipment - Mainten. and Repair",
    "sg:phone":"+32 2 427 13 27",
    "sg:postcode":"1020",
    "sg:province":"Bruxelles-Capitale",
    "wof:name":"Hitachi-aae-video Service",
    "wof:placetype":"venue"
},
  "geometry": {"coordinates":[4.354446888,50.8753471375],"type":"Point"}
}