{
  "type": "Feature",
  "properties": {
    "addr:full":"Rue Baty-saint-pierre 7 Gembloux Namur 5032",
    "addr:housenumber":"7",
    "addr:postcode":"5032",
    "addr:street":"Rue Baty-Saint-Pierre;Namur",
    "iso:country":"BE",
    "sg:address":"Rue Baty-saint-pierre 7",
    "sg:city":"Gembloux",
    "sg:orig_category":"Eleveurs de bovins",
    "sg:phone":"+32 81 56 60 35",
    "sg:postcode":"5032",
    "sg:province":"Namur",
    "wof:name":"Gilbert Denorme",
    "wof:placetype":"venue"
},
  "geometry": {"coordinates":[4.740860939,50.5074729919],"type":"Point"}
}