{
  "type": "Feature",
  "properties": {
    "addr:full":"Wilfordkaai 17 Temse Oost-Vlaanderen 9140",
    "addr:housenumber":"17",
    "addr:postcode":"9140",
    "addr:street":"Wilfordkaai",
    "iso:country":"BE",
    "sg:address":"Wilfordkaai 17",
    "sg:city":"Temse",
    "sg:classifiers":[
        {
            "category":"Restaurant",
            "type":"Food & Drink"
        }
    ],
    "sg:phone":"+32 3 771 03 70",
    "sg:postcode":"9140",
    "sg:province":"Oost-Vlaanderen",
    "wof:name":"Het Palingshuis",
    "wof:placetype":"venue"
},
  "geometry": {"coordinates":[4.2157869339,51.123462677],"type":"Point"}
}