{
  "type": "Feature",
  "properties": {
    "iso:country":"BE",
    "sg:address":"Grotesteenweg 132bb",
    "sg:city":"Geel",
    "sg:orig_category":"Radioproductie and uitzendingen Reclamebureaus",
    "sg:phone":"+32 14 53 85 38",
    "sg:postcode":"2440",
    "sg:province":"Antwerpen",
    "wof:name":"Radio Power",
    "wof:placetype":"venue"
},
  "geometry": {"coordinates":[4.9444198608,51.1008110046],"type":"Point"}
}