{
  "type": "Feature",
  "properties": {
    "addr:full":"Rue De La Cit\u00e9 81 Verviers Li\u00e8ge 4800",
    "addr:housenumber":"81",
    "addr:postcode":"4800",
    "addr:street":"Rue De La Cite\u0301",
    "iso:country":"BE",
    "sg:address":"Rue De La Cit\u00e9 81",
    "sg:city":"Verviers",
    "sg:classifiers":[
        {
            "category":"Landmark",
            "subcategory":"Memorial",
            "type":"Public Place"
        }
    ],
    "sg:phone":"+32 87 33 45 61",
    "sg:postcode":"4800",
    "sg:province":"Li\u00e8ge",
    "sg:tags":[
        "-",
        "monument"
    ],
    "wof:name":"Leclercq E",
    "wof:placetype":"venue"
},
  "geometry": {"coordinates":[5.8795199394,50.5976715088],"type":"Point"}
}