{
  "type": "Feature",
  "properties": {
    "addr:full":"Rue C\u00c9sar De Paepe 42 Soumagne Li\u00e8ge 4630",
    "addr:housenumber":"42",
    "addr:postcode":"4630",
    "addr:street":"Rue Ce\u0301Sar De Paepe",
    "iso:country":"BE",
    "sg:address":"Rue C\u00c9sar De Paepe 42",
    "sg:city":"Soumagne",
    "sg:classifiers":[
        {
            "category":"Restaurant",
            "type":"Food & Drink"
        }
    ],
    "sg:phone":"+32 4 377 27 13",
    "sg:postcode":"4630",
    "sg:province":"Li\u00e8ge",
    "wof:name":"Khan",
    "wof:placetype":"venue"
},
  "geometry": {"coordinates":[5.7347931862,50.6321144104],"type":"Point"}
}