{
  "type": "Feature",
  "properties": {
    "iso:country":"BE",
    "sg:address":"Industriepark 2",
    "sg:city":"Merelbeke",
    "sg:orig_category":"Plomberie, chauffage and installations sanitaires",
    "sg:phone":"+32 9 252 60 69",
    "sg:postcode":"9820",
    "sg:province":"Oost-Vlaanderen",
    "wof:name":"Apok",
    "wof:placetype":"venue"
},
  "geometry": {"coordinates":[3.7666819096,50.9876861572],"type":"Point"}
}