{
  "type": "Feature",
  "properties": {
    "addr:full":"Vrijheidstraat 53 Boom Antwerpen 2850",
    "addr:housenumber":"53",
    "addr:postcode":"2850",
    "addr:street":"Vrijheidstraat",
    "iso:country":"BE",
    "sg:address":"Vrijheidstraat 53",
    "sg:city":"Boom",
    "sg:classifiers":[
        {
            "category":"Transit Center",
            "subcategory":"Passenger",
            "type":"Transportation"
        }
    ],
    "sg:phone":"+32 3 844 29 60",
    "sg:postcode":"2850",
    "sg:province":"Antwerpen",
    "sg:tags":[
        "sand",
        "gravel"
    ],
    "wof:name":"Lauwers Nv",
    "wof:placetype":"venue"
},
  "geometry": {"coordinates":[4.3592739105,51.0889015198],"type":"Point"}
}