{
  "type": "Feature",
  "properties": {
    "addr:full":"Kampveldstraat 14 Oostkamp West-Vlaanderen 8020",
    "addr:housenumber":"14",
    "addr:postcode":"8020",
    "addr:street":"Kampveldstraat",
    "iso:country":"BE",
    "sg:address":"Kampveldstraat 14",
    "sg:city":"Oostkamp",
    "sg:orig_category":"Parfumeries",
    "sg:phone":"+32 50 82 34 04",
    "sg:postcode":"8020",
    "sg:province":"West-Vlaanderen",
    "wof:name":"Etienne Depestel",
    "wof:placetype":"venue"
},
  "geometry": {"coordinates":[3.2535259724,51.1322593689],"type":"Point"}
}