{
  "type": "Feature",
  "properties": {
    "iso:country":"BE",
    "sg:address":"Plockroy 53b1",
    "sg:city":"Meeuwen-gruitrode",
    "sg:orig_category":"Traitements param\u00e9dicaux",
    "sg:phone":"+32 11 79 36 10",
    "sg:postcode":"3670",
    "sg:province":"Limburg",
    "wof:name":"A. Broekx",
    "wof:placetype":"venue"
},
  "geometry": {"coordinates":[5.5276851654,51.0825042725],"type":"Point"}
}