{
  "type": "Feature",
  "properties": {
    "addr:full":"Rue R. Vanoverschelde 88 Moeskroen/mouscron Hainaut 7700",
    "addr:housenumber":"88",
    "addr:postcode":"7700",
    "addr:street":"Rue R. Vanoverschelde",
    "iso:country":"BE",
    "sg:address":"Rue R. Vanoverschelde 88",
    "sg:city":"Moeskroen/mouscron",
    "sg:classifiers":[
        {
            "category":"Personal",
            "subcategory":"Beauty Salon",
            "type":"Services"
        }
    ],
    "sg:phone":"+32 56 34 70 12",
    "sg:postcode":"7700",
    "sg:province":"Hainaut",
    "sg:tags":[
        "de",
        "coiffure"
    ],
    "wof:name":"Coiffure La Divine",
    "wof:placetype":"venue"
},
  "geometry": {"coordinates":[3.2323200703,50.7400932312],"type":"Point"}
}