{
  "type": "Feature",
  "properties": {
    "iso:country":"BE",
    "sg:address":"Breden Els 1",
    "sg:city":"Balen",
    "sg:orig_category":"Newspapers, magazines, periodicals - Distribution",
    "sg:phone":"+32 14 81 51 48",
    "sg:postcode":"2490",
    "sg:province":"Antwerpen",
    "wof:name":"Hoekske (het)",
    "wof:placetype":"venue"
},
  "geometry": {"coordinates":[5.1760377884,51.180267334],"type":"Point"}
}