{
  "type": "Feature",
  "properties": {
    "addr:full":"Rue Du Gaz 1 Waterloo Brabant Wallon 1410",
    "addr:housenumber":"1",
    "addr:postcode":"1410",
    "addr:street":"Rue Du Gaz",
    "iso:country":"BE",
    "sg:address":"Rue Du Gaz 1",
    "sg:city":"Waterloo",
    "sg:classifiers":[
        {
            "category":"Building & Trades",
            "subcategory":"Landscaping Services",
            "type":"Services"
        }
    ],
    "sg:phone":"+32 2 351 52 01",
    "sg:postcode":"1410",
    "sg:province":"Brabant Wallon",
    "sg:tags":[
        "handicraft"
    ],
    "wof:name":"Cr\u00e9atine",
    "wof:placetype":"venue"
},
  "geometry": {"coordinates":[4.4004387856,50.7135467529],"type":"Point"}
}