{
  "type": "Feature",
  "properties": {
    "iso:country":"BE",
    "sg:address":"Avenue Du Manoir 47",
    "sg:city":"Ukkel/uccle",
    "sg:orig_category":"Avocats and conseillers juridiques",
    "sg:phone":"+32 2 374 88 71",
    "sg:postcode":"1180",
    "sg:province":"Bruxelles-Capitale",
    "wof:name":"N. Jeanmart",
    "wof:placetype":"venue"
},
  "geometry": {"coordinates":[4.3467311859,50.8021392822],"type":"Point"}
}