{
  "type": "Feature",
  "properties": {
    "iso:country":"BE",
    "sg:address":"Sint-martensommegangstraat 45",
    "sg:city":"Hamme (moerzeke)",
    "sg:classifiers":[
        {
            "category":"Bars & Pubs",
            "type":"Food & Drink"
        }
    ],
    "sg:phone":"+32 52 47 41 93",
    "sg:postcode":"9220",
    "sg:province":"Oost-Vlaanderen",
    "wof:name":"Stapken ('t)",
    "wof:placetype":"venue"
},
  "geometry": {"coordinates":[4.1502599716,51.0682487488],"type":"Point"}
}