{
  "type": "Feature",
  "properties": {
    "iso:country":"BE",
    "sg:address":"Rue Du Trichon 97",
    "sg:city":"Morlanwelz (carni\u00e8res)",
    "sg:classifiers":[
        {
            "category":"Health Services",
            "subcategory":"Dentist",
            "type":"Services"
        }
    ],
    "sg:phone":"+32 64 45 10 23",
    "sg:postcode":"7141",
    "sg:province":"Hainaut",
    "wof:name":"Collard J",
    "wof:placetype":"venue"
},
  "geometry": {"coordinates":[4.2725849152,50.4519920349],"type":"Point"}
}