{
  "type": "Feature",
  "properties": {
    "iso:country":"BE",
    "sg:address":"Place De La Bouxhe 8",
    "sg:city":"Chaudfontaine",
    "sg:orig_category":"M\u00e9decins and sp\u00e9cialistes",
    "sg:phone":"+32 4 368 88 38",
    "sg:postcode":"4052",
    "sg:province":"Li\u00e8ge",
    "wof:name":"Jean-pierre Dejardin",
    "wof:placetype":"venue"
},
  "geometry": {"coordinates":[5.6394648552,50.5584106445],"type":"Point"}
}