{
  "type": "Feature",
  "properties": {
    "addr:full":"Route De Luxembourg 151 Arlon Luxembourg 6700",
    "addr:housenumber":"151",
    "addr:postcode":"6700",
    "addr:street":"Route De Luxembourg",
    "iso:country":"BE",
    "sg:address":"Route De Luxembourg 151",
    "sg:city":"Arlon",
    "sg:classifiers":[
        {
            "category":"Retail",
            "subcategory":"Auto Repair",
            "type":"Services"
        }
    ],
    "sg:phone":"+32 63 22 22 22",
    "sg:postcode":"6700",
    "sg:province":"Luxembourg",
    "sg:tags":[
        "breakdown",
        "automobile",
        "-",
        "recovery"
    ],
    "wof:name":"Depannage Barbier Sprl",
    "wof:placetype":"venue"
},
  "geometry": {"coordinates":[5.8254780769,49.6737632751],"type":"Point"}
}