{
  "type": "Feature",
  "properties": {
    "iso:country":"BE",
    "sg:address":"Stippelstraat 18 Box 2",
    "sg:city":"Sint-truiden (zepperen)",
    "sg:classifiers":[
        {
            "category":"Real Estate",
            "subcategory":"Architect",
            "type":"Services"
        }
    ],
    "sg:phone":"+32 11 31 15 21",
    "sg:postcode":"3800",
    "sg:province":"Limburg",
    "wof:name":"Nijs G",
    "wof:placetype":"venue"
},
  "geometry": {"coordinates":[5.2581911087,50.8413925171],"type":"Point"}
}