{
  "type": "Feature",
  "properties": {
    "addr:full":"Enclus Du Haut 41 Mont-de-l\u00b4enclus Hainaut 7750",
    "addr:housenumber":"41",
    "addr:postcode":"7750",
    "addr:street":"Mont-De-L\u00b4Enclus Hainaut",
    "iso:country":"BE",
    "sg:address":"Enclus Du Haut 41",
    "sg:city":"Mont-de-l\u00b4enclus",
    "sg:orig_category":"Caf\u00e9s Ruimtes voor conferenties, recepties and feesten",
    "sg:phone":"+32 69 45 45 85",
    "sg:postcode":"7750",
    "sg:province":"Hainaut",
    "wof:name":"Caf\u00c9 Palace",
    "wof:placetype":"venue"
},
  "geometry": {"coordinates":[3.4913370609,50.7575149536],"type":"Point"}
}