{
  "type": "Feature",
  "properties": {
    "addr:full":"Hoogstraat 106 Denderleeuw Oost-Vlaanderen 9472",
    "addr:housenumber":"106",
    "addr:postcode":"9472",
    "addr:street":"Hoogstraat",
    "iso:country":"BE",
    "sg:address":"Hoogstraat 106",
    "sg:city":"Denderleeuw",
    "sg:orig_category":"Eleveurs de bovins",
    "sg:phone":"+32 53 66 74 35",
    "sg:postcode":"9472",
    "sg:province":"Oost-Vlaanderen",
    "wof:name":"Luc Buydens",
    "wof:placetype":"venue"
},
  "geometry": {"coordinates":[4.0459918976,50.875957489],"type":"Point"}
}