{
  "type": "Feature",
  "properties": {
    "addr:full":"Lindelostraat 10 Lille Antwerpen 2275",
    "addr:housenumber":"10",
    "addr:postcode":"2275",
    "addr:street":"Lindelostraat",
    "iso:country":"BE",
    "sg:address":"Lindelostraat 10",
    "sg:city":"Lille",
    "sg:orig_category":"Maisons de repos and r\u00e9sidences",
    "sg:phone":"+32 14 88 99 11",
    "sg:postcode":"2275",
    "sg:province":"Antwerpen",
    "wof:name":"Rustoord Lindelo",
    "wof:placetype":"venue"
},
  "geometry": {"coordinates":[4.8239450455,51.2355117798],"type":"Point"}
}