{
  "type": "Feature",
  "properties": {
    "iso:country":"BE",
    "sg:address":"Woeker 20b10",
    "sg:city":"Oudenaarde",
    "sg:orig_category":"Avocats and conseillers juridiques",
    "sg:phone":"+32 55 30 24 05",
    "sg:postcode":"9700",
    "sg:province":"Oost-Vlaanderen",
    "wof:name":"Raymonda Glorieux",
    "wof:placetype":"venue"
},
  "geometry": {"coordinates":[3.6059000492,50.8453178406],"type":"Point"}
}