{
  "type": "Feature",
  "properties": {
    "iso:country":"BE",
    "sg:address":"Ferme Grosfils 89",
    "sg:city":"Jalhay",
    "sg:orig_category":"Groententeelt Rundveehouders",
    "sg:phone":"+32 87 64 77 50",
    "sg:postcode":"4845",
    "sg:province":"Li\u00e8ge",
    "wof:name":"Louis Deckers",
    "wof:placetype":"venue"
},
  "geometry": {"coordinates":[5.9845957756,50.5365142822],"type":"Point"}
}