{
  "type": "Feature",
  "properties": {
    "iso:country":"BE",
    "sg:address":"Frankrijkstraat 4",
    "sg:city":"Moeskroen/mouscron",
    "sg:orig_category":"Herstelling leer and schoeisel",
    "sg:phone":"+32 56 48 68 11",
    "sg:postcode":"7711",
    "sg:province":"Hainaut",
    "wof:name":"Cordonnerie Rapide",
    "wof:placetype":"venue"
},
  "geometry": {"coordinates":[3.3029398918,50.7274932861],"type":"Point"}
}