{
  "type": "Feature",
  "properties": {
    "addr:full":"Rue Des Sabli\u00e8res Mont-saint-guibert Brabant Wallon 1435",
    "addr:postcode":"1435",
    "addr:street":"Rue Des Sablie\u0300Res",
    "iso:country":"BE",
    "sg:address":"Rue Des Sabli\u00e8res",
    "sg:city":"Mont-saint-guibert",
    "sg:classifiers":[
        {
            "category":"Utilities",
            "subcategory":"Recycling",
            "type":"Services"
        }
    ],
    "sg:phone":"+32 10 61 12 27",
    "sg:postcode":"1435",
    "sg:province":"Brabant Wallon",
    "wof:name":"Recy-mat-haulotte",
    "wof:placetype":"venue"
},
  "geometry": {"coordinates":[4.6086540222,50.6435241699],"type":"Point"}
}