{
  "type": "Feature",
  "properties": {
    "addr:full":"Rue Du Village 94 Enghien Hainaut 7850",
    "addr:housenumber":"94",
    "addr:postcode":"7850",
    "addr:street":"Rue Du Village",
    "iso:country":"BE",
    "sg:address":"Rue Du Village 94",
    "sg:city":"Enghien",
    "sg:classifiers":[
        {
            "category":"Restaurant",
            "type":"Food & Drink"
        }
    ],
    "sg:phone":"+32 2 395 91 99",
    "sg:postcode":"7850",
    "sg:province":"Hainaut",
    "wof:name":"Le Cardinael",
    "wof:placetype":"venue"
},
  "geometry": {"coordinates":[4.0151782036,50.6914672852],"type":"Point"}
}