{
  "type": "Feature",
  "properties": {
    "addr:full":"Avenue Des Peupliers 8 Villers-la-ville (tilly) Brabant Wallon 1495",
    "addr:housenumber":"8",
    "addr:postcode":"1495",
    "addr:street":"Avenue Des Peupliers;Wallon",
    "iso:country":"BE",
    "sg:address":"Avenue Des Peupliers 8",
    "sg:city":"Villers-la-ville (tilly)",
    "sg:classifiers":[
        {
            "category":"Real Estate",
            "subcategory":"Architect",
            "type":"Services"
        }
    ],
    "sg:phone":"+32 71 88 74 92",
    "sg:postcode":"1495",
    "sg:province":"Brabant Wallon",
    "wof:name":"Wilfart G",
    "wof:placetype":"venue"
},
  "geometry": {"coordinates":[4.530477047,50.5786132812],"type":"Point"}
}