{
  "type": "Feature",
  "properties": {
    "iso:country":"BE",
    "sg:address":"Rue L\u00e9on Hachez 39",
    "sg:city":"Soignies",
    "sg:classifiers":[
        {
            "category":"Food & Beverages",
            "subcategory":"Specialty",
            "type":"Retail Goods"
        }
    ],
    "sg:phone":"+32 67 33 25 22",
    "sg:postcode":"7060",
    "sg:province":"Hainaut",
    "sg:tags":[
        "health",
        "dietary",
        "-",
        "biological"
    ],
    "wof:name":"Les Trois Epis Sprl",
    "wof:placetype":"venue"
},
  "geometry": {"coordinates":[4.0690979958,50.5812797546],"type":"Point"}
}