{
  "type": "Feature",
  "properties": {
    "addr:full":"Chauss\u00c9e De Charleroi 3 Sombreffe Namur 5140",
    "addr:housenumber":"3",
    "addr:postcode":"5140",
    "addr:street":"Chausse\u0301E De Charleroi",
    "iso:country":"BE",
    "sg:address":"Chauss\u00c9e De Charleroi 3",
    "sg:city":"Sombreffe",
    "sg:orig_category":"Benzinestations and brandstoffen",
    "sg:phone":"+32 71 88 64 40",
    "sg:postcode":"5140",
    "sg:province":"Namur",
    "wof:name":"Octa+",
    "wof:placetype":"venue"
},
  "geometry": {"coordinates":[4.587706089,50.5046806335],"type":"Point"}
}