{
  "type": "Feature",
  "properties": {
    "iso:country":"BE",
    "sg:address":"Grensstraat 17",
    "sg:city":"Kuurne",
    "sg:classifiers":[
        {
            "category":"Communications",
            "subcategory":"Film & Video Production",
            "type":"Services"
        }
    ],
    "sg:phone":"+32 56 70 33 00",
    "sg:postcode":"8520",
    "sg:province":"West-Vlaanderen",
    "sg:tags":[
        "sound",
        "recording",
        "studio"
    ],
    "wof:name":"Temple Of Tune Bvba",
    "wof:placetype":"venue"
},
  "geometry": {"coordinates":[3.2749300003,50.8710899353],"type":"Point"}
}