{
  "type": "Feature",
  "properties": {
    "iso:country":"BE",
    "sg:address":"Rue De Hesbaye 15",
    "sg:city":"Donceel",
    "sg:orig_category":"V\u00e9hicules automobiles. Entretien and r\u00e9parations de voitures",
    "sg:phone":"+32 19 54 42 95",
    "sg:postcode":"4357",
    "sg:province":"Li\u00e8ge",
    "wof:name":"Ets. Lebrun",
    "wof:placetype":"venue"
},
  "geometry": {"coordinates":[5.3182201385,50.661239624],"type":"Point"}
}