{
  "type": "Feature",
  "properties": {
    "iso:country":"BE",
    "sg:address":"Otegemstraat 21",
    "sg:city":"Zwevegem",
    "sg:classifiers":[
        {
            "category":"Bakery",
            "type":"Food & Drink"
        }
    ],
    "sg:phone":"+32 56 75 87 66",
    "sg:postcode":"8550",
    "sg:province":"West-Vlaanderen",
    "sg:tags":[
        "confectioner",
        "baker"
    ],
    "wof:name":"Croissanske",
    "wof:placetype":"venue"
},
  "geometry": {"coordinates":[3.3354549408,50.8129501343],"type":"Point"}
}