{
  "type": "Feature",
  "properties": {
    "iso:country":"BE",
    "sg:address":"Route De Gembloux 195",
    "sg:city":"Eghezee",
    "sg:orig_category":"Artsen and specialisten",
    "sg:phone":"+32 81 65 61 60",
    "sg:postcode":"5310",
    "sg:province":"Namur",
    "wof:name":"Ph. Tassart",
    "wof:placetype":"venue"
},
  "geometry": {"coordinates":[4.9023051262,50.591632843],"type":"Point"}
}