{
  "type": "Feature",
  "properties": {
    "iso:country":"BE",
    "sg:address":"Romershovenstraat 45",
    "sg:city":"Hoeselt",
    "sg:classifiers":[
        {
            "category":"Bars & Pubs",
            "type":"Food & Drink"
        }
    ],
    "sg:phone":"+32 89 51 42 26",
    "sg:postcode":"3730",
    "sg:province":"Limburg",
    "sg:tags":[
        "tavern"
    ],
    "wof:name":"Siebelke ('t)",
    "wof:placetype":"venue"
},
  "geometry": {"coordinates":[5.4615898132,50.8511390686],"type":"Point"}
}