{
  "type": "Feature",
  "properties": {
    "addr:full":"Stefaniestraat 49 Antwerpen Antwerpen 2018",
    "addr:housenumber":"49",
    "addr:postcode":"2018",
    "addr:street":"Stefaniestraat",
    "iso:country":"BE",
    "sg:address":"Stefaniestraat 49",
    "sg:city":"Antwerpen",
    "sg:orig_category":"Advocaten and juridische adviseurs",
    "sg:phone":"+32 3 237 18 87",
    "sg:postcode":"2018",
    "sg:province":"Antwerpen",
    "wof:name":"Hedwig Verhaaren",
    "wof:placetype":"venue"
},
  "geometry": {"coordinates":[4.402695179,51.2043647766],"type":"Point"}
}