{
  "type": "Feature",
  "properties": {
    "addr:full":"24 Rue L\u00e9opold De Swaef Bruxelles Bruxelles-Capitale 1070",
    "addr:housenumber":"24",
    "addr:postcode":"1070",
    "addr:street":"Rue Le\u0301Opold De Swaef",
    "iso:country":"BE",
    "sg:address":"24 Rue L\u00e9opold De Swaef",
    "sg:city":"Bruxelles",
    "sg:classifiers":[
        {
            "category":"Manufacturing",
            "subcategory":"Paper Products",
            "type":"Manufacturing & Wholesale Goods"
        }
    ],
    "sg:phone":"+32 2 523 78 93",
    "sg:postcode":"1070",
    "sg:province":"Bruxelles-Capitale",
    "sg:tags":[
        "finished",
        "cardboard",
        "-"
    ],
    "wof:name":"Rausch",
    "wof:placetype":"venue"
},
  "geometry": {"coordinates":[4.3129501343,50.8456840515],"type":"Point"}
}