{
  "type": "Feature",
  "properties": {
    "iso:country":"BE",
    "sg:address":"Rue Rondfontaine 11",
    "sg:city":"Trooz (for\u00eat)",
    "sg:classifiers":[
        {
            "category":"Education",
            "subcategory":"Dance Studio",
            "type":"Public Place"
        }
    ],
    "sg:phone":"+32 4 383 54 19",
    "sg:postcode":"4870",
    "sg:province":"Li\u00e8ge",
    "sg:tags":[
        "school",
        "dancing"
    ],
    "wof:name":"Expression 85 Asbl",
    "wof:placetype":"venue"
},
  "geometry": {"coordinates":[5.6695818901,50.5573310852],"type":"Point"}
}