{
  "type": "Feature",
  "properties": {
    "iso:country":"BE",
    "sg:address":"Luikersteenweg 615",
    "sg:city":"Tongeren",
    "sg:orig_category":"Articles non-alimentaires",
    "sg:phone":"+32 475 78 61 35",
    "sg:postcode":"3700",
    "sg:province":"Limburg",
    "wof:name":"Tits R",
    "wof:placetype":"venue"
},
  "geometry": {"coordinates":[5.4735898972,50.7632217407],"type":"Point"}
}