{
  "type": "Feature",
  "properties": {
    "addr:full":"Sint-lenaartseweg 48b4 Hoogstraten Antwerpen 2320",
    "addr:housenumber":"48b4",
    "addr:postcode":"2320",
    "addr:street":"Sint-Lenaartseweg",
    "iso:country":"BE",
    "sg:address":"Sint-lenaartseweg 48b4",
    "sg:city":"Hoogstraten",
    "sg:orig_category":"Produits pharmaceutiques Fab",
    "sg:phone":"+32 3 340 04 11",
    "sg:postcode":"2320",
    "sg:province":"Antwerpen",
    "wof:name":"Kempisch Laboratorium",
    "wof:placetype":"venue"
},
  "geometry": {"coordinates":[4.7403697968,51.3873748779],"type":"Point"}
}