{
  "type": "Feature",
  "properties": {
    "addr:full":"Heirbaan 28 Anzegem West-Vlaanderen 8570",
    "addr:housenumber":"28",
    "addr:postcode":"8570",
    "addr:street":"Heirbaan",
    "iso:country":"BE",
    "sg:address":"Heirbaan 28",
    "sg:city":"Anzegem",
    "sg:orig_category":"Enseignement maternel and primaire",
    "sg:phone":"+32 56 77 55 70",
    "sg:postcode":"8570",
    "sg:province":"West-Vlaanderen",
    "wof:name":"Vrije Kleuterschool",
    "wof:placetype":"venue"
},
  "geometry": {"coordinates":[3.4228959084,50.8415107727],"type":"Point"}
}