{
  "type": "Feature",
  "properties": {
    "addr:full":"Vossekotstraat 82 Sint-niklaas Oost-Vlaanderen 9100",
    "addr:housenumber":"82",
    "addr:postcode":"9100",
    "addr:street":"Vossekotstraat",
    "iso:country":"BE",
    "sg:address":"Vossekotstraat 82",
    "sg:city":"Sint-niklaas",
    "sg:orig_category":"Salons de coiffure. Parfumeries",
    "sg:phone":"+32 3 776 32 81",
    "sg:postcode":"9100",
    "sg:province":"Oost-Vlaanderen",
    "wof:name":"Freddy Wauters",
    "wof:placetype":"venue"
},
  "geometry": {"coordinates":[4.1996150017,51.1755905151],"type":"Point"}
}