{
  "type": "Feature",
  "properties": {
    "addr:full":"J. Vanzeerstraat 73 Diest Vlaams-Brabant 3290",
    "addr:housenumber":"73",
    "addr:postcode":"3290",
    "addr:street":"J. Vanzeerstraat",
    "iso:country":"BE",
    "sg:address":"J. Vanzeerstraat 73",
    "sg:city":"Diest",
    "sg:orig_category":"M\u00e9decins and sp\u00e9cialistes",
    "sg:phone":"+32 13 67 17 26",
    "sg:postcode":"3290",
    "sg:province":"Vlaams-Brabant",
    "wof:name":"G. Wouters",
    "wof:placetype":"venue"
},
  "geometry": {"coordinates":[5.0943188667,51.0380363464],"type":"Point"}
}