{
  "type": "Feature",
  "properties": {
    "iso:country":"BE",
    "sg:address":"Place De La Bouxhe 7",
    "sg:city":"Chaudfontaine",
    "sg:orig_category":"Diverse opleidingen and onderwijs",
    "sg:phone":"+32 4 368 65 57",
    "sg:postcode":"4052",
    "sg:province":"Li\u00e8ge",
    "wof:name":"P\u00cale-m\u00cale",
    "wof:placetype":"venue"
},
  "geometry": {"coordinates":[5.6392202377,50.5586051941],"type":"Point"}
}