{
  "type": "Feature",
  "properties": {
    "addr:full":"Vierde Lansierslaan 24 Tienen Vlaams-Brabant 3300",
    "addr:housenumber":"24",
    "addr:postcode":"3300",
    "addr:street":"Vierde Lansierslaan",
    "iso:country":"BE",
    "sg:address":"Vierde Lansierslaan 24",
    "sg:city":"Tienen",
    "sg:orig_category":"Notaires",
    "sg:phone":"+32 16 81 13 09",
    "sg:postcode":"3300",
    "sg:province":"Vlaams-Brabant",
    "wof:name":"G. Maquoi",
    "wof:placetype":"venue"
},
  "geometry": {"coordinates":[4.9290618896,50.8091087341],"type":"Point"}
}