{
  "type": "Feature",
  "properties": {
    "addr:full":"Grand-place 41ba Bertrix Luxembourg 6880",
    "addr:housenumber":"41ba",
    "addr:postcode":"6880",
    "addr:street":"Grand-Place",
    "iso:country":"BE",
    "sg:address":"Grand-place 41ba",
    "sg:city":"Bertrix",
    "sg:orig_category":"Peinture",
    "sg:phone":"+32 61 41 40 85",
    "sg:postcode":"6880",
    "sg:province":"Luxembourg",
    "wof:name":"Peint Deco Jean Houard",
    "wof:placetype":"venue"
},
  "geometry": {"coordinates":[5.2535948753,49.8544845581],"type":"Point"}
}