{
  "type": "Feature",
  "properties": {
    "iso:country":"BE",
    "sg:address":"Rue De Heps\u00c9e 10",
    "sg:city":"Verlaine",
    "sg:orig_category":"Eleveurs and marchands de porcs. Eleveurs de bovins",
    "sg:phone":"+32 4 259 53 78",
    "sg:postcode":"4537",
    "sg:province":"Li\u00e8ge",
    "wof:name":"Theodore Evrard",
    "wof:placetype":"venue"
},
  "geometry": {"coordinates":[5.3291478157,50.5970726013],"type":"Point"}
}