{
  "type": "Feature",
  "properties": {
    "iso:country":"BE",
    "sg:address":"Rue De L\u00b4ep\u00c9e 4",
    "sg:city":"Brussel/bruxelles",
    "sg:classifiers":[
        {
            "category":"Restaurant",
            "type":"Food & Drink"
        }
    ],
    "sg:phone":"+32 2 502 12 24",
    "sg:postcode":"1000",
    "sg:province":"Bruxelles-Capitale",
    "wof:name":"Restaurant Havana",
    "wof:placetype":"venue"
},
  "geometry": {"coordinates":[4.3505067825,50.838558197],"type":"Point"}
}