{
  "type": "Feature",
  "properties": {
    "iso:country":"BE",
    "sg:address":"Honzebroekstraat 44",
    "sg:city":"Roeselare",
    "sg:orig_category":"Enseignement maternel and primaire",
    "sg:phone":"+32 51 20 61 76",
    "sg:postcode":"8800",
    "sg:province":"West-Vlaanderen",
    "wof:name":"Vrije Basisschool",
    "wof:placetype":"venue"
},
  "geometry": {"coordinates":[3.1155569553,50.9602279663],"type":"Point"}
}