{
  "type": "Feature",
  "properties": {
    "addr:full":"Chauss\u00e9e De Lille 204 Mouscron Hainaut 7700",
    "addr:housenumber":"204",
    "addr:postcode":"7700",
    "addr:street":"Chausse\u0301E De Lille",
    "iso:country":"BE",
    "sg:address":"Chauss\u00e9e De Lille 204",
    "sg:city":"Mouscron",
    "sg:classifiers":[
        {
            "category":"Real Estate",
            "subcategory":"Real Estate Services",
            "type":"Services"
        }
    ],
    "sg:phone":"+32 56 84 67 41",
    "sg:postcode":"7700",
    "sg:province":"Hainaut",
    "wof:name":"Bureau Rondaert Sprl",
    "wof:placetype":"venue"
},
  "geometry": {"coordinates":[3.1871659756,50.7522888184],"type":"Point"}
}