{
  "type": "Feature",
  "properties": {
    "addr:full":"Duindoorngalerij 11 Bruxelles (woluwe-saint-lambert) Bruxelles-Capitale 1200",
    "addr:housenumber":"11",
    "addr:postcode":"1200",
    "addr:street":"Duindoorngalerij",
    "iso:country":"BE",
    "sg:address":"Duindoorngalerij 11",
    "sg:city":"Bruxelles (woluwe-saint-lambert)",
    "sg:classifiers":[
        {
            "category":"Bars & Pubs",
            "type":"Food & Drink"
        }
    ],
    "sg:phone":"+32 2 770 19 13",
    "sg:postcode":"1200",
    "sg:province":"Bruxelles-Capitale",
    "sg:tags":[
        "tavern"
    ],
    "wof:name":"R\u00e9verb\u00e8re (le)",
    "wof:placetype":"venue"
},
  "geometry": {"coordinates":[4.4510750771,50.850151062],"type":"Point"}
}