{
  "type": "Feature",
  "properties": {
    "iso:country":"BE",
    "sg:address":"Place Du Vieux March\u00e9 27",
    "sg:city":"Enghien",
    "sg:classifiers":[
        {
            "category":"Insurance",
            "subcategory":"Insurance Agent",
            "type":"Services"
        }
    ],
    "sg:phone":"+32 2 395 45 98",
    "sg:postcode":"7850",
    "sg:province":"Hainaut",
    "sg:tags":[
        "broker"
    ],
    "wof:name":"S.n.c.i. Sa",
    "wof:placetype":"venue"
},
  "geometry": {"coordinates":[4.0439257622,50.6950416565],"type":"Point"}
}