{
  "type": "Feature",
  "properties": {
    "iso:country":"BE",
    "sg:address":"119",
    "sg:city":"Kaulillerweg 3990 Peer",
    "sg:classifiers":[
        {
            "category":"Manufacturing",
            "subcategory":"Textiles",
            "type":"Manufacturing & Wholesale Goods"
        }
    ],
    "sg:phone":"+32 11 61 06 10",
    "sg:postcode":"119",
    "sg:tags":[
        "clothing",
        "accessory"
    ],
    "wof:name":"Spindor International Nv",
    "wof:placetype":"venue"
},
  "geometry": {"coordinates":[5.5107412338,51.1616287231],"type":"Point"}
}