{
  "type": "Feature",
  "properties": {
    "addr:full":"Route De Bouillon 222 Arlon Luxembourg 6700",
    "addr:housenumber":"222",
    "addr:postcode":"6700",
    "addr:street":"Route De Bouillon",
    "iso:country":"BE",
    "sg:address":"Route De Bouillon 222",
    "sg:city":"Arlon",
    "sg:classifiers":[
        {
            "category":"Farming",
            "subcategory":"Fish & Marine Products",
            "type":"Manufacturing & Wholesale Goods"
        }
    ],
    "sg:phone":"+32 69 54 86 17",
    "sg:postcode":"6700",
    "sg:province":"Luxembourg",
    "sg:tags":[
        "asphalt"
    ],
    "wof:name":"Enromac-sobelter S.a.",
    "wof:placetype":"venue"
},
  "geometry": {"coordinates":[3.4895250797,50.5959129333],"type":"Point"}
}