{
  "type": "Feature",
  "properties": {
    "addr:full":"Antwerpsesteenweg 430 Gent (sint-amandsberg) Oost-Vlaanderen 9040",
    "addr:housenumber":"430",
    "addr:postcode":"9040",
    "addr:street":"Antwerpsesteenweg",
    "iso:country":"BE",
    "sg:address":"Antwerpsesteenweg 430",
    "sg:city":"Gent (sint-amandsberg)",
    "sg:classifiers":[
        {
            "category":"Health Services",
            "subcategory":"Health Practitioner",
            "type":"Services"
        }
    ],
    "sg:phone":"+32 9 228 26 61",
    "sg:postcode":"9040",
    "sg:province":"Oost-Vlaanderen",
    "sg:tags":[
        "physiotherapist"
    ],
    "wof:name":"De Waele M",
    "wof:placetype":"venue"
},
  "geometry": {"coordinates":[3.7507350445,51.0628166199],"type":"Point"}
}