{
  "type": "Feature",
  "properties": {
    "iso:country":"BE",
    "sg:address":"Rue D\u00b4aulnois 28",
    "sg:city":"Blaregnies",
    "sg:orig_category":"Bouwmaterialen Gh Gespecialiseerde residenti\u00eble bouw SMEEDWERK, METAALBEWERKING AND POEDERMETALLURGI",
    "sg:phone":"+32 65 56 96 64",
    "sg:postcode":"7040",
    "sg:province":"Hainaut",
    "wof:name":"Bati Reno Chem.",
    "wof:placetype":"venue"
},
  "geometry": {"coordinates":[3.8968470097,50.352355957],"type":"Point"}
}