{
  "type": "Feature",
  "properties": {
    "iso:country":"BE",
    "sg:address":"Gentse Steenweg 142",
    "sg:city":"Zele",
    "sg:orig_category":"Agences d'exp\u00e9dition",
    "sg:phone":"+32 52 44 55 79",
    "sg:postcode":"9240",
    "sg:province":"Oost-Vlaanderen",
    "wof:name":"Ait Tex",
    "wof:placetype":"venue"
},
  "geometry": {"coordinates":[4.0195131302,51.0592193604],"type":"Point"}
}