{
  "type": "Feature",
  "properties": {
    "addr:full":"Dutselstraat 123 Holsbeek Vlaams-Brabant 3220",
    "addr:housenumber":"123",
    "addr:postcode":"3220",
    "addr:street":"Dutselstraat",
    "iso:country":"BE",
    "sg:address":"Dutselstraat 123",
    "sg:city":"Holsbeek",
    "sg:orig_category":"Reclamebureaus",
    "sg:phone":"+32 16 62 29 30",
    "sg:postcode":"3220",
    "sg:province":"Vlaams-Brabant",
    "wof:name":"Rene Boeckx",
    "wof:placetype":"venue"
},
  "geometry": {"coordinates":[4.7799768448,50.9204368591],"type":"Point"}
}