{
  "type": "Feature",
  "properties": {
    "addr:full":"Oosteinde 9 Lochristi Oost-Vlaanderen 9080",
    "addr:housenumber":"9",
    "addr:postcode":"9080",
    "addr:street":"Oosteinde",
    "iso:country":"BE",
    "sg:address":"Oosteinde 9",
    "sg:city":"Lochristi",
    "sg:orig_category":"Maatschappelijke dienstverlening",
    "sg:phone":"+32 9 355 52 24",
    "sg:postcode":"9080",
    "sg:province":"Oost-Vlaanderen",
    "wof:name":"Rode Kruis Lochristi-beervelde",
    "wof:placetype":"venue"
},
  "geometry": {"coordinates":[3.8651130199,51.1335144043],"type":"Point"}
}