{
  "type": "Feature",
  "properties": {
    "iso:country":"BE",
    "sg:address":"Oostendestraat 85",
    "sg:city":"Torhout",
    "sg:orig_category":"Opticiens",
    "sg:phone":"+32 50 21 45 19",
    "sg:postcode":"8820",
    "sg:province":"West-Vlaanderen",
    "wof:name":"Filip Meulemeester",
    "wof:placetype":"venue"
},
  "geometry": {"coordinates":[3.0959529877,51.0666465759],"type":"Point"}
}