{
  "type": "Feature",
  "properties": {
    "addr:full":"Leuvense Steenweg 106 Sint-joost-ten-node/saint-josse-ten-noode Bruxelles-Capitale 1210",
    "addr:housenumber":"106",
    "addr:postcode":"1210",
    "addr:street":"Leuvense Steenweg;Sint-Joost-Ten-Node /",
    "iso:country":"BE",
    "sg:address":"Leuvense Steenweg 106",
    "sg:city":"Sint-joost-ten-node/saint-josse-ten-noode",
    "sg:orig_category":"Slagers",
    "sg:phone":"+32 2 230 38 92",
    "sg:postcode":"1210",
    "sg:province":"Bruxelles-Capitale",
    "wof:name":"Boucherie Jean Ghysels",
    "wof:placetype":"venue"
},
  "geometry": {"coordinates":[4.3703098297,50.8534507751],"type":"Point"}
}