{
  "type": "Feature",
  "properties": {
    "addr:full":"Varkensmarkt 1 Diepenbeek Limburg 3590",
    "addr:housenumber":"1",
    "addr:postcode":"3590",
    "addr:street":"Varkensmarkt",
    "iso:country":"BE",
    "sg:address":"Varkensmarkt 1",
    "sg:city":"Diepenbeek",
    "sg:classifiers":[
        {
            "category":"Building & Trades",
            "subcategory":"Construction",
            "type":"Services"
        }
    ],
    "sg:phone":"+32 11 35 14 90",
    "sg:postcode":"3590",
    "sg:province":"Limburg",
    "sg:tags":[
        "surveyor",
        "-"
    ],
    "wof:name":"Hechtermans Bouw- En Studiebureau",
    "wof:placetype":"venue"
},
  "geometry": {"coordinates":[5.4198651314,50.9087333679],"type":"Point"}
}