{
  "type": "Feature",
  "properties": {
    "addr:full":"Kampenhoutsebaan 117 Zemst Vlaams-Brabant 1982",
    "addr:housenumber":"117",
    "addr:postcode":"1982",
    "addr:street":"Kampenhoutsebaan;Vlaams-Brabant",
    "iso:country":"BE",
    "sg:address":"Kampenhoutsebaan 117",
    "sg:city":"Zemst",
    "sg:orig_category":"Groententeelt",
    "sg:phone":"+32 16 65 09 28",
    "sg:postcode":"1982",
    "sg:province":"Vlaams-Brabant",
    "wof:name":"Marc Beullens",
    "wof:placetype":"venue"
},
  "geometry": {"coordinates":[4.51897192,50.9635620117],"type":"Point"}
}