{
  "type": "Feature",
  "properties": {
    "addr:full":"Grendelbaan 32 Diepenbeek Limburg 3590",
    "addr:housenumber":"32",
    "addr:postcode":"3590",
    "addr:street":"Grendelbaan",
    "iso:country":"BE",
    "sg:address":"Grendelbaan 32",
    "sg:city":"Diepenbeek",
    "sg:classifiers":[
        {
            "category":"Personal",
            "type":"Services"
        }
    ],
    "sg:phone":"+32 11 33 15 35",
    "sg:postcode":"3590",
    "sg:province":"Limburg",
    "sg:tags":[
        "party",
        "planning"
    ],
    "wof:name":"De Baenwinning",
    "wof:placetype":"venue"
},
  "geometry": {"coordinates":[5.4334220886,50.9045562744],"type":"Point"}
}