{
  "type": "Feature",
  "properties": {
    "addr:full":"Herentalse Steenweg 79 Herenthout Antwerpen 2270",
    "addr:housenumber":"79",
    "addr:postcode":"2270",
    "addr:street":"Herentalse Steenweg",
    "iso:country":"BE",
    "sg:address":"Herentalse Steenweg 79",
    "sg:city":"Herenthout",
    "sg:classifiers":[
        {
            "category":"Autos & Motor Vehicles",
            "subcategory":"Fuel & Gas Station",
            "type":"Retail Goods"
        }
    ],
    "sg:phone":"+32 14 51 50 63",
    "sg:postcode":"2270",
    "sg:province":"Antwerpen",
    "wof:name":"Verwimp R",
    "wof:placetype":"venue"
},
  "geometry": {"coordinates":[4.7891411781,51.1471290588],"type":"Point"}
}