{
  "type": "Feature",
  "properties": {
    "addr:full":"Nevelestraat 61 Aalter Oost-Vlaanderen 9880",
    "addr:housenumber":"61",
    "addr:postcode":"9880",
    "addr:street":"Nevelestraat",
    "iso:country":"BE",
    "sg:address":"Nevelestraat 61",
    "sg:city":"Aalter",
    "sg:orig_category":"Woningbouw",
    "sg:phone":"+32 9 371 75 66",
    "sg:postcode":"9880",
    "sg:province":"Oost-Vlaanderen",
    "wof:name":"Rogge",
    "wof:placetype":"venue"
},
  "geometry": {"coordinates":[3.4763669968,51.0450172424],"type":"Point"}
}