{
  "type": "Feature",
  "properties": {
    "iso:country":"BE",
    "sg:address":"Rue De Vaucelles 48",
    "sg:city":"Viroinval (maz\u00e9e)",
    "sg:classifiers":[
        {
            "category":"Health Services",
            "subcategory":"Doctor",
            "type":"Services"
        }
    ],
    "sg:phone":"+32 60 39 05 69",
    "sg:postcode":"5670",
    "sg:province":"Namur",
    "sg:tags":[
        "medicinephysicians",
        "surgeon"
    ],
    "wof:name":"Claes Giovanni",
    "wof:placetype":"venue"
},
  "geometry": {"coordinates":[4.7078418732,50.1035957336],"type":"Point"}
}