{
  "type": "Feature",
  "properties": {
    "addr:full":"Elfnovemberstraat 3 Gent (mariakerke) Oost-Vlaanderen 9030",
    "addr:housenumber":"3",
    "addr:postcode":"9030",
    "addr:street":"Elfnovemberstraat",
    "iso:country":"BE",
    "sg:address":"Elfnovemberstraat 3",
    "sg:city":"Gent (mariakerke)",
    "sg:orig_category":"Solariums",
    "sg:phone":"+32 9 227 91 21",
    "sg:postcode":"9030",
    "sg:province":"Oost-Vlaanderen",
    "wof:name":"Body Line",
    "wof:placetype":"venue"
},
  "geometry": {"coordinates":[3.6795580387,51.0721817017],"type":"Point"}
}