{
  "type": "Feature",
  "properties": {
    "iso:country":"BE",
    "sg:address":"Bld Edmond Machtens 147",
    "sg:city":"Sint-jans-molenbeek/molenbeek-saint-jean",
    "sg:orig_category":"Rev\u00eatements pour sols and murs. Installation de menuiserie en bois and plastique. Peinture",
    "sg:phone":"+32 2 410 58 08",
    "sg:postcode":"1080",
    "sg:province":"Bruxelles-Capitale",
    "wof:name":"Select Bois",
    "wof:placetype":"venue"
},
  "geometry": {"coordinates":[4.3033628464,50.8510551453],"type":"Point"}
}