{
  "type": "Feature",
  "properties": {
    "addr:full":"Avenue De Marlagne 206 Namur Namur 5000",
    "addr:housenumber":"206",
    "addr:postcode":"5000",
    "addr:street":"Avenue De Marlagne",
    "iso:country":"BE",
    "sg:address":"Avenue De Marlagne 206",
    "sg:city":"Namur",
    "sg:classifiers":[
        {
            "category":"Real Estate",
            "subcategory":"Architect",
            "type":"Services"
        }
    ],
    "sg:phone":"+32 81 73 71 65",
    "sg:postcode":"5000",
    "sg:province":"Namur",
    "wof:name":"Vermeren Ph",
    "wof:placetype":"venue"
},
  "geometry": {"coordinates":[4.8405079842,50.4515571594],"type":"Point"}
}