{
  "type": "Feature",
  "properties": {
    "addr:full":"Hauwaart 35 Oudenaarde Oost-Vlaanderen 9700",
    "addr:housenumber":"35",
    "addr:postcode":"9700",
    "addr:street":"Hauwaart",
    "iso:country":"BE",
    "sg:address":"Hauwaart 35",
    "sg:city":"Oudenaarde",
    "sg:orig_category":"Articles de camping and de sport. Installation de menuiserie en bois and plastique. Meubles D\u00e9tailla",
    "sg:phone":"+32 55 45 56 62",
    "sg:postcode":"9700",
    "sg:province":"Oost-Vlaanderen",
    "wof:name":"M. Beekman",
    "wof:placetype":"venue"
},
  "geometry": {"coordinates":[3.6598439217,50.831161499],"type":"Point"}
}