{
  "type": "Feature",
  "properties": {
    "addr:full":"Rue De Trazegnies 49 Courcelles Hainaut 6180",
    "addr:housenumber":"49",
    "addr:postcode":"6180",
    "addr:street":"Rue De Trazegnies",
    "iso:country":"BE",
    "sg:address":"Rue De Trazegnies 49",
    "sg:city":"Courcelles",
    "sg:orig_category":"Deurwaarders",
    "sg:phone":"+32 71 45 19 72",
    "sg:postcode":"6180",
    "sg:province":"Hainaut",
    "wof:name":"Jean-pol Rassart",
    "wof:placetype":"venue"
},
  "geometry": {"coordinates":[4.3604369164,50.4611587524],"type":"Point"}
}