{
  "type": "Feature",
  "properties": {
    "addr:full":"Dorpsstraat 162 Overpelt Limburg 3900",
    "addr:housenumber":"162",
    "addr:postcode":"3900",
    "addr:street":"Dorpsstraat",
    "iso:country":"BE",
    "sg:address":"Dorpsstraat 162",
    "sg:city":"Overpelt",
    "sg:classifiers":[
        {
            "category":"Restaurant",
            "type":"Food & Drink"
        }
    ],
    "sg:phone":"+32 11 64 12 00",
    "sg:postcode":"3900",
    "sg:province":"Limburg",
    "sg:tags":[
        "lamp",
        "hotels"
    ],
    "wof:name":"Wittke Design",
    "wof:placetype":"venue"
},
  "geometry": {"coordinates":[5.4214110374,51.2103729248],"type":"Point"}
}