{
  "type": "Feature",
  "properties": {
    "addr:full":"Place De La Ste.-famille 1 Sint-lambrechts-woluwe/woluwe-saint-lambert Bruxelles-Capitale 1200",
    "addr:housenumber":"1",
    "addr:postcode":"1200",
    "addr:street":"Place De La Ste.-Famille",
    "iso:country":"BE",
    "sg:address":"Place De La Ste.-famille 1",
    "sg:city":"Sint-lambrechts-woluwe/woluwe-saint-lambert",
    "sg:orig_category":"Enseignement maternel and primaire",
    "sg:phone":"+32 2 761 29 00",
    "sg:postcode":"1200",
    "sg:province":"Bruxelles-Capitale",
    "wof:name":"Gemeentelijke Basisschool",
    "wof:placetype":"venue"
},
  "geometry": {"coordinates":[4.4267802238,50.8497695923],"type":"Point"}
}