{
  "type": "Feature",
  "properties": {
    "addr:full":"Place Louis Delhaize 15 Charleroi (ransart) Hainaut 6043",
    "addr:housenumber":"15",
    "addr:postcode":"6043",
    "addr:street":"Place Louis Delhaize",
    "iso:country":"BE",
    "sg:address":"Place Louis Delhaize 15",
    "sg:city":"Charleroi (ransart)",
    "sg:classifiers":[
        {
            "category":"Restaurant",
            "type":"Food & Drink"
        }
    ],
    "sg:phone":"+32 71 35 44 18",
    "sg:postcode":"6043",
    "sg:province":"Hainaut",
    "wof:name":"Il Trulletto",
    "wof:placetype":"venue"
},
  "geometry": {"coordinates":[4.4839549065,50.4479637146],"type":"Point"}
}