{
  "type": "Feature",
  "properties": {
    "iso:country":"BE",
    "sg:address":"Kartuizersstraat 43",
    "sg:city":"Oud-heverlee",
    "sg:orig_category":"Herstelling leer and schoeisel",
    "sg:phone":"+32 16 40 23 28",
    "sg:postcode":"3052",
    "sg:province":"Vlaams-Brabant",
    "wof:name":"Edgard Gahy",
    "wof:placetype":"venue"
},
  "geometry": {"coordinates":[4.718670845,50.8235397339],"type":"Point"}
}