{
  "type": "Feature",
  "properties": {
    "addr:full":"Driesstraat 54 Avelgem West-Vlaanderen 8580",
    "addr:housenumber":"54",
    "addr:postcode":"8580",
    "addr:street":"Driesstraat",
    "iso:country":"BE",
    "sg:address":"Driesstraat 54",
    "sg:city":"Avelgem",
    "sg:classifiers":[
        {
            "category":"Retail",
            "subcategory":"Auto Repair",
            "type":"Services"
        }
    ],
    "sg:phone":"+32 56 64 40 26",
    "sg:postcode":"8580",
    "sg:province":"West-Vlaanderen",
    "sg:tags":[
        "garage"
    ],
    "wof:name":"Wolfvelde Garage",
    "wof:placetype":"venue"
},
  "geometry": {"coordinates":[3.4384679794,50.7792549133],"type":"Point"}
}