{
  "type": "Feature",
  "properties": {
    "iso:country":"BE",
    "sg:address":"Rue De La Roche 6",
    "sg:city":"Mons",
    "sg:orig_category":"Schoonheidssalons",
    "sg:phone":"+32 65 58 68 03",
    "sg:postcode":"7022",
    "sg:province":"Hainaut",
    "wof:name":"Jacqueline Dessale",
    "wof:placetype":"venue"
},
  "geometry": {"coordinates":[3.9892361164,50.3938789368],"type":"Point"}
}