{
  "type": "Feature",
  "properties": {
    "iso:country":"BE",
    "sg:address":"Asterstraat 1",
    "sg:city":"Lovendegem",
    "sg:orig_category":"Brood, gebak and snoepgoed",
    "sg:phone":"+32 9 372 59 75",
    "sg:postcode":"9920",
    "sg:province":"Oost-Vlaanderen",
    "wof:name":"Bakkerij De Dapper",
    "wof:placetype":"venue"
},
  "geometry": {"coordinates":[3.63539505,51.1055717468],"type":"Point"}
}