{
  "type": "Feature",
  "properties": {
    "iso:country":"BE",
    "sg:address":"Markt 11",
    "sg:city":"Sint-katelijne-waver",
    "sg:classifiers":[
        {
            "category":"Building & Trades",
            "subcategory":"Locksmith",
            "type":"Services"
        }
    ],
    "sg:phone":"+32 15 31 06 56",
    "sg:postcode":"2860",
    "sg:province":"Antwerpen",
    "sg:tags":[
        "lock",
        "key"
    ],
    "wof:name":"Algemene Slotenmakerij Wim",
    "wof:placetype":"venue"
},
  "geometry": {"coordinates":[4.5314469337,51.0698547363],"type":"Point"}
}