{
  "type": "Feature",
  "properties": {
    "addr:full":"Rue Du Centre 9 Couvin Namur 5660",
    "addr:housenumber":"9",
    "addr:postcode":"5660",
    "addr:street":"Rue Du Centre",
    "iso:country":"BE",
    "sg:address":"Rue Du Centre 9",
    "sg:city":"Couvin",
    "sg:orig_category":"Kapsalons",
    "sg:phone":"+32 60 34 72 47",
    "sg:postcode":"5660",
    "sg:province":"Namur",
    "wof:name":"Studio Nathalie",
    "wof:placetype":"venue"
},
  "geometry": {"coordinates":[4.4200348854,50.0248260498],"type":"Point"}
}