{
  "type": "Feature",
  "properties": {
    "addr:full":"Bellekouterlaan 18 Wichelen Oost-Vlaanderen 9260",
    "addr:housenumber":"18",
    "addr:postcode":"9260",
    "addr:street":"Bellekouterlaan",
    "iso:country":"BE",
    "sg:address":"Bellekouterlaan 18",
    "sg:city":"Wichelen",
    "sg:orig_category":"Installation \u00e9lectrique r\u00e9sidentielle",
    "sg:phone":"+32 9 366 18 42",
    "sg:postcode":"9260",
    "sg:province":"Oost-Vlaanderen",
    "wof:name":"Kris Bontinck",
    "wof:placetype":"venue"
},
  "geometry": {"coordinates":[3.9743049145,51.0067749023],"type":"Point"}
}