{
  "type": "Feature",
  "properties": {
    "addr:full":"Dr\u00c8ve Des Alli\u00c9s 81 Thuin Hainaut 6530",
    "addr:housenumber":"81",
    "addr:postcode":"6530",
    "addr:street":"Dre\u0300Ve Des Allie\u0301S",
    "iso:country":"BE",
    "sg:address":"Dr\u00c8ve Des Alli\u00c9s 81",
    "sg:city":"Thuin",
    "sg:orig_category":"Eclairage et \u00e9quipements du foyer. Peinture. Rev\u00eatements pour sols and murs",
    "sg:phone":"+32 71 59 18 57",
    "sg:postcode":"6530",
    "sg:province":"Hainaut",
    "wof:name":"Dr\u00c8ve Decor",
    "wof:placetype":"venue"
},
  "geometry": {"coordinates":[4.3045401573,50.3389663696],"type":"Point"}
}