{
  "type": "Feature",
  "properties": {
    "addr:full":"Rue Profondrieux 32 Ecaussinnes Hainaut 7190",
    "addr:housenumber":"32",
    "addr:postcode":"7190",
    "addr:street":"Rue Profondrieux;Hainaut",
    "iso:country":"BE",
    "sg:address":"Rue Profondrieux 32",
    "sg:city":"Ecaussinnes",
    "sg:orig_category":"Non-foodwinkels",
    "sg:phone":"+32 67 44 34 49",
    "sg:postcode":"7190",
    "sg:province":"Hainaut",
    "wof:name":"Jean-louis Romain",
    "wof:placetype":"venue"
},
  "geometry": {"coordinates":[4.1328701973,50.5659828186],"type":"Point"}
}