{
  "type": "Feature",
  "properties": {
    "addr:full":"Antoon Catriestraat 34 Gent (drongen) Oost-Vlaanderen 9031",
    "addr:housenumber":"34",
    "addr:postcode":"9031",
    "addr:street":"Antoon Catriestraat",
    "iso:country":"BE",
    "sg:address":"Antoon Catriestraat 34",
    "sg:city":"Gent (drongen)",
    "sg:classifiers":[
        {
            "category":"Professional",
            "subcategory":"Art Services",
            "type":"Services"
        }
    ],
    "sg:phone":"+32 9 232 28 88",
    "sg:postcode":"9031",
    "sg:province":"Oost-Vlaanderen",
    "sg:tags":[
        "photographer"
    ],
    "wof:name":"Artifix",
    "wof:placetype":"venue"
},
  "geometry": {"coordinates":[3.6513929367,51.054107666],"type":"Point"}
}