{
  "type": "Feature",
  "properties": {
    "iso:country":"BE",
    "sg:address":"Bankstraat 99",
    "sg:city":"Mechelen",
    "sg:orig_category":"Slagers",
    "sg:phone":"+32 15 41 38 84",
    "sg:postcode":"2811",
    "sg:province":"Antwerpen",
    "wof:name":"Jan Slachmuylders",
    "wof:placetype":"venue"
},
  "geometry": {"coordinates":[4.436975956,51.0126266479],"type":"Point"}
}