{
  "type": "Feature",
  "properties": {
    "iso:country":"BE",
    "sg:address":"Rue Du Gros Ch\u00cane 35",
    "sg:city":"Eghezee",
    "sg:orig_category":"Diverse grafische activiteiten",
    "sg:phone":"+32 81 65 83 94",
    "sg:postcode":"5310",
    "sg:province":"Namur",
    "wof:name":"Tapage Graphic",
    "wof:placetype":"venue"
},
  "geometry": {"coordinates":[4.8224449158,50.5821418762],"type":"Point"}
}