{
  "type": "Feature",
  "properties": {
    "iso:country":"BE",
    "sg:address":"Nachtegaalstraat 3",
    "sg:city":"Vosselaar",
    "sg:orig_category":"Zuivelproducten",
    "sg:phone":"+32 14 41 14 26",
    "sg:postcode":"2350",
    "sg:province":"Antwerpen",
    "wof:name":"Patrick Sas",
    "wof:placetype":"venue"
},
  "geometry": {"coordinates":[4.9056119919,51.303352356],"type":"Point"}
}