{
  "type": "Feature",
  "properties": {
    "addr:full":"Place L\u00c9opold Mons Hainaut 7000",
    "addr:postcode":"7000",
    "addr:street":"Place Le\u0301Opold;Hainaut",
    "iso:country":"BE",
    "sg:address":"Place L\u00c9opold",
    "sg:city":"Mons",
    "sg:orig_category":"Treinen and spoorwegen",
    "sg:phone":"+32 65 32 25 86",
    "sg:postcode":"7000",
    "sg:province":"Hainaut",
    "wof:name":"Gare De Mons",
    "wof:placetype":"venue"
},
  "geometry": {"coordinates":[3.9426589012,50.4537582397],"type":"Point"}
}