{
  "type": "Feature",
  "properties": {
    "addr:full":"Grand'rue 24-26 Gembloux-sur-orneau (gembloux) Namur 5030",
    "addr:postcode":"24-26;5030",
    "addr:street":"Grand'Rue",
    "iso:country":"BE",
    "sg:address":"Grand'rue 24-26",
    "sg:city":"Gembloux-sur-orneau (gembloux)",
    "sg:classifiers":[
        {
            "category":"Shopping",
            "subcategory":"Shoes",
            "type":"Retail Goods"
        }
    ],
    "sg:phone":"+32 81 61 25 90",
    "sg:postcode":"5030",
    "sg:province":"Namur",
    "sg:tags":[
        "slipper",
        "-"
    ],
    "wof:name":"Gallipette",
    "wof:placetype":"venue"
},
  "geometry": {"coordinates":[4.6945400238,50.5666313171],"type":"Point"}
}