{
  "type": "Feature",
  "properties": {
    "iso:country":"BE",
    "sg:address":"Mereldreef 7",
    "sg:city":"Herentals",
    "sg:classifiers":[
        {
            "category":"Professional",
            "subcategory":"Accounting & Tax Preparation",
            "type":"Services"
        }
    ],
    "sg:phone":"+32 14 21 26 92",
    "sg:postcode":"2200",
    "sg:province":"Antwerpen",
    "sg:tags":[
        "accountant"
    ],
    "wof:name":"Frans Smolders",
    "wof:placetype":"venue"
},
  "geometry": {"coordinates":[4.8224949837,51.1947212219],"type":"Point"}
}