{
  "type": "Feature",
  "properties": {
    "iso:country":"BE",
    "sg:address":"Hendrik Speecqvest 50",
    "sg:city":"Mechelen",
    "sg:orig_category":"Architecten",
    "sg:phone":"+32 15 41 39 01",
    "sg:postcode":"2800",
    "sg:province":"Antwerpen",
    "wof:name":"Peter Vermeulen",
    "wof:placetype":"venue"
},
  "geometry": {"coordinates":[4.4852700233,51.0209770203],"type":"Point"}
}