{
  "type": "Feature",
  "properties": {
    "iso:country":"BE",
    "sg:address":"Sint-amandsstraat 112",
    "sg:city":"Roeselare",
    "sg:orig_category":"Vakbonden",
    "sg:phone":"+32 51 20 25 70",
    "sg:postcode":"8800",
    "sg:province":"West-Vlaanderen",
    "wof:name":"A.b.v.v. West-vlaanderen",
    "wof:placetype":"venue"
},
  "geometry": {"coordinates":[3.1287610531,50.9495773315],"type":"Point"}
}