{
  "type": "Feature",
  "properties": {
    "addr:full":"Place Sommeleville 63 Verviers Li\u00e8ge 4800",
    "addr:housenumber":"63",
    "addr:postcode":"4800",
    "addr:street":"Place Sommeleville",
    "iso:country":"BE",
    "sg:address":"Place Sommeleville 63",
    "sg:city":"Verviers",
    "sg:classifiers":[
        {
            "category":"Personal",
            "subcategory":"Beauty Salon",
            "type":"Services"
        }
    ],
    "sg:phone":"+32 87 33 67 94",
    "sg:postcode":"4800",
    "sg:province":"Li\u00e8ge",
    "sg:tags":[
        "lady",
        "-",
        "hairdressing"
    ],
    "wof:name":"Christiane",
    "wof:placetype":"venue"
},
  "geometry": {"coordinates":[5.8724150658,50.5946884155],"type":"Point"}
}