{
  "type": "Feature",
  "properties": {
    "addr:full":"Vijfentwintig Augustusgalerij 24 Bruxelles Bruxelles-Capitale 1000",
    "addr:housenumber":"24",
    "addr:postcode":"1000",
    "iso:country":"BE",
    "sg:address":"Vijfentwintig Augustusgalerij 24",
    "sg:city":"Bruxelles",
    "sg:classifiers":[
        {
            "category":"Banks & Credit Unions",
            "subcategory":"Investment Brokerage",
            "type":"Services"
        }
    ],
    "sg:phone":"+32 2 219 22 02",
    "sg:postcode":"1000",
    "sg:province":"Bruxelles-Capitale",
    "sg:tags":[
        "jean",
        "casual",
        "wear"
    ],
    "wof:name":"Rivaldi I",
    "wof:placetype":"venue"
},
  "geometry": {"coordinates":[4.3483290672,50.8486366272],"type":"Point"}
}