{
  "type": "Feature",
  "properties": {
    "addr:full":"Boulevard Paul Janson 35 Charleroi Hainaut 6000",
    "addr:housenumber":"35",
    "addr:postcode":"6000",
    "addr:street":"Boulevard Paul Janson;Hainaut",
    "iso:country":"BE",
    "sg:address":"Boulevard Paul Janson 35",
    "sg:city":"Charleroi",
    "sg:classifiers":[
        {
            "category":"Organizations",
            "subcategory":"Community Association",
            "type":"Services"
        }
    ],
    "sg:phone":"+32 71 33 12 06",
    "sg:postcode":"6000",
    "sg:province":"Hainaut",
    "sg:tags":[
        "cultural"
    ],
    "wof:name":"S.i.e.p",
    "wof:placetype":"venue"
},
  "geometry": {"coordinates":[4.4470949173,50.4140129089],"type":"Point"}
}