{
  "type": "Feature",
  "properties": {
    "iso:country":"BE",
    "sg:address":"Rue De Strouvia 4",
    "sg:city":"Gesves",
    "sg:orig_category":"M\u00e9decins and sp\u00e9cialistes",
    "sg:phone":"+32 81 58 02 68",
    "sg:postcode":"5340",
    "sg:province":"Namur",
    "wof:name":"Fabien Ectors",
    "wof:placetype":"venue"
},
  "geometry": {"coordinates":[5.0189638138,50.444519043],"type":"Point"}
}