{
  "type": "Feature",
  "properties": {
    "addr:full":"Rue Du Pont De Wandre 189 Li\u00e8ge 1 (wandre) Li\u00e8ge 4020",
    "addr:housenumber":"189;1",
    "addr:postcode":"4020",
    "addr:street":"Rue Du Pont De Wandre",
    "iso:country":"BE",
    "sg:address":"Rue Du Pont De Wandre 189",
    "sg:city":"Li\u00e8ge 1 (wandre)",
    "sg:classifiers":[
        {
            "category":"Bars & Pubs",
            "type":"Food & Drink"
        }
    ],
    "sg:phone":"+32 4 362 61 91",
    "sg:postcode":"4020",
    "sg:province":"Li\u00e8ge",
    "wof:name":"Aurore (salle)",
    "wof:placetype":"venue"
},
  "geometry": {"coordinates":[5.5776939392,50.6450042725],"type":"Point"}
}