{
  "type": "Feature",
  "properties": {
    "iso:country":"BE",
    "sg:address":"Budastraat 7",
    "sg:city":"Kortrijk",
    "sg:classifiers":[
        {
            "category":"Building & Trades",
            "subcategory":"Equipment Rental",
            "type":"Services"
        }
    ],
    "sg:phone":"+32 477 93 93 65",
    "sg:postcode":"8500",
    "sg:province":"West-Vlaanderen",
    "sg:tags":[
        "sound",
        "-",
        "system"
    ],
    "wof:name":"Lsd",
    "wof:placetype":"venue"
},
  "geometry": {"coordinates":[3.2638309002,50.8300285339],"type":"Point"}
}