{
  "type": "Feature",
  "properties": {
    "iso:country":"BE",
    "sg:address":"Steenweg Op Turnhout 24",
    "sg:city":"Oud-turnhout",
    "sg:orig_category":"Advocaten and juridische adviseurs",
    "sg:phone":"+32 14 45 27 81",
    "sg:postcode":"2360",
    "sg:province":"Antwerpen",
    "wof:name":"Manu\u00cbl Huygaerts",
    "wof:placetype":"venue"
},
  "geometry": {"coordinates":[4.9797048569,51.3190612793],"type":"Point"}
}