{
  "type": "Feature",
  "properties": {
    "iso:country":"BE",
    "sg:address":"Rue Du Village 40",
    "sg:city":"Ohey",
    "sg:orig_category":"Sportclubs",
    "sg:phone":"+32 85 61 19 10",
    "sg:postcode":"5352",
    "sg:province":"Namur",
    "wof:name":"J.c. Condruzien",
    "wof:placetype":"venue"
},
  "geometry": {"coordinates":[5.1741771698,50.453212738],"type":"Point"}
}