{
  "type": "Feature",
  "properties": {
    "addr:full":"Lantaarnpad 6 Herentals Antwerpen 2200",
    "addr:housenumber":"6",
    "addr:postcode":"2200",
    "addr:street":"Lantaarnpad",
    "iso:country":"BE",
    "sg:address":"Lantaarnpad 6",
    "sg:city":"Herentals",
    "sg:classifiers":[
        {
            "category":"Shopping",
            "subcategory":"Photographic Equipment",
            "type":"Retail Goods"
        }
    ],
    "sg:phone":"+32 14 22 15 80",
    "sg:postcode":"2200",
    "sg:province":"Antwerpen",
    "sg:tags":[
        "whol",
        "-",
        "mfg&",
        "accessory"
    ],
    "wof:name":"Euro Lowie Bvba",
    "wof:placetype":"venue"
},
  "geometry": {"coordinates":[4.837220192,51.1759490967],"type":"Point"}
}