{
  "type": "Feature",
  "properties": {
    "addr:full":"Nassaustraat 15 Antwerpen Antwerpen 2000",
    "addr:housenumber":"15",
    "addr:postcode":"2000",
    "addr:street":"Nassaustraat",
    "iso:country":"BE",
    "sg:address":"Nassaustraat 15",
    "sg:city":"Antwerpen",
    "sg:classifiers":[
        {
            "category":"Professional",
            "subcategory":"Employment Agencies",
            "type":"Services"
        }
    ],
    "sg:phone":"+32 3 226 75 05",
    "sg:postcode":"2000",
    "sg:province":"Antwerpen",
    "sg:tags":[
        "shipping"
    ],
    "wof:name":"Ods Orient",
    "wof:placetype":"venue"
},
  "geometry": {"coordinates":[4.4056677818,51.2306022644],"type":"Point"}
}