{
  "type": "Feature",
  "properties": {
    "addr:full":"Avenue De La Vecqu\u00e9e 18b Neupr\u00e9 (neuville-en-condroz) Li\u00e8ge 4121",
    "addr:housenumber":"18b",
    "addr:postcode":"4121",
    "addr:street":"Avenue De La Vecque\u0301E",
    "iso:country":"BE",
    "sg:address":"Avenue De La Vecqu\u00e9e 18b",
    "sg:city":"Neupr\u00e9 (neuville-en-condroz)",
    "sg:classifiers":[
        {
            "category":"Arena",
            "subcategory":"Sports Club",
            "type":"Entertainment"
        }
    ],
    "sg:phone":"+32 4 371 22 22",
    "sg:postcode":"4121",
    "sg:province":"Li\u00e8ge",
    "wof:name":"Judo Neupr\u00e9 Wallonie",
    "wof:placetype":"venue"
},
  "geometry": {"coordinates":[5.4902977943,50.5470085144],"type":"Point"}
}