{
  "type": "Feature",
  "properties": {
    "iso:country":"BE",
    "sg:address":"Walvisstraat 44",
    "sg:city":"Antwerpen",
    "sg:classifiers":[
        {
            "category":"Real Estate",
            "subcategory":"Architect",
            "type":"Services"
        }
    ],
    "sg:phone":"+32 3 235 70 70",
    "sg:postcode":"2018",
    "sg:province":"Antwerpen",
    "wof:name":"Depuydt D",
    "wof:placetype":"venue"
},
  "geometry": {"coordinates":[4.4315662384,51.2079315186],"type":"Point"}
}