{
  "type": "Feature",
  "properties": {
    "iso:country":"BE",
    "sg:address":"Rue Mitoyenne 178",
    "sg:city":"Frameries",
    "sg:classifiers":[
        {
            "category":"Personal",
            "subcategory":"Beauty Salon",
            "type":"Services"
        }
    ],
    "sg:phone":"+32 65 67 45 74",
    "sg:postcode":"7080",
    "sg:province":"Hainaut",
    "sg:tags":[
        "de",
        "coiffure"
    ],
    "wof:name":"Coiffure Art & Beaut\u00c9",
    "wof:placetype":"venue"
},
  "geometry": {"coordinates":[3.8627889156,50.3886260986],"type":"Point"}
}