{
  "type": "Feature",
  "properties": {
    "iso:country":"BE",
    "sg:address":"Rue Des Olympiades 2",
    "sg:city":"Charleroi",
    "sg:orig_category":"Sportclubs",
    "sg:phone":"+32 71 33 08 13",
    "sg:postcode":"6000",
    "sg:province":"Hainaut",
    "wof:name":"La Coupole",
    "wof:placetype":"venue"
},
  "geometry": {"coordinates":[4.4471688271,50.424282074],"type":"Point"}
}