{
  "type": "Feature",
  "properties": {
    "iso:country":"BE",
    "sg:address":"Goei\u00efngen 20",
    "sg:city":"Evergem",
    "sg:classifiers":[
        {
            "category":"Home & Garden",
            "subcategory":"Garden Supply",
            "type":"Retail Goods"
        }
    ],
    "sg:phone":"+32 9 357 24 57",
    "sg:postcode":"9940",
    "sg:province":"Oost-Vlaanderen",
    "wof:name":"Bauwens P",
    "wof:placetype":"venue"
},
  "geometry": {"coordinates":[3.708024025,51.1333351135],"type":"Point"}
}