{
  "type": "Feature",
  "properties": {
    "iso:country":"BE",
    "sg:address":"Leuvensesteenweg 98",
    "sg:city":"Tervuren",
    "sg:orig_category":"Mat\u00e9riel de T\u00e9l\u00e9communication. Electrom\u00e9nager, t\u00e9l\u00e9visions and radios. R\u00e9parations d'appareils \u00e9lect",
    "sg:phone":"+32 2 768 13 14",
    "sg:postcode":"3080",
    "sg:province":"Vlaams-Brabant",
    "wof:name":"Sterckx Hifi Concept",
    "wof:placetype":"venue"
},
  "geometry": {"coordinates":[4.537498951,50.8366508484],"type":"Point"}
}