{
  "type": "Feature",
  "properties": {
    "addr:full":"Vosselaredorp 41 Nevele (vosselare) Oost-Vlaanderen 9850",
    "addr:housenumber":"41",
    "addr:postcode":"9850",
    "addr:street":"Vosselaredorp",
    "iso:country":"BE",
    "sg:address":"Vosselaredorp 41",
    "sg:city":"Nevele (vosselare)",
    "sg:orig_category":"Non-Classified Establishments",
    "sg:phone":"+32 9 371 52 06",
    "sg:postcode":"9850",
    "sg:province":"Oost-Vlaanderen",
    "wof:name":"Verhelle R",
    "wof:placetype":"venue"
},
  "geometry": {"coordinates":[3.5554358959,51.0268096924],"type":"Point"}
}