{
  "type": "Feature",
  "properties": {
    "addr:full":"Rue De La Station 27 Gembloux-sur-orneau (beuzet) Namur 5030",
    "addr:housenumber":"27",
    "addr:postcode":"5030",
    "addr:street":"Rue De La Station;Namur",
    "iso:country":"BE",
    "sg:address":"Rue De La Station 27",
    "sg:city":"Gembloux-sur-orneau (beuzet)",
    "sg:classifiers":[
        {
            "category":"Health Services",
            "subcategory":"Health Practitioner",
            "type":"Services"
        }
    ],
    "sg:phone":"+32 81 56 85 48",
    "sg:postcode":"5030",
    "sg:province":"Namur",
    "sg:tags":[
        "physiotherapist"
    ],
    "wof:name":"Belche B",
    "wof:placetype":"venue"
},
  "geometry": {"coordinates":[4.7443118095,50.5336685181],"type":"Point"}
}