{
  "type": "Feature",
  "properties": {
    "iso:country":"BE",
    "sg:address":"Opitterkiezel 45",
    "sg:city":"Bree",
    "sg:orig_category":"Antiek Herstelling and restauratie van meubelen Installatie van houten of kunststof schrijnwerk",
    "sg:phone":"+32 89 46 16 24",
    "sg:postcode":"3960",
    "sg:province":"Limburg",
    "wof:name":"Huis Vandewal",
    "wof:placetype":"venue"
},
  "geometry": {"coordinates":[5.6103057861,51.1359024048],"type":"Point"}
}