{
  "type": "Feature",
  "properties": {
    "addr:full":"Avenue De La Wallonie 127 Leuze-en-hainaut Hainaut 7900",
    "addr:housenumber":"127",
    "addr:postcode":"7900",
    "addr:street":"Avenue De La Wallonie",
    "iso:country":"BE",
    "sg:address":"Avenue De La Wallonie 127",
    "sg:city":"Leuze-en-hainaut",
    "sg:orig_category":"Rookartikelen",
    "sg:phone":"+32 69 66 63 57",
    "sg:postcode":"7900",
    "sg:province":"Hainaut",
    "wof:name":"Tabacs Leon Baelen",
    "wof:placetype":"venue"
},
  "geometry": {"coordinates":[3.6326498985,50.5834655762],"type":"Point"}
}