{
  "type": "Feature",
  "properties": {
    "addr:full":"Tentoonstellingslaan 113 Gent Oost-Vlaanderen 9000",
    "addr:housenumber":"113",
    "addr:postcode":"9000",
    "addr:street":"Tentoonstellingslaan;Oost-Vlaanderen",
    "iso:country":"BE",
    "sg:address":"Tentoonstellingslaan 113",
    "sg:city":"Gent",
    "sg:classifiers":[
        {
            "category":"Professional",
            "type":"Services"
        }
    ],
    "sg:phone":"+32 9 225 68 87",
    "sg:postcode":"9000",
    "sg:province":"Oost-Vlaanderen",
    "sg:tags":[
        "surveyor",
        "-",
        "valuer"
    ],
    "wof:name":"De Neef P",
    "wof:placetype":"venue"
},
  "geometry": {"coordinates":[3.7330040932,51.0403137207],"type":"Point"}
}