{
  "type": "Feature",
  "properties": {
    "iso:country":"BE",
    "sg:address":"Chauss\u00c9e Du Roeulx 218",
    "sg:city":"Mons",
    "sg:orig_category":"Services de Nettoyage and de D\u00e9sinfection",
    "sg:phone":"+32 65 84 71 88",
    "sg:postcode":"7000",
    "sg:province":"Hainaut",
    "wof:name":"Home Maintenance",
    "wof:placetype":"venue"
},
  "geometry": {"coordinates":[3.9766609669,50.4567298889],"type":"Point"}
}