{
  "type": "Feature",
  "properties": {
    "iso:country":"BE",
    "sg:address":"Rue Gaie 23ba",
    "sg:city":"Sombreffe",
    "sg:orig_category":"Electrom\u00e9nager, t\u00e9l\u00e9visions and radios",
    "sg:phone":"+32 71 88 95 01",
    "sg:postcode":"5140",
    "sg:province":"Namur",
    "wof:name":"Maison Potier",
    "wof:placetype":"venue"
},
  "geometry": {"coordinates":[4.5730371475,50.5169792175],"type":"Point"}
}