{
  "type": "Feature",
  "properties": {
    "iso:country":"BE",
    "sg:address":"Zavelstraat 44",
    "sg:city":"Diepenbeek",
    "sg:orig_category":"Rev\u00eatements de sols and murs. Mat\u00e9riaux de construction Gr",
    "sg:phone":"+32 11 32 34 87",
    "sg:postcode":"3590",
    "sg:province":"Limburg",
    "wof:name":"Hova",
    "wof:placetype":"venue"
},
  "geometry": {"coordinates":[5.4125728607,50.8956756592],"type":"Point"}
}