{
  "type": "Feature",
  "properties": {
    "addr:full":"Rue Du March\u00e9 Aux Herbes 79 Bruxelles Bruxelles-Capitale 1000",
    "addr:housenumber":"79",
    "addr:postcode":"1000",
    "addr:street":"Rue Du Marche\u0301 Aux Herbes",
    "iso:country":"BE",
    "sg:address":"Rue Du March\u00e9 Aux Herbes 79",
    "sg:city":"Bruxelles",
    "sg:classifiers":[
        {
            "category":"Travel",
            "subcategory":"Travel Agent",
            "type":"Entertainment"
        }
    ],
    "sg:phone":"+32 2 502 89 59",
    "sg:postcode":"1000",
    "sg:province":"Bruxelles-Capitale",
    "sg:tags":[
        "agency"
    ],
    "wof:name":"Anglo Encounter",
    "wof:placetype":"venue"
},
  "geometry": {"coordinates":[4.3538341522,50.8469581604],"type":"Point"}
}