{
  "type": "Feature",
  "properties": {
    "addr:full":"Place Des Alli\u00c9s 8 Mons Hainaut 7000",
    "addr:housenumber":"8",
    "addr:postcode":"7000",
    "addr:street":"Place Des Allie\u0301S;Hainaut",
    "iso:country":"BE",
    "sg:address":"Place Des Alli\u00c9s 8",
    "sg:city":"Mons",
    "sg:orig_category":"Installation de serres, double vitrage and fen\u00eatres",
    "sg:phone":"+32 65 35 23 99",
    "sg:postcode":"7000",
    "sg:province":"Hainaut",
    "wof:name":"Miroiteries Montoises",
    "wof:placetype":"venue"
},
  "geometry": {"coordinates":[3.938270092,50.4493598938],"type":"Point"}
}