{
  "type": "Feature",
  "properties": {
    "addr:full":"Bredabaan 196 Wuustwezel Antwerpen 2990",
    "addr:housenumber":"196",
    "addr:postcode":"2990",
    "addr:street":"Bredabaan",
    "iso:country":"BE",
    "sg:address":"Bredabaan 196",
    "sg:city":"Wuustwezel",
    "sg:orig_category":"Sportclubs",
    "sg:phone":"+32 3 669 77 31",
    "sg:postcode":"2990",
    "sg:province":"Antwerpen",
    "wof:name":"B.c. Teletronika",
    "wof:placetype":"venue"
},
  "geometry": {"coordinates":[4.6038799286,51.4000701904],"type":"Point"}
}