{
  "type": "Feature",
  "properties": {
    "iso:country":"BE",
    "sg:address":"Rue Neuve 8",
    "sg:city":"Villers-le-bouillet",
    "sg:orig_category":"Enseignement maternel and primaire",
    "sg:phone":"+32 85 21 26 05",
    "sg:postcode":"4530",
    "sg:province":"Li\u00e8ge",
    "wof:name":"E.f.l. St.martin",
    "wof:placetype":"venue"
},
  "geometry": {"coordinates":[5.2674589157,50.5651397705],"type":"Point"}
}