{
  "type": "Feature",
  "properties": {
    "iso:country":"BE",
    "sg:address":"Rue De La Sablonni\u00e8re 98",
    "sg:city":"Seraing (ougr\u00e9e)",
    "sg:classifiers":[
        {
            "category":"Personal",
            "subcategory":"Beauty Salon",
            "type":"Services"
        }
    ],
    "sg:phone":"+32 4 337 86 86",
    "sg:postcode":"4102",
    "sg:province":"Li\u00e8ge",
    "wof:name":"Christine",
    "wof:placetype":"venue"
},
  "geometry": {"coordinates":[5.5353288651,50.5956535339],"type":"Point"}
}