{
  "type": "Feature",
  "properties": {
    "iso:country":"BE",
    "sg:address":"Gasthuisstraat 15",
    "sg:city":"Meerhout",
    "sg:classifiers":[
        {
            "category":"Insurance",
            "subcategory":"Insurance Agent",
            "type":"Services"
        }
    ],
    "sg:phone":"+32 14 30 33 12",
    "sg:postcode":"2450",
    "sg:province":"Antwerpen",
    "sg:tags":[
        "verzekeringsmakelaars",
        "expert"
    ],
    "wof:name":"Verzekeringen Assubel",
    "wof:placetype":"venue"
},
  "geometry": {"coordinates":[5.0779027939,51.1337928772],"type":"Point"}
}