{
  "type": "Feature",
  "properties": {
    "addr:full":"Stationsstraat Gavere (asper) Oost-Vlaanderen 9890",
    "addr:postcode":"9890",
    "addr:street":"Stationsstraat",
    "iso:country":"BE",
    "sg:address":"Stationsstraat",
    "sg:city":"Gavere (asper)",
    "sg:classifiers":[
        {
            "category":"Fast Food",
            "type":"Food & Drink"
        }
    ],
    "sg:phone":"+32 9 384 92 77",
    "sg:postcode":"9890",
    "sg:province":"Oost-Vlaanderen",
    "sg:tags":[
        "fried",
        "stand",
        "potato"
    ],
    "wof:name":"Smulkotje",
    "wof:placetype":"venue"
},
  "geometry": {"coordinates":[3.6481599808,50.9293518066],"type":"Point"}
}