{
  "type": "Feature",
  "properties": {
    "addr:full":"Chemin Du Bois D'horrues 16 Seneffe Hainaut 7181",
    "addr:housenumber":"16",
    "addr:postcode":"7181",
    "addr:street":"Chemin Du Bois D'Horrues",
    "iso:country":"BE",
    "sg:address":"Chemin Du Bois D'horrues 16",
    "sg:city":"Seneffe",
    "sg:orig_category":"Eleveurs de bovins",
    "sg:phone":"+32 67 87 79 73",
    "sg:postcode":"7181",
    "sg:province":"Hainaut",
    "wof:name":"Yvan Flament",
    "wof:placetype":"venue"
},
  "geometry": {"coordinates":[4.23751688,50.5755767822],"type":"Point"}
}