{
  "type": "Feature",
  "properties": {
    "addr:full":"Avenue Des Sorbiers 1 Moeskroen/mouscron Hainaut 7711",
    "addr:housenumber":"1",
    "addr:postcode":"7711",
    "addr:street":"Avenue Des Sorbiers",
    "iso:country":"BE",
    "sg:address":"Avenue Des Sorbiers 1",
    "sg:city":"Moeskroen/mouscron",
    "sg:classifiers":[
        {
            "category":"Autos & Motor Vehicles",
            "subcategory":"Fuel & Gas Station",
            "type":"Retail Goods"
        }
    ],
    "sg:phone":"+32 56 48 79 07",
    "sg:postcode":"7711",
    "sg:province":"Hainaut",
    "sg:tags":[
        "stations-service",
        "carburants"
    ],
    "wof:name":"Willy Huyse",
    "wof:placetype":"venue"
},
  "geometry": {"coordinates":[3.2647418976,50.7371444702],"type":"Point"}
}