{
  "type": "Feature",
  "properties": {
    "addr:full":"Heilig Hartlaan 44 Aalst Oost-Vlaanderen 9300",
    "addr:housenumber":"44",
    "addr:postcode":"9300",
    "addr:street":"Hartlaan",
    "iso:country":"BE",
    "sg:address":"Heilig Hartlaan 44",
    "sg:city":"Aalst",
    "sg:orig_category":"Location de logements sociaux",
    "sg:phone":"+32 53 77 15 18",
    "sg:postcode":"9300",
    "sg:province":"Oost-Vlaanderen",
    "wof:name":"Veilig Wonen",
    "wof:placetype":"venue"
},
  "geometry": {"coordinates":[4.0416350365,50.9493370056],"type":"Point"}
}