{
  "type": "Feature",
  "properties": {
    "addr:full":"Petrus Van Der Jeugdlaan 10 Hamme Oost-Vlaanderen 9220",
    "addr:housenumber":"10",
    "addr:postcode":"9220",
    "addr:street":"Petrus Van Der Jeugdlaan",
    "iso:country":"BE",
    "sg:address":"Petrus Van Der Jeugdlaan 10",
    "sg:city":"Hamme",
    "sg:classifiers":[
        {
            "category":"Arts & Performance",
            "subcategory":"Art Gallery",
            "type":"Entertainment"
        }
    ],
    "sg:phone":"+32 52 38 04 25",
    "sg:postcode":"9220",
    "sg:province":"Oost-Vlaanderen",
    "wof:name":"Van Neygen E",
    "wof:placetype":"venue"
},
  "geometry": {"coordinates":[4.1556501389,51.0892562866],"type":"Point"}
}