{
  "type": "Feature",
  "properties": {
    "iso:country":"BE",
    "sg:address":"Malmedyer Strasse 22d",
    "sg:city":"Sankt Vith",
    "sg:classifiers":[
        {
            "category":"Home & Garden",
            "subcategory":"Home Furnishings",
            "type":"Retail Goods"
        }
    ],
    "sg:phone":"+32 80 22 73 55",
    "sg:postcode":"4780",
    "sg:province":"Li\u00e8ge",
    "sg:tags":[
        "interior",
        "decoration"
    ],
    "wof:name":"D\u00e9cor Center",
    "wof:placetype":"venue"
},
  "geometry": {"coordinates":[6.1233568192,50.2836914062],"type":"Point"}
}