{
  "type": "Feature",
  "properties": {
    "addr:full":"Trienenkantlaan 16 Westerlo (tongerlo) Antwerpen 2260",
    "addr:housenumber":"16",
    "addr:postcode":"2260",
    "addr:street":"Trienenkantlaan",
    "iso:country":"BE",
    "sg:address":"Trienenkantlaan 16",
    "sg:city":"Westerlo (tongerlo)",
    "sg:classifiers":[
        {
            "category":"Professional",
            "subcategory":"Art Services",
            "type":"Services"
        }
    ],
    "sg:phone":"+32 14 23 42 34",
    "sg:postcode":"2260",
    "sg:province":"Antwerpen",
    "sg:tags":[
        "photographer"
    ],
    "wof:name":"Studio Styling",
    "wof:placetype":"venue"
},
  "geometry": {"coordinates":[4.9037208557,51.1252708435],"type":"Point"}
}