{
  "type": "Feature",
  "properties": {
    "iso:country":"BE",
    "sg:address":"Rue Du Moulin 2",
    "sg:city":"Beaumont",
    "sg:orig_category":"Tuinen",
    "sg:phone":"+32 71 53 43 93",
    "sg:postcode":"6511",
    "sg:province":"Hainaut",
    "wof:name":"Jardinvert",
    "wof:placetype":"venue"
},
  "geometry": {"coordinates":[4.3070192337,50.275226593],"type":"Point"}
}