{
  "type": "Feature",
  "properties": {
    "iso:country":"BE",
    "sg:address":"7",
    "sg:city":"Bell-telephonelaan 2440 Geel",
    "sg:classifiers":[
        {
            "category":"Autos & Motor Vehicles",
            "subcategory":"Automobile Sales",
            "type":"Retail Goods"
        }
    ],
    "sg:phone":"+32 14 59 10 45",
    "sg:postcode":"7",
    "sg:tags":[
        "equipment",
        "industrial",
        "transport"
    ],
    "wof:name":"Garage De Laak Nv",
    "wof:placetype":"venue"
},
  "geometry": {"coordinates":[4.9509439468,51.1259307861],"type":"Point"}
}