{
  "type": "Feature",
  "properties": {
    "addr:full":"Stationstraat 20 Kapellen Antwerpen 2950",
    "addr:housenumber":"20",
    "addr:postcode":"2950",
    "addr:street":"Stationstraat",
    "iso:country":"BE",
    "sg:address":"Stationstraat 20",
    "sg:city":"Kapellen",
    "sg:orig_category":"Speelgoed",
    "sg:phone":"+32 3 664 36 77",
    "sg:postcode":"2950",
    "sg:province":"Antwerpen",
    "wof:name":"Tuf-tuf",
    "wof:placetype":"venue"
},
  "geometry": {"coordinates":[4.4307808876,51.3143882751],"type":"Point"}
}