{
  "type": "Feature",
  "properties": {
    "iso:country":"BE",
    "sg:address":"Merellaan 17",
    "sg:city":"Scherpenheuvel-zichem (scherpenheuvel)",
    "sg:classifiers":[
        {
            "category":"Shopping",
            "subcategory":"Clothing, Apparel, & Fashions",
            "type":"Retail Goods"
        }
    ],
    "sg:phone":"+32 13 78 20 87",
    "sg:postcode":"3270",
    "sg:province":"Vlaams-Brabant",
    "sg:tags":[
        "sportswear"
    ],
    "wof:name":"Mercurius Sport Nv",
    "wof:placetype":"venue"
},
  "geometry": {"coordinates":[4.960955143,50.9690895081],"type":"Point"}
}