{
  "type": "Feature",
  "properties": {
    "addr:full":"Rue De La Croy\u00c8re 54 Manage Hainaut 7170",
    "addr:housenumber":"54",
    "addr:postcode":"7170",
    "addr:street":"Rue De La Croye\u0300Re",
    "iso:country":"BE",
    "sg:address":"Rue De La Croy\u00c8re 54",
    "sg:city":"Manage",
    "sg:classifiers":[
        {
            "category":"Insurance",
            "subcategory":"Life Insurance",
            "type":"Services"
        }
    ],
    "sg:phone":"+32 64 55 46 63",
    "sg:postcode":"7170",
    "sg:province":"Hainaut",
    "sg:tags":[
        "assurance"
    ],
    "wof:name":"J. Jacob",
    "wof:placetype":"venue"
},
  "geometry": {"coordinates":[4.2229881287,50.4912605286],"type":"Point"}
}