{
  "type": "Feature",
  "properties": {
    "addr:full":"Rogier 2 Chimay Hainaut 6460",
    "addr:housenumber":"2",
    "addr:postcode":"6460",
    "addr:street":"Rogier",
    "iso:country":"BE",
    "sg:address":"Rogier 2",
    "sg:city":"Chimay",
    "sg:orig_category":"Antiek Lingerie and ondergoed",
    "sg:phone":"+32 60 21 10 40",
    "sg:postcode":"6460",
    "sg:province":"Hainaut",
    "wof:name":"Le Jardin Belle Epoque",
    "wof:placetype":"venue"
},
  "geometry": {"coordinates":[4.316467762,50.0492362976],"type":"Point"}
}