{
  "type": "Feature",
  "properties": {
    "iso:country":"BE",
    "sg:address":"R. Eglise-saint-philippe 14ba",
    "sg:city":"Philippeville",
    "sg:orig_category":"Sportclubs",
    "sg:phone":"+32 71 66 68 56",
    "sg:postcode":"5600",
    "sg:province":"Namur",
    "wof:name":"Tennis Club Philippeville",
    "wof:placetype":"venue"
},
  "geometry": {"coordinates":[4.5478649139,50.1955490112],"type":"Point"}
}