{
  "type": "Feature",
  "properties": {
    "addr:full":"Middaglijnstraat 70 Sint-joost-ten-node/saint-josse-ten-noode Bruxelles-Capitale 1210",
    "addr:housenumber":"70",
    "addr:postcode":"1210",
    "addr:street":"Middaglijnstraat",
    "iso:country":"BE",
    "sg:address":"Middaglijnstraat 70",
    "sg:city":"Sint-joost-ten-node/saint-josse-ten-noode",
    "sg:orig_category":"Postkantoren Verzekeringsmakelaars and experts",
    "sg:phone":"+32 2 217 53 57",
    "sg:postcode":"1210",
    "sg:province":"Bruxelles-Capitale",
    "wof:name":"De Post",
    "wof:placetype":"venue"
},
  "geometry": {"coordinates":[4.3690748215,50.8553276062],"type":"Point"}
}