{
  "type": "Feature",
  "properties": {
    "addr:full":"Avenue Bourgaux 41 Ottignies-louvain-la-neuve Brabant Wallon 1342",
    "addr:housenumber":"41",
    "addr:postcode":"1342",
    "addr:street":"Avenue Bourgaux",
    "iso:country":"BE",
    "sg:address":"Avenue Bourgaux 41",
    "sg:city":"Ottignies-louvain-la-neuve",
    "sg:orig_category":"Schoonmaakbedrijven and ongediertebestrijding",
    "sg:phone":"+32 10 41 97 57",
    "sg:postcode":"1342",
    "sg:province":"Brabant Wallon",
    "wof:name":"Multiclean",
    "wof:placetype":"venue"
},
  "geometry": {"coordinates":[4.5707659721,50.6777534485],"type":"Point"}
}