{
  "type": "Feature",
  "properties": {
    "iso:country":"BE",
    "sg:address":"Brusselsesteenweg 347",
    "sg:city":"Asse",
    "sg:orig_category":"Editeurs de journaux. Editeurs de revues and p\u00e9riodiques. Imprimeries and copyshops",
    "sg:phone":"+32 2 454 22 11",
    "sg:postcode":"1730",
    "sg:province":"Vlaams-Brabant",
    "wof:name":"De Persgroep",
    "wof:placetype":"venue"
},
  "geometry": {"coordinates":[4.2377400398,50.8961982727],"type":"Point"}
}