{
  "type": "Feature",
  "properties": {
    "addr:full":"Chauss\u00e9e D'hondzocht 13 Tubize Brabant Wallon 1480",
    "addr:housenumber":"13",
    "addr:postcode":"1480",
    "addr:street":"Chausse\u0301E D'Hondzocht;Wallon",
    "iso:country":"BE",
    "sg:address":"Chauss\u00e9e D'hondzocht 13",
    "sg:city":"Tubize",
    "sg:classifiers":[
        {
            "category":"Home & Garden",
            "subcategory":"Building Materials",
            "type":"Retail Goods"
        }
    ],
    "sg:phone":"+32 2 355 54 44",
    "sg:postcode":"1480",
    "sg:province":"Brabant Wallon",
    "sg:tags":[
        "window"
    ],
    "wof:name":"Renobai Sprl",
    "wof:placetype":"venue"
},
  "geometry": {"coordinates":[4.2036452293,50.6963577271],"type":"Point"}
}