{
  "type": "Feature",
  "properties": {
    "addr:full":"Rue Van Elewyck 35 Bruxelles (ixelles) Bruxelles-Capitale 1050",
    "addr:housenumber":"35",
    "addr:postcode":"1050",
    "addr:street":"Rue Van Elewyck",
    "iso:country":"BE",
    "sg:address":"Rue Van Elewyck 35",
    "sg:city":"Bruxelles (ixelles)",
    "sg:classifiers":[
        {
            "category":"Professional",
            "subcategory":"Engineering",
            "type":"Services"
        }
    ],
    "sg:phone":"+32 2 644 96 69",
    "sg:postcode":"1050",
    "sg:province":"Bruxelles-Capitale",
    "sg:tags":[
        "environmental",
        "technique",
        "-"
    ],
    "wof:name":"Eco Conseil",
    "wof:placetype":"venue"
},
  "geometry": {"coordinates":[4.3692178726,50.8282203674],"type":"Point"}
}