{
  "type": "Feature",
  "properties": {
    "addr:full":"Rue G\u00e9n\u00e9ral Leman 53 Bruxelles (etterbeek) Bruxelles-Capitale 1040",
    "addr:housenumber":"53",
    "addr:postcode":"1040",
    "addr:street":"Rue Ge\u0301Ne\u0301Ral Leman",
    "iso:country":"BE",
    "sg:address":"Rue G\u00e9n\u00e9ral Leman 53",
    "sg:city":"Bruxelles (etterbeek)",
    "sg:classifiers":[
        {
            "category":"Banks & Credit Unions",
            "subcategory":"Investment Brokerage",
            "type":"Services"
        }
    ],
    "sg:phone":"+32 2 646 88 17",
    "sg:postcode":"1040",
    "sg:province":"Bruxelles-Capitale",
    "sg:tags":[
        "printing",
        "-"
    ],
    "wof:name":"Idesprint Sprl",
    "wof:placetype":"venue"
},
  "geometry": {"coordinates":[4.3845720291,50.8365821838],"type":"Point"}
}