{
  "type": "Feature",
  "properties": {
    "addr:full":"Chauss\u00c9e Brunehault 69 Beloeil (groot) Hainaut 7972",
    "addr:housenumber":"69",
    "addr:postcode":"7972",
    "addr:street":"Chausse\u0301E Brunehault;Groot Hainaut",
    "iso:country":"BE",
    "sg:address":"Chauss\u00c9e Brunehault 69",
    "sg:city":"Beloeil (groot)",
    "sg:orig_category":"Kapsalons",
    "sg:phone":"+32 69 68 90 95",
    "sg:postcode":"7972",
    "sg:province":"Hainaut",
    "wof:name":"Coiffure Lucie",
    "wof:placetype":"venue"
},
  "geometry": {"coordinates":[3.69018507,50.5533065796],"type":"Point"}
}