{
  "type": "Feature",
  "properties": {
    "addr:full":"Vloeiherkstraat 27a Wellen Limburg 3830",
    "addr:housenumber":"27a",
    "addr:postcode":"3830",
    "addr:street":"Vloeiherkstraat",
    "iso:country":"BE",
    "sg:address":"Vloeiherkstraat 27a",
    "sg:city":"Wellen",
    "sg:classifiers":[
        {
            "category":"Banks & Credit Unions",
            "subcategory":"Investment Brokerage",
            "type":"Services"
        }
    ],
    "sg:phone":"+32 12 74 14 95",
    "sg:postcode":"3830",
    "sg:province":"Limburg",
    "sg:tags":[
        "printing",
        "-"
    ],
    "wof:name":"Noelanders",
    "wof:placetype":"venue"
},
  "geometry": {"coordinates":[5.3365459442,50.8449668884],"type":"Point"}
}