{
  "type": "Feature",
  "properties": {
    "iso:country":"BE",
    "sg:address":"81",
    "sg:city":"Rue De Rocroi 6464 Chimay",
    "sg:classifiers":[
        {
            "category":"Professional",
            "subcategory":"Engineering",
            "type":"Services"
        }
    ],
    "sg:phone":"+32 60 21 12 77",
    "sg:postcode":"81",
    "sg:tags":[
        "machine",
        "-",
        "mechanical"
    ],
    "wof:name":"Scierie Daniel Degive Sa",
    "wof:placetype":"venue"
},
  "geometry": {"coordinates":[4.3713898659,50.030128479],"type":"Point"}
}