{
  "type": "Feature",
  "properties": {
    "addr:full":"Rue Chasseurs Ardennais 16 Vielsalm Luxembourg 6690",
    "addr:housenumber":"16",
    "addr:postcode":"6690",
    "addr:street":"Rue Chasseurs Ardennais",
    "iso:country":"BE",
    "sg:address":"Rue Chasseurs Ardennais 16",
    "sg:city":"Vielsalm",
    "sg:orig_category":"Enseignement maternel and primaire",
    "sg:phone":"+32 80 21 48 23",
    "sg:postcode":"6690",
    "sg:province":"Luxembourg",
    "wof:name":"Ecole Fond. Communale",
    "wof:placetype":"venue"
},
  "geometry": {"coordinates":[5.9065051079,50.2878570557],"type":"Point"}
}