{
  "type": "Feature",
  "properties": {
    "addr:full":"Zonnebeekseweg 395 Ieper West-Vlaanderen 8900",
    "addr:housenumber":"395",
    "addr:postcode":"8900",
    "iso:country":"BE",
    "sg:address":"Zonnebeekseweg 395",
    "sg:city":"Ieper",
    "sg:classifiers":[
        {
            "category":"Home & Garden",
            "subcategory":"Garden Supply",
            "type":"Retail Goods"
        }
    ],
    "sg:phone":"+32 57 20 08 62",
    "sg:postcode":"8900",
    "sg:province":"West-Vlaanderen",
    "wof:name":"Florawest",
    "wof:placetype":"venue"
},
  "geometry": {"coordinates":[2.9295759201,50.8643531799],"type":"Point"}
}