{
  "type": "Feature",
  "properties": {
    "iso:country":"BE",
    "sg:address":"Camille Fran\u00c7oisstraat 99b2",
    "sg:city":"Machelen",
    "sg:orig_category":"Electrom\u00e9nager, t\u00e9l\u00e9visions and radios. Syst\u00e8mes de t\u00e9l\u00e9communications. R\u00e9parations d'appareils \u00e9lec",
    "sg:phone":"+32 2 251 70 48",
    "sg:postcode":"1830",
    "sg:province":"Vlaams-Brabant",
    "wof:name":"Jan Van Den Heuvel",
    "wof:placetype":"venue"
},
  "geometry": {"coordinates":[4.4429087639,50.9121437073],"type":"Point"}
}