{
  "type": "Feature",
  "properties": {
    "addr:full":"Av. De La Reine Des Pr\u00c9s 11 Brussel/bruxelles Bruxelles-Capitale 1020",
    "addr:housenumber":"11",
    "addr:postcode":"1020",
    "addr:street":"Av. De La Reine Des Pre\u0301S;/",
    "iso:country":"BE",
    "sg:address":"Av. De La Reine Des Pr\u00c9s 11",
    "sg:city":"Brussel/bruxelles",
    "sg:orig_category":"Studios photographiques",
    "sg:phone":"+32 2 241 68 00",
    "sg:postcode":"1020",
    "sg:province":"Bruxelles-Capitale",
    "wof:name":"Etienne Vander Auwera",
    "wof:placetype":"venue"
},
  "geometry": {"coordinates":[4.3725681305,50.8906440735],"type":"Point"}
}