{
  "type": "Feature",
  "properties": {
    "iso:country":"BE",
    "sg:address":"Rue Des Carrossiers 6",
    "sg:city":"Walcourt (thy-le-ch\u00e2teau)",
    "sg:classifiers":[
        {
            "category":"Shopping",
            "subcategory":"Bicycles & Sporting Goods",
            "type":"Retail Goods"
        }
    ],
    "sg:phone":"+32 71 68 55 24",
    "sg:postcode":"5651",
    "sg:province":"Namur",
    "sg:tags":[
        "-"
    ],
    "wof:name":"Cycles De La Thyria",
    "wof:placetype":"venue"
},
  "geometry": {"coordinates":[4.4262080193,50.2824401855],"type":"Point"}
}