{
  "type": "Feature",
  "properties": {
    "iso:country":"BE",
    "sg:address":"Place Louise 8",
    "sg:city":"Saint-gilles",
    "sg:orig_category":"Disneyland Parijs Reisbureaus",
    "sg:phone":"+32 2 537 00 20",
    "sg:postcode":"1060",
    "sg:province":"Bruxelles-Capitale",
    "wof:name":"Neckermann",
    "wof:placetype":"venue"
},
  "geometry": {"coordinates":[4.3551502228,50.8355064392],"type":"Point"}
}