{
  "type": "Feature",
  "properties": {
    "addr:full":"Ganzestraat 22 Ichtegem West-Vlaanderen 8480",
    "addr:housenumber":"22",
    "addr:postcode":"8480",
    "addr:street":"Ganzestraat",
    "iso:country":"BE",
    "sg:address":"Ganzestraat 22",
    "sg:city":"Ichtegem",
    "sg:orig_category":"Rundveehouders Varkenskwekers",
    "sg:phone":"+32 59 27 86 95",
    "sg:postcode":"8480",
    "sg:province":"West-Vlaanderen",
    "wof:name":"Julien Claeys",
    "wof:placetype":"venue"
},
  "geometry": {"coordinates":[2.9954500198,51.1325683594],"type":"Point"}
}