{
  "type": "Feature",
  "properties": {
    "addr:full":"Pironlaan 12 Heusden-zolder Limburg 3550",
    "addr:housenumber":"12",
    "addr:postcode":"3550",
    "addr:street":"Pironlaan",
    "iso:country":"BE",
    "sg:address":"Pironlaan 12",
    "sg:city":"Heusden-zolder",
    "sg:orig_category":"M\u00e9decins and sp\u00e9cialistes",
    "sg:phone":"+32 11 53 71 44",
    "sg:postcode":"3550",
    "sg:province":"Limburg",
    "wof:name":"P. Tielens",
    "wof:placetype":"venue"
},
  "geometry": {"coordinates":[5.3126091957,51.0238876343],"type":"Point"}
}