{
  "type": "Feature",
  "properties": {
    "iso:country":"BE",
    "sg:address":"Square De La Libert\u00e9 2",
    "sg:city":"Braine-le-comte",
    "sg:classifiers":[
        {
            "category":"Health Services",
            "subcategory":"Health Practitioner",
            "type":"Services"
        }
    ],
    "sg:phone":"+32 67 55 67 43",
    "sg:postcode":"7090",
    "sg:province":"Hainaut",
    "sg:tags":[
        "alternative",
        "therapy",
        "treatment"
    ],
    "wof:name":"F\u00e9d\u00e9ration Belge De Kin\u00e9siologie",
    "wof:placetype":"venue"
},
  "geometry": {"coordinates":[4.1474127769,50.6074028015],"type":"Point"}
}