{
  "type": "Feature",
  "properties": {
    "iso:country":"BE",
    "sg:address":"Chauss\u00c9e De Tongres 269",
    "sg:city":"Rocourt",
    "sg:orig_category":"Mobistar Centres Telecommunicatieapparaten",
    "sg:phone":"+32 4 239 25 22",
    "sg:postcode":"4000",
    "sg:province":"Li\u00e8ge",
    "wof:name":"Mobistar Center Design Diffusion",
    "wof:placetype":"venue"
},
  "geometry": {"coordinates":[5.5499567986,50.6700172424],"type":"Point"}
}