{
  "type": "Feature",
  "properties": {
    "iso:country":"BE",
    "sg:address":"Abdijstraat 38",
    "sg:city":"Hamme (moerzeke)",
    "sg:classifiers":[
        {
            "category":"Retail",
            "subcategory":"Auto Repair",
            "type":"Services"
        }
    ],
    "sg:phone":"+32 52 48 30 42",
    "sg:postcode":"9220",
    "sg:province":"Oost-Vlaanderen",
    "sg:tags":[
        "garage"
    ],
    "wof:name":"Aubroeck",
    "wof:placetype":"venue"
},
  "geometry": {"coordinates":[4.1708068848,51.0465240479],"type":"Point"}
}