{
  "type": "Feature",
  "properties": {
    "iso:country":"BE",
    "sg:address":"Grand'rue 18-20",
    "sg:city":"Gembloux",
    "sg:orig_category":"Schoenen",
    "sg:phone":"+32 81 61 39 03",
    "sg:postcode":"5030",
    "sg:province":"Namur",
    "wof:name":"Shoes In The Box",
    "wof:placetype":"venue"
},
  "geometry": {"coordinates":[4.6948981285,50.5607414246],"type":"Point"}
}