{
  "type": "Feature",
  "properties": {
    "addr:full":"Rue Des Muguets 70 Saint-nicolas Li\u00e8ge 4420",
    "addr:housenumber":"70",
    "addr:postcode":"4420",
    "addr:street":"Rue Des Muguets",
    "iso:country":"BE",
    "sg:address":"Rue Des Muguets 70",
    "sg:city":"Saint-nicolas",
    "sg:orig_category":"Artsen and specialisten",
    "sg:phone":"+32 4 252 50 88",
    "sg:postcode":"4420",
    "sg:province":"Li\u00e8ge",
    "wof:name":"Patricia Wolff",
    "wof:placetype":"venue"
},
  "geometry": {"coordinates":[5.5341382027,50.6299476624],"type":"Point"}
}