{
  "type": "Feature",
  "properties": {
    "addr:full":"Grotestraat 65 Genk Limburg 3600",
    "addr:housenumber":"65",
    "addr:postcode":"3600",
    "addr:street":"Grotestraat",
    "iso:country":"BE",
    "sg:address":"Grotestraat 65",
    "sg:city":"Genk",
    "sg:classifiers":[
        {
            "category":"Social Services",
            "type":"Services"
        }
    ],
    "sg:phone":"+32 89 62 90 20",
    "sg:postcode":"3600",
    "sg:province":"Limburg",
    "wof:name":"Nieuw Dak",
    "wof:placetype":"venue"
},
  "geometry": {"coordinates":[5.4930210114,50.9631881714],"type":"Point"}
}