{
  "type": "Feature",
  "properties": {
    "iso:country":"BE",
    "sg:address":"Aug. Van Landeghemplein 12",
    "sg:city":"Willebroek",
    "sg:orig_category":"Reisbureaus",
    "sg:phone":"+32 3 886 20 20",
    "sg:postcode":"2830",
    "sg:province":"Antwerpen",
    "wof:name":"Uniglobe Nuyenfs Reizen",
    "wof:placetype":"venue"
},
  "geometry": {"coordinates":[4.3607020378,51.0610122681],"type":"Point"}
}