{
  "type": "Feature",
  "properties": {
    "addr:full":"Rue D'arlon 14 Neufchateau Luxembourg 6840",
    "addr:housenumber":"14",
    "addr:postcode":"6840",
    "addr:street":"Rue D'Arlon",
    "iso:country":"BE",
    "sg:address":"Rue D'arlon 14",
    "sg:city":"Neufchateau",
    "sg:orig_category":"Installation \u00e9lectrique industrielle",
    "sg:phone":"+32 61 27 97 94",
    "sg:postcode":"6840",
    "sg:province":"Luxembourg",
    "wof:name":"A.f. Security",
    "wof:placetype":"venue"
},
  "geometry": {"coordinates":[5.4367198944,49.8396148682],"type":"Point"}
}