{
  "type": "Feature",
  "properties": {
    "iso:country":"BE",
    "sg:address":"Rue Rosa Luxembourg 11",
    "sg:city":"Soumagne",
    "sg:classifiers":[
        {
            "category":"Bakery",
            "type":"Food & Drink"
        }
    ],
    "sg:phone":"+32 4 377 46 01",
    "sg:postcode":"4630",
    "sg:province":"Li\u00e8ge",
    "sg:tags":[
        "confectioner",
        "baker"
    ],
    "wof:name":"Titi-m\u00e9m\u00e9 (chez)",
    "wof:placetype":"venue"
},
  "geometry": {"coordinates":[5.7484788895,50.6118202209],"type":"Point"}
}