{
  "type": "Feature",
  "properties": {
    "iso:country":"BE",
    "sg:address":"Chauss\u00c9e De Haecht 43",
    "sg:city":"Sint-joost-ten-node/saint-joss",
    "sg:orig_category":"Agences de voyages",
    "sg:phone":"+32 2 227 57 84",
    "sg:postcode":"1210",
    "sg:province":"Bruxelles-Capitale",
    "wof:name":"Agence Eole",
    "wof:placetype":"venue"
},
  "geometry": {"coordinates":[4.3683419228,50.8559417725],"type":"Point"}
}