{
  "type": "Feature",
  "properties": {
    "addr:full":"Rue Edith Cavell 238 Bruxelles (uccle) Bruxelles-Capitale 1180",
    "addr:housenumber":"238",
    "addr:postcode":"1180",
    "addr:street":"Rue Edith Cavell",
    "iso:country":"BE",
    "sg:address":"Rue Edith Cavell 238",
    "sg:city":"Bruxelles (uccle)",
    "sg:classifiers":[
        {
            "category":"Bars & Pubs",
            "type":"Food & Drink"
        }
    ],
    "sg:phone":"+32 2 372 36 92",
    "sg:postcode":"1180",
    "sg:province":"Bruxelles-Capitale",
    "wof:name":"Tee-time",
    "wof:placetype":"venue"
},
  "geometry": {"coordinates":[4.3587341309,50.8051795959],"type":"Point"}
}