{
  "type": "Feature",
  "properties": {
    "addr:full":"Hoogleedsesteenweg 39 Roeselare West-Vlaanderen 8800",
    "addr:housenumber":"39",
    "addr:postcode":"8800",
    "addr:street":"Hoogleedsesteenweg",
    "iso:country":"BE",
    "sg:address":"Hoogleedsesteenweg 39",
    "sg:city":"Roeselare",
    "sg:classifiers":[
        {
            "category":"Bakery",
            "type":"Food & Drink"
        }
    ],
    "sg:phone":"+32 51 20 36 18",
    "sg:postcode":"8800",
    "sg:province":"West-Vlaanderen",
    "sg:tags":[
        "confectioner",
        "baker"
    ],
    "wof:name":"Ceres",
    "wof:placetype":"venue"
},
  "geometry": {"coordinates":[3.1190099716,50.9518203735],"type":"Point"}
}