{
  "type": "Feature",
  "properties": {
    "iso:country":"BE",
    "sg:address":"Rue Du Prieur\u00c9 1",
    "sg:city":"Yvoir",
    "sg:orig_category":"Biblioth\u00e8ques and archives publiques",
    "sg:phone":"+32 81 41 16 62",
    "sg:postcode":"5530",
    "sg:province":"Namur",
    "wof:name":"Biblioth\u00c8que Publique",
    "wof:placetype":"venue"
},
  "geometry": {"coordinates":[4.866964817,50.3495407104],"type":"Point"}
}