{
  "type": "Feature",
  "properties": {
    "addr:full":"Rue De Floreffe 20 Floreffe (frani\u00e8re) Namur 5150",
    "addr:housenumber":"20",
    "addr:postcode":"5150",
    "addr:street":"Rue De Floreffe",
    "iso:country":"BE",
    "sg:address":"Rue De Floreffe 20",
    "sg:city":"Floreffe (frani\u00e8re)",
    "sg:classifiers":[
        {
            "category":"Health Services",
            "subcategory":"Health Practitioner",
            "type":"Services"
        }
    ],
    "sg:phone":"+32 81 44 01 19",
    "sg:postcode":"5150",
    "sg:province":"Namur",
    "sg:tags":[
        "physiotherapist"
    ],
    "wof:name":"Nijskens Anna",
    "wof:placetype":"venue"
},
  "geometry": {"coordinates":[4.7327270508,50.4369354248],"type":"Point"}
}