{
  "type": "Feature",
  "properties": {
    "addr:full":"Steenbakkersdam 2 Beerse Antwerpen 2340",
    "addr:housenumber":"2",
    "addr:postcode":"2340",
    "addr:street":"Steenbakkersdam",
    "iso:country":"BE",
    "sg:address":"Steenbakkersdam 2",
    "sg:city":"Beerse",
    "sg:classifiers":[
        {
            "category":"Home & Garden",
            "subcategory":"Building Materials",
            "type":"Retail Goods"
        }
    ],
    "sg:phone":"+32 14 61 64 06",
    "sg:postcode":"2340",
    "sg:province":"Antwerpen",
    "sg:tags":[
        "steel",
        "metal",
        "made",
        "door",
        "gate"
    ],
    "wof:name":"W. De Visscher Nv",
    "wof:placetype":"venue"
},
  "geometry": {"coordinates":[4.8628091812,51.3289909363],"type":"Point"}
}