{
  "type": "Feature",
  "properties": {
    "addr:full":"Neerpedestraat 997 Anderlecht/anderlecht Bruxelles-Capitale 1070",
    "addr:housenumber":"997",
    "addr:postcode":"1070",
    "addr:street":"Neerpedestraat",
    "iso:country":"BE",
    "sg:address":"Neerpedestraat 997",
    "sg:city":"Anderlecht/anderlecht",
    "sg:orig_category":"Groententeelt",
    "sg:phone":"+32 2 527 12 35",
    "sg:postcode":"1070",
    "sg:province":"Bruxelles-Capitale",
    "wof:name":"Daniel Devos",
    "wof:placetype":"venue"
},
  "geometry": {"coordinates":[4.2634840012,50.8279380798],"type":"Point"}
}