{
  "type": "Feature",
  "properties": {
    "addr:full":"Nieuwe Steenweg 3a Heers Limburg 3870",
    "addr:housenumber":"3a",
    "addr:postcode":"3870",
    "addr:street":"Nieuwe Steenweg",
    "iso:country":"BE",
    "sg:address":"Nieuwe Steenweg 3a",
    "sg:city":"Heers",
    "sg:classifiers":[
        {
            "category":"Health Services",
            "subcategory":"Health Practitioner",
            "type":"Services"
        }
    ],
    "sg:phone":"+32 11 48 44 09",
    "sg:postcode":"3870",
    "sg:province":"Limburg",
    "sg:tags":[
        "physiotherapist"
    ],
    "wof:name":"Kindermans S",
    "wof:placetype":"venue"
},
  "geometry": {"coordinates":[5.3001332283,50.7498970032],"type":"Point"}
}