{
  "type": "Feature",
  "properties": {
    "addr:full":"Av De La Croix Rouge 5 Bruxelles Bruxelles-Capitale 1020",
    "addr:housenumber":"5",
    "addr:postcode":"1020",
    "addr:street":"Av De La Croix Rouge",
    "iso:country":"BE",
    "sg:address":"Av De La Croix Rouge 5",
    "sg:city":"Bruxelles",
    "sg:classifiers":[
        {
            "category":"Wholesale",
            "subcategory":"Machinery & Supplies",
            "type":"Manufacturing & Wholesale Goods"
        }
    ],
    "sg:phone":"+32 2 262 23 02",
    "sg:postcode":"1020",
    "sg:province":"Bruxelles-Capitale",
    "sg:tags":[
        "equipment",
        "precision"
    ],
    "wof:name":"Safeguard Business Syst Sa",
    "wof:placetype":"venue"
},
  "geometry": {"coordinates":[4.3555941582,50.896068573],"type":"Point"}
}