{
  "type": "Feature",
  "properties": {
    "iso:country":"BE",
    "sg:address":"Ieperstraat 104",
    "sg:city":"Zonnebeke",
    "sg:orig_category":"Pain, p\u00e2tisseries and confiseries",
    "sg:phone":"+32 51 77 08 83",
    "sg:postcode":"8980",
    "sg:province":"West-Vlaanderen",
    "wof:name":"Dirk Saelen",
    "wof:placetype":"venue"
},
  "geometry": {"coordinates":[2.980453968,50.8705635071],"type":"Point"}
}