{
  "type": "Feature",
  "properties": {
    "addr:full":"Ninovestraat 102 Haaltert Oost-Vlaanderen 9450",
    "addr:housenumber":"102",
    "addr:postcode":"9450",
    "addr:street":"Ninovestraat",
    "iso:country":"BE",
    "sg:address":"Ninovestraat 102",
    "sg:city":"Haaltert",
    "sg:classifiers":[
        {
            "category":"Parking",
            "subcategory":"Lot",
            "type":"Transportation"
        }
    ],
    "sg:phone":"+32 53 83 15 93",
    "sg:postcode":"9450",
    "sg:province":"Oost-Vlaanderen",
    "sg:tags":[
        "parking-places",
        "laying-out"
    ],
    "wof:name":"Jordax",
    "wof:placetype":"venue"
},
  "geometry": {"coordinates":[4.0251579285,50.9008407593],"type":"Point"}
}