{
  "type": "Feature",
  "properties": {
    "addr:full":"Kollegestraat 19 Geel Antwerpen 2440",
    "addr:housenumber":"19",
    "addr:postcode":"2440",
    "addr:street":"Kollegestraat",
    "iso:country":"BE",
    "sg:address":"Kollegestraat 19",
    "sg:city":"Geel",
    "sg:orig_category":"Artsen and specialisten",
    "sg:phone":"+32 14 58 51 17",
    "sg:postcode":"2440",
    "sg:province":"Antwerpen",
    "wof:name":"Danielle Henderickx",
    "wof:placetype":"venue"
},
  "geometry": {"coordinates":[4.9941091537,51.1609039307],"type":"Point"}
}