{
  "type": "Feature",
  "properties": {
    "iso:country":"BE",
    "sg:address":"Rue D'ath 62",
    "sg:city":"Ronse/renaix",
    "sg:orig_category":"Cr\u00e9meries",
    "sg:phone":"+32 55 21 19 30",
    "sg:postcode":"9600",
    "sg:province":"Oost-Vlaanderen",
    "wof:name":"Jean-marie Sablain",
    "wof:placetype":"venue"
},
  "geometry": {"coordinates":[3.6049671173,50.7427024841],"type":"Point"}
}