{
  "type": "Feature",
  "properties": {
    "addr:full":"Veldenstraat 42b Putte (beerzel) Antwerpen 2580",
    "addr:housenumber":"42b",
    "addr:postcode":"2580",
    "addr:street":"Veldenstraat",
    "iso:country":"BE",
    "sg:address":"Veldenstraat 42b",
    "sg:city":"Putte (beerzel)",
    "sg:classifiers":[
        {
            "category":"Professional",
            "subcategory":"Accounting & Tax Preparation",
            "type":"Services"
        }
    ],
    "sg:phone":"+32 15 75 31 83",
    "sg:postcode":"2580",
    "sg:province":"Antwerpen",
    "sg:tags":[
        "bookkeeper"
    ],
    "wof:name":"Geens W",
    "wof:placetype":"venue"
},
  "geometry": {"coordinates":[4.6606440544,51.0568733215],"type":"Point"}
}