{
  "type": "Feature",
  "properties": {
    "addr:full":"Ouden Dendermondse Steenweg 307 Aalst Oost-Vlaanderen 9300",
    "addr:housenumber":"307",
    "addr:postcode":"9300",
    "addr:street":"Steenweg",
    "iso:country":"BE",
    "sg:address":"Ouden Dendermondse Steenweg 307",
    "sg:city":"Aalst",
    "sg:classifiers":[
        {
            "category":"Home & Garden",
            "subcategory":"Building Materials",
            "type":"Retail Goods"
        }
    ],
    "sg:phone":"+32 53 21 69 65",
    "sg:postcode":"9300",
    "sg:province":"Oost-Vlaanderen",
    "sg:tags":[
        "window"
    ],
    "wof:name":"De Meersman & Zonen Bvba",
    "wof:placetype":"venue"
},
  "geometry": {"coordinates":[4.0569400787,50.955783844],"type":"Point"}
}