{
  "type": "Feature",
  "properties": {
    "iso:country":"BE",
    "sg:address":"Stationsstraat 22",
    "sg:city":"Rotselaar",
    "sg:orig_category":"Herstelling horloges and juwelen Juwelen and horloges Opticiens",
    "sg:phone":"+32 16 44 56 80",
    "sg:postcode":"3110",
    "sg:province":"Vlaams-Brabant",
    "wof:name":"Guy Zekl",
    "wof:placetype":"venue"
},
  "geometry": {"coordinates":[4.7131018639,50.9493751526],"type":"Point"}
}