{
  "type": "Feature",
  "properties": {
    "addr:full":"Langerenstraat 17 Maaseik Limburg 3680",
    "addr:housenumber":"17",
    "addr:postcode":"3680",
    "addr:street":"Langerenstraat",
    "iso:country":"BE",
    "sg:address":"Langerenstraat 17",
    "sg:city":"Maaseik",
    "sg:classifiers":[
        {
            "category":"Arena",
            "subcategory":"Sports Club",
            "type":"Entertainment"
        }
    ],
    "sg:phone":"+32 89 86 80 24",
    "sg:postcode":"3680",
    "sg:province":"Limburg",
    "sg:tags":[
        "de"
    ],
    "wof:name":"Smash Neeroeteren T.c.",
    "wof:placetype":"venue"
},
  "geometry": {"coordinates":[5.791285038,51.0954208374],"type":"Point"}
}