{
  "type": "Feature",
  "properties": {
    "iso:country":"BE",
    "sg:address":"Lange-haagstraat 32",
    "sg:city":"Elsene/ixelles",
    "sg:classifiers":[
        {
            "category":"Travel",
            "subcategory":"Hotels & Motels",
            "type":"Entertainment"
        }
    ],
    "sg:phone":"+32 2 511 00 15",
    "sg:postcode":"1050",
    "sg:province":"Bruxelles-Capitale",
    "wof:name":"Treviso",
    "wof:placetype":"venue"
},
  "geometry": {"coordinates":[4.3615660667,50.8311080933],"type":"Point"}
}