{
  "type": "Feature",
  "properties": {
    "iso:country":"BE",
    "sg:address":"Klaverbladstraat 7",
    "sg:city":"Lummen",
    "sg:classifiers":[
        {
            "category":"Utilities",
            "subcategory":"Mobile Phone",
            "type":"Services"
        }
    ],
    "sg:phone":"+32 13 53 13 80",
    "sg:postcode":"3560",
    "sg:province":"Limburg",
    "sg:tags":[
        "ontwerp",
        "siemens",
        "fujitsu",
        "ontwikkeling",
        "software"
    ],
    "wof:name":"Project Systems",
    "wof:placetype":"venue"
},
  "geometry": {"coordinates":[5.2274580002,50.9971885681],"type":"Point"}
}