{
  "type": "Feature",
  "properties": {
    "iso:country":"BE",
    "sg:address":"Oude Fortemstraat 5",
    "sg:city":"Alveringem",
    "sg:orig_category":"Kantoormateriaal",
    "sg:phone":"+32 58 28 89 11",
    "sg:postcode":"8690",
    "sg:province":"West-Vlaanderen",
    "wof:name":"Walter Wackenier",
    "wof:placetype":"venue"
},
  "geometry": {"coordinates":[2.7121601105,51.0133743286],"type":"Point"}
}