{
  "type": "Feature",
  "properties": {
    "iso:country":"BE",
    "sg:address":"Oostmallebaan 94",
    "sg:city":"Zoersel",
    "sg:classifiers":[
        {
            "category":"Restaurant",
            "type":"Food & Drink"
        }
    ],
    "sg:phone":"+32 3 309 23 63",
    "sg:postcode":"2980",
    "sg:province":"Antwerpen",
    "wof:name":"Osaka City",
    "wof:placetype":"venue"
},
  "geometry": {"coordinates":[4.7174930573,51.2768440247],"type":"Point"}
}