{
  "type": "Feature",
  "properties": {
    "addr:full":"Holstraat 100 Evergem (ertvelde) Oost-Vlaanderen 9940",
    "addr:housenumber":"100",
    "addr:postcode":"9940",
    "addr:street":"Holstraat;Ertvelde Oost-Vlaanderen",
    "iso:country":"BE",
    "sg:address":"Holstraat 100",
    "sg:city":"Evergem (ertvelde)",
    "sg:classifiers":[
        {
            "category":"Building & Trades",
            "subcategory":"Construction",
            "type":"Services"
        }
    ],
    "sg:phone":"+32 9 344 82 73",
    "sg:postcode":"9940",
    "sg:province":"Oost-Vlaanderen",
    "sg:tags":[
        "installation",
        "-",
        "central",
        "heating"
    ],
    "wof:name":"Ross Heating",
    "wof:placetype":"venue"
},
  "geometry": {"coordinates":[3.7367880344,51.189163208],"type":"Point"}
}