{
  "type": "Feature",
  "properties": {
    "addr:full":"Bedevaartstraat 53 Tielt West-Vlaanderen 8700",
    "addr:housenumber":"53",
    "addr:postcode":"8700",
    "addr:street":"Bedevaartstraat",
    "iso:country":"BE",
    "sg:address":"Bedevaartstraat 53",
    "sg:city":"Tielt",
    "sg:classifiers":[
        {
            "category":"Manufacturing",
            "subcategory":"Tools & Machinery",
            "type":"Manufacturing & Wholesale Goods"
        }
    ],
    "sg:phone":"+32 51 40 35 60",
    "sg:postcode":"8700",
    "sg:province":"West-Vlaanderen",
    "sg:tags":[
        "diamond"
    ],
    "wof:name":"De Stalen Greep",
    "wof:placetype":"venue"
},
  "geometry": {"coordinates":[3.3327798843,50.9876670837],"type":"Point"}
}