{
  "type": "Feature",
  "properties": {
    "iso:country":"BE",
    "sg:address":"Rue Du Ch\u00e2teau De Ruyff 28",
    "sg:city":"Welkenraedt (henri-chapelle)",
    "sg:orig_category":"Non-Classified Establishments",
    "sg:phone":"+32 87 89 00 91",
    "sg:postcode":"4841",
    "sg:province":"Li\u00e8ge",
    "wof:name":"Pinckaers A",
    "wof:placetype":"venue"
},
  "geometry": {"coordinates":[5.9453101158,50.6749763489],"type":"Point"}
}