{
  "type": "Feature",
  "properties": {
    "iso:country":"BE",
    "sg:address":"Steenstraat 12",
    "sg:city":"Lede",
    "sg:orig_category":"Motos. Combustibles. V\u00e9los",
    "sg:phone":"+32 53 80 31 57",
    "sg:postcode":"9340",
    "sg:province":"Oost-Vlaanderen",
    "wof:name":"Luc De Brucker",
    "wof:placetype":"venue"
},
  "geometry": {"coordinates":[3.9996809959,50.9640960693],"type":"Point"}
}