{
  "type": "Feature",
  "properties": {
    "addr:full":"Rue De Berneau 16 Vis\u00e9 Li\u00e8ge 4600",
    "addr:housenumber":"16",
    "addr:postcode":"4600",
    "addr:street":"Rue De Berneau",
    "iso:country":"BE",
    "sg:address":"Rue De Berneau 16",
    "sg:city":"Vis\u00e9",
    "sg:classifiers":[
        {
            "category":"Education",
            "subcategory":"School",
            "type":"Public Place"
        }
    ],
    "sg:phone":"+32 4 379 76 05",
    "sg:postcode":"4600",
    "sg:province":"Li\u00e8ge",
    "sg:tags":[
        "primary"
    ],
    "wof:name":"E.e.s.p.c.f. Lieutenant Jacquemin",
    "wof:placetype":"venue"
},
  "geometry": {"coordinates":[5.7046761513,50.7367935181],"type":"Point"}
}