{
  "type": "Feature",
  "properties": {
    "addr:full":"Stationsstraat 14 Kapellen Antwerpen 2950",
    "addr:housenumber":"14",
    "addr:postcode":"2950",
    "addr:street":"Stationsstraat",
    "iso:country":"BE",
    "sg:address":"Stationsstraat 14",
    "sg:city":"Kapellen",
    "sg:classifiers":[
        {
            "category":"Shopping",
            "subcategory":"Clothing, Apparel, & Fashions",
            "type":"Retail Goods"
        }
    ],
    "sg:phone":"+32 3 664 58 84",
    "sg:postcode":"2950",
    "sg:province":"Antwerpen",
    "sg:tags":[
        "lingerie",
        "sous-v\u00eatements"
    ],
    "wof:name":"Marika",
    "wof:placetype":"venue"
},
  "geometry": {"coordinates":[4.4304838181,51.3144302368],"type":"Point"}
}