{
  "type": "Feature",
  "properties": {
    "addr:full":"Chauss\u00e9e De Bruxelles 201 Ottignies-louvain-la-neuve (c\u00e9roux-mousty) Brabant Wallon 1341",
    "addr:housenumber":"201",
    "addr:postcode":"1341",
    "addr:street":"Chausse\u0301E De Bruxelles;Wallon",
    "iso:country":"BE",
    "sg:address":"Chauss\u00e9e De Bruxelles 201",
    "sg:city":"Ottignies-louvain-la-neuve (c\u00e9roux-mousty)",
    "sg:classifiers":[
        {
            "category":"Personal",
            "subcategory":"Barber",
            "type":"Services"
        }
    ],
    "sg:phone":"+32 10 22 45 29",
    "sg:postcode":"1341",
    "sg:province":"Brabant Wallon",
    "sg:tags":[
        "gentleman",
        "salon",
        "-",
        "hairdressing"
    ],
    "wof:name":"Bernard Coiffure",
    "wof:placetype":"venue"
},
  "geometry": {"coordinates":[4.5627598763,50.6583099365],"type":"Point"}
}