{
  "type": "Feature",
  "properties": {
    "iso:country":"BE",
    "sg:address":"Rue Jean Ballegeer 69b28",
    "sg:city":"Ukkel/uccle",
    "sg:orig_category":"Location de logements sociaux",
    "sg:phone":"+32 2 374 57 36",
    "sg:postcode":"1180",
    "sg:province":"Bruxelles-Capitale",
    "wof:name":"Ukkelse Mij Huisvesting",
    "wof:placetype":"venue"
},
  "geometry": {"coordinates":[4.3406720161,50.7808227539],"type":"Point"}
}