{
  "type": "Feature",
  "properties": {
    "iso:country":"BE",
    "sg:address":"Rue Des B\u00c9guines 22",
    "sg:city":"Vise",
    "sg:orig_category":"Location de v\u00eatements, chaussures and textiles",
    "sg:phone":"+32 4 379 19 79",
    "sg:postcode":"4600",
    "sg:province":"Li\u00e8ge",
    "wof:name":"Maison Jamart",
    "wof:placetype":"venue"
},
  "geometry": {"coordinates":[5.694630146,50.7360649109],"type":"Point"}
}