{
  "type": "Feature",
  "properties": {
    "addr:full":"Boulevard Saint-michel 14 Sint-pieters-woluwe/woluwe-saint-pierre Bruxelles-Capitale 1150",
    "addr:housenumber":"14",
    "addr:postcode":"1150",
    "addr:street":"Boulevard Saint-Michel;/",
    "iso:country":"BE",
    "sg:address":"Boulevard Saint-michel 14",
    "sg:city":"Sint-pieters-woluwe/woluwe-saint-pierre",
    "sg:classifiers":[
        {
            "category":"Professional",
            "subcategory":"Business Services",
            "type":"Services"
        }
    ],
    "sg:phone":"+32 2 736 07 37",
    "sg:postcode":"1150",
    "sg:province":"Bruxelles-Capitale",
    "sg:tags":[
        "aux",
        "diver",
        "entreprises"
    ],
    "wof:name":"Bureau Next Event",
    "wof:placetype":"venue"
},
  "geometry": {"coordinates":[4.4074687958,50.8361434937],"type":"Point"}
}