{
  "type": "Feature",
  "properties": {
    "addr:full":"Oudeleeuwenrui 31 Antwerpen Antwerpen 2000",
    "addr:housenumber":"31",
    "addr:postcode":"2000",
    "addr:street":"Oudeleeuwenrui",
    "iso:country":"BE",
    "sg:address":"Oudeleeuwenrui 31",
    "sg:city":"Antwerpen",
    "sg:orig_category":"Decoratiestoffen and buitenhuistextiel Fab Kleding",
    "sg:phone":"+32 3 233 93 64",
    "sg:postcode":"2000",
    "sg:province":"Antwerpen",
    "wof:name":"Vlaggenmakerij De Wit R.",
    "wof:placetype":"venue"
},
  "geometry": {"coordinates":[4.4078798294,51.2272834778],"type":"Point"}
}