{
  "type": "Feature",
  "properties": {
    "addr:full":"Ardense Jagersstraat-gottem 27a Deinze (gottem) Oost-Vlaanderen 9800",
    "addr:housenumber":"27a",
    "addr:postcode":"9800",
    "iso:country":"BE",
    "sg:address":"Ardense Jagersstraat-gottem 27a",
    "sg:city":"Deinze (gottem)",
    "sg:classifiers":[
        {
            "category":"Building & Trades",
            "subcategory":"Pest Control",
            "type":"Services"
        }
    ],
    "sg:phone":"+32 9 386 50 77",
    "sg:postcode":"9800",
    "sg:province":"Oost-Vlaanderen",
    "sg:tags":[
        "painting",
        "contractor"
    ],
    "wof:name":"De Luycker D",
    "wof:placetype":"venue"
},
  "geometry": {"coordinates":[3.530174017,50.9863166809],"type":"Point"}
}