{
  "type": "Feature",
  "properties": {
    "iso:country":"BE",
    "sg:address":"Ezelstraat 15",
    "sg:city":"Brugge",
    "sg:orig_category":"Transports terrestres de voyageurs. Agences de voyages",
    "sg:phone":"+32 50 33 36 78",
    "sg:postcode":"8000",
    "sg:province":"West-Vlaanderen",
    "wof:name":"Albion Tours",
    "wof:placetype":"venue"
},
  "geometry": {"coordinates":[3.2199831009,51.2118415833],"type":"Point"}
}