{
  "type": "Feature",
  "properties": {
    "iso:country":"BE",
    "sg:address":"Zwingelaarstraat 7",
    "sg:city":"Kortrijk",
    "sg:orig_category":"Mat\u00e9riel de T\u00e9l\u00e9communication",
    "sg:phone":"+32 56 36 57 55",
    "sg:postcode":"8500",
    "sg:province":"West-Vlaanderen",
    "wof:name":"Cheyns",
    "wof:placetype":"venue"
},
  "geometry": {"coordinates":[3.2650549412,50.827999115],"type":"Point"}
}