{
  "type": "Feature",
  "properties": {
    "addr:full":"Rue Des Mimosas 46 Schaarbeek/schaerbeek Bruxelles-Capitale 1030",
    "addr:housenumber":"46",
    "addr:postcode":"1030",
    "addr:street":"Rue Des Mimosas",
    "iso:country":"BE",
    "sg:address":"Rue Des Mimosas 46",
    "sg:city":"Schaarbeek/schaerbeek",
    "sg:orig_category":"Architectes",
    "sg:phone":"+32 2 245 66 05",
    "sg:postcode":"1030",
    "sg:province":"Bruxelles-Capitale",
    "wof:name":"Bernard Kirsch",
    "wof:placetype":"venue"
},
  "geometry": {"coordinates":[4.3884720802,50.8638420105],"type":"Point"}
}