{
  "type": "Feature",
  "properties": {
    "iso:country":"BE",
    "sg:address":"Hogenhovestraat 34",
    "sg:city":"Tielt",
    "sg:orig_category":"Eleveurs de bovins. Eleveurs and marchands de porcs",
    "sg:phone":"+32 51 63 36 95",
    "sg:postcode":"8700",
    "sg:province":"West-Vlaanderen",
    "wof:name":"Noel De Blauwer",
    "wof:placetype":"venue"
},
  "geometry": {"coordinates":[3.4187049866,50.9872894287],"type":"Point"}
}