{
  "type": "Feature",
  "properties": {
    "addr:full":"Rue Locquenghien 41 Brussel/bruxelles Bruxelles-Capitale 1000",
    "addr:housenumber":"41",
    "addr:postcode":"1000",
    "addr:street":"Rue Locquenghien;/",
    "iso:country":"BE",
    "sg:address":"Rue Locquenghien 41",
    "sg:city":"Brussel/bruxelles",
    "sg:orig_category":"V\u00eatements. V\u00eatements pour Hommes",
    "sg:phone":"+32 2 219 52 94",
    "sg:postcode":"1000",
    "sg:province":"Bruxelles-Capitale",
    "wof:name":"Natan Couture",
    "wof:placetype":"venue"
},
  "geometry": {"coordinates":[4.3437719345,50.8541030884],"type":"Point"}
}