{
  "type": "Feature",
  "properties": {
    "iso:country":"BE",
    "sg:address":"Rue Du Manoir 5",
    "sg:city":"Marche-en-famenne",
    "sg:orig_category":"Artsen and specialisten",
    "sg:phone":"+32 84 32 19 30",
    "sg:postcode":"6900",
    "sg:province":"Luxembourg",
    "wof:name":"Robert Houbart",
    "wof:placetype":"venue"
},
  "geometry": {"coordinates":[5.342634201,50.2275695801],"type":"Point"}
}