{
  "type": "Feature",
  "properties": {
    "addr:full":"Chauss\u00c9e De Familleureux 8 Seneffe Hainaut 7181",
    "addr:housenumber":"8",
    "addr:postcode":"7181",
    "addr:street":"Chausse\u0301E De Familleureux",
    "iso:country":"BE",
    "sg:address":"Chauss\u00c9e De Familleureux 8",
    "sg:city":"Seneffe",
    "sg:orig_category":"Enseignement maternel and primaire",
    "sg:phone":"+32 67 87 71 40",
    "sg:postcode":"7181",
    "sg:province":"Hainaut",
    "wof:name":"Ecole Fondamentale Libre",
    "wof:placetype":"venue"
},
  "geometry": {"coordinates":[4.2589969635,50.5626296997],"type":"Point"}
}