{
  "type": "Feature",
  "properties": {
    "iso:country":"BE",
    "sg:address":"Rue Pont Au Lin 45",
    "sg:city":"Grez-doiceau",
    "sg:classifiers":[
        {
            "category":"Real Estate",
            "subcategory":"Surveying",
            "type":"Services"
        }
    ],
    "sg:phone":"+32 10 86 61 38",
    "sg:postcode":"1390",
    "sg:province":"Brabant Wallon",
    "sg:tags":[
        "surveyor",
        "land"
    ],
    "wof:name":"Wiame S",
    "wof:placetype":"venue"
},
  "geometry": {"coordinates":[4.6985301971,50.7401580811],"type":"Point"}
}