{
  "type": "Feature",
  "properties": {
    "addr:full":"Duvant L'v\u00e8v\u00ee 20 Malmedy Li\u00e8ge 4960",
    "addr:housenumber":"20",
    "addr:postcode":"4960",
    "addr:street":"\u0300Vi\u0302",
    "iso:country":"BE",
    "sg:address":"Duvant L'v\u00e8v\u00ee 20",
    "sg:city":"Malmedy",
    "sg:classifiers":[
        {
            "category":"Health Services",
            "subcategory":"Doctor",
            "type":"Services"
        }
    ],
    "sg:phone":"+32 80 33 99 26",
    "sg:postcode":"4960",
    "sg:province":"Li\u00e8ge",
    "sg:tags":[
        "medicinephysicians",
        "surgeon"
    ],
    "wof:name":"Burgeon Pascal",
    "wof:placetype":"venue"
},
  "geometry": {"coordinates":[6.0306200981,50.425239563],"type":"Point"}
}