{
  "type": "Feature",
  "properties": {
    "iso:country":"BE",
    "sg:address":"Grimstedestraat 38",
    "sg:city":"Turnhout",
    "sg:classifiers":[
        {
            "category":"Home & Garden",
            "subcategory":"Carpets & Floor Coverings",
            "type":"Retail Goods"
        }
    ],
    "sg:phone":"+32 14 43 79 19",
    "sg:postcode":"2300",
    "sg:province":"Antwerpen",
    "sg:tags":[
        "parquet"
    ],
    "wof:name":"Carat",
    "wof:placetype":"venue"
},
  "geometry": {"coordinates":[4.9521431923,51.317489624],"type":"Point"}
}