{
  "type": "Feature",
  "properties": {
    "addr:full":"Kwadepoelstraat 51 Zwevegem West-Vlaanderen 8550",
    "addr:housenumber":"51",
    "addr:postcode":"8550",
    "addr:street":"Kwadepoelstraat",
    "iso:country":"BE",
    "sg:address":"Kwadepoelstraat 51",
    "sg:city":"Zwevegem",
    "sg:classifiers":[
        {
            "category":"Restaurant",
            "type":"Food & Drink"
        }
    ],
    "sg:phone":"+32 56 75 93 97",
    "sg:postcode":"8550",
    "sg:province":"West-Vlaanderen",
    "wof:name":"Molenberg",
    "wof:placetype":"venue"
},
  "geometry": {"coordinates":[3.3292179108,50.8051223755],"type":"Point"}
}