{
  "type": "Feature",
  "properties": {
    "iso:country":"BE",
    "sg:address":"Prinsenbos 52",
    "sg:city":"Tessenderlo",
    "sg:orig_category":"Boekhouders",
    "sg:phone":"+32 13 32 35 92",
    "sg:postcode":"3980",
    "sg:province":"Limburg",
    "wof:name":"Betty Peeters",
    "wof:placetype":"venue"
},
  "geometry": {"coordinates":[5.0291190147,51.0236320496],"type":"Point"}
}