{
  "type": "Feature",
  "properties": {
    "iso:country":"BE",
    "sg:address":"Heirstraat 373",
    "sg:city":"Maasmechelen",
    "sg:orig_category":"Brood, gebak and snoepgoed Herstellingen and onderhoud van auto's",
    "sg:phone":"+32 89 76 40 50",
    "sg:postcode":"3630",
    "sg:province":"Limburg",
    "wof:name":"Bakkerij Dexters J.",
    "wof:placetype":"venue"
},
  "geometry": {"coordinates":[5.6855149269,50.9517936707],"type":"Point"}
}