{
  "type": "Feature",
  "properties": {
    "addr:full":"Hoeilaartsesteenweg 162 Overijse Vlaams-Brabant 3090",
    "addr:housenumber":"162",
    "addr:postcode":"3090",
    "addr:street":"Hoeilaartsesteenweg",
    "iso:country":"BE",
    "sg:address":"Hoeilaartsesteenweg 162",
    "sg:city":"Overijse",
    "sg:classifiers":[
        {
            "category":"Retail",
            "subcategory":"Event Space",
            "type":"Services"
        }
    ],
    "sg:phone":"+32 2 688 38 40",
    "sg:postcode":"3090",
    "sg:province":"Vlaams-Brabant",
    "sg:tags":[
        "organisation"
    ],
    "wof:name":"View Expo",
    "wof:placetype":"venue"
},
  "geometry": {"coordinates":[4.537779808,50.7731971741],"type":"Point"}
}