{
  "type": "Feature",
  "properties": {
    "addr:full":"Avenue De F\u00c9vrier 2 Sint-lambrechts-woluwe/woluwe-saint-lambert Bruxelles-Capitale 1200",
    "addr:housenumber":"2",
    "addr:postcode":"1200",
    "addr:street":"Avenue De Fe\u0301Vrier",
    "iso:country":"BE",
    "sg:address":"Avenue De F\u00c9vrier 2",
    "sg:city":"Sint-lambrechts-woluwe/woluwe-saint-lambert",
    "sg:orig_category":"Epiceries",
    "sg:phone":"+32 2 735 44 72",
    "sg:postcode":"1200",
    "sg:province":"Bruxelles-Capitale",
    "wof:name":"Shopwell",
    "wof:placetype":"venue"
},
  "geometry": {"coordinates":[4.4117469788,50.8503608704],"type":"Point"}
}