{
  "type": "Feature",
  "properties": {
    "addr:full":"Rue Tonin 2 Honnelles Hainaut 7387",
    "addr:housenumber":"2",
    "addr:postcode":"7387",
    "addr:street":"Rue Tonin;Hainaut",
    "iso:country":"BE",
    "sg:address":"Rue Tonin 2",
    "sg:city":"Honnelles",
    "sg:orig_category":"Boomkwekerijen Tuinen",
    "sg:phone":"+32 65 75 02 46",
    "sg:postcode":"7387",
    "sg:province":"Hainaut",
    "wof:name":"Aquapunt & P\u00c9pini\u00c8re D\u00b4autreppe",
    "wof:placetype":"venue"
},
  "geometry": {"coordinates":[3.7391049862,50.3513641357],"type":"Point"}
}