{
  "type": "Feature",
  "properties": {
    "iso:country":"BE",
    "sg:address":"Bosbeek 3",
    "sg:city":"Beveren",
    "sg:orig_category":"Schoonheidssalons",
    "sg:phone":"+32 3 775 15 52",
    "sg:postcode":"9120",
    "sg:province":"Oost-Vlaanderen",
    "wof:name":"Cecile Vyt",
    "wof:placetype":"venue"
},
  "geometry": {"coordinates":[4.2395691872,51.2027626038],"type":"Point"}
}