{
  "type": "Feature",
  "properties": {
    "iso:country":"BE",
    "sg:address":"Pontstraat 64",
    "sg:city":"Sint-martens-latem",
    "sg:orig_category":"Public-relationsbureaus",
    "sg:phone":"+32 9 281 01 53",
    "sg:postcode":"9831",
    "sg:province":"Oost-Vlaanderen",
    "wof:name":"Populier Producties",
    "wof:placetype":"venue"
},
  "geometry": {"coordinates":[3.6026110649,51.0043182373],"type":"Point"}
}