{
  "type": "Feature",
  "properties": {
    "addr:full":"Rue De Limbourg 43 Verviers Li\u00e8ge 4800",
    "addr:housenumber":"43",
    "addr:postcode":"4800",
    "addr:street":"Rue De Limbourg",
    "iso:country":"BE",
    "sg:address":"Rue De Limbourg 43",
    "sg:city":"Verviers",
    "sg:classifiers":[
        {
            "category":"Shopping",
            "subcategory":"Photographic Equipment",
            "type":"Retail Goods"
        }
    ],
    "sg:phone":"+32 87 33 11 60",
    "sg:postcode":"4800",
    "sg:province":"Li\u00e8ge",
    "sg:tags":[
        "whol",
        "-",
        "mfg&",
        "accessory"
    ],
    "wof:name":"Ortmans Ets Sa",
    "wof:placetype":"venue"
},
  "geometry": {"coordinates":[5.8776679039,50.5979423523],"type":"Point"}
}