{
  "type": "Feature",
  "properties": {
    "addr:full":"Rue De Biesme 172 Hasti\u00e8re (agimont) Namur 5544",
    "addr:housenumber":"172",
    "addr:postcode":"5544",
    "addr:street":"Rue De Biesme",
    "iso:country":"BE",
    "sg:address":"Rue De Biesme 172",
    "sg:city":"Hasti\u00e8re (agimont)",
    "sg:classifiers":[
        {
            "category":"Travel",
            "subcategory":"Resort",
            "type":"Entertainment"
        }
    ],
    "sg:phone":"+32 82 67 85 87",
    "sg:postcode":"5544",
    "sg:province":"Namur",
    "sg:tags":[
        "farm",
        "house",
        "holiday",
        "guest"
    ],
    "wof:name":"Rond Tienne Sprl",
    "wof:placetype":"venue"
},
  "geometry": {"coordinates":[4.7980809212,50.1645736694],"type":"Point"}
}