{
  "type": "Feature",
  "properties": {
    "iso:country":"BE",
    "sg:address":"Meersbloem - Leupegem 4",
    "sg:city":"Oudenaarde",
    "sg:orig_category":"Antiek Installatie van houten of kunststof schrijnwerk Vloer- and muurbekleding",
    "sg:phone":"+32 55 31 13 47",
    "sg:postcode":"9700",
    "sg:province":"Oost-Vlaanderen",
    "wof:name":"Historische Bouwmaterialen De Brauwere-peleman",
    "wof:placetype":"venue"
},
  "geometry": {"coordinates":[3.5960600376,50.8307266235],"type":"Point"}
}