{
  "type": "Feature",
  "properties": {
    "addr:full":"Heiwijkerweg 64 Zutendaal Limburg 3690",
    "addr:housenumber":"64",
    "addr:postcode":"3690",
    "addr:street":"Heiwijkerweg",
    "iso:country":"BE",
    "sg:address":"Heiwijkerweg 64",
    "sg:city":"Zutendaal",
    "sg:classifiers":[
        {
            "category":"Shopping",
            "subcategory":"Hobbies, Toys, & Games",
            "type":"Retail Goods"
        }
    ],
    "sg:phone":"+32 89 62 20 98",
    "sg:postcode":"3690",
    "sg:province":"Limburg",
    "sg:tags":[
        "product",
        "miscellaneous",
        "entertainment"
    ],
    "wof:name":"Vinck R M & Co Nv",
    "wof:placetype":"venue"
},
  "geometry": {"coordinates":[5.6009597778,50.9479789734],"type":"Point"}
}