{
  "type": "Feature",
  "properties": {
    "iso:country":"BE",
    "sg:address":"Langestraat 109",
    "sg:city":"Hulshout (houtvenne)",
    "sg:classifiers":[
        {
            "category":"Building & Trades",
            "subcategory":"Construction",
            "type":"Services"
        }
    ],
    "sg:phone":"+32 16 69 86 76",
    "sg:postcode":"2235",
    "sg:province":"Antwerpen",
    "sg:tags":[
        "carpenter"
    ],
    "wof:name":"Vaes J",
    "wof:placetype":"venue"
},
  "geometry": {"coordinates":[4.8010320663,51.0349159241],"type":"Point"}
}