{
  "type": "Feature",
  "properties": {
    "iso:country":"BE",
    "sg:address":".",
    "sg:city":"Lochristi (groot)",
    "sg:orig_category":"Apotheken",
    "sg:phone":"+32 900 10 500",
    "sg:postcode":"9080",
    "sg:province":"Oost-Vlaanderen",
    "wof:name":"Apothekers Van Wacht",
    "wof:placetype":"venue"
},
  "geometry": {"coordinates":[3.8256568909,51.094455719],"type":"Point"}
}