{
  "type": "Feature",
  "properties": {
    "addr:full":"Kaaistr 43 Affligem Vlaams-Brabant 1790",
    "addr:housenumber":"43",
    "addr:postcode":"1790",
    "addr:street":"Kaaistr",
    "iso:country":"BE",
    "sg:address":"Kaaistr 43",
    "sg:city":"Affligem",
    "sg:classifiers":[
        {
            "category":"Professional",
            "type":"Services"
        }
    ],
    "sg:phone":"+32 53 66 12 82",
    "sg:postcode":"1790",
    "sg:province":"Vlaams-Brabant",
    "sg:tags":[
        "transport",
        "road"
    ],
    "wof:name":"Louis Warin Bvba",
    "wof:placetype":"venue"
},
  "geometry": {"coordinates":[4.105984211,50.9132232666],"type":"Point"}
}