{
  "type": "Feature",
  "properties": {
    "iso:country":"BE",
    "sg:address":"Brialmontlei 10",
    "sg:city":"Antwerpen",
    "sg:classifiers":[
        {
            "category":"Professional",
            "subcategory":"Engineering",
            "type":"Services"
        }
    ],
    "sg:phone":"+32 3 280 00 40",
    "sg:postcode":"2018",
    "sg:province":"Antwerpen",
    "sg:tags":[
        "-"
    ],
    "wof:name":"Forma Concreta Nv",
    "wof:placetype":"venue"
},
  "geometry": {"coordinates":[4.4193677902,51.2096557617],"type":"Point"}
}