{
  "type": "Feature",
  "properties": {
    "iso:country":"BE",
    "sg:address":"Laarstraat 5",
    "sg:city":"Rumst (reet)",
    "sg:classifiers":[
        {
            "category":"Health Services",
            "subcategory":"Doctor",
            "type":"Services"
        }
    ],
    "sg:phone":"+32 3 888 02 79",
    "sg:postcode":"2840",
    "sg:province":"Antwerpen",
    "sg:tags":[
        "medicinephysicians",
        "surgeon"
    ],
    "wof:name":"Baetens Katelijne",
    "wof:placetype":"venue"
},
  "geometry": {"coordinates":[4.4139890671,51.1011276245],"type":"Point"}
}