{
  "type": "Feature",
  "properties": {
    "iso:country":"BE",
    "sg:address":"Sint-truidersteenweg 201",
    "sg:city":"Tongeren",
    "sg:classifiers":[
        {
            "category":"Autos & Motor Vehicles",
            "subcategory":"Automobile Sales",
            "type":"Retail Goods"
        }
    ],
    "sg:phone":"+32 12 23 24 92",
    "sg:postcode":"3700",
    "sg:province":"Limburg",
    "sg:tags":[
        "-",
        "truck"
    ],
    "wof:name":"L.a.r. Nv",
    "wof:placetype":"venue"
},
  "geometry": {"coordinates":[5.4437098503,50.7770805359],"type":"Point"}
}