{
  "type": "Feature",
  "properties": {
    "iso:country":"BE",
    "sg:address":"Chemin De Tongres 0",
    "sg:city":"Bitsingen",
    "sg:orig_category":"Diensten voor huisdieren",
    "sg:phone":"+32 4 367 69 31",
    "sg:postcode":"4690",
    "sg:province":"Li\u00e8ge",
    "wof:name":"Adoa",
    "wof:placetype":"venue"
},
  "geometry": {"coordinates":[5.6041021347,50.7644767761],"type":"Point"}
}