{
  "type": "Feature",
  "properties": {
    "iso:country":"BE",
    "sg:address":"Rue Saint-gilles 194",
    "sg:city":"Li\u00c8ge",
    "sg:orig_category":"Fleurs and plantes",
    "sg:phone":"+32 4 223 52 48",
    "sg:postcode":"4000",
    "sg:province":"Li\u00e8ge",
    "wof:name":"Kunsch Fleurs",
    "wof:placetype":"venue"
},
  "geometry": {"coordinates":[5.5621781349,50.637714386],"type":"Point"}
}