{
  "type": "Feature",
  "properties": {
    "addr:full":"Rue De Villers 227 Charleroi Hainaut 6010",
    "addr:housenumber":"227",
    "addr:postcode":"6010",
    "addr:street":"Rue De Villers;Hainaut",
    "iso:country":"BE",
    "sg:address":"Rue De Villers 227",
    "sg:city":"Charleroi",
    "sg:orig_category":"DIVERSE RECREATIEVE ACTIVITEITEN Musea and historische gebouwen",
    "sg:phone":"+32 71 60 03 00",
    "sg:postcode":"6010",
    "sg:province":"Hainaut",
    "wof:name":"Mus\u00c9e Sciences & Techn.",
    "wof:placetype":"venue"
},
  "geometry": {"coordinates":[4.4769711494,50.3856163025],"type":"Point"}
}