{
  "type": "Feature",
  "properties": {
    "iso:country":"BE",
    "sg:address":"Place P\u00e8re Bruno Reynders 16",
    "sg:city":"Ottignies-louvain-la-neuve (ottignies)",
    "sg:classifiers":[
        {
            "category":"Professional",
            "subcategory":"Testing Lab",
            "type":"Services"
        }
    ],
    "sg:phone":"+32 10 43 91 54",
    "sg:postcode":"1340",
    "sg:province":"Brabant Wallon",
    "sg:tags":[
        "chemist"
    ],
    "wof:name":"Peuple (pharmacie Du)",
    "wof:placetype":"venue"
},
  "geometry": {"coordinates":[4.553401947,50.6732330322],"type":"Point"}
}