{
  "type": "Feature",
  "properties": {
    "iso:country":"BE",
    "sg:address":"Frilinglei 73",
    "sg:city":"Brasschaat",
    "sg:classifiers":[
        {
            "category":"Banks & Credit Unions",
            "subcategory":"Investment Brokerage",
            "type":"Services"
        }
    ],
    "sg:phone":"+32 2 774 91 11",
    "sg:postcode":"2930",
    "sg:province":"Antwerpen",
    "sg:tags":[
        "auditor"
    ],
    "wof:name":"Swolfs L",
    "wof:placetype":"venue"
},
  "geometry": {"coordinates":[4.4736981392,51.2900619507],"type":"Point"}
}