{
  "type": "Feature",
  "properties": {
    "iso:country":"BE",
    "sg:address":"Schauwbroekstraat",
    "sg:city":"Zomergem",
    "sg:orig_category":"Royal Canin. Articles de jardin",
    "sg:phone":"+32 9 372 72 25",
    "sg:postcode":"9930",
    "sg:province":"Oost-Vlaanderen",
    "wof:name":"Plovijt Christiaan",
    "wof:placetype":"venue"
},
  "geometry": {"coordinates":[3.5722351074,51.1196517944],"type":"Point"}
}