{
  "type": "Feature",
  "properties": {
    "iso:country":"BE",
    "sg:address":"Minnezangerslaan 99",
    "sg:city":"Sint-jans-molenbeek/molenbeek-saint-jean",
    "sg:orig_category":"Boekhouders",
    "sg:phone":"+32 2 411 02 33",
    "sg:postcode":"1080",
    "sg:province":"Bruxelles-Capitale",
    "wof:name":"Eusebio-jos\u00c9 Iglesias Perez",
    "wof:placetype":"venue"
},
  "geometry": {"coordinates":[4.3087210655,50.8501014709],"type":"Point"}
}