{
  "type": "Feature",
  "properties": {
    "iso:country":"BE",
    "sg:address":"Spilstraat 56",
    "sg:city":"Zonnebeke",
    "sg:orig_category":"Varkenskwekers",
    "sg:phone":"+32 51 77 22 87",
    "sg:postcode":"8980",
    "sg:province":"West-Vlaanderen",
    "wof:name":"Luc Deleu",
    "wof:placetype":"venue"
},
  "geometry": {"coordinates":[3.0057449341,50.8629646301],"type":"Point"}
}