{
  "type": "Feature",
  "properties": {
    "iso:country":"BE",
    "sg:address":"Rue Arthur Andr\u00e9 75",
    "sg:city":"Bruxelles (woluwe-saint-pierre)",
    "sg:classifiers":[
        {
            "category":"Arts & Performance",
            "subcategory":"Music",
            "type":"Entertainment"
        }
    ],
    "sg:phone":"+32 2 772 76 20",
    "sg:postcode":"1150",
    "sg:province":"Bruxelles-Capitale",
    "sg:tags":[
        "freelance",
        "musician"
    ],
    "wof:name":"Guth S",
    "wof:placetype":"venue"
},
  "geometry": {"coordinates":[4.4593300819,50.8458099365],"type":"Point"}
}