{
  "type": "Feature",
  "properties": {
    "addr:full":"Chauss\u00c9e De Ninove 409 Anderlecht/anderlecht Bruxelles-Capitale 1070",
    "addr:housenumber":"409",
    "addr:postcode":"1070",
    "addr:street":"Chausse\u0301E De Ninove",
    "iso:country":"BE",
    "sg:address":"Chauss\u00c9e De Ninove 409",
    "sg:city":"Anderlecht/anderlecht",
    "sg:orig_category":"Blanchisseries and teintureries",
    "sg:phone":"+32 2 411 17 29",
    "sg:postcode":"1070",
    "sg:province":"Bruxelles-Capitale",
    "wof:name":"Nettoyage Gi-press",
    "wof:placetype":"venue"
},
  "geometry": {"coordinates":[4.3094887733,50.8479499817],"type":"Point"}
}