{
  "type": "Feature",
  "properties": {
    "iso:country":"BE",
    "sg:address":"Rostraat 17",
    "sg:city":"Nevele",
    "sg:orig_category":"Woningbouw",
    "sg:phone":"+32 9 371 66 71",
    "sg:postcode":"9850",
    "sg:province":"Oost-Vlaanderen",
    "wof:name":"Erik Van De Velde",
    "wof:placetype":"venue"
},
  "geometry": {"coordinates":[3.5397500992,51.0654830933],"type":"Point"}
}