{
  "type": "Feature",
  "properties": {
    "addr:full":"Meensesteenweg 249 Roeselare West-Vlaanderen 8800",
    "addr:housenumber":"249",
    "addr:postcode":"8800",
    "addr:street":"Meensesteenweg",
    "iso:country":"BE",
    "sg:address":"Meensesteenweg 249",
    "sg:city":"Roeselare",
    "sg:orig_category":"Brood, gebak and snoepgoed",
    "sg:phone":"+32 51 22 67 28",
    "sg:postcode":"8800",
    "sg:province":"West-Vlaanderen",
    "wof:name":"Pieter Ryckewaert",
    "wof:placetype":"venue"
},
  "geometry": {"coordinates":[3.1149880886,50.8993873596],"type":"Point"}
}