{
  "type": "Feature",
  "properties": {
    "iso:country":"BE",
    "sg:address":"Graven Egm. En Hoornlaan 18a",
    "sg:city":"Overijse",
    "sg:orig_category":"Notarissen",
    "sg:phone":"+32 2 687 83 20",
    "sg:postcode":"3090",
    "sg:province":"Vlaams-Brabant",
    "wof:name":"M. Van Den Moortel",
    "wof:placetype":"venue"
},
  "geometry": {"coordinates":[4.5396828651,50.7742614746],"type":"Point"}
}