{
  "type": "Feature",
  "properties": {
    "addr:full":"Avenue Du Roi 108 Bruxelles (forest) Bruxelles-Capitale 1190",
    "addr:housenumber":"108",
    "addr:postcode":"1190",
    "addr:street":"Avenue Du Roi",
    "iso:country":"BE",
    "sg:address":"Avenue Du Roi 108",
    "sg:city":"Bruxelles (forest)",
    "sg:classifiers":[
        {
            "category":"Communications",
            "type":"Services"
        }
    ],
    "sg:phone":"+32 2 534 23 20",
    "sg:postcode":"1190",
    "sg:province":"Bruxelles-Capitale",
    "sg:tags":[
        "telecommunication"
    ],
    "wof:name":"Global Com Belgium",
    "wof:placetype":"venue"
},
  "geometry": {"coordinates":[4.3344259262,50.8280639648],"type":"Point"}
}