{
  "type": "Feature",
  "properties": {
    "addr:full":"Chauss\u00e9e De Charleroi 135 Fleurus Hainaut 6220",
    "addr:housenumber":"135",
    "addr:postcode":"6220",
    "addr:street":"Chausse\u0301E De Charleroi",
    "iso:country":"BE",
    "sg:address":"Chauss\u00e9e De Charleroi 135",
    "sg:city":"Fleurus",
    "sg:classifiers":[
        {
            "category":"Insurance",
            "subcategory":"Insurance Agent",
            "type":"Services"
        }
    ],
    "sg:phone":"+32 71 81 15 78",
    "sg:postcode":"6220",
    "sg:province":"Hainaut",
    "sg:tags":[
        "broker"
    ],
    "wof:name":"Destr\u00e9e R Et Fils Sprl",
    "wof:placetype":"venue"
},
  "geometry": {"coordinates":[4.5535178185,50.4843711853],"type":"Point"}
}