{
  "type": "Feature",
  "properties": {
    "iso:country":"BE",
    "sg:address":"Mollentstraat 37",
    "sg:city":"Ranst (broechem)",
    "sg:classifiers":[
        {
            "category":"Farming",
            "subcategory":"Crops",
            "type":"Manufacturing & Wholesale Goods"
        }
    ],
    "sg:phone":"+32 3 485 80 74",
    "sg:postcode":"2520",
    "sg:province":"Antwerpen",
    "sg:tags":[
        "vegetable",
        "fruit",
        "-",
        "grower"
    ],
    "wof:name":"Martens F",
    "wof:placetype":"venue"
},
  "geometry": {"coordinates":[4.6180100441,51.1824645996],"type":"Point"}
}