{
  "type": "Feature",
  "properties": {
    "iso:country":"BE",
    "sg:address":"Ch De Lessines 259",
    "sg:city":"Soignies",
    "sg:orig_category":"Drukkerijen and copyshops",
    "sg:phone":"+32 67 41 03 40",
    "sg:postcode":"7060",
    "sg:province":"Hainaut",
    "wof:name":"Lietard Vanbutsele Print",
    "wof:placetype":"venue"
},
  "geometry": {"coordinates":[4.0543699265,50.5899810791],"type":"Point"}
}