{
  "type": "Feature",
  "properties": {
    "iso:country":"BE",
    "sg:address":"Place Eug\u00e8ne Keym 73",
    "sg:city":"Bruxelles (watermael-boitsfort)",
    "sg:classifiers":[
        {
            "category":"Shopping",
            "subcategory":"Clothing, Apparel, & Fashions",
            "type":"Retail Goods"
        }
    ],
    "sg:phone":"+32 2 660 64 47",
    "sg:postcode":"1170",
    "sg:province":"Bruxelles-Capitale",
    "sg:tags":[
        "lady",
        "clothing",
        "-"
    ],
    "wof:name":"Kokine",
    "wof:placetype":"venue"
},
  "geometry": {"coordinates":[4.4031891823,50.8093299866],"type":"Point"}
}