{
  "type": "Feature",
  "properties": {
    "addr:full":"Boulevard De G\u00c9rardchamps Verviers Li\u00e8ge 4800",
    "addr:postcode":"4800",
    "addr:street":"Boulevard De Ge\u0301Rardchamps",
    "iso:country":"BE",
    "sg:address":"Boulevard De G\u00c9rardchamps",
    "sg:city":"Verviers",
    "sg:orig_category":"Meubelzaken, woning- and keukeninrichting",
    "sg:phone":"+32 87 39 89 80",
    "sg:postcode":"4800",
    "sg:province":"Li\u00e8ge",
    "wof:name":"Salon Confort",
    "wof:placetype":"venue"
},
  "geometry": {"coordinates":[5.8471598625,50.5935783386],"type":"Point"}
}