{
  "type": "Feature",
  "properties": {
    "addr:full":"Rue Du Plan Inclin\u00c9 141-143 Luik Li\u00e8ge 4000",
    "addr:postcode":"141-143;4000",
    "addr:street":"Rue Du Plan Incline\u0301",
    "iso:country":"BE",
    "sg:address":"Rue Du Plan Inclin\u00c9 141-143",
    "sg:city":"Luik",
    "sg:orig_category":"Seksshops",
    "sg:phone":"+32 4 252 24 29",
    "sg:postcode":"4000",
    "sg:province":"Li\u00e8ge",
    "wof:name":"Erotic Discount Centre",
    "wof:placetype":"venue"
},
  "geometry": {"coordinates":[5.5656270981,50.6268081665],"type":"Point"}
}