{
  "type": "Feature",
  "properties": {
    "iso:country":"BE",
    "sg:address":"Rue Large 9",
    "sg:city":"Li\u00e8ge 1 (ch\u00ean\u00e9e)",
    "sg:classifiers":[
        {
            "category":"Wholesale",
            "subcategory":"Medical Equipment & Supplies",
            "type":"Manufacturing & Wholesale Goods"
        }
    ],
    "sg:phone":"+32 4 365 57 64",
    "sg:postcode":"4032",
    "sg:province":"Li\u00e8ge",
    "sg:tags":[
        "aid",
        "hearing"
    ],
    "wof:name":"Janssen P",
    "wof:placetype":"venue"
},
  "geometry": {"coordinates":[5.6146402359,50.6140136719],"type":"Point"}
}