{
  "type": "Feature",
  "properties": {
    "addr:full":"Stationsstraat 16 As Limburg 3665",
    "addr:housenumber":"16",
    "addr:postcode":"3665",
    "addr:street":"Stationsstraat",
    "iso:country":"BE",
    "sg:address":"Stationsstraat 16",
    "sg:city":"As",
    "sg:orig_category":"Artsen and specialisten",
    "sg:phone":"+32 89 65 99 81",
    "sg:postcode":"3665",
    "sg:province":"Limburg",
    "wof:name":"Ann Vandeurzen",
    "wof:placetype":"venue"
},
  "geometry": {"coordinates":[5.5919017792,51.0066375732],"type":"Point"}
}