{
  "type": "Feature",
  "properties": {
    "iso:country":"BE",
    "sg:address":"Bellemstraat 157",
    "sg:city":"Aalter",
    "sg:orig_category":"Eleveurs de bovins",
    "sg:phone":"+32 9 374 77 66",
    "sg:postcode":"9880",
    "sg:province":"Oost-Vlaanderen",
    "wof:name":"Willy Vervynckt",
    "wof:placetype":"venue"
},
  "geometry": {"coordinates":[3.4691460133,51.0890731812],"type":"Point"}
}