{
  "type": "Feature",
  "properties": {
    "iso:country":"BE",
    "sg:address":"Rue De P\u00c2turages 29",
    "sg:city":"Qu\u00c9vy",
    "sg:orig_category":"Bloemen and planten",
    "sg:phone":"+32 65 58 69 45",
    "sg:postcode":"7041",
    "sg:province":"Hainaut",
    "wof:name":"Berthaut Fleurs",
    "wof:placetype":"venue"
},
  "geometry": {"coordinates":[4.031317234,50.3789596558],"type":"Point"}
}