{
  "type": "Feature",
  "properties": {
    "addr:full":"Lichterveldsestraat 130 Ardooie West-Vlaanderen 8851",
    "addr:housenumber":"130",
    "addr:postcode":"8851",
    "addr:street":"Lichterveldsestraat",
    "iso:country":"BE",
    "sg:address":"Lichterveldsestraat 130",
    "sg:city":"Ardooie",
    "sg:orig_category":"Aanleg van wegen, sportterreinen and vliegvelden HUISBRANDOLIE",
    "sg:phone":"+32 51 74 47 81",
    "sg:postcode":"8851",
    "sg:province":"West-Vlaanderen",
    "wof:name":"Ver Eecke Vanneste & Co",
    "wof:placetype":"venue"
},
  "geometry": {"coordinates":[3.1883029938,51.0007629395],"type":"Point"}
}