{
  "type": "Feature",
  "properties": {
    "iso:country":"BE",
    "sg:address":"Torhoutbaan 10",
    "sg:city":"Ichtegem",
    "sg:classifiers":[
        {
            "category":"Tea Room",
            "subcategory":"None",
            "type":"Food & Drink"
        }
    ],
    "sg:phone":"+32 51 58 29 29",
    "sg:postcode":"8480",
    "sg:province":"West-Vlaanderen",
    "wof:name":"De Stove",
    "wof:placetype":"venue"
},
  "geometry": {"coordinates":[3.0331590176,51.1004714966],"type":"Point"}
}