{
  "type": "Feature",
  "properties": {
    "iso:country":"BE",
    "sg:address":"Molenstraat 3",
    "sg:city":"Vleteren",
    "sg:orig_category":"Eleveurs de bovins. Eleveurs and marchands de porcs",
    "sg:phone":"+32 57 40 04 71",
    "sg:postcode":"8640",
    "sg:province":"West-Vlaanderen",
    "wof:name":"Roland Devloo",
    "wof:placetype":"venue"
},
  "geometry": {"coordinates":[2.7352120876,50.9268417358],"type":"Point"}
}