{
  "type": "Feature",
  "properties": {
    "addr:full":"Hoge Mauw 23 Arendonk Antwerpen 2370",
    "addr:housenumber":"23",
    "addr:postcode":"2370",
    "addr:street":"Hoge Mauw",
    "iso:country":"BE",
    "sg:address":"Hoge Mauw 23",
    "sg:city":"Arendonk",
    "sg:classifiers":[
        {
            "category":"Shopping",
            "subcategory":"Bicycles & Sporting Goods",
            "type":"Retail Goods"
        }
    ],
    "sg:phone":"+32 14 67 20 43",
    "sg:postcode":"2370",
    "sg:province":"Antwerpen",
    "sg:tags":[
        "tyre"
    ],
    "wof:name":"Eurokarkas",
    "wof:placetype":"venue"
},
  "geometry": {"coordinates":[5.086771965,51.3202438354],"type":"Point"}
}