{
  "type": "Feature",
  "properties": {
    "addr:full":"Rue Du Pansy 227 Saint-nicolas Li\u00e8ge 4420",
    "addr:housenumber":"227",
    "addr:postcode":"4420",
    "addr:street":"Rue Du Pansy;Saint-Nicolas Lie\u0300Ge",
    "iso:country":"BE",
    "sg:address":"Rue Du Pansy 227",
    "sg:city":"Saint-nicolas",
    "sg:orig_category":"Epiceries",
    "sg:phone":"+32 4 233 96 23",
    "sg:postcode":"4420",
    "sg:province":"Li\u00e8ge",
    "wof:name":"Clelia Baricalla",
    "wof:placetype":"venue"
},
  "geometry": {"coordinates":[5.5195960999,50.6308631897],"type":"Point"}
}