{
  "type": "Feature",
  "properties": {
    "addr:full":"Alfons Gossetlaan 19 Dilbeek (groot - Bijgaarden) Vlaams-Brabant 1702",
    "addr:housenumber":"19;1702",
    "addr:street":"Alfons Gossetlaan;Groot Bijgaarden Vlaams-Brabant",
    "iso:country":"BE",
    "sg:address":"Alfons Gossetlaan 19",
    "sg:city":"Dilbeek (groot - Bijgaarden)",
    "sg:classifiers":[
        {
            "category":"Home & Garden",
            "subcategory":"Building Materials",
            "type":"Retail Goods"
        }
    ],
    "sg:phone":"+32 2 481 61 10",
    "sg:postcode":"1702",
    "sg:province":"Vlaams-Brabant",
    "sg:tags":[
        "granite",
        "stone",
        "natural",
        "marble"
    ],
    "wof:name":"Intercarro",
    "wof:placetype":"venue"
},
  "geometry": {"coordinates":[4.2736968994,50.8722991943],"type":"Point"}
}