{
  "type": "Feature",
  "properties": {
    "addr:full":"Rue De La Province 21 Seraing Li\u00e8ge 4100",
    "addr:housenumber":"21",
    "addr:postcode":"4100",
    "addr:street":"Rue De La Province",
    "iso:country":"BE",
    "sg:address":"Rue De La Province 21",
    "sg:city":"Seraing",
    "sg:orig_category":"Maatschappelijke dienstverlening",
    "sg:phone":"+32 4 337 19 20",
    "sg:postcode":"4100",
    "sg:province":"Li\u00e8ge",
    "wof:name":"Centre P.m.s.",
    "wof:placetype":"venue"
},
  "geometry": {"coordinates":[5.5070791245,50.6131324768],"type":"Point"}
}