{
  "type": "Feature",
  "properties": {
    "iso:country":"BE",
    "sg:address":"Henri Jasparlaan 114b1",
    "sg:city":"Sint-gillis/saint-gilles",
    "sg:orig_category":"Advocaten and juridische adviseurs",
    "sg:phone":"+32 2 534 90 76",
    "sg:postcode":"1060",
    "sg:province":"Bruxelles-Capitale",
    "wof:name":"Robert Bohi Seri",
    "wof:placetype":"venue"
},
  "geometry": {"coordinates":[4.3478550911,50.8327178955],"type":"Point"}
}