{
  "type": "Feature",
  "properties": {
    "addr:full":"Vosveld 17 Wijnegem Antwerpen 2110",
    "addr:housenumber":"17",
    "addr:postcode":"2110",
    "addr:street":"Vosveld",
    "iso:country":"BE",
    "sg:address":"Vosveld 17",
    "sg:city":"Wijnegem",
    "sg:classifiers":[
        {
            "category":"Professional",
            "subcategory":"Management & Consulting",
            "type":"Services"
        }
    ],
    "sg:phone":"+32 3 328 19 10",
    "sg:postcode":"2110",
    "sg:province":"Antwerpen",
    "sg:tags":[
        "consultant",
        "agency",
        "advertising"
    ],
    "wof:name":"The Ferry Man",
    "wof:placetype":"venue"
},
  "geometry": {"coordinates":[4.4963130951,51.2315292358],"type":"Point"}
}