{
  "type": "Feature",
  "properties": {
    "addr:full":"Rue Sart-tilman 352 Li\u00c8ge Li\u00e8ge 4031",
    "addr:housenumber":"352",
    "addr:postcode":"4031",
    "addr:street":"Rue Sart-Tilman",
    "iso:country":"BE",
    "sg:address":"Rue Sart-tilman 352",
    "sg:city":"Li\u00c8ge",
    "sg:classifiers":[
        {
            "category":"Food & Beverages",
            "subcategory":"Fruits & Vegetables",
            "type":"Retail Goods"
        }
    ],
    "sg:phone":"+32 4 367 67 29",
    "sg:postcode":"4031",
    "sg:province":"Li\u00e8ge",
    "sg:tags":[
        "groenten"
    ],
    "wof:name":"La L\u00c9gumerie",
    "wof:placetype":"venue"
},
  "geometry": {"coordinates":[5.5593299866,50.601940155],"type":"Point"}
}