{
  "type": "Feature",
  "properties": {
    "iso:country":"BE",
    "sg:address":"Liebaardstraat 119",
    "sg:city":"Waregem (desselgem)",
    "sg:classifiers":[
        {
            "category":"Professional",
            "subcategory":"Art Services",
            "type":"Services"
        }
    ],
    "sg:phone":"+32 56 72 91 86",
    "sg:postcode":"8792",
    "sg:province":"West-Vlaanderen",
    "sg:tags":[
        "photographer"
    ],
    "wof:name":"Eeckhout F",
    "wof:placetype":"venue"
},
  "geometry": {"coordinates":[3.3542220592,50.8832550049],"type":"Point"}
}