{
  "type": "Feature",
  "properties": {
    "iso:country":"BE",
    "sg:address":"Rue Des Tamaris 10",
    "sg:city":"Li\u00c8ge",
    "sg:orig_category":"Drogueries",
    "sg:phone":"+32 4 253 52 07",
    "sg:postcode":"4000",
    "sg:province":"Li\u00e8ge",
    "wof:name":"Michael Vos",
    "wof:placetype":"venue"
},
  "geometry": {"coordinates":[5.5560708046,50.621509552],"type":"Point"}
}