{
  "type": "Feature",
  "properties": {
    "addr:full":"Bredabaan 909 Brasschaat Antwerpen 2930",
    "addr:housenumber":"909",
    "addr:postcode":"2930",
    "addr:street":"Bredabaan",
    "iso:country":"BE",
    "sg:address":"Bredabaan 909",
    "sg:city":"Brasschaat",
    "sg:classifiers":[
        {
            "category":"Restaurant",
            "type":"Food & Drink"
        }
    ],
    "sg:phone":"+32 3 633 08 83",
    "sg:postcode":"2930",
    "sg:province":"Antwerpen",
    "wof:name":"Muziekcaf\u00c9 De Linde",
    "wof:placetype":"venue"
},
  "geometry": {"coordinates":[4.5179491043,51.3179321289],"type":"Point"}
}