{
  "type": "Feature",
  "properties": {
    "addr:full":"Georges Henrilaan 427 Sint-lambrechts-woluwe/woluwe-saint-lambert Bruxelles-Capitale 1200",
    "addr:housenumber":"427;/",
    "addr:postcode":"1200",
    "addr:street":"Henrilaan;Sint-Lambrechts-Woluwe",
    "iso:country":"BE",
    "sg:address":"Georges Henrilaan 427",
    "sg:city":"Sint-lambrechts-woluwe/woluwe-saint-lambert",
    "sg:orig_category":"Herstellingen and onderhoud van auto's Voertuigen",
    "sg:phone":"+32 2 735 25 60",
    "sg:postcode":"1200",
    "sg:province":"Bruxelles-Capitale",
    "wof:name":"Garage Keyers",
    "wof:placetype":"venue"
},
  "geometry": {"coordinates":[4.4056620598,50.8420257568],"type":"Point"}
}