{
  "type": "Feature",
  "properties": {
    "iso:country":"BE",
    "sg:address":"Ka\u00cfrostraat 93",
    "sg:city":"Oostende",
    "sg:orig_category":"Sportclubs",
    "sg:phone":"+32 59 50 28 69",
    "sg:postcode":"8400",
    "sg:province":"West-Vlaanderen",
    "wof:name":"Kon.oost.turnv.noordzee",
    "wof:placetype":"venue"
},
  "geometry": {"coordinates":[2.9131400585,51.2236595154],"type":"Point"}
}