{
  "type": "Feature",
  "properties": {
    "addr:full":"Grand'route 492 Flemalle Li\u00e8ge 4400",
    "addr:housenumber":"492",
    "addr:postcode":"4400",
    "addr:street":"Grand'Route",
    "iso:country":"BE",
    "sg:address":"Grand'route 492",
    "sg:city":"Flemalle",
    "sg:classifiers":[
        {
            "category":"Cafe",
            "type":"Food & Drink"
        }
    ],
    "sg:phone":"+32 4 234 34 17",
    "sg:postcode":"4400",
    "sg:province":"Li\u00e8ge",
    "sg:tags":[
        "caf\u00e9s"
    ],
    "wof:name":"Caf\u00c9 Le Chaffour",
    "wof:placetype":"venue"
},
  "geometry": {"coordinates":[5.4492239952,50.5986442566],"type":"Point"}
}