{
  "type": "Feature",
  "properties": {
    "addr:full":"Rue Souverain-pont 5 Li\u00c8ge Li\u00e8ge 4000",
    "addr:housenumber":"5",
    "addr:postcode":"4000",
    "addr:street":"Rue Souverain-Pont",
    "iso:country":"BE",
    "sg:address":"Rue Souverain-pont 5",
    "sg:city":"Li\u00c8ge",
    "sg:classifiers":[
        {
            "category":"Fast Food",
            "type":"Food & Drink"
        }
    ],
    "sg:phone":"+32 4 223 75 87",
    "sg:postcode":"4000",
    "sg:province":"Li\u00e8ge",
    "sg:tags":[
        "meeneem",
        "restaurant"
    ],
    "wof:name":"Restaurant Chez Tasso",
    "wof:placetype":"venue"
},
  "geometry": {"coordinates":[5.5748128891,50.6446342468],"type":"Point"}
}