{
  "type": "Feature",
  "properties": {
    "addr:full":"Melveren-centrum 178 Sint-truiden Limburg 3800",
    "addr:housenumber":"178",
    "addr:postcode":"3800",
    "addr:street":"Melveren-Centrum",
    "iso:country":"BE",
    "sg:address":"Melveren-centrum 178",
    "sg:city":"Sint-truiden",
    "sg:classifiers":[
        {
            "category":"Shopping",
            "subcategory":"Jewelry",
            "type":"Retail Goods"
        }
    ],
    "sg:phone":"+32 11 69 22 21",
    "sg:postcode":"3800",
    "sg:province":"Limburg",
    "sg:tags":[
        "jeweller",
        "-"
    ],
    "wof:name":"Paule J Nolens Art Consulting Bvba",
    "wof:placetype":"venue"
},
  "geometry": {"coordinates":[5.1910128593,50.8385162354],"type":"Point"}
}