{
  "type": "Feature",
  "properties": {
    "addr:full":"Bergstraat 13 Heist-op-den-berg Antwerpen 2220",
    "addr:housenumber":"13",
    "addr:postcode":"2220",
    "addr:street":"Bergstraat",
    "iso:country":"BE",
    "sg:address":"Bergstraat 13",
    "sg:city":"Heist-op-den-berg",
    "sg:orig_category":"Banken and kredietinstellingen",
    "sg:phone":"+32 15 24 44 61",
    "sg:postcode":"2220",
    "sg:province":"Antwerpen",
    "wof:name":"Fortis",
    "wof:placetype":"venue"
},
  "geometry": {"coordinates":[4.7257289886,51.0753250122],"type":"Point"}
}