{
  "type": "Feature",
  "properties": {
    "iso:country":"BE",
    "sg:address":"Berkenlaan 20",
    "sg:city":"Hove",
    "sg:classifiers":[
        {
            "category":"Shopping",
            "subcategory":"Crafts & Fabrics",
            "type":"Retail Goods"
        }
    ],
    "sg:phone":"+32 3 455 08 03",
    "sg:postcode":"2540",
    "sg:province":"Antwerpen",
    "sg:tags":[
        "textile",
        "clothing"
    ],
    "wof:name":"Vadotex Nv",
    "wof:placetype":"venue"
},
  "geometry": {"coordinates":[4.4713339806,51.1471443176],"type":"Point"}
}