{
  "type": "Feature",
  "properties": {
    "addr:full":"Rue Astrid 49 P\u00c9ruwelz Hainaut 7600",
    "addr:housenumber":"49",
    "addr:postcode":"7600",
    "addr:street":"Rue Astrid",
    "iso:country":"BE",
    "sg:address":"Rue Astrid 49",
    "sg:city":"P\u00c9ruwelz",
    "sg:orig_category":"Pain, p\u00e2tisseries and confiseries",
    "sg:phone":"+32 69 77 34 10",
    "sg:postcode":"7600",
    "sg:province":"Hainaut",
    "wof:name":"Boulangerie Provoost",
    "wof:placetype":"venue"
},
  "geometry": {"coordinates":[3.5913379192,50.5127296448],"type":"Point"}
}