{
  "type": "Feature",
  "properties": {
    "iso:country":"BE",
    "sg:address":"Duinenstraat 309",
    "sg:city":"Bredene",
    "sg:orig_category":"Diensten voor huisdieren",
    "sg:phone":"+32 59 32 32 47",
    "sg:postcode":"8450",
    "sg:province":"West-Vlaanderen",
    "wof:name":"Akita's Petshop",
    "wof:placetype":"venue"
},
  "geometry": {"coordinates":[2.9626059532,51.2456359863],"type":"Point"}
}