{
  "type": "Feature",
  "properties": {
    "addr:full":"Itterbeekse Laan 3 Anderlecht/anderlecht Bruxelles-Capitale 1070",
    "addr:housenumber":"3",
    "addr:postcode":"1070",
    "addr:street":"Laan",
    "iso:country":"BE",
    "sg:address":"Itterbeekse Laan 3",
    "sg:city":"Anderlecht/anderlecht",
    "sg:orig_category":"Bloemen and planten",
    "sg:phone":"+32 2 523 43 92",
    "sg:postcode":"1070",
    "sg:province":"Bruxelles-Capitale",
    "wof:name":"Chez Berthe",
    "wof:placetype":"venue"
},
  "geometry": {"coordinates":[4.2987718582,50.8355445862],"type":"Point"}
}