{
  "type": "Feature",
  "properties": {
    "addr:full":"Rue Octave Battaille 35 Beloeil (bas\u00e8cles) Hainaut 7971",
    "addr:housenumber":"35",
    "addr:postcode":"7971",
    "addr:street":"Rue Octave Battaille",
    "iso:country":"BE",
    "sg:address":"Rue Octave Battaille 35",
    "sg:city":"Beloeil (bas\u00e8cles)",
    "sg:classifiers":[
        {
            "category":"Banks & Credit Unions",
            "subcategory":"Investment Brokerage",
            "type":"Services"
        }
    ],
    "sg:phone":"+32 69 57 53 69",
    "sg:postcode":"7971",
    "sg:province":"Hainaut",
    "sg:tags":[
        "printing",
        "-"
    ],
    "wof:name":"Moderna Imprim'",
    "wof:placetype":"venue"
},
  "geometry": {"coordinates":[3.644464016,50.5274963379],"type":"Point"}
}