{
  "type": "Feature",
  "properties": {
    "iso:country":"BE",
    "sg:address":"Broechemsesteenweg 117",
    "sg:city":"Nijlen",
    "sg:classifiers":[
        {
            "category":"Shopping",
            "subcategory":"Bicycles & Sporting Goods",
            "type":"Retail Goods"
        }
    ],
    "sg:phone":"+32 3 481 85 91",
    "sg:postcode":"2560",
    "sg:province":"Antwerpen",
    "sg:tags":[
        "-"
    ],
    "wof:name":"Van Dessel R",
    "wof:placetype":"venue"
},
  "geometry": {"coordinates":[4.6607899666,51.164768219],"type":"Point"}
}