{
  "type": "Feature",
  "properties": {
    "addr:full":"Lampernissestraat 4 Ardooie West-Vlaanderen 8850",
    "addr:housenumber":"4",
    "addr:postcode":"8850",
    "addr:street":"Lampernissestraat",
    "iso:country":"BE",
    "sg:address":"Lampernissestraat 4",
    "sg:city":"Ardooie",
    "sg:orig_category":"Rundveehouders",
    "sg:phone":"+32 51 74 46 31",
    "sg:postcode":"8850",
    "sg:province":"West-Vlaanderen",
    "wof:name":"Andre Bouckaert",
    "wof:placetype":"venue"
},
  "geometry": {"coordinates":[3.2021460533,50.9918441772],"type":"Point"}
}