{
  "type": "Feature",
  "properties": {
    "addr:full":"Fran\u00c7ois-jos. Navezstr. 91-93 Schaarbeek/schaerbeek Bruxelles-Capitale 1030",
    "addr:housenumber":"91-93",
    "addr:postcode":"1030",
    "iso:country":"BE",
    "sg:address":"Fran\u00c7ois-jos. Navezstr. 91-93",
    "sg:city":"Schaarbeek/schaerbeek",
    "sg:orig_category":"Boekenuitgeverijen",
    "sg:phone":"+32 70 22 27 77",
    "sg:postcode":"1030",
    "sg:province":"Bruxelles-Capitale",
    "wof:name":"Guide De Rouck-bruxelles",
    "wof:placetype":"venue"
},
  "geometry": {"coordinates":[4.3732018471,50.8723716736],"type":"Point"}
}