{
  "type": "Feature",
  "properties": {
    "addr:full":"De Keyserlei 45 Antwerpen-centrum Antwerpen 2018",
    "addr:housenumber":"45",
    "addr:postcode":"2018",
    "addr:street":"De Keyserlei",
    "iso:country":"BE",
    "sg:address":"De Keyserlei 45",
    "sg:city":"Antwerpen-centrum",
    "sg:orig_category":"Agences de voyages",
    "sg:phone":"+32 3 233 22 55",
    "sg:postcode":"2018",
    "sg:province":"Antwerpen",
    "wof:name":"Tui Travel Center (royal Tours)",
    "wof:placetype":"venue"
},
  "geometry": {"coordinates":[4.4193558693,51.2174873352],"type":"Point"}
}