{
  "type": "Feature",
  "properties": {
    "iso:country":"BE",
    "sg:address":"Woestenseweg 7",
    "sg:city":"Poperinge",
    "sg:orig_category":"Rundveehouders",
    "sg:phone":"+32 57 33 33 95",
    "sg:postcode":"8970",
    "sg:province":"West-Vlaanderen",
    "wof:name":"Paul Lebbe",
    "wof:placetype":"venue"
},
  "geometry": {"coordinates":[2.7432079315,50.8756942749],"type":"Point"}
}