{
  "type": "Feature",
  "properties": {
    "addr:full":"Chauss\u00c9e De Ninove 555 Anderlecht/anderlecht Bruxelles-Capitale 1070",
    "addr:housenumber":"555",
    "addr:postcode":"1070",
    "addr:street":"Chausse\u0301E De Ninove",
    "iso:country":"BE",
    "sg:address":"Chauss\u00c9e De Ninove 555",
    "sg:city":"Anderlecht/anderlecht",
    "sg:orig_category":"Pain, p\u00e2tisseries and confiseries",
    "sg:phone":"+32 2 414 77 17",
    "sg:postcode":"1070",
    "sg:province":"Bruxelles-Capitale",
    "wof:name":"Boulangerie Chambord",
    "wof:placetype":"venue"
},
  "geometry": {"coordinates":[4.3020300865,50.847328186],"type":"Point"}
}