{
  "type": "Feature",
  "properties": {
    "iso:country":"BE",
    "sg:address":"Amerikaanse Straat 191",
    "sg:city":"Elsene/ixelles",
    "sg:orig_category":"Artsen and specialisten",
    "sg:phone":"+32 2 647 41 69",
    "sg:postcode":"1050",
    "sg:province":"Bruxelles-Capitale",
    "wof:name":"Marcel Demoulin",
    "wof:placetype":"venue"
},
  "geometry": {"coordinates":[4.3640270233,50.8215446472],"type":"Point"}
}