{
  "type": "Feature",
  "properties": {
    "addr:full":"Europalaan 13 Maasmechelen Limburg 3630",
    "addr:housenumber":"13",
    "addr:postcode":"3630",
    "addr:street":"Europalaan",
    "iso:country":"BE",
    "sg:address":"Europalaan 13",
    "sg:city":"Maasmechelen",
    "sg:orig_category":"Advocaten and juridische adviseurs",
    "sg:phone":"+32 89 76 32 88",
    "sg:postcode":"3630",
    "sg:province":"Limburg",
    "wof:name":"Guy Craybex",
    "wof:placetype":"venue"
},
  "geometry": {"coordinates":[5.6961350441,50.963848114],"type":"Point"}
}