{
  "type": "Feature",
  "properties": {
    "iso:country":"BE",
    "sg:address":"Marcel Windelsstraat 60",
    "sg:city":"Waregem",
    "sg:classifiers":[
        {
            "category":"Professional",
            "subcategory":"Management & Consulting",
            "type":"Services"
        }
    ],
    "sg:phone":"+32 56 61 00 95",
    "sg:postcode":"8790",
    "sg:province":"West-Vlaanderen",
    "sg:tags":[
        "consultant"
    ],
    "wof:name":"Ibso",
    "wof:placetype":"venue"
},
  "geometry": {"coordinates":[3.4324979782,50.8914718628],"type":"Point"}
}