{
  "type": "Feature",
  "properties": {
    "addr:full":"Huidevettersstraat 53 Antwerpen Antwerpen 2000",
    "addr:housenumber":"53",
    "addr:postcode":"2000",
    "addr:street":"Huidevettersstraat",
    "iso:country":"BE",
    "sg:address":"Huidevettersstraat 53",
    "sg:city":"Antwerpen",
    "sg:orig_category":"Parfumeries",
    "sg:phone":"+32 3 226 11 09",
    "sg:postcode":"2000",
    "sg:province":"Antwerpen",
    "wof:name":"Ici Paris Xl",
    "wof:placetype":"venue"
},
  "geometry": {"coordinates":[4.4050278664,51.2164497375],"type":"Point"}
}