{
  "type": "Feature",
  "properties": {
    "iso:country":"BE",
    "sg:address":"Industriestraat 12",
    "sg:city":"Ruiselede",
    "sg:orig_category":"Non-Classified Establishments",
    "sg:phone":"+32 51 68 82 53",
    "sg:postcode":"8755",
    "sg:province":"West-Vlaanderen",
    "wof:name":"Lamo Import-export Nv",
    "wof:placetype":"venue"
},
  "geometry": {"coordinates":[3.4095709324,51.045955658],"type":"Point"}
}