{
  "type": "Feature",
  "properties": {
    "iso:country":"BE",
    "sg:address":"Chauss\u00c9e De Waterloo 504",
    "sg:city":"Elsene/ixelles",
    "sg:orig_category":"Boucheries",
    "sg:phone":"+32 2 534 69 67",
    "sg:postcode":"1050",
    "sg:province":"Bruxelles-Capitale",
    "wof:name":"Dobbelaere",
    "wof:placetype":"venue"
},
  "geometry": {"coordinates":[4.3594169617,50.8203125],"type":"Point"}
}