{
  "type": "Feature",
  "properties": {
    "addr:full":"Korte Altaarstraat 9 Antwerpen Antwerpen 2018",
    "addr:housenumber":"9",
    "addr:postcode":"2018",
    "addr:street":"Korte Altaarstraat",
    "iso:country":"BE",
    "sg:address":"Korte Altaarstraat 9",
    "sg:city":"Antwerpen",
    "sg:orig_category":"Diverse zakelijke dienstverlening Installatie van houten of kunststof schrijnwerk Organisatie van be",
    "sg:phone":"+32 3 235 58 35",
    "sg:postcode":"2018",
    "sg:province":"Antwerpen",
    "wof:name":"Gulix En Partners",
    "wof:placetype":"venue"
},
  "geometry": {"coordinates":[4.4313879013,51.2070884705],"type":"Point"}
}