{
  "type": "Feature",
  "properties": {
    "iso:country":"BE",
    "sg:address":"Pelikaansstraat 96",
    "sg:city":"Antwerpen",
    "sg:orig_category":"Produits interm\u00e9diaires Gr",
    "sg:phone":"+32 3 232 53 17",
    "sg:postcode":"2018",
    "sg:province":"Antwerpen",
    "wof:name":"Rubin & Son",
    "wof:placetype":"venue"
},
  "geometry": {"coordinates":[4.4205780029,51.2137985229],"type":"Point"}
}