{
  "type": "Feature",
  "properties": {
    "iso:country":"BE",
    "sg:address":"Rue Dernier Patard 99",
    "sg:city":"Genappe",
    "sg:orig_category":"Rundveehouders",
    "sg:phone":"+32 67 77 22 91",
    "sg:postcode":"1470",
    "sg:province":"Brabant Wallon",
    "wof:name":"Jean-pierre Gossiaux",
    "wof:placetype":"venue"
},
  "geometry": {"coordinates":[4.4532408714,50.5690727234],"type":"Point"}
}