{
  "type": "Feature",
  "properties": {
    "iso:country":"BE",
    "sg:address":"Alphonse Renardstraat 29",
    "sg:city":"Elsene/ixelles",
    "sg:orig_category":"Architecten",
    "sg:phone":"+32 2 344 44 72",
    "sg:postcode":"1050",
    "sg:province":"Bruxelles-Capitale",
    "wof:name":"Diane Busselen",
    "wof:placetype":"venue"
},
  "geometry": {"coordinates":[4.3580131531,50.8179855347],"type":"Point"}
}