{
  "type": "Feature",
  "properties": {
    "addr:full":"Rue Du Moulin 29 Li\u00e8ge 1 (bressoux) Li\u00e8ge 4020",
    "addr:housenumber":"29;1",
    "addr:postcode":"4020",
    "addr:street":"Rue Du Moulin",
    "iso:country":"BE",
    "sg:address":"Rue Du Moulin 29",
    "sg:city":"Li\u00e8ge 1 (bressoux)",
    "sg:classifiers":[
        {
            "category":"Shopping",
            "subcategory":"Baby Store",
            "type":"Retail Goods"
        }
    ],
    "sg:phone":"+32 4 342 80 25",
    "sg:postcode":"4020",
    "sg:province":"Li\u00e8ge",
    "sg:tags":[
        "-",
        "accessory"
    ],
    "wof:name":"Confort Du Bebe Sprl",
    "wof:placetype":"venue"
},
  "geometry": {"coordinates":[5.5946941376,50.6407203674],"type":"Point"}
}