{
  "type": "Feature",
  "properties": {
    "iso:country":"BE",
    "sg:address":"Christinastraat 48",
    "sg:city":"Oostende",
    "sg:orig_category":"Telecommunicatieapparaten",
    "sg:phone":"+32 59 80 63 03",
    "sg:postcode":"8400",
    "sg:province":"West-Vlaanderen",
    "wof:name":"Doomtronix",
    "wof:placetype":"venue"
},
  "geometry": {"coordinates":[2.9168179035,51.2312431335],"type":"Point"}
}