{
  "type": "Feature",
  "properties": {
    "addr:full":"Maria Theresiastraat 12a Leuven Vlaams-Brabant 3000",
    "addr:housenumber":"12a",
    "addr:postcode":"3000",
    "addr:street":"Maria Theresiastraat",
    "iso:country":"BE",
    "sg:address":"Maria Theresiastraat 12a",
    "sg:city":"Leuven",
    "sg:classifiers":[
        {
            "category":"Personal",
            "subcategory":"Beauty Salon",
            "type":"Services"
        }
    ],
    "sg:phone":"+32 16 22 84 67",
    "sg:postcode":"3000",
    "sg:province":"Vlaams-Brabant",
    "sg:tags":[
        "equipment",
        "hairdressing",
        "-",
        "supply"
    ],
    "wof:name":"Goossens",
    "wof:placetype":"venue"
},
  "geometry": {"coordinates":[4.7097458839,50.8765029907],"type":"Point"}
}