{
  "type": "Feature",
  "properties": {
    "addr:full":"Hertsbergeveldstraat 16 Wingene West-Vlaanderen 8750",
    "addr:housenumber":"16",
    "addr:postcode":"8750",
    "addr:street":"Hertsbergeveldstraat",
    "iso:country":"BE",
    "sg:address":"Hertsbergeveldstraat 16",
    "sg:city":"Wingene",
    "sg:orig_category":"Eleveurs and marchands de porcs",
    "sg:phone":"+32 51 65 54 47",
    "sg:postcode":"8750",
    "sg:province":"West-Vlaanderen",
    "wof:name":"Vander Meulen & Deforche",
    "wof:placetype":"venue"
},
  "geometry": {"coordinates":[3.2690150738,51.0870933533],"type":"Point"}
}