{
  "type": "Feature",
  "properties": {
    "addr:full":"Stadionlaan 5 Denderleeuw (groot) Oost-Vlaanderen 9470",
    "addr:housenumber":"5",
    "addr:postcode":"9470",
    "addr:street":"Stadionlaan;Groot Oost-Vlaanderen",
    "iso:country":"BE",
    "sg:address":"Stadionlaan 5",
    "sg:city":"Denderleeuw (groot)",
    "sg:orig_category":"Sportclubs Sportterreinen and installaties behalve sportcentra",
    "sg:phone":"+32 53 66 91 92",
    "sg:postcode":"9470",
    "sg:province":"Oost-Vlaanderen",
    "wof:name":"Fc Denderleeuw",
    "wof:placetype":"venue"
},
  "geometry": {"coordinates":[4.0732707977,50.8841552734],"type":"Point"}
}