{
  "type": "Feature",
  "properties": {
    "addr:full":"Z.i. 4\u00e8me Avenue 114 Herstal Li\u00e8ge 4040",
    "addr:housenumber":"114",
    "addr:postcode":"4040",
    "addr:street":"Z.I. 4E\u0300Me",
    "iso:country":"BE",
    "sg:address":"Z.i. 4\u00e8me Avenue 114",
    "sg:city":"Herstal",
    "sg:classifiers":[
        {
            "category":"Manufacturing",
            "subcategory":"Tools & Machinery",
            "type":"Manufacturing & Wholesale Goods"
        }
    ],
    "sg:phone":"+32 64 67 15 00",
    "sg:postcode":"4040",
    "sg:province":"Li\u00e8ge",
    "sg:tags":[
        "equipment",
        "measurement",
        "-",
        "precision",
        "instrument"
    ],
    "wof:name":"Thermibel Sa",
    "wof:placetype":"venue"
},
  "geometry": {"coordinates":[4.1505050659,50.4826698303],"type":"Point"}
}