{
  "type": "Feature",
  "properties": {
    "iso:country":"BE",
    "sg:address":"Hijftestraat 43",
    "sg:city":"Lochristi",
    "sg:classifiers":[
        {
            "category":"Food & Beverages",
            "subcategory":"Fruits & Vegetables",
            "type":"Retail Goods"
        }
    ],
    "sg:phone":"+32 9 355 52 86",
    "sg:postcode":"9080",
    "sg:province":"Oost-Vlaanderen",
    "sg:tags":[
        "l\u00e9gumes",
        "gr"
    ],
    "wof:name":"Flore Serafien",
    "wof:placetype":"venue"
},
  "geometry": {"coordinates":[3.8174989223,51.1037559509],"type":"Point"}
}