{
  "type": "Feature",
  "properties": {
    "iso:country":"BE",
    "sg:address":"Rue Des Etampes 2",
    "sg:city":"Mons",
    "sg:orig_category":"Algemeen secundair onderwijs",
    "sg:phone":"+32 65 33 58 05",
    "sg:postcode":"7000",
    "sg:province":"Hainaut",
    "wof:name":"Ath\u00c9n\u00c9e Provincial",
    "wof:placetype":"venue"
},
  "geometry": {"coordinates":[3.9523398876,50.4567909241],"type":"Point"}
}