{
  "type": "Feature",
  "properties": {
    "addr:full":"Beverststraat 33 Bilzen (beverst) Limburg 3740",
    "addr:housenumber":"33",
    "addr:postcode":"3740",
    "addr:street":"Beverststraat",
    "iso:country":"BE",
    "sg:address":"Beverststraat 33",
    "sg:city":"Bilzen (beverst)",
    "sg:classifiers":[
        {
            "category":"Fast Food",
            "type":"Food & Drink"
        }
    ],
    "sg:phone":"+32 89 79 32 44",
    "sg:postcode":"3740",
    "sg:province":"Limburg",
    "sg:tags":[
        "fried",
        "stand",
        "potato"
    ],
    "wof:name":"Letitia",
    "wof:placetype":"venue"
},
  "geometry": {"coordinates":[5.4720458984,50.8928413391],"type":"Point"}
}