{
  "type": "Feature",
  "properties": {
    "addr:full":"Rue Du Relais 105 Elsene/ixelles Bruxelles-Capitale 1050",
    "addr:housenumber":"105",
    "addr:postcode":"1050",
    "addr:street":"Rue Du Relais",
    "iso:country":"BE",
    "sg:address":"Rue Du Relais 105",
    "sg:city":"Elsene/ixelles",
    "sg:orig_category":"Architecten",
    "sg:phone":"+32 2 675 85 08",
    "sg:postcode":"1050",
    "sg:province":"Bruxelles-Capitale",
    "wof:name":"Fares B.",
    "wof:placetype":"venue"
},
  "geometry": {"coordinates":[4.3950548172,50.8095855713],"type":"Point"}
}