{
  "type": "Feature",
  "properties": {
    "addr:full":"Appelmansstraat 19 Antwerpen Antwerpen 2018",
    "addr:housenumber":"19",
    "addr:postcode":"2018",
    "addr:street":"Appelmansstraat",
    "iso:country":"BE",
    "sg:address":"Appelmansstraat 19",
    "sg:city":"Antwerpen",
    "sg:orig_category":"Bijouteries and horlogeries",
    "sg:phone":"+32 3 231 97 80",
    "sg:postcode":"2018",
    "sg:province":"Antwerpen",
    "wof:name":"Huis Katz J.",
    "wof:placetype":"venue"
},
  "geometry": {"coordinates":[4.4176239967,51.216758728],"type":"Point"}
}