{
  "type": "Feature",
  "properties": {
    "iso:country":"BE",
    "sg:address":"Jean Paquotstraat 34",
    "sg:city":"Elsene/ixelles",
    "sg:orig_category":"Bloemen and planten",
    "sg:phone":"+32 2 646 64 35",
    "sg:postcode":"1050",
    "sg:province":"Bruxelles-Capitale",
    "wof:name":"Vert Olive",
    "wof:placetype":"venue"
},
  "geometry": {"coordinates":[4.3782558441,50.8267211914],"type":"Point"}
}