{
  "type": "Feature",
  "properties": {
    "iso:country":"BE",
    "sg:address":"Route De Neufch\u00c2teau 74",
    "sg:city":"Belgium",
    "sg:orig_category":"Diverse bouwafwerking and reiniging Kantoormateriaal Kantoormateriaal Gh",
    "sg:phone":"+32 61 22 37 43",
    "sg:postcode":"6800",
    "sg:province":"Luxembourg",
    "wof:name":"Noel Bureau/ets. Th\u00c9o No\u00cbl",
    "wof:placetype":"venue"
},
  "geometry": {"coordinates":[5.5333762169,49.9024543762],"type":"Point"}
}