{
  "type": "Feature",
  "properties": {
    "addr:full":"Meir 47 Antwerpen Antwerpen 2000",
    "addr:housenumber":"47",
    "addr:postcode":"2000",
    "addr:street":"Meir",
    "iso:country":"BE",
    "sg:address":"Meir 47",
    "sg:city":"Antwerpen",
    "sg:classifiers":[
        {
            "category":"Personal",
            "subcategory":"Beauty Salon",
            "type":"Services"
        }
    ],
    "sg:phone":"+32 3 289 89 09",
    "sg:postcode":"2000",
    "sg:province":"Antwerpen",
    "sg:tags":[
        "lady",
        "-",
        "hairdressing"
    ],
    "wof:name":"Kenzo Coiffure",
    "wof:placetype":"venue"
},
  "geometry": {"coordinates":[4.4083528519,51.2182579041],"type":"Point"}
}