{
  "type": "Feature",
  "properties": {
    "addr:full":"Woeringenstraat 73 Gent Oost-Vlaanderen 9000",
    "addr:housenumber":"73",
    "addr:postcode":"9000",
    "addr:street":"Woeringenstraat;Oost-Vlaanderen",
    "iso:country":"BE",
    "sg:address":"Woeringenstraat 73",
    "sg:city":"Gent",
    "sg:orig_category":"Mat\u00e9riel m\u00e9dical and orthop\u00e9dique and proth\u00e8ses Fab",
    "sg:phone":"+32 9 221 27 00",
    "sg:postcode":"9000",
    "sg:province":"Oost-Vlaanderen",
    "wof:name":"Dental Labo De Smedt",
    "wof:placetype":"venue"
},
  "geometry": {"coordinates":[3.7162849903,51.0326271057],"type":"Point"}
}