{
  "type": "Feature",
  "properties": {
    "addr:full":"Boulevard De La Sauveni\u00c8re 83 Luik Li\u00e8ge 4000",
    "addr:housenumber":"83",
    "addr:postcode":"4000",
    "addr:street":"Boulevard De La Sauvenie\u0300Re",
    "iso:country":"BE",
    "sg:address":"Boulevard De La Sauveni\u00c8re 83",
    "sg:city":"Luik",
    "sg:orig_category":"Articles m\u00e9dicaux and orthop\u00e9diques",
    "sg:phone":"+32 4 223 74 66",
    "sg:postcode":"4000",
    "sg:province":"Li\u00e8ge",
    "wof:name":"Audipha",
    "wof:placetype":"venue"
},
  "geometry": {"coordinates":[5.5661568642,50.6429977417],"type":"Point"}
}