{
  "type": "Feature",
  "properties": {
    "iso:country":"BE",
    "sg:address":"Rue Neuve 12",
    "sg:city":"Villers-le-bouillet",
    "sg:orig_category":"Installatie van houten of kunststof schrijnwerk",
    "sg:phone":"+32 85 21 14 20",
    "sg:postcode":"4530",
    "sg:province":"Li\u00e8ge",
    "wof:name":"Alain Tilquin",
    "wof:placetype":"venue"
},
  "geometry": {"coordinates":[5.2669939995,50.5654754639],"type":"Point"}
}