{
  "type": "Feature",
  "properties": {
    "addr:full":"Grote Thems 1bc Brugge West-Vlaanderen 8200",
    "addr:housenumber":"1bc",
    "addr:postcode":"8200",
    "addr:street":"Grote Thems",
    "iso:country":"BE",
    "sg:address":"Grote Thems 1bc",
    "sg:city":"Brugge",
    "sg:orig_category":"Experts-comptables",
    "sg:phone":"+32 50 39 15 96",
    "sg:postcode":"8200",
    "sg:province":"West-Vlaanderen",
    "wof:name":"Ludo Lievens",
    "wof:placetype":"venue"
},
  "geometry": {"coordinates":[3.1904699802,51.1992111206],"type":"Point"}
}