{
  "type": "Feature",
  "properties": {
    "iso:country":"BE",
    "sg:address":"Rue Trou Du Mont",
    "sg:city":"Comblain-au-pont",
    "sg:classifiers":[
        {
            "category":"Home & Garden",
            "subcategory":"Building Materials",
            "type":"Retail Goods"
        }
    ],
    "sg:phone":"+32 4 380 29 67",
    "sg:postcode":"4170",
    "sg:province":"Li\u00e8ge",
    "sg:tags":[
        "granite",
        "stone",
        "natural",
        "marble"
    ],
    "wof:name":"Flay-co Sprl",
    "wof:placetype":"venue"
},
  "geometry": {"coordinates":[5.5722699165,50.4899787903],"type":"Point"}
}