{
  "type": "Feature",
  "properties": {
    "iso:country":"BE",
    "sg:address":"Pontstraat 87",
    "sg:city":"Sint-martens-latem (deurle)",
    "sg:orig_category":"Fairs, shows, exhibitions",
    "sg:phone":"+32 9 282 99 76",
    "sg:postcode":"9831",
    "sg:province":"Oost-Vlaanderen",
    "wof:name":"Van Heuverswijn Gcv",
    "wof:placetype":"venue"
},
  "geometry": {"coordinates":[3.5970959663,51.0089950562],"type":"Point"}
}