{
  "type": "Feature",
  "properties": {
    "iso:country":"BE",
    "sg:address":"Tervuursevest 101",
    "sg:city":"Leuven",
    "sg:orig_category":"M\u00e9decins and sp\u00e9cialistes",
    "sg:phone":"+32 16 20 14 31",
    "sg:postcode":"3001",
    "sg:province":"Vlaams-Brabant",
    "wof:name":"Roeland Lysens",
    "wof:placetype":"venue"
},
  "geometry": {"coordinates":[4.6804161072,50.8760566711],"type":"Point"}
}