{
  "type": "Feature",
  "properties": {
    "iso:country":"BE",
    "sg:address":"Eersels 48",
    "sg:city":"Tessenderlo",
    "sg:orig_category":"Kapsalons",
    "sg:phone":"+32 13 66 36 15",
    "sg:postcode":"3980",
    "sg:province":"Limburg",
    "wof:name":"Pascale Hoobergs",
    "wof:placetype":"venue"
},
  "geometry": {"coordinates":[5.0969262123,51.0683021545],"type":"Point"}
}