{
  "type": "Feature",
  "properties": {
    "addr:full":"Rue De Sars 76 Frameries Hainaut 7080",
    "addr:housenumber":"76",
    "addr:postcode":"7080",
    "addr:street":"Rue De Sars",
    "iso:country":"BE",
    "sg:address":"Rue De Sars 76",
    "sg:city":"Frameries",
    "sg:classifiers":[
        {
            "category":"Recreation",
            "subcategory":"Fishing",
            "type":"Entertainment"
        }
    ],
    "sg:phone":"+32 65 66 91 77",
    "sg:postcode":"7080",
    "sg:province":"Hainaut",
    "sg:tags":[
        "tackle"
    ],
    "wof:name":"Aux Mille Farines",
    "wof:placetype":"venue"
},
  "geometry": {"coordinates":[3.8990280628,50.4056015015],"type":"Point"}
}