{
  "type": "Feature",
  "properties": {
    "addr:full":"Venuslaan 2 Boortmeerbeek Vlaams-Brabant 3190",
    "addr:housenumber":"2",
    "addr:postcode":"3190",
    "addr:street":"Venuslaan",
    "iso:country":"BE",
    "sg:address":"Venuslaan 2",
    "sg:city":"Boortmeerbeek",
    "sg:classifiers":[
        {
            "category":"Personal",
            "subcategory":"Beauty Salon",
            "type":"Services"
        }
    ],
    "sg:phone":"+32 15 51 20 57",
    "sg:postcode":"3190",
    "sg:province":"Vlaams-Brabant",
    "sg:tags":[
        "de",
        "coiffure"
    ],
    "wof:name":"Coiffure Jan Voor Alleman",
    "wof:placetype":"venue"
},
  "geometry": {"coordinates":[4.5792999268,50.9759368896],"type":"Point"}
}