{
  "type": "Feature",
  "properties": {
    "addr:full":"Boulevard Emile De Laveleye 191 Li\u00e8ge 1 (li\u00e8ge 2) Li\u00e8ge 4020",
    "addr:housenumber":"191;1;2",
    "addr:postcode":"4020",
    "addr:street":"Boulevard Emile De Laveleye",
    "iso:country":"BE",
    "sg:address":"Boulevard Emile De Laveleye 191",
    "sg:city":"Li\u00e8ge 1 (li\u00e8ge 2)",
    "sg:classifiers":[
        {
            "category":"Professional",
            "subcategory":"Management & Consulting",
            "type":"Services"
        }
    ],
    "sg:phone":"+32 4 340 35 02",
    "sg:postcode":"4020",
    "sg:province":"Li\u00e8ge",
    "sg:tags":[
        "consultant",
        "-",
        "legislation",
        "social"
    ],
    "wof:name":"Cong\u00e9 M\u00e9tal Asbl",
    "wof:placetype":"venue"
},
  "geometry": {"coordinates":[5.5915732384,50.6197509766],"type":"Point"}
}