{
  "type": "Feature",
  "properties": {
    "addr:full":"Rue De L'ange 57 Namur Namur 5000",
    "addr:housenumber":"57",
    "addr:postcode":"5000",
    "addr:street":"Rue De L'Ange",
    "iso:country":"BE",
    "sg:address":"Rue De L'ange 57",
    "sg:city":"Namur",
    "sg:orig_category":"Marketingbureaus",
    "sg:phone":"+32 81 23 12 97",
    "sg:postcode":"5000",
    "sg:province":"Namur",
    "wof:name":"Onauen Marketing",
    "wof:placetype":"venue"
},
  "geometry": {"coordinates":[4.8652458191,50.4638786316],"type":"Point"}
}