{
  "type": "Feature",
  "properties": {
    "addr:full":"Kasteellaan 184 Mouscron Hainaut 7700",
    "addr:housenumber":"184",
    "addr:postcode":"7700",
    "addr:street":"Kasteellaan",
    "iso:country":"BE",
    "sg:address":"Kasteellaan 184",
    "sg:city":"Mouscron",
    "sg:orig_category":"Articles textiles and tissus de d\u00e9coration Fab. Articles de f\u00eate, farces and attrapes",
    "sg:phone":"+32 56 85 50 55",
    "sg:postcode":"7700",
    "sg:province":"Hainaut",
    "wof:name":"Wollux",
    "wof:placetype":"venue"
},
  "geometry": {"coordinates":[3.2246699333,50.7473182678],"type":"Point"}
}