{
  "type": "Feature",
  "properties": {
    "iso:country":"BE",
    "sg:address":"Galerie Des Carmes 43",
    "sg:city":"Wavre",
    "sg:classifiers":[
        {
            "category":"Food & Beverages",
            "subcategory":"Chocolate",
            "type":"Retail Goods"
        }
    ],
    "sg:phone":"+32 10 24 52 81",
    "sg:postcode":"1300",
    "sg:province":"Brabant Wallon",
    "sg:tags":[
        "confectionery",
        "-"
    ],
    "wof:name":"Myst\u00e8re & Boule De Gomme",
    "wof:placetype":"venue"
},
  "geometry": {"coordinates":[4.6071801186,50.7156562805],"type":"Point"}
}