{
  "type": "Feature",
  "properties": {
    "addr:full":"Brugstraat 75 Aalter Oost-Vlaanderen 9880",
    "addr:housenumber":"75",
    "addr:postcode":"9880",
    "addr:street":"Brugstraat",
    "iso:country":"BE",
    "sg:address":"Brugstraat 75",
    "sg:city":"Aalter",
    "sg:orig_category":"Binnenhuisarchitecten",
    "sg:phone":"+32 9 375 25 92",
    "sg:postcode":"9880",
    "sg:province":"Oost-Vlaanderen",
    "wof:name":"Idylle",
    "wof:placetype":"venue"
},
  "geometry": {"coordinates":[3.4421200752,51.0968208313],"type":"Point"}
}