{
  "type": "Feature",
  "properties": {
    "addr:full":"Lange Minnestraat 122 Lebbeke Oost-Vlaanderen 9280",
    "addr:housenumber":"122",
    "addr:postcode":"9280",
    "addr:street":"Lange Minnestraat",
    "iso:country":"BE",
    "sg:address":"Lange Minnestraat 122",
    "sg:city":"Lebbeke",
    "sg:orig_category":"Eleveurs de bovins",
    "sg:phone":"+32 52 35 68 85",
    "sg:postcode":"9280",
    "sg:province":"Oost-Vlaanderen",
    "wof:name":"Jan Van Mulders",
    "wof:placetype":"venue"
},
  "geometry": {"coordinates":[4.1477952003,50.9871177673],"type":"Point"}
}