{
  "type": "Feature",
  "properties": {
    "iso:country":"BE",
    "sg:address":"Maastrichterstraat 181",
    "sg:city":"Bilzen (waltwilder)",
    "sg:classifiers":[
        {
            "category":"Bars & Pubs",
            "type":"Food & Drink"
        }
    ],
    "sg:phone":"+32 89 41 52 93",
    "sg:postcode":"3740",
    "sg:province":"Limburg",
    "wof:name":"Sport",
    "wof:placetype":"venue"
},
  "geometry": {"coordinates":[5.5271902084,50.8648300171],"type":"Point"}
}