{
  "type": "Feature",
  "properties": {
    "addr:full":"Pannestraat 18 Knokke-heist West-Vlaanderen 8301",
    "addr:housenumber":"18",
    "addr:postcode":"8301",
    "addr:street":"Pannestraat",
    "iso:country":"BE",
    "sg:address":"Pannestraat 18",
    "sg:city":"Knokke-heist",
    "sg:classifiers":[
        {
            "category":"Fast Food",
            "type":"Food & Drink"
        }
    ],
    "sg:phone":"+32 50 51 77 87",
    "sg:postcode":"8301",
    "sg:province":"West-Vlaanderen",
    "sg:tags":[
        "restaurant",
        "\u00c0",
        "domicile",
        "emporter",
        "livraison",
        "restaurants"
    ],
    "wof:name":"'t Keukentje",
    "wof:placetype":"venue"
},
  "geometry": {"coordinates":[3.2639000416,51.3396911621],"type":"Point"}
}