{
  "type": "Feature",
  "properties": {
    "addr:full":"Tentoonstellingslaan 121 Gent Oost-Vlaanderen 9000",
    "addr:housenumber":"121",
    "addr:postcode":"9000",
    "addr:street":"Tentoonstellingslaan;Oost-Vlaanderen",
    "iso:country":"BE",
    "sg:address":"Tentoonstellingslaan 121",
    "sg:city":"Gent",
    "sg:orig_category":"Newspapers, magazines, periodicals - Distribution",
    "sg:phone":"+32 9 223 70 34",
    "sg:postcode":"9000",
    "sg:province":"Oost-Vlaanderen",
    "wof:name":"News Shop",
    "wof:placetype":"venue"
},
  "geometry": {"coordinates":[3.7326300144,51.0401611328],"type":"Point"}
}