{
  "type": "Feature",
  "properties": {
    "iso:country":"BE",
    "sg:address":"Rue De La Hamaide 75",
    "sg:city":"Saint-ghislain (tertre)",
    "sg:classifiers":[
        {
            "category":"Wholesale",
            "subcategory":"Scrap",
            "type":"Manufacturing & Wholesale Goods"
        }
    ],
    "sg:phone":"+32 65 62 14 20",
    "sg:postcode":"7333",
    "sg:province":"Hainaut",
    "sg:tags":[
        "metal"
    ],
    "wof:name":"Hainaut Recyclage Sa",
    "wof:placetype":"venue"
},
  "geometry": {"coordinates":[3.8111400604,50.4655151367],"type":"Point"}
}