{
  "type": "Feature",
  "properties": {
    "iso:country":"BE",
    "sg:address":"Ninoofsesteenweg 63",
    "sg:city":"Halle",
    "sg:classifiers":[
        {
            "category":"Health Services",
            "subcategory":"Dentist",
            "type":"Services"
        }
    ],
    "sg:phone":"+32 2 356 55 00",
    "sg:postcode":"1500",
    "sg:province":"Vlaams-Brabant",
    "wof:name":"Minner P",
    "wof:placetype":"venue"
},
  "geometry": {"coordinates":[4.2339258194,50.7378425598],"type":"Point"}
}