{
  "type": "Feature",
  "properties": {
    "iso:country":"BE",
    "sg:address":"Lembergesteenweg 40",
    "sg:city":"Merelbeke",
    "sg:orig_category":"Bloemen and planten Gh",
    "sg:phone":"+32 9 230 77 46",
    "sg:postcode":"9820",
    "sg:province":"Oost-Vlaanderen",
    "wof:name":"Bockstaele",
    "wof:placetype":"venue"
},
  "geometry": {"coordinates":[3.7534370422,50.9930076599],"type":"Point"}
}