{
  "type": "Feature",
  "properties": {
    "iso:country":"BE",
    "sg:address":"Ten Doorn 3",
    "sg:city":"Mechelen (heffen)",
    "sg:classifiers":[
        {
            "category":"Professional",
            "subcategory":"Art Services",
            "type":"Services"
        }
    ],
    "sg:phone":"+32 3 886 43 57",
    "sg:postcode":"2801",
    "sg:province":"Antwerpen",
    "sg:tags":[
        "interior",
        "designer"
    ],
    "wof:name":"Horsten K",
    "wof:placetype":"venue"
},
  "geometry": {"coordinates":[4.4090800285,51.0511474609],"type":"Point"}
}