{
  "type": "Feature",
  "properties": {
    "iso:country":"BE",
    "sg:address":"Kapellekensdreef 32",
    "sg:city":"Heist-op-den-berg (wiekevorst)",
    "sg:classifiers":[
        {
            "category":"Building & Trades",
            "subcategory":"Construction",
            "type":"Services"
        }
    ],
    "sg:phone":"+32 14 27 71 57",
    "sg:postcode":"2222",
    "sg:province":"Antwerpen",
    "sg:tags":[
        "carpenter"
    ],
    "wof:name":"P.o.f.",
    "wof:placetype":"venue"
},
  "geometry": {"coordinates":[4.7292399406,51.1032218933],"type":"Point"}
}