{
  "type": "Feature",
  "properties": {
    "iso:country":"BE",
    "sg:address":"Koningin Astridlaan 60",
    "sg:city":"Maaseik",
    "sg:classifiers":[
        {
            "category":"Cafe",
            "type":"Food & Drink"
        }
    ],
    "sg:phone":"+32 89 56 55 99",
    "sg:postcode":"3680",
    "sg:province":"Limburg",
    "sg:tags":[
        "caf\u00e9s"
    ],
    "wof:name":"Caf\u00c9 Quarpinska",
    "wof:placetype":"venue"
},
  "geometry": {"coordinates":[5.7771639824,51.0987243652],"type":"Point"}
}