{
  "type": "Feature",
  "properties": {
    "addr:full":"Moerestraat 63 Koekelare West-Vlaanderen 8680",
    "addr:housenumber":"63",
    "addr:postcode":"8680",
    "addr:street":"Moerestraat",
    "iso:country":"BE",
    "sg:address":"Moerestraat 63",
    "sg:city":"Koekelare",
    "sg:classifiers":[
        {
            "category":"Shopping",
            "subcategory":"Florist",
            "type":"Retail Goods"
        }
    ],
    "sg:phone":"+32 51 58 10 19",
    "sg:postcode":"8680",
    "sg:province":"West-Vlaanderen",
    "wof:name":"De Papaver Bvba",
    "wof:placetype":"venue"
},
  "geometry": {"coordinates":[2.979968071,51.094871521],"type":"Point"}
}