{
  "type": "Feature",
  "properties": {
    "iso:country":"BE",
    "sg:address":"Rue Heyvaert 80",
    "sg:city":"Bruxelles (anderlecht)",
    "sg:classifiers":[
        {
            "category":"Retail",
            "subcategory":"Auto Repair",
            "type":"Services"
        }
    ],
    "sg:phone":"+32 2 520 50 00",
    "sg:postcode":"1070",
    "sg:province":"Bruxelles-Capitale",
    "sg:tags":[
        "automobile",
        "-",
        "wrecking"
    ],
    "wof:name":"Tofico Belgium Sa",
    "wof:placetype":"venue"
},
  "geometry": {"coordinates":[4.3332428932,50.8474121094],"type":"Point"}
}