{
  "type": "Feature",
  "properties": {
    "addr:full":"Rue Xhav\u00c9e 49 Verviers Li\u00e8ge 4800",
    "addr:housenumber":"49",
    "addr:postcode":"4800",
    "addr:street":"Rue Xhave\u0301E",
    "iso:country":"BE",
    "sg:address":"Rue Xhav\u00c9e 49",
    "sg:city":"Verviers",
    "sg:orig_category":"Agences d\u00b4interim and personnel temporaire",
    "sg:phone":"+32 87 31 69 03",
    "sg:postcode":"4800",
    "sg:province":"Li\u00e8ge",
    "wof:name":"Creyf\u00b4s Interim",
    "wof:placetype":"venue"
},
  "geometry": {"coordinates":[5.858725071,50.591003418],"type":"Point"}
}