{
  "type": "Feature",
  "properties": {
    "addr:full":"Rue De La D\u00e9portation 126 Tubize Brabant Wallon 1480",
    "addr:housenumber":"126",
    "addr:postcode":"1480",
    "addr:street":"Rue De La De\u0301Portation;Wallon",
    "iso:country":"BE",
    "sg:address":"Rue De La D\u00e9portation 126",
    "sg:city":"Tubize",
    "sg:classifiers":[
        {
            "category":"Professional",
            "subcategory":"Art Services",
            "type":"Services"
        }
    ],
    "sg:phone":"+32 2 355 69 06",
    "sg:postcode":"1480",
    "sg:province":"Brabant Wallon",
    "sg:tags":[
        "picture",
        "framer"
    ],
    "wof:name":"Nadia",
    "wof:placetype":"venue"
},
  "geometry": {"coordinates":[4.2114171982,50.6910552979],"type":"Point"}
}