{
  "type": "Feature",
  "properties": {
    "addr:full":"Turnhoutsebaan 645 Wijnegem Antwerpen 2110",
    "addr:housenumber":"645",
    "addr:postcode":"2110",
    "addr:street":"Turnhoutsebaan",
    "iso:country":"BE",
    "sg:address":"Turnhoutsebaan 645",
    "sg:city":"Wijnegem",
    "sg:classifiers":[
        {
            "category":"Health Services",
            "subcategory":"Dentist",
            "type":"Services"
        }
    ],
    "sg:phone":"+32 3 353 20 84",
    "sg:postcode":"2110",
    "sg:province":"Antwerpen",
    "wof:name":"Van Daele A",
    "wof:placetype":"venue"
},
  "geometry": {"coordinates":[4.5521798134,51.2310600281],"type":"Point"}
}