{
  "type": "Feature",
  "properties": {
    "addr:full":"Avenue De L'astronomie 13 Sint-joost-ten-node/saint-josse-ten-noode Bruxelles-Capitale 1210",
    "addr:housenumber":"13",
    "addr:postcode":"1210",
    "addr:street":"Avenue De L'Astronomie",
    "iso:country":"BE",
    "sg:address":"Avenue De L'astronomie 13",
    "sg:city":"Sint-joost-ten-node/saint-josse-ten-noode",
    "sg:classifiers":[
        {
            "category":"Health Services",
            "subcategory":"Nursing And Care Facility",
            "type":"Services"
        }
    ],
    "sg:phone":"+32 2 220 26 11",
    "sg:postcode":"1210",
    "sg:province":"Bruxelles-Capitale",
    "sg:tags":[
        "public"
    ],
    "wof:name":"Gemeentebestuur",
    "wof:placetype":"venue"
},
  "geometry": {"coordinates":[4.3692059517,50.8508987427],"type":"Point"}
}