{
  "type": "Feature",
  "properties": {
    "addr:full":"Josse Goffinlaan 75 Sint-agatha-berchem/berchem-sainte-agathe Bruxelles-Capitale 1082",
    "addr:housenumber":"75",
    "addr:postcode":"1082",
    "addr:street":"Josse Goffinlaan;/",
    "iso:country":"BE",
    "sg:address":"Josse Goffinlaan 75",
    "sg:city":"Sint-agatha-berchem/berchem-sainte-agathe",
    "sg:orig_category":"Kapsalons",
    "sg:phone":"+32 2 465 81 93",
    "sg:postcode":"1082",
    "sg:province":"Bruxelles-Capitale",
    "wof:name":"Coiffure Claude",
    "wof:placetype":"venue"
},
  "geometry": {"coordinates":[4.3011989594,50.8655052185],"type":"Point"}
}