{
  "type": "Feature",
  "properties": {
    "iso:country":"BE",
    "sg:address":"Les Champs Morais 82",
    "sg:city":"Bertrix",
    "sg:classifiers":[
        {
            "category":"Social Services",
            "type":"Services"
        }
    ],
    "sg:phone":"+32 61 41 51 90",
    "sg:postcode":"6880",
    "sg:province":"Luxembourg",
    "wof:name":"Avj Bertrix-lux",
    "wof:placetype":"venue"
},
  "geometry": {"coordinates":[5.2669529915,49.8524971008],"type":"Point"}
}