{
  "type": "Feature",
  "properties": {
    "addr:full":"Route De Philippeville 81 Florennes Namur 5620",
    "addr:housenumber":"81",
    "addr:postcode":"5620",
    "addr:street":"Route De Philippeville",
    "iso:country":"BE",
    "sg:address":"Route De Philippeville 81",
    "sg:city":"Florennes",
    "sg:orig_category":"Herstellingen and onderhoud van auto's",
    "sg:phone":"+32 71 68 97 33",
    "sg:postcode":"5620",
    "sg:province":"Namur",
    "wof:name":"B. Toussaint",
    "wof:placetype":"venue"
},
  "geometry": {"coordinates":[4.6011219025,50.2347412109],"type":"Point"}
}