{
  "type": "Feature",
  "properties": {
    "iso:country":"BE",
    "sg:address":"Place L\u00c9on D'adrimont 47",
    "sg:city":"Limbourg",
    "sg:classifiers":[
        {
            "category":"Restaurant",
            "type":"Food & Drink"
        }
    ],
    "sg:phone":"+32 87 76 35 92",
    "sg:postcode":"4830",
    "sg:province":"Li\u00e8ge",
    "wof:name":"A La Fontaine",
    "wof:placetype":"venue"
},
  "geometry": {"coordinates":[5.9423789978,50.6207466125],"type":"Point"}
}