{
  "type": "Feature",
  "properties": {
    "addr:full":"Rue Des Pr\u00e9montr\u00e9s 2 Li\u00e8ge 1 Li\u00e8ge 4000",
    "addr:housenumber":"2;1",
    "addr:postcode":"4000",
    "addr:street":"Rue Des Pre\u0301Montre\u0301S",
    "iso:country":"BE",
    "sg:address":"Rue Des Pr\u00e9montr\u00e9s 2",
    "sg:city":"Li\u00e8ge 1",
    "sg:classifiers":[
        {
            "category":"Professional",
            "subcategory":"Lawyer & Legal Services",
            "type":"Services"
        }
    ],
    "sg:phone":"+32 4 250 08 01",
    "sg:postcode":"4000",
    "sg:province":"Li\u00e8ge",
    "wof:name":"Cruyplants-eloy-hupin & Associes",
    "wof:placetype":"venue"
},
  "geometry": {"coordinates":[5.5736570358,50.6385421753],"type":"Point"}
}