{
  "type": "Feature",
  "properties": {
    "addr:full":"Kielenstraat 81 Box 9 Tongeren Limburg 3700",
    "addr:housenumber":"81;9",
    "addr:postcode":"3700",
    "addr:street":"Kielenstraat;Box",
    "iso:country":"BE",
    "sg:address":"Kielenstraat 81 Box 9",
    "sg:city":"Tongeren",
    "sg:classifiers":[
        {
            "category":"Professional",
            "subcategory":"Lawyer & Legal Services",
            "type":"Services"
        }
    ],
    "sg:phone":"+32 12 39 18 78",
    "sg:postcode":"3700",
    "sg:province":"Limburg",
    "wof:name":"Reard Jean",
    "wof:placetype":"venue"
},
  "geometry": {"coordinates":[5.4695529938,50.7797660828],"type":"Point"}
}