{
  "type": "Feature",
  "properties": {
    "addr:full":"Dorp 14b1 Herselt Antwerpen 2230",
    "addr:housenumber":"14b1",
    "addr:postcode":"2230",
    "addr:street":"Dorp",
    "iso:country":"BE",
    "sg:address":"Dorp 14b1",
    "sg:city":"Herselt",
    "sg:orig_category":"Banken and kredietinstellingen Verzekeringsmakelaars and experts",
    "sg:phone":"+32 14 54 26 35",
    "sg:postcode":"2230",
    "sg:province":"Antwerpen",
    "wof:name":"Groep Argenta",
    "wof:placetype":"venue"
},
  "geometry": {"coordinates":[4.8793859482,51.0518722534],"type":"Point"}
}