{
  "type": "Feature",
  "properties": {
    "iso:country":"BE",
    "sg:address":"Rue Uyttenhove 49",
    "sg:city":"Jette",
    "sg:orig_category":"D\u00e9taillants en pi\u00e8ces and accessoires de voitures",
    "sg:phone":"+32 2 421 00 00",
    "sg:postcode":"1090",
    "sg:province":"Bruxelles-Capitale",
    "wof:name":"Opel Parts Recup",
    "wof:placetype":"venue"
},
  "geometry": {"coordinates":[4.338092804,50.871055603],"type":"Point"}
}