{
  "type": "Feature",
  "properties": {
    "addr:full":"Beertegemstraat 64 Zingem Oost-Vlaanderen 9750",
    "addr:housenumber":"64",
    "addr:postcode":"9750",
    "addr:street":"Beertegemstraat",
    "iso:country":"BE",
    "sg:address":"Beertegemstraat 64",
    "sg:city":"Zingem",
    "sg:orig_category":"Maatkleding Fab",
    "sg:phone":"+32 9 384 29 63",
    "sg:postcode":"9750",
    "sg:province":"Oost-Vlaanderen",
    "wof:name":"Gaston Simoens",
    "wof:placetype":"venue"
},
  "geometry": {"coordinates":[3.6100199223,50.919090271],"type":"Point"}
}