{
  "type": "Feature",
  "properties": {
    "addr:full":"Provenplein 53 Poperinge West-Vlaanderen 8972",
    "addr:housenumber":"53",
    "addr:postcode":"8972",
    "addr:street":"Provenplein",
    "iso:country":"BE",
    "sg:address":"Provenplein 53",
    "sg:city":"Poperinge",
    "sg:orig_category":"Beautyfarms, relaxatie and lichamelijk welzijn Schoonheidssalons",
    "sg:phone":"+32 57 30 08 51",
    "sg:postcode":"8972",
    "sg:province":"West-Vlaanderen",
    "wof:name":"Valerie Viane",
    "wof:placetype":"venue"
},
  "geometry": {"coordinates":[2.656899929,50.8903808594],"type":"Point"}
}