{
  "type": "Feature",
  "properties": {
    "iso:country":"BE",
    "sg:address":"Nieuwstad 18",
    "sg:city":"Antwerpen",
    "sg:classifiers":[
        {
            "category":"Deli",
            "type":"Food & Drink"
        }
    ],
    "sg:phone":"+32 3 234 39 89",
    "sg:postcode":"2000",
    "sg:province":"Antwerpen",
    "sg:tags":[
        "delicatessen"
    ],
    "wof:name":"Id\u00e9",
    "wof:placetype":"venue"
},
  "geometry": {"coordinates":[4.4103069305,51.2140655518],"type":"Point"}
}