{
  "type": "Feature",
  "properties": {
    "addr:full":"Rue De Montigny 163 Charleroi Hainaut 6000",
    "addr:housenumber":"163",
    "addr:postcode":"6000",
    "addr:street":"Rue De Montigny;Hainaut",
    "iso:country":"BE",
    "sg:address":"Rue De Montigny 163",
    "sg:city":"Charleroi",
    "sg:classifiers":[
        {
            "category":"Professional",
            "subcategory":"Computer Services",
            "type":"Services"
        }
    ],
    "sg:phone":"+32 71 70 39 90",
    "sg:postcode":"6000",
    "sg:province":"Hainaut",
    "sg:tags":[
        "-",
        "processing",
        "data"
    ],
    "wof:name":"Pc Cool",
    "wof:placetype":"venue"
},
  "geometry": {"coordinates":[4.4510269165,50.4051399231],"type":"Point"}
}