{
  "type": "Feature",
  "properties": {
    "iso:country":"BE",
    "sg:address":"Rue Des Vennes 244",
    "sg:city":"Li\u00c8ge",
    "sg:orig_category":"Beautyfarms, relaxatie and lichamelijk welzijn Kapsalons",
    "sg:phone":"+32 4 342 63 65",
    "sg:postcode":"4020",
    "sg:province":"Li\u00e8ge",
    "wof:name":"Coiffure Claudine",
    "wof:placetype":"venue"
},
  "geometry": {"coordinates":[5.5909380913,50.6220626831],"type":"Point"}
}