{
  "type": "Feature",
  "properties": {
    "addr:full":"Rue Faurieux 15 Herstal Li\u00e8ge 4040",
    "addr:housenumber":"15",
    "addr:postcode":"4040",
    "addr:street":"Rue Faurieux",
    "iso:country":"BE",
    "sg:address":"Rue Faurieux 15",
    "sg:city":"Herstal",
    "sg:classifiers":[
        {
            "category":"Communications",
            "type":"Services"
        }
    ],
    "sg:phone":"+32 4 248 05 39",
    "sg:postcode":"4040",
    "sg:province":"Li\u00e8ge",
    "sg:tags":[
        "translator"
    ],
    "wof:name":"C.g.s.",
    "wof:placetype":"venue"
},
  "geometry": {"coordinates":[5.6286220551,50.6651077271],"type":"Point"}
}