{
  "type": "Feature",
  "properties": {
    "addr:full":"Rue De Campine 216 Li\u00e8ge 1 Li\u00e8ge 4000",
    "addr:housenumber":"216;1",
    "addr:postcode":"4000",
    "addr:street":"Rue De Campine",
    "iso:country":"BE",
    "sg:address":"Rue De Campine 216",
    "sg:city":"Li\u00e8ge 1",
    "sg:classifiers":[
        {
            "category":"Home & Garden",
            "subcategory":"Carpets & Floor Coverings",
            "type":"Retail Goods"
        }
    ],
    "sg:phone":"+32 4 224 04 03",
    "sg:postcode":"4000",
    "sg:province":"Li\u00e8ge",
    "sg:tags":[
        "tile"
    ],
    "wof:name":"Baroni",
    "wof:placetype":"venue"
},
  "geometry": {"coordinates":[5.5682458878,50.6532783508],"type":"Point"}
}