{
  "type": "Feature",
  "properties": {
    "addr:full":"Warandestraat 2 Kruishoutem Oost-Vlaanderen 9770",
    "addr:housenumber":"2",
    "addr:postcode":"9770",
    "addr:street":"Warandestraat",
    "iso:country":"BE",
    "sg:address":"Warandestraat 2",
    "sg:city":"Kruishoutem",
    "sg:orig_category":"Brandweer and civiele bescherming",
    "sg:phone":"+32 9 383 62 18",
    "sg:postcode":"9770",
    "sg:province":"Oost-Vlaanderen",
    "wof:name":"Brandweerkazerne",
    "wof:placetype":"venue"
},
  "geometry": {"coordinates":[3.5259609222,50.9019241333],"type":"Point"}
}