{
  "type": "Feature",
  "properties": {
    "addr:full":"Avenue Des Pagodes 431ba Brussel/bruxelles Bruxelles-Capitale 1020",
    "addr:postcode":"1020",
    "addr:street":"Avenue Des Pagodes 431Ba",
    "iso:country":"BE",
    "sg:address":"Avenue Des Pagodes 431ba",
    "sg:city":"Brussel/bruxelles",
    "sg:orig_category":"Entretien and r\u00e9parations de machines de bureau and ordinateurs. Ordinateurs and \u00e9quipement informat",
    "sg:phone":"+32 2 268 87 80",
    "sg:postcode":"1020",
    "sg:province":"Bruxelles-Capitale",
    "wof:name":"Dem And Cy",
    "wof:placetype":"venue"
},
  "geometry": {"coordinates":[4.3582348824,50.8958892822],"type":"Point"}
}