{
  "type": "Feature",
  "properties": {
    "addr:full":"Oostmolenstraat 94 Aalter Oost-Vlaanderen 9880",
    "addr:housenumber":"94",
    "addr:postcode":"9880",
    "addr:street":"Oostmolenstraat",
    "iso:country":"BE",
    "sg:address":"Oostmolenstraat 94",
    "sg:city":"Aalter",
    "sg:classifiers":[
        {
            "category":"Farming",
            "subcategory":"Livestock Farm",
            "type":"Manufacturing & Wholesale Goods"
        }
    ],
    "sg:phone":"+32 9 374 18 50",
    "sg:postcode":"9880",
    "sg:province":"Oost-Vlaanderen",
    "sg:tags":[
        "buyer"
    ],
    "wof:name":"Smessaert D",
    "wof:placetype":"venue"
},
  "geometry": {"coordinates":[3.4533040524,51.0996704102],"type":"Point"}
}