{
  "type": "Feature",
  "properties": {
    "addr:full":"Drogenberg 57a Overijse Vlaams-Brabant 3090",
    "addr:housenumber":"57a",
    "addr:postcode":"3090",
    "addr:street":"Drogenberg",
    "iso:country":"BE",
    "sg:address":"Drogenberg 57a",
    "sg:city":"Overijse",
    "sg:classifiers":[
        {
            "category":"Autos & Motor Vehicles",
            "subcategory":"Automobile Sales",
            "type":"Retail Goods"
        }
    ],
    "sg:phone":"+32 2 687 88 86",
    "sg:postcode":"3090",
    "sg:province":"Vlaams-Brabant",
    "sg:tags":[
        "motorhomes",
        "accessory"
    ],
    "wof:name":"Dewaet-van Delm Vof",
    "wof:placetype":"venue"
},
  "geometry": {"coordinates":[4.5242829323,50.7754211426],"type":"Point"}
}