{
  "type": "Feature",
  "properties": {
    "iso:country":"BE",
    "sg:address":"Basilieklaan 15",
    "sg:city":"Scherpenheuvel-zichem (scherpenheuvel)",
    "sg:classifiers":[
        {
            "category":"Shopping",
            "subcategory":"Clothing, Apparel, & Fashions",
            "type":"Retail Goods"
        }
    ],
    "sg:phone":"+32 13 77 77 68",
    "sg:postcode":"3270",
    "sg:province":"Vlaams-Brabant",
    "sg:tags":[
        "boutique"
    ],
    "wof:name":"Jos\u00e9phine",
    "wof:placetype":"venue"
},
  "geometry": {"coordinates":[4.975689888,50.9801177979],"type":"Point"}
}