{
  "type": "Feature",
  "properties": {
    "iso:country":"BE",
    "sg:address":"Gistelsesteenweg 546",
    "sg:city":"Jabbeke",
    "sg:classifiers":[
        {
            "category":"Retail",
            "subcategory":"Auto Rental",
            "type":"Services"
        }
    ],
    "sg:phone":"+32 50 81 90 10",
    "sg:postcode":"8490",
    "sg:province":"West-Vlaanderen",
    "sg:tags":[
        "quality",
        "ok",
        "opel",
        "car"
    ],
    "wof:name":"Garage Degroote",
    "wof:placetype":"venue"
},
  "geometry": {"coordinates":[3.1051840782,51.1787910461],"type":"Point"}
}