{
  "type": "Feature",
  "properties": {
    "iso:country":"BE",
    "sg:address":"Wilgenlaan 4",
    "sg:city":"Aartselaar",
    "sg:orig_category":"Agences de publicit\u00e9. Sondages and enqu\u00eates. Bureaux d'\u00e9tudes de march\u00e9",
    "sg:phone":"+32 3 844 84 04",
    "sg:postcode":"2630",
    "sg:province":"Antwerpen",
    "wof:name":"Dynamize Mark. & Consult",
    "wof:placetype":"venue"
},
  "geometry": {"coordinates":[4.3737230301,51.1145591736],"type":"Point"}
}