{
  "type": "Feature",
  "properties": {
    "iso:country":"BE",
    "sg:address":"Nonnenstraat 36",
    "sg:city":"Nijlen",
    "sg:classifiers":[
        {
            "category":"Building & Trades",
            "subcategory":"Pest Control",
            "type":"Services"
        }
    ],
    "sg:phone":"+32 3 411 06 03",
    "sg:postcode":"2560",
    "sg:province":"Antwerpen",
    "sg:tags":[
        "painting",
        "contractor"
    ],
    "wof:name":"Dankers Decor Bvba",
    "wof:placetype":"venue"
},
  "geometry": {"coordinates":[4.6703290939,51.164981842],"type":"Point"}
}