{
  "type": "Feature",
  "properties": {
    "iso:country":"BE",
    "sg:address":"2 Avenue Franklin Z.i. Nord",
    "sg:city":"Wavre",
    "sg:classifiers":[
        {
            "category":"Manufacturing",
            "subcategory":"Rubber & Plastics",
            "type":"Manufacturing & Wholesale Goods"
        }
    ],
    "sg:phone":"+32 10 22 69 55",
    "sg:postcode":"1301",
    "sg:province":"Brabant Wallon",
    "sg:tags":[
        "packaging",
        "material",
        "-"
    ],
    "wof:name":"Omniform",
    "wof:placetype":"venue"
},
  "geometry": {"coordinates":[4.5812849998,50.7129745483],"type":"Point"}
}