{
  "type": "Feature",
  "properties": {
    "addr:full":"Giststraat 46 Elsene/ixelles Bruxelles-Capitale 1050",
    "addr:housenumber":"46",
    "addr:postcode":"1050",
    "addr:street":"Giststraat",
    "iso:country":"BE",
    "sg:address":"Giststraat 46",
    "sg:city":"Elsene/ixelles",
    "sg:orig_category":"Paramedische behandelingen Schoonheidssalons",
    "sg:phone":"+32 2 647 86 55",
    "sg:postcode":"1050",
    "sg:province":"Bruxelles-Capitale",
    "wof:name":"Van Dommele",
    "wof:placetype":"venue"
},
  "geometry": {"coordinates":[4.376721859,50.8279266357],"type":"Point"}
}