{
  "type": "Feature",
  "properties": {
    "iso:country":"BE",
    "sg:address":"Rue Du Home 7",
    "sg:city":"Saint-hubert",
    "sg:orig_category":"Animations diverses",
    "sg:phone":"+32 61 61 17 29",
    "sg:postcode":"6870",
    "sg:province":"Luxembourg",
    "wof:name":"New Sensation",
    "wof:placetype":"venue"
},
  "geometry": {"coordinates":[5.3785791397,50.0257034302],"type":"Point"}
}