{
  "type": "Feature",
  "properties": {
    "addr:full":"Kerkstraat 18 Beveren Oost-Vlaanderen 9120",
    "addr:housenumber":"18",
    "addr:postcode":"9120",
    "addr:street":"Kerkstraat",
    "iso:country":"BE",
    "sg:address":"Kerkstraat 18",
    "sg:city":"Beveren",
    "sg:classifiers":[
        {
            "category":"Fast Food",
            "type":"Food & Drink"
        }
    ],
    "sg:phone":"+32 3 775 25 73",
    "sg:postcode":"9120",
    "sg:province":"Oost-Vlaanderen",
    "sg:tags":[
        "\u00c0",
        "restaurants",
        "emporter",
        "restaurant"
    ],
    "wof:name":"Amigo",
    "wof:placetype":"venue"
},
  "geometry": {"coordinates":[4.1947169304,51.2188415527],"type":"Point"}
}