{
  "type": "Feature",
  "properties": {
    "addr:full":"Minister Liebaertlaan 30 Kortrijk West-Vlaanderen 8500",
    "addr:housenumber":"30",
    "addr:postcode":"8500",
    "addr:street":"Minister Liebaertlaan",
    "iso:country":"BE",
    "sg:address":"Minister Liebaertlaan 30",
    "sg:city":"Kortrijk",
    "sg:classifiers":[
        {
            "category":"Health Services",
            "subcategory":"Dentist",
            "type":"Services"
        }
    ],
    "sg:phone":"+32 56 21 02 12",
    "sg:postcode":"8500",
    "sg:province":"West-Vlaanderen",
    "wof:name":"Ardenois Bernard",
    "wof:placetype":"venue"
},
  "geometry": {"coordinates":[3.2735209465,50.8323783875],"type":"Point"}
}