{
  "type": "Feature",
  "properties": {
    "addr:full":"Prosper Poulletlaan 4 Box 101 Leuven Vlaams-Brabant 3000",
    "addr:housenumber":"4 box 101",
    "addr:postcode":"3000",
    "addr:street":"Poulletlaan",
    "iso:country":"BE",
    "sg:address":"Prosper Poulletlaan 4 Box 101",
    "sg:city":"Leuven",
    "sg:classifiers":[
        {
            "category":"Professional",
            "subcategory":"Computer Services",
            "type":"Services"
        }
    ],
    "sg:phone":"+32 16 58 25 15",
    "sg:postcode":"3000",
    "sg:province":"Vlaams-Brabant",
    "sg:tags":[
        "webdesign",
        "-",
        "internet"
    ],
    "wof:name":"I-media Webdesign",
    "wof:placetype":"venue"
},
  "geometry": {"coordinates":[4.6938080788,50.8743209839],"type":"Point"}
}