{
  "type": "Feature",
  "properties": {
    "iso:country":"BE",
    "sg:address":"Lange Pastoorstraat 25-27",
    "sg:city":"Berchem",
    "sg:classifiers":[
        {
            "category":"Communications",
            "subcategory":"Newspaper",
            "type":"Services"
        }
    ],
    "sg:phone":"+32 3 239 61 29",
    "sg:postcode":"2600",
    "sg:province":"Antwerpen",
    "sg:tags":[
        "printing",
        "publishing"
    ],
    "wof:name":"Vzw Epo",
    "wof:placetype":"venue"
},
  "geometry": {"coordinates":[4.4190587997,51.1934051514],"type":"Point"}
}