{
  "type": "Feature",
  "properties": {
    "addr:full":"Av D'esneux 244 Merytilff Li\u00e8ge 4130",
    "addr:housenumber":"244",
    "addr:postcode":"4130",
    "addr:street":"Av D'Esneux",
    "iso:country":"BE",
    "sg:address":"Av D'esneux 244",
    "sg:city":"Merytilff",
    "sg:classifiers":[
        {
            "category":"Bakery",
            "type":"Food & Drink"
        }
    ],
    "sg:phone":"+32 4 388 13 24",
    "sg:postcode":"4130",
    "sg:province":"Li\u00e8ge",
    "sg:tags":[
        "cake",
        "product",
        "related",
        "bread"
    ],
    "wof:name":"Boulangerie Riga Sa",
    "wof:placetype":"venue"
},
  "geometry": {"coordinates":[5.5902152061,50.5480804443],"type":"Point"}
}