{
  "type": "Feature",
  "properties": {
    "addr:full":"Rue De La Dr\u00e8ve 1 Les Bons Villers (wayaux) Hainaut 6210",
    "addr:housenumber":"1",
    "addr:postcode":"6210",
    "addr:street":"Rue De La Dre\u0300Ve",
    "iso:country":"BE",
    "sg:address":"Rue De La Dr\u00e8ve 1",
    "sg:city":"Les Bons Villers (wayaux)",
    "sg:classifiers":[
        {
            "category":"Building & Trades",
            "subcategory":"Landscaping Services",
            "type":"Services"
        }
    ],
    "sg:phone":"+32 71 85 10 70",
    "sg:postcode":"6210",
    "sg:province":"Hainaut",
    "sg:tags":[
        "gardening",
        "garden",
        "maintenance"
    ],
    "wof:name":"Gryspeert D",
    "wof:placetype":"venue"
},
  "geometry": {"coordinates":[4.4511561394,50.5378227234],"type":"Point"}
}