{
  "type": "Feature",
  "properties": {
    "addr:full":"Place De Beclers 24ba Tournai Hainaut 7532",
    "addr:housenumber":"24ba",
    "addr:postcode":"7532",
    "addr:street":"Place De Beclers",
    "iso:country":"BE",
    "sg:address":"Place De Beclers 24ba",
    "sg:city":"Tournai",
    "sg:orig_category":"Rev\u00eatements pour sols and murs. Peinture",
    "sg:phone":"+32 69 54 85 62",
    "sg:postcode":"7532",
    "sg:province":"Hainaut",
    "wof:name":"Marc Delannay",
    "wof:placetype":"venue"
},
  "geometry": {"coordinates":[3.5036530495,50.621131897],"type":"Point"}
}