{
  "type": "Feature",
  "properties": {
    "addr:full":"De Brulen 44 Arendonk Antwerpen 2370",
    "addr:housenumber":"44",
    "addr:postcode":"2370",
    "addr:street":"De Brulen",
    "iso:country":"BE",
    "sg:address":"De Brulen 44",
    "sg:city":"Arendonk",
    "sg:classifiers":[
        {
            "category":"Health Services",
            "subcategory":"Health Practitioner",
            "type":"Services"
        }
    ],
    "sg:phone":"+32 14 67 84 20",
    "sg:postcode":"2370",
    "sg:province":"Antwerpen",
    "sg:tags":[
        "physiotherapist"
    ],
    "wof:name":"Blockx Peggy",
    "wof:placetype":"venue"
},
  "geometry": {"coordinates":[5.1037998199,51.3387985229],"type":"Point"}
}