{
  "type": "Feature",
  "properties": {
    "addr:full":"Chaussee De Liege 216 Lontzen Li\u00e8ge 4710",
    "addr:housenumber":"216",
    "addr:postcode":"4710",
    "addr:street":"Chaussee De Liege",
    "iso:country":"BE",
    "sg:address":"Chaussee De Liege 216",
    "sg:city":"Lontzen",
    "sg:classifiers":[
        {
            "category":"Building & Trades",
            "subcategory":"Construction",
            "type":"Services"
        }
    ],
    "sg:phone":"+32 87 78 59 98",
    "sg:postcode":"4710",
    "sg:province":"Li\u00e8ge",
    "sg:tags":[
        "glazier"
    ],
    "wof:name":"Keutgens Vitrerie",
    "wof:placetype":"venue"
},
  "geometry": {"coordinates":[5.9720320702,50.6976394653],"type":"Point"}
}