{
  "type": "Feature",
  "properties": {
    "addr:full":"Rue De Marcinelle 59 Ham-sur-heure-nalinnes (nalinnes) Hainaut 6120",
    "addr:housenumber":"59",
    "addr:postcode":"6120",
    "addr:street":"Rue De Marcinelle",
    "iso:country":"BE",
    "sg:address":"Rue De Marcinelle 59",
    "sg:city":"Ham-sur-heure-nalinnes (nalinnes)",
    "sg:classifiers":[
        {
            "category":"Shopping",
            "subcategory":"Books",
            "type":"Retail Goods"
        }
    ],
    "sg:phone":"+32 71 21 89 13",
    "sg:postcode":"6120",
    "sg:province":"Hainaut",
    "sg:tags":[
        "bookseller"
    ],
    "wof:name":"Petit Bouquineur (au)",
    "wof:placetype":"venue"
},
  "geometry": {"coordinates":[4.4414868355,50.3432998657],"type":"Point"}
}