{
  "type": "Feature",
  "properties": {
    "addr:full":"Rue Hodinfosse 7a Amay Li\u00e8ge 4540",
    "addr:housenumber":"7a",
    "addr:postcode":"4540",
    "addr:street":"Rue Hodinfosse",
    "iso:country":"BE",
    "sg:address":"Rue Hodinfosse 7a",
    "sg:city":"Amay",
    "sg:classifiers":[
        {
            "category":"Retail",
            "subcategory":"Auto Repair",
            "type":"Services"
        }
    ],
    "sg:phone":"+32 85 31 23 62",
    "sg:postcode":"4540",
    "sg:province":"Li\u00e8ge",
    "sg:tags":[
        "garage"
    ],
    "wof:name":"Mortel\u00e9 Et Fils",
    "wof:placetype":"venue"
},
  "geometry": {"coordinates":[5.3111538887,50.5520896912],"type":"Point"}
}