{
  "type": "Feature",
  "properties": {
    "iso:country":"BE",
    "sg:address":"Rue Des Martyrs 31",
    "sg:city":"Anthisnes",
    "sg:orig_category":"Woningbouw",
    "sg:phone":"+32 4 383 60 99",
    "sg:postcode":"4162",
    "sg:province":"Li\u00e8ge",
    "wof:name":"Nicolas Reul",
    "wof:placetype":"venue"
},
  "geometry": {"coordinates":[5.5004739761,50.4883041382],"type":"Point"}
}