{
  "type": "Feature",
  "properties": {
    "addr:full":"Avenue Du Bois De Chapelle 84 Lasne Brabant Wallon 1380",
    "addr:housenumber":"84",
    "addr:postcode":"1380",
    "addr:street":"Avenue Du Bois De Chapelle",
    "iso:country":"BE",
    "sg:address":"Avenue Du Bois De Chapelle 84",
    "sg:city":"Lasne",
    "sg:orig_category":"Immobili\u00ebnkantoren Woningbouw",
    "sg:phone":"+32 2 653 08 45",
    "sg:postcode":"1380",
    "sg:province":"Brabant Wallon",
    "wof:name":"Della Faille E",
    "wof:placetype":"venue"
},
  "geometry": {"coordinates":[4.5120100975,50.7000656128],"type":"Point"}
}