{
  "type": "Feature",
  "properties": {
    "addr:full":"Mechanicaln. 6-8 Wilrijk Antwerpen 2610",
    "addr:housenumber":"6-8",
    "addr:postcode":"2610",
    "addr:street":"Mechanicaln.;Antwerpen",
    "iso:country":"BE",
    "sg:address":"Mechanicaln. 6-8",
    "sg:city":"Wilrijk",
    "sg:classifiers":[
        {
            "category":"Building & Trades",
            "subcategory":"Electrical",
            "type":"Services"
        }
    ],
    "sg:phone":"+32 2 377 91 24",
    "sg:postcode":"2610",
    "sg:province":"Antwerpen",
    "sg:tags":[
        "electronic",
        "lighting",
        "equipment"
    ],
    "wof:name":"Mitralux Belgium Sa",
    "wof:placetype":"venue"
},
  "geometry": {"coordinates":[-80.3545837402,25.5979595184],"type":"Point"}
}