{
  "type": "Feature",
  "properties": {
    "addr:full":"Noordstraat 210a Roeselare West-Vlaanderen 8800",
    "addr:housenumber":"210a",
    "addr:postcode":"8800",
    "addr:street":"Noordstraat",
    "iso:country":"BE",
    "sg:address":"Noordstraat 210a",
    "sg:city":"Roeselare",
    "sg:classifiers":[
        {
            "category":"Transit Center",
            "subcategory":"Freight",
            "type":"Transportation"
        }
    ],
    "sg:phone":"+32 51 24 63 49",
    "sg:postcode":"8800",
    "sg:province":"West-Vlaanderen",
    "sg:tags":[
        "import",
        "export",
        "-"
    ],
    "wof:name":"Socobel Trading Bvba",
    "wof:placetype":"venue"
},
  "geometry": {"coordinates":[3.1201810837,50.9507789612],"type":"Point"}
}