{
  "type": "Feature",
  "properties": {
    "iso:country":"BE",
    "sg:address":"Grote Markt 46",
    "sg:city":"Tienen",
    "sg:classifiers":[
        {
            "category":"Restaurant",
            "type":"Food & Drink"
        }
    ],
    "sg:phone":"+32 16 81 55 09",
    "sg:postcode":"3300",
    "sg:province":"Vlaams-Brabant",
    "sg:tags":[
        "caf\u00e9s"
    ],
    "wof:name":"Taverne Den Driesch",
    "wof:placetype":"venue"
},
  "geometry": {"coordinates":[4.9359750748,50.8076553345],"type":"Point"}
}