{
  "type": "Feature",
  "properties": {
    "iso:country":"BE",
    "sg:address":"Weerstandslaan 40",
    "sg:city":"Lommel",
    "sg:orig_category":"Banques and organismes de cr\u00e9dit. Assurances",
    "sg:phone":"+32 11 64 75 47",
    "sg:postcode":"3920",
    "sg:province":"Limburg",
    "wof:name":"Bureau Willekens-gerits",
    "wof:placetype":"venue"
},
  "geometry": {"coordinates":[5.3629798889,51.2400512695],"type":"Point"}
}