{
  "type": "Feature",
  "properties": {
    "addr:full":"Kortrijksesteenweg 224 Sint-martens-latem Oost-Vlaanderen 9830",
    "addr:housenumber":"224",
    "addr:postcode":"9830",
    "addr:street":"Kortrijksesteenweg",
    "iso:country":"BE",
    "sg:address":"Kortrijksesteenweg 224",
    "sg:city":"Sint-martens-latem",
    "sg:classifiers":[
        {
            "category":"Building & Trades",
            "subcategory":"Cleaning & Sanitation",
            "type":"Services"
        }
    ],
    "sg:phone":"+32 9 281 01 58",
    "sg:postcode":"9830",
    "sg:province":"Oost-Vlaanderen",
    "sg:tags":[
        "cleaner",
        "domestic",
        "vacuum"
    ],
    "wof:name":"Rainbow-hoofdzetel Rainair Benelux",
    "wof:placetype":"venue"
},
  "geometry": {"coordinates":[3.6287600994,51.0068397522],"type":"Point"}
}