{
  "type": "Feature",
  "properties": {
    "addr:full":"Rue Lakisse 3 Profondeville (bois-de-villers) Namur 5170",
    "addr:housenumber":"3",
    "addr:postcode":"5170",
    "addr:street":"Rue Lakisse",
    "iso:country":"BE",
    "sg:address":"Rue Lakisse 3",
    "sg:city":"Profondeville (bois-de-villers)",
    "sg:classifiers":[
        {
            "category":"Farming",
            "subcategory":"Livestock Farm",
            "type":"Manufacturing & Wholesale Goods"
        }
    ],
    "sg:phone":"+32 81 43 32 36",
    "sg:postcode":"5170",
    "sg:province":"Namur",
    "sg:tags":[
        "buyer"
    ],
    "wof:name":"Dewez F",
    "wof:placetype":"venue"
},
  "geometry": {"coordinates":[4.8275141716,50.4067153931],"type":"Point"}
}