{
  "type": "Feature",
  "properties": {
    "iso:country":"BE",
    "sg:address":"Boulevard De Merckem 7",
    "sg:city":"Namur",
    "sg:classifiers":[
        {
            "category":"Education",
            "subcategory":"University",
            "type":"Public Place"
        }
    ],
    "sg:phone":"+32 81 74 45 46",
    "sg:postcode":"5000",
    "sg:province":"Namur",
    "sg:tags":[
        "higher"
    ],
    "wof:name":"Institut Eco-conseil",
    "wof:placetype":"venue"
},
  "geometry": {"coordinates":[4.8563199043,50.4700584412],"type":"Point"}
}