{
  "type": "Feature",
  "properties": {
    "iso:country":"BE",
    "sg:address":"Rue D'acoz 11",
    "sg:city":"Ham-sur-heure-nalinnes",
    "sg:orig_category":"Biens d'occasion",
    "sg:phone":"+32 71 21 86 31",
    "sg:postcode":"6120",
    "sg:province":"Hainaut",
    "wof:name":"Des Habits Et Vous",
    "wof:placetype":"venue"
},
  "geometry": {"coordinates":[4.472014904,50.3426589966],"type":"Point"}
}