{
  "type": "Feature",
  "properties": {
    "addr:full":"Beselarestraat 223 Zonnebeke West-Vlaanderen 8980",
    "addr:housenumber":"223",
    "addr:postcode":"8980",
    "addr:street":"Beselarestraat",
    "iso:country":"BE",
    "sg:address":"Beselarestraat 223",
    "sg:city":"Zonnebeke",
    "sg:orig_category":"Kapsalons",
    "sg:phone":"+32 57 46 87 11",
    "sg:postcode":"8980",
    "sg:province":"West-Vlaanderen",
    "wof:name":"Coiffure Nathalie",
    "wof:placetype":"venue"
},
  "geometry": {"coordinates":[3.0097019672,50.8606758118],"type":"Point"}
}