{
  "type": "Feature",
  "properties": {
    "iso:country":"BE",
    "sg:address":"Avenue De La Concorde 21",
    "sg:city":"Seraing",
    "sg:orig_category":"R\u00e9cup\u00e9ration de mati\u00e8res m\u00e9talliques recyclables and d\u00e9molisseurs de voitures",
    "sg:phone":"+32 4 337 49 58",
    "sg:postcode":"4100",
    "sg:province":"Li\u00e8ge",
    "wof:name":"Porsche-dincar",
    "wof:placetype":"venue"
},
  "geometry": {"coordinates":[5.5027937889,50.5964622498],"type":"Point"}
}