{
  "type": "Feature",
  "properties": {
    "iso:country":"BE",
    "sg:address":"Boterstraat 14",
    "sg:city":"Izegem",
    "sg:classifiers":[
        {
            "category":"Real Estate",
            "subcategory":"Surveying",
            "type":"Services"
        }
    ],
    "sg:phone":"+32 56 50 94 39",
    "sg:postcode":"8870",
    "sg:province":"West-Vlaanderen",
    "sg:tags":[
        "surveyor",
        "land",
        "-",
        "equipment"
    ],
    "wof:name":"C.t.p. International",
    "wof:placetype":"venue"
},
  "geometry": {"coordinates":[3.1937470436,50.9004402161],"type":"Point"}
}