{
  "type": "Feature",
  "properties": {
    "iso:country":"BE",
    "sg:address":"Ch De Mons 14",
    "sg:city":"Chimay",
    "sg:classifiers":[
        {
            "category":"Home & Garden",
            "subcategory":"Furniture",
            "type":"Retail Goods"
        }
    ],
    "sg:phone":"+32 60 21 17 49",
    "sg:postcode":"6460",
    "sg:province":"Hainaut",
    "sg:tags":[
        "household",
        "wood"
    ],
    "wof:name":"Marcel Vaisiere Sprl",
    "wof:placetype":"venue"
},
  "geometry": {"coordinates":[4.3079900742,50.0544586182],"type":"Point"}
}