{
  "type": "Feature",
  "properties": {
    "addr:full":"Guido Gezellestraat 100 Aartselaar Antwerpen 2630",
    "addr:housenumber":"100",
    "addr:postcode":"2630",
    "addr:street":"Guido Gezellestraat",
    "iso:country":"BE",
    "sg:address":"Guido Gezellestraat 100",
    "sg:city":"Aartselaar",
    "sg:orig_category":"Kapsalons",
    "sg:phone":"+32 3 887 29 07",
    "sg:postcode":"2630",
    "sg:province":"Antwerpen",
    "wof:name":"Coiffure Dany",
    "wof:placetype":"venue"
},
  "geometry": {"coordinates":[4.3815078735,51.1366271973],"type":"Point"}
}