{
  "type": "Feature",
  "properties": {
    "addr:full":"Boonstede 38ba Gent Oost-Vlaanderen 9031",
    "addr:housenumber":"38ba",
    "addr:postcode":"9031",
    "addr:street":"Boonstede;Oost-Vlaanderen",
    "iso:country":"BE",
    "sg:address":"Boonstede 38ba",
    "sg:city":"Gent",
    "sg:orig_category":"Woningbouw",
    "sg:phone":"+32 9 282 78 69",
    "sg:postcode":"9031",
    "sg:province":"Oost-Vlaanderen",
    "wof:name":"Linda Expeels",
    "wof:placetype":"venue"
},
  "geometry": {"coordinates":[3.6630249023,51.0503692627],"type":"Point"}
}