{
  "type": "Feature",
  "properties": {
    "iso:country":"BE",
    "sg:address":"Kalkenstr 86",
    "sg:city":"Buggenhout",
    "sg:classifiers":[
        {
            "category":"Shopping",
            "subcategory":"Crafts & Fabrics",
            "type":"Retail Goods"
        }
    ],
    "sg:phone":"+32 52 39 93 70",
    "sg:postcode":"9255",
    "sg:province":"Oost-Vlaanderen",
    "sg:tags":[
        "textile",
        "linen",
        "clothing"
    ],
    "wof:name":"Louis Baert & Co Nv",
    "wof:placetype":"venue"
},
  "geometry": {"coordinates":[4.1981930733,51.0015411377],"type":"Point"}
}