{
  "type": "Feature",
  "properties": {
    "iso:country":"BE",
    "sg:address":"Avenue Des Capucines 30",
    "sg:city":"Brussel",
    "sg:orig_category":"Tuinen",
    "sg:phone":"+32 2 242 94 14",
    "sg:postcode":"1030",
    "sg:province":"Bruxelles-Capitale",
    "wof:name":"Cavirot F",
    "wof:placetype":"venue"
},
  "geometry": {"coordinates":[4.3882408142,50.8653297424],"type":"Point"}
}