{
  "type": "Feature",
  "properties": {
    "iso:country":"BE",
    "sg:address":"Wingenesteenweg 2",
    "sg:city":"Ruiselede",
    "sg:classifiers":[
        {
            "category":"Home & Garden",
            "subcategory":"Home Furnishings",
            "type":"Retail Goods"
        }
    ],
    "sg:phone":"+32 51 68 85 21",
    "sg:postcode":"8755",
    "sg:province":"West-Vlaanderen",
    "sg:tags":[
        "-",
        "furniture"
    ],
    "wof:name":"Mannens L",
    "wof:placetype":"venue"
},
  "geometry": {"coordinates":[3.3742759228,51.0586051941],"type":"Point"}
}