{
  "type": "Feature",
  "properties": {
    "iso:country":"BE",
    "sg:address":"10",
    "sg:city":"Rue Van Den Corput 1190 Bruxelles",
    "sg:orig_category":"Miscellaneous Products",
    "sg:phone":"+32 2 343 80 21",
    "sg:postcode":"10",
    "wof:name":"Lerat J Sprl",
    "wof:placetype":"venue"
},
  "geometry": {"coordinates":[4.3434901237,50.8188438416],"type":"Point"}
}