{
  "type": "Feature",
  "properties": {
    "addr:full":"Staatsbaan 144 Bekkevoort Vlaams-Brabant 3460",
    "addr:housenumber":"144",
    "addr:postcode":"3460",
    "addr:street":"Staatsbaan",
    "iso:country":"BE",
    "sg:address":"Staatsbaan 144",
    "sg:city":"Bekkevoort",
    "sg:classifiers":[
        {
            "category":"Insurance",
            "subcategory":"Life Insurance",
            "type":"Services"
        }
    ],
    "sg:phone":"+32 13 32 79 34",
    "sg:postcode":"3460",
    "sg:province":"Vlaams-Brabant",
    "sg:tags":[
        "assurance"
    ],
    "wof:name":"W. Van Hoeyveld",
    "wof:placetype":"venue"
},
  "geometry": {"coordinates":[4.9748821259,50.9445953369],"type":"Point"}
}