{
  "type": "Feature",
  "properties": {
    "addr:full":"Noorderlaan 485 Antwerpen Antwerpen 2030",
    "addr:housenumber":"485",
    "addr:postcode":"2030",
    "addr:street":"Noorderlaan",
    "iso:country":"BE",
    "sg:address":"Noorderlaan 485",
    "sg:city":"Antwerpen",
    "sg:classifiers":[
        {
            "category":"Harbor",
            "type":"Transportation"
        }
    ],
    "sg:phone":"+32 3 543 99 92",
    "sg:postcode":"2030",
    "sg:province":"Antwerpen",
    "sg:tags":[
        "port",
        "facility"
    ],
    "wof:name":"Wijngaard Natie Transport",
    "wof:placetype":"venue"
},
  "geometry": {"coordinates":[4.3488612175,51.2944984436],"type":"Point"}
}