{
  "type": "Feature",
  "properties": {
    "addr:full":"Chauss\u00e9e De Theux 60 Verviers (heusy) Li\u00e8ge 4802",
    "addr:housenumber":"60",
    "addr:postcode":"4802",
    "addr:street":"Chausse\u0301E De Theux",
    "iso:country":"BE",
    "sg:address":"Chauss\u00e9e De Theux 60",
    "sg:city":"Verviers (heusy)",
    "sg:classifiers":[
        {
            "category":"Bars & Pubs",
            "type":"Food & Drink"
        }
    ],
    "sg:phone":"+32 87 22 92 79",
    "sg:postcode":"4802",
    "sg:province":"Li\u00e8ge",
    "wof:name":"As De Pomme (l')",
    "wof:placetype":"venue"
},
  "geometry": {"coordinates":[5.8671250343,50.5714111328],"type":"Point"}
}