{
  "type": "Feature",
  "properties": {
    "addr:full":"Rue Charles Magnette 1c Li\u00e8ge 1 Li\u00e8ge 4000",
    "addr:housenumber":"1c;1",
    "addr:postcode":"4000",
    "addr:street":"Rue Charles Magnette",
    "iso:country":"BE",
    "sg:address":"Rue Charles Magnette 1c",
    "sg:city":"Li\u00e8ge 1",
    "sg:classifiers":[
        {
            "category":"Shopping",
            "subcategory":"Books",
            "type":"Retail Goods"
        }
    ],
    "sg:phone":"+32 4 223 56 58",
    "sg:postcode":"4000",
    "sg:province":"Li\u00e8ge",
    "sg:tags":[
        "bookseller"
    ],
    "wof:name":"Petit Kioske (le)",
    "wof:placetype":"venue"
},
  "geometry": {"coordinates":[5.5744538307,50.6409187317],"type":"Point"}
}