{
  "type": "Feature",
  "properties": {
    "iso:country":"BE",
    "sg:address":"Doornendijkstraat 7",
    "sg:city":"Assenede",
    "sg:orig_category":"Woningbouw",
    "sg:phone":"+32 9 373 43 59",
    "sg:postcode":"9960",
    "sg:province":"Oost-Vlaanderen",
    "wof:name":"Baute",
    "wof:placetype":"venue"
},
  "geometry": {"coordinates":[3.7394189835,51.2452049255],"type":"Point"}
}