{
  "type": "Feature",
  "properties": {
    "addr:full":"Rue De Steenkerque 80 Silly (hoves) Hainaut 7830",
    "addr:housenumber":"80",
    "addr:postcode":"7830",
    "addr:street":"Rue De Steenkerque",
    "iso:country":"BE",
    "sg:address":"Rue De Steenkerque 80",
    "sg:city":"Silly (hoves)",
    "sg:classifiers":[
        {
            "category":"Utilities",
            "subcategory":"Fuel Oil & Lpg",
            "type":"Services"
        }
    ],
    "sg:phone":"+32 2 395 88 06",
    "sg:postcode":"7830",
    "sg:province":"Hainaut",
    "wof:name":"Monsieur Deketele Alain",
    "wof:placetype":"venue"
},
  "geometry": {"coordinates":[4.0587320328,50.6605262756],"type":"Point"}
}