{
  "type": "Feature",
  "properties": {
    "iso:country":"BE",
    "sg:address":"Florencestraat 1",
    "sg:city":"Brussel/bruxelles",
    "sg:orig_category":"Verhuur immobili\u00ebn eigen bezit",
    "sg:phone":"+32 2 543 33 90",
    "sg:postcode":"1000",
    "sg:province":"Bruxelles-Capitale",
    "wof:name":"Residence Florence",
    "wof:placetype":"venue"
},
  "geometry": {"coordinates":[4.3605008125,50.8299446106],"type":"Point"}
}