{
  "type": "Feature",
  "properties": {
    "addr:full":"Stationsplein 5 Lichtervelde West-Vlaanderen 8810",
    "addr:housenumber":"5",
    "addr:postcode":"8810",
    "addr:street":"Stationsplein",
    "iso:country":"BE",
    "sg:address":"Stationsplein 5",
    "sg:city":"Lichtervelde",
    "sg:orig_category":"Treinen and spoorwegen",
    "sg:phone":"+32 51 72 57 24",
    "sg:postcode":"8810",
    "sg:province":"West-Vlaanderen",
    "wof:name":"Station Lichtervelde",
    "wof:placetype":"venue"
},
  "geometry": {"coordinates":[3.14083004,51.0276145935],"type":"Point"}
}