{
  "type": "Feature",
  "properties": {
    "addr:full":"Leuvenstraat 29 Tienen Vlaams-Brabant 3300",
    "addr:housenumber":"29",
    "addr:postcode":"3300",
    "addr:street":"Leuvenstraat",
    "iso:country":"BE",
    "sg:address":"Leuvenstraat 29",
    "sg:city":"Tienen",
    "sg:classifiers":[
        {
            "category":"Utilities",
            "subcategory":"Telephone",
            "type":"Services"
        }
    ],
    "sg:phone":"+32 16 76 84 10",
    "sg:postcode":"3300",
    "sg:province":"Vlaams-Brabant",
    "sg:tags":[
        "phone",
        "telecommunicatiesystemen",
        "house"
    ],
    "wof:name":"The Phone House",
    "wof:placetype":"venue"
},
  "geometry": {"coordinates":[4.9285850525,50.8101806641],"type":"Point"}
}