{
  "type": "Feature",
  "properties": {
    "addr:full":"Brouwerijstraat 29 Londerzeel (steenhuffel) Vlaams-Brabant 1840",
    "addr:housenumber":"29",
    "addr:postcode":"1840",
    "addr:street":"Brouwerijstraat",
    "iso:country":"BE",
    "sg:address":"Brouwerijstraat 29",
    "sg:city":"Londerzeel (steenhuffel)",
    "sg:classifiers":[
        {
            "category":"Bars & Pubs",
            "type":"Food & Drink"
        }
    ],
    "sg:phone":"+32 52 30 30 55",
    "sg:postcode":"1840",
    "sg:province":"Vlaams-Brabant",
    "sg:tags":[
        "tavern"
    ],
    "wof:name":"Leireken Taverne",
    "wof:placetype":"venue"
},
  "geometry": {"coordinates":[4.2688307762,50.9986763],"type":"Point"}
}