{
  "type": "Feature",
  "properties": {
    "addr:full":"Boulevard Fr\u00e8re-orban 9 Li\u00e8ge 1 Li\u00e8ge 4000",
    "addr:housenumber":"9;1",
    "addr:postcode":"4000",
    "addr:street":"Boulevard Fre\u0300Re-Orban",
    "iso:country":"BE",
    "sg:address":"Boulevard Fr\u00e8re-orban 9",
    "sg:city":"Li\u00e8ge 1",
    "sg:classifiers":[
        {
            "category":"Real Estate",
            "subcategory":"Architect",
            "type":"Services"
        }
    ],
    "sg:phone":"+32 4 222 90 50",
    "sg:postcode":"4000",
    "sg:province":"Li\u00e8ge",
    "wof:name":"Moureau E",
    "wof:placetype":"venue"
},
  "geometry": {"coordinates":[5.5716781616,50.6349182129],"type":"Point"}
}