{
  "type": "Feature",
  "properties": {
    "iso:country":"BE",
    "sg:address":"Tolpoortstraat 34",
    "sg:city":"Deinze",
    "sg:orig_category":"Disneyland Parijs",
    "sg:phone":"+32 9 386 12 97",
    "sg:postcode":"9800",
    "sg:province":"Oost-Vlaanderen",
    "wof:name":"De Globbetrotter Nv",
    "wof:placetype":"venue"
},
  "geometry": {"coordinates":[3.5294179916,50.9817123413],"type":"Point"}
}