{
  "type": "Feature",
  "properties": {
    "iso:country":"BE",
    "sg:address":"Eenbeekstraat 13",
    "sg:city":"Destelbergen",
    "sg:orig_category":"Sportclubs",
    "sg:phone":"+32 9 228 27 31",
    "sg:postcode":"9070",
    "sg:province":"Oost-Vlaanderen",
    "wof:name":"V.b.c. Melle",
    "wof:placetype":"venue"
},
  "geometry": {"coordinates":[3.7895610332,51.0571327209],"type":"Point"}
}