{
  "type": "Feature",
  "properties": {
    "iso:country":"BE",
    "sg:address":"Smoutstraat 11",
    "sg:city":"Sint-gillis-waas",
    "sg:classifiers":[
        {
            "category":"Building & Trades",
            "subcategory":"Plumbing",
            "type":"Services"
        }
    ],
    "sg:phone":"+32 3 770 53 61",
    "sg:postcode":"9170",
    "sg:province":"Oost-Vlaanderen",
    "sg:tags":[
        "pipe",
        "drain",
        "unblocking"
    ],
    "wof:name":"Ruimdienst Ringoot",
    "wof:placetype":"venue"
},
  "geometry": {"coordinates":[4.1411108971,51.2136268616],"type":"Point"}
}