{
  "type": "Feature",
  "properties": {
    "addr:full":"Ouwegemstraat 68 Zingem (ouwegem) Oost-Vlaanderen 9750",
    "addr:housenumber":"68",
    "addr:postcode":"9750",
    "addr:street":"Ouwegemstraat",
    "iso:country":"BE",
    "sg:address":"Ouwegemstraat 68",
    "sg:city":"Zingem (ouwegem)",
    "sg:orig_category":"Non-Classified Establishments",
    "sg:phone":"+32 9 384 55 24",
    "sg:postcode":"9750",
    "sg:province":"Oost-Vlaanderen",
    "wof:name":"Alcedo",
    "wof:placetype":"venue"
},
  "geometry": {"coordinates":[3.6519870758,50.9060554504],"type":"Point"}
}