{
  "type": "Feature",
  "properties": {
    "addr:full":"Vinaafstraat 31a Bierbeek Vlaams-Brabant 3360",
    "addr:housenumber":"31a",
    "addr:postcode":"3360",
    "addr:street":"Vinaafstraat",
    "iso:country":"BE",
    "sg:address":"Vinaafstraat 31a",
    "sg:city":"Bierbeek",
    "sg:classifiers":[
        {
            "category":"Communications",
            "type":"Services"
        }
    ],
    "sg:phone":"+32 16 73 42 54",
    "sg:postcode":"3360",
    "sg:province":"Vlaams-Brabant",
    "sg:tags":[
        "translator"
    ],
    "wof:name":"De Vos A",
    "wof:placetype":"venue"
},
  "geometry": {"coordinates":[4.7885699272,50.8167991638],"type":"Point"}
}