{
  "type": "Feature",
  "properties": {
    "addr:full":"Ardoystraat 17 Hamme Oost-Vlaanderen 9220",
    "addr:housenumber":"17",
    "addr:postcode":"9220",
    "addr:street":"Ardoystraat",
    "iso:country":"BE",
    "sg:address":"Ardoystraat 17",
    "sg:city":"Hamme",
    "sg:orig_category":"Eleveurs and marchands de porcs. Eleveurs de bovins",
    "sg:phone":"+32 52 47 35 59",
    "sg:postcode":"9220",
    "sg:province":"Oost-Vlaanderen",
    "wof:name":"Franciscus Van Havermaet",
    "wof:placetype":"venue"
},
  "geometry": {"coordinates":[4.1011071205,51.0919914246],"type":"Point"}
}