{
  "type": "Feature",
  "properties": {
    "iso:country":"BE",
    "sg:address":"Crutzenstraat 90",
    "sg:city":"Hasselt (kuringen)",
    "sg:classifiers":[
        {
            "category":"Health Services",
            "subcategory":"Dentist",
            "type":"Services"
        }
    ],
    "sg:phone":"+32 11 25 10 13",
    "sg:postcode":"3511",
    "sg:province":"Limburg",
    "wof:name":"Maris Johan",
    "wof:placetype":"venue"
},
  "geometry": {"coordinates":[5.3076457977,50.9423675537],"type":"Point"}
}