{
  "type": "Feature",
  "properties": {
    "addr:full":"Antwerpsesteenweg 237 Malle Antwerpen 2390",
    "addr:housenumber":"237",
    "addr:postcode":"2390",
    "addr:street":"Antwerpsesteenweg",
    "iso:country":"BE",
    "sg:address":"Antwerpsesteenweg 237",
    "sg:city":"Malle",
    "sg:orig_category":"Alternatieve geneeskunde",
    "sg:phone":"+32 3 312 52 20",
    "sg:postcode":"2390",
    "sg:province":"Antwerpen",
    "wof:name":"Elke Vermuyten",
    "wof:placetype":"venue"
},
  "geometry": {"coordinates":[4.6947031021,51.2966537476],"type":"Point"}
}