{
  "type": "Feature",
  "properties": {
    "iso:country":"BE",
    "sg:address":"Lievehereboomstraat 39",
    "sg:city":"Kortessem",
    "sg:orig_category":"Fruitteelt",
    "sg:phone":"+32 11 37 70 48",
    "sg:postcode":"3720",
    "sg:province":"Limburg",
    "wof:name":"Cuyx Eddy En Geert",
    "wof:placetype":"venue"
},
  "geometry": {"coordinates":[5.3813138008,50.8554191589],"type":"Point"}
}