{
  "type": "Feature",
  "properties": {
    "iso:country":"BE",
    "sg:address":"Hoogleedsesteenweg 317",
    "sg:city":"Roeselare",
    "sg:classifiers":[
        {
            "category":"Wholesale",
            "subcategory":"Fruits & Vegetables",
            "type":"Manufacturing & Wholesale Goods"
        }
    ],
    "sg:phone":"+32 51 22 78 97",
    "sg:postcode":"8800",
    "sg:province":"West-Vlaanderen",
    "sg:tags":[
        "whol",
        "-"
    ],
    "wof:name":"Maes Fruitexpress",
    "wof:placetype":"venue"
},
  "geometry": {"coordinates":[3.1038870811,50.9597892761],"type":"Point"}
}