{
  "type": "Feature",
  "properties": {
    "addr:full":"Baraplein 4 Anderlecht/anderlecht Bruxelles-Capitale 1070",
    "addr:housenumber":"4",
    "addr:postcode":"1070",
    "addr:street":"Baraplein",
    "iso:country":"BE",
    "sg:address":"Baraplein 4",
    "sg:city":"Anderlecht/anderlecht",
    "sg:orig_category":"Verplichte sociale verzekeringen",
    "sg:phone":"+32 2 523 37 77",
    "sg:postcode":"1070",
    "sg:province":"Bruxelles-Capitale",
    "wof:name":"Mutuelle Juive Inhumat.",
    "wof:placetype":"venue"
},
  "geometry": {"coordinates":[4.335755825,50.8394088745],"type":"Point"}
}