{
  "type": "Feature",
  "properties": {
    "addr:full":"Brusselsesteenweg 151 Grimbergen Vlaams-Brabant 1850",
    "addr:housenumber":"151",
    "addr:postcode":"1850",
    "addr:street":"Brusselsesteenweg",
    "iso:country":"BE",
    "sg:address":"Brusselsesteenweg 151",
    "sg:city":"Grimbergen",
    "sg:classifiers":[
        {
            "category":"Professional",
            "subcategory":"Management & Consulting",
            "type":"Services"
        }
    ],
    "sg:phone":"+32 2 305 74 20",
    "sg:postcode":"1850",
    "sg:province":"Vlaams-Brabant",
    "sg:tags":[
        "consultant"
    ],
    "wof:name":"Vabuco Office",
    "wof:placetype":"venue"
},
  "geometry": {"coordinates":[4.3665399551,50.9289016724],"type":"Point"}
}