{
  "type": "Feature",
  "properties": {
    "addr:full":"A. Vaucampslaan 154 Beersel (huizingen) Vlaams-Brabant 1654",
    "addr:housenumber":"154",
    "addr:postcode":"1654",
    "addr:street":"Vaucampslaan",
    "iso:country":"BE",
    "sg:address":"A. Vaucampslaan 154",
    "sg:city":"Beersel (huizingen)",
    "sg:classifiers":[
        {
            "category":"Professional",
            "subcategory":"Art Services",
            "type":"Services"
        }
    ],
    "sg:phone":"+32 486 55 69 58",
    "sg:postcode":"1654",
    "sg:province":"Vlaams-Brabant",
    "sg:tags":[
        "graphic",
        "designer"
    ],
    "wof:name":"Verkens L",
    "wof:placetype":"venue"
},
  "geometry": {"coordinates":[4.2727651596,50.7488441467],"type":"Point"}
}