{
  "type": "Feature",
  "properties": {
    "addr:full":"Chauss\u00e9e De Belle Vue 11d Bernissart (pommeroeul) Hainaut 7322",
    "addr:housenumber":"11d",
    "addr:postcode":"7322",
    "addr:street":"Chausse\u0301E De Belle Vue",
    "iso:country":"BE",
    "sg:address":"Chauss\u00e9e De Belle Vue 11d",
    "sg:city":"Bernissart (pommeroeul)",
    "sg:classifiers":[
        {
            "category":"Retail",
            "subcategory":"Repair Shop",
            "type":"Services"
        }
    ],
    "sg:phone":"+32 65 62 05 68",
    "sg:postcode":"7322",
    "sg:province":"Hainaut",
    "sg:tags":[
        "denture"
    ],
    "wof:name":"Dendal R",
    "wof:placetype":"venue"
},
  "geometry": {"coordinates":[3.7267279625,50.4763298035],"type":"Point"}
}