{
  "type": "Feature",
  "properties": {
    "addr:full":"Avenue Des Combattans 160a Genappe Brabant Wallon 1470",
    "addr:housenumber":"160a",
    "addr:postcode":"1470",
    "addr:street":"Avenue Des Combattans;Wallon",
    "iso:country":"BE",
    "sg:address":"Avenue Des Combattans 160a",
    "sg:city":"Genappe",
    "sg:orig_category":"Metaalbehandeling and -bekleding",
    "sg:phone":"+32 10 61 42 86",
    "sg:postcode":"1470",
    "sg:province":"Brabant Wallon",
    "wof:name":"Russo Pietro",
    "wof:placetype":"venue"
},
  "geometry": {"coordinates":[4.5344247818,50.6299285889],"type":"Point"}
}