{
  "type": "Feature",
  "properties": {
    "addr:full":"Chemin De Louvranges 60 Wavre Brabant Wallon 1300",
    "addr:housenumber":"60;1300",
    "addr:street":"Chemin De Louvranges",
    "iso:country":"BE",
    "sg:address":"Chemin De Louvranges 60",
    "sg:city":"Wavre",
    "sg:classifiers":[
        {
            "category":"Banks & Credit Unions",
            "subcategory":"Investment Brokerage",
            "type":"Services"
        }
    ],
    "sg:phone":"+32 475 81 61 38",
    "sg:postcode":"1300",
    "sg:province":"Brabant Wallon",
    "sg:tags":[
        "repair",
        "-",
        "installation",
        "sanitary",
        "article"
    ],
    "wof:name":"Sanibel",
    "wof:placetype":"venue"
},
  "geometry": {"coordinates":[4.6201839447,50.705696106],"type":"Point"}
}