{
  "type": "Feature",
  "properties": {
    "iso:country":"BE",
    "sg:address":"Jef Scheirsstr 56",
    "sg:city":"Oudegem",
    "sg:classifiers":[
        {
            "category":"Food & Beverages",
            "subcategory":"Groceries & Convenience Stores",
            "type":"Retail Goods"
        }
    ],
    "sg:phone":"+32 52 21 54 93",
    "sg:postcode":"9200",
    "sg:province":"Oost-Vlaanderen",
    "sg:tags":[
        "product",
        "grain",
        "cereal",
        "related"
    ],
    "wof:name":"Molens Abbeloos Nv",
    "wof:placetype":"venue"
},
  "geometry": {"coordinates":[4.0637841225,51.0145797729],"type":"Point"}
}