{
  "type": "Feature",
  "properties": {
    "iso:country":"BE",
    "sg:address":"Rue Des Combattants 8",
    "sg:city":"Charleroi",
    "sg:classifiers":[
        {
            "category":"Restaurant",
            "type":"Food & Drink"
        }
    ],
    "sg:phone":"+32 71 30 05 23",
    "sg:postcode":"6031",
    "sg:province":"Hainaut",
    "wof:name":"L' Ascolino",
    "wof:placetype":"venue"
},
  "geometry": {"coordinates":[4.4548988342,50.3859977722],"type":"Point"}
}