{
  "type": "Feature",
  "properties": {
    "addr:full":"Chauss\u00c9e De Fleurus 4 Gilly Hainaut 6060",
    "addr:housenumber":"4",
    "addr:postcode":"6060",
    "addr:street":"Chausse\u0301E De Fleurus",
    "iso:country":"BE",
    "sg:address":"Chauss\u00c9e De Fleurus 4",
    "sg:city":"Gilly",
    "sg:orig_category":"Opticiens",
    "sg:phone":"+32 71 41 25 16",
    "sg:postcode":"6060",
    "sg:province":"Hainaut",
    "wof:name":"Vision & Pr\u00c9cision",
    "wof:placetype":"venue"
},
  "geometry": {"coordinates":[4.480550766,50.4226570129],"type":"Point"}
}