{
  "type": "Feature",
  "properties": {
    "iso:country":"BE",
    "sg:address":"9230",
    "sg:city":"Wetteren (groot)",
    "sg:orig_category":"Pharmaciens",
    "sg:phone":"+32 900 10 500",
    "sg:postcode":"9230",
    "sg:province":"Oost-Vlaanderen",
    "wof:name":"Pharmacies De Garde",
    "wof:placetype":"venue"
},
  "geometry": {"coordinates":[3.8855400085,51.0070304871],"type":"Point"}
}