{
  "type": "Feature",
  "properties": {
    "iso:country":"BE",
    "sg:address":"Rue Edith Cavell 200",
    "sg:city":"Ukkel/uccle",
    "sg:orig_category":"Speelgoed",
    "sg:phone":"+32 2 374 66 01",
    "sg:postcode":"1180",
    "sg:province":"Bruxelles-Capitale",
    "wof:name":"Polichinelle",
    "wof:placetype":"venue"
},
  "geometry": {"coordinates":[4.3574547768,50.8067131042],"type":"Point"}
}