{
  "type": "Feature",
  "properties": {
    "addr:full":"Ingelmunstersteenweg 220 Oostrozebeke West-Vlaanderen 8780",
    "addr:housenumber":"220",
    "addr:postcode":"8780",
    "addr:street":"Ingelmunstersteenweg",
    "iso:country":"BE",
    "sg:address":"Ingelmunstersteenweg 220",
    "sg:city":"Oostrozebeke",
    "sg:orig_category":"Kapsalons",
    "sg:phone":"+32 56 66 70 44",
    "sg:postcode":"8780",
    "sg:province":"West-Vlaanderen",
    "wof:name":"Ludwine Declerck",
    "wof:placetype":"venue"
},
  "geometry": {"coordinates":[3.2968640327,50.914932251],"type":"Point"}
}