{
  "type": "Feature",
  "properties": {
    "addr:full":"Brugstraat 2 Bocholt Limburg 3950",
    "addr:housenumber":"2",
    "addr:postcode":"3950",
    "addr:street":"Brugstraat",
    "iso:country":"BE",
    "sg:address":"Brugstraat 2",
    "sg:city":"Bocholt",
    "sg:classifiers":[
        {
            "category":"Retail",
            "subcategory":"Laundry & Dry Cleaning",
            "type":"Services"
        }
    ],
    "sg:phone":"+32 89 46 74 12",
    "sg:postcode":"3950",
    "sg:province":"Limburg",
    "sg:tags":[
        "self",
        "-"
    ],
    "wof:name":"Heidi & Co",
    "wof:placetype":"venue"
},
  "geometry": {"coordinates":[5.5817508698,51.1744842529],"type":"Point"}
}