{
  "type": "Feature",
  "properties": {
    "addr:full":"Beemdenstraat 41 Aarschot Vlaams-Brabant 3200",
    "addr:housenumber":"41",
    "addr:postcode":"3200",
    "addr:street":"Beemdenstraat",
    "iso:country":"BE",
    "sg:address":"Beemdenstraat 41",
    "sg:city":"Aarschot",
    "sg:orig_category":"Producteurs de l\u00e9gumes",
    "sg:phone":"+32 16 56 83 75",
    "sg:postcode":"3200",
    "sg:province":"Vlaams-Brabant",
    "wof:name":"Raymond Nijs",
    "wof:placetype":"venue"
},
  "geometry": {"coordinates":[4.8315200806,50.9838638306],"type":"Point"}
}