{
  "type": "Feature",
  "properties": {
    "addr:full":"Kemmelseweg 46 Ieper West-Vlaanderen 8900",
    "addr:housenumber":"46",
    "addr:postcode":"8900",
    "addr:street":"Kemmelseweg",
    "iso:country":"BE",
    "sg:address":"Kemmelseweg 46",
    "sg:city":"Ieper",
    "sg:orig_category":"Geschenken and souvenirs Verlichting and huishoudartikelen",
    "sg:phone":"+32 57 21 61 24",
    "sg:postcode":"8900",
    "sg:province":"West-Vlaanderen",
    "wof:name":"Casa",
    "wof:placetype":"venue"
},
  "geometry": {"coordinates":[2.8760299683,50.8308601379],"type":"Point"}
}