{
  "type": "Feature",
  "properties": {
    "iso:country":"BE",
    "sg:address":"Oostlangeweg 7",
    "sg:city":"Beveren",
    "sg:orig_category":"Rundveehouders",
    "sg:phone":"+32 3 575 81 98",
    "sg:postcode":"9130",
    "sg:province":"Oost-Vlaanderen",
    "wof:name":"Eugeen Van Den Eynde",
    "wof:placetype":"venue"
},
  "geometry": {"coordinates":[4.2506289482,51.3112602234],"type":"Point"}
}