{
  "type": "Feature",
  "properties": {
    "addr:full":"Rue De La Sympathie 34 Bruxelles (anderlecht) Bruxelles-Capitale 1070",
    "addr:housenumber":"34",
    "addr:postcode":"1070",
    "addr:street":"Rue De La Sympathie",
    "iso:country":"BE",
    "sg:address":"Rue De La Sympathie 34",
    "sg:city":"Bruxelles (anderlecht)",
    "sg:classifiers":[
        {
            "category":"Health Services",
            "subcategory":"Health Practitioner",
            "type":"Services"
        }
    ],
    "sg:phone":"+32 2 522 11 41",
    "sg:postcode":"1070",
    "sg:province":"Bruxelles-Capitale",
    "sg:tags":[
        "physiotherapist"
    ],
    "wof:name":"Laermans Sabine",
    "wof:placetype":"venue"
},
  "geometry": {"coordinates":[4.3004698753,50.823097229],"type":"Point"}
}