{
  "type": "Feature",
  "properties": {
    "addr:full":"Rue De La Wallonie 10 Verviers Li\u00e8ge 4801",
    "addr:housenumber":"10",
    "addr:postcode":"4801",
    "addr:street":"Rue De La Wallonie",
    "iso:country":"BE",
    "sg:address":"Rue De La Wallonie 10",
    "sg:city":"Verviers",
    "sg:classifiers":[
        {
            "category":"Arena",
            "subcategory":"Sports Club",
            "type":"Entertainment"
        }
    ],
    "sg:phone":"+32 87 33 63 29",
    "sg:postcode":"4801",
    "sg:province":"Li\u00e8ge",
    "sg:tags":[
        "de"
    ],
    "wof:name":"P.c. A.b.f.",
    "wof:placetype":"venue"
},
  "geometry": {"coordinates":[5.8930549622,50.5922393799],"type":"Point"}
}