{
  "type": "Feature",
  "properties": {
    "iso:country":"BE",
    "sg:address":"Waterloose Steenweg 1103",
    "sg:city":"Ukkel/uccle",
    "sg:orig_category":"Benzinestations and brandstoffen",
    "sg:phone":"+32 2 374 18 70",
    "sg:postcode":"1180",
    "sg:province":"Bruxelles-Capitale",
    "wof:name":"Sheluc",
    "wof:placetype":"venue"
},
  "geometry": {"coordinates":[4.3733119965,50.8014564514],"type":"Point"}
}