{
  "type": "Feature",
  "properties": {
    "iso:country":"BE",
    "sg:address":"Driekoningenstraat 26",
    "sg:city":"Wielsbeke (sint-baafs-vijve)",
    "sg:classifiers":[
        {
            "category":"Farming",
            "subcategory":"Farm & Veterinary Services",
            "type":"Manufacturing & Wholesale Goods"
        }
    ],
    "sg:phone":"+32 51 63 31 22",
    "sg:postcode":"8710",
    "sg:province":"West-Vlaanderen",
    "sg:tags":[
        "agricultural",
        "contractor"
    ],
    "wof:name":"Comyn F",
    "wof:placetype":"venue"
},
  "geometry": {"coordinates":[3.3821489811,50.937877655],"type":"Point"}
}