{
  "type": "Feature",
  "properties": {
    "iso:country":"BE",
    "sg:address":"Brugse Steenweg 133",
    "sg:city":"Veurne",
    "sg:orig_category":"R\u00e9parations and entretien de motos",
    "sg:phone":"+32 58 31 48 48",
    "sg:postcode":"8630",
    "sg:province":"West-Vlaanderen",
    "wof:name":"Delva Bikes",
    "wof:placetype":"venue"
},
  "geometry": {"coordinates":[2.6801519394,51.0749855042],"type":"Point"}
}