{
  "type": "Feature",
  "properties": {
    "iso:country":"BE",
    "sg:address":"Deidenberg 119",
    "sg:city":"Amel/ambleve",
    "sg:classifiers":[
        {
            "category":"Arena",
            "subcategory":"Sports Club",
            "type":"Entertainment"
        }
    ],
    "sg:phone":"+32 80 34 93 43",
    "sg:postcode":"4770",
    "sg:province":"Li\u00e8ge",
    "sg:tags":[
        "de"
    ],
    "wof:name":"A.m.c. St.vith",
    "wof:placetype":"venue"
},
  "geometry": {"coordinates":[6.1876211166,50.3251914978],"type":"Point"}
}