{
  "type": "Feature",
  "properties": {
    "addr:full":"Rue De Fize 2 Villers-le-bouillet Li\u00e8ge 4530",
    "addr:housenumber":"2",
    "addr:postcode":"4530",
    "addr:street":"Rue De Fize",
    "iso:country":"BE",
    "sg:address":"Rue De Fize 2",
    "sg:city":"Villers-le-bouillet",
    "sg:orig_category":"Zalen voor culturele evenementen",
    "sg:phone":"+32 19 54 64 18",
    "sg:postcode":"4530",
    "sg:province":"Li\u00e8ge",
    "wof:name":"Galerie Michel Hanon",
    "wof:placetype":"venue"
},
  "geometry": {"coordinates":[5.2560482025,50.5916442871],"type":"Point"}
}