{
  "type": "Feature",
  "properties": {
    "iso:country":"BE",
    "sg:address":"Rue De Huy 124",
    "sg:city":"Celles (viemme)",
    "sg:classifiers":[
        {
            "category":"Autos & Motor Vehicles",
            "subcategory":"Motorcycle Sales",
            "type":"Retail Goods"
        }
    ],
    "sg:phone":"+32 19 33 28 66",
    "sg:postcode":"4317",
    "sg:province":"Li\u00e8ge",
    "sg:tags":[
        "scooter",
        "-",
        "moped"
    ],
    "wof:name":"Delre J",
    "wof:placetype":"venue"
},
  "geometry": {"coordinates":[5.2644500732,50.6564064026],"type":"Point"}
}