{
  "type": "Feature",
  "properties": {
    "iso:country":"BE",
    "sg:address":"Golden Hopestr 35",
    "sg:city":"Drogenbos",
    "sg:classifiers":[
        {
            "category":"Food Court",
            "type":"Food & Drink"
        }
    ],
    "sg:phone":"+32 2 331 15 00",
    "sg:postcode":"1620",
    "sg:province":"Vlaams-Brabant",
    "sg:tags":[
        "product",
        "related"
    ],
    "wof:name":"Bleuse Interwine Nv",
    "wof:placetype":"venue"
},
  "geometry": {"coordinates":[4.2928471565,50.7982406616],"type":"Point"}
}