{
  "type": "Feature",
  "properties": {
    "iso:country":"BE",
    "sg:address":"Rue De L\u00b4espinette 2",
    "sg:city":"Lierneux",
    "sg:orig_category":"Elektrische installaties voor woningen",
    "sg:phone":"+32 80 31 98 04",
    "sg:postcode":"4990",
    "sg:province":"Li\u00e8ge",
    "wof:name":"Luc Monfort",
    "wof:placetype":"venue"
},
  "geometry": {"coordinates":[5.7939682007,50.2831878662],"type":"Point"}
}