{
  "type": "Feature",
  "properties": {
    "iso:country":"BE",
    "sg:address":"Frederik De Merodestraat 49",
    "sg:city":"Mechelen",
    "sg:orig_category":"Advocaten and juridische adviseurs",
    "sg:phone":"+32 15 20 91 11",
    "sg:postcode":"2800",
    "sg:province":"Antwerpen",
    "wof:name":"B. De Neef",
    "wof:placetype":"venue"
},
  "geometry": {"coordinates":[4.4817781448,51.0304031372],"type":"Point"}
}