{
  "type": "Feature",
  "properties": {
    "addr:full":"Dr Charles Leemansstraat 1 Sint-agatha-berchem/berchem-sainte-agathe Bruxelles-Capitale 1082",
    "addr:housenumber":"1",
    "addr:postcode":"1082",
    "addr:street":"Leemansstraat",
    "iso:country":"BE",
    "sg:address":"Dr Charles Leemansstraat 1",
    "sg:city":"Sint-agatha-berchem/berchem-sainte-agathe",
    "sg:orig_category":"Verplichte sociale verzekeringen",
    "sg:phone":"+32 2 465 19 16",
    "sg:postcode":"1082",
    "sg:province":"Bruxelles-Capitale",
    "wof:name":"Christelijke Mutualiteit",
    "wof:placetype":"venue"
},
  "geometry": {"coordinates":[4.2948431969,50.8639564514],"type":"Point"}
}