{
  "type": "Feature",
  "properties": {
    "addr:full":"Krijgsbaan 241 Zwijndrecht Antwerpen 2070",
    "addr:housenumber":"241",
    "addr:postcode":"2070",
    "addr:street":"Krijgsbaan",
    "iso:country":"BE",
    "sg:address":"Krijgsbaan 241",
    "sg:city":"Zwijndrecht",
    "sg:orig_category":"Agences de publicit\u00e9",
    "sg:phone":"+32 3 254 10 00",
    "sg:postcode":"2070",
    "sg:province":"Antwerpen",
    "wof:name":"Quality Link",
    "wof:placetype":"venue"
},
  "geometry": {"coordinates":[4.3156499863,51.2073707581],"type":"Point"}
}