{
  "type": "Feature",
  "properties": {
    "addr:full":"Haachtsesteenweg 6b1 Rotselaar Vlaams-Brabant 3118",
    "addr:housenumber":"6b1",
    "addr:postcode":"3118",
    "addr:street":"Haachtsesteenweg",
    "iso:country":"BE",
    "sg:address":"Haachtsesteenweg 6b1",
    "sg:city":"Rotselaar",
    "sg:orig_category":"Traducteurs and interpr\u00e8tes. Formation and enseignement",
    "sg:phone":"+32 16 60 31 24",
    "sg:postcode":"3118",
    "sg:province":"Vlaams-Brabant",
    "wof:name":"Scheers-grauwen E. Cbtip/bkvtf",
    "wof:placetype":"venue"
},
  "geometry": {"coordinates":[4.6940898895,50.970489502],"type":"Point"}
}