{
  "type": "Feature",
  "properties": {
    "addr:full":"Leopoldstraat 13 Turnhout Antwerpen 2300",
    "addr:housenumber":"13",
    "addr:postcode":"2300",
    "addr:street":"Leopoldstraat",
    "iso:country":"BE",
    "sg:address":"Leopoldstraat 13",
    "sg:city":"Turnhout",
    "sg:classifiers":[
        {
            "category":"Banks & Credit Unions",
            "subcategory":"Investment Brokerage",
            "type":"Services"
        }
    ],
    "sg:phone":"+32 14 42 05 08",
    "sg:postcode":"2300",
    "sg:province":"Antwerpen",
    "sg:tags":[
        "jean",
        "casual",
        "wear"
    ],
    "wof:name":"Originals",
    "wof:placetype":"venue"
},
  "geometry": {"coordinates":[4.9445152283,51.3229293823],"type":"Point"}
}