{
  "type": "Feature",
  "properties": {
    "addr:full":"Stationsstraat 69 Zaventem Vlaams-Brabant 1930",
    "addr:housenumber":"69",
    "addr:postcode":"1930",
    "addr:street":"Stationsstraat",
    "iso:country":"BE",
    "sg:address":"Stationsstraat 69",
    "sg:city":"Zaventem",
    "sg:orig_category":"Begrafeniswezen Natuursteenbewerking",
    "sg:phone":"+32 2 725 40 00",
    "sg:postcode":"1930",
    "sg:province":"Vlaams-Brabant",
    "wof:name":"Begraf. Vangrunderbeek W.",
    "wof:placetype":"venue"
},
  "geometry": {"coordinates":[4.471850872,50.8832588196],"type":"Point"}
}