{
  "type": "Feature",
  "properties": {
    "addr:full":"F\u00c9ronstr\u00c9e 71 Li\u00c8ge Li\u00e8ge 4000",
    "addr:housenumber":"71",
    "addr:postcode":"4000",
    "addr:street":"Fe\u0301Ronstre\u0301E",
    "iso:country":"BE",
    "sg:address":"F\u00c9ronstr\u00c9e 71",
    "sg:city":"Li\u00c8ge",
    "sg:classifiers":[
        {
            "category":"Restaurant",
            "type":"Food & Drink"
        }
    ],
    "sg:phone":"+32 4 222 41 68",
    "sg:postcode":"4000",
    "sg:province":"Li\u00e8ge",
    "wof:name":"J. Dubois",
    "wof:placetype":"venue"
},
  "geometry": {"coordinates":[5.5790071487,50.6465377808],"type":"Point"}
}