{
  "type": "Feature",
  "properties": {
    "iso:country":"BE",
    "sg:address":"Antwerpsesteenweg 114ba",
    "sg:city":"Stabroek",
    "sg:orig_category":"Loodgieterij, verwarming and sanitaire installaties Schoonmaakbedrijven and ongediertebestrijding",
    "sg:phone":"+32 3 665 11 00",
    "sg:postcode":"2940",
    "sg:province":"Antwerpen",
    "wof:name":"'t Schouwvagerke",
    "wof:placetype":"venue"
},
  "geometry": {"coordinates":[4.3649148941,51.331943512],"type":"Point"}
}