{
  "type": "Feature",
  "properties": {
    "iso:country":"BE",
    "sg:address":"Koningin Astridlaan 37b Box 7",
    "sg:city":"Kapellen",
    "sg:classifiers":[
        {
            "category":"Government",
            "subcategory":"Embassy",
            "type":"Public Place"
        }
    ],
    "sg:phone":"+32 3 665 01 98",
    "sg:postcode":"2950",
    "sg:province":"Antwerpen",
    "sg:tags":[
        "consulate"
    ],
    "wof:name":"Zwitserland (consulaat)",
    "wof:placetype":"venue"
},
  "geometry": {"coordinates":[4.4410319328,51.3130607605],"type":"Point"}
}