{
  "type": "Feature",
  "properties": {
    "iso:country":"BE",
    "sg:address":"Rue De La B\u00c9\u00d4le 120",
    "sg:city":"Chaudfontaine",
    "sg:orig_category":"Instituts de beaut\u00e9",
    "sg:phone":"+32 4 355 14 29",
    "sg:postcode":"4050",
    "sg:province":"Li\u00e8ge",
    "wof:name":"P Hanquet",
    "wof:placetype":"venue"
},
  "geometry": {"coordinates":[5.6575098038,50.5975112915],"type":"Point"}
}