{
  "type": "Feature",
  "properties": {
    "addr:full":"Rue De Bastogne Arlon Luxembourg 6700",
    "addr:postcode":"6700",
    "addr:street":"Rue De Bastogne",
    "iso:country":"BE",
    "sg:address":"Rue De Bastogne",
    "sg:city":"Arlon",
    "sg:classifiers":[
        {
            "category":"Fast Food",
            "type":"Food & Drink"
        }
    ],
    "sg:phone":"+32 63 23 36 11",
    "sg:postcode":"6700",
    "sg:province":"Luxembourg",
    "sg:tags":[
        "fried",
        "stand",
        "potato"
    ],
    "wof:name":"Nino (chez)",
    "wof:placetype":"venue"
},
  "geometry": {"coordinates":[5.8107700348,49.6900100708],"type":"Point"}
}