{
  "type": "Feature",
  "properties": {
    "iso:country":"BE",
    "sg:address":"Geldmuntstraat 5",
    "sg:city":"Brugge",
    "sg:classifiers":[
        {
            "category":"Shopping",
            "subcategory":"Clothing, Apparel, & Fashions",
            "type":"Retail Goods"
        }
    ],
    "sg:phone":"+32 50 33 88 28",
    "sg:postcode":"8000",
    "sg:province":"West-Vlaanderen",
    "sg:tags":[
        "lady",
        "clothing",
        "-"
    ],
    "wof:name":"Moggy's",
    "wof:placetype":"venue"
},
  "geometry": {"coordinates":[3.2226669788,51.2090301514],"type":"Point"}
}