{
  "type": "Feature",
  "properties": {
    "addr:full":"Rue Branche Planchard 26 Ans Li\u00e8ge 4430",
    "addr:housenumber":"26",
    "addr:postcode":"4430",
    "addr:street":"Rue Branche Planchard",
    "iso:country":"BE",
    "sg:address":"Rue Branche Planchard 26",
    "sg:city":"Ans",
    "sg:classifiers":[
        {
            "category":"Taxi",
            "type":"Transportation"
        }
    ],
    "sg:phone":"+32 4 246 31 31",
    "sg:postcode":"4430",
    "sg:province":"Li\u00e8ge",
    "wof:name":"Euro Taxis Ans",
    "wof:placetype":"venue"
},
  "geometry": {"coordinates":[5.5186247826,50.6588249207],"type":"Point"}
}