{
  "type": "Feature",
  "properties": {
    "iso:country":"BE",
    "sg:address":"Warande 9",
    "sg:city":"Oud-turnhout",
    "sg:classifiers":[
        {
            "category":"Professional",
            "subcategory":"Accounting & Tax Preparation",
            "type":"Services"
        }
    ],
    "sg:phone":"+32 14 45 02 50",
    "sg:postcode":"2360",
    "sg:province":"Antwerpen",
    "sg:tags":[
        "accountant"
    ],
    "wof:name":"Actizet Bvba",
    "wof:placetype":"venue"
},
  "geometry": {"coordinates":[5.0089650154,51.310333252],"type":"Point"}
}