{
  "type": "Feature",
  "properties": {
    "addr:full":"Kempische Steenweg Hasselt Limburg 3500",
    "addr:postcode":"3500",
    "addr:street":"Kempische Steenweg",
    "iso:country":"BE",
    "sg:address":"Kempische Steenweg",
    "sg:city":"Hasselt",
    "sg:classifiers":[
        {
            "category":"Real Estate",
            "subcategory":"Real Estate Services",
            "type":"Services"
        }
    ],
    "sg:phone":"+32 11 23 93 50",
    "sg:postcode":"3500",
    "sg:province":"Limburg",
    "wof:name":"Research Campus Hasselt",
    "wof:placetype":"venue"
},
  "geometry": {"coordinates":[5.3409399986,50.9384346008],"type":"Point"}
}