{
  "type": "Feature",
  "properties": {
    "addr:full":"Bondgenotenlaan 97 Leuven Vlaams-Brabant 3000",
    "addr:housenumber":"97",
    "addr:postcode":"3000",
    "addr:street":"Bondgenotenlaan",
    "iso:country":"BE",
    "sg:address":"Bondgenotenlaan 97",
    "sg:city":"Leuven",
    "sg:orig_category":"Dameskledingzaken",
    "sg:phone":"+32 16 22 43 12",
    "sg:postcode":"3000",
    "sg:province":"Vlaams-Brabant",
    "wof:name":"Huis Maxmara",
    "wof:placetype":"venue"
},
  "geometry": {"coordinates":[4.7089700699,50.8803901672],"type":"Point"}
}