{
  "type": "Feature",
  "properties": {
    "addr:full":"Berkebossenln 7 Mol Antwerpen 2400",
    "addr:housenumber":"7",
    "addr:postcode":"2400",
    "addr:street":"Berkebossenln",
    "iso:country":"BE",
    "sg:address":"Berkebossenln 7",
    "sg:city":"Mol",
    "sg:classifiers":[
        {
            "category":"Professional",
            "type":"Services"
        }
    ],
    "sg:phone":"+32 14 82 98 98",
    "sg:postcode":"2400",
    "sg:province":"Antwerpen",
    "sg:tags":[
        "transport",
        "road"
    ],
    "wof:name":"Van Gansewinkel Nv",
    "wof:placetype":"venue"
},
  "geometry": {"coordinates":[5.163008213,51.2037239075],"type":"Point"}
}