{
  "type": "Feature",
  "properties": {
    "iso:country":"BE",
    "sg:address":"Rue Des Oveyes 118",
    "sg:city":"Ans (alleur)",
    "sg:classifiers":[
        {
            "category":"Health Services",
            "subcategory":"Doctor",
            "type":"Services"
        }
    ],
    "sg:phone":"+32 4 263 13 33",
    "sg:postcode":"4432",
    "sg:province":"Li\u00e8ge",
    "sg:tags":[
        "medicinephysicians",
        "surgeon"
    ],
    "wof:name":"Appeldoorn J",
    "wof:placetype":"venue"
},
  "geometry": {"coordinates":[5.5219941139,50.6800804138],"type":"Point"}
}