{
  "type": "Feature",
  "properties": {
    "iso:country":"BE",
    "sg:address":"Boekelbaan 131",
    "sg:city":"Zwalm",
    "sg:orig_category":"Slagers",
    "sg:phone":"+32 55 49 91 44",
    "sg:postcode":"9630",
    "sg:province":"Oost-Vlaanderen",
    "wof:name":"C. Dossche",
    "wof:placetype":"venue"
},
  "geometry": {"coordinates":[3.7215299606,50.8520584106],"type":"Point"}
}