{
  "type": "Feature",
  "properties": {
    "iso:country":"BE",
    "sg:address":"Bertelsheide 6",
    "sg:city":"Huldenberg",
    "sg:orig_category":"Groententeelt",
    "sg:phone":"+32 16 47 74 32",
    "sg:postcode":"3040",
    "sg:province":"Vlaams-Brabant",
    "wof:name":"Hubert Trappeniers",
    "wof:placetype":"venue"
},
  "geometry": {"coordinates":[4.6143941879,50.8079566956],"type":"Point"}
}