{
  "type": "Feature",
  "properties": {
    "iso:country":"BE",
    "sg:address":"Rue G\u00e9n\u00e9ral Fiv\u00e9 7b",
    "sg:city":"Bruxelles (etterbeek)",
    "sg:classifiers":[
        {
            "category":"Retail",
            "subcategory":"Repair Shop",
            "type":"Services"
        }
    ],
    "sg:phone":"+32 2 648 09 33",
    "sg:postcode":"1040",
    "sg:province":"Bruxelles-Capitale",
    "sg:tags":[
        "-",
        "clothing",
        "alteration"
    ],
    "wof:name":"Leader Express",
    "wof:placetype":"venue"
},
  "geometry": {"coordinates":[4.3937129974,50.8286437988],"type":"Point"}
}