{
  "type": "Feature",
  "properties": {
    "addr:full":"Scheepsdalelaan 3 Brugge West-Vlaanderen 8000",
    "addr:housenumber":"3",
    "addr:postcode":"8000",
    "addr:street":"Scheepsdalelaan",
    "iso:country":"BE",
    "sg:address":"Scheepsdalelaan 3",
    "sg:city":"Brugge",
    "sg:orig_category":"Supermarch\u00e9s",
    "sg:phone":"+32 50 45 16 11",
    "sg:postcode":"8000",
    "sg:province":"West-Vlaanderen",
    "wof:name":"Super G.b.",
    "wof:placetype":"venue"
},
  "geometry": {"coordinates":[3.2136991024,51.2163887024],"type":"Point"}
}