{
  "type": "Feature",
  "properties": {
    "addr:full":"115 Jozef Verschaveweg 8380 Brugge Zeebrugge 115",
    "addr:housenumber":"115;115",
    "addr:postcode":"8380",
    "addr:street":"Jozef Verschaveweg;Zeebrugge",
    "iso:country":"BE",
    "sg:address":"115",
    "sg:city":"Jozef Verschaveweg 8380 Brugge Zeebrugge",
    "sg:classifiers":[
        {
            "category":"Banks & Credit Unions",
            "subcategory":"Investment Brokerage",
            "type":"Services"
        }
    ],
    "sg:phone":"+32 50 54 40 24",
    "sg:postcode":"115",
    "sg:tags":[
        "-",
        "transport",
        "related"
    ],
    "wof:name":"Belgian Coastal Agencies Nv",
    "wof:placetype":"venue"
},
  "geometry": {"coordinates":[3.2027099133,51.327495575],"type":"Point"}
}