{
  "type": "Feature",
  "properties": {
    "iso:country":"BE",
    "sg:address":"Grand Rue 45",
    "sg:city":"Tellin (resteigne)",
    "sg:classifiers":[
        {
            "category":"Building & Trades",
            "subcategory":"Construction",
            "type":"Services"
        }
    ],
    "sg:phone":"+32 84 38 70 52",
    "sg:postcode":"6927",
    "sg:province":"Luxembourg",
    "sg:tags":[
        "installation",
        "-",
        "central",
        "heating"
    ],
    "wof:name":"Collignon M Ets",
    "wof:placetype":"venue"
},
  "geometry": {"coordinates":[5.1757569313,50.0824203491],"type":"Point"}
}