{
  "type": "Feature",
  "properties": {
    "iso:country":"BE",
    "sg:address":"Rue Du Moulin 27",
    "sg:city":"Libramont-chevigny (freux)",
    "sg:classifiers":[
        {
            "category":"Shopping",
            "subcategory":"Discount & Variety Stores",
            "type":"Retail Goods"
        }
    ],
    "sg:phone":"+32 61 68 89 21",
    "sg:postcode":"6800",
    "sg:province":"Luxembourg",
    "sg:tags":[
        "shop",
        "clearers",
        "curiosity",
        "furniture"
    ],
    "wof:name":"Acanthe (l')",
    "wof:placetype":"venue"
},
  "geometry": {"coordinates":[5.4588608742,49.9749984741],"type":"Point"}
}