{
  "type": "Feature",
  "properties": {
    "addr:full":"Avenue Paul Pastur 6 Charleroi (mont-sur-marchienne) Hainaut 6032",
    "addr:housenumber":"6",
    "addr:postcode":"6032",
    "addr:street":"Avenue Paul Pastur",
    "iso:country":"BE",
    "sg:address":"Avenue Paul Pastur 6",
    "sg:city":"Charleroi (mont-sur-marchienne)",
    "sg:classifiers":[
        {
            "category":"Bakery",
            "type":"Food & Drink"
        }
    ],
    "sg:phone":"+32 71 36 31 32",
    "sg:postcode":"6032",
    "sg:province":"Hainaut",
    "sg:tags":[
        "confectioner",
        "baker"
    ],
    "wof:name":"Vandamme F",
    "wof:placetype":"venue"
},
  "geometry": {"coordinates":[4.404088974,50.3883209229],"type":"Point"}
}