{
  "type": "Feature",
  "properties": {
    "iso:country":"BE",
    "sg:address":"Rue Petit 5ba",
    "sg:city":"Anhee",
    "sg:classifiers":[
        {
            "category":"Travel",
            "subcategory":"Hotels & Motels",
            "type":"Entertainment"
        }
    ],
    "sg:phone":"+32 82 61 32 89",
    "sg:postcode":"5537",
    "sg:province":"Namur",
    "sg:tags":[
        "caf\u00e9s"
    ],
    "wof:name":"Taverne Le Mosan",
    "wof:placetype":"venue"
},
  "geometry": {"coordinates":[4.8819060326,50.3102073669],"type":"Point"}
}