{
  "type": "Feature",
  "properties": {
    "iso:country":"BE",
    "sg:address":"Kronekalseide 266",
    "sg:city":"Maldegem",
    "sg:orig_category":"Woningbouw",
    "sg:phone":"+32 50 72 08 05",
    "sg:postcode":"9990",
    "sg:province":"Oost-Vlaanderen",
    "wof:name":"Van Nieuwenhuyse",
    "wof:placetype":"venue"
},
  "geometry": {"coordinates":[3.3883299828,51.205619812],"type":"Point"}
}