{
  "type": "Feature",
  "properties": {
    "iso:country":"BE",
    "sg:address":"Stationsstraat 28",
    "sg:city":"Lendelede",
    "sg:orig_category":"Meubelzaken, woning- and keukeninrichting",
    "sg:phone":"+32 51 31 35 42",
    "sg:postcode":"8860",
    "sg:province":"West-Vlaanderen",
    "wof:name":"Martin Vanhove",
    "wof:placetype":"venue"
},
  "geometry": {"coordinates":[3.2420680523,50.885383606],"type":"Point"}
}