{
  "type": "Feature",
  "properties": {
    "addr:full":"Grote Baan 53-55 Lovendegem Oost-Vlaanderen 9920",
    "addr:housenumber":"53-55",
    "addr:postcode":"9920",
    "addr:street":"Grote Baan",
    "iso:country":"BE",
    "sg:address":"Grote Baan 53-55",
    "sg:city":"Lovendegem",
    "sg:classifiers":[
        {
            "category":"Food & Beverages",
            "subcategory":"Meat & Fish",
            "type":"Retail Goods"
        }
    ],
    "sg:phone":"+32 9 370 50 50",
    "sg:postcode":"9920",
    "sg:province":"Oost-Vlaanderen",
    "sg:tags":[
        "bacon",
        "ham"
    ],
    "wof:name":"Dufina Nv",
    "wof:placetype":"venue"
},
  "geometry": {"coordinates":[3.6390120983,51.0968933105],"type":"Point"}
}