{
  "type": "Feature",
  "properties": {
    "iso:country":"BE",
    "sg:address":"Hoevensebaan 111-113",
    "sg:city":"Kapellen",
    "sg:classifiers":[
        {
            "category":"Health Services",
            "subcategory":"Doctor",
            "type":"Services"
        }
    ],
    "sg:phone":"+32 3 664 20 10",
    "sg:postcode":"2950",
    "sg:province":"Antwerpen",
    "sg:tags":[
        "orthopedist"
    ],
    "wof:name":"Orthopedische Schoentechniek Bart Smeets Bvba",
    "wof:placetype":"venue"
},
  "geometry": {"coordinates":[4.4245820045,51.3129577637],"type":"Point"}
}