{
  "type": "Feature",
  "properties": {
    "addr:full":"Albert I Laan 64/w-1d Nieuwpoort West-Vlaanderen 8620",
    "addr:housenumber":"64 / w-1d",
    "addr:postcode":"8620",
    "addr:street":"Albert I Laan",
    "iso:country":"BE",
    "sg:address":"Albert I Laan 64/w-1d",
    "sg:city":"Nieuwpoort",
    "sg:orig_category":"Jardinage",
    "sg:phone":"+32 58 24 05 58",
    "sg:postcode":"8620",
    "sg:province":"West-Vlaanderen",
    "wof:name":"De Clerck F",
    "wof:placetype":"venue"
},
  "geometry": {"coordinates":[2.7409288883,51.1371994019],"type":"Point"}
}