{
  "type": "Feature",
  "properties": {
    "addr:full":"Rue De Hollogne 35 Gr\u00e2ce-hollogne (bierset) Li\u00e8ge 4460",
    "addr:housenumber":"35",
    "addr:postcode":"4460",
    "addr:street":"Rue De Hollogne;Bierset",
    "iso:country":"BE",
    "sg:address":"Rue De Hollogne 35",
    "sg:city":"Gr\u00e2ce-hollogne (bierset)",
    "sg:classifiers":[
        {
            "category":"Retail",
            "subcategory":"Funeral Services",
            "type":"Services"
        }
    ],
    "sg:phone":"+32 4 227 16 01",
    "sg:postcode":"4460",
    "sg:province":"Li\u00e8ge",
    "sg:tags":[
        "director"
    ],
    "wof:name":"For\u00eat Fun\u00e9railles",
    "wof:placetype":"venue"
},
  "geometry": {"coordinates":[5.455039978,50.6486206055],"type":"Point"}
}