{
  "type": "Feature",
  "properties": {
    "addr:full":"Kerkwegels 3 Kruibeke Oost-Vlaanderen 9150",
    "addr:housenumber":"3",
    "addr:postcode":"9150",
    "addr:street":"Kerkwegels",
    "iso:country":"BE",
    "sg:address":"Kerkwegels 3",
    "sg:city":"Kruibeke",
    "sg:orig_category":"Woningbouw",
    "sg:phone":"+32 3 774 21 40",
    "sg:postcode":"9150",
    "sg:province":"Oost-Vlaanderen",
    "wof:name":"Patrick Volckerick",
    "wof:placetype":"venue"
},
  "geometry": {"coordinates":[4.2949018478,51.1478004456],"type":"Point"}
}