{
  "type": "Feature",
  "properties": {
    "iso:country":"BE",
    "sg:address":"Loveldakker 9",
    "sg:city":"Destelbergen (heusden)",
    "sg:classifiers":[
        {
            "category":"Professional",
            "subcategory":"Secretarial Services",
            "type":"Services"
        }
    ],
    "sg:phone":"+32 9 232 56 89",
    "sg:postcode":"9070",
    "sg:province":"Oost-Vlaanderen",
    "sg:tags":[
        "firm"
    ],
    "wof:name":"Vermast P",
    "wof:placetype":"venue"
},
  "geometry": {"coordinates":[3.8192489147,51.0307388306],"type":"Point"}
}