{
  "type": "Feature",
  "properties": {
    "iso:country":"BE",
    "sg:address":"Montagne Sainte-walburge 31",
    "sg:city":"Li\u00c8ge",
    "sg:orig_category":"M\u00e9decins and sp\u00e9cialistes",
    "sg:phone":"+32 4 226 26 78",
    "sg:postcode":"4000",
    "sg:province":"Li\u00e8ge",
    "wof:name":"Louis Meys",
    "wof:placetype":"venue"
},
  "geometry": {"coordinates":[5.56731987,50.6485176086],"type":"Point"}
}