{
  "type": "Feature",
  "properties": {
    "iso:country":"BE",
    "sg:address":"Sint-jacobsnieuwstraat 104",
    "sg:city":"Gent",
    "sg:classifiers":[
        {
            "category":"Building & Trades",
            "subcategory":"Locksmith",
            "type":"Services"
        }
    ],
    "sg:phone":"+32 9 223 70 39",
    "sg:postcode":"9000",
    "sg:province":"Oost-Vlaanderen",
    "sg:tags":[
        "lock",
        "key"
    ],
    "wof:name":"Fks",
    "wof:placetype":"venue"
},
  "geometry": {"coordinates":[3.7297399044,51.0547485352],"type":"Point"}
}