{
  "type": "Feature",
  "properties": {
    "addr:full":"Rue Caporal Claes 6 Box 15 Bruxelles (schaerbeek) Bruxelles-Capitale 1030",
    "addr:housenumber":"6 box 15",
    "addr:postcode":"1030",
    "addr:street":"Rue Caporal Claes",
    "iso:country":"BE",
    "sg:address":"Rue Caporal Claes 6 Box 15",
    "sg:city":"Bruxelles (schaerbeek)",
    "sg:classifiers":[
        {
            "category":"Professional",
            "subcategory":"Accounting & Tax Preparation",
            "type":"Services"
        }
    ],
    "sg:phone":"+32 2 242 05 93",
    "sg:postcode":"1030",
    "sg:province":"Bruxelles-Capitale",
    "sg:tags":[
        "bookkeeper"
    ],
    "wof:name":"International Fiscal Agreement Sa",
    "wof:placetype":"venue"
},
  "geometry": {"coordinates":[4.3887138367,50.8675270081],"type":"Point"}
}