{
  "type": "Feature",
  "properties": {
    "addr:full":"Kerkstraat 1 Opwijk Vlaams-Brabant 1745",
    "addr:housenumber":"1",
    "addr:postcode":"1745",
    "addr:street":"Kerkstraat",
    "iso:country":"BE",
    "sg:address":"Kerkstraat 1",
    "sg:city":"Opwijk",
    "sg:orig_category":"Banken and kredietinstellingen",
    "sg:phone":"+32 52 35 77 11",
    "sg:postcode":"1745",
    "sg:province":"Vlaams-Brabant",
    "wof:name":"Zakenkantoor Bogemans",
    "wof:placetype":"venue"
},
  "geometry": {"coordinates":[4.1897721291,50.9693946838],"type":"Point"}
}