{
  "type": "Feature",
  "properties": {
    "iso:country":"BE",
    "sg:address":"Rue Saint-roch 68",
    "sg:city":"Mettet (biesme)",
    "sg:classifiers":[
        {
            "category":"Shopping",
            "subcategory":"Bicycles & Sporting Goods",
            "type":"Retail Goods"
        }
    ],
    "sg:phone":"+32 71 72 63 90",
    "sg:postcode":"5640",
    "sg:province":"Namur",
    "sg:tags":[
        "-"
    ],
    "wof:name":"F.g. Cycles",
    "wof:placetype":"venue"
},
  "geometry": {"coordinates":[4.6231679916,50.3307151794],"type":"Point"}
}