{
  "type": "Feature",
  "properties": {
    "iso:country":"BE",
    "sg:address":"Place Fr\u00e9d\u00e9ric 14",
    "sg:city":"Charleroi (roux)",
    "sg:classifiers":[
        {
            "category":"Real Estate",
            "subcategory":"Architect",
            "type":"Services"
        }
    ],
    "sg:phone":"+32 71 46 00 45",
    "sg:postcode":"6044",
    "sg:province":"Hainaut",
    "wof:name":"Audrit J",
    "wof:placetype":"venue"
},
  "geometry": {"coordinates":[4.3840718269,50.4334449768],"type":"Point"}
}