{
  "type": "Feature",
  "properties": {
    "iso:country":"BE",
    "sg:address":"Rue D'havr\u00c9 8",
    "sg:city":"Mons",
    "sg:orig_category":"Voedingsspeciaalzaken Zuivelproducten",
    "sg:phone":"+32 65 31 84 32",
    "sg:postcode":"7000",
    "sg:province":"Hainaut",
    "wof:name":"Dominique Vandoorne",
    "wof:placetype":"venue"
},
  "geometry": {"coordinates":[3.9529678822,50.4537200928],"type":"Point"}
}