{
  "type": "Feature",
  "properties": {
    "iso:country":"BE",
    "sg:address":"Rue Basse-wez 315",
    "sg:city":"Li\u00c8ge",
    "sg:orig_category":"Apotheken",
    "sg:phone":"+32 4 343 10 13",
    "sg:postcode":"4020",
    "sg:province":"Li\u00e8ge",
    "wof:name":"Pascale Puts",
    "wof:placetype":"venue"
},
  "geometry": {"coordinates":[5.5881919861,50.6322402954],"type":"Point"}
}