{
  "type": "Feature",
  "properties": {
    "iso:country":"BE",
    "sg:address":"Kaaskerkestraat 115",
    "sg:city":"Diksmuide",
    "sg:orig_category":"Rundveehouders Varkenskwekers",
    "sg:phone":"+32 51 50 00 23",
    "sg:postcode":"8600",
    "sg:province":"West-Vlaanderen",
    "wof:name":"Gerard Voet",
    "wof:placetype":"venue"
},
  "geometry": {"coordinates":[2.8290829659,51.0379714966],"type":"Point"}
}