{
  "type": "Feature",
  "properties": {
    "addr:full":"Antwerpsestr 302 Boom Antwerpen 2850",
    "addr:housenumber":"302",
    "addr:postcode":"2850",
    "iso:country":"BE",
    "sg:address":"Antwerpsestr 302",
    "sg:city":"Boom",
    "sg:classifiers":[
        {
            "category":"Travel",
            "subcategory":"Hotels & Motels",
            "type":"Entertainment"
        }
    ],
    "sg:phone":"+32 3 888 65 68",
    "sg:postcode":"2850",
    "sg:province":"Antwerpen",
    "sg:tags":[
        "hotels",
        "business",
        "restaurant"
    ],
    "wof:name":"Beukenhof Nv",
    "wof:placetype":"venue"
},
  "geometry": {"coordinates":[4.3673272133,51.0966682434],"type":"Point"}
}