{
  "type": "Feature",
  "properties": {
    "iso:country":"BE",
    "sg:address":"Arbeidsstraat 1",
    "sg:city":"Anderlecht",
    "sg:orig_category":"Verhuisdiensten",
    "sg:phone":"+32 2 523 23 23",
    "sg:postcode":"1070",
    "sg:province":"Bruxelles-Capitale",
    "wof:name":"Les Transports Verts",
    "wof:placetype":"venue"
},
  "geometry": {"coordinates":[4.3091449738,50.820148468],"type":"Point"}
}