{
  "type": "Feature",
  "properties": {
    "addr:full":"Antwerpsesteenweg 50 Gent Oost-Vlaanderen 9000",
    "addr:housenumber":"50",
    "addr:postcode":"9000",
    "addr:street":"Antwerpsesteenweg;Oost-Vlaanderen",
    "iso:country":"BE",
    "sg:address":"Antwerpsesteenweg 50",
    "sg:city":"Gent",
    "sg:classifiers":[
        {
            "category":"Cafe",
            "type":"Food & Drink"
        }
    ],
    "sg:phone":"+32 9 219 07 56",
    "sg:postcode":"9000",
    "sg:province":"Oost-Vlaanderen",
    "sg:tags":[
        "snack-bars"
    ],
    "wof:name":"Take It Easy",
    "wof:placetype":"venue"
},
  "geometry": {"coordinates":[3.742882967,51.0580062866],"type":"Point"}
}