{
  "type": "Feature",
  "properties": {
    "iso:country":"BE",
    "sg:address":"Edingsestweg 67",
    "sg:city":"Asse",
    "sg:orig_category":"Herstellingen and onderhoud van auto's",
    "sg:phone":"+32 2 452 64 42",
    "sg:postcode":"1730",
    "sg:province":"Vlaams-Brabant",
    "wof:name":"Joss L",
    "wof:placetype":"venue"
},
  "geometry": {"coordinates":[4.1875400543,50.903793335],"type":"Point"}
}