{
  "type": "Feature",
  "properties": {
    "addr:full":"Rue Du Grand-hy 0 Rochefort Namur 5580",
    "addr:housenumber":"0",
    "addr:postcode":"5580",
    "addr:street":"Rue Du Grand-Hy",
    "iso:country":"BE",
    "sg:address":"Rue Du Grand-hy 0",
    "sg:city":"Rochefort",
    "sg:orig_category":"Kampeerterreinen",
    "sg:phone":"+32 84 37 72 90",
    "sg:postcode":"5580",
    "sg:province":"Namur",
    "wof:name":"Camping Du Pirot",
    "wof:placetype":"venue"
},
  "geometry": {"coordinates":[5.1869068146,50.1231842041],"type":"Point"}
}