{
  "type": "Feature",
  "properties": {
    "iso:country":"BE",
    "sg:address":"Hofstraat 52",
    "sg:city":"Gent",
    "sg:orig_category":"Balie van Gent. Avocats and conseillers juridiques. Avocats and conseillers juridiques",
    "sg:phone":"+32 9 269 08 44",
    "sg:postcode":"9000",
    "sg:province":"Oost-Vlaanderen",
    "wof:name":"Carrette Maud",
    "wof:placetype":"venue"
},
  "geometry": {"coordinates":[3.7306470871,51.0444641113],"type":"Point"}
}