{
  "type": "Feature",
  "properties": {
    "iso:country":"BE",
    "sg:address":"Dorp West 46",
    "sg:city":"Zwijndrecht",
    "sg:orig_category":"Kapsalons",
    "sg:phone":"+32 3 252 58 66",
    "sg:postcode":"2070",
    "sg:province":"Antwerpen",
    "wof:name":"Coiffure Cokure",
    "wof:placetype":"venue"
},
  "geometry": {"coordinates":[4.3233089447,51.2189216614],"type":"Point"}
}