{
  "type": "Feature",
  "properties": {
    "addr:full":"Clos Du Chemin Creux 4b18 Schaarbeek/schaerbeek Bruxelles-Capitale 1030",
    "addr:housenumber":"4b18",
    "addr:postcode":"1030",
    "addr:street":"Clos Du Chemin Creux",
    "iso:country":"BE",
    "sg:address":"Clos Du Chemin Creux 4b18",
    "sg:city":"Schaarbeek/schaerbeek",
    "sg:classifiers":[
        {
            "category":"Insurance",
            "subcategory":"Life Insurance",
            "type":"Services"
        }
    ],
    "sg:phone":"+32 2 241 67 33",
    "sg:postcode":"1030",
    "sg:province":"Bruxelles-Capitale",
    "sg:tags":[
        "assurance"
    ],
    "wof:name":"Daelmans",
    "wof:placetype":"venue"
},
  "geometry": {"coordinates":[4.3936471939,50.8647460938],"type":"Point"}
}