{
  "type": "Feature",
  "properties": {
    "iso:country":"BE",
    "sg:address":"Vremdesesteenweg 200",
    "sg:city":"Boechout",
    "sg:orig_category":"Plomberie, chauffage and installations sanitaires",
    "sg:phone":"+32 3 455 07 07",
    "sg:postcode":"2530",
    "sg:province":"Antwerpen",
    "wof:name":"Gerd Molenaar",
    "wof:placetype":"venue"
},
  "geometry": {"coordinates":[4.5083031654,51.1678962708],"type":"Point"}
}