{
  "type": "Feature",
  "properties": {
    "addr:full":"Frankrijklei 72 Antwerpen Antwerpen 2000",
    "addr:housenumber":"72",
    "addr:postcode":"2000",
    "addr:street":"Frankrijklei",
    "iso:country":"BE",
    "sg:address":"Frankrijklei 72",
    "sg:city":"Antwerpen",
    "sg:classifiers":[
        {
            "category":"Community Center",
            "subcategory":"Social",
            "type":"Public Place"
        }
    ],
    "sg:phone":"+32 3 232 40 52",
    "sg:postcode":"2000",
    "sg:province":"Antwerpen",
    "sg:tags":[
        "-",
        "haute",
        "clothing",
        "couture"
    ],
    "wof:name":"Georgia",
    "wof:placetype":"venue"
},
  "geometry": {"coordinates":[4.4138689041,51.2164421082],"type":"Point"}
}