{
  "type": "Feature",
  "properties": {
    "iso:country":"BE",
    "sg:address":"Kerselarendreef 84",
    "sg:city":"Sint-gillis-waas",
    "sg:classifiers":[
        {
            "category":"Cafe",
            "type":"Food & Drink"
        }
    ],
    "sg:phone":"+32 3 770 79 23",
    "sg:postcode":"9170",
    "sg:province":"Oost-Vlaanderen",
    "sg:tags":[
        "caf\u00e9s"
    ],
    "wof:name":"Marleen De Smet",
    "wof:placetype":"venue"
},
  "geometry": {"coordinates":[4.0975217819,51.2594490051],"type":"Point"}
}