{
  "type": "Feature",
  "properties": {
    "addr:full":"Dr\u00c8ve De La Ferme 36 Wezembeek-oppem/wezembeek-oppem Vlaams-Brabant 1970",
    "addr:housenumber":"36",
    "addr:postcode":"1970",
    "addr:street":"Dre\u0300Ve De La Ferme",
    "iso:country":"BE",
    "sg:address":"Dr\u00c8ve De La Ferme 36",
    "sg:city":"Wezembeek-oppem/wezembeek-oppem",
    "sg:orig_category":"M\u00e9decins and sp\u00e9cialistes",
    "sg:phone":"+32 2 731 13 91",
    "sg:postcode":"1970",
    "sg:province":"Vlaams-Brabant",
    "wof:name":"J. Walraet",
    "wof:placetype":"venue"
},
  "geometry": {"coordinates":[4.4912700653,50.8503608704],"type":"Point"}
}