{
  "type": "Feature",
  "properties": {
    "addr:full":"Donkerstraat 30 Roosdaal Vlaams-Brabant 1760",
    "addr:housenumber":"30",
    "addr:postcode":"1760",
    "addr:street":"Donkerstraat",
    "iso:country":"BE",
    "sg:address":"Donkerstraat 30",
    "sg:city":"Roosdaal",
    "sg:orig_category":"Herstellingen and onderhoud aan huis voor voertuigen",
    "sg:phone":"+32 2 581 01 70",
    "sg:postcode":"1760",
    "sg:province":"Vlaams-Brabant",
    "wof:name":"Blomme Ninove",
    "wof:placetype":"venue"
},
  "geometry": {"coordinates":[4.0744271278,50.8435707092],"type":"Point"}
}