{
  "type": "Feature",
  "properties": {
    "addr:full":"Rue Devant Haz\u00c9e 5 Lierneux Li\u00e8ge 4990",
    "addr:housenumber":"5",
    "addr:postcode":"4990",
    "addr:street":"Rue Devant Haze\u0301E",
    "iso:country":"BE",
    "sg:address":"Rue Devant Haz\u00c9e 5",
    "sg:city":"Lierneux",
    "sg:orig_category":"Dierenartsen",
    "sg:phone":"+32 80 31 94 18",
    "sg:postcode":"4990",
    "sg:province":"Li\u00e8ge",
    "wof:name":"Barbara Denys",
    "wof:placetype":"venue"
},
  "geometry": {"coordinates":[5.7894439697,50.2858772278],"type":"Point"}
}