{
  "type": "Feature",
  "properties": {
    "addr:full":"Lange Haagstraat 20bb Wichelen Oost-Vlaanderen 9260",
    "addr:housenumber":"20bb",
    "addr:postcode":"9260",
    "addr:street":"Lange Haagstraat",
    "iso:country":"BE",
    "sg:address":"Lange Haagstraat 20bb",
    "sg:city":"Wichelen",
    "sg:orig_category":"Elektrische installaties voor woningen Huishoudapparaten, televisies and radio's",
    "sg:phone":"+32 9 369 63 26",
    "sg:postcode":"9260",
    "sg:province":"Oost-Vlaanderen",
    "wof:name":"Henri De Coninck",
    "wof:placetype":"venue"
},
  "geometry": {"coordinates":[3.9630949497,51.0004692078],"type":"Point"}
}