{
  "type": "Feature",
  "properties": {
    "iso:country":"BE",
    "sg:address":"Langvoort 55",
    "sg:city":"Laakdal (forest)",
    "sg:classifiers":[
        {
            "category":"Professional",
            "type":"Services"
        }
    ],
    "sg:phone":"+32 13 67 13 35",
    "sg:postcode":"2430",
    "sg:province":"Antwerpen",
    "sg:tags":[
        "industrial",
        "work",
        "-",
        "maintenance"
    ],
    "wof:name":"Mannytech Bvba",
    "wof:placetype":"venue"
},
  "geometry": {"coordinates":[5.0836091042,51.0963668823],"type":"Point"}
}