{
  "type": "Feature",
  "properties": {
    "iso:country":"BE",
    "sg:address":"Rue Joseph Ii 19",
    "sg:city":"Bruxelles",
    "sg:classifiers":[
        {
            "category":"Cafe",
            "type":"Food & Drink"
        }
    ],
    "sg:phone":"+32 2 280 15 14",
    "sg:postcode":"1000",
    "sg:province":"Bruxelles-Capitale",
    "sg:tags":[
        "snack-bars"
    ],
    "wof:name":"Foro Romano",
    "wof:placetype":"venue"
},
  "geometry": {"coordinates":[4.3707680702,50.845954895],"type":"Point"}
}