{
  "type": "Feature",
  "properties": {
    "iso:country":"BE",
    "sg:address":"Nieuwe Westweg-haven 742",
    "sg:city":"Antwerpen",
    "sg:classifiers":[
        {
            "category":"Banks & Credit Unions",
            "subcategory":"Investment Brokerage",
            "type":"Services"
        }
    ],
    "sg:phone":"+32 3 561 55 11",
    "sg:postcode":"2040",
    "sg:province":"Antwerpen",
    "sg:tags":[
        "transshipment",
        "port"
    ],
    "wof:name":"Antwerp Combined Terminals Nv",
    "wof:placetype":"venue"
},
  "geometry": {"coordinates":[4.3351092339,51.3326950073],"type":"Point"}
}