{
  "type": "Feature",
  "properties": {
    "iso:country":"BE",
    "sg:address":"Rue Henri Fays 27",
    "sg:city":"Anthisnes",
    "sg:orig_category":"Artsen and specialisten",
    "sg:phone":"+32 4 383 75 41",
    "sg:postcode":"4160",
    "sg:province":"Li\u00e8ge",
    "wof:name":"R. Louis",
    "wof:placetype":"venue"
},
  "geometry": {"coordinates":[5.5121321678,50.4843597412],"type":"Point"}
}