{
  "type": "Feature",
  "properties": {
    "iso:country":"BE",
    "sg:address":"Stationsstraat 37",
    "sg:city":"Ieper",
    "sg:classifiers":[
        {
            "category":"Bars & Pubs",
            "type":"Food & Drink"
        }
    ],
    "sg:phone":"+32 57 20 14 15",
    "sg:postcode":"8900",
    "sg:province":"West-Vlaanderen",
    "wof:name":"St-sebastiaan",
    "wof:placetype":"venue"
},
  "geometry": {"coordinates":[2.880012989,50.8487892151],"type":"Point"}
}