{
  "type": "Feature",
  "properties": {
    "addr:full":"Kardinaal Sterckxlaan 38 Meise Vlaams-Brabant 1860",
    "addr:housenumber":"38",
    "addr:postcode":"1860",
    "addr:street":"Kardinaal Sterckxlaan",
    "iso:country":"BE",
    "sg:address":"Kardinaal Sterckxlaan 38",
    "sg:city":"Meise",
    "sg:orig_category":"Pleisterwerk",
    "sg:phone":"+32 2 269 06 27",
    "sg:postcode":"1860",
    "sg:province":"Vlaams-Brabant",
    "wof:name":"Etienne Hermans",
    "wof:placetype":"venue"
},
  "geometry": {"coordinates":[4.3001608849,50.9391403198],"type":"Point"}
}