{
  "type": "Feature",
  "properties": {
    "iso:country":"BE",
    "sg:address":"Sint-jobstraat 188",
    "sg:city":"Heusden-zolder",
    "sg:orig_category":"Epiceries",
    "sg:phone":"+32 11 25 04 49",
    "sg:postcode":"3550",
    "sg:province":"Limburg",
    "wof:name":"Fa. Quetin",
    "wof:placetype":"venue"
},
  "geometry": {"coordinates":[5.2746949196,50.9807357788],"type":"Point"}
}