{
  "type": "Feature",
  "properties": {
    "addr:full":"Rue Du Maquis 35 Seraing Li\u00e8ge 4100",
    "addr:housenumber":"35",
    "addr:postcode":"4100",
    "addr:street":"Rue Du Maquis",
    "iso:country":"BE",
    "sg:address":"Rue Du Maquis 35",
    "sg:city":"Seraing",
    "sg:classifiers":[
        {
            "category":"Professional",
            "subcategory":"Engineering",
            "type":"Services"
        }
    ],
    "sg:phone":"+32 4 330 94 00",
    "sg:postcode":"4100",
    "sg:province":"Li\u00e8ge",
    "sg:tags":[
        "-"
    ],
    "wof:name":"Busi F",
    "wof:placetype":"venue"
},
  "geometry": {"coordinates":[5.5206050873,50.5968933105],"type":"Point"}
}