{
  "type": "Feature",
  "properties": {
    "iso:country":"BE",
    "sg:address":"Avenue De L\u00b4observatoire 112b7",
    "sg:city":"Ukkel/uccle",
    "sg:orig_category":"Evaluation and estimation de biens immobiliers",
    "sg:phone":"+32 2 374 74 15",
    "sg:postcode":"1180",
    "sg:province":"Bruxelles-Capitale",
    "wof:name":"R. Pick",
    "wof:placetype":"venue"
},
  "geometry": {"coordinates":[4.3650288582,50.799495697],"type":"Point"}
}