{
  "type": "Feature",
  "properties": {
    "addr:full":"Rue De L'expansion 14 Ans (alleur) Li\u00e8ge 4432",
    "addr:housenumber":"14",
    "addr:postcode":"4432",
    "addr:street":"Rue De L'Expansion",
    "iso:country":"BE",
    "sg:address":"Rue De L'expansion 14",
    "sg:city":"Ans (alleur)",
    "sg:classifiers":[
        {
            "category":"Retail",
            "subcategory":"Auto Repair",
            "type":"Services"
        }
    ],
    "sg:phone":"+32 4 247 12 76",
    "sg:postcode":"4432",
    "sg:province":"Li\u00e8ge",
    "sg:tags":[
        "automobile-body"
    ],
    "wof:name":"A.u.r.e.lie",
    "wof:placetype":"venue"
},
  "geometry": {"coordinates":[5.5291252136,50.6798400879],"type":"Point"}
}