{
  "type": "Feature",
  "properties": {
    "addr:full":"Stationsstraat 34a Zedelgem (loppem) West-Vlaanderen 8210",
    "addr:housenumber":"34a",
    "addr:postcode":"8210",
    "addr:street":"Stationsstraat",
    "iso:country":"BE",
    "sg:address":"Stationsstraat 34a",
    "sg:city":"Zedelgem (loppem)",
    "sg:classifiers":[
        {
            "category":"Real Estate",
            "subcategory":"Real Estate Services",
            "type":"Services"
        }
    ],
    "sg:phone":"+32 50 82 69 12",
    "sg:postcode":"8210",
    "sg:province":"West-Vlaanderen",
    "wof:name":"Vandaele Nv",
    "wof:placetype":"venue"
},
  "geometry": {"coordinates":[3.1498448849,51.1381645203],"type":"Point"}
}