{
  "type": "Feature",
  "properties": {
    "addr:full":"Rue Des Trois Rivages 1 Li\u00e8ge 1 (wandre) Li\u00e8ge 4020",
    "addr:housenumber":"1;1",
    "addr:postcode":"4020",
    "addr:street":"Rue Des Trois Rivages",
    "iso:country":"BE",
    "sg:address":"Rue Des Trois Rivages 1",
    "sg:city":"Li\u00e8ge 1 (wandre)",
    "sg:classifiers":[
        {
            "category":"Building & Trades",
            "subcategory":"Pest Control",
            "type":"Services"
        }
    ],
    "sg:phone":"+32 4 362 24 58",
    "sg:postcode":"4020",
    "sg:province":"Li\u00e8ge",
    "sg:tags":[
        "painting",
        "contractor"
    ],
    "wof:name":"Cr\u00e8me P",
    "wof:placetype":"venue"
},
  "geometry": {"coordinates":[5.652463913,50.6595726013],"type":"Point"}
}