{
  "type": "Feature",
  "properties": {
    "addr:full":"Boembeekstraat 39 Oudenaarde Oost-Vlaanderen 9700",
    "addr:housenumber":"39",
    "addr:postcode":"9700",
    "addr:street":"Boembeekstraat",
    "iso:country":"BE",
    "sg:address":"Boembeekstraat 39",
    "sg:city":"Oudenaarde",
    "sg:classifiers":[
        {
            "category":"Building & Trades",
            "subcategory":"Electrical",
            "type":"Services"
        }
    ],
    "sg:phone":"+32 55 31 24 63",
    "sg:postcode":"9700",
    "sg:province":"Oost-Vlaanderen",
    "sg:tags":[
        "electric",
        "-",
        "housewiring",
        "contractor"
    ],
    "wof:name":"Vanden Berghe",
    "wof:placetype":"venue"
},
  "geometry": {"coordinates":[3.6317980289,50.8335838318],"type":"Point"}
}