{
  "type": "Feature",
  "properties": {
    "addr:full":"Rue De La Station 17 Paliseul Luxembourg 6850",
    "addr:housenumber":"17",
    "addr:postcode":"6850",
    "addr:street":"Rue De La Station",
    "iso:country":"BE",
    "sg:address":"Rue De La Station 17",
    "sg:city":"Paliseul",
    "sg:orig_category":"Woodenware",
    "sg:phone":"+32 61 53 31 09",
    "sg:postcode":"6850",
    "sg:province":"Luxembourg",
    "wof:name":"De Maerteleire",
    "wof:placetype":"venue"
},
  "geometry": {"coordinates":[5.1322040558,49.9024963379],"type":"Point"}
}