{
  "type": "Feature",
  "properties": {
    "addr:full":"Oude Dorpsweg 52-1 Jabbeke West-Vlaanderen 8490",
    "addr:housenumber":"52-1",
    "addr:postcode":"8490",
    "addr:street":"Oude Dorpsweg",
    "iso:country":"BE",
    "sg:address":"Oude Dorpsweg 52-1",
    "sg:city":"Jabbeke",
    "sg:orig_category":"Herstellingen and onderhoud van auto's",
    "sg:phone":"+32 50 39 58 06",
    "sg:postcode":"8490",
    "sg:province":"West-Vlaanderen",
    "wof:name":"Automeca",
    "wof:placetype":"venue"
},
  "geometry": {"coordinates":[3.0908770561,51.1822242737],"type":"Point"}
}