{
  "type": "Feature",
  "properties": {
    "iso:country":"BE",
    "sg:address":"Steenweg Op Weelde 5",
    "sg:city":"Merksplas",
    "sg:orig_category":"Chaussures",
    "sg:phone":"+32 14 63 27 07",
    "sg:postcode":"2330",
    "sg:province":"Antwerpen",
    "wof:name":"Huis Veja",
    "wof:placetype":"venue"
},
  "geometry": {"coordinates":[4.8669829369,51.369052887],"type":"Point"}
}