{
  "type": "Feature",
  "properties": {
    "addr:full":"Graankaai 5 Roeselare West-Vlaanderen 8800",
    "addr:housenumber":"5",
    "addr:postcode":"8800",
    "addr:street":"Graankaai",
    "iso:country":"BE",
    "sg:address":"Graankaai 5",
    "sg:city":"Roeselare",
    "sg:classifiers":[
        {
            "category":"Autos & Motor Vehicles",
            "subcategory":"Automobile Sales",
            "type":"Retail Goods"
        }
    ],
    "sg:phone":"+32 50 31 31 18",
    "sg:postcode":"8800",
    "sg:province":"West-Vlaanderen",
    "sg:tags":[
        "-",
        "truck"
    ],
    "wof:name":"Spillier Daf Trucks",
    "wof:placetype":"venue"
},
  "geometry": {"coordinates":[3.1580550671,50.9434738159],"type":"Point"}
}