{
  "type": "Feature",
  "properties": {
    "addr:full":"Rue De Loverval 16 Ch\u00c2telet Hainaut 6200",
    "addr:housenumber":"16",
    "addr:postcode":"6200",
    "addr:street":"Rue De Loverval",
    "iso:country":"BE",
    "sg:address":"Rue De Loverval 16",
    "sg:city":"Ch\u00c2telet",
    "sg:orig_category":"Schoonheidssalons",
    "sg:phone":"+32 71 39 33 60",
    "sg:postcode":"6200",
    "sg:province":"Hainaut",
    "wof:name":"Thalasso-relax-beaut\u00c9",
    "wof:placetype":"venue"
},
  "geometry": {"coordinates":[4.5178790092,50.4030418396],"type":"Point"}
}