{
  "type": "Feature",
  "properties": {
    "addr:full":"Stapelstraat 68 Sint-truiden Limburg 3800",
    "addr:housenumber":"68",
    "addr:postcode":"3800",
    "addr:street":"Stapelstraat",
    "iso:country":"BE",
    "sg:address":"Stapelstraat 68",
    "sg:city":"Sint-truiden",
    "sg:orig_category":"Baby- and kinderkleding",
    "sg:phone":"+32 11 68 72 74",
    "sg:postcode":"3800",
    "sg:province":"Limburg",
    "wof:name":"Huis Sukie",
    "wof:placetype":"venue"
},
  "geometry": {"coordinates":[5.1819648743,50.8154602051],"type":"Point"}
}