{
  "type": "Feature",
  "properties": {
    "addr:full":"Leuvensesteenweg 210 Aarschot (gelrode) Vlaams-Brabant 3200",
    "addr:housenumber":"210",
    "addr:postcode":"3200",
    "addr:street":"Leuvensesteenweg",
    "iso:country":"BE",
    "sg:address":"Leuvensesteenweg 210",
    "sg:city":"Aarschot (gelrode)",
    "sg:classifiers":[
        {
            "category":"Real Estate",
            "subcategory":"Surveying",
            "type":"Services"
        }
    ],
    "sg:phone":"+32 16 55 15 63",
    "sg:postcode":"3200",
    "sg:province":"Vlaams-Brabant",
    "sg:tags":[
        "lettering",
        "letter"
    ],
    "wof:name":"Complet",
    "wof:placetype":"venue"
},
  "geometry": {"coordinates":[4.8172521591,50.978225708],"type":"Point"}
}