{
  "type": "Feature",
  "properties": {
    "iso:country":"BE",
    "sg:address":"Rue Albert Ier 41",
    "sg:city":"Hannut",
    "sg:orig_category":"Apotheken",
    "sg:phone":"+32 19 51 11 45",
    "sg:postcode":"4280",
    "sg:province":"Li\u00e8ge",
    "wof:name":"Philippe Gustin",
    "wof:placetype":"venue"
},
  "geometry": {"coordinates":[5.081964016,50.6703643799],"type":"Point"}
}