{
  "type": "Feature",
  "properties": {
    "iso:country":"BE",
    "sg:address":"Rue De Nimy 84",
    "sg:city":"Mons",
    "sg:classifiers":[
        {
            "category":"Fast Food",
            "type":"Food & Drink"
        }
    ],
    "sg:phone":"+32 65 34 85 85",
    "sg:postcode":"7000",
    "sg:province":"Hainaut",
    "sg:tags":[
        "restaurant",
        "\u00c0",
        "domicile",
        "emporter",
        "livraison",
        "restaurants"
    ],
    "wof:name":"Au Petit'creux",
    "wof:placetype":"venue"
},
  "geometry": {"coordinates":[3.9555130005,50.4578781128],"type":"Point"}
}