{
  "type": "Feature",
  "properties": {
    "iso:country":"BE",
    "sg:address":"Place Laixheau 35",
    "sg:city":"Herstal",
    "sg:classifiers":[
        {
            "category":"Health Services",
            "subcategory":"Dentist",
            "type":"Services"
        }
    ],
    "sg:phone":"+32 4 248 36 96",
    "sg:postcode":"4040",
    "sg:province":"Li\u00e8ge",
    "wof:name":"Honhon Daniel",
    "wof:placetype":"venue"
},
  "geometry": {"coordinates":[5.6259012222,50.6679611206],"type":"Point"}
}