{
  "type": "Feature",
  "properties": {
    "iso:country":"BE",
    "sg:address":"Chauss\u00c9e De Ten-brielen 1",
    "sg:city":"Komen-waasten/comines-warneton",
    "sg:orig_category":"Banques and organismes de cr\u00e9dit",
    "sg:phone":"+32 56 55 79 26",
    "sg:postcode":"7780",
    "sg:province":"Hainaut",
    "wof:name":"Centea",
    "wof:placetype":"venue"
},
  "geometry": {"coordinates":[2.9990000725,50.7806243896],"type":"Point"}
}