{
  "type": "Feature",
  "properties": {
    "addr:full":"Rue Du Moulin 19 Habay (houdemont) Luxembourg 6724",
    "addr:housenumber":"19",
    "addr:postcode":"6724",
    "addr:street":"Rue Du Moulin",
    "iso:country":"BE",
    "sg:address":"Rue Du Moulin 19",
    "sg:city":"Habay (houdemont)",
    "sg:classifiers":[
        {
            "category":"Building & Trades",
            "subcategory":"Landscaping Services",
            "type":"Services"
        }
    ],
    "sg:phone":"+32 63 41 24 87",
    "sg:postcode":"6724",
    "sg:province":"Luxembourg",
    "sg:tags":[
        "gardening",
        "garden",
        "maintenance"
    ],
    "wof:name":"Grandjean P",
    "wof:placetype":"venue"
},
  "geometry": {"coordinates":[5.5597100258,49.7180557251],"type":"Point"}
}