{
  "type": "Feature",
  "properties": {
    "iso:country":"BE",
    "sg:address":"Kaulillerweg 4 Box 1",
    "sg:city":"Bocholt",
    "sg:classifiers":[
        {
            "category":"Shopping",
            "subcategory":"Clothing, Apparel, & Fashions",
            "type":"Retail Goods"
        }
    ],
    "sg:phone":"+32 89 46 30 22",
    "sg:postcode":"3950",
    "sg:province":"Limburg",
    "sg:tags":[
        "boutique"
    ],
    "wof:name":"G - Fashion",
    "wof:placetype":"venue"
},
  "geometry": {"coordinates":[5.5786581039,51.1731681824],"type":"Point"}
}