{
  "type": "Feature",
  "properties": {
    "addr:full":"Koning-albertlaan 103 Lochristi Oost-Vlaanderen 9080",
    "addr:housenumber":"103",
    "addr:postcode":"9080",
    "iso:country":"BE",
    "sg:address":"Koning-albertlaan 103",
    "sg:city":"Lochristi",
    "sg:orig_category":"Installatie van houten of kunststof schrijnwerk",
    "sg:phone":"+32 9 355 95 85",
    "sg:postcode":"9080",
    "sg:province":"Oost-Vlaanderen",
    "wof:name":"Jozef Bracke",
    "wof:placetype":"venue"
},
  "geometry": {"coordinates":[3.8259880543,51.1041297913],"type":"Point"}
}