{
  "type": "Feature",
  "properties": {
    "iso:country":"BE",
    "sg:address":"Rue De La Braie 24",
    "sg:city":"Bruxelles",
    "sg:classifiers":[
        {
            "category":"Education",
            "subcategory":"School",
            "type":"Public Place"
        }
    ],
    "sg:phone":"+32 2 502 05 04",
    "sg:postcode":"1000",
    "sg:province":"Bruxelles-Capitale",
    "sg:tags":[
        "boarding"
    ],
    "wof:name":"Kunsthumaniora Muziek En Woord",
    "wof:placetype":"venue"
},
  "geometry": {"coordinates":[4.3451738358,50.8499107361],"type":"Point"}
}