{
  "type": "Feature",
  "properties": {
    "iso:country":"BE",
    "sg:address":"Chemin De La Valli\u00e8re 43",
    "sg:city":"Mons",
    "sg:classifiers":[
        {
            "category":"Insurance",
            "subcategory":"Insurance Agent",
            "type":"Services"
        }
    ],
    "sg:phone":"+32 65 36 36 40",
    "sg:postcode":"7000",
    "sg:province":"Hainaut",
    "sg:tags":[
        "broker"
    ],
    "wof:name":"Pirot Pierre Sprl",
    "wof:placetype":"venue"
},
  "geometry": {"coordinates":[3.9490129948,50.4419708252],"type":"Point"}
}