{
  "type": "Feature",
  "properties": {
    "addr:full":"Rue De Grimohaye 59 A Limal Brabant Wallon 1300",
    "addr:housenumber":"59 a",
    "addr:postcode":"1300",
    "addr:street":"Rue De Grimohaye;Wallon",
    "iso:country":"BE",
    "sg:address":"Rue De Grimohaye 59 A",
    "sg:city":"Limal",
    "sg:orig_category":"Tuinen",
    "sg:phone":"+32 10 40 20 07",
    "sg:postcode":"1300",
    "sg:province":"Brabant Wallon",
    "wof:name":"L'eau Et Le Jardin",
    "wof:placetype":"venue"
},
  "geometry": {"coordinates":[4.5544729233,50.6950759888],"type":"Point"}
}