{
  "type": "Feature",
  "properties": {
    "addr:full":"Chauss\u00c9e De Louvain 65 Wavre Brabant Wallon 1300",
    "addr:housenumber":"65;1300",
    "addr:street":"Chausse\u0301E De Louvain",
    "iso:country":"BE",
    "sg:address":"Chauss\u00c9e De Louvain 65",
    "sg:city":"Wavre",
    "sg:orig_category":"Epiceries",
    "sg:phone":"+32 10 24 21 22",
    "sg:postcode":"1300",
    "sg:province":"Brabant Wallon",
    "wof:name":"Traiteur La Bottega",
    "wof:placetype":"venue"
},
  "geometry": {"coordinates":[4.6150608063,50.7144012451],"type":"Point"}
}