{
  "type": "Feature",
  "properties": {
    "iso:country":"BE",
    "sg:address":"Heirbaan 25",
    "sg:city":"Grobbendonk",
    "sg:orig_category":"Radioproductie and uitzendingen",
    "sg:phone":"+32 14 51 66 51",
    "sg:postcode":"2280",
    "sg:province":"Antwerpen",
    "wof:name":"Radio Montana",
    "wof:placetype":"venue"
},
  "geometry": {"coordinates":[4.7340278625,51.20262146],"type":"Point"}
}