{
  "type": "Feature",
  "properties": {
    "iso:country":"BE",
    "sg:address":"Blookstraat 43",
    "sg:city":"Hasselt (kuringen)",
    "sg:orig_category":"Non-Classified Establishments",
    "sg:phone":"+32 11 23 66 66",
    "sg:postcode":"3511",
    "sg:province":"Limburg",
    "wof:name":"K-teg Bvba",
    "wof:placetype":"venue"
},
  "geometry": {"coordinates":[5.3034238815,50.9432487488],"type":"Point"}
}