{
  "type": "Feature",
  "properties": {
    "iso:country":"BE",
    "sg:address":"Weimeerslaan 4",
    "sg:city":"Kortrijk",
    "sg:classifiers":[
        {
            "category":"Insurance",
            "subcategory":"Life Insurance",
            "type":"Services"
        }
    ],
    "sg:phone":"+32 56 21 82 19",
    "sg:postcode":"8510",
    "sg:province":"West-Vlaanderen",
    "sg:tags":[
        "assurance"
    ],
    "wof:name":"H. Dekeyzer",
    "wof:placetype":"venue"
},
  "geometry": {"coordinates":[3.2633709908,50.7634735107],"type":"Point"}
}