{
  "type": "Feature",
  "properties": {
    "iso:country":"BE",
    "sg:address":"Nieuwelaan 117",
    "sg:city":"Grimbergen (strombeek-bever)",
    "sg:classifiers":[
        {
            "category":"Manufacturing",
            "subcategory":"Metals",
            "type":"Manufacturing & Wholesale Goods"
        }
    ],
    "sg:phone":"+32 2 267 58 09",
    "sg:postcode":"1853",
    "sg:province":"Vlaams-Brabant",
    "sg:tags":[
        "treatment",
        "surface"
    ],
    "wof:name":"Scheffers Chemic Nv",
    "wof:placetype":"venue"
},
  "geometry": {"coordinates":[4.3486089706,50.9036369324],"type":"Point"}
}