{
  "type": "Feature",
  "properties": {
    "iso:country":"BE",
    "sg:address":"Peraltastraat 61",
    "sg:city":"Brugge",
    "sg:classifiers":[
        {
            "category":"Professional",
            "subcategory":"Accounting & Tax Preparation",
            "type":"Services"
        }
    ],
    "sg:phone":"+32 50 31 10 92",
    "sg:postcode":"8000",
    "sg:province":"West-Vlaanderen",
    "sg:tags":[
        "underwater",
        "work"
    ],
    "wof:name":"Deco Duikwerken Nv",
    "wof:placetype":"venue"
},
  "geometry": {"coordinates":[3.2138810158,51.2420806885],"type":"Point"}
}