{
  "type": "Feature",
  "properties": {
    "addr:full":"Avenue Alexander Fleming 3 Fleurus Hainaut 6220",
    "addr:housenumber":"3",
    "addr:postcode":"6220",
    "addr:street":"Avenue Alexander Fleming",
    "iso:country":"BE",
    "sg:address":"Avenue Alexander Fleming 3",
    "sg:city":"Fleurus",
    "sg:orig_category":"Boekbinderijen and afwerking Drukkerijen and copyshops",
    "sg:phone":"+32 71 34 12 88",
    "sg:postcode":"6220",
    "sg:province":"Hainaut",
    "wof:name":"Graphing Grafossart",
    "wof:placetype":"venue"
},
  "geometry": {"coordinates":[4.4881100655,50.4734458923],"type":"Point"}
}