{
  "type": "Feature",
  "properties": {
    "iso:country":"BE",
    "sg:address":"Noordlaan 2ba",
    "sg:city":"Genk",
    "sg:orig_category":"Decoratieve kunst and kunstbenodigdheden Drukkerijen and copyshops",
    "sg:phone":"+32 89 35 61 58",
    "sg:postcode":"3600",
    "sg:province":"Limburg",
    "wof:name":"D.t.a.",
    "wof:placetype":"venue"
},
  "geometry": {"coordinates":[5.4869241714,50.9785385132],"type":"Point"}
}