{
  "type": "Feature",
  "properties": {
    "addr:full":"Leopoldlaan 31 Middelkerke West-Vlaanderen 8430",
    "addr:housenumber":"31",
    "addr:postcode":"8430",
    "addr:street":"Leopoldlaan",
    "iso:country":"BE",
    "sg:address":"Leopoldlaan 31",
    "sg:city":"Middelkerke",
    "sg:classifiers":[
        {
            "category":"Shopping",
            "subcategory":"Clothing, Apparel, & Fashions",
            "type":"Retail Goods"
        }
    ],
    "sg:phone":"+32 59 31 35 78",
    "sg:postcode":"8430",
    "sg:province":"West-Vlaanderen",
    "sg:tags":[
        "lady",
        "clothing",
        "-"
    ],
    "wof:name":"Newport",
    "wof:placetype":"venue"
},
  "geometry": {"coordinates":[2.815666914,51.1877250671],"type":"Point"}
}