{
  "type": "Feature",
  "properties": {
    "iso:country":"BE",
    "sg:address":"Otterstraat 151",
    "sg:city":"Turnhout",
    "sg:classifiers":[
        {
            "category":"Sports & Exercise",
            "subcategory":"Ice Rink",
            "type":"Entertainment"
        }
    ],
    "sg:phone":"+32 14 41 97 62",
    "sg:postcode":"2300",
    "sg:province":"Antwerpen",
    "sg:tags":[
        "skating"
    ],
    "wof:name":"Kempisch Ijsstadion Nv",
    "wof:placetype":"venue"
},
  "geometry": {"coordinates":[4.9567317963,51.3215103149],"type":"Point"}
}