{
  "type": "Feature",
  "properties": {
    "addr:full":"Chauss\u00c9e De Louvain 709 Lasne Brabant Wallon 1380",
    "addr:housenumber":"709",
    "addr:postcode":"1380",
    "addr:street":"Chausse\u0301E De Louvain",
    "iso:country":"BE",
    "sg:address":"Chauss\u00c9e De Louvain 709",
    "sg:city":"Lasne",
    "sg:orig_category":"Catering and organisatie van feesten Fast food and meeneem restaurants Restaurants",
    "sg:phone":"+32 2 653 64 97",
    "sg:postcode":"1380",
    "sg:province":"Brabant Wallon",
    "wof:name":"Auberge D'ohain",
    "wof:placetype":"venue"
},
  "geometry": {"coordinates":[4.483235836,50.6850166321],"type":"Point"}
}