{
  "type": "Feature",
  "properties": {
    "iso:country":"BE",
    "sg:address":"Joseph Cardijnstraat 28",
    "sg:city":"Erpe-mere",
    "sg:orig_category":"Installatie van houten of kunststof schrijnwerk Installatie van metalen schrijnwerk",
    "sg:phone":"+32 53 80 77 22",
    "sg:postcode":"9420",
    "sg:province":"Oost-Vlaanderen",
    "wof:name":"De Saedeleer",
    "wof:placetype":"venue"
},
  "geometry": {"coordinates":[3.958714962,50.934337616],"type":"Point"}
}