{
  "type": "Feature",
  "properties": {
    "iso:country":"BE",
    "sg:address":"Zeelaan 248",
    "sg:city":"Koksijde",
    "sg:orig_category":"Boucheries",
    "sg:phone":"+32 58 51 10 14",
    "sg:postcode":"8670",
    "sg:province":"West-Vlaanderen",
    "wof:name":"Erik Aneca",
    "wof:placetype":"venue"
},
  "geometry": {"coordinates":[2.6361761093,51.1181602478],"type":"Point"}
}