{
  "type": "Feature",
  "properties": {
    "iso:country":"BE",
    "sg:address":"Chauss\u00e9e De Jodoigne 33",
    "sg:city":"Grez-doiceau",
    "sg:classifiers":[
        {
            "category":"Health Services",
            "subcategory":"Dentist",
            "type":"Services"
        }
    ],
    "sg:phone":"+32 10 84 50 19",
    "sg:postcode":"1390",
    "sg:province":"Brabant Wallon",
    "wof:name":"Sterckx J C",
    "wof:placetype":"venue"
},
  "geometry": {"coordinates":[4.700067997,50.7378196716],"type":"Point"}
}