{
  "type": "Feature",
  "properties": {
    "iso:country":"BE",
    "sg:address":"Kleinaartstraat 7",
    "sg:city":"Wellen",
    "sg:classifiers":[
        {
            "category":"Arena",
            "subcategory":"Sports Club",
            "type":"Entertainment"
        }
    ],
    "sg:phone":"+32 12 74 40 00",
    "sg:postcode":"3832",
    "sg:province":"Limburg",
    "sg:tags":[
        "de"
    ],
    "wof:name":"M.c. Free Wellen",
    "wof:placetype":"venue"
},
  "geometry": {"coordinates":[5.3032231331,50.8431739807],"type":"Point"}
}