{
  "type": "Feature",
  "properties": {
    "iso:country":"BE",
    "sg:address":"Leestdorp 22",
    "sg:city":"Mechelen",
    "sg:classifiers":[
        {
            "category":"Insurance",
            "subcategory":"Life Insurance",
            "type":"Services"
        }
    ],
    "sg:phone":"+32 15 27 78 73",
    "sg:postcode":"2811",
    "sg:province":"Antwerpen",
    "sg:tags":[
        "assurance"
    ],
    "wof:name":"De Smet Els & Jos",
    "wof:placetype":"venue"
},
  "geometry": {"coordinates":[4.4183988571,51.0327301025],"type":"Point"}
}