{
  "type": "Feature",
  "properties": {
    "iso:country":"BE",
    "sg:address":"Chemin Vert 13",
    "sg:city":"Estaimpuis (n\u00e9chin)",
    "sg:classifiers":[
        {
            "category":"Health Services",
            "subcategory":"Health Practitioner",
            "type":"Services"
        }
    ],
    "sg:phone":"+32 69 35 37 55",
    "sg:postcode":"7730",
    "sg:province":"Hainaut",
    "sg:tags":[
        "physiotherapist"
    ],
    "wof:name":"Payen J-l",
    "wof:placetype":"venue"
},
  "geometry": {"coordinates":[3.252876997,50.6718254089],"type":"Point"}
}