{
  "type": "Feature",
  "properties": {
    "iso:country":"BE",
    "sg:address":"Groeshoeve 20",
    "sg:city":"Nijlen (kessel)",
    "sg:classifiers":[
        {
            "category":"Health Services",
            "subcategory":"Dentist",
            "type":"Services"
        }
    ],
    "sg:phone":"+32 3 488 28 33",
    "sg:postcode":"2560",
    "sg:province":"Antwerpen",
    "wof:name":"Van Cant C Mevr",
    "wof:placetype":"venue"
},
  "geometry": {"coordinates":[4.6258478165,51.1531295776],"type":"Point"}
}