{
  "type": "Feature",
  "properties": {
    "iso:country":"BE",
    "sg:address":"Herderstraat 6",
    "sg:city":"Temse",
    "sg:classifiers":[
        {
            "category":"Education",
            "subcategory":"Music School",
            "type":"Public Place"
        }
    ],
    "sg:phone":"+32 3 771 58 43",
    "sg:postcode":"9140",
    "sg:province":"Oost-Vlaanderen",
    "sg:tags":[
        "-",
        "teacher",
        "private"
    ],
    "wof:name":"Van Landeghem",
    "wof:placetype":"venue"
},
  "geometry": {"coordinates":[4.196709156,51.1291351318],"type":"Point"}
}