{
  "type": "Feature",
  "properties": {
    "addr:full":"Rue Du Coq 58 Anderlues Hainaut 6150",
    "addr:housenumber":"58",
    "addr:postcode":"6150",
    "addr:street":"Rue Du Coq",
    "iso:country":"BE",
    "sg:address":"Rue Du Coq 58",
    "sg:city":"Anderlues",
    "sg:classifiers":[
        {
            "category":"Building & Trades",
            "subcategory":"Electrical",
            "type":"Services"
        }
    ],
    "sg:phone":"+32 71 52 66 13",
    "sg:postcode":"6150",
    "sg:province":"Hainaut",
    "sg:tags":[
        "electric",
        "-",
        "housewiring",
        "contractor"
    ],
    "wof:name":"Joseph A",
    "wof:placetype":"venue"
},
  "geometry": {"coordinates":[4.2799701691,50.4124679565],"type":"Point"}
}