{
  "type": "Feature",
  "properties": {
    "addr:full":"Olieberg 43 Zwevegem 8552",
    "addr:housenumber":"43",
    "addr:postcode":"8552",
    "addr:street":"Olieberg",
    "iso:country":"BE",
    "sg:address":"Olieberg 43",
    "sg:city":"Zwevegem",
    "sg:classifiers":[
        {
            "category":"Arena",
            "subcategory":"Sports Club",
            "type":"Entertainment"
        }
    ],
    "sg:phone":"+32 56 64 68 27",
    "sg:postcode":"8552",
    "sg:tags":[
        "de"
    ],
    "wof:name":"De Moense Gordel",
    "wof:placetype":"venue"
},
  "geometry": {"coordinates":[3.393846035,50.7724380493],"type":"Point"}
}