{
  "type": "Feature",
  "properties": {
    "addr:full":"Tieltsesteenweg 30 Box 2 Eeklo Oost-Vlaanderen 9900",
    "addr:housenumber":"30;2",
    "addr:postcode":"9900",
    "addr:street":"Tieltsesteenweg;Box",
    "iso:country":"BE",
    "sg:address":"Tieltsesteenweg 30 Box 2",
    "sg:city":"Eeklo",
    "sg:classifiers":[
        {
            "category":"Social Services",
            "type":"Services"
        }
    ],
    "sg:phone":"+32 9 377 77 74",
    "sg:postcode":"9900",
    "sg:province":"Oost-Vlaanderen",
    "wof:name":"Kringloopcentrum",
    "wof:placetype":"venue"
},
  "geometry": {"coordinates":[3.5560150146,51.1844902039],"type":"Point"}
}