{
  "type": "Feature",
  "properties": {
    "addr:full":"Place Du March\u00c9 34 Saint-hubert Luxembourg 6870",
    "addr:housenumber":"34",
    "addr:postcode":"6870",
    "addr:street":"Place Du Marche\u0301",
    "iso:country":"BE",
    "sg:address":"Place Du March\u00c9 34",
    "sg:city":"Saint-hubert",
    "sg:orig_category":"Opticiens. Articles m\u00e9dicaux and orthop\u00e9diques",
    "sg:phone":"+32 61 61 25 69",
    "sg:postcode":"6870",
    "sg:province":"Luxembourg",
    "wof:name":"Optique Sonnet",
    "wof:placetype":"venue"
},
  "geometry": {"coordinates":[5.3735599518,50.0254211426],"type":"Point"}
}