{
  "type": "Feature",
  "properties": {
    "iso:country":"BE",
    "sg:address":"Elzenlaan 30",
    "sg:city":"Diepenbeek",
    "sg:orig_category":"Mat\u00e9riaux de construction Meubles D\u00e9taillants, Am\u00e9nagement de B\u00e2timents et de Cuisines",
    "sg:phone":"+32 11 32 36 73",
    "sg:postcode":"3590",
    "sg:province":"Limburg",
    "wof:name":"Emiel Reekmans",
    "wof:placetype":"venue"
},
  "geometry": {"coordinates":[5.4344220161,50.9340858459],"type":"Point"}
}