{
  "type": "Feature",
  "properties": {
    "iso:country":"BE",
    "sg:address":"Kapelstraat 47",
    "sg:city":"Temse",
    "sg:orig_category":"Gespecialiseerde residenti\u00eble bouw",
    "sg:phone":"+32 3 774 31 11",
    "sg:postcode":"9140",
    "sg:province":"Oost-Vlaanderen",
    "wof:name":"Johan Vandenbussche",
    "wof:placetype":"venue"
},
  "geometry": {"coordinates":[4.2492799759,51.1289596558],"type":"Point"}
}