{
  "type": "Feature",
  "properties": {
    "iso:country":"BE",
    "sg:address":"Rue Derri\u00c8re La Gare 12",
    "sg:city":"Malmedy",
    "sg:orig_category":"Technisch and beroeps secundair onderwijs",
    "sg:phone":"+32 80 33 01 83",
    "sg:postcode":"4960",
    "sg:province":"Li\u00e8ge",
    "wof:name":"Institut Notre-dame",
    "wof:placetype":"venue"
},
  "geometry": {"coordinates":[6.0325698853,50.4240684509],"type":"Point"}
}