{
  "type": "Feature",
  "properties": {
    "iso:country":"BE",
    "sg:address":"Avenue Marius Meur\u00c9e 83",
    "sg:city":"Charleroi",
    "sg:orig_category":"Autoverhuur",
    "sg:phone":"+32 71 36 62 59",
    "sg:postcode":"6001",
    "sg:province":"Hainaut",
    "wof:name":"Avis",
    "wof:placetype":"venue"
},
  "geometry": {"coordinates":[4.4451069832,50.4019165039],"type":"Point"}
}