{
  "type": "Feature",
  "properties": {
    "iso:country":"BE",
    "sg:address":"Rupellaan 1",
    "sg:city":"Willebroek",
    "sg:classifiers":[
        {
            "category":"Social Services",
            "type":"Services"
        }
    ],
    "sg:phone":"+32 3 866 10 68",
    "sg:postcode":"2830",
    "sg:province":"Antwerpen",
    "sg:tags":[
        "handicapped",
        "-"
    ],
    "wof:name":"I.e. Zwembad",
    "wof:placetype":"venue"
},
  "geometry": {"coordinates":[4.3439898491,51.0608100891],"type":"Point"}
}