{
  "type": "Feature",
  "properties": {
    "addr:full":"Rue Des Pres 5 Hamois Namur 5364",
    "addr:housenumber":"5",
    "addr:postcode":"5364",
    "addr:street":"Rue Des Pres",
    "iso:country":"BE",
    "sg:address":"Rue Des Pres 5",
    "sg:city":"Hamois",
    "sg:orig_category":"Traitements param\u00e9dicaux",
    "sg:phone":"+32 83 61 19 97",
    "sg:postcode":"5364",
    "sg:province":"Namur",
    "wof:name":"M.m. Thirion",
    "wof:placetype":"venue"
},
  "geometry": {"coordinates":[5.1273488998,50.3706359863],"type":"Point"}
}