{
  "type": "Feature",
  "properties": {
    "addr:full":"Winterslagstraat 41 Genk Limburg 3600",
    "addr:housenumber":"41",
    "addr:postcode":"3600",
    "addr:street":"Winterslagstraat",
    "iso:country":"BE",
    "sg:address":"Winterslagstraat 41",
    "sg:city":"Genk",
    "sg:classifiers":[
        {
            "category":"Bars & Pubs",
            "type":"Food & Drink"
        }
    ],
    "sg:phone":"+32 89 30 44 69",
    "sg:postcode":"3600",
    "sg:province":"Limburg",
    "wof:name":"Amadeus",
    "wof:placetype":"venue"
},
  "geometry": {"coordinates":[5.4986081123,50.965637207],"type":"Point"}
}