{
  "type": "Feature",
  "properties": {
    "addr:full":"Rue Claus 22 Jurbise Hainaut 7050",
    "addr:housenumber":"22",
    "addr:postcode":"7050",
    "addr:street":"Rue Claus",
    "iso:country":"BE",
    "sg:address":"Rue Claus 22",
    "sg:city":"Jurbise",
    "sg:orig_category":"Eleveurs de bovins",
    "sg:phone":"+32 65 22 98 15",
    "sg:postcode":"7050",
    "sg:province":"Hainaut",
    "wof:name":"Francis Massart",
    "wof:placetype":"venue"
},
  "geometry": {"coordinates":[3.9299199581,50.5175895691],"type":"Point"}
}