{
  "type": "Feature",
  "properties": {
    "iso:country":"BE",
    "sg:address":"Busstraat 16",
    "sg:city":"Lochristi",
    "sg:orig_category":"Eleveurs and marchands de porcs. Eleveurs de bovins",
    "sg:phone":"+32 9 355 64 18",
    "sg:postcode":"9080",
    "sg:province":"Oost-Vlaanderen",
    "wof:name":"Astere Van Hecke",
    "wof:placetype":"venue"
},
  "geometry": {"coordinates":[3.8302600384,51.1338653564],"type":"Point"}
}