{
  "type": "Feature",
  "properties": {
    "iso:country":"BE",
    "sg:address":"Crilsplein 8",
    "sg:city":"Westerlo (tongerlo)",
    "sg:classifiers":[
        {
            "category":"Bakery",
            "type":"Food & Drink"
        }
    ],
    "sg:phone":"+32 14 23 04 45",
    "sg:postcode":"2260",
    "sg:province":"Antwerpen",
    "sg:tags":[
        "confectioner",
        "baker"
    ],
    "wof:name":"Broodkruimel (de)",
    "wof:placetype":"venue"
},
  "geometry": {"coordinates":[4.9009170532,51.1263847351],"type":"Point"}
}