{
  "type": "Feature",
  "properties": {
    "iso:country":"BE",
    "sg:address":"Wespelaarsebaan 42",
    "sg:city":"Boortmeerbeek",
    "sg:classifiers":[
        {
            "category":"Shopping",
            "subcategory":"Jewelry",
            "type":"Retail Goods"
        }
    ],
    "sg:phone":"+32 15 52 90 85",
    "sg:postcode":"3190",
    "sg:province":"Vlaams-Brabant",
    "sg:tags":[
        "jeweller",
        "-"
    ],
    "wof:name":"Jacobs K",
    "wof:placetype":"venue"
},
  "geometry": {"coordinates":[4.5763912201,50.979221344],"type":"Point"}
}