{
  "type": "Feature",
  "properties": {
    "iso:country":"BE",
    "sg:address":"Avenue Du Ch\u00e2teau 12",
    "sg:city":"Bruxelles (koekelberg)",
    "sg:classifiers":[
        {
            "category":"Bakery",
            "type":"Food & Drink"
        }
    ],
    "sg:phone":"+32 2 411 08 98",
    "sg:postcode":"1081",
    "sg:province":"Bruxelles-Capitale",
    "sg:tags":[
        "confectioner",
        "baker"
    ],
    "wof:name":"De Cyper",
    "wof:placetype":"venue"
},
  "geometry": {"coordinates":[4.3147311211,50.8625183105],"type":"Point"}
}