{
  "type": "Feature",
  "properties": {
    "addr:full":"Berlaarsesteenweg 5 Lier Antwerpen 2500",
    "addr:housenumber":"5",
    "addr:postcode":"2500",
    "addr:street":"Berlaarsesteenweg",
    "iso:country":"BE",
    "sg:address":"Berlaarsesteenweg 5",
    "sg:city":"Lier",
    "sg:classifiers":[
        {
            "category":"Insurance",
            "subcategory":"Insurance Agent",
            "type":"Services"
        }
    ],
    "sg:phone":"+32 3 489 12 46",
    "sg:postcode":"2500",
    "sg:province":"Antwerpen",
    "sg:tags":[
        "broker"
    ],
    "wof:name":"Zakenkantoor Anita",
    "wof:placetype":"venue"
},
  "geometry": {"coordinates":[4.5836119652,51.1284141541],"type":"Point"}
}