{
  "type": "Feature",
  "properties": {
    "iso:country":"BE",
    "sg:address":"Peperstraat 29",
    "sg:city":"Kampenhout (nederokkerzeel)",
    "sg:classifiers":[
        {
            "category":"Building & Trades",
            "subcategory":"Landscaping Services",
            "type":"Services"
        }
    ],
    "sg:phone":"+32 16 65 04 29",
    "sg:postcode":"1910",
    "sg:province":"Vlaams-Brabant",
    "sg:tags":[
        "gardening",
        "garden",
        "maintenance"
    ],
    "wof:name":"Van Gucht S",
    "wof:placetype":"venue"
},
  "geometry": {"coordinates":[4.5652570724,50.9226989746],"type":"Point"}
}