{
  "type": "Feature",
  "properties": {
    "addr:full":"Oude Dendermondsebaan 27 Asse Vlaams-Brabant 1730",
    "addr:housenumber":"27",
    "addr:postcode":"1730",
    "addr:street":"Oude Dendermondsebaan",
    "iso:country":"BE",
    "sg:address":"Oude Dendermondsebaan 27",
    "sg:city":"Asse",
    "sg:classifiers":[
        {
            "category":"Personal",
            "subcategory":"Beauty Salon",
            "type":"Services"
        }
    ],
    "sg:phone":"+32 2 452 98 75",
    "sg:postcode":"1730",
    "sg:province":"Vlaams-Brabant",
    "sg:tags":[
        "lady",
        "-",
        "hairdressing"
    ],
    "wof:name":"Ingrid",
    "wof:placetype":"venue"
},
  "geometry": {"coordinates":[4.1864089966,50.9227027893],"type":"Point"}
}