{
  "type": "Feature",
  "properties": {
    "iso:country":"BE",
    "sg:address":"Zwarte-beeklaan 14",
    "sg:city":"Kapellen",
    "sg:orig_category":"Elektrische installaties voor woningen",
    "sg:phone":"+32 3 665 12 64",
    "sg:postcode":"2950",
    "sg:province":"Antwerpen",
    "wof:name":"Electro R De Coninck",
    "wof:placetype":"venue"
},
  "geometry": {"coordinates":[4.4416151047,51.3222618103],"type":"Point"}
}