{
  "type": "Feature",
  "properties": {
    "addr:full":"5 Avenue Ariane 1200 Brussels 5",
    "addr:housenumber":"5",
    "addr:postcode":"1200",
    "addr:street":"Avenue Ariane",
    "iso:country":"BE",
    "sg:address":"5",
    "sg:city":"Avenue Ariane 1200 Brussels",
    "sg:classifiers":[
        {
            "category":"Banks & Credit Unions",
            "subcategory":"Investment Brokerage",
            "type":"Services"
        }
    ],
    "sg:phone":"+32 2 776 91 11",
    "sg:postcode":"5",
    "sg:tags":[
        "-",
        "transport",
        "related"
    ],
    "wof:name":"Ups",
    "wof:placetype":"venue"
},
  "geometry": {"coordinates":[4.4323801994,50.8583946228],"type":"Point"}
}