{
  "type": "Feature",
  "properties": {
    "addr:full":"Elsense Steenweg 61 Elsene/ixelles Bruxelles-Capitale 1050",
    "addr:housenumber":"61",
    "addr:postcode":"1050",
    "addr:street":"Elsense Steenweg",
    "iso:country":"BE",
    "sg:address":"Elsense Steenweg 61",
    "sg:city":"Elsene/ixelles",
    "sg:orig_category":"Dameskledingzaken",
    "sg:phone":"+32 2 512 92 23",
    "sg:postcode":"1050",
    "sg:province":"Bruxelles-Capitale",
    "wof:name":"M&s Mode",
    "wof:placetype":"venue"
},
  "geometry": {"coordinates":[4.3627419472,50.8361968994],"type":"Point"}
}