{
  "type": "Feature",
  "properties": {
    "addr:full":"Sneppestraat 2 Kortemark West-Vlaanderen 8610",
    "addr:housenumber":"2",
    "addr:postcode":"8610",
    "addr:street":"Sneppestraat",
    "iso:country":"BE",
    "sg:address":"Sneppestraat 2",
    "sg:city":"Kortemark",
    "sg:classifiers":[
        {
            "category":"Utilities",
            "subcategory":"Telephone",
            "type":"Services"
        }
    ],
    "sg:phone":"+32 51 56 65 07",
    "sg:postcode":"8610",
    "sg:province":"West-Vlaanderen",
    "sg:tags":[
        "addressing",
        "mailing"
    ],
    "wof:name":"Direct-mail",
    "wof:placetype":"venue"
},
  "geometry": {"coordinates":[3.0343821049,51.029510498],"type":"Point"}
}