{
  "type": "Feature",
  "properties": {
    "addr:full":"Westkerksestraat 143 Oudenburg (westkerke) West-Vlaanderen 8460",
    "addr:housenumber":"143",
    "addr:postcode":"8460",
    "addr:street":"Westkerksestraat",
    "iso:country":"BE",
    "sg:address":"Westkerksestraat 143",
    "sg:city":"Oudenburg (westkerke)",
    "sg:classifiers":[
        {
            "category":"Insurance",
            "subcategory":"Insurance Agent",
            "type":"Services"
        }
    ],
    "sg:phone":"+32 59 26 68 99",
    "sg:postcode":"8460",
    "sg:province":"West-Vlaanderen",
    "sg:tags":[
        "broker"
    ],
    "wof:name":"Lesaffre-denduyver G",
    "wof:placetype":"venue"
},
  "geometry": {"coordinates":[3.0077080727,51.1757125854],"type":"Point"}
}