{
  "type": "Feature",
  "properties": {
    "iso:country":"BE",
    "sg:address":"Wervikstraat 17bb",
    "sg:city":"Wervik",
    "sg:orig_category":"Schoonheidssalons",
    "sg:phone":"+32 56 53 21 00",
    "sg:postcode":"8940",
    "sg:province":"West-Vlaanderen",
    "wof:name":"Anne-marie Ruysschaert",
    "wof:placetype":"venue"
},
  "geometry": {"coordinates":[3.0721890926,50.8090324402],"type":"Point"}
}