{
  "type": "Feature",
  "properties": {
    "iso:country":"BE",
    "sg:address":"Clos De B\u00e9rine 55",
    "sg:city":"Waterloo",
    "sg:classifiers":[
        {
            "category":"Professional",
            "subcategory":"Management & Consulting",
            "type":"Services"
        }
    ],
    "sg:phone":"+32 2 384 40 30",
    "sg:postcode":"1410",
    "sg:province":"Brabant Wallon",
    "sg:tags":[
        "-",
        "processing",
        "data",
        "consultant"
    ],
    "wof:name":"J & C Consulting",
    "wof:placetype":"venue"
},
  "geometry": {"coordinates":[4.4030909538,50.6913833618],"type":"Point"}
}