{
  "type": "Feature",
  "properties": {
    "iso:country":"BE",
    "sg:address":"Rue D'horrues 112",
    "sg:city":"Braine-le-comte",
    "sg:orig_category":"Rev\u00eatements pour sols and murs. Peinture",
    "sg:phone":"+32 67 56 05 94",
    "sg:postcode":"7090",
    "sg:province":"Hainaut",
    "wof:name":"Jean Heugens",
    "wof:placetype":"venue"
},
  "geometry": {"coordinates":[4.0905909538,50.6249694824],"type":"Point"}
}