{
  "type": "Feature",
  "properties": {
    "iso:country":"BE",
    "sg:address":"Molenstraat 11",
    "sg:city":"Nieuwpoort",
    "sg:orig_category":"Brood, gebak and snoepgoed",
    "sg:phone":"+32 58 23 90 80",
    "sg:postcode":"8620",
    "sg:province":"West-Vlaanderen",
    "wof:name":"Johan Baert",
    "wof:placetype":"venue"
},
  "geometry": {"coordinates":[2.7608540058,51.109790802],"type":"Point"}
}