{
  "type": "Feature",
  "properties": {
    "addr:full":"Jodenstraat 45 Mechelen Antwerpen 2800",
    "addr:housenumber":"45",
    "addr:postcode":"2800",
    "addr:street":"Jodenstraat",
    "iso:country":"BE",
    "sg:address":"Jodenstraat 45",
    "sg:city":"Mechelen",
    "sg:classifiers":[
        {
            "category":"Health Services",
            "subcategory":"Doctor",
            "type":"Services"
        }
    ],
    "sg:phone":"+32 15 29 13 22",
    "sg:postcode":"2800",
    "sg:province":"Antwerpen",
    "sg:tags":[
        "psychotherapist",
        "psychoanalyst"
    ],
    "wof:name":"Fouquaert V",
    "wof:placetype":"venue"
},
  "geometry": {"coordinates":[4.4803538322,51.0327796936],"type":"Point"}
}