{
  "type": "Feature",
  "properties": {
    "iso:country":"BE",
    "sg:address":"Rue De La Cordonnerie 12",
    "sg:city":"Doornik",
    "sg:orig_category":"Baby- and kinderkleding Dameskledingzaken Herenkledingzaken",
    "sg:phone":"+32 69 21 26 09",
    "sg:postcode":"7500",
    "sg:province":"Hainaut",
    "wof:name":"Benetton",
    "wof:placetype":"venue"
},
  "geometry": {"coordinates":[3.3904058933,50.6065979004],"type":"Point"}
}