{
  "type": "Feature",
  "properties": {
    "iso:country":"BE",
    "sg:address":"Meensesteenweg 244",
    "sg:city":"Moorslede",
    "sg:orig_category":"Installation de menuiserie en bois and plastique",
    "sg:phone":"+32 56 50 68 98",
    "sg:postcode":"8890",
    "sg:province":"West-Vlaanderen",
    "wof:name":"D'hondt",
    "wof:placetype":"venue"
},
  "geometry": {"coordinates":[3.1123890877,50.8413772583],"type":"Point"}
}