{
  "type": "Feature",
  "properties": {
    "iso:country":"BE",
    "sg:address":"Rollegemstraat 173",
    "sg:city":"Ledegem",
    "sg:orig_category":"Epiceries. Journaux",
    "sg:phone":"+32 56 50 91 12",
    "sg:postcode":"8880",
    "sg:province":"West-Vlaanderen",
    "wof:name":"Huis Maria",
    "wof:placetype":"venue"
},
  "geometry": {"coordinates":[3.1346240044,50.8613052368],"type":"Point"}
}