{
  "type": "Feature",
  "properties": {
    "addr:full":"Nederenamestraat 30 Oudenaarde Oost-Vlaanderen 9700",
    "addr:housenumber":"30",
    "addr:postcode":"9700",
    "addr:street":"Nederenamestraat",
    "iso:country":"BE",
    "sg:address":"Nederenamestraat 30",
    "sg:city":"Oudenaarde",
    "sg:classifiers":[
        {
            "category":"Education",
            "subcategory":"School",
            "type":"Public Place"
        }
    ],
    "sg:phone":"+32 55 30 37 66",
    "sg:postcode":"9700",
    "sg:province":"Oost-Vlaanderen",
    "sg:tags":[
        "primary"
    ],
    "wof:name":"Vier Tuinen (de)",
    "wof:placetype":"venue"
},
  "geometry": {"coordinates":[3.6545000076,50.8692207336],"type":"Point"}
}