{
  "type": "Feature",
  "properties": {
    "addr:full":"Rue Saint-nicolas 119bc Namur Namur 5000",
    "addr:housenumber":"119bc",
    "addr:postcode":"5000",
    "addr:street":"Rue Saint-Nicolas",
    "iso:country":"BE",
    "sg:address":"Rue Saint-nicolas 119bc",
    "sg:city":"Namur",
    "sg:classifiers":[
        {
            "category":"Fast Food",
            "type":"Food & Drink"
        }
    ],
    "sg:phone":"+32 81 23 06 55",
    "sg:postcode":"5000",
    "sg:province":"Namur",
    "sg:tags":[
        "meeneem",
        "restaurant"
    ],
    "wof:name":"Friterie Michelle",
    "wof:placetype":"venue"
},
  "geometry": {"coordinates":[4.8735599518,50.46509552],"type":"Point"}
}