{
  "type": "Feature",
  "properties": {
    "addr:full":"Kerkstraat 18 Rotselaar Vlaams-Brabant 3111",
    "addr:housenumber":"18",
    "addr:postcode":"3111",
    "addr:street":"Kerkstraat",
    "iso:country":"BE",
    "sg:address":"Kerkstraat 18",
    "sg:city":"Rotselaar",
    "sg:orig_category":"Industri\u00eble wasserijen and droogkuis Kantoormateriaal Krantenwinkels Rookartikelen",
    "sg:phone":"+32 16 58 13 89",
    "sg:postcode":"3111",
    "sg:province":"Vlaams-Brabant",
    "wof:name":"Video-star",
    "wof:placetype":"venue"
},
  "geometry": {"coordinates":[4.7547087669,50.9484176636],"type":"Point"}
}