{
  "type": "Feature",
  "properties": {
    "iso:country":"BE",
    "sg:address":"Rue De Fiennes 17",
    "sg:city":"Anderlecht",
    "sg:orig_category":"Epiceries",
    "sg:phone":"+32 2 524 40 81",
    "sg:postcode":"1070",
    "sg:province":"Bruxelles-Capitale",
    "wof:name":"Night Shops Minhas",
    "wof:placetype":"venue"
},
  "geometry": {"coordinates":[4.3346199989,50.8391685486],"type":"Point"}
}