{
  "type": "Feature",
  "properties": {
    "addr:full":"Eltenbos 84 Lommel Limburg 3920",
    "addr:housenumber":"84",
    "addr:postcode":"3920",
    "addr:street":"Eltenbos",
    "iso:country":"BE",
    "sg:address":"Eltenbos 84",
    "sg:city":"Lommel",
    "sg:orig_category":"Enseignement maternel and primaire",
    "sg:phone":"+32 11 54 13 74",
    "sg:postcode":"3920",
    "sg:province":"Limburg",
    "wof:name":"Vrije Kleuterschool",
    "wof:placetype":"venue"
},
  "geometry": {"coordinates":[5.2980542183,51.2247390747],"type":"Point"}
}