{
  "type": "Feature",
  "properties": {
    "iso:country":"BE",
    "sg:address":"Mechelsesteenweg 7",
    "sg:city":"Leuven",
    "sg:orig_category":"Pharmaciens",
    "sg:phone":"+32 16 23 20 73",
    "sg:postcode":"3012",
    "sg:province":"Vlaams-Brabant",
    "wof:name":"Hubert Berckenbosch",
    "wof:placetype":"venue"
},
  "geometry": {"coordinates":[4.694852829,50.8899726868],"type":"Point"}
}