{
  "type": "Feature",
  "properties": {
    "iso:country":"BE",
    "sg:address":"Chauss\u00c9e De Nivelles 89 B",
    "sg:city":"Manage",
    "sg:orig_category":"Boissons. Boissons Gr",
    "sg:phone":"+32 64 54 19 78",
    "sg:postcode":"7170",
    "sg:province":"Hainaut",
    "wof:name":"Centrale De Boissons",
    "wof:placetype":"venue"
},
  "geometry": {"coordinates":[4.241768837,50.5101318359],"type":"Point"}
}