{
  "type": "Feature",
  "properties": {
    "addr:full":"Rue Bois D'ohey 265b Ohey Namur 5350",
    "addr:housenumber":"265b",
    "addr:postcode":"5350",
    "addr:street":"Rue Bois D'Ohey",
    "iso:country":"BE",
    "sg:address":"Rue Bois D'ohey 265b",
    "sg:city":"Ohey",
    "sg:classifiers":[
        {
            "category":"Parking",
            "subcategory":"Lot",
            "type":"Transportation"
        }
    ],
    "sg:phone":"+32 85 61 31 53",
    "sg:postcode":"5350",
    "sg:province":"Namur",
    "sg:tags":[
        "parking-places",
        "laying-out"
    ],
    "wof:name":"Cloet S",
    "wof:placetype":"venue"
},
  "geometry": {"coordinates":[5.0777330399,50.4311981201],"type":"Point"}
}