{
  "type": "Feature",
  "properties": {
    "iso:country":"BE",
    "sg:address":"Kerkstraat 6",
    "sg:city":"Sint-niklaas",
    "sg:orig_category":"Banken and kredietinstellingen",
    "sg:phone":"+32 3 772 30 22",
    "sg:postcode":"9111",
    "sg:province":"Oost-Vlaanderen",
    "wof:name":"Kbc",
    "wof:placetype":"venue"
},
  "geometry": {"coordinates":[4.0889000893,51.1495285034],"type":"Point"}
}