{
  "type": "Feature",
  "properties": {
    "iso:country":"BE",
    "sg:address":"Rue Sainte-walburge 76",
    "sg:city":"Li\u00c8ge",
    "sg:classifiers":[
        {
            "category":"Cinema",
            "subcategory":"Movie Rental",
            "type":"Entertainment"
        }
    ],
    "sg:phone":"+32 4 224 05 48",
    "sg:postcode":"4000",
    "sg:province":"Li\u00e8ge",
    "sg:tags":[
        "de",
        "cassette",
        "location",
        "vid\u00e9o",
        "audio"
    ],
    "wof:name":"Vid\u00c9o Vanina",
    "wof:placetype":"venue"
},
  "geometry": {"coordinates":[5.5715389252,50.6562004089],"type":"Point"}
}