{
  "type": "Feature",
  "properties": {
    "addr:full":"Route Nationale 5 5 Charleroi (gosselies) Hainaut 6041",
    "addr:housenumber":"5",
    "addr:postcode":"6041",
    "addr:street":"Route Nationale 5",
    "iso:country":"BE",
    "sg:address":"Route Nationale 5 5",
    "sg:city":"Charleroi (gosselies)",
    "sg:classifiers":[
        {
            "category":"Sports & Exercise",
            "subcategory":"Bowling",
            "type":"Entertainment"
        }
    ],
    "sg:phone":"+32 71 34 50 41",
    "sg:postcode":"6041",
    "sg:province":"Hainaut",
    "sg:tags":[
        "skittle",
        "alley"
    ],
    "wof:name":"Bowlings One",
    "wof:placetype":"venue"
},
  "geometry": {"coordinates":[4.4314317703,50.4685935974],"type":"Point"}
}