{
  "type": "Feature",
  "properties": {
    "iso:country":"BE",
    "sg:address":"Rue Haute 31",
    "sg:city":"Rebecq",
    "sg:orig_category":"Jardins botaniques, zoologiques, observatoires and r\u00e9serves naturelles",
    "sg:phone":"+32 67 63 82 26",
    "sg:postcode":"1430",
    "sg:province":"Brabant Wallon",
    "wof:name":"La Ferme Du Manoir",
    "wof:placetype":"venue"
},
  "geometry": {"coordinates":[4.1294999123,50.6474075317],"type":"Point"}
}