{
  "type": "Feature",
  "properties": {
    "addr:full":"Oude-maasstraat 73 Hasselt Limburg 3500",
    "addr:housenumber":"73",
    "addr:postcode":"3500",
    "addr:street":"Oude-Maasstraat",
    "iso:country":"BE",
    "sg:address":"Oude-maasstraat 73",
    "sg:city":"Hasselt",
    "sg:classifiers":[
        {
            "category":"Arena",
            "subcategory":"Sports Club",
            "type":"Entertainment"
        }
    ],
    "sg:phone":"+32 11 27 32 02",
    "sg:postcode":"3500",
    "sg:province":"Limburg",
    "sg:tags":[
        "de"
    ],
    "wof:name":"Terug Op Stap",
    "wof:placetype":"venue"
},
  "geometry": {"coordinates":[5.2949099541,50.9189186096],"type":"Point"}
}