{
  "type": "Feature",
  "properties": {
    "iso:country":"BE",
    "sg:address":"Ezelstraat 73",
    "sg:city":"Brugge",
    "sg:classifiers":[
        {
            "category":"Shopping",
            "subcategory":"Antiques",
            "type":"Retail Goods"
        }
    ],
    "sg:phone":"+32 50 33 60 62",
    "sg:postcode":"8000",
    "sg:province":"West-Vlaanderen",
    "wof:name":"Gallery Bossaert",
    "wof:placetype":"venue"
},
  "geometry": {"coordinates":[3.2178599834,51.2134056091],"type":"Point"}
}