{
  "type": "Feature",
  "properties": {
    "iso:country":"BE",
    "sg:address":"Place 24",
    "sg:city":"Mesen/messines",
    "sg:orig_category":"G\u00e9om\u00e8tres",
    "sg:phone":"+32 57 44 62 30",
    "sg:postcode":"8957",
    "sg:province":"West-Vlaanderen",
    "wof:name":"Daniel Liefooghe",
    "wof:placetype":"venue"
},
  "geometry": {"coordinates":[2.8977940083,50.765296936],"type":"Point"}
}