{
  "type": "Feature",
  "properties": {
    "iso:country":"BE",
    "sg:address":"Chauss\u00c9e De Waterloo 996",
    "sg:city":"Ukkel/uccle",
    "sg:orig_category":"Boucheries",
    "sg:phone":"+32 2 374 51 83",
    "sg:postcode":"1180",
    "sg:province":"Bruxelles-Capitale",
    "wof:name":"Vert Chasseur",
    "wof:placetype":"venue"
},
  "geometry": {"coordinates":[4.3743019104,50.8009910583],"type":"Point"}
}