{
  "type": "Feature",
  "properties": {
    "addr:full":"Ieperstraat 76 Tielt West-Vlaanderen 8700",
    "addr:housenumber":"76",
    "addr:postcode":"8700",
    "addr:street":"Ieperstraat",
    "iso:country":"BE",
    "sg:address":"Ieperstraat 76",
    "sg:city":"Tielt",
    "sg:classifiers":[
        {
            "category":"Health Services",
            "subcategory":"Dentist",
            "type":"Services"
        }
    ],
    "sg:phone":"+32 51 40 53 60",
    "sg:postcode":"8700",
    "sg:province":"West-Vlaanderen",
    "wof:name":"De Craene Luc",
    "wof:placetype":"venue"
},
  "geometry": {"coordinates":[3.3224699497,50.9980316162],"type":"Point"}
}