{
  "type": "Feature",
  "properties": {
    "iso:country":"BE",
    "sg:address":"Mottestraat 101",
    "sg:city":"Aarschot (rillaar)",
    "sg:classifiers":[
        {
            "category":"Building & Trades",
            "subcategory":"Pest Control",
            "type":"Services"
        }
    ],
    "sg:phone":"+32 16 50 32 92",
    "sg:postcode":"3202",
    "sg:province":"Vlaams-Brabant",
    "sg:tags":[
        "painting",
        "contractor"
    ],
    "wof:name":"Hendrickx Bert Bvba",
    "wof:placetype":"venue"
},
  "geometry": {"coordinates":[4.8742790222,50.9840431213],"type":"Point"}
}