{
  "type": "Feature",
  "properties": {
    "iso:country":"BE",
    "sg:address":"Rue De Sedent 62b31",
    "sg:city":"Namur",
    "sg:orig_category":"Dakwerken Woningbouw",
    "sg:phone":"+32 81 31 15 25",
    "sg:postcode":"5100",
    "sg:province":"Namur",
    "wof:name":"Boxus C",
    "wof:placetype":"venue"
},
  "geometry": {"coordinates":[4.8738741875,50.4432983398],"type":"Point"}
}