{
  "type": "Feature",
  "properties": {
    "addr:full":"Neerstalse Steenweg 56-70 Vorst/forest Bruxelles-Capitale 1190",
    "addr:housenumber":"56-70",
    "addr:postcode":"1190",
    "addr:street":"Neerstalse Steenweg;/ Forest",
    "iso:country":"BE",
    "sg:address":"Neerstalse Steenweg 56-70",
    "sg:city":"Vorst/forest",
    "sg:orig_category":"Slagers",
    "sg:phone":"+32 2 376 30 39",
    "sg:postcode":"1190",
    "sg:province":"Bruxelles-Capitale",
    "wof:name":"Renmans",
    "wof:placetype":"venue"
},
  "geometry": {"coordinates":[4.3162240982,50.8077087402],"type":"Point"}
}