{
  "type": "Feature",
  "properties": {
    "iso:country":"BE",
    "sg:address":"Zelestraat 41",
    "sg:city":"Lokeren",
    "sg:classifiers":[
        {
            "category":"Personal",
            "subcategory":"Beauty Salon",
            "type":"Services"
        }
    ],
    "sg:phone":"+32 9 348 26 46",
    "sg:postcode":"9160",
    "sg:province":"Oost-Vlaanderen",
    "sg:tags":[
        "lady",
        "-",
        "hairdressing"
    ],
    "wof:name":"Vercauteren G",
    "wof:placetype":"venue"
},
  "geometry": {"coordinates":[3.9980640411,51.1011199951],"type":"Point"}
}