{
  "type": "Feature",
  "properties": {
    "addr:full":"Diestersteenweg 265 Hasselt Limburg 3510",
    "addr:housenumber":"265",
    "addr:postcode":"3510",
    "addr:street":"Diestersteenweg",
    "iso:country":"BE",
    "sg:address":"Diestersteenweg 265",
    "sg:city":"Hasselt",
    "sg:orig_category":"M\u00e9decins and sp\u00e9cialistes",
    "sg:phone":"+32 11 25 18 78",
    "sg:postcode":"3510",
    "sg:province":"Limburg",
    "wof:name":"Jan Menten",
    "wof:placetype":"venue"
},
  "geometry": {"coordinates":[5.2359399796,50.947719574],"type":"Point"}
}