{
  "type": "Feature",
  "properties": {
    "iso:country":"BE",
    "sg:address":"Nestor De Ti\u00c8restraat 9",
    "sg:city":"Oudenaarde",
    "sg:orig_category":"Fabrication and montage de mobilier",
    "sg:phone":"+32 55 30 19 36",
    "sg:postcode":"9700",
    "sg:province":"Oost-Vlaanderen",
    "wof:name":"Steven Beunens",
    "wof:placetype":"venue"
},
  "geometry": {"coordinates":[3.6124699116,50.8636627197],"type":"Point"}
}