{
  "type": "Feature",
  "properties": {
    "addr:full":"Coenenhofweg 2 Peer Limburg 3990",
    "addr:housenumber":"2",
    "addr:postcode":"3990",
    "addr:street":"Coenenhofweg",
    "iso:country":"BE",
    "sg:address":"Coenenhofweg 2",
    "sg:city":"Peer",
    "sg:orig_category":"Schoonmaakbedrijven and ongediertebestrijding",
    "sg:phone":"+32 11 61 28 88",
    "sg:postcode":"3990",
    "sg:province":"Limburg",
    "wof:name":"Sun-clean",
    "wof:placetype":"venue"
},
  "geometry": {"coordinates":[5.5116348267,51.1374664307],"type":"Point"}
}