{
  "type": "Feature",
  "properties": {
    "addr:full":"Grote Markt 68 Turnhout Antwerpen 2300",
    "addr:housenumber":"68",
    "addr:postcode":"2300",
    "addr:street":"Grote Markt",
    "iso:country":"BE",
    "sg:address":"Grote Markt 68",
    "sg:city":"Turnhout",
    "sg:classifiers":[
        {
            "category":"Utilities",
            "subcategory":"Mobile Phone",
            "type":"Services"
        }
    ],
    "sg:phone":"+32 14 46 25 10",
    "sg:postcode":"2300",
    "sg:province":"Antwerpen",
    "sg:tags":[
        "house",
        "mat\u00e9riel",
        "de",
        "t\u00e9l\u00e9communication"
    ],
    "wof:name":"The Phone House",
    "wof:placetype":"venue"
},
  "geometry": {"coordinates":[4.9479179382,51.3225860596],"type":"Point"}
}