{
  "type": "Feature",
  "properties": {
    "addr:full":"Rue Hook 31bz Eupen Li\u00e8ge 4700",
    "addr:postcode":"4700",
    "addr:street":"Rue Hook 31Bz",
    "iso:country":"BE",
    "sg:address":"Rue Hook 31bz",
    "sg:city":"Eupen",
    "sg:classifiers":[
        {
            "category":"Fast Food",
            "type":"Food & Drink"
        }
    ],
    "sg:phone":"+32 87 55 29 89",
    "sg:postcode":"4700",
    "sg:province":"Li\u00e8ge",
    "sg:tags":[
        "\u00c0",
        "emporter",
        "restaurants"
    ],
    "wof:name":"Friterie Woopy Snacks",
    "wof:placetype":"venue"
},
  "geometry": {"coordinates":[6.037858963,50.6331253052],"type":"Point"}
}