{
  "type": "Feature",
  "properties": {
    "addr:full":"Edgard Tinelstraat 92 Gent (sint-amandsberg) Oost-Vlaanderen 9040",
    "addr:housenumber":"92",
    "addr:postcode":"9040",
    "addr:street":"Edgard Tinelstraat",
    "iso:country":"BE",
    "sg:address":"Edgard Tinelstraat 92",
    "sg:city":"Gent (sint-amandsberg)",
    "sg:classifiers":[
        {
            "category":"Education",
            "subcategory":"University",
            "type":"Public Place"
        }
    ],
    "sg:phone":"+32 9 218 89 30",
    "sg:postcode":"9040",
    "sg:province":"Oost-Vlaanderen",
    "sg:tags":[
        "adult"
    ],
    "wof:name":"Vormingsleerg. Sociaal En Pedag. Werk",
    "wof:placetype":"venue"
},
  "geometry": {"coordinates":[3.768009901,51.0733413696],"type":"Point"}
}