{
  "type": "Feature",
  "properties": {
    "iso:country":"BE",
    "sg:address":"Rue Longchamp 60",
    "sg:city":"Braine L'alleud (braine-l'alleud)",
    "sg:classifiers":[
        {
            "category":"Building & Trades",
            "subcategory":"Landscaping Services",
            "type":"Services"
        }
    ],
    "sg:phone":"+32 2 384 91 76",
    "sg:postcode":"1420",
    "sg:province":"Brabant Wallon",
    "sg:tags":[
        "-",
        "lopping",
        "work",
        "tree",
        "felling"
    ],
    "wof:name":"Butler M",
    "wof:placetype":"venue"
},
  "geometry": {"coordinates":[5.2658081055,47.2069892883],"type":"Point"}
}