{
  "type": "Feature",
  "properties": {
    "iso:country":"BE",
    "sg:address":"Borgersteinlei 103",
    "sg:city":"Mechelen",
    "sg:classifiers":[
        {
            "category":"Shopping",
            "subcategory":"Photographic Equipment",
            "type":"Retail Goods"
        }
    ],
    "sg:phone":"+32 475 87 63 17",
    "sg:postcode":"2800",
    "sg:province":"Antwerpen",
    "sg:tags":[
        "supplie",
        "billiard",
        "-"
    ],
    "wof:name":"Jorge Biljartkeu's",
    "wof:placetype":"venue"
},
  "geometry": {"coordinates":[4.5092549324,51.0383148193],"type":"Point"}
}