{
  "type": "Feature",
  "properties": {
    "addr:full":"Rue Saint-luc 8 Namur Namur 5004",
    "addr:housenumber":"8",
    "addr:postcode":"5004",
    "addr:street":"Rue Saint-Luc",
    "iso:country":"BE",
    "sg:address":"Rue Saint-luc 8",
    "sg:city":"Namur",
    "sg:orig_category":"M\u00e9decins and sp\u00e9cialistes",
    "sg:phone":"+32 81 20 90 91",
    "sg:postcode":"5004",
    "sg:province":"Namur",
    "wof:name":"J.-p. Joris",
    "wof:placetype":"venue"
},
  "geometry": {"coordinates":[4.8813591003,50.4779815674],"type":"Point"}
}