{
  "type": "Feature",
  "properties": {
    "iso:country":"BE",
    "sg:address":"Industrieweg 19",
    "sg:city":"Malle (westmalle)",
    "sg:classifiers":[
        {
            "category":"Banks & Credit Unions",
            "subcategory":"Atm",
            "type":"Services"
        }
    ],
    "sg:phone":"+32 3 312 97 01",
    "sg:postcode":"2390",
    "sg:province":"Antwerpen",
    "sg:tags":[
        "case",
        "crate",
        "maker"
    ],
    "wof:name":"Pasec Nv",
    "wof:placetype":"venue"
},
  "geometry": {"coordinates":[4.7013349533,51.2927932739],"type":"Point"}
}