{
  "type": "Feature",
  "properties": {
    "addr:full":"Quai De Wallonie 51 Li\u00e8ge 1 Li\u00e8ge 4000",
    "addr:housenumber":"51;1",
    "addr:postcode":"4000",
    "addr:street":"Quai De Wallonie",
    "iso:country":"BE",
    "sg:address":"Quai De Wallonie 51",
    "sg:city":"Li\u00e8ge 1",
    "sg:classifiers":[
        {
            "category":"Banks & Credit Unions",
            "subcategory":"Investment Brokerage",
            "type":"Services"
        }
    ],
    "sg:phone":"+32 4 240 60 08",
    "sg:postcode":"4000",
    "sg:province":"Li\u00e8ge",
    "sg:tags":[
        "-",
        "sale",
        "yachts",
        "accessory",
        "pleasure",
        "boat"
    ],
    "wof:name":"Neptunia Sa",
    "wof:placetype":"venue"
},
  "geometry": {"coordinates":[5.5962791443,50.6564750671],"type":"Point"}
}