{
  "type": "Feature",
  "properties": {
    "addr:full":"Enclos Aux Epines 19 Neupre Li\u00e8ge 4121",
    "addr:housenumber":"19",
    "addr:postcode":"4121",
    "addr:street":"Enclos Aux Epines",
    "iso:country":"BE",
    "sg:address":"Enclos Aux Epines 19",
    "sg:city":"Neupre",
    "sg:orig_category":"Hypotheken and hypotheekbanken Immobili\u00ebnkantoren Verbruikerskredietinstellingen Verzekeringsmakelaa",
    "sg:phone":"+32 4 372 02 03",
    "sg:postcode":"4121",
    "sg:province":"Li\u00e8ge",
    "wof:name":"Cr\u00c9dit Immobilier Li\u00c9g.",
    "wof:placetype":"venue"
},
  "geometry": {"coordinates":[5.467318058,50.5536994934],"type":"Point"}
}