{
  "type": "Feature",
  "properties": {
    "addr:full":"Rue Du Roua 50 Ans Li\u00e8ge 4432",
    "addr:housenumber":"50",
    "addr:postcode":"4432",
    "addr:street":"Rue Du Roua",
    "iso:country":"BE",
    "sg:address":"Rue Du Roua 50",
    "sg:city":"Ans",
    "sg:orig_category":"Artsen and specialisten",
    "sg:phone":"+32 4 263 80 99",
    "sg:postcode":"4432",
    "sg:province":"Li\u00e8ge",
    "wof:name":"Eva Bartoszewicz",
    "wof:placetype":"venue"
},
  "geometry": {"coordinates":[5.5083470345,50.6727561951],"type":"Point"}
}