{
  "type": "Feature",
  "properties": {
    "addr:full":"Rue De Malm\u00e9dy 7 Weismes Li\u00e8ge 4950",
    "addr:housenumber":"7",
    "addr:postcode":"4950",
    "addr:street":"Rue De Malme\u0301Dy",
    "iso:country":"BE",
    "sg:address":"Rue De Malm\u00e9dy 7",
    "sg:city":"Weismes",
    "sg:classifiers":[
        {
            "category":"Health Services",
            "subcategory":"Dentist",
            "type":"Services"
        }
    ],
    "sg:phone":"+32 80 67 98 74",
    "sg:postcode":"4950",
    "sg:province":"Li\u00e8ge",
    "wof:name":"Loxhet Bernadette",
    "wof:placetype":"venue"
},
  "geometry": {"coordinates":[6.1088180542,50.4147834778],"type":"Point"}
}