{
  "type": "Feature",
  "properties": {
    "iso:country":"BE",
    "sg:address":"Rue Des Battis 34",
    "sg:city":"Chimay",
    "sg:orig_category":"Activit\u00e9s r\u00e9cr\u00e9atives diverses",
    "sg:phone":"+32 60 51 10 02",
    "sg:postcode":"6464",
    "sg:province":"Hainaut",
    "wof:name":"Club D'echecs Du Sud-hainaut",
    "wof:placetype":"venue"
},
  "geometry": {"coordinates":[4.3713622093,50.0306396484],"type":"Point"}
}