{
  "type": "Feature",
  "properties": {
    "addr:full":"Paapsemlaan 22 Anderlecht Bruxelles-Capitale 1070",
    "addr:housenumber":"22",
    "addr:postcode":"1070",
    "addr:street":"Paapsemlaan",
    "iso:country":"BE",
    "sg:address":"Paapsemlaan 22",
    "sg:city":"Anderlecht",
    "sg:orig_category":"Drukkerijen and copyshops",
    "sg:phone":"+32 2 521 17 15",
    "sg:postcode":"1070",
    "sg:province":"Bruxelles-Capitale",
    "wof:name":"Hens & Markadieu",
    "wof:placetype":"venue"
},
  "geometry": {"coordinates":[4.3143959045,50.8238182068],"type":"Point"}
}