{
  "type": "Feature",
  "properties": {
    "iso:country":"BE",
    "sg:address":"Stationsstraat 173",
    "sg:city":"Duffel",
    "sg:orig_category":"Journaux",
    "sg:phone":"+32 15 31 83 98",
    "sg:postcode":"2570",
    "sg:province":"Antwerpen",
    "wof:name":"'t Station",
    "wof:placetype":"venue"
},
  "geometry": {"coordinates":[4.4944181442,51.0909080505],"type":"Point"}
}