{
  "type": "Feature",
  "properties": {
    "iso:country":"BE",
    "sg:address":"Eindhoutdorp 27",
    "sg:city":"Laakdal (eindhout)",
    "sg:classifiers":[
        {
            "category":"Insurance",
            "subcategory":"Insurance Agent",
            "type":"Services"
        }
    ],
    "sg:phone":"+32 14 86 67 27",
    "sg:postcode":"2430",
    "sg:province":"Antwerpen",
    "sg:tags":[
        "broker"
    ],
    "wof:name":"Adverba",
    "wof:placetype":"venue"
},
  "geometry": {"coordinates":[5.0687851906,51.0857543945],"type":"Point"}
}