{
  "type": "Feature",
  "properties": {
    "addr:full":"Dorpsstraat 44 Beveren (kieldrecht) Oost-Vlaanderen 9130",
    "addr:housenumber":"44",
    "addr:postcode":"9130",
    "addr:street":"Dorpsstraat",
    "iso:country":"BE",
    "sg:address":"Dorpsstraat 44",
    "sg:city":"Beveren (kieldrecht)",
    "sg:classifiers":[
        {
            "category":"Shopping",
            "subcategory":"Clothing, Apparel, & Fashions",
            "type":"Retail Goods"
        }
    ],
    "sg:phone":"+32 3 773 29 50",
    "sg:postcode":"9130",
    "sg:province":"Oost-Vlaanderen",
    "sg:tags":[
        "boutique"
    ],
    "wof:name":"Scorpios",
    "wof:placetype":"venue"
},
  "geometry": {"coordinates":[4.1744389534,51.2911987305],"type":"Point"}
}