{
  "type": "Feature",
  "properties": {
    "iso:country":"BE",
    "sg:address":"Avenue De La R\u00c9sistance",
    "sg:city":"Soumagne",
    "sg:orig_category":"Fabrication and montage de mobilier",
    "sg:phone":"+32 4 377 24 67",
    "sg:postcode":"4630",
    "sg:province":"Li\u00e8ge",
    "wof:name":"Euro-cuisines",
    "wof:placetype":"venue"
},
  "geometry": {"coordinates":[5.7301630974,50.6296195984],"type":"Point"}
}