{
  "type": "Feature",
  "properties": {
    "addr:full":"Duivelstraat Je3 Ardooie West-Vlaanderen 8850",
    "addr:postcode":"je3;8850",
    "addr:street":"Duivelstraat",
    "iso:country":"BE",
    "sg:address":"Duivelstraat Je3",
    "sg:city":"Ardooie",
    "sg:orig_category":"Ordinateurs and \u00e9quipement informatique",
    "sg:phone":"+32 51 74 00 00",
    "sg:postcode":"8850",
    "sg:province":"West-Vlaanderen",
    "wof:name":"Sanders Computers",
    "wof:placetype":"venue"
},
  "geometry": {"coordinates":[3.1982800961,50.9782142639],"type":"Point"}
}