{
  "type": "Feature",
  "properties": {
    "addr:full":"Rue De Rechain 41 Dison Li\u00e8ge 4820",
    "addr:housenumber":"41",
    "addr:postcode":"4820",
    "addr:street":"Rue De Rechain",
    "iso:country":"BE",
    "sg:address":"Rue De Rechain 41",
    "sg:city":"Dison",
    "sg:orig_category":"Charpentes and couvertures",
    "sg:phone":"+32 87 31 13 95",
    "sg:postcode":"4820",
    "sg:province":"Li\u00e8ge",
    "wof:name":"Mohamed Majeri",
    "wof:placetype":"venue"
},
  "geometry": {"coordinates":[5.8471450806,50.611579895],"type":"Point"}
}