{
  "type": "Feature",
  "properties": {
    "iso:country":"BE",
    "sg:address":"Rue Lohest 90",
    "sg:city":"Li\u00c8ge",
    "sg:classifiers":[
        {
            "category":"Restaurant",
            "type":"Food & Drink"
        }
    ],
    "sg:phone":"+32 4 247 43 46",
    "sg:postcode":"4000",
    "sg:province":"Li\u00e8ge",
    "wof:name":"Au Rythme Du Rail",
    "wof:placetype":"venue"
},
  "geometry": {"coordinates":[5.5443758965,50.6786575317],"type":"Point"}
}