{
  "type": "Feature",
  "properties": {
    "addr:full":"Fortuinstraat 56 Mechelen Antwerpen 2800",
    "addr:housenumber":"56",
    "addr:postcode":"2800",
    "addr:street":"Fortuinstraat",
    "iso:country":"BE",
    "sg:address":"Fortuinstraat 56",
    "sg:city":"Mechelen",
    "sg:orig_category":"M\u00e9decins and sp\u00e9cialistes",
    "sg:phone":"+32 15 42 22 01",
    "sg:postcode":"2800",
    "sg:province":"Antwerpen",
    "wof:name":"M. Hermans",
    "wof:placetype":"venue"
},
  "geometry": {"coordinates":[4.4660429955,51.0186805725],"type":"Point"}
}