{
  "type": "Feature",
  "properties": {
    "iso:country":"BE",
    "sg:address":"Esenstraat 58a",
    "sg:city":"Kortemark (zarren-werken)",
    "sg:classifiers":[
        {
            "category":"Quarry",
            "type":"Physical Feature"
        }
    ],
    "sg:phone":"+32 51 57 05 20",
    "sg:postcode":"8610",
    "sg:province":"West-Vlaanderen",
    "sg:tags":[
        "granite",
        "work",
        "marble"
    ],
    "wof:name":"Vandekerckhove M",
    "wof:placetype":"venue"
},
  "geometry": {"coordinates":[2.9534111023,51.0171737671],"type":"Point"}
}