{
  "type": "Feature",
  "properties": {
    "addr:full":"Grote Markt Koning Albert I 43 Ieper West-Vlaanderen 8900",
    "addr:housenumber":"43",
    "addr:postcode":"8900",
    "addr:street":"Grote Markt Koning Albert I",
    "iso:country":"BE",
    "sg:address":"Grote Markt Koning Albert I 43",
    "sg:city":"Ieper",
    "sg:classifiers":[
        {
            "category":"Food & Beverages",
            "subcategory":"Chocolate",
            "type":"Retail Goods"
        }
    ],
    "sg:phone":"+32 57 21 73 06",
    "sg:postcode":"8900",
    "sg:province":"West-Vlaanderen",
    "sg:tags":[
        "confectionery",
        "-"
    ],
    "wof:name":"De Groote P",
    "wof:placetype":"venue"
},
  "geometry": {"coordinates":[2.8878269196,50.8513641357],"type":"Point"}
}