{
  "type": "Feature",
  "properties": {
    "addr:full":"Aarschotstraat 26 Antwerpen Antwerpen 2018",
    "addr:housenumber":"26",
    "addr:postcode":"2018",
    "addr:street":"Aarschotstraat",
    "iso:country":"BE",
    "sg:address":"Aarschotstraat 26",
    "sg:city":"Antwerpen",
    "sg:orig_category":"Antiquit\u00e9s",
    "sg:phone":"+32 3 238 55 01",
    "sg:postcode":"2018",
    "sg:province":"Antwerpen",
    "wof:name":"Polyedre",
    "wof:placetype":"venue"
},
  "geometry": {"coordinates":[4.4081587791,51.206741333],"type":"Point"}
}