{
  "type": "Feature",
  "properties": {
    "addr:full":"Rue Principale 9 B\u00fcllingen Li\u00e8ge 4760",
    "addr:housenumber":"9",
    "addr:postcode":"4760",
    "addr:street":"Rue Principale",
    "iso:country":"BE",
    "sg:address":"Rue Principale 9",
    "sg:city":"B\u00fcllingen",
    "sg:classifiers":[
        {
            "category":"Personal",
            "subcategory":"Beauty Salon",
            "type":"Services"
        }
    ],
    "sg:phone":"+32 80 64 76 00",
    "sg:postcode":"4760",
    "sg:province":"Li\u00e8ge",
    "sg:tags":[
        "lady",
        "-",
        "hairdressing"
    ],
    "wof:name":"Hennes - Halmes G",
    "wof:placetype":"venue"
},
  "geometry": {"coordinates":[6.2557492256,50.4061813354],"type":"Point"}
}