{
  "type": "Feature",
  "properties": {
    "addr:full":"Rue Blanche 8 Box 4 Bruxelles Bruxelles-Capitale 1000",
    "addr:housenumber":"8;4",
    "addr:postcode":"1000",
    "addr:street":"Rue Blanche;Box",
    "iso:country":"BE",
    "sg:address":"Rue Blanche 8 Box 4",
    "sg:city":"Bruxelles",
    "sg:classifiers":[
        {
            "category":"Professional",
            "subcategory":"Engineering",
            "type":"Services"
        }
    ],
    "sg:phone":"+32 2 537 46 25",
    "sg:postcode":"1000",
    "sg:province":"Bruxelles-Capitale",
    "sg:tags":[
        "civil",
        "offices-"
    ],
    "wof:name":"Vibek Sa",
    "wof:placetype":"venue"
},
  "geometry": {"coordinates":[4.3592839241,50.8304328918],"type":"Point"}
}