{
  "type": "Feature",
  "properties": {
    "addr:full":"Atlasstr 7 Koekelare West-Vlaanderen 8680",
    "addr:housenumber":"7",
    "addr:postcode":"8680",
    "addr:street":"Atlasstr",
    "iso:country":"BE",
    "sg:address":"Atlasstr 7",
    "sg:city":"Koekelare",
    "sg:classifiers":[
        {
            "category":"Home & Garden",
            "subcategory":"Furniture",
            "type":"Retail Goods"
        }
    ],
    "sg:phone":"+32 51 58 33 00",
    "sg:postcode":"8680",
    "sg:province":"West-Vlaanderen",
    "sg:tags":[
        "household",
        "wood"
    ],
    "wof:name":"Ameel Dirk Bvba",
    "wof:placetype":"venue"
},
  "geometry": {"coordinates":[2.9668319225,51.0921363831],"type":"Point"}
}