{
  "type": "Feature",
  "properties": {
    "iso:country":"BE",
    "sg:address":"Rue De La Warchenne 1",
    "sg:city":"Malmedy",
    "sg:classifiers":[
        {
            "category":"Health Services",
            "subcategory":"Health Practitioner",
            "type":"Services"
        }
    ],
    "sg:phone":"+32 80 77 15 33",
    "sg:postcode":"4960",
    "sg:province":"Li\u00e8ge",
    "sg:tags":[
        "physiotherapist"
    ],
    "wof:name":"Gabriel Laurence",
    "wof:placetype":"venue"
},
  "geometry": {"coordinates":[6.0278949738,50.4245643616],"type":"Point"}
}