{
  "type": "Feature",
  "properties": {
    "addr:full":"Avenue Nellie Melba 42 Bruxelles (anderlecht) Bruxelles-Capitale 1070",
    "addr:housenumber":"42",
    "addr:postcode":"1070",
    "addr:street":"Avenue Nellie Melba",
    "iso:country":"BE",
    "sg:address":"Avenue Nellie Melba 42",
    "sg:city":"Bruxelles (anderlecht)",
    "sg:classifiers":[
        {
            "category":"Utilities",
            "subcategory":"Natural Gas",
            "type":"Services"
        }
    ],
    "sg:phone":"+32 2 521 24 72",
    "sg:postcode":"1070",
    "sg:province":"Bruxelles-Capitale",
    "sg:tags":[
        "hide",
        "skin"
    ],
    "wof:name":"Moris Sprl",
    "wof:placetype":"venue"
},
  "geometry": {"coordinates":[4.2937889099,50.8300323486],"type":"Point"}
}