{
  "type": "Feature",
  "properties": {
    "addr:full":"Molenstraat 41 Oudenaarde Oost-Vlaanderen 9700",
    "addr:housenumber":"41",
    "addr:postcode":"9700",
    "addr:street":"Molenstraat",
    "iso:country":"BE",
    "sg:address":"Molenstraat 41",
    "sg:city":"Oudenaarde",
    "sg:classifiers":[
        {
            "category":"Personal",
            "subcategory":"Beauty Salon",
            "type":"Services"
        }
    ],
    "sg:phone":"+32 55 31 25 04",
    "sg:postcode":"9700",
    "sg:province":"Oost-Vlaanderen",
    "sg:tags":[
        "lady",
        "-",
        "hairdressing"
    ],
    "wof:name":"R\u00e9gine",
    "wof:placetype":"venue"
},
  "geometry": {"coordinates":[3.6122500896,50.8751716614],"type":"Point"}
}