{
  "type": "Feature",
  "properties": {
    "iso:country":"BE",
    "sg:address":"Rubenslaan 38",
    "sg:city":"Ranst",
    "sg:orig_category":"Woningbouw",
    "sg:phone":"+32 3 485 74 33",
    "sg:postcode":"2520",
    "sg:province":"Antwerpen",
    "wof:name":"Weyers M.",
    "wof:placetype":"venue"
},
  "geometry": {"coordinates":[4.5909228325,51.185836792],"type":"Point"}
}