{
  "type": "Feature",
  "properties": {
    "iso:country":"BE",
    "sg:address":"Rue Du Petit Villerot 298",
    "sg:city":"Saint-ghislain (hautrage)",
    "sg:classifiers":[
        {
            "category":"Food & Beverages",
            "subcategory":"Groceries & Convenience Stores",
            "type":"Retail Goods"
        }
    ],
    "sg:phone":"+32 65 62 32 48",
    "sg:postcode":"7334",
    "sg:province":"Hainaut",
    "sg:tags":[
        "grocer"
    ],
    "wof:name":"Gualano E",
    "wof:placetype":"venue"
},
  "geometry": {"coordinates":[3.7807068825,50.4662055969],"type":"Point"}
}