{
  "type": "Feature",
  "properties": {
    "addr:full":"Kruisbergstraat 17 Ruiselede West-Vlaanderen 8755",
    "addr:housenumber":"17",
    "addr:postcode":"8755",
    "addr:street":"Kruisbergstraat",
    "iso:country":"BE",
    "sg:address":"Kruisbergstraat 17",
    "sg:city":"Ruiselede",
    "sg:orig_category":"Woningbouw",
    "sg:phone":"+32 51 68 61 37",
    "sg:postcode":"8755",
    "sg:province":"West-Vlaanderen",
    "wof:name":"Van Eeghem-decock",
    "wof:placetype":"venue"
},
  "geometry": {"coordinates":[3.3849670887,51.0723609924],"type":"Point"}
}