{
  "type": "Feature",
  "properties": {
    "iso:country":"BE",
    "sg:address":"Rue G\u00c9n\u00c9ral-leman 21",
    "sg:city":"Nivelles",
    "sg:orig_category":"Boekhouders",
    "sg:phone":"+32 67 21 17 62",
    "sg:postcode":"1400",
    "sg:province":"Brabant Wallon",
    "wof:name":"Joseph Scheen",
    "wof:placetype":"venue"
},
  "geometry": {"coordinates":[4.331152916,50.6003112793],"type":"Point"}
}