{
  "type": "Feature",
  "properties": {
    "addr:full":"Amb. Zone De Waerde 1332b15 Zonhoven Limburg 3520",
    "addr:postcode":"3520",
    "addr:street":"1332B15",
    "iso:country":"BE",
    "sg:address":"Amb. Zone De Waerde 1332b15",
    "sg:city":"Zonhoven",
    "sg:orig_category":"Entretien and r\u00e9parations de voitures",
    "sg:phone":"+32 11 81 66 11",
    "sg:postcode":"3520",
    "sg:province":"Limburg",
    "wof:name":"Carrosserie P.c.m.",
    "wof:placetype":"venue"
},
  "geometry": {"coordinates":[5.3854022026,51.0003929138],"type":"Point"}
}