{
  "type": "Feature",
  "properties": {
    "addr:full":"Rue L\u00e9opold I 465 Bruxelles (jette) Bruxelles-Capitale 1090",
    "addr:housenumber":"465",
    "addr:postcode":"1090",
    "addr:street":"Rue Le\u0301Opold I",
    "iso:country":"BE",
    "sg:address":"Rue L\u00e9opold I 465",
    "sg:city":"Bruxelles (jette)",
    "sg:classifiers":[
        {
            "category":"Retail",
            "subcategory":"Auto Repair",
            "type":"Services"
        }
    ],
    "sg:phone":"+32 2 420 00 34",
    "sg:postcode":"1090",
    "sg:province":"Bruxelles-Capitale",
    "sg:tags":[
        "garage"
    ],
    "wof:name":"Banbanasti G",
    "wof:placetype":"venue"
},
  "geometry": {"coordinates":[4.3305668831,50.8738899231],"type":"Point"}
}