{
  "type": "Feature",
  "properties": {
    "addr:full":"Sint Annaboomstraat 63a Zwijndrecht Antwerpen 2070",
    "addr:housenumber":"63a",
    "addr:postcode":"2070",
    "addr:street":"Annaboomstraat",
    "iso:country":"BE",
    "sg:address":"Sint Annaboomstraat 63a",
    "sg:city":"Zwijndrecht",
    "sg:classifiers":[
        {
            "category":"Building & Trades",
            "subcategory":"Construction",
            "type":"Services"
        }
    ],
    "sg:phone":"+32 3 252 76 41",
    "sg:postcode":"2070",
    "sg:province":"Antwerpen",
    "sg:tags":[
        "central",
        "heating",
        "system"
    ],
    "wof:name":"R. Heyndrickx & Co B.v.b.a.",
    "wof:placetype":"venue"
},
  "geometry": {"coordinates":[4.3216919899,51.2174606323],"type":"Point"}
}