{
  "type": "Feature",
  "properties": {
    "iso:country":"BE",
    "sg:address":"Ekkergemstraat 74",
    "sg:city":"Gent",
    "sg:classifiers":[
        {
            "category":"Communications",
            "type":"Services"
        }
    ],
    "sg:phone":"+32 9 329 05 78",
    "sg:postcode":"9000",
    "sg:province":"Oost-Vlaanderen",
    "sg:tags":[
        "translator"
    ],
    "wof:name":"Coppens S",
    "wof:placetype":"venue"
},
  "geometry": {"coordinates":[3.7039179802,51.0508766174],"type":"Point"}
}