{
  "type": "Feature",
  "properties": {
    "iso:country":"BE",
    "sg:address":"Rue De Petit Axhe 26",
    "sg:city":"Waremme",
    "sg:classifiers":[
        {
            "category":"Building & Trades",
            "subcategory":"Construction",
            "type":"Services"
        }
    ],
    "sg:phone":"+32 19 32 40 95",
    "sg:postcode":"4300",
    "sg:province":"Li\u00e8ge",
    "sg:tags":[
        "installation",
        "-",
        "central",
        "heating"
    ],
    "wof:name":"Jamart J & Fils",
    "wof:placetype":"venue"
},
  "geometry": {"coordinates":[5.2341032028,50.6841812134],"type":"Point"}
}