{
  "type": "Feature",
  "properties": {
    "addr:full":"Route De Mons 52 Sivry-rance Hainaut 6470",
    "addr:housenumber":"52",
    "addr:postcode":"6470",
    "addr:street":"Route De Mons",
    "iso:country":"BE",
    "sg:address":"Route De Mons 52",
    "sg:city":"Sivry-rance",
    "sg:orig_category":"Musea and historische gebouwen Natuurwetenschappelijk onderzoek",
    "sg:phone":"+32 60 45 51 28",
    "sg:postcode":"6470",
    "sg:province":"Hainaut",
    "wof:name":"Observatoire Du Centre Perm. De La Nature",
    "wof:placetype":"venue"
},
  "geometry": {"coordinates":[4.2273278236,50.1782836914],"type":"Point"}
}