{
  "type": "Feature",
  "properties": {
    "iso:country":"BE",
    "sg:address":"Rue Du Grand Central 61",
    "sg:city":"Charleroi",
    "sg:classifiers":[
        {
            "category":"Travel",
            "subcategory":"Travel Agent",
            "type":"Entertainment"
        }
    ],
    "sg:phone":"+32 71 33 42 47",
    "sg:postcode":"6000",
    "sg:province":"Hainaut",
    "sg:tags":[
        "agency"
    ],
    "wof:name":"Aladin Tours",
    "wof:placetype":"venue"
},
  "geometry": {"coordinates":[4.4367899895,50.4092330933],"type":"Point"}
}