{
  "type": "Feature",
  "properties": {
    "addr:full":"Remichampagne 25 Vaux-sur-sure Luxembourg 6640",
    "addr:housenumber":"25",
    "addr:postcode":"6640",
    "addr:street":"Remichampagne",
    "iso:country":"BE",
    "sg:address":"Remichampagne 25",
    "sg:city":"Vaux-sur-sure",
    "sg:orig_category":"Artsen and specialisten",
    "sg:phone":"+32 61 26 64 28",
    "sg:postcode":"6640",
    "sg:province":"Luxembourg",
    "wof:name":"Fran\u00c7oise Pottier",
    "wof:placetype":"venue"
},
  "geometry": {"coordinates":[5.6431288719,49.9348716736],"type":"Point"}
}