{
  "type": "Feature",
  "properties": {
    "iso:country":"BE",
    "sg:address":"Rue Petit Aaz 20",
    "sg:city":"Oupeye",
    "sg:classifiers":[
        {
            "category":"Professional",
            "subcategory":"Accounting & Tax Preparation",
            "type":"Services"
        }
    ],
    "sg:phone":"+32 4 278 34 67",
    "sg:postcode":"4680",
    "sg:province":"Li\u00e8ge",
    "sg:tags":[
        "bookkeeper"
    ],
    "wof:name":"Klontz E",
    "wof:placetype":"venue"
},
  "geometry": {"coordinates":[5.6237602234,50.7157897949],"type":"Point"}
}