{
  "type": "Feature",
  "properties": {
    "addr:full":"Rue Des Mini\u00c8res 14 Verviers Li\u00e8ge 4800",
    "addr:housenumber":"14",
    "addr:postcode":"4800",
    "addr:street":"Rue Des Minie\u0300Res",
    "iso:country":"BE",
    "sg:address":"Rue Des Mini\u00c8res 14",
    "sg:city":"Verviers",
    "sg:orig_category":"Deurwaarders",
    "sg:phone":"+32 87 22 87 57",
    "sg:postcode":"4800",
    "sg:province":"Li\u00e8ge",
    "wof:name":"Thierry Collard",
    "wof:placetype":"venue"
},
  "geometry": {"coordinates":[5.8579640388,50.588809967],"type":"Point"}
}