{
  "type": "Feature",
  "properties": {
    "addr:full":"Chauss\u00c9e De Huy 201 Wavre Brabant Wallon 1300",
    "addr:housenumber":"201;1300",
    "addr:street":"Chausse\u0301E De Huy",
    "iso:country":"BE",
    "sg:address":"Chauss\u00c9e De Huy 201",
    "sg:city":"Wavre",
    "sg:orig_category":"Immobili\u00ebnkantoren Landmeters and schatters",
    "sg:phone":"+32 10 24 33 66",
    "sg:postcode":"1300",
    "sg:province":"Brabant Wallon",
    "wof:name":"Logis 2000",
    "wof:placetype":"venue"
},
  "geometry": {"coordinates":[4.6385641098,50.7040634155],"type":"Point"}
}