{
  "type": "Feature",
  "properties": {
    "iso:country":"BE",
    "sg:address":"Avenue De Boetendael 16",
    "sg:city":"Uccle",
    "sg:orig_category":"Assistances juridiques. Conseillers fiscaux",
    "sg:phone":"+32 2 374 43 68",
    "sg:postcode":"1180",
    "sg:province":"Bruxelles-Capitale",
    "wof:name":"Andre Joary",
    "wof:placetype":"venue"
},
  "geometry": {"coordinates":[4.3451662064,50.8046302795],"type":"Point"}
}