{
  "type": "Feature",
  "properties": {
    "iso:country":"BE",
    "sg:address":"Bernstraat 33",
    "sg:city":"Gavere (asper)",
    "sg:orig_category":"Non-Classified Establishments",
    "sg:phone":"+32 9 384 90 62",
    "sg:postcode":"9890",
    "sg:province":"Oost-Vlaanderen",
    "wof:name":"Eco-lights Benelux",
    "wof:placetype":"venue"
},
  "geometry": {"coordinates":[3.6378378868,50.9370651245],"type":"Point"}
}