{
  "type": "Feature",
  "properties": {
    "iso:country":"BE",
    "sg:address":"Rue Du Presbyt\u00c8re 8",
    "sg:city":"Remicourt",
    "sg:orig_category":"Openbare bibliotheken and archieven",
    "sg:phone":"+32 19 54 53 07",
    "sg:postcode":"4350",
    "sg:province":"Li\u00e8ge",
    "wof:name":"Biblioth\u00c8que Publique",
    "wof:placetype":"venue"
},
  "geometry": {"coordinates":[5.3287148476,50.6800613403],"type":"Point"}
}