{
  "type": "Feature",
  "properties": {
    "iso:country":"BE",
    "sg:address":"Rue De La Victoire 25",
    "sg:city":"Charleroi",
    "sg:orig_category":"Paramedische behandelingen",
    "sg:phone":"+32 71 37 57 67",
    "sg:postcode":"6044",
    "sg:province":"Hainaut",
    "wof:name":"C. Bourgoin",
    "wof:placetype":"venue"
},
  "geometry": {"coordinates":[4.3968467712,50.441078186],"type":"Point"}
}