{
  "type": "Feature",
  "properties": {
    "iso:country":"BE",
    "sg:address":"Rue Monchamps 7",
    "sg:city":"Chaudfontaine",
    "sg:orig_category":"Instituts de beaut\u00e9",
    "sg:phone":"+32 4 368 82 54",
    "sg:postcode":"4052",
    "sg:province":"Li\u00e8ge",
    "wof:name":"Marie Dorsinfang",
    "wof:placetype":"venue"
},
  "geometry": {"coordinates":[5.6392202377,50.5586051941],"type":"Point"}
}