{
  "type": "Feature",
  "properties": {
    "addr:full":"Rue Du Ma\u00efeur Renard 5 Qu\u00e9vy (genly) Hainaut 7040",
    "addr:housenumber":"5",
    "addr:postcode":"7040",
    "addr:street":"Rue Du Mai\u0308Eur Renard;Hainaut",
    "iso:country":"BE",
    "sg:address":"Rue Du Ma\u00efeur Renard 5",
    "sg:city":"Qu\u00e9vy (genly)",
    "sg:classifiers":[
        {
            "category":"Building & Trades",
            "subcategory":"Plumbing",
            "type":"Services"
        }
    ],
    "sg:phone":"+32 65 56 91 59",
    "sg:postcode":"7040",
    "sg:province":"Hainaut",
    "sg:tags":[
        "contractor"
    ],
    "wof:name":"Santucci F Sprl",
    "wof:placetype":"venue"
},
  "geometry": {"coordinates":[3.9151248932,50.3917007446],"type":"Point"}
}