{
  "type": "Feature",
  "properties": {
    "addr:full":"Rue Des Combattants 1 Pepinster Li\u00e8ge 4860",
    "addr:housenumber":"1",
    "addr:postcode":"4860",
    "addr:street":"Rue Des Combattants",
    "iso:country":"BE",
    "sg:address":"Rue Des Combattants 1",
    "sg:city":"Pepinster",
    "sg:orig_category":"Enseignement maternel and primaire",
    "sg:phone":"+32 87 46 93 32",
    "sg:postcode":"4860",
    "sg:province":"Li\u00e8ge",
    "wof:name":"Ecole Fond. Communale",
    "wof:placetype":"venue"
},
  "geometry": {"coordinates":[5.8189201355,50.5796890259],"type":"Point"}
}