{
  "type": "Feature",
  "properties": {
    "iso:country":"BE",
    "sg:address":"Schoonhoudtdtraat 70",
    "sg:city":"Sint-niklaas",
    "sg:orig_category":"Plantes and fleurs Gr",
    "sg:phone":"+32 3 722 05 09",
    "sg:postcode":"9111",
    "sg:province":"Oost-Vlaanderen",
    "wof:name":"D'haen",
    "wof:placetype":"venue"
},
  "geometry": {"coordinates":[4.0897397995,51.1463394165],"type":"Point"}
}