{
  "type": "Feature",
  "properties": {
    "addr:full":"Rue Centre 28 Fauvillers Luxembourg 6637",
    "addr:housenumber":"28",
    "addr:postcode":"6637",
    "addr:street":"Rue Centre",
    "iso:country":"BE",
    "sg:address":"Rue Centre 28",
    "sg:city":"Fauvillers",
    "sg:classifiers":[
        {
            "category":"Manufacturing",
            "subcategory":"Wood Products",
            "type":"Manufacturing & Wholesale Goods"
        }
    ],
    "sg:phone":"+32 63 60 09 52",
    "sg:postcode":"6637",
    "sg:province":"Luxembourg",
    "sg:tags":[
        "firewood"
    ],
    "wof:name":"Strepenne E",
    "wof:placetype":"venue"
},
  "geometry": {"coordinates":[5.6638197899,49.8519592285],"type":"Point"}
}