{
  "type": "Feature",
  "properties": {
    "iso:country":"BE",
    "sg:address":"Tongersesteenweg 1b2",
    "sg:city":"Hoeselt",
    "sg:orig_category":"Parfumeries",
    "sg:phone":"+32 89 51 19 57",
    "sg:postcode":"3730",
    "sg:province":"Limburg",
    "wof:name":"Huis Aphrodite",
    "wof:placetype":"venue"
},
  "geometry": {"coordinates":[5.4907770157,50.84973526],"type":"Point"}
}