{
  "type": "Feature",
  "properties": {
    "addr:full":"Rue De Heuseux 39 Blegny Li\u00e8ge 4671",
    "addr:housenumber":"39",
    "addr:postcode":"4671",
    "addr:street":"Rue De Heuseux",
    "iso:country":"BE",
    "sg:address":"Rue De Heuseux 39",
    "sg:city":"Blegny",
    "sg:orig_category":"Eleveurs de bovins",
    "sg:phone":"+32 4 387 40 13",
    "sg:postcode":"4671",
    "sg:province":"Li\u00e8ge",
    "wof:name":"Jean Fortemps",
    "wof:placetype":"venue"
},
  "geometry": {"coordinates":[5.7008261681,50.6654014587],"type":"Point"}
}