{
  "type": "Feature",
  "properties": {
    "addr:full":"Kroonlaan 128 Elsene/ixelles Bruxelles-Capitale 1050",
    "addr:housenumber":"128",
    "addr:postcode":"1050",
    "addr:street":"Kroonlaan",
    "iso:country":"BE",
    "sg:address":"Kroonlaan 128",
    "sg:city":"Elsene/ixelles",
    "sg:orig_category":"Tijdelijke werkgelegenheid and uitzendkantoren",
    "sg:phone":"+32 2 640 65 63",
    "sg:postcode":"1050",
    "sg:province":"Bruxelles-Capitale",
    "wof:name":"Interim Partner",
    "wof:placetype":"venue"
},
  "geometry": {"coordinates":[4.3800768852,50.8291015625],"type":"Point"}
}