{
  "type": "Feature",
  "properties": {
    "iso:country":"BE",
    "sg:address":"Parijsstraat 5",
    "sg:city":"Leuven",
    "sg:classifiers":[
        {
            "category":"Shopping",
            "subcategory":"Clothing, Apparel, & Fashions",
            "type":"Retail Goods"
        }
    ],
    "sg:phone":"+32 16 23 57 58",
    "sg:postcode":"3000",
    "sg:province":"Vlaams-Brabant",
    "sg:tags":[
        "boutique"
    ],
    "wof:name":"Kris",
    "wof:placetype":"venue"
},
  "geometry": {"coordinates":[4.6997561455,50.8792495728],"type":"Point"}
}