{
  "type": "Feature",
  "properties": {
    "iso:country":"BE",
    "sg:address":"Slachterijstraat 18",
    "sg:city":"Westerlo",
    "sg:classifiers":[
        {
            "category":"Professional",
            "subcategory":"Engineering",
            "type":"Services"
        }
    ],
    "sg:phone":"+32 14 26 19 41",
    "sg:postcode":"2260",
    "sg:province":"Antwerpen",
    "sg:tags":[
        "-"
    ],
    "wof:name":"Vaveco Bvba",
    "wof:placetype":"venue"
},
  "geometry": {"coordinates":[4.865085125,51.1034584045],"type":"Point"}
}