{
  "type": "Feature",
  "properties": {
    "iso:country":"BE",
    "sg:address":"Zomerweg 14",
    "sg:city":"Jabbeke",
    "sg:classifiers":[
        {
            "category":"Wholesale",
            "subcategory":"Plants",
            "type":"Manufacturing & Wholesale Goods"
        }
    ],
    "sg:phone":"+32 50 81 17 09",
    "sg:postcode":"8490",
    "sg:province":"West-Vlaanderen",
    "sg:tags":[
        "whol",
        "flower",
        "-",
        "grower"
    ],
    "wof:name":"Timmerman Geert",
    "wof:placetype":"venue"
},
  "geometry": {"coordinates":[3.0972499847,51.1727371216],"type":"Point"}
}