{
  "type": "Feature",
  "properties": {
    "addr:full":"Kapellestraat 99 Tervuren Vlaams-Brabant 3080",
    "addr:housenumber":"99",
    "addr:postcode":"3080",
    "addr:street":"Kapellestraat",
    "iso:country":"BE",
    "sg:address":"Kapellestraat 99",
    "sg:city":"Tervuren",
    "sg:orig_category":"Pain, p\u00e2tisseries and confiseries",
    "sg:phone":"+32 2 767 35 73",
    "sg:postcode":"3080",
    "sg:province":"Vlaams-Brabant",
    "wof:name":"Bakkerij De Kapelle",
    "wof:placetype":"venue"
},
  "geometry": {"coordinates":[4.5075740814,50.820350647],"type":"Point"}
}