{
  "type": "Feature",
  "properties": {
    "addr:full":"Diegemstraat 17 Machelen Vlaams-Brabant 1830",
    "addr:housenumber":"17",
    "addr:postcode":"1830",
    "addr:street":"Diegemstraat",
    "iso:country":"BE",
    "sg:address":"Diegemstraat 17",
    "sg:city":"Machelen",
    "sg:orig_category":"Cr\u00e9meries. Equipement divers pour commerces Gr",
    "sg:phone":"+32 2 251 18 13",
    "sg:postcode":"1830",
    "sg:province":"Vlaams-Brabant",
    "wof:name":"Vanov",
    "wof:placetype":"venue"
},
  "geometry": {"coordinates":[4.4352607727,50.9085655212],"type":"Point"}
}