{
  "type": "Feature",
  "properties": {
    "iso:country":"BE",
    "sg:address":"Markt 23",
    "sg:city":"Brugge",
    "sg:classifiers":[
        {
            "category":"Restaurant",
            "type":"Food & Drink"
        }
    ],
    "sg:phone":"+32 50 33 61 10",
    "sg:postcode":"8000",
    "sg:province":"West-Vlaanderen",
    "wof:name":"Restaurant Da Mario",
    "wof:placetype":"venue"
},
  "geometry": {"coordinates":[3.2237360477,51.2089576721],"type":"Point"}
}