{
  "type": "Feature",
  "properties": {
    "addr:full":"Daillyplein 17 Schaarbeek/schaerbeek Bruxelles-Capitale 1030",
    "addr:housenumber":"17",
    "addr:postcode":"1030",
    "addr:street":"Daillyplein",
    "iso:country":"BE",
    "sg:address":"Daillyplein 17",
    "sg:city":"Schaarbeek/schaerbeek",
    "sg:orig_category":"Schoenen",
    "sg:phone":"+32 2 733 62 32",
    "sg:postcode":"1030",
    "sg:province":"Bruxelles-Capitale",
    "wof:name":"Au P'tit Copain",
    "wof:placetype":"venue"
},
  "geometry": {"coordinates":[4.3807997704,50.8583259583],"type":"Point"}
}