{
  "type": "Feature",
  "properties": {
    "addr:full":"Chauss\u00c9e Braine-le-comte 103 Nivelles Brabant Wallon 1400",
    "addr:housenumber":"103",
    "addr:postcode":"1400",
    "addr:street":"Chausse\u0301E Braine-Le-Comte",
    "iso:country":"BE",
    "sg:address":"Chauss\u00c9e Braine-le-comte 103",
    "sg:city":"Nivelles",
    "sg:orig_category":"Pain, p\u00e2tisseries and confiseries",
    "sg:phone":"+32 67 84 02 01",
    "sg:postcode":"1400",
    "sg:province":"Brabant Wallon",
    "wof:name":"Giovanni Del Popolo",
    "wof:placetype":"venue"
},
  "geometry": {"coordinates":[4.3032598495,50.5992012024],"type":"Point"}
}