{
  "type": "Feature",
  "properties": {
    "addr:full":"Koolkuil 13b3 Tongeren Limburg 3700",
    "addr:housenumber":"13b3",
    "addr:postcode":"3700",
    "addr:street":"Koolkuil",
    "iso:country":"BE",
    "sg:address":"Koolkuil 13b3",
    "sg:city":"Tongeren",
    "sg:orig_category":"Persagentschappen",
    "sg:phone":"+32 12 24 19 70",
    "sg:postcode":"3700",
    "sg:province":"Limburg",
    "wof:name":"Marleen Fransen",
    "wof:placetype":"venue"
},
  "geometry": {"coordinates":[5.4658489227,50.779045105],"type":"Point"}
}