{
  "type": "Feature",
  "properties": {
    "iso:country":"BE",
    "sg:address":"Rue De La Tulipe 31a",
    "sg:city":"Bruxelles",
    "sg:orig_category":"Biens d'occasion. R\u00e9parations d'appareils \u00e9lectrom\u00e9nagers",
    "sg:phone":"+32 475 84 31 11",
    "sg:postcode":"1050",
    "sg:province":"Bruxelles-Capitale",
    "wof:name":"Electro Tulipe",
    "wof:placetype":"venue"
},
  "geometry": {"coordinates":[4.3674821854,50.8345031738],"type":"Point"}
}