{
  "type": "Feature",
  "properties": {
    "addr:full":"Generaal Lemanstraat 2ba Sint-pieters-leeuw Vlaams-Brabant 1600",
    "addr:housenumber":"2ba",
    "addr:postcode":"1600",
    "addr:street":"Generaal Lemanstraat",
    "iso:country":"BE",
    "sg:address":"Generaal Lemanstraat 2ba",
    "sg:city":"Sint-pieters-leeuw",
    "sg:classifiers":[
        {
            "category":"Building & Trades",
            "subcategory":"Construction",
            "type":"Services"
        }
    ],
    "sg:phone":"+32 2 334 74 74",
    "sg:postcode":"1600",
    "sg:province":"Vlaams-Brabant",
    "sg:tags":[
        "ventilation",
        "conditionn\u00e9",
        "air"
    ],
    "wof:name":"Magec",
    "wof:placetype":"venue"
},
  "geometry": {"coordinates":[4.2839241028,50.7929191589],"type":"Point"}
}