{
  "type": "Feature",
  "properties": {
    "iso:country":"BE",
    "sg:address":"Rue D'ombret 252",
    "sg:city":"Engis",
    "sg:orig_category":"Herstellingen and onderhoud van auto's",
    "sg:phone":"+32 85 31 25 48",
    "sg:postcode":"4480",
    "sg:province":"Li\u00e8ge",
    "wof:name":"J. Pesch",
    "wof:placetype":"venue"
},
  "geometry": {"coordinates":[5.3381791115,50.5445404053],"type":"Point"}
}