{
  "type": "Feature",
  "properties": {
    "iso:country":"BE",
    "sg:address":"Titecastraat 114",
    "sg:city":"Brugge (sint-michiels)",
    "sg:classifiers":[
        {
            "category":"Building & Trades",
            "subcategory":"Plumbing",
            "type":"Services"
        }
    ],
    "sg:phone":"+32 50 39 25 77",
    "sg:postcode":"8200",
    "sg:province":"West-Vlaanderen",
    "sg:tags":[
        "pipe",
        "drain",
        "unblocking"
    ],
    "wof:name":"Gouwy P",
    "wof:placetype":"venue"
},
  "geometry": {"coordinates":[3.2034699917,51.1934318542],"type":"Point"}
}