{
  "type": "Feature",
  "properties": {
    "iso:country":"BE",
    "sg:address":"Romeinsesteenweg 466",
    "sg:city":"Grimbergen",
    "sg:orig_category":"Effectenmakelaars and vermogensbeheer Verzekeringsmakelaars and experts",
    "sg:phone":"+32 2 267 38 05",
    "sg:postcode":"1853",
    "sg:province":"Vlaams-Brabant",
    "wof:name":"Favere A.v.",
    "wof:placetype":"venue"
},
  "geometry": {"coordinates":[4.3530139923,50.9014205933],"type":"Point"}
}