{
  "type": "Feature",
  "properties": {
    "addr:full":"Rue Montante 12 Ciney (serinchamps) Namur 5590",
    "addr:housenumber":"12",
    "addr:postcode":"5590",
    "addr:street":"Rue Montante",
    "iso:country":"BE",
    "sg:address":"Rue Montante 12",
    "sg:city":"Ciney (serinchamps)",
    "sg:classifiers":[
        {
            "category":"Personal",
            "subcategory":"Nail Salon",
            "type":"Services"
        }
    ],
    "sg:phone":"+32 83 68 90 12",
    "sg:postcode":"5590",
    "sg:province":"Namur",
    "sg:tags":[
        "pedicure"
    ],
    "wof:name":"Rosiere M",
    "wof:placetype":"venue"
},
  "geometry": {"coordinates":[5.1022520065,50.297088623],"type":"Point"}
}