{
  "type": "Feature",
  "properties": {
    "iso:country":"BE",
    "sg:address":"Uikhoverstraat 18",
    "sg:city":"Maasmechelen",
    "sg:orig_category":"Entretien and r\u00e9parations de voitures",
    "sg:phone":"+32 89 72 20 79",
    "sg:postcode":"3631",
    "sg:province":"Limburg",
    "wof:name":"Guido Maesen",
    "wof:placetype":"venue"
},
  "geometry": {"coordinates":[5.7239232063,50.9423713684],"type":"Point"}
}