{
  "type": "Feature",
  "properties": {
    "iso:country":"BE",
    "sg:address":"Karel Keymolenstraat 2",
    "sg:city":"Lennik",
    "sg:orig_category":"Avocats and conseillers juridiques",
    "sg:phone":"+32 2 532 22 60",
    "sg:postcode":"1750",
    "sg:province":"Vlaams-Brabant",
    "wof:name":"G. Daem",
    "wof:placetype":"venue"
},
  "geometry": {"coordinates":[4.1545171738,50.8059806824],"type":"Point"}
}