{
  "type": "Feature",
  "properties": {
    "addr:full":"Pastorijstraat 3 Buggenhout Oost-Vlaanderen 9255",
    "addr:housenumber":"3",
    "addr:postcode":"9255",
    "addr:street":"Pastorijstraat",
    "iso:country":"BE",
    "sg:address":"Pastorijstraat 3",
    "sg:city":"Buggenhout",
    "sg:orig_category":"Artsen and specialisten",
    "sg:phone":"+32 52 33 36 55",
    "sg:postcode":"9255",
    "sg:province":"Oost-Vlaanderen",
    "wof:name":"Hilde Van Humbeeck",
    "wof:placetype":"venue"
},
  "geometry": {"coordinates":[4.2040047646,51.0149765015],"type":"Point"}
}