{
  "type": "Feature",
  "properties": {
    "addr:full":"Avenue Neptune 7 Bruxelles (forest) Bruxelles-Capitale 1190",
    "addr:housenumber":"7",
    "addr:postcode":"1190",
    "addr:street":"Avenue Neptune",
    "iso:country":"BE",
    "sg:address":"Avenue Neptune 7",
    "sg:city":"Bruxelles (forest)",
    "sg:classifiers":[
        {
            "category":"Health Services",
            "subcategory":"Health Practitioner",
            "type":"Services"
        }
    ],
    "sg:phone":"+32 2 345 73 82",
    "sg:postcode":"1190",
    "sg:province":"Bruxelles-Capitale",
    "sg:tags":[
        "physiotherapist"
    ],
    "wof:name":"Greisch O",
    "wof:placetype":"venue"
},
  "geometry": {"coordinates":[4.3313508034,50.8136367798],"type":"Point"}
}