{
  "type": "Feature",
  "properties": {
    "iso:country":"BE",
    "sg:address":"Avenue De Loudun 122-124",
    "sg:city":"Leuze-en-hainaut",
    "sg:orig_category":"Non-Classified Establishments",
    "sg:phone":"+32 69 66 15 28",
    "sg:postcode":"7900",
    "sg:province":"Hainaut",
    "wof:name":"Degroote",
    "wof:placetype":"venue"
},
  "geometry": {"coordinates":[3.6193380356,50.5768089294],"type":"Point"}
}