{
  "type": "Feature",
  "properties": {
    "iso:country":"BE",
    "sg:address":"Oostergemstraat 7ba",
    "sg:city":"Nevele",
    "sg:orig_category":"Antiek",
    "sg:phone":"+32 9 371 82 21",
    "sg:postcode":"9850",
    "sg:province":"Oost-Vlaanderen",
    "wof:name":"Lieve Lambrecht",
    "wof:placetype":"venue"
},
  "geometry": {"coordinates":[3.5894930363,51.0863265991],"type":"Point"}
}