{
  "type": "Feature",
  "properties": {
    "iso:country":"BE",
    "sg:address":"Rue De La Beinvenue 15",
    "sg:city":"Anderlecht",
    "sg:orig_category":"Electrom\u00e9nager, t\u00e9l\u00e9visions and radios. R\u00e9parations d'appareils \u00e9lectrom\u00e9nagers",
    "sg:phone":"+32 2 536 31 85",
    "sg:postcode":"1070",
    "sg:province":"Bruxelles-Capitale",
    "wof:name":"Balay",
    "wof:placetype":"venue"
},
  "geometry": {"coordinates":[4.3057599068,50.8140487671],"type":"Point"}
}