{
  "type": "Feature",
  "properties": {
    "addr:full":"Hollandsebaan 27 Geel Antwerpen 2440",
    "addr:housenumber":"27",
    "addr:postcode":"2440",
    "addr:street":"Hollandsebaan",
    "iso:country":"BE",
    "sg:address":"Hollandsebaan 27",
    "sg:city":"Geel",
    "sg:orig_category":"Dameskledingzaken",
    "sg:phone":"+32 14 58 01 91",
    "sg:postcode":"2440",
    "sg:province":"Antwerpen",
    "wof:name":"Majomi",
    "wof:placetype":"venue"
},
  "geometry": {"coordinates":[5.0011501312,51.130771637],"type":"Point"}
}