{
  "type": "Feature",
  "properties": {
    "addr:full":"Avenue Centrale 63 Charleroi (marcinelle) Hainaut 6001",
    "addr:housenumber":"63",
    "addr:postcode":"6001",
    "addr:street":"Avenue Centrale",
    "iso:country":"BE",
    "sg:address":"Avenue Centrale 63",
    "sg:city":"Charleroi (marcinelle)",
    "sg:classifiers":[
        {
            "category":"Communications",
            "subcategory":"Film & Video Production",
            "type":"Services"
        }
    ],
    "sg:phone":"+32 71 36 69 81",
    "sg:postcode":"6001",
    "sg:province":"Hainaut",
    "sg:tags":[
        "realisation",
        "-"
    ],
    "wof:name":"F.d.p. Production Sprl",
    "wof:placetype":"venue"
},
  "geometry": {"coordinates":[4.4363918304,50.3548660278],"type":"Point"}
}