{
  "type": "Feature",
  "properties": {
    "iso:country":"BE",
    "sg:address":"Poperingestraat 38",
    "sg:city":"Gent",
    "sg:orig_category":"Slagers",
    "sg:phone":"+32 9 226 15 55",
    "sg:postcode":"9000",
    "sg:province":"Oost-Vlaanderen",
    "wof:name":"Luc Vanoverschelde",
    "wof:placetype":"venue"
},
  "geometry": {"coordinates":[3.708605051,51.0752067566],"type":"Point"}
}