{
  "type": "Feature",
  "properties": {
    "iso:country":"BE",
    "sg:address":"Avenue Du Grand Bois 16",
    "sg:city":"Waterloo",
    "sg:classifiers":[
        {
            "category":"Arts & Performance",
            "subcategory":"Music",
            "type":"Entertainment"
        }
    ],
    "sg:phone":"+32 2 351 13 74",
    "sg:postcode":"1410",
    "sg:province":"Brabant Wallon",
    "sg:tags":[
        "freelance",
        "musician"
    ],
    "wof:name":"Horemansx-e",
    "wof:placetype":"venue"
},
  "geometry": {"coordinates":[4.3855571747,50.7109107971],"type":"Point"}
}