{
  "type": "Feature",
  "properties": {
    "iso:country":"BE",
    "sg:address":"Rue Neufmoulin 80",
    "sg:city":"Dison",
    "sg:classifiers":[
        {
            "category":"Cafe",
            "type":"Food & Drink"
        }
    ],
    "sg:phone":"+32 87 33 16 51",
    "sg:postcode":"4820",
    "sg:province":"Li\u00e8ge",
    "sg:tags":[
        "caf\u00e9s"
    ],
    "wof:name":"Georges Marette",
    "wof:placetype":"venue"
},
  "geometry": {"coordinates":[5.8529200554,50.6018104553],"type":"Point"}
}