{
  "type": "Feature",
  "properties": {
    "addr:full":"Boulevard Brand Whitlock 99 Sint-lambrechts-woluwe/woluwe-saint-lambert Bruxelles-Capitale 1200",
    "addr:housenumber":"99",
    "addr:postcode":"1200",
    "addr:street":"Boulevard Brand Whitlock",
    "iso:country":"BE",
    "sg:address":"Boulevard Brand Whitlock 99",
    "sg:city":"Sint-lambrechts-woluwe/woluwe-saint-lambert",
    "sg:classifiers":[
        {
            "category":"Fast Food",
            "type":"Food & Drink"
        }
    ],
    "sg:phone":"+32 2 734 59 12",
    "sg:postcode":"1200",
    "sg:province":"Bruxelles-Capitale",
    "sg:tags":[
        "\u00c0",
        "restaurants",
        "emporter",
        "restaurant"
    ],
    "wof:name":"L'orchidee Bleue",
    "wof:placetype":"venue"
},
  "geometry": {"coordinates":[4.4060120583,50.8421020508],"type":"Point"}
}