{
  "type": "Feature",
  "properties": {
    "addr:full":"Reukenstraat 1 Geraardsbergen (ophasselt) Oost-Vlaanderen 9500",
    "addr:housenumber":"1",
    "addr:postcode":"9500",
    "addr:street":"Reukenstraat",
    "iso:country":"BE",
    "sg:address":"Reukenstraat 1",
    "sg:city":"Geraardsbergen (ophasselt)",
    "sg:classifiers":[
        {
            "category":"Professional",
            "subcategory":"Computer Services",
            "type":"Services"
        }
    ],
    "sg:phone":"+32 54 50 44 71",
    "sg:postcode":"9500",
    "sg:province":"Oost-Vlaanderen",
    "sg:tags":[
        "-",
        "processing",
        "data",
        "software"
    ],
    "wof:name":"Ap Soft",
    "wof:placetype":"venue"
},
  "geometry": {"coordinates":[3.8843801022,50.7716445923],"type":"Point"}
}