{
  "type": "Feature",
  "properties": {
    "addr:full":"Industriepark Centrum-zuid 1527 Houthalen-helchteren Limburg 3530",
    "addr:housenumber":"1527",
    "addr:postcode":"3530",
    "addr:street":"Industriepark Centrum-Zuid",
    "iso:country":"BE",
    "sg:address":"Industriepark Centrum-zuid 1527",
    "sg:city":"Houthalen-helchteren",
    "sg:classifiers":[
        {
            "category":"Landmark",
            "subcategory":"Marketplace",
            "type":"Public Place"
        }
    ],
    "sg:phone":"+32 11 52 05 20",
    "sg:postcode":"3530",
    "sg:province":"Limburg",
    "sg:tags":[
        "survey",
        "market",
        "software"
    ],
    "wof:name":"Real Software - Division Business & Government",
    "wof:placetype":"venue"
},
  "geometry": {"coordinates":[5.3624520302,51.0265808105],"type":"Point"}
}