{
  "type": "Feature",
  "properties": {
    "addr:full":"Francois Laurentplein 1-bus 4 Gent Oost-Vlaanderen 9000",
    "addr:housenumber":"4",
    "addr:postcode":"9000",
    "addr:street":"Oost-Vlaanderen",
    "iso:country":"BE",
    "sg:address":"Francois Laurentplein 1-bus 4",
    "sg:city":"Gent",
    "sg:orig_category":"Avocats and conseillers juridiques. Balie van Gent. Avocats and conseillers juridiques",
    "sg:phone":"+32 9 265 83 83",
    "sg:postcode":"9000",
    "sg:province":"Oost-Vlaanderen",
    "wof:name":"Honore Els",
    "wof:placetype":"venue"
},
  "geometry": {"coordinates":[3.7284560204,51.0512886047],"type":"Point"}
}