{
  "type": "Feature",
  "properties": {
    "addr:full":"Vissersstraat 24 Ukkel/uccle Bruxelles-Capitale 1180",
    "addr:housenumber":"24",
    "addr:postcode":"1180",
    "addr:street":"Vissersstraat;/",
    "iso:country":"BE",
    "sg:address":"Vissersstraat 24",
    "sg:city":"Ukkel/uccle",
    "sg:orig_category":"Sportclubs Sportterreinen and installaties behalve sportcentra",
    "sg:phone":"+32 2 374 94 34",
    "sg:postcode":"1180",
    "sg:province":"Bruxelles-Capitale",
    "wof:name":"S.c. R. Ixelles",
    "wof:placetype":"venue"
},
  "geometry": {"coordinates":[4.3492240906,50.7932624817],"type":"Point"}
}