{
  "type": "Feature",
  "properties": {
    "addr:full":"Avenue F. A. M. Gochet 0 Sambreville Namur 5060",
    "addr:housenumber":"0",
    "addr:postcode":"5060",
    "addr:street":"Avenue F. A. M. Gochet",
    "iso:country":"BE",
    "sg:address":"Avenue F. A. M. Gochet 0",
    "sg:city":"Sambreville",
    "sg:orig_category":"Kunstonderwijs",
    "sg:phone":"+32 71 77 47 47",
    "sg:postcode":"5060",
    "sg:province":"Namur",
    "wof:name":"Ecole Des Beaux-arts",
    "wof:placetype":"venue"
},
  "geometry": {"coordinates":[4.6285200119,50.4448738098],"type":"Point"}
}