{
  "type": "Feature",
  "properties": {
    "iso:country":"BE",
    "sg:address":"Lange Slachterijstraat 66b78",
    "sg:city":"Antwerpen",
    "sg:orig_category":"Boucheries. Produits surgel\u00e9s Gr",
    "sg:phone":"+32 3 236 80 83",
    "sg:postcode":"2060",
    "sg:province":"Antwerpen",
    "wof:name":"Derycker Daniel",
    "wof:placetype":"venue"
},
  "geometry": {"coordinates":[4.4303297997,51.229927063],"type":"Point"}
}