{
  "type": "Feature",
  "properties": {
    "iso:country":"BE",
    "sg:address":"Baekveldstraat 8",
    "sg:city":"Glabbeek",
    "sg:orig_category":"Plaatsen van vloer- and muurbekleding Schilders",
    "sg:phone":"+32 16 77 04 70",
    "sg:postcode":"3380",
    "sg:province":"Vlaams-Brabant",
    "wof:name":"Marc Vangilbergen",
    "wof:placetype":"venue"
},
  "geometry": {"coordinates":[4.9530382156,50.8461456299],"type":"Point"}
}