{
  "type": "Feature",
  "properties": {
    "iso:country":"BE",
    "sg:address":"Kampveldstraat 51",
    "sg:city":"Oostkamp",
    "sg:classifiers":[
        {
            "category":"Military Area",
            "subcategory":"Air Force Base",
            "type":"Public Place"
        }
    ],
    "sg:phone":"+32 50 82 69 07",
    "sg:postcode":"8020",
    "sg:province":"West-Vlaanderen",
    "sg:tags":[
        "gear"
    ],
    "wof:name":"Mechan Constructie Watteeuw Nv",
    "wof:placetype":"venue"
},
  "geometry": {"coordinates":[3.2512099743,51.1264610291],"type":"Point"}
}