{
  "type": "Feature",
  "properties": {
    "addr:full":"Rue Du Pont 23 Hamoir Li\u00e8ge 4180",
    "addr:housenumber":"23",
    "addr:postcode":"4180",
    "addr:street":"Rue Du Pont",
    "iso:country":"BE",
    "sg:address":"Rue Du Pont 23",
    "sg:city":"Hamoir",
    "sg:orig_category":"Librairies",
    "sg:phone":"+32 86 38 87 12",
    "sg:postcode":"4180",
    "sg:province":"Li\u00e8ge",
    "wof:name":"Petit Bazar",
    "wof:placetype":"venue"
},
  "geometry": {"coordinates":[5.5329761505,50.4265785217],"type":"Point"}
}