{
  "type": "Feature",
  "properties": {
    "addr:full":"Sentier De La Meunerie 44 Hannut (avin) Li\u00e8ge 4280",
    "addr:housenumber":"44",
    "addr:postcode":"4280",
    "addr:street":"Sentier De La Meunerie;Avin",
    "iso:country":"BE",
    "sg:address":"Sentier De La Meunerie 44",
    "sg:city":"Hannut (avin)",
    "sg:classifiers":[
        {
            "category":"Building & Trades",
            "subcategory":"Construction",
            "type":"Services"
        }
    ],
    "sg:phone":"+32 19 69 98 84",
    "sg:postcode":"4280",
    "sg:province":"Li\u00e8ge",
    "sg:tags":[
        "carpenter"
    ],
    "wof:name":"Fontaine J",
    "wof:placetype":"venue"
},
  "geometry": {"coordinates":[5.0599031448,50.6288986206],"type":"Point"}
}