{
  "type": "Feature",
  "properties": {
    "iso:country":"BE",
    "sg:address":"Mechelsevest 2",
    "sg:city":"Leuven",
    "sg:classifiers":[
        {
            "category":"Education",
            "subcategory":"School",
            "type":"Public Place"
        }
    ],
    "sg:phone":"+32 16 23 35 31",
    "sg:postcode":"3000",
    "sg:province":"Vlaams-Brabant",
    "sg:tags":[
        "primary"
    ],
    "wof:name":"Sint-jansschool",
    "wof:placetype":"venue"
},
  "geometry": {"coordinates":[4.6856842041,50.8846282959],"type":"Point"}
}