{
  "type": "Feature",
  "properties": {
    "iso:country":"BE",
    "sg:address":"Slachthuisstraat 68",
    "sg:city":"Turnhout",
    "sg:orig_category":"Revolving Doors",
    "sg:phone":"+32 14 40 19 32",
    "sg:postcode":"2300",
    "sg:province":"Antwerpen",
    "wof:name":"M2d",
    "wof:placetype":"venue"
},
  "geometry": {"coordinates":[4.9238181114,51.3042144775],"type":"Point"}
}