{
  "type": "Feature",
  "properties": {
    "iso:country":"BE",
    "sg:address":"Avenue De L'h\u00f4pital Fran\u00e7ais 37",
    "sg:city":"Bruxelles (koekelberg)",
    "sg:classifiers":[
        {
            "category":"Building & Trades",
            "subcategory":"Landscaping Services",
            "type":"Services"
        }
    ],
    "sg:phone":"+32 477 51 44 63",
    "sg:postcode":"1081",
    "sg:province":"Bruxelles-Capitale",
    "sg:tags":[
        "gardening",
        "garden",
        "maintenance"
    ],
    "wof:name":"Ville & Nature",
    "wof:placetype":"venue"
},
  "geometry": {"coordinates":[4.3129520416,50.8669052124],"type":"Point"}
}