{
  "type": "Feature",
  "properties": {
    "addr:full":"Rauwstraat 30 Laakdal Antwerpen 2431",
    "addr:housenumber":"30",
    "addr:postcode":"2431",
    "addr:street":"Rauwstraat",
    "iso:country":"BE",
    "sg:address":"Rauwstraat 30",
    "sg:city":"Laakdal",
    "sg:orig_category":"Plomberie, chauffage and installations sanitaires",
    "sg:phone":"+32 14 84 07 87",
    "sg:postcode":"2431",
    "sg:province":"Antwerpen",
    "wof:name":"Willy Geukens",
    "wof:placetype":"venue"
},
  "geometry": {"coordinates":[4.997563839,51.0760688782],"type":"Point"}
}