{
  "type": "Feature",
  "properties": {
    "addr:full":"Sentier Du Br\u00dbl\u00c9 31 Quaregnon Hainaut 7390",
    "addr:housenumber":"31",
    "addr:postcode":"7390",
    "addr:street":"Sentier Du Bru\u0302Le\u0301",
    "iso:country":"BE",
    "sg:address":"Sentier Du Br\u00dbl\u00c9 31",
    "sg:city":"Quaregnon",
    "sg:orig_category":"R\u00e9cup\u00e9ration de mati\u00e8res m\u00e9talliques recyclables and d\u00e9molisseurs de voitures. V\u00e9hicules automobiles",
    "sg:phone":"+32 65 79 32 34",
    "sg:postcode":"7390",
    "sg:province":"Hainaut",
    "wof:name":"T.e.a.",
    "wof:placetype":"venue"
},
  "geometry": {"coordinates":[3.8649580479,50.4465370178],"type":"Point"}
}