{
  "type": "Feature",
  "properties": {
    "addr:full":"Goodveerdegemstraat 15b13 Zottegem Oost-Vlaanderen 9620",
    "addr:housenumber":"15b13",
    "addr:postcode":"9620",
    "addr:street":"Goodveerdegemstraat",
    "iso:country":"BE",
    "sg:address":"Goodveerdegemstraat 15b13",
    "sg:city":"Zottegem",
    "sg:classifiers":[
        {
            "category":"Personal",
            "subcategory":"Beauty Salon",
            "type":"Services"
        }
    ],
    "sg:phone":"+32 9 361 26 26",
    "sg:postcode":"9620",
    "sg:province":"Oost-Vlaanderen",
    "sg:tags":[
        "de",
        "coiffure"
    ],
    "wof:name":"Hairstudio Tom",
    "wof:placetype":"venue"
},
  "geometry": {"coordinates":[3.8183269501,50.8647956848],"type":"Point"}
}