{
  "type": "Feature",
  "properties": {
    "addr:full":"Wulfhoekstraat 13-15 Hooglede West-Vlaanderen 8830",
    "addr:postcode":"13-15;8830",
    "addr:street":"Wulfhoekstraat",
    "iso:country":"BE",
    "sg:address":"Wulfhoekstraat 13-15",
    "sg:city":"Hooglede",
    "sg:classifiers":[
        {
            "category":"Shopping",
            "subcategory":"Pets & Pet Supplies",
            "type":"Retail Goods"
        }
    ],
    "sg:phone":"+32 51 70 00 72",
    "sg:postcode":"8830",
    "sg:province":"West-Vlaanderen",
    "sg:tags":[
        "horseriding"
    ],
    "wof:name":"Desot D (koetsen)",
    "wof:placetype":"venue"
},
  "geometry": {"coordinates":[3.061549902,50.9645500183],"type":"Point"}
}