{
  "type": "Feature",
  "properties": {
    "iso:country":"BE",
    "sg:address":"Dorpsstraat 102",
    "sg:city":"Stabroek",
    "sg:orig_category":"Artsen and specialisten",
    "sg:phone":"+32 3 568 65 00",
    "sg:postcode":"2940",
    "sg:province":"Antwerpen",
    "wof:name":"K. Luyten",
    "wof:placetype":"venue"
},
  "geometry": {"coordinates":[4.3688240051,51.3334274292],"type":"Point"}
}