{
  "type": "Feature",
  "properties": {
    "addr:full":"Rue Pierre Flamand 103 Braine-l'alleud Brabant Wallon 1420",
    "addr:housenumber":"103",
    "addr:postcode":"1420",
    "addr:street":"Rue Pierre Flamand",
    "iso:country":"BE",
    "sg:address":"Rue Pierre Flamand 103",
    "sg:city":"Braine-l'alleud",
    "sg:classifiers":[
        {
            "category":"Professional",
            "subcategory":"Computer Services",
            "type":"Services"
        }
    ],
    "sg:phone":"+32 2 387 33 88",
    "sg:postcode":"1420",
    "sg:province":"Brabant Wallon",
    "sg:tags":[
        "kantoormateriaal",
        "fab",
        "computerapparatuur",
        "microsoft",
        "gh"
    ],
    "wof:name":"Texar",
    "wof:placetype":"venue"
},
  "geometry": {"coordinates":[-75.60595703120001,37.7877616882],"type":"Point"}
}