{
  "type": "Feature",
  "properties": {
    "iso:country":"BE",
    "sg:address":"Bergenkruislaan 8",
    "sg:city":"Destelbergen",
    "sg:classifiers":[
        {
            "category":"Education",
            "subcategory":"Special Training",
            "type":"Public Place"
        }
    ],
    "sg:phone":"+32 9 238 16 41",
    "sg:postcode":"9070",
    "sg:province":"Oost-Vlaanderen",
    "sg:tags":[
        "-",
        "processing",
        "data"
    ],
    "wof:name":"Applied Soft Service",
    "wof:placetype":"venue"
},
  "geometry": {"coordinates":[3.7967460155,51.0646476746],"type":"Point"}
}