{
  "type": "Feature",
  "properties": {
    "iso:country":"BE",
    "sg:address":"Dorpsstraat 123",
    "sg:city":"Heusden-zolder",
    "sg:orig_category":"Epiceries",
    "sg:phone":"+32 11 53 76 37",
    "sg:postcode":"3550",
    "sg:province":"Limburg",
    "wof:name":"J. Gijbels",
    "wof:placetype":"venue"
},
  "geometry": {"coordinates":[5.3187952042,51.0244178772],"type":"Point"}
}