{
  "type": "Feature",
  "properties": {
    "iso:country":"BE",
    "sg:address":"Stationsstraat 2",
    "sg:city":"Ingelmunster",
    "sg:orig_category":"Installation \u00e9lectrique r\u00e9sidentielle",
    "sg:phone":"+32 51 33 51 51",
    "sg:postcode":"8770",
    "sg:province":"West-Vlaanderen",
    "wof:name":"Fami",
    "wof:placetype":"venue"
},
  "geometry": {"coordinates":[3.2527959347,50.9205055237],"type":"Point"}
}