{
  "type": "Feature",
  "properties": {
    "iso:country":"BE",
    "sg:address":"Rue Claude-de-humyns 17",
    "sg:city":"Bastogne",
    "sg:orig_category":"Agences de relations publiques",
    "sg:phone":"+32 61 21 63 50",
    "sg:postcode":"6600",
    "sg:province":"Luxembourg",
    "wof:name":"Conseils & D\u00c9veloppements",
    "wof:placetype":"venue"
},
  "geometry": {"coordinates":[5.7116470337,50.0031089783],"type":"Point"}
}