{
  "type": "Feature",
  "properties": {
    "iso:country":"BE",
    "sg:address":"Spikkaertstraat 21",
    "sg:city":"Landen",
    "sg:orig_category":"Schoonheidssalons",
    "sg:phone":"+32 11 88 52 87",
    "sg:postcode":"3400",
    "sg:province":"Vlaams-Brabant",
    "wof:name":"Anne-marie Vergeylen",
    "wof:placetype":"venue"
},
  "geometry": {"coordinates":[5.0760741234,50.7696266174],"type":"Point"}
}