{
  "type": "Feature",
  "properties": {
    "iso:country":"BE",
    "sg:address":"Kerkstraat 15",
    "sg:city":"Houthulst",
    "sg:classifiers":[
        {
            "category":"Shopping",
            "subcategory":"Computers & Home Electronics",
            "type":"Retail Goods"
        }
    ],
    "sg:phone":"+32 51 70 39 07",
    "sg:postcode":"8650",
    "sg:province":"West-Vlaanderen",
    "sg:tags":[
        "-",
        "television",
        "radio"
    ],
    "wof:name":"Beheydt F",
    "wof:placetype":"venue"
},
  "geometry": {"coordinates":[2.9492909908,50.977935791],"type":"Point"}
}