{
  "type": "Feature",
  "properties": {
    "addr:full":"Nestor De Ti\u00c8restraat 170 Oudenaarde Oost-Vlaanderen 9700",
    "addr:housenumber":"170",
    "addr:postcode":"9700",
    "addr:street":"Nestor De Tie\u0300Restraat",
    "iso:country":"BE",
    "sg:address":"Nestor De Ti\u00c8restraat 170",
    "sg:city":"Oudenaarde",
    "sg:orig_category":"Opticiens",
    "sg:phone":"+32 55 31 61 92",
    "sg:postcode":"9700",
    "sg:province":"Oost-Vlaanderen",
    "wof:name":"Optiek Anne",
    "wof:placetype":"venue"
},
  "geometry": {"coordinates":[3.6211550236,50.8695678711],"type":"Point"}
}