{
  "type": "Feature",
  "properties": {
    "addr:full":"Pronkenbergstraat 29b Kontich Antwerpen 2550",
    "addr:housenumber":"29b",
    "addr:postcode":"2550",
    "addr:street":"Pronkenbergstraat",
    "iso:country":"BE",
    "sg:address":"Pronkenbergstraat 29b",
    "sg:city":"Kontich",
    "sg:classifiers":[
        {
            "category":"Professional",
            "subcategory":"Art Services",
            "type":"Services"
        }
    ],
    "sg:phone":"+32 3 457 42 38",
    "sg:postcode":"2550",
    "sg:province":"Antwerpen",
    "sg:tags":[
        "photographer"
    ],
    "wof:name":"Van Leijden R & V Nv",
    "wof:placetype":"venue"
},
  "geometry": {"coordinates":[4.4674301147,51.1273384094],"type":"Point"}
}