{
  "type": "Feature",
  "properties": {
    "addr:full":"Rue Des Fonds 31 Braine-le-ch\u00e2teau Brabant Wallon 1440",
    "addr:housenumber":"31",
    "addr:postcode":"1440",
    "addr:street":"Rue Des Fonds",
    "iso:country":"BE",
    "sg:address":"Rue Des Fonds 31",
    "sg:city":"Braine-le-ch\u00e2teau",
    "sg:classifiers":[
        {
            "category":"Building & Trades",
            "subcategory":"Electrical",
            "type":"Services"
        }
    ],
    "sg:phone":"+32 2 366 14 31",
    "sg:postcode":"1440",
    "sg:province":"Brabant Wallon",
    "sg:tags":[
        "-",
        "electric",
        "contractor"
    ],
    "wof:name":"Mosselman M",
    "wof:placetype":"venue"
},
  "geometry": {"coordinates":[4.2794938087,50.6889190674],"type":"Point"}
}