{
  "type": "Feature",
  "properties": {
    "addr:full":"Waterstraat 25a Merelbeke (groot) Oost-Vlaanderen 9820",
    "addr:housenumber":"25a",
    "addr:postcode":"9820",
    "addr:street":"Waterstraat;Groot Oost-Vlaanderen",
    "iso:country":"BE",
    "sg:address":"Waterstraat 25a",
    "sg:city":"Merelbeke (groot)",
    "sg:orig_category":"Divers amusement HERSTELLING ELEKTRISCHE HUISHOUDAPPARATEN Huishoudapparaten, televisies and radio's",
    "sg:phone":"+32 9 232 03 55",
    "sg:postcode":"9820",
    "sg:province":"Oost-Vlaanderen",
    "wof:name":"Swing",
    "wof:placetype":"venue"
},
  "geometry": {"coordinates":[3.7491691113,51.0015716553],"type":"Point"}
}