{
  "type": "Feature",
  "properties": {
    "addr:full":"Rue De La Clef 6 Fl\u00c9ron Li\u00e8ge 4621",
    "addr:housenumber":"6",
    "addr:postcode":"4621",
    "addr:street":"Rue De La Clef",
    "iso:country":"BE",
    "sg:address":"Rue De La Clef 6",
    "sg:city":"Fl\u00c9ron",
    "sg:orig_category":"Drukkerijen and copyshops",
    "sg:phone":"+32 4 355 39 35",
    "sg:postcode":"4621",
    "sg:province":"Li\u00e8ge",
    "wof:name":"Copy-center",
    "wof:placetype":"venue"
},
  "geometry": {"coordinates":[5.6890239716,50.6147766113],"type":"Point"}
}