{
  "type": "Feature",
  "properties": {
    "addr:full":"Abeelstraat 19 Ronse/renaix Oost-Vlaanderen 9600",
    "addr:housenumber":"19",
    "addr:postcode":"9600",
    "addr:street":"Abeelstraat",
    "iso:country":"BE",
    "sg:address":"Abeelstraat 19",
    "sg:city":"Ronse/renaix",
    "sg:orig_category":"Tweedehandsgoederen",
    "sg:phone":"+32 55 20 61 77",
    "sg:postcode":"9600",
    "sg:province":"Oost-Vlaanderen",
    "wof:name":"Clothing Box",
    "wof:placetype":"venue"
},
  "geometry": {"coordinates":[3.5999310017,50.7452774048],"type":"Point"}
}