{
  "type": "Feature",
  "properties": {
    "addr:full":"L.vanderkelenstraat 28 Leuven Vlaams-Brabant 3000",
    "addr:housenumber":"28",
    "addr:postcode":"3000",
    "addr:street":"L.Vanderkelenstraat",
    "iso:country":"BE",
    "sg:address":"L.vanderkelenstraat 28",
    "sg:city":"Leuven",
    "sg:orig_category":"Biblioth\u00e8ques and archives publiques",
    "sg:phone":"+32 16 22 65 22",
    "sg:postcode":"3000",
    "sg:province":"Vlaams-Brabant",
    "wof:name":"Hoofdbibliotheek",
    "wof:placetype":"venue"
},
  "geometry": {"coordinates":[4.7048640251,50.8787193298],"type":"Point"}
}