{
  "type": "Feature",
  "properties": {
    "addr:full":"Turnhoutsebaan 279 Wijnegem Antwerpen 2110",
    "addr:housenumber":"279",
    "addr:postcode":"2110",
    "addr:street":"Turnhoutsebaan",
    "iso:country":"BE",
    "sg:address":"Turnhoutsebaan 279",
    "sg:city":"Wijnegem",
    "sg:orig_category":"Huisdieren and benodigdheden Royal Canin",
    "sg:phone":"+32 3 353 16 54",
    "sg:postcode":"2110",
    "sg:province":"Antwerpen",
    "wof:name":"Vermeulen-brughmans",
    "wof:placetype":"venue"
},
  "geometry": {"coordinates":[4.518184185,51.2267341614],"type":"Point"}
}