{
  "type": "Feature",
  "properties": {
    "iso:country":"BE",
    "sg:address":"Zwijnaardsesteenweg 104",
    "sg:city":"Gent",
    "sg:classifiers":[
        {
            "category":"Restaurant",
            "type":"Food & Drink"
        }
    ],
    "sg:phone":"+32 9 221 87 32",
    "sg:postcode":"9000",
    "sg:province":"Oost-Vlaanderen",
    "sg:tags":[
        "caf\u00e9s"
    ],
    "wof:name":"Ette Ibibio Culture",
    "wof:placetype":"venue"
},
  "geometry": {"coordinates":[3.7251470089,51.033996582],"type":"Point"}
}