{
  "type": "Feature",
  "properties": {
    "iso:country":"BE",
    "sg:address":"Beekstraat 62",
    "sg:city":"Kortrijk",
    "sg:orig_category":"Non-Classified Establishments",
    "sg:phone":"+32 56 22 65 85",
    "sg:postcode":"8500",
    "sg:province":"West-Vlaanderen",
    "wof:name":"Bts Jewels Bvba",
    "wof:placetype":"venue"
},
  "geometry": {"coordinates":[3.2849841118,50.8190002441],"type":"Point"}
}