{
  "type": "Feature",
  "properties": {
    "addr:full":"Aveschoot 7 Kaprijke Oost-Vlaanderen 9971",
    "addr:housenumber":"7",
    "addr:postcode":"9971",
    "addr:street":"Aveschoot",
    "iso:country":"BE",
    "sg:address":"Aveschoot 7",
    "sg:city":"Kaprijke",
    "sg:orig_category":"M\u00e9decins and sp\u00e9cialistes",
    "sg:phone":"+32 9 377 81 82",
    "sg:postcode":"9971",
    "sg:province":"Oost-Vlaanderen",
    "wof:name":"M. Cattoir",
    "wof:placetype":"venue"
},
  "geometry": {"coordinates":[3.6294469833,51.1938362122],"type":"Point"}
}