{
  "type": "Feature",
  "properties": {
    "addr:full":"Rue Neuve 57 Merbes-le-ch\u00e2teau (labuissi\u00e8re) Hainaut 6567",
    "addr:housenumber":"57",
    "addr:postcode":"6567",
    "addr:street":"Rue Neuve",
    "iso:country":"BE",
    "sg:address":"Rue Neuve 57",
    "sg:city":"Merbes-le-ch\u00e2teau (labuissi\u00e8re)",
    "sg:classifiers":[
        {
            "category":"Airport",
            "subcategory":"International",
            "type":"Transportation"
        }
    ],
    "sg:phone":"+32 71 55 31 13",
    "sg:postcode":"6567",
    "sg:province":"Hainaut",
    "sg:tags":[
        "-",
        "transport"
    ],
    "wof:name":"Douillez Fils Transports",
    "wof:placetype":"venue"
},
  "geometry": {"coordinates":[4.1861138344,50.3150863647],"type":"Point"}
}