{
  "type": "Feature",
  "properties": {
    "iso:country":"BE",
    "sg:address":"Hertogstraat 112",
    "sg:city":"Leuven (heverlee)",
    "sg:classifiers":[
        {
            "category":"Health Services",
            "subcategory":"Health Practitioner",
            "type":"Services"
        }
    ],
    "sg:phone":"+32 16 40 71 93",
    "sg:postcode":"3001",
    "sg:province":"Vlaams-Brabant",
    "sg:tags":[
        "physiotherapist"
    ],
    "wof:name":"Moons Jan",
    "wof:placetype":"venue"
},
  "geometry": {"coordinates":[4.6980891228,50.8602981567],"type":"Point"}
}