{
  "type": "Feature",
  "properties": {
    "addr:full":"Rue Paul Janson 1 Anderlues Hainaut 6150",
    "addr:housenumber":"1",
    "addr:postcode":"6150",
    "addr:street":"Rue Paul Janson",
    "iso:country":"BE",
    "sg:address":"Rue Paul Janson 1",
    "sg:city":"Anderlues",
    "sg:orig_category":"Banques and organismes de cr\u00e9dit",
    "sg:phone":"+32 71 54 88 60",
    "sg:postcode":"6150",
    "sg:province":"Hainaut",
    "wof:name":"Bbl",
    "wof:placetype":"venue"
},
  "geometry": {"coordinates":[4.2728881836,50.4058151245],"type":"Point"}
}