{
  "type": "Feature",
  "properties": {
    "addr:full":"St.eloois-winkelsestraat 83ba Roeselare West-Vlaanderen 8800",
    "addr:housenumber":"83ba",
    "addr:postcode":"8800",
    "addr:street":"St.Eloois-Winkelsestraat",
    "iso:country":"BE",
    "sg:address":"St.eloois-winkelsestraat 83ba",
    "sg:city":"Roeselare",
    "sg:orig_category":"Woningbouw",
    "sg:phone":"+32 51 20 05 11",
    "sg:postcode":"8800",
    "sg:province":"West-Vlaanderen",
    "wof:name":"Cool W.",
    "wof:placetype":"venue"
},
  "geometry": {"coordinates":[3.1606030464,50.9084968567],"type":"Point"}
}