{
  "type": "Feature",
  "properties": {
    "iso:country":"BE",
    "sg:address":"Kroondreef 28",
    "sg:city":"Jabbeke",
    "sg:orig_category":"Woningbouw",
    "sg:phone":"+32 50 81 63 79",
    "sg:postcode":"8490",
    "sg:province":"West-Vlaanderen",
    "wof:name":"Benny Rommelaere",
    "wof:placetype":"venue"
},
  "geometry": {"coordinates":[3.1011180878,51.1811141968],"type":"Point"}
}