{
  "type": "Feature",
  "properties": {
    "addr:full":"Rue Achille Debacker 20 Mouscron Hainaut 7700",
    "addr:housenumber":"20",
    "addr:postcode":"7700",
    "addr:street":"Rue Achille Debacker",
    "iso:country":"BE",
    "sg:address":"Rue Achille Debacker 20",
    "sg:city":"Mouscron",
    "sg:classifiers":[
        {
            "category":"Health Services",
            "subcategory":"Health Practitioner",
            "type":"Services"
        }
    ],
    "sg:phone":"+32 56 34 68 76",
    "sg:postcode":"7700",
    "sg:province":"Hainaut",
    "sg:tags":[
        "physiotherapist"
    ],
    "wof:name":"De Houck G",
    "wof:placetype":"venue"
},
  "geometry": {"coordinates":[3.2232439518,50.7424354553],"type":"Point"}
}