{
  "type": "Feature",
  "properties": {
    "iso:country":"BE",
    "sg:address":"Houtstraat 49",
    "sg:city":"Gingelom",
    "sg:orig_category":"Boucheries",
    "sg:phone":"+32 11 48 23 43",
    "sg:postcode":"3890",
    "sg:province":"Limburg",
    "wof:name":"Johan Tossens",
    "wof:placetype":"venue"
},
  "geometry": {"coordinates":[5.2106881142,50.7360877991],"type":"Point"}
}