{
  "type": "Feature",
  "properties": {
    "addr:full":"Rue Englebert Lescrenier 16 Awans (oth\u00e9e) Li\u00e8ge 4340",
    "addr:housenumber":"16",
    "addr:postcode":"4340",
    "addr:street":"Rue Englebert Lescrenier;Othe\u0301E",
    "iso:country":"BE",
    "sg:address":"Rue Englebert Lescrenier 16",
    "sg:city":"Awans (oth\u00e9e)",
    "sg:classifiers":[
        {
            "category":"Social Services",
            "type":"Services"
        }
    ],
    "sg:phone":"+32 4 257 79 28",
    "sg:postcode":"4340",
    "sg:province":"Li\u00e8ge",
    "wof:name":"C.i.p.a.d Asbl",
    "wof:placetype":"venue"
},
  "geometry": {"coordinates":[5.4693088531,50.7092323303],"type":"Point"}
}