{
  "type": "Feature",
  "properties": {
    "addr:full":"Gentsebaan 57 Sint-niklaas Oost-Vlaanderen 9100",
    "addr:housenumber":"57",
    "addr:postcode":"9100",
    "addr:street":"Gentsebaan",
    "iso:country":"BE",
    "sg:address":"Gentsebaan 57",
    "sg:city":"Sint-niklaas",
    "sg:orig_category":"Herstellingen and onderhoud van auto's Voertuigen",
    "sg:phone":"+32 3 776 47 28",
    "sg:postcode":"9100",
    "sg:province":"Oost-Vlaanderen",
    "wof:name":"Garage Euro Ster",
    "wof:placetype":"venue"
},
  "geometry": {"coordinates":[4.1267991066,51.1494598389],"type":"Point"}
}