{
  "type": "Feature",
  "properties": {
    "addr:full":"Begijnhof 41 Aalst Oost-Vlaanderen 9300",
    "addr:housenumber":"41",
    "addr:postcode":"9300",
    "addr:street":"Begijnhof",
    "iso:country":"BE",
    "sg:address":"Begijnhof 41",
    "sg:city":"Aalst",
    "sg:orig_category":"Location de logements sociaux",
    "sg:phone":"+32 53 21 56 80",
    "sg:postcode":"9300",
    "sg:province":"Oost-Vlaanderen",
    "wof:name":"C.v. Voor Huisvesting",
    "wof:placetype":"venue"
},
  "geometry": {"coordinates":[4.0448160172,50.9356193542],"type":"Point"}
}