{
  "type": "Feature",
  "properties": {
    "addr:full":"Tommenstraat 17 Hoeselt Limburg 3730",
    "addr:housenumber":"17",
    "addr:postcode":"3730",
    "addr:street":"Tommenstraat",
    "iso:country":"BE",
    "sg:address":"Tommenstraat 17",
    "sg:city":"Hoeselt",
    "sg:orig_category":"Fruitteelt Rundveehouders",
    "sg:phone":"+32 12 39 42 02",
    "sg:postcode":"3730",
    "sg:province":"Limburg",
    "wof:name":"Joseph Caproens",
    "wof:placetype":"venue"
},
  "geometry": {"coordinates":[5.4506511688,50.8253974915],"type":"Point"}
}