{
  "type": "Feature",
  "properties": {
    "addr:full":"Avenue Des Platanes 93 Herve Li\u00e8ge 4650",
    "addr:housenumber":"93",
    "addr:postcode":"4650",
    "addr:street":"Avenue Des Platanes",
    "iso:country":"BE",
    "sg:address":"Avenue Des Platanes 93",
    "sg:city":"Herve",
    "sg:orig_category":"IJzerwaren, bouw- and verfmaterialen MEUBELONTWERP AND -INSTALLATIE",
    "sg:phone":"+32 87 31 47 32",
    "sg:postcode":"4650",
    "sg:province":"Li\u00e8ge",
    "wof:name":"Constant Cuisines Equip\u00c9s",
    "wof:placetype":"venue"
},
  "geometry": {"coordinates":[5.8121972084,50.6077880859],"type":"Point"}
}