{
  "type": "Feature",
  "properties": {
    "iso:country":"BE",
    "sg:address":"Weg Naar Opoeteren 1",
    "sg:city":"Opglabbeek",
    "sg:classifiers":[
        {
            "category":"Personal",
            "subcategory":"Beauty Salon",
            "type":"Services"
        }
    ],
    "sg:phone":"+32 89 85 35 72",
    "sg:postcode":"3660",
    "sg:province":"Limburg",
    "sg:tags":[
        "lady",
        "-",
        "hairdressing"
    ],
    "wof:name":"Susy",
    "wof:placetype":"venue"
},
  "geometry": {"coordinates":[5.5859680176,51.0443115234],"type":"Point"}
}