{
  "type": "Feature",
  "properties": {
    "addr:full":"Chauss\u00e9e De Neerstalle 495 Bruxelles (uccle) Bruxelles-Capitale 1180",
    "addr:housenumber":"495",
    "addr:postcode":"1180",
    "addr:street":"Chausse\u0301E De Neerstalle",
    "iso:country":"BE",
    "sg:address":"Chauss\u00e9e De Neerstalle 495",
    "sg:city":"Bruxelles (uccle)",
    "sg:classifiers":[
        {
            "category":"Health Services",
            "subcategory":"Health Practitioner",
            "type":"Services"
        }
    ],
    "sg:phone":"+32 2 376 34 25",
    "sg:postcode":"1180",
    "sg:province":"Bruxelles-Capitale",
    "sg:tags":[
        "physiotherapist"
    ],
    "wof:name":"Trigaux R",
    "wof:placetype":"venue"
},
  "geometry": {"coordinates":[4.3208518028,50.7967605591],"type":"Point"}
}