{
  "type": "Feature",
  "properties": {
    "addr:full":"Kerkkouter 42 Oudenaarde Oost-Vlaanderen 9700",
    "addr:housenumber":"42",
    "addr:postcode":"9700",
    "addr:street":"Kerkkouter",
    "iso:country":"BE",
    "sg:address":"Kerkkouter 42",
    "sg:city":"Oudenaarde",
    "sg:classifiers":[
        {
            "category":"Social Services",
            "type":"Services"
        }
    ],
    "sg:phone":"+32 55 30 96 44",
    "sg:postcode":"9700",
    "sg:province":"Oost-Vlaanderen",
    "wof:name":"Buurtinformatie Netwerken",
    "wof:placetype":"venue"
},
  "geometry": {"coordinates":[3.596544981,50.8539962769],"type":"Point"}
}