{
  "type": "Feature",
  "properties": {
    "addr:full":"Pl A Favresse 75 La Hulpe Brabant Wallon 1310",
    "addr:housenumber":"75",
    "addr:postcode":"1310",
    "addr:street":"Pl;Favresse",
    "iso:country":"BE",
    "sg:address":"Pl A Favresse 75",
    "sg:city":"La Hulpe",
    "sg:orig_category":"Drukkerijen and copyshops",
    "sg:phone":"+32 2 654 02 87",
    "sg:postcode":"1310",
    "sg:province":"Brabant Wallon",
    "wof:name":"Arteplan",
    "wof:placetype":"venue"
},
  "geometry": {"coordinates":[4.4877438545,50.7310256958],"type":"Point"}
}