{
  "type": "Feature",
  "properties": {
    "addr:full":"Meersstraat 61 Gent Oost-Vlaanderen 9000",
    "addr:housenumber":"61",
    "addr:postcode":"9000",
    "addr:street":"Meersstraat;Oost-Vlaanderen",
    "iso:country":"BE",
    "sg:address":"Meersstraat 61",
    "sg:city":"Gent",
    "sg:classifiers":[
        {
            "category":"Professional",
            "subcategory":"Engineering",
            "type":"Services"
        }
    ],
    "sg:phone":"+32 9 221 73 13",
    "sg:postcode":"9000",
    "sg:province":"Oost-Vlaanderen",
    "sg:tags":[
        "-"
    ],
    "wof:name":"Vsi Planning",
    "wof:placetype":"venue"
},
  "geometry": {"coordinates":[3.714963913,51.0407028198],"type":"Point"}
}