{
  "type": "Feature",
  "properties": {
    "addr:full":"Biesstraat 2 Zwalm Oost-Vlaanderen 9636",
    "addr:housenumber":"2",
    "addr:postcode":"9636",
    "addr:street":"Biesstraat;Oost-Vlaanderen",
    "iso:country":"BE",
    "sg:address":"Biesstraat 2",
    "sg:city":"Zwalm",
    "sg:orig_category":"Slagers",
    "sg:phone":"+32 55 49 91 32",
    "sg:postcode":"9636",
    "sg:province":"Oost-Vlaanderen",
    "wof:name":"Danyvan",
    "wof:placetype":"venue"
},
  "geometry": {"coordinates":[3.6893730164,50.8871650696],"type":"Point"}
}