{
  "type": "Feature",
  "properties": {
    "addr:full":"Kalenbergstraat 23 Dilbeek Vlaams-Brabant 1700",
    "addr:housenumber":"23",
    "addr:postcode":"1700",
    "addr:street":"Kalenbergstraat",
    "iso:country":"BE",
    "sg:address":"Kalenbergstraat 23",
    "sg:city":"Dilbeek",
    "sg:classifiers":[
        {
            "category":"Health Services",
            "subcategory":"Dentist",
            "type":"Services"
        }
    ],
    "sg:phone":"+32 2 569 31 83",
    "sg:postcode":"1700",
    "sg:province":"Vlaams-Brabant",
    "wof:name":"De Vos Marleen",
    "wof:placetype":"venue"
},
  "geometry": {"coordinates":[4.2594780922,50.8422851562],"type":"Point"}
}