{
  "type": "Feature",
  "properties": {
    "iso:country":"BE",
    "sg:address":"Stationsstraat 25",
    "sg:city":"Geel",
    "sg:orig_category":"RESTAURANTS: CAF\u00c9S",
    "sg:phone":"+32 14 58 64 92",
    "sg:postcode":"2440",
    "sg:province":"Antwerpen",
    "wof:name":"Taverne Avenue",
    "wof:placetype":"venue"
},
  "geometry": {"coordinates":[4.9905028343,51.1634674072],"type":"Point"}
}