{
  "type": "Feature",
  "properties": {
    "addr:full":"Jacob Jacobstraat 11 Antwerpen Antwerpen 2018",
    "addr:housenumber":"11",
    "addr:postcode":"2018",
    "addr:street":"Jacob Jacobstraat",
    "iso:country":"BE",
    "sg:address":"Jacob Jacobstraat 11",
    "sg:city":"Antwerpen",
    "sg:orig_category":"Bijouteries and horlogeries",
    "sg:phone":"+32 3 226 51 51",
    "sg:postcode":"2018",
    "sg:province":"Antwerpen",
    "wof:name":"De Luxe Juwelen",
    "wof:placetype":"venue"
},
  "geometry": {"coordinates":[4.4183998108,51.2112503052],"type":"Point"}
}