{
  "type": "Feature",
  "properties": {
    "addr:full":"Heizijdestraat 10 Lebbeke Oost-Vlaanderen 9280",
    "addr:housenumber":"10",
    "addr:postcode":"9280",
    "addr:street":"Heizijdestraat",
    "iso:country":"BE",
    "sg:address":"Heizijdestraat 10",
    "sg:city":"Lebbeke",
    "sg:classifiers":[
        {
            "category":"Utilities",
            "subcategory":"Natural Gas",
            "type":"Services"
        }
    ],
    "sg:phone":"+32 52 41 00 21",
    "sg:postcode":"9280",
    "sg:province":"Oost-Vlaanderen",
    "sg:tags":[
        "hide",
        "skin"
    ],
    "wof:name":"Hofmans & Zn Nv",
    "wof:placetype":"venue"
},
  "geometry": {"coordinates":[4.1486010551,51.0009498596],"type":"Point"}
}