{
  "type": "Feature",
  "properties": {
    "iso:country":"BE",
    "sg:address":"Hoeledensesteenweg 2",
    "sg:city":"Glabbeek",
    "sg:orig_category":"Eleveurs and marchands de porcs",
    "sg:phone":"+32 16 77 91 11",
    "sg:postcode":"3380",
    "sg:province":"Vlaams-Brabant",
    "wof:name":"Franciscus Kempeneers",
    "wof:placetype":"venue"
},
  "geometry": {"coordinates":[4.9762988091,50.8726158142],"type":"Point"}
}