{
  "type": "Feature",
  "properties": {
    "iso:country":"BE",
    "sg:address":"Rue Du Bon Pasteur 55b19",
    "sg:city":"Evere/evere",
    "sg:orig_category":"Administration d'immeubles",
    "sg:phone":"+32 2 245 11 00",
    "sg:postcode":"1140",
    "sg:province":"Bruxelles-Capitale",
    "wof:name":"Dista",
    "wof:placetype":"venue"
},
  "geometry": {"coordinates":[4.4022321701,50.8798446655],"type":"Point"}
}