{
  "type": "Feature",
  "properties": {
    "iso:country":"BE",
    "sg:address":"Staatsbaan 111",
    "sg:city":"Halen",
    "sg:orig_category":"V\u00e9hicules automobiles",
    "sg:phone":"+32 13 44 34 43",
    "sg:postcode":"3545",
    "sg:province":"Limburg",
    "wof:name":"Autohandel Kennes",
    "wof:placetype":"venue"
},
  "geometry": {"coordinates":[5.0849227905,50.9610786438],"type":"Point"}
}