{
  "type": "Feature",
  "properties": {
    "addr:full":"Rue Large 194 Trooz Li\u00e8ge 4870",
    "addr:housenumber":"194",
    "addr:postcode":"4870",
    "addr:street":"Rue Large",
    "iso:country":"BE",
    "sg:address":"Rue Large 194",
    "sg:city":"Trooz",
    "sg:orig_category":"V\u00eatements pour Hommes. V\u00eatements pour Dames",
    "sg:phone":"+32 87 26 81 25",
    "sg:postcode":"4870",
    "sg:province":"Li\u00e8ge",
    "wof:name":"Georges Dimblon",
    "wof:placetype":"venue"
},
  "geometry": {"coordinates":[5.6734352112,50.5785331726],"type":"Point"}
}