{
  "type": "Feature",
  "properties": {
    "iso:country":"BE",
    "sg:address":"122",
    "sg:city":"Geraardsbergsestraat 9300 Aalst",
    "sg:classifiers":[
        {
            "category":"Professional",
            "subcategory":"Engineering",
            "type":"Services"
        }
    ],
    "sg:phone":"+32 53 21 38 38",
    "sg:postcode":"122",
    "sg:tags":[
        "machine",
        "-",
        "mechanical"
    ],
    "wof:name":"Bouwrama Nv",
    "wof:placetype":"venue"
},
  "geometry": {"coordinates":[4.0356340408,50.9299049377],"type":"Point"}
}