{
  "type": "Feature",
  "properties": {
    "iso:country":"BE",
    "sg:address":"Mieksebaan 148",
    "sg:city":"Brecht",
    "sg:orig_category":"Diverse bouwafwerking and reiniging Plaatsen van vloer- and muurbekleding Schilders",
    "sg:phone":"+32 3 633 16 85",
    "sg:postcode":"2960",
    "sg:province":"Antwerpen",
    "wof:name":"Paint Service",
    "wof:placetype":"venue"
},
  "geometry": {"coordinates":[4.5813069344,51.3250999451],"type":"Point"}
}