{
  "type": "Feature",
  "properties": {
    "addr:full":"Snepkaai 2 Gent Oost-Vlaanderen 9000",
    "addr:housenumber":"2",
    "addr:postcode":"9000",
    "addr:street":"Snepkaai;Oost-Vlaanderen",
    "iso:country":"BE",
    "sg:address":"Snepkaai 2",
    "sg:city":"Gent",
    "sg:classifiers":[
        {
            "category":"Cafe",
            "type":"Food & Drink"
        }
    ],
    "sg:phone":"+32 9 220 21 02",
    "sg:postcode":"9000",
    "sg:province":"Oost-Vlaanderen",
    "sg:tags":[
        "caf\u00e9s"
    ],
    "wof:name":"Caf\u00c9 Leiezicht",
    "wof:placetype":"venue"
},
  "geometry": {"coordinates":[3.6872739792,51.0339622498],"type":"Point"}
}