{
  "type": "Feature",
  "properties": {
    "iso:country":"BE",
    "sg:address":"Slachthuisstraat 4a",
    "sg:city":"Eeklo",
    "sg:orig_category":"Non-Classified Establishments",
    "sg:phone":"+32 9 377 32 15",
    "sg:postcode":"9900",
    "sg:province":"Oost-Vlaanderen",
    "wof:name":"Decolux",
    "wof:placetype":"venue"
},
  "geometry": {"coordinates":[3.5483009815,51.1833229065],"type":"Point"}
}