{
  "type": "Feature",
  "properties": {
    "iso:country":"BE",
    "sg:address":"Segherslaan 97",
    "sg:city":"Koekelberg",
    "sg:orig_category":"Artsen and specialisten",
    "sg:phone":"+32 2 414 45 08",
    "sg:postcode":"1081",
    "sg:province":"Bruxelles-Capitale",
    "wof:name":"Mario Moreno Reyes",
    "wof:placetype":"venue"
},
  "geometry": {"coordinates":[4.320306778,50.8645820618],"type":"Point"}
}