{
  "type": "Feature",
  "properties": {
    "addr:full":"Rue De L'aub\u00e9pine 15 Beauraing Namur 5570",
    "addr:housenumber":"15",
    "addr:postcode":"5570",
    "addr:street":"Rue De L'Aube \u0301Pine",
    "iso:country":"BE",
    "sg:address":"Rue De L'aub\u00e9pine 15",
    "sg:city":"Beauraing",
    "sg:classifiers":[
        {
            "category":"Bars & Pubs",
            "type":"Food & Drink"
        }
    ],
    "sg:phone":"+32 82 71 30 61",
    "sg:postcode":"5570",
    "sg:province":"Namur",
    "wof:name":"Esplanade (l')",
    "wof:placetype":"venue"
},
  "geometry": {"coordinates":[4.9609851837,50.1091346741],"type":"Point"}
}