{
  "type": "Feature",
  "properties": {
    "addr:full":"Kammerstraat 11 Gent Oost-Vlaanderen 9000",
    "addr:housenumber":"11",
    "addr:postcode":"9000",
    "addr:street":"Kammerstraat;Oost-Vlaanderen",
    "iso:country":"BE",
    "sg:address":"Kammerstraat 11",
    "sg:city":"Gent",
    "sg:classifiers":[
        {
            "category":"Shopping",
            "subcategory":"Jewelry",
            "type":"Retail Goods"
        }
    ],
    "sg:phone":"+32 9 233 42 17",
    "sg:postcode":"9000",
    "sg:province":"Oost-Vlaanderen",
    "sg:tags":[
        "jeweller",
        "-"
    ],
    "wof:name":"Adriaenssens I",
    "wof:placetype":"venue"
},
  "geometry": {"coordinates":[3.7266910076,51.0562057495],"type":"Point"}
}