{
  "type": "Feature",
  "properties": {
    "addr:full":"Kleiputtendreef 15 Poperinge West-Vlaanderen 8970",
    "addr:housenumber":"15",
    "addr:postcode":"8970",
    "addr:street":"Kleiputtendreef",
    "iso:country":"BE",
    "sg:address":"Kleiputtendreef 15",
    "sg:city":"Poperinge",
    "sg:orig_category":"Installation \u00e9lectrique r\u00e9sidentielle",
    "sg:phone":"+32 57 33 98 28",
    "sg:postcode":"8970",
    "sg:province":"West-Vlaanderen",
    "wof:name":"Ronny Vermeulen",
    "wof:placetype":"venue"
},
  "geometry": {"coordinates":[2.7285339832,50.8462028503],"type":"Point"}
}