{
  "type": "Feature",
  "properties": {
    "addr:full":"J.-b. Carnoyplein 22 Sint-lambrechts-woluwe/woluwe-saint-lambert Bruxelles-Capitale 1200",
    "addr:housenumber":"22",
    "addr:postcode":"1200",
    "addr:street":"J.-B. Carnoyplein",
    "iso:country":"BE",
    "sg:address":"J.-b. Carnoyplein 22",
    "sg:city":"Sint-lambrechts-woluwe/woluwe-saint-lambert",
    "sg:orig_category":"Levering aan huis restaurants Restaurants",
    "sg:phone":"+32 2 772 62 63",
    "sg:postcode":"1200",
    "sg:province":"Bruxelles-Capitale",
    "wof:name":"Snack-bar Pick & Eat",
    "wof:placetype":"venue"
},
  "geometry": {"coordinates":[4.4160528183,50.8516426086],"type":"Point"}
}