{
  "type": "Feature",
  "properties": {
    "addr:full":"Avenue Facult\u00c9-d'agronomie 12 Gembloux Namur 5030",
    "addr:housenumber":"12",
    "addr:postcode":"5030",
    "addr:street":"Avenue Faculte\u0301-D ' Agronomie;Namur",
    "iso:country":"BE",
    "sg:address":"Avenue Facult\u00c9-d'agronomie 12",
    "sg:city":"Gembloux",
    "sg:orig_category":"Banques and organismes de cr\u00e9dit",
    "sg:phone":"+32 81 61 21 46",
    "sg:postcode":"5030",
    "sg:province":"Namur",
    "wof:name":"Dexia",
    "wof:placetype":"venue"
},
  "geometry": {"coordinates":[4.6969089508,50.5646591187],"type":"Point"}
}