{
  "type": "Feature",
  "properties": {
    "addr:full":"Burgemeester R. Vandemaeleplein 2 Lendelede West-Vlaanderen 8860",
    "addr:housenumber":"2",
    "addr:postcode":"8860",
    "addr:street":"Burgemeester R. Vandemaeleplein",
    "iso:country":"BE",
    "sg:address":"Burgemeester R. Vandemaeleplein 2",
    "sg:city":"Lendelede",
    "sg:classifiers":[
        {
            "category":"Personal",
            "subcategory":"Beauty Salon",
            "type":"Services"
        }
    ],
    "sg:phone":"+32 51 30 36 53",
    "sg:postcode":"8860",
    "sg:province":"West-Vlaanderen",
    "sg:tags":[
        "lady",
        "-",
        "hairdressing"
    ],
    "wof:name":"Mf Coiffure",
    "wof:placetype":"venue"
},
  "geometry": {"coordinates":[3.2373230457,50.8853721619],"type":"Point"}
}