{
  "type": "Feature",
  "properties": {
    "addr:full":"Molenbergstraat 1 Rumst Antwerpen 2840",
    "addr:housenumber":"1",
    "addr:postcode":"2840",
    "addr:street":"Molenbergstraat",
    "iso:country":"BE",
    "sg:address":"Molenbergstraat 1",
    "sg:city":"Rumst",
    "sg:classifiers":[
        {
            "category":"Personal",
            "subcategory":"Beauty Salon",
            "type":"Services"
        }
    ],
    "sg:phone":"+32 3 888 03 72",
    "sg:postcode":"2840",
    "sg:province":"Antwerpen",
    "wof:name":"Huys I",
    "wof:placetype":"venue"
},
  "geometry": {"coordinates":[4.4232602119,51.0781402588],"type":"Point"}
}