{
  "type": "Feature",
  "properties": {
    "iso:country":"BE",
    "sg:address":"De Burburestraat 14",
    "sg:city":"Antwerpen",
    "sg:orig_category":"Rev\u00eatements de sols and murs",
    "sg:phone":"+32 3 248 52 96",
    "sg:postcode":"2000",
    "sg:province":"Antwerpen",
    "wof:name":"Arjan Van Herk",
    "wof:placetype":"venue"
},
  "geometry": {"coordinates":[4.3913969994,51.2091293335],"type":"Point"}
}