{
  "type": "Feature",
  "properties": {
    "addr:full":"Avenue Frans Courtens 110 Bruxelles (schaerbeek) Bruxelles-Capitale 1030",
    "addr:housenumber":"110",
    "addr:postcode":"1030",
    "addr:street":"Avenue Frans Courtens",
    "iso:country":"BE",
    "sg:address":"Avenue Frans Courtens 110",
    "sg:city":"Bruxelles (schaerbeek)",
    "sg:classifiers":[
        {
            "category":"Building & Trades",
            "subcategory":"Plumbing",
            "type":"Services"
        }
    ],
    "sg:phone":"+32 2 705 67 66",
    "sg:postcode":"1030",
    "sg:province":"Bruxelles-Capitale",
    "sg:tags":[
        "contractor"
    ],
    "wof:name":"Denie E",
    "wof:placetype":"venue"
},
  "geometry": {"coordinates":[4.4028191566,50.8594779968],"type":"Point"}
}