{
  "type": "Feature",
  "properties": {
    "addr:full":"Grote Markt 51 Turnhout Antwerpen 2300",
    "addr:housenumber":"51",
    "addr:postcode":"2300",
    "addr:street":"Grote Markt",
    "iso:country":"BE",
    "sg:address":"Grote Markt 51",
    "sg:city":"Turnhout",
    "sg:orig_category":"Opticiens",
    "sg:phone":"+32 14 41 14 60",
    "sg:postcode":"2300",
    "sg:province":"Antwerpen",
    "wof:name":"Meeussen P.",
    "wof:placetype":"venue"
},
  "geometry": {"coordinates":[4.947865963,51.3228111267],"type":"Point"}
}