{
  "type": "Feature",
  "properties": {
    "iso:country":"BE",
    "sg:address":"Hoogstraat 71",
    "sg:city":"Tisselt",
    "sg:orig_category":"Messageries",
    "sg:phone":"+32 3 866 54 31",
    "sg:postcode":"2830",
    "sg:province":"Antwerpen",
    "wof:name":"Steenackers",
    "wof:placetype":"venue"
},
  "geometry": {"coordinates":[4.3621220589,51.0311431885],"type":"Point"}
}