{
  "type": "Feature",
  "properties": {
    "addr:full":"Beekstraat 12 Kortenberg Vlaams-Brabant 3070",
    "addr:housenumber":"12",
    "addr:postcode":"3070",
    "addr:street":"Beekstraat;Vlaams-Brabant",
    "iso:country":"BE",
    "sg:address":"Beekstraat 12",
    "sg:city":"Kortenberg",
    "sg:classifiers":[
        {
            "category":"Personal",
            "subcategory":"Beauty Salon",
            "type":"Services"
        }
    ],
    "sg:phone":"+32 2 759 98 55",
    "sg:postcode":"3070",
    "sg:province":"Vlaams-Brabant",
    "sg:tags":[
        "lady",
        "-",
        "hairdressing"
    ],
    "wof:name":"Suzy",
    "wof:placetype":"venue"
},
  "geometry": {"coordinates":[4.5413627625,50.8841133118],"type":"Point"}
}