{
  "type": "Feature",
  "properties": {
    "iso:country":"BE",
    "sg:address":"Oude Dendermondsebaan 75",
    "sg:city":"Asse",
    "sg:orig_category":"Eclairage et \u00e9quipements du foyer",
    "sg:phone":"+32 2 452 27 60",
    "sg:postcode":"1730",
    "sg:province":"Vlaams-Brabant",
    "wof:name":"Technilite",
    "wof:placetype":"venue"
},
  "geometry": {"coordinates":[4.185459137,50.9255561829],"type":"Point"}
}