{
  "type": "Feature",
  "properties": {
    "iso:country":"BE",
    "sg:address":"Kaarderslaan 13",
    "sg:city":"Lokeren",
    "sg:orig_category":"Non-Classified Establishments",
    "sg:phone":"+32 9 348 76 18",
    "sg:postcode":"9160",
    "sg:province":"Oost-Vlaanderen",
    "wof:name":"Simath Bvba",
    "wof:placetype":"venue"
},
  "geometry": {"coordinates":[4.0190248489,51.1100502014],"type":"Point"}
}