{
  "type": "Feature",
  "properties": {
    "addr:full":"Rue Croti\u00c8re 22 Tournai Hainaut 7530",
    "addr:housenumber":"22",
    "addr:postcode":"7530",
    "addr:street":"Rue Crotie\u0300Re",
    "iso:country":"BE",
    "sg:address":"Rue Croti\u00c8re 22",
    "sg:city":"Tournai",
    "sg:orig_category":"Sportclubs",
    "sg:phone":"+32 69 54 70 76",
    "sg:postcode":"7530",
    "sg:province":"Hainaut",
    "wof:name":"La Colombe Amoureuse",
    "wof:placetype":"venue"
},
  "geometry": {"coordinates":[3.5028760433,50.6014480591],"type":"Point"}
}