{
  "type": "Feature",
  "properties": {
    "iso:country":"BE",
    "sg:address":"Komvest 45",
    "sg:city":"Brugge",
    "sg:classifiers":[
        {
            "category":"Insurance",
            "subcategory":"Insurance Agent",
            "type":"Services"
        }
    ],
    "sg:phone":"+32 50 35 13 05",
    "sg:postcode":"8000",
    "sg:province":"West-Vlaanderen",
    "sg:tags":[
        "broker"
    ],
    "wof:name":"Fedes (federatie Dans & Sport)",
    "wof:placetype":"venue"
},
  "geometry": {"coordinates":[3.2252659798,51.2207679749],"type":"Point"}
}