{
  "type": "Feature",
  "properties": {
    "iso:country":"BE",
    "sg:address":"Doorniksesteenweg 422",
    "sg:city":"Avelgem",
    "sg:orig_category":"Bouwwerktuigen Gh Verhuur bouwmachines",
    "sg:phone":"+32 56 45 50 39",
    "sg:postcode":"8583",
    "sg:province":"West-Vlaanderen",
    "wof:name":"Volcke/manitou",
    "wof:placetype":"venue"
},
  "geometry": {"coordinates":[3.4079370499,50.7479705811],"type":"Point"}
}