{
  "type": "Feature",
  "properties": {
    "iso:country":"BE",
    "sg:address":"Rue Du Petit-leez 17",
    "sg:city":"Gembloux",
    "sg:orig_category":"Architecten",
    "sg:phone":"+32 81 64 03 07",
    "sg:postcode":"5031",
    "sg:province":"Namur",
    "wof:name":"S\u00c9bastien Mouffe",
    "wof:placetype":"venue"
},
  "geometry": {"coordinates":[4.7746758461,50.5795974731],"type":"Point"}
}