{
  "type": "Feature",
  "properties": {
    "addr:full":"Kerkweg 31 Herent Vlaams-Brabant 3020",
    "addr:housenumber":"31",
    "addr:postcode":"3020",
    "addr:street":"Kerkweg",
    "iso:country":"BE",
    "sg:address":"Kerkweg 31",
    "sg:city":"Herent",
    "sg:classifiers":[
        {
            "category":"Real Estate",
            "subcategory":"Real Estate Services",
            "type":"Services"
        }
    ],
    "sg:phone":"+32 16 23 52 34",
    "sg:postcode":"3020",
    "sg:province":"Vlaams-Brabant",
    "wof:name":"Plancq-invest Nv",
    "wof:placetype":"venue"
},
  "geometry": {"coordinates":[4.6698880196,50.9103546143],"type":"Point"}
}