{
  "type": "Feature",
  "properties": {
    "addr:full":"Laarbeeklaan 46 Asse Vlaams-Brabant 1731",
    "addr:housenumber":"46",
    "addr:postcode":"1731",
    "addr:street":"Laarbeeklaan",
    "iso:country":"BE",
    "sg:address":"Laarbeeklaan 46",
    "sg:city":"Asse",
    "sg:orig_category":"Installatie van houten of kunststof schrijnwerk",
    "sg:phone":"+32 2 466 28 63",
    "sg:postcode":"1731",
    "sg:province":"Vlaams-Brabant",
    "wof:name":"Fierens",
    "wof:placetype":"venue"
},
  "geometry": {"coordinates":[4.2786369324,50.8852348328],"type":"Point"}
}