{
  "type": "Feature",
  "properties": {
    "addr:full":"Serpentestraat 4 Brakel Oost-Vlaanderen 9660",
    "addr:housenumber":"4",
    "addr:postcode":"9660",
    "addr:street":"Serpentestraat",
    "iso:country":"BE",
    "sg:address":"Serpentestraat 4",
    "sg:city":"Brakel",
    "sg:orig_category":"Banken and kredietinstellingen",
    "sg:phone":"+32 55 42 25 21",
    "sg:postcode":"9660",
    "sg:province":"Oost-Vlaanderen",
    "wof:name":"Kbc",
    "wof:placetype":"venue"
},
  "geometry": {"coordinates":[3.7637889385,50.8041267395],"type":"Point"}
}