{
  "type": "Feature",
  "properties": {
    "addr:full":"Sparrenboslaan 3 De Haan (klemskerke) West-Vlaanderen 8420",
    "addr:housenumber":"3",
    "addr:postcode":"8420",
    "addr:street":"Sparrenboslaan",
    "iso:country":"BE",
    "sg:address":"Sparrenboslaan 3",
    "sg:city":"De Haan (klemskerke)",
    "sg:classifiers":[
        {
            "category":"Social Services",
            "subcategory":"Child Care",
            "type":"Services"
        }
    ],
    "sg:phone":"+32 59 23 32 79",
    "sg:postcode":"8420",
    "sg:province":"West-Vlaanderen",
    "sg:tags":[
        "home"
    ],
    "wof:name":"Duinen En Velden",
    "wof:placetype":"venue"
},
  "geometry": {"coordinates":[3.0273549557,51.2694587708],"type":"Point"}
}