{
  "type": "Feature",
  "properties": {
    "addr:full":"Quellinstraat 29 Antwerpen Antwerpen 2018",
    "addr:housenumber":"29",
    "addr:postcode":"2018",
    "addr:street":"Quellinstraat",
    "iso:country":"BE",
    "sg:address":"Quellinstraat 29",
    "sg:city":"Antwerpen",
    "sg:classifiers":[
        {
            "category":"Shopping",
            "subcategory":"Clothing, Apparel, & Fashions",
            "type":"Retail Goods"
        }
    ],
    "sg:phone":"+32 3 232 51 75",
    "sg:postcode":"2018",
    "sg:province":"Antwerpen",
    "sg:tags":[
        "-",
        "fur"
    ],
    "wof:name":"De Laet F Bvba",
    "wof:placetype":"venue"
},
  "geometry": {"coordinates":[4.4163532257,51.2161483765],"type":"Point"}
}