{
  "type": "Feature",
  "properties": {
    "iso:country":"BE",
    "sg:address":"Rue De Tournai 32",
    "sg:city":"Mouscron",
    "sg:orig_category":"Reisbureaus",
    "sg:phone":"+32 56 34 51 51",
    "sg:postcode":"7700",
    "sg:province":"Hainaut",
    "wof:name":"J.d. Montaine",
    "wof:placetype":"venue"
},
  "geometry": {"coordinates":[3.2169840336,50.7434997559],"type":"Point"}
}