{
  "type": "Feature",
  "properties": {
    "addr:full":"Acht Eeuwenlaan 1 Edegem Antwerpen 2650",
    "addr:housenumber":"1",
    "addr:postcode":"2650",
    "addr:street":"Acht Eeuwenlaan",
    "iso:country":"BE",
    "sg:address":"Acht Eeuwenlaan 1",
    "sg:city":"Edegem",
    "sg:orig_category":"Databeheer and gegevensverwerking Informaticaconsulenten",
    "sg:phone":"+32 3 457 74 32",
    "sg:postcode":"2650",
    "sg:province":"Antwerpen",
    "wof:name":"Ideal-computers",
    "wof:placetype":"venue"
},
  "geometry": {"coordinates":[4.4335970879,51.1554450989],"type":"Point"}
}