{
  "type": "Feature",
  "properties": {
    "addr:full":"Markt 12 Brugge West-Vlaanderen 8000",
    "addr:housenumber":"12",
    "addr:postcode":"8000",
    "addr:street":"Markt",
    "iso:country":"BE",
    "sg:address":"Markt 12",
    "sg:city":"Brugge",
    "sg:classifiers":[
        {
            "category":"Shopping",
            "subcategory":"Books",
            "type":"Retail Goods"
        }
    ],
    "sg:phone":"+32 50 33 34 03",
    "sg:postcode":"8000",
    "sg:province":"West-Vlaanderen",
    "sg:tags":[
        "bookseller"
    ],
    "wof:name":"De Reyghere",
    "wof:placetype":"venue"
},
  "geometry": {"coordinates":[3.2237439156,51.2088356018],"type":"Point"}
}