{
  "type": "Feature",
  "properties": {
    "addr:full":"Voskenslaan 88 Gent Oost-Vlaanderen 9000",
    "addr:housenumber":"88",
    "addr:postcode":"9000",
    "addr:street":"Voskenslaan;Oost-Vlaanderen",
    "iso:country":"BE",
    "sg:address":"Voskenslaan 88",
    "sg:city":"Gent",
    "sg:orig_category":"M\u00e9decins and sp\u00e9cialistes",
    "sg:phone":"+32 9 222 09 09",
    "sg:postcode":"9000",
    "sg:province":"Oost-Vlaanderen",
    "wof:name":"Pieter Beirinckx",
    "wof:placetype":"venue"
},
  "geometry": {"coordinates":[3.707775116,51.0334892273],"type":"Point"}
}