{
  "type": "Feature",
  "properties": {
    "iso:country":"BE",
    "sg:address":"Rue Stalis 25",
    "sg:city":"Oupeye",
    "sg:orig_category":"Loodgieterij, verwarming and sanitaire installaties",
    "sg:phone":"+32 4 240 26 83",
    "sg:postcode":"4681",
    "sg:province":"Li\u00e8ge",
    "wof:name":"A.b. Confort",
    "wof:placetype":"venue"
},
  "geometry": {"coordinates":[5.6587381363,50.7102813721],"type":"Point"}
}