{
  "type": "Feature",
  "properties": {
    "addr:full":"Moorseelsestraat 78 Kortrijk West-Vlaanderen 8500",
    "addr:housenumber":"78",
    "addr:postcode":"8500",
    "addr:street":"Moorseelsestraat",
    "iso:country":"BE",
    "sg:address":"Moorseelsestraat 78",
    "sg:city":"Kortrijk",
    "sg:classifiers":[
        {
            "category":"Health Services",
            "subcategory":"Health Practitioner",
            "type":"Services"
        }
    ],
    "sg:phone":"+32 56 36 03 69",
    "sg:postcode":"8500",
    "sg:province":"West-Vlaanderen",
    "sg:tags":[
        "physiotherapist"
    ],
    "wof:name":"Breye Eveline",
    "wof:placetype":"venue"
},
  "geometry": {"coordinates":[3.250549078,50.8321342468],"type":"Point"}
}