{
  "type": "Feature",
  "properties": {
    "iso:country":"BE",
    "sg:address":"Rue Haute 46",
    "sg:city":"Rixensart",
    "sg:orig_category":"Flanges According To Society Of Automotive Engineers Sae Standards",
    "sg:phone":"+32 2 653 72 45",
    "sg:postcode":"1330",
    "sg:province":"Brabant Wallon",
    "wof:name":"Hydraulic Assistance S.p.r.l.",
    "wof:placetype":"venue"
},
  "geometry": {"coordinates":[4.5115818977,50.7081108093],"type":"Point"}
}