{
  "type": "Feature",
  "properties": {
    "iso:country":"BE",
    "sg:address":"Rue Fran\u00e7ois Bruyerre 34",
    "sg:city":"Gosselies",
    "sg:classifiers":[
        {
            "category":"Food & Beverages",
            "subcategory":"Chocolate",
            "type":"Retail Goods"
        }
    ],
    "sg:phone":"+32 71 25 01 40",
    "sg:postcode":"6041",
    "sg:province":"Hainaut",
    "sg:tags":[
        "candy"
    ],
    "wof:name":"Bruyerre S.a. Departement Chocolaterie",
    "wof:placetype":"venue"
},
  "geometry": {"coordinates":[4.4372229576,50.4758796692],"type":"Point"}
}