{
  "type": "Feature",
  "properties": {
    "iso:country":"BE",
    "sg:address":"Rue Taillie 4",
    "sg:city":"Mons (jemappes)",
    "sg:classifiers":[
        {
            "category":"Personal",
            "subcategory":"Nail Salon",
            "type":"Services"
        }
    ],
    "sg:phone":"+32 65 82 30 40",
    "sg:postcode":"7012",
    "sg:province":"Hainaut",
    "sg:tags":[
        "pedicure"
    ],
    "wof:name":"Lecocq J",
    "wof:placetype":"venue"
},
  "geometry": {"coordinates":[3.8894600868,50.4481964111],"type":"Point"}
}