{
  "type": "Feature",
  "properties": {
    "iso:country":"BE",
    "sg:address":"Ter Kommerenweg 11",
    "sg:city":"Wevelgem",
    "sg:orig_category":"Installation de menuiserie en bois and plastique",
    "sg:phone":"+32 56 50 40 93",
    "sg:postcode":"8560",
    "sg:province":"West-Vlaanderen",
    "wof:name":"Dirk Vanmarcke",
    "wof:placetype":"venue"
},
  "geometry": {"coordinates":[3.1301879883,50.8406448364],"type":"Point"}
}