{
  "type": "Feature",
  "properties": {
    "addr:full":"Brusselsestraat 180 Leuven Vlaams-Brabant 3000",
    "addr:housenumber":"180",
    "addr:postcode":"3000",
    "addr:street":"Brusselsestraat",
    "iso:country":"BE",
    "sg:address":"Brusselsestraat 180",
    "sg:city":"Leuven",
    "sg:classifiers":[
        {
            "category":"Professional",
            "subcategory":"Management & Consulting",
            "type":"Services"
        }
    ],
    "sg:phone":"+32 16 22 25 33",
    "sg:postcode":"3000",
    "sg:province":"Vlaams-Brabant",
    "sg:tags":[
        "consultant"
    ],
    "wof:name":"Amazone Consult Bvba",
    "wof:placetype":"venue"
},
  "geometry": {"coordinates":[4.6918430328,50.8809814453],"type":"Point"}
}