{
  "type": "Feature",
  "properties": {
    "addr:full":"Chauss\u00c9e De Douai 63 Tournai Hainaut 7506",
    "addr:housenumber":"63",
    "addr:postcode":"7506",
    "addr:street":"Chausse\u0301E De Douai",
    "iso:country":"BE",
    "sg:address":"Chauss\u00c9e De Douai 63",
    "sg:city":"Tournai",
    "sg:orig_category":"Installation \u00e9lectrique r\u00e9sidentielle",
    "sg:phone":"+32 69 64 74 22",
    "sg:postcode":"7506",
    "sg:province":"Hainaut",
    "wof:name":"Edouard Delcourt",
    "wof:placetype":"venue"
},
  "geometry": {"coordinates":[3.3533399105,50.5886306763],"type":"Point"}
}