{
  "type": "Feature",
  "properties": {
    "addr:full":"Lakensestraat 157 Brussel/bruxelles Bruxelles-Capitale 1000",
    "addr:housenumber":"157",
    "addr:postcode":"1000",
    "addr:street":"Lakensestraat;/",
    "iso:country":"BE",
    "sg:address":"Lakensestraat 157",
    "sg:city":"Brussel/bruxelles",
    "sg:classifiers":[
        {
            "category":"Restaurant",
            "type":"Food & Drink"
        }
    ],
    "sg:phone":"+32 2 223 78 81",
    "sg:postcode":"1000",
    "sg:province":"Bruxelles-Capitale",
    "sg:tags":[
        "caf\u00e9s"
    ],
    "wof:name":"Taverne Black Jack",
    "wof:placetype":"venue"
},
  "geometry": {"coordinates":[4.352481842,50.8553771973],"type":"Point"}
}