{
  "type": "Feature",
  "properties": {
    "iso:country":"BE",
    "sg:address":"Rue De L'escaille 16",
    "sg:city":"Ecaussinnes (ecaussinnes-lalaing)",
    "sg:classifiers":[
        {
            "category":"Real Estate",
            "subcategory":"Architect",
            "type":"Services"
        }
    ],
    "sg:phone":"+32 67 44 31 28",
    "sg:postcode":"7191",
    "sg:province":"Hainaut",
    "wof:name":"Leveque C",
    "wof:placetype":"venue"
},
  "geometry": {"coordinates":[4.1967282295,50.5699996948],"type":"Point"}
}