{
  "type": "Feature",
  "properties": {
    "addr:full":"Rijksweg 519 Maasmechelen Limburg 3630",
    "addr:housenumber":"519",
    "addr:postcode":"3630",
    "addr:street":"Rijksweg",
    "iso:country":"BE",
    "sg:address":"Rijksweg 519",
    "sg:city":"Maasmechelen",
    "sg:classifiers":[
        {
            "category":"Insurance",
            "subcategory":"Life Insurance",
            "type":"Services"
        }
    ],
    "sg:phone":"+32 89 77 11 71",
    "sg:postcode":"3630",
    "sg:province":"Limburg",
    "sg:tags":[
        "assurance"
    ],
    "wof:name":"Bureau Mulenbruck",
    "wof:placetype":"venue"
},
  "geometry": {"coordinates":[5.6936130524,50.9490432739],"type":"Point"}
}