{
  "type": "Feature",
  "properties": {
    "iso:country":"BE",
    "sg:address":"Chauss\u00c9e De Bruxelles 248",
    "sg:city":"Braine-le-comte",
    "sg:orig_category":"Woningbouw",
    "sg:phone":"+32 67 55 45 18",
    "sg:postcode":"7090",
    "sg:province":"Hainaut",
    "wof:name":"C.g.t.b.",
    "wof:placetype":"venue"
},
  "geometry": {"coordinates":[4.1448898315,50.6265335083],"type":"Point"}
}