{
  "type": "Feature",
  "properties": {
    "iso:country":"BE",
    "sg:address":"Noordlaan 89b3",
    "sg:city":"Dendermonde",
    "sg:orig_category":"G\u00e9om\u00e8tres",
    "sg:phone":"+32 52 22 58 57",
    "sg:postcode":"9200",
    "sg:province":"Oost-Vlaanderen",
    "wof:name":"Hubert Platteaux",
    "wof:placetype":"venue"
},
  "geometry": {"coordinates":[4.0921998024,51.0334320068],"type":"Point"}
}