{
  "type": "Feature",
  "properties": {
    "addr:full":"Rue Marcel-lespagne 28 Hastiere Namur 5540",
    "addr:housenumber":"28",
    "addr:postcode":"5540",
    "addr:street":"Rue Marcel-Lespagne;Namur",
    "iso:country":"BE",
    "sg:address":"Rue Marcel-lespagne 28",
    "sg:city":"Hastiere",
    "sg:orig_category":"Brood, gebak and snoepgoed",
    "sg:phone":"+32 82 64 55 21",
    "sg:postcode":"5540",
    "sg:province":"Namur",
    "wof:name":"Boulangerie Brihaye",
    "wof:placetype":"venue"
},
  "geometry": {"coordinates":[4.8226470947,50.2155799866],"type":"Point"}
}