{
  "type": "Feature",
  "properties": {
    "addr:full":"Route Des Ardennes 92 Aywaille Li\u00e8ge 4920",
    "addr:housenumber":"92",
    "addr:postcode":"4920",
    "addr:street":"Route Des Ardennes",
    "iso:country":"BE",
    "sg:address":"Route Des Ardennes 92",
    "sg:city":"Aywaille",
    "sg:classifiers":[
        {
            "category":"Food & Beverages",
            "subcategory":"Candy",
            "type":"Retail Goods"
        }
    ],
    "sg:phone":"+32 4 384 68 60",
    "sg:postcode":"4920",
    "sg:province":"Li\u00e8ge",
    "sg:tags":[
        "fab",
        "producten",
        "diverse"
    ],
    "wof:name":"Richard Fr",
    "wof:placetype":"venue"
},
  "geometry": {"coordinates":[5.6670889854,50.455280304],"type":"Point"}
}