{
  "type": "Feature",
  "properties": {
    "addr:full":"Rue Du Montys 25bc Tinlot Li\u00e8ge 4557",
    "addr:housenumber":"25bc",
    "addr:postcode":"4557",
    "addr:street":"Rue Du Montys",
    "iso:country":"BE",
    "sg:address":"Rue Du Montys 25bc",
    "sg:city":"Tinlot",
    "sg:orig_category":"V\u00e9hicules automobiles. R\u00e9cup\u00e9ration de mati\u00e8res m\u00e9talliques recyclables and d\u00e9molisseurs de voitures",
    "sg:phone":"+32 85 51 31 51",
    "sg:postcode":"4557",
    "sg:province":"Li\u00e8ge",
    "wof:name":"Garage Montys Motor",
    "wof:placetype":"venue"
},
  "geometry": {"coordinates":[5.3869037628,50.4721298218],"type":"Point"}
}