{
  "type": "Feature",
  "properties": {
    "addr:full":"Avenue De La Basilique 23 Peruwelz Hainaut 7603",
    "addr:housenumber":"23",
    "addr:postcode":"7603",
    "addr:street":"Avenue De La Basilique;Hainaut",
    "iso:country":"BE",
    "sg:address":"Avenue De La Basilique 23",
    "sg:city":"Peruwelz",
    "sg:orig_category":"Electrom\u00e9nager, t\u00e9l\u00e9visions and radios",
    "sg:phone":"+32 69 77 50 50",
    "sg:postcode":"7603",
    "sg:province":"Hainaut",
    "wof:name":"Electronic Center",
    "wof:placetype":"venue"
},
  "geometry": {"coordinates":[3.6057069302,50.498134613],"type":"Point"}
}