{
  "type": "Feature",
  "properties": {
    "iso:country":"BE",
    "sg:address":"Rue Du Bosquet 8",
    "sg:city":"Jodoigne",
    "sg:orig_category":"Banken and kredietinstellingen",
    "sg:phone":"+32 10 81 31 15",
    "sg:postcode":"1370",
    "sg:province":"Brabant Wallon",
    "wof:name":"Cr\u00c9dit Agricole",
    "wof:placetype":"venue"
},
  "geometry": {"coordinates":[4.871860981,50.7241783142],"type":"Point"}
}