{
  "type": "Feature",
  "properties": {
    "addr:full":"Place Du Peuple 3b1 Mont-saint-guibert Brabant Wallon 1435",
    "addr:housenumber":"3b1",
    "addr:postcode":"1435",
    "addr:street":"Place Du Peuple",
    "iso:country":"BE",
    "sg:address":"Place Du Peuple 3b1",
    "sg:city":"Mont-saint-guibert",
    "sg:orig_category":"D\u00e9taillants en pi\u00e8ces and accessoires de voitures",
    "sg:phone":"+32 10 65 12 98",
    "sg:postcode":"1435",
    "sg:province":"Brabant Wallon",
    "wof:name":"C.b.g.",
    "wof:placetype":"venue"
},
  "geometry": {"coordinates":[4.6101951599,50.6333885193],"type":"Point"}
}