{
  "type": "Feature",
  "properties": {
    "addr:full":"Eikenlei 181 Brecht (sint-job-in-'t Goor) Antwerpen 2960",
    "addr:housenumber":"181",
    "addr:postcode":"2960",
    "addr:street":"Eikenlei;' T Goor",
    "iso:country":"BE",
    "sg:address":"Eikenlei 181",
    "sg:city":"Brecht (sint-job-in-'t Goor)",
    "sg:classifiers":[
        {
            "category":"Professional",
            "subcategory":"Engineering",
            "type":"Services"
        }
    ],
    "sg:phone":"+32 3 633 89 00",
    "sg:postcode":"2960",
    "sg:province":"Antwerpen",
    "sg:tags":[
        "-"
    ],
    "wof:name":"Controlec Engineering Belgi\u00eb Nv",
    "wof:placetype":"venue"
},
  "geometry": {"coordinates":[4.5522041321,51.2964897156],"type":"Point"}
}