{
  "type": "Feature",
  "properties": {
    "iso:country":"BE",
    "sg:address":"Zamanstraat 71",
    "sg:city":"Lokeren",
    "sg:orig_category":"Rundveehouders",
    "sg:phone":"+32 9 348 24 46",
    "sg:postcode":"9160",
    "sg:province":"Oost-Vlaanderen",
    "wof:name":"Marcel De Wilde",
    "wof:placetype":"venue"
},
  "geometry": {"coordinates":[3.9445979595,51.1027641296],"type":"Point"}
}