{
  "type": "Feature",
  "properties": {
    "addr:full":"Quai March\u00c9 Au Poisson 14 Tournai Hainaut 7500",
    "addr:housenumber":"14",
    "addr:postcode":"7500",
    "addr:street":"Quai Marche\u0301 Au Poisson",
    "iso:country":"BE",
    "sg:address":"Quai March\u00c9 Au Poisson 14",
    "sg:city":"Tournai",
    "sg:orig_category":"Timbres, monnaies and troph\u00e9es",
    "sg:phone":"+32 69 21 09 36",
    "sg:postcode":"7500",
    "sg:province":"Hainaut",
    "wof:name":"Au Collectionneur",
    "wof:placetype":"venue"
},
  "geometry": {"coordinates":[3.3917601109,50.607460022],"type":"Point"}
}