{
  "type": "Feature",
  "properties": {
    "iso:country":"BE",
    "sg:address":"Avenue Ernest Cambier 39",
    "sg:city":"Schaarbeek/schaerbeek",
    "sg:orig_category":"Avocats and conseillers juridiques",
    "sg:phone":"+32 2 245 25 20",
    "sg:postcode":"1030",
    "sg:province":"Bruxelles-Capitale",
    "wof:name":"P. Leclerc",
    "wof:placetype":"venue"
},
  "geometry": {"coordinates":[4.3926548958,50.8584480286],"type":"Point"}
}