{
  "type": "Feature",
  "properties": {
    "addr:full":"Rue Du Conroye 90 Erquelinnes Hainaut 6560",
    "addr:housenumber":"90",
    "addr:postcode":"6560",
    "addr:street":"Rue Du Conroye",
    "iso:country":"BE",
    "sg:address":"Rue Du Conroye 90",
    "sg:city":"Erquelinnes",
    "sg:classifiers":[
        {
            "category":"Health Services",
            "subcategory":"Health Practitioner",
            "type":"Services"
        }
    ],
    "sg:phone":"+32 71 55 77 49",
    "sg:postcode":"6560",
    "sg:province":"Hainaut",
    "sg:tags":[
        "physiotherapist"
    ],
    "wof:name":"Toussaint A",
    "wof:placetype":"venue"
},
  "geometry": {"coordinates":[4.1242041588,50.3168449402],"type":"Point"}
}