{
  "type": "Feature",
  "properties": {
    "iso:country":"BE",
    "sg:address":"Rue Emile Vandervelde 59",
    "sg:city":"Charleroi",
    "sg:orig_category":"Opticiens",
    "sg:phone":"+32 71 32 29 41",
    "sg:postcode":"6030",
    "sg:province":"Hainaut",
    "wof:name":"Maison Bauwens-deprez",
    "wof:placetype":"venue"
},
  "geometry": {"coordinates":[4.3940491676,50.4099960327],"type":"Point"}
}