{
  "type": "Feature",
  "properties": {
    "addr:full":"Rue De La Salle 11 Neupr\u00e9 (rotheux-rimi\u00e8re) Li\u00e8ge 4120",
    "addr:housenumber":"11",
    "addr:postcode":"4120",
    "addr:street":"Rue De La Salle;Rotheux-Rimie\u0300Re",
    "iso:country":"BE",
    "sg:address":"Rue De La Salle 11",
    "sg:city":"Neupr\u00e9 (rotheux-rimi\u00e8re)",
    "sg:classifiers":[
        {
            "category":"Wholesale",
            "subcategory":"Books, Periodicals, & Newspapers",
            "type":"Manufacturing & Wholesale Goods"
        }
    ],
    "sg:phone":"+32 4 372 13 66",
    "sg:postcode":"4120",
    "sg:province":"Li\u00e8ge",
    "sg:tags":[
        "publisher"
    ],
    "wof:name":"Riga E",
    "wof:placetype":"venue"
},
  "geometry": {"coordinates":[5.4995641708,50.5317687988],"type":"Point"}
}