{
  "type": "Feature",
  "properties": {
    "addr:full":"Pluimstraat 125 Kortrijk West-Vlaanderen 8500",
    "addr:housenumber":"125",
    "addr:postcode":"8500",
    "addr:street":"Pluimstraat",
    "iso:country":"BE",
    "sg:address":"Pluimstraat 125",
    "sg:city":"Kortrijk",
    "sg:classifiers":[
        {
            "category":"Building & Trades",
            "subcategory":"Construction",
            "type":"Services"
        }
    ],
    "sg:phone":"+32 56 31 12 57",
    "sg:postcode":"8500",
    "sg:province":"West-Vlaanderen",
    "sg:tags":[
        "carpenter"
    ],
    "wof:name":"David Vincent",
    "wof:placetype":"venue"
},
  "geometry": {"coordinates":[3.2764360905,50.8261222839],"type":"Point"}
}