{
  "type": "Feature",
  "properties": {
    "addr:full":"Kruisstraat 47 Tremelo Vlaams-Brabant 3120",
    "addr:housenumber":"47",
    "addr:postcode":"3120",
    "addr:street":"Kruisstraat",
    "iso:country":"BE",
    "sg:address":"Kruisstraat 47",
    "sg:city":"Tremelo",
    "sg:orig_category":"Maroquinerie and articles de voyage. Accessoires vestimentaires",
    "sg:phone":"+32 16 53 32 47",
    "sg:postcode":"3120",
    "sg:province":"Vlaams-Brabant",
    "wof:name":"Lederwaren Sodiba",
    "wof:placetype":"venue"
},
  "geometry": {"coordinates":[4.7011260986,50.9938659668],"type":"Point"}
}