{
  "type": "Feature",
  "properties": {
    "iso:country":"BE",
    "sg:address":"Borrestraat 69",
    "sg:city":"Overijse",
    "sg:classifiers":[
        {
            "category":"Building & Trades",
            "subcategory":"Construction",
            "type":"Services"
        }
    ],
    "sg:phone":"+32 2 687 75 91",
    "sg:postcode":"3090",
    "sg:province":"Vlaams-Brabant",
    "sg:tags":[
        "carpenter"
    ],
    "wof:name":"Castiaux D",
    "wof:placetype":"venue"
},
  "geometry": {"coordinates":[4.5511012077,50.758026123],"type":"Point"}
}