{
  "type": "Feature",
  "properties": {
    "addr:full":"Toekomstlaan 19 Beerse Antwerpen 2340",
    "addr:housenumber":"19",
    "addr:postcode":"2340",
    "addr:street":"Toekomstlaan",
    "iso:country":"BE",
    "sg:address":"Toekomstlaan 19",
    "sg:city":"Beerse",
    "sg:classifiers":[
        {
            "category":"Shopping",
            "subcategory":"Discount & Variety Stores",
            "type":"Retail Goods"
        }
    ],
    "sg:phone":"+32 14 61 80 17",
    "sg:postcode":"2340",
    "sg:province":"Antwerpen",
    "sg:tags":[
        "warehouse",
        "-",
        "merchandise"
    ],
    "wof:name":"Valacom Nv",
    "wof:placetype":"venue"
},
  "geometry": {"coordinates":[4.8418259621,51.3044776917],"type":"Point"}
}