{
  "type": "Feature",
  "properties": {
    "iso:country":"BE",
    "sg:address":"Rue D'arlon 50",
    "sg:city":"Florenville",
    "sg:classifiers":[
        {
            "category":"Wholesale",
            "subcategory":"Vending Machines",
            "type":"Manufacturing & Wholesale Goods"
        }
    ],
    "sg:phone":"+32 61 32 82 88",
    "sg:postcode":"6820",
    "sg:province":"Luxembourg",
    "sg:tags":[
        "coudre",
        "textile",
        "tricoter",
        "\u00e0"
    ],
    "wof:name":"New Mercerie",
    "wof:placetype":"venue"
},
  "geometry": {"coordinates":[5.3215770721,49.6957817078],"type":"Point"}
}