{
  "type": "Feature",
  "properties": {
    "addr:full":"Valmeerstraat 136 Riemst (valmeer) Limburg 3770",
    "addr:housenumber":"136",
    "addr:postcode":"3770",
    "addr:street":"Valmeerstraat",
    "iso:country":"BE",
    "sg:address":"Valmeerstraat 136",
    "sg:city":"Riemst (valmeer)",
    "sg:classifiers":[
        {
            "category":"Health Services",
            "subcategory":"Doctor",
            "type":"Services"
        }
    ],
    "sg:phone":"+32 12 45 23 61",
    "sg:postcode":"3770",
    "sg:province":"Limburg",
    "sg:tags":[
        "medicinephysicians",
        "surgeon"
    ],
    "wof:name":"Cuypers Karel",
    "wof:placetype":"venue"
},
  "geometry": {"coordinates":[5.5861368179,50.7934188843],"type":"Point"}
}