{
  "type": "Feature",
  "properties": {
    "addr:full":"Bredabaan 531 Merksem Antwerpen 2170",
    "addr:housenumber":"531",
    "addr:postcode":"2170",
    "addr:street":"Bredabaan",
    "iso:country":"BE",
    "sg:address":"Bredabaan 531",
    "sg:city":"Merksem",
    "sg:orig_category":"Randstad. Agences d\u00b4interim and personnel temporaire",
    "sg:phone":"+32 3 647 20 16",
    "sg:postcode":"2170",
    "sg:province":"Antwerpen",
    "wof:name":"Randstad",
    "wof:placetype":"venue"
},
  "geometry": {"coordinates":[4.449034214,51.2458953857],"type":"Point"}
}