{
  "type": "Feature",
  "properties": {
    "iso:country":"BE",
    "sg:address":"Avenue Des Muguets 0",
    "sg:city":"Charleroi",
    "sg:orig_category":"Sportterreinen and installaties behalve sportcentra",
    "sg:phone":"+32 71 29 74 00",
    "sg:postcode":"6001",
    "sg:province":"Hainaut",
    "wof:name":"Centre De D\u00c9lassement De Marcinelle",
    "wof:placetype":"venue"
},
  "geometry": {"coordinates":[4.4571518898,50.373298645],"type":"Point"}
}