{
  "type": "Feature",
  "properties": {
    "iso:country":"BE",
    "sg:address":"Gaston Burssenslaan 1",
    "sg:city":"Antwerpen",
    "sg:classifiers":[
        {
            "category":"Parking",
            "subcategory":"Bicycle",
            "type":"Transportation"
        }
    ],
    "sg:phone":"+32 3 219 54 51",
    "sg:postcode":"2050",
    "sg:province":"Antwerpen",
    "sg:tags":[
        "chiropodist"
    ],
    "wof:name":"Voetstudio/steppe Pascale",
    "wof:placetype":"venue"
},
  "geometry": {"coordinates":[4.382147789,51.2191925049],"type":"Point"}
}