{
  "type": "Feature",
  "properties": {
    "iso:country":"BE",
    "sg:address":"Avenue Van Volxem 320-4",
    "sg:city":"Bruxelles (forest)",
    "sg:classifiers":[
        {
            "category":"Bars & Pubs",
            "type":"Food & Drink"
        }
    ],
    "sg:phone":"+32 2 346 95 84",
    "sg:postcode":"1190",
    "sg:province":"Bruxelles-Capitale",
    "sg:tags":[
        "tavern"
    ],
    "wof:name":"Riviera",
    "wof:placetype":"venue"
},
  "geometry": {"coordinates":[4.3257188797,50.8230895996],"type":"Point"}
}