{
  "type": "Feature",
  "properties": {
    "addr:full":"Lentakkerstraat 5ba Aalter Oost-Vlaanderen 9880",
    "addr:postcode":"9880",
    "addr:street":"Lentakkerstraat;Oost-Vlaanderen",
    "iso:country":"BE",
    "sg:address":"Lentakkerstraat 5ba",
    "sg:city":"Aalter",
    "sg:orig_category":"Eleveurs and marchands de porcs",
    "sg:phone":"+32 51 68 75 27",
    "sg:postcode":"9880",
    "sg:province":"Oost-Vlaanderen",
    "wof:name":"Wouter Devlieghere",
    "wof:placetype":"venue"
},
  "geometry": {"coordinates":[3.4728620052,51.0367469788],"type":"Point"}
}