{
  "type": "Feature",
  "properties": {
    "addr:full":"Chauss\u00e9e De Mons 344 Tubize Brabant Wallon 1480",
    "addr:housenumber":"344",
    "addr:postcode":"1480",
    "addr:street":"Chausse\u0301E De Mons;Wallon",
    "iso:country":"BE",
    "sg:address":"Chauss\u00e9e De Mons 344",
    "sg:city":"Tubize",
    "sg:classifiers":[
        {
            "category":"Professional",
            "subcategory":"Engineering",
            "type":"Services"
        }
    ],
    "sg:phone":"+32 2 355 80 11",
    "sg:postcode":"1480",
    "sg:province":"Brabant Wallon",
    "sg:tags":[
        "-"
    ],
    "wof:name":"Richart J-c",
    "wof:placetype":"venue"
},
  "geometry": {"coordinates":[4.1935501099,50.6822357178],"type":"Point"}
}