{
  "type": "Feature",
  "properties": {
    "iso:country":"BE",
    "sg:address":"Rue Herbert Hoover 1",
    "sg:city":"Ch\u00e2telet (ch\u00e2telineau)",
    "sg:classifiers":[
        {
            "category":"Health Services",
            "subcategory":"Health Practitioner",
            "type":"Services"
        }
    ],
    "sg:phone":"+32 71 38 69 96",
    "sg:postcode":"6200",
    "sg:province":"Hainaut",
    "sg:tags":[
        "psychologist"
    ],
    "wof:name":"Bettinville J M",
    "wof:placetype":"venue"
},
  "geometry": {"coordinates":[4.5197682381,50.4119224548],"type":"Point"}
}