{
  "type": "Feature",
  "properties": {
    "iso:country":"BE",
    "sg:address":"Langstraat 25",
    "sg:city":"Wellen",
    "sg:orig_category":"Eleveurs and marchands de porcs. Producteurs de fruits",
    "sg:phone":"+32 12 74 14 39",
    "sg:postcode":"3830",
    "sg:province":"Limburg",
    "wof:name":"Hubert Bleus",
    "wof:placetype":"venue"
},
  "geometry": {"coordinates":[5.3508071899,50.8497123718],"type":"Point"}
}