{
  "type": "Feature",
  "properties": {
    "addr:full":"Schoorbakkestr 25 Pervijze West-Vlaanderen 8600",
    "addr:housenumber":"25",
    "addr:postcode":"8600",
    "addr:street":"Schoorbakkestr;West-Vlaanderen",
    "iso:country":"BE",
    "sg:address":"Schoorbakkestr 25",
    "sg:city":"Pervijze",
    "sg:classifiers":[
        {
            "category":"Farming",
            "subcategory":"Livestock Farm",
            "type":"Manufacturing & Wholesale Goods"
        }
    ],
    "sg:phone":"+32 51 55 50 05",
    "sg:postcode":"8600",
    "sg:province":"West-Vlaanderen",
    "sg:tags":[
        "grain",
        "agriculture",
        "cereal"
    ],
    "wof:name":"Vandeweghe Bvba",
    "wof:placetype":"venue"
},
  "geometry": {"coordinates":[2.7975239754,51.0742530823],"type":"Point"}
}