{
  "type": "Feature",
  "properties": {
    "iso:country":"BE",
    "sg:address":"Steenweg 51",
    "sg:city":"Opwijk",
    "sg:orig_category":"Zuivelproducten",
    "sg:phone":"+32 52 35 08 62",
    "sg:postcode":"1745",
    "sg:province":"Vlaams-Brabant",
    "wof:name":"Kaashuisje Lanto",
    "wof:placetype":"venue"
},
  "geometry": {"coordinates":[4.1709060669,50.9417304993],"type":"Point"}
}