{
  "type": "Feature",
  "properties": {
    "addr:full":"Rue Haute-saive 41a Blegny Li\u00e8ge 4671",
    "addr:housenumber":"41a",
    "addr:postcode":"4671",
    "addr:street":"Rue Haute-Saive",
    "iso:country":"BE",
    "sg:address":"Rue Haute-saive 41a",
    "sg:city":"Blegny",
    "sg:orig_category":"Herstellingen and onderhoud van auto's",
    "sg:phone":"+32 4 370 09 69",
    "sg:postcode":"4671",
    "sg:province":"Li\u00e8ge",
    "wof:name":"Carrosserie Thierry Rensonnet",
    "wof:placetype":"venue"
},
  "geometry": {"coordinates":[5.6761050224,50.6561889648],"type":"Point"}
}