{
  "type": "Feature",
  "properties": {
    "iso:country":"BE",
    "sg:address":"Leliedreef 7",
    "sg:city":"Knokke-heist (westkapelle)",
    "sg:classifiers":[
        {
            "category":"Personal",
            "type":"Services"
        }
    ],
    "sg:phone":"+32 50 61 42 42",
    "sg:postcode":"8300",
    "sg:province":"West-Vlaanderen",
    "sg:tags":[
        "party",
        "planning"
    ],
    "wof:name":"Govaert E",
    "wof:placetype":"venue"
},
  "geometry": {"coordinates":[3.287694931,51.3467254639],"type":"Point"}
}