{
  "type": "Feature",
  "properties": {
    "addr:full":"Rue Camus 60 Andenne Namur 5300",
    "addr:housenumber":"60",
    "addr:postcode":"5300",
    "addr:street":"Rue Camus",
    "iso:country":"BE",
    "sg:address":"Rue Camus 60",
    "sg:city":"Andenne",
    "sg:orig_category":"D\u00e9taillants en pi\u00e8ces and accessoires de voitures",
    "sg:phone":"+32 85 84 41 02",
    "sg:postcode":"5300",
    "sg:province":"Namur",
    "wof:name":"Auto D\u00c9cor",
    "wof:placetype":"venue"
},
  "geometry": {"coordinates":[5.1021938324,50.490688324],"type":"Point"}
}