{
  "type": "Feature",
  "properties": {
    "iso:country":"BE",
    "sg:address":"Arkstraat 73",
    "sg:city":"Lanaken",
    "sg:orig_category":"Artsen and specialisten",
    "sg:phone":"+32 89 71 82 60",
    "sg:postcode":"3620",
    "sg:province":"Limburg",
    "wof:name":"Hilde Willems",
    "wof:placetype":"venue"
},
  "geometry": {"coordinates":[5.6458120346,50.8898582458],"type":"Point"}
}