{
  "type": "Feature",
  "properties": {
    "iso:country":"BE",
    "sg:address":"Rue Anixhe 146",
    "sg:city":"Juprelle",
    "sg:orig_category":"Ordinateurs and \u00e9quipement informatique",
    "sg:phone":"+32 4 278 02 66",
    "sg:postcode":"4458",
    "sg:province":"Li\u00e8ge",
    "wof:name":"Visual Concept Informat.",
    "wof:placetype":"venue"
},
  "geometry": {"coordinates":[5.5693540573,50.7038497925],"type":"Point"}
}