{
  "type": "Feature",
  "properties": {
    "iso:country":"BE",
    "sg:address":"Turmstrasse 23",
    "sg:city":"Raeren",
    "sg:orig_category":"Plaatsen van vloer- and muurbekleding Schilders",
    "sg:phone":"+32 87 85 00 05",
    "sg:postcode":"4730",
    "sg:province":"Li\u00e8ge",
    "wof:name":"Fa. Kicken-nussbaum",
    "wof:placetype":"venue"
},
  "geometry": {"coordinates":[6.1370887756,50.6752586365],"type":"Point"}
}