{
  "type": "Feature",
  "properties": {
    "addr:full":"Noordlaan 156 Dendermonde Oost-Vlaanderen 9200",
    "addr:housenumber":"156",
    "addr:postcode":"9200",
    "addr:street":"Noordlaan;Oost-Vlaanderen",
    "iso:country":"BE",
    "sg:address":"Noordlaan 156",
    "sg:city":"Dendermonde",
    "sg:classifiers":[
        {
            "category":"Health Services",
            "subcategory":"Dentist",
            "type":"Services"
        }
    ],
    "sg:phone":"+32 52 20 07 83",
    "sg:postcode":"9200",
    "sg:province":"Oost-Vlaanderen",
    "wof:name":"Vancoppenolle Sophie",
    "wof:placetype":"venue"
},
  "geometry": {"coordinates":[4.0918908119,51.0337944031],"type":"Point"}
}