{
  "type": "Feature",
  "properties": {
    "iso:country":"BE",
    "sg:address":"Rue De Mons 135",
    "sg:city":"Mons",
    "sg:orig_category":"Cr\u00e8ches and garderies d'enfants",
    "sg:phone":"+32 65 84 08 35",
    "sg:postcode":"7011",
    "sg:province":"Hainaut",
    "wof:name":"La Maison Des Babies",
    "wof:placetype":"venue"
},
  "geometry": {"coordinates":[3.8567180634,50.4755744934],"type":"Point"}
}