{
  "type": "Feature",
  "properties": {
    "addr:full":"41 Stationsstraat 1702 Groot Bijgaarden 41",
    "addr:housenumber":"1702;41",
    "addr:street":"Stationsstraat;Groot Bijgaarden",
    "iso:country":"BE",
    "sg:address":"41",
    "sg:city":"Stationsstraat 1702 Groot Bijgaarden",
    "sg:classifiers":[
        {
            "category":"Utilities",
            "subcategory":"Telephone",
            "type":"Services"
        }
    ],
    "sg:phone":"+32 2 466 88 80",
    "sg:postcode":"41",
    "sg:tags":[
        "telecommunication"
    ],
    "wof:name":"Trionic Nv",
    "wof:placetype":"venue"
},
  "geometry": {"coordinates":[4.2758440971,50.8720779419],"type":"Point"}
}