{
  "type": "Feature",
  "properties": {
    "addr:full":"Pater De Grootstraat 16 Scherpenheuvel-zichem Vlaams-Brabant 3271",
    "addr:housenumber":"16",
    "addr:postcode":"3271",
    "addr:street":"Pater De Grootstraat",
    "iso:country":"BE",
    "sg:address":"Pater De Grootstraat 16",
    "sg:city":"Scherpenheuvel-zichem",
    "sg:orig_category":"Artsen and specialisten",
    "sg:phone":"+32 13 78 43 52",
    "sg:postcode":"3271",
    "sg:province":"Vlaams-Brabant",
    "wof:name":"Inge Buseyne",
    "wof:placetype":"venue"
},
  "geometry": {"coordinates":[4.9633421898,51.0418434143],"type":"Point"}
}