{
  "type": "Feature",
  "properties": {
    "addr:full":"Molenberg 55a Meerhout Antwerpen 2450",
    "addr:housenumber":"55a",
    "addr:postcode":"2450",
    "addr:street":"Molenberg",
    "iso:country":"BE",
    "sg:address":"Molenberg 55a",
    "sg:city":"Meerhout",
    "sg:orig_category":"Royal Canin. Animaux domestiques and accessoires. Articles de camping and de sport",
    "sg:phone":"+32 14 30 32 19",
    "sg:postcode":"2450",
    "sg:province":"Antwerpen",
    "wof:name":"Sloeber Nijs Carine",
    "wof:placetype":"venue"
},
  "geometry": {"coordinates":[5.0711188316,51.1333351135],"type":"Point"}
}