{
  "type": "Feature",
  "properties": {
    "addr:full":"Rue Du Wez Bajole 20 Ch\u00e2telet Hainaut 6200",
    "addr:housenumber":"20",
    "addr:postcode":"6200",
    "addr:street":"Rue Du Wez Bajole",
    "iso:country":"BE",
    "sg:address":"Rue Du Wez Bajole 20",
    "sg:city":"Ch\u00e2telet",
    "sg:orig_category":"Aircraft Parts, Components, Modules, And Construction Supplies",
    "sg:phone":"+32 71 24 45 45",
    "sg:postcode":"6200",
    "sg:province":"Hainaut",
    "wof:name":"Etablissements Gr\u00e4fe S.p.r.l.",
    "wof:placetype":"venue"
},
  "geometry": {"coordinates":[4.5354452133,50.3999290466],"type":"Point"}
}