{
  "type": "Feature",
  "properties": {
    "iso:country":"BE",
    "sg:address":"Plezantstraat 11",
    "sg:city":"Hamme",
    "sg:classifiers":[
        {
            "category":"Wholesale",
            "subcategory":"Sporting Goods",
            "type":"Manufacturing & Wholesale Goods"
        }
    ],
    "sg:phone":"+32 52 47 85 22",
    "sg:postcode":"9220",
    "sg:province":"Oost-Vlaanderen",
    "sg:tags":[
        "sport-",
        "kampeermateriaal"
    ],
    "wof:name":"De Berghut",
    "wof:placetype":"venue"
},
  "geometry": {"coordinates":[4.1365017891,51.0966644287],"type":"Point"}
}