{
  "type": "Feature",
  "properties": {
    "addr:full":"Venlosesteenweg 77 Kinrooi Limburg 3640",
    "addr:housenumber":"77",
    "addr:postcode":"3640",
    "addr:street":"Venlosesteenweg",
    "iso:country":"BE",
    "sg:address":"Venlosesteenweg 77",
    "sg:city":"Kinrooi",
    "sg:classifiers":[
        {
            "category":"Fast Food",
            "type":"Food & Drink"
        }
    ],
    "sg:phone":"+32 89 56 13 14",
    "sg:postcode":"3640",
    "sg:province":"Limburg",
    "sg:tags":[
        "meeneem",
        "restaurant"
    ],
    "wof:name":"Lotus",
    "wof:placetype":"venue"
},
  "geometry": {"coordinates":[5.8018450737,51.1250648499],"type":"Point"}
}