{
  "type": "Feature",
  "properties": {
    "iso:country":"BE",
    "sg:address":"Avenue De La Citadelle 50",
    "sg:city":"Namur (jambes)",
    "sg:classifiers":[
        {
            "category":"Freight",
            "type":"Transportation"
        }
    ],
    "sg:phone":"+32 81 30 10 69",
    "sg:postcode":"5100",
    "sg:province":"Namur",
    "sg:tags":[
        "express",
        "transport"
    ],
    "wof:name":"Collignon Georges",
    "wof:placetype":"venue"
},
  "geometry": {"coordinates":[4.8713750839,50.4566345215],"type":"Point"}
}