{
  "type": "Feature",
  "properties": {
    "addr:full":"Route De L'etat 41 Lasne Brabant Wallon 1380",
    "addr:housenumber":"41",
    "addr:postcode":"1380",
    "addr:street":"Route De L'Etat",
    "iso:country":"BE",
    "sg:address":"Route De L'etat 41",
    "sg:city":"Lasne",
    "sg:orig_category":"Herstellingen and onderhoud aan huis voor voertuigen Metaalafval, schrootrecyclage and sloperijen",
    "sg:phone":"+32 2 633 51 86",
    "sg:postcode":"1380",
    "sg:province":"Brabant Wallon",
    "wof:name":"Jean-marie Langhendries",
    "wof:placetype":"venue"
},
  "geometry": {"coordinates":[4.4787259102,50.6808547974],"type":"Point"}
}