{
  "type": "Feature",
  "properties": {
    "iso:country":"BE",
    "sg:address":"Hemelhofweg 1",
    "sg:city":"Wevelgem (gullegem)",
    "sg:classifiers":[
        {
            "category":"Building & Trades",
            "subcategory":"Electrical",
            "type":"Services"
        }
    ],
    "sg:phone":"+32 56 42 64 27",
    "sg:postcode":"8560",
    "sg:province":"West-Vlaanderen",
    "sg:tags":[
        "electric",
        "-",
        "housewiring",
        "contractor"
    ],
    "wof:name":"Elektro - Goemaere",
    "wof:placetype":"venue"
},
  "geometry": {"coordinates":[3.1914629936,50.8370132446],"type":"Point"}
}