{
  "type": "Feature",
  "properties": {
    "iso:country":"BE",
    "sg:address":"Rue Du Bailli 22",
    "sg:city":"Elsene/ixelles",
    "sg:orig_category":"Fleurs and plantes",
    "sg:phone":"+32 2 648 11 84",
    "sg:postcode":"1050",
    "sg:province":"Bruxelles-Capitale",
    "wof:name":"Fleurs Du Matin",
    "wof:placetype":"venue"
},
  "geometry": {"coordinates":[4.3620100021,50.8265914917],"type":"Point"}
}