{
  "type": "Feature",
  "properties": {
    "iso:country":"BE",
    "sg:address":"Mortselsesteenweg 204",
    "sg:city":"Hove",
    "sg:classifiers":[
        {
            "category":"Health Services",
            "subcategory":"Health Practitioner",
            "type":"Services"
        }
    ],
    "sg:phone":"+32 3 455 47 69",
    "sg:postcode":"2540",
    "sg:province":"Antwerpen",
    "sg:tags":[
        "dietitian"
    ],
    "wof:name":"Sprengers H",
    "wof:placetype":"venue"
},
  "geometry": {"coordinates":[4.470676899,51.161605835],"type":"Point"}
}