{
  "type": "Feature",
  "properties": {
    "iso:country":"BE",
    "sg:address":"Robert Molsstraat 26",
    "sg:city":"Antwerpen",
    "sg:orig_category":"Artiesten and kunstenaars",
    "sg:phone":"+32 3 237 31 87",
    "sg:postcode":"2018",
    "sg:province":"Antwerpen",
    "wof:name":"Brigitte De Man",
    "wof:placetype":"venue"
},
  "geometry": {"coordinates":[4.4022011757,51.2005233765],"type":"Point"}
}