{
  "type": "Feature",
  "properties": {
    "addr:full":"Spekestraat 1 Tessenderlo Limburg 3980",
    "addr:housenumber":"1",
    "addr:postcode":"3980",
    "addr:street":"Spekestraat",
    "iso:country":"BE",
    "sg:address":"Spekestraat 1",
    "sg:city":"Tessenderlo",
    "sg:orig_category":"Kinderopvang",
    "sg:phone":"+32 13 66 42 89",
    "sg:postcode":"3980",
    "sg:province":"Limburg",
    "wof:name":"'t Nestje",
    "wof:placetype":"venue"
},
  "geometry": {"coordinates":[5.1258301735,51.0671386719],"type":"Point"}
}