{
  "type": "Feature",
  "properties": {
    "addr:full":"Comouthstrasse 24 Kelmis Li\u00e8ge 4720",
    "addr:housenumber":"24",
    "addr:postcode":"4720",
    "addr:street":"Comouthstrasse",
    "iso:country":"BE",
    "sg:address":"Comouthstrasse 24",
    "sg:city":"Kelmis",
    "sg:classifiers":[
        {
            "category":"Health Services",
            "subcategory":"Nursing And Care Facility",
            "type":"Services"
        }
    ],
    "sg:phone":"+32 87 65 87 69",
    "sg:postcode":"4720",
    "sg:province":"Li\u00e8ge",
    "sg:tags":[
        "home"
    ],
    "wof:name":"Lemmens-dumbruch",
    "wof:placetype":"venue"
},
  "geometry": {"coordinates":[6.0121908188,50.7216796875],"type":"Point"}
}