{
  "type": "Feature",
  "properties": {
    "iso:country":"BE",
    "sg:address":"Kazerneweg 35",
    "sg:city":"Kapellen (mariaburg)",
    "sg:classifiers":[
        {
            "category":"Social Services",
            "type":"Services"
        }
    ],
    "sg:phone":"+32 3 660 19 00",
    "sg:postcode":"2950",
    "sg:province":"Antwerpen",
    "wof:name":"Onthaalcentrum Voor Vluchtelingen",
    "wof:placetype":"venue"
},
  "geometry": {"coordinates":[4.4534602165,51.3111000061],"type":"Point"}
}