{
  "type": "Feature",
  "properties": {
    "addr:full":"Bredabaan 967 Schoten Antwerpen 2900",
    "addr:housenumber":"967",
    "addr:postcode":"2900",
    "addr:street":"Bredabaan",
    "iso:country":"BE",
    "sg:address":"Bredabaan 967",
    "sg:city":"Schoten",
    "sg:orig_category":"Onderdelen and accessoires voor auto's",
    "sg:phone":"+32 3 641 66 00",
    "sg:postcode":"2900",
    "sg:province":"Antwerpen",
    "wof:name":"Auto 5",
    "wof:placetype":"venue"
},
  "geometry": {"coordinates":[4.4634990692,51.2585601807],"type":"Point"}
}