{
  "type": "Feature",
  "properties": {
    "addr:full":"Rue De Tellin 1 Tellin (bure) Luxembourg 6927",
    "addr:housenumber":"1",
    "addr:postcode":"6927",
    "addr:street":"Rue De Tellin",
    "iso:country":"BE",
    "sg:address":"Rue De Tellin 1",
    "sg:city":"Tellin (bure)",
    "sg:classifiers":[
        {
            "category":"Retail",
            "subcategory":"Auto Repair",
            "type":"Services"
        }
    ],
    "sg:phone":"+32 84 36 65 52",
    "sg:postcode":"6927",
    "sg:province":"Luxembourg",
    "sg:tags":[
        "garage"
    ],
    "wof:name":"Rondeaux Sprl",
    "wof:placetype":"venue"
},
  "geometry": {"coordinates":[5.2595949173,50.0881919861],"type":"Point"}
}