{
  "type": "Feature",
  "properties": {
    "iso:country":"BE",
    "sg:address":"Maantjessteenweg 194",
    "sg:city":"Merksem",
    "sg:classifiers":[
        {
            "category":"Shopping",
            "subcategory":"Computers & Home Electronics",
            "type":"Retail Goods"
        }
    ],
    "sg:phone":"+32 3 645 54 99",
    "sg:postcode":"2170",
    "sg:province":"Antwerpen",
    "sg:tags":[
        "nec",
        "computerapparatuur",
        "packard",
        "bell"
    ],
    "wof:name":"Pema Systems",
    "wof:placetype":"venue"
},
  "geometry": {"coordinates":[4.4376888275,51.2547721863],"type":"Point"}
}