{
  "type": "Feature",
  "properties": {
    "iso:country":"BE",
    "sg:address":"Rue Des Morts 12a",
    "sg:city":"Tournai (blandain - Hertain)",
    "sg:classifiers":[
        {
            "category":"Home & Garden",
            "subcategory":"Building Materials",
            "type":"Retail Goods"
        }
    ],
    "sg:phone":"+32 69 84 61 75",
    "sg:postcode":"7522",
    "sg:province":"Hainaut",
    "sg:tags":[
        "house"
    ],
    "wof:name":"Moyart R",
    "wof:placetype":"venue"
},
  "geometry": {"coordinates":[3.2998220921,50.5959892273],"type":"Point"}
}