{
  "type": "Feature",
  "properties": {
    "iso:country":"BE",
    "sg:address":"Chauss\u00c9e De Ninove 510",
    "sg:city":"Bruxelles",
    "sg:orig_category":"Rev\u00eatements de sols and murs. Textiles. Quincailleries. Eclairage et \u00e9quipements du foyer",
    "sg:phone":"+32 2 521 52 99",
    "sg:postcode":"1070",
    "sg:province":"Bruxelles-Capitale",
    "wof:name":"Home Market",
    "wof:placetype":"venue"
},
  "geometry": {"coordinates":[4.3062958717,50.8473930359],"type":"Point"}
}