{
  "type": "Feature",
  "properties": {
    "addr:full":"Rue De L'association 49 Brussel/bruxelles Bruxelles-Capitale 1000",
    "addr:housenumber":"49",
    "addr:postcode":"1000",
    "addr:street":"Rue De L'Association;/",
    "iso:country":"BE",
    "sg:address":"Rue De L'association 49",
    "sg:city":"Brussel/bruxelles",
    "sg:orig_category":"Mat\u00e9riel m\u00e9dical and orthop\u00e9dique and proth\u00e8ses Fab",
    "sg:phone":"+32 2 219 64 78",
    "sg:postcode":"1000",
    "sg:province":"Bruxelles-Capitale",
    "wof:name":"Labo Dent. Suray-o.d.f.",
    "wof:placetype":"venue"
},
  "geometry": {"coordinates":[4.3658599854,50.8507347107],"type":"Point"}
}