{
  "type": "Feature",
  "properties": {
    "iso:country":"BE",
    "sg:address":"Steendonkstraat 66",
    "sg:city":"Temse",
    "sg:orig_category":"Eleveurs de bovins. Eleveurs and marchands de porcs",
    "sg:phone":"+32 3 771 08 27",
    "sg:postcode":"9140",
    "sg:province":"Oost-Vlaanderen",
    "wof:name":"Jul. Samson",
    "wof:placetype":"venue"
},
  "geometry": {"coordinates":[4.2186141014,51.1607322693],"type":"Point"}
}