{
  "type": "Feature",
  "properties": {
    "iso:country":"BE",
    "sg:address":"Van Halmalelaan 7",
    "sg:city":"Ranst (oelegem)",
    "sg:classifiers":[
        {
            "category":"Manufacturing",
            "subcategory":"Tobacco Products",
            "type":"Manufacturing & Wholesale Goods"
        }
    ],
    "sg:phone":"+32 3 383 67 61",
    "sg:postcode":"2520",
    "sg:province":"Antwerpen",
    "sg:tags":[
        "fertilizer",
        "merchant",
        "-"
    ],
    "wof:name":"Simons G",
    "wof:placetype":"venue"
},
  "geometry": {"coordinates":[4.5819759369,51.2179107666],"type":"Point"}
}