{
  "type": "Feature",
  "properties": {
    "addr:full":"Diksmuidseweg 10 Nieuwpoort West-Vlaanderen 8620",
    "addr:housenumber":"10",
    "addr:postcode":"8620",
    "addr:street":"Diksmuidseweg",
    "iso:country":"BE",
    "sg:address":"Diksmuidseweg 10",
    "sg:city":"Nieuwpoort",
    "sg:orig_category":"Antiquit\u00e9s",
    "sg:phone":"+32 58 23 34 37",
    "sg:postcode":"8620",
    "sg:province":"West-Vlaanderen",
    "wof:name":"Philippe Beguin",
    "wof:placetype":"venue"
},
  "geometry": {"coordinates":[2.767580986,51.1004447937],"type":"Point"}
}