{
  "type": "Feature",
  "properties": {
    "addr:full":"Rue Les Oies 32 Chaudfontaine Li\u00e8ge 4052",
    "addr:housenumber":"32",
    "addr:postcode":"4052",
    "addr:street":"Rue Les Oies",
    "iso:country":"BE",
    "sg:address":"Rue Les Oies 32",
    "sg:city":"Chaudfontaine",
    "sg:orig_category":"Glaszetten and glaswerk",
    "sg:phone":"+32 4 368 79 77",
    "sg:postcode":"4052",
    "sg:province":"Li\u00e8ge",
    "wof:name":"Atelier Art Pirotte J.m.",
    "wof:placetype":"venue"
},
  "geometry": {"coordinates":[5.620762825,50.5673599243],"type":"Point"}
}