{
  "type": "Feature",
  "properties": {
    "addr:full":"Rue De L'argili\u00e8re 4 Mons (jemappes) Hainaut 7012",
    "addr:housenumber":"4",
    "addr:postcode":"7012",
    "addr:street":"Rue De L'Argilie \u0300Re",
    "iso:country":"BE",
    "sg:address":"Rue De L'argili\u00e8re 4",
    "sg:city":"Mons (jemappes)",
    "sg:classifiers":[
        {
            "category":"Retail",
            "subcategory":"Auto Repair",
            "type":"Services"
        }
    ],
    "sg:phone":"+32 65 82 41 36",
    "sg:postcode":"7012",
    "sg:province":"Hainaut",
    "sg:tags":[
        "lpg",
        "automobile",
        "-",
        "system"
    ],
    "wof:name":"Maton Lpg Sprlu",
    "wof:placetype":"venue"
},
  "geometry": {"coordinates":[3.8919980526,50.4454078674],"type":"Point"}
}