{
  "type": "Feature",
  "properties": {
    "addr:full":"Rerum Novarumstraat 20 Blankenberge West-Vlaanderen 8370",
    "addr:housenumber":"20",
    "addr:postcode":"8370",
    "addr:street":"Rerum Novarumstraat",
    "iso:country":"BE",
    "sg:address":"Rerum Novarumstraat 20",
    "sg:city":"Blankenberge",
    "sg:orig_category":"Binnenhuisarchitecten",
    "sg:phone":"+32 50 41 42 57",
    "sg:postcode":"8370",
    "sg:province":"West-Vlaanderen",
    "wof:name":"Crispijn",
    "wof:placetype":"venue"
},
  "geometry": {"coordinates":[3.1365959644,51.3075027466],"type":"Point"}
}