{
  "type": "Feature",
  "properties": {
    "iso:country":"BE",
    "sg:address":"Sint-annakerkstraat 114",
    "sg:city":"Koekelberg",
    "sg:orig_category":"Installatie van metalen schrijnwerk",
    "sg:phone":"+32 2 410 69 07",
    "sg:postcode":"1081",
    "sg:province":"Bruxelles-Capitale",
    "wof:name":"Ch\u00c2ssis-tec",
    "wof:placetype":"venue"
},
  "geometry": {"coordinates":[4.3304572105,50.858959198],"type":"Point"}
}