{
  "type": "Feature",
  "properties": {
    "addr:full":"Rue De Fl\u00c9ron 84 Fleron Li\u00e8ge 4623",
    "addr:housenumber":"84",
    "addr:postcode":"4623",
    "addr:street":"Rue De Fle\u0301Ron",
    "iso:country":"BE",
    "sg:address":"Rue De Fl\u00c9ron 84",
    "sg:city":"Fleron",
    "sg:orig_category":"Elektrische installaties voor woningen",
    "sg:phone":"+32 4 358 42 36",
    "sg:postcode":"4623",
    "sg:province":"Li\u00e8ge",
    "wof:name":"Donato Potenza",
    "wof:placetype":"venue"
},
  "geometry": {"coordinates":[5.6785302162,50.6081771851],"type":"Point"}
}