{
  "type": "Feature",
  "properties": {
    "addr:full":"Zandstraat 15 Brugge (sint-andries) West-Vlaanderen 8200",
    "addr:housenumber":"15",
    "addr:postcode":"8200",
    "addr:street":"Zandstraat",
    "iso:country":"BE",
    "sg:address":"Zandstraat 15",
    "sg:city":"Brugge (sint-andries)",
    "sg:classifiers":[
        {
            "category":"Banks & Credit Unions",
            "subcategory":"Investment Brokerage",
            "type":"Services"
        }
    ],
    "sg:phone":"+32 50 31 63 63",
    "sg:postcode":"8200",
    "sg:province":"West-Vlaanderen",
    "sg:tags":[
        "coil",
        "electric",
        "winding"
    ],
    "wof:name":"Detroit (the)",
    "wof:placetype":"venue"
},
  "geometry": {"coordinates":[3.2047719955,51.2030181885],"type":"Point"}
}