{
  "type": "Feature",
  "properties": {
    "iso:country":"BE",
    "sg:address":"Rue Neuve 23",
    "sg:city":"Pepinster",
    "sg:classifiers":[
        {
            "category":"Restaurant",
            "type":"Food & Drink"
        }
    ],
    "sg:phone":"+32 87 46 17 89",
    "sg:postcode":"4860",
    "sg:province":"Li\u00e8ge",
    "wof:name":"Secret De Polichinelle",
    "wof:placetype":"venue"
},
  "geometry": {"coordinates":[5.8031659126,50.5673751831],"type":"Point"}
}