{
  "type": "Feature",
  "properties": {
    "iso:country":"BE",
    "sg:address":"Neerzand 11",
    "sg:city":"Lille",
    "sg:classifiers":[
        {
            "category":"Home & Garden",
            "subcategory":"Building Materials",
            "type":"Retail Goods"
        }
    ],
    "sg:phone":"+32 14 41 46 05",
    "sg:postcode":"2275",
    "sg:province":"Antwerpen",
    "sg:tags":[
        "bathroom",
        "installation",
        "accessory"
    ],
    "wof:name":"Van Den Berghe I",
    "wof:placetype":"venue"
},
  "geometry": {"coordinates":[4.8279738426,51.217956543],"type":"Point"}
}