{
  "type": "Feature",
  "properties": {
    "addr:full":"Sint-truidersteenweg 10 Hasselt Limburg 3500",
    "addr:housenumber":"10",
    "addr:postcode":"3500",
    "addr:street":"Sint-Truidersteenweg",
    "iso:country":"BE",
    "sg:address":"Sint-truidersteenweg 10",
    "sg:city":"Hasselt",
    "sg:orig_category":"Avocats and conseillers juridiques",
    "sg:phone":"+32 11 23 30 64",
    "sg:postcode":"3500",
    "sg:province":"Limburg",
    "wof:name":"R. Demal",
    "wof:placetype":"venue"
},
  "geometry": {"coordinates":[5.3358168602,50.9265365601],"type":"Point"}
}