{
  "type": "Feature",
  "properties": {
    "addr:full":"Rue Des Mays 27 Fontaine-l'ev\u00eaque Hainaut 6140",
    "addr:housenumber":"27",
    "addr:postcode":"6140",
    "addr:street":"Rue Des Mays;\u0302Que Hainaut",
    "iso:country":"BE",
    "sg:address":"Rue Des Mays 27",
    "sg:city":"Fontaine-l'ev\u00eaque",
    "sg:classifiers":[
        {
            "category":"Animal Shelter",
            "type":"Public Place"
        }
    ],
    "sg:phone":"+32 71 54 27 61",
    "sg:postcode":"6140",
    "sg:province":"Hainaut",
    "wof:name":"Chenil Des Mays",
    "wof:placetype":"venue"
},
  "geometry": {"coordinates":[-111.9644622803,46.2507972717],"type":"Point"}
}