{
  "type": "Feature",
  "properties": {
    "addr:full":"Avenue De Messidor 215 Box 1 Bruxelles (uccle) Bruxelles-Capitale 1180",
    "addr:housenumber":"215;1",
    "addr:postcode":"1180",
    "addr:street":"Avenue De Messidor;Box",
    "iso:country":"BE",
    "sg:address":"Avenue De Messidor 215 Box 1",
    "sg:city":"Bruxelles (uccle)",
    "sg:classifiers":[
        {
            "category":"Health Services",
            "subcategory":"Health Practitioner",
            "type":"Services"
        }
    ],
    "sg:phone":"+32 2 344 73 70",
    "sg:postcode":"1180",
    "sg:province":"Bruxelles-Capitale",
    "sg:tags":[
        "physiotherapist"
    ],
    "wof:name":"Malm T",
    "wof:placetype":"venue"
},
  "geometry": {"coordinates":[4.3511800766,50.8111457825],"type":"Point"}
}