{
  "type": "Feature",
  "properties": {
    "addr:full":"Voordestraat 21 Wetteren Oost-Vlaanderen 9230",
    "addr:housenumber":"21",
    "addr:postcode":"9230",
    "addr:street":"Voordestraat",
    "iso:country":"BE",
    "sg:address":"Voordestraat 21",
    "sg:city":"Wetteren",
    "sg:orig_category":"Eleveurs de bovins. Eleveurs and marchands de porcs",
    "sg:phone":"+32 9 369 21 44",
    "sg:postcode":"9230",
    "sg:province":"Oost-Vlaanderen",
    "wof:name":"Daniel Oosterlinck",
    "wof:placetype":"venue"
},
  "geometry": {"coordinates":[3.8553318977,51.0102462769],"type":"Point"}
}