{
  "type": "Feature",
  "properties": {
    "iso:country":"BE",
    "sg:address":"De Villegaslaan 38b4",
    "sg:city":"Ganshoren",
    "sg:orig_category":"Belastingconsulenten Diverse juridische dienstverlening",
    "sg:phone":"+32 2 426 63 72",
    "sg:postcode":"1083",
    "sg:province":"Bruxelles-Capitale",
    "wof:name":"Roberto Trappolini",
    "wof:placetype":"venue"
},
  "geometry": {"coordinates":[4.3088741302,50.8709411621],"type":"Point"}
}