{
  "type": "Feature",
  "properties": {
    "addr:full":"Avekapellestraat 15 Veurne West-Vlaanderen 8630",
    "addr:housenumber":"15",
    "addr:postcode":"8630",
    "addr:street":"Avekapellestraat",
    "iso:country":"BE",
    "sg:address":"Avekapellestraat 15",
    "sg:city":"Veurne",
    "sg:orig_category":"Installation \u00e9lectrique r\u00e9sidentielle",
    "sg:phone":"+32 58 31 52 65",
    "sg:postcode":"8630",
    "sg:province":"West-Vlaanderen",
    "wof:name":"Samalec",
    "wof:placetype":"venue"
},
  "geometry": {"coordinates":[2.7327640057,51.0675773621],"type":"Point"}
}