{
  "type": "Feature",
  "properties": {
    "addr:full":"Hendrik Heymanplein 7 Sint-niklaas Oost-Vlaanderen 9100",
    "addr:housenumber":"7",
    "addr:postcode":"9100",
    "addr:street":"Heymanplein",
    "iso:country":"BE",
    "sg:address":"Hendrik Heymanplein 7",
    "sg:city":"Sint-niklaas",
    "sg:classifiers":[
        {
            "category":"Bars & Pubs",
            "type":"Food & Drink"
        }
    ],
    "sg:phone":"+32 3 778 17 71",
    "sg:postcode":"9100",
    "sg:province":"Oost-Vlaanderen",
    "wof:name":"Gildenhuis",
    "wof:placetype":"venue"
},
  "geometry": {"coordinates":[4.1394891739,51.1621513367],"type":"Point"}
}