{
  "type": "Feature",
  "properties": {
    "iso:country":"BE",
    "sg:address":"Pol De Montstraat 28",
    "sg:city":"Ternat",
    "sg:orig_category":"Entretien and r\u00e9parations de voitures",
    "sg:phone":"+32 2 582 45 66",
    "sg:postcode":"1741",
    "sg:province":"Vlaams-Brabant",
    "wof:name":"J. Geerooms",
    "wof:placetype":"venue"
},
  "geometry": {"coordinates":[4.1609859467,50.8517837524],"type":"Point"}
}