{
  "type": "Feature",
  "properties": {
    "iso:country":"BE",
    "sg:address":"Leuvensesteenweg 110",
    "sg:city":"Diest",
    "sg:classifiers":[
        {
            "category":"Retail",
            "subcategory":"Laundry & Dry Cleaning",
            "type":"Services"
        }
    ],
    "sg:phone":"+32 13 33 64 07",
    "sg:postcode":"3290",
    "sg:province":"Vlaams-Brabant",
    "sg:tags":[
        "dyer",
        "cleaner"
    ],
    "wof:name":"Bubbels En Co",
    "wof:placetype":"venue"
},
  "geometry": {"coordinates":[5.0409479141,50.974697113],"type":"Point"}
}