{
  "type": "Feature",
  "properties": {
    "addr:full":"Rue Aux Fleurs 42 Binche (leval-trahegnies) Hainaut 7134",
    "addr:housenumber":"42",
    "addr:postcode":"7134",
    "addr:street":"Rue Aux Fleurs",
    "iso:country":"BE",
    "sg:address":"Rue Aux Fleurs 42",
    "sg:city":"Binche (leval-trahegnies)",
    "sg:classifiers":[
        {
            "category":"Real Estate",
            "subcategory":"Surveying",
            "type":"Services"
        }
    ],
    "sg:phone":"+32 64 33 69 71",
    "sg:postcode":"7134",
    "sg:province":"Hainaut",
    "sg:tags":[
        "surveyor",
        "land"
    ],
    "wof:name":"Saldi Nicola",
    "wof:placetype":"venue"
},
  "geometry": {"coordinates":[4.2175779343,50.4159622192],"type":"Point"}
}