{
  "type": "Feature",
  "properties": {
    "addr:full":"Avenue De La Couronne 313 Bruxelles (ixelles) Bruxelles-Capitale 1050",
    "addr:housenumber":"313",
    "addr:postcode":"1050",
    "addr:street":"Avenue De La Couronne",
    "iso:country":"BE",
    "sg:address":"Avenue De La Couronne 313",
    "sg:city":"Bruxelles (ixelles)",
    "sg:classifiers":[
        {
            "category":"Cafe",
            "type":"Food & Drink"
        }
    ],
    "sg:phone":"+32 2 644 38 87",
    "sg:postcode":"1050",
    "sg:province":"Bruxelles-Capitale",
    "sg:tags":[
        "snack-bars"
    ],
    "wof:name":"Spirou (le)",
    "wof:placetype":"venue"
},
  "geometry": {"coordinates":[4.3912339211,50.8193435669],"type":"Point"}
}