{
  "type": "Feature",
  "properties": {
    "iso:country":"BE",
    "sg:address":"Langdorpsesteenweg 129",
    "sg:city":"Aarschot",
    "sg:classifiers":[
        {
            "category":"Health Services",
            "subcategory":"Hospital",
            "type":"Services"
        }
    ],
    "sg:phone":"+32 16 56 70 92",
    "sg:postcode":"3200",
    "sg:province":"Vlaams-Brabant",
    "sg:tags":[
        "ambulance"
    ],
    "wof:name":"Ziekenwagen Aarschot",
    "wof:placetype":"venue"
},
  "geometry": {"coordinates":[4.8478198051,50.9935379028],"type":"Point"}
}