{
  "type": "Feature",
  "properties": {
    "iso:country":"BE",
    "sg:address":"Rue Berkendael 175",
    "sg:city":"Elsene/ixelles",
    "sg:orig_category":"Instituts de beaut\u00e9. M\u00e9decines alternatives",
    "sg:phone":"+32 2 344 22 74",
    "sg:postcode":"1050",
    "sg:province":"Bruxelles-Capitale",
    "wof:name":"Institut L\u00b4ornatrice",
    "wof:placetype":"venue"
},
  "geometry": {"coordinates":[4.3518538475,50.8167953491],"type":"Point"}
}