{
  "type": "Feature",
  "properties": {
    "iso:country":"BE",
    "sg:address":"Nijverheidsstraat 28",
    "sg:city":"Malle (oostmalle)",
    "sg:classifiers":[
        {
            "category":"Wholesale",
            "subcategory":"Meat",
            "type":"Manufacturing & Wholesale Goods"
        }
    ],
    "sg:phone":"+32 3 311 66 60",
    "sg:postcode":"2390",
    "sg:province":"Antwerpen",
    "sg:tags":[
        "whol",
        "-"
    ],
    "wof:name":"Der Kinderen & Co Bvba",
    "wof:placetype":"venue"
},
  "geometry": {"coordinates":[4.7126998901,51.2927398682],"type":"Point"}
}