{
  "type": "Feature",
  "properties": {
    "iso:country":"BE",
    "sg:address":"Kasteellei 13",
    "sg:city":"Brasschaat",
    "sg:orig_category":"Instituts de beaut\u00e9",
    "sg:phone":"+32 3 645 31 62",
    "sg:postcode":"2930",
    "sg:province":"Antwerpen",
    "wof:name":"Van Antwerpen-westdorp",
    "wof:placetype":"venue"
},
  "geometry": {"coordinates":[4.4633469582,51.2747840881],"type":"Point"}
}