{
  "type": "Feature",
  "properties": {
    "addr:full":"Dasstraat 19 Wommelgem Antwerpen 2160",
    "addr:housenumber":"19",
    "addr:postcode":"2160",
    "addr:street":"Dasstraat",
    "iso:country":"BE",
    "sg:address":"Dasstraat 19",
    "sg:city":"Wommelgem",
    "sg:classifiers":[
        {
            "category":"Retail",
            "subcategory":"Repair Shop",
            "type":"Services"
        }
    ],
    "sg:phone":"+32 3 353 02 37",
    "sg:postcode":"2160",
    "sg:province":"Antwerpen",
    "sg:tags":[
        "photographic",
        "equipment",
        "-",
        "accessory"
    ],
    "wof:name":"Smekens C",
    "wof:placetype":"venue"
},
  "geometry": {"coordinates":[4.5212659836,51.2038993835],"type":"Point"}
}