{
  "type": "Feature",
  "properties": {
    "addr:full":"Antwerpsestraat 36 Niel Antwerpen 2845",
    "addr:housenumber":"36",
    "addr:postcode":"2845",
    "addr:street":"Antwerpsestraat",
    "iso:country":"BE",
    "sg:address":"Antwerpsestraat 36",
    "sg:city":"Niel",
    "sg:classifiers":[
        {
            "category":"Food & Beverages",
            "subcategory":"Groceries & Convenience Stores",
            "type":"Retail Goods"
        }
    ],
    "sg:phone":"+32 3 888 12 41",
    "sg:postcode":"2845",
    "sg:province":"Antwerpen",
    "sg:tags":[
        "grocer"
    ],
    "wof:name":"Ramael A",
    "wof:placetype":"venue"
},
  "geometry": {"coordinates":[4.3302741051,51.1085624695],"type":"Point"}
}