{
  "type": "Feature",
  "properties": {
    "iso:country":"BE",
    "sg:address":"Peperstraat 19",
    "sg:city":"Zwalm",
    "sg:orig_category":"Entretien and r\u00e9parations de voitures",
    "sg:phone":"+32 55 49 84 04",
    "sg:postcode":"9636",
    "sg:province":"Oost-Vlaanderen",
    "wof:name":"Ignace Desmet",
    "wof:placetype":"venue"
},
  "geometry": {"coordinates":[3.6816310883,50.8931427002],"type":"Point"}
}