{
  "type": "Feature",
  "properties": {
    "iso:country":"BE",
    "sg:address":"Chauss\u00e9e De L'europe 20",
    "sg:city":"Couvin (cul-des-sarts)",
    "sg:classifiers":[
        {
            "category":"Retail",
            "subcategory":"Animal Services",
            "type":"Services"
        }
    ],
    "sg:phone":"+32 60 37 85 90",
    "sg:postcode":"5660",
    "sg:province":"Namur",
    "sg:tags":[
        "grooming",
        "-",
        "dog"
    ],
    "wof:name":"Hollywouf Sprl",
    "wof:placetype":"venue"
},
  "geometry": {"coordinates":[4.4537410736,49.9605827332],"type":"Point"}
}