{
  "type": "Feature",
  "properties": {
    "iso:country":"BE",
    "sg:address":"Rue De Qui\u00e9vrain 7",
    "sg:city":"Boussu",
    "sg:classifiers":[
        {
            "category":"Insurance",
            "subcategory":"Insurance Agent",
            "type":"Services"
        }
    ],
    "sg:phone":"+32 65 79 45 29",
    "sg:postcode":"7300",
    "sg:province":"Hainaut",
    "sg:tags":[
        "broker"
    ],
    "wof:name":"Andries & Fils Scrl",
    "wof:placetype":"venue"
},
  "geometry": {"coordinates":[3.7922871113,50.4293823242],"type":"Point"}
}