{
  "type": "Feature",
  "properties": {
    "iso:country":"BE",
    "sg:address":"Rue De Von\u00e8che 136",
    "sg:city":"Daverdisse (haut-fays)",
    "sg:classifiers":[
        {
            "category":"Building & Trades",
            "subcategory":"Construction",
            "type":"Services"
        }
    ],
    "sg:phone":"+32 61 58 87 17",
    "sg:postcode":"6929",
    "sg:province":"Luxembourg",
    "sg:tags":[
        "installation",
        "-",
        "central",
        "heating"
    ],
    "wof:name":"Giard Christian",
    "wof:placetype":"venue"
},
  "geometry": {"coordinates":[5.1175727844,50.0223236084],"type":"Point"}
}