{
  "type": "Feature",
  "properties": {
    "addr:full":"Rue Des Echevins 1ba7 Elsene/ixelles Bruxelles-Capitale 1050",
    "addr:postcode":"1050",
    "addr:street":"Rue Des Echevins 1Ba7",
    "iso:country":"BE",
    "sg:address":"Rue Des Echevins 1ba7",
    "sg:city":"Elsene/ixelles",
    "sg:orig_category":"Avocats and conseillers juridiques",
    "sg:phone":"+32 2 375 86 25",
    "sg:postcode":"1050",
    "sg:province":"Bruxelles-Capitale",
    "wof:name":"Dietrich Traudt",
    "wof:placetype":"venue"
},
  "geometry": {"coordinates":[4.37606287,50.8237304688],"type":"Point"}
}