{
  "type": "Feature",
  "properties": {
    "iso:country":"BE",
    "sg:address":"Rue De Loverval 38",
    "sg:city":"Chatelet",
    "sg:orig_category":"Avocats and conseillers juridiques",
    "sg:phone":"+32 71 38 84 06",
    "sg:postcode":"6200",
    "sg:province":"Hainaut",
    "wof:name":"H. Flamion",
    "wof:placetype":"venue"
},
  "geometry": {"coordinates":[4.5170297623,50.4026451111],"type":"Point"}
}