{
  "type": "Feature",
  "properties": {
    "addr:full":"Place Du Th\u00c9atre 2 Namur Namur 5000",
    "addr:housenumber":"2",
    "addr:postcode":"5000",
    "addr:street":"Place Du The\u0301Atre",
    "iso:country":"BE",
    "sg:address":"Place Du Th\u00c9atre 2",
    "sg:city":"Namur",
    "sg:orig_category":"Agences de relations publiques",
    "sg:phone":"+32 81 25 61 74",
    "sg:postcode":"5000",
    "sg:province":"Namur",
    "wof:name":"Th\u00c9\u00c2tre Evenements",
    "wof:placetype":"venue"
},
  "geometry": {"coordinates":[4.8674402237,50.4641647339],"type":"Point"}
}