{
  "type": "Feature",
  "properties": {
    "iso:country":"BE",
    "sg:address":"Herman Lovelingstraat 1",
    "sg:city":"Nevele",
    "sg:orig_category":"Goederenvervoer over de weg Koerierbedrijven",
    "sg:phone":"+32 9 371 56 78",
    "sg:postcode":"9850",
    "sg:province":"Oost-Vlaanderen",
    "wof:name":"Verthriest & Zoon",
    "wof:placetype":"venue"
},
  "geometry": {"coordinates":[3.5479130745,51.0354003906],"type":"Point"}
}