{
  "type": "Feature",
  "properties": {
    "iso:country":"BE",
    "sg:address":"Kauwlei 1",
    "sg:city":"Kontich",
    "sg:classifiers":[
        {
            "category":"Retail",
            "subcategory":"Auto Repair",
            "type":"Services"
        }
    ],
    "sg:phone":"+32 3 457 66 84",
    "sg:postcode":"2550",
    "sg:province":"Antwerpen",
    "sg:tags":[
        "automobile-body"
    ],
    "wof:name":"Verhulst B",
    "wof:placetype":"venue"
},
  "geometry": {"coordinates":[4.4702382088,51.1348876953],"type":"Point"}
}