{
  "type": "Feature",
  "properties": {
    "addr:full":"Molenstraat 39 Londerzeel (groot) Vlaams-Brabant 1840",
    "addr:housenumber":"39;1840",
    "addr:street":"Molenstraat;Groot Vlaams-Brabant",
    "iso:country":"BE",
    "sg:address":"Molenstraat 39",
    "sg:city":"Londerzeel (groot)",
    "sg:orig_category":"Supermarkten",
    "sg:phone":"+32 52 30 58 77",
    "sg:postcode":"1840",
    "sg:province":"Vlaams-Brabant",
    "wof:name":"Colruyt",
    "wof:placetype":"venue"
},
  "geometry": {"coordinates":[4.3002409935,51.0041542053],"type":"Point"}
}