{
  "type": "Feature",
  "properties": {
    "iso:country":"BE",
    "sg:address":"Emiel Stalmanslaan 12",
    "sg:city":"Westerlo",
    "sg:orig_category":"Diverse bouwafwerking and reiniging Pleisterwerk",
    "sg:phone":"+32 14 26 54 37",
    "sg:postcode":"2260",
    "sg:province":"Antwerpen",
    "wof:name":"Ceuppens Gevelwerken",
    "wof:placetype":"venue"
},
  "geometry": {"coordinates":[4.8657298088,51.1257896423],"type":"Point"}
}