{
  "type": "Feature",
  "properties": {
    "addr:full":"Rue Du Rat D'eau 56 Honnelles Hainaut 7387",
    "addr:housenumber":"56",
    "addr:postcode":"7387",
    "addr:street":"Rue Du Rat D'Eau;Hainaut",
    "iso:country":"BE",
    "sg:address":"Rue Du Rat D'eau 56",
    "sg:city":"Honnelles",
    "sg:orig_category":"Epiceries",
    "sg:phone":"+32 65 65 93 38",
    "sg:postcode":"7387",
    "sg:province":"Hainaut",
    "wof:name":"Battard",
    "wof:placetype":"venue"
},
  "geometry": {"coordinates":[3.7829239368,50.3538551331],"type":"Point"}
}