{
  "type": "Feature",
  "properties": {
    "addr:full":"Industriepark 59 Beernem West-Vlaanderen 8730",
    "addr:housenumber":"59",
    "addr:postcode":"8730",
    "addr:street":"Industriepark",
    "iso:country":"BE",
    "sg:address":"Industriepark 59",
    "sg:city":"Beernem",
    "sg:orig_category":"Installatie van houten of kunststof schrijnwerk",
    "sg:phone":"+32 50 79 02 19",
    "sg:postcode":"8730",
    "sg:province":"West-Vlaanderen",
    "wof:name":"Ronny Willem",
    "wof:placetype":"venue"
},
  "geometry": {"coordinates":[3.3459091187,51.1249313354],"type":"Point"}
}