{
  "type": "Feature",
  "properties": {
    "iso:country":"BE",
    "sg:address":"Graaf De Smet De Naeyerlaan 95",
    "sg:city":"Kortrijk",
    "sg:classifiers":[
        {
            "category":"Communications",
            "subcategory":"Film & Video Production",
            "type":"Services"
        }
    ],
    "sg:phone":"+32 56 35 23 89",
    "sg:postcode":"8500",
    "sg:province":"West-Vlaanderen",
    "sg:tags":[
        "multimedia",
        "-",
        "system"
    ],
    "wof:name":"Point X Multimedia",
    "wof:placetype":"venue"
},
  "geometry": {"coordinates":[3.2574720383,50.8351325989],"type":"Point"}
}