{
  "type": "Feature",
  "properties": {
    "iso:country":"BE",
    "sg:address":"Ommegangstraat 14",
    "sg:city":"Geraardsbergen (ophasselt)",
    "sg:classifiers":[
        {
            "category":"Health Services",
            "subcategory":"Dentist",
            "type":"Services"
        }
    ],
    "sg:phone":"+32 54 50 14 03",
    "sg:postcode":"9500",
    "sg:province":"Oost-Vlaanderen",
    "wof:name":"De Cock Roland",
    "wof:placetype":"venue"
},
  "geometry": {"coordinates":[3.8843801022,50.7716445923],"type":"Point"}
}