{
  "type": "Feature",
  "properties": {
    "addr:full":"Ramskapellestraat 126 Nieuwpoort (ramskapelle) West-Vlaanderen 8620",
    "addr:housenumber":"126",
    "addr:postcode":"8620",
    "addr:street":"Ramskapellestraat",
    "iso:country":"BE",
    "sg:address":"Ramskapellestraat 126",
    "sg:city":"Nieuwpoort (ramskapelle)",
    "sg:classifiers":[
        {
            "category":"Building & Trades",
            "subcategory":"Electrical",
            "type":"Services"
        }
    ],
    "sg:phone":"+32 58 23 47 73",
    "sg:postcode":"8620",
    "sg:province":"West-Vlaanderen",
    "sg:tags":[
        "-",
        "electric",
        "contractor"
    ],
    "wof:name":"Vandorpe Elektro",
    "wof:placetype":"venue"
},
  "geometry": {"coordinates":[2.764482975,51.1041374207],"type":"Point"}
}