{
  "type": "Feature",
  "properties": {
    "iso:country":"BE",
    "sg:address":"Chauss\u00e9e De Hannut 404",
    "sg:city":"Gr\u00e2ce-hollogne (bierset)",
    "sg:classifiers":[
        {
            "category":"Shopping",
            "subcategory":"Books",
            "type":"Retail Goods"
        }
    ],
    "sg:phone":"+32 4 250 44 84",
    "sg:postcode":"4460",
    "sg:province":"Li\u00e8ge",
    "sg:tags":[
        "bookseller"
    ],
    "wof:name":"Alphabet (l')",
    "wof:placetype":"venue"
},
  "geometry": {"coordinates":[5.448281765,50.6524772644],"type":"Point"}
}