{
  "type": "Feature",
  "properties": {
    "iso:country":"BE",
    "sg:address":"Massinweg 6",
    "sg:city":"Hasselt (stokrooie)",
    "sg:classifiers":[
        {
            "category":"Home & Garden",
            "subcategory":"Carpets & Floor Coverings",
            "type":"Retail Goods"
        }
    ],
    "sg:phone":"+32 11 87 41 06",
    "sg:postcode":"3511",
    "sg:province":"Limburg",
    "sg:tags":[
        "layer",
        "mosaicists"
    ],
    "wof:name":"De Vos Philip",
    "wof:placetype":"venue"
},
  "geometry": {"coordinates":[5.2835888863,50.9732551575],"type":"Point"}
}