{
  "type": "Feature",
  "properties": {
    "addr:full":"Vin\u00c2ve Des Str\u00c9ats 16 Verlaine Li\u00e8ge 4537",
    "addr:housenumber":"16",
    "addr:postcode":"4537",
    "addr:street":"Vina\u0302Ve Des Stre\u0301Ats",
    "iso:country":"BE",
    "sg:address":"Vin\u00c2ve Des Str\u00c9ats 16",
    "sg:city":"Verlaine",
    "sg:orig_category":"Paramedische behandelingen",
    "sg:phone":"+32 4 259 74 51",
    "sg:postcode":"4537",
    "sg:province":"Li\u00e8ge",
    "wof:name":"N. Roland",
    "wof:placetype":"venue"
},
  "geometry": {"coordinates":[5.3208317757,50.6059455872],"type":"Point"}
}