{
  "type": "Feature",
  "properties": {
    "addr:full":"Ter Ferrants 14 Kuurne West-Vlaanderen 8520",
    "addr:housenumber":"14",
    "addr:postcode":"8520",
    "iso:country":"BE",
    "sg:address":"Ter Ferrants 14",
    "sg:city":"Kuurne",
    "sg:orig_category":"Boucheries",
    "sg:phone":"+32 56 37 28 20",
    "sg:postcode":"8520",
    "sg:province":"West-Vlaanderen",
    "wof:name":"Renmans",
    "wof:placetype":"venue"
},
  "geometry": {"coordinates":[3.2651209831,50.8496322632],"type":"Point"}
}