{
  "type": "Feature",
  "properties": {
    "addr:full":"Rue De La R\u00e9gence 67 Bruxelles Bruxelles-Capitale 1000",
    "addr:housenumber":"67",
    "addr:postcode":"1000",
    "addr:street":"Rue De La Re\u0301Gence",
    "iso:country":"BE",
    "sg:address":"Rue De La R\u00e9gence 67",
    "sg:city":"Bruxelles",
    "sg:classifiers":[
        {
            "category":"Wholesale",
            "subcategory":"Books, Periodicals, & Newspapers",
            "type":"Manufacturing & Wholesale Goods"
        }
    ],
    "sg:phone":"+32 2 512 98 45",
    "sg:postcode":"1000",
    "sg:province":"Bruxelles-Capitale",
    "sg:tags":[
        "publisher"
    ],
    "wof:name":"Creadif-groep Bruylant Nv",
    "wof:placetype":"venue"
},
  "geometry": {"coordinates":[4.3531761169,50.8378944397],"type":"Point"}
}