{
  "type": "Feature",
  "properties": {
    "addr:full":"Rue Du Manoir 1ba Andenne Namur 5300",
    "addr:housenumber":"1ba",
    "addr:postcode":"5300",
    "addr:street":"Rue Du Manoir",
    "iso:country":"BE",
    "sg:address":"Rue Du Manoir 1ba",
    "sg:city":"Andenne",
    "sg:orig_category":"ACCOUNTANTS Boekhouders",
    "sg:phone":"+32 85 84 10 84",
    "sg:postcode":"5300",
    "sg:province":"Namur",
    "wof:name":"Jacques Gouverneur",
    "wof:placetype":"venue"
},
  "geometry": {"coordinates":[5.0841851234,50.4700126648],"type":"Point"}
}