{
  "type": "Feature",
  "properties": {
    "iso:country":"BE",
    "sg:address":"Rue De Florival 24",
    "sg:city":"Grez-doiceau (archennes)",
    "sg:classifiers":[
        {
            "category":"Retail",
            "subcategory":"Event Space",
            "type":"Services"
        }
    ],
    "sg:phone":"+32 10 84 18 53",
    "sg:postcode":"1390",
    "sg:province":"Brabant Wallon",
    "sg:tags":[
        "rental",
        "-",
        "hall"
    ],
    "wof:name":"Coulemont (le)",
    "wof:placetype":"venue"
},
  "geometry": {"coordinates":[4.6686549187,50.7528991699],"type":"Point"}
}