{
  "type": "Feature",
  "properties": {
    "addr:full":"Chauss\u00e9e De Ninove 361 Bruxelles (anderlecht) Bruxelles-Capitale 1070",
    "addr:housenumber":"361",
    "addr:postcode":"1070",
    "addr:street":"Chausse\u0301E De Ninove",
    "iso:country":"BE",
    "sg:address":"Chauss\u00e9e De Ninove 361",
    "sg:city":"Bruxelles (anderlecht)",
    "sg:classifiers":[
        {
            "category":"Personal",
            "subcategory":"Beauty Salon",
            "type":"Services"
        }
    ],
    "sg:phone":"+32 2 285 00 80",
    "sg:postcode":"1070",
    "sg:province":"Bruxelles-Capitale",
    "sg:tags":[
        "equipment",
        "hairdressing",
        "-",
        "supply"
    ],
    "wof:name":"Les Ateliers Moureau M Nv-sa",
    "wof:placetype":"venue"
},
  "geometry": {"coordinates":[4.3120450974,50.8481521606],"type":"Point"}
}