{
  "type": "Feature",
  "properties": {
    "addr:full":"Kanaalstraat 200 Leopoldsburg (heppen) Limburg 3971",
    "addr:housenumber":"200",
    "addr:postcode":"3971",
    "addr:street":"Kanaalstraat",
    "iso:country":"BE",
    "sg:address":"Kanaalstraat 200",
    "sg:city":"Leopoldsburg (heppen)",
    "sg:classifiers":[
        {
            "category":"Wholesale",
            "subcategory":"Construction Materials",
            "type":"Manufacturing & Wholesale Goods"
        }
    ],
    "sg:phone":"+32 11 39 31 54",
    "sg:postcode":"3971",
    "sg:province":"Limburg",
    "sg:tags":[
        "joint",
        "packing"
    ],
    "wof:name":"Jaeger Seals Bvba",
    "wof:placetype":"venue"
},
  "geometry": {"coordinates":[5.2432909012,51.1288566589],"type":"Point"}
}