{
  "type": "Feature",
  "properties": {
    "iso:country":"BE",
    "sg:address":"Tongersesteenweg 9",
    "sg:city":"Borgloon",
    "sg:classifiers":[
        {
            "category":"Insurance",
            "subcategory":"Insurance Agent",
            "type":"Services"
        }
    ],
    "sg:phone":"+32 12 74 38 02",
    "sg:postcode":"3840",
    "sg:province":"Limburg",
    "sg:tags":[
        "verzekeringsmakelaars",
        "expert"
    ],
    "wof:name":"B. Pirard",
    "wof:placetype":"venue"
},
  "geometry": {"coordinates":[5.3493518829,50.8023719788],"type":"Point"}
}