{
  "type": "Feature",
  "properties": {
    "iso:country":"BE",
    "sg:address":"Route De Cortil-wodon 37",
    "sg:city":"Eghez\u00c9e",
    "sg:orig_category":"Sportclubs",
    "sg:phone":"+32 81 51 33 76",
    "sg:postcode":"5310",
    "sg:province":"Namur",
    "wof:name":"Andenne Volley",
    "wof:placetype":"venue"
},
  "geometry": {"coordinates":[4.9130401611,50.5619392395],"type":"Point"}
}