{
  "type": "Feature",
  "properties": {
    "addr:full":"Pollenusstraat 31 Hasselt (kermt) Limburg 3510",
    "addr:housenumber":"31",
    "addr:postcode":"3510",
    "addr:street":"Pollenusstraat",
    "iso:country":"BE",
    "sg:address":"Pollenusstraat 31",
    "sg:city":"Hasselt (kermt)",
    "sg:classifiers":[
        {
            "category":"Home & Garden",
            "subcategory":"Building Materials",
            "type":"Retail Goods"
        }
    ],
    "sg:phone":"+32 495 99 11 54",
    "sg:postcode":"3510",
    "sg:province":"Limburg",
    "sg:tags":[
        "window"
    ],
    "wof:name":"Steijlen J",
    "wof:placetype":"venue"
},
  "geometry": {"coordinates":[5.2531552315,50.9474906921],"type":"Point"}
}