{
  "type": "Feature",
  "properties": {
    "iso:country":"BE",
    "sg:address":"Stationsstraat",
    "sg:city":"Wichelen",
    "sg:orig_category":"Treinen and spoorwegen",
    "sg:phone":"+32 9 369 02 87",
    "sg:postcode":"9260",
    "sg:province":"Oost-Vlaanderen",
    "wof:name":"Station Schellebelle",
    "wof:placetype":"venue"
},
  "geometry": {"coordinates":[3.9261350632,51.0108642578],"type":"Point"}
}