{
  "type": "Feature",
  "properties": {
    "addr:full":"Gaston Gheldolflaan 3 Gent (mariakerke) Oost-Vlaanderen 9030",
    "addr:housenumber":"3",
    "addr:postcode":"9030",
    "addr:street":"Gheldolflaan",
    "iso:country":"BE",
    "sg:address":"Gaston Gheldolflaan 3",
    "sg:city":"Gent (mariakerke)",
    "sg:classifiers":[
        {
            "category":"Health Services",
            "subcategory":"Doctor",
            "type":"Services"
        }
    ],
    "sg:phone":"+32 9 224 24 42",
    "sg:postcode":"9030",
    "sg:province":"Oost-Vlaanderen",
    "sg:tags":[
        "psychotherapist",
        "psychoanalyst"
    ],
    "wof:name":"Lampe A",
    "wof:placetype":"venue"
},
  "geometry": {"coordinates":[3.6914200783,51.0731658936],"type":"Point"}
}