{
  "type": "Feature",
  "properties": {
    "iso:country":"BE",
    "sg:address":"Korte Gasthuisstraat 23",
    "sg:city":"Antwerpen",
    "sg:classifiers":[
        {
            "category":"Shopping",
            "subcategory":"Jewelry",
            "type":"Retail Goods"
        }
    ],
    "sg:phone":"+32 3 231 63 43",
    "sg:postcode":"2000",
    "sg:province":"Antwerpen",
    "sg:tags":[
        "-",
        "imitation"
    ],
    "wof:name":"Taeymans N",
    "wof:placetype":"venue"
},
  "geometry": {"coordinates":[4.4045271873,51.2169151306],"type":"Point"}
}