{
  "type": "Feature",
  "properties": {
    "iso:country":"BE",
    "sg:address":"Oeverstraat 30",
    "sg:city":"Temse",
    "sg:orig_category":"Salles de conf\u00e9rences and de r\u00e9ceptions",
    "sg:phone":"+32 3 771 51 12",
    "sg:postcode":"9140",
    "sg:province":"Oost-Vlaanderen",
    "wof:name":"Salons Den Oever",
    "wof:placetype":"venue"
},
  "geometry": {"coordinates":[4.2114682198,51.1247444153],"type":"Point"}
}