{
  "type": "Feature",
  "properties": {
    "addr:full":"Otegemstraat 238 Zwevegem West-Vlaanderen 8550",
    "addr:housenumber":"238",
    "addr:postcode":"8550",
    "addr:street":"Otegemstraat",
    "iso:country":"BE",
    "sg:address":"Otegemstraat 238",
    "sg:city":"Zwevegem",
    "sg:classifiers":[
        {
            "category":"Arena",
            "subcategory":"Sports Club",
            "type":"Entertainment"
        }
    ],
    "sg:phone":"+32 56 75 69 02",
    "sg:postcode":"8550",
    "sg:province":"West-Vlaanderen",
    "wof:name":"Mini Racing Club",
    "wof:placetype":"venue"
},
  "geometry": {"coordinates":[3.3512320518,50.8166313171],"type":"Point"}
}