{
  "type": "Feature",
  "properties": {
    "addr:full":"Rue Du Moulin 64 La Louviere Hainaut 7100",
    "addr:housenumber":"64",
    "addr:postcode":"7100",
    "addr:street":"Rue Du Moulin",
    "iso:country":"BE",
    "sg:address":"Rue Du Moulin 64",
    "sg:city":"La Louviere",
    "sg:orig_category":"Papierwaren",
    "sg:phone":"+32 64 22 32 65",
    "sg:postcode":"7100",
    "sg:province":"Hainaut",
    "wof:name":"Capiau P",
    "wof:placetype":"venue"
},
  "geometry": {"coordinates":[4.1955537796,50.4807624817],"type":"Point"}
}