{
  "type": "Feature",
  "properties": {
    "addr:full":"Rue De L'institut 47 Chiny (izel) Luxembourg 6810",
    "addr:housenumber":"47",
    "addr:postcode":"6810",
    "addr:street":"Rue De L'Institut",
    "iso:country":"BE",
    "sg:address":"Rue De L'institut 47",
    "sg:city":"Chiny (izel)",
    "sg:classifiers":[
        {
            "category":"Education",
            "subcategory":"School",
            "type":"Public Place"
        }
    ],
    "sg:phone":"+32 61 31 24 56",
    "sg:postcode":"6810",
    "sg:province":"Luxembourg",
    "sg:tags":[
        "primary"
    ],
    "wof:name":"Athen\u00e9e Royal G Et G Gilson",
    "wof:placetype":"venue"
},
  "geometry": {"coordinates":[5.3797187805,49.6910438538],"type":"Point"}
}