{
  "type": "Feature",
  "properties": {
    "addr:full":"Perksesteenweg 30c Steenokkerzeel (melsbroek) Vlaams-Brabant 1820",
    "addr:housenumber":"30c",
    "addr:postcode":"1820",
    "addr:street":"Perksesteenweg",
    "iso:country":"BE",
    "sg:address":"Perksesteenweg 30c",
    "sg:city":"Steenokkerzeel (melsbroek)",
    "sg:classifiers":[
        {
            "category":"Building & Trades",
            "subcategory":"Construction",
            "type":"Services"
        }
    ],
    "sg:phone":"+32 2 751 81 24",
    "sg:postcode":"1820",
    "sg:province":"Vlaams-Brabant",
    "sg:tags":[
        "stucco",
        "contractor"
    ],
    "wof:name":"Perpet F",
    "wof:placetype":"venue"
},
  "geometry": {"coordinates":[4.4940090179,50.9232444763],"type":"Point"}
}