{
  "type": "Feature",
  "properties": {
    "addr:full":"Lage Bokstraat 18 Sint-niklaas (belsele) Oost-Vlaanderen 9111",
    "addr:housenumber":"18",
    "addr:postcode":"9111",
    "addr:street":"Bokstraat",
    "iso:country":"BE",
    "sg:address":"Lage Bokstraat 18",
    "sg:city":"Sint-niklaas (belsele)",
    "sg:classifiers":[
        {
            "category":"Professional",
            "subcategory":"Management & Consulting",
            "type":"Services"
        }
    ],
    "sg:phone":"+32 3 765 15 00",
    "sg:postcode":"9111",
    "sg:province":"Oost-Vlaanderen",
    "sg:tags":[
        "marketing",
        "-",
        "direct",
        "consultant"
    ],
    "wof:name":"Van Hauwermeiren W.p.",
    "wof:placetype":"venue"
},
  "geometry": {"coordinates":[4.1191167831,51.1644935608],"type":"Point"}
}