{
  "type": "Feature",
  "properties": {
    "iso:country":"BE",
    "sg:address":"Rue Victor Horta 47",
    "sg:city":"Ottignies-louvain-la-neuve (louvain-la-neuve)",
    "sg:classifiers":[
        {
            "category":"Health Services",
            "subcategory":"Dentist",
            "type":"Services"
        }
    ],
    "sg:phone":"+32 10 45 02 32",
    "sg:postcode":"1348",
    "sg:province":"Brabant Wallon",
    "wof:name":"Yanez M.adriana",
    "wof:placetype":"venue"
},
  "geometry": {"coordinates":[4.6065387726,50.6639404297],"type":"Point"}
}