{
  "type": "Feature",
  "properties": {
    "iso:country":"BE",
    "sg:address":"Boterlaarbaan 267-269",
    "sg:city":"Deurne",
    "sg:orig_category":"Herstellingen and onderhoud van auto's",
    "sg:phone":"+32 477 61 27 37",
    "sg:postcode":"2100",
    "sg:province":"Antwerpen",
    "wof:name":"Car Wash Sacr\u00c9",
    "wof:placetype":"venue"
},
  "geometry": {"coordinates":[4.471157074,51.20911026],"type":"Point"}
}