{
  "type": "Feature",
  "properties": {
    "addr:full":"Achterstraat 42 Tongeren Limburg 3700",
    "addr:housenumber":"42",
    "addr:postcode":"3700",
    "addr:street":"Achterstraat",
    "iso:country":"BE",
    "sg:address":"Achterstraat 42",
    "sg:city":"Tongeren",
    "sg:orig_category":"Quincailleries. Bois Gr",
    "sg:phone":"+32 12 24 12 28",
    "sg:postcode":"3700",
    "sg:province":"Limburg",
    "wof:name":"Lamywood",
    "wof:placetype":"venue"
},
  "geometry": {"coordinates":[5.4636240005,50.7807197571],"type":"Point"}
}