{
  "type": "Feature",
  "properties": {
    "addr:full":"Boulevard Des Invalides 243 Box 7 Bruxelles (auderghem) Bruxelles-Capitale 1160",
    "addr:housenumber":"243;7",
    "addr:postcode":"1160",
    "addr:street":"Boulevard Des Invalides;Box",
    "iso:country":"BE",
    "sg:address":"Boulevard Des Invalides 243 Box 7",
    "sg:city":"Bruxelles (auderghem)",
    "sg:classifiers":[
        {
            "category":"Building & Trades",
            "subcategory":"Construction",
            "type":"Services"
        }
    ],
    "sg:phone":"+32 2 672 93 60",
    "sg:postcode":"1160",
    "sg:province":"Bruxelles-Capitale",
    "sg:tags":[
        "carpenter"
    ],
    "wof:name":"Leclercqz J-m",
    "wof:placetype":"venue"
},
  "geometry": {"coordinates":[4.4066181183,50.8185997009],"type":"Point"}
}