{
  "type": "Feature",
  "properties": {
    "iso:country":"BE",
    "sg:address":"Avenue G\u00c9n\u00c9ral-jacques 46",
    "sg:city":"Nivelles",
    "sg:orig_category":"Advocaten and juridische adviseurs",
    "sg:phone":"+32 67 84 06 13",
    "sg:postcode":"1400",
    "sg:province":"Brabant Wallon",
    "wof:name":"D. Carneroli",
    "wof:placetype":"venue"
},
  "geometry": {"coordinates":[4.3310928345,50.5943222046],"type":"Point"}
}