{
  "type": "Feature",
  "properties": {
    "addr:full":"Rue De Mollendael 18 Beauvechain Brabant Wallon 1320",
    "addr:housenumber":"18",
    "addr:postcode":"1320",
    "addr:street":"Rue De Mollendael",
    "iso:country":"BE",
    "sg:address":"Rue De Mollendael 18",
    "sg:city":"Beauvechain",
    "sg:orig_category":"Agences immobili\u00e8res",
    "sg:phone":"+32 10 86 08 76",
    "sg:postcode":"1320",
    "sg:province":"Brabant Wallon",
    "wof:name":"Ass. Mgnt & Invest. Corp.",
    "wof:placetype":"venue"
},
  "geometry": {"coordinates":[4.7649798393,50.7996711731],"type":"Point"}
}