{
  "type": "Feature",
  "properties": {
    "iso:country":"BE",
    "sg:address":"Rue Du Chambge 45",
    "sg:city":"Tournai",
    "sg:orig_category":"Advocaten and juridische adviseurs",
    "sg:phone":"+32 69 22 55 81",
    "sg:postcode":"7500",
    "sg:province":"Hainaut",
    "wof:name":"Pierre Leroy",
    "wof:placetype":"venue"
},
  "geometry": {"coordinates":[3.3885068893,50.6016998291],"type":"Point"}
}