{
  "type": "Feature",
  "properties": {
    "addr:full":"Overwinningsstraat 113 Sint-gillis/saint-gilles Bruxelles-Capitale 1060",
    "addr:housenumber":"113",
    "addr:postcode":"1060",
    "addr:street":"Overwinningsstraat",
    "iso:country":"BE",
    "sg:address":"Overwinningsstraat 113",
    "sg:city":"Sint-gillis/saint-gilles",
    "sg:orig_category":"Artsen and specialisten",
    "sg:phone":"+32 2 537 06 78",
    "sg:postcode":"1060",
    "sg:province":"Bruxelles-Capitale",
    "wof:name":"A. Dekeuleneer",
    "wof:placetype":"venue"
},
  "geometry": {"coordinates":[4.3504109383,50.8285903931],"type":"Point"}
}