{
  "type": "Feature",
  "properties": {
    "iso:country":"BE",
    "sg:address":"Molenstraat 206",
    "sg:city":"Waarschoot",
    "sg:orig_category":"Woningbouw",
    "sg:phone":"+32 9 377 44 27",
    "sg:postcode":"9950",
    "sg:province":"Oost-Vlaanderen",
    "wof:name":"Johan De Vilder",
    "wof:placetype":"venue"
},
  "geometry": {"coordinates":[3.6201028824,51.1477737427],"type":"Point"}
}