{
  "type": "Feature",
  "properties": {
    "iso:country":"BE",
    "sg:address":"Rue De Virginal 23",
    "sg:city":"Ittre",
    "sg:orig_category":"Quincailleries",
    "sg:phone":"+32 67 64 92 93",
    "sg:postcode":"1460",
    "sg:province":"Brabant Wallon",
    "wof:name":"Usigroup",
    "wof:placetype":"venue"
},
  "geometry": {"coordinates":[4.2553257942,50.6453704834],"type":"Point"}
}