{
  "type": "Feature",
  "properties": {
    "addr:full":"Rue De La Marbrerie 6 Trooz (for\u00eat) Li\u00e8ge 4870",
    "addr:housenumber":"6",
    "addr:postcode":"4870",
    "addr:street":"Rue De La Marbrerie;Fore\u0302T",
    "iso:country":"BE",
    "sg:address":"Rue De La Marbrerie 6",
    "sg:city":"Trooz (for\u00eat)",
    "sg:orig_category":"Non-Classified Establishments",
    "sg:phone":"+32 4 351 72 36",
    "sg:postcode":"4870",
    "sg:province":"Li\u00e8ge",
    "wof:name":"Nissan-noroma Detail Car",
    "wof:placetype":"venue"
},
  "geometry": {"coordinates":[5.6797151566,50.5764274597],"type":"Point"}
}