{
  "type": "Feature",
  "properties": {
    "iso:country":"BE",
    "sg:address":"109",
    "sg:city":"Rue Puits-en-sock 4020 Li\u00e8ge",
    "sg:classifiers":[
        {
            "category":"Wholesale",
            "subcategory":"Machinery & Supplies",
            "type":"Manufacturing & Wholesale Goods"
        }
    ],
    "sg:phone":"+32 4 343 93 54",
    "sg:postcode":"109",
    "sg:tags":[
        "food",
        "processing",
        "-",
        "machine",
        "equipment",
        "engineering",
        "mechanical"
    ],
    "wof:name":"Mcb Sprl",
    "wof:placetype":"venue"
},
  "geometry": {"coordinates":[5.5824899673,50.6409645081],"type":"Point"}
}