{
  "type": "Feature",
  "properties": {
    "addr:full":"Guido Gezellelaan 125 Deinze Oost-Vlaanderen 9800",
    "addr:housenumber":"125",
    "addr:postcode":"9800",
    "addr:street":"Guido Gezellelaan",
    "iso:country":"BE",
    "sg:address":"Guido Gezellelaan 125",
    "sg:city":"Deinze",
    "sg:orig_category":"M\u00e9decins and sp\u00e9cialistes",
    "sg:phone":"+32 9 386 54 36",
    "sg:postcode":"9800",
    "sg:province":"Oost-Vlaanderen",
    "wof:name":"Anna-maria Stevens",
    "wof:placetype":"venue"
},
  "geometry": {"coordinates":[3.5336151123,50.9804763794],"type":"Point"}
}