{
  "type": "Feature",
  "properties": {
    "iso:country":"BE",
    "sg:address":"Weertersteenweg 36",
    "sg:city":"Kinrooi",
    "sg:classifiers":[
        {
            "category":"Building & Trades",
            "subcategory":"Plumbing",
            "type":"Services"
        }
    ],
    "sg:phone":"+32 89 70 14 19",
    "sg:postcode":"3640",
    "sg:province":"Limburg",
    "sg:tags":[
        "repair",
        "mainten",
        "-",
        "central",
        "heating"
    ],
    "wof:name":"Op 't Eijnde J",
    "wof:placetype":"venue"
},
  "geometry": {"coordinates":[5.7556800842,51.1363182068],"type":"Point"}
}