{
  "type": "Feature",
  "properties": {
    "iso:country":"BE",
    "sg:address":"Boomgaardstraat 17",
    "sg:city":"Zemst",
    "sg:orig_category":"Beveiligingsdiensten and bewakingsbedrijven",
    "sg:phone":"+32 15 61 52 08",
    "sg:postcode":"1981",
    "sg:province":"Vlaams-Brabant",
    "wof:name":"Int. Close Protect.agency",
    "wof:placetype":"venue"
},
  "geometry": {"coordinates":[4.5120959282,50.9944534302],"type":"Point"}
}