{
  "type": "Feature",
  "properties": {
    "iso:country":"BE",
    "sg:address":"Rue Du Transvaal 142",
    "sg:city":"Charleroi (couillet)",
    "sg:classifiers":[
        {
            "category":"Communications",
            "subcategory":"Film & Video Production",
            "type":"Services"
        }
    ],
    "sg:phone":"+32 71 47 07 51",
    "sg:postcode":"6010",
    "sg:province":"Hainaut",
    "sg:tags":[
        "producer",
        "realizators"
    ],
    "wof:name":"Zen-it Sprlu",
    "wof:placetype":"venue"
},
  "geometry": {"coordinates":[4.4569621086,50.3851165771],"type":"Point"}
}