{
  "type": "Feature",
  "properties": {
    "iso:country":"BE",
    "sg:address":"Rijselstraat 225",
    "sg:city":"Menen",
    "sg:orig_category":"Boucheries",
    "sg:phone":"+32 56 51 16 44",
    "sg:postcode":"8930",
    "sg:province":"West-Vlaanderen",
    "wof:name":"Jean-paul Maeseele",
    "wof:placetype":"venue"
},
  "geometry": {"coordinates":[3.1271049976,50.7879638672],"type":"Point"}
}