{
  "type": "Feature",
  "properties": {
    "addr:full":"Rue Joseph Wauters 41 Engis Li\u00e8ge 4480",
    "addr:housenumber":"41",
    "addr:postcode":"4480",
    "addr:street":"Rue Joseph Wauters",
    "iso:country":"BE",
    "sg:address":"Rue Joseph Wauters 41",
    "sg:city":"Engis",
    "sg:orig_category":"Supermarkten",
    "sg:phone":"+32 4 275 68 41",
    "sg:postcode":"4480",
    "sg:province":"Li\u00e8ge",
    "wof:name":"Sodefa",
    "wof:placetype":"venue"
},
  "geometry": {"coordinates":[5.4016418457,50.5800209045],"type":"Point"}
}