{
  "type": "Feature",
  "properties": {
    "addr:full":"Rue De Chamborgneau 21 Gerpinnes Hainaut 6280",
    "addr:housenumber":"21",
    "addr:postcode":"6280",
    "addr:street":"Rue De Chamborgneau;Hainaut",
    "iso:country":"BE",
    "sg:address":"Rue De Chamborgneau 21",
    "sg:city":"Gerpinnes",
    "sg:classifiers":[
        {
            "category":"Insurance",
            "subcategory":"Insurance Agent",
            "type":"Services"
        }
    ],
    "sg:phone":"+32 71 50 13 20",
    "sg:postcode":"6280",
    "sg:province":"Hainaut",
    "sg:tags":[
        "verzekeringsmakelaars",
        "expert"
    ],
    "wof:name":"A. Rosar",
    "wof:placetype":"venue"
},
  "geometry": {"coordinates":[4.5276851654,50.3365364075],"type":"Point"}
}