{
  "type": "Feature",
  "properties": {
    "addr:full":"Turnhoutsebaan 351 Wijnegem Antwerpen 2110",
    "addr:housenumber":"351",
    "addr:postcode":"2110",
    "addr:street":"Turnhoutsebaan",
    "iso:country":"BE",
    "sg:address":"Turnhoutsebaan 351",
    "sg:city":"Wijnegem",
    "sg:orig_category":"Pharmaciens",
    "sg:phone":"+32 3 353 61 31",
    "sg:postcode":"2110",
    "sg:province":"Antwerpen",
    "wof:name":"Apotheek Meeussen",
    "wof:placetype":"venue"
},
  "geometry": {"coordinates":[4.522550106,51.2273674011],"type":"Point"}
}