{
  "type": "Feature",
  "properties": {
    "addr:full":"Drieswegel 8 Zwevegem (sint-denijs) West-Vlaanderen 8554",
    "addr:housenumber":"8",
    "addr:postcode":"8554",
    "addr:street":"Drieswegel",
    "iso:country":"BE",
    "sg:address":"Drieswegel 8",
    "sg:city":"Zwevegem (sint-denijs)",
    "sg:classifiers":[
        {
            "category":"Personal",
            "subcategory":"Beauty Salon",
            "type":"Services"
        }
    ],
    "sg:phone":"+32 56 45 50 63",
    "sg:postcode":"8554",
    "sg:province":"West-Vlaanderen",
    "sg:tags":[
        "lady",
        "-",
        "hairdressing"
    ],
    "wof:name":"Thibaut",
    "wof:placetype":"venue"
},
  "geometry": {"coordinates":[3.3638589382,50.7563819885],"type":"Point"}
}