{
  "type": "Feature",
  "properties": {
    "addr:full":"Rijselstraat 71 Brugge West-Vlaanderen 8200",
    "addr:housenumber":"71",
    "addr:postcode":"8200",
    "addr:street":"Rijselstraat",
    "iso:country":"BE",
    "sg:address":"Rijselstraat 71",
    "sg:city":"Brugge",
    "sg:orig_category":"Enseignement maternel and primaire",
    "sg:phone":"+32 50 38 44 71",
    "sg:postcode":"8200",
    "sg:province":"West-Vlaanderen",
    "wof:name":"Gemeentelijke Basisschool",
    "wof:placetype":"venue"
},
  "geometry": {"coordinates":[3.2113099098,51.1885986328],"type":"Point"}
}