{
  "type": "Feature",
  "properties": {
    "addr:full":"Bredabaan 161b6 Brasschaat Antwerpen 2930",
    "addr:housenumber":"161b6",
    "addr:postcode":"2930",
    "addr:street":"Bredabaan",
    "iso:country":"BE",
    "sg:address":"Bredabaan 161b6",
    "sg:city":"Brasschaat",
    "sg:classifiers":[
        {
            "category":"Building & Trades",
            "subcategory":"Pest Control",
            "type":"Services"
        }
    ],
    "sg:phone":"+32 3 653 18 68",
    "sg:postcode":"2930",
    "sg:province":"Antwerpen",
    "sg:tags":[
        "automation"
    ],
    "wof:name":"Mas-multi Automation Service B.v.b.a.",
    "wof:placetype":"venue"
},
  "geometry": {"coordinates":[4.4844250679,51.2855606079],"type":"Point"}
}