{
  "type": "Feature",
  "properties": {
    "iso:country":"BE",
    "sg:address":"Route De Mons 16",
    "sg:city":"Charleroi (dampremy)",
    "sg:classifiers":[
        {
            "category":"Building & Trades",
            "subcategory":"Cleaning & Sanitation",
            "type":"Services"
        }
    ],
    "sg:postcode":"6020",
    "sg:province":"Hainaut",
    "sg:tags":[
        "equipment",
        "industrial",
        "maintenance"
    ],
    "wof:name":"Centre Karcher-smi Sa",
    "wof:placetype":"venue"
},
  "geometry": {"coordinates":[4.4352221489,50.412071228],"type":"Point"}
}