{
  "type": "Feature",
  "properties": {
    "addr:full":"Rue Des Waibes 69 Lobbes Hainaut 6540",
    "addr:housenumber":"69",
    "addr:postcode":"6540",
    "addr:street":"Rue Des Waibes",
    "iso:country":"BE",
    "sg:address":"Rue Des Waibes 69",
    "sg:city":"Lobbes",
    "sg:orig_category":"Zuivelproducten",
    "sg:phone":"+32 71 59 06 81",
    "sg:postcode":"6540",
    "sg:province":"Hainaut",
    "wof:name":"Chez Pierre & Caroline",
    "wof:placetype":"venue"
},
  "geometry": {"coordinates":[4.2765059471,50.3661727905],"type":"Point"}
}