{
  "type": "Feature",
  "properties": {
    "iso:country":"BE",
    "sg:address":"Sint-bernardusstraat 97",
    "sg:city":"Sint-gillis/saint-gilles",
    "sg:orig_category":"Plaatsen van vloer- and muurbekleding Schilders",
    "sg:phone":"+32 2 537 81 65",
    "sg:postcode":"1060",
    "sg:province":"Bruxelles-Capitale",
    "wof:name":"Decorum J P",
    "wof:placetype":"venue"
},
  "geometry": {"coordinates":[4.3523230553,50.8277130127],"type":"Point"}
}