{
  "type": "Feature",
  "properties": {
    "iso:country":"BE",
    "sg:address":"Rue Grande 52",
    "sg:city":"Farciennes",
    "sg:orig_category":"Banken and kredietinstellingen",
    "sg:phone":"+32 71 38 30 08",
    "sg:postcode":"6240",
    "sg:province":"Hainaut",
    "wof:name":"Bbl",
    "wof:placetype":"venue"
},
  "geometry": {"coordinates":[4.5516600609,50.426700592],"type":"Point"}
}