{
  "type": "Feature",
  "properties": {
    "addr:full":"Pastoor Verrieststraat 101 Anzegem (ingooigem) West-Vlaanderen 8570",
    "addr:housenumber":"101",
    "addr:postcode":"8570",
    "addr:street":"Pastoor Verrieststraat",
    "iso:country":"BE",
    "sg:address":"Pastoor Verrieststraat 101",
    "sg:city":"Anzegem (ingooigem)",
    "sg:classifiers":[
        {
            "category":"Building & Trades",
            "subcategory":"Electrical",
            "type":"Services"
        }
    ],
    "sg:phone":"+32 56 77 88 25",
    "sg:postcode":"8570",
    "sg:province":"West-Vlaanderen",
    "sg:tags":[
        "heating"
    ],
    "wof:name":"De Brauwer Elektro Bvba",
    "wof:placetype":"venue"
},
  "geometry": {"coordinates":[3.4393730164,50.8212966919],"type":"Point"}
}