{
  "type": "Feature",
  "properties": {
    "addr:full":"Rue De Roulers 1 Mouscron Hainaut 7700",
    "addr:housenumber":"1",
    "addr:postcode":"7700",
    "addr:street":"Rue De Roulers",
    "iso:country":"BE",
    "sg:address":"Rue De Roulers 1",
    "sg:city":"Mouscron",
    "sg:classifiers":[
        {
            "category":"Community Center",
            "type":"Public Place"
        }
    ],
    "sg:phone":"+32 56 33 02 57",
    "sg:postcode":"7700",
    "sg:province":"Hainaut",
    "sg:tags":[
        "box",
        "juke"
    ],
    "wof:name":"Seynaeve Ets",
    "wof:placetype":"venue"
},
  "geometry": {"coordinates":[3.2120599747,50.7482185364],"type":"Point"}
}