{
  "type": "Feature",
  "properties": {
    "addr:full":"Menapi\u00cbrsstraat 30 Etterbeek/etterbeek Bruxelles-Capitale 1040",
    "addr:housenumber":"30",
    "addr:postcode":"1040",
    "addr:street":"Menapie\u0308Rsstraat",
    "iso:country":"BE",
    "sg:address":"Menapi\u00cbrsstraat 30",
    "sg:city":"Etterbeek/etterbeek",
    "sg:orig_category":"Paramedische behandelingen",
    "sg:phone":"+32 2 733 82 56",
    "sg:postcode":"1040",
    "sg:province":"Bruxelles-Capitale",
    "wof:name":"A. De Heering",
    "wof:placetype":"venue"
},
  "geometry": {"coordinates":[4.4015798569,50.8398246765],"type":"Point"}
}