{
  "type": "Feature",
  "properties": {
    "addr:full":"Jevign\u00c9 28 Lierneux Li\u00e8ge 4990",
    "addr:housenumber":"28",
    "addr:postcode":"4990",
    "addr:street":"Jevigne\u0301",
    "iso:country":"BE",
    "sg:address":"Jevign\u00c9 28",
    "sg:city":"Lierneux",
    "sg:orig_category":"Maisons de vacances",
    "sg:phone":"+32 80 31 96 09",
    "sg:postcode":"4990",
    "sg:province":"Li\u00e8ge",
    "wof:name":"Marichal Fabien",
    "wof:placetype":"venue"
},
  "geometry": {"coordinates":[5.7682328224,50.2939987183],"type":"Point"}
}