{
  "type": "Feature",
  "properties": {
    "addr:full":"Rue De M\u00e9rode 34 Bruxelles (saint-gilles) Bruxelles-Capitale 1060",
    "addr:housenumber":"34",
    "addr:postcode":"1060",
    "addr:street":"Rue De Me\u0301Rode",
    "iso:country":"BE",
    "sg:address":"Rue De M\u00e9rode 34",
    "sg:city":"Bruxelles (saint-gilles)",
    "sg:classifiers":[
        {
            "category":"Travel",
            "subcategory":"Travel Agent",
            "type":"Entertainment"
        }
    ],
    "sg:phone":"+32 2 538 50 52",
    "sg:postcode":"1060",
    "sg:province":"Bruxelles-Capitale",
    "sg:tags":[
        "agency"
    ],
    "wof:name":"Regine (voyages)",
    "wof:placetype":"venue"
},
  "geometry": {"coordinates":[4.3400630951,50.8357048035],"type":"Point"}
}