{
  "type": "Feature",
  "properties": {
    "addr:full":"\u00b4t Zand 0 Brugge West-Vlaanderen 8000",
    "addr:housenumber":"0",
    "addr:postcode":"8000",
    "addr:street":"\u00b4T Zand",
    "iso:country":"BE",
    "sg:address":"\u00b4t Zand 0",
    "sg:city":"Brugge",
    "sg:orig_category":"Services annexes des transports terrestres",
    "sg:phone":"+32 50 34 06 52",
    "sg:postcode":"8000",
    "sg:province":"West-Vlaanderen",
    "wof:name":"Interparking",
    "wof:placetype":"venue"
},
  "geometry": {"coordinates":[3.218818903,51.2043533325],"type":"Point"}
}