{
  "type": "Feature",
  "properties": {
    "iso:country":"BE",
    "sg:address":"Tuttegemstraat 81",
    "sg:city":"Zulte (machelen)",
    "sg:classifiers":[
        {
            "category":"Military Area",
            "subcategory":"Restricted Area",
            "type":"Public Place"
        }
    ],
    "sg:phone":"+32 9 386 48 72",
    "sg:postcode":"9870",
    "sg:province":"Oost-Vlaanderen",
    "sg:tags":[
        "mfrs",
        "silo"
    ],
    "wof:name":"Van Brabandt C",
    "wof:placetype":"venue"
},
  "geometry": {"coordinates":[3.4973399639,50.9441719055],"type":"Point"}
}