{
  "type": "Feature",
  "properties": {
    "iso:country":"BE",
    "sg:address":"Oudestraat 24",
    "sg:city":"Peer",
    "sg:classifiers":[
        {
            "category":"Manufacturing",
            "subcategory":"Textiles",
            "type":"Manufacturing & Wholesale Goods"
        }
    ],
    "sg:phone":"+32 11 63 21 50",
    "sg:postcode":"3990",
    "sg:province":"Limburg",
    "sg:tags":[
        "lingerie",
        "textiles",
        "sous-v\u00eatements"
    ],
    "wof:name":"Huis Edelweis",
    "wof:placetype":"venue"
},
  "geometry": {"coordinates":[5.4578762054,51.1308441162],"type":"Point"}
}