{
  "type": "Feature",
  "properties": {
    "addr:full":"Rue Du Vieux Sourdiau 2a Binche Hainaut 7130",
    "addr:housenumber":"2a",
    "addr:postcode":"7130",
    "addr:street":"Rue Du Vieux Sourdiau",
    "iso:country":"BE",
    "sg:address":"Rue Du Vieux Sourdiau 2a",
    "sg:city":"Binche",
    "sg:classifiers":[
        {
            "category":"Professional",
            "subcategory":"Accounting & Tax Preparation",
            "type":"Services"
        }
    ],
    "sg:phone":"+32 64 33 80 20",
    "sg:postcode":"7130",
    "sg:province":"Hainaut",
    "sg:tags":[
        "accountant",
        "diverse",
        "bedrijfsbeheeradviesbureaus"
    ],
    "wof:name":"Socosid",
    "wof:placetype":"venue"
},
  "geometry": {"coordinates":[4.1685051918,50.4119987488],"type":"Point"}
}