{
  "type": "Feature",
  "properties": {
    "addr:full":"Lommelsesteenweg 28 Leopoldsburg Limburg 3970",
    "addr:housenumber":"28",
    "addr:postcode":"3970",
    "addr:street":"Lommelsesteenweg",
    "iso:country":"BE",
    "sg:address":"Lommelsesteenweg 28",
    "sg:city":"Leopoldsburg",
    "sg:classifiers":[
        {
            "category":"Health Services",
            "subcategory":"Doctor",
            "type":"Services"
        }
    ],
    "sg:phone":"+32 11 34 12 22",
    "sg:postcode":"3970",
    "sg:province":"Limburg",
    "sg:tags":[
        "medicinephysicians",
        "surgeon"
    ],
    "wof:name":"Luysterborg Lucien",
    "wof:placetype":"venue"
},
  "geometry": {"coordinates":[5.2570180893,51.1258964539],"type":"Point"}
}