{
  "type": "Feature",
  "properties": {
    "iso:country":"BE",
    "sg:address":"Avenue Brugmann 259",
    "sg:city":"Ukkel/uccle",
    "sg:classifiers":[
        {
            "category":"Personal",
            "subcategory":"Beauty Salon",
            "type":"Services"
        }
    ],
    "sg:phone":"+32 2 344 20 07",
    "sg:postcode":"1180",
    "sg:province":"Bruxelles-Capitale",
    "sg:tags":[
        "de",
        "coiffure"
    ],
    "wof:name":"Voet",
    "wof:placetype":"venue"
},
  "geometry": {"coordinates":[4.3473467827,50.8130493164],"type":"Point"}
}