{
  "type": "Feature",
  "properties": {
    "addr:full":"Lebekestraat 43 Ninove (outer) Oost-Vlaanderen 9406",
    "addr:housenumber":"43",
    "addr:postcode":"9406",
    "addr:street":"Lebekestraat;Outer Oost-Vlaanderen",
    "iso:country":"BE",
    "sg:address":"Lebekestraat 43",
    "sg:city":"Ninove (outer)",
    "sg:classifiers":[
        {
            "category":"Building & Trades",
            "subcategory":"Construction",
            "type":"Services"
        }
    ],
    "sg:phone":"+32 54 33 80 06",
    "sg:postcode":"9406",
    "sg:province":"Oost-Vlaanderen",
    "sg:tags":[
        "stucco",
        "contractor"
    ],
    "wof:name":"Callebaut E",
    "wof:placetype":"venue"
},
  "geometry": {"coordinates":[3.9885869026,50.849155426],"type":"Point"}
}