{
  "type": "Feature",
  "properties": {
    "iso:country":"BE",
    "sg:address":"Route De L\u00b4etat 270",
    "sg:city":"Lasne",
    "sg:classifiers":[
        {
            "category":"Arena",
            "subcategory":"Sports Club",
            "type":"Entertainment"
        }
    ],
    "sg:phone":"+32 447856639",
    "sg:postcode":"1380",
    "sg:province":"Brabant Wallon",
    "sg:tags":[
        "de"
    ],
    "wof:name":"H.c. Polo D\u00b4argenteuil",
    "wof:placetype":"venue"
},
  "geometry": {"coordinates":[4.4808998108,50.6837387085],"type":"Point"}
}