{
  "type": "Feature",
  "properties": {
    "addr:full":"Avenue De Villez 6 La Roche-en-ardenne Luxembourg 6980",
    "addr:housenumber":"6",
    "addr:postcode":"6980",
    "addr:street":"Avenue De Villez",
    "iso:country":"BE",
    "sg:address":"Avenue De Villez 6",
    "sg:city":"La Roche-en-ardenne",
    "sg:orig_category":"Kampeerterreinen Restaurants Ruimtes voor conferenties, recepties and feesten Vakantiedorpen Vakanti",
    "sg:phone":"+32 84 21 94 11",
    "sg:postcode":"6980",
    "sg:province":"Luxembourg",
    "wof:name":"Flor\u00c9al Club",
    "wof:placetype":"venue"
},
  "geometry": {"coordinates":[5.5823287964,50.1820526123],"type":"Point"}
}