{
  "type": "Feature",
  "properties": {
    "iso:country":"BE",
    "sg:address":"Veerstraat 37",
    "sg:city":"Wellen",
    "sg:classifiers":[
        {
            "category":"Insurance",
            "subcategory":"Insurance Agent",
            "type":"Services"
        }
    ],
    "sg:phone":"+32 12 74 12 44",
    "sg:postcode":"3830",
    "sg:province":"Limburg",
    "sg:tags":[
        "verzekeringsmakelaars",
        "expert"
    ],
    "wof:name":"Vanschoenwinkel",
    "wof:placetype":"venue"
},
  "geometry": {"coordinates":[5.3219690323,50.8445243835],"type":"Point"}
}