{
  "type": "Feature",
  "properties": {
    "addr:full":"Schrijbergstraat 4 Waasmunster Oost-Vlaanderen 9250",
    "addr:housenumber":"4",
    "addr:postcode":"9250",
    "addr:street":"Schrijbergstraat",
    "iso:country":"BE",
    "sg:address":"Schrijbergstraat 4",
    "sg:city":"Waasmunster",
    "sg:classifiers":[
        {
            "category":"Health Services",
            "subcategory":"Health Practitioner",
            "type":"Services"
        }
    ],
    "sg:phone":"+32 3 772 26 29",
    "sg:postcode":"9250",
    "sg:province":"Oost-Vlaanderen",
    "sg:tags":[
        "dietitian"
    ],
    "wof:name":"Peersman T",
    "wof:placetype":"venue"
},
  "geometry": {"coordinates":[4.0772137642,51.1336860657],"type":"Point"}
}