{
  "type": "Feature",
  "properties": {
    "addr:full":"Steenstraat 4 Koekelare West-Vlaanderen 8680",
    "addr:housenumber":"4",
    "addr:postcode":"8680",
    "addr:street":"Steenstraat",
    "iso:country":"BE",
    "sg:address":"Steenstraat 4",
    "sg:city":"Koekelare",
    "sg:orig_category":"Groententeelt",
    "sg:phone":"+32 51 58 85 08",
    "sg:postcode":"8680",
    "sg:province":"West-Vlaanderen",
    "wof:name":"Rik Cool",
    "wof:placetype":"venue"
},
  "geometry": {"coordinates":[3.0094759464,51.06848526],"type":"Point"}
}