{
  "type": "Feature",
  "properties": {
    "addr:full":"Wilderstraat 4 Ninove Oost-Vlaanderen 9400",
    "addr:housenumber":"4",
    "addr:postcode":"9400",
    "addr:street":"Wilderstraat",
    "iso:country":"BE",
    "sg:address":"Wilderstraat 4",
    "sg:city":"Ninove",
    "sg:orig_category":"Verplichte sociale verzekeringen",
    "sg:phone":"+32 54 33 29 10",
    "sg:postcode":"9400",
    "sg:province":"Oost-Vlaanderen",
    "wof:name":"Bond Moyson",
    "wof:placetype":"venue"
},
  "geometry": {"coordinates":[4.0232000351,50.8349113464],"type":"Point"}
}