{
  "type": "Feature",
  "properties": {
    "addr:full":"Molenstraat 28 Essen Antwerpen 2910",
    "addr:housenumber":"28",
    "addr:postcode":"2910",
    "addr:street":"Molenstraat",
    "iso:country":"BE",
    "sg:address":"Molenstraat 28",
    "sg:city":"Essen",
    "sg:orig_category":"Peinture. Rev\u00eatements pour sols and murs",
    "sg:phone":"+32 3 667 23 85",
    "sg:postcode":"2910",
    "sg:province":"Antwerpen",
    "wof:name":"Van Hees Roger & Zn.",
    "wof:placetype":"venue"
},
  "geometry": {"coordinates":[4.4616627693,51.4643249512],"type":"Point"}
}