{
  "type": "Feature",
  "properties": {
    "addr:full":"Toekomststraat 8 Machelen Vlaams-Brabant 1830",
    "addr:housenumber":"8",
    "addr:postcode":"1830",
    "addr:street":"Toekomststraat",
    "iso:country":"BE",
    "sg:address":"Toekomststraat 8",
    "sg:city":"Machelen",
    "sg:classifiers":[
        {
            "category":"Home & Garden",
            "subcategory":"Carpets & Floor Coverings",
            "type":"Retail Goods"
        }
    ],
    "sg:phone":"+32 2 251 11 42",
    "sg:postcode":"1830",
    "sg:province":"Vlaams-Brabant",
    "sg:tags":[
        "layer",
        "mosaicists"
    ],
    "wof:name":"Coninx Martin Bvba",
    "wof:placetype":"venue"
},
  "geometry": {"coordinates":[4.4356818199,50.9084854126],"type":"Point"}
}