{
  "type": "Feature",
  "properties": {
    "addr:full":"Offerandestraat 67 Antwerpen Antwerpen 2060",
    "addr:housenumber":"67",
    "addr:postcode":"2060",
    "addr:street":"Offerandestraat",
    "iso:country":"BE",
    "sg:address":"Offerandestraat 67",
    "sg:city":"Antwerpen",
    "sg:classifiers":[
        {
            "category":"Shopping",
            "subcategory":"Jewelry",
            "type":"Retail Goods"
        }
    ],
    "sg:phone":"+32 3 232 31 39",
    "sg:postcode":"2060",
    "sg:province":"Antwerpen",
    "sg:tags":[
        "jeweller",
        "-"
    ],
    "wof:name":"Silver Planet",
    "wof:placetype":"venue"
},
  "geometry": {"coordinates":[4.4264740944,51.2210540771],"type":"Point"}
}