{
  "type": "Feature",
  "properties": {
    "addr:full":"Ch. De Martelange 8 Neufch\u00e2teau Luxembourg 6840",
    "addr:housenumber":"8",
    "addr:postcode":"6840",
    "addr:street":"Ch. De Martelange",
    "iso:country":"BE",
    "sg:address":"Ch. De Martelange 8",
    "sg:city":"Neufch\u00e2teau",
    "sg:classifiers":[
        {
            "category":"Building & Trades",
            "subcategory":"Equipment Rental",
            "type":"Services"
        }
    ],
    "sg:phone":"+32 61 27 73 79",
    "sg:postcode":"6840",
    "sg:province":"Luxembourg",
    "sg:tags":[
        "horticultural"
    ],
    "wof:name":"Ardennes Jardins S.a.",
    "wof:placetype":"venue"
},
  "geometry": {"coordinates":[5.4346451759,49.8411598206],"type":"Point"}
}