{
  "type": "Feature",
  "properties": {
    "addr:full":"Rue Dameries 24 Leuze-en-hainaut Hainaut 7900",
    "addr:housenumber":"24",
    "addr:postcode":"7900",
    "addr:street":"Rue Dameries",
    "iso:country":"BE",
    "sg:address":"Rue Dameries 24",
    "sg:city":"Leuze-en-hainaut",
    "sg:orig_category":"Eleveurs de bovins",
    "sg:phone":"+32 69 86 60 03",
    "sg:postcode":"7900",
    "sg:province":"Hainaut",
    "wof:name":"Marcel Bille",
    "wof:placetype":"venue"
},
  "geometry": {"coordinates":[3.6563611031,50.6406135559],"type":"Point"}
}