{
  "type": "Feature",
  "properties": {
    "addr:full":"Vlinderbeekstraat 3a Ledegem West-Vlaanderen 8880",
    "addr:housenumber":"3a",
    "addr:postcode":"8880",
    "addr:street":"Vlinderbeekstraat",
    "iso:country":"BE",
    "sg:address":"Vlinderbeekstraat 3a",
    "sg:city":"Ledegem",
    "sg:orig_category":"Restaurants Ruimtes voor conferenties, recepties and feesten",
    "sg:phone":"+32 51 31 54 14",
    "sg:postcode":"8880",
    "sg:province":"West-Vlaanderen",
    "wof:name":"'t Vlinderke",
    "wof:placetype":"venue"
},
  "geometry": {"coordinates":[3.1760590076,50.8880844116],"type":"Point"}
}