{
  "type": "Feature",
  "properties": {
    "iso:country":"BE",
    "sg:address":"Stationsstraat 60",
    "sg:city":"Heusden-zolder (zolder)",
    "sg:classifiers":[
        {
            "category":"Manufacturing",
            "subcategory":"Lumber",
            "type":"Manufacturing & Wholesale Goods"
        }
    ],
    "sg:phone":"+32 11 53 66 16",
    "sg:postcode":"3550",
    "sg:province":"Limburg",
    "sg:tags":[
        "timber"
    ],
    "wof:name":"Van Houdt R Bvba",
    "wof:placetype":"venue"
},
  "geometry": {"coordinates":[5.3295469284,51.0326690674],"type":"Point"}
}