{
  "type": "Feature",
  "properties": {
    "addr:full":"Schoolstraat 2 Lochristi Oost-Vlaanderen 9080",
    "addr:housenumber":"2",
    "addr:postcode":"9080",
    "addr:street":"Schoolstraat",
    "iso:country":"BE",
    "sg:address":"Schoolstraat 2",
    "sg:city":"Lochristi",
    "sg:classifiers":[
        {
            "category":"Building & Trades",
            "subcategory":"Equipment Rental",
            "type":"Services"
        }
    ],
    "sg:phone":"+32 477 32 51 20",
    "sg:postcode":"9080",
    "sg:province":"Oost-Vlaanderen",
    "sg:tags":[
        "sound",
        "-",
        "system"
    ],
    "wof:name":"Music Power",
    "wof:placetype":"venue"
},
  "geometry": {"coordinates":[3.8292250633,51.095539093],"type":"Point"}
}