{
  "type": "Feature",
  "properties": {
    "addr:full":"Hofeinde 221 Vosselaar Antwerpen 2350",
    "addr:housenumber":"221",
    "addr:postcode":"2350",
    "addr:street":"Hofeinde",
    "iso:country":"BE",
    "sg:address":"Hofeinde 221",
    "sg:city":"Vosselaar",
    "sg:classifiers":[
        {
            "category":"Health Services",
            "subcategory":"Health Practitioner",
            "type":"Services"
        }
    ],
    "sg:phone":"+32 14 61 68 50",
    "sg:postcode":"2350",
    "sg:province":"Antwerpen",
    "sg:tags":[
        "physiotherapist"
    ],
    "wof:name":"Broeckx Kris",
    "wof:placetype":"venue"
},
  "geometry": {"coordinates":[4.8777599335,51.3253707886],"type":"Point"}
}