{
  "type": "Feature",
  "properties": {
    "addr:full":"Diesterstraat 27 Box 12 Sint-truiden Limburg 3800",
    "addr:housenumber":"27 box 12",
    "addr:postcode":"3800",
    "addr:street":"Diesterstraat",
    "iso:country":"BE",
    "sg:address":"Diesterstraat 27 Box 12",
    "sg:city":"Sint-truiden",
    "sg:classifiers":[
        {
            "category":"Professional",
            "subcategory":"Business Services",
            "type":"Services"
        }
    ],
    "sg:phone":"+32 11 68 07 80",
    "sg:postcode":"3800",
    "sg:province":"Limburg",
    "sg:tags":[
        "bookkeeping"
    ],
    "wof:name":"D & D Consulting",
    "wof:placetype":"venue"
},
  "geometry": {"coordinates":[5.1853461266,50.8175468445],"type":"Point"}
}