{
  "type": "Feature",
  "properties": {
    "addr:full":"Siemenslaan 7a Dilsen-stokkem (lanklaar) Limburg 3650",
    "addr:housenumber":"7a",
    "addr:postcode":"3650",
    "addr:street":"Siemenslaan",
    "iso:country":"BE",
    "sg:address":"Siemenslaan 7a",
    "sg:city":"Dilsen-stokkem (lanklaar)",
    "sg:classifiers":[
        {
            "category":"Banks & Credit Unions",
            "subcategory":"Investment Brokerage",
            "type":"Services"
        }
    ],
    "sg:phone":"+32 89 75 27 64",
    "sg:postcode":"3650",
    "sg:province":"Limburg",
    "sg:tags":[
        "printing",
        "-"
    ],
    "wof:name":"Media Partners Nv",
    "wof:placetype":"venue"
},
  "geometry": {"coordinates":[5.7065601349,51.0166816711],"type":"Point"}
}