{
  "type": "Feature",
  "properties": {
    "addr:full":"Geerdegemstraat 152 Mechelen Antwerpen 2800",
    "addr:housenumber":"152",
    "addr:postcode":"2800",
    "addr:street":"Geerdegemstraat",
    "iso:country":"BE",
    "sg:address":"Geerdegemstraat 152",
    "sg:city":"Mechelen",
    "sg:orig_category":"M\u00e9decins and sp\u00e9cialistes",
    "sg:phone":"+32 15 41 26 76",
    "sg:postcode":"2800",
    "sg:province":"Antwerpen",
    "wof:name":"Clement Borghgraef",
    "wof:placetype":"venue"
},
  "geometry": {"coordinates":[4.4736089706,50.9957084656],"type":"Point"}
}