{
  "type": "Feature",
  "properties": {
    "addr:full":"Kastelein 124 Turnhout Antwerpen 2300",
    "addr:housenumber":"124",
    "addr:postcode":"2300",
    "addr:street":"Kastelein",
    "iso:country":"BE",
    "sg:address":"Kastelein 124",
    "sg:city":"Turnhout",
    "sg:orig_category":"Woningbouw",
    "sg:phone":"+32 14 41 70 64",
    "sg:postcode":"2300",
    "sg:province":"Antwerpen",
    "wof:name":"Frederik Brosens",
    "wof:placetype":"venue"
},
  "geometry": {"coordinates":[4.9431757927,51.346244812],"type":"Point"}
}