{
  "type": "Feature",
  "properties": {
    "iso:country":"BE",
    "sg:address":"Victor Bocqu\u00e9straat 17",
    "sg:city":"Aalst",
    "sg:classifiers":[
        {
            "category":"Autos & Motor Vehicles",
            "subcategory":"Automobile Sales",
            "type":"Retail Goods"
        }
    ],
    "sg:phone":"+32 53 77 90 20",
    "sg:postcode":"9300",
    "sg:province":"Oost-Vlaanderen",
    "sg:tags":[
        "car",
        "used",
        "-"
    ],
    "wof:name":"Autobedrijf Robbe Nv",
    "wof:placetype":"venue"
},
  "geometry": {"coordinates":[4.0379590988,50.9506950378],"type":"Point"}
}