{
  "type": "Feature",
  "properties": {
    "addr:full":"Karestraat 11 Halen Limburg 3545",
    "addr:housenumber":"11",
    "addr:postcode":"3545",
    "addr:street":"Karestraat",
    "iso:country":"BE",
    "sg:address":"Karestraat 11",
    "sg:city":"Halen",
    "sg:orig_category":"Dameskledingzaken",
    "sg:phone":"+32 13 44 23 06",
    "sg:postcode":"3545",
    "sg:province":"Limburg",
    "wof:name":"Hilda Vanschoenwinkel",
    "wof:placetype":"venue"
},
  "geometry": {"coordinates":[5.1121621132,50.9758682251],"type":"Point"}
}