{
  "type": "Feature",
  "properties": {
    "addr:full":"Rue Le Marais 52 Villers-le-bouillet (fize-fontaine) Li\u00e8ge 4530",
    "addr:housenumber":"52",
    "addr:postcode":"4530",
    "addr:street":"Rue Le Marais",
    "iso:country":"BE",
    "sg:address":"Rue Le Marais 52",
    "sg:city":"Villers-le-bouillet (fize-fontaine)",
    "sg:classifiers":[
        {
            "category":"Health Services",
            "subcategory":"Health Practitioner",
            "type":"Services"
        }
    ],
    "sg:phone":"+32 4 259 69 18",
    "sg:postcode":"4530",
    "sg:province":"Li\u00e8ge",
    "sg:tags":[
        "physiotherapist"
    ],
    "wof:name":"Dehay Marc",
    "wof:placetype":"venue"
},
  "geometry": {"coordinates":[5.2652001381,50.5784301758],"type":"Point"}
}