{
  "type": "Feature",
  "properties": {
    "iso:country":"BE",
    "sg:address":"Grotstr 74",
    "sg:city":"Oostrozebeke",
    "sg:classifiers":[
        {
            "category":"Home & Garden",
            "subcategory":"Furniture",
            "type":"Retail Goods"
        }
    ],
    "sg:phone":"+32 51 40 47 18",
    "sg:postcode":"8780",
    "sg:province":"West-Vlaanderen",
    "sg:tags":[
        "household",
        "wood"
    ],
    "wof:name":"Tack Keukens En Meubelen Nv",
    "wof:placetype":"venue"
},
  "geometry": {"coordinates":[3.3569760323,50.9451942444],"type":"Point"}
}