{
  "type": "Feature",
  "properties": {
    "addr:full":"Schootstraat 67 Heusden-zolder (heusden) Limburg 3550",
    "addr:housenumber":"67",
    "addr:postcode":"3550",
    "addr:street":"Schootstraat",
    "iso:country":"BE",
    "sg:address":"Schootstraat 67",
    "sg:city":"Heusden-zolder (heusden)",
    "sg:classifiers":[
        {
            "category":"Home & Garden",
            "subcategory":"Carpets & Floor Coverings",
            "type":"Retail Goods"
        }
    ],
    "sg:phone":"+32 11 42 11 53",
    "sg:postcode":"3550",
    "sg:province":"Limburg",
    "sg:tags":[
        "armoring"
    ],
    "wof:name":"Monochappe Nv",
    "wof:placetype":"venue"
},
  "geometry": {"coordinates":[5.2799930573,51.0281028748],"type":"Point"}
}