{
  "type": "Feature",
  "properties": {
    "addr:full":"Carillolei 76 Aartselaar Antwerpen 2630",
    "addr:housenumber":"76",
    "addr:postcode":"2630",
    "addr:street":"Carillolei",
    "iso:country":"BE",
    "sg:address":"Carillolei 76",
    "sg:city":"Aartselaar",
    "sg:classifiers":[
        {
            "category":"Professional",
            "subcategory":"Accounting & Tax Preparation",
            "type":"Services"
        }
    ],
    "sg:phone":"+32 3 645 30 35",
    "sg:postcode":"2630",
    "sg:province":"Antwerpen",
    "sg:tags":[
        "accountant"
    ],
    "wof:name":"Cornelius Van Aerde",
    "wof:placetype":"venue"
},
  "geometry": {"coordinates":[4.3824858665,51.1311225891],"type":"Point"}
}