{
  "type": "Feature",
  "properties": {
    "addr:full":"Rue De Blanmont 14b1 Walhain Brabant Wallon 1457",
    "addr:housenumber":"14b1;1457",
    "addr:street":"Rue De Blanmont",
    "iso:country":"BE",
    "sg:address":"Rue De Blanmont 14b1",
    "sg:city":"Walhain",
    "sg:orig_category":"Groententeelt Landbouwmachines Gh Tuinen",
    "sg:phone":"+32 10 65 73 24",
    "sg:postcode":"1457",
    "sg:province":"Brabant Wallon",
    "wof:name":"M.r. Jardin",
    "wof:placetype":"venue"
},
  "geometry": {"coordinates":[4.650785923,50.6305389404],"type":"Point"}
}