{
  "type": "Feature",
  "properties": {
    "iso:country":"BE",
    "sg:address":"Avenue Schlogel 43",
    "sg:city":"Ciney",
    "sg:classifiers":[
        {
            "category":"Health Services",
            "subcategory":"Doctor",
            "type":"Services"
        }
    ],
    "sg:phone":"+32 83 21 20 93",
    "sg:postcode":"5590",
    "sg:province":"Namur",
    "sg:tags":[
        "medicinephysicians",
        "surgeon"
    ],
    "wof:name":"De Thier Tanguy",
    "wof:placetype":"venue"
},
  "geometry": {"coordinates":[5.1078848839,50.2977752686],"type":"Point"}
}