{
  "type": "Feature",
  "properties": {
    "iso:country":"BE",
    "sg:address":"Wakkensteenweg 24",
    "sg:city":"Wielsbeke (sint-baafs-vijve)",
    "sg:orig_category":"Domotics",
    "sg:phone":"+32 56 61 49 66",
    "sg:postcode":"8710",
    "sg:province":"West-Vlaanderen",
    "wof:name":"Goderis B",
    "wof:placetype":"venue"
},
  "geometry": {"coordinates":[3.3960630894,50.9163627625],"type":"Point"}
}