{
  "type": "Feature",
  "properties": {
    "iso:country":"BE",
    "sg:address":"Gebroeders Van Raemdoncklaan 60",
    "sg:city":"Edegem",
    "sg:classifiers":[
        {
            "category":"Professional",
            "subcategory":"Art Services",
            "type":"Services"
        }
    ],
    "sg:phone":"+32 3 457 34 44",
    "sg:postcode":"2650",
    "sg:province":"Antwerpen",
    "sg:tags":[
        "designer",
        "display"
    ],
    "wof:name":"Abc Etalages",
    "wof:placetype":"venue"
},
  "geometry": {"coordinates":[4.4250030518,51.1535835266],"type":"Point"}
}