{
  "type": "Feature",
  "properties": {
    "addr:full":"Energielaan 11 Kapellen Antwerpen 2950",
    "addr:housenumber":"11",
    "addr:postcode":"2950",
    "addr:street":"Energielaan",
    "iso:country":"BE",
    "sg:address":"Energielaan 11",
    "sg:city":"Kapellen",
    "sg:orig_category":"Non-Classified Establishments",
    "sg:phone":"+32 3 666 06 00",
    "sg:postcode":"2950",
    "sg:province":"Antwerpen",
    "wof:name":"Ambiarte Nv",
    "wof:placetype":"venue"
},
  "geometry": {"coordinates":[4.502726078,51.3553237915],"type":"Point"}
}