{
  "type": "Feature",
  "properties": {
    "iso:country":"BE",
    "sg:address":"Grand'rue 152",
    "sg:city":"Moeskroen/mouscron",
    "sg:classifiers":[
        {
            "category":"Personal",
            "subcategory":"Beauty Salon",
            "type":"Services"
        }
    ],
    "sg:phone":"+32 56 33 00 33",
    "sg:postcode":"7700",
    "sg:province":"Hainaut",
    "sg:tags":[
        "de",
        "coiffure"
    ],
    "wof:name":"Coiffure Mireille",
    "wof:placetype":"venue"
},
  "geometry": {"coordinates":[3.2147009373,50.7433891296],"type":"Point"}
}