{
  "type": "Feature",
  "properties": {
    "iso:country":"BE",
    "sg:address":"Burgemeester Mayeurlaan 38",
    "sg:city":"Kortrijk",
    "sg:orig_category":"Imitation jewelry - Mfg.& Whol.",
    "sg:phone":"+32 56 21 97 22",
    "sg:postcode":"8500",
    "sg:province":"West-Vlaanderen",
    "wof:name":"Gento Jewels-xavier Verdonckt",
    "wof:placetype":"venue"
},
  "geometry": {"coordinates":[3.2785871029,50.814163208],"type":"Point"}
}