{
  "type": "Feature",
  "properties": {
    "addr:full":"Processiestraat 13 Beringen (paal) Limburg 3583",
    "addr:housenumber":"13",
    "addr:postcode":"3583",
    "addr:street":"Processiestraat",
    "iso:country":"BE",
    "sg:address":"Processiestraat 13",
    "sg:city":"Beringen (paal)",
    "sg:classifiers":[
        {
            "category":"Professional",
            "subcategory":"Management & Consulting",
            "type":"Services"
        }
    ],
    "sg:phone":"+32 11 43 66 07",
    "sg:postcode":"3583",
    "sg:province":"Limburg",
    "sg:tags":[
        "-",
        "processing",
        "data",
        "consultant"
    ],
    "wof:name":"Kerkhofs Information Systems Solutions Bvba",
    "wof:placetype":"venue"
},
  "geometry": {"coordinates":[5.1706700325,51.0389442444],"type":"Point"}
}