{
  "type": "Feature",
  "properties": {
    "iso:country":"BE",
    "sg:address":"Rue De Mangombroux 175",
    "sg:city":"Verviers",
    "sg:orig_category":"Non-Classified Establishments",
    "sg:phone":"+32 87 31 69 97",
    "sg:postcode":"4800",
    "sg:province":"Li\u00e8ge",
    "wof:name":"Ma\u00efpa\u00ef",
    "wof:placetype":"venue"
},
  "geometry": {"coordinates":[5.8727488518,50.5879211426],"type":"Point"}
}