{
  "type": "Feature",
  "properties": {
    "iso:country":"BE",
    "sg:address":"Clos Del'm\u00e9 31",
    "sg:city":"Ans (alleur)",
    "sg:classifiers":[
        {
            "category":"Building & Trades",
            "subcategory":"Plumbing",
            "type":"Services"
        }
    ],
    "sg:phone":"+32 4 246 59 02",
    "sg:postcode":"4432",
    "sg:province":"Li\u00e8ge",
    "sg:tags":[
        "repair",
        "mainten",
        "-",
        "central",
        "heating"
    ],
    "wof:name":"Flam-eco",
    "wof:placetype":"venue"
},
  "geometry": {"coordinates":[5.5058450699,50.6685256958],"type":"Point"}
}