{
  "type": "Feature",
  "properties": {
    "iso:country":"BE",
    "sg:address":"Rue Adolphe-sax 76",
    "sg:city":"Dinant",
    "sg:orig_category":"Blanchisseries and teintureries",
    "sg:phone":"+32 82 22 67 70",
    "sg:postcode":"5500",
    "sg:province":"Namur",
    "wof:name":"La Pince \u00c0 Linge",
    "wof:placetype":"venue"
},
  "geometry": {"coordinates":[4.9101147652,50.2622795105],"type":"Point"}
}