{
  "type": "Feature",
  "properties": {
    "addr:full":"Patrijzenlaan 11 Overijse Vlaams-Brabant 3090",
    "addr:housenumber":"11",
    "addr:postcode":"3090",
    "addr:street":"Patrijzenlaan",
    "iso:country":"BE",
    "sg:address":"Patrijzenlaan 11",
    "sg:city":"Overijse",
    "sg:orig_category":"Installation \u00e9lectrique r\u00e9sidentielle",
    "sg:phone":"+32 2 687 77 28",
    "sg:postcode":"3090",
    "sg:province":"Vlaams-Brabant",
    "wof:name":"Electra-city",
    "wof:placetype":"venue"
},
  "geometry": {"coordinates":[4.4949231148,50.7443275452],"type":"Point"}
}