{
  "type": "Feature",
  "properties": {
    "addr:full":"Kortrijksestraat 131 Kuurne West-Vlaanderen 8520",
    "addr:housenumber":"131",
    "addr:postcode":"8520",
    "addr:street":"Kortrijksestraat",
    "iso:country":"BE",
    "sg:address":"Kortrijksestraat 131",
    "sg:city":"Kuurne",
    "sg:orig_category":"Herstellingen and onderhoud van auto's",
    "sg:phone":"+32 56 37 39 69",
    "sg:postcode":"8520",
    "sg:province":"West-Vlaanderen",
    "wof:name":"Carwash Joleen",
    "wof:placetype":"venue"
},
  "geometry": {"coordinates":[3.2763209343,50.8454551697],"type":"Point"}
}