{
  "type": "Feature",
  "properties": {
    "addr:full":"Veenzijde 63 Lille (gierle) Antwerpen 2275",
    "addr:housenumber":"63",
    "addr:postcode":"2275",
    "addr:street":"Veenzijde",
    "iso:country":"BE",
    "sg:address":"Veenzijde 63",
    "sg:city":"Lille (gierle)",
    "sg:classifiers":[
        {
            "category":"Real Estate",
            "subcategory":"Architect",
            "type":"Services"
        }
    ],
    "sg:phone":"+32 14 55 58 95",
    "sg:postcode":"2275",
    "sg:province":"Antwerpen",
    "wof:name":"Hoskens A",
    "wof:placetype":"venue"
},
  "geometry": {"coordinates":[4.86454916,51.2575531006],"type":"Point"}
}