{
  "type": "Feature",
  "properties": {
    "iso:country":"BE",
    "sg:address":"Groenstraat 3",
    "sg:city":"Lummen",
    "sg:orig_category":"D\u00e9corateurs d'int\u00e9rieur",
    "sg:phone":"+32 13 52 30 78",
    "sg:postcode":"3560",
    "sg:province":"Limburg",
    "wof:name":"Machteld Theys",
    "wof:placetype":"venue"
},
  "geometry": {"coordinates":[5.1937618256,50.991104126],"type":"Point"}
}