{
  "type": "Feature",
  "properties": {
    "addr:full":"Mierdsedijk 82 Ravels Antwerpen 2382",
    "addr:housenumber":"82",
    "addr:postcode":"2382",
    "addr:street":"Mierdsedijk",
    "iso:country":"BE",
    "sg:address":"Mierdsedijk 82",
    "sg:city":"Ravels",
    "sg:orig_category":"Epiceries",
    "sg:phone":"+32 14 65 51 65",
    "sg:postcode":"2382",
    "sg:province":"Antwerpen",
    "wof:name":"Theresia Devue",
    "wof:placetype":"venue"
},
  "geometry": {"coordinates":[5.041768074,51.4469108582],"type":"Point"}
}