{
  "type": "Feature",
  "properties": {
    "addr:full":"Rue De Virelles 17 Couvin Namur 5660",
    "addr:housenumber":"17",
    "addr:postcode":"5660",
    "addr:street":"Rue De Virelles",
    "iso:country":"BE",
    "sg:address":"Rue De Virelles 17",
    "sg:city":"Couvin",
    "sg:classifiers":[
        {
            "category":"Recreation",
            "type":"Entertainment"
        }
    ],
    "sg:phone":"+32 60 34 56 98",
    "sg:postcode":"5660",
    "sg:province":"Namur",
    "sg:tags":[
        "diver",
        "amusement"
    ],
    "wof:name":"Sono Mega-mix",
    "wof:placetype":"venue"
},
  "geometry": {"coordinates":[4.4018349648,50.070186615],"type":"Point"}
}