{
  "type": "Feature",
  "properties": {
    "addr:full":"Place Communale 7 Assesse Namur 5330",
    "addr:housenumber":"7",
    "addr:postcode":"5330",
    "addr:street":"Place Communale",
    "iso:country":"BE",
    "sg:address":"Place Communale 7",
    "sg:city":"Assesse",
    "sg:classifiers":[
        {
            "category":"Retail",
            "subcategory":"Auto Repair",
            "type":"Services"
        }
    ],
    "sg:phone":"+32 83 65 65 00",
    "sg:postcode":"5330",
    "sg:province":"Namur",
    "sg:tags":[
        "automobile-body"
    ],
    "wof:name":"Assesse Car",
    "wof:placetype":"venue"
},
  "geometry": {"coordinates":[5.0234217644,50.3715896606],"type":"Point"}
}