{
  "type": "Feature",
  "properties": {
    "addr:full":"Leopoldplein 4 Hasselt Limburg 3500",
    "addr:housenumber":"4",
    "addr:postcode":"3500",
    "addr:street":"Leopoldplein",
    "iso:country":"BE",
    "sg:address":"Leopoldplein 4",
    "sg:city":"Hasselt",
    "sg:orig_category":"Agences de voyages",
    "sg:phone":"+32 11 23 25 88",
    "sg:postcode":"3500",
    "sg:province":"Limburg",
    "wof:name":"Joker Toerisme",
    "wof:placetype":"venue"
},
  "geometry": {"coordinates":[5.335588932,50.9272422791],"type":"Point"}
}