{
  "type": "Feature",
  "properties": {
    "iso:country":"BE",
    "sg:address":"Hasseltsebaan 66",
    "sg:city":"Diest (deurne)",
    "sg:classifiers":[
        {
            "category":"Bakery",
            "type":"Food & Drink"
        }
    ],
    "sg:phone":"+32 13 67 71 27",
    "sg:postcode":"3290",
    "sg:province":"Vlaams-Brabant",
    "sg:tags":[
        "confectioner",
        "baker"
    ],
    "wof:name":"Christophe",
    "wof:placetype":"venue"
},
  "geometry": {"coordinates":[5.0540127754,50.9808807373],"type":"Point"}
}