{
  "type": "Feature",
  "properties": {
    "iso:country":"BE",
    "sg:address":"Markt 4",
    "sg:city":"Aalter",
    "sg:orig_category":"Banken and kredietinstellingen",
    "sg:phone":"+32 9 374 17 47",
    "sg:postcode":"9880",
    "sg:province":"Oost-Vlaanderen",
    "wof:name":"Ippa",
    "wof:placetype":"venue"
},
  "geometry": {"coordinates":[3.4483699799,51.0837402344],"type":"Point"}
}