{
  "type": "Feature",
  "properties": {
    "addr:full":"Chauss\u00c9e De Tongres 457 Luik Li\u00e8ge 4000",
    "addr:housenumber":"457",
    "addr:postcode":"4000",
    "addr:street":"Chausse\u0301E De Tongres;Luik Lie\u0300Ge",
    "iso:country":"BE",
    "sg:address":"Chauss\u00c9e De Tongres 457",
    "sg:city":"Luik",
    "sg:orig_category":"Tuinen",
    "sg:phone":"+32 4 247 33 33",
    "sg:postcode":"4000",
    "sg:province":"Li\u00e8ge",
    "wof:name":"Jfd Entreprise",
    "wof:placetype":"venue"
},
  "geometry": {"coordinates":[5.5448517799,50.6773948669],"type":"Point"}
}