{
  "type": "Feature",
  "properties": {
    "iso:country":"BE",
    "sg:address":"Lombardenvest 33",
    "sg:city":"Antwerpen",
    "sg:orig_category":"Diverse textielproducten Fab Textiel",
    "sg:phone":"+32 3 231 14 39",
    "sg:postcode":"2000",
    "sg:province":"Antwerpen",
    "wof:name":"Jannel",
    "wof:placetype":"venue"
},
  "geometry": {"coordinates":[4.4017558098,51.2174797058],"type":"Point"}
}