{
  "type": "Feature",
  "properties": {
    "addr:full":"Hollandstraat 13 Gooik Vlaams-Brabant 1755",
    "addr:housenumber":"13",
    "addr:postcode":"1755",
    "addr:street":"Hollandstraat",
    "iso:country":"BE",
    "sg:address":"Hollandstraat 13",
    "sg:city":"Gooik",
    "sg:classifiers":[
        {
            "category":"Shopping",
            "subcategory":"Bicycles & Sporting Goods",
            "type":"Retail Goods"
        }
    ],
    "sg:phone":"+32 54 56 91 42",
    "sg:postcode":"1755",
    "sg:province":"Vlaams-Brabant",
    "sg:tags":[
        "article",
        "de",
        "sport",
        "camping"
    ],
    "wof:name":"Constructie-atelier Van Der Speeten",
    "wof:placetype":"venue"
},
  "geometry": {"coordinates":[4.0756998062,50.7590675354],"type":"Point"}
}