{
  "type": "Feature",
  "properties": {
    "iso:country":"BE",
    "sg:address":"Gulledelle 98",
    "sg:city":"Bruxelles (woluwe-saint-lambert)",
    "sg:classifiers":[
        {
            "category":"Professional",
            "subcategory":"Management & Consulting",
            "type":"Services"
        }
    ],
    "sg:phone":"+32 2 776 02 22",
    "sg:postcode":"1200",
    "sg:province":"Bruxelles-Capitale",
    "sg:tags":[
        "consultant",
        "agency",
        "advertising"
    ],
    "wof:name":"Fcb Worldwide Sa",
    "wof:placetype":"venue"
},
  "geometry": {"coordinates":[4.4252090454,50.8559494019],"type":"Point"}
}