{
  "type": "Feature",
  "properties": {
    "addr:full":"Veldstraat 9 Balen (olmen) Antwerpen 2491",
    "addr:housenumber":"9",
    "addr:postcode":"2491",
    "addr:street":"Veldstraat",
    "iso:country":"BE",
    "sg:address":"Veldstraat 9",
    "sg:city":"Balen (olmen)",
    "sg:orig_category":"Newspapers, magazines, periodicals - Distribution",
    "sg:phone":"+32 14 30 81 23",
    "sg:postcode":"2491",
    "sg:province":"Antwerpen",
    "wof:name":"Boekhandel Christel",
    "wof:placetype":"venue"
},
  "geometry": {"coordinates":[5.153181076,51.1383934021],"type":"Point"}
}