{
  "type": "Feature",
  "properties": {
    "iso:country":"BE",
    "sg:address":"Rue De Gembloux 13",
    "sg:city":"La Bruyere",
    "sg:orig_category":"Avocats and conseillers juridiques",
    "sg:phone":"+32 81 56 66 25",
    "sg:postcode":"5080",
    "sg:province":"Namur",
    "wof:name":"B. Dozin",
    "wof:placetype":"venue"
},
  "geometry": {"coordinates":[4.7969341278,50.4988594055],"type":"Point"}
}