{
  "type": "Feature",
  "properties": {
    "addr:full":"Kapelweg 27 Neerpelt Limburg 3910",
    "addr:housenumber":"27",
    "addr:postcode":"3910",
    "addr:street":"Kapelweg",
    "iso:country":"BE",
    "sg:address":"Kapelweg 27",
    "sg:city":"Neerpelt",
    "sg:orig_category":"Sportclubs",
    "sg:phone":"+32 11 64 84 41",
    "sg:postcode":"3910",
    "sg:province":"Limburg",
    "wof:name":"Goju Ryu",
    "wof:placetype":"venue"
},
  "geometry": {"coordinates":[5.4469709396,51.2000656128],"type":"Point"}
}