{
  "type": "Feature",
  "properties": {
    "iso:country":"BE",
    "sg:address":"Dorpsstraat 73",
    "sg:city":"Damme",
    "sg:classifiers":[
        {
            "category":"Cafe",
            "type":"Food & Drink"
        }
    ],
    "sg:phone":"+32 50 37 17 19",
    "sg:postcode":"8340",
    "sg:province":"West-Vlaanderen",
    "sg:tags":[
        "caf\u00e9s"
    ],
    "wof:name":"The Q-ball",
    "wof:placetype":"venue"
},
  "geometry": {"coordinates":[3.3257060051,51.2015647888],"type":"Point"}
}