{
  "type": "Feature",
  "properties": {
    "addr:full":"Westlaan 104 Roeselare West-Vlaanderen 8800",
    "addr:housenumber":"104",
    "addr:postcode":"8800",
    "addr:street":"Westlaan",
    "iso:country":"BE",
    "sg:address":"Westlaan 104",
    "sg:city":"Roeselare",
    "sg:orig_category":"Entretien and r\u00e9parations de voitures. R\u00e9cup\u00e9ration de mati\u00e8res m\u00e9talliques recyclables and d\u00e9moliss",
    "sg:phone":"+32 51 22 01 22",
    "sg:postcode":"8800",
    "sg:province":"West-Vlaanderen",
    "wof:name":"A. A. M.",
    "wof:placetype":"venue"
},
  "geometry": {"coordinates":[3.116574049,50.9396133423],"type":"Point"}
}