{
  "type": "Feature",
  "properties": {
    "addr:full":"Korspelsesteenweg 43 Beringen Limburg 3581",
    "addr:housenumber":"43",
    "addr:postcode":"3581",
    "addr:street":"Korspelsesteenweg",
    "iso:country":"BE",
    "sg:address":"Korspelsesteenweg 43",
    "sg:city":"Beringen",
    "sg:orig_category":"Enseignement maternel and primaire",
    "sg:phone":"+32 11 34 54 93",
    "sg:postcode":"3581",
    "sg:province":"Limburg",
    "wof:name":"Vrije Kleuterschool",
    "wof:placetype":"venue"
},
  "geometry": {"coordinates":[5.2228298187,51.0881996155],"type":"Point"}
}