{
  "type": "Feature",
  "properties": {
    "addr:full":"Zevekotestraat 61 Gistel West-Vlaanderen 8470",
    "addr:housenumber":"61",
    "addr:postcode":"8470",
    "addr:street":"Zevekotestraat",
    "iso:country":"BE",
    "sg:address":"Zevekotestraat 61",
    "sg:city":"Gistel",
    "sg:orig_category":"Instituts de beaut\u00e9",
    "sg:phone":"+32 59 27 90 27",
    "sg:postcode":"8470",
    "sg:province":"West-Vlaanderen",
    "wof:name":"Pedicure Maenhout",
    "wof:placetype":"venue"
},
  "geometry": {"coordinates":[2.9172310829,51.1350021362],"type":"Point"}
}