{
  "type": "Feature",
  "properties": {
    "addr:full":"Vlamingstraat 30 Brugge West-Vlaanderen 8000",
    "addr:housenumber":"30",
    "addr:postcode":"8000",
    "addr:street":"Vlamingstraat",
    "iso:country":"BE",
    "sg:address":"Vlamingstraat 30",
    "sg:city":"Brugge",
    "sg:classifiers":[
        {
            "category":"Shopping",
            "subcategory":"Jewelry",
            "type":"Retail Goods"
        }
    ],
    "sg:phone":"+32 50 33 52 86",
    "sg:postcode":"8000",
    "sg:province":"West-Vlaanderen",
    "sg:tags":[
        "jeweller",
        "-"
    ],
    "wof:name":"Adj",
    "wof:placetype":"venue"
},
  "geometry": {"coordinates":[3.2246570587,51.2101974487],"type":"Point"}
}