{
  "type": "Feature",
  "properties": {
    "iso:country":"BE",
    "sg:address":"Zone Du Grand-pr\u00c9 6",
    "sg:city":"Mont-de-l`enclus",
    "sg:orig_category":"Imprimeries and copyshops",
    "sg:phone":"+32 69 76 99 07",
    "sg:postcode":"7750",
    "sg:province":"Hainaut",
    "wof:name":"Eco Prints",
    "wof:placetype":"venue"
},
  "geometry": {"coordinates":[-64.3072967529,45.1012001038],"type":"Point"}
}