{
  "type": "Feature",
  "properties": {
    "addr:full":"Ijzerplein 4 Brussel/bruxelles Bruxelles-Capitale 1000",
    "addr:housenumber":"4",
    "addr:postcode":"1000",
    "addr:street":"Ijzerplein;/",
    "iso:country":"BE",
    "sg:address":"Ijzerplein 4",
    "sg:city":"Brussel/bruxelles",
    "sg:orig_category":"Benzinestations and brandstoffen Herstellingen and onderhoud van auto's",
    "sg:phone":"+32 2 217 74 44",
    "sg:postcode":"1000",
    "sg:province":"Bruxelles-Capitale",
    "wof:name":"Shell",
    "wof:placetype":"venue"
},
  "geometry": {"coordinates":[4.3486361504,50.8578987122],"type":"Point"}
}