{
  "type": "Feature",
  "properties": {
    "iso:country":"BE",
    "sg:address":"Avenue Ambiorix 29",
    "sg:city":"Wemmel/wemmel",
    "sg:orig_category":"Agences immobili\u00e8res",
    "sg:phone":"+32 2 461 27 18",
    "sg:postcode":"1780",
    "sg:province":"Vlaams-Brabant",
    "wof:name":"Avimmo",
    "wof:placetype":"venue"
},
  "geometry": {"coordinates":[4.3070898056,50.9067382812],"type":"Point"}
}