{
  "type": "Feature",
  "properties": {
    "addr:full":"Rue De La Station 16 Mont-saint-guibert Brabant Wallon 1435",
    "addr:housenumber":"16",
    "addr:postcode":"1435",
    "addr:street":"Rue De La Station",
    "iso:country":"BE",
    "sg:address":"Rue De La Station 16",
    "sg:city":"Mont-saint-guibert",
    "sg:orig_category":"Treinen and spoorwegen",
    "sg:phone":"+32 10 65 53 73",
    "sg:postcode":"1435",
    "sg:province":"Brabant Wallon",
    "wof:name":"Gare De Mont-saint-guibert",
    "wof:placetype":"venue"
},
  "geometry": {"coordinates":[4.6140828133,50.6375198364],"type":"Point"}
}