{
  "type": "Feature",
  "properties": {
    "addr:full":"Raapstraat 55 Sint-niklaas Oost-Vlaanderen 9100",
    "addr:housenumber":"55",
    "addr:postcode":"9100",
    "addr:street":"Raapstraat",
    "iso:country":"BE",
    "sg:address":"Raapstraat 55",
    "sg:city":"Sint-niklaas",
    "sg:classifiers":[
        {
            "category":"Fast Food",
            "type":"Food & Drink"
        }
    ],
    "sg:phone":"+32 3 780 77 21",
    "sg:postcode":"9100",
    "sg:province":"Oost-Vlaanderen",
    "sg:tags":[
        "\u00c0",
        "emporter",
        "restaurants"
    ],
    "wof:name":"Het Belegde Broodje",
    "wof:placetype":"venue"
},
  "geometry": {"coordinates":[4.1627821922,51.1715278625],"type":"Point"}
}