{
  "type": "Feature",
  "properties": {
    "addr:full":"Mechelse Steenweg 33 Antwerpen Antwerpen 2018",
    "addr:housenumber":"33",
    "addr:postcode":"2018",
    "addr:street":"Steenweg",
    "iso:country":"BE",
    "sg:address":"Mechelse Steenweg 33",
    "sg:city":"Antwerpen",
    "sg:classifiers":[
        {
            "category":"Professional",
            "subcategory":"Lawyer & Legal Services",
            "type":"Services"
        }
    ],
    "sg:phone":"+32 3 232 50 60",
    "sg:postcode":"2018",
    "sg:province":"Antwerpen",
    "wof:name":"Vernaillen Sven",
    "wof:placetype":"venue"
},
  "geometry": {"coordinates":[4.4083337784,51.2095108032],"type":"Point"}
}