{
  "type": "Feature",
  "properties": {
    "iso:country":"BE",
    "sg:address":"Rue Du Belv\u00c9d\u00c8re 41",
    "sg:city":"Namur",
    "sg:orig_category":"Cin\u00e9mas",
    "sg:phone":"+32 81 73 64 69",
    "sg:postcode":"5000",
    "sg:province":"Namur",
    "wof:name":"Cin\u00c9 Forum",
    "wof:placetype":"venue"
},
  "geometry": {"coordinates":[4.8442730904,50.4617347717],"type":"Point"}
}