{
  "type": "Feature",
  "properties": {
    "iso:country":"BE",
    "sg:address":"Avenue Libert Froidmont 37",
    "sg:city":"Oupeye",
    "sg:orig_category":"Fruitteelt GROENTEN AND FRUIT",
    "sg:phone":"+32 4 379 16 73",
    "sg:postcode":"4684",
    "sg:province":"Li\u00e8ge",
    "wof:name":"Maison Morrier & Busem",
    "wof:placetype":"venue"
},
  "geometry": {"coordinates":[5.6659240723,50.7388076782],"type":"Point"}
}