{
  "type": "Feature",
  "properties": {
    "addr:full":"Speltstraat 7 Diksmuide West-Vlaanderen 8600",
    "addr:housenumber":"7",
    "addr:postcode":"8600",
    "addr:street":"Speltstraat",
    "iso:country":"BE",
    "sg:address":"Speltstraat 7",
    "sg:city":"Diksmuide",
    "sg:classifiers":[
        {
            "category":"Home & Garden",
            "subcategory":"Carpets & Floor Coverings",
            "type":"Retail Goods"
        }
    ],
    "sg:phone":"+32 51 50 59 26",
    "sg:postcode":"8600",
    "sg:province":"West-Vlaanderen",
    "sg:tags":[
        "layer",
        "mosaicists"
    ],
    "wof:name":"Seys K",
    "wof:placetype":"venue"
},
  "geometry": {"coordinates":[2.8751900196,51.0293807983],"type":"Point"}
}