{
  "type": "Feature",
  "properties": {
    "addr:full":"Schalienhoevedreef 7 Industriepark Noord 1 Mechelen Antwerpen 2800",
    "addr:housenumber":"1",
    "addr:postcode":"2800",
    "addr:street":"Schalienhoevedreef;Industriepark Noord",
    "iso:country":"BE",
    "sg:address":"Schalienhoevedreef 7 Industriepark Noord 1",
    "sg:city":"Mechelen",
    "sg:classifiers":[
        {
            "category":"Manufacturing",
            "subcategory":"Metals",
            "type":"Manufacturing & Wholesale Goods"
        }
    ],
    "sg:phone":"+32 15 71 99 99",
    "sg:postcode":"2800",
    "sg:province":"Antwerpen",
    "sg:tags":[
        "-",
        "machine",
        "equipment",
        "engineering",
        "machinery",
        "mechanical"
    ],
    "wof:name":"Saint-gobain Diamond Products Nv",
    "wof:placetype":"venue"
},
  "geometry": {"coordinates":[4.4854397774,51.0289268494],"type":"Point"}
}