{
  "type": "Feature",
  "properties": {
    "addr:full":"Vogelheide 18 Gent (zwijnaarde) Oost-Vlaanderen 9052",
    "addr:housenumber":"18",
    "addr:postcode":"9052",
    "addr:street":"Vogelheide",
    "iso:country":"BE",
    "sg:address":"Vogelheide 18",
    "sg:city":"Gent (zwijnaarde)",
    "sg:classifiers":[
        {
            "category":"Health Services",
            "subcategory":"Doctor",
            "type":"Services"
        }
    ],
    "sg:phone":"+32 9 221 40 10",
    "sg:postcode":"9052",
    "sg:province":"Oost-Vlaanderen",
    "sg:tags":[
        "medicinephysicians",
        "surgeon"
    ],
    "wof:name":"Bouckaert L",
    "wof:placetype":"venue"
},
  "geometry": {"coordinates":[3.7253649235,51.0505599976],"type":"Point"}
}