{
  "type": "Feature",
  "properties": {
    "iso:country":"BE",
    "sg:address":"Chauss\u00c9e De Wemmel 90",
    "sg:city":"Jette",
    "sg:classifiers":[
        {
            "category":"Cafe",
            "type":"Food & Drink"
        }
    ],
    "sg:phone":"+32 2 420 17 56",
    "sg:postcode":"1090",
    "sg:province":"Bruxelles-Capitale",
    "sg:tags":[
        "caf\u00e9s"
    ],
    "wof:name":"Mikesand",
    "wof:placetype":"venue"
},
  "geometry": {"coordinates":[4.3248977661,50.8755073547],"type":"Point"}
}