{
  "type": "Feature",
  "properties": {
    "addr:full":"Joseph Depauwstraat 90 Sint-pieters-leeuw Vlaams-Brabant 1600",
    "addr:housenumber":"90",
    "addr:postcode":"1600",
    "addr:street":"Depauwstraat",
    "iso:country":"BE",
    "sg:address":"Joseph Depauwstraat 90",
    "sg:city":"Sint-pieters-leeuw",
    "sg:orig_category":"Boucheries",
    "sg:phone":"+32 2 377 18 46",
    "sg:postcode":"1600",
    "sg:province":"Vlaams-Brabant",
    "wof:name":"Alain Overath",
    "wof:placetype":"venue"
},
  "geometry": {"coordinates":[4.2472381592,50.7755317688],"type":"Point"}
}