{
  "type": "Feature",
  "properties": {
    "iso:country":"BE",
    "sg:address":"Kloosterstraat 10",
    "sg:city":"Bilzen",
    "sg:classifiers":[
        {
            "category":"Shopping",
            "subcategory":"Bicycles & Sporting Goods",
            "type":"Retail Goods"
        }
    ],
    "sg:phone":"+32 89 41 17 75",
    "sg:postcode":"3740",
    "sg:province":"Limburg",
    "sg:tags":[
        "article",
        "de",
        "sport",
        "camping"
    ],
    "wof:name":"Roco Sport",
    "wof:placetype":"venue"
},
  "geometry": {"coordinates":[5.5183200836,50.8713035583],"type":"Point"}
}