{
  "type": "Feature",
  "properties": {
    "addr:full":"Chauss\u00c9e De Tongres 281 Amay Li\u00e8ge 4540",
    "addr:housenumber":"281",
    "addr:postcode":"4540",
    "addr:street":"Chausse\u0301E De Tongres",
    "iso:country":"BE",
    "sg:address":"Chauss\u00c9e De Tongres 281",
    "sg:city":"Amay",
    "sg:orig_category":"Woningbouw",
    "sg:phone":"+32 85 31 39 52",
    "sg:postcode":"4540",
    "sg:province":"Li\u00e8ge",
    "wof:name":"Jacques Parmentier",
    "wof:placetype":"venue"
},
  "geometry": {"coordinates":[5.3071889877,50.5617408752],"type":"Point"}
}