{
  "type": "Feature",
  "properties": {
    "iso:country":"BE",
    "sg:address":"Komedieplaats 17",
    "sg:city":"Antwerpen",
    "sg:orig_category":"Bagage and lederwaren",
    "sg:phone":"+32 3 232 02 47",
    "sg:postcode":"2000",
    "sg:province":"Antwerpen",
    "wof:name":"Huis Delvaux",
    "wof:placetype":"venue"
},
  "geometry": {"coordinates":[4.4066271782,51.2162437439],"type":"Point"}
}