{
  "type": "Feature",
  "properties": {
    "addr:full":"Rue Du V\u00c9lodrome 8 Fleron Li\u00e8ge 4621",
    "addr:housenumber":"8",
    "addr:postcode":"4621",
    "addr:street":"Rue Du Ve\u0301Lodrome",
    "iso:country":"BE",
    "sg:address":"Rue Du V\u00c9lodrome 8",
    "sg:city":"Fleron",
    "sg:orig_category":"M\u00e9decins and sp\u00e9cialistes",
    "sg:phone":"+32 4 342 72 91",
    "sg:postcode":"4621",
    "sg:province":"Li\u00e8ge",
    "wof:name":"Mathieu",
    "wof:placetype":"venue"
},
  "geometry": {"coordinates":[5.6970129013,50.6292953491],"type":"Point"}
}