{
  "type": "Feature",
  "properties": {
    "addr:full":"Chauss\u00c9e De Boondael 328 Elsene/ixelles Bruxelles-Capitale 1050",
    "addr:housenumber":"328",
    "addr:postcode":"1050",
    "addr:street":"Chausse\u0301E De Boondael",
    "iso:country":"BE",
    "sg:address":"Chauss\u00c9e De Boondael 328",
    "sg:city":"Elsene/ixelles",
    "sg:classifiers":[
        {
            "category":"Fast Food",
            "type":"Food & Drink"
        }
    ],
    "sg:phone":"+32 2 646 12 83",
    "sg:postcode":"1050",
    "sg:province":"Bruxelles-Capitale",
    "sg:tags":[
        "\u00c0",
        "restaurants",
        "emporter",
        "restaurant"
    ],
    "wof:name":"Restaurant G\u00c9n\u00c9ration",
    "wof:placetype":"venue"
},
  "geometry": {"coordinates":[4.384704113,50.818359375],"type":"Point"}
}