{
  "type": "Feature",
  "properties": {
    "iso:country":"BE",
    "sg:address":"Lusthoflaan 89",
    "sg:city":"Gent (mariakerke)",
    "sg:classifiers":[
        {
            "category":"Health Services",
            "subcategory":"Health Practitioner",
            "type":"Services"
        }
    ],
    "sg:phone":"+32 9 227 41 91",
    "sg:postcode":"9030",
    "sg:province":"Oost-Vlaanderen",
    "sg:tags":[
        "physiotherapist"
    ],
    "wof:name":"Everaert M",
    "wof:placetype":"venue"
},
  "geometry": {"coordinates":[3.6966130733,51.0786933899],"type":"Point"}
}