{
  "type": "Feature",
  "properties": {
    "addr:full":"Rue De Li\u00c8ge 33 Houffalize Luxembourg 6660",
    "addr:housenumber":"33",
    "addr:postcode":"6660",
    "addr:street":"Rue De Lie\u0300Ge",
    "iso:country":"BE",
    "sg:address":"Rue De Li\u00c8ge 33",
    "sg:city":"Houffalize",
    "sg:orig_category":"Rev\u00eatements pour sols and murs. Rev\u00eatements de sols and murs",
    "sg:phone":"+32 61 28 81 05",
    "sg:postcode":"6660",
    "sg:province":"Luxembourg",
    "wof:name":"Louis Kremer",
    "wof:placetype":"venue"
},
  "geometry": {"coordinates":[5.7893390656,50.1384048462],"type":"Point"}
}