{
  "type": "Feature",
  "properties": {
    "addr:full":"Rue Louis Demeuse 18 Herstal Li\u00e8ge 4040",
    "addr:housenumber":"18",
    "addr:postcode":"4040",
    "addr:street":"Rue Louis Demeuse",
    "iso:country":"BE",
    "sg:address":"Rue Louis Demeuse 18",
    "sg:city":"Herstal",
    "sg:orig_category":"Brood, gebak and snoepgoed",
    "sg:phone":"+32 4 264 22 65",
    "sg:postcode":"4040",
    "sg:province":"Li\u00e8ge",
    "wof:name":"Boulangerie Horrembach",
    "wof:placetype":"venue"
},
  "geometry": {"coordinates":[5.6347608566,50.6762046814],"type":"Point"}
}