{
  "type": "Feature",
  "properties": {
    "addr:full":"Louizalaan 421 Brussel/bruxelles Bruxelles-Capitale 1050",
    "addr:housenumber":"421",
    "addr:postcode":"1050",
    "addr:street":"Louizalaan;/",
    "iso:country":"BE",
    "sg:address":"Louizalaan 421",
    "sg:city":"Brussel/bruxelles",
    "sg:orig_category":"Beheer onroerend goed",
    "sg:phone":"+32 2 647 30 06",
    "sg:postcode":"1050",
    "sg:province":"Bruxelles-Capitale",
    "wof:name":"Jacobs",
    "wof:placetype":"venue"
},
  "geometry": {"coordinates":[4.356962204,50.8341941833],"type":"Point"}
}