{
  "type": "Feature",
  "properties": {
    "addr:full":"Place Henri-collignon 11 Onhaye Namur 5520",
    "addr:housenumber":"11",
    "addr:postcode":"5520",
    "addr:street":"Place Henri-Collignon",
    "iso:country":"BE",
    "sg:address":"Place Henri-collignon 11",
    "sg:city":"Onhaye",
    "sg:orig_category":"Openbare veiligheid",
    "sg:phone":"+32 82 64 40 25",
    "sg:postcode":"5520",
    "sg:province":"Namur",
    "wof:name":"Police F\u00c9d\u00c9rale",
    "wof:placetype":"venue"
},
  "geometry": {"coordinates":[4.8400158882,50.2426223755],"type":"Point"}
}