{
  "type": "Feature",
  "properties": {
    "iso:country":"BE",
    "sg:address":"Strombeeksesteenweg 208",
    "sg:city":"Vilvoorde",
    "sg:orig_category":"Alimentation sp\u00e9cialis\u00e9e. Producteurs de l\u00e9gumes",
    "sg:phone":"+32 2 267 42 12",
    "sg:postcode":"1800",
    "sg:province":"Vlaams-Brabant",
    "wof:name":"Frans Van Overbeke",
    "wof:placetype":"venue"
},
  "geometry": {"coordinates":[4.3739900589,50.9052200317],"type":"Point"}
}