{
  "type": "Feature",
  "properties": {
    "addr:full":"Rue Anixhe 43 Juprelle (fexhe-slins) Li\u00e8ge 4458",
    "addr:housenumber":"43",
    "addr:postcode":"4458",
    "addr:street":"Rue Anixhe;Fexhe-Slins",
    "iso:country":"BE",
    "sg:address":"Rue Anixhe 43",
    "sg:city":"Juprelle (fexhe-slins)",
    "sg:classifiers":[
        {
            "category":"Bus Station",
            "type":"Transportation"
        }
    ],
    "sg:phone":"+32 4 278 71 98",
    "sg:postcode":"4458",
    "sg:province":"Li\u00e8ge",
    "sg:tags":[
        "automobile",
        "-",
        "transport"
    ],
    "wof:name":"Transma-li\u00e8ge",
    "wof:placetype":"venue"
},
  "geometry": {"coordinates":[5.5701799393,50.706451416],"type":"Point"}
}