{
  "type": "Feature",
  "properties": {
    "addr:full":"Bist 14 Aartselaar Antwerpen 2630",
    "addr:housenumber":"14",
    "addr:postcode":"2630",
    "addr:street":"Bist",
    "iso:country":"BE",
    "sg:address":"Bist 14",
    "sg:city":"Aartselaar",
    "sg:classifiers":[
        {
            "category":"Utilities",
            "subcategory":"Cable",
            "type":"Services"
        }
    ],
    "sg:phone":"+32 3 870 74 00",
    "sg:postcode":"2630",
    "sg:province":"Antwerpen",
    "sg:tags":[
        "conduit"
    ],
    "wof:name":"Obo Bettermann Belgium Nv/sa",
    "wof:placetype":"venue"
},
  "geometry": {"coordinates":[4.3714089394,51.1244163513],"type":"Point"}
}