{
  "type": "Feature",
  "properties": {
    "addr:full":"Heikant 182 Zele Oost-Vlaanderen 9240",
    "addr:housenumber":"182",
    "addr:postcode":"9240",
    "addr:street":"Heikant",
    "iso:country":"BE",
    "sg:address":"Heikant 182",
    "sg:city":"Zele",
    "sg:classifiers":[
        {
            "category":"Home & Garden",
            "subcategory":"Kitchen Supply",
            "type":"Retail Goods"
        }
    ],
    "sg:phone":"+32 52 45 26 85",
    "sg:postcode":"9240",
    "sg:province":"Oost-Vlaanderen",
    "sg:tags":[
        "installation"
    ],
    "wof:name":"Van Extergem Jaak Bvba",
    "wof:placetype":"venue"
},
  "geometry": {"coordinates":[3.9983310699,51.0639839172],"type":"Point"}
}