{
  "type": "Feature",
  "properties": {
    "addr:full":"Sint-lievenslaan 125 Gent Oost-Vlaanderen 9000",
    "addr:housenumber":"125",
    "addr:postcode":"9000",
    "addr:street":"Sint-Lievenslaan;Oost-Vlaanderen",
    "iso:country":"BE",
    "sg:address":"Sint-lievenslaan 125",
    "sg:city":"Gent",
    "sg:orig_category":"Studios photographiques",
    "sg:phone":"+32 9 223 46 75",
    "sg:postcode":"9000",
    "sg:province":"Oost-Vlaanderen",
    "wof:name":"Bureau Vincent-david",
    "wof:placetype":"venue"
},
  "geometry": {"coordinates":[3.7356939316,51.0385055542],"type":"Point"}
}