{
  "type": "Feature",
  "properties": {
    "addr:full":"Winterslagstraat 20b4 Genk Limburg 3600",
    "addr:housenumber":"20b4",
    "addr:postcode":"3600",
    "addr:street":"Winterslagstraat",
    "iso:country":"BE",
    "sg:address":"Winterslagstraat 20b4",
    "sg:city":"Genk",
    "sg:orig_category":"Parfumeries. Instituts de beaut\u00e9. M\u00e9decines alternatives",
    "sg:phone":"+32 89 35 53 78",
    "sg:postcode":"3600",
    "sg:province":"Limburg",
    "wof:name":"Parfumurie Ega",
    "wof:placetype":"venue"
},
  "geometry": {"coordinates":[5.4987230301,50.9645195007],"type":"Point"}
}