{
  "type": "Feature",
  "properties": {
    "addr:full":"Rue De Mangombroux 405 Verviers Li\u00e8ge 4800",
    "addr:housenumber":"405",
    "addr:postcode":"4800",
    "addr:street":"Rue De Mangombroux",
    "iso:country":"BE",
    "sg:address":"Rue De Mangombroux 405",
    "sg:city":"Verviers",
    "sg:orig_category":"Travaux de pl\u00e2trage",
    "sg:phone":"+32 87 33 96 15",
    "sg:postcode":"4800",
    "sg:province":"Li\u00e8ge",
    "wof:name":"Aldo Daniele",
    "wof:placetype":"venue"
},
  "geometry": {"coordinates":[5.874060154,50.5871505737],"type":"Point"}
}