{
  "type": "Feature",
  "properties": {
    "iso:country":"BE",
    "sg:address":"Rue Sainte Marie 12",
    "sg:city":"Libramont-chevigny",
    "sg:orig_category":"Jardinage",
    "sg:phone":"+32 61 22 54 19",
    "sg:postcode":"6800",
    "sg:province":"Luxembourg",
    "wof:name":"Van Eenoo D.",
    "wof:placetype":"venue"
},
  "geometry": {"coordinates":[5.3761348724,49.9199943542],"type":"Point"}
}