{
  "type": "Feature",
  "properties": {
    "addr:full":"Rue Jan Van Ruusbroeck 13 Bruxelles (evere) Bruxelles-Capitale 1140",
    "addr:housenumber":"13",
    "addr:postcode":"1140",
    "addr:street":"Rue Jan Van Ruusbroeck",
    "iso:country":"BE",
    "sg:address":"Rue Jan Van Ruusbroeck 13",
    "sg:city":"Bruxelles (evere)",
    "sg:classifiers":[
        {
            "category":"Building & Trades",
            "subcategory":"Equipment Rental",
            "type":"Services"
        }
    ],
    "sg:phone":"+32 2 241 45 79",
    "sg:postcode":"1140",
    "sg:province":"Bruxelles-Capitale",
    "sg:tags":[
        "crane",
        "-"
    ],
    "wof:name":"Inov-r Sprl",
    "wof:placetype":"venue"
},
  "geometry": {"coordinates":[4.4009771347,50.8690948486],"type":"Point"}
}