{
  "type": "Feature",
  "properties": {
    "addr:full":"Perrikweg 13 Gavere (vurste) Oost-Vlaanderen 9890",
    "addr:housenumber":"13",
    "addr:postcode":"9890",
    "addr:street":"Perrikweg",
    "iso:country":"BE",
    "sg:address":"Perrikweg 13",
    "sg:city":"Gavere (vurste)",
    "sg:classifiers":[
        {
            "category":"Professional",
            "type":"Services"
        }
    ],
    "sg:phone":"+32 9 384 53 76",
    "sg:postcode":"9890",
    "sg:province":"Oost-Vlaanderen",
    "sg:tags":[
        "entertainer"
    ],
    "wof:name":"Alonso-magical Moments",
    "wof:placetype":"venue"
},
  "geometry": {"coordinates":[3.6588599682,50.9283752441],"type":"Point"}
}