{
  "type": "Feature",
  "properties": {
    "addr:full":"Beirtje 1 Waarschoot Oost-Vlaanderen 9950",
    "addr:housenumber":"1",
    "addr:postcode":"9950",
    "addr:street":"Beirtje",
    "iso:country":"BE",
    "sg:address":"Beirtje 1",
    "sg:city":"Waarschoot",
    "sg:classifiers":[
        {
            "category":"Home & Garden",
            "subcategory":"Carpets & Floor Coverings",
            "type":"Retail Goods"
        }
    ],
    "sg:phone":"+32 9 378 64 00",
    "sg:postcode":"9950",
    "sg:province":"Oost-Vlaanderen",
    "sg:tags":[
        "material",
        "waterproofing"
    ],
    "wof:name":"Bextra Nv",
    "wof:placetype":"venue"
},
  "geometry": {"coordinates":[3.6150209904,51.1393051147],"type":"Point"}
}