{
  "type": "Feature",
  "properties": {
    "addr:full":"Rue Brasseurs 14 Nivelles Brabant Wallon 1400",
    "addr:housenumber":"14",
    "addr:postcode":"1400",
    "addr:street":"Rue Brasseurs",
    "iso:country":"BE",
    "sg:address":"Rue Brasseurs 14",
    "sg:city":"Nivelles",
    "sg:classifiers":[
        {
            "category":"Restaurant",
            "type":"Food & Drink"
        }
    ],
    "sg:phone":"+32 67 21 35 00",
    "sg:postcode":"1400",
    "sg:province":"Brabant Wallon",
    "wof:name":"Le Champenois",
    "wof:placetype":"venue"
},
  "geometry": {"coordinates":[4.3239941597,50.5965423584],"type":"Point"}
}