{
  "type": "Feature",
  "properties": {
    "iso:country":"BE",
    "sg:address":"Rue De Luxembourg 39",
    "sg:city":"L\u00c9glise",
    "sg:orig_category":"Baby- and kinderkleding Dameskledingzaken Herenkledingzaken",
    "sg:phone":"+32 63 43 30 82",
    "sg:postcode":"6860",
    "sg:province":"Luxembourg",
    "wof:name":"Maison La Grange",
    "wof:placetype":"venue"
},
  "geometry": {"coordinates":[5.5363469124,49.7993621826],"type":"Point"}
}