{
  "type": "Feature",
  "properties": {
    "addr:full":"Chemin De La Masure 70 Mons Hainaut 7000",
    "addr:housenumber":"70",
    "addr:postcode":"7000",
    "addr:street":"Chemin De La Masure;Hainaut",
    "iso:country":"BE",
    "sg:address":"Chemin De La Masure 70",
    "sg:city":"Mons",
    "sg:orig_category":"Cr\u00e9meries",
    "sg:phone":"+32 65 35 22 88",
    "sg:postcode":"7000",
    "sg:province":"Hainaut",
    "wof:name":"Willy Catelle",
    "wof:placetype":"venue"
},
  "geometry": {"coordinates":[3.9676010609,50.4640846252],"type":"Point"}
}