{
  "type": "Feature",
  "properties": {
    "iso:country":"BE",
    "sg:address":"Chauss\u00e9e D'estinnes 79",
    "sg:city":"Binche (waudrez)",
    "sg:classifiers":[
        {
            "category":"Building & Trades",
            "subcategory":"Construction",
            "type":"Services"
        }
    ],
    "sg:phone":"+32 64 33 53 99",
    "sg:postcode":"7131",
    "sg:province":"Hainaut",
    "sg:tags":[
        "stucco",
        "contractor"
    ],
    "wof:name":"Lescart J-l",
    "wof:placetype":"venue"
},
  "geometry": {"coordinates":[4.1371588707,50.4115409851],"type":"Point"}
}