{
  "type": "Feature",
  "properties": {
    "iso:country":"BE",
    "sg:address":"Nijverheidsstraat 44",
    "sg:city":"Westerlo (oevel)",
    "sg:classifiers":[
        {
            "category":"Home & Garden",
            "subcategory":"Household Appliances",
            "type":"Retail Goods"
        }
    ],
    "sg:phone":"+32 14 23 52 96",
    "sg:postcode":"2260",
    "sg:province":"Antwerpen",
    "sg:tags":[
        "repair",
        "mainten",
        "-",
        "electric"
    ],
    "wof:name":"Computer Repair Service",
    "wof:placetype":"venue"
},
  "geometry": {"coordinates":[4.8988881111,51.1435813904],"type":"Point"}
}