{
  "type": "Feature",
  "properties": {
    "addr:full":"Vismarkt 12-14 Mechelen Antwerpen 2800",
    "addr:postcode":"12-14;2800",
    "addr:street":"Vismarkt",
    "iso:country":"BE",
    "sg:address":"Vismarkt 12-14",
    "sg:city":"Mechelen",
    "sg:classifiers":[
        {
            "category":"Farming",
            "subcategory":"Fish & Marine Products",
            "type":"Manufacturing & Wholesale Goods"
        }
    ],
    "sg:phone":"+32 15 20 24 79",
    "sg:postcode":"2800",
    "sg:province":"Antwerpen",
    "sg:tags":[
        "curers",
        "smoker"
    ],
    "wof:name":"Verberckmoes Jef Nv",
    "wof:placetype":"venue"
},
  "geometry": {"coordinates":[4.4767069817,51.0266342163],"type":"Point"}
}