{
  "type": "Feature",
  "properties": {
    "iso:country":"BE",
    "sg:address":"Roodkruisstraat 60",
    "sg:city":"Hamme",
    "sg:classifiers":[
        {
            "category":"Insurance",
            "subcategory":"Insurance Agent",
            "type":"Services"
        }
    ],
    "sg:phone":"+32 52 47 22 09",
    "sg:postcode":"9220",
    "sg:province":"Oost-Vlaanderen",
    "sg:tags":[
        "broker"
    ],
    "wof:name":"Van Gucht G",
    "wof:placetype":"venue"
},
  "geometry": {"coordinates":[4.1401529312,51.1003189087],"type":"Point"}
}