{
  "type": "Feature",
  "properties": {
    "iso:country":"BE",
    "sg:address":"Herkkantstraat 88",
    "sg:city":"Hasselt",
    "sg:orig_category":"Fruitteelt",
    "sg:phone":"+32 11 31 25 79",
    "sg:postcode":"3510",
    "sg:province":"Limburg",
    "wof:name":"Willy Windmolders",
    "wof:placetype":"venue"
},
  "geometry": {"coordinates":[5.22352314,50.9279327393],"type":"Point"}
}