{
  "type": "Feature",
  "properties": {
    "iso:country":"BE",
    "sg:address":"Markt 2",
    "sg:city":"Londerzeel",
    "sg:classifiers":[
        {
            "category":"Restaurant",
            "type":"Food & Drink"
        }
    ],
    "sg:phone":"+32 52 30 93 37",
    "sg:postcode":"1840",
    "sg:province":"Vlaams-Brabant",
    "sg:tags":[
        "caf\u00e9s"
    ],
    "wof:name":"Caf\u00c9 Scoozi",
    "wof:placetype":"venue"
},
  "geometry": {"coordinates":[4.3015117645,51.0013313293],"type":"Point"}
}