{
  "type": "Feature",
  "properties": {
    "addr:full":"Rue Des Ecoles 23 Orp-jauche Brabant Wallon 1350",
    "addr:housenumber":"23",
    "addr:postcode":"1350",
    "addr:street":"Rue Des Ecoles",
    "iso:country":"BE",
    "sg:address":"Rue Des Ecoles 23",
    "sg:city":"Orp-jauche",
    "sg:classifiers":[
        {
            "category":"Arena",
            "subcategory":"Sports Club",
            "type":"Entertainment"
        }
    ],
    "sg:phone":"+32 19 63 52 34",
    "sg:postcode":"1350",
    "sg:province":"Brabant Wallon",
    "sg:tags":[
        "de"
    ],
    "wof:name":"Groupe Sportif Jauchois",
    "wof:placetype":"venue"
},
  "geometry": {"coordinates":[4.97920084,50.6738891602],"type":"Point"}
}