{
  "type": "Feature",
  "properties": {
    "iso:country":"BE",
    "sg:address":"Rue De Bravy 12",
    "sg:city":"Herbeumont",
    "sg:orig_category":"M\u00e9decins and sp\u00e9cialistes",
    "sg:phone":"+32 61 41 14 56",
    "sg:postcode":"6887",
    "sg:province":"Luxembourg",
    "wof:name":"Gustave Renauld",
    "wof:placetype":"venue"
},
  "geometry": {"coordinates":[5.2390432358,49.7786560059],"type":"Point"}
}