{
  "type": "Feature",
  "properties": {
    "iso:country":"BE",
    "sg:address":"August Van Putlei 178",
    "sg:city":"Borsbeek",
    "sg:orig_category":"Brood, gebak and snoepgoed Decoratieve kunst and kunstbenodigdheden Drukkerijen and copyshops",
    "sg:phone":"+32 3 322 67 57",
    "sg:postcode":"2150",
    "sg:province":"Antwerpen",
    "wof:name":"Freddy Cools",
    "wof:placetype":"venue"
},
  "geometry": {"coordinates":[4.4711828232,51.1979866028],"type":"Point"}
}