{
  "type": "Feature",
  "properties": {
    "addr:full":"Rue Philom\u00c8ne 90 Schaarbeek/schaerbeek Bruxelles-Capitale 1030",
    "addr:housenumber":"90",
    "addr:postcode":"1030",
    "addr:street":"Rue Philome\u0300Ne",
    "iso:country":"BE",
    "sg:address":"Rue Philom\u00c8ne 90",
    "sg:city":"Schaarbeek/schaerbeek",
    "sg:orig_category":"Installation \u00e9lectrique r\u00e9sidentielle",
    "sg:phone":"+32 2 245 01 72",
    "sg:postcode":"1030",
    "sg:province":"Bruxelles-Capitale",
    "wof:name":"Dimitrios Michailidis",
    "wof:placetype":"venue"
},
  "geometry": {"coordinates":[4.3734388351,50.8567886353],"type":"Point"}
}