{
  "type": "Feature",
  "properties": {
    "addr:full":"Boskant 133 Lille Antwerpen 2275",
    "addr:housenumber":"133",
    "addr:postcode":"2275",
    "addr:street":"Boskant",
    "iso:country":"BE",
    "sg:address":"Boskant 133",
    "sg:city":"Lille",
    "sg:classifiers":[
        {
            "category":"Arena",
            "subcategory":"Sports Club",
            "type":"Entertainment"
        }
    ],
    "sg:phone":"+32 14 51 24 47",
    "sg:postcode":"2275",
    "sg:province":"Antwerpen",
    "sg:tags":[
        "de"
    ],
    "wof:name":"Mc Lille",
    "wof:placetype":"venue"
},
  "geometry": {"coordinates":[4.8713498116,51.2974205017],"type":"Point"}
}