{
  "type": "Feature",
  "properties": {
    "iso:country":"BE",
    "sg:address":"Rue Mounie 2",
    "sg:city":"Huy",
    "sg:classifiers":[
        {
            "category":"Personal",
            "subcategory":"Beauty Salon",
            "type":"Services"
        }
    ],
    "sg:phone":"+32 85 51 48 58",
    "sg:postcode":"4500",
    "sg:province":"Li\u00e8ge",
    "sg:tags":[
        "lady",
        "-",
        "hairdressing"
    ],
    "wof:name":"Olivier Dachkin Sprl",
    "wof:placetype":"venue"
},
  "geometry": {"coordinates":[5.2404351234,50.5183677673],"type":"Point"}
}