{
  "type": "Feature",
  "properties": {
    "iso:country":"BE",
    "sg:address":"11",
    "sg:city":"Aven Ackers 9130 Beveren-verrebroek",
    "sg:classifiers":[
        {
            "category":"Manufacturing",
            "subcategory":"Printing",
            "type":"Manufacturing & Wholesale Goods"
        }
    ],
    "sg:phone":"+32 3 735 02 62",
    "sg:postcode":"11",
    "sg:tags":[
        "publishing"
    ],
    "wof:name":"Media Express Nv",
    "wof:placetype":"venue"
},
  "geometry": {"coordinates":[4.175344944,51.2897109985],"type":"Point"}
}