{
  "type": "Feature",
  "properties": {
    "addr:full":"Rue De Chassart 10 Fleurus Hainaut 6221",
    "addr:housenumber":"10",
    "addr:postcode":"6221",
    "addr:street":"Rue De Chassart",
    "iso:country":"BE",
    "sg:address":"Rue De Chassart 10",
    "sg:city":"Fleurus",
    "sg:orig_category":"Eleveurs de bovins",
    "sg:phone":"+32 71 85 18 48",
    "sg:postcode":"6221",
    "sg:province":"Hainaut",
    "wof:name":"Wattiaux Jules & Philippe",
    "wof:placetype":"venue"
},
  "geometry": {"coordinates":[4.5451278687,50.5142593384],"type":"Point"}
}