{
  "type": "Feature",
  "properties": {
    "iso:country":"BE",
    "sg:address":"Herenweg 120",
    "sg:city":"Tongeren",
    "sg:classifiers":[
        {
            "category":"Banks & Credit Unions",
            "subcategory":"Investment Brokerage",
            "type":"Services"
        }
    ],
    "sg:phone":"+32 12 39 46 79",
    "sg:postcode":"3700",
    "sg:province":"Limburg",
    "sg:tags":[
        "fence"
    ],
    "wof:name":"Smolders S",
    "wof:placetype":"venue"
},
  "geometry": {"coordinates":[5.4413619041,50.7764320374],"type":"Point"}
}