{
  "type": "Feature",
  "properties": {
    "addr:full":"Posthoornstraat 43 Aalst Oost-Vlaanderen 9300",
    "addr:housenumber":"43",
    "addr:postcode":"9300",
    "addr:street":"Posthoornstraat",
    "iso:country":"BE",
    "sg:address":"Posthoornstraat 43",
    "sg:city":"Aalst",
    "sg:classifiers":[
        {
            "category":"Real Estate",
            "subcategory":"Architect",
            "type":"Services"
        }
    ],
    "sg:phone":"+32 53 77 77 62",
    "sg:postcode":"9300",
    "sg:province":"Oost-Vlaanderen",
    "wof:name":"De Bruyn E",
    "wof:placetype":"venue"
},
  "geometry": {"coordinates":[4.0257730484,50.9362297058],"type":"Point"}
}