{
  "type": "Feature",
  "properties": {
    "addr:full":"Overhemsestraat 55 Heers Limburg 3870",
    "addr:housenumber":"55",
    "addr:postcode":"3870",
    "addr:street":"Overhemsestraat",
    "iso:country":"BE",
    "sg:address":"Overhemsestraat 55",
    "sg:city":"Heers",
    "sg:orig_category":"Eleveurs and marchands de porcs",
    "sg:phone":"+32 11 48 62 50",
    "sg:postcode":"3870",
    "sg:province":"Limburg",
    "wof:name":"Noel Strauven",
    "wof:placetype":"venue"
},
  "geometry": {"coordinates":[5.3332700729,50.7622413635],"type":"Point"}
}