{
  "type": "Feature",
  "properties": {
    "addr:full":"Quai De Rome 1 Li\u00e8ge 1 Li\u00e8ge 4000",
    "addr:housenumber":"1;1",
    "addr:postcode":"4000",
    "addr:street":"Quai De Rome",
    "iso:country":"BE",
    "sg:address":"Quai De Rome 1",
    "sg:city":"Li\u00e8ge 1",
    "sg:classifiers":[
        {
            "category":"Industrial Area",
            "type":"Public Place"
        }
    ],
    "sg:phone":"+32 3 326 22 45",
    "sg:postcode":"4000",
    "sg:province":"Li\u00e8ge",
    "sg:tags":[
        "large",
        "private"
    ],
    "wof:name":"Axias N.v.",
    "wof:placetype":"venue"
},
  "geometry": {"coordinates":[4.4586100578,51.2203941345],"type":"Point"}
}