{
  "type": "Feature",
  "properties": {
    "iso:country":"BE",
    "sg:address":"Maastrichterstraat 1b37",
    "sg:city":"Hasselt",
    "sg:orig_category":"Parfumeries",
    "sg:phone":"+32 11 23 32 40",
    "sg:postcode":"3500",
    "sg:province":"Limburg",
    "wof:name":"Parfums Theo Exclusief",
    "wof:placetype":"venue"
},
  "geometry": {"coordinates":[5.3379402161,50.9291534424],"type":"Point"}
}