{
  "type": "Feature",
  "properties": {
    "iso:country":"BE",
    "sg:address":"Beverlaai 59",
    "sg:city":"Kortrijk",
    "sg:orig_category":"Artsen and specialisten",
    "sg:phone":"+32 56 21 49 68",
    "sg:postcode":"8500",
    "sg:province":"West-Vlaanderen",
    "wof:name":"J. De Groeve",
    "wof:placetype":"venue"
},
  "geometry": {"coordinates":[3.2628469467,50.8203964233],"type":"Point"}
}