{
  "type": "Feature",
  "properties": {
    "iso:country":"BE",
    "sg:address":"Renerkesstraat 20",
    "sg:city":"Genk",
    "sg:classifiers":[
        {
            "category":"Professional",
            "subcategory":"Secretarial Services",
            "type":"Services"
        }
    ],
    "sg:phone":"+32 800 93 096",
    "sg:postcode":"3600",
    "sg:province":"Limburg",
    "sg:tags":[
        "firm"
    ],
    "wof:name":"Offitel\u00ae Nv",
    "wof:placetype":"venue"
},
  "geometry": {"coordinates":[5.5180602074,50.9346351624],"type":"Point"}
}