{
  "type": "Feature",
  "properties": {
    "iso:country":"BE",
    "sg:address":"Rue Des Pr\u00c9s 3",
    "sg:city":"Mont-saint-guibert",
    "sg:orig_category":"Woningbouw",
    "sg:phone":"+32 10 65 02 24",
    "sg:postcode":"1435",
    "sg:province":"Brabant Wallon",
    "wof:name":"Euro-construct",
    "wof:placetype":"venue"
},
  "geometry": {"coordinates":[4.6565651894,50.646987915],"type":"Point"}
}