{
  "type": "Feature",
  "properties": {
    "addr:full":"Rue Voie Des Vaux 57 Saint-nicolas Li\u00e8ge 4420",
    "addr:housenumber":"57",
    "addr:postcode":"4420",
    "addr:street":"Rue Voie Des Vaux",
    "iso:country":"BE",
    "sg:address":"Rue Voie Des Vaux 57",
    "sg:city":"Saint-nicolas",
    "sg:orig_category":"Boissons",
    "sg:phone":"+32 4 247 03 60",
    "sg:postcode":"4420",
    "sg:province":"Li\u00e8ge",
    "wof:name":"Somycee Diffusion",
    "wof:placetype":"venue"
},
  "geometry": {"coordinates":[5.5142798424,50.6371879578],"type":"Point"}
}