{
  "type": "Feature",
  "properties": {
    "addr:full":"Rue De Joie 189 Li\u00c8ge Li\u00e8ge 4000",
    "addr:housenumber":"189",
    "addr:postcode":"4000",
    "addr:street":"Rue De Joie",
    "iso:country":"BE",
    "sg:address":"Rue De Joie 189",
    "sg:city":"Li\u00c8ge",
    "sg:orig_category":"Traitements param\u00e9dicaux",
    "sg:phone":"+32 4 253 57 92",
    "sg:postcode":"4000",
    "sg:province":"Li\u00e8ge",
    "wof:name":"C. Wittezaele",
    "wof:placetype":"venue"
},
  "geometry": {"coordinates":[5.5543651581,50.6249923706],"type":"Point"}
}