{
  "type": "Feature",
  "properties": {
    "iso:country":"BE",
    "sg:address":"Rue Montagne Du Stimont 2",
    "sg:city":"Ottignies-louvain-la-neuve",
    "sg:orig_category":"Bloemen and planten",
    "sg:phone":"+32 10 41 44 91",
    "sg:postcode":"1340",
    "sg:province":"Brabant Wallon",
    "wof:name":"Maison Art Floral",
    "wof:placetype":"venue"
},
  "geometry": {"coordinates":[4.5717420578,50.6670227051],"type":"Point"}
}