{
  "type": "Feature",
  "properties": {
    "addr:full":"Bonderstraat 12 Genk Limburg 3600",
    "addr:housenumber":"12",
    "addr:postcode":"3600",
    "addr:street":"Bonderstraat",
    "iso:country":"BE",
    "sg:address":"Bonderstraat 12",
    "sg:city":"Genk",
    "sg:orig_category":"Artsen and specialisten",
    "sg:phone":"+32 89 35 06 95",
    "sg:postcode":"3600",
    "sg:province":"Limburg",
    "wof:name":"Michel Hilkens",
    "wof:placetype":"venue"
},
  "geometry": {"coordinates":[5.5294032097,50.976600647],"type":"Point"}
}