{
  "type": "Feature",
  "properties": {
    "addr:full":"Av.jean Fran\u00c7ois Leemans 87 Oudergem/auderghem Bruxelles-Capitale 1160",
    "addr:housenumber":"87",
    "addr:postcode":"1160",
    "addr:street":"Leemans;/",
    "iso:country":"BE",
    "sg:address":"Av.jean Fran\u00c7ois Leemans 87",
    "sg:city":"Oudergem/auderghem",
    "sg:classifiers":[
        {
            "category":"Shopping",
            "subcategory":"Bicycles & Sporting Goods",
            "type":"Retail Goods"
        }
    ],
    "sg:phone":"+32 2 672 79 99",
    "sg:postcode":"1160",
    "sg:province":"Bruxelles-Capitale",
    "sg:tags":[
        "article",
        "de",
        "sport",
        "camping"
    ],
    "wof:name":"Claude Walach Repair Shop",
    "wof:placetype":"venue"
},
  "geometry": {"coordinates":[4.4391860962,50.8040657043],"type":"Point"}
}