{
  "type": "Feature",
  "properties": {
    "iso:country":"BE",
    "sg:address":"Legerstraat 5",
    "sg:city":"Poperinge",
    "sg:orig_category":"Rundveehouders Varkenskwekers",
    "sg:phone":"+32 57 30 02 15",
    "sg:postcode":"8972",
    "sg:province":"West-Vlaanderen",
    "wof:name":"Joel Boury",
    "wof:placetype":"venue"
},
  "geometry": {"coordinates":[2.6801989079,50.8985862732],"type":"Point"}
}