{
  "type": "Feature",
  "properties": {
    "iso:country":"BE",
    "sg:address":"Jan Frans Gellyncklaan 93",
    "sg:city":"Hove",
    "sg:orig_category":"Installatie van houten of kunststof schrijnwerk Installatie van metalen schrijnwerk",
    "sg:phone":"+32 3 455 31 62",
    "sg:postcode":"2540",
    "sg:province":"Antwerpen",
    "wof:name":"Clement F",
    "wof:placetype":"venue"
},
  "geometry": {"coordinates":[4.4656171799,51.1492271423],"type":"Point"}
}