{
  "type": "Feature",
  "properties": {
    "iso:country":"BE",
    "sg:address":"A L'eau 6",
    "sg:city":"Durbuy",
    "sg:orig_category":"Sportclubs",
    "sg:phone":"+32 86 36 64 63",
    "sg:postcode":"6941",
    "sg:province":"Luxembourg",
    "wof:name":"La Traction Universelle",
    "wof:placetype":"venue"
},
  "geometry": {"coordinates":[5.4467158318,50.4103279114],"type":"Point"}
}