{
  "type": "Feature",
  "properties": {
    "addr:full":"Markt 33 Lede Oost-Vlaanderen 9340",
    "addr:housenumber":"33",
    "addr:postcode":"9340",
    "addr:street":"Markt",
    "iso:country":"BE",
    "sg:address":"Markt 33",
    "sg:city":"Lede",
    "sg:orig_category":"Boekhandels Krantenwinkels Rookartikelen",
    "sg:phone":"+32 53 80 64 76",
    "sg:postcode":"9340",
    "sg:province":"Oost-Vlaanderen",
    "wof:name":"Boekhandel Conscience",
    "wof:placetype":"venue"
},
  "geometry": {"coordinates":[3.9778740406,50.9665527344],"type":"Point"}
}