{
  "type": "Feature",
  "properties": {
    "addr:full":"Nieuwstraat 4 Beernem West-Vlaanderen 8730",
    "addr:housenumber":"4",
    "addr:postcode":"8730",
    "addr:street":"Nieuwstraat",
    "iso:country":"BE",
    "sg:address":"Nieuwstraat 4",
    "sg:city":"Beernem",
    "sg:orig_category":"Articles de jardin. P\u00e9pini\u00e9ristes",
    "sg:phone":"+32 50 78 99 98",
    "sg:postcode":"8730",
    "sg:province":"West-Vlaanderen",
    "wof:name":"M. Van Hauwaert",
    "wof:placetype":"venue"
},
  "geometry": {"coordinates":[3.3635220528,51.1849937439],"type":"Point"}
}