{
  "type": "Feature",
  "properties": {
    "iso:country":"BE",
    "sg:address":"Route De Hannut 91",
    "sg:city":"Namur (bouge)",
    "sg:classifiers":[
        {
            "category":"Health Services",
            "subcategory":"Doctor",
            "type":"Services"
        }
    ],
    "sg:phone":"+32 81 20 16 16",
    "sg:postcode":"5004",
    "sg:province":"Namur",
    "sg:tags":[
        "medicinephysicians",
        "surgeon"
    ],
    "wof:name":"El Khoury Elie",
    "wof:placetype":"venue"
},
  "geometry": {"coordinates":[4.904364109,50.4741134644],"type":"Point"}
}