{
  "type": "Feature",
  "properties": {
    "addr:full":"Rue De La Vall\u00e9e 53 Ham-sur-sambre Namur 5190",
    "addr:housenumber":"53",
    "addr:postcode":"5190",
    "addr:street":"Rue De La Valle\u0301E;Namur",
    "iso:country":"BE",
    "sg:address":"Rue De La Vall\u00e9e 53",
    "sg:city":"Ham-sur-sambre",
    "sg:classifiers":[
        {
            "category":"Manufacturing",
            "subcategory":"Metals",
            "type":"Manufacturing & Wholesale Goods"
        }
    ],
    "sg:phone":"+32 71 78 45 00",
    "sg:postcode":"5190",
    "sg:province":"Namur",
    "sg:tags":[
        "metallurgy",
        "metalworking",
        "processing"
    ],
    "wof:name":"Exploitation Durjau Sa",
    "wof:placetype":"venue"
},
  "geometry": {"coordinates":[4.6763300896,50.439201355],"type":"Point"}
}