{
  "type": "Feature",
  "properties": {
    "addr:full":"Prins Karellaan 1 Brugge West-Vlaanderen 8310",
    "addr:housenumber":"1",
    "addr:postcode":"8310",
    "addr:street":"Prins Karellaan",
    "iso:country":"BE",
    "sg:address":"Prins Karellaan 1",
    "sg:city":"Brugge",
    "sg:orig_category":"Blanchisseries and teintureries",
    "sg:phone":"+32 50 35 31 62",
    "sg:postcode":"8310",
    "sg:province":"West-Vlaanderen",
    "wof:name":"Droogkuis Aneca-st.andr\u00c9",
    "wof:placetype":"venue"
},
  "geometry": {"coordinates":[3.2492859364,51.1995849609],"type":"Point"}
}