{
  "type": "Feature",
  "properties": {
    "iso:country":"BE",
    "sg:address":"Hof Ten Bergestraat 51",
    "sg:city":"Aalst",
    "sg:classifiers":[
        {
            "category":"Professional",
            "subcategory":"Lawyer & Legal Services",
            "type":"Services"
        }
    ],
    "sg:phone":"+32 53 21 41 15",
    "sg:postcode":"9300",
    "sg:province":"Oost-Vlaanderen",
    "wof:name":"Van Geert N",
    "wof:placetype":"venue"
},
  "geometry": {"coordinates":[4.0672512054,50.9366531372],"type":"Point"}
}