{
  "type": "Feature",
  "properties": {
    "iso:country":"BE",
    "sg:address":"Onderwijslaan 4ba",
    "sg:city":"Diepenbeek",
    "sg:orig_category":"Centres de relaxation and bien-\u00eatre. Instituts de beaut\u00e9",
    "sg:phone":"+32 11 33 22 58",
    "sg:postcode":"3590",
    "sg:province":"Limburg",
    "wof:name":"Patricia Bien",
    "wof:placetype":"venue"
},
  "geometry": {"coordinates":[5.4502739906,50.9220809937],"type":"Point"}
}