{
  "type": "Feature",
  "properties": {
    "iso:country":"BE",
    "sg:address":"Theo Verbeecklaan 1",
    "sg:city":"Anderlecht (brussel)",
    "sg:classifiers":[
        {
            "category":"Cafe",
            "type":"Food & Drink"
        }
    ],
    "sg:phone":"+32 2 522 23 89",
    "sg:postcode":"1070",
    "sg:province":"Bruxelles-Capitale",
    "sg:tags":[
        "caf\u00e9s"
    ],
    "wof:name":"La Taverne Du Stade",
    "wof:placetype":"venue"
},
  "geometry": {"coordinates":[4.2986540794,50.8353767395],"type":"Point"}
}