{
  "type": "Feature",
  "properties": {
    "iso:country":"BE",
    "sg:address":"Rue Du Sart 1",
    "sg:city":"Jodoigne (m\u00e9lin)",
    "sg:classifiers":[
        {
            "category":"Social Services",
            "subcategory":"Child Care",
            "type":"Services"
        }
    ],
    "sg:phone":"+32 10 81 27 87",
    "sg:postcode":"1370",
    "sg:province":"Brabant Wallon",
    "sg:tags":[
        "baby",
        "nursery",
        "day",
        "sitting"
    ],
    "wof:name":"P'tits Diables (les)",
    "wof:placetype":"venue"
},
  "geometry": {"coordinates":[4.805475235,50.7421760559],"type":"Point"}
}