{
  "type": "Feature",
  "properties": {
    "addr:full":"Industrieweg 11 Antwerpen Antwerpen 2030",
    "addr:housenumber":"11",
    "addr:postcode":"2030",
    "addr:street":"Industrieweg",
    "iso:country":"BE",
    "sg:address":"Industrieweg 11",
    "sg:city":"Antwerpen",
    "sg:orig_category":"Huisvuilophaling and -verwerking",
    "sg:phone":"+32 3 540 12 12",
    "sg:postcode":"2030",
    "sg:province":"Antwerpen",
    "wof:name":"B.o.s.",
    "wof:placetype":"venue"
},
  "geometry": {"coordinates":[4.3478717804,51.253490448],"type":"Point"}
}