{
  "type": "Feature",
  "properties": {
    "addr:full":"Georges Gilliotstraat 1 Hemiksem Antwerpen 2620",
    "addr:housenumber":"1",
    "addr:postcode":"2620",
    "addr:street":"Georges Gilliotstraat",
    "iso:country":"BE",
    "sg:address":"Georges Gilliotstraat 1",
    "sg:city":"Hemiksem",
    "sg:classifiers":[
        {
            "category":"Home & Garden",
            "subcategory":"Building Materials",
            "type":"Retail Goods"
        }
    ],
    "sg:phone":"+32 3 887 23 11",
    "sg:postcode":"2620",
    "sg:province":"Antwerpen",
    "sg:tags":[
        "window"
    ],
    "wof:name":"De Cock F",
    "wof:placetype":"venue"
},
  "geometry": {"coordinates":[4.3387260437,51.1332969666],"type":"Point"}
}