{
  "type": "Feature",
  "properties": {
    "iso:country":"BE",
    "sg:address":"Rue Saint-gilles 386",
    "sg:city":"Li\u00e8ge 1",
    "sg:classifiers":[
        {
            "category":"Recreation",
            "subcategory":"Gun Range",
            "type":"Entertainment"
        }
    ],
    "sg:phone":"+32 4 252 02 11",
    "sg:postcode":"4000",
    "sg:province":"Li\u00e8ge",
    "sg:tags":[
        "ammunition",
        "-",
        "retail"
    ],
    "wof:name":"Lebeau Courally-verrees Sa",
    "wof:placetype":"venue"
},
  "geometry": {"coordinates":[5.5555319786,50.6351699829],"type":"Point"}
}