{
  "type": "Feature",
  "properties": {
    "addr:full":"Place Colignon 55 Schaarbeek/schaerbeek Bruxelles-Capitale 1030",
    "addr:housenumber":"55",
    "addr:postcode":"1030",
    "addr:street":"Place Colignon",
    "iso:country":"BE",
    "sg:address":"Place Colignon 55",
    "sg:city":"Schaarbeek/schaerbeek",
    "sg:orig_category":"Cr\u00e9dit \u00e0 la consommation",
    "sg:phone":"+32 2 242 30 32",
    "sg:postcode":"1030",
    "sg:province":"Bruxelles-Capitale",
    "wof:name":"Bureau Van Droogenbroeck",
    "wof:placetype":"venue"
},
  "geometry": {"coordinates":[4.3738517761,50.8681983948],"type":"Point"}
}