{
  "type": "Feature",
  "properties": {
    "addr:full":"Rue Du Roi Albert 181 Oupeye Li\u00e8ge 4680",
    "addr:housenumber":"181",
    "addr:postcode":"4680",
    "addr:street":"Rue Du Roi Albert",
    "iso:country":"BE",
    "sg:address":"Rue Du Roi Albert 181",
    "sg:city":"Oupeye",
    "sg:orig_category":"Bloemen and planten",
    "sg:phone":"+32 4 240 40 50",
    "sg:postcode":"4680",
    "sg:province":"Li\u00e8ge",
    "wof:name":"Floral D\u00c9cor",
    "wof:placetype":"venue"
},
  "geometry": {"coordinates":[5.6463088989,50.708278656],"type":"Point"}
}