{
  "type": "Feature",
  "properties": {
    "addr:full":"Rue Sous-le-ch\u00e2teau 25 Huy Li\u00e8ge 4500",
    "addr:housenumber":"25",
    "addr:postcode":"4500",
    "addr:street":"Rue Sous-Le-Cha\u0302Teau",
    "iso:country":"BE",
    "sg:address":"Rue Sous-le-ch\u00e2teau 25",
    "sg:city":"Huy",
    "sg:classifiers":[
        {
            "category":"Personal",
            "subcategory":"Shoe Repair & Shine",
            "type":"Services"
        }
    ],
    "sg:phone":"+32 85 21 68 45",
    "sg:postcode":"4500",
    "sg:province":"Li\u00e8ge",
    "sg:tags":[
        "shoemaker"
    ],
    "wof:name":"Van Meigem R",
    "wof:placetype":"venue"
},
  "geometry": {"coordinates":[5.2393507957,50.5177154541],"type":"Point"}
}