{
  "type": "Feature",
  "properties": {
    "iso:country":"BE",
    "sg:address":"Avenue Jacques Pastur 7",
    "sg:city":"Bruxelles (uccle)",
    "sg:classifiers":[
        {
            "category":"Insurance",
            "subcategory":"Insurance Agent",
            "type":"Services"
        }
    ],
    "sg:phone":"+32 2 375 91 31",
    "sg:postcode":"1180",
    "sg:province":"Bruxelles-Capitale",
    "sg:tags":[
        "broker"
    ],
    "wof:name":"Stievenart J-p",
    "wof:placetype":"venue"
},
  "geometry": {"coordinates":[4.3743782043,50.7883720398],"type":"Point"}
}