{
  "type": "Feature",
  "properties": {
    "iso:country":"BE",
    "sg:address":"27",
    "sg:city":"Rue Charles-magnette 4000 Li\u00e8ge",
    "sg:orig_category":"Miscellaneous Products",
    "sg:phone":"+32 4 223 62 18",
    "sg:postcode":"27",
    "wof:name":"Maison Moreau Freres Sa",
    "wof:placetype":"venue"
},
  "geometry": {"coordinates":[5.5726499557,50.6407051086],"type":"Point"}
}