{
  "type": "Feature",
  "properties": {
    "iso:country":"BE",
    "sg:address":"Avenue Albert Ier 30",
    "sg:city":"Rixensart",
    "sg:orig_category":"Decoratieve kunst and kunstbenodigdheden",
    "sg:phone":"+32 2 653 20 98",
    "sg:postcode":"1332",
    "sg:province":"Brabant Wallon",
    "wof:name":"Fe. L'astula",
    "wof:placetype":"venue"
},
  "geometry": {"coordinates":[4.4974551201,50.7170753479],"type":"Point"}
}