{
  "type": "Feature",
  "properties": {
    "addr:full":"Kastanjewal 58 Tongeren Limburg 3700",
    "addr:housenumber":"58",
    "addr:postcode":"3700",
    "addr:street":"Kastanjewal",
    "iso:country":"BE",
    "sg:address":"Kastanjewal 58",
    "sg:city":"Tongeren",
    "sg:classifiers":[
        {
            "category":"Health Services",
            "subcategory":"Nursing And Care Facility",
            "type":"Services"
        }
    ],
    "sg:phone":"+32 12 23 80 09",
    "sg:postcode":"3700",
    "sg:province":"Limburg",
    "sg:tags":[
        "home"
    ],
    "wof:name":"Kraamcentrum Amerytje",
    "wof:placetype":"venue"
},
  "geometry": {"coordinates":[5.4649291039,50.7766189575],"type":"Point"}
}