{
  "type": "Feature",
  "properties": {
    "iso:country":"BE",
    "sg:address":"Inakker 32",
    "sg:city":"Heusden-zolder",
    "sg:orig_category":"Herstellingen and onderhoud aan huis voor voertuigen Metaalafval, schrootrecyclage and sloperijen",
    "sg:phone":"+32 11 53 62 27",
    "sg:postcode":"3550",
    "sg:province":"Limburg",
    "wof:name":"Francois Berden",
    "wof:placetype":"venue"
},
  "geometry": {"coordinates":[5.3120031357,51.0211601257],"type":"Point"}
}