{
  "type": "Feature",
  "properties": {
    "addr:full":"Hauzeur 3 Herve Li\u00e8ge 4650",
    "addr:housenumber":"3",
    "addr:postcode":"4650",
    "addr:street":"Hauzeur",
    "iso:country":"BE",
    "sg:address":"Hauzeur 3",
    "sg:city":"Herve",
    "sg:orig_category":"Loodgieterij, verwarming and sanitaire installaties",
    "sg:phone":"+32 87 66 01 54",
    "sg:postcode":"4650",
    "sg:province":"Li\u00e8ge",
    "wof:name":"Jean-marie Straeten",
    "wof:placetype":"venue"
},
  "geometry": {"coordinates":[5.8412737846,50.6369514465],"type":"Point"}
}