{
  "type": "Feature",
  "properties": {
    "addr:full":"Place De Rome 12 Malmedy Li\u00e8ge 4960",
    "addr:housenumber":"12",
    "addr:postcode":"4960",
    "addr:street":"Place De Rome",
    "iso:country":"BE",
    "sg:address":"Place De Rome 12",
    "sg:city":"Malmedy",
    "sg:classifiers":[
        {
            "category":"Professional",
            "subcategory":"Computer Services",
            "type":"Services"
        }
    ],
    "sg:phone":"+32 80 44 81 25",
    "sg:postcode":"4960",
    "sg:province":"Li\u00e8ge",
    "sg:tags":[
        "webdesign",
        "-",
        "internet"
    ],
    "wof:name":"Noweb.be",
    "wof:placetype":"venue"
},
  "geometry": {"coordinates":[6.0250191689,50.4262924194],"type":"Point"}
}