{
  "type": "Feature",
  "properties": {
    "iso:country":"BE",
    "sg:address":"Rue De La R\u00e9gence 45",
    "sg:city":"Charleroi",
    "sg:classifiers":[
        {
            "category":"Building & Trades",
            "subcategory":"Construction",
            "type":"Services"
        }
    ],
    "sg:phone":"+32 71 30 25 35",
    "sg:postcode":"6000",
    "sg:province":"Hainaut",
    "sg:tags":[
        "truss-makers"
    ],
    "wof:name":"Line-ortho",
    "wof:placetype":"venue"
},
  "geometry": {"coordinates":[4.446554184,50.4133453369],"type":"Point"}
}