{
  "type": "Feature",
  "properties": {
    "addr:full":"Brusselsestraat 44-46 Leuven Vlaams-Brabant 3000",
    "addr:postcode":"44-46;3000",
    "addr:street":"Brusselsestraat",
    "iso:country":"BE",
    "sg:address":"Brusselsestraat 44-46",
    "sg:city":"Leuven",
    "sg:classifiers":[
        {
            "category":"Shopping",
            "subcategory":"Crafts & Fabrics",
            "type":"Retail Goods"
        }
    ],
    "sg:phone":"+32 16 22 48 67",
    "sg:postcode":"3000",
    "sg:province":"Vlaams-Brabant",
    "sg:tags":[
        "graphic",
        "art",
        "supply",
        "-",
        "painting",
        "drawing"
    ],
    "wof:name":"Reekmans A.h. Bvba",
    "wof:placetype":"venue"
},
  "geometry": {"coordinates":[4.6980619431,50.8799629211],"type":"Point"}
}