{
  "type": "Feature",
  "properties": {
    "iso:country":"BE",
    "sg:address":"Rue De Lorraine 95",
    "sg:city":"Musson",
    "sg:orig_category":"Epiceries",
    "sg:phone":"+32 63 57 13 60",
    "sg:postcode":"6750",
    "sg:province":"Luxembourg",
    "wof:name":"Lydie Sibille",
    "wof:placetype":"venue"
},
  "geometry": {"coordinates":[5.6543998718,49.5545463562],"type":"Point"}
}