{
  "type": "Feature",
  "properties": {
    "iso:country":"BE",
    "sg:address":"Frankrijkstraat 9",
    "sg:city":"Berlare",
    "sg:classifiers":[
        {
            "category":"Building & Trades",
            "subcategory":"Landscaping Services",
            "type":"Services"
        }
    ],
    "sg:phone":"+32 52 42 32 48",
    "sg:postcode":"9290",
    "sg:province":"Oost-Vlaanderen",
    "sg:tags":[
        "nurseryman"
    ],
    "wof:name":"De Gend P",
    "wof:placetype":"venue"
},
  "geometry": {"coordinates":[4.005428791,51.0214347839],"type":"Point"}
}