{
  "type": "Feature",
  "properties": {
    "addr:full":"Lostraat 5 Alveringem (leisele) West-Vlaanderen 8691",
    "addr:housenumber":"5",
    "addr:postcode":"8691",
    "addr:street":"Lostraat",
    "iso:country":"BE",
    "sg:address":"Lostraat 5",
    "sg:city":"Alveringem (leisele)",
    "sg:classifiers":[
        {
            "category":"Bars & Pubs",
            "type":"Food & Drink"
        }
    ],
    "sg:phone":"+32 58 29 90 71",
    "sg:postcode":"8691",
    "sg:province":"West-Vlaanderen",
    "wof:name":"Caf\u00e9 De La Douane",
    "wof:placetype":"venue"
},
  "geometry": {"coordinates":[2.6665480137,50.970489502],"type":"Point"}
}