{
  "type": "Feature",
  "properties": {
    "addr:full":"Rue De Birmingham 44 Bruxelles Bruxelles-Capitale 1080",
    "addr:housenumber":"44",
    "addr:postcode":"1080",
    "addr:street":"Rue De Birmingham",
    "iso:country":"BE",
    "sg:address":"Rue De Birmingham 44",
    "sg:city":"Bruxelles",
    "sg:classifiers":[
        {
            "category":"Retail",
            "subcategory":"Storage",
            "type":"Services"
        }
    ],
    "sg:phone":"+32 2 242 43 23",
    "sg:postcode":"1080",
    "sg:province":"Bruxelles-Capitale",
    "sg:tags":[
        "box",
        "cardboard",
        "fine"
    ],
    "wof:name":"Almar S.p.r.l.",
    "wof:placetype":"venue"
},
  "geometry": {"coordinates":[4.3265800476,50.8476295471],"type":"Point"}
}