{
  "type": "Feature",
  "properties": {
    "iso:country":"BE",
    "sg:address":"Rue De Berneau 23",
    "sg:city":"Vise",
    "sg:orig_category":"Studios photographiques",
    "sg:phone":"+32 4 379 37 22",
    "sg:postcode":"4600",
    "sg:province":"Li\u00e8ge",
    "wof:name":"Fernand Hick",
    "wof:placetype":"venue"
},
  "geometry": {"coordinates":[5.7046031952,50.7370567322],"type":"Point"}
}