{
  "type": "Feature",
  "properties": {
    "iso:country":"BE",
    "sg:address":"Rue Pauline Hubert 1",
    "sg:city":"Sivry-rance",
    "sg:orig_category":"Pain, p\u00e2tisseries and confiseries",
    "sg:phone":"+32 60 41 29 63",
    "sg:postcode":"6470",
    "sg:province":"Hainaut",
    "wof:name":"Boulangerie Douchamps",
    "wof:placetype":"venue"
},
  "geometry": {"coordinates":[4.2778301239,50.1422080994],"type":"Point"}
}