{
  "type": "Feature",
  "properties": {
    "addr:full":"Kluizenhof 25 Sint-gillis-waas Oost-Vlaanderen 9170",
    "addr:housenumber":"25",
    "addr:postcode":"9170",
    "addr:street":"Kluizenhof",
    "iso:country":"BE",
    "sg:address":"Kluizenhof 25",
    "sg:city":"Sint-gillis-waas",
    "sg:orig_category":"Locations de machines and \u00e9quipement pour la construction. Equipements pour la construction Location",
    "sg:phone":"+32 3 727 11 27",
    "sg:postcode":"9170",
    "sg:province":"Oost-Vlaanderen",
    "wof:name":"Real Verhuur - Location",
    "wof:placetype":"venue"
},
  "geometry": {"coordinates":[4.0920529366,51.2290458679],"type":"Point"}
}