{
  "type": "Feature",
  "properties": {
    "iso:country":"BE",
    "sg:address":"Sterstraat 4",
    "sg:city":"Temse",
    "sg:orig_category":"Slagers",
    "sg:phone":"+32 3 774 14 15",
    "sg:postcode":"9140",
    "sg:province":"Oost-Vlaanderen",
    "wof:name":"G. Van Rossen",
    "wof:placetype":"venue"
},
  "geometry": {"coordinates":[4.2685828209,51.1298332214],"type":"Point"}
}