{
  "type": "Feature",
  "properties": {
    "iso:country":"BE",
    "sg:address":"Rue Du Ch\u00e2teau 51",
    "sg:city":"Tubize (clabecq)",
    "sg:classifiers":[
        {
            "category":"Professional",
            "subcategory":"Testing Lab",
            "type":"Services"
        }
    ],
    "sg:phone":"+32 2 355 75 41",
    "sg:postcode":"1480",
    "sg:province":"Brabant Wallon",
    "sg:tags":[
        "chemist"
    ],
    "wof:name":"De Ruydts E",
    "wof:placetype":"venue"
},
  "geometry": {"coordinates":[4.2233400345,50.6867675781],"type":"Point"}
}