{
  "type": "Feature",
  "properties": {
    "iso:country":"BE",
    "sg:address":"Kerkhofstraat 15",
    "sg:city":"Zomergem",
    "sg:classifiers":[
        {
            "category":"Health Services",
            "subcategory":"Dentist",
            "type":"Services"
        }
    ],
    "sg:phone":"+32 9 372 61 71",
    "sg:postcode":"9930",
    "sg:province":"Oost-Vlaanderen",
    "wof:name":"Moentjens W",
    "wof:placetype":"venue"
},
  "geometry": {"coordinates":[3.5650808811,51.1188964844],"type":"Point"}
}