{
  "type": "Feature",
  "properties": {
    "iso:country":"BE",
    "sg:address":"Groene Biezenlaan 57",
    "sg:city":"De Panne",
    "sg:classifiers":[
        {
            "category":"Arena",
            "subcategory":"Sports Club",
            "type":"Entertainment"
        }
    ],
    "sg:phone":"+32 58 41 15 45",
    "sg:postcode":"8660",
    "sg:province":"West-Vlaanderen",
    "sg:tags":[
        "federation"
    ],
    "wof:name":"Belgische Federatie Der Land Yacht Clubs",
    "wof:placetype":"venue"
},
  "geometry": {"coordinates":[2.5712339878,51.093711853],"type":"Point"}
}