{
  "type": "Feature",
  "properties": {
    "addr:full":"Rue Grand Vin\u00e2ve 55 Seraing (jemeppe-sur-meuse) Li\u00e8ge 4101",
    "addr:housenumber":"55",
    "addr:postcode":"4101",
    "addr:street":"Rue Grand Vina\u0302Ve;Jemeppe-Sur-Meuse",
    "iso:country":"BE",
    "sg:address":"Rue Grand Vin\u00e2ve 55",
    "sg:city":"Seraing (jemeppe-sur-meuse)",
    "sg:classifiers":[
        {
            "category":"Personal",
            "subcategory":"Beauty Salon",
            "type":"Services"
        }
    ],
    "sg:phone":"+32 4 234 39 30",
    "sg:postcode":"4101",
    "sg:province":"Li\u00e8ge",
    "wof:name":"Stapelle Esth\u00e9tique",
    "wof:placetype":"venue"
},
  "geometry": {"coordinates":[5.5061497688,50.6168479919],"type":"Point"}
}