{
  "type": "Feature",
  "properties": {
    "addr:full":"Heieweg 20 De Haan West-Vlaanderen 8420",
    "addr:housenumber":"20",
    "addr:postcode":"8420",
    "addr:street":"Heieweg",
    "iso:country":"BE",
    "sg:address":"Heieweg 20",
    "sg:city":"De Haan",
    "sg:orig_category":"Rev\u00eatements pour sols and murs. Construction de maisons",
    "sg:phone":"+32 59 23 34 33",
    "sg:postcode":"8420",
    "sg:province":"West-Vlaanderen",
    "wof:name":"De Nolf-demarest",
    "wof:placetype":"venue"
},
  "geometry": {"coordinates":[2.998593092,51.2501335144],"type":"Point"}
}