{
  "type": "Feature",
  "properties": {
    "addr:full":"Antwerpsestraat 2 Rumst Antwerpen 2840",
    "addr:housenumber":"2",
    "addr:postcode":"2840",
    "addr:street":"Antwerpsestraat",
    "iso:country":"BE",
    "sg:address":"Antwerpsestraat 2",
    "sg:city":"Rumst",
    "sg:orig_category":"Benzinestations and brandstoffen",
    "sg:phone":"+32 3 888 22 28",
    "sg:postcode":"2840",
    "sg:province":"Antwerpen",
    "wof:name":"Esso",
    "wof:placetype":"venue"
},
  "geometry": {"coordinates":[4.4522819519,51.0859146118],"type":"Point"}
}