{
  "type": "Feature",
  "properties": {
    "addr:full":"Place Abbe Joseph Andr\u00c9 11 Namur Namur 5000",
    "addr:housenumber":"11",
    "addr:postcode":"5000",
    "addr:street":"Place Abbe Joseph Andre\u0301",
    "iso:country":"BE",
    "sg:address":"Place Abbe Joseph Andr\u00c9 11",
    "sg:city":"Namur",
    "sg:classifiers":[
        {
            "category":"Fast Food",
            "type":"Food & Drink"
        }
    ],
    "sg:phone":"+32 81 73 83 37",
    "sg:postcode":"5000",
    "sg:province":"Namur",
    "sg:tags":[
        "\u00c0",
        "restaurants",
        "emporter",
        "restaurant"
    ],
    "wof:name":"Restaurant La Pagode",
    "wof:placetype":"venue"
},
  "geometry": {"coordinates":[4.8579730988,50.4649772644],"type":"Point"}
}