{
  "type": "Feature",
  "properties": {
    "iso:country":"BE",
    "sg:address":"Veltemweg 35",
    "sg:city":"Brugge",
    "sg:classifiers":[
        {
            "category":"Cafe",
            "type":"Food & Drink"
        }
    ],
    "sg:phone":"+32 50 36 46 96",
    "sg:postcode":"8310",
    "sg:province":"West-Vlaanderen",
    "sg:tags":[
        "caf\u00e9s"
    ],
    "wof:name":"Madeleine Blommaert",
    "wof:placetype":"venue"
},
  "geometry": {"coordinates":[3.2564809322,51.2083206177],"type":"Point"}
}