{
  "type": "Feature",
  "properties": {
    "addr:full":"Pallekensbergstraat 35 Hasselt (kuringen) Limburg 3511",
    "addr:housenumber":"35",
    "addr:postcode":"3511",
    "addr:street":"Pallekensbergstraat",
    "iso:country":"BE",
    "sg:address":"Pallekensbergstraat 35",
    "sg:city":"Hasselt (kuringen)",
    "sg:classifiers":[
        {
            "category":"Insurance",
            "subcategory":"Insurance Agent",
            "type":"Services"
        }
    ],
    "sg:phone":"+32 11 26 17 19",
    "sg:postcode":"3511",
    "sg:province":"Limburg",
    "sg:tags":[
        "broker"
    ],
    "wof:name":"Stulens F",
    "wof:placetype":"venue"
},
  "geometry": {"coordinates":[5.3034238815,50.9432487488],"type":"Point"}
}