{
  "type": "Feature",
  "properties": {
    "iso:country":"BE",
    "sg:address":"Stasegemsesteenweg 82",
    "sg:city":"Kortrijk",
    "sg:orig_category":"Diverse bouwinstallaties",
    "sg:phone":"+32 56 22 33 96",
    "sg:postcode":"8500",
    "sg:province":"West-Vlaanderen",
    "wof:name":"Gravotech",
    "wof:placetype":"venue"
},
  "geometry": {"coordinates":[3.291631937,50.8302955627],"type":"Point"}
}