{
  "type": "Feature",
  "properties": {
    "addr:full":"Plantijnlei 46 Schoten Antwerpen 2900",
    "addr:housenumber":"46",
    "addr:postcode":"2900",
    "addr:street":"Plantijnlei",
    "iso:country":"BE",
    "sg:address":"Plantijnlei 46",
    "sg:city":"Schoten",
    "sg:classifiers":[
        {
            "category":"Wholesale",
            "subcategory":"Construction Materials",
            "type":"Manufacturing & Wholesale Goods"
        }
    ],
    "sg:phone":"+32 3 645 24 89",
    "sg:postcode":"2900",
    "sg:province":"Antwerpen",
    "sg:tags":[
        "elevator"
    ],
    "wof:name":"Liftronics Bvba",
    "wof:placetype":"venue"
},
  "geometry": {"coordinates":[4.4656438828,51.2475509644],"type":"Point"}
}