{
  "type": "Feature",
  "properties": {
    "addr:full":"Rue Albert Michiels 3 Namur Namur 5100",
    "addr:housenumber":"3",
    "addr:postcode":"5100",
    "addr:street":"Rue Albert Michiels",
    "iso:country":"BE",
    "sg:address":"Rue Albert Michiels 3",
    "sg:city":"Namur",
    "sg:orig_category":"Activit\u00e9s r\u00e9cr\u00e9atives diverses",
    "sg:phone":"+32 81 30 10 34",
    "sg:postcode":"5100",
    "sg:province":"Namur",
    "wof:name":"Herisson Philat\u00c9l. Club",
    "wof:placetype":"venue"
},
  "geometry": {"coordinates":[4.8713750839,50.4566345215],"type":"Point"}
}