{
  "type": "Feature",
  "properties": {
    "addr:full":"J. Mertensstraat 85 Dilbeek Vlaams-Brabant 1702",
    "addr:housenumber":"85",
    "addr:postcode":"1702",
    "addr:street":"J. Mertensstraat",
    "iso:country":"BE",
    "sg:address":"J. Mertensstraat 85",
    "sg:city":"Dilbeek",
    "sg:orig_category":"Schoonheidssalons",
    "sg:phone":"+32 2 466 18 26",
    "sg:postcode":"1702",
    "sg:province":"Vlaams-Brabant",
    "wof:name":"Patricia De Samblanx",
    "wof:placetype":"venue"
},
  "geometry": {"coordinates":[4.2541542053,50.8767929077],"type":"Point"}
}