{
  "type": "Feature",
  "properties": {
    "addr:full":"Binnenstraat 312 Aalst Oost-Vlaanderen 9300",
    "addr:housenumber":"312",
    "addr:postcode":"9300",
    "addr:street":"Binnenstraat",
    "iso:country":"BE",
    "sg:address":"Binnenstraat 312",
    "sg:city":"Aalst",
    "sg:orig_category":"Newspapers, magazines, periodicals - Distribution",
    "sg:phone":"+32 53 70 23 13",
    "sg:postcode":"9300",
    "sg:province":"Oost-Vlaanderen",
    "wof:name":"Lotto Shop",
    "wof:placetype":"venue"
},
  "geometry": {"coordinates":[4.0548038483,50.949886322],"type":"Point"}
}