{
  "type": "Feature",
  "properties": {
    "iso:country":"BE",
    "sg:address":"Populierenstraat 101",
    "sg:city":"Maasmechelen",
    "sg:orig_category":"Pain, p\u00e2tisseries and confiseries",
    "sg:phone":"+32 89 76 70 12",
    "sg:postcode":"3630",
    "sg:province":"Limburg",
    "wof:name":"Bakkerij Truyens-ramakers",
    "wof:placetype":"venue"
},
  "geometry": {"coordinates":[5.6961350441,50.963848114],"type":"Point"}
}