{
  "type": "Feature",
  "properties": {
    "addr:full":"Yokkerstraat 8 Hooglede West-Vlaanderen 8830",
    "addr:housenumber":"8",
    "addr:postcode":"8830",
    "addr:street":"Yokkerstraat",
    "iso:country":"BE",
    "sg:address":"Yokkerstraat 8",
    "sg:city":"Hooglede",
    "sg:orig_category":"Groententeelt Varkenskwekers",
    "sg:phone":"+32 51 70 39 65",
    "sg:postcode":"8830",
    "sg:province":"West-Vlaanderen",
    "wof:name":"Luc Wullepit",
    "wof:placetype":"venue"
},
  "geometry": {"coordinates":[3.0564050674,50.9759063721],"type":"Point"}
}