{
  "type": "Feature",
  "properties": {
    "addr:full":"Rue De Turenne 27 Braine-le-comte (steenkerque) Hainaut 7090",
    "addr:housenumber":"27",
    "addr:postcode":"7090",
    "addr:street":"Rue De Turenne;Hainaut",
    "iso:country":"BE",
    "sg:address":"Rue De Turenne 27",
    "sg:city":"Braine-le-comte (steenkerque)",
    "sg:classifiers":[
        {
            "category":"Farming",
            "subcategory":"Livestock Farm",
            "type":"Manufacturing & Wholesale Goods"
        }
    ],
    "sg:phone":"+32 67 63 64 10",
    "sg:postcode":"7090",
    "sg:province":"Hainaut",
    "sg:tags":[
        "breeding"
    ],
    "wof:name":"Antoine G",
    "wof:placetype":"venue"
},
  "geometry": {"coordinates":[4.0672101974,50.6410255432],"type":"Point"}
}