{
  "type": "Feature",
  "properties": {
    "iso:country":"BE",
    "sg:address":"Diestersteenweg 30",
    "sg:city":"Leopoldsburg",
    "sg:orig_category":"Pain, p\u00e2tisseries and confiseries",
    "sg:phone":"+32 11 34 58 86",
    "sg:postcode":"3970",
    "sg:province":"Limburg",
    "wof:name":"Bakkerij Kris",
    "wof:placetype":"venue"
},
  "geometry": {"coordinates":[5.2549171448,51.1157608032],"type":"Point"}
}