{
  "type": "Feature",
  "properties": {
    "addr:full":"Avenue De L'equerre 23 Ottignies-louvain-la-neuve (louvain-la-neuve) Brabant Wallon 1348",
    "addr:housenumber":"23",
    "addr:postcode":"1348",
    "addr:street":"Avenue De L'Equerre",
    "iso:country":"BE",
    "sg:address":"Avenue De L'equerre 23",
    "sg:city":"Ottignies-louvain-la-neuve (louvain-la-neuve)",
    "sg:classifiers":[
        {
            "category":"Health Services",
            "subcategory":"Dentist",
            "type":"Services"
        }
    ],
    "sg:phone":"+32 10 45 47 27",
    "sg:postcode":"1348",
    "sg:province":"Brabant Wallon",
    "wof:name":"Somers A (mme)",
    "wof:placetype":"venue"
},
  "geometry": {"coordinates":[4.6088118553,50.6647796631],"type":"Point"}
}