{
  "type": "Feature",
  "properties": {
    "iso:country":"BE",
    "sg:address":"Opperstraat 18",
    "sg:city":"Moerbeke",
    "sg:orig_category":"Poissonniers and \u00e9caillers",
    "sg:phone":"+32 9 346 83 86",
    "sg:postcode":"9180",
    "sg:province":"Oost-Vlaanderen",
    "wof:name":"Huis Aquaria",
    "wof:placetype":"venue"
},
  "geometry": {"coordinates":[3.9403400421,51.1741256714],"type":"Point"}
}