{
  "type": "Feature",
  "properties": {
    "addr:full":"Hoogveld 24 Westerlo Antwerpen 2260",
    "addr:housenumber":"24",
    "addr:postcode":"2260",
    "addr:street":"Hoogveld",
    "iso:country":"BE",
    "sg:address":"Hoogveld 24",
    "sg:city":"Westerlo",
    "sg:orig_category":"Sportclubs Sportterreinen and installaties behalve sportcentra",
    "sg:phone":"+32 14 26 57 93",
    "sg:postcode":"2260",
    "sg:province":"Antwerpen",
    "wof:name":"Kfc Oosterzon. Oosterwijk",
    "wof:placetype":"venue"
},
  "geometry": {"coordinates":[4.8612470627,51.128528595],"type":"Point"}
}