{
  "type": "Feature",
  "properties": {
    "addr:full":"Ruilare 113 Lochristi Oost-Vlaanderen 9080",
    "addr:housenumber":"113",
    "addr:postcode":"9080",
    "addr:street":"Ruilare",
    "iso:country":"BE",
    "sg:address":"Ruilare 113",
    "sg:city":"Lochristi",
    "sg:orig_category":"Plomberie, chauffage and installations sanitaires. Ramassage and traitement des d\u00e9chets m\u00e9nagers",
    "sg:phone":"+32 9 355 11 30",
    "sg:postcode":"9080",
    "sg:province":"Oost-Vlaanderen",
    "wof:name":"Condebo",
    "wof:placetype":"venue"
},
  "geometry": {"coordinates":[3.8978450298,51.1203651428],"type":"Point"}
}