{
  "type": "Feature",
  "properties": {
    "addr:full":"Moli\u00c8relaan 175 Vorst/forest Bruxelles-Capitale 1190",
    "addr:housenumber":"175",
    "addr:postcode":"1190",
    "addr:street":"Molie\u0300Relaan;/ Forest",
    "iso:country":"BE",
    "sg:address":"Moli\u00c8relaan 175",
    "sg:city":"Vorst/forest",
    "sg:orig_category":"Algemeen secundair onderwijs Technisch and beroeps secundair onderwijs",
    "sg:phone":"+32 2 347 32 23",
    "sg:postcode":"1190",
    "sg:province":"Bruxelles-Capitale",
    "wof:name":"Lyc\u00c9e Moli\u00c8re",
    "wof:placetype":"venue"
},
  "geometry": {"coordinates":[4.3492431641,50.8160858154],"type":"Point"}
}