{
  "type": "Feature",
  "properties": {
    "iso:country":"BE",
    "sg:address":"Eikhofstraat 16",
    "sg:city":"Diksmuide (groot)",
    "sg:orig_category":"Sociale secretariaten Verplichte sociale verzekeringen",
    "sg:phone":"+32 51 50 14 12",
    "sg:postcode":"8600",
    "sg:province":"West-Vlaanderen",
    "wof:name":"Partena",
    "wof:placetype":"venue"
},
  "geometry": {"coordinates":[2.8688380718,51.0197219849],"type":"Point"}
}