{
  "type": "Feature",
  "properties": {
    "addr:full":"Sint-gerolfstraat 33 Gent Oost-Vlaanderen 9031",
    "addr:housenumber":"33",
    "addr:postcode":"9031",
    "addr:street":"Sint-Gerolfstraat;Oost-Vlaanderen",
    "iso:country":"BE",
    "sg:address":"Sint-gerolfstraat 33",
    "sg:city":"Gent",
    "sg:orig_category":"Eleveurs de bovins",
    "sg:phone":"+32 9 227 33 90",
    "sg:postcode":"9031",
    "sg:province":"Oost-Vlaanderen",
    "wof:name":"Valere Dhaeyere",
    "wof:placetype":"venue"
},
  "geometry": {"coordinates":[3.6324129105,51.0443458557],"type":"Point"}
}