{
  "type": "Feature",
  "properties": {
    "addr:full":"Antoon Catriestraat 38 Gent (drongen) Oost-Vlaanderen 9031",
    "addr:housenumber":"38",
    "addr:postcode":"9031",
    "addr:street":"Antoon Catriestraat",
    "iso:country":"BE",
    "sg:address":"Antoon Catriestraat 38",
    "sg:city":"Gent (drongen)",
    "sg:classifiers":[
        {
            "category":"Health Services",
            "subcategory":"Health Practitioner",
            "type":"Services"
        }
    ],
    "sg:phone":"+32 9 227 69 71",
    "sg:postcode":"9031",
    "sg:province":"Oost-Vlaanderen",
    "sg:tags":[
        "physiotherapist"
    ],
    "wof:name":"De Zutter T",
    "wof:placetype":"venue"
},
  "geometry": {"coordinates":[3.6511490345,51.0542373657],"type":"Point"}
}