{
  "type": "Feature",
  "properties": {
    "iso:country":"BE",
    "sg:address":"Rue Dechamps 10",
    "sg:city":"Manage",
    "sg:orig_category":"Enseignement maternel and primaire",
    "sg:phone":"+32 64 55 47 29",
    "sg:postcode":"7170",
    "sg:province":"Hainaut",
    "wof:name":"Ecole Fondamentale Libre",
    "wof:placetype":"venue"
},
  "geometry": {"coordinates":[4.2342281342,50.5031929016],"type":"Point"}
}