{
  "type": "Feature",
  "properties": {
    "iso:country":"BE",
    "sg:address":"Rue De L'invasion 7-9",
    "sg:city":"Limbourg (go\u00e9)",
    "sg:classifiers":[
        {
            "category":"Manufacturing",
            "subcategory":"Lumber",
            "type":"Manufacturing & Wholesale Goods"
        }
    ],
    "sg:phone":"+32 87 76 09 11",
    "sg:postcode":"4834",
    "sg:province":"Li\u00e8ge",
    "sg:tags":[
        "timber"
    ],
    "wof:name":"Zimmermann Sa",
    "wof:placetype":"venue"
},
  "geometry": {"coordinates":[5.9711608887,50.6022224426],"type":"Point"}
}