{
  "type": "Feature",
  "properties": {
    "iso:country":"BE",
    "sg:address":"Ossogne 26",
    "sg:city":"Havelange",
    "sg:classifiers":[
        {
            "category":"Building & Trades",
            "subcategory":"Construction",
            "type":"Services"
        }
    ],
    "sg:phone":"+32 83 63 39 71",
    "sg:postcode":"5370",
    "sg:province":"Namur",
    "sg:tags":[
        "carpenter"
    ],
    "wof:name":"Donnay J M",
    "wof:placetype":"venue"
},
  "geometry": {"coordinates":[5.2221999168,50.405128479],"type":"Point"}
}