{
  "type": "Feature",
  "properties": {
    "iso:country":"BE",
    "sg:address":"Rue De Saintes 17",
    "sg:city":"Nivelles",
    "sg:classifiers":[
        {
            "category":"Restaurant",
            "type":"Food & Drink"
        }
    ],
    "sg:phone":"+32 67 84 22 08",
    "sg:postcode":"1400",
    "sg:province":"Brabant Wallon",
    "sg:tags":[
        "caf\u00e9s"
    ],
    "wof:name":"Taverne De Paris",
    "wof:placetype":"venue"
},
  "geometry": {"coordinates":[4.3253040314,50.596572876],"type":"Point"}
}