{
  "type": "Feature",
  "properties": {
    "iso:country":"BE",
    "sg:address":"Koning Albertstraat 9",
    "sg:city":"Aalst",
    "sg:orig_category":"Gespecialiseerde residenti\u00eble bouw Plaatsen van vloer- and muurbekleding",
    "sg:phone":"+32 53 70 47 91",
    "sg:postcode":"9310",
    "sg:province":"Oost-Vlaanderen",
    "wof:name":"Frans Raes",
    "wof:placetype":"venue"
},
  "geometry": {"coordinates":[4.0857958794,50.9576072693],"type":"Point"}
}