{
  "type": "Feature",
  "properties": {
    "iso:country":"BE",
    "sg:address":"Nachtegaalstraat 36",
    "sg:city":"Jabbeke (stalhille)",
    "sg:classifiers":[
        {
            "category":"Communications",
            "type":"Services"
        }
    ],
    "sg:phone":"+32 50 82 02 22",
    "sg:postcode":"8490",
    "sg:province":"West-Vlaanderen",
    "sg:tags":[
        "translator"
    ],
    "wof:name":"Jazyk Bvba",
    "wof:placetype":"venue"
},
  "geometry": {"coordinates":[3.0767879486,51.2168426514],"type":"Point"}
}