{
  "type": "Feature",
  "properties": {
    "addr:full":"Alphonse Asselbergsstr. 70 Ukkel/uccle Bruxelles-Capitale 1180",
    "addr:housenumber":"70",
    "addr:postcode":"1180",
    "addr:street":"/",
    "iso:country":"BE",
    "sg:address":"Alphonse Asselbergsstr. 70",
    "sg:city":"Ukkel/uccle",
    "sg:orig_category":"Artsen and specialisten",
    "sg:phone":"+32 2 345 44 12",
    "sg:postcode":"1180",
    "sg:province":"Bruxelles-Capitale",
    "wof:name":"Lyse Descamps",
    "wof:placetype":"venue"
},
  "geometry": {"coordinates":[4.3333668709,50.8056564331],"type":"Point"}
}