{
  "type": "Feature",
  "properties": {
    "addr:full":"Rue Lavalle 71 Ham-sur-heure-nalinnes Hainaut 6120",
    "addr:housenumber":"71",
    "addr:postcode":"6120",
    "addr:street":"Rue Lavalle;Hainaut",
    "iso:country":"BE",
    "sg:address":"Rue Lavalle 71",
    "sg:city":"Ham-sur-heure-nalinnes",
    "sg:orig_category":"Diverse bouwafwerking and reiniging Installatie van houten of kunststof schrijnwerk",
    "sg:phone":"+32 71 21 34 80",
    "sg:postcode":"6120",
    "sg:province":"Hainaut",
    "wof:name":"Massart-brassini",
    "wof:placetype":"venue"
},
  "geometry": {"coordinates":[4.4394359589,50.3184738159],"type":"Point"}
}