{
  "type": "Feature",
  "properties": {
    "addr:full":"Just. Lipsiusplein 5 Overijse Vlaams-Brabant 3090",
    "addr:housenumber":"5",
    "addr:postcode":"3090",
    "iso:country":"BE",
    "sg:address":"Just. Lipsiusplein 5",
    "sg:city":"Overijse",
    "sg:classifiers":[
        {
            "category":"Insurance",
            "subcategory":"Life Insurance",
            "type":"Services"
        }
    ],
    "sg:phone":"+32 2 687 44 44",
    "sg:postcode":"3090",
    "sg:province":"Vlaams-Brabant",
    "sg:tags":[
        "assurance"
    ],
    "wof:name":"Detienne",
    "wof:placetype":"venue"
},
  "geometry": {"coordinates":[4.5372872353,50.772983551],"type":"Point"}
}