{
  "type": "Feature",
  "properties": {
    "iso:country":"BE",
    "sg:address":"Rue De Sartiau 12",
    "sg:city":"Thuin",
    "sg:orig_category":"Woningbouw",
    "sg:phone":"+32 71 59 12 21",
    "sg:postcode":"6530",
    "sg:province":"Hainaut",
    "wof:name":"Daniel Hennuy",
    "wof:placetype":"venue"
},
  "geometry": {"coordinates":[4.2674927711,50.3383026123],"type":"Point"}
}