{
  "type": "Feature",
  "properties": {
    "addr:full":"Potaardestraat 82 Lebbeke Oost-Vlaanderen 9280",
    "addr:housenumber":"82",
    "addr:postcode":"9280",
    "addr:street":"Potaardestraat",
    "iso:country":"BE",
    "sg:address":"Potaardestraat 82",
    "sg:city":"Lebbeke",
    "sg:orig_category":"Installation de menuiserie en bois and plastique",
    "sg:phone":"+32 52 41 35 52",
    "sg:postcode":"9280",
    "sg:province":"Oost-Vlaanderen",
    "wof:name":"Pierre Jansegers",
    "wof:placetype":"venue"
},
  "geometry": {"coordinates":[4.1613512039,51.0051040649],"type":"Point"}
}