{
  "type": "Feature",
  "properties": {
    "addr:full":"Chauss\u00e9e De Louvain 601 Bruxelles (schaerbeek) Bruxelles-Capitale 1030",
    "addr:housenumber":"601",
    "addr:postcode":"1030",
    "addr:street":"Chausse\u0301E De Louvain",
    "iso:country":"BE",
    "sg:address":"Chauss\u00e9e De Louvain 601",
    "sg:city":"Bruxelles (schaerbeek)",
    "sg:classifiers":[
        {
            "category":"Travel",
            "subcategory":"Travel Agent",
            "type":"Entertainment"
        }
    ],
    "sg:phone":"+32 2 726 11 21",
    "sg:postcode":"1030",
    "sg:province":"Bruxelles-Capitale",
    "sg:tags":[
        "accessory",
        "mountaineering"
    ],
    "wof:name":"Avventura Brussels",
    "wof:placetype":"venue"
},
  "geometry": {"coordinates":[4.403717041,50.8565216064],"type":"Point"}
}