{
  "type": "Feature",
  "properties": {
    "addr:full":"L\u00b4h\u00d4tel De Ville 1 Namur Namur 5000",
    "addr:housenumber":"1",
    "addr:postcode":"5000",
    "iso:country":"BE",
    "sg:address":"L\u00b4h\u00d4tel De Ville 1",
    "sg:city":"Namur",
    "sg:orig_category":"Overheidsdiensten",
    "sg:phone":"+32 81 24 65 60",
    "sg:postcode":"5000",
    "sg:province":"Namur",
    "wof:name":"Administration Communale",
    "wof:placetype":"venue"
},
  "geometry": {"coordinates":[4.8657398224,50.4667167664],"type":"Point"}
}