{
  "type": "Feature",
  "properties": {
    "addr:full":"Jachtlaan 17 Balen Antwerpen 2490",
    "addr:housenumber":"17",
    "addr:postcode":"2490",
    "addr:street":"Jachtlaan",
    "iso:country":"BE",
    "sg:address":"Jachtlaan 17",
    "sg:city":"Balen",
    "sg:classifiers":[
        {
            "category":"Retail",
            "subcategory":"Animal Services",
            "type":"Services"
        }
    ],
    "sg:phone":"+32 14 81 33 50",
    "sg:postcode":"2490",
    "sg:province":"Antwerpen",
    "sg:tags":[
        "breeding",
        "selling",
        "-",
        "dog"
    ],
    "wof:name":"Lejo's Black Fires",
    "wof:placetype":"venue"
},
  "geometry": {"coordinates":[5.246571064,51.1886062622],"type":"Point"}
}