{
  "type": "Feature",
  "properties": {
    "addr:full":"Houveign\u00c9 4 Stavelot Li\u00e8ge 4970",
    "addr:housenumber":"4",
    "addr:postcode":"4970",
    "addr:street":"Houveigne\u0301",
    "iso:country":"BE",
    "sg:address":"Houveign\u00c9 4",
    "sg:city":"Stavelot",
    "sg:orig_category":"Fotografen and fotostudio's",
    "sg:phone":"+32 80 86 26 74",
    "sg:postcode":"4970",
    "sg:province":"Li\u00e8ge",
    "wof:name":"Charles Chaineux",
    "wof:placetype":"venue"
},
  "geometry": {"coordinates":[6.0065398216,50.3534698486],"type":"Point"}
}