{
  "type": "Feature",
  "properties": {
    "addr:full":"Rue Des Bruy\u00c8res 101 Mons Hainaut 7034",
    "addr:housenumber":"101",
    "addr:postcode":"7034",
    "addr:street":"Rue Des Bruye\u0300Res;Hainaut",
    "iso:country":"BE",
    "sg:address":"Rue Des Bruy\u00c8res 101",
    "sg:city":"Mons",
    "sg:orig_category":"Kantoormateriaal",
    "sg:phone":"+32 65 31 40 92",
    "sg:postcode":"7034",
    "sg:province":"Hainaut",
    "wof:name":"Mecano-buro",
    "wof:placetype":"venue"
},
  "geometry": {"coordinates":[4.0086159706,50.4765396118],"type":"Point"}
}