{
  "type": "Feature",
  "properties": {
    "addr:full":"Chee De Namur 5 Hamme 5990",
    "addr:housenumber":"5",
    "addr:postcode":"5990",
    "addr:street":"Chee;Namur",
    "iso:country":"BE",
    "sg:address":"Chee De Namur 5",
    "sg:city":"Hamme",
    "sg:classifiers":[
        {
            "category":"Banks & Credit Unions",
            "subcategory":"Bank",
            "type":"Services"
        }
    ],
    "sg:phone":"+32 10 86 60 19",
    "sg:postcode":"5990",
    "wof:name":"Cr\u00e9dit Communal",
    "wof:placetype":"venue"
},
  "geometry": {"coordinates":[4.8617601395,50.4657211304],"type":"Point"}
}