{
  "type": "Feature",
  "properties": {
    "addr:full":"Rue De Bruxelles 6 Genappe Brabant Wallon 1470",
    "addr:housenumber":"6",
    "addr:postcode":"1470",
    "addr:street":"Rue De Bruxelles;Wallon",
    "iso:country":"BE",
    "sg:address":"Rue De Bruxelles 6",
    "sg:city":"Genappe",
    "sg:classifiers":[
        {
            "category":"Farming",
            "subcategory":"Fish & Marine Products",
            "type":"Manufacturing & Wholesale Goods"
        }
    ],
    "sg:phone":"+32 67 77 23 17",
    "sg:postcode":"1470",
    "sg:province":"Brabant Wallon",
    "sg:tags":[
        "retail",
        "-",
        "shellfish"
    ],
    "wof:name":"La Sol Do R\u00e9",
    "wof:placetype":"venue"
},
  "geometry": {"coordinates":[4.4504599571,50.6110954285],"type":"Point"}
}