{
  "type": "Feature",
  "properties": {
    "iso:country":"BE",
    "sg:address":"Chauss\u00c9e De Jolimont 11",
    "sg:city":"Haine-saint-pierre",
    "sg:orig_category":"Fleurop Interflora",
    "sg:phone":"+32 64 22 44 59",
    "sg:postcode":"7100",
    "sg:province":"Hainaut",
    "wof:name":"Willam",
    "wof:placetype":"venue"
},
  "geometry": {"coordinates":[4.2157001495,50.4721488953],"type":"Point"}
}