{
  "type": "Feature",
  "properties": {
    "addr:full":"Place Du Vieux March\u00c9 8 Edingen/enghien Hainaut 7850",
    "addr:housenumber":"8",
    "addr:postcode":"7850",
    "addr:street":"Place Du Vieux Marche\u0301",
    "iso:country":"BE",
    "sg:address":"Place Du Vieux March\u00c9 8",
    "sg:city":"Edingen/enghien",
    "sg:classifiers":[
        {
            "category":"Arena",
            "subcategory":"Sports Club",
            "type":"Entertainment"
        }
    ],
    "sg:phone":"+32 2 395 31 56",
    "sg:postcode":"7850",
    "sg:province":"Hainaut",
    "sg:tags":[
        "de"
    ],
    "wof:name":"B.c. Ceba Enghien",
    "wof:placetype":"venue"
},
  "geometry": {"coordinates":[4.0429401398,50.6952667236],"type":"Point"}
}