{
  "type": "Feature",
  "properties": {
    "addr:full":"Henningenlaan 69 Wuustwezel (loenhout) Antwerpen 2990",
    "addr:housenumber":"69",
    "addr:postcode":"2990",
    "addr:street":"Henningenlaan",
    "iso:country":"BE",
    "sg:address":"Henningenlaan 69",
    "sg:city":"Wuustwezel (loenhout)",
    "sg:classifiers":[
        {
            "category":"Personal",
            "subcategory":"Beauty Salon",
            "type":"Services"
        }
    ],
    "sg:phone":"+32 3 669 94 76",
    "sg:postcode":"2990",
    "sg:province":"Antwerpen",
    "sg:tags":[
        "lady",
        "-",
        "hairdressing"
    ],
    "wof:name":"De Knipboetiek",
    "wof:placetype":"venue"
},
  "geometry": {"coordinates":[4.6352372169,51.4013366699],"type":"Point"}
}