{
  "type": "Feature",
  "properties": {
    "iso:country":"BE",
    "sg:address":"Rue Charles Rittw\u00c9ger 196",
    "sg:city":"Theux",
    "sg:orig_category":"Kinderopvang",
    "sg:phone":"+32 87 54 27 23",
    "sg:postcode":"4910",
    "sg:province":"Li\u00e8ge",
    "wof:name":"Cr\u00c8che Les Marmousets",
    "wof:placetype":"venue"
},
  "geometry": {"coordinates":[5.8128199577,50.5394210815],"type":"Point"}
}