{
  "type": "Feature",
  "properties": {
    "addr:full":"Bredabaan 528 Brasschaat Antwerpen 2930",
    "addr:housenumber":"528",
    "addr:postcode":"2930",
    "addr:street":"Bredabaan",
    "iso:country":"BE",
    "sg:address":"Bredabaan 528",
    "sg:city":"Brasschaat",
    "sg:orig_category":"Art and fournitures artistiques. R\u00e9paration and restauration de meubles",
    "sg:phone":"+32 3 651 78 40",
    "sg:postcode":"2930",
    "sg:province":"Antwerpen",
    "wof:name":"F.a.f.",
    "wof:placetype":"venue"
},
  "geometry": {"coordinates":[4.5012612343,51.300945282],"type":"Point"}
}