{
  "type": "Feature",
  "properties": {
    "addr:full":"Sint-amandsesteenweg 395 Bornem Antwerpen 2880",
    "addr:housenumber":"395",
    "addr:postcode":"2880",
    "addr:street":"Bornem Antwerpen",
    "iso:country":"BE",
    "sg:address":"Sint-amandsesteenweg 395",
    "sg:city":"Bornem",
    "sg:classifiers":[
        {
            "category":"Shopping",
            "subcategory":"Shoes",
            "type":"Retail Goods"
        }
    ],
    "sg:phone":"+32 3 889 30 37",
    "sg:postcode":"2880",
    "sg:province":"Antwerpen",
    "sg:tags":[
        "slipper",
        "-"
    ],
    "wof:name":"Van Steen R",
    "wof:placetype":"venue"
},
  "geometry": {"coordinates":[4.209897995,51.0725250244],"type":"Point"}
}