{
  "type": "Feature",
  "properties": {
    "addr:full":"Brugsestraat 147 Harelbeke West-Vlaanderen 8531",
    "addr:housenumber":"147",
    "addr:postcode":"8531",
    "addr:street":"Brugsestraat",
    "iso:country":"BE",
    "sg:address":"Brugsestraat 147",
    "sg:city":"Harelbeke",
    "sg:orig_category":"Eleveurs de bovins",
    "sg:phone":"+32 56 71 58 43",
    "sg:postcode":"8531",
    "sg:province":"West-Vlaanderen",
    "wof:name":"Jacques D'halluin",
    "wof:placetype":"venue"
},
  "geometry": {"coordinates":[3.3104400635,50.8748130798],"type":"Point"}
}