{
  "type": "Feature",
  "properties": {
    "addr:full":"Rue Des Combattants 7 Donceel Li\u00e8ge 4357",
    "addr:housenumber":"7",
    "addr:postcode":"4357",
    "addr:street":"Rue Des Combattants",
    "iso:country":"BE",
    "sg:address":"Rue Des Combattants 7",
    "sg:city":"Donceel",
    "sg:classifiers":[
        {
            "category":"Arena",
            "subcategory":"Sports Club",
            "type":"Entertainment"
        }
    ],
    "sg:phone":"+32 19 54 51 03",
    "sg:postcode":"4357",
    "sg:province":"Li\u00e8ge",
    "sg:tags":[
        "de"
    ],
    "wof:name":"S.c.m.l. Mammouth",
    "wof:placetype":"venue"
},
  "geometry": {"coordinates":[5.3115987778,50.6595420837],"type":"Point"}
}