{
  "type": "Feature",
  "properties": {
    "addr:full":"Avenue Moli\u00e8re 114 Bruxelles (forest) Bruxelles-Capitale 1190",
    "addr:housenumber":"114",
    "addr:postcode":"1190",
    "addr:street":"Avenue Molie\u0300Re",
    "iso:country":"BE",
    "sg:address":"Avenue Moli\u00e8re 114",
    "sg:city":"Bruxelles (forest)",
    "sg:classifiers":[
        {
            "category":"Health Services",
            "subcategory":"Health Practitioner",
            "type":"Services"
        }
    ],
    "sg:phone":"+32 2 347 21 34",
    "sg:postcode":"1190",
    "sg:province":"Bruxelles-Capitale",
    "sg:tags":[
        "physiotherapist"
    ],
    "wof:name":"Magain H",
    "wof:placetype":"venue"
},
  "geometry": {"coordinates":[4.3491082191,50.8163833618],"type":"Point"}
}