{
  "type": "Feature",
  "properties": {
    "iso:country":"BE",
    "sg:address":"Grote Markt 3",
    "sg:city":"Aalst",
    "sg:classifiers":[
        {
            "category":"Social Services",
            "subcategory":"Child Care",
            "type":"Services"
        }
    ],
    "sg:phone":"+32 53 73 22 92",
    "sg:postcode":"9300",
    "sg:province":"Oost-Vlaanderen",
    "sg:tags":[
        "baby",
        "nursery",
        "day",
        "sitting"
    ],
    "wof:name":"Dienst Gezin Kinderdagverblijven Aalst",
    "wof:placetype":"venue"
},
  "geometry": {"coordinates":[4.0381097794,50.9384269714],"type":"Point"}
}