{
  "type": "Feature",
  "properties": {
    "addr:full":"Ganzendries 74 Lubbeek Vlaams-Brabant 3212",
    "addr:housenumber":"74",
    "addr:postcode":"3212",
    "addr:street":"Ganzendries",
    "iso:country":"BE",
    "sg:address":"Ganzendries 74",
    "sg:city":"Lubbeek",
    "sg:orig_category":"RESTAURANTS: CAF\u00c9S",
    "sg:phone":"+32 16 46 45 66",
    "sg:postcode":"3212",
    "sg:province":"Vlaams-Brabant",
    "wof:name":"Taverne Het Lindeke",
    "wof:placetype":"venue"
},
  "geometry": {"coordinates":[4.7935700417,50.8666038513],"type":"Point"}
}