{
  "type": "Feature",
  "properties": {
    "iso:country":"BE",
    "sg:address":"Dolezlaan 111",
    "sg:city":"Ukkel/uccle",
    "sg:orig_category":"Installatie van houten of kunststof schrijnwerk",
    "sg:phone":"+32 2 374 54 43",
    "sg:postcode":"1180",
    "sg:province":"Bruxelles-Capitale",
    "wof:name":"Jean-marc Moors",
    "wof:placetype":"venue"
},
  "geometry": {"coordinates":[4.3590869904,50.7886734009],"type":"Point"}
}