{
  "type": "Feature",
  "properties": {
    "addr:full":"Place Des Guillemins 2 Li\u00c8ge Li\u00e8ge 4000",
    "addr:housenumber":"2",
    "addr:postcode":"4000",
    "addr:street":"Place Des Guillemins",
    "iso:country":"BE",
    "sg:address":"Place Des Guillemins 2",
    "sg:city":"Li\u00c8ge",
    "sg:classifiers":[
        {
            "category":"Restaurant",
            "type":"Food & Drink"
        }
    ],
    "sg:phone":"+32 4 254 15 92",
    "sg:postcode":"4000",
    "sg:province":"Li\u00e8ge",
    "sg:tags":[
        "caf\u00e9s"
    ],
    "wof:name":"Buffet De La Gare",
    "wof:placetype":"venue"
},
  "geometry": {"coordinates":[5.5663871765,50.6254043579],"type":"Point"}
}