{
  "type": "Feature",
  "properties": {
    "iso:country":"BE",
    "sg:address":"Mahatma Gandhistraat 11b301",
    "sg:city":"Mechelen",
    "sg:classifiers":[
        {
            "category":"Cafe",
            "type":"Food & Drink"
        }
    ],
    "sg:phone":"+32 15 42 37 23",
    "sg:postcode":"2800",
    "sg:province":"Antwerpen",
    "sg:tags":[
        "caf\u00e9s"
    ],
    "wof:name":"Gilberte Somers",
    "wof:placetype":"venue"
},
  "geometry": {"coordinates":[4.4868822098,50.9987983704],"type":"Point"}
}