{
  "type": "Feature",
  "properties": {
    "iso:country":"BE",
    "sg:address":"Monterreystraat 22",
    "sg:city":"Gent",
    "sg:classifiers":[
        {
            "category":"Cafe",
            "type":"Food & Drink"
        }
    ],
    "sg:phone":"+32 9 245 16 44",
    "sg:postcode":"9000",
    "sg:province":"Oost-Vlaanderen",
    "sg:tags":[
        "caf\u00e9s"
    ],
    "wof:name":"Evalex",
    "wof:placetype":"venue"
},
  "geometry": {"coordinates":[3.7207000256,51.0346412659],"type":"Point"}
}