{
  "type": "Feature",
  "properties": {
    "addr:full":"Grand'rue 26 Lessines Hainaut 7860",
    "addr:housenumber":"26",
    "addr:postcode":"7860",
    "addr:street":"Grand'Rue;Hainaut",
    "iso:country":"BE",
    "sg:address":"Grand'rue 26",
    "sg:city":"Lessines",
    "sg:orig_category":"Banques and organismes de cr\u00e9dit",
    "sg:phone":"+32 68 33 46 57",
    "sg:postcode":"7860",
    "sg:province":"Hainaut",
    "wof:name":"Cbc",
    "wof:placetype":"venue"
},
  "geometry": {"coordinates":[3.8290889263,50.7124633789],"type":"Point"}
}