{
  "type": "Feature",
  "properties": {
    "addr:full":"Noordervaart 39-1 Herentals Antwerpen 2200",
    "addr:housenumber":"39-1",
    "addr:postcode":"2200",
    "addr:street":"Noordervaart",
    "iso:country":"BE",
    "sg:address":"Noordervaart 39-1",
    "sg:city":"Herentals",
    "sg:classifiers":[
        {
            "category":"Home & Garden",
            "subcategory":"Building Materials",
            "type":"Retail Goods"
        }
    ],
    "sg:phone":"+32 14 23 03 22",
    "sg:postcode":"2200",
    "sg:province":"Antwerpen",
    "sg:tags":[
        "veranda"
    ],
    "wof:name":"I.m. Veranda's Bvba",
    "wof:placetype":"venue"
},
  "geometry": {"coordinates":[4.8540730476,51.1746025085],"type":"Point"}
}