{
  "type": "Feature",
  "properties": {
    "iso:country":"BE",
    "sg:address":"Toevluchtweg 15a",
    "sg:city":"Nieuwpoort",
    "sg:orig_category":"Diverse voedingsmiddelen Gh",
    "sg:phone":"+32 58 23 26 62",
    "sg:postcode":"8620",
    "sg:province":"West-Vlaanderen",
    "wof:name":"Gadus",
    "wof:placetype":"venue"
},
  "geometry": {"coordinates":[2.7636170387,51.1269798279],"type":"Point"}
}