{
  "type": "Feature",
  "properties": {
    "addr:full":"Provincieweg 497 Herzele (hillegem) Oost-Vlaanderen 9550",
    "addr:housenumber":"497",
    "addr:postcode":"9550",
    "addr:street":"Provincieweg",
    "iso:country":"BE",
    "sg:address":"Provincieweg 497",
    "sg:city":"Herzele (hillegem)",
    "sg:classifiers":[
        {
            "category":"Bakery",
            "type":"Food & Drink"
        }
    ],
    "sg:phone":"+32 9 360 22 38",
    "sg:postcode":"9550",
    "sg:province":"Oost-Vlaanderen",
    "sg:tags":[
        "confectioner",
        "baker"
    ],
    "wof:name":"D'haemers M",
    "wof:placetype":"venue"
},
  "geometry": {"coordinates":[3.8787400723,50.8998908997],"type":"Point"}
}