{
  "type": "Feature",
  "properties": {
    "iso:country":"BE",
    "sg:address":"Researchpark Haasrode - Interleuven",
    "sg:city":"Heverlee",
    "sg:classifiers":[
        {
            "category":"Landmark",
            "subcategory":"Tourist Information",
            "type":"Public Place"
        }
    ],
    "sg:phone":"+32 16 40 30 39",
    "sg:postcode":"3001",
    "sg:province":"Vlaams-Brabant",
    "sg:tags":[
        "geographic",
        "system",
        "gi"
    ],
    "wof:name":"Gim Geographic Informations Management Nv",
    "wof:placetype":"venue"
},
  "geometry": {"coordinates":[4.723733902,50.8510437012],"type":"Point"}
}