{
  "type": "Feature",
  "properties": {
    "addr:full":"Eburonenlaan 18 Leuven (heverlee) Vlaams-Brabant 3001",
    "addr:housenumber":"18",
    "addr:postcode":"3001",
    "addr:street":"Eburonenlaan",
    "iso:country":"BE",
    "sg:address":"Eburonenlaan 18",
    "sg:city":"Leuven (heverlee)",
    "sg:classifiers":[
        {
            "category":"Professional",
            "subcategory":"Lawyer & Legal Services",
            "type":"Services"
        }
    ],
    "sg:phone":"+32 16 38 94 74",
    "sg:postcode":"3001",
    "sg:province":"Vlaams-Brabant",
    "wof:name":"Denis Yolande",
    "wof:placetype":"venue"
},
  "geometry": {"coordinates":[4.6905469894,50.858745575],"type":"Point"}
}