{
  "type": "Feature",
  "properties": {
    "addr:full":"Zuurbemdesteenweg 2 Kortenaken (hoeleden) Vlaams-Brabant 3471",
    "addr:housenumber":"2",
    "addr:postcode":"3471",
    "addr:street":"Zuurbemdesteenweg",
    "iso:country":"BE",
    "sg:address":"Zuurbemdesteenweg 2",
    "sg:city":"Kortenaken (hoeleden)",
    "sg:classifiers":[
        {
            "category":"Museum",
            "type":"Entertainment"
        }
    ],
    "sg:phone":"+32 16 77 98 33",
    "sg:postcode":"3471",
    "sg:province":"Vlaams-Brabant",
    "wof:name":"Jacobinahof",
    "wof:placetype":"venue"
},
  "geometry": {"coordinates":[4.9824671745,50.8676147461],"type":"Point"}
}