{
  "type": "Feature",
  "properties": {
    "addr:full":"Rotterweg 1 Eupen Li\u00e8ge 4700",
    "addr:housenumber":"1",
    "addr:postcode":"4700",
    "addr:street":"Rotterweg",
    "iso:country":"BE",
    "sg:address":"Rotterweg 1",
    "sg:city":"Eupen",
    "sg:classifiers":[
        {
            "category":"Professional",
            "subcategory":"Computer Services",
            "type":"Services"
        }
    ],
    "sg:phone":"+32 87 76 53 35",
    "sg:postcode":"4700",
    "sg:province":"Li\u00e8ge",
    "sg:tags":[
        "webdesign",
        "-",
        "internet"
    ],
    "wof:name":"Graphik Und Werbedesign",
    "wof:placetype":"venue"
},
  "geometry": {"coordinates":[6.0489268303,50.6180839539],"type":"Point"}
}