{
  "type": "Feature",
  "properties": {
    "iso:country":"BE",
    "sg:address":"Pastorijstraat 24",
    "sg:city":"Tielt",
    "sg:orig_category":"Electrom\u00e9nager, t\u00e9l\u00e9visions and radios. Installation \u00e9lectrique r\u00e9sidentielle",
    "sg:phone":"+32 51 63 36 22",
    "sg:postcode":"8700",
    "sg:province":"West-Vlaanderen",
    "wof:name":"Jacques Van Overbeke",
    "wof:placetype":"venue"
},
  "geometry": {"coordinates":[3.4250719547,50.9952850342],"type":"Point"}
}