{
  "type": "Feature",
  "properties": {
    "addr:full":"Rue Bas-bout 12 Brunehaut Hainaut 7620",
    "addr:housenumber":"12",
    "addr:postcode":"7620",
    "addr:street":"Rue Bas-Bout",
    "iso:country":"BE",
    "sg:address":"Rue Bas-bout 12",
    "sg:city":"Brunehaut",
    "sg:orig_category":"Eleveurs de bovins",
    "sg:phone":"+32 69 64 81 13",
    "sg:postcode":"7620",
    "sg:province":"Hainaut",
    "wof:name":"Alexandre Jacques & Louis",
    "wof:placetype":"venue"
},
  "geometry": {"coordinates":[3.373333931,50.5503387451],"type":"Point"}
}