{
  "type": "Feature",
  "properties": {
    "addr:full":"Ossegemstraat 49 Meise Vlaams-Brabant 1860",
    "addr:housenumber":"49",
    "addr:postcode":"1860",
    "addr:street":"Ossegemstraat",
    "iso:country":"BE",
    "sg:address":"Ossegemstraat 49",
    "sg:city":"Meise",
    "sg:orig_category":"Groententeelt",
    "sg:phone":"+32 2 269 09 33",
    "sg:postcode":"1860",
    "sg:province":"Vlaams-Brabant",
    "wof:name":"Jan Cranshof",
    "wof:placetype":"venue"
},
  "geometry": {"coordinates":[4.3212099075,50.9640388489],"type":"Point"}
}