{
  "type": "Feature",
  "properties": {
    "addr:full":"Clement Cartuyvelsstraat 39 Sint-truiden Limburg 3800",
    "addr:housenumber":"39",
    "addr:postcode":"3800",
    "addr:street":"Cartuyvelsstraat",
    "iso:country":"BE",
    "sg:address":"Clement Cartuyvelsstraat 39",
    "sg:city":"Sint-truiden",
    "sg:classifiers":[
        {
            "category":"Insurance",
            "subcategory":"Insurance Agent",
            "type":"Services"
        }
    ],
    "sg:phone":"+32 11 69 30 11",
    "sg:postcode":"3800",
    "sg:province":"Limburg",
    "sg:tags":[
        "verzekeringsmakelaars",
        "expert"
    ],
    "wof:name":"P&v",
    "wof:placetype":"venue"
},
  "geometry": {"coordinates":[5.191259861,50.8190193176],"type":"Point"}
}