{
  "type": "Feature",
  "properties": {
    "addr:full":"Rue Dagly 6 Spa Li\u00e8ge 4900",
    "addr:housenumber":"6",
    "addr:postcode":"4900",
    "addr:street":"Rue Dagly",
    "iso:country":"BE",
    "sg:address":"Rue Dagly 6",
    "sg:city":"Spa",
    "sg:orig_category":"Boucheries",
    "sg:phone":"+32 87 77 17 20",
    "sg:postcode":"4900",
    "sg:province":"Li\u00e8ge",
    "wof:name":"Andr\u00c9 Servais",
    "wof:placetype":"venue"
},
  "geometry": {"coordinates":[5.8659281731,50.4924430847],"type":"Point"}
}