{
  "type": "Feature",
  "properties": {
    "addr:full":"Rue Du Luxembourg Marche-en-famenne Luxembourg 6900",
    "addr:postcode":"6900",
    "addr:street":"Rue Du Luxembourg",
    "iso:country":"BE",
    "sg:address":"Rue Du Luxembourg",
    "sg:city":"Marche-en-famenne",
    "sg:classifiers":[
        {
            "category":"Utilities",
            "subcategory":"Natural Gas",
            "type":"Services"
        }
    ],
    "sg:phone":"+32 84 31 18 76",
    "sg:postcode":"6900",
    "sg:province":"Luxembourg",
    "sg:tags":[
        "combustible",
        "royal",
        "canin"
    ],
    "wof:name":"Gissart",
    "wof:placetype":"venue"
},
  "geometry": {"coordinates":[5.3462700844,50.2203483582],"type":"Point"}
}