{
  "type": "Feature",
  "properties": {
    "iso:country":"BE",
    "sg:address":"Place Omer Musch 19",
    "sg:city":"Chapelle-lez-herlaimont (pi\u00e9ton)",
    "sg:classifiers":[
        {
            "category":"Bars & Pubs",
            "type":"Food & Drink"
        }
    ],
    "sg:phone":"+32 71 52 52 15",
    "sg:postcode":"7160",
    "sg:province":"Hainaut",
    "wof:name":"Maison Du Peuple (le)",
    "wof:placetype":"venue"
},
  "geometry": {"coordinates":[4.2946572304,50.4398384094],"type":"Point"}
}