{
  "type": "Feature",
  "properties": {
    "iso:country":"BE",
    "sg:address":"Mezennestje 6",
    "sg:city":"Wuustwezel",
    "sg:orig_category":"Pleisterwerk",
    "sg:phone":"+32 3 663 49 34",
    "sg:postcode":"2990",
    "sg:province":"Antwerpen",
    "wof:name":"Johny Looyen",
    "wof:placetype":"venue"
},
  "geometry": {"coordinates":[4.544426918,51.356803894],"type":"Point"}
}