{
  "type": "Feature",
  "properties": {
    "addr:full":"Arthur Borghijsstraat 28 Puurs (ruisbroek) Antwerpen 2870",
    "addr:housenumber":"28",
    "addr:postcode":"2870",
    "addr:street":"Borghijsstraat",
    "iso:country":"BE",
    "sg:address":"Arthur Borghijsstraat 28",
    "sg:city":"Puurs (ruisbroek)",
    "sg:orig_category":"Non-Classified Establishments",
    "sg:phone":"+32 3 866 58 38",
    "sg:postcode":"2870",
    "sg:province":"Antwerpen",
    "wof:name":"Biovitaal Belgi\u00eb Vof",
    "wof:placetype":"venue"
},
  "geometry": {"coordinates":[4.3266730309,51.07862854],"type":"Point"}
}