{
  "type": "Feature",
  "properties": {
    "iso:country":"BE",
    "sg:address":"Koning Leopold Iii-straat 9",
    "sg:city":"Kuurne",
    "sg:classifiers":[
        {
            "category":"Retail",
            "subcategory":"Event Space",
            "type":"Services"
        }
    ],
    "sg:phone":"+32 56 70 11 11",
    "sg:postcode":"8520",
    "sg:province":"West-Vlaanderen",
    "sg:tags":[
        "rental",
        "-",
        "hall"
    ],
    "wof:name":"Cappellerie (de)",
    "wof:placetype":"venue"
},
  "geometry": {"coordinates":[3.289689064,50.8516426086],"type":"Point"}
}