{
  "type": "Feature",
  "properties": {
    "addr:full":"Rue Du Blacet 45b Yvoir Namur 5530",
    "addr:housenumber":"45b",
    "addr:postcode":"5530",
    "addr:street":"Rue Du Blacet",
    "iso:country":"BE",
    "sg:address":"Rue Du Blacet 45b",
    "sg:city":"Yvoir",
    "sg:classifiers":[
        {
            "category":"Home & Garden",
            "subcategory":"Carpets & Floor Coverings",
            "type":"Retail Goods"
        }
    ],
    "sg:phone":"+32 82 61 18 96",
    "sg:postcode":"5530",
    "sg:province":"Namur",
    "sg:tags":[
        "tile"
    ],
    "wof:name":"Gregoire A",
    "wof:placetype":"venue"
},
  "geometry": {"coordinates":[4.882101059,50.3280143738],"type":"Point"}
}