{
  "type": "Feature",
  "properties": {
    "addr:full":"Rue Henri Lema\u00eetre 53 Namur Namur 5000",
    "addr:housenumber":"53",
    "addr:postcode":"5000",
    "addr:street":"Rue Henri Lemai\u0302Tre",
    "iso:country":"BE",
    "sg:address":"Rue Henri Lema\u00eetre 53",
    "sg:city":"Namur",
    "sg:classifiers":[
        {
            "category":"Real Estate",
            "subcategory":"Surveying",
            "type":"Services"
        }
    ],
    "sg:phone":"+32 81 74 39 74",
    "sg:postcode":"5000",
    "sg:province":"Namur",
    "sg:tags":[
        "surveyor",
        "land"
    ],
    "wof:name":"Delcorde J",
    "wof:placetype":"venue"
},
  "geometry": {"coordinates":[4.8546590805,50.4645957947],"type":"Point"}
}