{
  "type": "Feature",
  "properties": {
    "addr:full":"Chauss\u00e9e D'enghien 1 Silly (hoves) Hainaut 7830",
    "addr:housenumber":"1",
    "addr:postcode":"7830",
    "addr:street":"Chausse\u0301E D'Enghien",
    "iso:country":"BE",
    "sg:address":"Chauss\u00e9e D'enghien 1",
    "sg:city":"Silly (hoves)",
    "sg:classifiers":[
        {
            "category":"Farming",
            "subcategory":"Livestock Farm",
            "type":"Manufacturing & Wholesale Goods"
        }
    ],
    "sg:phone":"+32 2 395 64 15",
    "sg:postcode":"7830",
    "sg:province":"Hainaut",
    "sg:tags":[
        "stud"
    ],
    "wof:name":"Gombeer-barbieux",
    "wof:placetype":"venue"
},
  "geometry": {"coordinates":[4.0349898338,50.671787262],"type":"Point"}
}