{
  "type": "Feature",
  "properties": {
    "iso:country":"BE",
    "sg:address":"Neuringen 105",
    "sg:city":"Ninove (denderwindeke)",
    "sg:classifiers":[
        {
            "category":"Farming",
            "subcategory":"Livestock Farm",
            "type":"Manufacturing & Wholesale Goods"
        }
    ],
    "sg:phone":"+32 54 33 35 25",
    "sg:postcode":"9400",
    "sg:province":"Oost-Vlaanderen",
    "sg:tags":[
        "buyer"
    ],
    "wof:name":"Coppens H",
    "wof:placetype":"venue"
},
  "geometry": {"coordinates":[4.0145401955,50.8044395447],"type":"Point"}
}