{
  "type": "Feature",
  "properties": {
    "addr:full":"Kuipersberg 8 Bertem Vlaams-Brabant 3060",
    "addr:housenumber":"8",
    "addr:postcode":"3060",
    "addr:street":"Kuipersberg",
    "iso:country":"BE",
    "sg:address":"Kuipersberg 8",
    "sg:city":"Bertem",
    "sg:classifiers":[
        {
            "category":"Health Services",
            "subcategory":"Nursing And Care Facility",
            "type":"Services"
        }
    ],
    "sg:phone":"+32 16 49 04 75",
    "sg:postcode":"3060",
    "sg:province":"Vlaams-Brabant",
    "sg:tags":[
        "home"
    ],
    "wof:name":"Swings Ingrid",
    "wof:placetype":"venue"
},
  "geometry": {"coordinates":[4.6092782021,50.8589286804],"type":"Point"}
}