{
  "type": "Feature",
  "properties": {
    "addr:full":"Floris Primsstraat 1 Grobbendonk Antwerpen 2280",
    "addr:housenumber":"1",
    "addr:postcode":"2280",
    "addr:street":"Floris Primsstraat",
    "iso:country":"BE",
    "sg:address":"Floris Primsstraat 1",
    "sg:city":"Grobbendonk",
    "sg:orig_category":"Antiquit\u00e9s",
    "sg:phone":"+32 14 51 32 30",
    "sg:postcode":"2280",
    "sg:province":"Antwerpen",
    "wof:name":"Gidwi",
    "wof:placetype":"venue"
},
  "geometry": {"coordinates":[4.7255520821,51.1950759888],"type":"Point"}
}