{
  "type": "Feature",
  "properties": {
    "addr:full":"Zwaarveld 73a Hamme Oost-Vlaanderen 9220",
    "addr:housenumber":"73a",
    "addr:postcode":"9220",
    "addr:street":"Zwaarveld",
    "iso:country":"BE",
    "sg:address":"Zwaarveld 73a",
    "sg:city":"Hamme",
    "sg:classifiers":[
        {
            "category":"Building & Trades",
            "subcategory":"Construction",
            "type":"Services"
        }
    ],
    "sg:phone":"+32 52 21 85 10",
    "sg:postcode":"9220",
    "sg:province":"Oost-Vlaanderen",
    "sg:tags":[
        "installation",
        "-",
        "central",
        "heating"
    ],
    "wof:name":"Matthijssens",
    "wof:placetype":"venue"
},
  "geometry": {"coordinates":[4.1336789131,51.0737342834],"type":"Point"}
}