{
  "type": "Feature",
  "properties": {
    "iso:country":"BE",
    "sg:address":"Rue Marcel Hubert 2",
    "sg:city":"Eghezee",
    "sg:orig_category":"Maisons de repos and r\u00e9sidences",
    "sg:phone":"+32 81 51 23 01",
    "sg:postcode":"5310",
    "sg:province":"Namur",
    "wof:name":"Mais. Repos Jours Heureux",
    "wof:placetype":"venue"
},
  "geometry": {"coordinates":[4.8995819092,50.5774841309],"type":"Point"}
}