{
  "type": "Feature",
  "properties": {
    "addr:full":"2 Rue Potagere Brussels Bruxelles-Capitale 1210",
    "addr:housenumber":"2",
    "addr:postcode":"1210",
    "addr:street":"Rue Potagere",
    "iso:country":"BE",
    "sg:address":"2 Rue Potagere",
    "sg:city":"Brussels",
    "sg:classifiers":[
        {
            "category":"Shopping",
            "subcategory":"Computers & Home Electronics",
            "type":"Retail Goods"
        }
    ],
    "sg:phone":"+32 2 223 07 24",
    "sg:postcode":"1210",
    "sg:province":"Bruxelles-Capitale",
    "sg:tags":[
        "chamber",
        "commerce"
    ],
    "wof:name":"Chamber Of Commerce Belgium Luxembourg South East Europe",
    "wof:placetype":"venue"
},
  "geometry": {"coordinates":[4.3734397888,50.8554992676],"type":"Point"}
}