{
  "type": "Feature",
  "properties": {
    "iso:country":"BE",
    "sg:address":"Veestraat 34",
    "sg:city":"Vosselaar",
    "sg:classifiers":[
        {
            "category":"Arena",
            "subcategory":"Sports Club",
            "type":"Entertainment"
        }
    ],
    "sg:phone":"+32 14 61 66 98",
    "sg:postcode":"2350",
    "sg:province":"Antwerpen",
    "sg:tags":[
        "de"
    ],
    "wof:name":"Vosselaarse T.c.",
    "wof:placetype":"venue"
},
  "geometry": {"coordinates":[4.8837537766,51.3072128296],"type":"Point"}
}