{
  "type": "Feature",
  "properties": {
    "addr:full":"Rue De L'arayou 65 Binche Hainaut 7130",
    "addr:housenumber":"65",
    "addr:postcode":"7130",
    "addr:street":"Rue De L'Arayou",
    "iso:country":"BE",
    "sg:address":"Rue De L'arayou 65",
    "sg:city":"Binche",
    "sg:orig_category":"Non-Classified Establishments",
    "sg:phone":"+32 64 33 21 36",
    "sg:postcode":"7130",
    "sg:province":"Hainaut",
    "wof:name":"Lizon J",
    "wof:placetype":"venue"
},
  "geometry": {"coordinates":[4.1703438759,50.4078865051],"type":"Point"}
}