{
  "type": "Feature",
  "properties": {
    "addr:full":"Oscar Van Kesbeeckstraat 44 Mechelen Antwerpen 2800",
    "addr:housenumber":"44",
    "addr:postcode":"2800",
    "addr:street":"Oscar Van Kesbeeckstraat",
    "iso:country":"BE",
    "sg:address":"Oscar Van Kesbeeckstraat 44",
    "sg:city":"Mechelen",
    "sg:classifiers":[
        {
            "category":"Health Services",
            "subcategory":"Doctor",
            "type":"Services"
        }
    ],
    "sg:phone":"+32 494 80 68 33",
    "sg:postcode":"2800",
    "sg:province":"Antwerpen",
    "sg:tags":[
        "medicinephysicians",
        "surgeon"
    ],
    "wof:name":"Bennasser Farid",
    "wof:placetype":"venue"
},
  "geometry": {"coordinates":[4.4736270905,51.0380783081],"type":"Point"}
}