{
  "type": "Feature",
  "properties": {
    "addr:full":"Rue Chantraine 1 Villers-le-bouillet (warnant-dreye) Li\u00e8ge 4530",
    "addr:housenumber":"1",
    "addr:postcode":"4530",
    "addr:street":"Rue Chantraine;Warnant-Dreye",
    "iso:country":"BE",
    "sg:address":"Rue Chantraine 1",
    "sg:city":"Villers-le-bouillet (warnant-dreye)",
    "sg:classifiers":[
        {
            "category":"Autos & Motor Vehicles",
            "subcategory":"Automobile Sales",
            "type":"Retail Goods"
        }
    ],
    "sg:phone":"+32 19 56 72 97",
    "sg:postcode":"4530",
    "sg:province":"Li\u00e8ge",
    "sg:tags":[
        "motorhomes",
        "accessory"
    ],
    "wof:name":"Dallemagne Motorhomes",
    "wof:placetype":"venue"
},
  "geometry": {"coordinates":[5.2022929192,50.6017341614],"type":"Point"}
}