{
  "type": "Feature",
  "properties": {
    "addr:full":"Dikkebusseweg 5 Ieper West-Vlaanderen 8900",
    "addr:housenumber":"5",
    "addr:postcode":"8900",
    "addr:street":"Dikkebusseweg",
    "iso:country":"BE",
    "sg:address":"Dikkebusseweg 5",
    "sg:city":"Ieper",
    "sg:classifiers":[
        {
            "category":"Cafe",
            "type":"Food & Drink"
        }
    ],
    "sg:phone":"+32 57 21 87 34",
    "sg:postcode":"8900",
    "sg:province":"West-Vlaanderen",
    "sg:tags":[
        "caf\u00e9s"
    ],
    "wof:name":"Caf\u00c9 De Statie",
    "wof:placetype":"venue"
},
  "geometry": {"coordinates":[2.8775289059,50.8458595276],"type":"Point"}
}