{
  "type": "Feature",
  "properties": {
    "addr:full":"Eenmeilaan 108 Leuven (kessel-lo) Vlaams-Brabant 3010",
    "addr:housenumber":"108",
    "addr:postcode":"3010",
    "addr:street":"Eenmeilaan",
    "iso:country":"BE",
    "sg:address":"Eenmeilaan 108",
    "sg:city":"Leuven (kessel-lo)",
    "sg:classifiers":[
        {
            "category":"Retail",
            "subcategory":"Driving School",
            "type":"Services"
        }
    ],
    "sg:phone":"+32 16 25 39 40",
    "sg:postcode":"3010",
    "sg:province":"Vlaams-Brabant",
    "sg:tags":[
        "automobile",
        "officially",
        "-",
        "recognized"
    ],
    "wof:name":"Adviesbureau Voor Rijvaardigheid",
    "wof:placetype":"venue"
},
  "geometry": {"coordinates":[4.7304501534,50.889755249],"type":"Point"}
}