{
  "type": "Feature",
  "properties": {
    "iso:country":"BE",
    "sg:address":"Zi",
    "sg:city":"Clermont-sous-huy",
    "sg:orig_category":"Metallurgy and Metalworking Steels and metals Transport - related services Transport services",
    "sg:phone":"+32 4 275 82 11",
    "sg:postcode":"4480",
    "sg:province":"Li\u00e8ge",
    "wof:name":"Intramet Nv Sa",
    "wof:placetype":"venue"
},
  "geometry": {"coordinates":[5.3854050636,50.5656242371],"type":"Point"}
}