{
  "type": "Feature",
  "properties": {
    "addr:full":"Gemeentestraat 63 Lubbeek Vlaams-Brabant 3210",
    "addr:housenumber":"63",
    "addr:postcode":"3210",
    "addr:street":"Gemeentestraat",
    "iso:country":"BE",
    "sg:address":"Gemeentestraat 63",
    "sg:city":"Lubbeek",
    "sg:classifiers":[
        {
            "category":"Cafe",
            "type":"Food & Drink"
        }
    ],
    "sg:phone":"+32 16 62 27 07",
    "sg:postcode":"3210",
    "sg:province":"Vlaams-Brabant",
    "sg:tags":[
        "caf\u00e9s"
    ],
    "wof:name":"Duivenlokaal",
    "wof:placetype":"venue"
},
  "geometry": {"coordinates":[4.7742099762,50.8933334351],"type":"Point"}
}