{
  "type": "Feature",
  "properties": {
    "addr:full":"Antwerpseweg 64 Beerse Antwerpen 2340",
    "addr:housenumber":"64",
    "addr:postcode":"2340",
    "addr:street":"Antwerpseweg",
    "iso:country":"BE",
    "sg:address":"Antwerpseweg 64",
    "sg:city":"Beerse",
    "sg:orig_category":"Bars Dancings and nachtclubs Erotische Etablissementen Erotische- and Escortediensten",
    "sg:phone":"+32 14 61 04 61",
    "sg:postcode":"2340",
    "sg:province":"Antwerpen",
    "wof:name":"The Saloon",
    "wof:placetype":"venue"
},
  "geometry": {"coordinates":[4.8283729553,51.3065872192],"type":"Point"}
}