{
  "type": "Feature",
  "properties": {
    "addr:full":"Turnhoutsebaan 46 Tessenderlo Limburg 3980",
    "addr:housenumber":"46",
    "addr:postcode":"3980",
    "addr:street":"Turnhoutsebaan",
    "iso:country":"BE",
    "sg:address":"Turnhoutsebaan 46",
    "sg:city":"Tessenderlo",
    "sg:orig_category":"Studios photographiques",
    "sg:phone":"+32 13 78 15 44",
    "sg:postcode":"3980",
    "sg:province":"Limburg",
    "wof:name":"Phot'things",
    "wof:placetype":"venue"
},
  "geometry": {"coordinates":[5.011785984,51.0341911316],"type":"Point"}
}