{
  "type": "Feature",
  "properties": {
    "addr:full":"Hoveniersstraat 64a Aalst Oost-Vlaanderen 9300",
    "addr:housenumber":"64a",
    "addr:postcode":"9300",
    "addr:street":"Hoveniersstraat",
    "iso:country":"BE",
    "sg:address":"Hoveniersstraat 64a",
    "sg:city":"Aalst",
    "sg:classifiers":[
        {
            "category":"Home & Garden",
            "subcategory":"Home Furnishings",
            "type":"Retail Goods"
        }
    ],
    "sg:postcode":"9300",
    "sg:province":"Oost-Vlaanderen",
    "sg:tags":[
        "curtain",
        "-",
        "fixture"
    ],
    "wof:name":"Huis Mertens",
    "wof:placetype":"venue"
},
  "geometry": {"coordinates":[4.0458130836,50.9430885315],"type":"Point"}
}