{
  "type": "Feature",
  "properties": {
    "iso:country":"BE",
    "sg:address":"Otegemstraat 122",
    "sg:city":"Deerlijk",
    "sg:orig_category":"Rev\u00eatements de sols and murs",
    "sg:phone":"+32 56 77 34 83",
    "sg:postcode":"8540",
    "sg:province":"West-Vlaanderen",
    "wof:name":"Fa. Parketec",
    "wof:placetype":"venue"
},
  "geometry": {"coordinates":[3.3912398815,50.8225097656],"type":"Point"}
}