{
  "type": "Feature",
  "properties": {
    "addr:full":"En Grande Foxhalle 160 Herstal Li\u00e8ge 4040",
    "addr:housenumber":"160",
    "addr:postcode":"4040",
    "iso:country":"BE",
    "sg:address":"En Grande Foxhalle 160",
    "sg:city":"Herstal",
    "sg:orig_category":"Accumulating Roller Conveyors",
    "sg:phone":"+32 4 264 04 38",
    "sg:postcode":"4040",
    "sg:province":"Li\u00e8ge",
    "wof:name":"Marganne S.a.",
    "wof:placetype":"venue"
},
  "geometry": {"coordinates":[5.6192851067,50.6643371582],"type":"Point"}
}