{
  "type": "Feature",
  "properties": {
    "iso:country":"BE",
    "sg:address":"Beiaardstraat 3",
    "sg:city":"Lendelede",
    "sg:classifiers":[
        {
            "category":"Farming",
            "subcategory":"Farm & Veterinary Services",
            "type":"Manufacturing & Wholesale Goods"
        }
    ],
    "sg:phone":"+32 56 35 72 95",
    "sg:postcode":"8860",
    "sg:province":"West-Vlaanderen",
    "sg:tags":[
        "agricultural",
        "contractor"
    ],
    "wof:name":"Huysentruyt M",
    "wof:placetype":"venue"
},
  "geometry": {"coordinates":[3.2215120792,50.8754997253],"type":"Point"}
}