{
  "type": "Feature",
  "properties": {
    "iso:country":"BE",
    "sg:address":"Elenestraat 295",
    "sg:city":"Zottegem (elene - Oombergen)",
    "sg:classifiers":[
        {
            "category":"Shopping",
            "subcategory":"Clothing, Apparel, & Fashions",
            "type":"Retail Goods"
        }
    ],
    "sg:phone":"+32 9 360 15 67",
    "sg:postcode":"9620",
    "sg:province":"Oost-Vlaanderen",
    "sg:tags":[
        "underwear",
        "lingerie",
        "-"
    ],
    "wof:name":"De Cuyper-coppens",
    "wof:placetype":"venue"
},
  "geometry": {"coordinates":[3.8086929321,50.8774681091],"type":"Point"}
}