{
  "type": "Feature",
  "properties": {
    "addr:full":"Rue De Tr\u00e8ves 49 Bruxelles (etterbeek) Bruxelles-Capitale 1040",
    "addr:housenumber":"49",
    "addr:postcode":"1040",
    "addr:street":"Rue De Tre\u0300Ves",
    "iso:country":"BE",
    "sg:address":"Rue De Tr\u00e8ves 49",
    "sg:city":"Bruxelles (etterbeek)",
    "sg:classifiers":[
        {
            "category":"Professional",
            "subcategory":"Engineering",
            "type":"Services"
        }
    ],
    "sg:phone":"+32 2 280 19 46",
    "sg:postcode":"1040",
    "sg:province":"Bruxelles-Capitale",
    "sg:tags":[
        "-"
    ],
    "wof:name":"N T U-bruxelles",
    "wof:placetype":"venue"
},
  "geometry": {"coordinates":[4.3753848076,50.842792511],"type":"Point"}
}