{
  "type": "Feature",
  "properties": {
    "addr:full":"Kasteelstraat 206 Buggenhout Oost-Vlaanderen 9255",
    "addr:housenumber":"206",
    "addr:postcode":"9255",
    "addr:street":"Kasteelstraat",
    "iso:country":"BE",
    "sg:address":"Kasteelstraat 206",
    "sg:city":"Buggenhout",
    "sg:orig_category":"Marketingbureaus",
    "sg:phone":"+32 52 33 72 85",
    "sg:postcode":"9255",
    "sg:province":"Oost-Vlaanderen",
    "wof:name":"T For G",
    "wof:placetype":"venue"
},
  "geometry": {"coordinates":[4.2135372162,50.9917221069],"type":"Point"}
}