{
  "type": "Feature",
  "properties": {
    "iso:country":"BE",
    "sg:address":"Rue De Neerpede 815",
    "sg:city":"Bruxelles (anderlecht)",
    "sg:orig_category":"Fiduciairies",
    "sg:phone":"+32 2 528 08 14",
    "sg:postcode":"1070",
    "sg:province":"Bruxelles-Capitale",
    "wof:name":"Fiduciaire D.t.a. Sprl",
    "wof:placetype":"venue"
},
  "geometry": {"coordinates":[4.2688579559,50.8280982971],"type":"Point"}
}