{
  "type": "Feature",
  "properties": {
    "addr:full":"Rue Emmmanuel Hiel 41 Schaarbeek/schaerbeek Bruxelles-Capitale 1030",
    "addr:housenumber":"41",
    "addr:postcode":"1030",
    "addr:street":"Rue Emmmanuel Hiel",
    "iso:country":"BE",
    "sg:address":"Rue Emmmanuel Hiel 41",
    "sg:city":"Schaarbeek/schaerbeek",
    "sg:orig_category":"Agences de presse",
    "sg:phone":"+32 2 245 66 52",
    "sg:postcode":"1030",
    "sg:province":"Bruxelles-Capitale",
    "wof:name":"Joris Hintjens",
    "wof:placetype":"venue"
},
  "geometry": {"coordinates":[4.3712539673,50.8660469055],"type":"Point"}
}