{
  "type": "Feature",
  "properties": {
    "iso:country":"BE",
    "sg:address":"Jaagpad 4",
    "sg:city":"Ieper",
    "sg:orig_category":"Afval and schroot Gh",
    "sg:phone":"+32 57 20 02 02",
    "sg:postcode":"8900",
    "sg:province":"West-Vlaanderen",
    "wof:name":"Degels-metal",
    "wof:placetype":"venue"
},
  "geometry": {"coordinates":[2.8820159435,50.8696861267],"type":"Point"}
}