{
  "type": "Feature",
  "properties": {
    "addr:full":"Aalstersesteenweg 397a Ninove Oost-Vlaanderen 9400",
    "addr:housenumber":"397a",
    "addr:postcode":"9400",
    "addr:street":"Aalstersesteenweg",
    "iso:country":"BE",
    "sg:address":"Aalstersesteenweg 397a",
    "sg:city":"Ninove",
    "sg:orig_category":"Airconditioning and ventilatie Loodgieterij and centrale verwarming Gh Loodgieterij, verwarming and ",
    "sg:phone":"+32 54 33 58 35",
    "sg:postcode":"9400",
    "sg:province":"Oost-Vlaanderen",
    "wof:name":"Rosenberg Belgium",
    "wof:placetype":"venue"
},
  "geometry": {"coordinates":[4.0348000526,50.8542289734],"type":"Point"}
}