{
  "type": "Feature",
  "properties": {
    "iso:country":"BE",
    "sg:address":"Dries 2",
    "sg:city":"Sint-niklaas",
    "sg:orig_category":"Banken and kredietinstellingen",
    "sg:phone":"+32 3 772 39 69",
    "sg:postcode":"9112",
    "sg:province":"Oost-Vlaanderen",
    "wof:name":"Kbc",
    "wof:placetype":"venue"
},
  "geometry": {"coordinates":[4.044479847,51.1562843323],"type":"Point"}
}