{
  "type": "Feature",
  "properties": {
    "addr:full":"Humbeekstraat 29a Meise Vlaams-Brabant 1860",
    "addr:housenumber":"29a",
    "addr:postcode":"1860",
    "addr:street":"Humbeekstraat",
    "iso:country":"BE",
    "sg:address":"Humbeekstraat 29a",
    "sg:city":"Meise",
    "sg:classifiers":[
        {
            "category":"Retail",
            "subcategory":"Event Space",
            "type":"Services"
        }
    ],
    "sg:phone":"+32 2 269 93 12",
    "sg:postcode":"1860",
    "sg:province":"Vlaams-Brabant",
    "sg:tags":[
        "rental",
        "-",
        "hall"
    ],
    "wof:name":"Traiteur Hutse Actual Concept",
    "wof:placetype":"venue"
},
  "geometry": {"coordinates":[4.3407139778,50.9445114136],"type":"Point"}
}