{
  "type": "Feature",
  "properties": {
    "addr:full":"Rue Puissant 2 Charleroi (jumet) Hainaut 6040",
    "addr:housenumber":"2",
    "addr:postcode":"6040",
    "addr:street":"Rue Puissant",
    "iso:country":"BE",
    "sg:address":"Rue Puissant 2",
    "sg:city":"Charleroi (jumet)",
    "sg:classifiers":[
        {
            "category":"Food & Beverages",
            "subcategory":"Groceries & Convenience Stores",
            "type":"Retail Goods"
        }
    ],
    "sg:phone":"+32 71 34 55 76",
    "sg:postcode":"6040",
    "sg:province":"Hainaut",
    "sg:tags":[
        "grocer"
    ],
    "wof:name":"Jardinet (le)",
    "wof:placetype":"venue"
},
  "geometry": {"coordinates":[4.4383997917,50.4390830994],"type":"Point"}
}