{
  "type": "Feature",
  "properties": {
    "addr:full":"Vladslostraat 9a Diksmuide West-Vlaanderen 8600",
    "addr:housenumber":"9a",
    "addr:postcode":"8600",
    "addr:street":"Vladslostraat",
    "iso:country":"BE",
    "sg:address":"Vladslostraat 9a",
    "sg:city":"Diksmuide",
    "sg:classifiers":[
        {
            "category":"Park",
            "subcategory":"National",
            "type":"Public Place"
        }
    ],
    "sg:phone":"+32 51 50 41 15",
    "sg:postcode":"8600",
    "sg:province":"West-Vlaanderen",
    "sg:tags":[
        "recreation"
    ],
    "wof:name":"Attracties Dewilde A",
    "wof:placetype":"venue"
},
  "geometry": {"coordinates":[2.902780056,51.0307884216],"type":"Point"}
}