{
  "type": "Feature",
  "properties": {
    "addr:full":"Rue Des Trieux 28 La Louvi\u00e8re (houdeng-goegnies) Hainaut 7110",
    "addr:housenumber":"28",
    "addr:postcode":"7110",
    "addr:street":"Rue Des Trieux",
    "iso:country":"BE",
    "sg:address":"Rue Des Trieux 28",
    "sg:city":"La Louvi\u00e8re (houdeng-goegnies)",
    "sg:classifiers":[
        {
            "category":"Cafe",
            "type":"Food & Drink"
        }
    ],
    "sg:phone":"+32 64 22 49 59",
    "sg:postcode":"7110",
    "sg:province":"Hainaut",
    "sg:tags":[
        "snack-bars"
    ],
    "wof:name":"Petit Creux (au)",
    "wof:placetype":"venue"
},
  "geometry": {"coordinates":[4.1505050659,50.4826698303],"type":"Point"}
}