{
  "type": "Feature",
  "properties": {
    "addr:full":"Marais Garette 12 Flobecq Hainaut 7880",
    "addr:housenumber":"12",
    "addr:postcode":"7880",
    "addr:street":"Garette;Hainaut",
    "iso:country":"BE",
    "sg:address":"Marais Garette 12",
    "sg:city":"Flobecq",
    "sg:classifiers":[
        {
            "category":"Farming",
            "subcategory":"Fish & Marine Products",
            "type":"Manufacturing & Wholesale Goods"
        }
    ],
    "sg:phone":"+32 68 44 87 95",
    "sg:postcode":"7880",
    "sg:province":"Hainaut",
    "sg:tags":[
        "equipment",
        "fishery"
    ],
    "wof:name":"Bras Pascal",
    "wof:placetype":"venue"
},
  "geometry": {"coordinates":[3.744879961,50.7414283752],"type":"Point"}
}