{
  "type": "Feature",
  "properties": {
    "addr:full":"Molendries 15 Bilzen Limburg 3740",
    "addr:housenumber":"15",
    "addr:postcode":"3740",
    "addr:street":"Molendries",
    "iso:country":"BE",
    "sg:address":"Molendries 15",
    "sg:city":"Bilzen",
    "sg:orig_category":"Sportclubs",
    "sg:phone":"+32 89 41 39 70",
    "sg:postcode":"3740",
    "sg:province":"Limburg",
    "wof:name":"Ko Budo",
    "wof:placetype":"venue"
},
  "geometry": {"coordinates":[5.5695328712,50.8810081482],"type":"Point"}
}