{
  "type": "Feature",
  "properties": {
    "iso:country":"BE",
    "sg:address":"Rue Du Prince Royal 7",
    "sg:city":"Bruxelles (ixelles)",
    "sg:classifiers":[
        {
            "category":"Shopping",
            "subcategory":"Jewelry",
            "type":"Retail Goods"
        }
    ],
    "sg:phone":"+32 2 511 41 78",
    "sg:postcode":"1050",
    "sg:province":"Bruxelles-Capitale",
    "sg:tags":[
        "jeweller",
        "-"
    ],
    "wof:name":"Touijar",
    "wof:placetype":"venue"
},
  "geometry": {"coordinates":[4.3631181717,50.8353462219],"type":"Point"}
}