{
  "type": "Feature",
  "properties": {
    "iso:country":"BE",
    "sg:address":"Place De Belle Vue 3",
    "sg:city":"Aiseau-presles (presles)",
    "sg:classifiers":[
        {
            "category":"Arts & Performance",
            "subcategory":"Theater",
            "type":"Entertainment"
        }
    ],
    "sg:phone":"+32 71 40 44 55",
    "sg:postcode":"6250",
    "sg:province":"Hainaut",
    "sg:tags":[
        "theatrical",
        "agency"
    ],
    "wof:name":"B D Productions Sc",
    "wof:placetype":"venue"
},
  "geometry": {"coordinates":[4.5863847733,50.40990448],"type":"Point"}
}