{
  "type": "Feature",
  "properties": {
    "addr:full":"Wijnstokstraat 10 Elsene/ixelles Bruxelles-Capitale 1050",
    "addr:housenumber":"10",
    "addr:postcode":"1050",
    "addr:street":"Wijnstokstraat",
    "iso:country":"BE",
    "sg:address":"Wijnstokstraat 10",
    "sg:city":"Elsene/ixelles",
    "sg:orig_category":"Artsen and specialisten",
    "sg:phone":"+32 2 660 44 60",
    "sg:postcode":"1050",
    "sg:province":"Bruxelles-Capitale",
    "wof:name":"Lionel Van Maldergem",
    "wof:placetype":"venue"
},
  "geometry": {"coordinates":[4.3932909966,50.8089408875],"type":"Point"}
}