{
  "type": "Feature",
  "properties": {
    "addr:full":"Hondzochtstraat 49 Pepingen (bellingen) Vlaams-Brabant 1674",
    "addr:housenumber":"49",
    "addr:postcode":"1674",
    "addr:street":"Hondzochtstraat",
    "iso:country":"BE",
    "sg:address":"Hondzochtstraat 49",
    "sg:city":"Pepingen (bellingen)",
    "sg:classifiers":[
        {
            "category":"Personal",
            "subcategory":"Beauty Salon",
            "type":"Services"
        }
    ],
    "sg:phone":"+32 2 360 21 49",
    "sg:postcode":"1674",
    "sg:province":"Vlaams-Brabant",
    "sg:tags":[
        "lady",
        "-",
        "hairdressing"
    ],
    "wof:name":"Christiane",
    "wof:placetype":"venue"
},
  "geometry": {"coordinates":[4.160569191,50.7273979187],"type":"Point"}
}