{
  "type": "Feature",
  "properties": {
    "addr:full":"Rue Du Levant 1 Box 3 Nivelles Brabant Wallon 1400",
    "addr:housenumber":"1;3",
    "addr:postcode":"1400",
    "addr:street":"Rue Du Levant;Box",
    "iso:country":"BE",
    "sg:address":"Rue Du Levant 1 Box 3",
    "sg:city":"Nivelles",
    "sg:classifiers":[
        {
            "category":"Building & Trades",
            "subcategory":"Construction",
            "type":"Services"
        }
    ],
    "sg:phone":"+32 67 84 17 42",
    "sg:postcode":"1400",
    "sg:province":"Brabant Wallon",
    "sg:tags":[
        "carpenter"
    ],
    "wof:name":"L.m. Menuiserie",
    "wof:placetype":"venue"
},
  "geometry": {"coordinates":[4.3340320587,50.5896949768],"type":"Point"}
}