{
  "type": "Feature",
  "properties": {
    "iso:country":"BE",
    "sg:address":"Granges 84",
    "sg:city":"Engis",
    "sg:orig_category":"Elektrische installaties voor woningen Herstelling aan huis van huishoudartikelen Loodgieterij, verw",
    "sg:phone":"+32 4 275 24 14",
    "sg:postcode":"4480",
    "sg:province":"Li\u00e8ge",
    "wof:name":"Bourguignon Et Fils",
    "wof:placetype":"venue"
},
  "geometry": {"coordinates":[5.4026389122,50.5567893982],"type":"Point"}
}