{
  "type": "Feature",
  "properties": {
    "addr:full":"Chauss\u00e9e De Louvain 497 Bruxelles (schaerbeek) Bruxelles-Capitale 1030",
    "addr:housenumber":"497",
    "addr:postcode":"1030",
    "addr:street":"Chausse\u0301E De Louvain",
    "iso:country":"BE",
    "sg:address":"Chauss\u00e9e De Louvain 497",
    "sg:city":"Bruxelles (schaerbeek)",
    "sg:classifiers":[
        {
            "category":"Professional",
            "subcategory":"Testing Lab",
            "type":"Services"
        }
    ],
    "sg:phone":"+32 2 735 82 56",
    "sg:postcode":"1030",
    "sg:province":"Bruxelles-Capitale",
    "sg:tags":[
        "chemist"
    ],
    "wof:name":"Collinge M",
    "wof:placetype":"venue"
},
  "geometry": {"coordinates":[4.3970022202,50.8548240662],"type":"Point"}
}