{
  "type": "Feature",
  "properties": {
    "iso:country":"BE",
    "sg:address":"Zagerijstraat 23",
    "sg:city":"Brecht",
    "sg:orig_category":"Diverse bouwafwerking and reiniging Installatie van houten of kunststof schrijnwerk Woningbouw",
    "sg:phone":"+32 3 633 29 00",
    "sg:postcode":"2960",
    "sg:province":"Antwerpen",
    "wof:name":"Vochten Gebroeders",
    "wof:placetype":"venue"
},
  "geometry": {"coordinates":[4.5511817932,51.2993583679],"type":"Point"}
}