{
  "type": "Feature",
  "properties": {
    "iso:country":"BE",
    "sg:address":"Chauss\u00c9e De Mons 288",
    "sg:city":"Tubize",
    "sg:orig_category":"Notaires",
    "sg:phone":"+32 2 390 02 18",
    "sg:postcode":"1480",
    "sg:province":"Brabant Wallon",
    "wof:name":"Etienne De Rycke",
    "wof:placetype":"venue"
},
  "geometry": {"coordinates":[4.1948809624,50.684211731],"type":"Point"}
}