{
  "type": "Feature",
  "properties": {
    "addr:full":"Dr\u00e8ve Des Br\u00fbl\u00e9s 59 Bruxelles (woluwe-saint-pierre) Bruxelles-Capitale 1150",
    "addr:housenumber":"59",
    "addr:postcode":"1150",
    "addr:street":"Dre\u0300Ve Des Bru\u0302Le\u0301S",
    "iso:country":"BE",
    "sg:address":"Dr\u00e8ve Des Br\u00fbl\u00e9s 59",
    "sg:city":"Bruxelles (woluwe-saint-pierre)",
    "sg:classifiers":[
        {
            "category":"Arena",
            "subcategory":"Sports Club",
            "type":"Entertainment"
        }
    ],
    "sg:phone":"+32 2 770 00 66",
    "sg:postcode":"1150",
    "sg:province":"Bruxelles-Capitale",
    "wof:name":"Or\u00e9e T.h.b.",
    "wof:placetype":"venue"
},
  "geometry": {"coordinates":[4.458106041,50.8223381042],"type":"Point"}
}