{
  "type": "Feature",
  "properties": {
    "addr:full":"Coenraedt Keynslaan 2 Herent (winksele) Vlaams-Brabant 3020",
    "addr:housenumber":"2",
    "addr:postcode":"3020",
    "addr:street":"Coenraedt Keynslaan",
    "iso:country":"BE",
    "sg:address":"Coenraedt Keynslaan 2",
    "sg:city":"Herent (winksele)",
    "sg:classifiers":[
        {
            "category":"Personal",
            "subcategory":"Beauty Salon",
            "type":"Services"
        }
    ],
    "sg:phone":"+32 16 29 53 36",
    "sg:postcode":"3020",
    "sg:province":"Vlaams-Brabant",
    "wof:name":"Doms Reinhilde",
    "wof:placetype":"venue"
},
  "geometry": {"coordinates":[4.6641597748,50.8852615356],"type":"Point"}
}