{
  "type": "Feature",
  "properties": {
    "addr:full":"Hoogstraat 74 Deerlijk West-Vlaanderen 8540",
    "addr:housenumber":"74",
    "addr:postcode":"8540",
    "addr:street":"Hoogstraat",
    "iso:country":"BE",
    "sg:address":"Hoogstraat 74",
    "sg:city":"Deerlijk",
    "sg:orig_category":"Banken and kredietinstellingen",
    "sg:phone":"+32 56 71 14 94",
    "sg:postcode":"8540",
    "sg:province":"West-Vlaanderen",
    "wof:name":"Bacob",
    "wof:placetype":"venue"
},
  "geometry": {"coordinates":[3.3560960293,50.8547515869],"type":"Point"}
}