{
  "type": "Feature",
  "properties": {
    "addr:full":"Ter Rivierenwal 6 Bree Limburg 3960",
    "addr:housenumber":"6",
    "addr:postcode":"3960",
    "addr:street":"Ter Rivierenwal",
    "iso:country":"BE",
    "sg:address":"Ter Rivierenwal 6",
    "sg:city":"Bree",
    "sg:classifiers":[
        {
            "category":"Shopping",
            "subcategory":"Clothing, Apparel, & Fashions",
            "type":"Retail Goods"
        }
    ],
    "sg:phone":"+32 89 47 36 08",
    "sg:postcode":"3960",
    "sg:province":"Limburg",
    "sg:tags":[
        "hosiery"
    ],
    "wof:name":"Biligi",
    "wof:placetype":"venue"
},
  "geometry": {"coordinates":[5.5951099396,51.1405181885],"type":"Point"}
}