{
  "type": "Feature",
  "properties": {
    "iso:country":"BE",
    "sg:address":"Honzebroekstraat 57",
    "sg:city":"Roeselare",
    "sg:classifiers":[
        {
            "category":"Wholesale",
            "subcategory":"Sporting Goods",
            "type":"Manufacturing & Wholesale Goods"
        }
    ],
    "sg:phone":"+32 51 69 00 09",
    "sg:postcode":"8800",
    "sg:province":"West-Vlaanderen",
    "sg:tags":[
        "windsurfing",
        "accessory"
    ],
    "wof:name":"Surfshop Roeselare",
    "wof:placetype":"venue"
},
  "geometry": {"coordinates":[3.1140179634,50.9620933533],"type":"Point"}
}