{
  "type": "Feature",
  "properties": {
    "iso:country":"BE",
    "sg:address":"Broes Enderdik 33",
    "sg:city":"Neerpelt",
    "sg:classifiers":[
        {
            "category":"Wholesale",
            "subcategory":"Machinery & Supplies",
            "type":"Manufacturing & Wholesale Goods"
        }
    ],
    "sg:phone":"+32 11 64 84 40",
    "sg:postcode":"3910",
    "sg:province":"Limburg",
    "sg:tags":[
        "handling",
        "material",
        "-",
        "machine",
        "equipment",
        "engineering",
        "mechanical"
    ],
    "wof:name":"Heftruck Service Limburg Bvba",
    "wof:placetype":"venue"
},
  "geometry": {"coordinates":[5.4269390106,51.2388916016],"type":"Point"}
}