{
  "type": "Feature",
  "properties": {
    "addr:full":"Rue De La Clawenne 119 Herstal Li\u00e8ge 4040",
    "addr:housenumber":"119",
    "addr:postcode":"4040",
    "addr:street":"Rue De La Clawenne",
    "iso:country":"BE",
    "sg:address":"Rue De La Clawenne 119",
    "sg:city":"Herstal",
    "sg:classifiers":[
        {
            "category":"Community Center",
            "type":"Public Place"
        }
    ],
    "sg:phone":"+32 4 264 68 67",
    "sg:postcode":"4040",
    "sg:province":"Li\u00e8ge",
    "sg:tags":[
        "box",
        "juke"
    ],
    "wof:name":"Interautomatic Sa",
    "wof:placetype":"venue"
},
  "geometry": {"coordinates":[5.6363348961,50.6750984192],"type":"Point"}
}