{
  "type": "Feature",
  "properties": {
    "addr:full":"Doornstraat 12 Dilbeek Vlaams-Brabant 1700",
    "addr:housenumber":"12",
    "addr:postcode":"1700",
    "addr:street":"Doornstraat",
    "iso:country":"BE",
    "sg:address":"Doornstraat 12",
    "sg:city":"Dilbeek",
    "sg:orig_category":"R\u00e9alisation de programmes and logiciels. Agences de publicit\u00e9",
    "sg:phone":"+32 2 569 75 53",
    "sg:postcode":"1700",
    "sg:province":"Vlaams-Brabant",
    "wof:name":"Belgium Pme Diffusion",
    "wof:placetype":"venue"
},
  "geometry": {"coordinates":[4.2562818527,50.8363380432],"type":"Point"}
}