{
  "type": "Feature",
  "properties": {
    "addr:full":"Dries 58 Lede Oost-Vlaanderen 9340",
    "addr:housenumber":"58",
    "addr:postcode":"9340",
    "addr:street":"Dries",
    "iso:country":"BE",
    "sg:address":"Dries 58",
    "sg:city":"Lede",
    "sg:orig_category":"Pain, p\u00e2tisseries and confiseries",
    "sg:phone":"+32 9 369 09 40",
    "sg:postcode":"9340",
    "sg:province":"Oost-Vlaanderen",
    "wof:name":"Huis Sofie",
    "wof:placetype":"venue"
},
  "geometry": {"coordinates":[3.8914709091,50.9628715515],"type":"Point"}
}