{
  "type": "Feature",
  "properties": {
    "addr:full":"Oostrozebekestraat 7 Dentergem West-Vlaanderen 8720",
    "addr:housenumber":"7",
    "addr:postcode":"8720",
    "addr:street":"Oostrozebekestraat",
    "iso:country":"BE",
    "sg:address":"Oostrozebekestraat 7",
    "sg:city":"Dentergem",
    "sg:orig_category":"Installatie van metalen schrijnwerk",
    "sg:phone":"+32 51 63 30 73",
    "sg:postcode":"8720",
    "sg:province":"West-Vlaanderen",
    "wof:name":"Raphael De Smet",
    "wof:placetype":"venue"
},
  "geometry": {"coordinates":[3.3914880753,50.9550895691],"type":"Point"}
}