{
  "type": "Feature",
  "properties": {
    "iso:country":"BE",
    "sg:address":"Albertwal 29",
    "sg:city":"Tongeren",
    "sg:classifiers":[
        {
            "category":"Health Services",
            "subcategory":"Dentist",
            "type":"Services"
        }
    ],
    "sg:phone":"+32 12 23 27 64",
    "sg:postcode":"3700",
    "sg:province":"Limburg",
    "wof:name":"Franssen M",
    "wof:placetype":"venue"
},
  "geometry": {"coordinates":[5.460504055,50.7767982483],"type":"Point"}
}