{
  "type": "Feature",
  "properties": {
    "addr:full":"Boulvard D' Avroy 278 Liege Li\u00e8ge 4000",
    "addr:housenumber":"278",
    "addr:postcode":"4000",
    "addr:street":"Boulvard D ' Avroy",
    "iso:country":"BE",
    "sg:address":"Boulvard D' Avroy 278",
    "sg:city":"Liege",
    "sg:orig_category":"Ordinateurs and \u00e9quipement informatique. Entretien and r\u00e9parations de machines de bureau and ordinat",
    "sg:phone":"+32 4 254 22 61",
    "sg:postcode":"4000",
    "sg:province":"Li\u00e8ge",
    "wof:name":"G.i.a. Consulting",
    "wof:placetype":"venue"
},
  "geometry": {"coordinates":[5.5678458214,50.6307411194],"type":"Point"}
}