{
  "type": "Feature",
  "properties": {
    "addr:full":"Spichtestraat 24 Avelgem West-Vlaanderen 8580",
    "addr:housenumber":"24",
    "addr:postcode":"8580",
    "addr:street":"Spichtestraat",
    "iso:country":"BE",
    "sg:address":"Spichtestraat 24",
    "sg:city":"Avelgem",
    "sg:orig_category":"Airconditioning and ventilatie Winkelinrichting and handelsuitrusting Gh",
    "sg:phone":"+32 56 64 74 63",
    "sg:postcode":"8580",
    "sg:province":"West-Vlaanderen",
    "wof:name":"D D Cool",
    "wof:placetype":"venue"
},
  "geometry": {"coordinates":[3.422837019,50.7777252197],"type":"Point"}
}