{
  "type": "Feature",
  "properties": {
    "iso:country":"BE",
    "sg:address":"J. Vanzeerstraat 34",
    "sg:city":"Diest",
    "sg:orig_category":"Eleveurs and marchands de porcs",
    "sg:phone":"+32 13 66 45 59",
    "sg:postcode":"3290",
    "sg:province":"Vlaams-Brabant",
    "wof:name":"Rene Van Dijck",
    "wof:placetype":"venue"
},
  "geometry": {"coordinates":[5.0910539627,51.0379447937],"type":"Point"}
}