{
  "type": "Feature",
  "properties": {
    "addr:full":"Rue Reine Astrid 27 Sambreville Namur 5060",
    "addr:housenumber":"27",
    "addr:postcode":"5060",
    "addr:street":"Rue Reine Astrid",
    "iso:country":"BE",
    "sg:address":"Rue Reine Astrid 27",
    "sg:city":"Sambreville",
    "sg:classifiers":[
        {
            "category":"Insurance",
            "subcategory":"Insurance Agent",
            "type":"Services"
        }
    ],
    "sg:phone":"+32 71 81 81 69",
    "sg:postcode":"5060",
    "sg:province":"Namur",
    "sg:tags":[
        "verzekeringsmakelaars",
        "expert"
    ],
    "wof:name":"Bureau Chavanne",
    "wof:placetype":"venue"
},
  "geometry": {"coordinates":[4.5941910744,50.4652481079],"type":"Point"}
}