{
  "type": "Feature",
  "properties": {
    "iso:country":"BE",
    "sg:address":"Snijbos 38",
    "sg:city":"Dilbeek (groot - Bijgaarden)",
    "sg:classifiers":[
        {
            "category":"Communications",
            "type":"Services"
        }
    ],
    "sg:phone":"+32 2 522 77 30",
    "sg:postcode":"1702",
    "sg:province":"Vlaams-Brabant",
    "sg:tags":[
        "translator"
    ],
    "wof:name":"Anigee Communication",
    "wof:placetype":"venue"
},
  "geometry": {"coordinates":[4.2537541389,50.8639831543],"type":"Point"}
}