{
  "type": "Feature",
  "properties": {
    "iso:country":"BE",
    "sg:address":"Hoekje 165",
    "sg:city":"Waarschoot",
    "sg:orig_category":"Installation \u00e9lectrique r\u00e9sidentielle",
    "sg:phone":"+32 9 377 65 46",
    "sg:postcode":"9950",
    "sg:province":"Oost-Vlaanderen",
    "wof:name":"Christophe Willems",
    "wof:placetype":"venue"
},
  "geometry": {"coordinates":[3.6174819469,51.1629676819],"type":"Point"}
}