{
  "type": "Feature",
  "properties": {
    "addr:full":"Voorhout 64 Stekene Oost-Vlaanderen 9190",
    "addr:housenumber":"64",
    "addr:postcode":"9190",
    "addr:street":"Voorhout",
    "iso:country":"BE",
    "sg:address":"Voorhout 64",
    "sg:city":"Stekene",
    "sg:orig_category":"G\u00e9om\u00e8tres",
    "sg:phone":"+32 3 779 77 77",
    "sg:postcode":"9190",
    "sg:province":"Oost-Vlaanderen",
    "wof:name":"Marc Hofkens",
    "wof:placetype":"venue"
},
  "geometry": {"coordinates":[4.0688209534,51.2183685303],"type":"Point"}
}