{
  "type": "Feature",
  "properties": {
    "iso:country":"BE",
    "sg:address":"Rue Du Chapelain 142",
    "sg:city":"Ath",
    "sg:orig_category":"Rundveehouders",
    "sg:phone":"+32 68 28 28 52",
    "sg:postcode":"7800",
    "sg:province":"Hainaut",
    "wof:name":"Jean-charles Carlier",
    "wof:placetype":"venue"
},
  "geometry": {"coordinates":[3.7936449051,50.6304206848],"type":"Point"}
}