{
  "type": "Feature",
  "properties": {
    "iso:country":"BE",
    "sg:address":"Evangeliestraat 109",
    "sg:city":"Hamme",
    "sg:classifiers":[
        {
            "category":"Retail",
            "subcategory":"Auto Repair",
            "type":"Services"
        }
    ],
    "sg:phone":"+32 52 47 42 08",
    "sg:postcode":"9220",
    "sg:province":"Oost-Vlaanderen",
    "sg:tags":[
        "garage"
    ],
    "wof:name":"Chami Cars",
    "wof:placetype":"venue"
},
  "geometry": {"coordinates":[4.1208939552,51.092086792],"type":"Point"}
}