{
  "type": "Feature",
  "properties": {
    "addr:full":"Rue De La Bruy\u00c8re 157 Rixensart Brabant Wallon 1332",
    "addr:housenumber":"157",
    "addr:postcode":"1332",
    "addr:street":"Rue De La Bruye\u0300Re;Wallon",
    "iso:country":"BE",
    "sg:address":"Rue De La Bruy\u00c8re 157",
    "sg:city":"Rixensart",
    "sg:orig_category":"Software ontwikkeling and ontwerp",
    "sg:phone":"+32 2 652 04 02",
    "sg:postcode":"1332",
    "sg:province":"Brabant Wallon",
    "wof:name":"Biac",
    "wof:placetype":"venue"
},
  "geometry": {"coordinates":[4.4884037971,50.72448349],"type":"Point"}
}