{
  "type": "Feature",
  "properties": {
    "addr:full":"Rue Haute 4a Jemeppe-sur-sambre (spy) Namur 5190",
    "addr:housenumber":"4a",
    "addr:postcode":"5190",
    "addr:street":"Rue Haute",
    "iso:country":"BE",
    "sg:address":"Rue Haute 4a",
    "sg:city":"Jemeppe-sur-sambre (spy)",
    "sg:classifiers":[
        {
            "category":"Professional",
            "subcategory":"Testing Lab",
            "type":"Services"
        }
    ],
    "sg:phone":"+32 71 78 50 59",
    "sg:postcode":"5190",
    "sg:province":"Namur",
    "sg:tags":[
        "chemist"
    ],
    "wof:name":"Thiry-bronfort Sprl",
    "wof:placetype":"venue"
},
  "geometry": {"coordinates":[4.7086019516,50.4812507629],"type":"Point"}
}