{
  "type": "Feature",
  "properties": {
    "iso:country":"BE",
    "sg:address":"Pensmarkt 2",
    "sg:city":"Gent",
    "sg:classifiers":[
        {
            "category":"Professional",
            "subcategory":"Employment Agencies",
            "type":"Services"
        }
    ],
    "sg:phone":"+32 9 265 94 30",
    "sg:postcode":"9000",
    "sg:province":"Oost-Vlaanderen",
    "sg:tags":[
        "market",
        "research"
    ],
    "wof:name":"Fieldforce Bvba Bvba",
    "wof:placetype":"venue"
},
  "geometry": {"coordinates":[3.7215280533,51.0556526184],"type":"Point"}
}