{
  "type": "Feature",
  "properties": {
    "iso:country":"BE",
    "sg:address":"Avelgemstraat 37",
    "sg:city":"Zwevegem",
    "sg:classifiers":[
        {
            "category":"Shopping",
            "subcategory":"Bicycles & Sporting Goods",
            "type":"Retail Goods"
        }
    ],
    "sg:phone":"+32 56 75 61 84",
    "sg:postcode":"8550",
    "sg:province":"West-Vlaanderen",
    "sg:tags":[
        "sport",
        "-"
    ],
    "wof:name":"D'haenens Sport",
    "wof:placetype":"venue"
},
  "geometry": {"coordinates":[3.334841013,50.8108024597],"type":"Point"}
}