{
  "type": "Feature",
  "properties": {
    "addr:full":"Rue Des Alli\u00c9s 54 Frameries Hainaut 7080",
    "addr:housenumber":"54",
    "addr:postcode":"7080",
    "addr:street":"Rue Des Allie\u0301S",
    "iso:country":"BE",
    "sg:address":"Rue Des Alli\u00c9s 54",
    "sg:city":"Frameries",
    "sg:orig_category":"Brood, gebak and snoepgoed",
    "sg:phone":"+32 65 51 53 83",
    "sg:postcode":"7080",
    "sg:province":"Hainaut",
    "wof:name":"V. Flock",
    "wof:placetype":"venue"
},
  "geometry": {"coordinates":[3.8942239285,50.4093856812],"type":"Point"}
}