{
  "type": "Feature",
  "properties": {
    "addr:full":"Industriepark 58 Beernem West-Vlaanderen 8730",
    "addr:housenumber":"58",
    "addr:postcode":"8730",
    "addr:street":"Industriepark",
    "iso:country":"BE",
    "sg:address":"Industriepark 58",
    "sg:city":"Beernem",
    "sg:classifiers":[
        {
            "category":"Professional",
            "subcategory":"Engineering",
            "type":"Services"
        }
    ],
    "sg:phone":"+32 50 79 92 00",
    "sg:postcode":"8730",
    "sg:province":"West-Vlaanderen",
    "sg:tags":[
        "precision"
    ],
    "wof:name":"Meta-tec Nv",
    "wof:placetype":"venue"
},
  "geometry": {"coordinates":[3.3456630707,51.1249656677],"type":"Point"}
}