{
  "type": "Feature",
  "properties": {
    "addr:full":"Avenue De L'hippodrome 60 Box 10 Bruxelles (ixelles) Bruxelles-Capitale 1050",
    "addr:housenumber":"60 box 10",
    "addr:postcode":"1050",
    "addr:street":"Avenue De L'Hippodrome",
    "iso:country":"BE",
    "sg:address":"Avenue De L'hippodrome 60 Box 10",
    "sg:city":"Bruxelles (ixelles)",
    "sg:classifiers":[
        {
            "category":"Professional",
            "subcategory":"Accounting & Tax Preparation",
            "type":"Services"
        }
    ],
    "sg:phone":"+32 2 646 30 94",
    "sg:postcode":"1050",
    "sg:province":"Bruxelles-Capitale",
    "sg:tags":[
        "accountant"
    ],
    "wof:name":"Finexco Sc",
    "wof:placetype":"venue"
},
  "geometry": {"coordinates":[4.3757371902,50.8221435547],"type":"Point"}
}