{
  "type": "Feature",
  "properties": {
    "iso:country":"BE",
    "sg:address":"Chauss\u00e9e Roosevelt 18",
    "sg:city":"Amay",
    "sg:classifiers":[
        {
            "category":"Food & Beverages",
            "subcategory":"Chocolate",
            "type":"Retail Goods"
        }
    ],
    "sg:phone":"+32 85 31 64 37",
    "sg:postcode":"4540",
    "sg:province":"Li\u00e8ge",
    "sg:tags":[
        "confectionery",
        "-"
    ],
    "wof:name":"Leonidas- L'ilot Pralin",
    "wof:placetype":"venue"
},
  "geometry": {"coordinates":[5.3166460991,50.5473747253],"type":"Point"}
}