{
  "type": "Feature",
  "properties": {
    "iso:country":"BE",
    "sg:address":"Route De Philippeville 272",
    "sg:city":"Charleroi",
    "sg:orig_category":"Antiek",
    "sg:phone":"+32 71 36 35 47",
    "sg:postcode":"6010",
    "sg:province":"Hainaut",
    "wof:name":"J.f. Devaux",
    "wof:placetype":"venue"
},
  "geometry": {"coordinates":[4.4627289772,50.3857803345],"type":"Point"}
}