{
  "type": "Feature",
  "properties": {
    "addr:full":"Rue De La Clairi\u00e8re 42 Braine-le-ch\u00e2teau Brabant Wallon 1440",
    "addr:housenumber":"42",
    "addr:postcode":"1440",
    "addr:street":"Rue De La Clairie\u0300Re",
    "iso:country":"BE",
    "sg:address":"Rue De La Clairi\u00e8re 42",
    "sg:city":"Braine-le-ch\u00e2teau",
    "sg:classifiers":[
        {
            "category":"Professional",
            "subcategory":"Accounting & Tax Preparation",
            "type":"Services"
        }
    ],
    "sg:phone":"+32 2 366 11 84",
    "sg:postcode":"1440",
    "sg:province":"Brabant Wallon",
    "sg:tags":[
        "bookkeeper"
    ],
    "wof:name":"Lenclus P",
    "wof:placetype":"venue"
},
  "geometry": {"coordinates":[4.2860569954,50.672039032],"type":"Point"}
}