{
  "type": "Feature",
  "properties": {
    "addr:full":"Rollegemstraat 140 Ledegem West-Vlaanderen 8880",
    "addr:housenumber":"140",
    "addr:postcode":"8880",
    "addr:street":"Rollegemstraat",
    "iso:country":"BE",
    "sg:address":"Rollegemstraat 140",
    "sg:city":"Ledegem",
    "sg:classifiers":[
        {
            "category":"Arena",
            "subcategory":"Sports Club",
            "type":"Entertainment"
        }
    ],
    "sg:phone":"+32 56 50 49 60",
    "sg:postcode":"8880",
    "sg:province":"West-Vlaanderen",
    "sg:tags":[
        "de"
    ],
    "wof:name":"V.t. Maro",
    "wof:placetype":"venue"
},
  "geometry": {"coordinates":[3.1340339184,50.8598098755],"type":"Point"}
}