{
  "type": "Feature",
  "properties": {
    "iso:country":"BE",
    "sg:address":"Rue De La Madeleine 47",
    "sg:city":"Brussel/bruxelles",
    "sg:orig_category":"Antiquit\u00e9s. Biens d'occasion. Librairies",
    "sg:phone":"+32 2 512 92 53",
    "sg:postcode":"1000",
    "sg:province":"Bruxelles-Capitale",
    "wof:name":"Book Market",
    "wof:placetype":"venue"
},
  "geometry": {"coordinates":[4.3551402092,50.8451347351],"type":"Point"}
}