{
  "type": "Feature",
  "properties": {
    "iso:country":"BE",
    "sg:address":"Vaartstraat 16",
    "sg:city":"Leuven",
    "sg:orig_category":"Solariums",
    "sg:phone":"+32 16 20 75 51",
    "sg:postcode":"3000",
    "sg:province":"Vlaams-Brabant",
    "wof:name":"Sunday's",
    "wof:placetype":"venue"
},
  "geometry": {"coordinates":[4.7027192116,50.8806304932],"type":"Point"}
}