{
  "type": "Feature",
  "properties": {
    "iso:country":"BE",
    "sg:address":"Nachtegaal 87",
    "sg:city":"Sint-truiden",
    "sg:classifiers":[
        {
            "category":"Personal",
            "subcategory":"Beauty Salon",
            "type":"Services"
        }
    ],
    "sg:phone":"+32 11 31 36 58",
    "sg:postcode":"3800",
    "sg:province":"Limburg",
    "sg:tags":[
        "de",
        "coiffure"
    ],
    "wof:name":"Rita Budo",
    "wof:placetype":"venue"
},
  "geometry": {"coordinates":[5.1863641739,50.8153343201],"type":"Point"}
}