{
  "type": "Feature",
  "properties": {
    "iso:country":"BE",
    "sg:address":"Quellinstraat 1",
    "sg:city":"Antwerpen",
    "sg:classifiers":[
        {
            "category":"Community Center",
            "subcategory":"Youth",
            "type":"Public Place"
        }
    ],
    "sg:phone":"+32 3 233 18 72",
    "sg:postcode":"2018",
    "sg:province":"Antwerpen",
    "sg:tags":[
        "parasol",
        "umbrella"
    ],
    "wof:name":"New's",
    "wof:placetype":"venue"
},
  "geometry": {"coordinates":[4.4168767929,51.2176437378],"type":"Point"}
}