{
  "type": "Feature",
  "properties": {
    "iso:country":"BE",
    "sg:address":"Rue Royale 54",
    "sg:city":"Tournai",
    "sg:orig_category":"Antiek",
    "sg:phone":"+32 69 22 32 52",
    "sg:postcode":"7500",
    "sg:province":"Hainaut",
    "wof:name":"Isabelle Jeudy",
    "wof:placetype":"venue"
},
  "geometry": {"coordinates":[3.3929440975,50.6100654602],"type":"Point"}
}