{
  "type": "Feature",
  "properties": {
    "addr:full":"Brusselstraat 55bb Dilbeek Vlaams-Brabant 1700",
    "addr:housenumber":"55bb",
    "addr:postcode":"1700",
    "addr:street":"Brusselstraat",
    "iso:country":"BE",
    "sg:address":"Brusselstraat 55bb",
    "sg:city":"Dilbeek",
    "sg:classifiers":[
        {
            "category":"Shopping",
            "subcategory":"Clothing, Apparel, & Fashions",
            "type":"Retail Goods"
        }
    ],
    "sg:phone":"+32 2 453 05 73",
    "sg:postcode":"1700",
    "sg:province":"Vlaams-Brabant",
    "sg:tags":[
        "ondergoed",
        "lingerie"
    ],
    "wof:name":"Best-socks",
    "wof:placetype":"venue"
},
  "geometry": {"coordinates":[4.2083501816,50.8759994507],"type":"Point"}
}