{
  "type": "Feature",
  "properties": {
    "addr:full":"Peerderbaan 54 Meeuwen-gruitrode Limburg 3670",
    "addr:housenumber":"54",
    "addr:postcode":"3670",
    "addr:street":"Peerderbaan",
    "iso:country":"BE",
    "sg:address":"Peerderbaan 54",
    "sg:city":"Meeuwen-gruitrode",
    "sg:orig_category":"Woningbouw",
    "sg:phone":"+32 11 79 16 48",
    "sg:postcode":"3670",
    "sg:province":"Limburg",
    "wof:name":"Horemans Houtskeletbouw",
    "wof:placetype":"venue"
},
  "geometry": {"coordinates":[5.5085339546,51.1074295044],"type":"Point"}
}