{
  "type": "Feature",
  "properties": {
    "addr:full":"Rue Des Alli\u00e9s 10 Charleroi (roux) Hainaut 6044",
    "addr:housenumber":"10;6044",
    "addr:street":"Rue Des Allie\u0301S",
    "iso:country":"BE",
    "sg:address":"Rue Des Alli\u00e9s 10",
    "sg:city":"Charleroi (roux)",
    "sg:classifiers":[
        {
            "category":"Shopping",
            "subcategory":"Clothing, Apparel, & Fashions",
            "type":"Retail Goods"
        }
    ],
    "sg:phone":"+32 71 45 00 18",
    "sg:postcode":"6044",
    "sg:province":"Hainaut",
    "sg:tags":[
        "lady",
        "clothing",
        "-"
    ],
    "wof:name":"Bas National (au)",
    "wof:placetype":"venue"
},
  "geometry": {"coordinates":[4.391723156,50.4408760071],"type":"Point"}
}