{
  "type": "Feature",
  "properties": {
    "addr:full":"Meiboomlaan 88 Roeselare West-Vlaanderen 8800",
    "addr:housenumber":"88",
    "addr:postcode":"8800",
    "addr:street":"Meiboomlaan",
    "iso:country":"BE",
    "sg:address":"Meiboomlaan 88",
    "sg:city":"Roeselare",
    "sg:orig_category":"Instruments de musique",
    "sg:phone":"+32 51 24 55 22",
    "sg:postcode":"8800",
    "sg:province":"West-Vlaanderen",
    "wof:name":"Koenraad Vanneste",
    "wof:placetype":"venue"
},
  "geometry": {"coordinates":[3.1150400639,50.9327888489],"type":"Point"}
}