{
  "type": "Feature",
  "properties": {
    "iso:country":"BE",
    "sg:address":"Rue Du Chateau 16",
    "sg:city":"Trazegnies",
    "sg:classifiers":[
        {
            "category":"Building & Trades",
            "subcategory":"Locksmith",
            "type":"Services"
        }
    ],
    "sg:phone":"+32 71 45 35 38",
    "sg:postcode":"6183",
    "sg:province":"Hainaut",
    "sg:tags":[
        "roofing",
        "industrial"
    ],
    "wof:name":"Deplus Marcel",
    "wof:placetype":"venue"
},
  "geometry": {"coordinates":[4.3289499283,50.4606895447],"type":"Point"}
}