{
  "type": "Feature",
  "properties": {
    "iso:country":"BE",
    "sg:address":"Chauss\u00e9e Romaine 79",
    "sg:city":"Gembloux-sur-orneau (gembloux)",
    "sg:classifiers":[
        {
            "category":"Manufacturing",
            "subcategory":"Motor Vehicles & Parts",
            "type":"Manufacturing & Wholesale Goods"
        }
    ],
    "sg:phone":"+32 81 61 14 79",
    "sg:postcode":"5030",
    "sg:province":"Namur",
    "sg:tags":[
        "exhaust",
        "system"
    ],
    "wof:name":"Gembloux Pneus Centre Auto Sa",
    "wof:placetype":"venue"
},
  "geometry": {"coordinates":[4.6849861145,50.579284668],"type":"Point"}
}