{
  "type": "Feature",
  "properties": {
    "addr:full":"Stationsstraat 76 Boortmeerbeek (hever) Vlaams-Brabant 3191",
    "addr:housenumber":"76",
    "addr:postcode":"3191",
    "addr:street":"Stationsstraat",
    "iso:country":"BE",
    "sg:address":"Stationsstraat 76",
    "sg:city":"Boortmeerbeek (hever)",
    "sg:classifiers":[
        {
            "category":"Health Services",
            "subcategory":"Dentist",
            "type":"Services"
        }
    ],
    "sg:phone":"+32 15 51 23 41",
    "sg:postcode":"3191",
    "sg:province":"Vlaams-Brabant",
    "wof:name":"Limantoro S",
    "wof:placetype":"venue"
},
  "geometry": {"coordinates":[4.5487642288,50.9965209961],"type":"Point"}
}