{
  "type": "Feature",
  "properties": {
    "addr:full":"Vilvoordelaan 17 Zaventem Vlaams-Brabant 1930",
    "addr:housenumber":"17",
    "addr:postcode":"1930",
    "addr:street":"Vilvoordelaan",
    "iso:country":"BE",
    "sg:address":"Vilvoordelaan 17",
    "sg:city":"Zaventem",
    "sg:orig_category":"Verlichting and huishoudartikelen",
    "sg:phone":"+32 2 720 84 22",
    "sg:postcode":"1930",
    "sg:province":"Vlaams-Brabant",
    "wof:name":"Knus",
    "wof:placetype":"venue"
},
  "geometry": {"coordinates":[4.4706339836,50.8866462708],"type":"Point"}
}