{
  "type": "Feature",
  "properties": {
    "iso:country":"BE",
    "sg:address":"Chauss\u00c9e De Gand 81",
    "sg:city":"Sint-jans-molenbeek/molenbeek-saint-jean",
    "sg:orig_category":"Meubles D\u00e9taillants, Am\u00e9nagement de B\u00e2timents et de Cuisines",
    "sg:phone":"+32 2 410 30 56",
    "sg:postcode":"1080",
    "sg:province":"Bruxelles-Capitale",
    "wof:name":"Ozlem",
    "wof:placetype":"venue"
},
  "geometry": {"coordinates":[4.3369779587,50.8541030884],"type":"Point"}
}