{
  "type": "Feature",
  "properties": {
    "iso:country":"BE",
    "sg:address":"Rue Du Commerce 37",
    "sg:city":"Ciney",
    "sg:classifiers":[
        {
            "category":"Shopping",
            "subcategory":"Gifts & Souvenirs",
            "type":"Retail Goods"
        }
    ],
    "sg:phone":"+32 83 21 80 42",
    "sg:postcode":"5590",
    "sg:province":"Namur",
    "sg:tags":[
        "-"
    ],
    "wof:name":"Deux Maisons Plus Loin",
    "wof:placetype":"venue"
},
  "geometry": {"coordinates":[5.0989751816,50.2940406799],"type":"Point"}
}