{
  "type": "Feature",
  "properties": {
    "iso:country":"BE",
    "sg:address":"Galerie Du Douaire",
    "sg:city":"Ottignies-louvain-la-neuve (ottignies)",
    "sg:classifiers":[
        {
            "category":"Shopping",
            "subcategory":"Clothing, Apparel, & Fashions",
            "type":"Retail Goods"
        }
    ],
    "sg:phone":"+32 10 40 17 53",
    "sg:postcode":"1340",
    "sg:province":"Brabant Wallon",
    "sg:tags":[
        "boutique"
    ],
    "wof:name":"Cap Horn",
    "wof:placetype":"venue"
},
  "geometry": {"coordinates":[4.5668802261,50.6634902954],"type":"Point"}
}