{
  "type": "Feature",
  "properties": {
    "iso:country":"BE",
    "sg:address":"Westerlosesteenweg 40",
    "sg:city":"Herselt",
    "sg:classifiers":[
        {
            "category":"Retail",
            "subcategory":"Veterinary Services",
            "type":"Services"
        }
    ],
    "sg:phone":"+32 14 54 81 82",
    "sg:postcode":"2230",
    "sg:province":"Antwerpen",
    "sg:tags":[
        "veterinarian"
    ],
    "wof:name":"Mertens G",
    "wof:placetype":"venue"
},
  "geometry": {"coordinates":[4.888961792,51.0612182617],"type":"Point"}
}