{
  "type": "Feature",
  "properties": {
    "addr:full":"Doelstraat 158 Ingelmunster West-Vlaanderen 8770",
    "addr:housenumber":"158",
    "addr:postcode":"8770",
    "addr:street":"Doelstraat",
    "iso:country":"BE",
    "sg:address":"Doelstraat 158",
    "sg:city":"Ingelmunster",
    "sg:orig_category":"Poissonniers and \u00e9caillers",
    "sg:phone":"+32 51 30 32 74",
    "sg:postcode":"8770",
    "sg:province":"West-Vlaanderen",
    "wof:name":"Vishandel Ren\u00c9",
    "wof:placetype":"venue"
},
  "geometry": {"coordinates":[3.2416620255,50.935005188],"type":"Point"}
}