{
  "type": "Feature",
  "properties": {
    "iso:country":"BE",
    "sg:address":"Cortil-waha 12",
    "sg:city":"Namur",
    "sg:orig_category":"Equipements pour la construction Construction de rev\u00eatements routiers and sportifs. D\u00e9molition d\u00b4imm",
    "sg:phone":"+32 81 44 12 78",
    "sg:postcode":"5020",
    "sg:province":"Namur",
    "wof:name":"Christian Dubois",
    "wof:placetype":"venue"
},
  "geometry": {"coordinates":[4.7952418327,50.4352035522],"type":"Point"}
}