{
  "type": "Feature",
  "properties": {
    "addr:full":"Dorpsstraat 62 Jabbeke West-Vlaanderen 8490",
    "addr:housenumber":"62",
    "addr:postcode":"8490",
    "addr:street":"Dorpsstraat",
    "iso:country":"BE",
    "sg:address":"Dorpsstraat 62",
    "sg:city":"Jabbeke",
    "sg:classifiers":[
        {
            "category":"Bakery",
            "type":"Food & Drink"
        }
    ],
    "sg:phone":"+32 50 81 13 84",
    "sg:postcode":"8490",
    "sg:province":"West-Vlaanderen",
    "sg:tags":[
        "confectioner",
        "baker"
    ],
    "wof:name":"Demarest F",
    "wof:placetype":"venue"
},
  "geometry": {"coordinates":[3.0902440548,51.1820793152],"type":"Point"}
}