{
  "type": "Feature",
  "properties": {
    "addr:full":"Hoesnaek 18ba Pepingen Vlaams-Brabant 1670",
    "addr:housenumber":"18ba",
    "addr:postcode":"1670",
    "addr:street":"Hoesnaek",
    "iso:country":"BE",
    "sg:address":"Hoesnaek 18ba",
    "sg:city":"Pepingen",
    "sg:orig_category":"Artsen and specialisten",
    "sg:phone":"+32 2 356 02 80",
    "sg:postcode":"1670",
    "sg:province":"Vlaams-Brabant",
    "wof:name":"Jean-marie Berthot",
    "wof:placetype":"venue"
},
  "geometry": {"coordinates":[4.154815197,50.7582168579],"type":"Point"}
}