{
  "type": "Feature",
  "properties": {
    "iso:country":"BE",
    "sg:address":"Generaal Deprezstraat 98",
    "sg:city":"Harelbeke",
    "sg:orig_category":"Alimentation sp\u00e9cialis\u00e9e",
    "sg:phone":"+32 56 21 50 05",
    "sg:postcode":"8530",
    "sg:province":"West-Vlaanderen",
    "wof:name":"De Witte Tokke",
    "wof:placetype":"venue"
},
  "geometry": {"coordinates":[3.3139140606,50.83411026],"type":"Point"}
}