{
  "type": "Feature",
  "properties": {
    "iso:country":"BE",
    "sg:address":"Lutselusstraat 147",
    "sg:city":"Diepenbeek",
    "sg:orig_category":"Kapsalons",
    "sg:phone":"+32 11 32 37 45",
    "sg:postcode":"3590",
    "sg:province":"Limburg",
    "wof:name":"Degraen Camille",
    "wof:placetype":"venue"
},
  "geometry": {"coordinates":[5.457930088,50.9132499695],"type":"Point"}
}