{
  "type": "Feature",
  "properties": {
    "iso:country":"BE",
    "sg:address":"Kloosterstraat 25",
    "sg:city":"Kortrijk (marke)",
    "sg:classifiers":[
        {
            "category":"Health Services",
            "subcategory":"Nursing And Care Facility",
            "type":"Services"
        }
    ],
    "sg:phone":"+32 56 24 55 24",
    "sg:postcode":"8510",
    "sg:province":"West-Vlaanderen",
    "sg:tags":[
        "home",
        "rest"
    ],
    "wof:name":"Woon- & Zorgcentrum De Ruyschaert Vzw",
    "wof:placetype":"venue"
},
  "geometry": {"coordinates":[3.2354779243,50.8062744141],"type":"Point"}
}