{
  "type": "Feature",
  "properties": {
    "addr:full":"Scheestraat 74 Lennik (sint-martens-lennik) Vlaams-Brabant 1750",
    "addr:housenumber":"74",
    "addr:postcode":"1750",
    "addr:street":"Scheestraat",
    "iso:country":"BE",
    "sg:address":"Scheestraat 74",
    "sg:city":"Lennik (sint-martens-lennik)",
    "sg:classifiers":[
        {
            "category":"Education",
            "subcategory":"School",
            "type":"Public Place"
        }
    ],
    "sg:phone":"+32 2 568 11 09",
    "sg:postcode":"1750",
    "sg:province":"Vlaams-Brabant",
    "sg:tags":[
        "primary"
    ],
    "wof:name":"Levenslust Blo",
    "wof:placetype":"venue"
},
  "geometry": {"coordinates":[4.2007389069,50.8264503479],"type":"Point"}
}