{
  "type": "Feature",
  "properties": {
    "iso:country":"BE",
    "sg:address":"Rue Des Loups 2 Box 302",
    "sg:city":"La Louvi\u00e8re",
    "sg:classifiers":[
        {
            "category":"Health Services",
            "subcategory":"Nursing And Care Facility",
            "type":"Services"
        }
    ],
    "sg:phone":"+32 64 44 18 41",
    "sg:postcode":"7100",
    "sg:province":"Hainaut",
    "sg:tags":[
        "home"
    ],
    "wof:name":"Lemaire Yannic",
    "wof:placetype":"venue"
},
  "geometry": {"coordinates":[4.2021098137,50.4797668457],"type":"Point"}
}