{
  "type": "Feature",
  "properties": {
    "iso:country":"BE",
    "sg:address":"Gelindenstraat 131",
    "sg:city":"Heers (mechelen-bovelingen)",
    "sg:classifiers":[
        {
            "category":"Bars & Pubs",
            "type":"Food & Drink"
        }
    ],
    "sg:phone":"+32 11 48 60 93",
    "sg:postcode":"3870",
    "sg:province":"Limburg",
    "wof:name":"Hubbe (cafe)",
    "wof:placetype":"venue"
},
  "geometry": {"coordinates":[5.2547459602,50.7405052185],"type":"Point"}
}