{
  "type": "Feature",
  "properties": {
    "addr:full":"Avenue Ch\u00e2teau De Walzin 7 Box 17 Bruxelles (uccle) Bruxelles-Capitale 1180",
    "addr:housenumber":"7 box 17",
    "addr:postcode":"1180",
    "addr:street":"Avenue Cha\u0302Teau De Walzin",
    "iso:country":"BE",
    "sg:address":"Avenue Ch\u00e2teau De Walzin 7 Box 17",
    "sg:city":"Bruxelles (uccle)",
    "sg:classifiers":[
        {
            "category":"Health Services",
            "subcategory":"Health Practitioner",
            "type":"Services"
        }
    ],
    "sg:phone":"+32 2 784 31 82",
    "sg:postcode":"1180",
    "sg:province":"Bruxelles-Capitale",
    "sg:tags":[
        "psychologist"
    ],
    "wof:name":"Lauwereys J-p",
    "wof:placetype":"venue"
},
  "geometry": {"coordinates":[4.3458871841,50.8078346252],"type":"Point"}
}