{
  "type": "Feature",
  "properties": {
    "iso:country":"BE",
    "sg:address":"Berten Pilstraat 7",
    "sg:city":"Zonnebeke",
    "sg:orig_category":"Enseignement maternel and primaire",
    "sg:phone":"+32 51 77 82 44",
    "sg:postcode":"8980",
    "sg:province":"West-Vlaanderen",
    "wof:name":"Gemeentel. Lagere School",
    "wof:placetype":"venue"
},
  "geometry": {"coordinates":[2.9865889549,50.8705215454],"type":"Point"}
}