{
  "type": "Feature",
  "properties": {
    "addr:full":"T Hielsstraat 10 Kruibeke Oost-Vlaanderen 9150",
    "addr:housenumber":"10",
    "addr:postcode":"9150",
    "addr:street":"Hielsstraat",
    "iso:country":"BE",
    "sg:address":"T Hielsstraat 10",
    "sg:city":"Kruibeke",
    "sg:orig_category":"Instituts de beaut\u00e9",
    "sg:phone":"+32 3 744 17 77",
    "sg:postcode":"9150",
    "sg:province":"Oost-Vlaanderen",
    "wof:name":"Instituut Ingrid",
    "wof:placetype":"venue"
},
  "geometry": {"coordinates":[4.3131599426,51.1718406677],"type":"Point"}
}