{
  "type": "Feature",
  "properties": {
    "addr:full":"Rue De La Brasserie 141 Linkebeek Vlaams-Brabant 1630",
    "addr:housenumber":"141",
    "addr:postcode":"1630",
    "addr:street":"Rue De La Brasserie",
    "iso:country":"BE",
    "sg:address":"Rue De La Brasserie 141",
    "sg:city":"Linkebeek",
    "sg:classifiers":[
        {
            "category":"Real Estate",
            "subcategory":"Architect",
            "type":"Services"
        }
    ],
    "sg:phone":"+32 2 380 56 17",
    "sg:postcode":"1630",
    "sg:province":"Vlaams-Brabant",
    "wof:name":"Thieffry O",
    "wof:placetype":"venue"
},
  "geometry": {"coordinates":[4.3269739151,50.7782516479],"type":"Point"}
}