{
  "type": "Feature",
  "properties": {
    "iso:country":"BE",
    "sg:address":"Rue De La Station 4",
    "sg:city":"Oupeye",
    "sg:classifiers":[
        {
            "category":"Cafe",
            "type":"Food & Drink"
        }
    ],
    "sg:phone":"+32 4 286 33 27",
    "sg:postcode":"4682",
    "sg:province":"Li\u00e8ge",
    "sg:tags":[
        "caf\u00e9s"
    ],
    "wof:name":"Belbrew",
    "wof:placetype":"venue"
},
  "geometry": {"coordinates":[5.6134128571,50.7410469055],"type":"Point"}
}