{
  "type": "Feature",
  "properties": {
    "iso:country":"BE",
    "sg:address":"Beheerstraat 19",
    "sg:city":"Kortrijk",
    "sg:classifiers":[
        {
            "category":"Food & Beverages",
            "subcategory":"Groceries & Convenience Stores",
            "type":"Retail Goods"
        }
    ],
    "sg:phone":"+32 56 20 18 99",
    "sg:postcode":"8500",
    "sg:province":"West-Vlaanderen",
    "sg:tags":[
        "grocer"
    ],
    "wof:name":"Assalam",
    "wof:placetype":"venue"
},
  "geometry": {"coordinates":[3.2578949928,50.8263664246],"type":"Point"}
}