{
  "type": "Feature",
  "properties": {
    "addr:full":"Avenue Victor Tesch 5-7 Arlon Luxembourg 6700",
    "addr:housenumber":"5-7",
    "addr:postcode":"6700",
    "addr:street":"Avenue Victor Tesch",
    "iso:country":"BE",
    "sg:address":"Avenue Victor Tesch 5-7",
    "sg:city":"Arlon",
    "sg:classifiers":[
        {
            "category":"Professional",
            "subcategory":"Lawyer & Legal Services",
            "type":"Services"
        }
    ],
    "sg:phone":"+32 63 22 47 44",
    "sg:postcode":"6700",
    "sg:province":"Luxembourg",
    "wof:name":"Crochet Nathalie",
    "wof:placetype":"venue"
},
  "geometry": {"coordinates":[5.8123002052,49.6809463501],"type":"Point"}
}