{
  "type": "Feature",
  "properties": {
    "iso:country":"BE",
    "sg:address":"Rue Traversi\u00e8re 45",
    "sg:city":"Bruxelles (saint-josse-ten-noode)",
    "sg:classifiers":[
        {
            "category":"Arts & Performance",
            "subcategory":"Theater",
            "type":"Entertainment"
        }
    ],
    "sg:phone":"+32 2 219 11 86",
    "sg:postcode":"1210",
    "sg:province":"Bruxelles-Capitale",
    "sg:tags":[
        "concert-halls",
        "theatre"
    ],
    "wof:name":"Th\u00e9\u00e2tre De La Vie Asbl",
    "wof:placetype":"venue"
},
  "geometry": {"coordinates":[4.3695788383,50.8542175293],"type":"Point"}
}