{
  "type": "Feature",
  "properties": {
    "addr:full":"Th\u00c9odore Verhaegenstraat 68 Sint-gillis/saint-gilles Bruxelles-Capitale 1060",
    "addr:housenumber":"68",
    "addr:postcode":"1060",
    "addr:street":"The\u0301Odore Verhaegenstraat",
    "iso:country":"BE",
    "sg:address":"Th\u00c9odore Verhaegenstraat 68",
    "sg:city":"Sint-gillis/saint-gilles",
    "sg:orig_category":"Herstellingen and onderhoud van auto's",
    "sg:phone":"+32 2 537 30 11",
    "sg:postcode":"1060",
    "sg:province":"Bruxelles-Capitale",
    "wof:name":"Garage Alfa 2",
    "wof:placetype":"venue"
},
  "geometry": {"coordinates":[4.3406381607,50.8285446167],"type":"Point"}
}