{
  "type": "Feature",
  "properties": {
    "iso:country":"BE",
    "sg:address":"Place Du Bronze 15",
    "sg:city":"La Roche-en-ardenne",
    "sg:orig_category":"Cin\u00e9mas",
    "sg:phone":"+32 84 41 25 80",
    "sg:postcode":"6980",
    "sg:province":"Luxembourg",
    "wof:name":"Cin\u00c9ma Le Carrefour",
    "wof:placetype":"venue"
},
  "geometry": {"coordinates":[5.5765609741,50.1798782349],"type":"Point"}
}