{
  "type": "Feature",
  "properties": {
    "iso:country":"BE",
    "sg:address":"Klaverbladstraat 17",
    "sg:city":"Lummen",
    "sg:classifiers":[
        {
            "category":"Utilities",
            "subcategory":"Fuel Oil & Lpg",
            "type":"Services"
        }
    ],
    "sg:phone":"+32 13 52 15 12",
    "sg:postcode":"3560",
    "sg:province":"Limburg",
    "sg:tags":[
        "antioxidant"
    ],
    "wof:name":"Sch\u00e4fer Sb Nv",
    "wof:placetype":"venue"
},
  "geometry": {"coordinates":[5.2290492058,50.9965515137],"type":"Point"}
}