{
  "type": "Feature",
  "properties": {
    "iso:country":"BE",
    "sg:address":"Weidestraat 19",
    "sg:city":"Beringen",
    "sg:orig_category":"Industri\u00eble and commerci\u00eble bouw Woningbouw",
    "sg:phone":"+32 11 34 86 87",
    "sg:postcode":"3581",
    "sg:province":"Limburg",
    "wof:name":"T.o.b.",
    "wof:placetype":"venue"
},
  "geometry": {"coordinates":[5.1990180016,51.0807113647],"type":"Point"}
}