{
  "type": "Feature",
  "properties": {
    "addr:full":"Industrielaan 2 Eeklo Oost-Vlaanderen 9900",
    "addr:housenumber":"2",
    "addr:postcode":"9900",
    "addr:street":"Industrielaan",
    "iso:country":"BE",
    "sg:address":"Industrielaan 2",
    "sg:city":"Eeklo",
    "sg:orig_category":"Services de t\u00e9l\u00e9communications. Production and distribution d'\u00e9lectricit\u00e9. Production and distributi",
    "sg:phone":"+32 78 35 35 35",
    "sg:postcode":"9900",
    "sg:province":"Oost-Vlaanderen",
    "wof:name":"Electrabel",
    "wof:placetype":"venue"
},
  "geometry": {"coordinates":[3.5371201038,51.1819801331],"type":"Point"}
}