{
  "type": "Feature",
  "properties": {
    "iso:country":"BE",
    "sg:address":"Rozendaal 36",
    "sg:city":"Geel",
    "sg:classifiers":[
        {
            "category":"Bars & Pubs",
            "type":"Food & Drink"
        }
    ],
    "sg:phone":"+32 14 58 82 62",
    "sg:postcode":"2440",
    "sg:province":"Antwerpen",
    "wof:name":"Sportvriend",
    "wof:placetype":"venue"
},
  "geometry": {"coordinates":[4.9896850586,51.1674919128],"type":"Point"}
}