{
  "type": "Feature",
  "properties": {
    "iso:country":"BE",
    "sg:address":"L\u00fctticher Strasse 45",
    "sg:city":"Kelmis (neu Moresnet)",
    "sg:classifiers":[
        {
            "category":"Communications",
            "subcategory":"Film & Video Production",
            "type":"Services"
        }
    ],
    "sg:phone":"+32 87 65 76 76",
    "sg:postcode":"4721",
    "sg:province":"Li\u00e8ge",
    "sg:tags":[
        "sound",
        "recording",
        "studio"
    ],
    "wof:name":"Boderline Sound & Vision",
    "wof:placetype":"venue"
},
  "geometry": {"coordinates":[6.0287680626,50.7232398987],"type":"Point"}
}