{
  "type": "Feature",
  "properties": {
    "addr:full":"Linciaux 3 Ciney Namur 5590",
    "addr:housenumber":"3",
    "addr:postcode":"5590",
    "addr:street":"Linciaux",
    "iso:country":"BE",
    "sg:address":"Linciaux 3",
    "sg:city":"Ciney",
    "sg:orig_category":"Eleveurs de bovins",
    "sg:phone":"+32 83 21 56 17",
    "sg:postcode":"5590",
    "sg:province":"Namur",
    "wof:name":"Dumortier",
    "wof:placetype":"venue"
},
  "geometry": {"coordinates":[5.1350269318,50.2760505676],"type":"Point"}
}