{
  "type": "Feature",
  "properties": {
    "addr:full":"Glorieuxstraat 4 Maarkedal Oost-Vlaanderen 9681",
    "addr:housenumber":"4",
    "addr:postcode":"9681",
    "addr:street":"Glorieuxstraat",
    "iso:country":"BE",
    "sg:address":"Glorieuxstraat 4",
    "sg:city":"Maarkedal",
    "sg:orig_category":"Enseignement maternel and primaire",
    "sg:phone":"+32 55 21 04 69",
    "sg:postcode":"9681",
    "sg:province":"Oost-Vlaanderen",
    "wof:name":"Vrije Basisschool",
    "wof:placetype":"venue"
},
  "geometry": {"coordinates":[3.5952050686,50.7969856262],"type":"Point"}
}