{
  "type": "Feature",
  "properties": {
    "addr:full":"Bilzersteenweg 245 Tongeren Limburg 3700",
    "addr:housenumber":"245",
    "addr:postcode":"3700",
    "addr:street":"Bilzersteenweg",
    "iso:country":"BE",
    "sg:address":"Bilzersteenweg 245",
    "sg:city":"Tongeren",
    "sg:classifiers":[
        {
            "category":"Retail",
            "subcategory":"Auto Repair",
            "type":"Services"
        }
    ],
    "sg:phone":"+32 12 23 23 56",
    "sg:postcode":"3700",
    "sg:province":"Limburg",
    "sg:tags":[
        "garage"
    ],
    "wof:name":"Vanhees",
    "wof:placetype":"venue"
},
  "geometry": {"coordinates":[5.4650249481,50.7939949036],"type":"Point"}
}