{
  "type": "Feature",
  "properties": {
    "iso:country":"BE",
    "sg:address":"Vlierstraat 4",
    "sg:city":"De Pinte",
    "sg:orig_category":"Balie van Gent. Avocats and conseillers juridiques",
    "sg:phone":"+32 9 281 28 12",
    "sg:postcode":"9840",
    "sg:province":"Oost-Vlaanderen",
    "wof:name":"Ockerman Stefan",
    "wof:placetype":"venue"
},
  "geometry": {"coordinates":[3.6478509903,50.9992332458],"type":"Point"}
}