{
  "type": "Feature",
  "properties": {
    "iso:country":"BE",
    "sg:address":"Rue Vital Fran\u00c7oisse 220",
    "sg:city":"Charleroi",
    "sg:orig_category":"Woningbouw",
    "sg:phone":"+32 71 47 77 42",
    "sg:postcode":"6001",
    "sg:province":"Hainaut",
    "wof:name":"Engebaty",
    "wof:placetype":"venue"
},
  "geometry": {"coordinates":[4.4245409966,50.4035491943],"type":"Point"}
}