{
  "type": "Feature",
  "properties": {
    "addr:full":"Necropolisstraat 1 Tongeren Limburg 3700",
    "addr:housenumber":"1",
    "addr:postcode":"3700",
    "addr:street":"Necropolisstraat",
    "iso:country":"BE",
    "sg:address":"Necropolisstraat 1",
    "sg:city":"Tongeren",
    "sg:classifiers":[
        {
            "category":"Cafe",
            "type":"Food & Drink"
        }
    ],
    "sg:phone":"+32 12 26 11 18",
    "sg:postcode":"3700",
    "sg:province":"Limburg",
    "sg:tags":[
        "caf\u00e9s"
    ],
    "wof:name":"Tonny Roggen",
    "wof:placetype":"venue"
},
  "geometry": {"coordinates":[5.4498491287,50.7746009827],"type":"Point"}
}