{
  "type": "Feature",
  "properties": {
    "iso:country":"BE",
    "sg:address":"Riet 106bw",
    "sg:city":"Stekene",
    "sg:orig_category":"Woningbouw Zalen voor culturele evenementen",
    "sg:phone":"+32 3 789 18 63",
    "sg:postcode":"9190",
    "sg:province":"Oost-Vlaanderen",
    "wof:name":"Inter-x",
    "wof:placetype":"venue"
},
  "geometry": {"coordinates":[3.9982259274,51.2372131348],"type":"Point"}
}