{
  "type": "Feature",
  "properties": {
    "iso:country":"BE",
    "sg:address":"Rue Grande 1",
    "sg:city":"Quievrain",
    "sg:orig_category":"Equipement photographique. Studios photographiques",
    "sg:phone":"+32 65 45 83 22",
    "sg:postcode":"7380",
    "sg:province":"Hainaut",
    "wof:name":"L'atelier Photographique",
    "wof:placetype":"venue"
},
  "geometry": {"coordinates":[3.6830029488,50.4074478149],"type":"Point"}
}