{
  "type": "Feature",
  "properties": {
    "addr:full":"Koningin Elisabethlaan 34 Brugge West-Vlaanderen 8000",
    "addr:housenumber":"34",
    "addr:postcode":"8000",
    "addr:street":"Koningin Elisabethlaan",
    "iso:country":"BE",
    "sg:address":"Koningin Elisabethlaan 34",
    "sg:city":"Brugge",
    "sg:orig_category":"Maatschappelijke dienstverlening",
    "sg:phone":"+32 50 34 57 57",
    "sg:postcode":"8000",
    "sg:province":"West-Vlaanderen",
    "wof:name":"Vertrouwenscentrum Kind In Nood",
    "wof:placetype":"venue"
},
  "geometry": {"coordinates":[3.2177219391,51.2160797119],"type":"Point"}
}