{
  "type": "Feature",
  "properties": {
    "iso:country":"BE",
    "sg:address":"Monnikenwerve 54b56",
    "sg:city":"Brugge",
    "sg:orig_category":"Produits surgel\u00e9s Gr",
    "sg:phone":"+32 50 31 05 47",
    "sg:postcode":"8000",
    "sg:province":"West-Vlaanderen",
    "wof:name":"De Prest",
    "wof:placetype":"venue"
},
  "geometry": {"coordinates":[3.2021570206,51.2488441467],"type":"Point"}
}