{
  "type": "Feature",
  "properties": {
    "iso:country":"BE",
    "sg:address":"Weststraat 10",
    "sg:city":"Evergem (sleidinge)",
    "sg:classifiers":[
        {
            "category":"Shopping",
            "subcategory":"Jewelry",
            "type":"Retail Goods"
        }
    ],
    "sg:phone":"+32 9 357 32 67",
    "sg:postcode":"9940",
    "sg:province":"Oost-Vlaanderen",
    "sg:tags":[
        "jeweller",
        "-"
    ],
    "wof:name":"Lehoucq",
    "wof:placetype":"venue"
},
  "geometry": {"coordinates":[3.6778259277,51.131893158],"type":"Point"}
}