{
  "type": "Feature",
  "properties": {
    "iso:country":"BE",
    "sg:address":"Molenstraat 169",
    "sg:city":"Lommel",
    "sg:orig_category":"Installation de menuiserie en bois and plastique",
    "sg:phone":"+32 11 55 34 44",
    "sg:postcode":"3920",
    "sg:province":"Limburg",
    "wof:name":"Verboven W",
    "wof:placetype":"venue"
},
  "geometry": {"coordinates":[5.328081131,51.2330284119],"type":"Point"}
}