{
  "type": "Feature",
  "properties": {
    "iso:country":"BE",
    "sg:address":"Zwaluwenlaan 35",
    "sg:city":"Sint-genesius-rode/rhode-saint-genese",
    "sg:orig_category":"Artsen and specialisten",
    "sg:phone":"+32 2 358 56 42",
    "sg:postcode":"1640",
    "sg:province":"Vlaams-Brabant",
    "wof:name":"J-l Mertens",
    "wof:placetype":"venue"
},
  "geometry": {"coordinates":[4.3739042282,50.7374839783],"type":"Point"}
}