{
  "type": "Feature",
  "properties": {
    "iso:country":"BE",
    "sg:address":"Rue Des Enhauts 52",
    "sg:city":"Le Roeulx",
    "sg:orig_category":"Elektrische installaties voor woningen",
    "sg:phone":"+32 65 87 11 16",
    "sg:postcode":"7070",
    "sg:province":"Hainaut",
    "wof:name":"Favart",
    "wof:placetype":"venue"
},
  "geometry": {"coordinates":[4.0645709038,50.4775886536],"type":"Point"}
}