{
  "type": "Feature",
  "properties": {
    "addr:full":"Rue De Maestricht 96 Herve (battice) Li\u00e8ge 4651",
    "addr:housenumber":"96",
    "addr:postcode":"4651",
    "addr:street":"Rue De Maestricht",
    "iso:country":"BE",
    "sg:address":"Rue De Maestricht 96",
    "sg:city":"Herve (battice)",
    "sg:classifiers":[
        {
            "category":"Home & Garden",
            "subcategory":"Building Materials",
            "type":"Retail Goods"
        }
    ],
    "sg:phone":"+32 87 69 20 10",
    "sg:postcode":"4651",
    "sg:province":"Li\u00e8ge",
    "sg:tags":[
        "granite",
        "stone",
        "natural",
        "marble"
    ],
    "wof:name":"Euroconfort Sa",
    "wof:placetype":"venue"
},
  "geometry": {"coordinates":[5.7984428406,50.654335022],"type":"Point"}
}