{
  "type": "Feature",
  "properties": {
    "addr:full":"Gasdam 17 Beveren Oost-Vlaanderen 9120",
    "addr:housenumber":"17",
    "addr:postcode":"9120",
    "addr:street":"Gasdam",
    "iso:country":"BE",
    "sg:address":"Gasdam 17",
    "sg:city":"Beveren",
    "sg:orig_category":"Installation de menuiserie en bois and plastique",
    "sg:phone":"+32 3 775 93 75",
    "sg:postcode":"9120",
    "sg:province":"Oost-Vlaanderen",
    "wof:name":"W. Staut",
    "wof:placetype":"venue"
},
  "geometry": {"coordinates":[4.2633619308,51.2079582214],"type":"Point"}
}