{
  "type": "Feature",
  "properties": {
    "addr:full":"Vrijheidsplein 3 Lokeren Oost-Vlaanderen 9160",
    "addr:housenumber":"3",
    "addr:postcode":"9160",
    "addr:street":"Vrijheidsplein",
    "iso:country":"BE",
    "sg:address":"Vrijheidsplein 3",
    "sg:city":"Lokeren",
    "sg:orig_category":"Overheidsdiensten",
    "sg:phone":"+32 9 348 49 66",
    "sg:postcode":"9160",
    "sg:province":"Oost-Vlaanderen",
    "wof:name":"Admin. Directe Belast.",
    "wof:placetype":"venue"
},
  "geometry": {"coordinates":[3.9873409271,51.1018676758],"type":"Point"}
}