{
  "type": "Feature",
  "properties": {
    "iso:country":"BE",
    "sg:address":"Karel Mirystraat 2",
    "sg:city":"Antwerpen",
    "sg:orig_category":"Opvangtehuizen and vluchthuizen",
    "sg:phone":"+32 3 247 88 11",
    "sg:postcode":"2020",
    "sg:province":"Antwerpen",
    "wof:name":"C.a.w. De Mare",
    "wof:placetype":"venue"
},
  "geometry": {"coordinates":[4.3717741966,51.1911697388],"type":"Point"}
}