{
  "type": "Feature",
  "properties": {
    "iso:country":"BE",
    "sg:address":"Asbroekstraat 64",
    "sg:city":"Zoutleeuw (halle-booienhoven)",
    "sg:classifiers":[
        {
            "category":"Professional",
            "subcategory":"Management & Consulting",
            "type":"Services"
        }
    ],
    "sg:phone":"+32 11 78 06 69",
    "sg:postcode":"3440",
    "sg:province":"Vlaams-Brabant",
    "sg:tags":[
        "tax-consultants"
    ],
    "wof:name":"Stragier F",
    "wof:placetype":"venue"
},
  "geometry": {"coordinates":[5.1164708138,50.8071174622],"type":"Point"}
}