{
  "type": "Feature",
  "properties": {
    "addr:full":"Heistraat 56 Antwerpen (wilrijk) Antwerpen 2610",
    "addr:housenumber":"56",
    "addr:postcode":"2610",
    "addr:street":"Heistraat;Antwerpen",
    "iso:country":"BE",
    "sg:address":"Heistraat 56",
    "sg:city":"Antwerpen (wilrijk)",
    "sg:classifiers":[
        {
            "category":"Personal",
            "type":"Services"
        }
    ],
    "sg:phone":"+32 3 295 96 30",
    "sg:postcode":"2610",
    "sg:province":"Antwerpen",
    "sg:tags":[
        "party",
        "planning"
    ],
    "wof:name":"Theadr\u00f4me",
    "wof:placetype":"venue"
},
  "geometry": {"coordinates":[4.3908619881,51.1809959412],"type":"Point"}
}