{
  "type": "Feature",
  "properties": {
    "addr:full":"Tieltsesteenweg 203 Eeklo Oost-Vlaanderen 9900",
    "addr:housenumber":"203",
    "addr:postcode":"9900",
    "addr:street":"Tieltsesteenweg",
    "iso:country":"BE",
    "sg:address":"Tieltsesteenweg 203",
    "sg:city":"Eeklo",
    "sg:orig_category":"Mat\u00e9riel de T\u00e9l\u00e9communication",
    "sg:phone":"+32 9 378 11 36",
    "sg:postcode":"9900",
    "sg:province":"Oost-Vlaanderen",
    "wof:name":"Elektro Groothandel Meetjesland",
    "wof:placetype":"venue"
},
  "geometry": {"coordinates":[3.549808979,51.1781044006],"type":"Point"}
}