{
  "type": "Feature",
  "properties": {
    "iso:country":"BE",
    "sg:address":"Rue Thier Du Moulin 19",
    "sg:city":"Villers-le-bouillet",
    "sg:orig_category":"Artsen and specialisten",
    "sg:phone":"+32 85 23 44 63",
    "sg:postcode":"4530",
    "sg:province":"Li\u00e8ge",
    "wof:name":"P. Pogorzelski",
    "wof:placetype":"venue"
},
  "geometry": {"coordinates":[5.2788901329,50.5643806458],"type":"Point"}
}