{
  "type": "Feature",
  "properties": {
    "iso:country":"BE",
    "sg:address":"Rue De L'ath\u00e9n\u00e9e 17",
    "sg:city":"Mons",
    "sg:classifiers":[
        {
            "category":"Organizations",
            "subcategory":"Community Association",
            "type":"Services"
        }
    ],
    "sg:phone":"+32 65 84 45 77",
    "sg:postcode":"7000",
    "sg:province":"Hainaut",
    "sg:tags":[
        "cultural"
    ],
    "wof:name":"Alphab\u00e9tisation Asbl",
    "wof:placetype":"venue"
},
  "geometry": {"coordinates":[3.9450941086,50.4518356323],"type":"Point"}
}