{
  "type": "Feature",
  "properties": {
    "iso:country":"BE",
    "sg:address":"Stationstraat 27",
    "sg:city":"Hamont-achel",
    "sg:orig_category":"Tijdelijke werkgelegenheid and uitzendkantoren",
    "sg:phone":"+32 11 44 50 15",
    "sg:postcode":"3930",
    "sg:province":"Limburg",
    "wof:name":"Creyf\u00b4s Interim",
    "wof:placetype":"venue"
},
  "geometry": {"coordinates":[5.5450549126,51.2511863708],"type":"Point"}
}