{
  "type": "Feature",
  "properties": {
    "addr:full":"Malmedyer Strasse 20 Sankt Vith Li\u00e8ge 4780",
    "addr:housenumber":"20",
    "addr:postcode":"4780",
    "addr:street":"Malmedyer Strasse",
    "iso:country":"BE",
    "sg:address":"Malmedyer Strasse 20",
    "sg:city":"Sankt Vith",
    "sg:classifiers":[
        {
            "category":"Bars & Pubs",
            "type":"Food & Drink"
        }
    ],
    "sg:phone":"+32 80 22 10 52",
    "sg:postcode":"4780",
    "sg:province":"Li\u00e8ge",
    "sg:tags":[
        "tavern"
    ],
    "wof:name":"Grappa (la)",
    "wof:placetype":"venue"
},
  "geometry": {"coordinates":[6.1234078407,50.2836418152],"type":"Point"}
}