{
  "type": "Feature",
  "properties": {
    "iso:country":"BE",
    "sg:address":"Avenue Coghen 35",
    "sg:city":"Ukkel/uccle",
    "sg:orig_category":"Animations diverses",
    "sg:phone":"+32 2 345 26 93",
    "sg:postcode":"1180",
    "sg:province":"Bruxelles-Capitale",
    "wof:name":"Alpha",
    "wof:placetype":"venue"
},
  "geometry": {"coordinates":[4.340118885,50.8126411438],"type":"Point"}
}