{
  "type": "Feature",
  "properties": {
    "addr:full":"Clos Bourgm. De Keyser 15 Ukkel/uccle Bruxelles-Capitale 1180",
    "addr:housenumber":"15",
    "addr:postcode":"1180",
    "addr:street":"Clos;Keyser;/",
    "iso:country":"BE",
    "sg:address":"Clos Bourgm. De Keyser 15",
    "sg:city":"Ukkel/uccle",
    "sg:orig_category":"Peinture. Rev\u00eatements pour sols and murs",
    "sg:phone":"+32 2 374 31 42",
    "sg:postcode":"1180",
    "sg:province":"Bruxelles-Capitale",
    "wof:name":"Carlos Malnero",
    "wof:placetype":"venue"
},
  "geometry": {"coordinates":[4.3502559662,50.7913818359],"type":"Point"}
}