{
  "type": "Feature",
  "properties": {
    "addr:full":"Nieuwe Steenweg 117 Temse Oost-Vlaanderen 9140",
    "addr:housenumber":"117",
    "addr:postcode":"9140",
    "addr:street":"Nieuwe Steenweg",
    "iso:country":"BE",
    "sg:address":"Nieuwe Steenweg 117",
    "sg:city":"Temse",
    "sg:classifiers":[
        {
            "category":"Autos & Motor Vehicles",
            "subcategory":"Fuel & Gas Station",
            "type":"Retail Goods"
        }
    ],
    "sg:phone":"+32 52 46 04 01",
    "sg:postcode":"9140",
    "sg:province":"Oost-Vlaanderen",
    "sg:tags":[
        "stations-service",
        "carburants"
    ],
    "wof:name":"Esso",
    "wof:placetype":"venue"
},
  "geometry": {"coordinates":[4.1452150345,51.1268005371],"type":"Point"}
}