{
  "type": "Feature",
  "properties": {
    "addr:full":"Ch De Belle-vue 35 Pommeroeul Hainaut 7322",
    "addr:housenumber":"35",
    "addr:postcode":"7322",
    "addr:street":"Ch De Belle-Vue;Hainaut",
    "iso:country":"BE",
    "sg:address":"Ch De Belle-vue 35",
    "sg:city":"Pommeroeul",
    "sg:classifiers":[
        {
            "category":"Health Services",
            "subcategory":"Health Practitioner",
            "type":"Services"
        }
    ],
    "sg:phone":"+32 65 78 32 26",
    "sg:postcode":"7322",
    "sg:province":"Hainaut",
    "sg:tags":[
        "physiotherapist"
    ],
    "wof:name":"Douillez Pascal",
    "wof:placetype":"venue"
},
  "geometry": {"coordinates":[3.7294270992,50.4702835083],"type":"Point"}
}