{
  "type": "Feature",
  "properties": {
    "iso:country":"BE",
    "sg:address":"Mechelsesteenweg 24",
    "sg:city":"Lier",
    "sg:orig_category":"Dranken Gh",
    "sg:phone":"+32 3 480 04 12",
    "sg:postcode":"2500",
    "sg:province":"Antwerpen",
    "wof:name":"Fa. Truyen",
    "wof:placetype":"venue"
},
  "geometry": {"coordinates":[4.5611991882,51.1303482056],"type":"Point"}
}