{
  "type": "Feature",
  "properties": {
    "addr:full":"Steenhouwerslaan 2ba Maldegem Oost-Vlaanderen 9990",
    "addr:housenumber":"2ba",
    "addr:postcode":"9990",
    "addr:street":"Steenhouwerslaan",
    "iso:country":"BE",
    "sg:address":"Steenhouwerslaan 2ba",
    "sg:city":"Maldegem",
    "sg:orig_category":"Installatie van houten of kunststof schrijnwerk Woningbouw",
    "sg:phone":"+32 50 71 78 80",
    "sg:postcode":"9990",
    "sg:province":"Oost-Vlaanderen",
    "wof:name":"Armaca",
    "wof:placetype":"venue"
},
  "geometry": {"coordinates":[3.4702539444,51.1944732666],"type":"Point"}
}