{
  "type": "Feature",
  "properties": {
    "addr:full":"Diestsesteenweg 261 Aarschot (rillaar) Vlaams-Brabant 3202",
    "addr:housenumber":"261",
    "addr:postcode":"3202",
    "addr:street":"Diestsesteenweg",
    "iso:country":"BE",
    "sg:address":"Diestsesteenweg 261",
    "sg:city":"Aarschot (rillaar)",
    "sg:classifiers":[
        {
            "category":"Professional",
            "subcategory":"Lawyer & Legal Services",
            "type":"Services"
        }
    ],
    "sg:phone":"+32 16 50 24 20",
    "sg:postcode":"3202",
    "sg:province":"Vlaams-Brabant",
    "sg:tags":[
        "notary"
    ],
    "wof:name":"Boogaerts P",
    "wof:placetype":"venue"
},
  "geometry": {"coordinates":[4.8886737823,50.975063324],"type":"Point"}
}