{
  "type": "Feature",
  "properties": {
    "iso:country":"BE",
    "sg:address":"Hooghuisgaverstraat 4",
    "sg:city":"Zingem",
    "sg:orig_category":"Eleveurs de bovins. Eleveurs and marchands de porcs",
    "sg:phone":"+32 9 384 11 69",
    "sg:postcode":"9750",
    "sg:province":"Oost-Vlaanderen",
    "wof:name":"Eddy Van Hove",
    "wof:placetype":"venue"
},
  "geometry": {"coordinates":[3.6519870758,50.9060554504],"type":"Point"}
}