{
  "type": "Feature",
  "properties": {
    "iso:country":"BE",
    "sg:address":"Destelbergenstraat 52",
    "sg:city":"Gent (sint-amandsberg)",
    "sg:classifiers":[
        {
            "category":"Building & Trades",
            "subcategory":"Electrical",
            "type":"Services"
        }
    ],
    "sg:phone":"+32 9 229 24 43",
    "sg:postcode":"9040",
    "sg:province":"Oost-Vlaanderen",
    "sg:tags":[
        "electric",
        "-",
        "housewiring",
        "contractor"
    ],
    "wof:name":"Alg. Electr.w. Vander Minnen Bvba",
    "wof:placetype":"venue"
},
  "geometry": {"coordinates":[3.755286932,51.0503616333],"type":"Point"}
}