{
  "type": "Feature",
  "properties": {
    "addr:full":"Rue Nazarethbattice 16 Battice Li\u00e8ge 4651",
    "addr:housenumber":"16",
    "addr:postcode":"4651",
    "addr:street":"Rue Nazarethbattice",
    "iso:country":"BE",
    "sg:address":"Rue Nazarethbattice 16",
    "sg:city":"Battice",
    "sg:orig_category":"Heating And Furnace Controls",
    "sg:phone":"+32 87 67 98 50",
    "sg:postcode":"4651",
    "sg:province":"Li\u00e8ge",
    "wof:name":"Era S.p.r.l.",
    "wof:placetype":"venue"
},
  "geometry": {"coordinates":[5.837928772,50.6389312744],"type":"Point"}
}