{
  "type": "Feature",
  "properties": {
    "addr:full":"Katersberg 120 Geel Antwerpen 2440",
    "addr:housenumber":"120",
    "addr:postcode":"2440",
    "addr:street":"Katersberg",
    "iso:country":"BE",
    "sg:address":"Katersberg 120",
    "sg:city":"Geel",
    "sg:orig_category":"Agences de publicit\u00e9",
    "sg:phone":"+32 14 58 35 75",
    "sg:postcode":"2440",
    "sg:province":"Antwerpen",
    "wof:name":"Publi Delta",
    "wof:placetype":"venue"
},
  "geometry": {"coordinates":[5.0027580261,51.1800918579],"type":"Point"}
}