{
  "type": "Feature",
  "properties": {
    "iso:country":"BE",
    "sg:address":"Ganzendries 204",
    "sg:city":"Gent",
    "sg:classifiers":[
        {
            "category":"Cafe",
            "type":"Food & Drink"
        }
    ],
    "sg:phone":"+32 9 220 73 76",
    "sg:postcode":"9000",
    "sg:province":"Oost-Vlaanderen",
    "sg:tags":[
        "snack-bars"
    ],
    "wof:name":"Crocque-americain",
    "wof:placetype":"venue"
},
  "geometry": {"coordinates":[3.7110230923,51.0342445374],"type":"Point"}
}