{
  "type": "Feature",
  "properties": {
    "addr:full":"Sint-amandsplein 15 Grimbergen (strombeek-bever) Vlaams-Brabant 1853",
    "addr:housenumber":"15",
    "addr:postcode":"1853",
    "addr:street":"Sint-Amandsplein",
    "iso:country":"BE",
    "sg:address":"Sint-amandsplein 15",
    "sg:city":"Grimbergen (strombeek-bever)",
    "sg:classifiers":[
        {
            "category":"Personal",
            "subcategory":"Barber",
            "type":"Services"
        }
    ],
    "sg:phone":"+32 2 267 06 14",
    "sg:postcode":"1853",
    "sg:province":"Vlaams-Brabant",
    "sg:tags":[
        "gentleman",
        "salon",
        "-",
        "hairdressing"
    ],
    "wof:name":"Men's Coiffure Edouard",
    "wof:placetype":"venue"
},
  "geometry": {"coordinates":[4.3549771309,50.910030365],"type":"Point"}
}