{
  "type": "Feature",
  "properties": {
    "iso:country":"BE",
    "sg:address":"Leopoldplein 42",
    "sg:city":"Nieuwpoort",
    "sg:orig_category":"Installation de menuiserie en bois and plastique",
    "sg:phone":"+32 58 23 79 76",
    "sg:postcode":"8620",
    "sg:province":"West-Vlaanderen",
    "wof:name":"Fa. Ternier Henri & Eric",
    "wof:placetype":"venue"
},
  "geometry": {"coordinates":[2.7108500004,51.1461601257],"type":"Point"}
}