{
  "type": "Feature",
  "properties": {
    "addr:full":"Kasteellaan 158 Gent Oost-Vlaanderen 9000",
    "addr:housenumber":"158",
    "addr:postcode":"9000",
    "addr:street":"Kasteellaan;Oost-Vlaanderen",
    "iso:country":"BE",
    "sg:address":"Kasteellaan 158",
    "sg:city":"Gent",
    "sg:classifiers":[
        {
            "category":"Professional",
            "subcategory":"Lawyer & Legal Services",
            "type":"Services"
        }
    ],
    "sg:phone":"+32 9 224 42 68",
    "sg:postcode":"9000",
    "sg:province":"Oost-Vlaanderen",
    "wof:name":"Strobbe Jan",
    "wof:placetype":"venue"
},
  "geometry": {"coordinates":[3.7408909798,51.0505180359],"type":"Point"}
}