{
  "type": "Feature",
  "properties": {
    "addr:full":"Brusselsesteenweg 439 Mechelen Antwerpen 2800",
    "addr:housenumber":"439",
    "addr:postcode":"2800",
    "addr:street":"Brusselsesteenweg",
    "iso:country":"BE",
    "sg:address":"Brusselsesteenweg 439",
    "sg:city":"Mechelen",
    "sg:orig_category":"Bagage and lederwaren Schoenen",
    "sg:phone":"+32 15 41 01 43",
    "sg:postcode":"2800",
    "sg:province":"Antwerpen",
    "wof:name":"Brantano",
    "wof:placetype":"venue"
},
  "geometry": {"coordinates":[4.4747838974,50.9940185547],"type":"Point"}
}