{
  "type": "Feature",
  "properties": {
    "addr:full":"Rue R Astrid 228 La Louviere Hainaut 7110",
    "addr:housenumber":"228",
    "addr:postcode":"7110",
    "addr:street":"Rue R Astrid",
    "iso:country":"BE",
    "sg:address":"Rue R Astrid 228",
    "sg:city":"La Louviere",
    "sg:orig_category":"Installation \u00e9lectrique r\u00e9sidentielle",
    "sg:phone":"+32 64 67 69 89",
    "sg:postcode":"7110",
    "sg:province":"Hainaut",
    "wof:name":"Flabelec",
    "wof:placetype":"venue"
},
  "geometry": {"coordinates":[4.1505050659,50.4826698303],"type":"Point"}
}