{
  "type": "Feature",
  "properties": {
    "iso:country":"BE",
    "sg:address":"Val De La Berwinne 8",
    "sg:city":"Thimister-clermont (clermont)",
    "sg:classifiers":[
        {
            "category":"Manufacturing",
            "subcategory":"Furniture",
            "type":"Manufacturing & Wholesale Goods"
        }
    ],
    "sg:phone":"+32 87 44 57 56",
    "sg:postcode":"4890",
    "sg:province":"Li\u00e8ge",
    "sg:tags":[
        "made",
        "-",
        "custom"
    ],
    "wof:name":"Koch & Freiter Eb\u00e9nisterie",
    "wof:placetype":"venue"
},
  "geometry": {"coordinates":[5.8969597816,50.6781997681],"type":"Point"}
}