{
  "type": "Feature",
  "properties": {
    "addr:full":"Hazenpad 11 Nijlen Antwerpen 2560",
    "addr:housenumber":"11",
    "addr:postcode":"2560",
    "addr:street":"Hazenpad",
    "iso:country":"BE",
    "sg:address":"Hazenpad 11",
    "sg:city":"Nijlen",
    "sg:orig_category":"Installation \u00e9lectrique industrielle",
    "sg:phone":"+32 3 481 91 13",
    "sg:postcode":"2560",
    "sg:province":"Antwerpen",
    "wof:name":"Lumelux Beveiligingssystemen",
    "wof:placetype":"venue"
},
  "geometry": {"coordinates":[4.6905460358,51.1673202515],"type":"Point"}
}