{
  "type": "Feature",
  "properties": {
    "iso:country":"BE",
    "sg:address":"Bevrijdingslaan 47",
    "sg:city":"Sint-genesius-rode/rhode-saint-genese",
    "sg:orig_category":"Speelgoed",
    "sg:phone":"+32 2 358 39 76",
    "sg:postcode":"1640",
    "sg:province":"Vlaams-Brabant",
    "wof:name":"Bernard Van Schrieck",
    "wof:placetype":"venue"
},
  "geometry": {"coordinates":[4.3652839661,50.755241394],"type":"Point"}
}