{
  "type": "Feature",
  "properties": {
    "addr:full":"Klaaie 19 Brakel Oost-Vlaanderen 9660",
    "addr:housenumber":"19",
    "addr:postcode":"9660",
    "addr:street":"Klaaie",
    "iso:country":"BE",
    "sg:address":"Klaaie 19",
    "sg:city":"Brakel",
    "sg:orig_category":"Eleveurs de bovins",
    "sg:phone":"+32 55 42 10 63",
    "sg:postcode":"9660",
    "sg:province":"Oost-Vlaanderen",
    "wof:name":"Luc Vandorpe",
    "wof:placetype":"venue"
},
  "geometry": {"coordinates":[3.804764986,50.7696456909],"type":"Point"}
}