{
  "type": "Feature",
  "properties": {
    "addr:full":"Schrieksebaan 67 Tremelo Vlaams-Brabant 3120",
    "addr:housenumber":"67",
    "addr:postcode":"3120",
    "addr:street":"Schrieksebaan",
    "iso:country":"BE",
    "sg:address":"Schrieksebaan 67",
    "sg:city":"Tremelo",
    "sg:classifiers":[
        {
            "category":"Shopping",
            "subcategory":"Florist",
            "type":"Retail Goods"
        }
    ],
    "sg:phone":"+32 16 53 13 82",
    "sg:postcode":"3120",
    "sg:province":"Vlaams-Brabant",
    "wof:name":"Van Leemputten",
    "wof:placetype":"venue"
},
  "geometry": {"coordinates":[4.7069411278,50.9934005737],"type":"Point"}
}