{
  "type": "Feature",
  "properties": {
    "addr:full":"Chauss\u00c9e Brunehault 2 Leuze-en-hainaut Hainaut 7903",
    "addr:housenumber":"2",
    "addr:postcode":"7903",
    "addr:street":"Chausse\u0301E Brunehault",
    "iso:country":"BE",
    "sg:address":"Chauss\u00c9e Brunehault 2",
    "sg:city":"Leuze-en-hainaut",
    "sg:orig_category":"Eleveurs de bovins",
    "sg:phone":"+32 69 66 21 90",
    "sg:postcode":"7903",
    "sg:province":"Hainaut",
    "wof:name":"Roger Lefebvre",
    "wof:placetype":"venue"
},
  "geometry": {"coordinates":[3.6909039021,50.5856285095],"type":"Point"}
}