{
  "type": "Feature",
  "properties": {
    "iso:country":"BE",
    "sg:address":"Place De Mesvin 34",
    "sg:city":"Mons (mesvin)",
    "sg:classifiers":[
        {
            "category":"Health Services",
            "subcategory":"Health Practitioner",
            "type":"Services"
        }
    ],
    "sg:phone":"+32 65 84 22 40",
    "sg:postcode":"7022",
    "sg:province":"Hainaut",
    "sg:tags":[
        "physiotherapist"
    ],
    "wof:name":"Deprez Laurent",
    "wof:placetype":"venue"
},
  "geometry": {"coordinates":[3.9601809978,50.4293556213],"type":"Point"}
}