{
  "type": "Feature",
  "properties": {
    "addr:full":"Rue Bauduin Pierre 5 Huy Li\u00e8ge 4500",
    "addr:housenumber":"5",
    "addr:postcode":"4500",
    "addr:street":"Rue Bauduin Pierre",
    "iso:country":"BE",
    "sg:address":"Rue Bauduin Pierre 5",
    "sg:city":"Huy",
    "sg:orig_category":"Non-Classified Establishments",
    "sg:phone":"+32 85 21 32 71",
    "sg:postcode":"4500",
    "sg:province":"Li\u00e8ge",
    "wof:name":"Mafe Sprl",
    "wof:placetype":"venue"
},
  "geometry": {"coordinates":[5.2347698212,50.5216178894],"type":"Point"}
}