{
  "type": "Feature",
  "properties": {
    "iso:country":"BE",
    "sg:address":"Nieuwstraat 40",
    "sg:city":"Tienen",
    "sg:classifiers":[
        {
            "category":"Restaurant",
            "type":"Food & Drink"
        }
    ],
    "sg:phone":"+32 16 81 52 20",
    "sg:postcode":"3300",
    "sg:province":"Vlaams-Brabant",
    "wof:name":"De Nelson",
    "wof:placetype":"venue"
},
  "geometry": {"coordinates":[4.9398889542,50.80676651],"type":"Point"}
}