{
  "type": "Feature",
  "properties": {
    "addr:full":"Slachthuisstraat 73 Sint-niklaas (groot) Oost-Vlaanderen 9100",
    "addr:housenumber":"73",
    "addr:postcode":"9100",
    "addr:street":"Slachthuisstraat;Groot Oost-Vlaanderen",
    "iso:country":"BE",
    "sg:address":"Slachthuisstraat 73",
    "sg:city":"Sint-niklaas (groot)",
    "sg:classifiers":[
        {
            "category":"Insurance",
            "subcategory":"Life Insurance",
            "type":"Services"
        }
    ],
    "sg:phone":"+32 3 780 78 50",
    "sg:postcode":"9100",
    "sg:province":"Oost-Vlaanderen",
    "sg:tags":[
        "assurance"
    ],
    "wof:name":"Omob",
    "wof:placetype":"venue"
},
  "geometry": {"coordinates":[4.1420168877,51.1736831665],"type":"Point"}
}