{
  "type": "Feature",
  "properties": {
    "addr:full":"Volkslaan 111 Menen West-Vlaanderen 8930",
    "addr:housenumber":"111",
    "addr:postcode":"8930",
    "addr:street":"Volkslaan",
    "iso:country":"BE",
    "sg:address":"Volkslaan 111",
    "sg:city":"Menen",
    "sg:orig_category":"Pharmaciens",
    "sg:phone":"+32 56 51 94 18",
    "sg:postcode":"8930",
    "sg:province":"West-Vlaanderen",
    "wof:name":"Apotheek Ververken",
    "wof:placetype":"venue"
},
  "geometry": {"coordinates":[3.1215109825,50.8064079285],"type":"Point"}
}