{
  "type": "Feature",
  "properties": {
    "addr:full":"Gistelsteenweg 243 Jabbeke West-Vlaanderen 8490",
    "addr:housenumber":"243",
    "addr:postcode":"8490",
    "addr:street":"Gistelsteenweg",
    "iso:country":"BE",
    "sg:address":"Gistelsteenweg 243",
    "sg:city":"Jabbeke",
    "sg:orig_category":"Artiesten and kunstenaars",
    "sg:phone":"+32 50 81 29 22",
    "sg:postcode":"8490",
    "sg:province":"West-Vlaanderen",
    "wof:name":"Lode Blomme",
    "wof:placetype":"venue"
},
  "geometry": {"coordinates":[3.1111450195,51.1791343689],"type":"Point"}
}