{
  "type": "Feature",
  "properties": {
    "iso:country":"BE",
    "sg:address":"Laiche 1",
    "sg:city":"Florenville",
    "sg:orig_category":"Maisons de vacances",
    "sg:phone":"+32 61 31 23 38",
    "sg:postcode":"6824",
    "sg:province":"Luxembourg",
    "wof:name":"Le Marci",
    "wof:placetype":"venue"
},
  "geometry": {"coordinates":[5.2801289558,49.7144203186],"type":"Point"}
}