{
  "type": "Feature",
  "properties": {
    "addr:full":"Rue De La Gare 47 Kelmis/la Calamine Li\u00e8ge 4728",
    "addr:housenumber":"47",
    "addr:postcode":"4728",
    "addr:street":"Rue De La Gare",
    "iso:country":"BE",
    "sg:address":"Rue De La Gare 47",
    "sg:city":"Kelmis/la Calamine",
    "sg:orig_category":"V\u00e9hicules automobiles. Stations-service and carburants",
    "sg:phone":"+32 87 65 97 49",
    "sg:postcode":"4728",
    "sg:province":"Li\u00e8ge",
    "wof:name":"Garage Jungbluth",
    "wof:placetype":"venue"
},
  "geometry": {"coordinates":[6.0384187698,50.708190918],"type":"Point"}
}