{
  "type": "Feature",
  "properties": {
    "iso:country":"BE",
    "sg:address":"Strandlaan 220",
    "sg:city":"Koksijde",
    "sg:classifiers":[
        {
            "category":"Professional",
            "subcategory":"Testing Lab",
            "type":"Services"
        }
    ],
    "sg:phone":"+32 58 52 07 63",
    "sg:postcode":"8670",
    "sg:province":"West-Vlaanderen",
    "sg:tags":[
        "laboratory",
        "medical"
    ],
    "wof:name":"Klinisch Labo Woestyn",
    "wof:placetype":"venue"
},
  "geometry": {"coordinates":[2.6492800713,51.1061401367],"type":"Point"}
}