{
  "type": "Feature",
  "properties": {
    "iso:country":"BE",
    "sg:address":"Steegstraat 52",
    "sg:city":"Balen",
    "sg:orig_category":"Non-Classified Establishments",
    "sg:phone":"+32 14 81 11 31",
    "sg:postcode":"2490",
    "sg:province":"Antwerpen",
    "wof:name":"Delsupehe For Fashion Modecenter Nv",
    "wof:placetype":"venue"
},
  "geometry": {"coordinates":[5.1720972061,51.168006897],"type":"Point"}
}