{
  "type": "Feature",
  "properties": {
    "addr:full":"35 Rue De Stassart Brussels Bruxelles-Capitale 1050",
    "addr:housenumber":"35",
    "addr:postcode":"1050",
    "addr:street":"Rue De Stassart",
    "iso:country":"BE",
    "sg:address":"35 Rue De Stassart",
    "sg:city":"Brussels",
    "sg:classifiers":[
        {
            "category":"Industrial Area",
            "type":"Public Place"
        }
    ],
    "sg:phone":"+32 51 26 61 11",
    "sg:postcode":"1050",
    "sg:province":"Bruxelles-Capitale",
    "sg:tags":[
        "large",
        "private"
    ],
    "wof:name":"Roularta Media Group Nv",
    "wof:placetype":"venue"
},
  "geometry": {"coordinates":[3.1183199883,50.9344482422],"type":"Point"}
}