{
  "type": "Feature",
  "properties": {
    "iso:country":"BE",
    "sg:address":"Technologielaan 21",
    "sg:city":"Leuven",
    "sg:orig_category":"R\u00e9alisation de programmes and logiciels",
    "sg:phone":"+32 16 39 63 00",
    "sg:postcode":"3001",
    "sg:province":"Vlaams-Brabant",
    "wof:name":"Co Ware",
    "wof:placetype":"venue"
},
  "geometry": {"coordinates":[4.7350292206,50.8508453369],"type":"Point"}
}