{
  "type": "Feature",
  "properties": {
    "iso:country":"BE",
    "sg:address":"Livinus Walravenslaan 2a",
    "sg:city":"Dilbeek",
    "sg:classifiers":[
        {
            "category":"Manufacturing",
            "subcategory":"Musical Instruments",
            "type":"Manufacturing & Wholesale Goods"
        }
    ],
    "sg:phone":"+32 2 567 96 42",
    "sg:postcode":"1700",
    "sg:province":"Vlaams-Brabant",
    "sg:tags":[
        "piano"
    ],
    "wof:name":"Piano's Van De Winkel Bvba",
    "wof:placetype":"venue"
},
  "geometry": {"coordinates":[4.2769861221,50.8445854187],"type":"Point"}
}