{
  "type": "Feature",
  "properties": {
    "iso:country":"BE",
    "sg:address":"Liersesteenweg 321",
    "sg:city":"Begijnendijk",
    "sg:classifiers":[
        {
            "category":"Shopping",
            "subcategory":"Crafts & Fabrics",
            "type":"Retail Goods"
        }
    ],
    "sg:phone":"+32 16 56 10 62",
    "sg:postcode":"3130",
    "sg:province":"Vlaams-Brabant",
    "sg:tags":[
        "hi-fi",
        "equipment",
        "stereophonic",
        "-"
    ],
    "wof:name":"Audiomix Hifi Bvba",
    "wof:placetype":"venue"
},
  "geometry": {"coordinates":[4.8095059395,51.0108757019],"type":"Point"}
}