{
  "type": "Feature",
  "properties": {
    "addr:full":"Rue Du Pont D'arcole 226 Charleroi (gilly) Hainaut 6060",
    "addr:housenumber":"226",
    "addr:postcode":"6060",
    "addr:street":"Rue Du Pont D'Arcole",
    "iso:country":"BE",
    "sg:address":"Rue Du Pont D'arcole 226",
    "sg:city":"Charleroi (gilly)",
    "sg:classifiers":[
        {
            "category":"Arena",
            "subcategory":"Sports Club",
            "type":"Entertainment"
        }
    ],
    "sg:phone":"+32 71 41 21 10",
    "sg:postcode":"6060",
    "sg:province":"Hainaut",
    "sg:tags":[
        "federation"
    ],
    "wof:name":"Tyou L",
    "wof:placetype":"venue"
},
  "geometry": {"coordinates":[4.5028557777,50.4331474304],"type":"Point"}
}