{
  "type": "Feature",
  "properties": {
    "iso:country":"BE",
    "sg:address":"Binnendijkstr 3",
    "sg:city":"Bornem-weert",
    "sg:classifiers":[
        {
            "category":"Shopping",
            "subcategory":"Hobbies, Toys, & Games",
            "type":"Retail Goods"
        }
    ],
    "sg:phone":"+32 3 889 00 56",
    "sg:postcode":"2880",
    "sg:province":"Antwerpen",
    "sg:tags":[
        "product",
        "miscellaneous",
        "entertainment"
    ],
    "wof:name":"Iene Miene Mutte Bvba",
    "wof:placetype":"venue"
},
  "geometry": {"coordinates":[4.268225193,51.1032791138],"type":"Point"}
}