{
  "type": "Feature",
  "properties": {
    "iso:country":"BE",
    "sg:address":"Otegemse Steenweg 46",
    "sg:city":"Deerlijk",
    "sg:classifiers":[
        {
            "category":"Building & Trades",
            "subcategory":"Cleaning & Sanitation",
            "type":"Services"
        }
    ],
    "sg:phone":"+32 56 75 54 13",
    "sg:postcode":"8540",
    "sg:province":"West-Vlaanderen",
    "sg:tags":[
        "fa\u00e7ade",
        "maintenance"
    ],
    "wof:name":"M.b. Clean",
    "wof:placetype":"venue"
},
  "geometry": {"coordinates":[3.3765609264,50.8153800964],"type":"Point"}
}