{
  "type": "Feature",
  "properties": {
    "iso:country":"BE",
    "sg:address":"Rue De La Hocaille 9",
    "sg:city":"Grez-doiceau (archennes)",
    "sg:classifiers":[
        {
            "category":"Real Estate",
            "subcategory":"Architect",
            "type":"Services"
        }
    ],
    "sg:phone":"+32 10 84 64 97",
    "sg:postcode":"1390",
    "sg:province":"Brabant Wallon",
    "wof:name":"Pecheur S",
    "wof:placetype":"venue"
},
  "geometry": {"coordinates":[4.6767029762,50.7523040771],"type":"Point"}
}