{
  "type": "Feature",
  "properties": {
    "addr:full":"Guillaume Crocklaan 41 Oudergem/auderghem Bruxelles-Capitale 1160",
    "addr:housenumber":"41",
    "addr:postcode":"1160",
    "addr:street":"Guillaume Crocklaan;/",
    "iso:country":"BE",
    "sg:address":"Guillaume Crocklaan 41",
    "sg:city":"Oudergem/auderghem",
    "sg:orig_category":"Beheer onroerend goed",
    "sg:phone":"+32 2 673 47 85",
    "sg:postcode":"1160",
    "sg:province":"Bruxelles-Capitale",
    "wof:name":"Guy Sabaux",
    "wof:placetype":"venue"
},
  "geometry": {"coordinates":[4.4207930565,50.8115081787],"type":"Point"}
}