{
  "type": "Feature",
  "properties": {
    "addr:full":"Prins De Merodelaan 1 Averbode Vlaams-Brabant 3271",
    "addr:housenumber":"1",
    "addr:postcode":"3271",
    "addr:street":"Prins De Merodelaan",
    "iso:country":"BE",
    "sg:address":"Prins De Merodelaan 1",
    "sg:city":"Averbode",
    "sg:classifiers":[
        {
            "category":"Travel",
            "subcategory":"Hotels & Motels",
            "type":"Entertainment"
        }
    ],
    "sg:phone":"+32 13 77 10 67",
    "sg:postcode":"3271",
    "sg:province":"Vlaams-Brabant",
    "sg:tags":[
        "restaurant"
    ],
    "wof:name":"Hotel St.norbertus",
    "wof:placetype":"venue"
},
  "geometry": {"coordinates":[4.9819488525,51.0293579102],"type":"Point"}
}