{
  "type": "Feature",
  "properties": {
    "iso:country":"BE",
    "sg:address":"Avenue Du Br\u00c9sil 3",
    "sg:city":"Brussel/bruxelles",
    "sg:classifiers":[
        {
            "category":"Building & Trades",
            "subcategory":"Landscaping Services",
            "type":"Services"
        }
    ],
    "sg:phone":"+32 2 660 00 20",
    "sg:postcode":"1000",
    "sg:province":"Bruxelles-Capitale",
    "sg:tags":[
        "etude",
        "technique",
        "ing\u00e9nierie"
    ],
    "wof:name":"Ciet Ii",
    "wof:placetype":"venue"
},
  "geometry": {"coordinates":[4.3887500763,50.8025398254],"type":"Point"}
}