{
  "type": "Feature",
  "properties": {
    "iso:country":"BE",
    "sg:address":"Gerhagen 5",
    "sg:city":"Olen",
    "sg:classifiers":[
        {
            "category":"Bars & Pubs",
            "type":"Food & Drink"
        }
    ],
    "sg:phone":"+32 14 21 21 88",
    "sg:postcode":"2250",
    "sg:province":"Antwerpen",
    "wof:name":"Franskes Place",
    "wof:placetype":"venue"
},
  "geometry": {"coordinates":[4.9124798775,51.1634407043],"type":"Point"}
}