{
  "type": "Feature",
  "properties": {
    "addr:full":"Oude Houtlei 130 Gent Oost-Vlaanderen 9000",
    "addr:housenumber":"130",
    "addr:postcode":"9000",
    "addr:street":"Oude Houtlei;Oost-Vlaanderen",
    "iso:country":"BE",
    "sg:address":"Oude Houtlei 130",
    "sg:city":"Gent",
    "sg:orig_category":"Activit\u00e9s diverses d'imprimerie",
    "sg:phone":"+32 9 233 38 08",
    "sg:postcode":"9000",
    "sg:province":"Oost-Vlaanderen",
    "wof:name":"Groep Damp",
    "wof:placetype":"venue"
},
  "geometry": {"coordinates":[3.7168910503,51.0509796143],"type":"Point"}
}