{
  "type": "Feature",
  "properties": {
    "iso:country":"BE",
    "sg:address":"Leopold I Straat 409",
    "sg:city":"Jette",
    "sg:orig_category":"Diverse meubelen Fab Elektrische installaties voor woningen Loodgieterij, verwarming and sanitaire i",
    "sg:phone":"+32 2 426 42 00",
    "sg:postcode":"1090",
    "sg:province":"Bruxelles-Capitale",
    "wof:name":"Soc. Europ. Distr. & Imp.",
    "wof:placetype":"venue"
},
  "geometry": {"coordinates":[4.3331670761,50.8747558594],"type":"Point"}
}