{
  "type": "Feature",
  "properties": {
    "addr:full":"Nieuwe Boekhoutestraat 28ba Assenede Oost-Vlaanderen 9968",
    "addr:housenumber":"28ba",
    "addr:postcode":"9968",
    "addr:street":"Nieuwe Boekhoutestraat",
    "iso:country":"BE",
    "sg:address":"Nieuwe Boekhoutestraat 28ba",
    "sg:city":"Assenede",
    "sg:orig_category":"V\u00e9t\u00e9rinaires",
    "sg:phone":"+32 9 373 93 40",
    "sg:postcode":"9968",
    "sg:province":"Oost-Vlaanderen",
    "wof:name":"Koen Van De Velde",
    "wof:placetype":"venue"
},
  "geometry": {"coordinates":[3.6812028885,51.2313995361],"type":"Point"}
}