{
  "type": "Feature",
  "properties": {
    "iso:country":"BE",
    "sg:address":"Vest 6",
    "sg:city":"Herselt",
    "sg:classifiers":[
        {
            "category":"Home & Garden",
            "subcategory":"Carpets & Floor Coverings",
            "type":"Retail Goods"
        }
    ],
    "sg:phone":"+32 14 54 29 01",
    "sg:postcode":"2230",
    "sg:province":"Antwerpen",
    "sg:tags":[
        "parquet"
    ],
    "wof:name":"A.w.i.",
    "wof:placetype":"venue"
},
  "geometry": {"coordinates":[4.8832697868,51.055809021],"type":"Point"}
}