{
  "type": "Feature",
  "properties": {
    "addr:full":"Boulevard H. Rollin 2b Waterloo Brabant Wallon 1410",
    "addr:housenumber":"2b",
    "addr:postcode":"1410",
    "addr:street":"Boulevard H. Rollin",
    "iso:country":"BE",
    "sg:address":"Boulevard H. Rollin 2b",
    "sg:city":"Waterloo",
    "sg:orig_category":"Mat\u00e9riel de T\u00e9l\u00e9communication",
    "sg:phone":"+32 2 351 51 21",
    "sg:postcode":"1410",
    "sg:province":"Brabant Wallon",
    "wof:name":"Action Shop",
    "wof:placetype":"venue"
},
  "geometry": {"coordinates":[4.3980250359,50.7174263],"type":"Point"}
}