{
  "type": "Feature",
  "properties": {
    "addr:full":"Rue De Mons 63 Tubize Brabant Wallon 1480",
    "addr:housenumber":"63",
    "addr:postcode":"1480",
    "addr:street":"Rue De Mons;Wallon",
    "iso:country":"BE",
    "sg:address":"Rue De Mons 63",
    "sg:city":"Tubize",
    "sg:orig_category":"Parfumeries",
    "sg:phone":"+32 2 355 35 50",
    "sg:postcode":"1480",
    "sg:province":"Brabant Wallon",
    "wof:name":"Parfumerie De Paris",
    "wof:placetype":"venue"
},
  "geometry": {"coordinates":[4.2027258873,50.6907958984],"type":"Point"}
}