{
  "type": "Feature",
  "properties": {
    "addr:full":"Wespelaarsebaan 91 Boortmeerbeek Vlaams-Brabant 3190",
    "addr:housenumber":"91",
    "addr:postcode":"3190",
    "addr:street":"Wespelaarsebaan",
    "iso:country":"BE",
    "sg:address":"Wespelaarsebaan 91",
    "sg:city":"Boortmeerbeek",
    "sg:classifiers":[
        {
            "category":"Insurance",
            "subcategory":"Insurance Agent",
            "type":"Services"
        }
    ],
    "sg:phone":"+32 15 52 90 20",
    "sg:postcode":"3190",
    "sg:province":"Vlaams-Brabant",
    "sg:tags":[
        "verzekeringsmakelaars",
        "expert"
    ],
    "wof:name":"R. Vanherp",
    "wof:placetype":"venue"
},
  "geometry": {"coordinates":[4.5829901695,50.9778327942],"type":"Point"}
}