{
  "type": "Feature",
  "properties": {
    "iso:country":"BE",
    "sg:address":"Rue Jean-lambert Sauveur 60",
    "sg:city":"Herstal",
    "sg:classifiers":[
        {
            "category":"Military Area",
            "subcategory":"Air Force Base",
            "type":"Public Place"
        }
    ],
    "sg:phone":"+32 4 264 20 22",
    "sg:postcode":"4040",
    "sg:province":"Li\u00e8ge",
    "sg:tags":[
        "gear"
    ],
    "wof:name":"Dighaye A Sprl",
    "wof:placetype":"venue"
},
  "geometry": {"coordinates":[5.6295962334,50.6741943359],"type":"Point"}
}