{
  "type": "Feature",
  "properties": {
    "addr:full":"Gaston Burssenslaan 3 Antwerpen Antwerpen 2050",
    "addr:housenumber":"3",
    "addr:postcode":"2050",
    "addr:street":"Burssenslaan",
    "iso:country":"BE",
    "sg:address":"Gaston Burssenslaan 3",
    "sg:city":"Antwerpen",
    "sg:orig_category":"Epiceries",
    "sg:phone":"+32 3 219 51 52",
    "sg:postcode":"2050",
    "sg:province":"Antwerpen",
    "wof:name":"Jean-pierre Sels",
    "wof:placetype":"venue"
},
  "geometry": {"coordinates":[4.3821959496,51.2191429138],"type":"Point"}
}