{
  "type": "Feature",
  "properties": {
    "addr:full":"Heistraat 318 Antwerpen (wilrijk) Antwerpen 2610",
    "addr:housenumber":"318",
    "addr:postcode":"2610",
    "addr:street":"Heistraat;Antwerpen",
    "iso:country":"BE",
    "sg:address":"Heistraat 318",
    "sg:city":"Antwerpen (wilrijk)",
    "sg:classifiers":[
        {
            "category":"Shopping",
            "subcategory":"Florist",
            "type":"Retail Goods"
        }
    ],
    "sg:phone":"+32 3 830 58 94",
    "sg:postcode":"2610",
    "sg:province":"Antwerpen",
    "sg:tags":[
        "-",
        "supply"
    ],
    "wof:name":"Utopia Bvba",
    "wof:placetype":"venue"
},
  "geometry": {"coordinates":[4.3908619881,51.1809959412],"type":"Point"}
}