{
  "type": "Feature",
  "properties": {
    "addr:full":"Rossemdorp 4 Meise Vlaams-Brabant 1861",
    "addr:housenumber":"4",
    "addr:postcode":"1861",
    "addr:street":"Rossemdorp",
    "iso:country":"BE",
    "sg:address":"Rossemdorp 4",
    "sg:city":"Meise",
    "sg:orig_category":"Boucheries",
    "sg:phone":"+32 52 37 08 38",
    "sg:postcode":"1861",
    "sg:province":"Vlaams-Brabant",
    "wof:name":"Marie-jose De Boeck",
    "wof:placetype":"venue"
},
  "geometry": {"coordinates":[4.2766799927,50.9727210999],"type":"Point"}
}