{
  "type": "Feature",
  "properties": {
    "iso:country":"BE",
    "sg:address":"Chauss\u00c9e De Bruxelles 402",
    "sg:city":"Charleroi",
    "sg:orig_category":"Herstellingen and onderhoud aan huis voor voertuigen Metaalafval, schrootrecyclage and sloperijen On",
    "sg:phone":"+32 71 37 03 31",
    "sg:postcode":"6040",
    "sg:province":"Hainaut",
    "wof:name":"Fe. Vulcarpneu",
    "wof:placetype":"venue"
},
  "geometry": {"coordinates":[4.4316649437,50.4560890198],"type":"Point"}
}