{
  "type": "Feature",
  "properties": {
    "addr:full":"Place De Lille 10 Tournai Hainaut 7500",
    "addr:housenumber":"10",
    "addr:postcode":"7500",
    "addr:street":"Place De Lille",
    "iso:country":"BE",
    "sg:address":"Place De Lille 10",
    "sg:city":"Tournai",
    "sg:orig_category":"Pain, p\u00e2tisseries and confiseries",
    "sg:phone":"+32 69 84 78 16",
    "sg:postcode":"7500",
    "sg:province":"Hainaut",
    "wof:name":"Maison Leger",
    "wof:placetype":"venue"
},
  "geometry": {"coordinates":[3.380546093,50.6066169739],"type":"Point"}
}