{
  "type": "Feature",
  "properties": {
    "iso:country":"BE",
    "sg:address":"Fabriekstraat 139",
    "sg:city":"Beveren",
    "sg:orig_category":"Eleveurs and marchands de porcs",
    "sg:phone":"+32 3 575 09 53",
    "sg:postcode":"9120",
    "sg:province":"Oost-Vlaanderen",
    "wof:name":"Gilbert Van Hoorebeke",
    "wof:placetype":"venue"
},
  "geometry": {"coordinates":[4.2745127678,51.2581138611],"type":"Point"}
}