{
  "type": "Feature",
  "properties": {
    "addr:full":"Chaussee Houtart 319 Houdeng Goegnies Hainaut 7070",
    "addr:housenumber":"319",
    "addr:postcode":"7070",
    "addr:street":"Houdeng Goegnies Hainaut",
    "iso:country":"BE",
    "sg:address":"Chaussee Houtart 319",
    "sg:city":"Houdeng Goegnies",
    "sg:classifiers":[
        {
            "category":"Banks & Credit Unions",
            "subcategory":"Bank",
            "type":"Services"
        }
    ],
    "sg:phone":"+32 64 22 09 34",
    "sg:postcode":"7070",
    "sg:province":"Hainaut",
    "wof:name":"Aslk-cger Bank",
    "wof:placetype":"venue"
},
  "geometry": {"coordinates":[4.1086750031,50.5015830994],"type":"Point"}
}