{
  "type": "Feature",
  "properties": {
    "addr:full":"Avenue De L'abbaye 14 Anthisnes Li\u00e8ge 4160",
    "addr:housenumber":"14",
    "addr:postcode":"4160",
    "addr:street":"Avenue De L'Abbaye",
    "iso:country":"BE",
    "sg:address":"Avenue De L'abbaye 14",
    "sg:city":"Anthisnes",
    "sg:orig_category":"Apotheken",
    "sg:phone":"+32 4 383 62 12",
    "sg:postcode":"4160",
    "sg:province":"Li\u00e8ge",
    "wof:name":"P. Wagner",
    "wof:placetype":"venue"
},
  "geometry": {"coordinates":[5.5226302147,50.4793357849],"type":"Point"}
}