{
  "type": "Feature",
  "properties": {
    "iso:country":"BE",
    "sg:address":"Willem De Roolaan 1",
    "sg:city":"Nieuwpoort",
    "sg:orig_category":"Enseignement maternel and primaire",
    "sg:phone":"+32 58 23 22 11",
    "sg:postcode":"8620",
    "sg:province":"West-Vlaanderen",
    "wof:name":"Kleuterschool",
    "wof:placetype":"venue"
},
  "geometry": {"coordinates":[2.7565801144,51.1318283081],"type":"Point"}
}