{
  "type": "Feature",
  "properties": {
    "iso:country":"BE",
    "sg:address":"Chem De La Guelenne 66",
    "sg:city":"Soignies",
    "sg:classifiers":[
        {
            "category":"Manufacturing",
            "subcategory":"Printing",
            "type":"Manufacturing & Wholesale Goods"
        }
    ],
    "sg:phone":"+32 67 33 41 48",
    "sg:postcode":"7060",
    "sg:province":"Hainaut",
    "sg:tags":[
        "publishing"
    ],
    "wof:name":"Garnier Poisonnet-vuillard Belgique Sa",
    "wof:placetype":"venue"
},
  "geometry": {"coordinates":[4.0734601021,50.5891609192],"type":"Point"}
}