{
  "type": "Feature",
  "properties": {
    "addr:full":"Hulststraat 16 Aarschot Vlaams-Brabant 3201",
    "addr:housenumber":"16",
    "addr:postcode":"3201",
    "addr:street":"Hulststraat",
    "iso:country":"BE",
    "sg:address":"Hulststraat 16",
    "sg:city":"Aarschot",
    "sg:classifiers":[
        {
            "category":"Personal",
            "subcategory":"Beauty Salon",
            "type":"Services"
        }
    ],
    "sg:phone":"+32 16 56 42 93",
    "sg:postcode":"3201",
    "sg:province":"Vlaams-Brabant",
    "sg:tags":[
        "de",
        "coiffure"
    ],
    "wof:name":"Kapsalon Hilde",
    "wof:placetype":"venue"
},
  "geometry": {"coordinates":[4.8749079704,51.0051498413],"type":"Point"}
}