{
  "type": "Feature",
  "properties": {
    "addr:full":"Rue D'harscamp 48 Li\u00e8ge 1 (li\u00e8ge 2) Li\u00e8ge 4020",
    "addr:housenumber":"48;1;2",
    "addr:postcode":"4020",
    "addr:street":"Rue D'Harscamp",
    "iso:country":"BE",
    "sg:address":"Rue D'harscamp 48",
    "sg:city":"Li\u00e8ge 1 (li\u00e8ge 2)",
    "sg:classifiers":[
        {
            "category":"Cafe",
            "type":"Food & Drink"
        }
    ],
    "sg:phone":"+32 4 344 04 96",
    "sg:postcode":"4020",
    "sg:province":"Li\u00e8ge",
    "sg:tags":[
        "snack-bars"
    ],
    "wof:name":"Regala (la)",
    "wof:placetype":"venue"
},
  "geometry": {"coordinates":[5.5799150467,50.6335449219],"type":"Point"}
}