{
  "type": "Feature",
  "properties": {
    "iso:country":"BE",
    "sg:address":"Rue Corneil Gomz\u00c9 21bb",
    "sg:city":"Verviers",
    "sg:orig_category":"Evaluation and estimation de biens immobiliers. G\u00e9om\u00e8tres",
    "sg:phone":"+32 87 22 17 74",
    "sg:postcode":"4800",
    "sg:province":"Li\u00e8ge",
    "wof:name":"Robert Michaux",
    "wof:placetype":"venue"
},
  "geometry": {"coordinates":[5.8704600334,50.5820503235],"type":"Point"}
}