{
  "type": "Feature",
  "properties": {
    "iso:country":"BE",
    "sg:address":"Rue De Monin 87ba",
    "sg:city":"Hamois",
    "sg:orig_category":"Woningbouw",
    "sg:phone":"+32 83 61 24 74",
    "sg:postcode":"5362",
    "sg:province":"Namur",
    "wof:name":"Coulon C",
    "wof:placetype":"venue"
},
  "geometry": {"coordinates":[5.1487522125,50.3143234253],"type":"Point"}
}