{
  "type": "Feature",
  "properties": {
    "iso:country":"BE",
    "sg:address":"Rooberg 30",
    "sg:city":"Oosterzele",
    "sg:orig_category":"Verplichte sociale verzekeringen",
    "sg:phone":"+32 9 362 55 42",
    "sg:postcode":"9860",
    "sg:province":"Oost-Vlaanderen",
    "wof:name":"Liberale Mutualiteit",
    "wof:placetype":"venue"
},
  "geometry": {"coordinates":[3.8028619289,50.9645271301],"type":"Point"}
}