{
  "type": "Feature",
  "properties": {
    "iso:country":"BE",
    "sg:address":"Stenemolenstraat 8",
    "sg:city":"Buggenhout",
    "sg:orig_category":"V\u00e9t\u00e9rinaires",
    "sg:phone":"+32 52 34 23 19",
    "sg:postcode":"9255",
    "sg:province":"Oost-Vlaanderen",
    "wof:name":"Michel Baets",
    "wof:placetype":"venue"
},
  "geometry": {"coordinates":[4.2018060684,51.0139122009],"type":"Point"}
}