{
  "type": "Feature",
  "properties": {
    "addr:full":"Huttert 88 Merchtem Vlaams-Brabant 1785",
    "addr:housenumber":"88",
    "addr:postcode":"1785",
    "addr:street":"Huttert",
    "iso:country":"BE",
    "sg:address":"Huttert 88",
    "sg:city":"Merchtem",
    "sg:classifiers":[
        {
            "category":"Arena",
            "subcategory":"Sports Club",
            "type":"Entertainment"
        }
    ],
    "sg:phone":"+32 52 37 35 36",
    "sg:postcode":"1785",
    "sg:province":"Vlaams-Brabant",
    "sg:tags":[
        "de"
    ],
    "wof:name":"W.c. Nachtegaalvrienden",
    "wof:placetype":"venue"
},
  "geometry": {"coordinates":[4.221405983,50.9578895569],"type":"Point"}
}