{
  "type": "Feature",
  "properties": {
    "addr:full":"Rue Albert Ier 16 Montigny-le-tilleul Hainaut 6111",
    "addr:housenumber":"16",
    "addr:postcode":"6111",
    "addr:street":"Rue Albert Ier",
    "iso:country":"BE",
    "sg:address":"Rue Albert Ier 16",
    "sg:city":"Montigny-le-tilleul",
    "sg:classifiers":[
        {
            "category":"Cafe",
            "type":"Food & Drink"
        }
    ],
    "sg:phone":"+32 71 51 50 90",
    "sg:postcode":"6111",
    "sg:province":"Hainaut",
    "sg:tags":[
        "caf\u00e9s"
    ],
    "wof:name":"Lovasz-mouraux & Fils",
    "wof:placetype":"venue"
},
  "geometry": {"coordinates":[4.3517651558,50.3781700134],"type":"Point"}
}