{
  "type": "Feature",
  "properties": {
    "iso:country":"BE",
    "sg:address":"Rue Martin Legros 4",
    "sg:city":"Malmedy",
    "sg:orig_category":"Non-Classified Establishments",
    "sg:phone":"+32 80 77 16 84",
    "sg:postcode":"4960",
    "sg:province":"Li\u00e8ge",
    "wof:name":"International Sport Services",
    "wof:placetype":"venue"
},
  "geometry": {"coordinates":[6.0177869797,50.4217033386],"type":"Point"}
}