{
  "type": "Feature",
  "properties": {
    "iso:country":"BE",
    "sg:address":"Avenue De La Lib\u00c9ration 0",
    "sg:city":"Mons",
    "sg:orig_category":"Supermarkten",
    "sg:phone":"+32 65 84 40 09",
    "sg:postcode":"7011",
    "sg:province":"Hainaut",
    "wof:name":"Intermarch\u00c9",
    "wof:placetype":"venue"
},
  "geometry": {"coordinates":[3.912539959,50.4712982178],"type":"Point"}
}