{
  "type": "Feature",
  "properties": {
    "addr:full":"Van Iseghemlaan 62 Oostende West-Vlaanderen 8400",
    "addr:housenumber":"62",
    "addr:postcode":"8400",
    "addr:street":"Iseghemlaan",
    "iso:country":"BE",
    "sg:address":"Van Iseghemlaan 62",
    "sg:city":"Oostende",
    "sg:classifiers":[
        {
            "category":"Bars & Pubs",
            "type":"Food & Drink"
        }
    ],
    "sg:phone":"+32 59 80 57 32",
    "sg:postcode":"8400",
    "sg:province":"West-Vlaanderen",
    "wof:name":"La Notte",
    "wof:placetype":"venue"
},
  "geometry": {"coordinates":[2.9134631157,51.2317695618],"type":"Point"}
}