{
  "type": "Feature",
  "properties": {
    "iso:country":"BE",
    "sg:address":"Steenweg Op Kleine Brogel 75",
    "sg:city":"Bocholt",
    "sg:classifiers":[
        {
            "category":"Home & Garden",
            "subcategory":"Carpets & Floor Coverings",
            "type":"Retail Goods"
        }
    ],
    "sg:phone":"+32 11 62 19 62",
    "sg:postcode":"3950",
    "sg:province":"Limburg",
    "sg:tags":[
        "synthetic",
        "machine-woven",
        "carpets"
    ],
    "wof:name":"General Carpet Nv",
    "wof:placetype":"venue"
},
  "geometry": {"coordinates":[5.5010528564,51.1904335022],"type":"Point"}
}