{
  "type": "Feature",
  "properties": {
    "iso:country":"BE",
    "sg:address":"Breendonk-dorp 73",
    "sg:city":"Puurs (breendonk)",
    "sg:classifiers":[
        {
            "category":"Bars & Pubs",
            "type":"Food & Drink"
        }
    ],
    "sg:phone":"+32 3 886 72 33",
    "sg:postcode":"2870",
    "sg:province":"Antwerpen",
    "wof:name":"Vetten Os",
    "wof:placetype":"venue"
},
  "geometry": {"coordinates":[4.3257069588,51.0429725647],"type":"Point"}
}