{
  "type": "Feature",
  "properties": {
    "iso:country":"BE",
    "sg:address":"De Dries 51",
    "sg:city":"Lanaken (gellik)",
    "sg:classifiers":[
        {
            "category":"Communications",
            "subcategory":"Television Station",
            "type":"Services"
        }
    ],
    "sg:phone":"+32 89 71 82 54",
    "sg:postcode":"3620",
    "sg:province":"Limburg",
    "sg:tags":[
        "report",
        "video"
    ],
    "wof:name":"Kidjemet T",
    "wof:placetype":"venue"
},
  "geometry": {"coordinates":[5.6551351547,50.8912277222],"type":"Point"}
}