{
  "type": "Feature",
  "properties": {
    "addr:full":"Rue Bois L'ev\u00eaque 2a Li\u00e8ge 1 Li\u00e8ge 4000",
    "addr:housenumber":"2a;1",
    "addr:postcode":"4000",
    "addr:street":"Rue Bois L'Eve \u0302Que",
    "iso:country":"BE",
    "sg:address":"Rue Bois L'ev\u00eaque 2a",
    "sg:city":"Li\u00e8ge 1",
    "sg:classifiers":[
        {
            "category":"Utilities",
            "subcategory":"Telephone",
            "type":"Services"
        }
    ],
    "sg:phone":"+32 4 252 28 50",
    "sg:postcode":"4000",
    "sg:province":"Li\u00e8ge",
    "sg:tags":[
        "-",
        "internet"
    ],
    "wof:name":"Reality Media Sa",
    "wof:placetype":"venue"
},
  "geometry": {"coordinates":[5.5610179901,50.6287994385],"type":"Point"}
}