{
  "type": "Feature",
  "properties": {
    "addr:full":"Dirk Martensstraat 2b1 Aalst Oost-Vlaanderen 9300",
    "addr:housenumber":"2b1",
    "addr:postcode":"9300",
    "addr:street":"Dirk Martensstraat",
    "iso:country":"BE",
    "sg:address":"Dirk Martensstraat 2b1",
    "sg:city":"Aalst",
    "sg:orig_category":"M\u00e9decines alternatives",
    "sg:phone":"+32 53 21 41 80",
    "sg:postcode":"9300",
    "sg:province":"Oost-Vlaanderen",
    "wof:name":"Futurshape",
    "wof:placetype":"venue"
},
  "geometry": {"coordinates":[4.0348320007,50.9422988892],"type":"Point"}
}