{
  "type": "Feature",
  "properties": {
    "addr:full":"Avenue Du 10i\u00c8me De Ligne 13 Arlon Luxembourg 6700",
    "addr:housenumber":"13",
    "addr:postcode":"6700",
    "addr:street":"Avenue Du 10Ie\u0300Me De Ligne",
    "iso:country":"BE",
    "sg:address":"Avenue Du 10i\u00c8me De Ligne 13",
    "sg:city":"Arlon",
    "sg:orig_category":"Loodgieterij, verwarming and sanitaire installaties",
    "sg:phone":"+32 63 22 10 82",
    "sg:postcode":"6700",
    "sg:province":"Luxembourg",
    "wof:name":"Christian Fievet",
    "wof:placetype":"venue"
},
  "geometry": {"coordinates":[5.8203349113,49.6863098145],"type":"Point"}
}