{
  "type": "Feature",
  "properties": {
    "addr:full":"Meylandtlaan 182 Heusden-zolder (zolder) Limburg 3550",
    "addr:housenumber":"182",
    "addr:postcode":"3550",
    "addr:street":"Meylandtlaan",
    "iso:country":"BE",
    "sg:address":"Meylandtlaan 182",
    "sg:city":"Heusden-zolder (zolder)",
    "sg:classifiers":[
        {
            "category":"Autos & Motor Vehicles",
            "subcategory":"Boat Sales",
            "type":"Retail Goods"
        }
    ],
    "sg:phone":"+32 11 53 38 28",
    "sg:postcode":"3550",
    "sg:province":"Limburg",
    "sg:tags":[
        "automobile",
        "racing",
        "accessory"
    ],
    "wof:name":"Howell Racing Fuel",
    "wof:placetype":"venue"
},
  "geometry": {"coordinates":[5.2966618538,51.0126419067],"type":"Point"}
}