{
  "type": "Feature",
  "properties": {
    "addr:full":"Terhulpensesteenweg 367 Overijse Vlaams-Brabant 3090",
    "addr:housenumber":"367",
    "addr:postcode":"3090",
    "addr:street":"Terhulpensesteenweg",
    "iso:country":"BE",
    "sg:address":"Terhulpensesteenweg 367",
    "sg:city":"Overijse",
    "sg:orig_category":"Herstellingen and onderhoud van auto's Voertuigen",
    "sg:phone":"+32 2 687 37 35",
    "sg:postcode":"3090",
    "sg:province":"Vlaams-Brabant",
    "wof:name":"Garage Hamron",
    "wof:placetype":"venue"
},
  "geometry": {"coordinates":[4.5366621017,50.7620811462],"type":"Point"}
}