{
  "type": "Feature",
  "properties": {
    "iso:country":"BE",
    "sg:address":"Donklaan 293",
    "sg:city":"Berlare",
    "sg:classifiers":[
        {
            "category":"Restaurant",
            "type":"Food & Drink"
        }
    ],
    "sg:phone":"+32 9 367 62 95",
    "sg:postcode":"9290",
    "sg:province":"Oost-Vlaanderen",
    "wof:name":"Wong",
    "wof:placetype":"venue"
},
  "geometry": {"coordinates":[3.9795000553,51.0246582031],"type":"Point"}
}