{
  "type": "Feature",
  "properties": {
    "addr:full":"Binnenstraat 41a Aalst Oost-Vlaanderen 9300",
    "addr:housenumber":"41a",
    "addr:postcode":"9300",
    "addr:street":"Binnenstraat",
    "iso:country":"BE",
    "sg:address":"Binnenstraat 41a",
    "sg:city":"Aalst",
    "sg:classifiers":[
        {
            "category":"Professional",
            "subcategory":"Art Services",
            "type":"Services"
        }
    ],
    "sg:phone":"+32 53 70 60 88",
    "sg:postcode":"9300",
    "sg:province":"Oost-Vlaanderen",
    "sg:tags":[
        "-",
        "valuer"
    ],
    "wof:name":"D'oude Galerij",
    "wof:placetype":"venue"
},
  "geometry": {"coordinates":[4.0480690002,50.9431991577],"type":"Point"}
}