{
  "type": "Feature",
  "properties": {
    "addr:full":"Mechelsesteenweg 2018 Herent Vlaams-Brabant 3020",
    "addr:housenumber":"2018",
    "addr:postcode":"3020",
    "addr:street":"Mechelsesteenweg",
    "iso:country":"BE",
    "sg:address":"Mechelsesteenweg 2018",
    "sg:city":"Herent",
    "sg:classifiers":[
        {
            "category":"Retail",
            "subcategory":"Auto Repair",
            "type":"Services"
        }
    ],
    "sg:phone":"+32 16 60 28 83",
    "sg:postcode":"3020",
    "sg:province":"Vlaams-Brabant",
    "sg:tags":[
        "truck-body"
    ],
    "wof:name":"Thirry",
    "wof:placetype":"venue"
},
  "geometry": {"coordinates":[4.6489782333,50.9196052551],"type":"Point"}
}