{
  "type": "Feature",
  "properties": {
    "iso:country":"BE",
    "sg:address":"Rue De L'eglise 9",
    "sg:city":"Ittre (haut-ittre)",
    "sg:classifiers":[
        {
            "category":"Communications",
            "subcategory":"Film & Video Production",
            "type":"Services"
        }
    ],
    "sg:phone":"+32 67 21 89 24",
    "sg:postcode":"1461",
    "sg:province":"Brabant Wallon",
    "sg:tags":[
        "realisation",
        "-"
    ],
    "wof:name":"Message Video",
    "wof:placetype":"venue"
},
  "geometry": {"coordinates":[4.2978210449,50.652721405],"type":"Point"}
}