{
  "type": "Feature",
  "properties": {
    "addr:full":"Rendries 2 Herne Vlaams-Brabant 1540",
    "addr:housenumber":"2",
    "addr:postcode":"1540",
    "addr:street":"Rendries",
    "iso:country":"BE",
    "sg:address":"Rendries 2",
    "sg:city":"Herne",
    "sg:classifiers":[
        {
            "category":"Health Services",
            "subcategory":"Dentist",
            "type":"Services"
        }
    ],
    "sg:phone":"+32 2 396 28 25",
    "sg:postcode":"1540",
    "sg:province":"Vlaams-Brabant",
    "wof:name":"Corron John",
    "wof:placetype":"venue"
},
  "geometry": {"coordinates":[4.0239229202,50.7250556946],"type":"Point"}
}