{
  "type": "Feature",
  "properties": {
    "iso:country":"BE",
    "sg:address":"Hunningen 106",
    "sg:city":"B\u00dcllingen/bullange",
    "sg:orig_category":"Rundveehouders",
    "sg:phone":"+32 80 64 24 27",
    "sg:postcode":"4760",
    "sg:province":"Li\u00e8ge",
    "wof:name":"Viktor Weber",
    "wof:placetype":"venue"
},
  "geometry": {"coordinates":[6.304910183,50.4083137512],"type":"Point"}
}