{
  "type": "Feature",
  "properties": {
    "addr:full":"Rue Des Tiennes 367bc Andenne Namur 5300",
    "addr:housenumber":"367bc",
    "addr:postcode":"5300",
    "addr:street":"Rue Des Tiennes",
    "iso:country":"BE",
    "sg:address":"Rue Des Tiennes 367bc",
    "sg:city":"Andenne",
    "sg:orig_category":"Epiceries",
    "sg:phone":"+32 81 58 98 21",
    "sg:postcode":"5300",
    "sg:province":"Namur",
    "wof:name":"Antoine Delory",
    "wof:placetype":"venue"
},
  "geometry": {"coordinates":[5.0373601913,50.4890708923],"type":"Point"}
}