{
  "type": "Feature",
  "properties": {
    "iso:country":"BE",
    "sg:address":"Oudenaardsesteenweg 366",
    "sg:city":"Kortrijk",
    "sg:classifiers":[
        {
            "category":"Home & Garden",
            "subcategory":"Home Furnishings",
            "type":"Retail Goods"
        }
    ],
    "sg:phone":"+32 56 22 84 56",
    "sg:postcode":"8500",
    "sg:province":"West-Vlaanderen",
    "sg:tags":[
        "interior",
        "decoration"
    ],
    "wof:name":"Delobelle Jozef-products",
    "wof:placetype":"venue"
},
  "geometry": {"coordinates":[3.3029909134,50.8161621094],"type":"Point"}
}