{
  "type": "Feature",
  "properties": {
    "iso:country":"BE",
    "sg:address":"Diksmuidseweg 3",
    "sg:city":"Ieper",
    "sg:classifiers":[
        {
            "category":"Park",
            "subcategory":"National",
            "type":"Public Place"
        }
    ],
    "sg:phone":"+32 57 20 10 08",
    "sg:postcode":"8900",
    "sg:province":"West-Vlaanderen",
    "sg:tags":[
        "recreation"
    ],
    "wof:name":"Kapoentje ('t)",
    "wof:placetype":"venue"
},
  "geometry": {"coordinates":[2.8845911026,50.8577041626],"type":"Point"}
}