{
  "type": "Feature",
  "properties": {
    "iso:country":"BE",
    "sg:address":"Dorpsstraat 14",
    "sg:city":"Leopoldsburg",
    "sg:orig_category":"Meubles D\u00e9taillants, Am\u00e9nagement de B\u00e2timents et de Cuisines. Eclairage et \u00e9quipements du foyer",
    "sg:phone":"+32 11 34 37 09",
    "sg:postcode":"3971",
    "sg:province":"Limburg",
    "wof:name":"Rietshop",
    "wof:placetype":"venue"
},
  "geometry": {"coordinates":[5.2295570374,51.108745575],"type":"Point"}
}