{
  "type": "Feature",
  "properties": {
    "addr:full":"Burg 8 Brugge West-Vlaanderen 8000",
    "addr:housenumber":"8",
    "addr:postcode":"8000",
    "addr:street":"Burg",
    "iso:country":"BE",
    "sg:address":"Burg 8",
    "sg:city":"Brugge",
    "sg:classifiers":[
        {
            "category":"Bars & Pubs",
            "type":"Food & Drink"
        }
    ],
    "sg:phone":"+32 50 34 45 02",
    "sg:postcode":"8000",
    "sg:province":"West-Vlaanderen",
    "sg:tags":[
        "restaurant"
    ],
    "wof:name":"Celtic Ireland",
    "wof:placetype":"venue"
},
  "geometry": {"coordinates":[3.2271180153,51.2092132568],"type":"Point"}
}