{
  "type": "Feature",
  "properties": {
    "iso:country":"BE",
    "sg:address":"Rue De Rotheux 53c",
    "sg:city":"Seraing",
    "sg:classifiers":[
        {
            "category":"Shopping",
            "subcategory":"Clothing, Apparel, & Fashions",
            "type":"Retail Goods"
        }
    ],
    "sg:phone":"+32 4 336 79 15",
    "sg:postcode":"4100",
    "sg:province":"Li\u00e8ge",
    "sg:tags":[
        "-",
        "clothing",
        "child"
    ],
    "wof:name":"Mar\u00e8se",
    "wof:placetype":"venue"
},
  "geometry": {"coordinates":[5.505106926,50.5856742859],"type":"Point"}
}