{
  "type": "Feature",
  "properties": {
    "iso:country":"BE",
    "sg:address":"Langestraat 38",
    "sg:city":"Asse",
    "sg:orig_category":"Agences d'exp\u00e9dition",
    "sg:phone":"+32 2 453 16 80",
    "sg:postcode":"1730",
    "sg:province":"Vlaams-Brabant",
    "wof:name":"Bowell",
    "wof:placetype":"venue"
},
  "geometry": {"coordinates":[4.2366600037,50.8955802917],"type":"Point"}
}