{
  "type": "Feature",
  "properties": {
    "iso:country":"BE",
    "sg:address":"Zegelaan 22",
    "sg:city":"Bredene",
    "sg:orig_category":"Cosmetica and toiletartikelen Kapsalons",
    "sg:phone":"+32 59 32 13 83",
    "sg:postcode":"8450",
    "sg:province":"West-Vlaanderen",
    "wof:name":"Eddy Verkempynck",
    "wof:placetype":"venue"
},
  "geometry": {"coordinates":[2.9592599869,51.242401123],"type":"Point"}
}