{
  "type": "Feature",
  "properties": {
    "addr:full":"Callaertstraat 26 Sint-niklaas Oost-Vlaanderen 9100",
    "addr:housenumber":"26",
    "addr:postcode":"9100",
    "addr:street":"Callaertstraat",
    "iso:country":"BE",
    "sg:address":"Callaertstraat 26",
    "sg:city":"Sint-niklaas",
    "sg:orig_category":"D\u00e9molition d\u00b4immeubles and terrassements. Construction de maisons. Constructions r\u00e9sidentielles sp\u00e9c",
    "sg:phone":"+32 3 776 91 69",
    "sg:postcode":"9100",
    "sg:province":"Oost-Vlaanderen",
    "wof:name":"De Pagie",
    "wof:placetype":"venue"
},
  "geometry": {"coordinates":[4.1717429161,51.1775627136],"type":"Point"}
}