{
  "type": "Feature",
  "properties": {
    "iso:country":"BE",
    "sg:address":"Rue Des Deux Auvelais 2",
    "sg:city":"Sambreville (auvelais)",
    "sg:classifiers":[
        {
            "category":"Professional",
            "subcategory":"Testing Lab",
            "type":"Services"
        }
    ],
    "sg:phone":"+32 71 74 18 05",
    "sg:postcode":"5060",
    "sg:province":"Namur",
    "sg:tags":[
        "chemist"
    ],
    "wof:name":"Paindaveine P",
    "wof:placetype":"venue"
},
  "geometry": {"coordinates":[4.6341710091,50.4472465515],"type":"Point"}
}