{
  "type": "Feature",
  "properties": {
    "addr:full":"Kerkhofstraat 5 Rotselaar Vlaams-Brabant 3110",
    "addr:housenumber":"5",
    "addr:postcode":"3110",
    "addr:street":"Kerkhofstraat",
    "iso:country":"BE",
    "sg:address":"Kerkhofstraat 5",
    "sg:city":"Rotselaar",
    "sg:orig_category":"Boekenuitgeverijen",
    "sg:phone":"+32 16 58 32 85",
    "sg:postcode":"3110",
    "sg:province":"Vlaams-Brabant",
    "wof:name":"Jules Philipsen",
    "wof:placetype":"venue"
},
  "geometry": {"coordinates":[4.7348351479,50.9622764587],"type":"Point"}
}