{
  "type": "Feature",
  "properties": {
    "addr:full":"Oude Galgenstraat 170 Kapellen Antwerpen 2950",
    "addr:housenumber":"170",
    "addr:postcode":"2950",
    "addr:street":"Oude Galgenstraat",
    "iso:country":"BE",
    "sg:address":"Oude Galgenstraat 170",
    "sg:city":"Kapellen",
    "sg:orig_category":"Agences d'exp\u00e9dition",
    "sg:phone":"+32 3 666 01 05",
    "sg:postcode":"2950",
    "sg:province":"Antwerpen",
    "wof:name":"Orisa Benelux",
    "wof:placetype":"venue"
},
  "geometry": {"coordinates":[4.4447388649,51.360118866],"type":"Point"}
}