{
  "type": "Feature",
  "properties": {
    "iso:country":"BE",
    "sg:address":"Grootzand 148",
    "sg:city":"Dendermonde",
    "sg:orig_category":"Brood, gebak and snoepgoed",
    "sg:phone":"+32 52 21 61 09",
    "sg:postcode":"9200",
    "sg:province":"Oost-Vlaanderen",
    "wof:name":"Bakkery Van Damme R. & A.",
    "wof:placetype":"venue"
},
  "geometry": {"coordinates":[4.104516983,51.043094635],"type":"Point"}
}