{
  "type": "Feature",
  "properties": {
    "addr:full":"Rue Saint-paul 38 Li\u00c8ge Li\u00e8ge 4000",
    "addr:housenumber":"38",
    "addr:postcode":"4000",
    "addr:street":"Rue Saint-Paul",
    "iso:country":"BE",
    "sg:address":"Rue Saint-paul 38",
    "sg:city":"Li\u00c8ge",
    "sg:orig_category":"Fournitures de bureau",
    "sg:phone":"+32 4 223 29 26",
    "sg:postcode":"4000",
    "sg:province":"Li\u00e8ge",
    "wof:name":"Recto Verso",
    "wof:placetype":"venue"
},
  "geometry": {"coordinates":[5.5730128288,50.639541626],"type":"Point"}
}