{
  "type": "Feature",
  "properties": {
    "addr:full":"Stationsstraat 28 Halen Limburg 3545",
    "addr:housenumber":"28",
    "addr:postcode":"3545",
    "addr:street":"Stationsstraat",
    "iso:country":"BE",
    "sg:address":"Stationsstraat 28",
    "sg:city":"Halen",
    "sg:orig_category":"Animations diverses",
    "sg:phone":"+32 13 46 18 56",
    "sg:postcode":"3545",
    "sg:province":"Limburg",
    "wof:name":"L. Forceville",
    "wof:placetype":"venue"
},
  "geometry": {"coordinates":[5.1144881248,50.9757232666],"type":"Point"}
}