{
  "type": "Feature",
  "properties": {
    "iso:country":"BE",
    "sg:address":"Rue De Beho 26b",
    "sg:city":"Gouvy (limerl\u00e9)",
    "sg:classifiers":[
        {
            "category":"Home & Garden",
            "subcategory":"Carpets & Floor Coverings",
            "type":"Retail Goods"
        }
    ],
    "sg:phone":"+32 80 51 74 38",
    "sg:postcode":"6670",
    "sg:province":"Luxembourg",
    "sg:tags":[
        "armoring"
    ],
    "wof:name":"Scheuren & Fils",
    "wof:placetype":"venue"
},
  "geometry": {"coordinates":[5.9658198357,50.200553894],"type":"Point"}
}