{
  "type": "Feature",
  "properties": {
    "addr:full":"Rue De L'egalit\u00e9 1 Quaregnon Hainaut 7390",
    "addr:housenumber":"1",
    "addr:postcode":"7390",
    "addr:street":"Rue De L'Egalite \u0301",
    "iso:country":"BE",
    "sg:address":"Rue De L'egalit\u00e9 1",
    "sg:city":"Quaregnon",
    "sg:classifiers":[
        {
            "category":"Food & Beverages",
            "subcategory":"Fruits & Vegetables",
            "type":"Retail Goods"
        }
    ],
    "sg:phone":"+32 65 79 30 06",
    "sg:postcode":"7390",
    "sg:province":"Hainaut",
    "sg:tags":[
        "-"
    ],
    "wof:name":"Iannafruit",
    "wof:placetype":"venue"
},
  "geometry": {"coordinates":[3.8648409843,50.4415054321],"type":"Point"}
}