{
  "type": "Feature",
  "properties": {
    "iso:country":"BE",
    "sg:address":"Hille 76",
    "sg:city":"Wingene (zwevezele)",
    "sg:classifiers":[
        {
            "category":"Food & Beverages",
            "subcategory":"Groceries & Convenience Stores",
            "type":"Retail Goods"
        }
    ],
    "sg:phone":"+32 51 61 11 15",
    "sg:postcode":"8750",
    "sg:province":"West-Vlaanderen",
    "sg:tags":[
        "grocer"
    ],
    "wof:name":"Soetaert M",
    "wof:placetype":"venue"
},
  "geometry": {"coordinates":[3.226295948,51.0498352051],"type":"Point"}
}