{
  "type": "Feature",
  "properties": {
    "addr:full":"Avenue D\u00b4hyon 45 Mons Hainaut 7000",
    "addr:housenumber":"45",
    "addr:postcode":"7000",
    "addr:street":"Avenue D\u00b4Hyon;Hainaut",
    "iso:country":"BE",
    "sg:address":"Avenue D\u00b4hyon 45",
    "sg:city":"Mons",
    "sg:orig_category":"Maatschappelijke dienstverlening",
    "sg:phone":"+32 65 35 43 71",
    "sg:postcode":"7000",
    "sg:province":"Hainaut",
    "wof:name":"Centre Guidance Psychol.",
    "wof:placetype":"venue"
},
  "geometry": {"coordinates":[3.954750061,50.4472808838],"type":"Point"}
}