{
  "type": "Feature",
  "properties": {
    "addr:full":"Nieder-emmels 89 Sankt Vith/saint-vith Li\u00e8ge 4784",
    "addr:housenumber":"89",
    "addr:postcode":"4784",
    "addr:street":"Nieder-Emmels",
    "iso:country":"BE",
    "sg:address":"Nieder-emmels 89",
    "sg:city":"Sankt Vith/saint-vith",
    "sg:orig_category":"Apotheken",
    "sg:phone":"+32 80 22 91 06",
    "sg:postcode":"4784",
    "sg:province":"Li\u00e8ge",
    "wof:name":"J. Bungert",
    "wof:placetype":"venue"
},
  "geometry": {"coordinates":[6.0922560692,50.3106842041],"type":"Point"}
}