{
  "type": "Feature",
  "properties": {
    "iso:country":"BE",
    "sg:address":"Rue De Toernich 81",
    "sg:city":"Arlon",
    "sg:orig_category":"HUISBRANDOLIE",
    "sg:phone":"+32 63 22 02 61",
    "sg:postcode":"6700",
    "sg:province":"Luxembourg",
    "wof:name":"Fina Humblet",
    "wof:placetype":"venue"
},
  "geometry": {"coordinates":[5.8038988113,49.6755065918],"type":"Point"}
}