{
  "type": "Feature",
  "properties": {
    "addr:full":"Rue Des Flawn\u00e9es 34 Namur (naninne) Namur 5100",
    "addr:housenumber":"34",
    "addr:postcode":"5100",
    "addr:street":"Rue Des Flawne\u0301Es",
    "iso:country":"BE",
    "sg:address":"Rue Des Flawn\u00e9es 34",
    "sg:city":"Namur (naninne)",
    "sg:classifiers":[
        {
            "category":"Health Services",
            "subcategory":"Doctor",
            "type":"Services"
        }
    ],
    "sg:phone":"+32 81 40 28 06",
    "sg:postcode":"5100",
    "sg:province":"Namur",
    "sg:tags":[
        "psychotherapist",
        "psychoanalyst"
    ],
    "wof:name":"Kestemont P",
    "wof:placetype":"venue"
},
  "geometry": {"coordinates":[4.8713750839,50.4566345215],"type":"Point"}
}