{
  "type": "Feature",
  "properties": {
    "iso:country":"BE",
    "sg:address":"Boulevard Pierre Mayence 19",
    "sg:city":"Charleroi",
    "sg:classifiers":[
        {
            "category":"Professional",
            "subcategory":"Lawyer & Legal Services",
            "type":"Services"
        }
    ],
    "sg:phone":"+32 71 31 01 89",
    "sg:postcode":"6000",
    "sg:province":"Hainaut",
    "wof:name":"Bossard Philippe",
    "wof:placetype":"venue"
},
  "geometry": {"coordinates":[4.4524869919,50.40858078],"type":"Point"}
}