{
  "type": "Feature",
  "properties": {
    "addr:full":"Brusselbaan 28 Affligem Vlaams-Brabant 1790",
    "addr:housenumber":"28",
    "addr:postcode":"1790",
    "addr:street":"Brusselbaan",
    "iso:country":"BE",
    "sg:address":"Brusselbaan 28",
    "sg:city":"Affligem",
    "sg:orig_category":"Cr\u00e9dits divers",
    "sg:postcode":"1790",
    "sg:province":"Vlaams-Brabant",
    "wof:name":"Bancontact-mister Cash",
    "wof:placetype":"venue"
},
  "geometry": {"coordinates":[4.099339962,50.9148330688],"type":"Point"}
}