{
  "type": "Feature",
  "properties": {
    "iso:country":"BE",
    "sg:address":"Beernemstraat 57",
    "sg:city":"Wingene",
    "sg:orig_category":"Schoenen",
    "sg:phone":"+32 51 65 63 27",
    "sg:postcode":"8750",
    "sg:province":"West-Vlaanderen",
    "wof:name":"Huis Marischa",
    "wof:placetype":"venue"
},
  "geometry": {"coordinates":[3.2776920795,51.0625228882],"type":"Point"}
}