{
  "type": "Feature",
  "properties": {
    "addr:full":"Europalaan 30 Willebroek Antwerpen 2830",
    "addr:housenumber":"30",
    "addr:postcode":"2830",
    "addr:street":"Europalaan",
    "iso:country":"BE",
    "sg:address":"Europalaan 30",
    "sg:city":"Willebroek",
    "sg:classifiers":[
        {
            "category":"Personal",
            "subcategory":"Beauty Salon",
            "type":"Services"
        }
    ],
    "sg:phone":"+32 3 886 36 32",
    "sg:postcode":"2830",
    "sg:province":"Antwerpen",
    "sg:tags":[
        "de",
        "coiffure"
    ],
    "wof:name":"Denise Verlinden",
    "wof:placetype":"venue"
},
  "geometry": {"coordinates":[4.3454117775,51.0514831543],"type":"Point"}
}