{
  "type": "Feature",
  "properties": {
    "iso:country":"BE",
    "sg:address":"Kapelhofstraat 6",
    "sg:city":"Erpe-mere",
    "sg:orig_category":"Enseignement maternel and primaire",
    "sg:phone":"+32 53 80 85 10",
    "sg:postcode":"9420",
    "sg:province":"Oost-Vlaanderen",
    "wof:name":"Vrije Basisschool",
    "wof:placetype":"venue"
},
  "geometry": {"coordinates":[3.9535338879,50.9387245178],"type":"Point"}
}