{
  "type": "Feature",
  "properties": {
    "addr:full":"Gebr. Van Der Auwerabaan 32 Borsbeek Antwerpen 2150",
    "addr:housenumber":"32",
    "addr:postcode":"2150",
    "iso:country":"BE",
    "sg:address":"Gebr. Van Der Auwerabaan 32",
    "sg:city":"Borsbeek",
    "sg:orig_category":"Groententeelt",
    "sg:phone":"+32 3 321 93 65",
    "sg:postcode":"2150",
    "sg:province":"Antwerpen",
    "wof:name":"Willy Van Nuffelen",
    "wof:placetype":"venue"
},
  "geometry": {"coordinates":[4.4919929504,51.185459137],"type":"Point"}
}