{
  "type": "Feature",
  "properties": {
    "iso:country":"BE",
    "sg:address":"M. Fochstraat 7",
    "sg:city":"Leopoldsburg",
    "sg:orig_category":"Pain, p\u00e2tisseries and confiseries",
    "sg:phone":"+32 11 34 44 08",
    "sg:postcode":"3970",
    "sg:province":"Limburg",
    "wof:name":"Doopsuiker Bieke",
    "wof:placetype":"venue"
},
  "geometry": {"coordinates":[5.2640199661,51.1179618835],"type":"Point"}
}