{
  "type": "Feature",
  "properties": {
    "addr:full":"Diesterstraat 92 Tessenderlo Limburg 3980",
    "addr:housenumber":"92",
    "addr:postcode":"3980",
    "addr:street":"Diesterstraat",
    "iso:country":"BE",
    "sg:address":"Diesterstraat 92",
    "sg:city":"Tessenderlo",
    "sg:orig_category":"Boucheries",
    "sg:phone":"+32 13 66 63 83",
    "sg:postcode":"3980",
    "sg:province":"Limburg",
    "wof:name":"Renmans",
    "wof:placetype":"venue"
},
  "geometry": {"coordinates":[5.0886240005,51.0630874634],"type":"Point"}
}