{
  "type": "Feature",
  "properties": {
    "addr:full":"Rue Bruy\u00e8re De Jurbise 20 Mons (maisi\u00e8res) Hainaut 7020",
    "addr:housenumber":"20",
    "addr:postcode":"7020",
    "addr:street":"Rue Bruye\u0300Re De Jurbise",
    "iso:country":"BE",
    "sg:address":"Rue Bruy\u00e8re De Jurbise 20",
    "sg:city":"Mons (maisi\u00e8res)",
    "sg:classifiers":[
        {
            "category":"Professional",
            "subcategory":"Advertising",
            "type":"Services"
        }
    ],
    "sg:phone":"+32 65 73 16 28",
    "sg:postcode":"7020",
    "sg:province":"Hainaut",
    "sg:tags":[
        "bill",
        "-",
        "posting"
    ],
    "wof:name":"Van Huffel Ets",
    "wof:placetype":"venue"
},
  "geometry": {"coordinates":[3.9553449154,50.4761772156],"type":"Point"}
}