{
  "type": "Feature",
  "properties": {
    "iso:country":"BE",
    "sg:address":"Dries 12",
    "sg:city":"Sint-gillis-waas",
    "sg:orig_category":"Banken and kredietinstellingen",
    "sg:phone":"+32 3 776 67 28",
    "sg:postcode":"9170",
    "sg:province":"Oost-Vlaanderen",
    "wof:name":"Bbl",
    "wof:placetype":"venue"
},
  "geometry": {"coordinates":[4.0969772339,51.1929168701],"type":"Point"}
}