{
  "type": "Feature",
  "properties": {
    "addr:full":"Papebrugstraat 8 Torhout West-Vlaanderen 8820",
    "addr:housenumber":"8",
    "addr:postcode":"8820",
    "addr:street":"Papebrugstraat",
    "iso:country":"BE",
    "sg:address":"Papebrugstraat 8",
    "sg:city":"Torhout",
    "sg:orig_category":"Activit\u00e9s d\u00b4action sociale sans h\u00e9bergement",
    "sg:phone":"+32 50 22 15 13",
    "sg:postcode":"8820",
    "sg:province":"West-Vlaanderen",
    "wof:name":"Clb",
    "wof:placetype":"venue"
},
  "geometry": {"coordinates":[3.1040840149,51.0663986206],"type":"Point"}
}