{
  "type": "Feature",
  "properties": {
    "addr:full":"Rue De La Vacherie 26 Sambreville Namur 5060",
    "addr:housenumber":"26",
    "addr:postcode":"5060",
    "addr:street":"Rue De La Vacherie",
    "iso:country":"BE",
    "sg:address":"Rue De La Vacherie 26",
    "sg:city":"Sambreville",
    "sg:orig_category":"Machines \u00e0 coudre and tricoter",
    "sg:phone":"+32 71 77 13 63",
    "sg:postcode":"5060",
    "sg:province":"Namur",
    "wof:name":"Calomne",
    "wof:placetype":"venue"
},
  "geometry": {"coordinates":[4.6285200119,50.4448738098],"type":"Point"}
}