{
  "type": "Feature",
  "properties": {
    "addr:full":"Bredabaan 832 Brasschaat Antwerpen 2930",
    "addr:housenumber":"832",
    "addr:postcode":"2930",
    "addr:street":"Bredabaan",
    "iso:country":"BE",
    "sg:address":"Bredabaan 832",
    "sg:city":"Brasschaat",
    "sg:classifiers":[
        {
            "category":"Shopping",
            "subcategory":"Clothing, Apparel, & Fashions",
            "type":"Retail Goods"
        }
    ],
    "sg:phone":"+32 3 663 83 63",
    "sg:postcode":"2930",
    "sg:province":"Antwerpen",
    "sg:tags":[
        "lady",
        "clothing",
        "-"
    ],
    "wof:name":"Bobo Women & Teens",
    "wof:placetype":"venue"
},
  "geometry": {"coordinates":[4.5214829445,51.3267211914],"type":"Point"}
}