{
  "type": "Feature",
  "properties": {
    "iso:country":"BE",
    "sg:address":"Rue De L'enseignement 81",
    "sg:city":"Brussel/bruxelles",
    "sg:orig_category":"Salles de spectacles",
    "sg:phone":"+32 2 218 20 15",
    "sg:postcode":"1000",
    "sg:province":"Bruxelles-Capitale",
    "wof:name":"Cirque Royal/koninklijk Circus",
    "wof:placetype":"venue"
},
  "geometry": {"coordinates":[4.3657860756,50.849105835],"type":"Point"}
}