{
  "type": "Feature",
  "properties": {
    "addr:full":"Nijverheidszone 'begijnenmeers' 22 Liedekerke Vlaams-Brabant 1770",
    "addr:postcode":"1770",
    "addr:street":"Vlaams-Brabant",
    "iso:country":"BE",
    "sg:address":"Nijverheidszone 'begijnenmeers' 22",
    "sg:city":"Liedekerke",
    "sg:classifiers":[
        {
            "category":"Retail",
            "subcategory":"Event Space",
            "type":"Services"
        }
    ],
    "sg:phone":"+32 53 66 81 72",
    "sg:postcode":"1770",
    "sg:province":"Vlaams-Brabant",
    "sg:tags":[
        "product",
        "snack",
        "speciality",
        "potato",
        "stand",
        "fried"
    ],
    "wof:name":"Snacks Bosteels Bvba",
    "wof:placetype":"venue"
},
  "geometry": {"coordinates":[4.0872688293,50.8854942322],"type":"Point"}
}