{
  "type": "Feature",
  "properties": {
    "addr:full":"Avenue Roi Albert 240 Andenne Namur 5300",
    "addr:housenumber":"240",
    "addr:postcode":"5300",
    "addr:street":"Avenue Roi Albert",
    "iso:country":"BE",
    "sg:address":"Avenue Roi Albert 240",
    "sg:city":"Andenne",
    "sg:classifiers":[
        {
            "category":"Professional",
            "subcategory":"Testing Lab",
            "type":"Services"
        }
    ],
    "sg:phone":"+32 85 84 18 47",
    "sg:postcode":"5300",
    "sg:province":"Namur",
    "sg:tags":[
        "chemist"
    ],
    "wof:name":"D'andenelle Sa",
    "wof:placetype":"venue"
},
  "geometry": {"coordinates":[5.1122789383,50.49477005],"type":"Point"}
}