{
  "type": "Feature",
  "properties": {
    "addr:full":"Wieltjes Turnhout Antwerpen 2300",
    "addr:postcode":"2300",
    "iso:country":"BE",
    "sg:address":"Wieltjes",
    "sg:city":"Turnhout",
    "sg:classifiers":[
        {
            "category":"Building & Trades",
            "subcategory":"Equipment Rental",
            "type":"Services"
        }
    ],
    "sg:phone":"+32 14 41 18 76",
    "sg:postcode":"2300",
    "sg:province":"Antwerpen",
    "sg:tags":[
        "crane",
        "-"
    ],
    "wof:name":"Van Gorp",
    "wof:placetype":"venue"
},
  "geometry": {"coordinates":[4.9173750877,51.3309783936],"type":"Point"}
}