{
  "type": "Feature",
  "properties": {
    "addr:full":"Rue Pr\u00e9sident Kennedy 3 Andenne Namur 5300",
    "addr:housenumber":"3",
    "addr:postcode":"5300",
    "addr:street":"Rue Pre\u0301Sident Kennedy",
    "iso:country":"BE",
    "sg:address":"Rue Pr\u00e9sident Kennedy 3",
    "sg:city":"Andenne",
    "sg:classifiers":[
        {
            "category":"Taxi",
            "type":"Transportation"
        }
    ],
    "sg:phone":"+32 475 43 35 77",
    "sg:postcode":"5300",
    "sg:province":"Namur",
    "sg:tags":[
        "taxicab"
    ],
    "wof:name":"Eurovans Andenne",
    "wof:placetype":"venue"
},
  "geometry": {"coordinates":[5.0891718864,50.4866943359],"type":"Point"}
}