{
  "type": "Feature",
  "properties": {
    "iso:country":"BE",
    "sg:address":"Vleminkstraat 91",
    "sg:city":"Aarschot",
    "sg:orig_category":"G\u00e9om\u00e8tres",
    "sg:phone":"+32 16 56 07 77",
    "sg:postcode":"3201",
    "sg:province":"Vlaams-Brabant",
    "wof:name":"Hans Artels",
    "wof:placetype":"venue"
},
  "geometry": {"coordinates":[4.8869447708,51.0180511475],"type":"Point"}
}