{
  "type": "Feature",
  "properties": {
    "iso:country":"BE",
    "sg:address":"Avenue Van Volxem 429",
    "sg:city":"Bruxelles (forest)",
    "sg:classifiers":[
        {
            "category":"Arena",
            "subcategory":"Sports Club",
            "type":"Entertainment"
        }
    ],
    "sg:phone":"+32 2 534 04 42",
    "sg:postcode":"1190",
    "sg:province":"Bruxelles-Capitale",
    "wof:name":"Jeunesse Sportive Forestoise Asbl (la)",
    "wof:placetype":"venue"
},
  "geometry": {"coordinates":[4.3274497986,50.8269233704],"type":"Point"}
}