{
  "type": "Feature",
  "properties": {
    "iso:country":"BE",
    "sg:address":"Rue Beausoir 10",
    "sg:city":"Frasnes-lez-anvaing (oeudeghien)",
    "sg:classifiers":[
        {
            "category":"Bakery",
            "type":"Food & Drink"
        }
    ],
    "sg:phone":"+32 68 64 52 02",
    "sg:postcode":"7911",
    "sg:province":"Hainaut",
    "sg:tags":[
        "confectioner",
        "baker"
    ],
    "wof:name":"Vanstals M",
    "wof:placetype":"venue"
},
  "geometry": {"coordinates":[3.6875910759,50.6837005615],"type":"Point"}
}