{
  "type": "Feature",
  "properties": {
    "addr:full":"Remonval 8 Waimes/waimes Li\u00e8ge 4950",
    "addr:housenumber":"8",
    "addr:postcode":"4950",
    "addr:street":"Remonval",
    "iso:country":"BE",
    "sg:address":"Remonval 8",
    "sg:city":"Waimes/waimes",
    "sg:orig_category":"Landmeters",
    "sg:phone":"+32 80 67 84 20",
    "sg:postcode":"4950",
    "sg:province":"Li\u00e8ge",
    "wof:name":"Eric Piront",
    "wof:placetype":"venue"
},
  "geometry": {"coordinates":[6.1406908035,50.4036178589],"type":"Point"}
}