{
  "type": "Feature",
  "properties": {
    "iso:country":"BE",
    "sg:address":"Chauss\u00e9e De Mons 46",
    "sg:city":"Braine-le-comte",
    "sg:classifiers":[
        {
            "category":"Personal",
            "subcategory":"Beauty Salon",
            "type":"Services"
        }
    ],
    "sg:phone":"+32 67 55 58 90",
    "sg:postcode":"7090",
    "sg:province":"Hainaut",
    "sg:tags":[
        "lady",
        "-",
        "hairdressing"
    ],
    "wof:name":"Nadia (coiffure)",
    "wof:placetype":"venue"
},
  "geometry": {"coordinates":[4.1299071312,50.6030502319],"type":"Point"}
}