{
  "type": "Feature",
  "properties": {
    "iso:country":"BE",
    "sg:address":"Burg. De Lausnaystraat 4",
    "sg:city":"Berlare",
    "sg:orig_category":"Slagers",
    "sg:phone":"+32 9 367 53 52",
    "sg:postcode":"9290",
    "sg:province":"Oost-Vlaanderen",
    "wof:name":"Luc De Backer",
    "wof:placetype":"venue"
},
  "geometry": {"coordinates":[4.005710125,51.0165214539],"type":"Point"}
}