{
  "type": "Feature",
  "properties": {
    "iso:country":"BE",
    "sg:address":"Quai Henri-borguet 41",
    "sg:city":"Li\u00e8ge 1 (ch\u00ean\u00e9e)",
    "sg:classifiers":[
        {
            "category":"Utilities",
            "subcategory":"Recycling",
            "type":"Services"
        }
    ],
    "sg:phone":"+32 4 365 47 05",
    "sg:postcode":"4032",
    "sg:province":"Li\u00e8ge",
    "sg:tags":[
        "rubbish",
        "removal"
    ],
    "wof:name":"Curages Poncelet D",
    "wof:placetype":"venue"
},
  "geometry": {"coordinates":[5.6217718124,50.6101646423],"type":"Point"}
}