{
  "type": "Feature",
  "properties": {
    "iso:country":"BE",
    "sg:address":"Rue Du Congo 1",
    "sg:city":"Libin",
    "sg:orig_category":"Herstellingen and onderhoud van auto's",
    "sg:phone":"+32 61 22 39 09",
    "sg:postcode":"6890",
    "sg:province":"Luxembourg",
    "wof:name":"Garage Marlet",
    "wof:placetype":"venue"
},
  "geometry": {"coordinates":[5.2836761475,49.9298591614],"type":"Point"}
}