{
  "type": "Feature",
  "properties": {
    "addr:full":"Chauss\u00c9e De Jette 132 Bruxelles Bruxelles-Capitale 1081",
    "addr:housenumber":"132",
    "addr:postcode":"1081",
    "addr:street":"Chausse\u0301E De Jette",
    "iso:country":"BE",
    "sg:address":"Chauss\u00c9e De Jette 132",
    "sg:city":"Bruxelles",
    "sg:classifiers":[
        {
            "category":"Autos & Motor Vehicles",
            "subcategory":"Fuel & Gas Station",
            "type":"Retail Goods"
        }
    ],
    "sg:phone":"+32 2 411 45 35",
    "sg:postcode":"1081",
    "sg:province":"Bruxelles-Capitale",
    "sg:tags":[
        "stations-service",
        "carburants"
    ],
    "wof:name":"Mecanoo Garage",
    "wof:placetype":"venue"
},
  "geometry": {"coordinates":[4.3352689743,50.85912323],"type":"Point"}
}