{
  "type": "Feature",
  "properties": {
    "iso:country":"BE",
    "sg:address":"La Batte 29",
    "sg:city":"Li\u00c8ge",
    "sg:orig_category":"Disquaires",
    "sg:phone":"+32 4 223 69 01",
    "sg:postcode":"4000",
    "sg:province":"Li\u00e8ge",
    "wof:name":"Discobatte",
    "wof:placetype":"venue"
},
  "geometry": {"coordinates":[5.5809440613,50.6460037231],"type":"Point"}
}