{
  "type": "Feature",
  "properties": {
    "addr:full":"Antwerpseweg 74 Geel Antwerpen 2440",
    "addr:housenumber":"74",
    "addr:postcode":"2440",
    "addr:street":"Antwerpseweg",
    "iso:country":"BE",
    "sg:address":"Antwerpseweg 74",
    "sg:city":"Geel",
    "sg:orig_category":"V\u00eatements pour b\u00e9b\u00e9s and enfants. V\u00eatements pour Dames. V\u00eatements pour Hommes",
    "sg:phone":"+32 14 58 52 04",
    "sg:postcode":"2440",
    "sg:province":"Antwerpen",
    "wof:name":"Jbc Mode",
    "wof:placetype":"venue"
},
  "geometry": {"coordinates":[4.9586000443,51.14635849],"type":"Point"}
}