{
  "type": "Feature",
  "properties": {
    "addr:full":"Haachtsesteenweg 847-849 Evere/evere Bruxelles-Capitale 1140",
    "addr:housenumber":"847-849",
    "addr:postcode":"1140",
    "addr:street":"Haachtsesteenweg",
    "iso:country":"BE",
    "sg:address":"Haachtsesteenweg 847-849",
    "sg:city":"Evere/evere",
    "sg:orig_category":"Herstellingen and onderhoud van auto's Onderdelen and accessoires voor auto's Voertuigen",
    "sg:phone":"+32 2 216 92 45",
    "sg:postcode":"1140",
    "sg:province":"Bruxelles-Capitale",
    "wof:name":"Europe Motors",
    "wof:placetype":"venue"
},
  "geometry": {"coordinates":[4.3963069916,50.8721237183],"type":"Point"}
}