{
  "type": "Feature",
  "properties": {
    "iso:country":"BE",
    "sg:address":"Windmolenweg 41",
    "sg:city":"Maasmechelen (opgrimbie)",
    "sg:classifiers":[
        {
            "category":"Health Services",
            "subcategory":"Nursing And Care Facility",
            "type":"Services"
        }
    ],
    "sg:phone":"+32 89 77 29 52",
    "sg:postcode":"3630",
    "sg:province":"Limburg",
    "sg:tags":[
        "home"
    ],
    "wof:name":"Home Service Nv",
    "wof:placetype":"venue"
},
  "geometry": {"coordinates":[5.6961350441,50.963848114],"type":"Point"}
}