{
  "type": "Feature",
  "properties": {
    "addr:full":"Heuvelstraat 4 Overijse Vlaams-Brabant 3090",
    "addr:housenumber":"4",
    "addr:postcode":"3090",
    "addr:street":"Heuvelstraat",
    "iso:country":"BE",
    "sg:address":"Heuvelstraat 4",
    "sg:city":"Overijse",
    "sg:orig_category":"Banques and organismes de cr\u00e9dit",
    "sg:phone":"+32 2 687 33 03",
    "sg:postcode":"3090",
    "sg:province":"Vlaams-Brabant",
    "wof:name":"Groep Argenta",
    "wof:placetype":"venue"
},
  "geometry": {"coordinates":[4.5364151001,50.7729988098],"type":"Point"}
}