{
  "type": "Feature",
  "properties": {
    "iso:country":"BE",
    "sg:address":"Laasveldstraat 187b",
    "sg:city":"Willebroek",
    "sg:orig_category":"Diverse bedrijfsbeheeradviesbureaus",
    "sg:phone":"+32 3 886 75 05",
    "sg:postcode":"2830",
    "sg:province":"Antwerpen",
    "wof:name":"K-consult",
    "wof:placetype":"venue"
},
  "geometry": {"coordinates":[4.3757801056,51.0431365967],"type":"Point"}
}