{
  "type": "Feature",
  "properties": {
    "addr:full":"Rue Grande 86 Messancy Luxembourg 6780",
    "addr:housenumber":"86",
    "addr:postcode":"6780",
    "addr:street":"Rue Grande",
    "iso:country":"BE",
    "sg:address":"Rue Grande 86",
    "sg:city":"Messancy",
    "sg:orig_category":"Banken and kredietinstellingen",
    "sg:phone":"+32 63 38 51 56",
    "sg:postcode":"6780",
    "sg:province":"Luxembourg",
    "wof:name":"Fortis",
    "wof:placetype":"venue"
},
  "geometry": {"coordinates":[5.8146028519,49.5941772461],"type":"Point"}
}