{
  "type": "Feature",
  "properties": {
    "addr:full":"Kruidenlaan 60 Genk Limburg 3600",
    "addr:housenumber":"60",
    "addr:postcode":"3600",
    "addr:street":"Kruidenlaan",
    "iso:country":"BE",
    "sg:address":"Kruidenlaan 60",
    "sg:city":"Genk",
    "sg:orig_category":"Epiceries",
    "sg:phone":"+32 89 84 26 50",
    "sg:postcode":"3600",
    "sg:province":"Limburg",
    "wof:name":"Joannes Politis",
    "wof:placetype":"venue"
},
  "geometry": {"coordinates":[5.5061402321,51.0016479492],"type":"Point"}
}