{
  "type": "Feature",
  "properties": {
    "addr:full":"Generaal Deschachtstraat 12ba Sint-katelijne-waver Antwerpen 2860",
    "addr:housenumber":"12ba",
    "addr:postcode":"2860",
    "addr:street":"Generaal Deschachtstraat",
    "iso:country":"BE",
    "sg:address":"Generaal Deschachtstraat 12ba",
    "sg:city":"Sint-katelijne-waver",
    "sg:orig_category":"Pain, p\u00e2tisseries and confiseries",
    "sg:phone":"+32 15 31 96 93",
    "sg:postcode":"2860",
    "sg:province":"Antwerpen",
    "wof:name":"Peter Torfs",
    "wof:placetype":"venue"
},
  "geometry": {"coordinates":[4.5317349434,51.0696525574],"type":"Point"}
}