{
  "type": "Feature",
  "properties": {
    "addr:full":"Rue De L'abbaye 113 Bruxelles (ixelles) Bruxelles-Capitale 1050",
    "addr:housenumber":"113",
    "addr:postcode":"1050",
    "addr:street":"Rue De L'Abbaye",
    "iso:country":"BE",
    "sg:address":"Rue De L'abbaye 113",
    "sg:city":"Bruxelles (ixelles)",
    "sg:classifiers":[
        {
            "category":"Shopping",
            "subcategory":"Pets & Pet Supplies",
            "type":"Retail Goods"
        }
    ],
    "sg:phone":"+32 2 343 37 48",
    "sg:postcode":"1050",
    "sg:province":"Bruxelles-Capitale",
    "sg:tags":[
        "shop",
        "-"
    ],
    "wof:name":"Cleb'art",
    "wof:placetype":"venue"
},
  "geometry": {"coordinates":[4.3635439873,50.8186225891],"type":"Point"}
}