{
  "type": "Feature",
  "properties": {
    "addr:full":"Nazarethsestraat 1 Kruishoutem Oost-Vlaanderen 9770",
    "addr:housenumber":"1",
    "addr:postcode":"9770",
    "addr:street":"Nazarethsestraat",
    "iso:country":"BE",
    "sg:address":"Nazarethsestraat 1",
    "sg:city":"Kruishoutem",
    "sg:classifiers":[
        {
            "category":"Arena",
            "subcategory":"Sports Club",
            "type":"Entertainment"
        }
    ],
    "sg:phone":"+32 9 386 86 77",
    "sg:postcode":"9770",
    "sg:province":"Oost-Vlaanderen",
    "sg:tags":[
        "de"
    ],
    "wof:name":"De Vlaamse Zonen",
    "wof:placetype":"venue"
},
  "geometry": {"coordinates":[3.5395550728,50.9381446838],"type":"Point"}
}