{
  "type": "Feature",
  "properties": {
    "addr:full":"Fortuinstraat 55 Sint-kruis West-Vlaanderen 8310",
    "addr:housenumber":"55",
    "addr:postcode":"8310",
    "addr:street":"Fortuinstraat",
    "iso:country":"BE",
    "sg:address":"Fortuinstraat 55",
    "sg:city":"Sint-kruis",
    "sg:classifiers":[
        {
            "category":"Autos & Motor Vehicles",
            "subcategory":"Automobile Sales",
            "type":"Retail Goods"
        }
    ],
    "sg:phone":"+32 50 38 57 11",
    "sg:postcode":"8310",
    "sg:province":"West-Vlaanderen",
    "sg:tags":[
        "equipment",
        "motor-cars",
        "transport"
    ],
    "wof:name":"De Groote Gebroeders Bvba",
    "wof:placetype":"venue"
},
  "geometry": {"coordinates":[3.2537150383,51.2066307068],"type":"Point"}
}