{
  "type": "Feature",
  "properties": {
    "iso:country":"BE",
    "sg:address":"Rumbeeksestraat 2",
    "sg:city":"Moorslede",
    "sg:orig_category":"Eleveurs de bovins. Eleveurs and marchands de porcs",
    "sg:phone":"+32 51 77 72 22",
    "sg:postcode":"8890",
    "sg:province":"West-Vlaanderen",
    "wof:name":"Gilbert Lievens",
    "wof:placetype":"venue"
},
  "geometry": {"coordinates":[3.1025640965,50.9020729065],"type":"Point"}
}