{
  "type": "Feature",
  "properties": {
    "addr:full":"Gistelsteenweg 348 Jabbeke West-Vlaanderen 8490",
    "addr:housenumber":"348",
    "addr:postcode":"8490",
    "addr:street":"Gistelsteenweg",
    "iso:country":"BE",
    "sg:address":"Gistelsteenweg 348",
    "sg:city":"Jabbeke",
    "sg:classifiers":[
        {
            "category":"Real Estate",
            "subcategory":"Architect",
            "type":"Services"
        }
    ],
    "sg:phone":"+32 50 81 49 70",
    "sg:postcode":"8490",
    "sg:province":"West-Vlaanderen",
    "wof:name":"Knockaert K",
    "wof:placetype":"venue"
},
  "geometry": {"coordinates":[3.082310915,51.1794128418],"type":"Point"}
}