{
  "type": "Feature",
  "properties": {
    "iso:country":"BE",
    "sg:address":"Statiestraat 143",
    "sg:city":"Ternat",
    "sg:classifiers":[
        {
            "category":"Food & Beverages",
            "subcategory":"Chocolate",
            "type":"Retail Goods"
        }
    ],
    "sg:phone":"+32 2 582 01 40",
    "sg:postcode":"1740",
    "sg:province":"Vlaams-Brabant",
    "sg:tags":[
        "confectionery",
        "-"
    ],
    "wof:name":"Ooievaar (de)",
    "wof:placetype":"venue"
},
  "geometry": {"coordinates":[4.1635842323,50.8743515015],"type":"Point"}
}