{
  "type": "Feature",
  "properties": {
    "iso:country":"BE",
    "sg:address":"Avenue Docteur Pierre Gaspar 1",
    "sg:city":"Spa",
    "sg:classifiers":[
        {
            "category":"Health Services",
            "subcategory":"Nursing And Care Facility",
            "type":"Services"
        }
    ],
    "sg:phone":"+32 87 77 14 39",
    "sg:postcode":"4900",
    "sg:province":"Li\u00e8ge",
    "sg:tags":[
        "home",
        "rest"
    ],
    "wof:name":"Seniorie De Creppe (la)",
    "wof:placetype":"venue"
},
  "geometry": {"coordinates":[5.8576068878,50.4888343811],"type":"Point"}
}