{
  "type": "Feature",
  "properties": {
    "addr:full":"Halensebaan 41ba Bekkevoort Vlaams-Brabant 3461",
    "addr:housenumber":"41ba",
    "addr:postcode":"3461",
    "addr:street":"Halensebaan",
    "iso:country":"BE",
    "sg:address":"Halensebaan 41ba",
    "sg:city":"Bekkevoort",
    "sg:orig_category":"Eleveurs de bovins",
    "sg:phone":"+32 16 63 34 97",
    "sg:postcode":"3461",
    "sg:province":"Vlaams-Brabant",
    "wof:name":"Joannes Van Cauwenbergh",
    "wof:placetype":"venue"
},
  "geometry": {"coordinates":[4.9432191849,50.9184112549],"type":"Point"}
}