{
  "type": "Feature",
  "properties": {
    "iso:country":"BE",
    "sg:address":"Rijksweg 477",
    "sg:city":"Maasmechelen",
    "sg:classifiers":[
        {
            "category":"Arena",
            "subcategory":"Sports Club",
            "type":"Entertainment"
        }
    ],
    "sg:phone":"+32 89 76 58 37",
    "sg:postcode":"3630",
    "sg:province":"Limburg",
    "sg:tags":[
        "de"
    ],
    "wof:name":"Landelijke Wandelvrienden",
    "wof:placetype":"venue"
},
  "geometry": {"coordinates":[5.6948151588,50.9546356201],"type":"Point"}
}