{
  "type": "Feature",
  "properties": {
    "addr:full":"P. Stautstraat 52 Beveren Oost-Vlaanderen 9120",
    "addr:housenumber":"52",
    "addr:postcode":"9120",
    "addr:street":"Stautstraat",
    "iso:country":"BE",
    "sg:address":"P. Stautstraat 52",
    "sg:city":"Beveren",
    "sg:orig_category":"Installatie van houten of kunststof schrijnwerk Natuursteenbewerking Vloer- and muurbekleding",
    "sg:phone":"+32 3 775 77 93",
    "sg:postcode":"9120",
    "sg:province":"Oost-Vlaanderen",
    "wof:name":"Van Ombergen Gebr.",
    "wof:placetype":"venue"
},
  "geometry": {"coordinates":[4.2591118813,51.2047805786],"type":"Point"}
}