{
  "type": "Feature",
  "properties": {
    "addr:full":"Rue De La Sambre 9 Arlon Luxembourg 6700",
    "addr:housenumber":"9",
    "addr:postcode":"6700",
    "addr:street":"Rue De La Sambre",
    "iso:country":"BE",
    "sg:address":"Rue De La Sambre 9",
    "sg:city":"Arlon",
    "sg:classifiers":[
        {
            "category":"Social Services",
            "type":"Services"
        }
    ],
    "sg:phone":"+32 63 22 29 87",
    "sg:postcode":"6700",
    "sg:province":"Luxembourg",
    "wof:name":"Habitations Sud-luxembourg",
    "wof:placetype":"venue"
},
  "geometry": {"coordinates":[5.8161759377,49.6740493774],"type":"Point"}
}