{
  "type": "Feature",
  "properties": {
    "addr:full":"Chauss\u00c9e De Mons 201 Beaumont Hainaut 6500",
    "addr:housenumber":"201",
    "addr:postcode":"6500",
    "addr:street":"Chausse\u0301E De Mons;Hainaut",
    "iso:country":"BE",
    "sg:address":"Chauss\u00c9e De Mons 201",
    "sg:city":"Beaumont",
    "sg:orig_category":"Rundveehouders",
    "sg:phone":"+32 71 58 84 57",
    "sg:postcode":"6500",
    "sg:province":"Hainaut",
    "wof:name":"Aernoudt Paul Et Philippe",
    "wof:placetype":"venue"
},
  "geometry": {"coordinates":[4.2353157997,50.2410697937],"type":"Point"}
}