{
  "type": "Feature",
  "properties": {
    "iso:country":"BE",
    "sg:address":"Rue Ongena 2",
    "sg:city":"Bruxelles (jette)",
    "sg:orig_category":"Non-Classified Establishments",
    "sg:phone":"+32 2 426 94 70",
    "sg:postcode":"1090",
    "sg:province":"Bruxelles-Capitale",
    "wof:name":"Audipack",
    "wof:placetype":"venue"
},
  "geometry": {"coordinates":[4.3319811821,50.8661231995],"type":"Point"}
}