{
  "type": "Feature",
  "properties": {
    "iso:country":"BE",
    "sg:address":"Rue Victor Rousseau 4",
    "sg:city":"Seneffe",
    "sg:orig_category":"Architectes",
    "sg:phone":"+32 67 87 75 76",
    "sg:postcode":"7181",
    "sg:province":"Hainaut",
    "wof:name":"Frederic Van Keymeulen",
    "wof:placetype":"venue"
},
  "geometry": {"coordinates":[4.2532992363,50.5622825623],"type":"Point"}
}