{
  "type": "Feature",
  "properties": {
    "addr:full":"Scheldestraat 16 Zwalm (nederzwalm-hermelgem) Oost-Vlaanderen 9636",
    "addr:housenumber":"16",
    "addr:postcode":"9636",
    "addr:street":"Scheldestraat;Nederzwalm-Hermelgem",
    "iso:country":"BE",
    "sg:address":"Scheldestraat 16",
    "sg:city":"Zwalm (nederzwalm-hermelgem)",
    "sg:classifiers":[
        {
            "category":"Personal",
            "subcategory":"Beauty Salon",
            "type":"Services"
        }
    ],
    "sg:phone":"+32 55 49 66 68",
    "sg:postcode":"9636",
    "sg:province":"Oost-Vlaanderen",
    "sg:tags":[
        "lady",
        "-",
        "hairdressing"
    ],
    "wof:name":"A.d.m.",
    "wof:placetype":"venue"
},
  "geometry": {"coordinates":[3.6854660511,50.8924636841],"type":"Point"}
}