{
  "type": "Feature",
  "properties": {
    "addr:full":"Zuidstraat 23 Wervik (geluwe) West-Vlaanderen 8940",
    "addr:housenumber":"23",
    "addr:postcode":"8940",
    "addr:street":"Zuidstraat",
    "iso:country":"BE",
    "sg:address":"Zuidstraat 23",
    "sg:city":"Wervik (geluwe)",
    "sg:classifiers":[
        {
            "category":"Personal",
            "subcategory":"Beauty Salon",
            "type":"Services"
        }
    ],
    "sg:phone":"+32 56 51 24 90",
    "sg:postcode":"8940",
    "sg:province":"West-Vlaanderen",
    "sg:tags":[
        "lady",
        "-",
        "hairdressing"
    ],
    "wof:name":"Diana",
    "wof:placetype":"venue"
},
  "geometry": {"coordinates":[3.076941967,50.8085441589],"type":"Point"}
}