{
  "type": "Feature",
  "properties": {
    "iso:country":"BE",
    "sg:address":"Isabellalei 22b4a",
    "sg:city":"Antwerpen",
    "sg:orig_category":"Produits interm\u00e9diaires Gr",
    "sg:phone":"+32 3 230 66 26",
    "sg:postcode":"2018",
    "sg:province":"Antwerpen",
    "wof:name":"Shanti Gems",
    "wof:placetype":"venue"
},
  "geometry": {"coordinates":[4.415304184,51.2060890198],"type":"Point"}
}