{
  "type": "Feature",
  "properties": {
    "iso:country":"BE",
    "sg:address":"Heerdweg 38",
    "sg:city":"Deinze (vinkt)",
    "sg:classifiers":[
        {
            "category":"Building & Trades",
            "subcategory":"Landscaping Services",
            "type":"Services"
        }
    ],
    "sg:phone":"+32 475 52 14 26",
    "sg:postcode":"9800",
    "sg:province":"Oost-Vlaanderen",
    "sg:tags":[
        "gardening",
        "garden",
        "maintenance"
    ],
    "wof:name":"Cordons D",
    "wof:placetype":"venue"
},
  "geometry": {"coordinates":[3.5045800209,51.0156211853],"type":"Point"}
}