{
  "type": "Feature",
  "properties": {
    "iso:country":"BE",
    "sg:address":"Kastelein 166",
    "sg:city":"Turnhout",
    "sg:classifiers":[
        {
            "category":"Banks & Credit Unions",
            "subcategory":"Investment Brokerage",
            "type":"Services"
        }
    ],
    "sg:phone":"+32 14 41 94 53",
    "sg:postcode":"2300",
    "sg:province":"Antwerpen",
    "sg:tags":[
        "repair",
        "-",
        "installation",
        "sanitary",
        "article"
    ],
    "wof:name":"Van Den Bergh P",
    "wof:placetype":"venue"
},
  "geometry": {"coordinates":[4.9415888786,51.3502502441],"type":"Point"}
}