{
  "type": "Feature",
  "properties": {
    "iso:country":"BE",
    "sg:address":"Elsegemplein 44",
    "sg:city":"Wortegem-petegem",
    "sg:orig_category":"Beheer onroerend goed",
    "sg:phone":"+32 56 68 87 88",
    "sg:postcode":"9790",
    "sg:province":"Oost-Vlaanderen",
    "wof:name":"Luc Vander Meeren",
    "wof:placetype":"venue"
},
  "geometry": {"coordinates":[3.5354158878,50.8243942261],"type":"Point"}
}