{
  "type": "Feature",
  "properties": {
    "addr:full":"Tomboslaan 25 Lochristi Oost-Vlaanderen 9080",
    "addr:housenumber":"25",
    "addr:postcode":"9080",
    "addr:street":"Tomboslaan",
    "iso:country":"BE",
    "sg:address":"Tomboslaan 25",
    "sg:city":"Lochristi",
    "sg:classifiers":[
        {
            "category":"Taxi",
            "type":"Transportation"
        }
    ],
    "sg:phone":"+32 9 356 89 46",
    "sg:postcode":"9080",
    "sg:province":"Oost-Vlaanderen",
    "wof:name":"Alderweireldt",
    "wof:placetype":"venue"
},
  "geometry": {"coordinates":[3.8605730534,51.0952644348],"type":"Point"}
}