{
  "type": "Feature",
  "properties": {
    "addr:full":"Desmedtstraat 23 Hoogstraten Antwerpen 2322",
    "addr:housenumber":"23",
    "addr:postcode":"2322",
    "addr:street":"Desmedtstraat",
    "iso:country":"BE",
    "sg:address":"Desmedtstraat 23",
    "sg:city":"Hoogstraten",
    "sg:orig_category":"Belastingconsulenten Diverse juridische dienstverlening",
    "sg:phone":"+32 3 340 27 20",
    "sg:postcode":"2322",
    "sg:province":"Antwerpen",
    "wof:name":"S.b.b.",
    "wof:placetype":"venue"
},
  "geometry": {"coordinates":[4.763384819,51.4160041809],"type":"Point"}
}