{
  "type": "Feature",
  "properties": {
    "iso:country":"BE",
    "sg:address":"Rue De Marchienne 27",
    "sg:city":"Thuin (goz\u00e9e)",
    "sg:classifiers":[
        {
            "category":"Health Services",
            "subcategory":"Nursing And Care Facility",
            "type":"Services"
        }
    ],
    "sg:phone":"+32 71 51 84 52",
    "sg:postcode":"6534",
    "sg:province":"Hainaut",
    "sg:tags":[
        "home"
    ],
    "wof:name":"Stevens C",
    "wof:placetype":"venue"
},
  "geometry": {"coordinates":[4.3537039757,50.3357887268],"type":"Point"}
}