{
  "type": "Feature",
  "properties": {
    "iso:country":"BE",
    "sg:address":"Parc Industriel De Prayon",
    "sg:city":"Foret",
    "sg:orig_category":"Fiduciairies",
    "sg:phone":"+32 4 351 74 01",
    "sg:postcode":"4870",
    "sg:province":"Li\u00e8ge",
    "wof:name":"Fiduciaire Integrity",
    "wof:placetype":"venue"
},
  "geometry": {"coordinates":[5.6997218132,50.5836601257],"type":"Point"}
}