{
  "type": "Feature",
  "properties": {
    "addr:full":"Rue Fernand Stilmant 41 Farciennes Hainaut 6240",
    "addr:housenumber":"41",
    "addr:postcode":"6240",
    "addr:street":"Rue Fernand Stilmant",
    "iso:country":"BE",
    "sg:address":"Rue Fernand Stilmant 41",
    "sg:city":"Farciennes",
    "sg:orig_category":"Apotheken",
    "sg:phone":"+32 71 38 22 14",
    "sg:postcode":"6240",
    "sg:province":"Hainaut",
    "wof:name":"Pharmacie Glorieux",
    "wof:placetype":"venue"
},
  "geometry": {"coordinates":[4.5319371223,50.4231872559],"type":"Point"}
}