{
  "type": "Feature",
  "properties": {
    "addr:full":"Avenue De L'europe 19 Charleroi Hainaut 6000",
    "addr:housenumber":"19",
    "addr:postcode":"6000",
    "addr:street":"Avenue De L'Europe;Hainaut",
    "iso:country":"BE",
    "sg:address":"Avenue De L'europe 19",
    "sg:city":"Charleroi",
    "sg:classifiers":[
        {
            "category":"Cafe",
            "type":"Food & Drink"
        }
    ],
    "sg:phone":"+32 71 30 15 33",
    "sg:postcode":"6000",
    "sg:province":"Hainaut",
    "sg:tags":[
        "caf\u00e9s"
    ],
    "wof:name":"Scamardi-deflorian",
    "wof:placetype":"venue"
},
  "geometry": {"coordinates":[4.4363341331,50.40990448],"type":"Point"}
}