{
  "type": "Feature",
  "properties": {
    "addr:full":"Steenovenstraat 51 Meulebeke West-Vlaanderen 8760",
    "addr:housenumber":"51",
    "addr:postcode":"8760",
    "addr:street":"Steenovenstraat",
    "iso:country":"BE",
    "sg:address":"Steenovenstraat 51",
    "sg:city":"Meulebeke",
    "sg:orig_category":"M\u00e9decins and sp\u00e9cialistes",
    "sg:phone":"+32 51 48 97 78",
    "sg:postcode":"8760",
    "sg:province":"West-Vlaanderen",
    "wof:name":"Eddy Debeuf",
    "wof:placetype":"venue"
},
  "geometry": {"coordinates":[3.3268809319,50.9569625854],"type":"Point"}
}