{
  "type": "Feature",
  "properties": {
    "addr:full":"Serafien De Rijckelaan 34 De Pinte Oost-Vlaanderen 9840",
    "addr:housenumber":"34",
    "addr:postcode":"9840",
    "addr:street":"Rijckelaan",
    "iso:country":"BE",
    "sg:address":"Serafien De Rijckelaan 34",
    "sg:city":"De Pinte",
    "sg:orig_category":"Rev\u00eatements pour sols and murs. Rev\u00eatements de sols and murs. Peinture",
    "sg:phone":"+32 9 282 87 47",
    "sg:postcode":"9840",
    "sg:province":"Oost-Vlaanderen",
    "wof:name":"De Wilde Edwig",
    "wof:placetype":"venue"
},
  "geometry": {"coordinates":[3.6365799904,50.9932250977],"type":"Point"}
}