{
  "type": "Feature",
  "properties": {
    "addr:full":"Avenue Du Prince H\u00e9ritier 186 Bruxelles (woluwe-saint-lambert) Bruxelles-Capitale 1200",
    "addr:housenumber":"186",
    "addr:postcode":"1200",
    "addr:street":"Avenue Du Prince He\u0301Ritier",
    "iso:country":"BE",
    "sg:address":"Avenue Du Prince H\u00e9ritier 186",
    "sg:city":"Bruxelles (woluwe-saint-lambert)",
    "sg:classifiers":[
        {
            "category":"Professional",
            "subcategory":"Art Services",
            "type":"Services"
        }
    ],
    "sg:phone":"+32 2 736 76 10",
    "sg:postcode":"1200",
    "sg:province":"Bruxelles-Capitale",
    "sg:tags":[
        "graphic",
        "designer"
    ],
    "wof:name":"Dopp\u00e9e J",
    "wof:placetype":"venue"
},
  "geometry": {"coordinates":[4.4088439941,50.8467521667],"type":"Point"}
}