{
  "type": "Feature",
  "properties": {
    "addr:full":"Hundelgemsesteenweg 387 Merelbeke Oost-Vlaanderen 9820",
    "addr:housenumber":"387",
    "addr:postcode":"9820",
    "addr:street":"Hundelgemsesteenweg",
    "iso:country":"BE",
    "sg:address":"Hundelgemsesteenweg 387",
    "sg:city":"Merelbeke",
    "sg:classifiers":[
        {
            "category":"Personal",
            "subcategory":"Beauty Salon",
            "type":"Services"
        }
    ],
    "sg:phone":"+32 9 230 52 85",
    "sg:postcode":"9820",
    "sg:province":"Oost-Vlaanderen",
    "sg:tags":[
        "lady",
        "-",
        "hairdressing"
    ],
    "wof:name":"Coiffure Rudy",
    "wof:placetype":"venue"
},
  "geometry": {"coordinates":[3.7461690903,50.9936408997],"type":"Point"}
}