{
  "type": "Feature",
  "properties": {
    "iso:country":"BE",
    "sg:address":"Dendermondsesteenweg 95",
    "sg:city":"Lebbeke",
    "sg:orig_category":"Entretien and r\u00e9parations de voitures",
    "sg:phone":"+32 52 21 15 52",
    "sg:postcode":"9280",
    "sg:province":"Oost-Vlaanderen",
    "wof:name":"Carrosserie Broothaerts",
    "wof:placetype":"venue"
},
  "geometry": {"coordinates":[4.1231369972,51.0055656433],"type":"Point"}
}