{
  "type": "Feature",
  "properties": {
    "addr:full":"Chocoladesteeg 12 Gent Oost-Vlaanderen 9000",
    "addr:housenumber":"12",
    "addr:postcode":"9000",
    "addr:street":"Chocoladesteeg;Oost-Vlaanderen",
    "iso:country":"BE",
    "sg:address":"Chocoladesteeg 12",
    "sg:city":"Gent",
    "sg:classifiers":[
        {
            "category":"Health Services",
            "subcategory":"Health Practitioner",
            "type":"Services"
        }
    ],
    "sg:phone":"+32 9 259 04 08",
    "sg:postcode":"9000",
    "sg:province":"Oost-Vlaanderen",
    "sg:tags":[
        "physiotherapist"
    ],
    "wof:name":"Mingneau Natalie",
    "wof:placetype":"venue"
},
  "geometry": {"coordinates":[3.7298629284,51.0753440857],"type":"Point"}
}