{
  "type": "Feature",
  "properties": {
    "iso:country":"BE",
    "sg:address":"Begonialaan 11",
    "sg:city":"Wervik",
    "sg:orig_category":"Caf\u00e9s Diverse organisaties and verenigingen",
    "sg:phone":"+32 56 31 21 31",
    "sg:postcode":"8940",
    "sg:province":"West-Vlaanderen",
    "wof:name":"De Bierpompe",
    "wof:placetype":"venue"
},
  "geometry": {"coordinates":[3.0550448895,50.7852020264],"type":"Point"}
}