{
  "type": "Feature",
  "properties": {
    "iso:country":"BE",
    "sg:address":"Rue Du Petit-bois 59",
    "sg:city":"Marche-en-famenne",
    "sg:orig_category":"Woningbouw",
    "sg:phone":"+32 84 31 12 59",
    "sg:postcode":"6900",
    "sg:province":"Luxembourg",
    "wof:name":"Andre Micha",
    "wof:placetype":"venue"
},
  "geometry": {"coordinates":[5.3446321487,50.2076911926],"type":"Point"}
}