{
  "type": "Feature",
  "properties": {
    "iso:country":"BE",
    "sg:address":"Geenrijt 2",
    "sg:city":"Heusden-zolder (heusden)",
    "sg:classifiers":[
        {
            "category":"Health Services",
            "subcategory":"Dentist",
            "type":"Services"
        }
    ],
    "sg:phone":"+32 11 42 36 12",
    "sg:postcode":"3550",
    "sg:province":"Limburg",
    "wof:name":"Fransen J",
    "wof:placetype":"venue"
},
  "geometry": {"coordinates":[5.2812561989,51.0376472473],"type":"Point"}
}