{
  "type": "Feature",
  "properties": {
    "iso:country":"BE",
    "sg:address":"Kerkhovensesteenweg 383",
    "sg:city":"Lommel",
    "sg:classifiers":[
        {
            "category":"Fast Food",
            "type":"Food & Drink"
        }
    ],
    "sg:phone":"+32 11 39 30 15",
    "sg:postcode":"3920",
    "sg:province":"Limburg",
    "sg:tags":[
        "fried",
        "stand",
        "potato"
    ],
    "wof:name":"Kris",
    "wof:placetype":"venue"
},
  "geometry": {"coordinates":[5.2690382004,51.1631851196],"type":"Point"}
}