{
  "type": "Feature",
  "properties": {
    "iso:country":"BE",
    "sg:address":"Lucas De Heerestraat 25",
    "sg:city":"Gent",
    "sg:orig_category":"Dansscholen",
    "sg:phone":"+32 9 220 82 96",
    "sg:postcode":"9000",
    "sg:province":"Oost-Vlaanderen",
    "wof:name":"Tormenta",
    "wof:placetype":"venue"
},
  "geometry": {"coordinates":[3.7244861126,51.034034729],"type":"Point"}
}