{
  "type": "Feature",
  "properties": {
    "addr:full":"Putsesteenweg 27 Mechelen Antwerpen 2800",
    "addr:housenumber":"27",
    "addr:postcode":"2800",
    "addr:street":"Putsesteenweg",
    "iso:country":"BE",
    "sg:address":"Putsesteenweg 27",
    "sg:city":"Mechelen",
    "sg:orig_category":"Banken and kredietinstellingen",
    "sg:phone":"+32 15 55 19 22",
    "sg:postcode":"2800",
    "sg:province":"Antwerpen",
    "wof:name":"Dexia",
    "wof:placetype":"venue"
},
  "geometry": {"coordinates":[4.5104222298,51.0346641541],"type":"Point"}
}