{
  "type": "Feature",
  "properties": {
    "addr:full":"Rue De Leuze 411 Andenne (vezin) Namur 5300",
    "addr:housenumber":"411",
    "addr:postcode":"5300",
    "addr:street":"Rue De Leuze",
    "iso:country":"BE",
    "sg:address":"Rue De Leuze 411",
    "sg:city":"Andenne (vezin)",
    "sg:classifiers":[
        {
            "category":"Autos & Motor Vehicles",
            "subcategory":"Motorcycle Sales",
            "type":"Retail Goods"
        }
    ],
    "sg:phone":"+32 81 58 87 19",
    "sg:postcode":"5300",
    "sg:province":"Namur",
    "sg:tags":[
        "motorbike"
    ],
    "wof:name":"Posocco P",
    "wof:placetype":"venue"
},
  "geometry": {"coordinates":[5.0060658455,50.4989471436],"type":"Point"}
}