{
  "type": "Feature",
  "properties": {
    "iso:country":"BE",
    "sg:address":"Torhoutsesteenweg 20",
    "sg:city":"Oostende",
    "sg:orig_category":"Bloemen and planten",
    "sg:phone":"+32 59 50 42 87",
    "sg:postcode":"8400",
    "sg:province":"West-Vlaanderen",
    "wof:name":"Huis Utopia",
    "wof:placetype":"venue"
},
  "geometry": {"coordinates":[2.9101600647,51.2270812988],"type":"Point"}
}