{
  "type": "Feature",
  "properties": {
    "iso:country":"BE",
    "sg:address":"Sint-josefplein 2",
    "sg:city":"Oudenaarde",
    "sg:orig_category":"Disneyland Paris. Agences de voyages",
    "sg:phone":"+32 55 31 49 49",
    "sg:postcode":"9700",
    "sg:province":"Oost-Vlaanderen",
    "wof:name":"Ttc Oudenaarde",
    "wof:placetype":"venue"
},
  "geometry": {"coordinates":[3.6109900475,50.8519859314],"type":"Point"}
}