{
  "type": "Feature",
  "properties": {
    "iso:country":"BE",
    "sg:address":"Meerstraat 120",
    "sg:city":"Hamme",
    "sg:classifiers":[
        {
            "category":"Building & Trades",
            "subcategory":"Plumbing",
            "type":"Services"
        }
    ],
    "sg:phone":"+32 52 47 15 02",
    "sg:postcode":"9220",
    "sg:province":"Oost-Vlaanderen",
    "sg:tags":[
        "pipe",
        "pushing"
    ],
    "wof:name":"Van Goethem & Co Bvba",
    "wof:placetype":"venue"
},
  "geometry": {"coordinates":[4.1113729477,51.0759773254],"type":"Point"}
}