{
  "type": "Feature",
  "properties": {
    "iso:country":"BE",
    "sg:address":"Rue De La Barri\u00e8re 1",
    "sg:city":"Philippeville (romedenne)",
    "sg:classifiers":[
        {
            "category":"Bars & Pubs",
            "type":"Food & Drink"
        }
    ],
    "sg:phone":"+32 82 67 77 75",
    "sg:postcode":"5600",
    "sg:province":"Namur",
    "wof:name":"Nationale 46 (la)",
    "wof:placetype":"venue"
},
  "geometry": {"coordinates":[4.6906638145,50.1558456421],"type":"Point"}
}