{
  "type": "Feature",
  "properties": {
    "addr:full":"Van Doornelaan 3 Westerlo Antwerpen 2260",
    "addr:housenumber":"3",
    "addr:postcode":"2260",
    "addr:street":"Van Doornelaan",
    "iso:country":"BE",
    "sg:address":"Van Doornelaan 3",
    "sg:city":"Westerlo",
    "sg:orig_category":"Messageries",
    "sg:phone":"+32 14 58 56 11",
    "sg:postcode":"2260",
    "sg:province":"Antwerpen",
    "wof:name":"Zuiderkempen Vervoer",
    "wof:placetype":"venue"
},
  "geometry": {"coordinates":[4.9378399849,51.1264610291],"type":"Point"}
}