{
  "type": "Feature",
  "properties": {
    "addr:full":"Ginderbuiten 59 Box 2 Mol Antwerpen 2400",
    "addr:housenumber":"59;2",
    "addr:postcode":"2400",
    "addr:street":"Ginderbuiten;Box",
    "iso:country":"BE",
    "sg:address":"Ginderbuiten 59 Box 2",
    "sg:city":"Mol",
    "sg:classifiers":[
        {
            "category":"Health Services",
            "subcategory":"Health Practitioner",
            "type":"Services"
        }
    ],
    "sg:phone":"+32 14 32 39 73",
    "sg:postcode":"2400",
    "sg:province":"Antwerpen",
    "sg:tags":[
        "psychologist"
    ],
    "wof:name":"Altena Management-& Organisatie Advies",
    "wof:placetype":"venue"
},
  "geometry": {"coordinates":[5.146900177,51.2030792236],"type":"Point"}
}