{
  "type": "Feature",
  "properties": {
    "addr:full":"Hoge Weg 13 Zottegem (grotenberge) Oost-Vlaanderen 9620",
    "addr:housenumber":"13",
    "addr:postcode":"9620",
    "addr:street":"Hoge Weg",
    "iso:country":"BE",
    "sg:address":"Hoge Weg 13",
    "sg:city":"Zottegem (grotenberge)",
    "sg:classifiers":[
        {
            "category":"Utilities",
            "subcategory":"Recycling",
            "type":"Services"
        }
    ],
    "sg:phone":"+32 9 360 64 39",
    "sg:postcode":"9620",
    "sg:province":"Oost-Vlaanderen",
    "sg:tags":[
        "rubbish",
        "removal"
    ],
    "wof:name":"Coppens D",
    "wof:placetype":"venue"
},
  "geometry": {"coordinates":[3.8112111092,50.871181488],"type":"Point"}
}