{
  "type": "Feature",
  "properties": {
    "addr:full":"Avenue Pr\u00e9sident Roosevelt 33 Sambreville (tamines) Namur 5060",
    "addr:housenumber":"33",
    "addr:postcode":"5060",
    "addr:street":"Avenue Pre\u0301Sident Roosevelt",
    "iso:country":"BE",
    "sg:address":"Avenue Pr\u00e9sident Roosevelt 33",
    "sg:city":"Sambreville (tamines)",
    "sg:classifiers":[
        {
            "category":"Shopping",
            "subcategory":"Clothing, Apparel, & Fashions",
            "type":"Retail Goods"
        }
    ],
    "sg:phone":"+32 71 77 01 15",
    "sg:postcode":"5060",
    "sg:province":"Namur",
    "sg:tags":[
        "underwear",
        "lingerie",
        "-"
    ],
    "wof:name":"Ambre Lingerie",
    "wof:placetype":"venue"
},
  "geometry": {"coordinates":[4.6285200119,50.4448738098],"type":"Point"}
}