{
  "type": "Feature",
  "properties": {
    "addr:full":"15 Rue Du Chemin De Fer 6041 Charleroi 15",
    "addr:housenumber":"15;15",
    "addr:postcode":"6041",
    "addr:street":"Rue Du Chemin De Fer;Charleroi",
    "iso:country":"BE",
    "sg:address":"15",
    "sg:city":"Rue Du Chemin De Fer 6041 Charleroi",
    "sg:classifiers":[
        {
            "category":"Utilities",
            "subcategory":"Electric",
            "type":"Services"
        }
    ],
    "sg:phone":"+32 71 35 78 35",
    "sg:postcode":"15",
    "sg:tags":[
        "electricity",
        "electronic",
        "electrical",
        "equipment"
    ],
    "wof:name":"Electrotechnic Sprl",
    "wof:placetype":"venue"
},
  "geometry": {"coordinates":[4.4314317703,50.4685935974],"type":"Point"}
}