{
  "type": "Feature",
  "properties": {
    "iso:country":"BE",
    "sg:address":"Vlasmarkt 33",
    "sg:city":"Dendermonde",
    "sg:orig_category":"Souvenirs and objets artisanaux",
    "sg:phone":"+32 52 21 21 09",
    "sg:postcode":"9200",
    "sg:province":"Oost-Vlaanderen",
    "wof:name":"Pop Art",
    "wof:placetype":"venue"
},
  "geometry": {"coordinates":[4.0991921425,51.0292778015],"type":"Point"}
}