{
  "type": "Feature",
  "properties": {
    "iso:country":"BE",
    "sg:address":"Du Montstraat 51",
    "sg:city":"Deurne",
    "sg:classifiers":[
        {
            "category":"Bakery",
            "type":"Food & Drink"
        }
    ],
    "sg:phone":"+32 3 324 31 00",
    "sg:postcode":"2100",
    "sg:province":"Antwerpen",
    "sg:tags":[
        "cake",
        "product",
        "related",
        "bread"
    ],
    "wof:name":"Bakkerij De Kort Nv",
    "wof:placetype":"venue"
},
  "geometry": {"coordinates":[4.4586868286,51.2275238037],"type":"Point"}
}