{
  "type": "Feature",
  "properties": {
    "addr:full":"Mont 26ba Theux Li\u00e8ge 4910",
    "addr:housenumber":"26ba",
    "addr:postcode":"4910",
    "addr:street":"Mont",
    "iso:country":"BE",
    "sg:address":"Mont 26ba",
    "sg:city":"Theux",
    "sg:orig_category":"Eleveurs de bovins",
    "sg:phone":"+32 87 54 15 35",
    "sg:postcode":"4910",
    "sg:province":"Li\u00e8ge",
    "wof:name":"Andre Labasse-delforge",
    "wof:placetype":"venue"
},
  "geometry": {"coordinates":[5.7880001068,50.5357627869],"type":"Point"}
}