{
  "type": "Feature",
  "properties": {
    "addr:full":"Bankstraat 30 Wevelgem (gullegem) West-Vlaanderen 8560",
    "addr:housenumber":"30",
    "addr:postcode":"8560",
    "addr:street":"Bankstraat",
    "iso:country":"BE",
    "sg:address":"Bankstraat 30",
    "sg:city":"Wevelgem (gullegem)",
    "sg:classifiers":[
        {
            "category":"Real Estate",
            "subcategory":"Architect",
            "type":"Services"
        }
    ],
    "sg:phone":"+32 56 42 23 62",
    "sg:postcode":"8560",
    "sg:province":"West-Vlaanderen",
    "wof:name":"Vandeputte S",
    "wof:placetype":"venue"
},
  "geometry": {"coordinates":[3.2024359703,50.8443984985],"type":"Point"}
}