{
  "type": "Feature",
  "properties": {
    "iso:country":"BE",
    "sg:address":"Rue Du Croly 4",
    "sg:city":"Chaumont-gistoux (corroy-le-grand)",
    "sg:classifiers":[
        {
            "category":"Building & Trades",
            "subcategory":"Landscaping Services",
            "type":"Services"
        }
    ],
    "sg:phone":"+32 10 68 94 79",
    "sg:postcode":"1325",
    "sg:province":"Brabant Wallon",
    "sg:tags":[
        "gardening",
        "garden",
        "maintenance"
    ],
    "wof:name":"Pellegrin Jardins",
    "wof:placetype":"venue"
},
  "geometry": {"coordinates":[4.6731028557,50.6671676636],"type":"Point"}
}