{
  "type": "Feature",
  "properties": {
    "addr:full":"Kerkstraat 76 Anzegem West-Vlaanderen 8570",
    "addr:housenumber":"76",
    "addr:postcode":"8570",
    "addr:street":"Kerkstraat",
    "iso:country":"BE",
    "sg:address":"Kerkstraat 76",
    "sg:city":"Anzegem",
    "sg:orig_category":"Tabac. Journaux",
    "sg:phone":"+32 56 68 15 89",
    "sg:postcode":"8570",
    "sg:province":"West-Vlaanderen",
    "wof:name":"Huis 't Cursiefje",
    "wof:placetype":"venue"
},
  "geometry": {"coordinates":[3.4751870632,50.8378295898],"type":"Point"}
}