{
  "type": "Feature",
  "properties": {
    "addr:full":"Linde 39 Londerzeel Vlaams-Brabant 1840",
    "addr:housenumber":"39",
    "addr:postcode":"1840",
    "addr:street":"Linde",
    "iso:country":"BE",
    "sg:address":"Linde 39",
    "sg:city":"Londerzeel",
    "sg:orig_category":"Installation de menuiserie en bois and plastique",
    "sg:phone":"+32 52 30 21 99",
    "sg:postcode":"1840",
    "sg:province":"Vlaams-Brabant",
    "wof:name":"Home Renovation",
    "wof:placetype":"venue"
},
  "geometry": {"coordinates":[4.3021111488,51.0093269348],"type":"Point"}
}