{
  "type": "Feature",
  "properties": {
    "addr:full":"Koningin Elisabethlaan 65 Sint-niklaas Oost-Vlaanderen 9100",
    "addr:housenumber":"65",
    "addr:postcode":"9100",
    "addr:street":"Koningin Elisabethlaan",
    "iso:country":"BE",
    "sg:address":"Koningin Elisabethlaan 65",
    "sg:city":"Sint-niklaas",
    "sg:orig_category":"V\u00e9t\u00e9rinaires",
    "sg:phone":"+32 3 777 53 60",
    "sg:postcode":"9100",
    "sg:province":"Oost-Vlaanderen",
    "wof:name":"Anna Van Roey",
    "wof:placetype":"venue"
},
  "geometry": {"coordinates":[4.150829792,51.1717796326],"type":"Point"}
}