{
  "type": "Feature",
  "properties": {
    "iso:country":"BE",
    "sg:address":"Chauss\u00e9e D'alsemberg 84",
    "sg:city":"Bruxelles (saint-gilles)",
    "sg:classifiers":[
        {
            "category":"Shopping",
            "subcategory":"Bicycles & Sporting Goods",
            "type":"Retail Goods"
        }
    ],
    "sg:phone":"+32 2 539 35 04",
    "sg:postcode":"1060",
    "sg:province":"Bruxelles-Capitale",
    "sg:tags":[
        "sport",
        "-"
    ],
    "wof:name":"Claudy Sport",
    "wof:placetype":"venue"
},
  "geometry": {"coordinates":[4.3404240608,50.831653595],"type":"Point"}
}