{
  "type": "Feature",
  "properties": {
    "addr:full":"Kapellestraat 173 Mol Antwerpen 2400",
    "addr:housenumber":"173",
    "addr:postcode":"2400",
    "addr:street":"Kapellestraat",
    "iso:country":"BE",
    "sg:address":"Kapellestraat 173",
    "sg:city":"Mol",
    "sg:classifiers":[
        {
            "category":"Bakery",
            "type":"Food & Drink"
        }
    ],
    "sg:phone":"+32 14 31 70 56",
    "sg:postcode":"2400",
    "sg:province":"Antwerpen",
    "sg:tags":[
        "confectioner",
        "baker"
    ],
    "wof:name":"Meeus L",
    "wof:placetype":"venue"
},
  "geometry": {"coordinates":[5.1337151527,51.199382782],"type":"Point"}
}