{
  "type": "Feature",
  "properties": {
    "addr:full":"Heirweg 10 Middelkerke (wilskerke) West-Vlaanderen 8431",
    "addr:housenumber":"10",
    "addr:postcode":"8431",
    "addr:street":"Heirweg",
    "iso:country":"BE",
    "sg:address":"Heirweg 10",
    "sg:city":"Middelkerke (wilskerke)",
    "sg:classifiers":[
        {
            "category":"Bars & Pubs",
            "type":"Food & Drink"
        }
    ],
    "sg:phone":"+32 59 30 50 81",
    "sg:postcode":"8431",
    "sg:province":"West-Vlaanderen",
    "wof:name":"Bierpotje ('t)",
    "wof:placetype":"venue"
},
  "geometry": {"coordinates":[2.8148980141,51.1814651489],"type":"Point"}
}