{
  "type": "Feature",
  "properties": {
    "iso:country":"BE",
    "sg:address":"Rue De La Franco-belge 126",
    "sg:city":"La Louvi\u00c8re",
    "sg:orig_category":"Eclairage et \u00e9quipements du foyer. Souvenirs and objets artisanaux. Jeux and jouets",
    "sg:phone":"+32 64 26 56 88",
    "sg:postcode":"7100",
    "sg:province":"Hainaut",
    "wof:name":"Blokker",
    "wof:placetype":"venue"
},
  "geometry": {"coordinates":[4.2108540535,50.4849510193],"type":"Point"}
}