{
  "type": "Feature",
  "properties": {
    "iso:country":"BE",
    "sg:address":"Watermolenwal 9",
    "sg:city":"Kortrijk",
    "sg:orig_category":"Slagers",
    "sg:phone":"+32 56 35 28 67",
    "sg:postcode":"8501",
    "sg:province":"West-Vlaanderen",
    "wof:name":"Frank Lefevre",
    "wof:placetype":"venue"
},
  "geometry": {"coordinates":[3.2557599545,50.8423614502],"type":"Point"}
}