{
  "type": "Feature",
  "properties": {
    "iso:country":"BE",
    "sg:address":"Limburgstraat 2b",
    "sg:city":"Gent",
    "sg:orig_category":"Hotels Ruimtes voor conferenties, recepties and feesten",
    "sg:phone":"+32 9 233 00 00",
    "sg:postcode":"9000",
    "sg:province":"Oost-Vlaanderen",
    "wof:name":"Ibis St. Baafs Kathedraal",
    "wof:placetype":"venue"
},
  "geometry": {"coordinates":[3.7260639668,51.0529708862],"type":"Point"}
}