{
  "type": "Feature",
  "properties": {
    "iso:country":"BE",
    "sg:address":"Chauss\u00c9e De Lille 63",
    "sg:city":"Tournai",
    "sg:orig_category":"Herstellingen and onderhoud van auto's",
    "sg:phone":"+32 69 22 65 75",
    "sg:postcode":"7501",
    "sg:province":"Hainaut",
    "wof:name":"A. Foret",
    "wof:placetype":"venue"
},
  "geometry": {"coordinates":[3.3724191189,50.6049461365],"type":"Point"}
}