{
  "type": "Feature",
  "properties": {
    "addr:full":"Rue Masure 23 Charleroi Hainaut 6040",
    "addr:housenumber":"23",
    "addr:postcode":"6040",
    "addr:street":"Rue Masure;Hainaut",
    "iso:country":"BE",
    "sg:address":"Rue Masure 23",
    "sg:city":"Charleroi",
    "sg:orig_category":"Belastingconsulenten Diverse juridische dienstverlening",
    "sg:phone":"+32 71 35 47 66",
    "sg:postcode":"6040",
    "sg:province":"Hainaut",
    "wof:name":"Deroeck & Fils",
    "wof:placetype":"venue"
},
  "geometry": {"coordinates":[4.4118928909,50.442653656],"type":"Point"}
}