{
  "type": "Feature",
  "properties": {
    "iso:country":"BE",
    "sg:address":"Sint-gillislaan 54b3",
    "sg:city":"Dendermonde",
    "sg:orig_category":"Traitements param\u00e9dicaux",
    "sg:phone":"+32 52 21 52 43",
    "sg:postcode":"9200",
    "sg:province":"Oost-Vlaanderen",
    "wof:name":"K. Bleys",
    "wof:placetype":"venue"
},
  "geometry": {"coordinates":[4.1096482277,51.020072937],"type":"Point"}
}