{
  "type": "Feature",
  "properties": {
    "addr:full":"Rue De L'institut 40 Soumagne (cerexhe-heuseux) Li\u00e8ge 4632",
    "addr:housenumber":"40",
    "addr:postcode":"4632",
    "addr:street":"Rue De L'Institut;Cerexhe-Heuseux",
    "iso:country":"BE",
    "sg:address":"Rue De L'institut 40",
    "sg:city":"Soumagne (cerexhe-heuseux)",
    "sg:classifiers":[
        {
            "category":"Social Services",
            "subcategory":"Child Care",
            "type":"Services"
        }
    ],
    "sg:phone":"+32 4 377 91 77",
    "sg:postcode":"4632",
    "sg:province":"Li\u00e8ge",
    "sg:tags":[
        "home"
    ],
    "wof:name":"Acis Asbl Institut Notre-dame",
    "wof:placetype":"venue"
},
  "geometry": {"coordinates":[5.7188930511,50.6558532715],"type":"Point"}
}