{
  "type": "Feature",
  "properties": {
    "iso:country":"BE",
    "sg:address":"Geraardsbergenstraat 210",
    "sg:city":"Oudenaarde",
    "sg:classifiers":[
        {
            "category":"Health Services",
            "subcategory":"Nursing And Care Facility",
            "type":"Services"
        }
    ],
    "sg:phone":"+32 55 33 06 36",
    "sg:postcode":"9700",
    "sg:province":"Oost-Vlaanderen",
    "sg:tags":[
        "home"
    ],
    "wof:name":"Rombout L",
    "wof:placetype":"venue"
},
  "geometry": {"coordinates":[3.6416499615,50.829208374],"type":"Point"}
}