{
  "type": "Feature",
  "properties": {
    "iso:country":"BE",
    "sg:address":"Vaderlandstraat 16",
    "sg:city":"Gent",
    "sg:classifiers":[
        {
            "category":"Shopping",
            "subcategory":"Antiques",
            "type":"Retail Goods"
        }
    ],
    "sg:phone":"+32 9 220 74 73",
    "sg:postcode":"9000",
    "sg:province":"Oost-Vlaanderen",
    "wof:name":"Antique Academy (the)",
    "wof:placetype":"venue"
},
  "geometry": {"coordinates":[3.7148270607,51.0313148499],"type":"Point"}
}