{
  "type": "Feature",
  "properties": {
    "addr:full":"August Dierckxlaan 12 Schilde Antwerpen 2970",
    "addr:housenumber":"12",
    "addr:postcode":"2970",
    "addr:street":"Dierckxlaan",
    "iso:country":"BE",
    "sg:address":"August Dierckxlaan 12",
    "sg:city":"Schilde",
    "sg:classifiers":[
        {
            "category":"Retail",
            "subcategory":"Repair Shop",
            "type":"Services"
        }
    ],
    "sg:phone":"+32 3 384 37 07",
    "sg:postcode":"2970",
    "sg:province":"Antwerpen",
    "wof:name":"Thaens P",
    "wof:placetype":"venue"
},
  "geometry": {"coordinates":[4.5852122307,51.2358894348],"type":"Point"}
}