{
  "type": "Feature",
  "properties": {
    "addr:full":"Rue Stanley 93 Bruxelles (uccle) Bruxelles-Capitale 1180",
    "addr:housenumber":"93",
    "addr:postcode":"1180",
    "addr:street":"Rue Stanley",
    "iso:country":"BE",
    "sg:address":"Rue Stanley 93",
    "sg:city":"Bruxelles (uccle)",
    "sg:classifiers":[
        {
            "category":"Shopping",
            "subcategory":"Books",
            "type":"Retail Goods"
        }
    ],
    "sg:phone":"+32 2 345 81 85",
    "sg:postcode":"1180",
    "sg:province":"Bruxelles-Capitale",
    "sg:tags":[
        "bookseller"
    ],
    "wof:name":"Am Stram Gram",
    "wof:placetype":"venue"
},
  "geometry": {"coordinates":[4.3645238876,50.8147239685],"type":"Point"}
}