{
  "type": "Feature",
  "properties": {
    "addr:full":"Chauss\u00e9e De Boondael 390 Bruxelles (ixelles) Bruxelles-Capitale 1050",
    "addr:housenumber":"390",
    "addr:postcode":"1050",
    "addr:street":"Chausse\u0301E De Boondael",
    "iso:country":"BE",
    "sg:address":"Chauss\u00e9e De Boondael 390",
    "sg:city":"Bruxelles (ixelles)",
    "sg:classifiers":[
        {
            "category":"Health Services",
            "subcategory":"Nursing And Care Facility",
            "type":"Services"
        }
    ],
    "sg:phone":"+32 2 649 41 28",
    "sg:postcode":"1050",
    "sg:province":"Bruxelles-Capitale",
    "sg:tags":[
        "home"
    ],
    "wof:name":"Aremis Asbl",
    "wof:placetype":"venue"
},
  "geometry": {"coordinates":[4.3871560097,50.817855835],"type":"Point"}
}