{
  "type": "Feature",
  "properties": {
    "addr:full":"Rue Pierre Broodcoorens 54 La Hulpe Brabant Wallon 1310",
    "addr:housenumber":"54",
    "addr:postcode":"1310",
    "addr:street":"Rue Pierre Broodcoorens",
    "iso:country":"BE",
    "sg:address":"Rue Pierre Broodcoorens 54",
    "sg:city":"La Hulpe",
    "sg:orig_category":"Brood, gebak and snoepgoed",
    "sg:phone":"+32 2 654 00 43",
    "sg:postcode":"1310",
    "sg:province":"Brabant Wallon",
    "wof:name":"Corn\u00c9 Port-royal Chocolatier",
    "wof:placetype":"venue"
},
  "geometry": {"coordinates":[4.48523283,50.7271957397],"type":"Point"}
}