{
  "type": "Feature",
  "properties": {
    "iso:country":"BE",
    "sg:address":"Oostkaai 6",
    "sg:city":"Ieper",
    "sg:orig_category":"Quincailleries",
    "sg:phone":"+32 57 21 78 72",
    "sg:postcode":"8900",
    "sg:province":"West-Vlaanderen",
    "wof:name":"Delva Shopping",
    "wof:placetype":"venue"
},
  "geometry": {"coordinates":[2.8846380711,50.8590621948],"type":"Point"}
}