{
  "type": "Feature",
  "properties": {
    "iso:country":"BE",
    "sg:address":"Rue Du Parc 21",
    "sg:city":"Charleroi",
    "sg:classifiers":[
        {
            "category":"Health Services",
            "subcategory":"Health Practitioner",
            "type":"Services"
        }
    ],
    "sg:phone":"+32 71 30 40 53",
    "sg:postcode":"6000",
    "sg:province":"Hainaut",
    "sg:tags":[
        "physiotherapist"
    ],
    "wof:name":"Badibengy B",
    "wof:placetype":"venue"
},
  "geometry": {"coordinates":[4.4496469498,50.4095916748],"type":"Point"}
}