{
  "type": "Feature",
  "properties": {
    "iso:country":"BE",
    "sg:address":"Oostmalsebaan 9",
    "sg:city":"Lille",
    "sg:orig_category":"Afvalophaling and -verwerking industrie, landbouw and bouwpuin",
    "sg:phone":"+32 3 309 20 49",
    "sg:postcode":"2275",
    "sg:province":"Antwerpen",
    "wof:name":"A.m.s.",
    "wof:placetype":"venue"
},
  "geometry": {"coordinates":[4.7848567963,51.2638702393],"type":"Point"}
}