{
  "type": "Feature",
  "properties": {
    "iso:country":"BE",
    "sg:address":"Industrieter. Leuerbroek 1038",
    "sg:city":"Kinrooi",
    "sg:orig_category":"Installation \u00e9lectrique r\u00e9sidentielle. Installation \u00e9lectrique industrielle",
    "sg:phone":"+32 89 70 15 73",
    "sg:postcode":"3640",
    "sg:province":"Limburg",
    "wof:name":"Maco",
    "wof:placetype":"venue"
},
  "geometry": {"coordinates":[5.7478260994,51.1378135681],"type":"Point"}
}