{
  "type": "Feature",
  "properties": {
    "iso:country":"BE",
    "sg:address":"Liersesteenweg 193",
    "sg:city":"Sint-katelijne-waver",
    "sg:classifiers":[
        {
            "category":"Food & Beverages",
            "subcategory":"Groceries & Convenience Stores",
            "type":"Retail Goods"
        }
    ],
    "sg:phone":"+32 15 20 62 46",
    "sg:postcode":"2860",
    "sg:province":"Antwerpen",
    "sg:tags":[
        "grocer"
    ],
    "wof:name":"Verniers",
    "wof:placetype":"venue"
},
  "geometry": {"coordinates":[4.4796409607,51.0602607727],"type":"Point"}
}