{
  "type": "Feature",
  "properties": {
    "addr:full":"Industrielaan 53 Schoten Antwerpen 2900",
    "addr:housenumber":"53",
    "addr:postcode":"2900",
    "addr:street":"Industrielaan",
    "iso:country":"BE",
    "sg:address":"Industrielaan 53",
    "sg:city":"Schoten",
    "sg:orig_category":"Non-Classified Establishments",
    "sg:phone":"+32 3 324 48 98",
    "sg:postcode":"2900",
    "sg:province":"Antwerpen",
    "wof:name":"I.t.m. Bvba",
    "wof:placetype":"venue"
},
  "geometry": {"coordinates":[4.4774580002,51.2382621765],"type":"Point"}
}