{
  "type": "Feature",
  "properties": {
    "addr:full":"Engelse Wandeling 2 Kortrijk West-Vlaanderen 8500",
    "addr:housenumber":"2",
    "addr:postcode":"8500",
    "addr:street":"Engelse Wandeling",
    "iso:country":"BE",
    "sg:address":"Engelse Wandeling 2",
    "sg:city":"Kortrijk",
    "sg:classifiers":[
        {
            "category":"Bars & Pubs",
            "type":"Food & Drink"
        }
    ],
    "sg:phone":"+32 56 25 66 61",
    "sg:postcode":"8500",
    "sg:province":"West-Vlaanderen",
    "wof:name":"Factory (the)",
    "wof:placetype":"venue"
},
  "geometry": {"coordinates":[3.2476019859,50.8158874512],"type":"Point"}
}