{
  "type": "Feature",
  "properties": {
    "addr:full":"Heusdendorp 6 Destelbergen Oost-Vlaanderen 9070",
    "addr:housenumber":"6",
    "addr:postcode":"9070",
    "addr:street":"Heusdendorp",
    "iso:country":"BE",
    "sg:address":"Heusdendorp 6",
    "sg:city":"Destelbergen",
    "sg:orig_category":"Centres de relaxation and bien-\u00eatre. Instituts de beaut\u00e9",
    "sg:phone":"+32 9 230 44 82",
    "sg:postcode":"9070",
    "sg:province":"Oost-Vlaanderen",
    "wof:name":"Instituut Delphine",
    "wof:placetype":"venue"
},
  "geometry": {"coordinates":[3.8002920151,51.0289840698],"type":"Point"}
}