{
  "type": "Feature",
  "properties": {
    "addr:full":"J. De Troozlaan 80 Blankenberge West-Vlaanderen 8370",
    "addr:housenumber":"80",
    "addr:postcode":"8370",
    "addr:street":"J. De Troozlaan",
    "iso:country":"BE",
    "sg:address":"J. De Troozlaan 80",
    "sg:city":"Blankenberge",
    "sg:classifiers":[
        {
            "category":"Health Services",
            "subcategory":"Doctor",
            "type":"Services"
        }
    ],
    "sg:phone":"+32 50 42 88 88",
    "sg:postcode":"8370",
    "sg:province":"West-Vlaanderen",
    "sg:tags":[
        "medicinephysicians",
        "surgeon"
    ],
    "wof:name":"Albrecht J",
    "wof:placetype":"venue"
},
  "geometry": {"coordinates":[3.1351299286,51.3170700073],"type":"Point"}
}