{
  "type": "Feature",
  "properties": {
    "addr:full":"Stationsplein 1 Tielt West-Vlaanderen 8700",
    "addr:housenumber":"1",
    "addr:postcode":"8700",
    "addr:street":"Stationsplein",
    "iso:country":"BE",
    "sg:address":"Stationsplein 1",
    "sg:city":"Tielt",
    "sg:classifiers":[
        {
            "category":"Professional",
            "subcategory":"Art Services",
            "type":"Services"
        }
    ],
    "sg:phone":"+32 51 40 26 82",
    "sg:postcode":"8700",
    "sg:province":"West-Vlaanderen",
    "sg:tags":[
        "automobile",
        "transit",
        "-",
        "export",
        "import"
    ],
    "wof:name":"Goethals",
    "wof:placetype":"venue"
},
  "geometry": {"coordinates":[3.3257000446,50.9941902161],"type":"Point"}
}