{
  "type": "Feature",
  "properties": {
    "addr:full":"Chauss\u00c9e De Li\u00c8ge 14 Welkenraedt/welkenraedt Li\u00e8ge 4841",
    "addr:housenumber":"14",
    "addr:postcode":"4841",
    "addr:street":"Chausse\u0301E De Lie\u0300Ge",
    "iso:country":"BE",
    "sg:address":"Chauss\u00c9e De Li\u00c8ge 14",
    "sg:city":"Welkenraedt/welkenraedt",
    "sg:orig_category":"Artsen and specialisten",
    "sg:phone":"+32 87 88 05 43",
    "sg:postcode":"4841",
    "sg:province":"Li\u00e8ge",
    "wof:name":"Myriam Henkens",
    "wof:placetype":"venue"
},
  "geometry": {"coordinates":[5.9260559082,50.6764907837],"type":"Point"}
}