{
  "type": "Feature",
  "properties": {
    "iso:country":"BE",
    "sg:address":"Meersstr 45",
    "sg:city":"Avelgem",
    "sg:classifiers":[
        {
            "category":"Shopping",
            "subcategory":"Clothing, Apparel, & Fashions",
            "type":"Retail Goods"
        }
    ],
    "sg:phone":"+32 56 64 53 43",
    "sg:postcode":"8580",
    "sg:province":"West-Vlaanderen",
    "sg:tags":[
        "textile",
        "clothing",
        "clothes"
    ],
    "wof:name":"Deweer Security Nv",
    "wof:placetype":"venue"
},
  "geometry": {"coordinates":[3.4487199783,50.7695198059],"type":"Point"}
}