{
  "type": "Feature",
  "properties": {
    "addr:full":"Rue De La Crosse 1 Hannut Li\u00e8ge 4280",
    "addr:housenumber":"1",
    "addr:postcode":"4280",
    "addr:street":"Rue De La Crosse",
    "iso:country":"BE",
    "sg:address":"Rue De La Crosse 1",
    "sg:city":"Hannut",
    "sg:orig_category":"M\u00e9decins and sp\u00e9cialistes",
    "sg:phone":"+32 19 51 60 22",
    "sg:postcode":"4280",
    "sg:province":"Li\u00e8ge",
    "wof:name":"Annick Compes",
    "wof:placetype":"venue"
},
  "geometry": {"coordinates":[5.0948500633,50.6564941406],"type":"Point"}
}