{
  "type": "Feature",
  "properties": {
    "iso:country":"BE",
    "sg:address":"Route De L'etat 206",
    "sg:city":"Lasne",
    "sg:orig_category":"Artistes ind\u00e9pendants",
    "sg:phone":"+32 2 633 41 85",
    "sg:postcode":"1380",
    "sg:province":"Brabant Wallon",
    "wof:name":"Jacqueline Crabeels",
    "wof:placetype":"venue"
},
  "geometry": {"coordinates":[4.464577198,50.6696472168],"type":"Point"}
}