{
  "type": "Feature",
  "properties": {
    "addr:full":"Leopoldlaan 79 Middelkerke West-Vlaanderen 8430",
    "addr:housenumber":"79",
    "addr:postcode":"8430",
    "addr:street":"Leopoldlaan",
    "iso:country":"BE",
    "sg:address":"Leopoldlaan 79",
    "sg:city":"Middelkerke",
    "sg:classifiers":[
        {
            "category":"Restaurant",
            "type":"Food & Drink"
        }
    ],
    "sg:phone":"+32 59 30 43 20",
    "sg:postcode":"8430",
    "sg:province":"West-Vlaanderen",
    "sg:tags":[
        "caf\u00e9s"
    ],
    "wof:name":"Restaurant Octopussy",
    "wof:placetype":"venue"
},
  "geometry": {"coordinates":[2.8139469624,51.1870155334],"type":"Point"}
}