{
  "type": "Feature",
  "properties": {
    "addr:full":"Schoolstraat 15 Wijnegem Antwerpen 2110",
    "addr:housenumber":"15",
    "addr:postcode":"2110",
    "addr:street":"Schoolstraat",
    "iso:country":"BE",
    "sg:address":"Schoolstraat 15",
    "sg:city":"Wijnegem",
    "sg:classifiers":[
        {
            "category":"Personal",
            "subcategory":"Beauty Salon",
            "type":"Services"
        }
    ],
    "sg:phone":"+32 3 353 09 72",
    "sg:postcode":"2110",
    "sg:province":"Antwerpen",
    "sg:tags":[
        "lady",
        "-",
        "hairdressing"
    ],
    "wof:name":"Carla",
    "wof:placetype":"venue"
},
  "geometry": {"coordinates":[4.5209817886,51.2279167175],"type":"Point"}
}