{
  "type": "Feature",
  "properties": {
    "addr:full":"Rue De Haillot 56 Andenne Namur 5300",
    "addr:housenumber":"56",
    "addr:postcode":"5300",
    "addr:street":"Rue De Haillot",
    "iso:country":"BE",
    "sg:address":"Rue De Haillot 56",
    "sg:city":"Andenne",
    "sg:classifiers":[
        {
            "category":"Insurance",
            "subcategory":"Life Insurance",
            "type":"Services"
        }
    ],
    "sg:phone":"+32 85 84 14 18",
    "sg:postcode":"5300",
    "sg:province":"Namur",
    "sg:tags":[
        "assurance"
    ],
    "wof:name":"Andennassur",
    "wof:placetype":"venue"
},
  "geometry": {"coordinates":[5.1131119728,50.4827575684],"type":"Point"}
}