{
  "type": "Feature",
  "properties": {
    "addr:full":"Spoele 1 Lokeren Oost-Vlaanderen 9160",
    "addr:housenumber":"1",
    "addr:postcode":"9160",
    "addr:street":"Spoele",
    "iso:country":"BE",
    "sg:address":"Spoele 1",
    "sg:city":"Lokeren",
    "sg:classifiers":[
        {
            "category":"Bars & Pubs",
            "type":"Food & Drink"
        }
    ],
    "sg:phone":"+32 9 348 43 43",
    "sg:postcode":"9160",
    "sg:province":"Oost-Vlaanderen",
    "wof:name":"Statie(de)",
    "wof:placetype":"venue"
},
  "geometry": {"coordinates":[3.994590044,51.09141922],"type":"Point"}
}