{
  "type": "Feature",
  "properties": {
    "iso:country":"BE",
    "sg:address":"Samberstraat 48-50",
    "sg:city":"Antwerpen",
    "sg:classifiers":[
        {
            "category":"Wholesale",
            "subcategory":"Machinery & Supplies",
            "type":"Manufacturing & Wholesale Goods"
        }
    ],
    "sg:phone":"+32 3 227 20 96",
    "sg:postcode":"2060",
    "sg:province":"Antwerpen",
    "sg:tags":[
        "equipment",
        "ship"
    ],
    "wof:name":"Dalseide Shipping Services Nv",
    "wof:placetype":"venue"
},
  "geometry": {"coordinates":[4.4282999039,51.2334594727],"type":"Point"}
}