{
  "type": "Feature",
  "properties": {
    "iso:country":"BE",
    "sg:address":"Pelserstraat 25",
    "sg:city":"Maaseik",
    "sg:classifiers":[
        {
            "category":"Shopping",
            "subcategory":"Party Supplies",
            "type":"Retail Goods"
        }
    ],
    "sg:phone":"+32 89 56 47 01",
    "sg:postcode":"3680",
    "sg:province":"Limburg",
    "wof:name":"Fop Shop",
    "wof:placetype":"venue"
},
  "geometry": {"coordinates":[5.7891821861,51.0961303711],"type":"Point"}
}