{
  "type": "Feature",
  "properties": {
    "iso:country":"BE",
    "sg:address":"Heykavel 4b19",
    "sg:city":"Sint-gillis-waas",
    "sg:orig_category":"Schoonmaakbedrijven and ongediertebestrijding Wasserijen, Reiniging and Droogkuis",
    "sg:phone":"+32 3 707 08 25",
    "sg:postcode":"9170",
    "sg:province":"Oost-Vlaanderen",
    "wof:name":"D.l. Luc's Glazenwasserij",
    "wof:placetype":"venue"
},
  "geometry": {"coordinates":[4.1104278564,51.2629203796],"type":"Point"}
}