{
  "type": "Feature",
  "properties": {
    "addr:full":"Moerenstraat 1 Tongeren Limburg 3700",
    "addr:housenumber":"1",
    "addr:postcode":"3700",
    "addr:street":"Moerenstraat",
    "iso:country":"BE",
    "sg:address":"Moerenstraat 1",
    "sg:city":"Tongeren",
    "sg:classifiers":[
        {
            "category":"Professional",
            "subcategory":"Lawyer & Legal Services",
            "type":"Services"
        }
    ],
    "sg:phone":"+32 12 23 18 47",
    "sg:postcode":"3700",
    "sg:province":"Limburg",
    "wof:name":"Geukens Ludo",
    "wof:placetype":"venue"
},
  "geometry": {"coordinates":[5.4688539505,50.781162262],"type":"Point"}
}