{
  "type": "Feature",
  "properties": {
    "iso:country":"BE",
    "sg:address":"Rue De La Piraille 37",
    "sg:city":"Thuin",
    "sg:classifiers":[
        {
            "category":"Social Services",
            "type":"Services"
        }
    ],
    "sg:phone":"+32 71 59 42 70",
    "sg:postcode":"6530",
    "sg:province":"Hainaut",
    "wof:name":"Croix Rouge (la)",
    "wof:placetype":"venue"
},
  "geometry": {"coordinates":[4.28332901,50.3390731812],"type":"Point"}
}