{
  "type": "Feature",
  "properties": {
    "iso:country":"BE",
    "sg:address":"Gemeentestraat 41",
    "sg:city":"Nijlen",
    "sg:orig_category":"Enseignement secondaire technique and professionnel",
    "sg:phone":"+32 3 410 03 20",
    "sg:postcode":"2560",
    "sg:province":"Antwerpen",
    "wof:name":"Inst.techn. & Handelsond.",
    "wof:placetype":"venue"
},
  "geometry": {"coordinates":[4.6735777855,51.1617431641],"type":"Point"}
}