{
  "type": "Feature",
  "properties": {
    "iso:country":"BE",
    "sg:address":"Marktplein 23",
    "sg:city":"Diepenbeek",
    "sg:orig_category":"Eclairage et \u00e9quipements du foyer",
    "sg:phone":"+32 11 32 36 60",
    "sg:postcode":"3590",
    "sg:province":"Limburg",
    "wof:name":"Vande Gaer",
    "wof:placetype":"venue"
},
  "geometry": {"coordinates":[5.4188542366,50.9072151184],"type":"Point"}
}