{
  "type": "Feature",
  "properties": {
    "addr:full":"Rue Bois Du Sart 133 Courcelles Hainaut 6180",
    "addr:housenumber":"133",
    "addr:postcode":"6180",
    "addr:street":"Rue Bois Du Sart",
    "iso:country":"BE",
    "sg:address":"Rue Bois Du Sart 133",
    "sg:city":"Courcelles",
    "sg:classifiers":[
        {
            "category":"Professional",
            "subcategory":"Accounting & Tax Preparation",
            "type":"Services"
        }
    ],
    "sg:phone":"+32 71 45 33 74",
    "sg:postcode":"6180",
    "sg:province":"Hainaut",
    "sg:tags":[
        "bookkeeper"
    ],
    "wof:name":"Silence Cl",
    "wof:placetype":"venue"
},
  "geometry": {"coordinates":[4.3938097954,50.4536170959],"type":"Point"}
}