{
  "type": "Feature",
  "properties": {
    "iso:country":"BE",
    "sg:address":"De Kluis 2",
    "sg:city":"Schilde",
    "sg:orig_category":"Artsen and specialisten",
    "sg:phone":"+32 3 383 49 20",
    "sg:postcode":"2970",
    "sg:province":"Antwerpen",
    "wof:name":"R. De Clerck",
    "wof:placetype":"venue"
},
  "geometry": {"coordinates":[4.5657010078,51.235710144],"type":"Point"}
}