{
  "type": "Feature",
  "properties": {
    "iso:country":"BE",
    "sg:address":"Kapellestraat 10",
    "sg:city":"De Haan",
    "sg:classifiers":[
        {
            "category":"Restaurant",
            "type":"Food & Drink"
        }
    ],
    "sg:phone":"+32 59 23 56 26",
    "sg:postcode":"8420",
    "sg:province":"West-Vlaanderen",
    "wof:name":"Pizzeria Piano Piano",
    "wof:placetype":"venue"
},
  "geometry": {"coordinates":[3.0343089104,51.2714233398],"type":"Point"}
}