{
  "type": "Feature",
  "properties": {
    "iso:country":"BE",
    "sg:address":"Galgenstraat 7",
    "sg:city":"Eeklo",
    "sg:classifiers":[
        {
            "category":"Insurance",
            "subcategory":"Insurance Agent",
            "type":"Services"
        }
    ],
    "sg:phone":"+32 9 377 30 76",
    "sg:postcode":"9900",
    "sg:province":"Oost-Vlaanderen",
    "sg:tags":[
        "verzekeringsmakelaars",
        "expert"
    ],
    "wof:name":"A. Slock",
    "wof:placetype":"venue"
},
  "geometry": {"coordinates":[3.5430860519,51.188949585],"type":"Point"}
}