{
  "type": "Feature",
  "properties": {
    "addr:full":"Rue De La Source 4 Saint-ghislain Hainaut 7331",
    "addr:housenumber":"4",
    "addr:postcode":"7331",
    "addr:street":"Rue De La Source;Hainaut",
    "iso:country":"BE",
    "sg:address":"Rue De La Source 4",
    "sg:city":"Saint-ghislain",
    "sg:orig_category":"Sportclubs",
    "sg:phone":"+32 65 64 19 87",
    "sg:postcode":"7331",
    "sg:province":"Hainaut",
    "wof:name":"J.c. Baudour",
    "wof:placetype":"venue"
},
  "geometry": {"coordinates":[3.8388669491,50.4864311218],"type":"Point"}
}