{
  "type": "Feature",
  "properties": {
    "iso:country":"BE",
    "sg:address":"Th. De Beckerstraat 28",
    "sg:city":"Aarschot",
    "sg:orig_category":"Textiel",
    "sg:phone":"+32 16 56 60 74",
    "sg:postcode":"3200",
    "sg:province":"Vlaams-Brabant",
    "wof:name":"Henckaerts",
    "wof:placetype":"venue"
},
  "geometry": {"coordinates":[4.8371748924,50.9852600098],"type":"Point"}
}