{
  "type": "Feature",
  "properties": {
    "iso:country":"BE",
    "sg:address":"Rue Louis Boumal 71",
    "sg:city":"Li\u00e8ge 1",
    "sg:classifiers":[
        {
            "category":"Health Services",
            "subcategory":"Dentist",
            "type":"Services"
        }
    ],
    "sg:phone":"+32 4 254 09 29",
    "sg:postcode":"4000",
    "sg:province":"Li\u00e8ge",
    "wof:name":"Plum Y",
    "wof:placetype":"venue"
},
  "geometry": {"coordinates":[5.5578861237,50.6319465637],"type":"Point"}
}