{
  "type": "Feature",
  "properties": {
    "addr:full":"Rue De Chiny 57a Tintigny (rossignol) Luxembourg 6730",
    "addr:housenumber":"57a",
    "addr:postcode":"6730",
    "addr:street":"Rue De Chiny",
    "iso:country":"BE",
    "sg:address":"Rue De Chiny 57a",
    "sg:city":"Tintigny (rossignol)",
    "sg:classifiers":[
        {
            "category":"Farming",
            "subcategory":"Berry Farm",
            "type":"Manufacturing & Wholesale Goods"
        }
    ],
    "sg:phone":"+32 63 41 20 67",
    "sg:postcode":"6730",
    "sg:province":"Luxembourg",
    "sg:tags":[
        "horticulture",
        "-",
        "broker",
        "whol",
        "seed",
        "grain",
        "agriculture"
    ],
    "wof:name":"Scam Sc",
    "wof:placetype":"venue"
},
  "geometry": {"coordinates":[5.4795670509,49.7180747986],"type":"Point"}
}