{
  "type": "Feature",
  "properties": {
    "addr:full":"Zomerstraat 38 Gent Oost-Vlaanderen 9000",
    "addr:housenumber":"38",
    "addr:postcode":"9000",
    "addr:street":"Zomerstraat;Oost-Vlaanderen",
    "iso:country":"BE",
    "sg:address":"Zomerstraat 38",
    "sg:city":"Gent",
    "sg:classifiers":[
        {
            "category":"Professional",
            "subcategory":"Accounting & Tax Preparation",
            "type":"Services"
        }
    ],
    "sg:phone":"+32 9 221 45 20",
    "sg:postcode":"9000",
    "sg:province":"Oost-Vlaanderen",
    "sg:tags":[
        "bookkeeper"
    ],
    "wof:name":"Notebaert A",
    "wof:placetype":"venue"
},
  "geometry": {"coordinates":[3.7282879353,51.0322799683],"type":"Point"}
}