{
  "type": "Feature",
  "properties": {
    "iso:country":"BE",
    "sg:address":"Beustereind 106",
    "sg:city":"Laakdal",
    "sg:orig_category":"Peinture. Rev\u00eatements pour sols and murs",
    "sg:phone":"+32 13 66 23 57",
    "sg:postcode":"2430",
    "sg:province":"Antwerpen",
    "wof:name":"Franky Bervoets",
    "wof:placetype":"venue"
},
  "geometry": {"coordinates":[5.0440502167,51.0848731995],"type":"Point"}
}