{
  "type": "Feature",
  "properties": {
    "iso:country":"BE",
    "sg:address":"Rue Croisette 16b",
    "sg:city":"Genappe (baisy-thy)",
    "sg:classifiers":[
        {
            "category":"Health Services",
            "subcategory":"Health Practitioner",
            "type":"Services"
        }
    ],
    "sg:phone":"+32 67 79 05 25",
    "sg:postcode":"1470",
    "sg:province":"Brabant Wallon",
    "sg:tags":[
        "physiotherapist"
    ],
    "wof:name":"Van Erp P",
    "wof:placetype":"venue"
},
  "geometry": {"coordinates":[4.480661869,50.593875885],"type":"Point"}
}