{
  "type": "Feature",
  "properties": {
    "iso:country":"BE",
    "sg:address":"Rue De L'ath\u00c9n\u00c9e 5",
    "sg:city":"Charleroi",
    "sg:orig_category":"Avocats and conseillers juridiques",
    "sg:phone":"+32 71 32 54 48",
    "sg:postcode":"6000",
    "sg:province":"Hainaut",
    "wof:name":"A. T'kint",
    "wof:placetype":"venue"
},
  "geometry": {"coordinates":[4.4486198425,50.4071311951],"type":"Point"}
}