{
  "type": "Feature",
  "properties": {
    "iso:country":"BE",
    "sg:address":"Rue Hubert Stiernet 42",
    "sg:city":"Waremme",
    "sg:classifiers":[
        {
            "category":"Shopping",
            "subcategory":"Computers & Home Electronics",
            "type":"Retail Goods"
        }
    ],
    "sg:phone":"+32 19 32 49 68",
    "sg:postcode":"4300",
    "sg:province":"Li\u00e8ge",
    "sg:tags":[
        "-",
        "television",
        "radio"
    ],
    "wof:name":"Martin Ets.",
    "wof:placetype":"venue"
},
  "geometry": {"coordinates":[5.2568888664,50.699131012],"type":"Point"}
}