{
  "type": "Feature",
  "properties": {
    "addr:full":"Oude Staatsbaan 176 Maldegem Oost-Vlaanderen 9991",
    "addr:housenumber":"176",
    "addr:postcode":"9991",
    "addr:street":"Oude Staatsbaan",
    "iso:country":"BE",
    "sg:address":"Oude Staatsbaan 176",
    "sg:city":"Maldegem",
    "sg:orig_category":"V\u00e9los",
    "sg:phone":"+32 9 377 85 43",
    "sg:postcode":"9991",
    "sg:province":"Oost-Vlaanderen",
    "wof:name":"Johan Toortelboom",
    "wof:placetype":"venue"
},
  "geometry": {"coordinates":[3.5141589642,51.2056694031],"type":"Point"}
}