{
  "type": "Feature",
  "properties": {
    "addr:full":"Antwerpsebaan 4 Zandhoven Antwerpen 2240",
    "addr:housenumber":"4",
    "addr:postcode":"2240",
    "addr:street":"Antwerpsebaan",
    "iso:country":"BE",
    "sg:address":"Antwerpsebaan 4",
    "sg:city":"Zandhoven",
    "sg:orig_category":"Rundveehouders",
    "sg:phone":"+32 3 484 32 25",
    "sg:postcode":"2240",
    "sg:province":"Antwerpen",
    "wof:name":"Dennendael",
    "wof:placetype":"venue"
},
  "geometry": {"coordinates":[4.6403689384,51.2037353516],"type":"Point"}
}