{
  "type": "Feature",
  "properties": {
    "addr:full":"Huiveldestraat 3 Dendermonde Oost-Vlaanderen 9200",
    "addr:housenumber":"3",
    "addr:postcode":"9200",
    "addr:street":"Huiveldestraat;Oost-Vlaanderen",
    "iso:country":"BE",
    "sg:address":"Huiveldestraat 3",
    "sg:city":"Dendermonde",
    "sg:orig_category":"Eleveurs de volaille",
    "sg:phone":"+32 52 21 63 03",
    "sg:postcode":"9200",
    "sg:province":"Oost-Vlaanderen",
    "wof:name":"Edmond Neirynck",
    "wof:placetype":"venue"
},
  "geometry": {"coordinates":[4.0906047821,51.0638504028],"type":"Point"}
}