{
  "type": "Feature",
  "properties": {
    "addr:full":"Vorstheide 12 Herselt Antwerpen 2230",
    "addr:housenumber":"12",
    "addr:postcode":"2230",
    "addr:street":"Vorstheide",
    "iso:country":"BE",
    "sg:address":"Vorstheide 12",
    "sg:city":"Herselt",
    "sg:classifiers":[
        {
            "category":"Building & Trades",
            "subcategory":"Electrical",
            "type":"Services"
        }
    ],
    "sg:phone":"+32 14 54 98 90",
    "sg:postcode":"2230",
    "sg:province":"Antwerpen",
    "sg:tags":[
        "electric",
        "-",
        "housewiring",
        "contractor"
    ],
    "wof:name":"Van Der Veken M",
    "wof:placetype":"venue"
},
  "geometry": {"coordinates":[4.892375946,51.0342521667],"type":"Point"}
}