{
  "type": "Feature",
  "properties": {
    "iso:country":"BE",
    "sg:address":"De Merodelei 93",
    "sg:city":"Turnhout",
    "sg:classifiers":[
        {
            "category":"Insurance",
            "subcategory":"Insurance Agent",
            "type":"Services"
        }
    ],
    "sg:phone":"+32 14 41 51 11",
    "sg:postcode":"2300",
    "sg:province":"Antwerpen",
    "sg:tags":[
        "broker"
    ],
    "wof:name":"Keysers R",
    "wof:placetype":"venue"
},
  "geometry": {"coordinates":[4.9380450249,51.3216133118],"type":"Point"}
}