{
  "type": "Feature",
  "properties": {
    "addr:full":"Heerstraat 13 Hechtel-eksel Limburg 3941",
    "addr:housenumber":"13",
    "addr:postcode":"3941",
    "addr:street":"Heerstraat",
    "iso:country":"BE",
    "sg:address":"Heerstraat 13",
    "sg:city":"Hechtel-eksel",
    "sg:orig_category":"Souvenirs and objets artisanaux",
    "sg:phone":"+32 11 73 30 48",
    "sg:postcode":"3941",
    "sg:province":"Limburg",
    "wof:name":"Spooren M.",
    "wof:placetype":"venue"
},
  "geometry": {"coordinates":[5.3919901848,51.1546516418],"type":"Point"}
}