{
  "type": "Feature",
  "properties": {
    "iso:country":"BE",
    "sg:address":"Ruiseledesteenweg 76",
    "sg:city":"Wingene",
    "sg:orig_category":"Eleveurs and marchands de porcs",
    "sg:phone":"+32 51 65 68 89",
    "sg:postcode":"8750",
    "sg:province":"West-Vlaanderen",
    "wof:name":"Marnix D'hoore",
    "wof:placetype":"venue"
},
  "geometry": {"coordinates":[3.322384119,51.0555648804],"type":"Point"}
}