{
  "type": "Feature",
  "properties": {
    "addr:full":"Ambachtenlaan 32 Heverlee Vlaams-Brabant 3001",
    "addr:housenumber":"32",
    "addr:postcode":"3001",
    "addr:street":"Ambachtenlaan",
    "iso:country":"BE",
    "sg:address":"Ambachtenlaan 32",
    "sg:city":"Heverlee",
    "sg:classifiers":[
        {
            "category":"Banks & Credit Unions",
            "subcategory":"Investment Brokerage",
            "type":"Services"
        }
    ],
    "sg:phone":"+32 16 40 02 21",
    "sg:postcode":"3001",
    "sg:province":"Vlaams-Brabant",
    "sg:tags":[
        "equipment",
        "accessory",
        "swimming-pool"
    ],
    "wof:name":"Duktrad Marketing B.v.b.a.",
    "wof:placetype":"venue"
},
  "geometry": {"coordinates":[4.715900898,50.8485488892],"type":"Point"}
}