{
  "type": "Feature",
  "properties": {
    "iso:country":"BE",
    "sg:address":"Posterijlaan 3",
    "sg:city":"Pittem",
    "sg:classifiers":[
        {
            "category":"Structure",
            "subcategory":"Building",
            "type":"Public Place"
        }
    ],
    "sg:phone":"+32 51 46 41 30",
    "sg:postcode":"8740",
    "sg:province":"West-Vlaanderen",
    "sg:tags":[
        "door"
    ],
    "wof:name":"A-design",
    "wof:placetype":"venue"
},
  "geometry": {"coordinates":[3.2567110062,50.9915046692],"type":"Point"}
}