{
  "type": "Feature",
  "properties": {
    "iso:country":"BE",
    "sg:address":"Steenovenstraat 14b",
    "sg:city":"Hechtel-eksel (eksel)",
    "sg:classifiers":[
        {
            "category":"Home & Garden",
            "subcategory":"Kitchen Supply",
            "type":"Retail Goods"
        }
    ],
    "sg:phone":"+32 11 73 49 66",
    "sg:postcode":"3941",
    "sg:province":"Limburg",
    "sg:tags":[
        "installation"
    ],
    "wof:name":"Vanderhoydonks Marc Bvba",
    "wof:placetype":"venue"
},
  "geometry": {"coordinates":[5.3824920654,51.1497039795],"type":"Point"}
}