{
  "type": "Feature",
  "properties": {
    "iso:country":"BE",
    "sg:address":"Rue Du Quai 4",
    "sg:city":"Namur",
    "sg:classifiers":[
        {
            "category":"Retail",
            "subcategory":"Auto Repair",
            "type":"Services"
        }
    ],
    "sg:phone":"+32 81 22 11 20",
    "sg:postcode":"5000",
    "sg:province":"Namur",
    "sg:tags":[
        "garage"
    ],
    "wof:name":"Havelange",
    "wof:placetype":"venue"
},
  "geometry": {"coordinates":[4.8790102005,50.4655265808],"type":"Point"}
}