{
  "type": "Feature",
  "properties": {
    "addr:full":"Kerkveldweg 54 Grimbergen (humbeek) Vlaams-Brabant 1851",
    "addr:housenumber":"54",
    "addr:postcode":"1851",
    "addr:street":"Kerkveldweg",
    "iso:country":"BE",
    "sg:address":"Kerkveldweg 54",
    "sg:city":"Grimbergen (humbeek)",
    "sg:classifiers":[
        {
            "category":"Freight",
            "type":"Transportation"
        }
    ],
    "sg:phone":"+32 2 269 04 42",
    "sg:postcode":"1851",
    "sg:province":"Vlaams-Brabant",
    "sg:tags":[
        "-",
        "transport"
    ],
    "wof:name":"Rydams R",
    "wof:placetype":"venue"
},
  "geometry": {"coordinates":[4.384750843,50.9692993164],"type":"Point"}
}