{
  "type": "Feature",
  "properties": {
    "iso:country":"BE",
    "sg:address":"Caudenberg 4",
    "sg:city":"Lierde (sint-maria-lierde)",
    "sg:classifiers":[
        {
            "category":"Building & Trades",
            "subcategory":"Landscaping Services",
            "type":"Services"
        }
    ],
    "sg:postcode":"9570",
    "sg:province":"Oost-Vlaanderen",
    "sg:tags":[
        "gardening",
        "garden",
        "maintenance"
    ],
    "wof:name":"Holderbeke Tuinen",
    "wof:placetype":"venue"
},
  "geometry": {"coordinates":[3.8252260685,50.8181381226],"type":"Point"}
}