{
  "type": "Feature",
  "properties": {
    "iso:country":"BE",
    "sg:address":"Jan Rosierlaan 98",
    "sg:city":"Lanaken",
    "sg:orig_category":"Entretien and r\u00e9parations de voitures",
    "sg:phone":"+32 89 72 23 16",
    "sg:postcode":"3620",
    "sg:province":"Limburg",
    "wof:name":"Francisco Nunez",
    "wof:placetype":"venue"
},
  "geometry": {"coordinates":[5.6565790176,50.8878326416],"type":"Point"}
}