{
  "type": "Feature",
  "properties": {
    "iso:country":"BE",
    "sg:address":"Hoogveldstraat 55",
    "sg:city":"Genk",
    "sg:orig_category":"Boekhouders",
    "sg:phone":"+32 89 35 26 61",
    "sg:postcode":"3600",
    "sg:province":"Limburg",
    "wof:name":"Marie Ramaekers",
    "wof:placetype":"venue"
},
  "geometry": {"coordinates":[5.5441279411,50.9677658081],"type":"Point"}
}