{
  "type": "Feature",
  "properties": {
    "iso:country":"BE",
    "sg:address":"Rue Neuve 8",
    "sg:city":"Chatelet",
    "sg:classifiers":[
        {
            "category":"Restaurant",
            "type":"Food & Drink"
        }
    ],
    "sg:phone":"+32 71 40 49 74",
    "sg:postcode":"6200",
    "sg:province":"Hainaut",
    "wof:name":"Casa Del Gelato",
    "wof:placetype":"venue"
},
  "geometry": {"coordinates":[4.5221500397,50.4054222107],"type":"Point"}
}