{
  "type": "Feature",
  "properties": {
    "addr:full":"Stationstraat 13 Ardooie West-Vlaanderen 8850",
    "addr:housenumber":"13",
    "addr:postcode":"8850",
    "addr:street":"Stationstraat",
    "iso:country":"BE",
    "sg:address":"Stationstraat 13",
    "sg:city":"Ardooie",
    "sg:orig_category":"Evaluation and estimation de biens immobiliers",
    "sg:phone":"+32 51 74 41 32",
    "sg:postcode":"8850",
    "sg:province":"West-Vlaanderen",
    "wof:name":"Luc Hoornaert",
    "wof:placetype":"venue"
},
  "geometry": {"coordinates":[3.2037050724,50.9893112183],"type":"Point"}
}