{
  "type": "Feature",
  "properties": {
    "addr:full":"Lage Kaart 39 Brasschaat Antwerpen 2930",
    "addr:housenumber":"39",
    "addr:postcode":"2930",
    "addr:street":"Lage Kaart",
    "iso:country":"BE",
    "sg:address":"Lage Kaart 39",
    "sg:city":"Brasschaat",
    "sg:classifiers":[
        {
            "category":"Professional",
            "subcategory":"Management & Consulting",
            "type":"Services"
        }
    ],
    "sg:phone":"+32 3 653 58 50",
    "sg:postcode":"2930",
    "sg:province":"Antwerpen",
    "sg:tags":[
        "consultant"
    ],
    "wof:name":"Advelgo Bvba",
    "wof:placetype":"venue"
},
  "geometry": {"coordinates":[4.4582262039,51.2941093445],"type":"Point"}
}