{
  "type": "Feature",
  "properties": {
    "iso:country":"BE",
    "sg:address":"Quai Du Rempart 20",
    "sg:city":"Bouillon",
    "sg:classifiers":[
        {
            "category":"Retail",
            "subcategory":"Laundry & Dry Cleaning",
            "type":"Services"
        }
    ],
    "sg:phone":"+32 61 51 34 76",
    "sg:postcode":"6830",
    "sg:province":"Luxembourg",
    "sg:tags":[
        "self",
        "-"
    ],
    "wof:name":"Nettex",
    "wof:placetype":"venue"
},
  "geometry": {"coordinates":[5.0666642189,49.7928009033],"type":"Point"}
}