{
  "type": "Feature",
  "properties": {
    "addr:full":"Rue Ed. Malherbe 27 Flemalle Li\u00e8ge 4400",
    "addr:housenumber":"27",
    "addr:postcode":"4400",
    "addr:street":"Rue Ed. Malherbe",
    "iso:country":"BE",
    "sg:address":"Rue Ed. Malherbe 27",
    "sg:city":"Flemalle",
    "sg:orig_category":"Installation de menuiserie en bois and plastique",
    "sg:phone":"+32 4 250 40 38",
    "sg:postcode":"4400",
    "sg:province":"Li\u00e8ge",
    "wof:name":"Protain",
    "wof:placetype":"venue"
},
  "geometry": {"coordinates":[5.4576430321,50.5693130493],"type":"Point"}
}