{
  "type": "Feature",
  "properties": {
    "addr:full":"Waterstraat 69 Schilde Antwerpen 2970",
    "addr:housenumber":"69",
    "addr:postcode":"2970",
    "addr:street":"Waterstraat",
    "iso:country":"BE",
    "sg:address":"Waterstraat 69",
    "sg:city":"Schilde",
    "sg:orig_category":"Artiesten and kunstenaars",
    "sg:phone":"+32 3 383 44 80",
    "sg:postcode":"2970",
    "sg:province":"Antwerpen",
    "wof:name":"F. Van Dijk",
    "wof:placetype":"venue"
},
  "geometry": {"coordinates":[4.6108732224,51.2589149475],"type":"Point"}
}