{
  "type": "Feature",
  "properties": {
    "addr:full":"Rue De L'anglais 30 Mons Hainaut 7012",
    "addr:housenumber":"30",
    "addr:postcode":"7012",
    "addr:street":"Rue De L'Anglais;Hainaut",
    "iso:country":"BE",
    "sg:address":"Rue De L'anglais 30",
    "sg:city":"Mons",
    "sg:orig_category":"Rev\u00eatements pour sols and murs",
    "sg:phone":"+32 65 82 22 23",
    "sg:postcode":"7012",
    "sg:province":"Hainaut",
    "wof:name":"Guiseppe Nei",
    "wof:placetype":"venue"
},
  "geometry": {"coordinates":[3.8857369423,50.4309997559],"type":"Point"}
}