{
  "type": "Feature",
  "properties": {
    "addr:full":"L Lambrechtsstr 5 Hoeselt Limburg 3730",
    "addr:housenumber":"5",
    "addr:postcode":"3730",
    "iso:country":"BE",
    "sg:address":"L Lambrechtsstr 5",
    "sg:city":"Hoeselt",
    "sg:classifiers":[
        {
            "category":"Banks & Credit Unions",
            "subcategory":"Bank",
            "type":"Services"
        }
    ],
    "sg:phone":"+32 11 41 15 89",
    "sg:postcode":"3730",
    "sg:province":"Limburg",
    "wof:name":"Aslk-cger Bank",
    "wof:placetype":"venue"
},
  "geometry": {"coordinates":[5.4893660545,50.8497657776],"type":"Point"}
}