{
  "type": "Feature",
  "properties": {
    "addr:full":"Lavaselle 8 Vaux-sur-sure Luxembourg 6640",
    "addr:housenumber":"8",
    "addr:postcode":"6640",
    "addr:street":"Lavaselle",
    "iso:country":"BE",
    "sg:address":"Lavaselle 8",
    "sg:city":"Vaux-sur-sure",
    "sg:orig_category":"Jardinage",
    "sg:phone":"+32 61 26 63 20",
    "sg:postcode":"6640",
    "sg:province":"Luxembourg",
    "wof:name":"Jardins Du Laval",
    "wof:placetype":"venue"
},
  "geometry": {"coordinates":[5.5671000481,49.91065979],"type":"Point"}
}