{
  "type": "Feature",
  "properties": {
    "addr:full":"Rue Jules Cornet 6 Box 2 La Louvi\u00e8re Hainaut 7100",
    "addr:housenumber":"6;2",
    "addr:postcode":"7100",
    "addr:street":"Rue Jules Cornet;Box",
    "iso:country":"BE",
    "sg:address":"Rue Jules Cornet 6 Box 2",
    "sg:city":"La Louvi\u00e8re",
    "sg:classifiers":[
        {
            "category":"Real Estate",
            "subcategory":"Architect",
            "type":"Services"
        }
    ],
    "sg:phone":"+32 64 22 43 03",
    "sg:postcode":"7100",
    "sg:province":"Hainaut",
    "wof:name":"Fasbender B",
    "wof:placetype":"venue"
},
  "geometry": {"coordinates":[4.1821279526,50.4699745178],"type":"Point"}
}