{
  "type": "Feature",
  "properties": {
    "iso:country":"BE",
    "sg:address":"Mannekenshaagstraat 35",
    "sg:city":"Halen",
    "sg:orig_category":"Eleveurs and marchands de porcs",
    "sg:phone":"+32 13 44 25 36",
    "sg:postcode":"3545",
    "sg:province":"Limburg",
    "wof:name":"Marcel Demeer",
    "wof:placetype":"venue"
},
  "geometry": {"coordinates":[5.0825958252,50.9323234558],"type":"Point"}
}