{
  "type": "Feature",
  "properties": {
    "addr:full":"Grote Steenweg 284 Linter Vlaams-Brabant 3350",
    "addr:housenumber":"284",
    "addr:postcode":"3350",
    "addr:street":"Grote Steenweg;Vlaams-Brabant",
    "iso:country":"BE",
    "sg:address":"Grote Steenweg 284",
    "sg:city":"Linter",
    "sg:classifiers":[
        {
            "category":"Health Services",
            "subcategory":"Nursing And Care Facility",
            "type":"Services"
        }
    ],
    "sg:phone":"+32 11 78 23 80",
    "sg:postcode":"3350",
    "sg:province":"Vlaams-Brabant",
    "sg:tags":[
        "public"
    ],
    "wof:name":"O.c.m.w.",
    "wof:placetype":"venue"
},
  "geometry": {"coordinates":[5.0481529236,50.8450012207],"type":"Point"}
}