{
  "type": "Feature",
  "properties": {
    "addr:full":"Mechelsesteenweg 460 Zaventem Vlaams-Brabant 1930",
    "addr:housenumber":"460",
    "addr:postcode":"1930",
    "addr:street":"Mechelsesteenweg",
    "iso:country":"BE",
    "sg:address":"Mechelsesteenweg 460",
    "sg:city":"Zaventem",
    "sg:orig_category":"Restaurants Ruimtes voor conferenties, recepties and feesten",
    "sg:phone":"+32 2 757 91 57",
    "sg:postcode":"1930",
    "sg:province":"Vlaams-Brabant",
    "wof:name":"Weyveld",
    "wof:placetype":"venue"
},
  "geometry": {"coordinates":[4.507589817,50.877948761],"type":"Point"}
}