{
  "type": "Feature",
  "properties": {
    "iso:country":"BE",
    "sg:address":"Rue Du Pourcelet 52",
    "sg:city":"Mons",
    "sg:classifiers":[
        {
            "category":"Food & Beverages",
            "subcategory":"Fruits & Vegetables",
            "type":"Retail Goods"
        }
    ],
    "sg:phone":"+32 65 34 90 56",
    "sg:postcode":"7000",
    "sg:province":"Hainaut",
    "sg:tags":[
        "-"
    ],
    "wof:name":"Gallo S",
    "wof:placetype":"venue"
},
  "geometry": {"coordinates":[3.9592208862,50.4669952393],"type":"Point"}
}