{
  "type": "Feature",
  "properties": {
    "addr:full":"Solleveldstraat 20 Sint-lambrechts-woluwe/woluwe-saint-lambert Bruxelles-Capitale 1200",
    "addr:housenumber":"20",
    "addr:postcode":"1200",
    "addr:street":"Solleveldstraat",
    "iso:country":"BE",
    "sg:address":"Solleveldstraat 20",
    "sg:city":"Sint-lambrechts-woluwe/woluwe-saint-lambert",
    "sg:orig_category":"Medische apparatuur, orthopedische artikelen and prothesen Fab",
    "sg:phone":"+32 2 770 33 18",
    "sg:postcode":"1200",
    "sg:province":"Bruxelles-Capitale",
    "wof:name":"Up 2 D",
    "wof:placetype":"venue"
},
  "geometry": {"coordinates":[4.4294462204,50.8452339172],"type":"Point"}
}