{
  "type": "Feature",
  "properties": {
    "addr:full":"Place Des Tilleuls 28 Andenne Namur 5300",
    "addr:housenumber":"28",
    "addr:postcode":"5300",
    "addr:street":"Place Des Tilleuls",
    "iso:country":"BE",
    "sg:address":"Place Des Tilleuls 28",
    "sg:city":"Andenne",
    "sg:classifiers":[
        {
            "category":"Health Services",
            "subcategory":"Health Practitioner",
            "type":"Services"
        }
    ],
    "sg:phone":"+32 475 76 40 25",
    "sg:postcode":"5300",
    "sg:province":"Namur",
    "sg:tags":[
        "physiotherapist"
    ],
    "wof:name":"Bovenisty Olivier",
    "wof:placetype":"venue"
},
  "geometry": {"coordinates":[5.0953640938,50.4890899658],"type":"Point"}
}