{
  "type": "Feature",
  "properties": {
    "addr:full":"Rue Anti\u00c9mont 13 Marche-en-famenne Luxembourg 6900",
    "addr:housenumber":"13",
    "addr:postcode":"6900",
    "addr:street":"Rue Antie\u0301Mont",
    "iso:country":"BE",
    "sg:address":"Rue Anti\u00c9mont 13",
    "sg:city":"Marche-en-famenne",
    "sg:orig_category":"Brood, gebak and snoepgoed",
    "sg:phone":"+32 84 21 09 88",
    "sg:postcode":"6900",
    "sg:province":"Luxembourg",
    "wof:name":"Victor Delchambre",
    "wof:placetype":"venue"
},
  "geometry": {"coordinates":[5.28937006,50.1738815308],"type":"Point"}
}