{
  "type": "Feature",
  "properties": {
    "addr:full":"Quai D'arona Huy Li\u00e8ge 4500",
    "addr:postcode":"4500",
    "addr:street":"Quai D'Arona",
    "iso:country":"BE",
    "sg:address":"Quai D'arona",
    "sg:city":"Huy",
    "sg:classifiers":[
        {
            "category":"Fast Food",
            "type":"Food & Drink"
        }
    ],
    "sg:phone":"+32 85 21 65 40",
    "sg:postcode":"4500",
    "sg:province":"Li\u00e8ge",
    "sg:tags":[
        "\u00c0",
        "emporter",
        "restaurants"
    ],
    "wof:name":"Friterie Le Chalet",
    "wof:placetype":"venue"
},
  "geometry": {"coordinates":[5.2598991394,50.5348777771],"type":"Point"}
}