{
  "type": "Feature",
  "properties": {
    "addr:full":"Rue De La Madeleine 84 Tournai Hainaut 7500",
    "addr:housenumber":"84",
    "addr:postcode":"7500",
    "addr:street":"Rue De La Madeleine",
    "iso:country":"BE",
    "sg:address":"Rue De La Madeleine 84",
    "sg:city":"Tournai",
    "sg:classifiers":[
        {
            "category":"Professional",
            "subcategory":"Accounting & Tax Preparation",
            "type":"Services"
        }
    ],
    "sg:phone":"+32 69 22 64 95",
    "sg:postcode":"7500",
    "sg:province":"Hainaut",
    "sg:tags":[
        "accountant"
    ],
    "wof:name":"Genart J-c",
    "wof:placetype":"venue"
},
  "geometry": {"coordinates":[3.3813300133,50.6112289429],"type":"Point"}
}