{
  "type": "Feature",
  "properties": {
    "addr:full":"Meir 109 Antwerpen Antwerpen 2000",
    "addr:housenumber":"109",
    "addr:postcode":"2000",
    "addr:street":"Meir",
    "iso:country":"BE",
    "sg:address":"Meir 109",
    "sg:city":"Antwerpen",
    "sg:classifiers":[
        {
            "category":"Shopping",
            "subcategory":"Clothing, Apparel, & Fashions",
            "type":"Retail Goods"
        }
    ],
    "sg:phone":"+32 3 232 37 58",
    "sg:postcode":"2000",
    "sg:province":"Antwerpen",
    "sg:tags":[
        "underwear",
        "lingerie",
        "-"
    ],
    "wof:name":"Beldona",
    "wof:placetype":"venue"
},
  "geometry": {"coordinates":[4.411605835,51.2182388306],"type":"Point"}
}