{
  "type": "Feature",
  "properties": {
    "addr:full":"Schoolstraat 65 Geraardsbergen (goeferdinge) Oost-Vlaanderen 9500",
    "addr:housenumber":"65",
    "addr:postcode":"9500",
    "addr:street":"Schoolstraat",
    "iso:country":"BE",
    "sg:address":"Schoolstraat 65",
    "sg:city":"Geraardsbergen (goeferdinge)",
    "sg:classifiers":[
        {
            "category":"Retail",
            "subcategory":"Animal Services",
            "type":"Services"
        }
    ],
    "sg:phone":"+32 54 42 19 61",
    "sg:postcode":"9500",
    "sg:province":"Oost-Vlaanderen",
    "sg:tags":[
        "breeding",
        "selling",
        "-",
        "dog"
    ],
    "wof:name":"Dobermann Des Fridons D'ebene",
    "wof:placetype":"venue"
},
  "geometry": {"coordinates":[3.8481969833,50.7680130005],"type":"Point"}
}