{
  "type": "Feature",
  "properties": {
    "iso:country":"BE",
    "sg:address":"Avenue Van Goidtsenoven 56",
    "sg:city":"Ukkel/uccle",
    "sg:orig_category":"Baby- and kinderkleding Babyspullen",
    "sg:phone":"+32 2 345 21 84",
    "sg:postcode":"1180",
    "sg:province":"Bruxelles-Capitale",
    "wof:name":"Babydream",
    "wof:placetype":"venue"
},
  "geometry": {"coordinates":[4.3382000923,50.814491272],"type":"Point"}
}