{
  "type": "Feature",
  "properties": {
    "addr:full":"Avenue De Flor\u00c9al 77 Ukkel/uccle Bruxelles-Capitale 1180",
    "addr:housenumber":"77",
    "addr:postcode":"1180",
    "addr:street":"Avenue De Flore\u0301Al;/",
    "iso:country":"BE",
    "sg:address":"Avenue De Flor\u00c9al 77",
    "sg:city":"Ukkel/uccle",
    "sg:orig_category":"Traitements param\u00e9dicaux. Instituts de beaut\u00e9",
    "sg:phone":"+32 2 343 79 49",
    "sg:postcode":"1180",
    "sg:province":"Bruxelles-Capitale",
    "wof:name":"Vermeersch",
    "wof:placetype":"venue"
},
  "geometry": {"coordinates":[4.3442831039,50.8089828491],"type":"Point"}
}