{
  "type": "Feature",
  "properties": {
    "addr:full":"Brichautstraat 15 Schaarbeek/schaerbeek Bruxelles-Capitale 1030",
    "addr:housenumber":"15",
    "addr:postcode":"1030",
    "addr:street":"Brichautstraat",
    "iso:country":"BE",
    "sg:address":"Brichautstraat 15",
    "sg:city":"Schaarbeek/schaerbeek",
    "sg:orig_category":"Herstellingen and onderhoud van auto's",
    "sg:phone":"+32 2 243 04 29",
    "sg:postcode":"1030",
    "sg:province":"Bruxelles-Capitale",
    "wof:name":"Auto C.m.",
    "wof:placetype":"venue"
},
  "geometry": {"coordinates":[4.3678469658,50.8635406494],"type":"Point"}
}