{
  "type": "Feature",
  "properties": {
    "addr:full":"10 Nijvelsesteenweg 1500 Halle 10",
    "addr:housenumber":"10;1500;10",
    "addr:street":"Nijvelsesteenweg;Halle",
    "iso:country":"BE",
    "sg:address":"10",
    "sg:city":"Nijvelsesteenweg 1500 Halle",
    "sg:classifiers":[
        {
            "category":"Bakery",
            "type":"Food & Drink"
        }
    ],
    "sg:phone":"+32 2 356 68 92",
    "sg:postcode":"10",
    "sg:tags":[
        "cake",
        "product",
        "related",
        "bread"
    ],
    "wof:name":"Bakkerij Terrijn Bvba",
    "wof:placetype":"venue"
},
  "geometry": {"coordinates":[4.2475118637,50.72423172],"type":"Point"}
}