{
  "type": "Feature",
  "properties": {
    "iso:country":"BE",
    "sg:address":"Avenue Louis Bertrand 65",
    "sg:city":"Brussel/bruxelles",
    "sg:classifiers":[
        {
            "category":"Bars & Pubs",
            "subcategory":"Sports Bar",
            "type":"Food & Drink"
        }
    ],
    "sg:phone":"+32 2 242 42 30",
    "sg:postcode":"1030",
    "sg:province":"Bruxelles-Capitale",
    "sg:tags":[
        "bars",
        "restaurant"
    ],
    "wof:name":"La Buca Di Bacco",
    "wof:placetype":"venue"
},
  "geometry": {"coordinates":[4.3766641617,50.8633728027],"type":"Point"}
}