{
  "type": "Feature",
  "properties": {
    "addr:full":"Avenue G\u00e9n\u00e9ral Michel 1 Charleroi Hainaut 6000",
    "addr:housenumber":"1",
    "addr:postcode":"6000",
    "addr:street":"Avenue Ge\u0301Ne\u0301Ral Michel;Hainaut",
    "iso:country":"BE",
    "sg:address":"Avenue G\u00e9n\u00e9ral Michel 1",
    "sg:city":"Charleroi",
    "sg:classifiers":[
        {
            "category":"Museum",
            "type":"Entertainment"
        }
    ],
    "sg:phone":"+32 71 30 07 48",
    "sg:postcode":"6000",
    "sg:province":"Hainaut",
    "wof:name":"Mus\u00e9e Des Chasseurs \u00e0 Pied",
    "wof:placetype":"venue"
},
  "geometry": {"coordinates":[4.4504227638,50.4104766846],"type":"Point"}
}