{
  "type": "Feature",
  "properties": {
    "iso:country":"BE",
    "sg:address":"Hoogstraat 314",
    "sg:city":"As",
    "sg:classifiers":[
        {
            "category":"Real Estate",
            "subcategory":"Architect",
            "type":"Services"
        }
    ],
    "sg:phone":"+32 89 65 78 97",
    "sg:postcode":"3665",
    "sg:province":"Limburg",
    "wof:name":"Heyens J",
    "wof:placetype":"venue"
},
  "geometry": {"coordinates":[5.593334198,51.0103492737],"type":"Point"}
}