{
  "type": "Feature",
  "properties": {
    "iso:country":"BE",
    "sg:address":"Rue De La Commone 70",
    "sg:city":"Chaumont-gistoux (dion-valmont)",
    "sg:classifiers":[
        {
            "category":"Retail",
            "subcategory":"Driving School",
            "type":"Services"
        }
    ],
    "sg:phone":"+32 10 68 15 16",
    "sg:postcode":"1325",
    "sg:province":"Brabant Wallon",
    "sg:tags":[
        "proficiency",
        "automobile",
        "-"
    ],
    "wof:name":"Duquesnoy M",
    "wof:placetype":"venue"
},
  "geometry": {"coordinates":[4.6711001396,50.6908912659],"type":"Point"}
}