{
  "type": "Feature",
  "properties": {
    "iso:country":"BE",
    "sg:address":"Donk 31",
    "sg:city":"Oud-turnhout",
    "sg:classifiers":[
        {
            "category":"Government",
            "subcategory":"Fire Station",
            "type":"Public Place"
        }
    ],
    "sg:phone":"+32 14 45 00 62",
    "sg:postcode":"2360",
    "sg:province":"Antwerpen",
    "sg:tags":[
        "installation",
        "-",
        "air conditioning"
    ],
    "wof:name":"Remijsen Koel- & Electrotechnieken",
    "wof:placetype":"venue"
},
  "geometry": {"coordinates":[5.0247950554,51.2994041443],"type":"Point"}
}