{
  "type": "Feature",
  "properties": {
    "addr:full":"Boulevard Du Souverain 30-32 Bruxelles Bruxelles-Capitale 1170",
    "addr:postcode":"30-32;1170",
    "addr:street":"Boulevard Du Souverain",
    "iso:country":"BE",
    "sg:address":"Boulevard Du Souverain 30-32",
    "sg:city":"Bruxelles",
    "sg:classifiers":[
        {
            "category":"Professional",
            "subcategory":"Computer Services",
            "type":"Services"
        }
    ],
    "sg:phone":"+32 2 223 64 70",
    "sg:postcode":"1170",
    "sg:province":"Bruxelles-Capitale",
    "sg:tags":[
        "antistatic",
        "treatment",
        "system",
        "cleaning"
    ],
    "wof:name":"Computer Cleaning & Maintenance S.p.r.l.",
    "wof:placetype":"venue"
},
  "geometry": {"coordinates":[4.4231748581,50.802116394],"type":"Point"}
}