{
  "type": "Feature",
  "properties": {
    "addr:full":"Volpenswege 19 Evergem Oost-Vlaanderen 9940",
    "addr:housenumber":"19",
    "addr:postcode":"9940",
    "addr:street":"Volpenswege;Oost-Vlaanderen",
    "iso:country":"BE",
    "sg:address":"Volpenswege 19",
    "sg:city":"Evergem",
    "sg:orig_category":"Eleveurs de bovins. Eleveurs and marchands de porcs",
    "sg:phone":"+32 9 357 75 26",
    "sg:postcode":"9940",
    "sg:province":"Oost-Vlaanderen",
    "wof:name":"Philip Vereecke",
    "wof:placetype":"venue"
},
  "geometry": {"coordinates":[3.6946489811,51.147518158],"type":"Point"}
}