{
  "type": "Feature",
  "properties": {
    "addr:full":"Meertsveldstraat 7bb Duffel Antwerpen 2570",
    "addr:housenumber":"7bb",
    "addr:postcode":"2570",
    "addr:street":"Meertsveldstraat",
    "iso:country":"BE",
    "sg:address":"Meertsveldstraat 7bb",
    "sg:city":"Duffel",
    "sg:orig_category":"Enseignement maternel and primaire",
    "sg:phone":"+32 15 31 28 82",
    "sg:postcode":"2570",
    "sg:province":"Antwerpen",
    "wof:name":"Vrije Kleuterschool",
    "wof:placetype":"venue"
},
  "geometry": {"coordinates":[4.5068678856,51.1007194519],"type":"Point"}
}