{
  "type": "Feature",
  "properties": {
    "iso:country":"BE",
    "sg:address":"Sint-lenaartseweg 190",
    "sg:city":"Wuustwezel",
    "sg:orig_category":"Rundveehouders",
    "sg:phone":"+32 3 313 81 61",
    "sg:postcode":"2990",
    "sg:province":"Antwerpen",
    "wof:name":"Jan Aertsen",
    "wof:placetype":"venue"
},
  "geometry": {"coordinates":[4.6743488312,51.3809204102],"type":"Point"}
}