{
  "type": "Feature",
  "properties": {
    "iso:country":"BE",
    "sg:address":"Boulevard Gendebien 7",
    "sg:city":"Mons",
    "sg:classifiers":[
        {
            "category":"Social Services",
            "type":"Services"
        }
    ],
    "sg:phone":"+32 65 31 19 42",
    "sg:postcode":"7000",
    "sg:province":"Hainaut",
    "wof:name":"Fondation De Bourses D'etude Du Hainaut",
    "wof:placetype":"venue"
},
  "geometry": {"coordinates":[3.9422380924,50.4523468018],"type":"Point"}
}