{
  "type": "Feature",
  "properties": {
    "addr:full":"Mechelsesteenweg 126 Kontich Antwerpen 2550",
    "addr:housenumber":"126",
    "addr:postcode":"2550",
    "addr:street":"Mechelsesteenweg",
    "iso:country":"BE",
    "sg:address":"Mechelsesteenweg 126",
    "sg:city":"Kontich",
    "sg:orig_category":"Brood, gebak and snoepgoed",
    "sg:phone":"+32 3 458 33 62",
    "sg:postcode":"2550",
    "sg:province":"Antwerpen",
    "wof:name":"Huis Nina",
    "wof:placetype":"venue"
},
  "geometry": {"coordinates":[4.4582400322,51.1428222656],"type":"Point"}
}