{
  "type": "Feature",
  "properties": {
    "addr:full":"Nimfenstraat 12 Mechelen Antwerpen 2800",
    "addr:housenumber":"12",
    "addr:postcode":"2800",
    "addr:street":"Nimfenstraat",
    "iso:country":"BE",
    "sg:address":"Nimfenstraat 12",
    "sg:city":"Mechelen",
    "sg:classifiers":[
        {
            "category":"Communications",
            "subcategory":"News Services",
            "type":"Services"
        }
    ],
    "sg:phone":"+32 15 33 75 07",
    "sg:postcode":"2800",
    "sg:province":"Antwerpen",
    "sg:tags":[
        "illustrator"
    ],
    "wof:name":"Op De Beeck Karikaturen",
    "wof:placetype":"venue"
},
  "geometry": {"coordinates":[4.4835000038,51.0450782776],"type":"Point"}
}