{
  "type": "Feature",
  "properties": {
    "iso:country":"BE",
    "sg:address":"Isabellalei 69",
    "sg:city":"Antwerpen",
    "sg:orig_category":"Biblioth\u00e8ques and archives publiques",
    "sg:phone":"+32 3 218 43 55",
    "sg:postcode":"2018",
    "sg:province":"Antwerpen",
    "wof:name":"Stedelijke Openbare Bibliotheek",
    "wof:placetype":"venue"
},
  "geometry": {"coordinates":[4.4173989296,51.2044792175],"type":"Point"}
}