{
  "type": "Feature",
  "properties": {
    "addr:full":"Lintsesteenweg 203 Hove Antwerpen 2540",
    "addr:housenumber":"203",
    "addr:postcode":"2540",
    "addr:street":"Lintsesteenweg",
    "iso:country":"BE",
    "sg:address":"Lintsesteenweg 203",
    "sg:city":"Hove",
    "sg:classifiers":[
        {
            "category":"Building & Trades",
            "subcategory":"Plumbing",
            "type":"Services"
        }
    ],
    "sg:phone":"+32 3 455 71 33",
    "sg:postcode":"2540",
    "sg:province":"Antwerpen",
    "sg:tags":[
        "repair",
        "mainten",
        "-",
        "central",
        "heating"
    ],
    "wof:name":"Saniver Bvba",
    "wof:placetype":"venue"
},
  "geometry": {"coordinates":[4.4837698936,51.1492080688],"type":"Point"}
}