{
  "type": "Feature",
  "properties": {
    "addr:full":"Tolstraat 11 Antwerpen Antwerpen 2000",
    "addr:housenumber":"11",
    "addr:postcode":"2000",
    "addr:street":"Tolstraat",
    "iso:country":"BE",
    "sg:address":"Tolstraat 11",
    "sg:city":"Antwerpen",
    "sg:orig_category":"Notaires",
    "sg:phone":"+32 3 238 27 90",
    "sg:postcode":"2000",
    "sg:province":"Antwerpen",
    "wof:name":"J. Cleen",
    "wof:placetype":"venue"
},
  "geometry": {"coordinates":[4.3983659744,51.2102241516],"type":"Point"}
}