{
  "type": "Feature",
  "properties": {
    "iso:country":"BE",
    "sg:address":"Grand'rue 271a",
    "sg:city":"Charleroi",
    "sg:classifiers":[
        {
            "category":"Bars & Pubs",
            "type":"Food & Drink"
        }
    ],
    "sg:phone":"+32 71 41 84 25",
    "sg:postcode":"6000",
    "sg:province":"Hainaut",
    "wof:name":"King (le)",
    "wof:placetype":"venue"
},
  "geometry": {"coordinates":[4.4527988434,50.4181480408],"type":"Point"}
}