{
  "type": "Feature",
  "properties": {
    "addr:full":"Van Eycklaan 97 Box 11 Maaseik Limburg 3680",
    "addr:housenumber":"97 box 11",
    "addr:postcode":"3680",
    "addr:street":"Van Eycklaan",
    "iso:country":"BE",
    "sg:address":"Van Eycklaan 97 Box 11",
    "sg:city":"Maaseik",
    "sg:classifiers":[
        {
            "category":"Professional",
            "subcategory":"Credit Reporting & Collection",
            "type":"Services"
        }
    ],
    "sg:phone":"+32 89 56 30 73",
    "sg:postcode":"3680",
    "sg:province":"Limburg",
    "sg:tags":[
        "bailiff"
    ],
    "wof:name":"Haeldermans L",
    "wof:placetype":"venue"
},
  "geometry": {"coordinates":[5.783698082,51.0987243652],"type":"Point"}
}