{
  "type": "Feature",
  "properties": {
    "iso:country":"BE",
    "sg:address":"Avenue Brugmann 563",
    "sg:city":"Ukkel/uccle",
    "sg:orig_category":"Salles de spectacles",
    "sg:phone":"+32 2 346 35 19",
    "sg:postcode":"1180",
    "sg:province":"Bruxelles-Capitale",
    "wof:name":"Galerie Echancrure",
    "wof:placetype":"venue"
},
  "geometry": {"coordinates":[4.3388900757,50.8014144897],"type":"Point"}
}