{
  "type": "Feature",
  "properties": {
    "addr:full":"Oude Baan 626 Maasmechelen Limburg 3630",
    "addr:housenumber":"626",
    "addr:postcode":"3630",
    "addr:street":"Oude Baan",
    "iso:country":"BE",
    "sg:address":"Oude Baan 626",
    "sg:city":"Maasmechelen",
    "sg:orig_category":"Elektrische installaties voor woningen",
    "sg:phone":"+32 89 77 29 27",
    "sg:postcode":"3630",
    "sg:province":"Limburg",
    "wof:name":"Eddy Bollen",
    "wof:placetype":"venue"
},
  "geometry": {"coordinates":[5.667014122,50.9493293762],"type":"Point"}
}