{
  "type": "Feature",
  "properties": {
    "iso:country":"BE",
    "sg:address":"Herenstraat 36",
    "sg:city":"Sint-gillis-waas",
    "sg:orig_category":"Cr\u00e8ches and garderies d'enfants",
    "sg:phone":"+32 3 707 09 85",
    "sg:postcode":"9170",
    "sg:province":"Oost-Vlaanderen",
    "wof:name":"\u00b4t Kapoentje",
    "wof:placetype":"venue"
},
  "geometry": {"coordinates":[4.1207089424,51.2231407166],"type":"Point"}
}