{
  "type": "Feature",
  "properties": {
    "addr:full":"Mutsaertplaats 13 Vilvoorde Vlaams-Brabant 1800",
    "addr:housenumber":"13",
    "addr:postcode":"1800",
    "addr:street":"Mutsaertplaats",
    "iso:country":"BE",
    "sg:address":"Mutsaertplaats 13",
    "sg:city":"Vilvoorde",
    "sg:orig_category":"Traitements param\u00e9dicaux",
    "sg:phone":"+32 2 267 47 63",
    "sg:postcode":"1800",
    "sg:province":"Vlaams-Brabant",
    "wof:name":"Nancy Andre",
    "wof:placetype":"venue"
},
  "geometry": {"coordinates":[4.360888958,50.9014701843],"type":"Point"}
}