{
  "type": "Feature",
  "properties": {
    "addr:full":"Rue De L\u00b4industrie 13 Durbuy Luxembourg 6940",
    "addr:housenumber":"13",
    "addr:postcode":"6940",
    "addr:street":"Rue De L\u00b4Industrie",
    "iso:country":"BE",
    "sg:address":"Rue De L\u00b4industrie 13",
    "sg:city":"Durbuy",
    "sg:orig_category":"Quincailleries. Mat\u00e9riaux de construction Bois Gr",
    "sg:phone":"+32 86 21 35 71",
    "sg:postcode":"6940",
    "sg:province":"Luxembourg",
    "wof:name":"Fe. Gedimat",
    "wof:placetype":"venue"
},
  "geometry": {"coordinates":[5.4543361664,50.3515777588],"type":"Point"}
}