{
  "type": "Feature",
  "properties": {
    "addr:full":"Opstalstraat 1 Anzegem (vichte) West-Vlaanderen 8570",
    "addr:housenumber":"1",
    "addr:postcode":"8570",
    "addr:street":"Opstalstraat",
    "iso:country":"BE",
    "sg:address":"Opstalstraat 1",
    "sg:city":"Anzegem (vichte)",
    "sg:classifiers":[
        {
            "category":"Health Services",
            "subcategory":"Doctor",
            "type":"Services"
        }
    ],
    "sg:phone":"+32 56 77 64 00",
    "sg:postcode":"8570",
    "sg:province":"West-Vlaanderen",
    "sg:tags":[
        "medicinephysicians",
        "surgeon"
    ],
    "wof:name":"Lanneau Marleen",
    "wof:placetype":"venue"
},
  "geometry": {"coordinates":[3.3956100941,50.838760376],"type":"Point"}
}