{
  "type": "Feature",
  "properties": {
    "iso:country":"BE",
    "sg:address":"Rue Anne De Molina 44",
    "sg:city":"Dison",
    "sg:orig_category":"Services Erotiques et d'Escorte",
    "sg:phone":"+32 87 31 69 05",
    "sg:postcode":"4821",
    "sg:province":"Li\u00e8ge",
    "wof:name":"Business Agency Production",
    "wof:placetype":"venue"
},
  "geometry": {"coordinates":[5.8633050919,50.5993843079],"type":"Point"}
}