{
  "type": "Feature",
  "properties": {
    "iso:country":"BE",
    "sg:address":"Battelsesteenweg 455ba",
    "sg:city":"Malines",
    "sg:orig_category":"Produits chimiques Gr",
    "sg:phone":"+32 15 28 09 64",
    "sg:postcode":"2800",
    "sg:province":"Antwerpen",
    "wof:name":"Van Camp Chemicals",
    "wof:placetype":"venue"
},
  "geometry": {"coordinates":[4.450094223,51.0380706787],"type":"Point"}
}