{
  "type": "Feature",
  "properties": {
    "iso:country":"BE",
    "sg:address":"Avenue Des Commandants Borl\u00c9e19a",
    "sg:city":"Jodoigne",
    "sg:orig_category":"Mat\u00e9riel de T\u00e9l\u00e9communication",
    "sg:phone":"+32 10 24 21 27",
    "sg:postcode":"1370",
    "sg:province":"Brabant Wallon",
    "wof:name":"Go Tech Jodoigne",
    "wof:placetype":"venue"
},
  "geometry": {"coordinates":[4.8735589981,50.7224006653],"type":"Point"}
}