{
  "type": "Feature",
  "properties": {
    "addr:full":". Liedekerke Vlaams-Brabant 1770",
    "addr:postcode":"1770",
    "addr:street":"Vlaams-Brabant",
    "iso:country":"BE",
    "sg:address":".",
    "sg:city":"Liedekerke",
    "sg:orig_category":"Apotheken",
    "sg:phone":"+32 900 10 500",
    "sg:postcode":"1770",
    "sg:province":"Vlaams-Brabant",
    "wof:name":"Apothekers Van Wacht",
    "wof:placetype":"venue"
},
  "geometry": {"coordinates":[4.0815901756,50.8708457947],"type":"Point"}
}