{
  "type": "Feature",
  "properties": {
    "addr:full":"Kraaidreef 54 Zulte Oost-Vlaanderen 9870",
    "addr:housenumber":"54",
    "addr:postcode":"9870",
    "addr:street":"Kraaidreef",
    "iso:country":"BE",
    "sg:address":"Kraaidreef 54",
    "sg:city":"Zulte",
    "sg:orig_category":"Quincailleries",
    "sg:phone":"+32 56 60 92 19",
    "sg:postcode":"9870",
    "sg:province":"Oost-Vlaanderen",
    "wof:name":"Ruwomat",
    "wof:placetype":"venue"
},
  "geometry": {"coordinates":[3.4361429214,50.9097671509],"type":"Point"}
}