{
  "type": "Feature",
  "properties": {
    "addr:full":"Meistraat 128 Dessel Antwerpen 2480",
    "addr:housenumber":"128",
    "addr:postcode":"2480",
    "addr:street":"Meistraat",
    "iso:country":"BE",
    "sg:address":"Meistraat 128",
    "sg:city":"Dessel",
    "sg:orig_category":"Artsen and specialisten",
    "sg:phone":"+32 14 37 78 86",
    "sg:postcode":"2480",
    "sg:province":"Antwerpen",
    "wof:name":"Micha\u00cbl Brecx",
    "wof:placetype":"venue"
},
  "geometry": {"coordinates":[5.1602301598,51.2412605286],"type":"Point"}
}