{
  "type": "Feature",
  "properties": {
    "addr:full":"Rue Laplace 40 Seraing Li\u00e8ge 4100",
    "addr:housenumber":"40",
    "addr:postcode":"4100",
    "addr:street":"Rue Laplace",
    "iso:country":"BE",
    "sg:address":"Rue Laplace 40",
    "sg:city":"Seraing",
    "sg:orig_category":"M\u00e9decins and sp\u00e9cialistes. Cliniques and h\u00f4pitaux",
    "sg:phone":"+32 4 338 98 00",
    "sg:postcode":"4100",
    "sg:province":"Li\u00e8ge",
    "wof:name":"Polyclinique",
    "wof:placetype":"venue"
},
  "geometry": {"coordinates":[5.493680954,50.580242157],"type":"Point"}
}