{
  "type": "Feature",
  "properties": {
    "addr:full":"Grote Markt 6 Mechelen Antwerpen 2800",
    "addr:housenumber":"6",
    "addr:postcode":"2800",
    "addr:street":"Grote Markt",
    "iso:country":"BE",
    "sg:address":"Grote Markt 6",
    "sg:city":"Mechelen",
    "sg:orig_category":"Banques and organismes de cr\u00e9dit",
    "sg:phone":"+32 15 21 88 51",
    "sg:postcode":"2800",
    "sg:province":"Antwerpen",
    "wof:name":"Artesia",
    "wof:placetype":"venue"
},
  "geometry": {"coordinates":[4.479891777,51.0283470154],"type":"Point"}
}