{
  "type": "Feature",
  "properties": {
    "addr:full":"Kortrijkseweg 132 Waregem West-Vlaanderen 8791",
    "addr:housenumber":"132",
    "addr:postcode":"8791",
    "iso:country":"BE",
    "sg:address":"Kortrijkseweg 132",
    "sg:city":"Waregem",
    "sg:orig_category":"Paramedische behandelingen",
    "sg:phone":"+32 56 70 00 11",
    "sg:postcode":"8791",
    "sg:province":"West-Vlaanderen",
    "wof:name":"C. Demeyer",
    "wof:placetype":"venue"
},
  "geometry": {"coordinates":[3.3402218819,50.8707771301],"type":"Point"}
}