{
  "type": "Feature",
  "properties": {
    "addr:full":"Vijverstraat 9 Langemark-poelkapelle West-Vlaanderen 8920",
    "addr:housenumber":"9",
    "addr:postcode":"8920",
    "addr:street":"Vijverstraat",
    "iso:country":"BE",
    "sg:address":"Vijverstraat 9",
    "sg:city":"Langemark-poelkapelle",
    "sg:orig_category":"Postkantoren Verzekeringsmakelaars and experts",
    "sg:phone":"+32 57 48 80 50",
    "sg:postcode":"8920",
    "sg:province":"West-Vlaanderen",
    "wof:name":"De Post",
    "wof:placetype":"venue"
},
  "geometry": {"coordinates":[2.919770956,50.9132423401],"type":"Point"}
}