{
  "type": "Feature",
  "properties": {
    "addr:full":"Stapstraat 1 Herk-de-stad Limburg 3540",
    "addr:housenumber":"1",
    "addr:postcode":"3540",
    "addr:street":"Stapstraat",
    "iso:country":"BE",
    "sg:address":"Stapstraat 1",
    "sg:city":"Herk-de-stad",
    "sg:orig_category":"Pharmaciens",
    "sg:phone":"+32 13 55 18 51",
    "sg:postcode":"3540",
    "sg:province":"Limburg",
    "wof:name":"Ernest Mees",
    "wof:placetype":"venue"
},
  "geometry": {"coordinates":[5.19379282,50.9537506104],"type":"Point"}
}