{
  "type": "Feature",
  "properties": {
    "iso:country":"BE",
    "sg:address":"Rue De L'echauffour\u00e9e 42",
    "sg:city":"Mouscron",
    "sg:classifiers":[
        {
            "category":"Professional",
            "type":"Services"
        }
    ],
    "sg:phone":"+32 56 39 25 11",
    "sg:postcode":"7700",
    "sg:province":"Hainaut",
    "sg:tags":[
        "transport",
        "road"
    ],
    "wof:name":"Agence En Douane Et Transports A Boulanger Sa",
    "wof:placetype":"venue"
},
  "geometry": {"coordinates":[3.1822490692,50.7528762817],"type":"Point"}
}