{
  "type": "Feature",
  "properties": {
    "iso:country":"BE",
    "sg:address":"Dobbelhoefweg 27",
    "sg:city":"Grobbendonk",
    "sg:orig_category":"D\u00e9corateurs d'int\u00e9rieur",
    "sg:phone":"+32 14 51 41 31",
    "sg:postcode":"2280",
    "sg:province":"Antwerpen",
    "wof:name":"Co\u00d6rdinatie & Ontwerp",
    "wof:placetype":"venue"
},
  "geometry": {"coordinates":[4.7250528336,51.1887168884],"type":"Point"}
}