{
  "type": "Feature",
  "properties": {
    "addr:full":"Rot 31 Holsbeek (nieuwrode) Vlaams-Brabant 3221",
    "addr:housenumber":"31",
    "addr:postcode":"3221",
    "addr:street":"Rot",
    "iso:country":"BE",
    "sg:address":"Rot 31",
    "sg:city":"Holsbeek (nieuwrode)",
    "sg:classifiers":[
        {
            "category":"Bars & Pubs",
            "type":"Food & Drink"
        }
    ],
    "sg:phone":"+32 16 56 42 63",
    "sg:postcode":"3221",
    "sg:province":"Vlaams-Brabant",
    "wof:name":"Hogerop",
    "wof:placetype":"venue"
},
  "geometry": {"coordinates":[4.8183288574,50.9551467896],"type":"Point"}
}