{
  "type": "Feature",
  "properties": {
    "iso:country":"BE",
    "sg:address":"Route Militaire 374",
    "sg:city":"Ans",
    "sg:orig_category":"Centres de fitness. Installations and terrains de sport hors centres sportifs",
    "sg:phone":"+32 4 247 41 41",
    "sg:postcode":"4432",
    "sg:province":"Li\u00e8ge",
    "wof:name":"L\u00b4espace Vital",
    "wof:placetype":"venue"
},
  "geometry": {"coordinates":[5.5115470886,50.6803703308],"type":"Point"}
}