{
  "type": "Feature",
  "properties": {
    "iso:country":"BE",
    "sg:address":"Sint-truidersteenweg 508",
    "sg:city":"Borgloon",
    "sg:orig_category":"Fruitteelt",
    "sg:phone":"+32 11 68 41 23",
    "sg:postcode":"3840",
    "sg:province":"Limburg",
    "wof:name":"Georges Swennen",
    "wof:placetype":"venue"
},
  "geometry": {"coordinates":[5.2671952248,50.807800293],"type":"Point"}
}