{
  "type": "Feature",
  "properties": {
    "iso:country":"BE",
    "sg:address":"Rue Du Point D'arr\u00eat 2a",
    "sg:city":"Bi\u00e8vre",
    "sg:classifiers":[
        {
            "category":"Real Estate",
            "subcategory":"Architect",
            "type":"Services"
        }
    ],
    "sg:phone":"+32 61 51 15 24",
    "sg:postcode":"5555",
    "sg:province":"Namur",
    "wof:name":"Barr\u00e9 D",
    "wof:placetype":"venue"
},
  "geometry": {"coordinates":[5.01963377,49.9413528442],"type":"Point"}
}