{
  "type": "Feature",
  "properties": {
    "addr:full":"Paul Hymanslaan 127bb8 Sint-lambrechts-woluwe/woluwe-saint-lambert Bruxelles-Capitale 1200",
    "addr:housenumber":"127bb8 sint-lambrechts-woluwe",
    "addr:postcode":"1200",
    "addr:street":"Hymanslaan",
    "iso:country":"BE",
    "sg:address":"Paul Hymanslaan 127bb8",
    "sg:city":"Sint-lambrechts-woluwe/woluwe-saint-lambert",
    "sg:orig_category":"Advocaten and juridische adviseurs",
    "sg:phone":"+32 2 770 62 40",
    "sg:postcode":"1200",
    "sg:province":"Bruxelles-Capitale",
    "wof:name":"Catherine Sans",
    "wof:placetype":"venue"
},
  "geometry": {"coordinates":[4.4339690208,50.8473701477],"type":"Point"}
}