{
  "type": "Feature",
  "properties": {
    "iso:country":"BE",
    "sg:address":"Boulevard Sainctelette 12",
    "sg:city":"Mons",
    "sg:classifiers":[
        {
            "category":"Personal",
            "subcategory":"Beauty Salon",
            "type":"Services"
        }
    ],
    "sg:phone":"+32 65 23 58 20",
    "sg:postcode":"7000",
    "sg:province":"Hainaut",
    "sg:tags":[
        "slimming"
    ],
    "wof:name":"Remodelling-centre D'endermologie Sp\u00e9cialis\u00e9",
    "wof:placetype":"venue"
},
  "geometry": {"coordinates":[3.9467079639,50.4466247559],"type":"Point"}
}