{
  "type": "Feature",
  "properties": {
    "iso:country":"BE",
    "sg:address":"Dommelstraat 51",
    "sg:city":"Waasmunster",
    "sg:orig_category":"Sportclubs",
    "sg:phone":"+32 52 46 01 32",
    "sg:postcode":"9250",
    "sg:province":"Oost-Vlaanderen",
    "wof:name":"D.h.c. Waasmunster",
    "wof:placetype":"venue"
},
  "geometry": {"coordinates":[4.1071600914,51.1144561768],"type":"Point"}
}