{
  "type": "Feature",
  "properties": {
    "addr:full":"Nouvelle Route 336 Florennes Namur 5621",
    "addr:postcode":"5621",
    "addr:street":"Nouvelle Route 336",
    "iso:country":"BE",
    "sg:address":"Nouvelle Route 336",
    "sg:city":"Florennes",
    "sg:orig_category":"HUISBRANDOLIE",
    "sg:phone":"+32 71 68 83 44",
    "sg:postcode":"5621",
    "sg:province":"Namur",
    "wof:name":"Mahieu J.-p.",
    "wof:placetype":"venue"
},
  "geometry": {"coordinates":[4.5615420341,50.2775993347],"type":"Point"}
}