{
  "type": "Feature",
  "properties": {
    "addr:full":"Rumstsestraat 52 Rumst Antwerpen 2840",
    "addr:housenumber":"52",
    "addr:postcode":"2840",
    "addr:street":"Rumstsestraat",
    "iso:country":"BE",
    "sg:address":"Rumstsestraat 52",
    "sg:city":"Rumst",
    "sg:orig_category":"Artiesten and kunstenaars Divers amusement",
    "sg:phone":"+32 3 844 14 85",
    "sg:postcode":"2840",
    "sg:province":"Antwerpen",
    "wof:name":"Discobar Magic",
    "wof:placetype":"venue"
},
  "geometry": {"coordinates":[4.4165101051,51.0979804993],"type":"Point"}
}