{
  "type": "Feature",
  "properties": {
    "iso:country":"BE",
    "sg:address":"Kouterbaan 19b",
    "sg:city":"Meise (wolvertem)",
    "sg:classifiers":[
        {
            "category":"Professional",
            "subcategory":"Accounting & Tax Preparation",
            "type":"Services"
        }
    ],
    "sg:phone":"+32 2 269 51 04",
    "sg:postcode":"1861",
    "sg:province":"Vlaams-Brabant",
    "sg:tags":[
        "bookkeeper"
    ],
    "wof:name":"Maes J",
    "wof:placetype":"venue"
},
  "geometry": {"coordinates":[4.3029808998,50.9720954895],"type":"Point"}
}