{
  "type": "Feature",
  "properties": {
    "addr:full":"Rue De Binche 33 Merbes-le-ch\u00c2teau Hainaut 6567",
    "addr:housenumber":"33",
    "addr:postcode":"6567",
    "addr:street":"Rue De Binche",
    "iso:country":"BE",
    "sg:address":"Rue De Binche 33",
    "sg:city":"Merbes-le-ch\u00c2teau",
    "sg:orig_category":"Deurwaarders",
    "sg:phone":"+32 71 30 04 45",
    "sg:postcode":"6567",
    "sg:province":"Hainaut",
    "wof:name":"Christian Preaux",
    "wof:placetype":"venue"
},
  "geometry": {"coordinates":[4.1695690155,50.3259086609],"type":"Point"}
}