{
  "type": "Feature",
  "properties": {
    "addr:full":"Rue De La Treille 22 Li\u00e8ge 1 (sclessin) Li\u00e8ge 4000",
    "addr:housenumber":"22;1",
    "addr:postcode":"4000",
    "addr:street":"Rue De La Treille;Sclessin Lie\u0300Ge",
    "iso:country":"BE",
    "sg:address":"Rue De La Treille 22",
    "sg:city":"Li\u00e8ge 1 (sclessin)",
    "sg:classifiers":[
        {
            "category":"Real Estate",
            "subcategory":"Architect",
            "type":"Services"
        }
    ],
    "sg:phone":"+32 479 34 63 75",
    "sg:postcode":"4000",
    "sg:province":"Li\u00e8ge",
    "wof:name":"Conti A",
    "wof:placetype":"venue"
},
  "geometry": {"coordinates":[5.557202816,50.6176948547],"type":"Point"}
}