{
  "type": "Feature",
  "properties": {
    "addr:full":"Twaalfde-liniestraat 36 Kuurne West-Vlaanderen 8520",
    "addr:housenumber":"36",
    "addr:postcode":"8520",
    "addr:street":"Twaalfde-Liniestraat",
    "iso:country":"BE",
    "sg:address":"Twaalfde-liniestraat 36",
    "sg:city":"Kuurne",
    "sg:orig_category":"Immobili\u00ebnkantoren",
    "sg:phone":"+32 56 70 49 09",
    "sg:postcode":"8520",
    "sg:province":"West-Vlaanderen",
    "wof:name":"Interhome Kuurne",
    "wof:placetype":"venue"
},
  "geometry": {"coordinates":[3.2890460491,50.8510093689],"type":"Point"}
}