{
  "type": "Feature",
  "properties": {
    "addr:full":"Chauss\u00e9e De Wavre 1574 Box 1 Bruxelles (auderghem) Bruxelles-Capitale 1160",
    "addr:housenumber":"1574;1",
    "addr:postcode":"1160",
    "addr:street":"Chausse\u0301E De Wavre;Box",
    "iso:country":"BE",
    "sg:address":"Chauss\u00e9e De Wavre 1574 Box 1",
    "sg:city":"Bruxelles (auderghem)",
    "sg:classifiers":[
        {
            "category":"Professional",
            "subcategory":"Accounting & Tax Preparation",
            "type":"Services"
        }
    ],
    "sg:phone":"+32 2 672 02 95",
    "sg:postcode":"1160",
    "sg:province":"Bruxelles-Capitale",
    "sg:tags":[
        "bookkeeper"
    ],
    "wof:name":"Sauvaget A",
    "wof:placetype":"venue"
},
  "geometry": {"coordinates":[4.4231190681,50.8172340393],"type":"Point"}
}