{
  "type": "Feature",
  "properties": {
    "addr:full":"Kleiputtendreef 4 Poperinge West-Vlaanderen 8970",
    "addr:housenumber":"4",
    "addr:postcode":"8970",
    "addr:street":"Kleiputtendreef",
    "iso:country":"BE",
    "sg:address":"Kleiputtendreef 4",
    "sg:city":"Poperinge",
    "sg:orig_category":"Kapsalons",
    "sg:phone":"+32 57 33 36 39",
    "sg:postcode":"8970",
    "sg:province":"West-Vlaanderen",
    "wof:name":"Coiffure Charme",
    "wof:placetype":"venue"
},
  "geometry": {"coordinates":[2.7301259041,50.8452568054],"type":"Point"}
}