{
  "type": "Feature",
  "properties": {
    "addr:full":"Rijschootstr 10 Evergem (groot) Oost-Vlaanderen 9940",
    "addr:housenumber":"10",
    "addr:postcode":"9940",
    "addr:street":"Rijschootstr;Groot Oost-Vlaanderen",
    "iso:country":"BE",
    "sg:address":"Rijschootstr 10",
    "sg:city":"Evergem (groot)",
    "sg:orig_category":"Kapsalons",
    "sg:phone":"+32 9 344 39 25",
    "sg:postcode":"9940",
    "sg:province":"Oost-Vlaanderen",
    "wof:name":"Kreatief Kapsalon",
    "wof:placetype":"venue"
},
  "geometry": {"coordinates":[3.7497639656,51.1854743958],"type":"Point"}
}