{
  "type": "Feature",
  "properties": {
    "addr:full":"Afrikalaan 182-186 Gent Oost-Vlaanderen 9000",
    "addr:housenumber":"182-186",
    "addr:postcode":"9000",
    "addr:street":"Afrikalaan;Oost-Vlaanderen",
    "iso:country":"BE",
    "sg:address":"Afrikalaan 182-186",
    "sg:city":"Gent",
    "sg:classifiers":[
        {
            "category":"Shopping",
            "type":"Retail Goods"
        }
    ],
    "sg:phone":"+32 9 223 38 71",
    "sg:postcode":"9000",
    "sg:province":"Oost-Vlaanderen",
    "sg:tags":[
        "product",
        "cleaning",
        "maintenance"
    ],
    "wof:name":"Christeyns Nv",
    "wof:placetype":"venue"
},
  "geometry": {"coordinates":[3.7385759354,51.0682067871],"type":"Point"}
}