{
  "type": "Feature",
  "properties": {
    "addr:full":"Meenselbeekstraat 17 Glabbeek (bunsbeek) Vlaams-Brabant 3380",
    "addr:housenumber":"17",
    "addr:postcode":"3380",
    "addr:street":"Meenselbeekstraat",
    "iso:country":"BE",
    "sg:address":"Meenselbeekstraat 17",
    "sg:city":"Glabbeek (bunsbeek)",
    "sg:classifiers":[
        {
            "category":"Retail",
            "subcategory":"Repair Shop",
            "type":"Services"
        }
    ],
    "sg:phone":"+32 16 77 13 68",
    "sg:postcode":"3380",
    "sg:province":"Vlaams-Brabant",
    "wof:name":"Cad\u00e9",
    "wof:placetype":"venue"
},
  "geometry": {"coordinates":[4.957089901,50.8584976196],"type":"Point"}
}