{
  "type": "Feature",
  "properties": {
    "iso:country":"BE",
    "sg:address":"Rue \u00e0 La Barre 12bis",
    "sg:city":"Tournai (gaurain-ramecroix)",
    "sg:classifiers":[
        {
            "category":"Health Services",
            "subcategory":"Medical Lab",
            "type":"Services"
        }
    ],
    "sg:phone":"+32 69 54 76 73",
    "sg:postcode":"7530",
    "sg:province":"Hainaut",
    "sg:tags":[
        "laboratory",
        "dental"
    ],
    "wof:name":"Detournay M",
    "wof:placetype":"venue"
},
  "geometry": {"coordinates":[3.4995861053,50.5990257263],"type":"Point"}
}