{
  "type": "Feature",
  "properties": {
    "iso:country":"BE",
    "sg:address":"Rue Des Awirs 188",
    "sg:city":"Fl\u00e9malle (awirs)",
    "sg:classifiers":[
        {
            "category":"Arts & Performance",
            "subcategory":"Music",
            "type":"Entertainment"
        }
    ],
    "sg:phone":"+32 4 275 28 45",
    "sg:postcode":"4400",
    "sg:province":"Li\u00e8ge",
    "sg:tags":[
        "disc-jockeys"
    ],
    "wof:name":"Ambiance Karaoke",
    "wof:placetype":"venue"
},
  "geometry": {"coordinates":[5.3892731667,50.6146774292],"type":"Point"}
}