{
  "type": "Feature",
  "properties": {
    "iso:country":"BE",
    "sg:address":"Avenue Du Four \u00e0 Briques 5",
    "sg:city":"Bruxelles (evere)",
    "sg:classifiers":[
        {
            "category":"Professional",
            "subcategory":"Printing & Photocopies",
            "type":"Services"
        }
    ],
    "sg:phone":"+32 2 727 31 11",
    "sg:postcode":"1140",
    "sg:province":"Bruxelles-Capitale",
    "sg:tags":[
        "machine",
        "equipment"
    ],
    "wof:name":"Plantin Nv",
    "wof:placetype":"venue"
},
  "geometry": {"coordinates":[4.413626194,50.8655433655],"type":"Point"}
}