{
  "type": "Feature",
  "properties": {
    "addr:full":"Koolkerkse Steenweg 61 Brugge West-Vlaanderen 8000",
    "addr:housenumber":"61",
    "addr:postcode":"8000",
    "addr:street":"Koolkerkse Steenweg",
    "iso:country":"BE",
    "sg:address":"Koolkerkse Steenweg 61",
    "sg:city":"Brugge",
    "sg:classifiers":[
        {
            "category":"Cafe",
            "type":"Food & Drink"
        }
    ],
    "sg:phone":"+32 50 34 14 28",
    "sg:postcode":"8000",
    "sg:province":"West-Vlaanderen",
    "sg:tags":[
        "caf\u00e9s"
    ],
    "wof:name":"Caf\u00c9 Vespa",
    "wof:placetype":"venue"
},
  "geometry": {"coordinates":[3.2221269608,51.2065086365],"type":"Point"}
}