{
  "type": "Feature",
  "properties": {
    "iso:country":"BE",
    "sg:address":"Avenue Gevaert 32",
    "sg:city":"Rixensart",
    "sg:orig_category":"M\u00e9decins and sp\u00e9cialistes",
    "sg:phone":"+32 2 654 10 25",
    "sg:postcode":"1332",
    "sg:province":"Brabant Wallon",
    "wof:name":"Micheline Morant",
    "wof:placetype":"venue"
},
  "geometry": {"coordinates":[4.4981799126,50.718120575],"type":"Point"}
}