{
  "type": "Feature",
  "properties": {
    "iso:country":"BE",
    "sg:address":"Geelsebaan 32",
    "sg:city":"Kasterlee",
    "sg:orig_category":"Kapsalons",
    "sg:phone":"+32 14 85 05 27",
    "sg:postcode":"2460",
    "sg:province":"Antwerpen",
    "wof:name":"Anny Van De Walle",
    "wof:placetype":"venue"
},
  "geometry": {"coordinates":[4.9683251381,51.2387733459],"type":"Point"}
}