{
  "type": "Feature",
  "properties": {
    "addr:full":"Rue Joseph Servais 33 Ans Li\u00e8ge 4430",
    "addr:housenumber":"33",
    "addr:postcode":"4430",
    "addr:street":"Rue Joseph Servais",
    "iso:country":"BE",
    "sg:address":"Rue Joseph Servais 33",
    "sg:city":"Ans",
    "sg:classifiers":[
        {
            "category":"Health Services",
            "subcategory":"Health Practitioner",
            "type":"Services"
        }
    ],
    "sg:phone":"+32 496 41 17 45",
    "sg:postcode":"4430",
    "sg:province":"Li\u00e8ge",
    "sg:tags":[
        "physiotherapist"
    ],
    "wof:name":"Baccus Sylvie",
    "wof:placetype":"venue"
},
  "geometry": {"coordinates":[5.5182061195,50.6626625061],"type":"Point"}
}