{
  "type": "Feature",
  "properties": {
    "addr:full":"Korenbloemstraat 17 Gent Oost-Vlaanderen 9000",
    "addr:housenumber":"17",
    "addr:postcode":"9000",
    "addr:street":"Korenbloemstraat;Oost-Vlaanderen",
    "iso:country":"BE",
    "sg:address":"Korenbloemstraat 17",
    "sg:city":"Gent",
    "sg:orig_category":"Enseignement maternel and primaire",
    "sg:phone":"+32 9 223 34 63",
    "sg:postcode":"9000",
    "sg:province":"Oost-Vlaanderen",
    "wof:name":"Bulo Korenbloem",
    "wof:placetype":"venue"
},
  "geometry": {"coordinates":[3.7061998844,51.0521507263],"type":"Point"}
}