{
  "type": "Feature",
  "properties": {
    "iso:country":"BE",
    "sg:address":"Rue Fernand S\u00c9verin 62",
    "sg:city":"Schaarbeek/schaerbeek",
    "sg:orig_category":"E-activit\u00e9s. Conseils en syst\u00e8mes informatiques. Ordinateurs and \u00e9quipement informatique. R\u00e9alisatio",
    "sg:phone":"+32 2 247 93 27",
    "sg:postcode":"1030",
    "sg:province":"Bruxelles-Capitale",
    "wof:name":"Net7-netseven",
    "wof:placetype":"venue"
},
  "geometry": {"coordinates":[4.3899869919,50.876625061],"type":"Point"}
}