{
  "type": "Feature",
  "properties": {
    "addr:full":"Place De Saint-marc 8 Namur Namur 5003",
    "addr:housenumber":"8",
    "addr:postcode":"5003",
    "addr:street":"Place De Saint-Marc",
    "iso:country":"BE",
    "sg:address":"Place De Saint-marc 8",
    "sg:city":"Namur",
    "sg:classifiers":[
        {
            "category":"Cafe",
            "type":"Food & Drink"
        }
    ],
    "sg:phone":"+32 81 73 27 11",
    "sg:postcode":"5003",
    "sg:province":"Namur",
    "sg:tags":[
        "caf\u00e9s"
    ],
    "wof:name":"La Pelote St.marcoise",
    "wof:placetype":"venue"
},
  "geometry": {"coordinates":[4.8496718407,50.494430542],"type":"Point"}
}