{
  "type": "Feature",
  "properties": {
    "iso:country":"BE",
    "sg:address":"Rue L\u00c9on Fran\u00c7ois 59",
    "sg:city":"Profondeville",
    "sg:orig_category":"Boissons",
    "sg:phone":"+32 81 43 49 09",
    "sg:postcode":"5170",
    "sg:province":"Namur",
    "wof:name":"Maison Vinal",
    "wof:placetype":"venue"
},
  "geometry": {"coordinates":[4.8345098495,50.4020957947],"type":"Point"}
}