{
  "type": "Feature",
  "properties": {
    "addr:full":"Boekweitstraat 4 Zelzate Oost-Vlaanderen 9060",
    "addr:housenumber":"4",
    "addr:postcode":"9060",
    "addr:street":"Boekweitstraat",
    "iso:country":"BE",
    "sg:address":"Boekweitstraat 4",
    "sg:city":"Zelzate",
    "sg:orig_category":"Bijouteries and horlogeries",
    "sg:phone":"+32 9 342 97 50",
    "sg:postcode":"9060",
    "sg:province":"Oost-Vlaanderen",
    "wof:name":"Huis Adamant\u00c9",
    "wof:placetype":"venue"
},
  "geometry": {"coordinates":[3.8221170902,51.1998710632],"type":"Point"}
}