{
  "type": "Feature",
  "properties": {
    "addr:full":"Kleinenberg 28 Wuustwezel Antwerpen 2990",
    "addr:housenumber":"28",
    "addr:postcode":"2990",
    "addr:street":"Kleinenberg",
    "iso:country":"BE",
    "sg:address":"Kleinenberg 28",
    "sg:city":"Wuustwezel",
    "sg:orig_category":"Rundveehouders Varkenskwekers",
    "sg:phone":"+32 3 669 75 91",
    "sg:postcode":"2990",
    "sg:province":"Antwerpen",
    "wof:name":"Alphonsius Van Den Bergh",
    "wof:placetype":"venue"
},
  "geometry": {"coordinates":[4.5685300827,51.3833122253],"type":"Point"}
}