{
  "type": "Feature",
  "properties": {
    "addr:full":"Place Jean Jacobs 1 Bruxelles Bruxelles-Capitale 1000",
    "addr:housenumber":"1",
    "addr:postcode":"1000",
    "addr:street":"Place Jean Jacobs",
    "iso:country":"BE",
    "sg:address":"Place Jean Jacobs 1",
    "sg:city":"Bruxelles",
    "sg:classifiers":[
        {
            "category":"Professional",
            "subcategory":"Lawyer & Legal Services",
            "type":"Services"
        }
    ],
    "sg:phone":"+32 2 548 29 19",
    "sg:postcode":"1000",
    "sg:province":"Bruxelles-Capitale",
    "wof:name":"Denys Lieven",
    "wof:placetype":"venue"
},
  "geometry": {"coordinates":[4.3514928818,50.8352088928],"type":"Point"}
}