{
  "type": "Feature",
  "properties": {
    "addr:full":"Scheepswerfstraat 17 Dendermonde Oost-Vlaanderen 9200",
    "addr:housenumber":"17",
    "addr:postcode":"9200",
    "addr:street":"Scheepswerfstraat;Oost-Vlaanderen",
    "iso:country":"BE",
    "sg:address":"Scheepswerfstraat 17",
    "sg:city":"Dendermonde",
    "sg:orig_category":"Pharmaciens",
    "sg:phone":"+32 52 33 24 27",
    "sg:postcode":"9200",
    "sg:province":"Oost-Vlaanderen",
    "wof:name":"Apotheek Vooruit",
    "wof:placetype":"venue"
},
  "geometry": {"coordinates":[4.0983099937,51.0315208435],"type":"Point"}
}