{
  "type": "Feature",
  "properties": {
    "addr:full":"Zijp 23 Wemmel Vlaams-Brabant 1780",
    "addr:housenumber":"23",
    "addr:postcode":"1780",
    "addr:street":"Zijp;Vlaams-Brabant",
    "iso:country":"BE",
    "sg:address":"Zijp 23",
    "sg:city":"Wemmel",
    "sg:classifiers":[
        {
            "category":"Home & Garden",
            "subcategory":"Garden Supply",
            "type":"Retail Goods"
        }
    ],
    "sg:phone":"+32 2 460 30 72",
    "sg:postcode":"1780",
    "sg:province":"Vlaams-Brabant",
    "wof:name":"Garden Center Wemmel Bvba",
    "wof:placetype":"venue"
},
  "geometry": {"coordinates":[4.3226709366,50.9175376892],"type":"Point"}
}