{
  "type": "Feature",
  "properties": {
    "addr:full":"Grand'rue 52 Aubange Luxembourg 6791",
    "addr:housenumber":"52",
    "addr:postcode":"6791",
    "addr:street":"Grand'Rue",
    "iso:country":"BE",
    "sg:address":"Grand'rue 52",
    "sg:city":"Aubange",
    "sg:orig_category":"Magasins sp\u00e9cialis\u00e9s. Salons de coiffure",
    "sg:phone":"+32 63 38 53 59",
    "sg:postcode":"6791",
    "sg:province":"Luxembourg",
    "wof:name":"Coiffure Robin & Franka",
    "wof:placetype":"venue"
},
  "geometry": {"coordinates":[5.8356189728,49.5628623962],"type":"Point"}
}