{
  "type": "Feature",
  "properties": {
    "addr:full":"Rue Du Cimeti\u00e8re 8 Vis\u00e9 (lanaye) Li\u00e8ge 4600",
    "addr:housenumber":"8",
    "addr:postcode":"4600",
    "addr:street":"Rue Du Cimetie\u0300Re;Lanaye",
    "iso:country":"BE",
    "sg:address":"Rue Du Cimeti\u00e8re 8",
    "sg:city":"Vis\u00e9 (lanaye)",
    "sg:classifiers":[
        {
            "category":"Banks & Credit Unions",
            "subcategory":"Investment Brokerage",
            "type":"Services"
        }
    ],
    "sg:phone":"+32 4 379 78 22",
    "sg:postcode":"4600",
    "sg:province":"Li\u00e8ge",
    "sg:tags":[
        "repair",
        "-",
        "installation",
        "sanitary",
        "article"
    ],
    "wof:name":"Cardinaels D",
    "wof:placetype":"venue"
},
  "geometry": {"coordinates":[5.6960802078,50.7817573547],"type":"Point"}
}