{
  "type": "Feature",
  "properties": {
    "addr:full":"Pollare Dorp 87 Ninove (pollare) Oost-Vlaanderen 9401",
    "addr:housenumber":"87",
    "addr:postcode":"9401",
    "addr:street":"Pollare Dorp",
    "iso:country":"BE",
    "sg:address":"Pollare Dorp 87",
    "sg:city":"Ninove (pollare)",
    "sg:classifiers":[
        {
            "category":"Personal",
            "subcategory":"Shoe Repair & Shine",
            "type":"Services"
        }
    ],
    "sg:phone":"+32 54 32 58 77",
    "sg:postcode":"9401",
    "sg:province":"Oost-Vlaanderen",
    "sg:tags":[
        "shoemaker"
    ],
    "wof:name":"Paul",
    "wof:placetype":"venue"
},
  "geometry": {"coordinates":[4.0013818741,50.819984436],"type":"Point"}
}