{
  "type": "Feature",
  "properties": {
    "addr:full":"Rue Du Moulin 16 Gembloux-sur-orneau (gembloux) Namur 5030",
    "addr:housenumber":"16",
    "addr:postcode":"5030",
    "addr:street":"Rue Du Moulin;Namur",
    "iso:country":"BE",
    "sg:address":"Rue Du Moulin 16",
    "sg:city":"Gembloux-sur-orneau (gembloux)",
    "sg:orig_category":"Solariums",
    "sg:phone":"+32 81 61 60 34",
    "sg:postcode":"5030",
    "sg:province":"Namur",
    "wof:name":"Couleur Caf\u00e8",
    "wof:placetype":"venue"
},
  "geometry": {"coordinates":[4.6930551529,50.5619621277],"type":"Point"}
}