{
  "type": "Feature",
  "properties": {
    "addr:full":"Liersesteenweg 289 Box 1 Mortsel Antwerpen 2640",
    "addr:housenumber":"289;1",
    "addr:postcode":"2640",
    "addr:street":"Liersesteenweg;Box",
    "iso:country":"BE",
    "sg:address":"Liersesteenweg 289 Box 1",
    "sg:city":"Mortsel",
    "sg:classifiers":[
        {
            "category":"Building & Trades",
            "subcategory":"Electrical",
            "type":"Services"
        }
    ],
    "sg:phone":"+32 3 454 12 35",
    "sg:postcode":"2640",
    "sg:province":"Antwerpen",
    "sg:tags":[
        "electric",
        "-",
        "housewiring",
        "contractor"
    ],
    "wof:name":"Grade Elektriciteit & Automatisatie",
    "wof:placetype":"venue"
},
  "geometry": {"coordinates":[4.4744648933,51.168510437],"type":"Point"}
}