{
  "type": "Feature",
  "properties": {
    "addr:full":"Boereveldseweg 6 Zwijndrecht Antwerpen 2070",
    "addr:housenumber":"6",
    "addr:postcode":"2070",
    "addr:street":"Boereveldseweg",
    "iso:country":"BE",
    "sg:address":"Boereveldseweg 6",
    "sg:city":"Zwijndrecht",
    "sg:orig_category":"Non-Classified Establishments",
    "sg:phone":"+32 3 735 07 00",
    "sg:postcode":"2070",
    "sg:province":"Antwerpen",
    "wof:name":"Tci Europe Nv",
    "wof:placetype":"venue"
},
  "geometry": {"coordinates":[4.3017997742,51.2371902466],"type":"Point"}
}