{
  "type": "Feature",
  "properties": {
    "addr:full":"Pont Du Ch\u00cane 50 Verviers Li\u00e8ge 4800",
    "addr:housenumber":"50",
    "addr:postcode":"4800",
    "addr:street":"Pont Du Che\u0302Ne",
    "iso:country":"BE",
    "sg:address":"Pont Du Ch\u00cane 50",
    "sg:city":"Verviers",
    "sg:orig_category":"Epiceries",
    "sg:phone":"+32 87 31 40 81",
    "sg:postcode":"4800",
    "sg:province":"Li\u00e8ge",
    "wof:name":"I.l.d.",
    "wof:placetype":"venue"
},
  "geometry": {"coordinates":[5.8551898003,50.592300415],"type":"Point"}
}