{
  "type": "Feature",
  "properties": {
    "addr:full":"Zuidstraat 7 Jabbeke West-Vlaanderen 8490",
    "addr:housenumber":"7",
    "addr:postcode":"8490",
    "addr:street":"Zuidstraat",
    "iso:country":"BE",
    "sg:address":"Zuidstraat 7",
    "sg:city":"Jabbeke",
    "sg:orig_category":"Sportclubs",
    "sg:phone":"+32 50 81 22 30",
    "sg:postcode":"8490",
    "sg:province":"West-Vlaanderen",
    "wof:name":"Judo Centrum Jabbeke",
    "wof:placetype":"venue"
},
  "geometry": {"coordinates":[3.0866930485,51.1800765991],"type":"Point"}
}