{
  "type": "Feature",
  "properties": {
    "iso:country":"BE",
    "sg:address":"Kampstraat 10",
    "sg:city":"Geraardsbergen",
    "sg:orig_category":"Producteurs de l\u00e9gumes",
    "sg:phone":"+32 54 41 75 02",
    "sg:postcode":"9500",
    "sg:province":"Oost-Vlaanderen",
    "wof:name":"Bert Vandergeynst",
    "wof:placetype":"venue"
},
  "geometry": {"coordinates":[3.8843801022,50.7716445923],"type":"Point"}
}