{
  "type": "Feature",
  "properties": {
    "addr:full":"Rue Du Village 45 Plombieres Li\u00e8ge 4850",
    "addr:housenumber":"45",
    "addr:postcode":"4850",
    "addr:street":"Rue Du Village",
    "iso:country":"BE",
    "sg:address":"Rue Du Village 45",
    "sg:city":"Plombieres",
    "sg:orig_category":"P\u00e9pini\u00e9ristes. Jardinage",
    "sg:phone":"+32 87 78 49 96",
    "sg:postcode":"4850",
    "sg:province":"Li\u00e8ge",
    "wof:name":"Szlachta-garden Concept",
    "wof:placetype":"venue"
},
  "geometry": {"coordinates":[5.9626002312,50.7068138123],"type":"Point"}
}