{
  "type": "Feature",
  "properties": {
    "iso:country":"BE",
    "sg:address":"Stationsstraat 94",
    "sg:city":"Nevele",
    "sg:orig_category":"Treinen and spoorwegen",
    "sg:phone":"+32 9 241 21 61",
    "sg:postcode":"9850",
    "sg:province":"Oost-Vlaanderen",
    "wof:name":"Station Landegem",
    "wof:placetype":"venue"
},
  "geometry": {"coordinates":[3.5758700371,51.064201355],"type":"Point"}
}