{
  "type": "Feature",
  "properties": {
    "addr:full":"Nieuwstraat 34 Retie Antwerpen 2470",
    "addr:housenumber":"34",
    "addr:postcode":"2470",
    "addr:street":"Nieuwstraat",
    "iso:country":"BE",
    "sg:address":"Nieuwstraat 34",
    "sg:city":"Retie",
    "sg:classifiers":[
        {
            "category":"Shopping",
            "subcategory":"Gifts & Souvenirs",
            "type":"Retail Goods"
        }
    ],
    "sg:phone":"+32 14 37 79 28",
    "sg:postcode":"2470",
    "sg:province":"Antwerpen",
    "sg:tags":[
        "-"
    ],
    "wof:name":"Franimex",
    "wof:placetype":"venue"
},
  "geometry": {"coordinates":[5.0826840401,51.2622566223],"type":"Point"}
}