{
  "type": "Feature",
  "properties": {
    "addr:full":"Rue De P\u00c9crot Graven Brabant Wallon 1390",
    "addr:postcode":"1390",
    "addr:street":"Rue De Pe\u0301Crot Graven Brabant",
    "iso:country":"BE",
    "sg:address":"Rue De P\u00c9crot",
    "sg:city":"Graven",
    "sg:orig_category":"Installation de menuiserie en bois and plastique",
    "sg:phone":"+32 10 84 01 81",
    "sg:postcode":"1390",
    "sg:province":"Brabant Wallon",
    "wof:name":"Destr\u00c9e P.",
    "wof:placetype":"venue"
},
  "geometry": {"coordinates":[4.6550631523,50.7804489136],"type":"Point"}
}