{
  "type": "Feature",
  "properties": {
    "iso:country":"BE",
    "sg:address":"Astridlaan 272",
    "sg:city":"Overpelt",
    "sg:orig_category":"Charpentes and couvertures",
    "sg:phone":"+32 11 64 84 09",
    "sg:postcode":"3900",
    "sg:province":"Limburg",
    "wof:name":"Polydak",
    "wof:placetype":"venue"
},
  "geometry": {"coordinates":[5.3802928925,51.2146034241],"type":"Point"}
}