{
  "type": "Feature",
  "properties": {
    "iso:country":"BE",
    "sg:address":"Welvaartstraat 22",
    "sg:city":"Antwerpen",
    "sg:classifiers":[
        {
            "category":"Professional",
            "subcategory":"Management & Consulting",
            "type":"Services"
        }
    ],
    "sg:phone":"+32 3 238 64 62",
    "sg:postcode":"2000",
    "sg:province":"Antwerpen",
    "sg:tags":[
        "consultant",
        "law"
    ],
    "wof:name":"R.p. Consult Bvba",
    "wof:placetype":"venue"
},
  "geometry": {"coordinates":[4.3994431496,51.2102966309],"type":"Point"}
}