{
  "type": "Feature",
  "properties": {
    "addr:full":"Avenue De La Ch\u00canaie 7 Lasne Brabant Wallon 1380",
    "addr:housenumber":"7",
    "addr:postcode":"1380",
    "addr:street":"Avenue De La Che\u0302Naie",
    "iso:country":"BE",
    "sg:address":"Avenue De La Ch\u00canaie 7",
    "sg:city":"Lasne",
    "sg:orig_category":"Experts-comptables",
    "sg:phone":"+32 2 653 62 77",
    "sg:postcode":"1380",
    "sg:province":"Brabant Wallon",
    "wof:name":"Genevieve Van Tuyckom",
    "wof:placetype":"venue"
},
  "geometry": {"coordinates":[4.4930429459,50.698223114],"type":"Point"}
}