{
  "type": "Feature",
  "properties": {
    "addr:full":"Rue Du Domaine De Negri 7 Ottignies-louvain-la-neuve Brabant Wallon 1341",
    "addr:housenumber":"7",
    "addr:postcode":"1341",
    "addr:street":"Rue Du Domaine De Negri",
    "iso:country":"BE",
    "sg:address":"Rue Du Domaine De Negri 7",
    "sg:city":"Ottignies-louvain-la-neuve",
    "sg:classifiers":[
        {
            "category":"Recreation",
            "type":"Entertainment"
        }
    ],
    "sg:phone":"+32 10 61 68 81",
    "sg:postcode":"1341",
    "sg:province":"Brabant Wallon",
    "sg:tags":[
        "diver",
        "amusement"
    ],
    "wof:name":"Fakir Ramses",
    "wof:placetype":"venue"
},
  "geometry": {"coordinates":[4.5627598763,50.6583099365],"type":"Point"}
}