{
  "type": "Feature",
  "properties": {
    "addr:full":"Lange Steenstraat 43 Box 21 Kortrijk West-Vlaanderen 8500",
    "addr:housenumber":"43 box 21",
    "addr:postcode":"8500",
    "addr:street":"Lange Steenstraat",
    "iso:country":"BE",
    "sg:address":"Lange Steenstraat 43 Box 21",
    "sg:city":"Kortrijk",
    "sg:classifiers":[
        {
            "category":"Health Services",
            "subcategory":"Nursing And Care Facility",
            "type":"Services"
        }
    ],
    "sg:phone":"+32 56 25 73 47",
    "sg:postcode":"8500",
    "sg:province":"West-Vlaanderen",
    "sg:tags":[
        "home"
    ],
    "wof:name":"Tack S",
    "wof:placetype":"venue"
},
  "geometry": {"coordinates":[3.2686369419,50.827003479],"type":"Point"}
}