{
  "type": "Feature",
  "properties": {
    "addr:full":"Rue De Cent Pieds 170 Binche Hainaut 7133",
    "addr:housenumber":"170",
    "addr:postcode":"7133",
    "addr:street":"Rue De Cent Pieds",
    "iso:country":"BE",
    "sg:address":"Rue De Cent Pieds 170",
    "sg:city":"Binche",
    "sg:orig_category":"Rundveehouders",
    "sg:phone":"+32 64 33 98 17",
    "sg:postcode":"7133",
    "sg:province":"Hainaut",
    "wof:name":"Beno\u00cet De Looz Corswarem",
    "wof:placetype":"venue"
},
  "geometry": {"coordinates":[4.2187700272,50.3872299194],"type":"Point"}
}