{
  "type": "Feature",
  "properties": {
    "addr:full":"Rue De Treves 25 Bruxelles Bruxelles-Capitale 1040",
    "addr:housenumber":"25",
    "addr:postcode":"1040",
    "addr:street":"Rue De Treves",
    "iso:country":"BE",
    "sg:address":"Rue De Treves 25",
    "sg:city":"Bruxelles",
    "sg:classifiers":[
        {
            "category":"Banks & Credit Unions",
            "subcategory":"Financial Services",
            "type":"Services"
        }
    ],
    "sg:phone":"+32 2 285 20 20",
    "sg:postcode":"1040",
    "sg:province":"Bruxelles-Capitale",
    "sg:tags":[
        "banking",
        "finance",
        "insurance"
    ],
    "wof:name":"Bacob Cv",
    "wof:placetype":"venue"
},
  "geometry": {"coordinates":[4.3747291565,50.8415794373],"type":"Point"}
}