{
  "type": "Feature",
  "properties": {
    "addr:full":"Hunningen 60ba B\u00dcllingen/bullange Li\u00e8ge 4760",
    "addr:housenumber":"60ba",
    "addr:postcode":"4760",
    "addr:street":"Hunningen",
    "iso:country":"BE",
    "sg:address":"Hunningen 60ba",
    "sg:city":"B\u00dcllingen/bullange",
    "sg:orig_category":"Plaatsen van vloer- and muurbekleding",
    "sg:phone":"+32 80 64 76 22",
    "sg:postcode":"4760",
    "sg:province":"Li\u00e8ge",
    "wof:name":"Stoffels Erich",
    "wof:placetype":"venue"
},
  "geometry": {"coordinates":[6.304910183,50.4083137512],"type":"Point"}
}