{
  "type": "Feature",
  "properties": {
    "iso:country":"BE",
    "sg:address":"Stw Op Leuze 176",
    "sg:city":"Ronse",
    "sg:orig_category":"Elektrische and elektronische apparatuur Gh",
    "sg:phone":"+32 55 23 70 71",
    "sg:postcode":"9600",
    "sg:province":"Oost-Vlaanderen",
    "wof:name":"Dorhex",
    "wof:placetype":"venue"
},
  "geometry": {"coordinates":[3.5881519318,50.7291259766],"type":"Point"}
}