{
  "type": "Feature",
  "properties": {
    "addr:full":"Geleytsbeekstraat 222 Ukkel/uccle Bruxelles-Capitale 1180",
    "addr:housenumber":"222",
    "addr:postcode":"1180",
    "addr:street":"Geleytsbeekstraat;/",
    "iso:country":"BE",
    "sg:address":"Geleytsbeekstraat 222",
    "sg:city":"Ukkel/uccle",
    "sg:orig_category":"Herstellingen and onderhoud van auto's",
    "sg:phone":"+32 2 374 75 92",
    "sg:postcode":"1180",
    "sg:province":"Bruxelles-Capitale",
    "wof:name":"Garage Evenepoel",
    "wof:placetype":"venue"
},
  "geometry": {"coordinates":[4.3419981003,50.7896003723],"type":"Point"}
}