{
  "type": "Feature",
  "properties": {
    "addr:full":"Groentemarkt 10 Oostende West-Vlaanderen 8400",
    "addr:housenumber":"10",
    "addr:postcode":"8400",
    "addr:street":"Groentemarkt",
    "iso:country":"BE",
    "sg:address":"Groentemarkt 10",
    "sg:city":"Oostende",
    "sg:classifiers":[
        {
            "category":"Wholesale",
            "subcategory":"Wine & Distilled Alcoholic Beverages",
            "type":"Manufacturing & Wholesale Goods"
        }
    ],
    "sg:phone":"+32 59 50 81 01",
    "sg:postcode":"8400",
    "sg:province":"West-Vlaanderen",
    "sg:tags":[
        "whol",
        "-",
        "spirit",
        "mfg"
    ],
    "wof:name":"Cave Du Vin",
    "wof:placetype":"venue"
},
  "geometry": {"coordinates":[2.9200310707,51.2321891785],"type":"Point"}
}