{
  "type": "Feature",
  "properties": {
    "iso:country":"BE",
    "sg:address":"Rue De La Station 17b1",
    "sg:city":"Lobbes",
    "sg:orig_category":"Traitements param\u00e9dicaux",
    "sg:phone":"+32 71 59 28 30",
    "sg:postcode":"6540",
    "sg:province":"Hainaut",
    "wof:name":"A.s.d.",
    "wof:placetype":"venue"
},
  "geometry": {"coordinates":[4.2624440193,50.3456001282],"type":"Point"}
}