{
  "type": "Feature",
  "properties": {
    "addr:full":"Mont 18 Vielsalm Luxembourg 6698",
    "addr:housenumber":"18",
    "addr:postcode":"6698",
    "addr:street":"Mont",
    "iso:country":"BE",
    "sg:address":"Mont 18",
    "sg:city":"Vielsalm",
    "sg:orig_category":"Travaux de pl\u00e2trage",
    "sg:phone":"+32 80 21 47 98",
    "sg:postcode":"6698",
    "sg:province":"Luxembourg",
    "wof:name":"Guy Huberty",
    "wof:placetype":"venue"
},
  "geometry": {"coordinates":[5.8947229385,50.3214225769],"type":"Point"}
}