{
  "type": "Feature",
  "properties": {
    "iso:country":"BE",
    "sg:address":"Marelputstraat 8",
    "sg:city":"Izegem",
    "sg:classifiers":[
        {
            "category":"Professional",
            "subcategory":"Accounting & Tax Preparation",
            "type":"Services"
        }
    ],
    "sg:phone":"+32 51 31 36 35",
    "sg:postcode":"8870",
    "sg:province":"West-Vlaanderen",
    "sg:tags":[
        "bookkeeper"
    ],
    "wof:name":"Gheysen R",
    "wof:placetype":"venue"
},
  "geometry": {"coordinates":[3.18334198,50.9223175049],"type":"Point"}
}