{
  "type": "Feature",
  "properties": {
    "iso:country":"BE",
    "sg:address":"Hoenderstraat 22",
    "sg:city":"Wetteren",
    "sg:classifiers":[
        {
            "category":"Manufacturing",
            "subcategory":"Printing",
            "type":"Manufacturing & Wholesale Goods"
        }
    ],
    "sg:phone":"+32 9 369 15 95",
    "sg:postcode":"9230",
    "sg:province":"Oost-Vlaanderen",
    "sg:tags":[
        "publishing"
    ],
    "wof:name":"Cultura Bvba",
    "wof:placetype":"venue"
},
  "geometry": {"coordinates":[3.882060051,51.0040397644],"type":"Point"}
}