{
  "type": "Feature",
  "properties": {
    "iso:country":"BE",
    "sg:address":"Rue Saint-pierre 3",
    "sg:city":"Burdinne",
    "sg:orig_category":"Eleveurs and marchands de porcs. Eleveurs de bovins",
    "sg:phone":"+32 85 71 23 21",
    "sg:postcode":"4210",
    "sg:province":"Li\u00e8ge",
    "wof:name":"Etienne Dethier",
    "wof:placetype":"venue"
},
  "geometry": {"coordinates":[5.089507103,50.584274292],"type":"Point"}
}