{
  "type": "Feature",
  "properties": {
    "addr:full":"Flanders Language Valley 21a Ieper West-Vlaanderen 8900",
    "addr:housenumber":"21a",
    "addr:postcode":"8900",
    "iso:country":"BE",
    "sg:address":"Flanders Language Valley 21a",
    "sg:city":"Ieper",
    "sg:orig_category":"Postkantoren",
    "sg:phone":"+32 57 42 41 60",
    "sg:postcode":"8900",
    "sg:province":"West-Vlaanderen",
    "wof:name":"De Post",
    "wof:placetype":"venue"
},
  "geometry": {"coordinates":[2.8878269196,50.8513641357],"type":"Point"}
}