{
  "type": "Feature",
  "properties": {
    "iso:country":"BE",
    "sg:address":"Rue Dieusaum\u00c9 9",
    "sg:city":"Chaudfontaine",
    "sg:orig_category":"Artsen and specialisten",
    "sg:phone":"+32 4 365 46 31",
    "sg:postcode":"4053",
    "sg:province":"Li\u00e8ge",
    "wof:name":"Jean-pierre Joset",
    "wof:placetype":"venue"
},
  "geometry": {"coordinates":[5.6087331772,50.5949630737],"type":"Point"}
}