{
  "type": "Feature",
  "properties": {
    "iso:country":"BE",
    "sg:address":"Kleine Gammel 35",
    "sg:city":"Rijkevorsel",
    "sg:orig_category":"Varkenskwekers",
    "sg:phone":"+32 3 314 67 03",
    "sg:postcode":"2310",
    "sg:province":"Antwerpen",
    "wof:name":"Jos Van Dijck",
    "wof:placetype":"venue"
},
  "geometry": {"coordinates":[4.7439360619,51.3604431152],"type":"Point"}
}