{
  "type": "Feature",
  "properties": {
    "addr:full":"Rue De Nivelles 80 Anderlues Hainaut 6150",
    "addr:housenumber":"80",
    "addr:postcode":"6150",
    "addr:street":"Rue De Nivelles",
    "iso:country":"BE",
    "sg:address":"Rue De Nivelles 80",
    "sg:city":"Anderlues",
    "sg:orig_category":"Advocaten and juridische adviseurs",
    "sg:phone":"+32 71 54 54 94",
    "sg:postcode":"6150",
    "sg:province":"Hainaut",
    "wof:name":"D. Vincent",
    "wof:placetype":"venue"
},
  "geometry": {"coordinates":[4.2753558159,50.4198074341],"type":"Point"}
}