{
  "type": "Feature",
  "properties": {
    "iso:country":"BE",
    "sg:address":"Place Xavier Neujean 35",
    "sg:city":"Li\u00c8ge",
    "sg:orig_category":"Enseignement maternel and primaire",
    "sg:phone":"+32 4 223 15 44",
    "sg:postcode":"4000",
    "sg:province":"Li\u00e8ge",
    "wof:name":"Ecole Primaire Libre",
    "wof:placetype":"venue"
},
  "geometry": {"coordinates":[5.5671219826,50.642578125],"type":"Point"}
}