{
  "type": "Feature",
  "properties": {
    "iso:country":"BE",
    "sg:address":"Rue De Trazegnies 40",
    "sg:city":"Li\u00e8ge 1 (sclessin)",
    "sg:classifiers":[
        {
            "category":"Health Services",
            "subcategory":"Dentist",
            "type":"Services"
        }
    ],
    "sg:phone":"+32 4 252 30 01",
    "sg:postcode":"4000",
    "sg:province":"Li\u00e8ge",
    "wof:name":"Raboni D",
    "wof:placetype":"venue"
},
  "geometry": {"coordinates":[5.5519909859,50.6134033203],"type":"Point"}
}