{
  "type": "Feature",
  "properties": {
    "addr:full":"Chauss\u00e9e De Tongres 317 Amay Li\u00e8ge 4540",
    "addr:housenumber":"317",
    "addr:postcode":"4540",
    "addr:street":"Chausse\u0301E De Tongres",
    "iso:country":"BE",
    "sg:address":"Chauss\u00e9e De Tongres 317",
    "sg:city":"Amay",
    "sg:classifiers":[
        {
            "category":"Health Services",
            "subcategory":"Health Practitioner",
            "type":"Services"
        }
    ],
    "sg:phone":"+32 85 31 40 20",
    "sg:postcode":"4540",
    "sg:province":"Li\u00e8ge",
    "sg:tags":[
        "therapist",
        "speech"
    ],
    "wof:name":"Delferier R",
    "wof:placetype":"venue"
},
  "geometry": {"coordinates":[5.3095932007,50.5654296875],"type":"Point"}
}