{
  "type": "Feature",
  "properties": {
    "iso:country":"BE",
    "sg:address":"Avenue Englebert 19",
    "sg:city":"Rixensart",
    "sg:orig_category":"Schoonheidssalons",
    "sg:phone":"+32 2 653 66 88",
    "sg:postcode":"1331",
    "sg:province":"Brabant Wallon",
    "wof:name":"Institut Maricq",
    "wof:placetype":"venue"
},
  "geometry": {"coordinates":[4.5354580879,50.7312583923],"type":"Point"}
}