{
  "type": "Feature",
  "properties": {
    "iso:country":"BE",
    "sg:address":"Brugsestraat 113 Box 1-2",
    "sg:city":"Oostkamp",
    "sg:classifiers":[
        {
            "category":"Health Services",
            "subcategory":"Nursing And Care Facility",
            "type":"Services"
        }
    ],
    "sg:phone":"+32 50 82 27 52",
    "sg:postcode":"8020",
    "sg:province":"West-Vlaanderen",
    "sg:tags":[
        "home"
    ],
    "wof:name":"De Maesschalck H",
    "wof:placetype":"venue"
},
  "geometry": {"coordinates":[3.2350599766,51.1533241272],"type":"Point"}
}