{
  "type": "Feature",
  "properties": {
    "iso:country":"BE",
    "sg:address":"Chauss\u00e9e Des Pr\u00e9s 30",
    "sg:city":"Li\u00e8ge 1 (li\u00e8ge 2)",
    "sg:classifiers":[
        {
            "category":"Building & Trades",
            "subcategory":"Pest Control",
            "type":"Services"
        }
    ],
    "sg:phone":"+32 4 344 21 08",
    "sg:postcode":"4020",
    "sg:province":"Li\u00e8ge",
    "sg:tags":[
        "machine",
        "vending"
    ],
    "wof:name":"Sodamat Europe",
    "wof:placetype":"venue"
},
  "geometry": {"coordinates":[5.5814208984,50.6413612366],"type":"Point"}
}