{
  "type": "Feature",
  "properties": {
    "addr:full":"Hippodroomstraat 45 Waregem West-Vlaanderen 8790",
    "addr:housenumber":"45",
    "addr:postcode":"8790",
    "addr:street":"Hippodroomstraat",
    "iso:country":"BE",
    "sg:address":"Hippodroomstraat 45",
    "sg:city":"Waregem",
    "sg:classifiers":[
        {
            "category":"Food & Beverages",
            "subcategory":"Supermarket",
            "type":"Retail Goods"
        }
    ],
    "sg:phone":"+32 56 61 16 83",
    "sg:postcode":"8790",
    "sg:province":"West-Vlaanderen",
    "sg:tags":[
        "department",
        "store"
    ],
    "wof:name":"Foodwar Nv",
    "wof:placetype":"venue"
},
  "geometry": {"coordinates":[3.4422540665,50.8869361877],"type":"Point"}
}