{
  "type": "Feature",
  "properties": {
    "addr:full":"Sparrendreef 6 Oud-turnhout Antwerpen 2360",
    "addr:housenumber":"6",
    "addr:postcode":"2360",
    "addr:street":"Sparrendreef",
    "iso:country":"BE",
    "sg:address":"Sparrendreef 6",
    "sg:city":"Oud-turnhout",
    "sg:classifiers":[
        {
            "category":"Professional",
            "subcategory":"Engineering",
            "type":"Services"
        }
    ],
    "sg:phone":"+32 14 45 40 35",
    "sg:postcode":"2360",
    "sg:province":"Antwerpen",
    "sg:tags":[
        "-"
    ],
    "wof:name":"I.r.p. Bvba",
    "wof:placetype":"venue"
},
  "geometry": {"coordinates":[5.025911808,51.31690979],"type":"Point"}
}