{
  "type": "Feature",
  "properties": {
    "iso:country":"BE",
    "sg:address":"Bredestraat 191-193",
    "sg:city":"Gent",
    "sg:orig_category":"Plantes and fleurs Gr",
    "sg:phone":"+32 9 251 14 57",
    "sg:postcode":"9041",
    "sg:province":"Oost-Vlaanderen",
    "wof:name":"De Wulf",
    "wof:placetype":"venue"
},
  "geometry": {"coordinates":[3.7783870697,51.1061973572],"type":"Point"}
}