{
  "type": "Feature",
  "properties": {
    "iso:country":"BE",
    "sg:address":"Rue Du Beau Vallon 5",
    "sg:city":"Verviers",
    "sg:classifiers":[
        {
            "category":"Arena",
            "subcategory":"Sports Club",
            "type":"Entertainment"
        }
    ],
    "sg:phone":"+32 87 22 37 84",
    "sg:postcode":"4800",
    "sg:province":"Li\u00e8ge",
    "sg:tags":[
        "de"
    ],
    "wof:name":"A.m.b.a. La Reid",
    "wof:placetype":"venue"
},
  "geometry": {"coordinates":[5.897600174,50.5753593445],"type":"Point"}
}