{
  "type": "Feature",
  "properties": {
    "addr:full":"Elf Novemberlaan 2 Menen West-Vlaanderen 8930",
    "addr:housenumber":"2",
    "addr:postcode":"8930",
    "addr:street":"Elf Novemberlaan",
    "iso:country":"BE",
    "sg:address":"Elf Novemberlaan 2",
    "sg:city":"Menen",
    "sg:orig_category":"Woningbouw",
    "sg:phone":"+32 56 41 65 06",
    "sg:postcode":"8930",
    "sg:province":"West-Vlaanderen",
    "wof:name":"Kristof Ghyselinck",
    "wof:placetype":"venue"
},
  "geometry": {"coordinates":[3.1659719944,50.7813682556],"type":"Point"}
}