{
  "type": "Feature",
  "properties": {
    "addr:full":"Rue De Pair 3 Clavier Li\u00e8ge 4560",
    "addr:housenumber":"3",
    "addr:postcode":"4560",
    "addr:street":"Rue De Pair",
    "iso:country":"BE",
    "sg:address":"Rue De Pair 3",
    "sg:city":"Clavier",
    "sg:orig_category":"Eleveurs de bovins",
    "sg:phone":"+32 86 36 70 44",
    "sg:postcode":"4560",
    "sg:province":"Li\u00e8ge",
    "wof:name":"Marcel Godefroid",
    "wof:placetype":"venue"
},
  "geometry": {"coordinates":[5.3980741501,50.4375801086],"type":"Point"}
}