{
  "type": "Feature",
  "properties": {
    "addr:full":"Plotersgracht 6 Gent Oost-Vlaanderen 9000",
    "addr:housenumber":"6",
    "addr:postcode":"9000",
    "addr:street":"Plotersgracht;Oost-Vlaanderen",
    "iso:country":"BE",
    "sg:address":"Plotersgracht 6",
    "sg:city":"Gent",
    "sg:classifiers":[
        {
            "category":"Restaurant",
            "type":"Food & Drink"
        }
    ],
    "sg:phone":"+32 9 225 05 25",
    "sg:postcode":"9000",
    "sg:province":"Oost-Vlaanderen",
    "wof:name":"De Vier Tafels",
    "wof:placetype":"venue"
},
  "geometry": {"coordinates":[3.7224199772,51.0577850342],"type":"Point"}
}