{
  "type": "Feature",
  "properties": {
    "addr:full":"Roodebeeklaan 117 Schaarbeek/schaerbeek Bruxelles-Capitale 1030",
    "addr:housenumber":"117",
    "addr:postcode":"1030",
    "addr:street":"Roodebeeklaan",
    "iso:country":"BE",
    "sg:address":"Roodebeeklaan 117",
    "sg:city":"Schaarbeek/schaerbeek",
    "sg:orig_category":"Herstellingen and onderhoud van auto's",
    "sg:phone":"+32 2 733 56 08",
    "sg:postcode":"1030",
    "sg:province":"Bruxelles-Capitale",
    "wof:name":"Garage Latrech",
    "wof:placetype":"venue"
},
  "geometry": {"coordinates":[4.4002461433,50.8483810425],"type":"Point"}
}