{
  "type": "Feature",
  "properties": {
    "iso:country":"BE",
    "sg:address":"Pantheonlaan 74",
    "sg:city":"Koekelberg/koekelberg",
    "sg:orig_category":"Banken and kredietinstellingen",
    "sg:phone":"+32 2 411 36 04",
    "sg:postcode":"1081",
    "sg:province":"Bruxelles-Capitale",
    "wof:name":"Bbl",
    "wof:placetype":"venue"
},
  "geometry": {"coordinates":[4.3181948662,50.8653450012],"type":"Point"}
}