{
  "type": "Feature",
  "properties": {
    "addr:full":"Bremtstraat 114 Affligem (teralfene) Vlaams-Brabant 1790",
    "addr:housenumber":"114",
    "addr:postcode":"1790",
    "addr:street":"Bremtstraat",
    "iso:country":"BE",
    "sg:address":"Bremtstraat 114",
    "sg:city":"Affligem (teralfene)",
    "sg:classifiers":[
        {
            "category":"Professional",
            "subcategory":"Management & Consulting",
            "type":"Services"
        }
    ],
    "sg:phone":"+32 53 68 35 40",
    "sg:postcode":"1790",
    "sg:province":"Vlaams-Brabant",
    "sg:tags":[
        "tax-consultants"
    ],
    "wof:name":"De Nul C",
    "wof:placetype":"venue"
},
  "geometry": {"coordinates":[4.1065487862,50.8944282532],"type":"Point"}
}