{
  "type": "Feature",
  "properties": {
    "iso:country":"BE",
    "sg:address":"Bleukenlaan 5",
    "sg:city":"Turnhout",
    "sg:classifiers":[
        {
            "category":"Shopping",
            "subcategory":"Discount & Variety Stores",
            "type":"Retail Goods"
        }
    ],
    "sg:phone":"+32 14 44 00 52",
    "sg:postcode":"2300",
    "sg:province":"Antwerpen",
    "sg:tags":[
        "warehouse",
        "-",
        "merchandise"
    ],
    "wof:name":"G M B",
    "wof:placetype":"venue"
},
  "geometry": {"coordinates":[4.915968895,51.2855911255],"type":"Point"}
}