{
  "type": "Feature",
  "properties": {
    "addr:full":"Avenue Des Arts 46 Brussel/bruxelles Bruxelles-Capitale 1000",
    "addr:housenumber":"46",
    "addr:postcode":"1000",
    "addr:street":"Avenue Des Arts;/",
    "iso:country":"BE",
    "sg:address":"Avenue Des Arts 46",
    "sg:city":"Brussel/bruxelles",
    "sg:orig_category":"S\u00e9lection de personnel and placement",
    "sg:phone":"+32 2 504 48 11",
    "sg:postcode":"1000",
    "sg:province":"Bruxelles-Capitale",
    "wof:name":"Bureau A.t. Kearney",
    "wof:placetype":"venue"
},
  "geometry": {"coordinates":[4.3673357964,50.8423538208],"type":"Point"}
}