{
  "type": "Feature",
  "properties": {
    "addr:full":"Heidepark 52 Dendermonde Oost-Vlaanderen 9200",
    "addr:housenumber":"52",
    "addr:postcode":"9200",
    "addr:street":"Heidepark;Oost-Vlaanderen",
    "iso:country":"BE",
    "sg:address":"Heidepark 52",
    "sg:city":"Dendermonde",
    "sg:orig_category":"Pleisterwerk",
    "sg:phone":"+32 52 21 87 43",
    "sg:postcode":"9200",
    "sg:province":"Oost-Vlaanderen",
    "wof:name":"Eddy De Paepe",
    "wof:placetype":"venue"
},
  "geometry": {"coordinates":[4.0596327782,51.0279693604],"type":"Point"}
}