{
  "type": "Feature",
  "properties": {
    "addr:full":"Winterland 37 Kortrijk (heule) West-Vlaanderen 8501",
    "addr:housenumber":"37",
    "addr:postcode":"8501",
    "addr:street":"Winterland",
    "iso:country":"BE",
    "sg:address":"Winterland 37",
    "sg:city":"Kortrijk (heule)",
    "sg:classifiers":[
        {
            "category":"Professional",
            "subcategory":"Computer Services",
            "type":"Services"
        }
    ],
    "sg:phone":"+32 56 35 84 66",
    "sg:postcode":"8501",
    "sg:province":"West-Vlaanderen",
    "sg:tags":[
        "-",
        "processing",
        "data",
        "software"
    ],
    "wof:name":"Deweirt S",
    "wof:placetype":"venue"
},
  "geometry": {"coordinates":[3.2264630795,50.8392105103],"type":"Point"}
}