{
  "type": "Feature",
  "properties": {
    "iso:country":"BE",
    "sg:address":"Rue De La Grande Campagne 40",
    "sg:city":"Boussu (hornu)",
    "sg:classifiers":[
        {
            "category":"Professional",
            "subcategory":"Engineering",
            "type":"Services"
        }
    ],
    "sg:phone":"+32 65 79 34 76",
    "sg:postcode":"7301",
    "sg:province":"Hainaut",
    "sg:tags":[
        "environmental",
        "technique",
        "-"
    ],
    "wof:name":"I-mage Consult",
    "wof:placetype":"venue"
},
  "geometry": {"coordinates":[3.8257451057,50.4362258911],"type":"Point"}
}