{
  "type": "Feature",
  "properties": {
    "addr:full":"Walstraat 14 Oostkamp West-Vlaanderen 8020",
    "addr:housenumber":"14",
    "addr:postcode":"8020",
    "addr:street":"Walstraat",
    "iso:country":"BE",
    "sg:address":"Walstraat 14",
    "sg:city":"Oostkamp",
    "sg:orig_category":"Installation de menuiserie en bois and plastique. Construction de maisons",
    "sg:phone":"+32 50 82 22 72",
    "sg:postcode":"8020",
    "sg:province":"West-Vlaanderen",
    "wof:name":"De Baecke Gebroeders",
    "wof:placetype":"venue"
},
  "geometry": {"coordinates":[3.2332949638,51.1539916992],"type":"Point"}
}