{
  "type": "Feature",
  "properties": {
    "addr:full":"Rue De L' \u00c9glise Wavre Brabant Wallon 1300",
    "addr:housenumber":"1300",
    "addr:street":"Rue De L ' E\u0301Glise",
    "iso:country":"BE",
    "sg:address":"Rue De L' \u00c9glise",
    "sg:city":"Wavre",
    "sg:orig_category":"Loodgieterij, verwarming and sanitaire installaties",
    "sg:phone":"+32 10 40 18 00",
    "sg:postcode":"1300",
    "sg:province":"Brabant Wallon",
    "wof:name":"Antoine Dufour Chauffage",
    "wof:placetype":"venue"
},
  "geometry": {"coordinates":[4.5814862251,50.7155609131],"type":"Point"}
}