{
  "type": "Feature",
  "properties": {
    "addr:full":"Stationsweg 22-25 Lede Oost-Vlaanderen 9340",
    "addr:housenumber":"22-25",
    "addr:postcode":"9340",
    "addr:street":"Stationsweg",
    "iso:country":"BE",
    "sg:address":"Stationsweg 22-25",
    "sg:city":"Lede",
    "sg:classifiers":[
        {
            "category":"Shopping",
            "subcategory":"Bicycles & Sporting Goods",
            "type":"Retail Goods"
        }
    ],
    "sg:phone":"+32 53 80 08 87",
    "sg:postcode":"9340",
    "sg:province":"Oost-Vlaanderen",
    "sg:tags":[
        "-"
    ],
    "wof:name":"Van Der Snickt E",
    "wof:placetype":"venue"
},
  "geometry": {"coordinates":[3.9806530476,50.9686584473],"type":"Point"}
}