{
  "type": "Feature",
  "properties": {
    "iso:country":"BE",
    "sg:address":"Euerardstraat 58b1",
    "sg:city":"Eeklo",
    "sg:classifiers":[
        {
            "category":"Building & Trades",
            "subcategory":"Plumbing",
            "type":"Services"
        }
    ],
    "sg:phone":"+32 9 378 09 81",
    "sg:postcode":"9900",
    "sg:province":"Oost-Vlaanderen",
    "sg:tags":[
        "diver",
        "commerce",
        "gr",
        "pour",
        "equipement"
    ],
    "wof:name":"Dat Zit",
    "wof:placetype":"venue"
},
  "geometry": {"coordinates":[3.569480896,51.1778411865],"type":"Point"}
}