{
  "type": "Feature",
  "properties": {
    "iso:country":"BE",
    "sg:address":"Gentpoortstraat 44b1",
    "sg:city":"Deinze",
    "sg:orig_category":"Formation and enseignement. Ordinateurs and \u00e9quipement informatique",
    "sg:phone":"+32 9 381 50 80",
    "sg:postcode":"9800",
    "sg:province":"Oost-Vlaanderen",
    "wof:name":"Soft Connection",
    "wof:placetype":"venue"
},
  "geometry": {"coordinates":[3.5291409492,50.9848632812],"type":"Point"}
}