{
  "type": "Feature",
  "properties": {
    "addr:full":"Haachtsesteenweg 262 Schaarbeek/schaerbeek Bruxelles-Capitale 1030",
    "addr:housenumber":"262",
    "addr:postcode":"1030",
    "addr:street":"Haachtsesteenweg",
    "iso:country":"BE",
    "sg:address":"Haachtsesteenweg 262",
    "sg:city":"Schaarbeek/schaerbeek",
    "sg:orig_category":"Rusthuizen and serviceflats",
    "sg:phone":"+32 2 215 76 53",
    "sg:postcode":"1030",
    "sg:province":"Bruxelles-Capitale",
    "wof:name":"New Home St.servais",
    "wof:placetype":"venue"
},
  "geometry": {"coordinates":[4.3730068207,50.863067627],"type":"Point"}
}