{
  "type": "Feature",
  "properties": {
    "addr:full":"Weerstandlaan 19 Antwerpen (hoboken) Antwerpen 2660",
    "addr:housenumber":"19",
    "addr:postcode":"2660",
    "addr:street":"Weerstandlaan",
    "iso:country":"BE",
    "sg:address":"Weerstandlaan 19",
    "sg:city":"Antwerpen (hoboken)",
    "sg:classifiers":[
        {
            "category":"Health Services",
            "subcategory":"Health Practitioner",
            "type":"Services"
        }
    ],
    "sg:phone":"+32 3 825 31 42",
    "sg:postcode":"2660",
    "sg:province":"Antwerpen",
    "sg:tags":[
        "physiotherapist"
    ],
    "wof:name":"Theugels Nancy",
    "wof:placetype":"venue"
},
  "geometry": {"coordinates":[4.3729100227,51.1877593994],"type":"Point"}
}