{
  "type": "Feature",
  "properties": {
    "iso:country":"BE",
    "sg:address":"Dorp 5",
    "sg:city":"Hamme (moerzeke)",
    "sg:classifiers":[
        {
            "category":"Health Services",
            "subcategory":"Nursing And Care Facility",
            "type":"Services"
        }
    ],
    "sg:phone":"+32 52 47 66 96",
    "sg:postcode":"9220",
    "sg:province":"Oost-Vlaanderen",
    "sg:tags":[
        "home"
    ],
    "wof:name":"Van Belle L",
    "wof:placetype":"venue"
},
  "geometry": {"coordinates":[4.1537737846,51.0629959106],"type":"Point"}
}