{
  "type": "Feature",
  "properties": {
    "iso:country":"BE",
    "sg:address":"Vilvoordsesteenweg 159ba",
    "sg:city":"Grimbergen",
    "sg:orig_category":"Herstellingen and onderhoud van auto's",
    "sg:phone":"+32 2 270 81 73",
    "sg:postcode":"1850",
    "sg:province":"Vlaams-Brabant",
    "wof:name":"Garage Metdenanckxt",
    "wof:placetype":"venue"
},
  "geometry": {"coordinates":[4.383272171,50.929397583],"type":"Point"}
}