{
  "type": "Feature",
  "properties": {
    "iso:country":"BE",
    "sg:address":"Bboulevard Lambermont 382",
    "sg:city":"Schaarbeek/schaerbeek",
    "sg:orig_category":"Agences de relations publiques. Agences de publicit\u00e9. Agences de marketing. Bureaux d'\u00e9tudes de marc",
    "sg:phone":"+32 2 242 80 44",
    "sg:postcode":"1030",
    "sg:province":"Bruxelles-Capitale",
    "wof:name":"Bureau Carr\u00c9 Jaune",
    "wof:placetype":"venue"
},
  "geometry": {"coordinates":[4.386882782,50.8629837036],"type":"Point"}
}