{
  "type": "Feature",
  "properties": {
    "addr:full":"Rue Du Houblon 63 Bruxelles Bruxelles-Capitale 1000",
    "addr:housenumber":"63",
    "addr:postcode":"1000",
    "addr:street":"Rue Du Houblon",
    "iso:country":"BE",
    "sg:address":"Rue Du Houblon 63",
    "sg:city":"Bruxelles",
    "sg:classifiers":[
        {
            "category":"Professional",
            "subcategory":"Advertising",
            "type":"Services"
        }
    ],
    "sg:phone":"+32 2 511 32 98",
    "sg:postcode":"1000",
    "sg:province":"Bruxelles-Capitale",
    "sg:tags":[
        "item",
        "-",
        "business",
        "gift",
        "promotional"
    ],
    "wof:name":"Promocado",
    "wof:placetype":"venue"
},
  "geometry": {"coordinates":[4.3412270546,50.8512802124],"type":"Point"}
}