{
  "type": "Feature",
  "properties": {
    "addr:full":"Rue De Lantign\u00e9 22 Durbuy (grandhan) Luxembourg 6940",
    "addr:housenumber":"22",
    "addr:postcode":"6940",
    "addr:street":"Rue De Lantigne\u0301",
    "iso:country":"BE",
    "sg:address":"Rue De Lantign\u00e9 22",
    "sg:city":"Durbuy (grandhan)",
    "sg:classifiers":[
        {
            "category":"Food & Beverages",
            "subcategory":"Liquor & Beverages",
            "type":"Retail Goods"
        }
    ],
    "sg:phone":"+32 86 21 44 12",
    "sg:postcode":"6940",
    "sg:province":"Luxembourg",
    "sg:tags":[
        "-",
        "spirit",
        "wine"
    ],
    "wof:name":"Vignes Nobles (les)",
    "wof:placetype":"venue"
},
  "geometry": {"coordinates":[5.4366278648,50.3379402161],"type":"Point"}
}