{
  "type": "Feature",
  "properties": {
    "addr:full":"Luitenant Lippenslaan 30 Antwerpen (borgerhout) Antwerpen 2140",
    "addr:housenumber":"30",
    "addr:postcode":"2140",
    "addr:street":"Luitenant Lippenslaan",
    "iso:country":"BE",
    "sg:address":"Luitenant Lippenslaan 30",
    "sg:city":"Antwerpen (borgerhout)",
    "sg:classifiers":[
        {
            "category":"Professional",
            "subcategory":"Business Services",
            "type":"Services"
        }
    ],
    "sg:phone":"+32 3 238 77 36",
    "sg:postcode":"2140",
    "sg:province":"Antwerpen",
    "sg:tags":[
        "bookkeeping"
    ],
    "wof:name":"Fiduciaire K.b.a",
    "wof:placetype":"venue"
},
  "geometry": {"coordinates":[4.4332199097,51.2137565613],"type":"Point"}
}