{
  "type": "Feature",
  "properties": {
    "addr:full":"Rue Fernand Musin 7 Awans Li\u00e8ge 4340",
    "addr:housenumber":"7",
    "addr:postcode":"4340",
    "addr:street":"Rue Fernand Musin",
    "iso:country":"BE",
    "sg:address":"Rue Fernand Musin 7",
    "sg:city":"Awans",
    "sg:classifiers":[
        {
            "category":"Shopping",
            "subcategory":"Clothing, Apparel, & Fashions",
            "type":"Retail Goods"
        }
    ],
    "sg:phone":"+32 4 263 53 36",
    "sg:postcode":"4340",
    "sg:province":"Li\u00e8ge",
    "sg:tags":[
        "-",
        "clothing",
        "child"
    ],
    "wof:name":"Magon Sa",
    "wof:placetype":"venue"
},
  "geometry": {"coordinates":[5.4653458595,50.6645736694],"type":"Point"}
}