{
  "type": "Feature",
  "properties": {
    "addr:full":"Zonnedauwstraat 15 Herentals Antwerpen 2200",
    "addr:housenumber":"15",
    "addr:postcode":"2200",
    "addr:street":"Zonnedauwstraat",
    "iso:country":"BE",
    "sg:address":"Zonnedauwstraat 15",
    "sg:city":"Herentals",
    "sg:orig_category":"Gespecialiseerde residenti\u00eble bouw",
    "sg:phone":"+32 14 21 70 93",
    "sg:postcode":"2200",
    "sg:province":"Antwerpen",
    "wof:name":"Theo Helsen",
    "wof:placetype":"venue"
},
  "geometry": {"coordinates":[4.8181872368,51.1668663025],"type":"Point"}
}