{
  "type": "Feature",
  "properties": {
    "addr:full":"Place Joseph Wauters 0 Lessines Hainaut 7860",
    "addr:housenumber":"0",
    "addr:postcode":"7860",
    "addr:street":"Place Joseph Wauters;Hainaut",
    "iso:country":"BE",
    "sg:address":"Place Joseph Wauters 0",
    "sg:city":"Lessines",
    "sg:orig_category":"Enseignement maternel and primaire",
    "sg:phone":"+32 68 33 58 88",
    "sg:postcode":"7860",
    "sg:province":"Hainaut",
    "wof:name":"Ecole Matern. Communale",
    "wof:placetype":"venue"
},
  "geometry": {"coordinates":[3.8275880814,50.7023544312],"type":"Point"}
}