{
  "type": "Feature",
  "properties": {
    "iso:country":"BE",
    "sg:address":"Dirk Martensstraat 7",
    "sg:city":"Brugge",
    "sg:orig_category":"V\u00e9hicules automobiles",
    "sg:phone":"+32 50 32 01 50",
    "sg:postcode":"8200",
    "sg:province":"West-Vlaanderen",
    "wof:name":"Garage Baes",
    "wof:placetype":"venue"
},
  "geometry": {"coordinates":[3.1974949837,51.2101173401],"type":"Point"}
}