{
  "type": "Feature",
  "properties": {
    "addr:full":"Rue L\u00c9on-castilhon 24 Arlon Luxembourg 6700",
    "addr:housenumber":"24",
    "addr:postcode":"6700",
    "addr:street":"Rue Le\u0301On-Castilhon",
    "iso:country":"BE",
    "sg:address":"Rue L\u00c9on-castilhon 24",
    "sg:city":"Arlon",
    "sg:orig_category":"Notarissen",
    "sg:phone":"+32 63 22 06 38",
    "sg:postcode":"6700",
    "sg:province":"Luxembourg",
    "wof:name":"C. Simon",
    "wof:placetype":"venue"
},
  "geometry": {"coordinates":[5.808909893,49.6842155457],"type":"Point"}
}