{
  "type": "Feature",
  "properties": {
    "addr:full":"Boulevard L\u00c9opold Ii 99 Brussel/bruxelles Bruxelles-Capitale 1080",
    "addr:housenumber":"99",
    "addr:postcode":"1080",
    "addr:street":"Boulevard Le\u0301Opold Ii;/",
    "iso:country":"BE",
    "sg:address":"Boulevard L\u00c9opold Ii 99",
    "sg:city":"Brussel/bruxelles",
    "sg:classifiers":[
        {
            "category":"Building & Trades",
            "subcategory":"Construction",
            "type":"Services"
        }
    ],
    "sg:phone":"+32 2 428 20 60",
    "sg:postcode":"1080",
    "sg:province":"Bruxelles-Capitale",
    "sg:tags":[
        "ventilation",
        "conditionn\u00e9",
        "air"
    ],
    "wof:name":"Dynelec",
    "wof:placetype":"venue"
},
  "geometry": {"coordinates":[4.3400387764,50.8608131409],"type":"Point"}
}