{
  "type": "Feature",
  "properties": {
    "addr:full":"Rue Des Bois 49 Rumes (taintignies) Hainaut 7618",
    "addr:housenumber":"49",
    "addr:postcode":"7618",
    "addr:street":"Rue Des Bois",
    "iso:country":"BE",
    "sg:address":"Rue Des Bois 49",
    "sg:city":"Rumes (taintignies)",
    "sg:classifiers":[
        {
            "category":"Bars & Pubs",
            "type":"Food & Drink"
        }
    ],
    "sg:phone":"+32 69 64 02 74",
    "sg:postcode":"7618",
    "sg:province":"Hainaut",
    "wof:name":"Maison Du Peuple",
    "wof:placetype":"venue"
},
  "geometry": {"coordinates":[3.3400719166,50.5460205078],"type":"Point"}
}