{
  "type": "Feature",
  "properties": {
    "iso:country":"BE",
    "sg:address":"Kerkstraat 13",
    "sg:city":"Lovendegem",
    "sg:orig_category":"Cr\u00e9meries",
    "sg:phone":"+32 9 372 60 86",
    "sg:postcode":"9920",
    "sg:province":"Oost-Vlaanderen",
    "wof:name":"'t Kaashuis",
    "wof:placetype":"venue"
},
  "geometry": {"coordinates":[3.6076459885,51.0947647095],"type":"Point"}
}