{
  "type": "Feature",
  "properties": {
    "iso:country":"BE",
    "sg:address":"Chauss\u00e9e De Tirlemont 51",
    "sg:city":"Wanze",
    "sg:classifiers":[
        {
            "category":"Bakery",
            "type":"Food & Drink"
        }
    ],
    "sg:phone":"+32 85 21 64 09",
    "sg:postcode":"4520",
    "sg:province":"Li\u00e8ge",
    "sg:tags":[
        "confectioner",
        "baker"
    ],
    "wof:name":"Saveurs De Melanie (aux)",
    "wof:placetype":"venue"
},
  "geometry": {"coordinates":[5.2198047638,50.5360374451],"type":"Point"}
}