{
  "type": "Feature",
  "properties": {
    "iso:country":"BE",
    "sg:address":"Rue Saint-roch 22 A",
    "sg:city":"Neufchateau",
    "sg:orig_category":"HUISBRANDOLIE",
    "sg:phone":"+32 61 27 70 30",
    "sg:postcode":"6840",
    "sg:province":"Luxembourg",
    "wof:name":"Bourgeois Albert Et Fils",
    "wof:placetype":"venue"
},
  "geometry": {"coordinates":[5.4342851639,49.8427276611],"type":"Point"}
}