{
  "type": "Feature",
  "properties": {
    "iso:country":"BE",
    "sg:address":"Blv Botanique",
    "sg:city":"Brussel/bruxelles",
    "sg:orig_category":"Bloemen and planten",
    "sg:phone":"+32 495 86 42 03",
    "sg:postcode":"1000",
    "sg:province":"Bruxelles-Capitale",
    "wof:name":"Fleurs Helene",
    "wof:placetype":"venue"
},
  "geometry": {"coordinates":[4.368065834,50.8522872925],"type":"Point"}
}