{
  "type": "Feature",
  "properties": {
    "addr:full":"Chauss\u00c9e De Helmet 288 Schaarbeek/schaerbeek Bruxelles-Capitale 1030",
    "addr:housenumber":"288",
    "addr:postcode":"1030",
    "addr:street":"Chausse\u0301E De Helmet",
    "iso:country":"BE",
    "sg:address":"Chauss\u00c9e De Helmet 288",
    "sg:city":"Schaarbeek/schaerbeek",
    "sg:orig_category":"Maroquinerie and articles de voyage",
    "sg:phone":"+32 2 216 26 95",
    "sg:postcode":"1030",
    "sg:province":"Bruxelles-Capitale",
    "wof:name":"Maison Vandenhoven",
    "wof:placetype":"venue"
},
  "geometry": {"coordinates":[4.3888750076,50.8746452332],"type":"Point"}
}