{
  "type": "Feature",
  "properties": {
    "addr:full":"Oude-kreekweg 25 Bredene West-Vlaanderen 8450",
    "addr:housenumber":"25",
    "addr:postcode":"8450",
    "addr:street":"Oude-Kreekweg",
    "iso:country":"BE",
    "sg:address":"Oude-kreekweg 25",
    "sg:city":"Bredene",
    "sg:classifiers":[
        {
            "category":"Building & Trades",
            "subcategory":"Construction",
            "type":"Services"
        }
    ],
    "sg:phone":"+32 59 33 15 63",
    "sg:postcode":"8450",
    "sg:province":"West-Vlaanderen",
    "sg:tags":[
        "insulation",
        "thermical",
        "work",
        "acoustical"
    ],
    "wof:name":"Anseeuw J",
    "wof:placetype":"venue"
},
  "geometry": {"coordinates":[2.9688150883,51.222568512],"type":"Point"}
}