{
  "type": "Feature",
  "properties": {
    "iso:country":"BE",
    "sg:address":"Van Praetlei 6",
    "sg:city":"Antwerpen (merksem)",
    "sg:classifiers":[
        {
            "category":"Professional",
            "subcategory":"Management & Consulting",
            "type":"Services"
        }
    ],
    "sg:phone":"+32 3 644 35 82",
    "sg:postcode":"2170",
    "sg:province":"Antwerpen",
    "sg:tags":[
        "-",
        "processing",
        "data",
        "consultant"
    ],
    "wof:name":"Nexar",
    "wof:placetype":"venue"
},
  "geometry": {"coordinates":[4.4554691315,51.2497673035],"type":"Point"}
}