{
  "type": "Feature",
  "properties": {
    "addr:full":"Valender 32 Amel/ambleve Li\u00e8ge 4771",
    "addr:housenumber":"32",
    "addr:postcode":"4771",
    "addr:street":"Valender",
    "iso:country":"BE",
    "sg:address":"Valender 32",
    "sg:city":"Amel/ambleve",
    "sg:orig_category":"Rundveehouders",
    "sg:phone":"+32 80 34 94 05",
    "sg:postcode":"4771",
    "sg:province":"Li\u00e8ge",
    "wof:name":"Peter Schroeder",
    "wof:placetype":"venue"
},
  "geometry": {"coordinates":[6.2186770439,50.3613700867],"type":"Point"}
}