{
  "type": "Feature",
  "properties": {
    "iso:country":"BE",
    "sg:address":"Rue De Luttre 44",
    "sg:city":"Courcelles",
    "sg:orig_category":"Paramedische behandelingen",
    "sg:phone":"+32 71 45 47 13",
    "sg:postcode":"6181",
    "sg:province":"Hainaut",
    "wof:name":"B. Dalla Bella",
    "wof:placetype":"venue"
},
  "geometry": {"coordinates":[4.3359031677,50.4907150269],"type":"Point"}
}