{
  "type": "Feature",
  "properties": {
    "iso:country":"BE",
    "sg:address":"Gildelaan 38",
    "sg:city":"Genk",
    "sg:orig_category":"Leisure articles",
    "sg:phone":"+32 89 30 77 87",
    "sg:postcode":"3600",
    "sg:province":"Limburg",
    "wof:name":"Creane",
    "wof:placetype":"venue"
},
  "geometry": {"coordinates":[5.4843158722,50.9628715515],"type":"Point"}
}