{
  "type": "Feature",
  "properties": {
    "iso:country":"BE",
    "sg:address":"Jean Jaur\u00c8slaan 32",
    "sg:city":"Moeskroen/mouscron",
    "sg:orig_category":"Artsen and specialisten",
    "sg:phone":"+32 56 34 70 30",
    "sg:postcode":"7700",
    "sg:province":"Hainaut",
    "wof:name":"Alain Poucet",
    "wof:placetype":"venue"
},
  "geometry": {"coordinates":[3.2323200703,50.7400932312],"type":"Point"}
}