{
  "type": "Feature",
  "properties": {
    "addr:full":"Sint-michielsstraat 13 Gent Oost-Vlaanderen 9000",
    "addr:housenumber":"13",
    "addr:postcode":"9000",
    "addr:street":"Sint-Michielsstraat;Oost-Vlaanderen",
    "iso:country":"BE",
    "sg:address":"Sint-michielsstraat 13",
    "sg:city":"Gent",
    "sg:orig_category":"Enseignement maternel and primaire. Enseignement secondaire g\u00e9n\u00e9ral",
    "sg:phone":"+32 9 223 16 57",
    "sg:postcode":"9000",
    "sg:province":"Oost-Vlaanderen",
    "wof:name":"Vrije Lagere School",
    "wof:placetype":"venue"
},
  "geometry": {"coordinates":[3.7179720402,51.053894043],"type":"Point"}
}