{
  "type": "Feature",
  "properties": {
    "addr:full":"Vorsterielaan 30 Watermaal-bosvoorde/watermael-boitsfort Bruxelles-Capitale 1170",
    "addr:housenumber":"30",
    "addr:postcode":"1170",
    "addr:street":"Vorsterielaan",
    "iso:country":"BE",
    "sg:address":"Vorsterielaan 30",
    "sg:city":"Watermaal-bosvoorde/watermael-boitsfort",
    "sg:orig_category":"Benzinestations and brandstoffen",
    "sg:phone":"+32 2 673 74 46",
    "sg:postcode":"1170",
    "sg:province":"Bruxelles-Capitale",
    "wof:name":"Shell",
    "wof:placetype":"venue"
},
  "geometry": {"coordinates":[4.4203100204,50.7901802063],"type":"Point"}
}