{
  "type": "Feature",
  "properties": {
    "iso:country":"BE",
    "sg:address":"Stadensteenweg 42",
    "sg:city":"Langemark-poelkapelle",
    "sg:orig_category":"Woningbouw",
    "sg:phone":"+32 57 48 53 58",
    "sg:postcode":"8920",
    "sg:province":"West-Vlaanderen",
    "wof:name":"Geert Bouttelisier",
    "wof:placetype":"venue"
},
  "geometry": {"coordinates":[2.9650299549,50.9427490234],"type":"Point"}
}