{
  "type": "Feature",
  "properties": {
    "iso:country":"BE",
    "sg:address":"Walleweg 137",
    "sg:city":"Kortrijk",
    "sg:orig_category":"Dameskledingzaken",
    "sg:phone":"+32 56 20 21 08",
    "sg:postcode":"8500",
    "sg:province":"West-Vlaanderen",
    "wof:name":"Marie-lies",
    "wof:placetype":"venue"
},
  "geometry": {"coordinates":[3.2699520588,50.7912101746],"type":"Point"}
}