{
  "type": "Feature",
  "properties": {
    "iso:country":"BE",
    "sg:address":"Chauss\u00c9e De March\u00c9 443",
    "sg:city":"Namur",
    "sg:orig_category":"Entretien and r\u00e9parations de voitures",
    "sg:phone":"+32 81 30 19 17",
    "sg:postcode":"5101",
    "sg:province":"Namur",
    "wof:name":"Eurocam",
    "wof:placetype":"venue"
},
  "geometry": {"coordinates":[4.8961949348,50.44789505],"type":"Point"}
}