{
  "type": "Feature",
  "properties": {
    "addr:full":"Avenue Georges Henri 225 Bruxelles (woluwe-saint-lambert) Bruxelles-Capitale 1200",
    "addr:housenumber":"225",
    "addr:postcode":"1200",
    "addr:street":"Avenue Georges Henri",
    "iso:country":"BE",
    "sg:address":"Avenue Georges Henri 225",
    "sg:city":"Bruxelles (woluwe-saint-lambert)",
    "sg:classifiers":[
        {
            "category":"Shopping",
            "subcategory":"Crafts & Fabrics",
            "type":"Retail Goods"
        }
    ],
    "sg:phone":"+32 2 771 12 77",
    "sg:postcode":"1200",
    "sg:province":"Bruxelles-Capitale",
    "sg:tags":[
        "hi-fi",
        "equipment",
        "stereophonic",
        "-"
    ],
    "wof:name":"Verlinden & Fils",
    "wof:placetype":"venue"
},
  "geometry": {"coordinates":[4.4162940979,50.8446159363],"type":"Point"}
}