{
  "type": "Feature",
  "properties": {
    "iso:country":"BE",
    "sg:address":"Aarschotsebaan 10",
    "sg:city":"Kampenhout",
    "sg:orig_category":"HUISBRANDOLIE",
    "sg:phone":"+32 16 65 16 63",
    "sg:postcode":"1910",
    "sg:province":"Vlaams-Brabant",
    "wof:name":"Victor Aelbrecht",
    "wof:placetype":"venue"
},
  "geometry": {"coordinates":[4.5663361549,50.941368103],"type":"Point"}
}