{
  "type": "Feature",
  "properties": {
    "addr:full":"Molenput 16 Kuurne West-Vlaanderen 8520",
    "addr:housenumber":"16",
    "addr:postcode":"8520",
    "addr:street":"Molenput",
    "iso:country":"BE",
    "sg:address":"Molenput 16",
    "sg:city":"Kuurne",
    "sg:classifiers":[
        {
            "category":"Insurance",
            "subcategory":"Life Insurance",
            "type":"Services"
        }
    ],
    "sg:phone":"+32 56 71 91 11",
    "sg:postcode":"8520",
    "sg:province":"West-Vlaanderen",
    "sg:tags":[
        "assurance"
    ],
    "wof:name":"Fa. Serroen",
    "wof:placetype":"venue"
},
  "geometry": {"coordinates":[3.2738740444,50.8662147522],"type":"Point"}
}