{
  "type": "Feature",
  "properties": {
    "addr:full":"Petite Place 2 Peruwelz Hainaut 7600",
    "addr:housenumber":"2",
    "addr:postcode":"7600",
    "addr:street":"Petite Place;Hainaut",
    "iso:country":"BE",
    "sg:address":"Petite Place 2",
    "sg:city":"Peruwelz",
    "sg:orig_category":"Banques and organismes de cr\u00e9dit",
    "sg:phone":"+32 69 77 62 73",
    "sg:postcode":"7600",
    "sg:province":"Hainaut",
    "wof:name":"Cr\u00c9dit Professionnel",
    "wof:placetype":"venue"
},
  "geometry": {"coordinates":[3.5908699036,50.5080947876],"type":"Point"}
}