{
  "type": "Feature",
  "properties": {
    "addr:full":"Dendermondsesteenweg 61 Lebbeke Oost-Vlaanderen 9280",
    "addr:housenumber":"61",
    "addr:postcode":"9280",
    "addr:street":"Dendermondsesteenweg",
    "iso:country":"BE",
    "sg:address":"Dendermondsesteenweg 61",
    "sg:city":"Lebbeke",
    "sg:classifiers":[
        {
            "category":"Home & Garden",
            "subcategory":"Home Furnishings",
            "type":"Retail Goods"
        }
    ],
    "sg:phone":"+32 52 41 15 73",
    "sg:postcode":"9280",
    "sg:province":"Oost-Vlaanderen",
    "sg:tags":[
        "curtain",
        "-",
        "fixture"
    ],
    "wof:name":"Woonidee-moonen C Bvba",
    "wof:placetype":"venue"
},
  "geometry": {"coordinates":[4.1252999306,51.0035896301],"type":"Point"}
}