{
  "type": "Feature",
  "properties": {
    "iso:country":"BE",
    "sg:address":"Blauwstraat 40",
    "sg:city":"Boom",
    "sg:classifiers":[
        {
            "category":"Bakery",
            "type":"Food & Drink"
        }
    ],
    "sg:phone":"+32 3 230 30 64",
    "sg:postcode":"2850",
    "sg:province":"Antwerpen",
    "sg:tags":[
        "confectioner",
        "baker"
    ],
    "wof:name":"Sherat",
    "wof:placetype":"venue"
},
  "geometry": {"coordinates":[4.3677430153,51.0864753723],"type":"Point"}
}