{
  "type": "Feature",
  "properties": {
    "addr:full":"Koolmijnlaan 139 Houthalen-helchteren Limburg 3530",
    "addr:housenumber":"139",
    "addr:postcode":"3530",
    "addr:street":"Koolmijnlaan",
    "iso:country":"BE",
    "sg:address":"Koolmijnlaan 139",
    "sg:city":"Houthalen-helchteren",
    "sg:orig_category":"Installation de menuiserie m\u00e9tallique",
    "sg:phone":"+32 11 72 52 26",
    "sg:postcode":"3530",
    "sg:province":"Limburg",
    "wof:name":"Fa. Bay Style",
    "wof:placetype":"venue"
},
  "geometry": {"coordinates":[5.3888168335,51.0189552307],"type":"Point"}
}