{
  "type": "Feature",
  "properties": {
    "addr:full":"Wandelingstraat 38 Kortrijk West-Vlaanderen 8500",
    "addr:housenumber":"38",
    "addr:postcode":"8500",
    "addr:street":"Wandelingstraat",
    "iso:country":"BE",
    "sg:address":"Wandelingstraat 38",
    "sg:city":"Kortrijk",
    "sg:orig_category":"Eclairage et \u00e9quipements du foyer",
    "sg:phone":"+32 56 20 48 35",
    "sg:postcode":"8500",
    "sg:province":"West-Vlaanderen",
    "wof:name":"'t Cadeautje",
    "wof:placetype":"venue"
},
  "geometry": {"coordinates":[3.276184082,50.8263282776],"type":"Point"}
}