{
  "type": "Feature",
  "properties": {
    "iso:country":"BE",
    "sg:address":"Vaartlaan 29",
    "sg:city":"Brecht",
    "sg:orig_category":"Loodgieterij, verwarming and sanitaire installaties",
    "sg:phone":"+32 3 636 19 24",
    "sg:postcode":"2960",
    "sg:province":"Antwerpen",
    "wof:name":"Van Looveren-willems",
    "wof:placetype":"venue"
},
  "geometry": {"coordinates":[4.6441478729,51.3470077515],"type":"Point"}
}