{
  "type": "Feature",
  "properties": {
    "iso:country":"BE",
    "sg:address":"Oudestraat 7",
    "sg:city":"Bilzen",
    "sg:orig_category":"Installation \u00e9lectrique r\u00e9sidentielle",
    "sg:phone":"+32 89 50 35 41",
    "sg:postcode":"3740",
    "sg:province":"Limburg",
    "wof:name":"B. Jaspers",
    "wof:placetype":"venue"
},
  "geometry": {"coordinates":[5.4664940834,50.8950195312],"type":"Point"}
}