{
  "type": "Feature",
  "properties": {
    "addr:full":"Rue De Menin 20-12f Mouscron Hainaut 7700",
    "addr:housenumber":"20-12f",
    "addr:postcode":"7700",
    "addr:street":"Rue De Menin",
    "iso:country":"BE",
    "sg:address":"Rue De Menin 20-12f",
    "sg:city":"Mouscron",
    "sg:classifiers":[
        {
            "category":"Insurance",
            "subcategory":"Insurance Agent",
            "type":"Services"
        }
    ],
    "sg:phone":"+32 56 84 68 53",
    "sg:postcode":"7700",
    "sg:province":"Hainaut",
    "sg:tags":[
        "broker"
    ],
    "wof:name":"Assurances De Groote",
    "wof:placetype":"venue"
},
  "geometry": {"coordinates":[3.2158401012,50.7460212708],"type":"Point"}
}