{
  "type": "Feature",
  "properties": {
    "iso:country":"BE",
    "sg:address":"Sint-andriessteenweg 9",
    "sg:city":"Zottegem",
    "sg:orig_category":"Cr\u00e8ches and garderies d'enfants",
    "sg:phone":"+32 9 360 21 55",
    "sg:postcode":"9620",
    "sg:province":"Oost-Vlaanderen",
    "wof:name":"Kribbe Bambi",
    "wof:placetype":"venue"
},
  "geometry": {"coordinates":[3.8021988869,50.866809845],"type":"Point"}
}