{
  "type": "Feature",
  "properties": {
    "addr:full":"Bree\u00ebrweg 52 Bocholt Limburg 3950",
    "addr:housenumber":"52",
    "addr:postcode":"3950",
    "addr:street":"Breee\u0308Rweg",
    "iso:country":"BE",
    "sg:address":"Bree\u00ebrweg 52",
    "sg:city":"Bocholt",
    "sg:classifiers":[
        {
            "category":"Autos & Motor Vehicles",
            "subcategory":"Fuel & Gas Station",
            "type":"Retail Goods"
        }
    ],
    "sg:phone":"+32 89 46 54 21",
    "sg:postcode":"3950",
    "sg:province":"Limburg",
    "wof:name":"Koper-metsemakers Bvba",
    "wof:placetype":"venue"
},
  "geometry": {"coordinates":[5.5853228569,51.1669502258],"type":"Point"}
}