{
  "type": "Feature",
  "properties": {
    "iso:country":"BE",
    "sg:address":"Geelsebaan 110",
    "sg:city":"Kasterlee",
    "sg:classifiers":[
        {
            "category":"Manufacturing",
            "subcategory":"Motor Vehicles & Parts",
            "type":"Manufacturing & Wholesale Goods"
        }
    ],
    "sg:phone":"+32 14 85 10 85",
    "sg:postcode":"2460",
    "sg:province":"Antwerpen",
    "sg:tags":[
        "machine",
        "-",
        "indivisible",
        "transport"
    ],
    "wof:name":"Inter Exceptionnel Bvba",
    "wof:placetype":"venue"
},
  "geometry": {"coordinates":[4.9728369713,51.2279853821],"type":"Point"}
}