{
  "type": "Feature",
  "properties": {
    "iso:country":"BE",
    "sg:address":"Rue De Neufch\u00e2teau 16",
    "sg:city":"Bastogne",
    "sg:classifiers":[
        {
            "category":"Personal",
            "subcategory":"Beauty Salon",
            "type":"Services"
        }
    ],
    "sg:phone":"+32 61 21 81 76",
    "sg:postcode":"6600",
    "sg:province":"Luxembourg",
    "wof:name":"Amazone Institut",
    "wof:placetype":"venue"
},
  "geometry": {"coordinates":[5.7142357826,49.9995765686],"type":"Point"}
}