{
  "type": "Feature",
  "properties": {
    "addr:full":"Wippelgemdorp 9 Evergem Oost-Vlaanderen 9940",
    "addr:housenumber":"9",
    "addr:postcode":"9940",
    "addr:street":"Wippelgemdorp;Oost-Vlaanderen",
    "iso:country":"BE",
    "sg:address":"Wippelgemdorp 9",
    "sg:city":"Evergem",
    "sg:classifiers":[
        {
            "category":"Food & Beverages",
            "subcategory":"Meat & Fish",
            "type":"Retail Goods"
        }
    ],
    "sg:phone":"+32 9 357 21 41",
    "sg:postcode":"9940",
    "sg:province":"Oost-Vlaanderen",
    "sg:tags":[
        "vi",
        "zeevruchten"
    ],
    "wof:name":"'t Visboetiekje",
    "wof:placetype":"venue"
},
  "geometry": {"coordinates":[3.7320520878,51.1387214661],"type":"Point"}
}