{
  "type": "Feature",
  "properties": {
    "addr:full":"Nijvendries 28 Sint-amands Antwerpen 2890",
    "addr:housenumber":"28",
    "addr:postcode":"2890",
    "addr:street":"Nijvendries",
    "iso:country":"BE",
    "sg:address":"Nijvendries 28",
    "sg:city":"Sint-amands",
    "sg:classifiers":[
        {
            "category":"Professional",
            "subcategory":"Accounting & Tax Preparation",
            "type":"Services"
        }
    ],
    "sg:phone":"+32 3 889 64 71",
    "sg:postcode":"2890",
    "sg:province":"Antwerpen",
    "sg:tags":[
        "accountant"
    ],
    "wof:name":"Marc Van Gucht",
    "wof:placetype":"venue"
},
  "geometry": {"coordinates":[4.2375512123,51.0588226318],"type":"Point"}
}