{
  "type": "Feature",
  "properties": {
    "addr:full":"Perksestraat 142 Vilvoorde Vlaams-Brabant 1800",
    "addr:housenumber":"142",
    "addr:postcode":"1800",
    "addr:street":"Perksestraat",
    "iso:country":"BE",
    "sg:address":"Perksestraat 142",
    "sg:city":"Vilvoorde",
    "sg:classifiers":[
        {
            "category":"Bakery",
            "type":"Food & Drink"
        }
    ],
    "sg:phone":"+32 2 251 14 54",
    "sg:postcode":"1800",
    "sg:province":"Vlaams-Brabant",
    "sg:tags":[
        "confectioner",
        "baker"
    ],
    "wof:name":"Sint Antonius",
    "wof:placetype":"venue"
},
  "geometry": {"coordinates":[4.4396300316,50.928440094],"type":"Point"}
}