{
  "type": "Feature",
  "properties": {
    "iso:country":"BE",
    "sg:address":"Nieuwstraat 10",
    "sg:city":"Oud-turnhout",
    "sg:orig_category":"Loodgieterij, verwarming and sanitaire installaties",
    "sg:phone":"+32 14 42 21 50",
    "sg:postcode":"2360",
    "sg:province":"Antwerpen",
    "wof:name":"Eijkmans",
    "wof:placetype":"venue"
},
  "geometry": {"coordinates":[4.9723157883,51.3379631042],"type":"Point"}
}