{
  "type": "Feature",
  "properties": {
    "iso:country":"BE",
    "sg:address":"Rue Lanterne Magique 14",
    "sg:city":"Ottignies-louvain-la-neuve (louvain-la-neuve)",
    "sg:classifiers":[
        {
            "category":"Social Services",
            "subcategory":"Job Training",
            "type":"Services"
        }
    ],
    "sg:phone":"+32 10 47 27 43",
    "sg:postcode":"1348",
    "sg:province":"Brabant Wallon",
    "sg:tags":[
        "personnel"
    ],
    "wof:name":"Cecom",
    "wof:placetype":"venue"
},
  "geometry": {"coordinates":[4.612074852,50.6685676575],"type":"Point"}
}