{
  "type": "Feature",
  "properties": {
    "iso:country":"BE",
    "sg:address":"Markt 59",
    "sg:city":"Lokeren",
    "sg:orig_category":"Dameskledingzaken",
    "sg:phone":"+32 9 348 27 92",
    "sg:postcode":"9160",
    "sg:province":"Oost-Vlaanderen",
    "wof:name":"Bruno Antonini",
    "wof:placetype":"venue"
},
  "geometry": {"coordinates":[3.9864850044,51.1047401428],"type":"Point"}
}