{
  "type": "Feature",
  "properties": {
    "addr:full":"Rue Jean-hubert Cavens 35 Malmedy Li\u00e8ge 4960",
    "addr:housenumber":"35",
    "addr:postcode":"4960",
    "addr:street":"Rue Jean-Hubert Cavens",
    "iso:country":"BE",
    "sg:address":"Rue Jean-hubert Cavens 35",
    "sg:city":"Malmedy",
    "sg:classifiers":[
        {
            "category":"Personal",
            "subcategory":"Beauty Salon",
            "type":"Services"
        }
    ],
    "sg:phone":"+32 80 33 71 47",
    "sg:postcode":"4960",
    "sg:province":"Li\u00e8ge",
    "sg:tags":[
        "de",
        "coiffure"
    ],
    "wof:name":"Coiffure Raymond",
    "wof:placetype":"venue"
},
  "geometry": {"coordinates":[6.0246658325,50.4273529053],"type":"Point"}
}