{
  "type": "Feature",
  "properties": {
    "addr:full":"Weg Naar As 121ba20 Genk Limburg 3600",
    "addr:postcode":"121ba20;3600",
    "addr:street":"Weg Naar As",
    "iso:country":"BE",
    "sg:address":"Weg Naar As 121ba20",
    "sg:city":"Genk",
    "sg:orig_category":"M\u00e9decins and sp\u00e9cialistes",
    "sg:phone":"+32 89 36 13 07",
    "sg:postcode":"3600",
    "sg:province":"Limburg",
    "wof:name":"Bob Pulings",
    "wof:placetype":"venue"
},
  "geometry": {"coordinates":[5.5123472214,50.9704780579],"type":"Point"}
}