{
  "type": "Feature",
  "properties": {
    "iso:country":"BE",
    "sg:address":"Strandlaan 383",
    "sg:city":"Koksijde",
    "sg:classifiers":[
        {
            "category":"Bars & Pubs",
            "type":"Food & Drink"
        }
    ],
    "sg:phone":"+32 58 51 82 57",
    "sg:postcode":"8670",
    "sg:province":"West-Vlaanderen",
    "sg:tags":[
        "tavern"
    ],
    "wof:name":"Belle Vue",
    "wof:placetype":"venue"
},
  "geometry": {"coordinates":[2.6105499268,51.1115913391],"type":"Point"}
}