{
  "type": "Feature",
  "properties": {
    "iso:country":"BE",
    "sg:address":"Plankenstraat 115",
    "sg:city":"Dilbeek",
    "sg:orig_category":"Instituts de beaut\u00e9",
    "sg:phone":"+32 2 569 73 35",
    "sg:postcode":"1701",
    "sg:province":"Vlaams-Brabant",
    "wof:name":"Andree Van Den Hove",
    "wof:placetype":"venue"
},
  "geometry": {"coordinates":[4.2216920853,50.838558197],"type":"Point"}
}