{
  "type": "Feature",
  "properties": {
    "addr:full":"Kimpestraat 37 Brakel Oost-Vlaanderen 9660",
    "addr:housenumber":"37",
    "addr:postcode":"9660",
    "addr:street":"Kimpestraat",
    "iso:country":"BE",
    "sg:address":"Kimpestraat 37",
    "sg:city":"Brakel",
    "sg:orig_category":"Woningbouw",
    "sg:phone":"+32 55 42 17 30",
    "sg:postcode":"9660",
    "sg:province":"Oost-Vlaanderen",
    "wof:name":"Albert De Staercke",
    "wof:placetype":"venue"
},
  "geometry": {"coordinates":[3.7266979218,50.79347229],"type":"Point"}
}