{
  "type": "Feature",
  "properties": {
    "iso:country":"BE",
    "sg:address":"Grand'rue 31",
    "sg:city":"Manage",
    "sg:orig_category":"Brood, gebak and snoepgoed",
    "sg:phone":"+32 64 54 12 38",
    "sg:postcode":"7170",
    "sg:province":"Hainaut",
    "wof:name":"Edgard Valentin",
    "wof:placetype":"venue"
},
  "geometry": {"coordinates":[4.2365279198,50.5037574768],"type":"Point"}
}