{
  "type": "Feature",
  "properties": {
    "iso:country":"BE",
    "sg:address":"Sasboslaan 3",
    "sg:city":"Kortrijk (bellegem)",
    "sg:classifiers":[
        {
            "category":"Professional",
            "subcategory":"Art Services",
            "type":"Services"
        }
    ],
    "sg:phone":"+32 56 21 45 29",
    "sg:postcode":"8510",
    "sg:province":"West-Vlaanderen",
    "sg:tags":[
        "graphic",
        "designer"
    ],
    "wof:name":"Beulcke I",
    "wof:placetype":"venue"
},
  "geometry": {"coordinates":[3.3011410236,50.7650527954],"type":"Point"}
}