{
  "type": "Feature",
  "properties": {
    "addr:full":"Avenue Des Jardins 64b2 Schaarbeek/schaerbeek Bruxelles-Capitale 1030",
    "addr:housenumber":"64b2",
    "addr:postcode":"1030",
    "addr:street":"Avenue Des Jardins",
    "iso:country":"BE",
    "sg:address":"Avenue Des Jardins 64b2",
    "sg:city":"Schaarbeek/schaerbeek",
    "sg:orig_category":"Traitements param\u00e9dicaux",
    "sg:phone":"+32 2 726 14 88",
    "sg:postcode":"1030",
    "sg:province":"Bruxelles-Capitale",
    "wof:name":"Podologue Baltus",
    "wof:placetype":"venue"
},
  "geometry": {"coordinates":[4.4007549286,50.8615760803],"type":"Point"}
}