{
  "type": "Feature",
  "properties": {
    "iso:country":"BE",
    "sg:address":"Avenue Reine Astrid 177-189",
    "sg:city":"Verviers (heusy)",
    "sg:classifiers":[
        {
            "category":"Home & Garden",
            "subcategory":"Home Furnishings",
            "type":"Retail Goods"
        }
    ],
    "sg:postcode":"4802",
    "sg:province":"Li\u00e8ge",
    "sg:tags":[
        "-",
        "freezer",
        "refrigerator"
    ],
    "wof:name":"Gaspar G",
    "wof:placetype":"venue"
},
  "geometry": {"coordinates":[5.8872442245,50.5832939148],"type":"Point"}
}