{
  "type": "Feature",
  "properties": {
    "iso:country":"BE",
    "sg:address":"Driesstraat 10",
    "sg:city":"Bornem",
    "sg:orig_category":"Enseignement maternel and primaire",
    "sg:phone":"+32 3 889 44 74",
    "sg:postcode":"2880",
    "sg:province":"Antwerpen",
    "wof:name":"Vrije Lagere School",
    "wof:placetype":"venue"
},
  "geometry": {"coordinates":[4.2370991707,51.1000671387],"type":"Point"}
}