{
  "type": "Feature",
  "properties": {
    "addr:full":"Leuvensesteenweg 123 Mechelen Antwerpen 2800",
    "addr:housenumber":"123",
    "addr:postcode":"2800",
    "addr:street":"Leuvensesteenweg",
    "iso:country":"BE",
    "sg:address":"Leuvensesteenweg 123",
    "sg:city":"Mechelen",
    "sg:classifiers":[
        {
            "category":"Communications",
            "subcategory":"Film & Video Production",
            "type":"Services"
        }
    ],
    "sg:phone":"+32 15 41 98 18",
    "sg:postcode":"2800",
    "sg:province":"Antwerpen",
    "sg:tags":[
        "hiring",
        "-"
    ],
    "wof:name":"Videoclub Sound & Vision",
    "wof:placetype":"venue"
},
  "geometry": {"coordinates":[4.4939799309,51.0189628601],"type":"Point"}
}