{
  "type": "Feature",
  "properties": {
    "addr:full":"Stationsstraat 95 Londerzeel Vlaams-Brabant 1840",
    "addr:housenumber":"95",
    "addr:postcode":"1840",
    "addr:street":"Stationsstraat",
    "iso:country":"BE",
    "sg:address":"Stationsstraat 95",
    "sg:city":"Londerzeel",
    "sg:orig_category":"Mat\u00e9riel de T\u00e9l\u00e9communication. Electrom\u00e9nager, t\u00e9l\u00e9visions and radios",
    "sg:phone":"+32 52 30 96 18",
    "sg:postcode":"1840",
    "sg:province":"Vlaams-Brabant",
    "wof:name":"Selexion Broothaerts",
    "wof:placetype":"venue"
},
  "geometry": {"coordinates":[4.3004150391,51.007850647],"type":"Point"}
}