{
  "type": "Feature",
  "properties": {
    "iso:country":"BE",
    "sg:address":"Avenue De Bouillon 150",
    "sg:city":"Libramont-chevigny",
    "sg:orig_category":"V\u00e9hicules automobiles",
    "sg:phone":"+32 61 22 31 31",
    "sg:postcode":"6800",
    "sg:province":"Luxembourg",
    "wof:name":"Garage Libramont Motors",
    "wof:placetype":"venue"
},
  "geometry": {"coordinates":[5.3593502045,49.9141998291],"type":"Point"}
}