{
  "type": "Feature",
  "properties": {
    "addr:full":"Kruisstraat 54 Zomergem Oost-Vlaanderen 9930",
    "addr:housenumber":"54",
    "addr:postcode":"9930",
    "addr:street":"Kruisstraat",
    "iso:country":"BE",
    "sg:address":"Kruisstraat 54",
    "sg:city":"Zomergem",
    "sg:orig_category":"Eleveurs de bovins",
    "sg:phone":"+32 9 372 79 81",
    "sg:postcode":"9930",
    "sg:province":"Oost-Vlaanderen",
    "wof:name":"Roland Cornelis",
    "wof:placetype":"venue"
},
  "geometry": {"coordinates":[3.5626699924,51.1207389832],"type":"Point"}
}