{
  "type": "Feature",
  "properties": {
    "addr:full":"Rue De L'enseignement 90b5 Brussel/bruxelles Bruxelles-Capitale 1000",
    "addr:housenumber":"90b5",
    "addr:postcode":"1000",
    "addr:street":"Rue De L'Enseignement;/",
    "iso:country":"BE",
    "sg:address":"Rue De L'enseignement 90b5",
    "sg:city":"Brussel/bruxelles",
    "sg:orig_category":"Services annexes des transports terrestres",
    "sg:phone":"+32 2 218 41 80",
    "sg:postcode":"1000",
    "sg:province":"Bruxelles-Capitale",
    "wof:name":"Garage De Pelegyn",
    "wof:placetype":"venue"
},
  "geometry": {"coordinates":[4.3645138741,50.8483467102],"type":"Point"}
}