{
  "type": "Feature",
  "properties": {
    "addr:full":"Place De La Neuville 12 Ottignies-louvain-la-neuve Brabant Wallon 1348",
    "addr:housenumber":"12",
    "addr:postcode":"1348",
    "addr:street":"Place De La Neuville",
    "iso:country":"BE",
    "sg:address":"Place De La Neuville 12",
    "sg:city":"Ottignies-louvain-la-neuve",
    "sg:orig_category":"Artistes ind\u00e9pendants",
    "sg:phone":"+32 10 41 70 81",
    "sg:postcode":"1348",
    "sg:province":"Brabant Wallon",
    "wof:name":"Vincent Rouche",
    "wof:placetype":"venue"
},
  "geometry": {"coordinates":[4.6175842285,50.663734436],"type":"Point"}
}