{
  "type": "Feature",
  "properties": {
    "addr:full":"Nijverheidskaai 14 Gent (sint-amandsberg) Oost-Vlaanderen 9040",
    "addr:housenumber":"14",
    "addr:postcode":"9040",
    "addr:street":"Nijverheidskaai",
    "iso:country":"BE",
    "sg:address":"Nijverheidskaai 14",
    "sg:city":"Gent (sint-amandsberg)",
    "sg:classifiers":[
        {
            "category":"Wholesale",
            "subcategory":"Vending Machines",
            "type":"Manufacturing & Wholesale Goods"
        }
    ],
    "sg:phone":"+32 9 228 17 95",
    "sg:postcode":"9040",
    "sg:province":"Oost-Vlaanderen",
    "sg:tags":[
        "sieving",
        "installation"
    ],
    "wof:name":"De Coster Manufacturing Bvba",
    "wof:placetype":"venue"
},
  "geometry": {"coordinates":[3.7581119537,51.0478210449],"type":"Point"}
}