{
  "type": "Feature",
  "properties": {
    "addr:full":"Oudebaan 217 Leuven Vlaams-Brabant 3000",
    "addr:housenumber":"217",
    "addr:postcode":"3000",
    "addr:street":"Oudebaan",
    "iso:country":"BE",
    "sg:address":"Oudebaan 217",
    "sg:city":"Leuven",
    "sg:classifiers":[
        {
            "category":"Health Services",
            "subcategory":"Dentist",
            "type":"Services"
        }
    ],
    "sg:phone":"+32 16 25 03 32",
    "sg:postcode":"3000",
    "sg:province":"Vlaams-Brabant",
    "wof:name":"Fouarge Annemie",
    "wof:placetype":"venue"
},
  "geometry": {"coordinates":[4.742128849,50.8638000488],"type":"Point"}
}