{
  "type": "Feature",
  "properties": {
    "iso:country":"BE",
    "sg:address":"Merelstraat 8",
    "sg:city":"Maasmechelen",
    "sg:orig_category":"Architecten",
    "sg:phone":"+32 89 72 19 16",
    "sg:postcode":"3630",
    "sg:province":"Limburg",
    "wof:name":"Brigitte Stans",
    "wof:placetype":"venue"
},
  "geometry": {"coordinates":[5.6841340065,50.9610366821],"type":"Point"}
}