{
  "type": "Feature",
  "properties": {
    "addr:full":"Rue Du Bauloy 27 Ottignies-louvain-la-neuve Brabant Wallon 1340",
    "addr:housenumber":"27",
    "addr:postcode":"1340",
    "addr:street":"Rue Du Bauloy",
    "iso:country":"BE",
    "sg:address":"Rue Du Bauloy 27",
    "sg:city":"Ottignies-louvain-la-neuve",
    "sg:orig_category":"Epiceries",
    "sg:phone":"+32 10 41 39 82",
    "sg:postcode":"1340",
    "sg:province":"Brabant Wallon",
    "wof:name":"Louis Delhaize",
    "wof:placetype":"venue"
},
  "geometry": {"coordinates":[4.5808320045,50.6647834778],"type":"Point"}
}