{
  "type": "Feature",
  "properties": {
    "iso:country":"BE",
    "sg:address":"Boulevard Joseph Tirou 17 Box 50-51",
    "sg:city":"Charleroi",
    "sg:orig_category":"Fiduciairies",
    "sg:phone":"+32 2 774 91 11",
    "sg:postcode":"6000",
    "sg:province":"Hainaut",
    "wof:name":"Fiduc Delforge Et Zanotti Sa",
    "wof:placetype":"venue"
},
  "geometry": {"coordinates":[4.4434351921,50.41015625],"type":"Point"}
}