{
  "type": "Feature",
  "properties": {
    "addr:full":"Chemin Du Moulin 19 Lasne Brabant Wallon 1380",
    "addr:housenumber":"19",
    "addr:postcode":"1380",
    "addr:street":"Chemin Du Moulin",
    "iso:country":"BE",
    "sg:address":"Chemin Du Moulin 19",
    "sg:city":"Lasne",
    "sg:classifiers":[
        {
            "category":"Cafe",
            "type":"Food & Drink"
        }
    ],
    "sg:phone":"+32 2 633 50 74",
    "sg:postcode":"1380",
    "sg:province":"Brabant Wallon",
    "sg:tags":[
        "caf\u00e9s"
    ],
    "wof:name":"Norbert Kumps",
    "wof:placetype":"venue"
},
  "geometry": {"coordinates":[4.483235836,50.6850166321],"type":"Point"}
}