{
  "type": "Feature",
  "properties": {
    "iso:country":"BE",
    "sg:address":"Rue De Philippeville 20",
    "sg:city":"Dinant",
    "sg:orig_category":"Installation \u00e9lectrique r\u00e9sidentielle",
    "sg:phone":"+32 82 22 39 42",
    "sg:postcode":"5500",
    "sg:province":"Namur",
    "wof:name":"Roland Collin",
    "wof:placetype":"venue"
},
  "geometry": {"coordinates":[4.9093852043,50.2582359314],"type":"Point"}
}