{
  "type": "Feature",
  "properties": {
    "addr:full":"Hogestraat 6 Kortemark (werken) West-Vlaanderen 8610",
    "addr:housenumber":"6",
    "addr:postcode":"8610",
    "addr:street":"Hogestraat",
    "iso:country":"BE",
    "sg:address":"Hogestraat 6",
    "sg:city":"Kortemark (werken)",
    "sg:classifiers":[
        {
            "category":"Personal",
            "type":"Services"
        }
    ],
    "sg:phone":"+32 51 56 77 82",
    "sg:postcode":"8610",
    "sg:province":"West-Vlaanderen",
    "sg:tags":[
        "clothing",
        "men's",
        "tailor",
        "-"
    ],
    "wof:name":"Verhaeghe R",
    "wof:placetype":"venue"
},
  "geometry": {"coordinates":[3.0078439713,51.0482139587],"type":"Point"}
}