{
  "type": "Feature",
  "properties": {
    "iso:country":"BE",
    "sg:address":"Weverslaan 26",
    "sg:city":"Lokeren",
    "sg:classifiers":[
        {
            "category":"Home & Garden",
            "subcategory":"Kitchen Supply",
            "type":"Retail Goods"
        }
    ],
    "sg:phone":"+32 9 348 46 00",
    "sg:postcode":"9160",
    "sg:province":"Oost-Vlaanderen",
    "sg:tags":[
        "installation"
    ],
    "wof:name":"Haemelinck Interieur",
    "wof:placetype":"venue"
},
  "geometry": {"coordinates":[4.0147161484,51.1106033325],"type":"Point"}
}