{
  "type": "Feature",
  "properties": {
    "addr:full":"Chauss\u00e9e Saint-mort 1 Huy Li\u00e8ge 4500",
    "addr:housenumber":"1",
    "addr:postcode":"4500",
    "addr:street":"Chausse\u0301E Saint-Mort",
    "iso:country":"BE",
    "sg:address":"Chauss\u00e9e Saint-mort 1",
    "sg:city":"Huy",
    "sg:classifiers":[
        {
            "category":"Social Services",
            "type":"Services"
        }
    ],
    "sg:phone":"+32 85 51 45 51",
    "sg:postcode":"4500",
    "sg:province":"Li\u00e8ge",
    "wof:name":"H\u00e9bergement Prot\u00e9g\u00e9s Asbl",
    "wof:placetype":"venue"
},
  "geometry": {"coordinates":[5.2375669479,50.5147705078],"type":"Point"}
}