{
  "type": "Feature",
  "properties": {
    "addr:full":"Humaniteitslaan 292 Brussel Bruxelles-Capitale 1070",
    "addr:housenumber":"292",
    "addr:postcode":"1070",
    "addr:street":"Humaniteitslaan",
    "iso:country":"BE",
    "sg:address":"Humaniteitslaan 292",
    "sg:city":"Brussel",
    "sg:classifiers":[
        {
            "category":"Retail",
            "subcategory":"Laundry & Dry Cleaning",
            "type":"Services"
        }
    ],
    "sg:phone":"+32 2 333 66 66",
    "sg:postcode":"1070",
    "sg:province":"Bruxelles-Capitale",
    "sg:tags":[
        "dish",
        "commercial",
        "use",
        "washing",
        "detergent"
    ],
    "wof:name":"Unilever Belgi\u00eb Nv",
    "wof:placetype":"venue"
},
  "geometry": {"coordinates":[4.3070521355,50.8128814697],"type":"Point"}
}