{
  "type": "Feature",
  "properties": {
    "addr:full":"Rue Du Roua 39 Vis\u00e9 Li\u00e8ge 4600",
    "addr:housenumber":"39",
    "addr:postcode":"4600",
    "addr:street":"Rue Du Roua",
    "iso:country":"BE",
    "sg:address":"Rue Du Roua 39",
    "sg:city":"Vis\u00e9",
    "sg:classifiers":[
        {
            "category":"Retail",
            "subcategory":"Event Space",
            "type":"Services"
        }
    ],
    "sg:phone":"+32 4 374 28 20",
    "sg:postcode":"4600",
    "sg:province":"Li\u00e8ge",
    "sg:tags":[
        "organisation"
    ],
    "wof:name":"Sport Consulting",
    "wof:placetype":"venue"
},
  "geometry": {"coordinates":[5.6953802109,50.7308044434],"type":"Point"}
}