{
  "type": "Feature",
  "properties": {
    "iso:country":"BE",
    "sg:address":"Rue L\u00c9opold 12",
    "sg:city":"Li\u00c8ge",
    "sg:classifiers":[
        {
            "category":"Insurance",
            "subcategory":"Life Insurance",
            "type":"Services"
        }
    ],
    "sg:phone":"+32 4 223 63 26",
    "sg:postcode":"4000",
    "sg:province":"Li\u00e8ge",
    "sg:tags":[
        "assurance"
    ],
    "wof:name":"Crediass",
    "wof:placetype":"venue"
},
  "geometry": {"coordinates":[5.575302124,50.6445960999],"type":"Point"}
}