{
  "type": "Feature",
  "properties": {
    "iso:country":"BE",
    "sg:address":"Ijzerenleen 12",
    "sg:city":"Mechelen",
    "sg:classifiers":[
        {
            "category":"Shopping",
            "subcategory":"Clothing, Apparel, & Fashions",
            "type":"Retail Goods"
        }
    ],
    "sg:phone":"+32 15 21 66 50",
    "sg:postcode":"2800",
    "sg:province":"Antwerpen",
    "sg:tags":[
        "ondergoed",
        "lingerie"
    ],
    "wof:name":"Huis Claire",
    "wof:placetype":"venue"
},
  "geometry": {"coordinates":[4.4788198471,51.0272293091],"type":"Point"}
}