{
  "type": "Feature",
  "properties": {
    "addr:full":"Sur Les Heids 5 Chaudfontaine (embourg) Li\u00e8ge 4053",
    "addr:housenumber":"5",
    "addr:postcode":"4053",
    "addr:street":"Sur Les Heids",
    "iso:country":"BE",
    "sg:address":"Sur Les Heids 5",
    "sg:city":"Chaudfontaine (embourg)",
    "sg:classifiers":[
        {
            "category":"Professional",
            "subcategory":"Management & Consulting",
            "type":"Services"
        }
    ],
    "sg:phone":"+32 4 361 13 39",
    "sg:postcode":"4053",
    "sg:province":"Li\u00e8ge",
    "sg:tags":[
        "consultant",
        "agency",
        "advertising"
    ],
    "wof:name":"Carmel Design",
    "wof:placetype":"venue"
},
  "geometry": {"coordinates":[5.598069191,50.5958595276],"type":"Point"}
}