{
  "type": "Feature",
  "properties": {
    "iso:country":"BE",
    "sg:address":"Assesteenweg 306",
    "sg:city":"Ternat (sint-katherina-lombeek)",
    "sg:classifiers":[
        {
            "category":"Autos & Motor Vehicles",
            "subcategory":"Automobile Sales",
            "type":"Retail Goods"
        }
    ],
    "sg:phone":"+32 2 463 44 61",
    "sg:postcode":"1742",
    "sg:province":"Vlaams-Brabant",
    "sg:tags":[
        "car",
        "used",
        "-"
    ],
    "wof:name":"Nathan Autohandel",
    "wof:placetype":"venue"
},
  "geometry": {"coordinates":[4.1620998383,50.8723297119],"type":"Point"}
}