{
  "type": "Feature",
  "properties": {
    "iso:country":"BE",
    "sg:address":"Bergbeemden 12",
    "sg:city":"Turnhout",
    "sg:classifiers":[
        {
            "category":"Building & Trades",
            "subcategory":"Pest Control",
            "type":"Services"
        }
    ],
    "sg:phone":"+32 14 41 96 86",
    "sg:postcode":"2300",
    "sg:province":"Antwerpen",
    "sg:tags":[
        "painting",
        "contractor"
    ],
    "wof:name":"Luyts",
    "wof:placetype":"venue"
},
  "geometry": {"coordinates":[4.9527730942,51.3091049194],"type":"Point"}
}