{
  "type": "Feature",
  "properties": {
    "iso:country":"BE",
    "sg:address":"Rue Charles Parente 28b",
    "sg:city":"Bruxelles",
    "sg:classifiers":[
        {
            "category":"Banks & Credit Unions",
            "subcategory":"Investment Brokerage",
            "type":"Services"
        }
    ],
    "sg:phone":"+32 2 558 10 10",
    "sg:postcode":"1070",
    "sg:province":"Bruxelles-Capitale",
    "sg:tags":[
        "development",
        "hardware"
    ],
    "wof:name":"Redcorp Nv",
    "wof:placetype":"venue"
},
  "geometry": {"coordinates":[4.330534935,50.8339691162],"type":"Point"}
}