{
  "type": "Feature",
  "properties": {
    "addr:full":"Rue De Fer 2 Namur Namur 5000",
    "addr:housenumber":"2",
    "addr:postcode":"5000",
    "addr:street":"Rue De Fer",
    "iso:country":"BE",
    "sg:address":"Rue De Fer 2",
    "sg:city":"Namur",
    "sg:orig_category":"Dameskledingzaken",
    "sg:phone":"+32 81 22 59 89",
    "sg:postcode":"5000",
    "sg:province":"Namur",
    "wof:name":"Maison Odace",
    "wof:placetype":"venue"
},
  "geometry": {"coordinates":[4.8651638031,50.4650497437],"type":"Point"}
}