{
  "type": "Feature",
  "properties": {
    "addr:full":"Gistelsteenweg 70 Jabbeke West-Vlaanderen 8490",
    "addr:housenumber":"70",
    "addr:postcode":"8490",
    "addr:street":"Gistelsteenweg",
    "iso:country":"BE",
    "sg:address":"Gistelsteenweg 70",
    "sg:city":"Jabbeke",
    "sg:orig_category":"Advocaten and juridische adviseurs",
    "sg:phone":"+32 50 38 71 32",
    "sg:postcode":"8490",
    "sg:province":"West-Vlaanderen",
    "wof:name":"P. Viane",
    "wof:placetype":"venue"
},
  "geometry": {"coordinates":[3.1105320454,51.1793174744],"type":"Point"}
}