{
  "type": "Feature",
  "properties": {
    "iso:country":"BE",
    "sg:address":"Leliepark 36",
    "sg:city":"Zulte",
    "sg:orig_category":"Woningbouw",
    "sg:phone":"+32 9 386 82 24",
    "sg:postcode":"9870",
    "sg:province":"Oost-Vlaanderen",
    "wof:name":"Jean De Vos",
    "wof:placetype":"venue"
},
  "geometry": {"coordinates":[3.4996399879,50.952129364],"type":"Point"}
}