{
  "type": "Feature",
  "properties": {
    "addr:full":"Guido Gezellelaan 64 Sint-niklaas Oost-Vlaanderen 9100",
    "addr:housenumber":"64",
    "addr:postcode":"9100",
    "addr:street":"Guido Gezellelaan",
    "iso:country":"BE",
    "sg:address":"Guido Gezellelaan 64",
    "sg:city":"Sint-niklaas",
    "sg:classifiers":[
        {
            "category":"Professional",
            "subcategory":"Management & Consulting",
            "type":"Services"
        }
    ],
    "sg:phone":"+32 3 777 78 00",
    "sg:postcode":"9100",
    "sg:province":"Oost-Vlaanderen",
    "sg:tags":[
        "consultancy"
    ],
    "wof:name":"Wherco 2 B.v.b.a.",
    "wof:placetype":"venue"
},
  "geometry": {"coordinates":[4.126376152,51.1654434204],"type":"Point"}
}