{
  "type": "Feature",
  "properties": {
    "addr:full":"Hogeschuurstraat 2 Ardooie West-Vlaanderen 8850",
    "addr:housenumber":"2",
    "addr:postcode":"8850",
    "addr:street":"Hogeschuurstraat",
    "iso:country":"BE",
    "sg:address":"Hogeschuurstraat 2",
    "sg:city":"Ardooie",
    "sg:classifiers":[
        {
            "category":"Home & Garden",
            "subcategory":"Hardware",
            "type":"Retail Goods"
        }
    ],
    "sg:phone":"+32 51 74 43 49",
    "sg:postcode":"8850",
    "sg:province":"West-Vlaanderen",
    "sg:tags":[
        "equipment",
        "woodworking",
        "machinery"
    ],
    "wof:name":"Haco Trading Company",
    "wof:placetype":"venue"
},
  "geometry": {"coordinates":[3.2176780701,50.9790649414],"type":"Point"}
}