{
  "type": "Feature",
  "properties": {
    "iso:country":"BE",
    "sg:address":"Wilgenlaan 33",
    "sg:city":"Langemark-poelkapelle",
    "sg:orig_category":"HUISBRANDOLIE",
    "sg:phone":"+32 57 48 61 04",
    "sg:postcode":"8920",
    "sg:province":"West-Vlaanderen",
    "wof:name":"Delcroix",
    "wof:placetype":"venue"
},
  "geometry": {"coordinates":[2.919770956,50.9132423401],"type":"Point"}
}