{
  "type": "Feature",
  "properties": {
    "addr:full":"Rue Mouzin 37a Mons Hainaut 7020",
    "addr:housenumber":"37a",
    "addr:postcode":"7020",
    "addr:street":"Rue Mouzin;Hainaut",
    "iso:country":"BE",
    "sg:address":"Rue Mouzin 37a",
    "sg:city":"Mons",
    "sg:orig_category":"Diverse machines voor de nijverheid Gh",
    "sg:phone":"+32 65 84 48 60",
    "sg:postcode":"7020",
    "sg:province":"Hainaut",
    "wof:name":"Soudulec",
    "wof:placetype":"venue"
},
  "geometry": {"coordinates":[3.9553449154,50.4761772156],"type":"Point"}
}