{
  "type": "Feature",
  "properties": {
    "addr:full":"Rue De La D\u00eeme 1 Braives (ciplet) Li\u00e8ge 4260",
    "addr:housenumber":"1",
    "addr:postcode":"4260",
    "addr:street":"Rue De La Di\u0302Me;Ciplet",
    "iso:country":"BE",
    "sg:address":"Rue De La D\u00eeme 1",
    "sg:city":"Braives (ciplet)",
    "sg:classifiers":[
        {
            "category":"Health Services",
            "subcategory":"Health Practitioner",
            "type":"Services"
        }
    ],
    "sg:phone":"+32 19 69 98 72",
    "sg:postcode":"4260",
    "sg:province":"Li\u00e8ge",
    "sg:tags":[
        "physiotherapist"
    ],
    "wof:name":"Duhaut M-f",
    "wof:placetype":"venue"
},
  "geometry": {"coordinates":[5.0962719917,50.6198425293],"type":"Point"}
}