{
  "type": "Feature",
  "properties": {
    "iso:country":"BE",
    "sg:address":"Pleinlaan 5",
    "sg:city":"Elsene/ixelles",
    "sg:orig_category":"Farmaceutische bereidingen and geneesmiddelen Fab",
    "sg:phone":"+32 2 650 17 11",
    "sg:postcode":"1050",
    "sg:province":"Bruxelles-Capitale",
    "wof:name":"Fa. Baxter",
    "wof:placetype":"venue"
},
  "geometry": {"coordinates":[4.391849041,50.8214454651],"type":"Point"}
}