{
  "type": "Feature",
  "properties": {
    "addr:full":"Brialmontlei 10 Antwerpen Antwerpen 2018",
    "addr:housenumber":"10",
    "addr:postcode":"2018",
    "addr:street":"Brialmontlei",
    "iso:country":"BE",
    "sg:address":"Brialmontlei 10",
    "sg:city":"Antwerpen",
    "sg:orig_category":"Non-Classified Establishments",
    "sg:phone":"+32 3 213 16 13",
    "sg:postcode":"2018",
    "sg:province":"Antwerpen",
    "wof:name":"Rombouts Bvba",
    "wof:placetype":"venue"
},
  "geometry": {"coordinates":[4.4193677902,51.2096557617],"type":"Point"}
}