{
  "type": "Feature",
  "properties": {
    "addr:full":"Espenhoek 23ba Sint-lievens-houtem Oost-Vlaanderen 9520",
    "addr:postcode":"9520",
    "addr:street":"Espenhoek;Oost-Vlaanderen",
    "iso:country":"BE",
    "sg:address":"Espenhoek 23ba",
    "sg:city":"Sint-lievens-houtem",
    "sg:orig_category":"Woningbouw",
    "sg:phone":"+32 53 63 14 79",
    "sg:postcode":"9520",
    "sg:province":"Oost-Vlaanderen",
    "wof:name":"Ivan Leus",
    "wof:placetype":"venue"
},
  "geometry": {"coordinates":[3.8427610397,50.9065132141],"type":"Point"}
}