{
  "type": "Feature",
  "properties": {
    "addr:full":"Weg Naar Zwartberg 2 Opglabbeek Limburg 3660",
    "addr:housenumber":"2",
    "addr:postcode":"3660",
    "addr:street":"Weg Naar Zwartberg",
    "iso:country":"BE",
    "sg:address":"Weg Naar Zwartberg 2",
    "sg:city":"Opglabbeek",
    "sg:classifiers":[
        {
            "category":"Travel",
            "subcategory":"Hotels & Motels",
            "type":"Entertainment"
        }
    ],
    "sg:phone":"+32 89 85 44 64",
    "sg:postcode":"3660",
    "sg:province":"Limburg",
    "wof:name":"Brouwershuis",
    "wof:placetype":"venue"
},
  "geometry": {"coordinates":[5.582695961,51.0422973633],"type":"Point"}
}