{
  "type": "Feature",
  "properties": {
    "iso:country":"BE",
    "sg:address":"Lijnwaadstraat 33",
    "sg:city":"Roeselare",
    "sg:classifiers":[
        {
            "category":"Professional",
            "subcategory":"Art Services",
            "type":"Services"
        }
    ],
    "sg:phone":"+32 51 20 31 01",
    "sg:postcode":"8800",
    "sg:province":"West-Vlaanderen",
    "sg:tags":[
        "photographer"
    ],
    "wof:name":"Keirsschieter K",
    "wof:placetype":"venue"
},
  "geometry": {"coordinates":[3.1125841141,50.9666824341],"type":"Point"}
}