{
  "type": "Feature",
  "properties": {
    "iso:country":"BE",
    "sg:address":"Hasseltweg 240",
    "sg:city":"Genk",
    "sg:classifiers":[
        {
            "category":"Home & Garden",
            "subcategory":"Home Furnishings",
            "type":"Retail Goods"
        }
    ],
    "sg:phone":"+32 89 35 08 25",
    "sg:postcode":"3600",
    "sg:province":"Limburg",
    "sg:tags":[
        "-",
        "bed",
        "mattress"
    ],
    "wof:name":"Prenuptia",
    "wof:placetype":"venue"
},
  "geometry": {"coordinates":[5.4488530159,50.959903717],"type":"Point"}
}