{
  "type": "Feature",
  "properties": {
    "addr:full":"Chauss\u00c9e De Charleroi 739 Namur Namur 5020",
    "addr:housenumber":"739",
    "addr:postcode":"5020",
    "addr:street":"Chausse\u0301E De Charleroi",
    "iso:country":"BE",
    "sg:address":"Chauss\u00c9e De Charleroi 739",
    "sg:city":"Namur",
    "sg:orig_category":"Artistes ind\u00e9pendants",
    "sg:phone":"+32 81 44 00 06",
    "sg:postcode":"5020",
    "sg:province":"Namur",
    "wof:name":"Guy Alexandre",
    "wof:placetype":"venue"
},
  "geometry": {"coordinates":[4.7952418327,50.4352035522],"type":"Point"}
}