{
  "type": "Feature",
  "properties": {
    "addr:full":"Rue Neuve 21 Dison Li\u00e8ge 4820",
    "addr:housenumber":"21",
    "addr:postcode":"4820",
    "addr:street":"Rue Neuve",
    "iso:country":"BE",
    "sg:address":"Rue Neuve 21",
    "sg:city":"Dison",
    "sg:orig_category":"D\u00e9chets and d\u00e9bris Gr",
    "sg:phone":"+32 87 33 93 37",
    "sg:postcode":"4820",
    "sg:province":"Li\u00e8ge",
    "wof:name":"Antonio Bortone",
    "wof:placetype":"venue"
},
  "geometry": {"coordinates":[5.8571681976,50.6055374146],"type":"Point"}
}