{
  "type": "Feature",
  "properties": {
    "iso:country":"BE",
    "sg:address":"Galgenstraat 11",
    "sg:city":"Bree",
    "sg:orig_category":"Juwelen and horloges",
    "sg:phone":"+32 89 46 22 57",
    "sg:postcode":"3960",
    "sg:province":"Limburg",
    "wof:name":"Evi Van Der Gucht",
    "wof:placetype":"venue"
},
  "geometry": {"coordinates":[5.5849761963,51.113117218],"type":"Point"}
}