{
  "type": "Feature",
  "properties": {
    "addr:full":"Kasteelstraat 17 Kruishoutem Oost-Vlaanderen 9770",
    "addr:housenumber":"17",
    "addr:postcode":"9770",
    "addr:street":"Kasteelstraat",
    "iso:country":"BE",
    "sg:address":"Kasteelstraat 17",
    "sg:city":"Kruishoutem",
    "sg:classifiers":[
        {
            "category":"Professional",
            "type":"Services"
        }
    ],
    "sg:phone":"+32 9 383 04 19",
    "sg:postcode":"9770",
    "sg:province":"Oost-Vlaanderen",
    "sg:tags":[
        "industrial",
        "automation"
    ],
    "wof:name":"Abc Electronics",
    "wof:placetype":"venue"
},
  "geometry": {"coordinates":[3.5345430374,50.9112815857],"type":"Point"}
}