{
  "type": "Feature",
  "properties": {
    "addr:full":"Chauss\u00e9e De Maubeuge 361 Mons (hyon) Hainaut 7022",
    "addr:housenumber":"361",
    "addr:postcode":"7022",
    "addr:street":"Chausse\u0301E De Maubeuge",
    "iso:country":"BE",
    "sg:address":"Chauss\u00e9e De Maubeuge 361",
    "sg:city":"Mons (hyon)",
    "sg:classifiers":[
        {
            "category":"Banks & Credit Unions",
            "subcategory":"Financial Services",
            "type":"Services"
        }
    ],
    "sg:phone":"+32 65 36 01 59",
    "sg:postcode":"7022",
    "sg:province":"Hainaut",
    "sg:tags":[
        "financing"
    ],
    "wof:name":"P & C Finances Sprl",
    "wof:placetype":"venue"
},
  "geometry": {"coordinates":[3.9516630173,50.4191589355],"type":"Point"}
}