{
  "type": "Feature",
  "properties": {
    "addr:full":"Portweg 7 Diksmuide West-Vlaanderen 8600",
    "addr:housenumber":"7",
    "addr:postcode":"8600",
    "addr:street":"Portweg",
    "iso:country":"BE",
    "sg:address":"Portweg 7",
    "sg:city":"Diksmuide",
    "sg:orig_category":"Installation de menuiserie en bois and plastique. Eclairage et \u00e9quipements du foyer",
    "sg:phone":"+32 51 56 63 79",
    "sg:postcode":"8600",
    "sg:province":"West-Vlaanderen",
    "wof:name":"Trappen D'hondt",
    "wof:placetype":"venue"
},
  "geometry": {"coordinates":[2.9454989433,51.0467033386],"type":"Point"}
}