{
  "type": "Feature",
  "properties": {
    "addr:full":"Herentalse Steenweg 5 Grobbendonk Antwerpen 2280",
    "addr:housenumber":"5",
    "addr:postcode":"2280",
    "addr:street":"Herentalse Steenweg",
    "iso:country":"BE",
    "sg:address":"Herentalse Steenweg 5",
    "sg:city":"Grobbendonk",
    "sg:classifiers":[
        {
            "category":"Shopping",
            "subcategory":"Gifts & Souvenirs",
            "type":"Retail Goods"
        }
    ],
    "sg:phone":"+32 14 51 40 95",
    "sg:postcode":"2280",
    "sg:province":"Antwerpen",
    "sg:tags":[
        "-"
    ],
    "wof:name":"Zi-zo",
    "wof:placetype":"venue"
},
  "geometry": {"coordinates":[4.7442698479,51.1730041504],"type":"Point"}
}