{
  "type": "Feature",
  "properties": {
    "iso:country":"BE",
    "sg:address":"Statiestraat 1",
    "sg:city":"Zonnebeke",
    "sg:classifiers":[
        {
            "category":"Cafe",
            "type":"Food & Drink"
        }
    ],
    "sg:phone":"+32 51 78 02 18",
    "sg:postcode":"8980",
    "sg:province":"West-Vlaanderen",
    "sg:tags":[
        "caf\u00e9s"
    ],
    "wof:name":"Music Caf\u00c9",
    "wof:placetype":"venue"
},
  "geometry": {"coordinates":[3.0215299129,50.8998413086],"type":"Point"}
}