{
  "type": "Feature",
  "properties": {
    "addr:full":"Evert Larockstraat 22 Kapelle-op-den-bos Vlaams-Brabant 1880",
    "addr:housenumber":"22",
    "addr:postcode":"1880",
    "addr:street":"Evert Larockstraat",
    "iso:country":"BE",
    "sg:address":"Evert Larockstraat 22",
    "sg:city":"Kapelle-op-den-bos",
    "sg:orig_category":"Overheidsdiensten",
    "sg:phone":"+32 15 71 92 10",
    "sg:postcode":"1880",
    "sg:province":"Vlaams-Brabant",
    "wof:name":"O.c.m.w.",
    "wof:placetype":"venue"
},
  "geometry": {"coordinates":[4.3674678802,51.0134353638],"type":"Point"}
}