{
  "type": "Feature",
  "properties": {
    "iso:country":"BE",
    "sg:address":"Chemin De Soeret 1",
    "sg:city":"La Roche-en-ardenne",
    "sg:classifiers":[
        {
            "category":"Retail",
            "subcategory":"Veterinary Services",
            "type":"Services"
        }
    ],
    "sg:phone":"+32 84 41 22 05",
    "sg:postcode":"6980",
    "sg:province":"Luxembourg",
    "sg:tags":[
        "veterinarian"
    ],
    "wof:name":"Gillard D",
    "wof:placetype":"venue"
},
  "geometry": {"coordinates":[5.5796017647,50.1771392822],"type":"Point"}
}