{
  "type": "Feature",
  "properties": {
    "addr:full":"Eenmeilaan 48 Leuven (kessel-lo) Vlaams-Brabant 3010",
    "addr:housenumber":"48",
    "addr:postcode":"3010",
    "addr:street":"Eenmeilaan",
    "iso:country":"BE",
    "sg:address":"Eenmeilaan 48",
    "sg:city":"Leuven (kessel-lo)",
    "sg:classifiers":[
        {
            "category":"Professional",
            "subcategory":"Engineering",
            "type":"Services"
        }
    ],
    "sg:phone":"+32 16 25 28 00",
    "sg:postcode":"3010",
    "sg:province":"Vlaams-Brabant",
    "sg:tags":[
        "civil",
        "offices-"
    ],
    "wof:name":"Paridaens K.a.g.j.",
    "wof:placetype":"venue"
},
  "geometry": {"coordinates":[4.7304501534,50.889755249],"type":"Point"}
}