{
  "type": "Feature",
  "properties": {
    "addr:full":"Parc De La Hayoulle 11 Fleron Li\u00e8ge 4620",
    "addr:housenumber":"11",
    "addr:postcode":"4620",
    "addr:street":"Parc De La Hayoulle",
    "iso:country":"BE",
    "sg:address":"Parc De La Hayoulle 11",
    "sg:city":"Fleron",
    "sg:classifiers":[
        {
            "category":"Shopping",
            "subcategory":"Clothing, Apparel, & Fashions",
            "type":"Retail Goods"
        }
    ],
    "sg:phone":"+32 4 358 32 03",
    "sg:postcode":"4620",
    "sg:province":"Li\u00e8ge",
    "sg:tags":[
        "v\u00eatements",
        "pour",
        "dame"
    ],
    "wof:name":"Deco",
    "wof:placetype":"venue"
},
  "geometry": {"coordinates":[5.6880259514,50.6100273132],"type":"Point"}
}