{
  "type": "Feature",
  "properties": {
    "addr:full":"Veldonkstraat 5 Tremelo Vlaams-Brabant 3120",
    "addr:housenumber":"5",
    "addr:postcode":"3120",
    "addr:street":"Veldonkstraat",
    "iso:country":"BE",
    "sg:address":"Veldonkstraat 5",
    "sg:city":"Tremelo",
    "sg:orig_category":"Promoteurs immobiliers. Agences immobili\u00e8res",
    "sg:phone":"+32 16 53 00 45",
    "sg:postcode":"3120",
    "sg:province":"Vlaams-Brabant",
    "wof:name":"Immo Marina",
    "wof:placetype":"venue"
},
  "geometry": {"coordinates":[4.7061300278,50.9896202087],"type":"Point"}
}