{
  "type": "Feature",
  "properties": {
    "addr:full":"Pittemstraat 87 Meulebeke West-Vlaanderen 8760",
    "addr:housenumber":"87",
    "addr:postcode":"8760",
    "addr:street":"Pittemstraat",
    "iso:country":"BE",
    "sg:address":"Pittemstraat 87",
    "sg:city":"Meulebeke",
    "sg:orig_category":"Eleveurs de bovins. Eleveurs and marchands de porcs",
    "sg:phone":"+32 51 48 80 81",
    "sg:postcode":"8760",
    "sg:province":"West-Vlaanderen",
    "wof:name":"Dani\u00cbl Vandermersch",
    "wof:placetype":"venue"
},
  "geometry": {"coordinates":[3.283121109,50.9569358826],"type":"Point"}
}