{
  "type": "Feature",
  "properties": {
    "addr:full":"Lucasstraat 45 Staden West-Vlaanderen 8840",
    "addr:housenumber":"45",
    "addr:postcode":"8840",
    "addr:street":"Lucasstraat",
    "iso:country":"BE",
    "sg:address":"Lucasstraat 45",
    "sg:city":"Staden",
    "sg:orig_category":"Groententeelt Varkenskwekers",
    "sg:phone":"+32 51 70 11 58",
    "sg:postcode":"8840",
    "sg:province":"West-Vlaanderen",
    "wof:name":"Gabriel Desimpel",
    "wof:placetype":"venue"
},
  "geometry": {"coordinates":[3.0161550045,50.9893875122],"type":"Point"}
}