{
  "type": "Feature",
  "properties": {
    "addr:full":"Houtdok 27bb Antwerpen Antwerpen 2030",
    "addr:housenumber":"27bb",
    "addr:postcode":"2030",
    "addr:street":"Houtdok",
    "iso:country":"BE",
    "sg:address":"Houtdok 27bb",
    "sg:city":"Antwerpen",
    "sg:orig_category":"G\u00e9nie hydraulique",
    "sg:phone":"+32 3 231 71 38",
    "sg:postcode":"2030",
    "sg:province":"Antwerpen",
    "wof:name":"Benelux Diving Corp.",
    "wof:placetype":"venue"
},
  "geometry": {"coordinates":[4.4125499725,51.2360954285],"type":"Point"}
}