{
  "type": "Feature",
  "properties": {
    "addr:full":"Hoge Ieperweg 11 Houthulst (merkem) West-Vlaanderen 8650",
    "addr:housenumber":"11",
    "addr:postcode":"8650",
    "addr:street":"Hoge Ieperweg",
    "iso:country":"BE",
    "sg:address":"Hoge Ieperweg 11",
    "sg:city":"Houthulst (merkem)",
    "sg:classifiers":[
        {
            "category":"Utilities",
            "subcategory":"Refuse",
            "type":"Services"
        }
    ],
    "sg:phone":"+32 51 54 40 74",
    "sg:postcode":"8650",
    "sg:province":"West-Vlaanderen",
    "sg:tags":[
        "miller"
    ],
    "wof:name":"Van Robaeys C",
    "wof:placetype":"venue"
},
  "geometry": {"coordinates":[2.8862159252,50.9536781311],"type":"Point"}
}