{
  "type": "Feature",
  "properties": {
    "addr:full":"Merelstraat 11 Dendermonde Oost-Vlaanderen 9200",
    "addr:housenumber":"11",
    "addr:postcode":"9200",
    "addr:street":"Merelstraat;Oost-Vlaanderen",
    "iso:country":"BE",
    "sg:address":"Merelstraat 11",
    "sg:city":"Dendermonde",
    "sg:orig_category":"Architectes",
    "sg:phone":"+32 52 20 30 27",
    "sg:postcode":"9200",
    "sg:province":"Oost-Vlaanderen",
    "wof:name":"Koen Van Impe",
    "wof:placetype":"venue"
},
  "geometry": {"coordinates":[4.1183109283,51.0232810974],"type":"Point"}
}