{
  "type": "Feature",
  "properties": {
    "addr:full":"Rue Charles Quint 2 Bruxelles Bruxelles-Capitale 1000",
    "addr:housenumber":"2",
    "addr:postcode":"1000",
    "addr:street":"Rue Charles Quint",
    "iso:country":"BE",
    "sg:address":"Rue Charles Quint 2",
    "sg:city":"Bruxelles",
    "sg:classifiers":[
        {
            "category":"Professional",
            "type":"Services"
        }
    ],
    "sg:phone":"+32 2 732 12 17",
    "sg:postcode":"1000",
    "sg:province":"Bruxelles-Capitale",
    "sg:tags":[
        "entertainer"
    ],
    "wof:name":"Capuccino (le Clown)",
    "wof:placetype":"venue"
},
  "geometry": {"coordinates":[4.3811650276,50.850440979],"type":"Point"}
}