{
  "type": "Feature",
  "properties": {
    "iso:country":"BE",
    "sg:address":"Rue Franklin 62",
    "sg:city":"Bruxelles",
    "sg:classifiers":[
        {
            "category":"Professional",
            "subcategory":"Testing Lab",
            "type":"Services"
        }
    ],
    "sg:phone":"+32 2 733 11 62",
    "sg:postcode":"1000",
    "sg:province":"Bruxelles-Capitale",
    "sg:tags":[
        "chemist"
    ],
    "wof:name":"Euro-pharma",
    "wof:placetype":"venue"
},
  "geometry": {"coordinates":[4.3866958618,50.8454208374],"type":"Point"}
}