{
  "type": "Feature",
  "properties": {
    "iso:country":"BE",
    "sg:address":"21",
    "sg:city":"Rue De La Prelle 6041 Charleroi",
    "sg:classifiers":[
        {
            "category":"Autos & Motor Vehicles",
            "subcategory":"Automobile Sales",
            "type":"Retail Goods"
        }
    ],
    "sg:phone":"+32 71 35 92 23",
    "sg:postcode":"21",
    "sg:tags":[
        "equipment",
        "motor-cars",
        "transport"
    ],
    "wof:name":"Carrosserie Zarulli Freres Sa",
    "wof:placetype":"venue"
},
  "geometry": {"coordinates":[4.4314317703,50.4685935974],"type":"Point"}
}