{
  "type": "Feature",
  "properties": {
    "iso:country":"BE",
    "sg:address":"Avenue Haulet 47",
    "sg:city":"Verviers",
    "sg:orig_category":"Diensten voor huisdieren",
    "sg:phone":"+32 87 23 14 61",
    "sg:postcode":"4802",
    "sg:province":"Li\u00e8ge",
    "wof:name":"L\u00b4art Du Chien",
    "wof:placetype":"venue"
},
  "geometry": {"coordinates":[5.8671250343,50.5714111328],"type":"Point"}
}