{
  "type": "Feature",
  "properties": {
    "iso:country":"BE",
    "sg:address":"Rue Camille Borbouse 24",
    "sg:city":"Profondeville",
    "sg:orig_category":"Forge, Moulage and Profilage des M\u00e9taux",
    "sg:phone":"+32 81 43 46 44",
    "sg:postcode":"5170",
    "sg:province":"Namur",
    "wof:name":"Atelier Metal",
    "wof:placetype":"venue"
},
  "geometry": {"coordinates":[4.8674049377,50.3786392212],"type":"Point"}
}