{
  "type": "Feature",
  "properties": {
    "iso:country":"BE",
    "sg:address":"Grote Noordstraat 68",
    "sg:city":"Hooglede",
    "sg:orig_category":"Cr\u00e9meries",
    "sg:phone":"+32 51 20 67 96",
    "sg:postcode":"8830",
    "sg:province":"West-Vlaanderen",
    "wof:name":"Haelewijn",
    "wof:placetype":"venue"
},
  "geometry": {"coordinates":[3.0725040436,50.9973220825],"type":"Point"}
}