{
  "type": "Feature",
  "properties": {
    "iso:country":"BE",
    "sg:address":"Casinolaan 17",
    "sg:city":"Leuven",
    "sg:orig_category":"Banken and kredietinstellingen",
    "sg:phone":"+32 16 44 16 50",
    "sg:postcode":"3018",
    "sg:province":"Vlaams-Brabant",
    "wof:name":"Kbc",
    "wof:placetype":"venue"
},
  "geometry": {"coordinates":[4.6988887787,50.9257850647],"type":"Point"}
}