{
  "type": "Feature",
  "properties": {
    "addr:full":"Marktplein 10 Sint-lievens-houtem Oost-Vlaanderen 9520",
    "addr:housenumber":"10",
    "addr:postcode":"9520",
    "addr:street":"Marktplein;Oost-Vlaanderen",
    "iso:country":"BE",
    "sg:address":"Marktplein 10",
    "sg:city":"Sint-lievens-houtem",
    "sg:orig_category":"Brood, gebak and snoepgoed",
    "sg:phone":"+32 53 62 52 90",
    "sg:postcode":"9520",
    "sg:province":"Oost-Vlaanderen",
    "wof:name":"Geert De Winter",
    "wof:placetype":"venue"
},
  "geometry": {"coordinates":[3.8585739136,50.9207458496],"type":"Point"}
}