{
  "type": "Feature",
  "properties": {
    "addr:full":"Tolpoortstraat 75 Deinze Oost-Vlaanderen 9800",
    "addr:housenumber":"75",
    "addr:postcode":"9800",
    "addr:street":"Tolpoortstraat",
    "iso:country":"BE",
    "sg:address":"Tolpoortstraat 75",
    "sg:city":"Deinze",
    "sg:orig_category":"Herstelling leer and schoeisel",
    "sg:phone":"+32 9 386 43 90",
    "sg:postcode":"9800",
    "sg:province":"Oost-Vlaanderen",
    "wof:name":"Noel Debie",
    "wof:placetype":"venue"
},
  "geometry": {"coordinates":[3.529665947,50.980430603],"type":"Point"}
}