{
  "type": "Feature",
  "properties": {
    "addr:full":"Avenue Besme 84 Vorst/forest Bruxelles-Capitale 1190",
    "addr:housenumber":"84",
    "addr:postcode":"1190",
    "addr:street":"Avenue Besme;/ Forest",
    "iso:country":"BE",
    "sg:address":"Avenue Besme 84",
    "sg:city":"Vorst/forest",
    "sg:orig_category":"M\u00e9decins and sp\u00e9cialistes",
    "sg:phone":"+32 2 672 30 64",
    "sg:postcode":"1190",
    "sg:province":"Bruxelles-Capitale",
    "wof:name":"Sylvie Blondel",
    "wof:placetype":"venue"
},
  "geometry": {"coordinates":[4.3416762352,50.8217163086],"type":"Point"}
}