{
  "type": "Feature",
  "properties": {
    "addr:full":"Rue De La Station 19 Charleroi Hainaut 6043",
    "addr:housenumber":"19",
    "addr:postcode":"6043",
    "addr:street":"Rue De La Station;Hainaut",
    "iso:country":"BE",
    "sg:address":"Rue De La Station 19",
    "sg:city":"Charleroi",
    "sg:orig_category":"M\u00e9decins and sp\u00e9cialistes",
    "sg:phone":"+32 71 35 08 79",
    "sg:postcode":"6043",
    "sg:province":"Hainaut",
    "wof:name":"Vincent Calicis",
    "wof:placetype":"venue"
},
  "geometry": {"coordinates":[4.4841737747,50.457408905],"type":"Point"}
}