{
  "type": "Feature",
  "properties": {
    "iso:country":"BE",
    "sg:address":"Avenue De Vilvorde 440",
    "sg:city":"Brussel/bruxelles",
    "sg:orig_category":"D\u00e9taillants en pi\u00e8ces and accessoires de voitures",
    "sg:phone":"+32 2 245 37 78",
    "sg:postcode":"1130",
    "sg:province":"Bruxelles-Capitale",
    "wof:name":"Auto Baz Bek",
    "wof:placetype":"venue"
},
  "geometry": {"coordinates":[4.4128351212,50.9054374695],"type":"Point"}
}