{
  "type": "Feature",
  "properties": {
    "addr:full":"Steenweg Op Leuze 238 Ronse Oost-Vlaanderen 9600",
    "addr:housenumber":"238",
    "addr:postcode":"9600",
    "addr:street":"Steenweg Op Leuze",
    "iso:country":"BE",
    "sg:address":"Steenweg Op Leuze 238",
    "sg:city":"Ronse",
    "sg:orig_category":"Mat\u00e9riel de T\u00e9l\u00e9communication",
    "sg:phone":"+32 55 20 98 13",
    "sg:postcode":"9600",
    "sg:province":"Oost-Vlaanderen",
    "wof:name":"Van Coppernolle & Cie",
    "wof:placetype":"venue"
},
  "geometry": {"coordinates":[3.5898580551,50.7339172363],"type":"Point"}
}