{
  "type": "Feature",
  "properties": {
    "addr:full":"Koningin Astridlaan 25 Brugge West-Vlaanderen 8200",
    "addr:housenumber":"25",
    "addr:postcode":"8200",
    "addr:street":"Koningin Astridlaan",
    "iso:country":"BE",
    "sg:address":"Koningin Astridlaan 25",
    "sg:city":"Brugge",
    "sg:orig_category":"Diverse zakelijke dienstverlening Immobili\u00ebnkantoren Projectontwikkelaars Vakantiehuizen Verzekering",
    "sg:phone":"+32 50 55 15 00",
    "sg:postcode":"8200",
    "sg:province":"West-Vlaanderen",
    "wof:name":"Appel 2000",
    "wof:placetype":"venue"
},
  "geometry": {"coordinates":[3.248488903,51.2000770569],"type":"Point"}
}