{
  "type": "Feature",
  "properties": {
    "iso:country":"BE",
    "sg:address":"Beekstraat 38",
    "sg:city":"Sint-truiden",
    "sg:classifiers":[
        {
            "category":"Education",
            "subcategory":"Dance Studio",
            "type":"Public Place"
        }
    ],
    "sg:phone":"+32 11 68 08 08",
    "sg:postcode":"3800",
    "sg:province":"Limburg",
    "sg:tags":[
        "ballet",
        "school"
    ],
    "wof:name":"Acad. Cobaro Siegfried Dans & Beweging",
    "wof:placetype":"venue"
},
  "geometry": {"coordinates":[5.1852140427,50.8165245056],"type":"Point"}
}