{
  "type": "Feature",
  "properties": {
    "addr:full":"Dieplaan 51 Genk Limburg 3600",
    "addr:housenumber":"51",
    "addr:postcode":"3600",
    "addr:street":"Dieplaan",
    "iso:country":"BE",
    "sg:address":"Dieplaan 51",
    "sg:city":"Genk",
    "sg:orig_category":"Equipement photographique. Studios photographiques",
    "sg:phone":"+32 89 35 41 52",
    "sg:postcode":"3600",
    "sg:province":"Limburg",
    "wof:name":"Harsh Color Copy",
    "wof:placetype":"venue"
},
  "geometry": {"coordinates":[5.4939460754,50.9641571045],"type":"Point"}
}