{
  "type": "Feature",
  "properties": {
    "addr:full":"Beeklaan 24 Herzele Oost-Vlaanderen 9550",
    "addr:housenumber":"24",
    "addr:postcode":"9550",
    "addr:street":"Beeklaan;Oost-Vlaanderen",
    "iso:country":"BE",
    "sg:address":"Beeklaan 24",
    "sg:city":"Herzele",
    "sg:classifiers":[
        {
            "category":"Professional",
            "subcategory":"Computer Services",
            "type":"Services"
        }
    ],
    "sg:phone":"+32 53 62 58 85",
    "sg:postcode":"9550",
    "sg:province":"Oost-Vlaanderen",
    "sg:tags":[
        "-",
        "processing",
        "data",
        "software"
    ],
    "wof:name":"Jdldev",
    "wof:placetype":"venue"
},
  "geometry": {"coordinates":[3.8768250942,50.8962860107],"type":"Point"}
}