{
  "type": "Feature",
  "properties": {
    "addr:full":"Steenweg 101 Lanaken (rekem) Limburg 3621",
    "addr:housenumber":"101",
    "addr:postcode":"3621",
    "addr:street":"Steenweg",
    "iso:country":"BE",
    "sg:address":"Steenweg 101",
    "sg:city":"Lanaken (rekem)",
    "sg:classifiers":[
        {
            "category":"Shopping",
            "subcategory":"Pets & Pet Supplies",
            "type":"Retail Goods"
        }
    ],
    "sg:phone":"+32 89 71 22 75",
    "sg:postcode":"3621",
    "sg:province":"Limburg",
    "sg:tags":[
        "horseriding"
    ],
    "wof:name":"Doyenne Ruiterboetiek & Westernstore",
    "wof:placetype":"venue"
},
  "geometry": {"coordinates":[5.6845541,50.9197006226],"type":"Point"}
}