{
  "type": "Feature",
  "properties": {
    "iso:country":"BE",
    "sg:address":"Schierveldestraat 42",
    "sg:city":"Roeselare",
    "sg:classifiers":[
        {
            "category":"Personal",
            "subcategory":"Beauty Salon",
            "type":"Services"
        }
    ],
    "sg:phone":"+32 51 20 71 38",
    "sg:postcode":"8800",
    "sg:province":"West-Vlaanderen",
    "sg:tags":[
        "de",
        "coiffure"
    ],
    "wof:name":"Coiffure Charmy",
    "wof:placetype":"venue"
},
  "geometry": {"coordinates":[3.1106860638,50.9518203735],"type":"Point"}
}