{
  "type": "Feature",
  "properties": {
    "addr:full":"Kempenplein 7 Neerpelt Limburg 3910",
    "addr:housenumber":"7",
    "addr:postcode":"3910",
    "addr:street":"Kempenplein",
    "iso:country":"BE",
    "sg:address":"Kempenplein 7",
    "sg:city":"Neerpelt",
    "sg:classifiers":[
        {
            "category":"Shopping",
            "subcategory":"Gifts & Souvenirs",
            "type":"Retail Goods"
        }
    ],
    "sg:phone":"+32 11 80 35 55",
    "sg:postcode":"3910",
    "sg:province":"Limburg",
    "sg:tags":[
        "-"
    ],
    "wof:name":"Art\u00e9",
    "wof:placetype":"venue"
},
  "geometry": {"coordinates":[5.4319767952,51.2285728455],"type":"Point"}
}