{
  "type": "Feature",
  "properties": {
    "addr:full":"20 Rue Du Port 6250 Aiseau-presles 20",
    "addr:housenumber":"20;20",
    "addr:postcode":"6250",
    "addr:street":"Rue Du Port;Aiseau-Presles",
    "iso:country":"BE",
    "sg:address":"20",
    "sg:city":"Rue Du Port 6250 Aiseau-presles",
    "sg:classifiers":[
        {
            "category":"Banks & Credit Unions",
            "subcategory":"Investment Brokerage",
            "type":"Services"
        }
    ],
    "sg:phone":"+32 71 40 23 92",
    "sg:postcode":"20",
    "sg:tags":[
        "-",
        "transport",
        "related"
    ],
    "wof:name":"Euro-services Sa",
    "wof:placetype":"venue"
},
  "geometry": {"coordinates":[4.5484700203,50.4169998169],"type":"Point"}
}