{
  "type": "Feature",
  "properties": {
    "addr:full":"Rue De Fauconval 112 Ramillies (huppaye) Brabant Wallon 1367",
    "addr:housenumber":"112",
    "addr:postcode":"1367",
    "addr:street":"Rue De Fauconval;Wallon",
    "iso:country":"BE",
    "sg:address":"Rue De Fauconval 112",
    "sg:city":"Ramillies (huppaye)",
    "sg:classifiers":[
        {
            "category":"Freight",
            "type":"Transportation"
        }
    ],
    "sg:phone":"+32 10 81 23 31",
    "sg:postcode":"1367",
    "sg:province":"Brabant Wallon",
    "sg:tags":[
        "-",
        "transport"
    ],
    "wof:name":"Verbiest F",
    "wof:placetype":"venue"
},
  "geometry": {"coordinates":[4.9146900177,50.636631012],"type":"Point"}
}