{
  "type": "Feature",
  "properties": {
    "addr:full":"Chauss\u00c9e De Waterloo 1021 Ukkel/uccle Bruxelles-Capitale 1180",
    "addr:postcode":"1021;1180",
    "addr:street":"Chausse\u0301E De Waterloo",
    "iso:country":"BE",
    "sg:address":"Chauss\u00c9e De Waterloo 1021",
    "sg:city":"Ukkel/uccle",
    "sg:orig_category":"Mat\u00e9riel de T\u00e9l\u00e9communication",
    "sg:phone":"+32 2 372 12 72",
    "sg:postcode":"1180",
    "sg:province":"Bruxelles-Capitale",
    "wof:name":"A La Maison Du Bureau Et Du Gsm",
    "wof:placetype":"venue"
},
  "geometry": {"coordinates":[4.3718509674,50.805480957],"type":"Point"}
}