{
  "type": "Feature",
  "properties": {
    "iso:country":"BE",
    "sg:address":"Lombardsijdestraat 24",
    "sg:city":"Brussel/bruxelles",
    "sg:orig_category":"Paramedische behandelingen",
    "sg:phone":"+32 2 268 23 04",
    "sg:postcode":"1120",
    "sg:province":"Bruxelles-Capitale",
    "wof:name":"C. Heirbaut",
    "wof:placetype":"venue"
},
  "geometry": {"coordinates":[4.381816864,50.8935203552],"type":"Point"}
}