{
  "type": "Feature",
  "properties": {
    "addr:full":"Sint-janstraat 3 Beringen (paal) Limburg 3583",
    "addr:housenumber":"3",
    "addr:postcode":"3583",
    "addr:street":"Sint-Janstraat",
    "iso:country":"BE",
    "sg:address":"Sint-janstraat 3",
    "sg:city":"Beringen (paal)",
    "sg:classifiers":[
        {
            "category":"Shopping",
            "subcategory":"Beauty & Cosmetics",
            "type":"Retail Goods"
        }
    ],
    "sg:phone":"+32 11 43 70 03",
    "sg:postcode":"3583",
    "sg:province":"Limburg",
    "sg:tags":[
        "-",
        "perfumery"
    ],
    "wof:name":"An Schoonheidsinstituut",
    "wof:placetype":"venue"
},
  "geometry": {"coordinates":[5.174352169,51.0394287109],"type":"Point"}
}