{
  "type": "Feature",
  "properties": {
    "iso:country":"BE",
    "sg:address":"Parklaan 12",
    "sg:city":"Nieuwpoort",
    "sg:classifiers":[
        {
            "category":"Professional",
            "subcategory":"Lawyer & Legal Services",
            "type":"Services"
        }
    ],
    "sg:phone":"+32 58 23 71 77",
    "sg:postcode":"8620",
    "sg:province":"West-Vlaanderen",
    "wof:name":"Vanlerberghe Kurt",
    "wof:placetype":"venue"
},
  "geometry": {"coordinates":[2.7466080189,51.1321563721],"type":"Point"}
}