{
  "type": "Feature",
  "properties": {
    "addr:full":"Parvis Sainte-alix 4 Bruxelles (woluwe-saint-pierre) Bruxelles-Capitale 1150",
    "addr:housenumber":"4",
    "addr:postcode":"1150",
    "addr:street":"Parvis Sainte-Alix",
    "iso:country":"BE",
    "sg:address":"Parvis Sainte-alix 4",
    "sg:city":"Bruxelles (woluwe-saint-pierre)",
    "sg:classifiers":[
        {
            "category":"Personal",
            "subcategory":"Barber",
            "type":"Services"
        }
    ],
    "sg:phone":"+32 2 770 49 33",
    "sg:postcode":"1150",
    "sg:province":"Bruxelles-Capitale",
    "sg:tags":[
        "gentleman",
        "salon",
        "-",
        "hairdressing"
    ],
    "wof:name":"Christian",
    "wof:placetype":"venue"
},
  "geometry": {"coordinates":[4.4609689713,50.8275985718],"type":"Point"}
}