{
  "type": "Feature",
  "properties": {
    "iso:country":"BE",
    "sg:address":"Basse Cour 3",
    "sg:city":"Bassenge (wonck)",
    "sg:classifiers":[
        {
            "category":"Building & Trades",
            "subcategory":"Construction",
            "type":"Services"
        }
    ],
    "sg:phone":"+32 4 383 54 31",
    "sg:postcode":"4690",
    "sg:province":"Li\u00e8ge",
    "sg:tags":[
        "carpenter"
    ],
    "wof:name":"Marx-dubois M",
    "wof:placetype":"venue"
},
  "geometry": {"coordinates":[5.6296448708,50.7686271667],"type":"Point"}
}