{
  "type": "Feature",
  "properties": {
    "addr:full":"Rue Du Tabellion 2 Elsene/ixelles Bruxelles-Capitale 1050",
    "addr:housenumber":"2",
    "addr:postcode":"1050",
    "addr:street":"Rue Du Tabellion",
    "iso:country":"BE",
    "sg:address":"Rue Du Tabellion 2",
    "sg:city":"Elsene/ixelles",
    "sg:classifiers":[
        {
            "category":"Personal",
            "subcategory":"Beauty Salon",
            "type":"Services"
        }
    ],
    "sg:phone":"+32 2 537 33 29",
    "sg:postcode":"1050",
    "sg:province":"Bruxelles-Capitale",
    "sg:tags":[
        "de",
        "coiffure"
    ],
    "wof:name":"Ysatys",
    "wof:placetype":"venue"
},
  "geometry": {"coordinates":[4.358757019,50.8248596191],"type":"Point"}
}