{
  "type": "Feature",
  "properties": {
    "addr:full":"Rubbensstraat 146 Turnhout Antwerpen 2300",
    "addr:housenumber":"146",
    "addr:postcode":"2300",
    "addr:street":"Rubbensstraat",
    "iso:country":"BE",
    "sg:address":"Rubbensstraat 146",
    "sg:city":"Turnhout",
    "sg:orig_category":"Promoteurs immobiliers. Agences immobili\u00e8res",
    "sg:phone":"+32 14 59 19 60",
    "sg:postcode":"2300",
    "sg:province":"Antwerpen",
    "wof:name":"Century 21-bruyninckx Vastgoed",
    "wof:placetype":"venue"
},
  "geometry": {"coordinates":[4.9439601898,51.3146476746],"type":"Point"}
}