{
  "type": "Feature",
  "properties": {
    "addr:full":"Rue De La Station 99 Fleurus Hainaut 6220",
    "addr:housenumber":"99",
    "addr:postcode":"6220",
    "addr:street":"Rue De La Station",
    "iso:country":"BE",
    "sg:address":"Rue De La Station 99",
    "sg:city":"Fleurus",
    "sg:classifiers":[
        {
            "category":"Insurance",
            "subcategory":"Life Insurance",
            "type":"Services"
        }
    ],
    "sg:phone":"+32 71 81 31 69",
    "sg:postcode":"6220",
    "sg:province":"Hainaut",
    "sg:tags":[
        "assurance"
    ],
    "wof:name":"R. Tilmant",
    "wof:placetype":"venue"
},
  "geometry": {"coordinates":[4.5463218689,50.4834060669],"type":"Point"}
}