{
  "type": "Feature",
  "properties": {
    "addr:full":"Rue De L'orphelinat 5 Bruxelles (anderlecht) Bruxelles-Capitale 1070",
    "addr:housenumber":"5",
    "addr:postcode":"1070",
    "addr:street":"Rue De L'Orphelinat",
    "iso:country":"BE",
    "sg:address":"Rue De L'orphelinat 5",
    "sg:city":"Bruxelles (anderlecht)",
    "sg:classifiers":[
        {
            "category":"Building & Trades",
            "subcategory":"Electrical",
            "type":"Services"
        }
    ],
    "sg:phone":"+32 2 521 92 84",
    "sg:postcode":"1070",
    "sg:province":"Bruxelles-Capitale",
    "sg:tags":[
        "-",
        "electric",
        "contractor"
    ],
    "wof:name":"Elcibat Sprl",
    "wof:placetype":"venue"
},
  "geometry": {"coordinates":[4.3082499504,50.8462638855],"type":"Point"}
}