{
  "type": "Feature",
  "properties": {
    "iso:country":"BE",
    "sg:address":"Liersesteenweg 270",
    "sg:city":"Aarschot",
    "sg:orig_category":"Herstellingen and onderhoud van auto's",
    "sg:phone":"+32 16 57 24 54",
    "sg:postcode":"3200",
    "sg:province":"Vlaams-Brabant",
    "wof:name":"Smedts",
    "wof:placetype":"venue"
},
  "geometry": {"coordinates":[4.8104701042,51.0103797913],"type":"Point"}
}