{
  "type": "Feature",
  "properties": {
    "addr:full":"Vennestraat 331b1 Genk Limburg 3600",
    "addr:housenumber":"331b1",
    "addr:postcode":"3600",
    "addr:street":"Vennestraat",
    "iso:country":"BE",
    "sg:address":"Vennestraat 331b1",
    "sg:city":"Genk",
    "sg:orig_category":"Eclairage et \u00e9quipements du foyer",
    "sg:phone":"+32 89 36 44 41",
    "sg:postcode":"3600",
    "sg:province":"Limburg",
    "wof:name":"Aksent",
    "wof:placetype":"venue"
},
  "geometry": {"coordinates":[5.4867501259,50.9721908569],"type":"Point"}
}