{
  "type": "Feature",
  "properties": {
    "iso:country":"BE",
    "sg:address":"Lepelstraat 5",
    "sg:city":"Staden",
    "sg:classifiers":[
        {
            "category":"Restaurant",
            "type":"Food & Drink"
        }
    ],
    "sg:phone":"+32 51 22 94 30",
    "sg:postcode":"8840",
    "sg:province":"West-Vlaanderen",
    "wof:name":"Claudine Vanthuyne",
    "wof:placetype":"venue"
},
  "geometry": {"coordinates":[3.0585238934,50.9411849976],"type":"Point"}
}