{
  "type": "Feature",
  "properties": {
    "iso:country":"BE",
    "sg:address":"J. De Troozlaan 10",
    "sg:city":"Blankenberge",
    "sg:classifiers":[
        {
            "category":"Health Services",
            "subcategory":"Dentist",
            "type":"Services"
        }
    ],
    "sg:phone":"+32 50 41 75 49",
    "sg:postcode":"8370",
    "sg:province":"West-Vlaanderen",
    "wof:name":"Deketelaere Brigitte",
    "wof:placetype":"venue"
},
  "geometry": {"coordinates":[3.1322131157,51.3144798279],"type":"Point"}
}