{
  "type": "Feature",
  "properties": {
    "addr:full":"Tongersesteenweg 148b Sint-truiden Limburg 3800",
    "addr:housenumber":"148b",
    "addr:postcode":"3800",
    "addr:street":"Tongersesteenweg",
    "iso:country":"BE",
    "sg:address":"Tongersesteenweg 148b",
    "sg:city":"Sint-truiden",
    "sg:classifiers":[
        {
            "category":"Wholesale",
            "subcategory":"Fruits & Vegetables",
            "type":"Manufacturing & Wholesale Goods"
        }
    ],
    "sg:phone":"+32 11 68 26 74",
    "sg:postcode":"3800",
    "sg:province":"Limburg",
    "sg:tags":[
        "whol",
        "-"
    ],
    "wof:name":"Allfru",
    "wof:placetype":"venue"
},
  "geometry": {"coordinates":[5.2025198936,50.8111877441],"type":"Point"}
}