{
  "type": "Feature",
  "properties": {
    "addr:full":"Rue De L'eglise Saint-gilles 41 Bruxelles (saint-gilles) Bruxelles-Capitale 1060",
    "addr:housenumber":"41",
    "addr:postcode":"1060",
    "addr:street":"Rue De L'Eglise Saint-Gilles",
    "iso:country":"BE",
    "sg:address":"Rue De L'eglise Saint-gilles 41",
    "sg:city":"Bruxelles (saint-gilles)",
    "sg:classifiers":[
        {
            "category":"Transit Center",
            "subcategory":"Freight",
            "type":"Transportation"
        }
    ],
    "sg:phone":"+32 2 538 77 75",
    "sg:postcode":"1060",
    "sg:province":"Bruxelles-Capitale",
    "sg:tags":[
        "import",
        "export",
        "-"
    ],
    "wof:name":"Onzam-ex Ets",
    "wof:placetype":"venue"
},
  "geometry": {"coordinates":[4.3426270485,50.8311309814],"type":"Point"}
}