{
  "type": "Feature",
  "properties": {
    "addr:full":"Stationsstraat 23 Kortemark West-Vlaanderen 8610",
    "addr:housenumber":"23",
    "addr:postcode":"8610",
    "addr:street":"Stationsstraat",
    "iso:country":"BE",
    "sg:address":"Stationsstraat 23",
    "sg:city":"Kortemark",
    "sg:classifiers":[
        {
            "category":"Professional",
            "subcategory":"Art Services",
            "type":"Services"
        }
    ],
    "sg:phone":"+32 51 56 63 35",
    "sg:postcode":"8610",
    "sg:province":"West-Vlaanderen",
    "sg:tags":[
        "photography",
        "reporting",
        "-"
    ],
    "wof:name":"Foto Sinaeve",
    "wof:placetype":"venue"
},
  "geometry": {"coordinates":[3.0435600281,51.0253791809],"type":"Point"}
}