{
  "type": "Feature",
  "properties": {
    "iso:country":"BE",
    "sg:address":"Rue Des Pachis 37",
    "sg:city":"Belgium",
    "sg:orig_category":"Artiesten and kunstenaars Plaatsen van vloer- and muurbekleding Schilders",
    "sg:phone":"+32 10 61 56 38",
    "sg:postcode":"1341",
    "sg:province":"Brabant Wallon",
    "wof:name":"Philippe Jadot",
    "wof:placetype":"venue"
},
  "geometry": {"coordinates":[4.5617232323,50.6544570923],"type":"Point"}
}