{
  "type": "Feature",
  "properties": {
    "addr:full":"Rue Turenne 47b Charleroi Hainaut 6000",
    "addr:housenumber":"47b",
    "addr:postcode":"6000",
    "addr:street":"Rue Turenne;Hainaut",
    "iso:country":"BE",
    "sg:address":"Rue Turenne 47b",
    "sg:city":"Charleroi",
    "sg:classifiers":[
        {
            "category":"Bars & Pubs",
            "type":"Food & Drink"
        }
    ],
    "sg:phone":"+32 71 30 35 20",
    "sg:postcode":"6000",
    "sg:province":"Hainaut",
    "wof:name":"Mer Noire",
    "wof:placetype":"venue"
},
  "geometry": {"coordinates":[4.4400620461,50.4119567871],"type":"Point"}
}