{
  "type": "Feature",
  "properties": {
    "addr:full":"Weststraat 55 Ingelmunster West-Vlaanderen 8770",
    "addr:housenumber":"55",
    "addr:postcode":"8770",
    "addr:street":"Weststraat",
    "iso:country":"BE",
    "sg:address":"Weststraat 55",
    "sg:city":"Ingelmunster",
    "sg:orig_category":"Rusthuizen and serviceflats",
    "sg:phone":"+32 51 31 13 03",
    "sg:postcode":"8770",
    "sg:province":"West-Vlaanderen",
    "wof:name":"Residentie De Ermitage",
    "wof:placetype":"venue"
},
  "geometry": {"coordinates":[3.2483100891,50.9215507507],"type":"Point"}
}