{
  "type": "Feature",
  "properties": {
    "addr:full":"Rue De Boussu 84 Dour Hainaut 7370",
    "addr:housenumber":"84",
    "addr:postcode":"7370",
    "addr:street":"Rue De Boussu;Hainaut",
    "iso:country":"BE",
    "sg:address":"Rue De Boussu 84",
    "sg:city":"Dour",
    "sg:orig_category":"Formation permanente",
    "sg:phone":"+32 65 65 24 47",
    "sg:postcode":"7370",
    "sg:province":"Hainaut",
    "wof:name":"Inst.enseign.prom.sociale",
    "wof:placetype":"venue"
},
  "geometry": {"coordinates":[3.7823810577,50.4033966064],"type":"Point"}
}