{
  "type": "Feature",
  "properties": {
    "addr:full":"Rue De L\u00b4h\u00d4tel De Ville 40 La Louvi\u00c8re Hainaut 7100",
    "addr:housenumber":"40",
    "addr:postcode":"7100",
    "addr:street":"Rue De L\u00b4Ho\u0302Tel De Ville",
    "iso:country":"BE",
    "sg:address":"Rue De L\u00b4h\u00d4tel De Ville 40",
    "sg:city":"La Louvi\u00c8re",
    "sg:orig_category":"Schoonheidssalons",
    "sg:phone":"+32 64 22 71 65",
    "sg:postcode":"7100",
    "sg:province":"Hainaut",
    "wof:name":"Marie-france Flandroit",
    "wof:placetype":"venue"
},
  "geometry": {"coordinates":[4.1850848198,50.4748649597],"type":"Point"}
}