{
  "type": "Feature",
  "properties": {
    "addr:full":"Grand-rue 10 Morlanwelz Hainaut 7140",
    "addr:housenumber":"10",
    "addr:postcode":"7140",
    "addr:street":"Grand-Rue",
    "iso:country":"BE",
    "sg:address":"Grand-rue 10",
    "sg:city":"Morlanwelz",
    "sg:orig_category":"Pharmaciens",
    "sg:phone":"+32 64 44 20 62",
    "sg:postcode":"7140",
    "sg:province":"Hainaut",
    "wof:name":"Joel Debuigne",
    "wof:placetype":"venue"
},
  "geometry": {"coordinates":[4.2439498901,50.4551811218],"type":"Point"}
}