{
  "type": "Feature",
  "properties": {
    "addr:full":"Rue De La Ramonette 3 Bouillon Luxembourg 6830",
    "addr:housenumber":"3",
    "addr:postcode":"6830",
    "addr:street":"Rue De La Ramonette",
    "iso:country":"BE",
    "sg:address":"Rue De La Ramonette 3",
    "sg:city":"Bouillon",
    "sg:classifiers":[
        {
            "category":"Farming",
            "subcategory":"Livestock Farm",
            "type":"Manufacturing & Wholesale Goods"
        }
    ],
    "sg:phone":"+32 61 46 90 67",
    "sg:postcode":"6830",
    "sg:province":"Luxembourg",
    "sg:tags":[
        "buyer"
    ],
    "wof:name":"Verdin J",
    "wof:placetype":"venue"
},
  "geometry": {"coordinates":[5.0615382195,49.7873649597],"type":"Point"}
}