{
  "type": "Feature",
  "properties": {
    "iso:country":"BE",
    "sg:address":"Zeelaan 180",
    "sg:city":"Koksijde",
    "sg:classifiers":[
        {
            "category":"Shopping",
            "subcategory":"Antiques",
            "type":"Retail Goods"
        }
    ],
    "sg:phone":"+32 58 28 81 69",
    "sg:postcode":"8670",
    "sg:province":"West-Vlaanderen",
    "wof:name":"Ikoon Antiek",
    "wof:placetype":"venue"
},
  "geometry": {"coordinates":[2.637460947,51.1170120239],"type":"Point"}
}