{
  "type": "Feature",
  "properties": {
    "addr:full":"Duinkerkestraat 40 Poperinge West-Vlaanderen 8970",
    "addr:housenumber":"40",
    "addr:postcode":"8970",
    "addr:street":"Duinkerkestraat",
    "iso:country":"BE",
    "sg:address":"Duinkerkestraat 40",
    "sg:city":"Poperinge",
    "sg:classifiers":[
        {
            "category":"Food & Beverages",
            "subcategory":"Supermarket",
            "type":"Retail Goods"
        }
    ],
    "sg:phone":"+32 57 33 55 61",
    "sg:postcode":"8970",
    "sg:province":"West-Vlaanderen",
    "sg:tags":[
        "department",
        "store"
    ],
    "wof:name":"Louwagie Voedingsmarkt",
    "wof:placetype":"venue"
},
  "geometry": {"coordinates":[2.7200510502,50.8548965454],"type":"Point"}
}