{
  "type": "Feature",
  "properties": {
    "addr:full":"Rue De La Girafe 96 Bouillon (sensenruth) Luxembourg 6832",
    "addr:housenumber":"96",
    "addr:postcode":"6832",
    "addr:street":"Rue De La Girafe",
    "iso:country":"BE",
    "sg:address":"Rue De La Girafe 96",
    "sg:city":"Bouillon (sensenruth)",
    "sg:classifiers":[
        {
            "category":"Fast Food",
            "type":"Food & Drink"
        }
    ],
    "sg:phone":"+32 61 46 73 06",
    "sg:postcode":"6832",
    "sg:province":"Luxembourg",
    "sg:tags":[
        "fried",
        "stand",
        "potato"
    ],
    "wof:name":"Mille-pattes (au)",
    "wof:placetype":"venue"
},
  "geometry": {"coordinates":[5.0727958679,49.8251419067],"type":"Point"}
}