{
  "type": "Feature",
  "properties": {
    "iso:country":"BE",
    "sg:address":"Rue Gaston Delvaux 57",
    "sg:city":"Chastre (cortil-noirmont)",
    "sg:orig_category":"Non-Classified Establishments",
    "sg:phone":"+32 10 65 15 98",
    "sg:postcode":"1450",
    "sg:province":"Brabant Wallon",
    "wof:name":"P.s.o",
    "wof:placetype":"venue"
},
  "geometry": {"coordinates":[4.6469669342,50.6028327942],"type":"Point"}
}