{
  "type": "Feature",
  "properties": {
    "iso:country":"BE",
    "sg:address":"Zeedijk 101",
    "sg:city":"Oostende",
    "sg:classifiers":[
        {
            "category":"Education",
            "subcategory":"School",
            "type":"Public Place"
        }
    ],
    "sg:phone":"+32 59 56 89 80",
    "sg:postcode":"8400",
    "sg:province":"West-Vlaanderen",
    "sg:tags":[
        "boarding"
    ],
    "wof:name":"Kraal Khbo (de)",
    "wof:placetype":"venue"
},
  "geometry": {"coordinates":[2.8936500549,51.2228431702],"type":"Point"}
}