{
  "type": "Feature",
  "properties": {
    "addr:full":"Rue Hyacinthe Docquier 145 Waremme Li\u00e8ge 4300",
    "addr:housenumber":"145",
    "addr:postcode":"4300",
    "addr:street":"Rue Hyacinthe Docquier",
    "iso:country":"BE",
    "sg:address":"Rue Hyacinthe Docquier 145",
    "sg:city":"Waremme",
    "sg:classifiers":[
        {
            "category":"Professional",
            "subcategory":"Accounting & Tax Preparation",
            "type":"Services"
        }
    ],
    "sg:phone":"+32 19 33 25 31",
    "sg:postcode":"4300",
    "sg:province":"Li\u00e8ge",
    "sg:tags":[
        "accountant"
    ],
    "wof:name":"Chaumont C",
    "wof:placetype":"venue"
},
  "geometry": {"coordinates":[5.2796697617,50.6948204041],"type":"Point"}
}