{
  "type": "Feature",
  "properties": {
    "iso:country":"BE",
    "sg:address":"Chauss\u00e9e De Bascoup 170",
    "sg:city":"Anderlues",
    "sg:classifiers":[
        {
            "category":"Banks & Credit Unions",
            "subcategory":"Investment Brokerage",
            "type":"Services"
        }
    ],
    "sg:phone":"+32 71 52 06 38",
    "sg:postcode":"6150",
    "sg:province":"Hainaut",
    "sg:tags":[
        "auditor"
    ],
    "wof:name":"Joye C (mme)",
    "wof:placetype":"venue"
},
  "geometry": {"coordinates":[4.2828388214,50.4156417847],"type":"Point"}
}