{
  "type": "Feature",
  "properties": {
    "addr:full":"Vaarstr 38 Veurne West-Vlaanderen 8630",
    "addr:housenumber":"38",
    "addr:postcode":"8630",
    "addr:street":"Vaarstr",
    "iso:country":"BE",
    "sg:address":"Vaarstr 38",
    "sg:city":"Veurne",
    "sg:classifiers":[
        {
            "category":"Farming",
            "subcategory":"Crops",
            "type":"Manufacturing & Wholesale Goods"
        }
    ],
    "sg:phone":"+32 58 31 10 07",
    "sg:postcode":"8630",
    "sg:province":"West-Vlaanderen",
    "sg:tags":[
        "vegetable",
        "fruit",
        "agriculture",
        "livestock"
    ],
    "wof:name":"Seru & Annoot Nv",
    "wof:placetype":"venue"
},
  "geometry": {"coordinates":[2.6719150543,51.0621986389],"type":"Point"}
}