{
  "type": "Feature",
  "properties": {
    "iso:country":"BE",
    "sg:address":"Paul Chevroletstraat 7",
    "sg:city":"Beersel",
    "sg:orig_category":"Charpentes and couvertures",
    "sg:phone":"+32 2 377 70 29",
    "sg:postcode":"1651",
    "sg:province":"Vlaams-Brabant",
    "wof:name":"Dirk Ophals",
    "wof:placetype":"venue"
},
  "geometry": {"coordinates":[4.2724809647,50.761013031],"type":"Point"}
}