{
  "type": "Feature",
  "properties": {
    "iso:country":"BE",
    "sg:address":"Heirbaan 142",
    "sg:city":"Beveren",
    "sg:orig_category":"Producteurs de fruits",
    "sg:phone":"+32 3 775 21 70",
    "sg:postcode":"9120",
    "sg:province":"Oost-Vlaanderen",
    "wof:name":"Herman Blommaert",
    "wof:placetype":"venue"
},
  "geometry": {"coordinates":[4.2964000702,51.1906776428],"type":"Point"}
}