{
  "type": "Feature",
  "properties": {
    "iso:country":"BE",
    "sg:address":"Hondstraat 29",
    "sg:city":"Tielt",
    "sg:classifiers":[
        {
            "category":"Home & Garden",
            "subcategory":"Carpets & Floor Coverings",
            "type":"Retail Goods"
        }
    ],
    "sg:phone":"+32 51 40 45 26",
    "sg:postcode":"8700",
    "sg:province":"West-Vlaanderen",
    "sg:tags":[
        "layer",
        "mosaicists"
    ],
    "wof:name":"Sierens H",
    "wof:placetype":"venue"
},
  "geometry": {"coordinates":[3.3171739578,51.0052185059],"type":"Point"}
}