{
  "type": "Feature",
  "properties": {
    "iso:country":"BE",
    "sg:address":"Route De Lamorm\u00e9nil 46",
    "sg:city":"Manhay (grandmenil)",
    "sg:classifiers":[
        {
            "category":"Building & Trades",
            "subcategory":"Landscaping Services",
            "type":"Services"
        }
    ],
    "sg:phone":"+32 86 45 58 22",
    "sg:postcode":"6960",
    "sg:province":"Luxembourg",
    "sg:tags":[
        "forestry"
    ],
    "wof:name":"Cornet R",
    "wof:placetype":"venue"
},
  "geometry": {"coordinates":[5.6358428001,50.2571678162],"type":"Point"}
}