{
  "type": "Feature",
  "properties": {
    "iso:country":"BE",
    "sg:address":"Zuivelmarkt 21",
    "sg:city":"Hasselt",
    "sg:classifiers":[
        {
            "category":"Food & Beverages",
            "subcategory":"Meat & Fish",
            "type":"Retail Goods"
        }
    ],
    "sg:phone":"+32 11 23 13 93",
    "sg:postcode":"3500",
    "sg:province":"Limburg",
    "sg:tags":[
        "vi",
        "zeevruchten"
    ],
    "wof:name":"Pacific",
    "wof:placetype":"venue"
},
  "geometry": {"coordinates":[5.3402619362,50.9311523438],"type":"Point"}
}