{
  "type": "Feature",
  "properties": {
    "addr:full":"Rue Des Combattants 12b Chaudfontaine (vaux-sous-ch\u00e8vremont) Li\u00e8ge 4051",
    "addr:housenumber":"12b",
    "addr:postcode":"4051",
    "addr:street":"Rue Des Combattants",
    "iso:country":"BE",
    "sg:address":"Rue Des Combattants 12b",
    "sg:city":"Chaudfontaine (vaux-sous-ch\u00e8vremont)",
    "sg:classifiers":[
        {
            "category":"Real Estate",
            "subcategory":"Architect",
            "type":"Services"
        }
    ],
    "sg:phone":"+32 4 366 11 99",
    "sg:postcode":"4051",
    "sg:province":"Li\u00e8ge",
    "wof:name":"Van Hoye P",
    "wof:placetype":"venue"
},
  "geometry": {"coordinates":[5.629650116,50.6044692993],"type":"Point"}
}