{
  "type": "Feature",
  "properties": {
    "addr:full":"Ninoofsesteenweg 328-330 Anderlecht Bruxelles-Capitale 1070",
    "addr:housenumber":"328-330",
    "addr:postcode":"1070",
    "addr:street":"Ninoofsesteenweg",
    "iso:country":"BE",
    "sg:address":"Ninoofsesteenweg 328-330",
    "sg:city":"Anderlecht",
    "sg:orig_category":"Onderdelen and accessoires voertuigen Gh Onderdelen and accessoires voor auto's",
    "sg:phone":"+32 477 29 03 11",
    "sg:postcode":"1070",
    "sg:province":"Bruxelles-Capitale",
    "wof:name":"Mobil-pneu",
    "wof:placetype":"venue"
},
  "geometry": {"coordinates":[4.3140268326,50.8480453491],"type":"Point"}
}