{
  "type": "Feature",
  "properties": {
    "addr:full":"Meenseheirweg 53 Roeselare West-Vlaanderen 8800",
    "addr:housenumber":"53",
    "addr:postcode":"8800",
    "addr:street":"Meenseheirweg",
    "iso:country":"BE",
    "sg:address":"Meenseheirweg 53",
    "sg:city":"Roeselare",
    "sg:classifiers":[
        {
            "category":"Travel",
            "subcategory":"Travel Agent",
            "type":"Entertainment"
        }
    ],
    "sg:phone":"+32 51 24 82 96",
    "sg:postcode":"8800",
    "sg:province":"West-Vlaanderen",
    "sg:tags":[
        "agency"
    ],
    "wof:name":"Performance Travel Nv",
    "wof:placetype":"venue"
},
  "geometry": {"coordinates":[3.1257998943,50.9368019104],"type":"Point"}
}