{
  "type": "Feature",
  "properties": {
    "iso:country":"BE",
    "sg:address":"Rue De Familleureux 66",
    "sg:city":"Manage",
    "sg:orig_category":"Messageries",
    "sg:phone":"+32 64 55 57 40",
    "sg:postcode":"7170",
    "sg:province":"Hainaut",
    "wof:name":"G F M Services",
    "wof:placetype":"venue"
},
  "geometry": {"coordinates":[4.2327899933,50.5008239746],"type":"Point"}
}