{
  "type": "Feature",
  "properties": {
    "addr:full":"Rue Danvoie 6 Fleurus (lambusart) Hainaut 6220",
    "addr:housenumber":"6",
    "addr:postcode":"6220",
    "addr:street":"Rue Danvoie",
    "iso:country":"BE",
    "sg:address":"Rue Danvoie 6",
    "sg:city":"Fleurus (lambusart)",
    "sg:classifiers":[
        {
            "category":"Building & Trades",
            "subcategory":"Construction",
            "type":"Services"
        }
    ],
    "sg:phone":"+32 71 81 38 61",
    "sg:postcode":"6220",
    "sg:province":"Hainaut",
    "sg:tags":[
        "installation",
        "-",
        "central",
        "heating"
    ],
    "wof:name":"Montoisis Vincent Ets",
    "wof:placetype":"venue"
},
  "geometry": {"coordinates":[4.5496749878,50.4825363159],"type":"Point"}
}