{
  "type": "Feature",
  "properties": {
    "addr:full":"Marktstraat 7 Nieuwpoort West-Vlaanderen 8620",
    "addr:housenumber":"7",
    "addr:postcode":"8620",
    "addr:street":"Marktstraat",
    "iso:country":"BE",
    "sg:address":"Marktstraat 7",
    "sg:city":"Nieuwpoort",
    "sg:classifiers":[
        {
            "category":"Professional",
            "subcategory":"Printing & Photocopies",
            "type":"Services"
        }
    ],
    "sg:phone":"+32 58 23 37 26",
    "sg:postcode":"8620",
    "sg:province":"West-Vlaanderen",
    "sg:tags":[
        "-",
        "offset"
    ],
    "wof:name":"Dumon Drukkerij",
    "wof:placetype":"venue"
},
  "geometry": {"coordinates":[2.7518830299,51.1317863464],"type":"Point"}
}