{
  "type": "Feature",
  "properties": {
    "addr:full":"Rue De L'am\u00c9rique 55 Chiny Luxembourg 6810",
    "addr:housenumber":"55",
    "addr:postcode":"6810",
    "addr:street":"Rue De L'Ame \u0301Rique",
    "iso:country":"BE",
    "sg:address":"Rue De L'am\u00c9rique 55",
    "sg:city":"Chiny",
    "sg:orig_category":"Installatie van houten of kunststof schrijnwerk",
    "sg:phone":"+32 61 31 35 92",
    "sg:postcode":"6810",
    "sg:province":"Luxembourg",
    "wof:name":"Claude Raymond Et Fils",
    "wof:placetype":"venue"
},
  "geometry": {"coordinates":[5.3797559738,49.679775238],"type":"Point"}
}