{
  "type": "Feature",
  "properties": {
    "addr:full":"Dr\u00e8ve Des Chasseurs 27 Waterloo Brabant Wallon 1410",
    "addr:housenumber":"27",
    "addr:postcode":"1410",
    "addr:street":"Dre\u0300Ve Des Chasseurs",
    "iso:country":"BE",
    "sg:address":"Dr\u00e8ve Des Chasseurs 27",
    "sg:city":"Waterloo",
    "sg:classifiers":[
        {
            "category":"Home & Garden",
            "subcategory":"Kitchen Supply",
            "type":"Retail Goods"
        }
    ],
    "sg:phone":"+32 2 351 46 41",
    "sg:postcode":"1410",
    "sg:province":"Brabant Wallon",
    "sg:tags":[
        "equipment",
        "baker",
        "-"
    ],
    "wof:name":"Ecomec Sa",
    "wof:placetype":"venue"
},
  "geometry": {"coordinates":[4.393348217,50.7318534851],"type":"Point"}
}