{
  "type": "Feature",
  "properties": {
    "addr:full":"Rue Sous Lieutenant Catoire 19 Moeskroen/mouscron Hainaut 7711",
    "addr:housenumber":"19",
    "addr:postcode":"7711",
    "addr:street":"Rue Sous Lieutenant Catoire",
    "iso:country":"BE",
    "sg:address":"Rue Sous Lieutenant Catoire 19",
    "sg:city":"Moeskroen/mouscron",
    "sg:orig_category":"Rev\u00eatements pour sols and murs. Peinture",
    "sg:phone":"+32 56 48 76 03",
    "sg:postcode":"7711",
    "sg:province":"Hainaut",
    "wof:name":"Vanmeenen",
    "wof:placetype":"venue"
},
  "geometry": {"coordinates":[3.3126978874,50.7229728699],"type":"Point"}
}