{
  "type": "Feature",
  "properties": {
    "iso:country":"BE",
    "sg:address":"Kerkstraat 12",
    "sg:city":"Aalst",
    "sg:orig_category":"Banken and kredietinstellingen",
    "sg:phone":"+32 53 21 58 90",
    "sg:postcode":"9308",
    "sg:province":"Oost-Vlaanderen",
    "wof:name":"Bbl",
    "wof:placetype":"venue"
},
  "geometry": {"coordinates":[4.039894104,50.9382514954],"type":"Point"}
}