{
  "type": "Feature",
  "properties": {
    "addr:full":"Pathoekeweg 48 Brugge West-Vlaanderen 8000",
    "addr:housenumber":"48",
    "addr:postcode":"8000",
    "addr:street":"Pathoekeweg",
    "iso:country":"BE",
    "sg:address":"Pathoekeweg 48",
    "sg:city":"Brugge",
    "sg:orig_category":"Randstad Tijdelijke werkgelegenheid and uitzendkantoren",
    "sg:phone":"+32 50 32 98 50",
    "sg:postcode":"8000",
    "sg:province":"West-Vlaanderen",
    "wof:name":"Randstad",
    "wof:placetype":"venue"
},
  "geometry": {"coordinates":[3.2149169445,51.2262611389],"type":"Point"}
}