{
  "type": "Feature",
  "properties": {
    "addr:full":"Marktplein 9 Sint-lievens-houtem Oost-Vlaanderen 9520",
    "addr:housenumber":"9",
    "addr:postcode":"9520",
    "addr:street":"Marktplein;Oost-Vlaanderen",
    "iso:country":"BE",
    "sg:address":"Marktplein 9",
    "sg:city":"Sint-lievens-houtem",
    "sg:orig_category":"Pharmaciens",
    "sg:phone":"+32 53 62 36 85",
    "sg:postcode":"9520",
    "sg:province":"Oost-Vlaanderen",
    "wof:name":"Regina Faket",
    "wof:placetype":"venue"
},
  "geometry": {"coordinates":[3.858757019,50.9199562073],"type":"Point"}
}