{
  "type": "Feature",
  "properties": {
    "iso:country":"BE",
    "sg:address":"Rue Ernest Matagne 17",
    "sg:city":"Assesse",
    "sg:classifiers":[
        {
            "category":"Home & Garden",
            "subcategory":"Building Materials",
            "type":"Retail Goods"
        }
    ],
    "sg:phone":"+32 83 65 57 96",
    "sg:postcode":"5330",
    "sg:province":"Namur",
    "sg:tags":[
        "granite",
        "stone",
        "natural",
        "marble"
    ],
    "wof:name":"Pigrama Sprl",
    "wof:placetype":"venue"
},
  "geometry": {"coordinates":[5.0474438667,50.3686523438],"type":"Point"}
}