{
  "type": "Feature",
  "properties": {
    "addr:full":"Rue De Lenny 7 Hamois Namur 5360",
    "addr:housenumber":"7",
    "addr:postcode":"5360",
    "addr:street":"Rue De Lenny",
    "iso:country":"BE",
    "sg:address":"Rue De Lenny 7",
    "sg:city":"Hamois",
    "sg:orig_category":"Landmeters",
    "sg:phone":"+32 83 21 44 94",
    "sg:postcode":"5360",
    "sg:province":"Namur",
    "wof:name":"Philippe Biname",
    "wof:placetype":"venue"
},
  "geometry": {"coordinates":[5.0605092049,50.3349266052],"type":"Point"}
}