{
  "type": "Feature",
  "properties": {
    "iso:country":"BE",
    "sg:address":"Justitieplein 5",
    "sg:city":"Dendermonde",
    "sg:orig_category":"Advocaten and juridische adviseurs",
    "sg:phone":"+32 52 20 15 03",
    "sg:postcode":"9200",
    "sg:province":"Oost-Vlaanderen",
    "wof:name":"Annouk Segers",
    "wof:placetype":"venue"
},
  "geometry": {"coordinates":[4.098965168,51.0316963196],"type":"Point"}
}