{
  "type": "Feature",
  "properties": {
    "iso:country":"BE",
    "sg:address":"Kerkstraat 207",
    "sg:city":"Deerlijk",
    "sg:classifiers":[
        {
            "category":"Freight",
            "type":"Transportation"
        }
    ],
    "sg:phone":"+32 56 77 78 15",
    "sg:postcode":"8540",
    "sg:province":"West-Vlaanderen",
    "sg:tags":[
        "-",
        "transport"
    ],
    "wof:name":"Defoirdt Bvba",
    "wof:placetype":"venue"
},
  "geometry": {"coordinates":[3.384732008,50.8288993835],"type":"Point"}
}