{
  "type": "Feature",
  "properties": {
    "addr:full":"Moleneinde 43 Lochristi Oost-Vlaanderen 9080",
    "addr:housenumber":"43",
    "addr:postcode":"9080",
    "addr:street":"Moleneinde",
    "iso:country":"BE",
    "sg:address":"Moleneinde 43",
    "sg:city":"Lochristi",
    "sg:orig_category":"Bagage and lederwaren Schoenen",
    "sg:phone":"+32 9 355 19 45",
    "sg:postcode":"9080",
    "sg:province":"Oost-Vlaanderen",
    "wof:name":"Huis Pasquali",
    "wof:placetype":"venue"
},
  "geometry": {"coordinates":[3.8559119701,51.1304893494],"type":"Point"}
}