{
  "type": "Feature",
  "properties": {
    "iso:country":"BE",
    "sg:address":"Rue Des Allies 63",
    "sg:city":"Forrieres",
    "sg:orig_category":"Huisdieren and benodigdheden Royal Canin",
    "sg:phone":"+32 84 36 73 77",
    "sg:postcode":"6953",
    "sg:province":"Luxembourg",
    "wof:name":"Deflandre",
    "wof:placetype":"venue"
},
  "geometry": {"coordinates":[5.2837362289,50.1337509155],"type":"Point"}
}