{
  "type": "Feature",
  "properties": {
    "addr:full":"Zandstraat 36-38 Herentals Antwerpen 2200",
    "addr:postcode":"36-38;2200",
    "addr:street":"Zandstraat",
    "iso:country":"BE",
    "sg:address":"Zandstraat 36-38",
    "sg:city":"Herentals",
    "sg:orig_category":"Juwelen and horloges Swatch",
    "sg:phone":"+32 14 21 17 58",
    "sg:postcode":"2200",
    "sg:province":"Antwerpen",
    "wof:name":"Juwelier De Vooght",
    "wof:placetype":"venue"
},
  "geometry": {"coordinates":[4.834253788,51.1769180298],"type":"Point"}
}