{
  "type": "Feature",
  "properties": {
    "addr:full":"Tragel 7 Aalst Oost-Vlaanderen 9300",
    "addr:housenumber":"7",
    "addr:postcode":"9300",
    "addr:street":"Tragel",
    "iso:country":"BE",
    "sg:address":"Tragel 7",
    "sg:city":"Aalst",
    "sg:classifiers":[
        {
            "category":"Fast Food",
            "type":"Food & Drink"
        }
    ],
    "sg:phone":"+32 53 21 10 49",
    "sg:postcode":"9300",
    "sg:province":"Oost-Vlaanderen",
    "sg:tags":[
        "\u00c0",
        "restaurants",
        "emporter",
        "restaurant"
    ],
    "wof:name":"Estaminette Daens",
    "wof:placetype":"venue"
},
  "geometry": {"coordinates":[4.0364379883,50.9476966858],"type":"Point"}
}