{
  "type": "Feature",
  "properties": {
    "iso:country":"BE",
    "sg:address":"Oude Wijnendalestraat 48",
    "sg:city":"Torhout",
    "sg:classifiers":[
        {
            "category":"Health Services",
            "subcategory":"Nursing And Care Facility",
            "type":"Services"
        }
    ],
    "sg:phone":"+32 475 49 12 61",
    "sg:postcode":"8820",
    "sg:province":"West-Vlaanderen",
    "sg:tags":[
        "home"
    ],
    "wof:name":"Lanckriet Marijke",
    "wof:placetype":"venue"
},
  "geometry": {"coordinates":[3.0754408836,51.0841064453],"type":"Point"}
}