{
  "type": "Feature",
  "properties": {
    "iso:country":"BE",
    "sg:address":"Prins-bisschopssingel 4074",
    "sg:city":"Hasselt",
    "sg:classifiers":[
        {
            "category":"Retail",
            "subcategory":"Auto Repair",
            "type":"Services"
        }
    ],
    "sg:phone":"+32 11 28 33 90",
    "sg:postcode":"3500",
    "sg:province":"Limburg",
    "sg:tags":[
        "garage"
    ],
    "wof:name":"V.j.b. Motors",
    "wof:placetype":"venue"
},
  "geometry": {"coordinates":[5.338121891,50.9136199951],"type":"Point"}
}