{
  "type": "Feature",
  "properties": {
    "addr:full":"Rue Du Coll\u00c8ge 49 Verviers Li\u00e8ge 4800",
    "addr:housenumber":"49",
    "addr:postcode":"4800",
    "addr:street":"Rue Du Colle\u0300Ge",
    "iso:country":"BE",
    "sg:address":"Rue Du Coll\u00c8ge 49",
    "sg:city":"Verviers",
    "sg:orig_category":"Instituts pour enfants en difficult\u00e9. Orphelinats",
    "sg:phone":"+32 87 30 73 07",
    "sg:postcode":"4800",
    "sg:province":"Li\u00e8ge",
    "wof:name":"Maison D\u00b4enfants Cpas",
    "wof:placetype":"venue"
},
  "geometry": {"coordinates":[5.8642611504,50.5945587158],"type":"Point"}
}