{
  "type": "Feature",
  "properties": {
    "iso:country":"BE",
    "sg:address":"Uilenstraat 59",
    "sg:city":"Sint-pieters-woluwe/woluwe-saint-pierre",
    "sg:orig_category":"Imprimeries and copyshops. Secr\u00e9tariats",
    "sg:phone":"+32 2 772 42 50",
    "sg:postcode":"1150",
    "sg:province":"Bruxelles-Capitale",
    "wof:name":"Georges Packmans",
    "wof:placetype":"venue"
},
  "geometry": {"coordinates":[4.4593639374,50.8430366516],"type":"Point"}
}