{
  "type": "Feature",
  "properties": {
    "iso:country":"BE",
    "sg:address":"Smetledestraat 32",
    "sg:city":"Wetteren",
    "sg:classifiers":[
        {
            "category":"Communications",
            "subcategory":"News Services",
            "type":"Services"
        }
    ],
    "sg:phone":"+32 9 366 69 17",
    "sg:postcode":"9230",
    "sg:province":"Oost-Vlaanderen",
    "sg:tags":[
        "illustrator"
    ],
    "wof:name":"Graphshopper",
    "wof:placetype":"venue"
},
  "geometry": {"coordinates":[3.8968760967,50.9954948425],"type":"Point"}
}