{
  "type": "Feature",
  "properties": {
    "addr:full":"Viaductstraat 57 Elsene/ixelles Bruxelles-Capitale 1050",
    "addr:housenumber":"57",
    "addr:postcode":"1050",
    "addr:street":"Viaductstraat",
    "iso:country":"BE",
    "sg:address":"Viaductstraat 57",
    "sg:city":"Elsene/ixelles",
    "sg:orig_category":"Artsen and specialisten",
    "sg:phone":"+32 2 640 39 36",
    "sg:postcode":"1050",
    "sg:province":"Bruxelles-Capitale",
    "wof:name":"Guy Van Passel",
    "wof:placetype":"venue"
},
  "geometry": {"coordinates":[4.3700652122,50.8331565857],"type":"Point"}
}