{
  "type": "Feature",
  "properties": {
    "iso:country":"BE",
    "sg:address":"Twee Dreven 71",
    "sg:city":"Sint-martens-latem",
    "sg:orig_category":"Loodgieterij, verwarming and sanitaire installaties Schoonmaakbedrijven and ongediertebestrijding",
    "sg:phone":"+32 9 282 69 54",
    "sg:postcode":"9830",
    "sg:province":"Oost-Vlaanderen",
    "wof:name":"Willy De Clercq",
    "wof:placetype":"venue"
},
  "geometry": {"coordinates":[3.6346580982,50.9997215271],"type":"Point"}
}