{
  "type": "Feature",
  "properties": {
    "addr:full":"Bergenstraat 37 Oud-heverlee Vlaams-Brabant 3053",
    "addr:housenumber":"37",
    "addr:postcode":"3053",
    "addr:street":"Bergenstraat",
    "iso:country":"BE",
    "sg:address":"Bergenstraat 37",
    "sg:city":"Oud-heverlee",
    "sg:orig_category":"Producteurs de l\u00e9gumes. Fruits and l\u00e9gumes Gr",
    "sg:phone":"+32 16 40 18 54",
    "sg:postcode":"3053",
    "sg:province":"Vlaams-Brabant",
    "wof:name":"Guillaume Evers",
    "wof:placetype":"venue"
},
  "geometry": {"coordinates":[4.7358121872,50.8282585144],"type":"Point"}
}