{
  "type": "Feature",
  "properties": {
    "addr:full":"Proosdijstraat 58 Oostkamp (hertsberge) West-Vlaanderen 8020",
    "addr:housenumber":"58",
    "addr:postcode":"8020",
    "addr:street":"Proosdijstraat",
    "iso:country":"BE",
    "sg:address":"Proosdijstraat 58",
    "sg:city":"Oostkamp (hertsberge)",
    "sg:classifiers":[
        {
            "category":"Building & Trades",
            "subcategory":"Electrical",
            "type":"Services"
        }
    ],
    "sg:phone":"+32 50 27 51 31",
    "sg:postcode":"8020",
    "sg:province":"West-Vlaanderen",
    "sg:tags":[
        "electric",
        "-",
        "housewiring",
        "contractor"
    ],
    "wof:name":"Pyfferoen Lieven Electro Bvba",
    "wof:placetype":"venue"
},
  "geometry": {"coordinates":[3.2663459778,51.1064605713],"type":"Point"}
}