{
  "type": "Feature",
  "properties": {
    "iso:country":"BE",
    "sg:address":"Rue Des Balaives 2",
    "sg:city":"Erpent",
    "sg:orig_category":"Dakwerken",
    "sg:phone":"+32 81 30 54 06",
    "sg:postcode":"5101",
    "sg:province":"Namur",
    "wof:name":"Etablissement Michel Wynants",
    "wof:placetype":"venue"
},
  "geometry": {"coordinates":[4.9064679146,50.4420623779],"type":"Point"}
}