{
  "type": "Feature",
  "properties": {
    "iso:country":"BE",
    "sg:address":"Place Royale 21-23",
    "sg:city":"Spa",
    "sg:classifiers":[
        {
            "category":"Travel",
            "subcategory":"Hotels & Motels",
            "type":"Entertainment"
        }
    ],
    "sg:phone":"+32 87 77 10 64",
    "sg:postcode":"4900",
    "sg:province":"Li\u00e8ge",
    "wof:name":"Cardinal (h\u00f4tel)",
    "wof:placetype":"venue"
},
  "geometry": {"coordinates":[5.8634161949,50.4927482605],"type":"Point"}
}