{
  "type": "Feature",
  "properties": {
    "iso:country":"BE",
    "sg:address":"Stationsstraat 32",
    "sg:city":"Lanaken",
    "sg:classifiers":[
        {
            "category":"Fast Food",
            "type":"Food & Drink"
        }
    ],
    "sg:phone":"+32 89 71 38 76",
    "sg:postcode":"3620",
    "sg:province":"Limburg",
    "sg:tags":[
        "\u00c0",
        "restaurants",
        "emporter",
        "restaurant"
    ],
    "wof:name":"Restaurant Piccadilly",
    "wof:placetype":"venue"
},
  "geometry": {"coordinates":[5.649793148,50.8884353638],"type":"Point"}
}