{
  "type": "Feature",
  "properties": {
    "addr:full":"Rue De La Station 52 Viroinval Namur 5670",
    "addr:housenumber":"52",
    "addr:postcode":"5670",
    "addr:street":"Rue De La Station",
    "iso:country":"BE",
    "sg:address":"Rue De La Station 52",
    "sg:city":"Viroinval",
    "sg:classifiers":[
        {
            "category":"Arena",
            "subcategory":"Sports Club",
            "type":"Entertainment"
        }
    ],
    "sg:phone":"+32 60 31 13 02",
    "sg:postcode":"5670",
    "sg:province":"Namur",
    "sg:tags":[
        "terrain",
        "hors",
        "de",
        "installation",
        "sportifs"
    ],
    "wof:name":"O.c. Nismes",
    "wof:placetype":"venue"
},
  "geometry": {"coordinates":[4.5529499054,50.0813598633],"type":"Point"}
}