{
  "type": "Feature",
  "properties": {
    "iso:country":"BE",
    "sg:address":"Albert Woutersstraat 154",
    "sg:city":"Leuven",
    "sg:orig_category":"Bloemen and planten",
    "sg:phone":"+32 16 22 91 11",
    "sg:postcode":"3012",
    "sg:province":"Vlaams-Brabant",
    "wof:name":"Beatrice Verhoeven",
    "wof:placetype":"venue"
},
  "geometry": {"coordinates":[4.6958599091,50.8897743225],"type":"Point"}
}