{
  "type": "Feature",
  "properties": {
    "iso:country":"BE",
    "sg:address":"Sijselestraat 91",
    "sg:city":"Beernem (oedelem)",
    "sg:classifiers":[
        {
            "category":"Retail",
            "subcategory":"Repair Shop",
            "type":"Services"
        }
    ],
    "sg:phone":"+32 50 37 01 40",
    "sg:postcode":"8730",
    "sg:province":"West-Vlaanderen",
    "sg:tags":[
        "-",
        "clothing",
        "alteration"
    ],
    "wof:name":"Geirnaert P",
    "wof:placetype":"venue"
},
  "geometry": {"coordinates":[3.3312780857,51.1905593872],"type":"Point"}
}