{
  "type": "Feature",
  "properties": {
    "iso:country":"BE",
    "sg:address":"Aartrijkestraat 6",
    "sg:city":"Torhout",
    "sg:orig_category":"Maatschappelijke dienstverlening Zalen voor culturele evenementen",
    "sg:phone":"+32 50 22 11 50",
    "sg:postcode":"8820",
    "sg:province":"West-Vlaanderen",
    "wof:name":"Cult.centrum De Brouckere - Jip",
    "wof:placetype":"venue"
},
  "geometry": {"coordinates":[3.1013169289,51.066986084],"type":"Point"}
}