{
  "type": "Feature",
  "properties": {
    "addr:full":"Rue Albert I 78a Hannut Li\u00e8ge 4280",
    "addr:housenumber":"78a",
    "addr:postcode":"4280",
    "addr:street":"Rue Albert I",
    "iso:country":"BE",
    "sg:address":"Rue Albert I 78a",
    "sg:city":"Hannut",
    "sg:classifiers":[
        {
            "category":"Banks & Credit Unions",
            "subcategory":"Financial Services",
            "type":"Services"
        }
    ],
    "sg:phone":"+32 19 51 22 10",
    "sg:postcode":"4280",
    "sg:province":"Li\u00e8ge",
    "sg:tags":[
        "loan",
        "mortgage"
    ],
    "wof:name":"Bureau Tourneur G & Cie Sa",
    "wof:placetype":"venue"
},
  "geometry": {"coordinates":[5.0835189819,50.6692047119],"type":"Point"}
}