{
  "type": "Feature",
  "properties": {
    "iso:country":"BE",
    "sg:address":"Dorpsstraat 45",
    "sg:city":"Zulte (machelen)",
    "sg:classifiers":[
        {
            "category":"Health Services",
            "subcategory":"Health Practitioner",
            "type":"Services"
        }
    ],
    "sg:phone":"+32 9 386 96 31",
    "sg:postcode":"9870",
    "sg:province":"Oost-Vlaanderen",
    "sg:tags":[
        "physiotherapist"
    ],
    "wof:name":"De Smet Veerle",
    "wof:placetype":"venue"
},
  "geometry": {"coordinates":[3.4896020889,50.9580192566],"type":"Point"}
}