{
  "type": "Feature",
  "properties": {
    "iso:country":"BE",
    "sg:address":"Kapelstraat 92",
    "sg:city":"Bornem",
    "sg:classifiers":[
        {
            "category":"Home & Garden",
            "subcategory":"Home Furnishings",
            "type":"Retail Goods"
        }
    ],
    "sg:phone":"+32 3 889 07 13",
    "sg:postcode":"2880",
    "sg:province":"Antwerpen",
    "sg:tags":[
        "interior",
        "decoration"
    ],
    "wof:name":"Schilders Woningdekoratie Bvba",
    "wof:placetype":"venue"
},
  "geometry": {"coordinates":[4.2350091934,51.095741272],"type":"Point"}
}