{
  "type": "Feature",
  "properties": {
    "iso:country":"BE",
    "sg:address":"Smederijstraat 14",
    "sg:city":"Brecht (sint-job-in-'t Goor)",
    "sg:classifiers":[
        {
            "category":"Utilities",
            "subcategory":"Refuse",
            "type":"Services"
        }
    ],
    "sg:phone":"+32 3 633 26 61",
    "sg:postcode":"2960",
    "sg:province":"Antwerpen",
    "sg:tags":[
        "catering"
    ],
    "wof:name":"Multisnack Bvba",
    "wof:placetype":"venue"
},
  "geometry": {"coordinates":[4.5516281128,51.3010025024],"type":"Point"}
}