{
  "type": "Feature",
  "properties": {
    "addr:full":"Vis\u00e9steenweg 168 Riemst Limburg 3770",
    "addr:housenumber":"168",
    "addr:postcode":"3770",
    "addr:street":"Vise\u0301Steenweg",
    "iso:country":"BE",
    "sg:address":"Vis\u00e9steenweg 168",
    "sg:city":"Riemst",
    "sg:classifiers":[
        {
            "category":"Building & Trades",
            "subcategory":"Plumbing",
            "type":"Services"
        }
    ],
    "sg:phone":"+32 12 45 13 65",
    "sg:postcode":"3770",
    "sg:province":"Limburg",
    "sg:tags":[
        "repair",
        "mainten",
        "-",
        "central",
        "heating"
    ],
    "wof:name":"Heedfeld Nv Verwarming&sanitai Nv",
    "wof:placetype":"venue"
},
  "geometry": {"coordinates":[5.606347084,50.8036117554],"type":"Point"}
}