{
  "type": "Feature",
  "properties": {
    "iso:country":"BE",
    "sg:address":"Edestraat 19",
    "sg:city":"Maldegem",
    "sg:classifiers":[
        {
            "category":"Insurance",
            "subcategory":"Life Insurance",
            "type":"Services"
        }
    ],
    "sg:phone":"+32 50 71 53 04",
    "sg:postcode":"9990",
    "sg:province":"Oost-Vlaanderen",
    "sg:tags":[
        "assurance"
    ],
    "wof:name":"Codevas",
    "wof:placetype":"venue"
},
  "geometry": {"coordinates":[3.4468300343,51.2102851868],"type":"Point"}
}