{
  "type": "Feature",
  "properties": {
    "iso:country":"BE",
    "sg:address":"Rue Ernest Solvay 48",
    "sg:city":"Les Bons Villers (mellet)",
    "sg:classifiers":[
        {
            "category":"Health Services",
            "subcategory":"Health Practitioner",
            "type":"Services"
        }
    ],
    "sg:phone":"+32 71 85 16 58",
    "sg:postcode":"6211",
    "sg:province":"Hainaut",
    "sg:tags":[
        "physiotherapist"
    ],
    "wof:name":"Baquet Stephane",
    "wof:placetype":"venue"
},
  "geometry": {"coordinates":[4.4791898727,50.5055961609],"type":"Point"}
}