{
  "type": "Feature",
  "properties": {
    "addr:full":"Vissersstraat 2bb Oudenburg West-Vlaanderen 8460",
    "addr:housenumber":"2bb",
    "addr:postcode":"8460",
    "addr:street":"Vissersstraat",
    "iso:country":"BE",
    "sg:address":"Vissersstraat 2bb",
    "sg:city":"Oudenburg",
    "sg:orig_category":"Traitements param\u00e9dicaux",
    "sg:phone":"+32 59 26 86 56",
    "sg:postcode":"8460",
    "sg:province":"West-Vlaanderen",
    "wof:name":"D. De Coene",
    "wof:placetype":"venue"
},
  "geometry": {"coordinates":[2.9995100498,51.1861190796],"type":"Point"}
}