{
  "type": "Feature",
  "properties": {
    "addr:full":"Avenue De Waterloo 58 Charleroi Hainaut 6000",
    "addr:housenumber":"58",
    "addr:postcode":"6000",
    "addr:street":"Avenue De Waterloo;Hainaut",
    "iso:country":"BE",
    "sg:address":"Avenue De Waterloo 58",
    "sg:city":"Charleroi",
    "sg:orig_category":"Huishoudapparaten, televisies and radio's",
    "sg:phone":"+32 71 70 25 87",
    "sg:postcode":"6000",
    "sg:province":"Hainaut",
    "wof:name":"Maison Telfusion",
    "wof:placetype":"venue"
},
  "geometry": {"coordinates":[4.4485177994,50.4156951904],"type":"Point"}
}