{
  "type": "Feature",
  "properties": {
    "addr:full":"Ingberthoeveweg 17 Aartselaar Antwerpen 2630",
    "addr:housenumber":"17",
    "addr:postcode":"2630",
    "addr:street":"Ingberthoeveweg",
    "iso:country":"BE",
    "sg:address":"Ingberthoeveweg 17",
    "sg:city":"Aartselaar",
    "sg:classifiers":[
        {
            "category":"Health Services",
            "subcategory":"Hospital",
            "type":"Services"
        }
    ],
    "sg:phone":"+32 3 450 65 00",
    "sg:postcode":"2630",
    "sg:province":"Antwerpen",
    "sg:tags":[
        "hygiene"
    ],
    "wof:name":"Rentokil Initial Nv",
    "wof:placetype":"venue"
},
  "geometry": {"coordinates":[4.3957810402,51.1492080688],"type":"Point"}
}