{
  "type": "Feature",
  "properties": {
    "addr:full":"Rue Pre Au Loup 47 Naninne Namur 5100",
    "addr:housenumber":"47",
    "addr:postcode":"5100",
    "addr:street":"Rue Pre Au Loup",
    "iso:country":"BE",
    "sg:address":"Rue Pre Au Loup 47",
    "sg:city":"Naninne",
    "sg:orig_category":"Royal Canin. Eleveurs d'animaux domestiques. Services pour animaux domestiques",
    "sg:phone":"+32 81 40 28 07",
    "sg:postcode":"5100",
    "sg:province":"Namur",
    "wof:name":"Scardina Bonnaillie",
    "wof:placetype":"venue"
},
  "geometry": {"coordinates":[4.9320049286,50.4172592163],"type":"Point"}
}