{
  "type": "Feature",
  "properties": {
    "iso:country":"BE",
    "sg:address":"Salvialaan 2",
    "sg:city":"Nijlen",
    "sg:classifiers":[
        {
            "category":"Building & Trades",
            "subcategory":"Construction",
            "type":"Services"
        }
    ],
    "sg:phone":"+32 3 481 99 39",
    "sg:postcode":"2560",
    "sg:province":"Antwerpen",
    "sg:tags":[
        "stucco",
        "contractor"
    ],
    "wof:name":"Verhaegen Hedwig",
    "wof:placetype":"venue"
},
  "geometry": {"coordinates":[4.6606388092,51.1621704102],"type":"Point"}
}