{
  "type": "Feature",
  "properties": {
    "iso:country":"BE",
    "sg:address":"Rue Hamoir 7",
    "sg:city":"La Louvi\u00e8re",
    "sg:classifiers":[
        {
            "category":"Cafe",
            "type":"Food & Drink"
        }
    ],
    "sg:phone":"+32 64 26 79 99",
    "sg:postcode":"7100",
    "sg:province":"Hainaut",
    "sg:tags":[
        "snack-bars"
    ],
    "wof:name":"Bruit Qui Court (le)",
    "wof:placetype":"venue"
},
  "geometry": {"coordinates":[4.1869912148,50.4750137329],"type":"Point"}
}