{
  "type": "Feature",
  "properties": {
    "iso:country":"BE",
    "sg:address":"Steenweg Blaasveld 72",
    "sg:city":"Mechelen",
    "sg:classifiers":[
        {
            "category":"Real Estate",
            "subcategory":"Developer",
            "type":"Services"
        }
    ],
    "sg:phone":"+32 3 886 53 22",
    "sg:postcode":"2801",
    "sg:province":"Antwerpen",
    "sg:tags":[
        "plomberie",
        "chauffage",
        "mat\u00e9riel",
        "gr",
        "pour"
    ],
    "wof:name":"Aqua-claro",
    "wof:placetype":"venue"
},
  "geometry": {"coordinates":[4.4079771042,51.0472412109],"type":"Point"}
}