{
  "type": "Feature",
  "properties": {
    "addr:full":"Leiestraat 13 Wervik West-Vlaanderen 8940",
    "addr:housenumber":"13",
    "addr:postcode":"8940",
    "addr:street":"Leiestraat",
    "iso:country":"BE",
    "sg:address":"Leiestraat 13",
    "sg:city":"Wervik",
    "sg:orig_category":"Kansspelen",
    "sg:phone":"+32 56 31 20 92",
    "sg:postcode":"8940",
    "sg:province":"West-Vlaanderen",
    "wof:name":"Ladbroke",
    "wof:placetype":"venue"
},
  "geometry": {"coordinates":[3.0428249836,50.7773780823],"type":"Point"}
}