{
  "type": "Feature",
  "properties": {
    "iso:country":"BE",
    "sg:address":"Brugsesteenweg 57",
    "sg:city":"De Haan",
    "sg:orig_category":"V\u00eatements, chaussures and accessoires Gr",
    "sg:phone":"+32 50 41 65 15",
    "sg:postcode":"8420",
    "sg:province":"West-Vlaanderen",
    "wof:name":"Sunoptics",
    "wof:placetype":"venue"
},
  "geometry": {"coordinates":[3.0846810341,51.2956123352],"type":"Point"}
}