{
  "type": "Feature",
  "properties": {
    "addr:full":"Avenue Des Belettes 46 Ukkel/uccle Bruxelles-Capitale 1180",
    "addr:housenumber":"46",
    "addr:postcode":"1180",
    "addr:street":"Avenue Des Belettes;/",
    "iso:country":"BE",
    "sg:address":"Avenue Des Belettes 46",
    "sg:city":"Ukkel/uccle",
    "sg:orig_category":"Instituts de beaut\u00e9. Traitements param\u00e9dicaux",
    "sg:phone":"+32 2 374 80 88",
    "sg:postcode":"1180",
    "sg:province":"Bruxelles-Capitale",
    "wof:name":"Josiane De Raeck",
    "wof:placetype":"venue"
},
  "geometry": {"coordinates":[4.345993042,50.7772674561],"type":"Point"}
}