{
  "type": "Feature",
  "properties": {
    "iso:country":"BE",
    "sg:address":"Minneveldstraat 44",
    "sg:city":"Kortenberg",
    "sg:orig_category":"Non-Classified Establishments",
    "sg:phone":"+32 2 759 90 37",
    "sg:postcode":"3070",
    "sg:province":"Vlaams-Brabant",
    "wof:name":"Ellito Bvba",
    "wof:placetype":"venue"
},
  "geometry": {"coordinates":[4.5453262329,50.8867340088],"type":"Point"}
}