{
  "type": "Feature",
  "properties": {
    "addr:full":"Washingtonstraat 36 Elsene/ixelles Bruxelles-Capitale 1050",
    "addr:housenumber":"36",
    "addr:postcode":"1050",
    "addr:street":"Washingtonstraat",
    "iso:country":"BE",
    "sg:address":"Washingtonstraat 36",
    "sg:city":"Elsene/ixelles",
    "sg:orig_category":"Boekhouders",
    "sg:phone":"+32 2 647 12 82",
    "sg:postcode":"1050",
    "sg:province":"Bruxelles-Capitale",
    "wof:name":"Christian Dardilhac",
    "wof:placetype":"venue"
},
  "geometry": {"coordinates":[4.3635239601,50.8251304626],"type":"Point"}
}