{
  "type": "Feature",
  "properties": {
    "addr:full":"Boulevard Lalaing 33 Tournai Hainaut 7500",
    "addr:housenumber":"33",
    "addr:postcode":"7500",
    "addr:street":"Boulevard Lalaing",
    "iso:country":"BE",
    "sg:address":"Boulevard Lalaing 33",
    "sg:city":"Tournai",
    "sg:orig_category":"Advocaten and juridische adviseurs",
    "sg:phone":"+32 69 88 85 11",
    "sg:postcode":"7500",
    "sg:province":"Hainaut",
    "wof:name":"J.l. Claux",
    "wof:placetype":"venue"
},
  "geometry": {"coordinates":[3.3854489326,50.6008262634],"type":"Point"}
}