{
  "type": "Feature",
  "properties": {
    "addr:full":"Lippenslaan 38 Knokke-heist West-Vlaanderen 8300",
    "addr:housenumber":"38",
    "addr:postcode":"8300",
    "addr:street":"Lippenslaan",
    "iso:country":"BE",
    "sg:address":"Lippenslaan 38",
    "sg:city":"Knokke-heist",
    "sg:orig_category":"Bagage and lederwaren Kantoormateriaal Papierwaren",
    "sg:phone":"+32 50 60 23 47",
    "sg:postcode":"8300",
    "sg:province":"West-Vlaanderen",
    "wof:name":"Vanvooren",
    "wof:placetype":"venue"
},
  "geometry": {"coordinates":[3.2877819538,51.3421287537],"type":"Point"}
}