{
  "type": "Feature",
  "properties": {
    "addr:full":"Gentseweg 715 Waregem (groot) West-Vlaanderen 8793",
    "addr:housenumber":"715",
    "addr:postcode":"8793",
    "addr:street":"Gentseweg;Groot West-Vlaanderen",
    "iso:country":"BE",
    "sg:address":"Gentseweg 715",
    "sg:city":"Waregem (groot)",
    "sg:orig_category":"IJzerwaren, bouw- and verfmaterialen Plaatsen van vloer- and muurbekleding Schilders Textiel Verlich",
    "sg:phone":"+32 56 60 83 47",
    "sg:postcode":"8793",
    "sg:province":"West-Vlaanderen",
    "wof:name":"Heytens",
    "wof:placetype":"venue"
},
  "geometry": {"coordinates":[3.4103620052,50.9037818909],"type":"Point"}
}