{
  "type": "Feature",
  "properties": {
    "iso:country":"BE",
    "sg:address":"Mechelsesteenweg 24",
    "sg:city":"Dendermonde",
    "sg:orig_category":"Supermarkten",
    "sg:phone":"+32 52 25 98 11",
    "sg:postcode":"9200",
    "sg:province":"Oost-Vlaanderen",
    "wof:name":"Super G.b.",
    "wof:placetype":"venue"
},
  "geometry": {"coordinates":[4.1102170944,51.0331993103],"type":"Point"}
}