{
  "type": "Feature",
  "properties": {
    "addr:full":"Houtveldlaan 14 Beersel (alsemberg) Vlaams-Brabant 1652",
    "addr:housenumber":"14",
    "addr:postcode":"1652",
    "addr:street":"Houtveldlaan",
    "iso:country":"BE",
    "sg:address":"Houtveldlaan 14",
    "sg:city":"Beersel (alsemberg)",
    "sg:classifiers":[
        {
            "category":"Banks & Credit Unions",
            "subcategory":"Investment Brokerage",
            "type":"Services"
        }
    ],
    "sg:phone":"+32 2 380 30 11",
    "sg:postcode":"1652",
    "sg:province":"Vlaams-Brabant",
    "sg:tags":[
        "repair",
        "-",
        "installation",
        "sanitary",
        "article"
    ],
    "wof:name":"Sanichauf Vanmulder",
    "wof:placetype":"venue"
},
  "geometry": {"coordinates":[4.3361530304,50.7534141541],"type":"Point"}
}