{
  "type": "Feature",
  "properties": {
    "addr:full":"Eendrachtstraat 6 Assenede Oost-Vlaanderen 9968",
    "addr:housenumber":"6",
    "addr:postcode":"9968",
    "addr:street":"Eendrachtstraat",
    "iso:country":"BE",
    "sg:address":"Eendrachtstraat 6",
    "sg:city":"Assenede",
    "sg:orig_category":"Woningbouw",
    "sg:phone":"+32 9 373 84 59",
    "sg:postcode":"9968",
    "sg:province":"Oost-Vlaanderen",
    "wof:name":"Lieven Vermeire",
    "wof:placetype":"venue"
},
  "geometry": {"coordinates":[3.6887938976,51.1923027039],"type":"Point"}
}