{
  "type": "Feature",
  "properties": {
    "iso:country":"BE",
    "sg:address":"Wijk Kalberg 4",
    "sg:city":"Oostrozebeke",
    "sg:orig_category":"Installation de menuiserie en bois and plastique",
    "sg:phone":"+32 56 66 40 99",
    "sg:postcode":"8780",
    "sg:province":"West-Vlaanderen",
    "wof:name":"Carl Detavernier",
    "wof:placetype":"venue"
},
  "geometry": {"coordinates":[3.3474090099,50.926815033],"type":"Point"}
}