{
  "type": "Feature",
  "properties": {
    "addr:full":"Dorpsstraat 2 Meeuwen-gruitrode Limburg 3670",
    "addr:housenumber":"2",
    "addr:postcode":"3670",
    "addr:street":"Dorpsstraat",
    "iso:country":"BE",
    "sg:address":"Dorpsstraat 2",
    "sg:city":"Meeuwen-gruitrode",
    "sg:orig_category":"V\u00eatements pour b\u00e9b\u00e9s and enfants",
    "sg:phone":"+32 11 79 25 88",
    "sg:postcode":"3670",
    "sg:province":"Limburg",
    "wof:name":"Alfons Schepers",
    "wof:placetype":"venue"
},
  "geometry": {"coordinates":[5.5179710388,51.0977516174],"type":"Point"}
}