{
  "type": "Feature",
  "properties": {
    "iso:country":"BE",
    "sg:address":"Neerstraat 33",
    "sg:city":"Wuustwezel",
    "sg:classifiers":[
        {
            "category":"Professional",
            "subcategory":"Computer Services",
            "type":"Services"
        }
    ],
    "sg:phone":"+32 3 669 89 68",
    "sg:postcode":"2990",
    "sg:province":"Antwerpen",
    "sg:tags":[
        "-",
        "processing",
        "data",
        "software"
    ],
    "wof:name":"Softon Bvba",
    "wof:placetype":"venue"
},
  "geometry": {"coordinates":[4.579723835,51.3894767761],"type":"Point"}
}