{
  "type": "Feature",
  "properties": {
    "addr:full":"Hogeweg 317-319 Menen West-Vlaanderen 8930",
    "addr:housenumber":"317-319",
    "addr:postcode":"8930",
    "addr:street":"Hogeweg",
    "iso:country":"BE",
    "sg:address":"Hogeweg 317-319",
    "sg:city":"Menen",
    "sg:classifiers":[
        {
            "category":"Home & Garden",
            "subcategory":"Hardware",
            "type":"Retail Goods"
        }
    ],
    "sg:phone":"+32 56 51 29 46",
    "sg:postcode":"8930",
    "sg:province":"West-Vlaanderen",
    "sg:tags":[
        "gate",
        "opener",
        "door",
        "automatic"
    ],
    "wof:name":"Montr\u00e9-laga",
    "wof:placetype":"venue"
},
  "geometry": {"coordinates":[3.090059042,50.7946968079],"type":"Point"}
}