{
  "type": "Feature",
  "properties": {
    "iso:country":"BE",
    "sg:address":"Rue Des Ecoles 4",
    "sg:city":"Florennes",
    "sg:classifiers":[
        {
            "category":"Professional",
            "subcategory":"Art Services",
            "type":"Services"
        }
    ],
    "sg:phone":"+32 71 68 94 84",
    "sg:postcode":"5620",
    "sg:province":"Namur",
    "sg:tags":[
        "photographer",
        "-",
        "portrait"
    ],
    "wof:name":"Baeyens (studio)",
    "wof:placetype":"venue"
},
  "geometry": {"coordinates":[4.6063041687,50.2505874634],"type":"Point"}
}