{
  "type": "Feature",
  "properties": {
    "addr:full":"Chauss\u00c9e Paul Houtart 361 La Louviere Hainaut 7110",
    "addr:housenumber":"361",
    "addr:postcode":"7110",
    "addr:street":"Chausse\u0301E Paul Houtart",
    "iso:country":"BE",
    "sg:address":"Chauss\u00c9e Paul Houtart 361",
    "sg:city":"La Louviere",
    "sg:orig_category":"Pain, p\u00e2tisseries and confiseries",
    "sg:phone":"+32 64 22 43 52",
    "sg:postcode":"7110",
    "sg:province":"Hainaut",
    "wof:name":"La Gourmandise",
    "wof:placetype":"venue"
},
  "geometry": {"coordinates":[4.1532158852,50.4885025024],"type":"Point"}
}