{
  "type": "Feature",
  "properties": {
    "iso:country":"BE",
    "sg:address":"Rue Saint-denys 39bb",
    "sg:city":"Assesse",
    "sg:orig_category":"Agences de publicit\u00e9",
    "sg:phone":"+32 81 40 25 05",
    "sg:postcode":"5330",
    "sg:province":"Namur",
    "wof:name":"Fe. Imagi",
    "wof:placetype":"venue"
},
  "geometry": {"coordinates":[4.9497590065,50.404876709],"type":"Point"}
}