{
  "type": "Feature",
  "properties": {
    "addr:full":"Glabbeekstraat 37 Geetbets Vlaams-Brabant 3450",
    "addr:housenumber":"37",
    "addr:postcode":"3450",
    "addr:street":"Glabbeekstraat",
    "iso:country":"BE",
    "sg:address":"Glabbeekstraat 37",
    "sg:city":"Geetbets",
    "sg:classifiers":[
        {
            "category":"Recreation",
            "type":"Entertainment"
        }
    ],
    "sg:phone":"+32 11 58 46 06",
    "sg:postcode":"3450",
    "sg:province":"Vlaams-Brabant",
    "sg:tags":[
        "diver",
        "amusement"
    ],
    "wof:name":"Rafa\u00cbl",
    "wof:placetype":"venue"
},
  "geometry": {"coordinates":[5.1131839752,50.8852424622],"type":"Point"}
}