{
  "type": "Feature",
  "properties": {
    "addr:full":"Boulevard Aristide Briand 24 Bruxelles (anderlecht) Bruxelles-Capitale 1070",
    "addr:housenumber":"24",
    "addr:postcode":"1070",
    "addr:street":"Boulevard Aristide Briand",
    "iso:country":"BE",
    "sg:address":"Boulevard Aristide Briand 24",
    "sg:city":"Bruxelles (anderlecht)",
    "sg:classifiers":[
        {
            "category":"Building & Trades",
            "subcategory":"Electrical",
            "type":"Services"
        }
    ],
    "sg:phone":"+32 2 522 47 31",
    "sg:postcode":"1070",
    "sg:province":"Bruxelles-Capitale",
    "sg:tags":[
        "industrial",
        "-",
        "electric",
        "contractor"
    ],
    "wof:name":"Electroprint Sa",
    "wof:placetype":"venue"
},
  "geometry": {"coordinates":[4.3022069931,50.8285751343],"type":"Point"}
}