{
  "type": "Feature",
  "properties": {
    "iso:country":"BE",
    "sg:address":"Rue Du Heusay 56b",
    "sg:city":"Beyne-heusay",
    "sg:classifiers":[
        {
            "category":"Personal",
            "subcategory":"Beauty Salon",
            "type":"Services"
        }
    ],
    "sg:phone":"+32 4 358 64 10",
    "sg:postcode":"4610",
    "sg:province":"Li\u00e8ge",
    "sg:tags":[
        "lady",
        "-",
        "hairdressing"
    ],
    "wof:name":"Chantal Lardinois Coiffure",
    "wof:placetype":"venue"
},
  "geometry": {"coordinates":[5.655272007,50.6225471497],"type":"Point"}
}