{
  "type": "Feature",
  "properties": {
    "iso:country":"BE",
    "sg:address":"Rue Maur. Van Rolleghem 15",
    "sg:city":"Jette",
    "sg:classifiers":[
        {
            "category":"Arena",
            "subcategory":"Sports Club",
            "type":"Entertainment"
        }
    ],
    "sg:phone":"+32 2 478 42 56",
    "sg:postcode":"1090",
    "sg:province":"Bruxelles-Capitale",
    "sg:tags":[
        "de"
    ],
    "wof:name":"C.s.b. Ixelles",
    "wof:placetype":"venue"
},
  "geometry": {"coordinates":[4.3234019279,50.8907623291],"type":"Point"}
}