{
  "type": "Feature",
  "properties": {
    "addr:full":"Bergstraat 62 Hoeselt Limburg 3730",
    "addr:housenumber":"62",
    "addr:postcode":"3730",
    "addr:street":"Bergstraat",
    "iso:country":"BE",
    "sg:address":"Bergstraat 62",
    "sg:city":"Hoeselt",
    "sg:orig_category":"Mat\u00e9riaux de construction Gr",
    "sg:phone":"+32 89 41 18 12",
    "sg:postcode":"3730",
    "sg:province":"Limburg",
    "wof:name":"Knapen Bouwmaterialen",
    "wof:placetype":"venue"
},
  "geometry": {"coordinates":[5.4831929207,50.8571624756],"type":"Point"}
}