{
  "type": "Feature",
  "properties": {
    "addr:full":"Hekkestraat 2 Sint-amands Antwerpen 2890",
    "addr:housenumber":"2",
    "addr:postcode":"2890",
    "addr:street":"Hekkestraat",
    "iso:country":"BE",
    "sg:address":"Hekkestraat 2",
    "sg:city":"Sint-amands",
    "sg:orig_category":"Verlichting and huishoudartikelen",
    "sg:phone":"+32 52 33 22 28",
    "sg:postcode":"2890",
    "sg:province":"Antwerpen",
    "wof:name":"Deco Van Steen",
    "wof:placetype":"venue"
},
  "geometry": {"coordinates":[4.2042541504,51.0535621643],"type":"Point"}
}