{
  "type": "Feature",
  "properties": {
    "addr:full":"Hofeinde 49 Heusden-zolder (zolder) Limburg 3550",
    "addr:housenumber":"49",
    "addr:postcode":"3550",
    "addr:street":"Hofeinde",
    "iso:country":"BE",
    "sg:address":"Hofeinde 49",
    "sg:city":"Heusden-zolder (zolder)",
    "sg:classifiers":[
        {
            "category":"Professional",
            "type":"Services"
        }
    ],
    "sg:phone":"+32 11 53 66 98",
    "sg:postcode":"3550",
    "sg:province":"Limburg",
    "sg:tags":[
        "industrial",
        "work",
        "-",
        "maintenance"
    ],
    "wof:name":"Atd",
    "wof:placetype":"venue"
},
  "geometry": {"coordinates":[5.2918119431,51.0134048462],"type":"Point"}
}