{
  "type": "Feature",
  "properties": {
    "addr:full":"Hoekstraat 12 Stekene (kemzeke) Oost-Vlaanderen 9190",
    "addr:housenumber":"12",
    "addr:postcode":"9190",
    "addr:street":"Hoekstraat",
    "iso:country":"BE",
    "sg:address":"Hoekstraat 12",
    "sg:city":"Stekene (kemzeke)",
    "sg:classifiers":[
        {
            "category":"Food & Beverages",
            "subcategory":"Liquor & Beverages",
            "type":"Retail Goods"
        }
    ],
    "sg:phone":"+32 3 779 67 48",
    "sg:postcode":"9190",
    "sg:province":"Oost-Vlaanderen",
    "sg:tags":[
        "-",
        "spirit",
        "wine"
    ],
    "wof:name":"Wase Wijnkelder (de)",
    "wof:placetype":"venue"
},
  "geometry": {"coordinates":[4.0762038231,51.2055549622],"type":"Point"}
}