{
  "type": "Feature",
  "properties": {
    "addr:full":"Moresneter Strasse 108 Kelmis Li\u00e8ge 4720",
    "addr:housenumber":"108",
    "addr:postcode":"4720",
    "addr:street":"Moresneter Strasse",
    "iso:country":"BE",
    "sg:address":"Moresneter Strasse 108",
    "sg:city":"Kelmis",
    "sg:classifiers":[
        {
            "category":"Retail",
            "subcategory":"Auto Repair",
            "type":"Services"
        }
    ],
    "sg:phone":"+32 87 65 95 46",
    "sg:postcode":"4720",
    "sg:province":"Li\u00e8ge",
    "sg:tags":[
        "automobile-body"
    ],
    "wof:name":"Koch Carrosserie Sa",
    "wof:placetype":"venue"
},
  "geometry": {"coordinates":[6.0091428757,50.7225151062],"type":"Point"}
}