{
  "type": "Feature",
  "properties": {
    "addr:full":"Basiliekstraat 55 Halle Vlaams-Brabant 1500",
    "addr:housenumber":"55",
    "addr:postcode":"1500",
    "addr:street":"Basiliekstraat",
    "iso:country":"BE",
    "sg:address":"Basiliekstraat 55",
    "sg:city":"Halle",
    "sg:classifiers":[
        {
            "category":"Shopping",
            "subcategory":"Luggage & Leather Goods",
            "type":"Retail Goods"
        }
    ],
    "sg:phone":"+32 2 356 55 14",
    "sg:postcode":"1500",
    "sg:province":"Vlaams-Brabant",
    "sg:tags":[
        "-"
    ],
    "wof:name":"Demanet Sa",
    "wof:placetype":"venue"
},
  "geometry": {"coordinates":[4.2360601425,50.7346992493],"type":"Point"}
}