{
  "type": "Feature",
  "properties": {
    "iso:country":"BE",
    "sg:address":"Generaal Capiaumontstr. 2",
    "sg:city":"Etterbeek/etterbeek",
    "sg:classifiers":[
        {
            "category":"Restaurant",
            "type":"Food & Drink"
        }
    ],
    "sg:phone":"+32 2 648 75 03",
    "sg:postcode":"1040",
    "sg:province":"Bruxelles-Capitale",
    "wof:name":"Le Chat Qui P\u00cache",
    "wof:placetype":"venue"
},
  "geometry": {"coordinates":[4.3829669952,50.8326911926],"type":"Point"}
}