{
  "type": "Feature",
  "properties": {
    "addr:full":"Chauss\u00e9e De Bruxelles 105b Awans Li\u00e8ge 4340",
    "addr:housenumber":"105b",
    "addr:postcode":"4340",
    "addr:street":"Chausse\u0301E De Bruxelles",
    "iso:country":"BE",
    "sg:address":"Chauss\u00e9e De Bruxelles 105b",
    "sg:city":"Awans",
    "sg:classifiers":[
        {
            "category":"Retail",
            "subcategory":"Auto Repair",
            "type":"Services"
        }
    ],
    "sg:phone":"+32 4 239 03 89",
    "sg:postcode":"4340",
    "sg:province":"Li\u00e8ge",
    "sg:tags":[
        "automobile-body"
    ],
    "wof:name":"Scaffe Gilbert Ets",
    "wof:placetype":"venue"
},
  "geometry": {"coordinates":[5.47920084,50.6767921448],"type":"Point"}
}