{
  "type": "Feature",
  "properties": {
    "addr:full":"Avenue Pr\u00e9-aily 10 Li\u00e8ge 1 (angleur) Li\u00e8ge 4031",
    "addr:housenumber":"10;1",
    "addr:postcode":"4031",
    "addr:street":"Avenue Pre\u0301-Aily",
    "iso:country":"BE",
    "sg:address":"Avenue Pr\u00e9-aily 10",
    "sg:city":"Li\u00e8ge 1 (angleur)",
    "sg:classifiers":[
        {
            "category":"Professional",
            "subcategory":"Testing Lab",
            "type":"Services"
        }
    ],
    "sg:phone":"+32 4 361 42 32",
    "sg:postcode":"4031",
    "sg:province":"Li\u00e8ge",
    "sg:tags":[
        "laboratory",
        "-",
        "machines",
        "apparatus",
        "supply"
    ],
    "wof:name":"Zentech Sa",
    "wof:placetype":"venue"
},
  "geometry": {"coordinates":[5.5701580048,50.5985069275],"type":"Point"}
}