{
  "type": "Feature",
  "properties": {
    "addr:full":"Solariumlaan 2 Zemst Vlaams-Brabant 1982",
    "addr:housenumber":"2",
    "addr:postcode":"1982",
    "addr:street":"Solariumlaan;Vlaams-Brabant",
    "iso:country":"BE",
    "sg:address":"Solariumlaan 2",
    "sg:city":"Zemst",
    "sg:orig_category":"Agences de publicit\u00e9",
    "sg:phone":"+32 15 61 31 09",
    "sg:postcode":"1982",
    "sg:province":"Vlaams-Brabant",
    "wof:name":"D.h.d. Reclame",
    "wof:placetype":"venue"
},
  "geometry": {"coordinates":[4.5014629364,50.9762001038],"type":"Point"}
}