{
  "type": "Feature",
  "properties": {
    "addr:full":"Rue Du Cortil Bailly 2 Lasne (couture-saint-germain) Brabant Wallon 1380",
    "addr:housenumber":"2",
    "addr:postcode":"1380",
    "addr:street":"Rue Du Cortil Bailly;Wallon",
    "iso:country":"BE",
    "sg:address":"Rue Du Cortil Bailly 2",
    "sg:city":"Lasne (couture-saint-germain)",
    "sg:classifiers":[
        {
            "category":"Health Services",
            "subcategory":"Doctor",
            "type":"Services"
        }
    ],
    "sg:phone":"+32 2 633 39 91",
    "sg:postcode":"1380",
    "sg:province":"Brabant Wallon",
    "sg:tags":[
        "medicinephysicians",
        "surgeon"
    ],
    "wof:name":"Broers Matty",
    "wof:placetype":"venue"
},
  "geometry": {"coordinates":[4.483235836,50.6850166321],"type":"Point"}
}