{
  "type": "Feature",
  "properties": {
    "iso:country":"BE",
    "sg:address":"Clos Des M\u00c9sanges 23",
    "sg:city":"Tournai",
    "sg:orig_category":"Architectes",
    "sg:phone":"+32 69 22 31 84",
    "sg:postcode":"7503",
    "sg:province":"Hainaut",
    "wof:name":"Jacques Bruyere",
    "wof:placetype":"venue"
},
  "geometry": {"coordinates":[3.353110075,50.622833252],"type":"Point"}
}