{
  "type": "Feature",
  "properties": {
    "addr:full":"Avenue De La Station 35 Esneux Li\u00e8ge 4130",
    "addr:housenumber":"35",
    "addr:postcode":"4130",
    "addr:street":"Avenue De La Station",
    "iso:country":"BE",
    "sg:address":"Avenue De La Station 35",
    "sg:city":"Esneux",
    "sg:classifiers":[
        {
            "category":"Restaurant",
            "type":"Food & Drink"
        }
    ],
    "sg:phone":"+32 4 380 22 27",
    "sg:postcode":"4130",
    "sg:province":"Li\u00e8ge",
    "wof:name":"Restaurant Chez Sam",
    "wof:placetype":"venue"
},
  "geometry": {"coordinates":[5.5701770782,50.5318107605],"type":"Point"}
}