{
  "type": "Feature",
  "properties": {
    "iso:country":"BE",
    "sg:address":"Rue Puissant 15",
    "sg:city":"Charleroi",
    "sg:orig_category":"Diverse bedrijfsbeheeradviesbureaus",
    "sg:phone":"+32 71 23 57 12",
    "sg:postcode":"6000",
    "sg:province":"Hainaut",
    "wof:name":"Association Wallonne De La Qualit\u00c9",
    "wof:placetype":"venue"
},
  "geometry": {"coordinates":[4.4411258698,50.4067573547],"type":"Point"}
}