{
  "type": "Feature",
  "properties": {
    "addr:full":"Justitiestraat 20 Antwerpen Antwerpen 2018",
    "addr:housenumber":"20",
    "addr:postcode":"2018",
    "addr:street":"Justitiestraat",
    "iso:country":"BE",
    "sg:address":"Justitiestraat 20",
    "sg:city":"Antwerpen",
    "sg:classifiers":[
        {
            "category":"Professional",
            "subcategory":"Credit Reporting & Collection",
            "type":"Services"
        }
    ],
    "sg:phone":"+32 3 259 59 00",
    "sg:postcode":"2018",
    "sg:province":"Antwerpen",
    "sg:tags":[
        "bailiff"
    ],
    "wof:name":"Beerten M-de Belder J Mertens W-vendenhende R",
    "wof:placetype":"venue"
},
  "geometry": {"coordinates":[4.4065971375,51.2090759277],"type":"Point"}
}