{
  "type": "Feature",
  "properties": {
    "iso:country":"BE",
    "sg:address":"Chauss\u00e9e De Tirlemont 37",
    "sg:city":"Hannut",
    "sg:classifiers":[
        {
            "category":"Cemetery",
            "type":"Public Place"
        }
    ],
    "sg:phone":"+32 19 51 32 16",
    "sg:postcode":"4280",
    "sg:province":"Li\u00e8ge",
    "sg:tags":[
        "crematory"
    ],
    "wof:name":"Deldime-thonet & Fils",
    "wof:placetype":"venue"
},
  "geometry": {"coordinates":[5.0750641823,50.6735649109],"type":"Point"}
}