{
  "type": "Feature",
  "properties": {
    "iso:country":"BE",
    "sg:address":"Place Des Volontaires 32ba",
    "sg:city":"Herstal",
    "sg:orig_category":"Traitement and rev\u00eatement des m\u00e9taux",
    "sg:phone":"+32 4 264 64 22",
    "sg:postcode":"4040",
    "sg:province":"Li\u00e8ge",
    "wof:name":"Forir",
    "wof:placetype":"venue"
},
  "geometry": {"coordinates":[5.6264200211,50.6726799011],"type":"Point"}
}