{
  "type": "Feature",
  "properties": {
    "addr:full":"Leopold Gabri\u00eblslaan 15 Schilde Antwerpen 2970",
    "addr:housenumber":"15",
    "addr:postcode":"2970",
    "addr:street":"Gabrie\u0308Lslaan",
    "iso:country":"BE",
    "sg:address":"Leopold Gabri\u00eblslaan 15",
    "sg:city":"Schilde",
    "sg:classifiers":[
        {
            "category":"Professional",
            "subcategory":"Computer Services",
            "type":"Services"
        }
    ],
    "sg:phone":"+32 3 383 42 79",
    "sg:postcode":"2970",
    "sg:province":"Antwerpen",
    "sg:tags":[
        "-",
        "processing",
        "data",
        "software"
    ],
    "wof:name":"R S Consult Bvba",
    "wof:placetype":"venue"
},
  "geometry": {"coordinates":[4.5818991661,51.236946106],"type":"Point"}
}