{
  "type": "Feature",
  "properties": {
    "addr:full":"Frans Van Ryhovelaan 93 Gent Oost-Vlaanderen 9000",
    "addr:housenumber":"93",
    "addr:postcode":"9000",
    "addr:street":"Frans Van Ryhovelaan;Oost-Vlaanderen",
    "iso:country":"BE",
    "sg:address":"Frans Van Ryhovelaan 93",
    "sg:city":"Gent",
    "sg:orig_category":"Rijscholen",
    "sg:phone":"+32 9 226 03 44",
    "sg:postcode":"9000",
    "sg:province":"Oost-Vlaanderen",
    "wof:name":"Rijschool Sanderus",
    "wof:placetype":"venue"
},
  "geometry": {"coordinates":[3.7075209618,51.0691452026],"type":"Point"}
}