{
  "type": "Feature",
  "properties": {
    "iso:country":"BE",
    "sg:address":"Stationsstraat 2b12",
    "sg:city":"Sint-truiden",
    "sg:orig_category":"Parfumeries",
    "sg:phone":"+32 11 68 13 77",
    "sg:postcode":"3800",
    "sg:province":"Limburg",
    "wof:name":"Annie Vanderstegen",
    "wof:placetype":"venue"
},
  "geometry": {"coordinates":[5.1800251007,50.8156280518],"type":"Point"}
}