{
  "type": "Feature",
  "properties": {
    "addr:full":"Rue Saint-l\u00c9onard 113 Li\u00c8ge Li\u00e8ge 4000",
    "addr:housenumber":"113",
    "addr:postcode":"4000",
    "addr:street":"Rue Saint-Le\u0301Onard",
    "iso:country":"BE",
    "sg:address":"Rue Saint-l\u00c9onard 113",
    "sg:city":"Li\u00c8ge",
    "sg:orig_category":"Organisatie van beurzen, congressen and tentoonstellingen",
    "sg:phone":"+32 4 227 80 06",
    "sg:postcode":"4000",
    "sg:province":"Li\u00e8ge",
    "wof:name":"Carr\u00c9-swinnen",
    "wof:placetype":"venue"
},
  "geometry": {"coordinates":[5.5901851654,50.6491470337],"type":"Point"}
}