{
  "type": "Feature",
  "properties": {
    "addr:full":"Rue Arthur Maes 61 Brussel/bruxelles Bruxelles-Capitale 1130",
    "addr:housenumber":"61",
    "addr:postcode":"1130",
    "addr:street":"Rue Arthur Maes;/",
    "iso:country":"BE",
    "sg:address":"Rue Arthur Maes 61",
    "sg:city":"Brussel/bruxelles",
    "sg:orig_category":"R\u00e9cup\u00e9ration de mati\u00e8res m\u00e9talliques recyclables and d\u00e9molisseurs de voitures. D\u00e9chets and d\u00e9bris Gr",
    "sg:phone":"+32 2 705 13 72",
    "sg:postcode":"1130",
    "sg:province":"Bruxelles-Capitale",
    "wof:name":"M. Tutar/mehmet Tutar",
    "wof:placetype":"venue"
},
  "geometry": {"coordinates":[4.4209470749,50.8927154541],"type":"Point"}
}