{
  "type": "Feature",
  "properties": {
    "addr:full":"Rue Van Soust 549 Bruxelles (molenbeek-saint-jean) Bruxelles-Capitale 1080",
    "addr:housenumber":"549",
    "addr:postcode":"1080",
    "addr:street":"Rue Van Soust",
    "iso:country":"BE",
    "sg:address":"Rue Van Soust 549",
    "sg:city":"Bruxelles (molenbeek-saint-jean)",
    "sg:classifiers":[
        {
            "category":"Wholesale",
            "subcategory":"Computers",
            "type":"Manufacturing & Wholesale Goods"
        }
    ],
    "sg:phone":"+32 2 526 62 32",
    "sg:postcode":"1080",
    "sg:province":"Bruxelles-Capitale",
    "sg:tags":[
        "cabling",
        "processing",
        "-",
        "data"
    ],
    "wof:name":"Cde Sa",
    "wof:placetype":"venue"
},
  "geometry": {"coordinates":[4.2893781662,50.8455123901],"type":"Point"}
}