{
  "type": "Feature",
  "properties": {
    "iso:country":"BE",
    "sg:address":"Kalmthoutse Steenweg 112",
    "sg:city":"Wuustwezel",
    "sg:orig_category":"Entretien and r\u00e9parations de voitures. V\u00e9hicules automobiles",
    "sg:phone":"+32 3 669 91 61",
    "sg:postcode":"2990",
    "sg:province":"Antwerpen",
    "wof:name":"W.d.c.",
    "wof:placetype":"venue"
},
  "geometry": {"coordinates":[4.5810527802,51.3903083801],"type":"Point"}
}