{
  "type": "Feature",
  "properties": {
    "addr:full":"Carrefour Devillers 6 Clavier Li\u00e8ge 4560",
    "addr:housenumber":"6",
    "addr:postcode":"4560",
    "addr:street":"Devillers",
    "iso:country":"BE",
    "sg:address":"Carrefour Devillers 6",
    "sg:city":"Clavier",
    "sg:classifiers":[
        {
            "category":"Autos & Motor Vehicles",
            "subcategory":"Automobile Sales",
            "type":"Retail Goods"
        }
    ],
    "sg:phone":"+32 86 34 43 70",
    "sg:postcode":"4560",
    "sg:province":"Li\u00e8ge",
    "sg:tags":[
        "car",
        "used",
        "-"
    ],
    "wof:name":"Devillers Ets",
    "wof:placetype":"venue"
},
  "geometry": {"coordinates":[5.3458561897,50.4315185547],"type":"Point"}
}