{
  "type": "Feature",
  "properties": {
    "iso:country":"BE",
    "sg:address":"Vaatjesstraat 24",
    "sg:city":"Putte",
    "sg:orig_category":"Drogueries",
    "sg:phone":"+32 15 76 09 53",
    "sg:postcode":"2580",
    "sg:province":"Antwerpen",
    "wof:name":"Willem Dockx",
    "wof:placetype":"venue"
},
  "geometry": {"coordinates":[4.6088700294,51.0425453186],"type":"Point"}
}