{
  "type": "Feature",
  "properties": {
    "iso:country":"BE",
    "sg:address":"Stationsstraat 52",
    "sg:city":"Ninove",
    "sg:classifiers":[
        {
            "category":"Professional",
            "subcategory":"Lawyer & Legal Services",
            "type":"Services"
        }
    ],
    "sg:phone":"+32 54 33 26 20",
    "sg:postcode":"9400",
    "sg:province":"Oost-Vlaanderen",
    "wof:name":"Everaet R",
    "wof:placetype":"venue"
},
  "geometry": {"coordinates":[4.0246648788,50.8386802673],"type":"Point"}
}