{
  "type": "Feature",
  "properties": {
    "addr:full":"Grote Steenweg 422 Linter Vlaams-Brabant 3350",
    "addr:housenumber":"422",
    "addr:postcode":"3350",
    "addr:street":"Grote Steenweg;Vlaams-Brabant",
    "iso:country":"BE",
    "sg:address":"Grote Steenweg 422",
    "sg:city":"Linter",
    "sg:orig_category":"Salons de coiffure. Parfumeries",
    "sg:phone":"+32 11 78 12 41",
    "sg:postcode":"3350",
    "sg:province":"Vlaams-Brabant",
    "wof:name":"Adeleydis Allard",
    "wof:placetype":"venue"
},
  "geometry": {"coordinates":[5.059155941,50.8515853882],"type":"Point"}
}