{
  "type": "Feature",
  "properties": {
    "addr:full":"Siberi\u00cb 25 Lommel Limburg 3920",
    "addr:housenumber":"25",
    "addr:postcode":"3920",
    "addr:street":"Siberie\u0308",
    "iso:country":"BE",
    "sg:address":"Siberi\u00cb 25",
    "sg:city":"Lommel",
    "sg:orig_category":"Voertuigen",
    "sg:phone":"+32 11 64 46 23",
    "sg:postcode":"3920",
    "sg:province":"Limburg",
    "wof:name":"Guido Vanduffel",
    "wof:placetype":"venue"
},
  "geometry": {"coordinates":[5.3722958565,51.2243652344],"type":"Point"}
}