{
  "type": "Feature",
  "properties": {
    "addr:full":"Rue Des Weines 65 Verviers Li\u00e8ge 4800",
    "addr:housenumber":"65",
    "addr:postcode":"4800",
    "addr:street":"Rue Des Weines",
    "iso:country":"BE",
    "sg:address":"Rue Des Weines 65",
    "sg:city":"Verviers",
    "sg:classifiers":[
        {
            "category":"Bus Stop",
            "subcategory":"None",
            "type":"Transportation"
        }
    ],
    "sg:phone":"+32 3 830 40 00",
    "sg:postcode":"4800",
    "sg:province":"Li\u00e8ge",
    "sg:tags":[
        "closure",
        "canister"
    ],
    "wof:name":"Procap Hoboken",
    "wof:placetype":"venue"
},
  "geometry": {"coordinates":[4.3544859886,51.1861152649],"type":"Point"}
}