{
  "type": "Feature",
  "properties": {
    "addr:full":"Ijzerstraat 69 Box 6 Beveren (melsele) Oost-Vlaanderen 9120",
    "addr:housenumber":"69;6",
    "addr:postcode":"9120",
    "addr:street":"Ijzerstraat;Box",
    "iso:country":"BE",
    "sg:address":"Ijzerstraat 69 Box 6",
    "sg:city":"Beveren (melsele)",
    "sg:classifiers":[
        {
            "category":"Real Estate",
            "subcategory":"Architect",
            "type":"Services"
        }
    ],
    "sg:phone":"+32 3 775 21 58",
    "sg:postcode":"9120",
    "sg:province":"Oost-Vlaanderen",
    "wof:name":"Vercauteren G",
    "wof:placetype":"venue"
},
  "geometry": {"coordinates":[4.2812027931,51.2147026062],"type":"Point"}
}