{
  "type": "Feature",
  "properties": {
    "iso:country":"BE",
    "sg:address":"Rue G\u00c9n\u00c9ral-hontoy 15",
    "sg:city":"Philippeville",
    "sg:orig_category":"Rundveehouders",
    "sg:phone":"+32 71 66 62 33",
    "sg:postcode":"5600",
    "sg:province":"Namur",
    "wof:name":"Leon Delpire",
    "wof:placetype":"venue"
},
  "geometry": {"coordinates":[4.5322709084,50.2191543579],"type":"Point"}
}