{
  "type": "Feature",
  "properties": {
    "addr:full":"Rue Jules Des Essarts 44 Ch\u00e2telet (ch\u00e2telineau) Hainaut 6200",
    "addr:housenumber":"44",
    "addr:postcode":"6200",
    "addr:street":"Rue Jules Des Essarts",
    "iso:country":"BE",
    "sg:address":"Rue Jules Des Essarts 44",
    "sg:city":"Ch\u00e2telet (ch\u00e2telineau)",
    "sg:classifiers":[
        {
            "category":"Personal",
            "subcategory":"Nail Salon",
            "type":"Services"
        }
    ],
    "sg:phone":"+32 71 39 10 49",
    "sg:postcode":"6200",
    "sg:province":"Hainaut",
    "sg:tags":[
        "pedicure"
    ],
    "wof:name":"Tait F",
    "wof:placetype":"venue"
},
  "geometry": {"coordinates":[4.5202279091,50.4151268005],"type":"Point"}
}