{
  "type": "Feature",
  "properties": {
    "addr:full":"Chauss\u00c9e De Ciney 149bb Andenne Namur 5300",
    "addr:housenumber":"149bb",
    "addr:postcode":"5300",
    "addr:street":"Chausse\u0301E De Ciney",
    "iso:country":"BE",
    "sg:address":"Chauss\u00c9e De Ciney 149bb",
    "sg:city":"Andenne",
    "sg:orig_category":"Peinture",
    "sg:phone":"+32 85 84 30 07",
    "sg:postcode":"5300",
    "sg:province":"Namur",
    "wof:name":"Robert Matagne",
    "wof:placetype":"venue"
},
  "geometry": {"coordinates":[5.1037192345,50.4810676575],"type":"Point"}
}