{
  "type": "Feature",
  "properties": {
    "iso:country":"BE",
    "sg:address":"Waverse Steenweg 59",
    "sg:city":"Elsene/ixelles",
    "sg:orig_category":"Modellenbureaus",
    "sg:phone":"+32 2 511 10 11",
    "sg:postcode":"1050",
    "sg:province":"Bruxelles-Capitale",
    "wof:name":"The Blitz Group",
    "wof:placetype":"venue"
},
  "geometry": {"coordinates":[4.3649997711,50.836807251],"type":"Point"}
}