{
  "type": "Feature",
  "properties": {
    "addr:full":"Eetgoedstraat 7 Wichelen Oost-Vlaanderen 9260",
    "addr:housenumber":"7",
    "addr:postcode":"9260",
    "addr:street":"Eetgoedstraat",
    "iso:country":"BE",
    "sg:address":"Eetgoedstraat 7",
    "sg:city":"Wichelen",
    "sg:orig_category":"P\u00e9pini\u00e9ristes",
    "sg:phone":"+32 9 369 50 49",
    "sg:postcode":"9260",
    "sg:province":"Oost-Vlaanderen",
    "wof:name":"Fa. Van Der Eecken",
    "wof:placetype":"venue"
},
  "geometry": {"coordinates":[3.9402060509,50.9942970276],"type":"Point"}
}