{
  "type": "Feature",
  "properties": {
    "iso:country":"BE",
    "sg:address":"Rue Du W\u00e8rh\u00ea 11",
    "sg:city":"Weismes",
    "sg:classifiers":[
        {
            "category":"Health Services",
            "subcategory":"Doctor",
            "type":"Services"
        }
    ],
    "sg:phone":"+32 80 44 86 96",
    "sg:postcode":"4950",
    "sg:province":"Li\u00e8ge",
    "sg:tags":[
        "psychotherapist",
        "psychoanalyst"
    ],
    "wof:name":"Glorieux A",
    "wof:placetype":"venue"
},
  "geometry": {"coordinates":[6.098279953,50.3929405212],"type":"Point"}
}