{
  "type": "Feature",
  "properties": {
    "iso:country":"BE",
    "sg:address":"Leerwijk 1",
    "sg:city":"Antwerpen",
    "sg:orig_category":"Enseignement maternel and primaire",
    "sg:phone":"+32 3 541 77 66",
    "sg:postcode":"2030",
    "sg:province":"Antwerpen",
    "wof:name":"Vrije Kleuterschool",
    "wof:placetype":"venue"
},
  "geometry": {"coordinates":[4.4107198715,51.2794189453],"type":"Point"}
}