{
  "type": "Feature",
  "properties": {
    "addr:full":"Diesterstraat 123 Tessenderlo Limburg 3980",
    "addr:housenumber":"123",
    "addr:postcode":"3980",
    "addr:street":"Diesterstraat",
    "iso:country":"BE",
    "sg:address":"Diesterstraat 123",
    "sg:city":"Tessenderlo",
    "sg:orig_category":"G\u00e9om\u00e8tres",
    "sg:phone":"+32 13 66 24 26",
    "sg:postcode":"3980",
    "sg:province":"Limburg",
    "wof:name":"Carl Verheyen",
    "wof:placetype":"venue"
},
  "geometry": {"coordinates":[5.0892148018,51.0611114502],"type":"Point"}
}