{
  "type": "Feature",
  "properties": {
    "addr:full":"Rue De Chassepierre 17 Florenville (groot) Luxembourg 6820",
    "addr:housenumber":"17",
    "addr:postcode":"6820",
    "addr:street":"Rue De Chassepierre;Groot Luxembourg",
    "iso:country":"BE",
    "sg:address":"Rue De Chassepierre 17",
    "sg:city":"Florenville (groot)",
    "sg:classifiers":[
        {
            "category":"Personal",
            "subcategory":"Beauty Salon",
            "type":"Services"
        }
    ],
    "sg:phone":"+32 61 32 06 64",
    "sg:postcode":"6820",
    "sg:province":"Luxembourg",
    "sg:tags":[
        "de",
        "coiffure"
    ],
    "wof:name":"Coiffure Peignerie",
    "wof:placetype":"venue"
},
  "geometry": {"coordinates":[5.242729187,49.7278404236],"type":"Point"}
}