{
  "type": "Feature",
  "properties": {
    "iso:country":"BE",
    "sg:address":"Rue Georges Lemoine 14",
    "sg:city":"Charleroi",
    "sg:orig_category":"Boekhouders",
    "sg:phone":"+32 71 31 46 43",
    "sg:postcode":"6043",
    "sg:province":"Hainaut",
    "wof:name":"Claude Pouleur",
    "wof:placetype":"venue"
},
  "geometry": {"coordinates":[4.4850420952,50.4458465576],"type":"Point"}
}