{
  "type": "Feature",
  "properties": {
    "addr:full":"Sint-bavoplein 12b1 Boechout Antwerpen 2530",
    "addr:housenumber":"12b1",
    "addr:postcode":"2530",
    "addr:street":"Sint-Bavoplein",
    "iso:country":"BE",
    "sg:address":"Sint-bavoplein 12b1",
    "sg:city":"Boechout",
    "sg:orig_category":"Immobili\u00ebnkantoren",
    "sg:phone":"+32 3 454 20 60",
    "sg:postcode":"2530",
    "sg:province":"Antwerpen",
    "wof:name":"Bureau Else",
    "wof:placetype":"venue"
},
  "geometry": {"coordinates":[4.4923582077,51.158996582],"type":"Point"}
}