{
  "type": "Feature",
  "properties": {
    "iso:country":"BE",
    "sg:address":"Voortstraat 34a",
    "sg:city":"Sint-amands (oppuurs)",
    "sg:classifiers":[
        {
            "category":"Home & Garden",
            "subcategory":"Building Materials",
            "type":"Retail Goods"
        }
    ],
    "sg:phone":"+32 3 899 23 83",
    "sg:postcode":"2890",
    "sg:province":"Antwerpen",
    "sg:tags":[
        "aluminium",
        "construction",
        "-"
    ],
    "wof:name":"Van Meerbeeck F",
    "wof:placetype":"venue"
},
  "geometry": {"coordinates":[4.2437701225,51.0636367798],"type":"Point"}
}