{
  "type": "Feature",
  "properties": {
    "addr:full":"Rue Haute 12 Assesse Namur 5332",
    "addr:housenumber":"12",
    "addr:postcode":"5332",
    "addr:street":"Rue Haute",
    "iso:country":"BE",
    "sg:address":"Rue Haute 12",
    "sg:city":"Assesse",
    "sg:classifiers":[
        {
            "category":"Cafe",
            "type":"Food & Drink"
        }
    ],
    "sg:phone":"+32 83 69 98 26",
    "sg:postcode":"5332",
    "sg:province":"Namur",
    "sg:tags":[
        "caf\u00e9s"
    ],
    "wof:name":"Patrick Halut",
    "wof:placetype":"venue"
},
  "geometry": {"coordinates":[4.9603500366,50.3483772278],"type":"Point"}
}