{
  "type": "Feature",
  "properties": {
    "addr:full":"Keizerstraat 59 Bierbeek (lovenjoel) Vlaams-Brabant 3360",
    "addr:housenumber":"59",
    "addr:postcode":"3360",
    "addr:street":"Keizerstraat",
    "iso:country":"BE",
    "sg:address":"Keizerstraat 59",
    "sg:city":"Bierbeek (lovenjoel)",
    "sg:classifiers":[
        {
            "category":"Building & Trades",
            "subcategory":"Electrical",
            "type":"Services"
        }
    ],
    "sg:phone":"+32 16 46 25 45",
    "sg:postcode":"3360",
    "sg:province":"Vlaams-Brabant",
    "sg:tags":[
        "heating"
    ],
    "wof:name":"Meuleman Gary Nv",
    "wof:placetype":"venue"
},
  "geometry": {"coordinates":[4.7814288139,50.8558959961],"type":"Point"}
}