{
  "type": "Feature",
  "properties": {
    "addr:full":"Rue Sainte-anne 18 Brussel/bruxelles Bruxelles-Capitale 1000",
    "addr:housenumber":"18",
    "addr:postcode":"1000",
    "addr:street":"Rue Sainte-Anne;/",
    "iso:country":"BE",
    "sg:address":"Rue Sainte-anne 18",
    "sg:city":"Brussel/bruxelles",
    "sg:classifiers":[
        {
            "category":"Restaurant",
            "type":"Food & Drink"
        }
    ],
    "sg:phone":"+32 2 511 29 19",
    "sg:postcode":"1000",
    "sg:province":"Bruxelles-Capitale",
    "wof:name":"Taverne La Pirogue",
    "wof:placetype":"venue"
},
  "geometry": {"coordinates":[4.3561630249,50.841468811],"type":"Point"}
}