{
  "type": "Feature",
  "properties": {
    "iso:country":"BE",
    "sg:address":"Koningin Astridplein 27",
    "sg:city":"Antwerpen",
    "sg:classifiers":[
        {
            "category":"Professional",
            "subcategory":"Art Services",
            "type":"Services"
        }
    ],
    "sg:phone":"+32 3 232 54 24",
    "sg:postcode":"2018",
    "sg:province":"Antwerpen",
    "sg:tags":[
        "photographer"
    ],
    "wof:name":"Photofer Bvba",
    "wof:placetype":"venue"
},
  "geometry": {"coordinates":[4.421020031,51.217464447],"type":"Point"}
}