{
  "type": "Feature",
  "properties": {
    "addr:full":"Kapucijnenvoer 112 A Leuven (groot) Vlaams-Brabant 3000",
    "addr:housenumber":"112 a",
    "addr:postcode":"3000",
    "addr:street":"Kapucijnenvoer;Groot Vlaams-Brabant",
    "iso:country":"BE",
    "sg:address":"Kapucijnenvoer 112 A",
    "sg:city":"Leuven (groot)",
    "sg:orig_category":"Traitement de donn\u00e9es",
    "sg:phone":"+32 475 66 74 02",
    "sg:postcode":"3000",
    "sg:province":"Vlaams-Brabant",
    "wof:name":"Segers Consulting",
    "wof:placetype":"venue"
},
  "geometry": {"coordinates":[4.6910858154,50.8744277954],"type":"Point"}
}