{
  "type": "Feature",
  "properties": {
    "addr:full":"Buitenland 45 Bornem Antwerpen 2880",
    "addr:housenumber":"45",
    "addr:postcode":"2880",
    "addr:street":"Buitenland",
    "iso:country":"BE",
    "sg:address":"Buitenland 45",
    "sg:city":"Bornem",
    "sg:classifiers":[
        {
            "category":"Restaurant",
            "type":"Food & Drink"
        }
    ],
    "sg:phone":"+32 3 889 48 76",
    "sg:postcode":"2880",
    "sg:province":"Antwerpen",
    "wof:name":"De Hoeve",
    "wof:placetype":"venue"
},
  "geometry": {"coordinates":[4.2324771881,51.1156578064],"type":"Point"}
}