{
  "type": "Feature",
  "properties": {
    "addr:full":"Meersbloem Melden 46 Oudenaarde Oost-Vlaanderen 9700",
    "addr:housenumber":"46",
    "addr:postcode":"9700",
    "addr:street":"Melden",
    "iso:country":"BE",
    "sg:address":"Meersbloem Melden 46",
    "sg:city":"Oudenaarde",
    "sg:classifiers":[
        {
            "category":"Government",
            "subcategory":"Court House",
            "type":"Public Place"
        }
    ],
    "sg:phone":"+32 55 61 21 00",
    "sg:postcode":"9700",
    "sg:province":"Oost-Vlaanderen",
    "sg:tags":[
        "administration",
        "central"
    ],
    "wof:name":"Bc Vlaamse Ardennen Nv",
    "wof:placetype":"venue"
},
  "geometry": {"coordinates":[3.57385993,50.8169593811],"type":"Point"}
}