{
  "type": "Feature",
  "properties": {
    "addr:full":"Legerstraat 61ba Antwerpen Antwerpen 2610",
    "addr:housenumber":"61ba",
    "addr:postcode":"2610",
    "addr:street":"Legerstraat",
    "iso:country":"BE",
    "sg:address":"Legerstraat 61ba",
    "sg:city":"Antwerpen",
    "sg:orig_category":"Artsen and specialisten",
    "sg:phone":"+32 3 830 66 79",
    "sg:postcode":"2610",
    "sg:province":"Antwerpen",
    "wof:name":"Jeannette De Loor",
    "wof:placetype":"venue"
},
  "geometry": {"coordinates":[4.3946051598,51.1691131592],"type":"Point"}
}