{
  "type": "Feature",
  "properties": {
    "addr:full":"Rue Jean Fischbach 1bb Chimay Hainaut 6460",
    "addr:housenumber":"1bb",
    "addr:postcode":"6460",
    "addr:street":"Rue Jean Fischbach",
    "iso:country":"BE",
    "sg:address":"Rue Jean Fischbach 1bb",
    "sg:city":"Chimay",
    "sg:orig_category":"Brandweer and civiele bescherming",
    "sg:phone":"+32 60 21 14 16",
    "sg:postcode":"6460",
    "sg:province":"Hainaut",
    "wof:name":"Corps De Pompiers",
    "wof:placetype":"venue"
},
  "geometry": {"coordinates":[4.3180971146,50.0501441956],"type":"Point"}
}