{
  "type": "Feature",
  "properties": {
    "addr:full":"Chauss\u00c9e De Charleroi 1 Charleroi Hainaut 6061",
    "addr:housenumber":"1",
    "addr:postcode":"6061",
    "addr:street":"Chausse\u0301E De Charleroi;Hainaut",
    "iso:country":"BE",
    "sg:address":"Chauss\u00c9e De Charleroi 1",
    "sg:city":"Charleroi",
    "sg:classifiers":[
        {
            "category":"Cafe",
            "type":"Food & Drink"
        }
    ],
    "sg:phone":"+32 71 31 55 10",
    "sg:postcode":"6061",
    "sg:province":"Hainaut",
    "sg:tags":[
        "caf\u00e9s"
    ],
    "wof:name":"Caf\u00c9 Cercle St.charles",
    "wof:placetype":"venue"
},
  "geometry": {"coordinates":[4.4792981148,50.4009284973],"type":"Point"}
}