{
  "type": "Feature",
  "properties": {
    "addr:full":"Grand-rue 96 Courcelles Hainaut 6183",
    "addr:housenumber":"96",
    "addr:postcode":"6183",
    "addr:street":"Grand-Rue",
    "iso:country":"BE",
    "sg:address":"Grand-rue 96",
    "sg:city":"Courcelles",
    "sg:orig_category":"Paramedische behandelingen",
    "sg:phone":"+32 71 46 56 48",
    "sg:postcode":"6183",
    "sg:province":"Hainaut",
    "wof:name":"M.p. Doumont",
    "wof:placetype":"venue"
},
  "geometry": {"coordinates":[4.3350520134,50.4609794617],"type":"Point"}
}