{
  "type": "Feature",
  "properties": {
    "iso:country":"BE",
    "sg:address":"Rue Du Wainage 80",
    "sg:city":"Charleroi",
    "sg:orig_category":"Traitements param\u00e9dicaux",
    "sg:phone":"+32 71 48 96 63",
    "sg:postcode":"6060",
    "sg:province":"Hainaut",
    "wof:name":"Myriam Martini",
    "wof:placetype":"venue"
},
  "geometry": {"coordinates":[4.4880981445,50.4251937866],"type":"Point"}
}