{
  "type": "Feature",
  "properties": {
    "iso:country":"BE",
    "sg:address":"Zuidstraat 25",
    "sg:city":"Torhout",
    "sg:orig_category":"Meubles D\u00e9taillants, Am\u00e9nagement de B\u00e2timents et de Cuisines. Eclairage et \u00e9quipements du foyer",
    "sg:phone":"+32 50 21 43 74",
    "sg:postcode":"8820",
    "sg:province":"West-Vlaanderen",
    "wof:name":"Casa Ristia",
    "wof:placetype":"venue"
},
  "geometry": {"coordinates":[3.1021490097,51.0635986328],"type":"Point"}
}