{
  "type": "Feature",
  "properties": {
    "addr:full":"Chauss\u00e9e De Tongres 95 Juprelle (voroux-lez-liers) Li\u00e8ge 4451",
    "addr:housenumber":"95",
    "addr:postcode":"4451",
    "addr:street":"Chausse\u0301E De Tongres;Voroux-Lez-Liers",
    "iso:country":"BE",
    "sg:address":"Chauss\u00e9e De Tongres 95",
    "sg:city":"Juprelle (voroux-lez-liers)",
    "sg:classifiers":[
        {
            "category":"Personal",
            "subcategory":"Beauty Salon",
            "type":"Services"
        }
    ],
    "sg:phone":"+32 4 247 47 44",
    "sg:postcode":"4451",
    "sg:province":"Li\u00e8ge",
    "sg:tags":[
        "lady",
        "-",
        "hairdressing"
    ],
    "wof:name":"Sandra K",
    "wof:placetype":"venue"
},
  "geometry": {"coordinates":[5.537124157,50.689250946],"type":"Point"}
}