{
  "type": "Feature",
  "properties": {
    "addr:full":"Graanmarkt 26 Ninove Oost-Vlaanderen 9400",
    "addr:housenumber":"26",
    "addr:postcode":"9400",
    "addr:street":"Graanmarkt",
    "iso:country":"BE",
    "sg:address":"Graanmarkt 26",
    "sg:city":"Ninove",
    "sg:orig_category":"Banques and organismes de cr\u00e9dit",
    "sg:phone":"+32 54 32 33 10",
    "sg:postcode":"9400",
    "sg:province":"Oost-Vlaanderen",
    "wof:name":"Citibank",
    "wof:placetype":"venue"
},
  "geometry": {"coordinates":[4.024687767,50.8355789185],"type":"Point"}
}