{
  "type": "Feature",
  "properties": {
    "addr:full":"Rue De La Princesse 19 Binche Hainaut 7130",
    "addr:housenumber":"19",
    "addr:postcode":"7130",
    "addr:street":"Rue De La Princesse",
    "iso:country":"BE",
    "sg:address":"Rue De La Princesse 19",
    "sg:city":"Binche",
    "sg:orig_category":"Non-Classified Establishments",
    "sg:phone":"+32 64 36 92 67",
    "sg:postcode":"7130",
    "sg:province":"Hainaut",
    "wof:name":"Libinvest Cosmetics Sa",
    "wof:placetype":"venue"
},
  "geometry": {"coordinates":[4.1620168686,50.4156036377],"type":"Point"}
}