{
  "type": "Feature",
  "properties": {
    "addr:full":"Leemstraat 43 Essen Antwerpen 2910",
    "addr:housenumber":"43",
    "addr:postcode":"2910",
    "addr:street":"Leemstraat",
    "iso:country":"BE",
    "sg:address":"Leemstraat 43",
    "sg:city":"Essen",
    "sg:classifiers":[
        {
            "category":"Retail",
            "subcategory":"Veterinary Services",
            "type":"Services"
        }
    ],
    "sg:phone":"+32 3 677 18 28",
    "sg:postcode":"2910",
    "sg:province":"Antwerpen",
    "sg:tags":[
        "veterinarian"
    ],
    "wof:name":"Verbocht M",
    "wof:placetype":"venue"
},
  "geometry": {"coordinates":[4.4456272125,51.4520301819],"type":"Point"}
}