{
  "type": "Feature",
  "properties": {
    "iso:country":"BE",
    "sg:address":"Zandstraat 1bb",
    "sg:city":"Maaseik",
    "sg:classifiers":[
        {
            "category":"Food & Beverages",
            "subcategory":"Fruits & Vegetables",
            "type":"Retail Goods"
        }
    ],
    "sg:phone":"+32 89 86 78 64",
    "sg:postcode":"3680",
    "sg:province":"Limburg",
    "sg:tags":[
        "groenten"
    ],
    "wof:name":"Jozef Joris",
    "wof:placetype":"venue"
},
  "geometry": {"coordinates":[5.6584239006,51.0671844482],"type":"Point"}
}