{
  "type": "Feature",
  "properties": {
    "iso:country":"BE",
    "sg:address":"Rue De Chassart 4",
    "sg:city":"Fleurus (saint-amand)",
    "sg:classifiers":[
        {
            "category":"Building & Trades",
            "subcategory":"Landscaping Services",
            "type":"Services"
        }
    ],
    "sg:phone":"+32 71 85 33 92",
    "sg:postcode":"6221",
    "sg:province":"Hainaut",
    "sg:tags":[
        "gardening",
        "garden",
        "maintenance"
    ],
    "wof:name":"Redebel Sa",
    "wof:placetype":"venue"
},
  "geometry": {"coordinates":[4.5451278687,50.5142593384],"type":"Point"}
}