{
  "type": "Feature",
  "properties": {
    "iso:country":"BE",
    "sg:address":"De Smet De Naeyerlaan 11",
    "sg:city":"Blankenberge",
    "sg:orig_category":"H\u00f4tels",
    "sg:phone":"+32 50 42 92 61",
    "sg:postcode":"8370",
    "sg:province":"West-Vlaanderen",
    "wof:name":"Hotel Beaufort",
    "wof:placetype":"venue"
},
  "geometry": {"coordinates":[3.1220870018,51.3125305176],"type":"Point"}
}