{
  "type": "Feature",
  "properties": {
    "iso:country":"BE",
    "sg:address":"Rue De Brabant 153",
    "sg:city":"Schaarbeek/schaerbeek",
    "sg:orig_category":"Electrom\u00e9nager, t\u00e9l\u00e9visions and radios",
    "sg:phone":"+32 2 215 09 78",
    "sg:postcode":"1030",
    "sg:province":"Bruxelles-Capitale",
    "wof:name":"Radio-tele/radio T\u00c9l\u00c9",
    "wof:placetype":"venue"
},
  "geometry": {"coordinates":[4.3650460243,50.8626098633],"type":"Point"}
}