{
  "type": "Feature",
  "properties": {
    "addr:full":"Neerstraat 28 Zwalm (nederzwalm-hermelgem) Oost-Vlaanderen 9636",
    "addr:housenumber":"28",
    "addr:postcode":"9636",
    "addr:street":"Neerstraat;Nederzwalm-Hermelgem",
    "iso:country":"BE",
    "sg:address":"Neerstraat 28",
    "sg:city":"Zwalm (nederzwalm-hermelgem)",
    "sg:classifiers":[
        {
            "category":"Professional",
            "subcategory":"Engineering",
            "type":"Services"
        }
    ],
    "sg:phone":"+32 55 49 60 12",
    "sg:postcode":"9636",
    "sg:province":"Oost-Vlaanderen",
    "sg:tags":[
        "-"
    ],
    "wof:name":"P.v.s. Electronic Developments",
    "wof:placetype":"venue"
},
  "geometry": {"coordinates":[3.6905200481,50.8861694336],"type":"Point"}
}