{
  "type": "Feature",
  "properties": {
    "addr:full":"Bellemstraat 56 Aalter Oost-Vlaanderen 9880",
    "addr:housenumber":"56",
    "addr:postcode":"9880",
    "addr:street":"Bellemstraat",
    "iso:country":"BE",
    "sg:address":"Bellemstraat 56",
    "sg:city":"Aalter",
    "sg:orig_category":"Loodgieterij, verwarming and sanitaire installaties",
    "sg:phone":"+32 9 374 11 77",
    "sg:postcode":"9880",
    "sg:province":"Oost-Vlaanderen",
    "wof:name":"Jan Dombrecht",
    "wof:placetype":"venue"
},
  "geometry": {"coordinates":[3.4546020031,51.0853157043],"type":"Point"}
}