{
  "type": "Feature",
  "properties": {
    "addr:full":"Rue Lambert Darchis 55 Herstal Li\u00e8ge 4040",
    "addr:housenumber":"55",
    "addr:postcode":"4040",
    "addr:street":"Rue Lambert Darchis",
    "iso:country":"BE",
    "sg:address":"Rue Lambert Darchis 55",
    "sg:city":"Herstal",
    "sg:orig_category":"Loodgieterij, verwarming and sanitaire installaties",
    "sg:phone":"+32 4 278 58 18",
    "sg:postcode":"4040",
    "sg:province":"Li\u00e8ge",
    "wof:name":"Lucatelli",
    "wof:placetype":"venue"
},
  "geometry": {"coordinates":[5.5966930389,50.681224823],"type":"Point"}
}