{
  "type": "Feature",
  "properties": {
    "addr:full":"Place St Severin 6 Huy Li\u00e8ge 4500",
    "addr:housenumber":"6",
    "addr:postcode":"4500",
    "addr:street":"Place St Severin",
    "iso:country":"BE",
    "sg:address":"Place St Severin 6",
    "sg:city":"Huy",
    "sg:classifiers":[
        {
            "category":"Banks & Credit Unions",
            "subcategory":"Investment Brokerage",
            "type":"Services"
        }
    ],
    "sg:phone":"+32 85 21 48 68",
    "sg:postcode":"4500",
    "sg:province":"Li\u00e8ge",
    "sg:tags":[
        "energy",
        "recuperation",
        "saving"
    ],
    "wof:name":"Guichet De L'energie",
    "wof:placetype":"venue"
},
  "geometry": {"coordinates":[5.2395892143,50.5191268921],"type":"Point"}
}