{
  "type": "Feature",
  "properties": {
    "addr:full":"Tiensesteenweg 36 Kortenaken Vlaams-Brabant 3473",
    "addr:housenumber":"36",
    "addr:postcode":"3473",
    "addr:street":"Tiensesteenweg",
    "iso:country":"BE",
    "sg:address":"Tiensesteenweg 36",
    "sg:city":"Kortenaken",
    "sg:classifiers":[
        {
            "category":"Fast Food",
            "type":"Food & Drink"
        }
    ],
    "sg:phone":"+32 16 77 76 36",
    "sg:postcode":"3473",
    "sg:province":"Vlaams-Brabant",
    "sg:tags":[
        "\u00c0",
        "emporter",
        "restaurants"
    ],
    "wof:name":"Eddy",
    "wof:placetype":"venue"
},
  "geometry": {"coordinates":[5.0507049561,50.9000701904],"type":"Point"}
}