{
  "type": "Feature",
  "properties": {
    "iso:country":"BE",
    "sg:address":"Vennekeslaan 24",
    "sg:city":"As",
    "sg:classifiers":[
        {
            "category":"Building & Trades",
            "subcategory":"Electrical",
            "type":"Services"
        }
    ],
    "sg:phone":"+32 89 65 87 07",
    "sg:postcode":"3665",
    "sg:province":"Limburg",
    "sg:tags":[
        "electric",
        "-",
        "housewiring",
        "contractor"
    ],
    "wof:name":"Agc Noben",
    "wof:placetype":"venue"
},
  "geometry": {"coordinates":[5.558754921,51.000415802],"type":"Point"}
}