{
  "type": "Feature",
  "properties": {
    "iso:country":"BE",
    "sg:address":"Gelaagstraat 9",
    "sg:city":"Kruibeke",
    "sg:classifiers":[
        {
            "category":"Bars & Pubs",
            "subcategory":"Sports Bar",
            "type":"Food & Drink"
        }
    ],
    "sg:phone":"+32 3 744 08 33",
    "sg:postcode":"9150",
    "sg:province":"Oost-Vlaanderen",
    "sg:tags":[
        "fab",
        "diver",
        "aliment"
    ],
    "wof:name":"Soeperman",
    "wof:placetype":"venue"
},
  "geometry": {"coordinates":[4.2886328697,51.1257019043],"type":"Point"}
}