{
  "type": "Feature",
  "properties": {
    "addr:full":"Lange Nieuwstraat 74 Westerlo (tongerlo) Antwerpen 2260",
    "addr:housenumber":"74",
    "addr:postcode":"2260",
    "addr:street":"Lange Nieuwstraat",
    "iso:country":"BE",
    "sg:address":"Lange Nieuwstraat 74",
    "sg:city":"Westerlo (tongerlo)",
    "sg:classifiers":[
        {
            "category":"Personal",
            "subcategory":"Beauty Salon",
            "type":"Services"
        }
    ],
    "sg:phone":"+32 14 54 18 03",
    "sg:postcode":"2260",
    "sg:province":"Antwerpen",
    "sg:tags":[
        "lady",
        "-",
        "hairdressing"
    ],
    "wof:name":"Cheveux Bizarre Bvba",
    "wof:placetype":"venue"
},
  "geometry": {"coordinates":[4.911837101,51.0861434937],"type":"Point"}
}