{
  "type": "Feature",
  "properties": {
    "addr:full":"Wagenmakersstraat 2 B Kortrijk West-Vlaanderen 8500",
    "addr:housenumber":"2 b",
    "addr:postcode":"8500",
    "addr:street":"Wagenmakersstraat",
    "iso:country":"BE",
    "sg:address":"Wagenmakersstraat 2 B",
    "sg:city":"Kortrijk",
    "sg:orig_category":"Herstellingen and onderhoud aan huis voor voertuigen Voertuigen",
    "sg:phone":"+32 56 20 22 20",
    "sg:postcode":"8500",
    "sg:province":"West-Vlaanderen",
    "wof:name":"Carrosserie Mondy",
    "wof:placetype":"venue"
},
  "geometry": {"coordinates":[3.269769907,50.8188667297],"type":"Point"}
}