{
  "type": "Feature",
  "properties": {
    "iso:country":"BE",
    "sg:address":"Schapenweg 138",
    "sg:city":"Brussel/bruxelles",
    "sg:orig_category":"Plaatsen van vloer- and muurbekleding Schilders",
    "sg:phone":"+32 475 73 77 02",
    "sg:postcode":"1020",
    "sg:province":"Bruxelles-Capitale",
    "wof:name":"Gilbert Heyndels",
    "wof:placetype":"venue"
},
  "geometry": {"coordinates":[4.369161129,50.8991737366],"type":"Point"}
}