{
  "type": "Feature",
  "properties": {
    "iso:country":"BE",
    "sg:address":"Tiensestraat 228",
    "sg:city":"Leuven",
    "sg:orig_category":"Accessoires vestimentaires",
    "sg:phone":"+32 16 23 17 57",
    "sg:postcode":"3000",
    "sg:province":"Vlaams-Brabant",
    "wof:name":"Huis Henriette",
    "wof:placetype":"venue"
},
  "geometry": {"coordinates":[4.7120289803,50.874168396],"type":"Point"}
}