{
  "type": "Feature",
  "properties": {
    "iso:country":"BE",
    "sg:address":"Chauss\u00c9e De Mons 175",
    "sg:city":"Soignies",
    "sg:orig_category":"Herstellingen and onderhoud van auto's Voertuigen",
    "sg:phone":"+32 67 33 25 20",
    "sg:postcode":"7060",
    "sg:province":"Hainaut",
    "wof:name":"Alain Marcassin",
    "wof:placetype":"venue"
},
  "geometry": {"coordinates":[4.0606489182,50.5637321472],"type":"Point"}
}