{
  "type": "Feature",
  "properties": {
    "addr:full":"Alfons Pieterslaan 7 Oostende West-Vlaanderen 8400",
    "addr:housenumber":"7",
    "addr:postcode":"8400",
    "addr:street":"Alfons Pieterslaan",
    "iso:country":"BE",
    "sg:address":"Alfons Pieterslaan 7",
    "sg:city":"Oostende",
    "sg:orig_category":"Disneyland Parijs Reisbureaus",
    "sg:phone":"+32 59 50 21 70",
    "sg:postcode":"8400",
    "sg:province":"West-Vlaanderen",
    "wof:name":"Ostend Travel Shop",
    "wof:placetype":"venue"
},
  "geometry": {"coordinates":[2.9155950546,51.2266540527],"type":"Point"}
}