{
  "type": "Feature",
  "properties": {
    "addr:full":"Frederik Wouterslaan 21 Kampenhout Vlaams-Brabant 1910",
    "addr:housenumber":"21",
    "addr:postcode":"1910",
    "addr:street":"Frederik Wouterslaan",
    "iso:country":"BE",
    "sg:address":"Frederik Wouterslaan 21",
    "sg:city":"Kampenhout",
    "sg:orig_category":"Notarissen",
    "sg:phone":"+32 16 65 50 21",
    "sg:postcode":"1910",
    "sg:province":"Vlaams-Brabant",
    "wof:name":"Jean-fran\u00c7ois Coppin",
    "wof:placetype":"venue"
},
  "geometry": {"coordinates":[4.5512990952,50.9399452209],"type":"Point"}
}