{
  "type": "Feature",
  "properties": {
    "addr:full":"Guido Gezellestraat 83 Denderleeuw Oost-Vlaanderen 9470",
    "addr:housenumber":"83",
    "addr:postcode":"9470",
    "addr:street":"Guido Gezellestraat",
    "iso:country":"BE",
    "sg:address":"Guido Gezellestraat 83",
    "sg:city":"Denderleeuw",
    "sg:orig_category":"Pain, p\u00e2tisseries and confiseries",
    "sg:phone":"+32 53 68 44 78",
    "sg:postcode":"9470",
    "sg:province":"Oost-Vlaanderen",
    "wof:name":"Huis Zachary",
    "wof:placetype":"venue"
},
  "geometry": {"coordinates":[4.0780520439,50.8870315552],"type":"Point"}
}