{
  "type": "Feature",
  "properties": {
    "iso:country":"BE",
    "sg:address":"Elf Novemberstraat15",
    "sg:city":"Mechelen",
    "sg:orig_category":"Agences de publicit\u00e9. Imprimeries and copyshops",
    "sg:phone":"+32 15 41 70 13",
    "sg:postcode":"2800",
    "sg:province":"Antwerpen",
    "wof:name":"Ghekiere Publiciteit",
    "wof:placetype":"venue"
},
  "geometry": {"coordinates":[4.4863052368,51.0085868835],"type":"Point"}
}