{
  "type": "Feature",
  "properties": {
    "addr:full":"Passage De La Poste 1 Box 64 Mouscron Hainaut 7700",
    "addr:housenumber":"1 box 64",
    "addr:postcode":"7700",
    "addr:street":"Passage De La Poste",
    "iso:country":"BE",
    "sg:address":"Passage De La Poste 1 Box 64",
    "sg:city":"Mouscron",
    "sg:classifiers":[
        {
            "category":"Manufacturing",
            "subcategory":"Printing",
            "type":"Manufacturing & Wholesale Goods"
        }
    ],
    "sg:phone":"+32 56 33 40 36",
    "sg:postcode":"7700",
    "sg:province":"Hainaut",
    "sg:tags":[
        "textile",
        "-"
    ],
    "wof:name":"Publicity Shirts",
    "wof:placetype":"venue"
},
  "geometry": {"coordinates":[3.2142720222,50.7455863953],"type":"Point"}
}