{
  "type": "Feature",
  "properties": {
    "addr:full":"Rue D'arlon 36 Neufchateau Luxembourg 6840",
    "addr:housenumber":"36",
    "addr:postcode":"6840",
    "addr:street":"Rue D'Arlon",
    "iso:country":"BE",
    "sg:address":"Rue D'arlon 36",
    "sg:city":"Neufchateau",
    "sg:orig_category":"Protection civile",
    "sg:phone":"+32 61 27 85 20",
    "sg:postcode":"6840",
    "sg:province":"Luxembourg",
    "wof:name":"Corps De Pompiers",
    "wof:placetype":"venue"
},
  "geometry": {"coordinates":[5.4388642311,49.8396263123],"type":"Point"}
}