{
  "type": "Feature",
  "properties": {
    "addr:full":"Park Ter Daelmen 73 Zomergem Oost-Vlaanderen 9930",
    "addr:housenumber":"73",
    "addr:postcode":"9930",
    "addr:street":"Park Ter Daelmen",
    "iso:country":"BE",
    "sg:address":"Park Ter Daelmen 73",
    "sg:city":"Zomergem",
    "sg:orig_category":"Traitements param\u00e9dicaux",
    "sg:phone":"+32 9 372 81 51",
    "sg:postcode":"9930",
    "sg:province":"Oost-Vlaanderen",
    "wof:name":"S. Van Dycke",
    "wof:placetype":"venue"
},
  "geometry": {"coordinates":[3.5570290089,51.1264381409],"type":"Point"}
}