{
  "type": "Feature",
  "properties": {
    "addr:full":"Weststraat 50 Evergem Oost-Vlaanderen 9940",
    "addr:housenumber":"50",
    "addr:postcode":"9940",
    "addr:street":"Weststraat;Oost-Vlaanderen",
    "iso:country":"BE",
    "sg:address":"Weststraat 50",
    "sg:city":"Evergem",
    "sg:orig_category":"Epiceries",
    "sg:phone":"+32 9 357 41 85",
    "sg:postcode":"9940",
    "sg:province":"Oost-Vlaanderen",
    "wof:name":"Stefaan Dossche",
    "wof:placetype":"venue"
},
  "geometry": {"coordinates":[3.6757500172,51.1310157776],"type":"Point"}
}