{
  "type": "Feature",
  "properties": {
    "addr:full":"Kruisstraat 60 Vosselaar Antwerpen 2350",
    "addr:housenumber":"60",
    "addr:postcode":"2350",
    "addr:street":"Kruisstraat",
    "iso:country":"BE",
    "sg:address":"Kruisstraat 60",
    "sg:city":"Vosselaar",
    "sg:orig_category":"Woningbouw",
    "sg:phone":"+32 14 61 96 74",
    "sg:postcode":"2350",
    "sg:province":"Antwerpen",
    "wof:name":"Buys Bouwwerken",
    "wof:placetype":"venue"
},
  "geometry": {"coordinates":[4.888220787,51.3042564392],"type":"Point"}
}