{
  "type": "Feature",
  "properties": {
    "addr:full":"Rue Pastorale 25 Moeskroen/mouscron Hainaut 7711",
    "addr:housenumber":"25",
    "addr:postcode":"7711",
    "addr:street":"Rue Pastorale",
    "iso:country":"BE",
    "sg:address":"Rue Pastorale 25",
    "sg:city":"Moeskroen/mouscron",
    "sg:orig_category":"M\u00e9decins and sp\u00e9cialistes",
    "sg:phone":"+32 56 48 86 15",
    "sg:postcode":"7711",
    "sg:province":"Hainaut",
    "wof:name":"Paul Lippinois",
    "wof:placetype":"venue"
},
  "geometry": {"coordinates":[3.2929000854,50.7344207764],"type":"Point"}
}