{
  "type": "Feature",
  "properties": {
    "iso:country":"BE",
    "sg:address":"Lispersteenweg 240",
    "sg:city":"Lier",
    "sg:classifiers":[
        {
            "category":"Food & Beverages",
            "subcategory":"Chocolate",
            "type":"Retail Goods"
        }
    ],
    "sg:phone":"+32 3 480 00 66",
    "sg:postcode":"2500",
    "sg:province":"Antwerpen",
    "sg:tags":[
        "confectionery",
        "-"
    ],
    "wof:name":"Verbeeck",
    "wof:placetype":"venue"
},
  "geometry": {"coordinates":[4.5759267807,51.1443939209],"type":"Point"}
}