{
  "type": "Feature",
  "properties": {
    "iso:country":"BE",
    "sg:address":"Hoogland 11",
    "sg:city":"Zwevegem",
    "sg:orig_category":"Quincailleries",
    "sg:phone":"+32 56 75 89 08",
    "sg:postcode":"8550",
    "sg:province":"West-Vlaanderen",
    "wof:name":"Verschuere Luc",
    "wof:placetype":"venue"
},
  "geometry": {"coordinates":[3.3354239464,50.7998695374],"type":"Point"}
}