{
  "type": "Feature",
  "properties": {
    "iso:country":"BE",
    "sg:address":"Kaulillerweg 175",
    "sg:city":"Bocholt",
    "sg:orig_category":"Boekhouders",
    "sg:postcode":"3950",
    "sg:province":"Limburg",
    "wof:name":"Joannes Lipkens",
    "wof:placetype":"venue"
},
  "geometry": {"coordinates":[5.5444169044,51.1793251038],"type":"Point"}
}