{
  "type": "Feature",
  "properties": {
    "addr:full":"Rue De Mons 29 Braine-le-comte Hainaut 7090",
    "addr:housenumber":"29",
    "addr:postcode":"7090",
    "addr:street":"Rue De Mons",
    "iso:country":"BE",
    "sg:address":"Rue De Mons 29",
    "sg:city":"Braine-le-comte",
    "sg:classifiers":[
        {
            "category":"Cafe",
            "type":"Food & Drink"
        }
    ],
    "sg:phone":"+32 67 55 22 89",
    "sg:postcode":"7090",
    "sg:province":"Hainaut",
    "sg:tags":[
        "caf\u00e9s"
    ],
    "wof:name":"Michele Henskens",
    "wof:placetype":"venue"
},
  "geometry": {"coordinates":[4.1347341537,50.609577179],"type":"Point"}
}