{
  "type": "Feature",
  "properties": {
    "addr:full":"Avenue De Fr\u00c9 37 Ukkel/uccle Bruxelles-Capitale 1180",
    "addr:housenumber":"37",
    "addr:postcode":"1180",
    "addr:street":"Avenue De Fre\u0301;/",
    "iso:country":"BE",
    "sg:address":"Avenue De Fr\u00c9 37",
    "sg:city":"Ukkel/uccle",
    "sg:classifiers":[
        {
            "category":"Arena",
            "subcategory":"Sports Club",
            "type":"Entertainment"
        }
    ],
    "sg:phone":"+32 2 375 23 49",
    "sg:postcode":"1180",
    "sg:province":"Bruxelles-Capitale",
    "sg:tags":[
        "de"
    ],
    "wof:name":"R. Uccle Sport T.h.c.",
    "wof:placetype":"venue"
},
  "geometry": {"coordinates":[4.3455810547,50.8033866882],"type":"Point"}
}