{
  "type": "Feature",
  "properties": {
    "iso:country":"BE",
    "sg:address":"Kleine Markt 4b5",
    "sg:city":"Antwerpen",
    "sg:orig_category":"Editeurs de livres. Agences de publicit\u00e9",
    "sg:phone":"+32 3 231 28 00",
    "sg:postcode":"2000",
    "sg:province":"Antwerpen",
    "wof:name":"B. Promotion",
    "wof:placetype":"venue"
},
  "geometry": {"coordinates":[4.4020757675,51.215587616],"type":"Point"}
}