{
  "type": "Feature",
  "properties": {
    "addr:full":"De Fr\u00c9laan 44 Ukkel/uccle Bruxelles-Capitale 1180",
    "addr:housenumber":"44",
    "addr:postcode":"1180",
    "addr:street":"De Fre\u0301Laan;/",
    "iso:country":"BE",
    "sg:address":"De Fr\u00c9laan 44",
    "sg:city":"Ukkel/uccle",
    "sg:orig_category":"Zalen voor culturele evenementen",
    "sg:phone":"+32 2 375 15 63",
    "sg:postcode":"1180",
    "sg:province":"Bruxelles-Capitale",
    "wof:name":"Th\u00c9\u00c2tre Du Ratinet",
    "wof:placetype":"venue"
},
  "geometry": {"coordinates":[4.347867012,50.8038406372],"type":"Point"}
}