{
  "type": "Feature",
  "properties": {
    "addr:full":"Tervurenlaan 142 Sint-pieters-woluwe/woluwe-saint-pierre Bruxelles-Capitale 1150",
    "addr:housenumber":"142",
    "addr:postcode":"1150",
    "addr:street":"Tervurenlaan;/",
    "iso:country":"BE",
    "sg:address":"Tervurenlaan 142",
    "sg:city":"Sint-pieters-woluwe/woluwe-saint-pierre",
    "sg:orig_category":"Banken and kredietinstellingen",
    "sg:phone":"+32 2 551 99 21",
    "sg:postcode":"1150",
    "sg:province":"Bruxelles-Capitale",
    "wof:name":"Deutsche Bank",
    "wof:placetype":"venue"
},
  "geometry": {"coordinates":[4.4072999954,50.8374786377],"type":"Point"}
}