{
  "type": "Feature",
  "properties": {
    "addr:full":"Tiensesteenweg 78 Sint-truiden Limburg 3800",
    "addr:housenumber":"78",
    "addr:postcode":"3800",
    "addr:street":"Tiensesteenweg",
    "iso:country":"BE",
    "sg:address":"Tiensesteenweg 78",
    "sg:city":"Sint-truiden",
    "sg:classifiers":[
        {
            "category":"Banks & Credit Unions",
            "subcategory":"Investment Brokerage",
            "type":"Services"
        }
    ],
    "sg:phone":"+32 11 67 48 94",
    "sg:postcode":"3800",
    "sg:province":"Limburg",
    "wof:name":"Limbrassur Nv",
    "wof:placetype":"venue"
},
  "geometry": {"coordinates":[5.1762270927,50.8149185181],"type":"Point"}
}