{
  "type": "Feature",
  "properties": {
    "iso:country":"BE",
    "sg:address":"Schoonwinkelstraat 7",
    "sg:city":"Hasselt (sint-lambrechts-herk)",
    "sg:classifiers":[
        {
            "category":"Retail",
            "subcategory":"Auto Repair",
            "type":"Services"
        }
    ],
    "sg:phone":"+32 11 59 67 36",
    "sg:postcode":"3500",
    "sg:province":"Limburg",
    "sg:tags":[
        "truck-body"
    ],
    "wof:name":"De Reisduif",
    "wof:placetype":"venue"
},
  "geometry": {"coordinates":[5.3196082115,50.9013557434],"type":"Point"}
}