{
  "type": "Feature",
  "properties": {
    "iso:country":"BE",
    "sg:address":"Fruitmarkt 20",
    "sg:city":"Hasselt",
    "sg:classifiers":[
        {
            "category":"Personal",
            "subcategory":"Beauty Salon",
            "type":"Services"
        }
    ],
    "sg:phone":"+32 11 22 13 79",
    "sg:postcode":"3500",
    "sg:province":"Limburg",
    "sg:tags":[
        "de",
        "coiffure"
    ],
    "wof:name":"Deelkens Intercoiffure",
    "wof:placetype":"venue"
},
  "geometry": {"coordinates":[5.3387131691,50.9301986694],"type":"Point"}
}