{
  "type": "Feature",
  "properties": {
    "addr:full":"Breutheide 37 Sint-amands (lippelo) Antwerpen 2890",
    "addr:housenumber":"37",
    "addr:postcode":"2890",
    "addr:street":"Breutheide",
    "iso:country":"BE",
    "sg:address":"Breutheide 37",
    "sg:city":"Sint-amands (lippelo)",
    "sg:classifiers":[
        {
            "category":"Professional",
            "subcategory":"Management & Consulting",
            "type":"Services"
        }
    ],
    "sg:phone":"+32 52 34 28 80",
    "sg:postcode":"2890",
    "sg:province":"Antwerpen",
    "sg:tags":[
        "tax-consultants"
    ],
    "wof:name":"De Boeck M",
    "wof:placetype":"venue"
},
  "geometry": {"coordinates":[4.248737812,51.046169281],"type":"Point"}
}