{
  "type": "Feature",
  "properties": {
    "addr:full":"Kerklaan 19 Peer (kleine Brogel) Limburg 3990",
    "addr:housenumber":"19",
    "addr:postcode":"3990",
    "addr:street":"Kerklaan;Kleine Brogel Limburg",
    "iso:country":"BE",
    "sg:address":"Kerklaan 19",
    "sg:city":"Peer (kleine Brogel)",
    "sg:classifiers":[
        {
            "category":"Health Services",
            "subcategory":"Nursing And Care Facility",
            "type":"Services"
        }
    ],
    "sg:phone":"+32 11 63 72 91",
    "sg:postcode":"3990",
    "sg:province":"Limburg",
    "sg:tags":[
        "home"
    ],
    "wof:name":"Wolfs Sonia",
    "wof:placetype":"venue"
},
  "geometry": {"coordinates":[5.4520711899,51.1328849792],"type":"Point"}
}