{
  "type": "Feature",
  "properties": {
    "addr:full":"Bruggesteenweg 98 Hooglede (gits) West-Vlaanderen 8830",
    "addr:housenumber":"98",
    "addr:postcode":"8830",
    "addr:street":"Bruggesteenweg",
    "iso:country":"BE",
    "sg:address":"Bruggesteenweg 98",
    "sg:city":"Hooglede (gits)",
    "sg:classifiers":[
        {
            "category":"Autos & Motor Vehicles",
            "subcategory":"Automobile Sales",
            "type":"Retail Goods"
        }
    ],
    "sg:phone":"+32 51 22 70 48",
    "sg:postcode":"8830",
    "sg:province":"West-Vlaanderen",
    "sg:tags":[
        "car",
        "used",
        "-"
    ],
    "wof:name":"Garage De Rycke",
    "wof:placetype":"venue"
},
  "geometry": {"coordinates":[3.0915009975,50.9812393188],"type":"Point"}
}