{
  "type": "Feature",
  "properties": {
    "iso:country":"BE",
    "sg:address":"Dorpsstraat 50",
    "sg:city":"Stabroek",
    "sg:orig_category":"Boucheries",
    "sg:phone":"+32 3 568 62 82",
    "sg:postcode":"2940",
    "sg:province":"Antwerpen",
    "wof:name":"Cuypers-van Buynder",
    "wof:placetype":"venue"
},
  "geometry": {"coordinates":[4.3655967712,51.3321151733],"type":"Point"}
}