{
  "type": "Feature",
  "properties": {
    "addr:full":"Avenue D'ophem 1 Bruxelles (woluwe-saint-pierre) Bruxelles-Capitale 1150",
    "addr:housenumber":"1",
    "addr:postcode":"1150",
    "addr:street":"Avenue D'Ophem",
    "iso:country":"BE",
    "sg:address":"Avenue D'ophem 1",
    "sg:city":"Bruxelles (woluwe-saint-pierre)",
    "sg:classifiers":[
        {
            "category":"Professional",
            "subcategory":"Accounting & Tax Preparation",
            "type":"Services"
        }
    ],
    "sg:phone":"+32 2 772 52 06",
    "sg:postcode":"1150",
    "sg:province":"Bruxelles-Capitale",
    "sg:tags":[
        "bookkeeper"
    ],
    "wof:name":"Bouchat B",
    "wof:placetype":"venue"
},
  "geometry": {"coordinates":[4.4654350281,50.8414497375],"type":"Point"}
}