{
  "type": "Feature",
  "properties": {
    "iso:country":"BE",
    "sg:address":"Gentstraat 151",
    "sg:city":"Oudenaarde",
    "sg:orig_category":"M\u00e9decins and sp\u00e9cialistes",
    "sg:phone":"+32 55 31 22 37",
    "sg:postcode":"9700",
    "sg:province":"Oost-Vlaanderen",
    "wof:name":"Rudy Van Den Broecke",
    "wof:placetype":"venue"
},
  "geometry": {"coordinates":[3.6011760235,50.8578567505],"type":"Point"}
}