{
  "type": "Feature",
  "properties": {
    "addr:full":"Rue Doumier 110 Ans Li\u00e8ge 4430",
    "addr:housenumber":"110",
    "addr:postcode":"4430",
    "addr:street":"Rue Doumier",
    "iso:country":"BE",
    "sg:address":"Rue Doumier 110",
    "sg:city":"Ans",
    "sg:orig_category":"Plomberie, chauffage and installations sanitaires. Charpentes and couvertures",
    "sg:phone":"+32 4 246 12 73",
    "sg:postcode":"4430",
    "sg:province":"Li\u00e8ge",
    "wof:name":"Hubert Heyne",
    "wof:placetype":"venue"
},
  "geometry": {"coordinates":[5.5147480965,50.6561393738],"type":"Point"}
}