{
  "type": "Feature",
  "properties": {
    "addr:full":"Rue Victor Allard 4 Bruxelles (uccle) Bruxelles-Capitale 1180",
    "addr:housenumber":"4",
    "addr:postcode":"1180",
    "addr:street":"Rue Victor Allard",
    "iso:country":"BE",
    "sg:address":"Rue Victor Allard 4",
    "sg:city":"Bruxelles (uccle)",
    "sg:classifiers":[
        {
            "category":"Real Estate",
            "subcategory":"Real Estate Services",
            "type":"Services"
        }
    ],
    "sg:phone":"+32 2 672 16 58",
    "sg:postcode":"1180",
    "sg:province":"Bruxelles-Capitale",
    "wof:name":"Matiwear Sa",
    "wof:placetype":"venue"
},
  "geometry": {"coordinates":[4.3365559578,50.8026924133],"type":"Point"}
}