{
  "type": "Feature",
  "properties": {
    "addr:full":"Rue Sainte-walburge 195 Li\u00c8ge Li\u00e8ge 4000",
    "addr:housenumber":"195",
    "addr:postcode":"4000",
    "addr:street":"Rue Sainte-Walburge",
    "iso:country":"BE",
    "sg:address":"Rue Sainte-walburge 195",
    "sg:city":"Li\u00c8ge",
    "sg:orig_category":"Artsen and specialisten",
    "sg:phone":"+32 4 226 36 06",
    "sg:postcode":"4000",
    "sg:province":"Li\u00e8ge",
    "wof:name":"Elissaveta Nikolava",
    "wof:placetype":"venue"
},
  "geometry": {"coordinates":[5.5674409866,50.6587219238],"type":"Point"}
}