{
  "type": "Feature",
  "properties": {
    "addr:full":"Rue De La Fontaine 2 Brunehaut Hainaut 7620",
    "addr:housenumber":"2",
    "addr:postcode":"7620",
    "addr:street":"Rue De La Fontaine",
    "iso:country":"BE",
    "sg:address":"Rue De La Fontaine 2",
    "sg:city":"Brunehaut",
    "sg:classifiers":[
        {
            "category":"Restaurant",
            "type":"Food & Drink"
        }
    ],
    "sg:phone":"+32 69 34 67 90",
    "sg:postcode":"7620",
    "sg:province":"Hainaut",
    "wof:name":"J. Cardon",
    "wof:placetype":"venue"
},
  "geometry": {"coordinates":[3.4226100445,50.5399017334],"type":"Point"}
}