{
  "type": "Feature",
  "properties": {
    "iso:country":"BE",
    "sg:address":"Lozerstraat 9",
    "sg:city":"Kruishoutem",
    "sg:orig_category":"Alternatieve geneeskunde Drogisterijen",
    "sg:phone":"+32 9 383 82 62",
    "sg:postcode":"9770",
    "sg:province":"Oost-Vlaanderen",
    "wof:name":"Christiaan Van Audenhove",
    "wof:placetype":"venue"
},
  "geometry": {"coordinates":[3.5617570877,50.9236068726],"type":"Point"}
}