{
  "type": "Feature",
  "properties": {
    "iso:country":"BE",
    "sg:address":"Desmedtstraat 25",
    "sg:city":"Hoogstraten (minderhout)",
    "sg:classifiers":[
        {
            "category":"Health Services",
            "subcategory":"Health Practitioner",
            "type":"Services"
        }
    ],
    "sg:phone":"+32 3 314 96 65",
    "sg:postcode":"2322",
    "sg:province":"Antwerpen",
    "sg:tags":[
        "physiotherapist"
    ],
    "wof:name":"Marien Ilse",
    "wof:placetype":"venue"
},
  "geometry": {"coordinates":[4.763384819,51.4160041809],"type":"Point"}
}