{
  "type": "Feature",
  "properties": {
    "iso:country":"BE",
    "sg:address":"Leenstraat 9",
    "sg:city":"Zottegem",
    "sg:orig_category":"Dierenartsen",
    "sg:phone":"+32 9 360 17 66",
    "sg:postcode":"9620",
    "sg:province":"Oost-Vlaanderen",
    "wof:name":"Lieven De Wolf",
    "wof:placetype":"venue"
},
  "geometry": {"coordinates":[3.8365309238,50.8738479614],"type":"Point"}
}