{
  "type": "Feature",
  "properties": {
    "addr:full":"Molenkouterstraat 65 Zulte (machelen) Oost-Vlaanderen 9870",
    "addr:housenumber":"65",
    "addr:postcode":"9870",
    "addr:street":"Molenkouterstraat",
    "iso:country":"BE",
    "sg:address":"Molenkouterstraat 65",
    "sg:city":"Zulte (machelen)",
    "sg:classifiers":[
        {
            "category":"Shopping",
            "subcategory":"Pets & Pet Supplies",
            "type":"Retail Goods"
        }
    ],
    "sg:phone":"+32 9 328 03 77",
    "sg:postcode":"9870",
    "sg:province":"Oost-Vlaanderen",
    "sg:tags":[
        "shop",
        "-"
    ],
    "wof:name":"Karthuizer Of The Blue Silver Shadow",
    "wof:placetype":"venue"
},
  "geometry": {"coordinates":[3.4978671074,50.9582328796],"type":"Point"}
}