{
  "type": "Feature",
  "properties": {
    "iso:country":"BE",
    "sg:address":"Kasteeldreef 149",
    "sg:city":"Schilde",
    "sg:classifiers":[
        {
            "category":"Shopping",
            "subcategory":"Clothing, Apparel, & Fashions",
            "type":"Retail Goods"
        }
    ],
    "sg:phone":"+32 3 354 17 43",
    "sg:postcode":"2970",
    "sg:province":"Antwerpen",
    "sg:tags":[
        "v\u00eatements",
        "pour",
        "dame"
    ],
    "wof:name":"Boetiek Cadence",
    "wof:placetype":"venue"
},
  "geometry": {"coordinates":[4.552947998,51.2310600281],"type":"Point"}
}