{
  "type": "Feature",
  "properties": {
    "addr:full":"Wierookstraat 2 Deinze Oost-Vlaanderen 9800",
    "addr:housenumber":"2",
    "addr:postcode":"9800",
    "addr:street":"Wierookstraat",
    "iso:country":"BE",
    "sg:address":"Wierookstraat 2",
    "sg:city":"Deinze",
    "sg:orig_category":"Groententeelt",
    "sg:phone":"+32 9 386 75 63",
    "sg:postcode":"9800",
    "sg:province":"Oost-Vlaanderen",
    "wof:name":"Marnix Dhuygelaere",
    "wof:placetype":"venue"
},
  "geometry": {"coordinates":[3.5024929047,51.0029067993],"type":"Point"}
}