{
  "type": "Feature",
  "properties": {
    "iso:country":"BE",
    "sg:address":"Burggravestraat 5",
    "sg:city":"Temse",
    "sg:orig_category":"Kapsalons",
    "sg:phone":"+32 52 46 21 99",
    "sg:postcode":"9140",
    "sg:province":"Oost-Vlaanderen",
    "wof:name":"Hilde Van De Voorde",
    "wof:placetype":"venue"
},
  "geometry": {"coordinates":[4.1475629807,51.116771698],"type":"Point"}
}