{
  "type": "Feature",
  "properties": {
    "iso:country":"BE",
    "sg:address":"Deinsesteenweg 218",
    "sg:city":"Aarsele",
    "sg:orig_category":"Royal Canin. Fleurs and plantes. Articles de jardin",
    "sg:phone":"+32 51 63 30 64",
    "sg:postcode":"8700",
    "sg:province":"West-Vlaanderen",
    "wof:name":"Van Quaethem Franky",
    "wof:placetype":"venue"
},
  "geometry": {"coordinates":[3.4128201008,50.9924201965],"type":"Point"}
}