{
  "type": "Feature",
  "properties": {
    "addr:full":"Kolkstraat 19 Dessel Antwerpen 2480",
    "addr:housenumber":"19",
    "addr:postcode":"2480",
    "addr:street":"Kolkstraat",
    "iso:country":"BE",
    "sg:address":"Kolkstraat 19",
    "sg:city":"Dessel",
    "sg:classifiers":[
        {
            "category":"Professional",
            "subcategory":"Testing Lab",
            "type":"Services"
        }
    ],
    "sg:phone":"+32 14 37 70 64",
    "sg:postcode":"2480",
    "sg:province":"Antwerpen",
    "sg:tags":[
        "chemist"
    ],
    "wof:name":"Robeyns",
    "wof:placetype":"venue"
},
  "geometry": {"coordinates":[5.1143250465,51.2383117676],"type":"Point"}
}