{
  "type": "Feature",
  "properties": {
    "addr:full":"Pater Damiaanstraat 33ba Tremelo Vlaams-Brabant 3120",
    "addr:housenumber":"33ba",
    "addr:postcode":"3120",
    "addr:street":"Pater Damiaanstraat",
    "iso:country":"BE",
    "sg:address":"Pater Damiaanstraat 33ba",
    "sg:city":"Tremelo",
    "sg:orig_category":"Ziekenhuizen and zorginstellingen",
    "sg:phone":"+32 16 53 65 70",
    "sg:postcode":"3120",
    "sg:province":"Vlaams-Brabant",
    "wof:name":"Sticht. Psycho-geriatrie",
    "wof:placetype":"venue"
},
  "geometry": {"coordinates":[4.6769142151,50.9879188538],"type":"Point"}
}