{
  "type": "Feature",
  "properties": {
    "iso:country":"BE",
    "sg:address":"L\u00c9opold Sturbautstraat 27",
    "sg:city":"Ronse/renaix",
    "sg:orig_category":"Loodgieterij, verwarming and sanitaire installaties",
    "sg:phone":"+32 55 21 17 64",
    "sg:postcode":"9600",
    "sg:province":"Oost-Vlaanderen",
    "wof:name":"Albert Louesse-coppenolle",
    "wof:placetype":"venue"
},
  "geometry": {"coordinates":[3.5960180759,50.7422790527],"type":"Point"}
}