{
  "type": "Feature",
  "properties": {
    "addr:full":"Rue Louis Caty 135 Mons (baudour) Hainaut 7331",
    "addr:housenumber":"135",
    "addr:postcode":"7331",
    "addr:street":"Rue Louis Caty",
    "iso:country":"BE",
    "sg:address":"Rue Louis Caty 135",
    "sg:city":"Mons (baudour)",
    "sg:classifiers":[
        {
            "category":"Retail",
            "subcategory":"Event Space",
            "type":"Services"
        }
    ],
    "sg:phone":"+32 65 64 33 67",
    "sg:postcode":"7331",
    "sg:province":"Hainaut",
    "sg:tags":[
        "rental",
        "-",
        "hall"
    ],
    "wof:name":"Franky's",
    "wof:placetype":"venue"
},
  "geometry": {"coordinates":[3.832367897,50.4841804504],"type":"Point"}
}