{
  "type": "Feature",
  "properties": {
    "addr:full":"Sluisstraat 32/2 Hasselt Limburg 3500",
    "addr:housenumber":"32 / 2",
    "addr:postcode":"3500",
    "addr:street":"Sluisstraat",
    "iso:country":"BE",
    "sg:address":"Sluisstraat 32/2",
    "sg:city":"Hasselt",
    "sg:orig_category":"Metaalbehandeling and -bekleding",
    "sg:phone":"+32 11 24 29 70",
    "sg:postcode":"3500",
    "sg:province":"Limburg",
    "wof:name":"Valkeneers Peter Metaalwerken",
    "wof:placetype":"venue"
},
  "geometry": {"coordinates":[5.3759918213,50.9461402893],"type":"Point"}
}