{
  "type": "Feature",
  "properties": {
    "addr:full":"Onze-lieve-vrouwplein 2 Sint-niklaas Oost-Vlaanderen 9100",
    "addr:housenumber":"2",
    "addr:postcode":"9100",
    "addr:street":"Onze-Lieve-Vrouwplein",
    "iso:country":"BE",
    "sg:address":"Onze-lieve-vrouwplein 2",
    "sg:city":"Sint-niklaas",
    "sg:classifiers":[
        {
            "category":"Fast Food",
            "type":"Food & Drink"
        }
    ],
    "sg:phone":"+32 3 777 61 02",
    "sg:postcode":"9100",
    "sg:province":"Oost-Vlaanderen",
    "sg:tags":[
        "de",
        "restaurant",
        "organisation",
        "\u00e0",
        "catering",
        "emporter",
        "f\u00eates"
    ],
    "wof:name":"Sirtaki",
    "wof:placetype":"venue"
},
  "geometry": {"coordinates":[4.1386890411,51.1644096375],"type":"Point"}
}