{
  "type": "Feature",
  "properties": {
    "iso:country":"BE",
    "sg:address":"Avenue Royale 50",
    "sg:city":"Mouscron",
    "sg:classifiers":[
        {
            "category":"Education",
            "subcategory":"School",
            "type":"Public Place"
        }
    ],
    "sg:phone":"+32 56 85 57 00",
    "sg:postcode":"7700",
    "sg:province":"Hainaut",
    "sg:tags":[
        "secondary"
    ],
    "wof:name":"Coll\u00e8ge Technique St-henri",
    "wof:placetype":"venue"
},
  "geometry": {"coordinates":[3.2211680412,50.7464752197],"type":"Point"}
}