{
  "type": "Feature",
  "properties": {
    "addr:full":"Rue Seraphin Anthoine 89c Charleroi (mont-sur-marchienne) Hainaut 6032",
    "addr:housenumber":"89c",
    "addr:postcode":"6032",
    "addr:street":"Rue Seraphin Anthoine",
    "iso:country":"BE",
    "sg:address":"Rue Seraphin Anthoine 89c",
    "sg:city":"Charleroi (mont-sur-marchienne)",
    "sg:classifiers":[
        {
            "category":"Health Services",
            "subcategory":"Health Practitioner",
            "type":"Services"
        }
    ],
    "sg:phone":"+32 71 36 90 45",
    "sg:postcode":"6032",
    "sg:province":"Hainaut",
    "sg:tags":[
        "physiotherapist"
    ],
    "wof:name":"Devos J-m",
    "wof:placetype":"venue"
},
  "geometry": {"coordinates":[4.4163241386,50.3783874512],"type":"Point"}
}