{
  "type": "Feature",
  "properties": {
    "addr:full":"Crauwelsbos 13 Diest (molenstede) Vlaams-Brabant 3294",
    "addr:housenumber":"13",
    "addr:postcode":"3294",
    "addr:street":"Crauwelsbos",
    "iso:country":"BE",
    "sg:address":"Crauwelsbos 13",
    "sg:city":"Diest (molenstede)",
    "sg:orig_category":"Newspapers, magazines, periodicals - Publishers",
    "sg:phone":"+32 13 31 46 28",
    "sg:postcode":"3294",
    "sg:province":"Vlaams-Brabant",
    "wof:name":"Hotelnieuws",
    "wof:placetype":"venue"
},
  "geometry": {"coordinates":[5.024520874,50.9955253601],"type":"Point"}
}