{
  "type": "Feature",
  "properties": {
    "iso:country":"BE",
    "sg:address":"Rue De La Croix 37",
    "sg:city":"Ronse/renaix",
    "sg:orig_category":"Boucheries",
    "sg:phone":"+32 55 21 14 10",
    "sg:postcode":"9600",
    "sg:province":"Oost-Vlaanderen",
    "wof:name":"Roger Meire",
    "wof:placetype":"venue"
},
  "geometry": {"coordinates":[3.5962491035,50.7513580322],"type":"Point"}
}