{
  "type": "Feature",
  "properties": {
    "iso:country":"BE",
    "sg:address":"Popelierestraat 3",
    "sg:city":"Herk-de-stad",
    "sg:orig_category":"Groententeelt",
    "sg:phone":"+32 13 55 24 61",
    "sg:postcode":"3540",
    "sg:province":"Limburg",
    "wof:name":"Jozef Vanstraelen",
    "wof:placetype":"venue"
},
  "geometry": {"coordinates":[5.1832909584,50.9341392517],"type":"Point"}
}