{
  "type": "Feature",
  "properties": {
    "iso:country":"BE",
    "sg:address":"Middenhutlaan 34",
    "sg:city":"Sint-genesius-rode/rhode-saint-gen\u00c8se",
    "sg:orig_category":"Architecten",
    "sg:phone":"+32 2 381 08 39",
    "sg:postcode":"1640",
    "sg:province":"Vlaams-Brabant",
    "wof:name":"Delphine Herpain",
    "wof:placetype":"venue"
},
  "geometry": {"coordinates":[4.3771109581,50.7604827881],"type":"Point"}
}