{
  "type": "Feature",
  "properties": {
    "iso:country":"BE",
    "sg:address":"Sint-jakobsstraat 3",
    "sg:city":"Brugge",
    "sg:classifiers":[
        {
            "category":"Home & Garden",
            "subcategory":"Home Furnishings",
            "type":"Retail Goods"
        }
    ],
    "sg:phone":"+32 50 33 80 16",
    "sg:postcode":"8000",
    "sg:province":"West-Vlaanderen",
    "sg:tags":[
        "interior",
        "decoration"
    ],
    "wof:name":"Bazar Bizar",
    "wof:placetype":"venue"
},
  "geometry": {"coordinates":[3.2225220203,51.2092056274],"type":"Point"}
}