{
  "type": "Feature",
  "properties": {
    "addr:full":"Helststraat 49 Aartselaar Antwerpen 2630",
    "addr:housenumber":"49",
    "addr:postcode":"2630",
    "addr:street":"Helststraat",
    "iso:country":"BE",
    "sg:address":"Helststraat 49",
    "sg:city":"Aartselaar",
    "sg:classifiers":[
        {
            "category":"Shopping Center",
            "type":"Public Place"
        }
    ],
    "sg:phone":"+32 3 877 93 33",
    "sg:postcode":"2630",
    "sg:province":"Antwerpen",
    "sg:tags":[
        "dummy",
        "shop-window"
    ],
    "wof:name":"Acb Displays International",
    "wof:placetype":"venue"
},
  "geometry": {"coordinates":[4.3738479614,51.1372146606],"type":"Point"}
}