{
  "type": "Feature",
  "properties": {
    "addr:full":"Nieuwpoortsteenweg 7 Koksijde (oostduinkerke) West-Vlaanderen 8670",
    "addr:housenumber":"7",
    "addr:postcode":"8670",
    "addr:street":"Nieuwpoortsteenweg",
    "iso:country":"BE",
    "sg:address":"Nieuwpoortsteenweg 7",
    "sg:city":"Koksijde (oostduinkerke)",
    "sg:classifiers":[
        {
            "category":"Real Estate",
            "subcategory":"Architect",
            "type":"Services"
        }
    ],
    "sg:phone":"+32 58 52 04 36",
    "sg:postcode":"8670",
    "sg:province":"West-Vlaanderen",
    "wof:name":"Geldhof W",
    "wof:placetype":"venue"
},
  "geometry": {"coordinates":[2.6876010895,51.1170387268],"type":"Point"}
}