{
  "type": "Feature",
  "properties": {
    "iso:country":"BE",
    "sg:address":"Meenselstraat 81",
    "sg:city":"Lubbeek",
    "sg:classifiers":[
        {
            "category":"Personal",
            "subcategory":"Beauty Salon",
            "type":"Services"
        }
    ],
    "sg:phone":"+32 16 63 10 03",
    "sg:postcode":"3211",
    "sg:province":"Vlaams-Brabant",
    "sg:tags":[
        "de",
        "coiffure"
    ],
    "wof:name":"Coiffure Bianca",
    "wof:placetype":"venue"
},
  "geometry": {"coordinates":[4.8931708336,50.8781204224],"type":"Point"}
}