{
  "type": "Feature",
  "properties": {
    "addr:full":"Place Du Jeu De Balle 7 Brussel/bruxelles Bruxelles-Capitale 1000",
    "addr:housenumber":"7",
    "addr:postcode":"1000",
    "addr:street":"Place Du Jeu De Balle;/",
    "iso:country":"BE",
    "sg:address":"Place Du Jeu De Balle 7",
    "sg:city":"Brussel/bruxelles",
    "sg:orig_category":"Epiceries",
    "sg:phone":"+32 2 511 28 59",
    "sg:postcode":"1000",
    "sg:province":"Bruxelles-Capitale",
    "wof:name":"Molnar Maria/molnar Maria Thermal",
    "wof:placetype":"venue"
},
  "geometry": {"coordinates":[4.346601963,50.8375968933],"type":"Point"}
}