{
  "type": "Feature",
  "properties": {
    "addr:full":"Rue De Branchon 43 Fernelmont Namur 5380",
    "addr:housenumber":"43",
    "addr:postcode":"5380",
    "addr:street":"Rue De Branchon",
    "iso:country":"BE",
    "sg:address":"Rue De Branchon 43",
    "sg:city":"Fernelmont",
    "sg:orig_category":"Boucheries",
    "sg:phone":"+32 81 83 32 05",
    "sg:postcode":"5380",
    "sg:province":"Namur",
    "wof:name":"Andre Wilmotte",
    "wof:placetype":"venue"
},
  "geometry": {"coordinates":[4.9861078262,50.5531463623],"type":"Point"}
}