{
  "type": "Feature",
  "properties": {
    "iso:country":"BE",
    "sg:address":"Sint-sebastiaansstraat 28",
    "sg:city":"Oostende",
    "sg:classifiers":[
        {
            "category":"Personal",
            "subcategory":"Beauty Salon",
            "type":"Services"
        }
    ],
    "sg:phone":"+32 59 70 20 35",
    "sg:postcode":"8400",
    "sg:province":"West-Vlaanderen",
    "sg:tags":[
        "lady",
        "-",
        "hairdressing"
    ],
    "wof:name":"Freddy",
    "wof:placetype":"venue"
},
  "geometry": {"coordinates":[2.9154829979,51.2307624817],"type":"Point"}
}