{
  "type": "Feature",
  "properties": {
    "iso:country":"BE",
    "sg:address":"Solleveldstraat 68",
    "sg:city":"Sint-lambrechts-woluwe/woluwe-saint-lambert",
    "sg:orig_category":"Reclamebureaus",
    "sg:phone":"+32 2 772 01 65",
    "sg:postcode":"1200",
    "sg:province":"Bruxelles-Capitale",
    "wof:name":"A.d. & Com. Medicus",
    "wof:placetype":"venue"
},
  "geometry": {"coordinates":[4.4274477959,50.8450279236],"type":"Point"}
}