{
  "type": "Feature",
  "properties": {
    "addr:full":"Maastrichtersteenweg 314 Hasselt Limburg 3500",
    "addr:housenumber":"314",
    "addr:postcode":"3500",
    "addr:street":"Maastrichtersteenweg",
    "iso:country":"BE",
    "sg:address":"Maastrichtersteenweg 314",
    "sg:city":"Hasselt",
    "sg:classifiers":[
        {
            "category":"Building & Trades",
            "subcategory":"Pest Control",
            "type":"Services"
        }
    ],
    "sg:phone":"+32 11 22 26 88",
    "sg:postcode":"3500",
    "sg:province":"Limburg",
    "sg:tags":[
        "painting",
        "contractor"
    ],
    "wof:name":"Put Johnny",
    "wof:placetype":"venue"
},
  "geometry": {"coordinates":[5.3667497635,50.9259757996],"type":"Point"}
}