{
  "type": "Feature",
  "properties": {
    "addr:full":"Biezenstraat 20 Middelkerke West-Vlaanderen 8430",
    "addr:housenumber":"20",
    "addr:postcode":"8430",
    "addr:street":"Biezenstraat",
    "iso:country":"BE",
    "sg:address":"Biezenstraat 20",
    "sg:city":"Middelkerke",
    "sg:orig_category":"Entretien and r\u00e9parations de voitures",
    "sg:phone":"+32 59 31 25 98",
    "sg:postcode":"8430",
    "sg:province":"West-Vlaanderen",
    "wof:name":"Car Wash",
    "wof:placetype":"venue"
},
  "geometry": {"coordinates":[2.8456499577,51.1934547424],"type":"Point"}
}