{
  "type": "Feature",
  "properties": {
    "addr:full":"Hogeschoollaan 36 Elsene/ixelles Bruxelles-Capitale 1050",
    "addr:housenumber":"36",
    "addr:postcode":"1050",
    "addr:street":"Hogeschoollaan",
    "iso:country":"BE",
    "sg:address":"Hogeschoollaan 36",
    "sg:city":"Elsene/ixelles",
    "sg:classifiers":[
        {
            "category":"Restaurant",
            "type":"Food & Drink"
        }
    ],
    "sg:phone":"+32 2 644 14 98",
    "sg:postcode":"1050",
    "sg:province":"Bruxelles-Capitale",
    "wof:name":"La Table Du March\u00c9",
    "wof:placetype":"venue"
},
  "geometry": {"coordinates":[4.3882870674,50.814956665],"type":"Point"}
}