{
  "type": "Feature",
  "properties": {
    "addr:full":"Clos Du Chemin Creux 4b32 Schaarbeek/schaerbeek Bruxelles-Capitale 1030",
    "addr:housenumber":"4b32",
    "addr:postcode":"1030",
    "addr:street":"Clos Du Chemin Creux",
    "iso:country":"BE",
    "sg:address":"Clos Du Chemin Creux 4b32",
    "sg:city":"Schaarbeek/schaerbeek",
    "sg:orig_category":"Administration d'immeubles",
    "sg:phone":"+32 2 242 58 49",
    "sg:postcode":"1030",
    "sg:province":"Bruxelles-Capitale",
    "wof:name":"D H C",
    "wof:placetype":"venue"
},
  "geometry": {"coordinates":[4.3936471939,50.8647460938],"type":"Point"}
}