{
  "type": "Feature",
  "properties": {
    "iso:country":"BE",
    "sg:address":"Rue D'org\u00e9o 2",
    "sg:city":"Herbeumont (saint-m\u00e9dard)",
    "sg:classifiers":[
        {
            "category":"Personal",
            "subcategory":"Barber",
            "type":"Services"
        }
    ],
    "sg:phone":"+32 61 41 25 48",
    "sg:postcode":"6887",
    "sg:province":"Luxembourg",
    "sg:tags":[
        "gentleman",
        "salon",
        "-",
        "hairdressing"
    ],
    "wof:name":"Carmen Coiffure",
    "wof:placetype":"venue"
},
  "geometry": {"coordinates":[5.3239369392,49.8212203979],"type":"Point"}
}