{
  "type": "Feature",
  "properties": {
    "addr:full":"18 Vieux Chemin De Charleroi Beaumont Hainaut 6500",
    "addr:housenumber":"18",
    "addr:postcode":"6500",
    "addr:street":"Vieux Chemin De Charleroi;Hainaut",
    "iso:country":"BE",
    "sg:address":"18 Vieux Chemin De Charleroi",
    "sg:city":"Beaumont",
    "sg:classifiers":[
        {
            "category":"Communications",
            "type":"Services"
        }
    ],
    "sg:phone":"+32 71 58 87 10",
    "sg:postcode":"6500",
    "sg:province":"Hainaut",
    "sg:tags":[
        "advice",
        "interpretation",
        "translation",
        "business"
    ],
    "wof:name":"Rogien Petit",
    "wof:placetype":"venue"
},
  "geometry": {"coordinates":[4.253839016,50.2405738831],"type":"Point"}
}