{
  "type": "Feature",
  "properties": {
    "addr:full":"Turnhoutsebaan 234 Schilde Antwerpen 2970",
    "addr:housenumber":"234",
    "addr:postcode":"2970",
    "addr:street":"Turnhoutsebaan",
    "iso:country":"BE",
    "sg:address":"Turnhoutsebaan 234",
    "sg:city":"Schilde",
    "sg:classifiers":[
        {
            "category":"Personal",
            "subcategory":"Barber",
            "type":"Services"
        }
    ],
    "sg:phone":"+32 3 383 23 06",
    "sg:postcode":"2970",
    "sg:province":"Antwerpen",
    "sg:tags":[
        "gentleman",
        "salon",
        "-",
        "hairdressing"
    ],
    "wof:name":"Van Looy",
    "wof:placetype":"venue"
},
  "geometry": {"coordinates":[4.5787258148,51.2387046814],"type":"Point"}
}