{
  "type": "Feature",
  "properties": {
    "iso:country":"BE",
    "sg:address":"Melkmarkt 37",
    "sg:city":"Antwerpen",
    "sg:orig_category":"Antiek Meubelzaken, woning- and keukeninrichting Verlichting and huishoudartikelen",
    "sg:phone":"+32 3 233 82 30",
    "sg:postcode":"2000",
    "sg:province":"Antwerpen",
    "wof:name":"J Zeberg",
    "wof:placetype":"venue"
},
  "geometry": {"coordinates":[4.4030408859,51.2197189331],"type":"Point"}
}