{
  "type": "Feature",
  "properties": {
    "addr:full":"Chauss\u00c9e De Fagnolle 54 Couvin Namur 5660",
    "addr:housenumber":"54",
    "addr:postcode":"5660",
    "addr:street":"Chausse\u0301E De Fagnolle",
    "iso:country":"BE",
    "sg:address":"Chauss\u00c9e De Fagnolle 54",
    "sg:city":"Couvin",
    "sg:orig_category":"Maisons de repos and r\u00e9sidences",
    "sg:phone":"+32 60 31 20 43",
    "sg:postcode":"5660",
    "sg:province":"Namur",
    "wof:name":"Home Les Forsythias",
    "wof:placetype":"venue"
},
  "geometry": {"coordinates":[4.5324850082,50.0983734131],"type":"Point"}
}