{
  "type": "Feature",
  "properties": {
    "addr:full":"Kanaalweg 17 Tessenderlo Limburg 3980",
    "addr:housenumber":"17",
    "addr:postcode":"3980",
    "addr:street":"Kanaalweg",
    "iso:country":"BE",
    "sg:address":"Kanaalweg 17",
    "sg:city":"Tessenderlo",
    "sg:orig_category":"HUISBRANDOLIE",
    "sg:phone":"+32 13 66 19 31",
    "sg:postcode":"3980",
    "sg:province":"Limburg",
    "wof:name":"Eric Van Tentelen",
    "wof:placetype":"venue"
},
  "geometry": {"coordinates":[5.154820919,51.0753135681],"type":"Point"}
}