{
  "type": "Feature",
  "properties": {
    "addr:full":"Chauss\u00c9e De Haecht 413 Bruxelles Bruxelles-Capitale 1030",
    "addr:housenumber":"413",
    "addr:postcode":"1030",
    "addr:street":"Chausse\u0301E De Haecht",
    "iso:country":"BE",
    "sg:address":"Chauss\u00c9e De Haecht 413",
    "sg:city":"Bruxelles",
    "sg:orig_category":"Installation de menuiserie m\u00e9tallique",
    "sg:phone":"+32 2 245 20 55",
    "sg:postcode":"1030",
    "sg:province":"Bruxelles-Capitale",
    "wof:name":"Captson",
    "wof:placetype":"venue"
},
  "geometry": {"coordinates":[4.3762850761,50.8669128418],"type":"Point"}
}