{
  "type": "Feature",
  "properties": {
    "iso:country":"BE",
    "sg:address":"Brouwerijstraat 14",
    "sg:city":"Zwalm (dikkele)",
    "sg:orig_category":"Non-Classified Establishments",
    "sg:phone":"+32 55 49 79 83",
    "sg:postcode":"9630",
    "sg:province":"Oost-Vlaanderen",
    "wof:name":"Keramiekhoeve",
    "wof:placetype":"venue"
},
  "geometry": {"coordinates":[3.7389481068,50.905254364],"type":"Point"}
}