{
  "type": "Feature",
  "properties": {
    "iso:country":"BE",
    "sg:address":"Rue Des M\u00c9l\u00c8zes 63",
    "sg:city":"Elsene/ixelles",
    "sg:classifiers":[
        {
            "category":"Shopping",
            "subcategory":"Clothing, Apparel, & Fashions",
            "type":"Retail Goods"
        }
    ],
    "sg:phone":"+32 2 640 91 81",
    "sg:postcode":"1050",
    "sg:province":"Bruxelles-Capitale",
    "sg:tags":[
        "v\u00eatements",
        "pour",
        "dame"
    ],
    "wof:name":"Martin Bertouille",
    "wof:placetype":"venue"
},
  "geometry": {"coordinates":[4.3632340431,50.8204612732],"type":"Point"}
}