{
  "type": "Feature",
  "properties": {
    "addr:full":"Weststraat 138 Evergem (sleidinge) Oost-Vlaanderen 9940",
    "addr:housenumber":"138",
    "addr:postcode":"9940",
    "addr:street":"Weststraat",
    "iso:country":"BE",
    "sg:address":"Weststraat 138",
    "sg:city":"Evergem (sleidinge)",
    "sg:classifiers":[
        {
            "category":"Food & Beverages",
            "subcategory":"Supermarket",
            "type":"Retail Goods"
        }
    ],
    "sg:phone":"+32 9 357 31 38",
    "sg:postcode":"9940",
    "sg:province":"Oost-Vlaanderen",
    "sg:tags":[
        "department",
        "store"
    ],
    "wof:name":"Martens C",
    "wof:placetype":"venue"
},
  "geometry": {"coordinates":[3.6693611145,51.1277885437],"type":"Point"}
}