{
  "type": "Feature",
  "properties": {
    "addr:full":"Sint-rochusstraat 44 Halle Vlaams-Brabant 1500",
    "addr:housenumber":"44",
    "addr:postcode":"1500",
    "addr:street":"Sint-Rochusstraat",
    "iso:country":"BE",
    "sg:address":"Sint-rochusstraat 44",
    "sg:city":"Halle",
    "sg:orig_category":"Postkantoren Verzekeringsmakelaars and experts",
    "sg:phone":"+32 2 356 80 85",
    "sg:postcode":"1500",
    "sg:province":"Vlaams-Brabant",
    "wof:name":"De Post",
    "wof:placetype":"venue"
},
  "geometry": {"coordinates":[4.2395300865,50.7312049866],"type":"Point"}
}