{
  "type": "Feature",
  "properties": {
    "iso:country":"BE",
    "sg:address":"Otegemstraat 32",
    "sg:city":"Zwevegem",
    "sg:classifiers":[
        {
            "category":"Home & Garden",
            "subcategory":"Home Furnishings",
            "type":"Retail Goods"
        }
    ],
    "sg:phone":"+32 56 75 69 21",
    "sg:postcode":"8550",
    "sg:province":"West-Vlaanderen",
    "sg:tags":[
        "-",
        "furniture"
    ],
    "wof:name":"Meubelen De Linde",
    "wof:placetype":"venue"
},
  "geometry": {"coordinates":[3.3354799747,50.8126792908],"type":"Point"}
}