{
  "type": "Feature",
  "properties": {
    "iso:country":"BE",
    "sg:address":"Place Communale 15",
    "sg:city":"Estaimpuis (leers-nord)",
    "sg:classifiers":[
        {
            "category":"Recreation",
            "subcategory":"Fishing",
            "type":"Entertainment"
        }
    ],
    "sg:phone":"+32 56 48 87 52",
    "sg:postcode":"7730",
    "sg:province":"Hainaut",
    "sg:tags":[
        "tackle"
    ],
    "wof:name":"Maison Des P\u00eacheurs",
    "wof:placetype":"venue"
},
  "geometry": {"coordinates":[3.2714710236,50.6877479553],"type":"Point"}
}