{
  "type": "Feature",
  "properties": {
    "addr:full":"Stationlei 81 Vilvoorde Vlaams-Brabant 1800",
    "addr:housenumber":"81",
    "addr:postcode":"1800",
    "addr:street":"Stationlei",
    "iso:country":"BE",
    "sg:address":"Stationlei 81",
    "sg:city":"Vilvoorde",
    "sg:classifiers":[
        {
            "category":"Professional",
            "subcategory":"Accounting & Tax Preparation",
            "type":"Services"
        }
    ],
    "sg:phone":"+32 2 251 98 75",
    "sg:postcode":"1800",
    "sg:province":"Vlaams-Brabant",
    "sg:tags":[
        "accountant"
    ],
    "wof:name":"Milis E",
    "wof:placetype":"venue"
},
  "geometry": {"coordinates":[4.4316101074,50.9250144958],"type":"Point"}
}