{
  "type": "Feature",
  "properties": {
    "addr:full":"Sleutelhoflaan 2 Beveren (vrasene) Oost-Vlaanderen 9120",
    "addr:housenumber":"2",
    "addr:postcode":"9120",
    "addr:street":"Sleutelhoflaan",
    "iso:country":"BE",
    "sg:address":"Sleutelhoflaan 2",
    "sg:city":"Beveren (vrasene)",
    "sg:classifiers":[
        {
            "category":"Food & Beverages",
            "subcategory":"Supermarket",
            "type":"Retail Goods"
        }
    ],
    "sg:phone":"+32 3 755 56 36",
    "sg:postcode":"9120",
    "sg:province":"Oost-Vlaanderen",
    "sg:tags":[
        "department",
        "store"
    ],
    "wof:name":"Spar",
    "wof:placetype":"venue"
},
  "geometry": {"coordinates":[4.1999697685,51.2185897827],"type":"Point"}
}