{
  "type": "Feature",
  "properties": {
    "addr:full":"Kortenbergsesteenweg 33b1 Steenokkerzeel Vlaams-Brabant 1820",
    "addr:housenumber":"33b1",
    "addr:postcode":"1820",
    "addr:street":"Kortenbergsesteenweg",
    "iso:country":"BE",
    "sg:address":"Kortenbergsesteenweg 33b1",
    "sg:city":"Steenokkerzeel",
    "sg:orig_category":"Binnenhuisarchitecten",
    "sg:phone":"+32 2 759 23 33",
    "sg:postcode":"1820",
    "sg:province":"Vlaams-Brabant",
    "wof:name":"Bureau Ratio Patio",
    "wof:placetype":"venue"
},
  "geometry": {"coordinates":[4.5181097984,50.9044532776],"type":"Point"}
}