{
  "type": "Feature",
  "properties": {
    "iso:country":"BE",
    "sg:address":"5620",
    "sg:city":"Florennes (groot)",
    "sg:orig_category":"Pharmaciens",
    "sg:phone":"+32 900 10 500",
    "sg:postcode":"5620",
    "sg:province":"Namur",
    "wof:name":"Pharmacies De Garde",
    "wof:placetype":"venue"
},
  "geometry": {"coordinates":[4.6609201431,50.2378807068],"type":"Point"}
}