{
  "type": "Feature",
  "properties": {
    "addr:full":"Sint-amandsstraat 8 Grimbergen Vlaams-Brabant 1853",
    "addr:housenumber":"8",
    "addr:postcode":"1853",
    "addr:street":"Sint-Amandsstraat",
    "iso:country":"BE",
    "sg:address":"Sint-amandsstraat 8",
    "sg:city":"Grimbergen",
    "sg:orig_category":"Jeux de hasard",
    "sg:phone":"+32 2 267 78 22",
    "sg:postcode":"1853",
    "sg:province":"Vlaams-Brabant",
    "wof:name":"Ladbroke",
    "wof:placetype":"venue"
},
  "geometry": {"coordinates":[4.3571081161,50.9094924927],"type":"Point"}
}