{
  "type": "Feature",
  "properties": {
    "iso:country":"BE",
    "sg:address":"Messidorlaan 217",
    "sg:city":"Ukkel/uccle",
    "sg:orig_category":"Artsen and specialisten",
    "sg:phone":"+32 2 347 02 44",
    "sg:postcode":"1180",
    "sg:province":"Bruxelles-Capitale",
    "wof:name":"Jean-pierre Maisin",
    "wof:placetype":"venue"
},
  "geometry": {"coordinates":[4.3523621559,50.8114280701],"type":"Point"}
}