{
  "type": "Feature",
  "properties": {
    "addr:full":"Rue De La Station 2 Anderlues Hainaut 6150",
    "addr:housenumber":"2",
    "addr:postcode":"6150",
    "addr:street":"Rue De La Station",
    "iso:country":"BE",
    "sg:address":"Rue De La Station 2",
    "sg:city":"Anderlues",
    "sg:orig_category":"Architectes",
    "sg:phone":"+32 71 52 49 85",
    "sg:postcode":"6150",
    "sg:province":"Hainaut",
    "wof:name":"Didier Leleux",
    "wof:placetype":"venue"
},
  "geometry": {"coordinates":[4.2791690826,50.4015808105],"type":"Point"}
}