{
  "type": "Feature",
  "properties": {
    "iso:country":"BE",
    "sg:address":"Ardooisesteenweg 242",
    "sg:city":"Roeselare",
    "sg:classifiers":[
        {
            "category":"Autos & Motor Vehicles",
            "subcategory":"Automobile Sales",
            "type":"Retail Goods"
        }
    ],
    "sg:phone":"+32 51 24 09 82",
    "sg:postcode":"8800",
    "sg:province":"West-Vlaanderen",
    "sg:tags":[
        "commercial",
        "rental"
    ],
    "wof:name":"Hoet Trucking & Renting Nv",
    "wof:placetype":"venue"
},
  "geometry": {"coordinates":[3.1632399559,50.9480514526],"type":"Point"}
}