{
  "type": "Feature",
  "properties": {
    "iso:country":"BE",
    "sg:address":"Quai Mativa 23",
    "sg:city":"Li\u00c8ge",
    "sg:orig_category":"Software ontwikkeling and ontwerp",
    "sg:phone":"+32 4 343 42 22",
    "sg:postcode":"4020",
    "sg:province":"Li\u00e8ge",
    "wof:name":"Distrilog",
    "wof:placetype":"venue"
},
  "geometry": {"coordinates":[5.5797348022,50.627243042],"type":"Point"}
}