{
  "type": "Feature",
  "properties": {
    "iso:country":"BE",
    "sg:address":"Gitsbergstr 21",
    "sg:city":"Hooglede",
    "sg:classifiers":[
        {
            "category":"Manufacturing",
            "subcategory":"Textiles",
            "type":"Manufacturing & Wholesale Goods"
        }
    ],
    "sg:phone":"+32 51 20 25 91",
    "sg:postcode":"8830",
    "sg:province":"West-Vlaanderen",
    "sg:tags":[
        "linen",
        "clothing",
        "fabric"
    ],
    "wof:name":"Grymonpon Bvba",
    "wof:placetype":"venue"
},
  "geometry": {"coordinates":[3.0967860222,50.9952926636],"type":"Point"}
}