{
  "type": "Feature",
  "properties": {
    "iso:country":"BE",
    "sg:address":"Rue Achille Detienne 4b1",
    "sg:city":"Schaarbeek/schaerbeek",
    "sg:orig_category":"Plomberie, chauffage and installations sanitaires",
    "sg:phone":"+32 2 245 96 84",
    "sg:postcode":"1030",
    "sg:province":"Bruxelles-Capitale",
    "wof:name":"Marc Griner",
    "wof:placetype":"venue"
},
  "geometry": {"coordinates":[4.3887262344,50.8711128235],"type":"Point"}
}