{
  "type": "Feature",
  "properties": {
    "addr:full":"Oudenaardsesteenweg 366 Erpe-mere Oost-Vlaanderen 9420",
    "addr:housenumber":"366",
    "addr:postcode":"9420",
    "addr:street":"Oudenaardsesteenweg",
    "iso:country":"BE",
    "sg:address":"Oudenaardsesteenweg 366",
    "sg:city":"Erpe-mere",
    "sg:orig_category":"Plomberie, chauffage and installations sanitaires",
    "sg:phone":"+32 53 84 00 36",
    "sg:postcode":"9420",
    "sg:province":"Oost-Vlaanderen",
    "wof:name":"Louis Coppens",
    "wof:placetype":"venue"
},
  "geometry": {"coordinates":[3.9561390877,50.9266471863],"type":"Point"}
}