{
  "type": "Feature",
  "properties": {
    "iso:country":"BE",
    "sg:address":"Gentpoortstraat 12",
    "sg:city":"Brugge",
    "sg:orig_category":"Quincailleries. Electrom\u00e9nager, t\u00e9l\u00e9visions and radios",
    "sg:phone":"+32 50 33 62 61",
    "sg:postcode":"8000",
    "sg:province":"West-Vlaanderen",
    "wof:name":"Van Dale",
    "wof:placetype":"venue"
},
  "geometry": {"coordinates":[3.2318549156,51.2040252686],"type":"Point"}
}