{
  "type": "Feature",
  "properties": {
    "addr:full":"Rijksweg 86 Zulte (machelen) Oost-Vlaanderen 9870",
    "addr:housenumber":"86",
    "addr:postcode":"9870",
    "addr:street":"Rijksweg",
    "iso:country":"BE",
    "sg:address":"Rijksweg 86",
    "sg:city":"Zulte (machelen)",
    "sg:classifiers":[
        {
            "category":"Autos & Motor Vehicles",
            "subcategory":"Auto Supplies",
            "type":"Retail Goods"
        }
    ],
    "sg:phone":"+32 9 386 48 09",
    "sg:postcode":"9870",
    "sg:province":"Oost-Vlaanderen",
    "sg:tags":[
        "automobile",
        "-",
        "truck",
        "gear-boxes"
    ],
    "wof:name":"Valomo Bvba",
    "wof:placetype":"venue"
},
  "geometry": {"coordinates":[3.495896101,50.9567642212],"type":"Point"}
}