{
  "type": "Feature",
  "properties": {
    "addr:full":"Canadadreef 3 Bonheiden Antwerpen 2820",
    "addr:housenumber":"3",
    "addr:postcode":"2820",
    "addr:street":"Canadadreef",
    "iso:country":"BE",
    "sg:address":"Canadadreef 3",
    "sg:city":"Bonheiden",
    "sg:classifiers":[
        {
            "category":"Shopping",
            "subcategory":"Gifts & Souvenirs",
            "type":"Retail Goods"
        }
    ],
    "sg:phone":"+32 15 55 10 51",
    "sg:postcode":"2820",
    "sg:province":"Antwerpen",
    "sg:tags":[
        "product",
        "miscellaneous"
    ],
    "wof:name":"Special Things Bvba",
    "wof:placetype":"venue"
},
  "geometry": {"coordinates":[4.5104641914,51.0336494446],"type":"Point"}
}