{
  "type": "Feature",
  "properties": {
    "iso:country":"BE",
    "sg:address":"Rue De La Chapelle 35",
    "sg:city":"La Louvi\u00e8re (trivi\u00e8res)",
    "sg:classifiers":[
        {
            "category":"Real Estate",
            "subcategory":"Architect",
            "type":"Services"
        }
    ],
    "sg:phone":"+32 475 47 08 79",
    "sg:postcode":"7100",
    "sg:province":"Hainaut",
    "wof:name":"Baudoux F",
    "wof:placetype":"venue"
},
  "geometry": {"coordinates":[4.1850848198,50.4748649597],"type":"Point"}
}