{
  "type": "Feature",
  "properties": {
    "addr:full":"Colemontstraat 6 Hasselt (stokrooie) Limburg 3511",
    "addr:housenumber":"6",
    "addr:postcode":"3511",
    "addr:street":"Colemontstraat",
    "iso:country":"BE",
    "sg:address":"Colemontstraat 6",
    "sg:city":"Hasselt (stokrooie)",
    "sg:classifiers":[
        {
            "category":"Building & Trades",
            "subcategory":"Construction",
            "type":"Services"
        }
    ],
    "sg:phone":"+32 11 87 20 27",
    "sg:postcode":"3511",
    "sg:province":"Limburg",
    "sg:tags":[
        "carpenter"
    ],
    "wof:name":"Scsi Bvba",
    "wof:placetype":"venue"
},
  "geometry": {"coordinates":[5.2769670486,50.9738006592],"type":"Point"}
}