{
  "type": "Feature",
  "properties": {
    "iso:country":"BE",
    "sg:address":"Wondelgemstraat 192",
    "sg:city":"Gent",
    "sg:orig_category":"Solariums",
    "sg:phone":"+32 9 223 72 04",
    "sg:postcode":"9000",
    "sg:province":"Oost-Vlaanderen",
    "wof:name":"Helios Sauna & Zonnecenter",
    "wof:placetype":"venue"
},
  "geometry": {"coordinates":[3.7095088959,51.0648117065],"type":"Point"}
}