{
  "type": "Feature",
  "properties": {
    "addr:full":"Dr\u00c8ve Emmanuelle 4 Genappe Brabant Wallon 1470",
    "addr:housenumber":"4",
    "addr:postcode":"1470",
    "addr:street":"Dre\u0300Ve Emmanuelle;Wallon",
    "iso:country":"BE",
    "sg:address":"Dr\u00c8ve Emmanuelle 4",
    "sg:city":"Genappe",
    "sg:orig_category":"Installation de menuiserie en bois and plastique. Construction de maisons",
    "sg:phone":"+32 10 61 28 15",
    "sg:postcode":"1470",
    "sg:province":"Brabant Wallon",
    "wof:name":"Frison",
    "wof:placetype":"venue"
},
  "geometry": {"coordinates":[4.5365571976,50.6432571411],"type":"Point"}
}