{
  "type": "Feature",
  "properties": {
    "iso:country":"BE",
    "sg:address":"K. De Backerstraat 66",
    "sg:city":"Hemiksem",
    "sg:classifiers":[
        {
            "category":"Professional",
            "subcategory":"Art Services",
            "type":"Services"
        }
    ],
    "sg:phone":"+32 3 288 40 07",
    "sg:postcode":"2620",
    "sg:province":"Antwerpen",
    "sg:tags":[
        "graphic",
        "designer"
    ],
    "wof:name":"Talent",
    "wof:placetype":"venue"
},
  "geometry": {"coordinates":[4.3391289711,51.1453895569],"type":"Point"}
}