{
  "type": "Feature",
  "properties": {
    "addr:full":"Rue De Flemalle-grande 457 Flemalle Li\u00e8ge 4400",
    "addr:housenumber":"457",
    "addr:postcode":"4400",
    "addr:street":"Rue De Flemalle-Grande",
    "iso:country":"BE",
    "sg:address":"Rue De Flemalle-grande 457",
    "sg:city":"Flemalle",
    "sg:orig_category":"V\u00e9hicules automobiles. Stations-service and carburants",
    "sg:phone":"+32 4 233 59 81",
    "sg:postcode":"4400",
    "sg:province":"Li\u00e8ge",
    "wof:name":"Garage Spineux",
    "wof:placetype":"venue"
},
  "geometry": {"coordinates":[5.4728188515,50.6149177551],"type":"Point"}
}