{
  "type": "Feature",
  "properties": {
    "iso:country":"BE",
    "sg:address":"Grote Markt 10",
    "sg:city":"Roeselare",
    "sg:classifiers":[
        {
            "category":"Tea Room",
            "subcategory":"None",
            "type":"Food & Drink"
        }
    ],
    "sg:phone":"+32 51 24 29 06",
    "sg:postcode":"8800",
    "sg:province":"West-Vlaanderen",
    "wof:name":"Omer's Pannekoekenhuis",
    "wof:placetype":"venue"
},
  "geometry": {"coordinates":[3.1237440109,50.9448318481],"type":"Point"}
}