{
  "type": "Feature",
  "properties": {
    "addr:full":"Langestraat 172 Affligem Vlaams-Brabant 1790",
    "addr:housenumber":"172",
    "addr:postcode":"1790",
    "addr:street":"Langestraat",
    "iso:country":"BE",
    "sg:address":"Langestraat 172",
    "sg:city":"Affligem",
    "sg:orig_category":"Brood, gebak and snoepgoed",
    "sg:phone":"+32 53 67 34 40",
    "sg:postcode":"1790",
    "sg:province":"Vlaams-Brabant",
    "wof:name":"'t Schuurke",
    "wof:placetype":"venue"
},
  "geometry": {"coordinates":[4.1064791679,50.9202690125],"type":"Point"}
}