{
  "type": "Feature",
  "properties": {
    "addr:full":"Rue Des Wallons 33 Ottignies-louvain-la-neuve Brabant Wallon 1348",
    "addr:housenumber":"33",
    "addr:postcode":"1348",
    "addr:street":"Rue Des Wallons",
    "iso:country":"BE",
    "sg:address":"Rue Des Wallons 33",
    "sg:city":"Ottignies-louvain-la-neuve",
    "sg:orig_category":"R\u00e9parations d'appareils \u00e9lectrom\u00e9nagers. Quincailleries. Magasins de r\u00e9parations d'articles personne",
    "sg:phone":"+32 10 45 03 62",
    "sg:postcode":"1348",
    "sg:province":"Brabant Wallon",
    "wof:name":"Maison Le Trusquin",
    "wof:placetype":"venue"
},
  "geometry": {"coordinates":[4.616795063,50.6688156128],"type":"Point"}
}