{
  "type": "Feature",
  "properties": {
    "iso:country":"BE",
    "sg:address":"Hans Memlinglaan 2",
    "sg:city":"De Haan",
    "sg:classifiers":[
        {
            "category":"Restaurant",
            "type":"Food & Drink"
        }
    ],
    "sg:phone":"+32 59 23 65 32",
    "sg:postcode":"8420",
    "sg:province":"West-Vlaanderen",
    "wof:name":"Tearoom De Torre",
    "wof:placetype":"venue"
},
  "geometry": {"coordinates":[3.0324618816,51.2728805542],"type":"Point"}
}