{
  "type": "Feature",
  "properties": {
    "addr:full":"Rue F\u00c9licien Rops 10 Mettet Namur 5640",
    "addr:housenumber":"10",
    "addr:postcode":"5640",
    "addr:street":"Rue Fe\u0301Licien Rops",
    "iso:country":"BE",
    "sg:address":"Rue F\u00c9licien Rops 10",
    "sg:city":"Mettet",
    "sg:classifiers":[
        {
            "category":"Recreation",
            "type":"Entertainment"
        }
    ],
    "sg:phone":"+32 71 72 56 33",
    "sg:postcode":"5640",
    "sg:province":"Namur",
    "sg:tags":[
        "diver",
        "amusement"
    ],
    "wof:name":"Disco Sensation",
    "wof:placetype":"venue"
},
  "geometry": {"coordinates":[4.6632928848,50.3406219482],"type":"Point"}
}