{
  "type": "Feature",
  "properties": {
    "iso:country":"BE",
    "sg:address":"Patersveld 4ba",
    "sg:city":"Aalter",
    "sg:orig_category":"Eleveurs and marchands de porcs",
    "sg:phone":"+32 9 374 03 29",
    "sg:postcode":"9880",
    "sg:province":"Oost-Vlaanderen",
    "wof:name":"Geert Maenhout",
    "wof:placetype":"venue"
},
  "geometry": {"coordinates":[3.4162399769,51.1027755737],"type":"Point"}
}