{
  "type": "Feature",
  "properties": {
    "addr:full":"Rue G\u00c9n\u00c9ral Lotz 62 Ukkel/uccle Bruxelles-Capitale 1180",
    "addr:housenumber":"62",
    "addr:postcode":"1180",
    "addr:street":"Rue Ge\u0301Ne\u0301Ral Lotz;/",
    "iso:country":"BE",
    "sg:address":"Rue G\u00c9n\u00c9ral Lotz 62",
    "sg:city":"Ukkel/uccle",
    "sg:orig_category":"M\u00e9decins and sp\u00e9cialistes",
    "sg:phone":"+32 2 343 89 72",
    "sg:postcode":"1180",
    "sg:province":"Bruxelles-Capitale",
    "wof:name":"Dominique D\u00b4olne",
    "wof:placetype":"venue"
},
  "geometry": {"coordinates":[4.3587040901,50.8130378723],"type":"Point"}
}