{
  "type": "Feature",
  "properties": {
    "addr:full":"Place Du M\u00d4le 4 Braine-l\u00b4alleud Brabant Wallon 1420",
    "addr:housenumber":"4",
    "addr:postcode":"1420",
    "addr:street":"Place Du Mo\u0302Le;Brabant Wallon",
    "iso:country":"BE",
    "sg:address":"Place Du M\u00d4le 4",
    "sg:city":"Braine-l\u00b4alleud",
    "sg:orig_category":"Agences d\u00b4interim and personnel temporaire",
    "sg:phone":"+32 2 387 10 10",
    "sg:postcode":"1420",
    "sg:province":"Brabant Wallon",
    "wof:name":"Creyf\u00b4s Interim",
    "wof:placetype":"venue"
},
  "geometry": {"coordinates":[4.3702259064,50.6836662292],"type":"Point"}
}