{
  "type": "Feature",
  "properties": {
    "addr:full":"Nieuwpoortsesteenweg 53 Oostende West-Vlaanderen 8400",
    "addr:housenumber":"53",
    "addr:postcode":"8400",
    "addr:street":"Nieuwpoortsesteenweg",
    "iso:country":"BE",
    "sg:address":"Nieuwpoortsesteenweg 53",
    "sg:city":"Oostende",
    "sg:classifiers":[
        {
            "category":"Health Services",
            "subcategory":"Dentist",
            "type":"Services"
        }
    ],
    "sg:phone":"+32 59 50 05 62",
    "sg:postcode":"8400",
    "sg:province":"West-Vlaanderen",
    "wof:name":"Vantieghem Ann",
    "wof:placetype":"venue"
},
  "geometry": {"coordinates":[2.9062390327,51.2232246399],"type":"Point"}
}