{
  "type": "Feature",
  "properties": {
    "iso:country":"BE",
    "sg:address":"Rue Des Israelites",
    "sg:city":"Frameries",
    "sg:orig_category":"Epiceries",
    "sg:phone":"+32 65 66 77 28",
    "sg:postcode":"7370",
    "sg:province":"Hainaut",
    "wof:name":"Maison Delto",
    "wof:placetype":"venue"
},
  "geometry": {"coordinates":[3.7785201073,50.39635849],"type":"Point"}
}