{
  "type": "Feature",
  "properties": {
    "iso:country":"BE",
    "sg:address":"Pastoor De Swaeflaan 9",
    "sg:city":"Maldegem",
    "sg:classifiers":[
        {
            "category":"Farming",
            "subcategory":"Livestock Farm",
            "type":"Manufacturing & Wholesale Goods"
        }
    ],
    "sg:phone":"+32 50 71 29 49",
    "sg:postcode":"9990",
    "sg:province":"Oost-Vlaanderen",
    "sg:tags":[
        "buyer"
    ],
    "wof:name":"Vande Kerckhove J",
    "wof:placetype":"venue"
},
  "geometry": {"coordinates":[3.3833220005,51.2126846313],"type":"Point"}
}