{
  "type": "Feature",
  "properties": {
    "addr:full":"Oude Heirbaan 18-2 Lanaken Limburg 3620",
    "addr:housenumber":"18-2",
    "addr:postcode":"3620",
    "addr:street":"Oude Heirbaan",
    "iso:country":"BE",
    "sg:address":"Oude Heirbaan 18-2",
    "sg:city":"Lanaken",
    "sg:classifiers":[
        {
            "category":"Building & Trades",
            "subcategory":"Locksmith",
            "type":"Services"
        }
    ],
    "sg:phone":"+32 89 72 31 35",
    "sg:postcode":"3620",
    "sg:province":"Limburg",
    "sg:tags":[
        "material",
        "road"
    ],
    "wof:name":"Dero",
    "wof:placetype":"venue"
},
  "geometry": {"coordinates":[5.6839790344,50.9045982361],"type":"Point"}
}