{
  "type": "Feature",
  "properties": {
    "addr:full":"Zandkapelweg 94 Herentals (noorderwijk) Antwerpen 2200",
    "addr:housenumber":"94",
    "addr:postcode":"2200",
    "addr:street":"Zandkapelweg",
    "iso:country":"BE",
    "sg:address":"Zandkapelweg 94",
    "sg:city":"Herentals (noorderwijk)",
    "sg:classifiers":[
        {
            "category":"Arts & Performance",
            "subcategory":"Music",
            "type":"Entertainment"
        }
    ],
    "sg:phone":"+32 14 26 15 17",
    "sg:postcode":"2200",
    "sg:province":"Antwerpen",
    "sg:tags":[
        "disc-jockeys"
    ],
    "wof:name":"Dj Plons",
    "wof:placetype":"venue"
},
  "geometry": {"coordinates":[4.8414487839,51.1253967285],"type":"Point"}
}