{
  "type": "Feature",
  "properties": {
    "addr:full":"Plantin En Moretuslei 92 Antwerpen Antwerpen 2018",
    "addr:housenumber":"92",
    "addr:postcode":"2018",
    "addr:street":"Plantin En Moretuslei",
    "iso:country":"BE",
    "sg:address":"Plantin En Moretuslei 92",
    "sg:city":"Antwerpen",
    "sg:classifiers":[
        {
            "category":"Professional",
            "subcategory":"Testing Lab",
            "type":"Services"
        }
    ],
    "sg:phone":"+32 3 231 91 83",
    "sg:postcode":"2018",
    "sg:province":"Antwerpen",
    "sg:tags":[
        "chemist"
    ],
    "wof:name":"Mercurius Bvba",
    "wof:placetype":"venue"
},
  "geometry": {"coordinates":[4.4257698059,51.2105293274],"type":"Point"}
}