{
  "type": "Feature",
  "properties": {
    "iso:country":"BE",
    "sg:address":"Scottons 199",
    "sg:city":"Daverdisse",
    "sg:classifiers":[
        {
            "category":"Professional",
            "subcategory":"Accounting & Tax Preparation",
            "type":"Services"
        }
    ],
    "sg:phone":"+32 61 58 88 92",
    "sg:postcode":"6929",
    "sg:province":"Luxembourg",
    "sg:tags":[
        "accountant"
    ],
    "wof:name":"Albert Marchot",
    "wof:placetype":"venue"
},
  "geometry": {"coordinates":[5.0362682343,50.0102157593],"type":"Point"}
}