{
  "type": "Feature",
  "properties": {
    "addr:full":"Avenue Lavosier 18 Wavre Brabant Wallon 1300",
    "addr:housenumber":"18;1300",
    "addr:street":"Avenue Lavosier",
    "iso:country":"BE",
    "sg:address":"Avenue Lavosier 18",
    "sg:city":"Wavre",
    "sg:classifiers":[
        {
            "category":"Shopping",
            "subcategory":"Computers & Home Electronics",
            "type":"Retail Goods"
        }
    ],
    "sg:phone":"+32 10 23 30 50",
    "sg:postcode":"1300",
    "sg:province":"Brabant Wallon",
    "sg:tags":[
        "computerapparatuur",
        "microsoft"
    ],
    "wof:name":"Ics",
    "wof:placetype":"venue"
},
  "geometry": {"coordinates":[4.5886921883,50.735118866],"type":"Point"}
}