{
  "type": "Feature",
  "properties": {
    "addr:full":"Grote Singel 5 Schoten Antwerpen 2900",
    "addr:housenumber":"5",
    "addr:postcode":"2900",
    "addr:street":"Grote Singel",
    "iso:country":"BE",
    "sg:address":"Grote Singel 5",
    "sg:city":"Schoten",
    "sg:classifiers":[
        {
            "category":"Health Services",
            "subcategory":"Nursing And Care Facility",
            "type":"Services"
        }
    ],
    "sg:phone":"+32 3 658 18 31",
    "sg:postcode":"2900",
    "sg:province":"Antwerpen",
    "sg:tags":[
        "home",
        "rest"
    ],
    "wof:name":"Reinaert (home)",
    "wof:placetype":"venue"
},
  "geometry": {"coordinates":[4.5151309967,51.2545967102],"type":"Point"}
}