{
  "type": "Feature",
  "properties": {
    "iso:country":"BE",
    "sg:address":"Chemin D'oultre-heure 170",
    "sg:city":"Ham-sur-heure-nalinnes",
    "sg:orig_category":"Eleveurs de bovins",
    "sg:phone":"+32 71 21 31 18",
    "sg:postcode":"6120",
    "sg:province":"Hainaut",
    "wof:name":"Hubert Marlier",
    "wof:placetype":"venue"
},
  "geometry": {"coordinates":[4.4150328636,50.325958252],"type":"Point"}
}