{
  "type": "Feature",
  "properties": {
    "addr:full":"Eikhoekstraat 37 Vleteren West-Vlaanderen 8640",
    "addr:housenumber":"37",
    "addr:postcode":"8640",
    "addr:street":"Eikhoekstraat",
    "iso:country":"BE",
    "sg:address":"Eikhoekstraat 37",
    "sg:city":"Vleteren",
    "sg:orig_category":"Rundveehouders Varkenskwekers",
    "sg:phone":"+32 57 40 02 02",
    "sg:postcode":"8640",
    "sg:province":"West-Vlaanderen",
    "wof:name":"Filip Debergh",
    "wof:placetype":"venue"
},
  "geometry": {"coordinates":[2.7347838879,50.9163093567],"type":"Point"}
}