{
  "type": "Feature",
  "properties": {
    "iso:country":"BE",
    "sg:address":"Felix Beernaertsplein 15",
    "sg:city":"Wetteren",
    "sg:classifiers":[
        {
            "category":"Cafe",
            "type":"Food & Drink"
        }
    ],
    "sg:phone":"+32 9 369 63 77",
    "sg:postcode":"9230",
    "sg:province":"Oost-Vlaanderen",
    "sg:tags":[
        "caf\u00e9s"
    ],
    "wof:name":"Caf\u00c9 't Volkshuis",
    "wof:placetype":"venue"
},
  "geometry": {"coordinates":[3.8797519207,51.0028076172],"type":"Point"}
}