{
  "type": "Feature",
  "properties": {
    "iso:country":"BE",
    "sg:address":"Runkstersteenweg 172",
    "sg:city":"Hasselt",
    "sg:orig_category":"Woningbouw",
    "sg:phone":"+32 11 27 22 57",
    "sg:postcode":"3500",
    "sg:province":"Limburg",
    "wof:name":"Dicon",
    "wof:placetype":"venue"
},
  "geometry": {"coordinates":[5.3248448372,50.9257011414],"type":"Point"}
}