{
  "type": "Feature",
  "properties": {
    "addr:full":"Chemin Mitoyen 12b Estaimpuis (leers-nord) Hainaut 7730",
    "addr:housenumber":"12b",
    "addr:postcode":"7730",
    "addr:street":"Chemin Mitoyen",
    "iso:country":"BE",
    "sg:address":"Chemin Mitoyen 12b",
    "sg:city":"Estaimpuis (leers-nord)",
    "sg:classifiers":[
        {
            "category":"Education",
            "subcategory":"School",
            "type":"Public Place"
        }
    ],
    "sg:phone":"+32 56 48 30 50",
    "sg:postcode":"7730",
    "sg:province":"Hainaut",
    "sg:tags":[
        "primary"
    ],
    "wof:name":"Goelette (la)",
    "wof:placetype":"venue"
},
  "geometry": {"coordinates":[3.2735199928,50.6673164368],"type":"Point"}
}