{
  "type": "Feature",
  "properties": {
    "addr:full":"All\u00e9e Du Moulin \u00e0 Vent 13 Namur Namur 5000",
    "addr:housenumber":"13",
    "addr:postcode":"5000",
    "addr:street":"Alle\u0301E Du Moulin A\u0300 Vent",
    "iso:country":"BE",
    "sg:address":"All\u00e9e Du Moulin \u00e0 Vent 13",
    "sg:city":"Namur",
    "sg:classifiers":[
        {
            "category":"Professional",
            "subcategory":"Computer Services",
            "type":"Services"
        }
    ],
    "sg:phone":"+32 81 23 14 42",
    "sg:postcode":"5000",
    "sg:province":"Namur",
    "sg:tags":[
        "-",
        "processing",
        "data",
        "software"
    ],
    "wof:name":"C.d.i.",
    "wof:placetype":"venue"
},
  "geometry": {"coordinates":[4.8723201752,50.4763183594],"type":"Point"}
}