{
  "type": "Feature",
  "properties": {
    "addr:full":"Statielei 23-25 Mortsel Antwerpen 2640",
    "addr:postcode":"23-25;2640",
    "addr:street":"Statielei",
    "iso:country":"BE",
    "sg:address":"Statielei 23-25",
    "sg:city":"Mortsel",
    "sg:orig_category":"Geschenken and souvenirs Verlichting and huishoudartikelen",
    "sg:phone":"+32 3 449 03 34",
    "sg:postcode":"2640",
    "sg:province":"Antwerpen",
    "wof:name":"Princess",
    "wof:placetype":"venue"
},
  "geometry": {"coordinates":[4.4506030083,51.1707992554],"type":"Point"}
}