{
  "type": "Feature",
  "properties": {
    "iso:country":"BE",
    "sg:address":"Brakeleer 29",
    "sg:city":"Buggenhout",
    "sg:classifiers":[
        {
            "category":"Building & Trades",
            "subcategory":"Construction",
            "type":"Services"
        }
    ],
    "sg:phone":"+32 52 33 52 14",
    "sg:postcode":"9255",
    "sg:province":"Oost-Vlaanderen",
    "sg:tags":[
        "installation",
        "-",
        "central",
        "heating"
    ],
    "wof:name":"Inverco Nv",
    "wof:placetype":"venue"
},
  "geometry": {"coordinates":[4.1979899406,51.0195503235],"type":"Point"}
}