{
  "type": "Feature",
  "properties": {
    "addr:full":"Grand Place 17 Quaregnon Hainaut 7390",
    "addr:housenumber":"17",
    "addr:postcode":"7390",
    "addr:street":"Grand Place",
    "iso:country":"BE",
    "sg:address":"Grand Place 17",
    "sg:city":"Quaregnon",
    "sg:classifiers":[
        {
            "category":"Bars & Pubs",
            "type":"Food & Drink"
        }
    ],
    "sg:phone":"+32 65 78 60 41",
    "sg:postcode":"7390",
    "sg:province":"Hainaut",
    "wof:name":"Taverne (la)",
    "wof:placetype":"venue"
},
  "geometry": {"coordinates":[3.8651049137,50.4428939819],"type":"Point"}
}