{
  "type": "Feature",
  "properties": {
    "iso:country":"BE",
    "sg:address":"Rue Montoyer 14",
    "sg:city":"Bruxelles",
    "sg:classifiers":[
        {
            "category":"Organizations",
            "subcategory":"Non-profit Organization",
            "type":"Services"
        }
    ],
    "sg:phone":"+32 2 500 09 10",
    "sg:postcode":"1000",
    "sg:province":"Bruxelles-Capitale",
    "sg:tags":[
        "international",
        "organisation"
    ],
    "wof:name":"World Food Programme",
    "wof:placetype":"venue"
},
  "geometry": {"coordinates":[4.3691649437,50.841506958],"type":"Point"}
}