{
  "type": "Feature",
  "properties": {
    "addr:full":"Beernemsteenweg 49a Wingene West-Vlaanderen 8750",
    "addr:housenumber":"49a",
    "addr:postcode":"8750",
    "addr:street":"Beernemsteenweg",
    "iso:country":"BE",
    "sg:address":"Beernemsteenweg 49a",
    "sg:city":"Wingene",
    "sg:classifiers":[
        {
            "category":"Transit Center",
            "subcategory":"Freight",
            "type":"Transportation"
        }
    ],
    "sg:phone":"+32 51 65 00 10",
    "sg:postcode":"8750",
    "sg:province":"West-Vlaanderen",
    "sg:tags":[
        "glue"
    ],
    "wof:name":"Basin Chemie Nv",
    "wof:placetype":"venue"
},
  "geometry": {"coordinates":[3.2986629009,51.0783424377],"type":"Point"}
}