{
  "type": "Feature",
  "properties": {
    "addr:full":"Rue De La Croix De Fer 77 Brussel/bruxelles Bruxelles-Capitale 1000",
    "addr:housenumber":"77",
    "addr:postcode":"1000",
    "addr:street":"Rue De La Croix De Fer;/",
    "iso:country":"BE",
    "sg:address":"Rue De La Croix De Fer 77",
    "sg:city":"Brussel/bruxelles",
    "sg:classifiers":[
        {
            "category":"Government",
            "subcategory":"Police Station",
            "type":"Public Place"
        }
    ],
    "sg:phone":"+32 2 507 96 34",
    "sg:postcode":"1000",
    "sg:province":"Bruxelles-Capitale",
    "sg:tags":[
        "gendarmerie"
    ],
    "wof:name":"Police F\u00c9d\u00c9rale/federale Politie",
    "wof:placetype":"venue"
},
  "geometry": {"coordinates":[4.3513898849,50.8584594727],"type":"Point"}
}