{
  "type": "Feature",
  "properties": {
    "iso:country":"BE",
    "sg:address":"Dendermondse Steenweg 23",
    "sg:city":"Hamme",
    "sg:orig_category":"M\u00e9decins and sp\u00e9cialistes",
    "sg:phone":"+32 52 47 64 34",
    "sg:postcode":"9220",
    "sg:province":"Oost-Vlaanderen",
    "wof:name":"Ingrid Bogaert",
    "wof:placetype":"venue"
},
  "geometry": {"coordinates":[4.1177220345,51.0684776306],"type":"Point"}
}