{
  "type": "Feature",
  "properties": {
    "addr:full":"Rue Vandenbroeck 73 Elsene/ixelles Bruxelles-Capitale 1050",
    "addr:housenumber":"73",
    "addr:postcode":"1050",
    "addr:street":"Rue Vandenbroeck",
    "iso:country":"BE",
    "sg:address":"Rue Vandenbroeck 73",
    "sg:city":"Elsene/ixelles",
    "sg:orig_category":"M\u00e9decins and sp\u00e9cialistes",
    "sg:phone":"+32 2 649 39 50",
    "sg:postcode":"1050",
    "sg:province":"Bruxelles-Capitale",
    "wof:name":"B\u00c9atrice Swennen",
    "wof:placetype":"venue"
},
  "geometry": {"coordinates":[4.3764648438,50.8338813782],"type":"Point"}
}