{
  "type": "Feature",
  "properties": {
    "addr:full":"Gasthuisstraat 3 Brussel/bruxelles Bruxelles-Capitale 1000",
    "addr:housenumber":"3",
    "addr:postcode":"1000",
    "addr:street":"Gasthuisstraat;/",
    "iso:country":"BE",
    "sg:address":"Gasthuisstraat 3",
    "sg:city":"Brussel/bruxelles",
    "sg:orig_category":"Luchtvaart volgens dienstregeling",
    "sg:phone":"+32 2 514 03 03",
    "sg:postcode":"1000",
    "sg:province":"Bruxelles-Capitale",
    "wof:name":"Gulf Agency Transport",
    "wof:placetype":"venue"
},
  "geometry": {"coordinates":[4.3530678749,50.8443374634],"type":"Point"}
}