{
  "type": "Feature",
  "properties": {
    "addr:full":"Rue Jean Pain 35 Fontaine-l'ev\u00eaque Hainaut 6140",
    "addr:housenumber":"35",
    "addr:postcode":"6140",
    "addr:street":"Rue Jean Pain;\u0302Que Hainaut",
    "iso:country":"BE",
    "sg:address":"Rue Jean Pain 35",
    "sg:city":"Fontaine-l'ev\u00eaque",
    "sg:classifiers":[
        {
            "category":"Health Services",
            "subcategory":"Nursing And Care Facility",
            "type":"Services"
        }
    ],
    "sg:phone":"+32 71 52 49 64",
    "sg:postcode":"6140",
    "sg:province":"Hainaut",
    "sg:tags":[
        "home"
    ],
    "wof:name":"Gravante A",
    "wof:placetype":"venue"
},
  "geometry": {"coordinates":[-111.9644622803,46.2507972717],"type":"Point"}
}