{
  "type": "Feature",
  "properties": {
    "addr:full":"Massemsesteenweg 133 Wetteren Oost-Vlaanderen 9230",
    "addr:housenumber":"133",
    "addr:postcode":"9230",
    "addr:street":"Massemsesteenweg",
    "iso:country":"BE",
    "sg:address":"Massemsesteenweg 133",
    "sg:city":"Wetteren",
    "sg:classifiers":[
        {
            "category":"Food & Beverages",
            "subcategory":"Specialty",
            "type":"Retail Goods"
        }
    ],
    "sg:phone":"+32 9 368 03 40",
    "sg:postcode":"9230",
    "sg:province":"Oost-Vlaanderen",
    "sg:tags":[
        "health",
        "dietary",
        "-",
        "biological"
    ],
    "wof:name":"Blekerij (de)",
    "wof:placetype":"venue"
},
  "geometry": {"coordinates":[3.8790500164,50.9921302795],"type":"Point"}
}