{
  "type": "Feature",
  "properties": {
    "addr:full":"Stropet 1 Neufch\u00e2teau (longlier) Luxembourg 6840",
    "addr:housenumber":"1",
    "addr:postcode":"6840",
    "addr:street":"Stropet",
    "iso:country":"BE",
    "sg:address":"Stropet 1",
    "sg:city":"Neufch\u00e2teau (longlier)",
    "sg:classifiers":[
        {
            "category":"Autos & Motor Vehicles",
            "subcategory":"Motorcycle Sales",
            "type":"Retail Goods"
        }
    ],
    "sg:phone":"+32 61 27 97 04",
    "sg:postcode":"6840",
    "sg:province":"Luxembourg",
    "sg:tags":[
        "scooter",
        "-",
        "moped"
    ],
    "wof:name":"Offroad Moto-ktm",
    "wof:placetype":"venue"
},
  "geometry": {"coordinates":[5.4346451759,49.8411598206],"type":"Point"}
}