{
  "type": "Feature",
  "properties": {
    "iso:country":"BE",
    "sg:address":"Route De Paifve 8",
    "sg:city":"Bassenge",
    "sg:classifiers":[
        {
            "category":"Insurance",
            "subcategory":"Insurance Agent",
            "type":"Services"
        }
    ],
    "sg:phone":"+32 4 286 18 66",
    "sg:postcode":"4690",
    "sg:province":"Li\u00e8ge",
    "sg:tags":[
        "verzekeringsmakelaars",
        "expert"
    ],
    "wof:name":"X. Derriks",
    "wof:placetype":"venue"
},
  "geometry": {"coordinates":[5.5330820084,50.7513313293],"type":"Point"}
}