{
  "type": "Feature",
  "properties": {
    "addr:full":"Linterseweg 64 Zoutleeuw Vlaams-Brabant 3440",
    "addr:housenumber":"64",
    "addr:postcode":"3440",
    "addr:street":"Linterseweg;Vlaams-Brabant",
    "iso:country":"BE",
    "sg:address":"Linterseweg 64",
    "sg:city":"Zoutleeuw",
    "sg:orig_category":"Eleveurs and marchands de porcs",
    "sg:phone":"+32 11 58 01 51",
    "sg:postcode":"3440",
    "sg:province":"Vlaams-Brabant",
    "wof:name":"Maria Swinnen",
    "wof:placetype":"venue"
},
  "geometry": {"coordinates":[5.0779252052,50.8591957092],"type":"Point"}
}