{
  "type": "Feature",
  "properties": {
    "iso:country":"BE",
    "sg:address":"Rue Saint-jean 8",
    "sg:city":"Chi\u00e8vres",
    "sg:classifiers":[
        {
            "category":"Communications",
            "subcategory":"Film & Video Production",
            "type":"Services"
        }
    ],
    "sg:phone":"+32 68 65 83 14",
    "sg:postcode":"7950",
    "sg:province":"Hainaut",
    "sg:tags":[
        "hiring",
        "-"
    ],
    "wof:name":"Cin\u00e9-clap",
    "wof:placetype":"venue"
},
  "geometry": {"coordinates":[3.8078320026,50.5868186951],"type":"Point"}
}