{
  "type": "Feature",
  "properties": {
    "addr:full":"Nederenamestraat 263 Oudenaarde Oost-Vlaanderen 9700",
    "addr:housenumber":"263",
    "addr:postcode":"9700",
    "addr:street":"Nederenamestraat",
    "iso:country":"BE",
    "sg:address":"Nederenamestraat 263",
    "sg:city":"Oudenaarde",
    "sg:orig_category":"Zuivelproducten",
    "sg:phone":"+32 55 31 23 83",
    "sg:postcode":"9700",
    "sg:province":"Oost-Vlaanderen",
    "wof:name":"Alfons Van Bost",
    "wof:placetype":"venue"
},
  "geometry": {"coordinates":[3.6545000076,50.8692207336],"type":"Point"}
}