{
  "type": "Feature",
  "properties": {
    "addr:full":"Luikersteenweg 193 Hasselt Limburg 3500",
    "addr:housenumber":"193",
    "addr:postcode":"3500",
    "addr:street":"Luikersteenweg",
    "iso:country":"BE",
    "sg:address":"Luikersteenweg 193",
    "sg:city":"Hasselt",
    "sg:classifiers":[
        {
            "category":"Professional",
            "subcategory":"Testing Lab",
            "type":"Services"
        }
    ],
    "sg:phone":"+32 11 27 11 06",
    "sg:postcode":"3500",
    "sg:province":"Limburg",
    "sg:tags":[
        "chemist"
    ],
    "wof:name":"Van Gorp A",
    "wof:placetype":"venue"
},
  "geometry": {"coordinates":[5.3462610245,50.9171142578],"type":"Point"}
}