{
  "type": "Feature",
  "properties": {
    "addr:full":"Borrewal 25 Nevele Oost-Vlaanderen 9850",
    "addr:housenumber":"25",
    "addr:postcode":"9850",
    "addr:street":"Borrewal",
    "iso:country":"BE",
    "sg:address":"Borrewal 25",
    "sg:city":"Nevele",
    "sg:orig_category":"Elektrische installaties voor woningen",
    "sg:phone":"+32 9 371 43 33",
    "sg:postcode":"9850",
    "sg:province":"Oost-Vlaanderen",
    "wof:name":"Rudy Dhaeyere",
    "wof:placetype":"venue"
},
  "geometry": {"coordinates":[3.5466179848,51.0375747681],"type":"Point"}
}