{
  "type": "Feature",
  "properties": {
    "addr:full":"Enneven 52 Lommel Limburg 3920",
    "addr:housenumber":"52",
    "addr:postcode":"3920",
    "addr:street":"Enneven",
    "iso:country":"BE",
    "sg:address":"Enneven 52",
    "sg:city":"Lommel",
    "sg:classifiers":[
        {
            "category":"Personal",
            "subcategory":"Beauty Salon",
            "type":"Services"
        }
    ],
    "sg:phone":"+32 11 54 23 09",
    "sg:postcode":"3920",
    "sg:province":"Limburg",
    "sg:tags":[
        "de",
        "coiffure"
    ],
    "wof:name":"Hairdesign Peter",
    "wof:placetype":"venue"
},
  "geometry": {"coordinates":[5.3451647758,51.2335662842],"type":"Point"}
}