{
  "type": "Feature",
  "properties": {
    "iso:country":"BE",
    "sg:address":"Bergveld 82",
    "sg:city":"Westerlo",
    "sg:classifiers":[
        {
            "category":"Food & Beverages",
            "subcategory":"Fruits & Vegetables",
            "type":"Retail Goods"
        }
    ],
    "sg:phone":"+32 14 54 74 23",
    "sg:postcode":"2260",
    "sg:province":"Antwerpen",
    "sg:tags":[
        "groenten"
    ],
    "wof:name":"Lohi",
    "wof:placetype":"venue"
},
  "geometry": {"coordinates":[4.8758149147,51.0786628723],"type":"Point"}
}