{
  "type": "Feature",
  "properties": {
    "addr:full":"Hemelrijk 77 Essen Antwerpen 2910",
    "addr:housenumber":"77",
    "addr:postcode":"2910",
    "addr:street":"Hemelrijk",
    "iso:country":"BE",
    "sg:address":"Hemelrijk 77",
    "sg:city":"Essen",
    "sg:classifiers":[
        {
            "category":"Bars & Pubs",
            "type":"Food & Drink"
        }
    ],
    "sg:phone":"+32 3 677 03 91",
    "sg:postcode":"2910",
    "sg:province":"Antwerpen",
    "sg:tags":[
        "tavern"
    ],
    "wof:name":"Quarantaine Stallen",
    "wof:placetype":"venue"
},
  "geometry": {"coordinates":[4.4471559525,51.4681816101],"type":"Point"}
}