{
  "type": "Feature",
  "properties": {
    "iso:country":"BE",
    "sg:address":"Hogeweg 2",
    "sg:city":"Asse",
    "sg:orig_category":"Enseignement maternel and primaire",
    "sg:phone":"+32 2 452 86 44",
    "sg:postcode":"1730",
    "sg:province":"Vlaams-Brabant",
    "wof:name":"Kleuterschool",
    "wof:placetype":"venue"
},
  "geometry": {"coordinates":[4.1593389511,50.9065818787],"type":"Point"}
}