{
  "type": "Feature",
  "properties": {
    "iso:country":"BE",
    "sg:address":"Av. Des Bergeronnettes 7",
    "sg:city":"Braine-l'alleud",
    "sg:orig_category":"Agences immobili\u00e8res. Administration d'immeubles",
    "sg:phone":"+32 2 354 22 07",
    "sg:postcode":"1420",
    "sg:province":"Brabant Wallon",
    "wof:name":"Roja Invest",
    "wof:placetype":"venue"
},
  "geometry": {"coordinates":[15.2195005417,40.783657074],"type":"Point"}
}