{
  "type": "Feature",
  "properties": {
    "addr:full":"Avenue Eug\u00c8ne Mascaux 4 Charleroi Hainaut 6001",
    "addr:housenumber":"4",
    "addr:postcode":"6001",
    "addr:street":"Avenue Euge\u0300Ne Mascaux;Hainaut",
    "iso:country":"BE",
    "sg:address":"Avenue Eug\u00c8ne Mascaux 4",
    "sg:city":"Charleroi",
    "sg:orig_category":"Opticiens",
    "sg:phone":"+32 71 43 47 48",
    "sg:postcode":"6001",
    "sg:province":"Hainaut",
    "wof:name":"Centroptique Siega & Fils",
    "wof:placetype":"venue"
},
  "geometry": {"coordinates":[4.4475708008,50.4000205994],"type":"Point"}
}