{
  "type": "Feature",
  "properties": {
    "iso:country":"BE",
    "sg:address":"Heideroosje 6",
    "sg:city":"Meise",
    "sg:orig_category":"Artsen and specialisten",
    "sg:phone":"+32 2 269 24 15",
    "sg:postcode":"1860",
    "sg:province":"Vlaams-Brabant",
    "wof:name":"S. Jockmans",
    "wof:placetype":"venue"
},
  "geometry": {"coordinates":[4.2961912155,50.9451446533],"type":"Point"}
}