{
  "type": "Feature",
  "properties": {
    "iso:country":"BE",
    "sg:address":"D'hofstee 6",
    "sg:city":"Buggenhout",
    "sg:orig_category":"Sportclubs",
    "sg:phone":"+32 52 33 50 45",
    "sg:postcode":"9255",
    "sg:province":"Oost-Vlaanderen",
    "wof:name":"Union",
    "wof:placetype":"venue"
},
  "geometry": {"coordinates":[4.2203011513,51.025680542],"type":"Point"}
}