{
  "type": "Feature",
  "properties": {
    "iso:country":"BE",
    "sg:address":"Klaaie 7",
    "sg:city":"Brakel",
    "sg:orig_category":"Installatie van houten of kunststof schrijnwerk",
    "sg:phone":"+32 55 42 30 63",
    "sg:postcode":"9660",
    "sg:province":"Oost-Vlaanderen",
    "wof:name":"Dewolux",
    "wof:placetype":"venue"
},
  "geometry": {"coordinates":[3.8028829098,50.7729225159],"type":"Point"}
}