{
  "type": "Feature",
  "properties": {
    "iso:country":"BE",
    "sg:address":"Rue Principale 170",
    "sg:city":"Li\u00e8ge 1 (rocourt)",
    "sg:classifiers":[
        {
            "category":"Personal",
            "subcategory":"Beauty Salon",
            "type":"Services"
        }
    ],
    "sg:phone":"+32 4 263 26 99",
    "sg:postcode":"4000",
    "sg:province":"Li\u00e8ge",
    "sg:tags":[
        "lady",
        "-",
        "hairdressing"
    ],
    "wof:name":"Florent",
    "wof:placetype":"venue"
},
  "geometry": {"coordinates":[5.5559167862,50.6799087524],"type":"Point"}
}