{
  "type": "Feature",
  "properties": {
    "addr:full":"Hulskensweg 9 Zonhoven Limburg 3520",
    "addr:housenumber":"9",
    "addr:postcode":"3520",
    "addr:street":"Hulskensweg",
    "iso:country":"BE",
    "sg:address":"Hulskensweg 9",
    "sg:city":"Zonhoven",
    "sg:orig_category":"Epiceries",
    "sg:phone":"+32 11 81 89 66",
    "sg:postcode":"3520",
    "sg:province":"Limburg",
    "wof:name":"Robert Gaillard",
    "wof:placetype":"venue"
},
  "geometry": {"coordinates":[5.4161300659,50.9847755432],"type":"Point"}
}