{
  "type": "Feature",
  "properties": {
    "addr:full":"Boulevard Rener 6 Spa Li\u00e8ge 4900",
    "addr:housenumber":"6",
    "addr:postcode":"4900",
    "addr:street":"Boulevard Rener",
    "iso:country":"BE",
    "sg:address":"Boulevard Rener 6",
    "sg:city":"Spa",
    "sg:orig_category":"RESTAURANTS: H\u00d4TELS",
    "sg:phone":"+32 87 77 38 40",
    "sg:postcode":"4900",
    "sg:province":"Li\u00e8ge",
    "wof:name":"H\u00d4tel Gai S\u00c9jour",
    "wof:placetype":"venue"
},
  "geometry": {"coordinates":[5.865237236,50.4879302979],"type":"Point"}
}