{
  "type": "Feature",
  "properties": {
    "addr:full":"Rue De La Fagne 31 Jalhay Li\u00e8ge 4845",
    "addr:housenumber":"31",
    "addr:postcode":"4845",
    "addr:street":"Rue De La Fagne",
    "iso:country":"BE",
    "sg:address":"Rue De La Fagne 31",
    "sg:city":"Jalhay",
    "sg:classifiers":[
        {
            "category":"Building & Trades",
            "subcategory":"Landscaping Services",
            "type":"Services"
        }
    ],
    "sg:phone":"+32 87 64 76 22",
    "sg:postcode":"4845",
    "sg:province":"Li\u00e8ge",
    "sg:tags":[
        "gardening",
        "garden",
        "maintenance"
    ],
    "wof:name":"Rood J-f Sprl",
    "wof:placetype":"venue"
},
  "geometry": {"coordinates":[5.9706587791,50.5578117371],"type":"Point"}
}