{
  "type": "Feature",
  "properties": {
    "addr:full":"Rue C\u00e9sar De Paepe 2 Soumagne Li\u00e8ge 4630",
    "addr:housenumber":"2",
    "addr:postcode":"4630",
    "addr:street":"Rue Ce\u0301Sar De Paepe",
    "iso:country":"BE",
    "sg:address":"Rue C\u00e9sar De Paepe 2",
    "sg:city":"Soumagne",
    "sg:classifiers":[
        {
            "category":"Health Services",
            "subcategory":"Dentist",
            "type":"Services"
        }
    ],
    "sg:phone":"+32 4 330 94 12",
    "sg:postcode":"4630",
    "sg:province":"Li\u00e8ge",
    "wof:name":"Philippe Pierre",
    "wof:placetype":"venue"
},
  "geometry": {"coordinates":[5.735449791,50.6312294006],"type":"Point"}
}