{
  "type": "Feature",
  "properties": {
    "iso:country":"BE",
    "sg:address":"Terhulpensesteenweg 190",
    "sg:city":"Overijse",
    "sg:classifiers":[
        {
            "category":"Professional",
            "subcategory":"Computer Services",
            "type":"Services"
        }
    ],
    "sg:phone":"+32 2 688 12 46",
    "sg:postcode":"3090",
    "sg:province":"Vlaams-Brabant",
    "sg:tags":[
        "repair",
        "processing",
        "-",
        "maintenance",
        "data"
    ],
    "wof:name":"Simex",
    "wof:placetype":"venue"
},
  "geometry": {"coordinates":[4.5348291397,50.7606201172],"type":"Point"}
}