{
  "type": "Feature",
  "properties": {
    "iso:country":"BE",
    "sg:address":"Trieststraat 87",
    "sg:city":"Assenede",
    "sg:classifiers":[
        {
            "category":"Insurance",
            "subcategory":"Life Insurance",
            "type":"Services"
        }
    ],
    "sg:phone":"+32 9 343 08 57",
    "sg:postcode":"9960",
    "sg:province":"Oost-Vlaanderen",
    "sg:tags":[
        "assurance"
    ],
    "wof:name":"Wim Bogaert",
    "wof:placetype":"venue"
},
  "geometry": {"coordinates":[3.7531619072,51.2198944092],"type":"Point"}
}