{
  "type": "Feature",
  "properties": {
    "addr:full":"Luikerstraat 57 Sint-truiden Limburg 3800",
    "addr:housenumber":"57",
    "addr:postcode":"3800",
    "addr:street":"Luikerstraat",
    "iso:country":"BE",
    "sg:address":"Luikerstraat 57",
    "sg:city":"Sint-truiden",
    "sg:classifiers":[
        {
            "category":"Shopping",
            "subcategory":"Clothing, Apparel, & Fashions",
            "type":"Retail Goods"
        }
    ],
    "sg:phone":"+32 11 78 59 02",
    "sg:postcode":"3800",
    "sg:province":"Limburg",
    "sg:tags":[
        "-",
        "clothing",
        "child"
    ],
    "wof:name":"Pirouette",
    "wof:placetype":"venue"
},
  "geometry": {"coordinates":[5.1886601448,50.8139381409],"type":"Point"}
}