{
  "type": "Feature",
  "properties": {
    "iso:country":"BE",
    "sg:address":"Route De Florennes 137",
    "sg:city":"Gerpinnes",
    "sg:classifiers":[
        {
            "category":"Building & Trades",
            "subcategory":"Plumbing",
            "type":"Services"
        }
    ],
    "sg:phone":"+32 71 50 22 83",
    "sg:postcode":"6280",
    "sg:province":"Hainaut",
    "sg:tags":[
        "repair",
        "mainten",
        "-",
        "central",
        "heating"
    ],
    "wof:name":"Gambier D",
    "wof:placetype":"venue"
},
  "geometry": {"coordinates":[4.5363798141,50.3169212341],"type":"Point"}
}