{
  "type": "Feature",
  "properties": {
    "addr:full":"Rue Fond Marie 563 Theux Li\u00e8ge 4910",
    "addr:housenumber":"563",
    "addr:postcode":"4910",
    "addr:street":"Rue Fond Marie",
    "iso:country":"BE",
    "sg:address":"Rue Fond Marie 563",
    "sg:city":"Theux",
    "sg:orig_category":"Salles de conf\u00e9rences and de r\u00e9ceptions",
    "sg:phone":"+32 87 53 07 54",
    "sg:postcode":"4910",
    "sg:province":"Li\u00e8ge",
    "wof:name":"Le Parc \u00c0 Gibier Restaurant",
    "wof:placetype":"venue"
},
  "geometry": {"coordinates":[5.7783780098,50.5141067505],"type":"Point"}
}