{
  "type": "Feature",
  "properties": {
    "addr:full":"Pastorieweg 4 Brugge West-Vlaanderen 8310",
    "addr:housenumber":"4",
    "addr:postcode":"8310",
    "addr:street":"Pastorieweg",
    "iso:country":"BE",
    "sg:address":"Pastorieweg 4",
    "sg:city":"Brugge",
    "sg:orig_category":"Enseignement maternel and primaire",
    "sg:phone":"+32 50 35 12 10",
    "sg:postcode":"8310",
    "sg:province":"West-Vlaanderen",
    "wof:name":"Vrije Basisschool",
    "wof:placetype":"venue"
},
  "geometry": {"coordinates":[3.2506649494,51.2150993347],"type":"Point"}
}