{
  "type": "Feature",
  "properties": {
    "addr:full":"Lange Stuivenbergstraat 54-56 Antwerpen Antwerpen 2060",
    "addr:postcode":"54-56;2060",
    "addr:street":"Lange Stuivenbergstraat",
    "iso:country":"BE",
    "sg:address":"Lange Stuivenbergstraat 54-56",
    "sg:city":"Antwerpen",
    "sg:classifiers":[
        {
            "category":"Social Services",
            "type":"Services"
        }
    ],
    "sg:phone":"+32 3 235 34 05",
    "sg:postcode":"2060",
    "sg:province":"Antwerpen",
    "wof:name":"Protestants Sociaal Centrum",
    "wof:placetype":"venue"
},
  "geometry": {"coordinates":[4.4310469627,51.2247772217],"type":"Point"}
}