{
  "type": "Feature",
  "properties": {
    "iso:country":"BE",
    "sg:address":"Joseph Cardijnstraat 7",
    "sg:city":"Erpe",
    "sg:classifiers":[
        {
            "category":"Manufacturing",
            "subcategory":"Printing",
            "type":"Manufacturing & Wholesale Goods"
        }
    ],
    "sg:phone":"+32 53 82 70 20",
    "sg:postcode":"9420",
    "sg:province":"Oost-Vlaanderen",
    "sg:tags":[
        "publishing"
    ],
    "wof:name":"Belgian Cutting Company Nv",
    "wof:placetype":"venue"
},
  "geometry": {"coordinates":[3.9619688988,50.9324836731],"type":"Point"}
}