{
  "type": "Feature",
  "properties": {
    "addr:full":"Avenue Joseph Abras 60 Namur Namur 5001",
    "addr:housenumber":"60",
    "addr:postcode":"5001",
    "addr:street":"Avenue Joseph Abras",
    "iso:country":"BE",
    "sg:address":"Avenue Joseph Abras 60",
    "sg:city":"Namur",
    "sg:classifiers":[
        {
            "category":"Restaurant",
            "type":"Food & Drink"
        }
    ],
    "sg:phone":"+32 81 73 24 27",
    "sg:postcode":"5001",
    "sg:province":"Namur",
    "sg:tags":[
        "de",
        "organisation",
        "\u00e0",
        "fast",
        "catering",
        "emporter",
        "f\u00eates",
        "restaurants"
    ],
    "wof:name":"Le Bourguignon",
    "wof:placetype":"venue"
},
  "geometry": {"coordinates":[4.8257050514,50.4722557068],"type":"Point"}
}