{
  "type": "Feature",
  "properties": {
    "iso:country":"BE",
    "sg:address":"Kwadestraat 66",
    "sg:city":"Bekkevoort (assent)",
    "sg:classifiers":[
        {
            "category":"Education",
            "subcategory":"Special Training",
            "type":"Public Place"
        }
    ],
    "sg:phone":"+32 13 52 36 52",
    "sg:postcode":"3460",
    "sg:province":"Vlaams-Brabant",
    "sg:tags":[
        "-",
        "processing",
        "data"
    ],
    "wof:name":"Albir Bvba",
    "wof:placetype":"venue"
},
  "geometry": {"coordinates":[5.0284152031,50.9539871216],"type":"Point"}
}