{
  "type": "Feature",
  "properties": {
    "addr:full":"Chauss\u00c9e De Waterloo 169 Sint-gillis/saint-gilles Bruxelles-Capitale 1060",
    "addr:housenumber":"169",
    "addr:postcode":"1060",
    "addr:street":"Chausse\u0301E De Waterloo",
    "iso:country":"BE",
    "sg:address":"Chauss\u00c9e De Waterloo 169",
    "sg:city":"Sint-gillis/saint-gilles",
    "sg:orig_category":"Librairies",
    "sg:phone":"+32 2 537 96 20",
    "sg:postcode":"1060",
    "sg:province":"Bruxelles-Capitale",
    "wof:name":"Bedemania",
    "wof:placetype":"venue"
},
  "geometry": {"coordinates":[4.3448791504,50.8266448975],"type":"Point"}
}