{
  "type": "Feature",
  "properties": {
    "addr:full":"Steenhuizestraat 35 Herzele Oost-Vlaanderen 9550",
    "addr:housenumber":"35",
    "addr:postcode":"9550",
    "addr:street":"Steenhuizestraat;Oost-Vlaanderen",
    "iso:country":"BE",
    "sg:address":"Steenhuizestraat 35",
    "sg:city":"Herzele",
    "sg:orig_category":"Transports routiers de marchandises",
    "sg:phone":"+32 54 50 00 83",
    "sg:postcode":"9550",
    "sg:province":"Oost-Vlaanderen",
    "wof:name":"Pascotrans",
    "wof:placetype":"venue"
},
  "geometry": {"coordinates":[3.8872470856,50.8493804932],"type":"Point"}
}