{
  "type": "Feature",
  "properties": {
    "iso:country":"BE",
    "sg:address":"Prins Boudewijnlaan 9",
    "sg:city":"Kontich",
    "sg:classifiers":[
        {
            "category":"Building & Trades",
            "subcategory":"Plumbing",
            "type":"Services"
        }
    ],
    "sg:phone":"+32 3 457 94 50",
    "sg:postcode":"2550",
    "sg:province":"Antwerpen",
    "sg:tags":[
        "diver",
        "commerce",
        "gr",
        "pour",
        "equipement"
    ],
    "wof:name":"Gansow Belgium",
    "wof:placetype":"venue"
},
  "geometry": {"coordinates":[4.4366021156,51.1422386169],"type":"Point"}
}