{
  "type": "Feature",
  "properties": {
    "addr:full":"Rue Du Soleil 179 Ronse/renaix Oost-Vlaanderen 9600",
    "addr:housenumber":"179",
    "addr:postcode":"9600",
    "addr:street":"Rue Du Soleil",
    "iso:country":"BE",
    "sg:address":"Rue Du Soleil 179",
    "sg:city":"Ronse/renaix",
    "sg:orig_category":"M\u00e9decins and sp\u00e9cialistes",
    "sg:phone":"+32 55 20 97 50",
    "sg:postcode":"9600",
    "sg:province":"Oost-Vlaanderen",
    "wof:name":"Paul Van Der Veken",
    "wof:placetype":"venue"
},
  "geometry": {"coordinates":[3.5852301121,50.7494888306],"type":"Point"}
}