{
  "type": "Feature",
  "properties": {
    "iso:country":"BE",
    "sg:address":"8",
    "sg:city":"Melkerijweg 2240 Zandhoven",
    "sg:classifiers":[
        {
            "category":"Building & Trades",
            "subcategory":"Construction",
            "type":"Services"
        }
    ],
    "sg:phone":"+32 3 484 60 72",
    "sg:postcode":"8",
    "sg:tags":[
        "work",
        "public"
    ],
    "wof:name":"Luc D'hulst Bvba",
    "wof:placetype":"venue"
},
  "geometry": {"coordinates":[4.6743059158,51.223487854],"type":"Point"}
}