{
  "type": "Feature",
  "properties": {
    "iso:country":"BE",
    "sg:address":"Sint-apollonialaan 124",
    "sg:city":"Mol",
    "sg:classifiers":[
        {
            "category":"Wholesale",
            "subcategory":"Beer",
            "type":"Manufacturing & Wholesale Goods"
        }
    ],
    "sg:phone":"+32 14 31 28 49",
    "sg:postcode":"2400",
    "sg:province":"Antwerpen",
    "sg:tags":[
        "ale",
        "-"
    ],
    "wof:name":"Borms Bvba",
    "wof:placetype":"venue"
},
  "geometry": {"coordinates":[5.0989408493,51.1942329407],"type":"Point"}
}