{
  "type": "Feature",
  "properties": {
    "iso:country":"BE",
    "sg:address":"Ossegemstraat 10-12",
    "sg:city":"Meise",
    "sg:classifiers":[
        {
            "category":"Manufacturing",
            "subcategory":"Furniture",
            "type":"Manufacturing & Wholesale Goods"
        }
    ],
    "sg:phone":"+32 2 269 45 42",
    "sg:postcode":"1860",
    "sg:province":"Vlaams-Brabant",
    "sg:tags":[
        "design",
        "-"
    ],
    "wof:name":"Cockaert Design",
    "wof:placetype":"venue"
},
  "geometry": {"coordinates":[4.3183398247,50.9590110779],"type":"Point"}
}