{
  "type": "Feature",
  "properties": {
    "iso:country":"BE",
    "sg:address":"Rue Du V\u00c9lodrome 2",
    "sg:city":"Dinant",
    "sg:classifiers":[
        {
            "category":"Restaurant",
            "type":"Food & Drink"
        }
    ],
    "sg:phone":"+32 82 22 85 75",
    "sg:postcode":"5500",
    "sg:province":"Namur",
    "wof:name":"Le Martin P\u00cacheur",
    "wof:placetype":"venue"
},
  "geometry": {"coordinates":[4.9075469971,50.2379302979],"type":"Point"}
}