{
  "type": "Feature",
  "properties": {
    "addr:full":"Brusselsesteenweg 48 Asse Vlaams-Brabant 1730",
    "addr:housenumber":"48",
    "addr:postcode":"1730",
    "addr:street":"Brusselsesteenweg",
    "iso:country":"BE",
    "sg:address":"Brusselsesteenweg 48",
    "sg:city":"Asse",
    "sg:classifiers":[
        {
            "category":"Cafe",
            "type":"Food & Drink"
        }
    ],
    "sg:phone":"+32 2 452 35 14",
    "sg:postcode":"1730",
    "sg:province":"Vlaams-Brabant",
    "sg:tags":[
        "caf\u00e9s"
    ],
    "wof:name":"A De Munter",
    "wof:placetype":"venue"
},
  "geometry": {"coordinates":[4.2105970383,50.9044952393],"type":"Point"}
}