{
  "type": "Feature",
  "properties": {
    "addr:full":"Rue Adolphe Gillis 35-39 Braine-le-comte Hainaut 7090",
    "addr:postcode":"35-39;7090",
    "addr:street":"Rue Adolphe Gillis;Hainaut",
    "iso:country":"BE",
    "sg:address":"Rue Adolphe Gillis 35-39",
    "sg:city":"Braine-le-comte",
    "sg:classifiers":[
        {
            "category":"Education",
            "subcategory":"Special Training",
            "type":"Public Place"
        }
    ],
    "sg:phone":"+32 67 56 10 11",
    "sg:postcode":"7090",
    "sg:province":"Hainaut",
    "sg:tags":[
        "professional"
    ],
    "wof:name":"Polybat Asbl",
    "wof:placetype":"venue"
},
  "geometry": {"coordinates":[4.1364159584,50.6085281372],"type":"Point"}
}