{
  "type": "Feature",
  "properties": {
    "addr:full":"Toleindestraat 30bb Lochristi Oost-Vlaanderen 9080",
    "addr:housenumber":"30bb",
    "addr:postcode":"9080",
    "addr:street":"Toleindestraat",
    "iso:country":"BE",
    "sg:address":"Toleindestraat 30bb",
    "sg:city":"Lochristi",
    "sg:orig_category":"Dranken",
    "sg:phone":"+32 9 355 53 08",
    "sg:postcode":"9080",
    "sg:province":"Oost-Vlaanderen",
    "wof:name":"Fa. Brouwershof",
    "wof:placetype":"venue"
},
  "geometry": {"coordinates":[3.8831899166,51.0800933838],"type":"Point"}
}