{
  "type": "Feature",
  "properties": {
    "addr:full":"Roeselarestraat 1 Zonnebeke West-Vlaanderen 8980",
    "addr:housenumber":"1",
    "addr:postcode":"8980",
    "addr:street":"Roeselarestraat",
    "iso:country":"BE",
    "sg:address":"Roeselarestraat 1",
    "sg:city":"Zonnebeke",
    "sg:classifiers":[
        {
            "category":"Food & Beverages",
            "subcategory":"Fruits & Vegetables",
            "type":"Retail Goods"
        }
    ],
    "sg:phone":"+32 51 78 03 96",
    "sg:postcode":"8980",
    "sg:province":"West-Vlaanderen",
    "sg:tags":[
        "-"
    ],
    "wof:name":"Fruitoase",
    "wof:placetype":"venue"
},
  "geometry": {"coordinates":[2.9879579544,50.8729095459],"type":"Point"}
}