{
  "type": "Feature",
  "properties": {
    "iso:country":"BE",
    "sg:address":"Tongerlodorp 17",
    "sg:city":"Westerlo (tongerlo)",
    "sg:classifiers":[
        {
            "category":"Retail",
            "subcategory":"Auto Repair",
            "type":"Services"
        }
    ],
    "sg:phone":"+32 14 54 48 91",
    "sg:postcode":"2260",
    "sg:province":"Antwerpen",
    "sg:tags":[
        "automobile-body"
    ],
    "wof:name":"Torfs Garage",
    "wof:placetype":"venue"
},
  "geometry": {"coordinates":[4.9149489403,51.1069068909],"type":"Point"}
}