{
  "type": "Feature",
  "properties": {
    "addr:full":"Markt 14 Halen Limburg 3545",
    "addr:housenumber":"14",
    "addr:postcode":"3545",
    "addr:street":"Markt",
    "iso:country":"BE",
    "sg:address":"Markt 14",
    "sg:city":"Halen",
    "sg:orig_category":"Offices du tourisme",
    "sg:phone":"+32 13 44 10 56",
    "sg:postcode":"3545",
    "sg:province":"Limburg",
    "wof:name":"Dienst Voor Toerisme Halen",
    "wof:placetype":"venue"
},
  "geometry": {"coordinates":[5.1143708229,50.9476280212],"type":"Point"}
}