{
  "type": "Feature",
  "properties": {
    "addr:full":"Korenstraat 19 Bilzen Limburg 3740",
    "addr:housenumber":"19",
    "addr:postcode":"3740",
    "addr:street":"Korenstraat",
    "iso:country":"BE",
    "sg:address":"Korenstraat 19",
    "sg:city":"Bilzen",
    "sg:orig_category":"Studios photographiques",
    "sg:phone":"+32 89 41 28 56",
    "sg:postcode":"3740",
    "sg:province":"Limburg",
    "wof:name":"Reyskens & Bellen",
    "wof:placetype":"venue"
},
  "geometry": {"coordinates":[5.5139789581,50.8704376221],"type":"Point"}
}