{
  "type": "Feature",
  "properties": {
    "iso:country":"BE",
    "sg:address":"Rue De Saint-amand 49",
    "sg:city":"Peruwelz",
    "sg:orig_category":"Biens d'occasion",
    "sg:phone":"+32 69 77 10 54",
    "sg:postcode":"7603",
    "sg:province":"Hainaut",
    "wof:name":"Le Vieux Grenier",
    "wof:placetype":"venue"
},
  "geometry": {"coordinates":[3.6036019325,50.4958267212],"type":"Point"}
}