{
  "type": "Feature",
  "properties": {
    "addr:full":"Mooksteeg 22 Houthalen-helchteren Limburg 3530",
    "addr:housenumber":"22",
    "addr:postcode":"3530",
    "addr:street":"Mooksteeg",
    "iso:country":"BE",
    "sg:address":"Mooksteeg 22",
    "sg:city":"Houthalen-helchteren",
    "sg:classifiers":[
        {
            "category":"Personal",
            "subcategory":"Beauty Salon",
            "type":"Services"
        }
    ],
    "sg:phone":"+32 11 52 33 21",
    "sg:postcode":"3530",
    "sg:province":"Limburg",
    "sg:tags":[
        "de",
        "coiffure"
    ],
    "wof:name":"No\u00cblla's Kapsalon",
    "wof:placetype":"venue"
},
  "geometry": {"coordinates":[5.3938279152,51.0284538269],"type":"Point"}
}