{
  "type": "Feature",
  "properties": {
    "iso:country":"BE",
    "sg:address":"Sportstraat 386",
    "sg:city":"Gent",
    "sg:classifiers":[
        {
            "category":"Health Services",
            "subcategory":"Health Practitioner",
            "type":"Services"
        }
    ],
    "sg:phone":"+32 9 220 03 40",
    "sg:postcode":"9000",
    "sg:province":"Oost-Vlaanderen",
    "sg:tags":[
        "physiotherapist"
    ],
    "wof:name":"Eggermont M",
    "wof:placetype":"venue"
},
  "geometry": {"coordinates":[3.703068018,51.0404930115],"type":"Point"}
}