{
  "type": "Feature",
  "properties": {
    "addr:full":"Duinbergenlaan 88 Knokke-heist (heist-aan-zee) West-Vlaanderen 8301",
    "addr:housenumber":"88",
    "addr:postcode":"8301",
    "addr:street":"Duinbergenlaan",
    "iso:country":"BE",
    "sg:address":"Duinbergenlaan 88",
    "sg:city":"Knokke-heist (heist-aan-zee)",
    "sg:classifiers":[
        {
            "category":"Farming",
            "subcategory":"Fish & Marine Products",
            "type":"Manufacturing & Wholesale Goods"
        }
    ],
    "sg:phone":"+32 50 51 66 55",
    "sg:postcode":"8301",
    "sg:province":"West-Vlaanderen",
    "sg:tags":[
        "retail",
        "-",
        "shellfish"
    ],
    "wof:name":"Merlot",
    "wof:placetype":"venue"
},
  "geometry": {"coordinates":[3.2622420788,51.3405761719],"type":"Point"}
}