{
  "type": "Feature",
  "properties": {
    "addr:full":"Hendrikstraat 25 Alken Limburg 3570",
    "addr:housenumber":"25",
    "addr:postcode":"3570",
    "addr:street":"Hendrikstraat",
    "iso:country":"BE",
    "sg:address":"Hendrikstraat 25",
    "sg:city":"Alken",
    "sg:orig_category":"R\u00e9alisation de programmes and logiciels",
    "sg:phone":"+32 11 59 72 63",
    "sg:postcode":"3570",
    "sg:province":"Limburg",
    "wof:name":"Inconet",
    "wof:placetype":"venue"
},
  "geometry": {"coordinates":[5.2806601524,50.8730163574],"type":"Point"}
}