{
  "type": "Feature",
  "properties": {
    "addr:full":"Papiermolenstraat 117 Geraardsbergen Oost-Vlaanderen 9500",
    "addr:housenumber":"117",
    "addr:postcode":"9500",
    "addr:street":"Papiermolenstraat",
    "iso:country":"BE",
    "sg:address":"Papiermolenstraat 117",
    "sg:city":"Geraardsbergen",
    "sg:orig_category":"Traitement and fa\u00e7onnage de la pierre",
    "sg:phone":"+32 54 41 37 62",
    "sg:postcode":"9500",
    "sg:province":"Oost-Vlaanderen",
    "wof:name":"De Bremme H",
    "wof:placetype":"venue"
},
  "geometry": {"coordinates":[3.8698399067,50.7702789307],"type":"Point"}
}