{
  "type": "Feature",
  "properties": {
    "iso:country":"BE",
    "sg:address":"Rue Des Tilleuls 81",
    "sg:city":"Mont-saint-guibert",
    "sg:orig_category":"Elektrische installaties voor woningen",
    "sg:phone":"+32 10 65 00 38",
    "sg:postcode":"1435",
    "sg:province":"Brabant Wallon",
    "wof:name":"Francis Degey",
    "wof:placetype":"venue"
},
  "geometry": {"coordinates":[4.6174798012,50.629940033],"type":"Point"}
}