{
  "type": "Feature",
  "properties": {
    "addr:full":"Rue Du Tombeux 13bb Verviers Li\u00e8ge 4801",
    "addr:housenumber":"13bb",
    "addr:postcode":"4801",
    "addr:street":"Rue Du Tombeux",
    "iso:country":"BE",
    "sg:address":"Rue Du Tombeux 13bb",
    "sg:city":"Verviers",
    "sg:orig_category":"M\u00e9decins and sp\u00e9cialistes",
    "sg:phone":"+32 87 31 42 14",
    "sg:postcode":"4801",
    "sg:province":"Li\u00e8ge",
    "wof:name":"Pierre Counet",
    "wof:placetype":"venue"
},
  "geometry": {"coordinates":[5.8930549622,50.5922393799],"type":"Point"}
}