{
  "type": "Feature",
  "properties": {
    "iso:country":"BE",
    "sg:address":"Hazewindstraat 16",
    "sg:city":"Sint-niklaas",
    "sg:orig_category":"Pharmaciens",
    "sg:phone":"+32 3 766 06 66",
    "sg:postcode":"9100",
    "sg:province":"Oost-Vlaanderen",
    "wof:name":"Pharma Consult",
    "wof:placetype":"venue"
},
  "geometry": {"coordinates":[4.1326780319,51.1601257324],"type":"Point"}
}