{
  "type": "Feature",
  "properties": {
    "addr:full":"Burgemeester Reynaertstraat 17 Kortrijk West-Vlaanderen 8500",
    "addr:housenumber":"17",
    "addr:postcode":"8500",
    "addr:street":"Burgemeester Reynaertstraat",
    "iso:country":"BE",
    "sg:address":"Burgemeester Reynaertstraat 17",
    "sg:city":"Kortrijk",
    "sg:classifiers":[
        {
            "category":"Shopping",
            "subcategory":"Optician",
            "type":"Retail Goods"
        }
    ],
    "sg:phone":"+32 56 22 10 36",
    "sg:postcode":"8500",
    "sg:province":"West-Vlaanderen",
    "sg:tags":[
        "-"
    ],
    "wof:name":"Vanhoonacker J",
    "wof:placetype":"venue"
},
  "geometry": {"coordinates":[3.2649919987,50.8251342773],"type":"Point"}
}