{
  "type": "Feature",
  "properties": {
    "iso:country":"BE",
    "sg:address":"Rue Du Sart 57",
    "sg:city":"Ans",
    "sg:orig_category":"Artsen and specialisten",
    "sg:phone":"+32 4 263 22 49",
    "sg:postcode":"4432",
    "sg:province":"Li\u00e8ge",
    "wof:name":"F. Schouleur",
    "wof:placetype":"venue"
},
  "geometry": {"coordinates":[5.5096569061,50.666721344],"type":"Point"}
}