{
  "type": "Feature",
  "properties": {
    "iso:country":"BE",
    "sg:address":"Abstraat 123",
    "sg:city":"Overijse",
    "sg:classifiers":[
        {
            "category":"Home & Garden",
            "subcategory":"Home Furnishings",
            "type":"Retail Goods"
        }
    ],
    "sg:phone":"+32 2 411 56 97",
    "sg:postcode":"3090",
    "sg:province":"Vlaams-Brabant",
    "sg:tags":[
        "-",
        "furniture"
    ],
    "wof:name":"Vgs Sprl",
    "wof:placetype":"venue"
},
  "geometry": {"coordinates":[4.5857639313,50.7623596191],"type":"Point"}
}