{
  "type": "Feature",
  "properties": {
    "addr:full":"Rue Gr\u00c9try 43 Brussel/bruxelles Bruxelles-Capitale 1000",
    "addr:housenumber":"43",
    "addr:postcode":"1000",
    "addr:street":"Rue Gre\u0301Try;/",
    "iso:country":"BE",
    "sg:address":"Rue Gr\u00c9try 43",
    "sg:city":"Brussel/bruxelles",
    "sg:classifiers":[
        {
            "category":"Fast Food",
            "type":"Food & Drink"
        }
    ],
    "sg:phone":"+32 2 217 77 30",
    "sg:postcode":"1000",
    "sg:province":"Bruxelles-Capitale",
    "sg:tags":[
        "\u00c0",
        "emporter",
        "restaurants"
    ],
    "wof:name":"Restaurant Touett & Geo",
    "wof:placetype":"venue"
},
  "geometry": {"coordinates":[4.3515839577,50.8492279053],"type":"Point"}
}