{
  "type": "Feature",
  "properties": {
    "iso:country":"BE",
    "sg:address":"Werf 4",
    "sg:city":"Aalst",
    "sg:classifiers":[
        {
            "category":"Professional",
            "subcategory":"Testing Lab",
            "type":"Services"
        }
    ],
    "sg:phone":"+32 53 21 16 22",
    "sg:postcode":"9300",
    "sg:province":"Oost-Vlaanderen",
    "sg:tags":[
        "chemist"
    ],
    "wof:name":"Van Nuffel M",
    "wof:placetype":"venue"
},
  "geometry": {"coordinates":[4.042347908,50.9403991699],"type":"Point"}
}