{
  "type": "Feature",
  "properties": {
    "addr:full":"Kortestraat 9 Zonhoven Limburg 3520",
    "addr:housenumber":"9",
    "addr:postcode":"3520",
    "addr:street":"Kortestraat",
    "iso:country":"BE",
    "sg:address":"Kortestraat 9",
    "sg:city":"Zonhoven",
    "sg:classifiers":[
        {
            "category":"Health Services",
            "subcategory":"Health Practitioner",
            "type":"Services"
        }
    ],
    "sg:phone":"+32 11 81 46 82",
    "sg:postcode":"3520",
    "sg:province":"Limburg",
    "sg:tags":[
        "physiotherapist"
    ],
    "wof:name":"Vanrijkel Greta",
    "wof:placetype":"venue"
},
  "geometry": {"coordinates":[5.3408889771,50.9932441711],"type":"Point"}
}