{
  "type": "Feature",
  "properties": {
    "iso:country":"BE",
    "sg:address":"Govaertstraat 8",
    "sg:city":"Beernem",
    "sg:orig_category":"Speelgoed, sport- and kampeermateriaal Gh",
    "sg:phone":"+32 50 78 06 52",
    "sg:postcode":"8730",
    "sg:province":"West-Vlaanderen",
    "wof:name":"Batico",
    "wof:placetype":"venue"
},
  "geometry": {"coordinates":[3.3364429474,51.1703643799],"type":"Point"}
}