{
  "type": "Feature",
  "properties": {
    "addr:full":"Sint-jorislaan 140 Herk-de-stad Limburg 3540",
    "addr:housenumber":"140",
    "addr:postcode":"3540",
    "addr:street":"Sint-Jorislaan",
    "iso:country":"BE",
    "sg:address":"Sint-jorislaan 140",
    "sg:city":"Herk-de-stad",
    "sg:orig_category":"D\u00e9molition d\u00b4immeubles and terrassements",
    "sg:phone":"+32 13 55 33 76",
    "sg:postcode":"3540",
    "sg:province":"Limburg",
    "wof:name":"Y Clerx",
    "wof:placetype":"venue"
},
  "geometry": {"coordinates":[5.1975469589,50.949432373],"type":"Point"}
}