{
  "type": "Feature",
  "properties": {
    "addr:full":"Beernemsteenweg 82 Wingene West-Vlaanderen 8750",
    "addr:housenumber":"82",
    "addr:postcode":"8750",
    "addr:street":"Beernemsteenweg",
    "iso:country":"BE",
    "sg:address":"Beernemsteenweg 82",
    "sg:city":"Wingene",
    "sg:orig_category":"Elektrische installaties voor woningen",
    "sg:phone":"+32 51 65 51 43",
    "sg:postcode":"8750",
    "sg:province":"West-Vlaanderen",
    "wof:name":"Prosper Mortier",
    "wof:placetype":"venue"
},
  "geometry": {"coordinates":[3.3103849888,51.0931396484],"type":"Point"}
}