{
  "type": "Feature",
  "properties": {
    "iso:country":"BE",
    "sg:address":"Simon Stevinstraat 53",
    "sg:city":"Kortrijk",
    "sg:orig_category":"Kapsalons",
    "sg:phone":"+32 56 35 30 59",
    "sg:postcode":"8500",
    "sg:province":"West-Vlaanderen",
    "wof:name":"Coiffure Ginette",
    "wof:placetype":"venue"
},
  "geometry": {"coordinates":[3.2660551071,50.8370056152],"type":"Point"}
}