{
  "type": "Feature",
  "properties": {
    "iso:country":"BE",
    "sg:address":"Prins Albertstraat 52",
    "sg:city":"Sint-niklaas",
    "sg:orig_category":"Fleurs and plantes",
    "sg:phone":"+32 3 765 06 16",
    "sg:postcode":"9100",
    "sg:province":"Oost-Vlaanderen",
    "wof:name":"Zenzi",
    "wof:placetype":"venue"
},
  "geometry": {"coordinates":[4.1443681717,51.1692428589],"type":"Point"}
}