{
  "type": "Feature",
  "properties": {
    "iso:country":"BE",
    "sg:address":"Route Du Condroz 470",
    "sg:city":"Li\u00e8ge 1 (angleur)",
    "sg:classifiers":[
        {
            "category":"Professional",
            "subcategory":"Computer Services",
            "type":"Services"
        }
    ],
    "sg:phone":"+32 4 361 00 95",
    "sg:postcode":"4031",
    "sg:province":"Li\u00e8ge",
    "sg:tags":[
        "-",
        "processing",
        "data",
        "software"
    ],
    "wof:name":"Skill Partners.com",
    "wof:placetype":"venue"
},
  "geometry": {"coordinates":[5.5725960732,50.593208313],"type":"Point"}
}