{
  "type": "Feature",
  "properties": {
    "addr:full":"Goor 23 Tessenderlo Limburg 3980",
    "addr:housenumber":"23",
    "addr:postcode":"3980",
    "addr:street":"Goor",
    "iso:country":"BE",
    "sg:address":"Goor 23",
    "sg:city":"Tessenderlo",
    "sg:classifiers":[
        {
            "category":"Recreation",
            "subcategory":"Amusement Park",
            "type":"Entertainment"
        }
    ],
    "sg:phone":"+32 13 31 32 93",
    "sg:postcode":"3980",
    "sg:province":"Limburg",
    "sg:tags":[
        "attraction",
        "-",
        "sale",
        "fair",
        "hiring"
    ],
    "wof:name":"The Way Out Bvba",
    "wof:placetype":"venue"
},
  "geometry": {"coordinates":[5.0875849724,51.0672340393],"type":"Point"}
}