{
  "type": "Feature",
  "properties": {
    "addr:full":"Alsembergse Steenweg 402 Ukkel/uccle Bruxelles-Capitale 1180",
    "addr:housenumber":"402",
    "addr:postcode":"1180",
    "addr:street":"Alsembergse Steenweg;/",
    "iso:country":"BE",
    "sg:address":"Alsembergse Steenweg 402",
    "sg:city":"Ukkel/uccle",
    "sg:orig_category":"Brood, gebak and snoepgoed",
    "sg:phone":"+32 2 344 06 59",
    "sg:postcode":"1180",
    "sg:province":"Bruxelles-Capitale",
    "wof:name":"Boulangerie Van Eeckhoudt",
    "wof:placetype":"venue"
},
  "geometry": {"coordinates":[4.3392148018,50.8137626648],"type":"Point"}
}