{
  "type": "Feature",
  "properties": {
    "iso:country":"BE",
    "sg:address":"Frederik Peltzerstraat 8",
    "sg:city":"Lier",
    "sg:classifiers":[
        {
            "category":"Taxi",
            "type":"Transportation"
        }
    ],
    "sg:phone":"+32 3 480 11 71",
    "sg:postcode":"2500",
    "sg:province":"Antwerpen",
    "sg:tags":[
        "taxicab"
    ],
    "wof:name":"Reno-tax",
    "wof:placetype":"venue"
},
  "geometry": {"coordinates":[4.5717577934,51.135383606],"type":"Point"}
}