{
  "type": "Feature",
  "properties": {
    "addr:full":"Bosdel 28 Genk Limburg 3600",
    "addr:housenumber":"28",
    "addr:postcode":"3600",
    "addr:street":"Bosdel",
    "iso:country":"BE",
    "sg:address":"Bosdel 28",
    "sg:city":"Genk",
    "sg:orig_category":"Quincailleries. Drogueries",
    "sg:phone":"+32 89 36 22 22",
    "sg:postcode":"3600",
    "sg:province":"Limburg",
    "wof:name":"Fa Lumaro Doe Het Zelf",
    "wof:placetype":"venue"
},
  "geometry": {"coordinates":[5.4895329475,50.9492263794],"type":"Point"}
}