{
  "type": "Feature",
  "properties": {
    "iso:country":"BE",
    "sg:address":"Dumonpl 6",
    "sg:city":"St-pieters-woluwe",
    "sg:classifiers":[
        {
            "category":"Bakery",
            "type":"Food & Drink"
        }
    ],
    "sg:phone":"+32 2 772 70 42",
    "sg:postcode":"1150",
    "sg:province":"Bruxelles-Capitale",
    "sg:tags":[
        "cake",
        "product",
        "related",
        "bread"
    ],
    "wof:name":"Ingelbrecht Bvba",
    "wof:placetype":"venue"
},
  "geometry": {"coordinates":[4.4644699097,50.8396911621],"type":"Point"}
}