{
  "type": "Feature",
  "properties": {
    "iso:country":"BE",
    "sg:address":"Elizabetlaan 26",
    "sg:city":"Knokke-heist (knokke)",
    "sg:classifiers":[
        {
            "category":"Professional",
            "subcategory":"Lawyer & Legal Services",
            "type":"Services"
        }
    ],
    "sg:phone":"+32 50 60 18 83",
    "sg:postcode":"8300",
    "sg:province":"West-Vlaanderen",
    "wof:name":"Cnudde P",
    "wof:placetype":"venue"
},
  "geometry": {"coordinates":[3.2957220078,51.3502159119],"type":"Point"}
}