{
  "type": "Feature",
  "properties": {
    "addr:full":"Molsekiezel 29 Lommel Limburg 3920",
    "addr:housenumber":"29",
    "addr:postcode":"3920",
    "addr:street":"Molsekiezel",
    "iso:country":"BE",
    "sg:address":"Molsekiezel 29",
    "sg:city":"Lommel",
    "sg:orig_category":"Plaatsen van vloer- and muurbekleding Schilders",
    "sg:phone":"+32 11 54 43 72",
    "sg:postcode":"3920",
    "sg:province":"Limburg",
    "wof:name":"Brusselaers",
    "wof:placetype":"venue"
},
  "geometry": {"coordinates":[5.3048372269,51.2314453125],"type":"Point"}
}