{
  "type": "Feature",
  "properties": {
    "addr:full":"Boulevard Joseph Tirou 76-82 Charleroi Hainaut 6000",
    "addr:housenumber":"76-82",
    "addr:postcode":"6000",
    "addr:street":"Boulevard Joseph Tirou;Hainaut",
    "iso:country":"BE",
    "sg:address":"Boulevard Joseph Tirou 76-82",
    "sg:city":"Charleroi",
    "sg:classifiers":[
        {
            "category":"Education",
            "subcategory":"School",
            "type":"Public Place"
        }
    ],
    "sg:phone":"+32 71 32 52 86",
    "sg:postcode":"6000",
    "sg:province":"Hainaut",
    "sg:tags":[
        "-",
        "private"
    ],
    "wof:name":"Ecoles Internationales Tagnon",
    "wof:placetype":"venue"
},
  "geometry": {"coordinates":[4.4434361458,50.4075431824],"type":"Point"}
}