{
  "type": "Feature",
  "properties": {
    "addr:full":"Rue Cloquet Braine-l\u00b4alleud Brabant Wallon 1420",
    "addr:postcode":"1420",
    "addr:street":"Rue Cloquet Braine-L\u00b4Alleud Brabant Wallon",
    "iso:country":"BE",
    "sg:address":"Rue Cloquet",
    "sg:city":"Braine-l\u00b4alleud",
    "sg:orig_category":"Royal Canin. Animaux domestiques and accessoires",
    "sg:phone":"+32 2 384 38 98",
    "sg:postcode":"1420",
    "sg:province":"Brabant Wallon",
    "wof:name":"Detournay",
    "wof:placetype":"venue"
},
  "geometry": {"coordinates":[4.3704710007,50.684223175],"type":"Point"}
}