{
  "type": "Feature",
  "properties": {
    "addr:full":"Rue De La Lys 154 Tournai Hainaut 7500",
    "addr:housenumber":"154",
    "addr:postcode":"7500",
    "addr:street":"Rue De La Lys",
    "iso:country":"BE",
    "sg:address":"Rue De La Lys 154",
    "sg:city":"Tournai",
    "sg:classifiers":[
        {
            "category":"Cafe",
            "type":"Food & Drink"
        }
    ],
    "sg:phone":"+32 69 22 83 89",
    "sg:postcode":"7500",
    "sg:province":"Hainaut",
    "sg:tags":[
        "caf\u00e9s"
    ],
    "wof:name":"Caf\u00c9 La Bruyere",
    "wof:placetype":"venue"
},
  "geometry": {"coordinates":[3.4122200012,50.5967102051],"type":"Point"}
}