{
  "type": "Feature",
  "properties": {
    "addr:full":"Molenstraat 38 Pepingen Vlaams-Brabant 1670",
    "addr:housenumber":"38",
    "addr:postcode":"1670",
    "addr:street":"Molenstraat",
    "iso:country":"BE",
    "sg:address":"Molenstraat 38",
    "sg:city":"Pepingen",
    "sg:orig_category":"Rundveehouders",
    "sg:phone":"+32 2 360 33 24",
    "sg:postcode":"1670",
    "sg:province":"Vlaams-Brabant",
    "wof:name":"Raymond Heremans",
    "wof:placetype":"venue"
},
  "geometry": {"coordinates":[4.1344242096,50.730304718],"type":"Point"}
}