{
  "type": "Feature",
  "properties": {
    "iso:country":"BE",
    "sg:address":"Avenue Van Volxem 14",
    "sg:city":"Bruxelles (forest)",
    "sg:classifiers":[
        {
            "category":"Food & Beverages",
            "subcategory":"Fruits & Vegetables",
            "type":"Retail Goods"
        }
    ],
    "sg:phone":"+32 2 349 08 49",
    "sg:postcode":"1190",
    "sg:province":"Bruxelles-Capitale",
    "sg:tags":[
        "oil",
        "-",
        "fat"
    ],
    "wof:name":"O-live Point Net Sprl",
    "wof:placetype":"venue"
},
  "geometry": {"coordinates":[4.324780941,50.8141441345],"type":"Point"}
}