{
  "type": "Feature",
  "properties": {
    "iso:country":"BE",
    "sg:address":"Kouterlosstraat 88",
    "sg:city":"Deinze (petegem-aan-de-leie)",
    "sg:classifiers":[
        {
            "category":"Government",
            "subcategory":"Post Office",
            "type":"Public Place"
        }
    ],
    "sg:phone":"+32 9 380 08 69",
    "sg:postcode":"9800",
    "sg:province":"Oost-Vlaanderen",
    "sg:tags":[
        "picture",
        "restoring"
    ],
    "wof:name":"Hallaert V",
    "wof:placetype":"venue"
},
  "geometry": {"coordinates":[3.530174017,50.9863166809],"type":"Point"}
}