{
  "type": "Feature",
  "properties": {
    "iso:country":"BE",
    "sg:address":"Kerkeweg 25",
    "sg:city":"Overijse",
    "sg:orig_category":"Agences de publicit\u00e9. Conception d'\u00e9talages and de showrooms",
    "sg:phone":"+32 2 687 56 10",
    "sg:postcode":"3090",
    "sg:province":"Vlaams-Brabant",
    "wof:name":"Reklame Denis",
    "wof:placetype":"venue"
},
  "geometry": {"coordinates":[4.5259690285,50.7597694397],"type":"Point"}
}