{
  "type": "Feature",
  "properties": {
    "addr:full":"Gilseinde 107 Ravels Antwerpen 2380",
    "addr:housenumber":"107",
    "addr:postcode":"2380",
    "addr:street":"Gilseinde",
    "iso:country":"BE",
    "sg:address":"Gilseinde 107",
    "sg:city":"Ravels",
    "sg:classifiers":[
        {
            "category":"Home & Garden",
            "subcategory":"Home Furnishings",
            "type":"Retail Goods"
        }
    ],
    "sg:phone":"+32 14 65 71 19",
    "sg:postcode":"2380",
    "sg:province":"Antwerpen",
    "sg:tags":[
        "decoration"
    ],
    "wof:name":"Stessens M",
    "wof:placetype":"venue"
},
  "geometry": {"coordinates":[5.0089659691,51.3720741272],"type":"Point"}
}