{
  "type": "Feature",
  "properties": {
    "addr:full":"Ch\u00c9e De La Lib\u00c9ration 66 Grez-doiceau Brabant Wallon 1390",
    "addr:housenumber":"66",
    "addr:postcode":"1390",
    "iso:country":"BE",
    "sg:address":"Ch\u00c9e De La Lib\u00c9ration 66",
    "sg:city":"Grez-doiceau",
    "sg:orig_category":"Dierenartsen",
    "sg:phone":"+32 10 84 43 98",
    "sg:postcode":"1390",
    "sg:province":"Brabant Wallon",
    "wof:name":"Oliver Jacqmot",
    "wof:placetype":"venue"
},
  "geometry": {"coordinates":[4.6870279312,50.7420310974],"type":"Point"}
}