{
  "type": "Feature",
  "properties": {
    "addr:full":"Rue D'heuval 23 Court-saint-etienne Brabant Wallon 1490",
    "addr:housenumber":"23;1490",
    "addr:street":"Rue D'Heuval",
    "iso:country":"BE",
    "sg:address":"Rue D'heuval 23",
    "sg:city":"Court-saint-etienne",
    "sg:orig_category":"Sportclubs",
    "sg:phone":"+32 10 61 49 23",
    "sg:postcode":"1490",
    "sg:province":"Brabant Wallon",
    "wof:name":"V.c. Stephanois",
    "wof:placetype":"venue"
},
  "geometry": {"coordinates":[4.5419120789,50.6097412109],"type":"Point"}
}