{
  "type": "Feature",
  "properties": {
    "iso:country":"BE",
    "sg:address":"Rue De Ciply 16",
    "sg:city":"Mons",
    "sg:orig_category":"V\u00e9t\u00e9rinaires",
    "sg:phone":"+32 65 31 43 31",
    "sg:postcode":"7033",
    "sg:province":"Hainaut",
    "wof:name":"G\u00c9nevi\u00c8ve Desaever",
    "wof:placetype":"venue"
},
  "geometry": {"coordinates":[3.9253261089,50.4366378784],"type":"Point"}
}