{
  "type": "Feature",
  "properties": {
    "addr:full":"Coppensstraat 14 Brussel/bruxelles Bruxelles-Capitale 1000",
    "addr:housenumber":"14",
    "addr:postcode":"1000",
    "addr:street":"Coppensstraat;/",
    "iso:country":"BE",
    "sg:address":"Coppensstraat 14",
    "sg:city":"Brussel/bruxelles",
    "sg:orig_category":"Diverse zakelijke dienstverlening",
    "sg:phone":"+32 2 502 48 88",
    "sg:postcode":"1000",
    "sg:province":"Bruxelles-Capitale",
    "wof:name":"Bernard Cats",
    "wof:placetype":"venue"
},
  "geometry": {"coordinates":[4.3550319672,50.8396492004],"type":"Point"}
}