{
  "type": "Feature",
  "properties": {
    "iso:country":"BE",
    "sg:address":"Klinkaardstraat 10",
    "sg:city":"Harelbeke",
    "sg:classifiers":[
        {
            "category":"Manufacturing",
            "subcategory":"Textiles",
            "type":"Manufacturing & Wholesale Goods"
        }
    ],
    "sg:phone":"+32 56 20 31 93",
    "sg:postcode":"8530",
    "sg:province":"West-Vlaanderen",
    "sg:tags":[
        "technical"
    ],
    "wof:name":"Mitex",
    "wof:placetype":"venue"
},
  "geometry": {"coordinates":[3.3158559799,50.8285331726],"type":"Point"}
}