{
  "type": "Feature",
  "properties": {
    "iso:country":"BE",
    "sg:address":"Thiewinkelstraat 3",
    "sg:city":"Lummen",
    "sg:classifiers":[
        {
            "category":"Personal",
            "subcategory":"Beauty Salon",
            "type":"Services"
        }
    ],
    "sg:phone":"+32 13 52 17 53",
    "sg:postcode":"3560",
    "sg:province":"Limburg",
    "sg:tags":[
        "lady",
        "-",
        "hairdressing"
    ],
    "wof:name":"Linea",
    "wof:placetype":"venue"
},
  "geometry": {"coordinates":[5.2047319412,50.9825820923],"type":"Point"}
}