{
  "type": "Feature",
  "properties": {
    "iso:country":"BE",
    "sg:address":"Chauss\u00c9e De Bruxelles 195",
    "sg:city":"Waterloo",
    "sg:orig_category":"Postkantoren Verzekeringsmakelaars and experts",
    "sg:phone":"+32 2 354 76 60",
    "sg:postcode":"1410",
    "sg:province":"Brabant Wallon",
    "wof:name":"La Poste",
    "wof:placetype":"venue"
},
  "geometry": {"coordinates":[4.3986721039,50.7160491943],"type":"Point"}
}