{
  "type": "Feature",
  "properties": {
    "addr:full":"440 Edingseweg 9500 Geraardsbergen 440",
    "addr:housenumber":"440",
    "addr:postcode":"9500;440",
    "addr:street":"Edingseweg",
    "iso:country":"BE",
    "sg:address":"440",
    "sg:city":"Edingseweg 9500 Geraardsbergen",
    "sg:classifiers":[
        {
            "category":"Travel",
            "subcategory":"Hotels & Motels",
            "type":"Entertainment"
        }
    ],
    "sg:phone":"+32 54 58 83 80",
    "sg:postcode":"440",
    "sg:tags":[
        "hotels",
        "business",
        "restaurant"
    ],
    "wof:name":"Amhovia - Horeca & Amusement Bvba",
    "wof:placetype":"venue"
},
  "geometry": {"coordinates":[3.8957829475,50.7710800171],"type":"Point"}
}