{
  "type": "Feature",
  "properties": {
    "addr:full":"Wulpendammestraat 162 Veurne West-Vlaanderen 8630",
    "addr:housenumber":"162",
    "addr:postcode":"8630",
    "addr:street":"Wulpendammestraat",
    "iso:country":"BE",
    "sg:address":"Wulpendammestraat 162",
    "sg:city":"Veurne",
    "sg:classifiers":[
        {
            "category":"Arena",
            "subcategory":"Sports Club",
            "type":"Entertainment"
        }
    ],
    "sg:phone":"+32 58 31 59 25",
    "sg:postcode":"8630",
    "sg:province":"West-Vlaanderen",
    "sg:tags":[
        "de"
    ],
    "wof:name":"Kbc Bac Fortuintje Veurne",
    "wof:placetype":"venue"
},
  "geometry": {"coordinates":[2.6790750027,51.0791969299],"type":"Point"}
}