{
  "type": "Feature",
  "properties": {
    "addr:full":"Bosni\u00cbstraat 47 Sint-gillis/saint-gilles Bruxelles-Capitale 1060",
    "addr:housenumber":"47",
    "addr:postcode":"1060",
    "addr:street":"Bosnie\u0308Straat",
    "iso:country":"BE",
    "sg:address":"Bosni\u00cbstraat 47",
    "sg:city":"Sint-gillis/saint-gilles",
    "sg:orig_category":"Advocaten and juridische adviseurs",
    "sg:phone":"+32 2 538 99 84",
    "sg:postcode":"1060",
    "sg:province":"Bruxelles-Capitale",
    "wof:name":"Ndolao Luzeyemo",
    "wof:placetype":"venue"
},
  "geometry": {"coordinates":[4.3358111382,50.8283538818],"type":"Point"}
}