{
  "type": "Feature",
  "properties": {
    "addr:full":"Rue Albert I 17 Bernissart (blaton) Hainaut 7321",
    "addr:housenumber":"17",
    "addr:postcode":"7321",
    "addr:street":"Rue Albert I",
    "iso:country":"BE",
    "sg:address":"Rue Albert I 17",
    "sg:city":"Bernissart (blaton)",
    "sg:classifiers":[
        {
            "category":"Professional",
            "subcategory":"Testing Lab",
            "type":"Services"
        }
    ],
    "sg:phone":"+32 69 58 00 00",
    "sg:postcode":"7321",
    "sg:province":"Hainaut",
    "sg:tags":[
        "chemist"
    ],
    "wof:name":"Laurent Cl",
    "wof:placetype":"venue"
},
  "geometry": {"coordinates":[3.691546917,50.4778747559],"type":"Point"}
}