{
  "type": "Feature",
  "properties": {
    "iso:country":"BE",
    "sg:address":"Tuinweg 5ba",
    "sg:city":"Bilzen",
    "sg:orig_category":"Fruitteelt",
    "sg:phone":"+32 89 41 70 94",
    "sg:postcode":"3740",
    "sg:province":"Limburg",
    "wof:name":"Patrick Gerits",
    "wof:placetype":"venue"
},
  "geometry": {"coordinates":[5.5120549202,50.8818664551],"type":"Point"}
}