{
  "type": "Feature",
  "properties": {
    "addr:full":"Rue Des Trois Ponts 33 Auderghem Bruxelles-Capitale 1160",
    "addr:housenumber":"33",
    "addr:postcode":"1160",
    "addr:street":"Rue Des Trois Ponts",
    "iso:country":"BE",
    "sg:address":"Rue Des Trois Ponts 33",
    "sg:city":"Auderghem",
    "sg:orig_category":"Sportterreinen and installaties behalve sportcentra",
    "sg:phone":"+32 2 675 42 86",
    "sg:postcode":"1160",
    "sg:province":"Bruxelles-Capitale",
    "wof:name":"Accompagnateur De L'ardenne",
    "wof:placetype":"venue"
},
  "geometry": {"coordinates":[4.4075279236,50.8207550049],"type":"Point"}
}