{
  "type": "Feature",
  "properties": {
    "addr:full":"Zikastraat 39 Geraardsbergen (moerbeke) Oost-Vlaanderen 9500",
    "addr:housenumber":"39",
    "addr:postcode":"9500",
    "addr:street":"Zikastraat",
    "iso:country":"BE",
    "sg:address":"Zikastraat 39",
    "sg:city":"Geraardsbergen (moerbeke)",
    "sg:classifiers":[
        {
            "category":"Building & Trades",
            "subcategory":"Construction",
            "type":"Services"
        }
    ],
    "sg:phone":"+32 54 41 55 67",
    "sg:postcode":"9500",
    "sg:province":"Oost-Vlaanderen",
    "sg:tags":[
        "installation",
        "-",
        "central",
        "heating"
    ],
    "wof:name":"De Roeck-vandenabeele Bvba",
    "wof:placetype":"venue"
},
  "geometry": {"coordinates":[3.9138300419,50.7536392212],"type":"Point"}
}