{
  "type": "Feature",
  "properties": {
    "addr:full":"Rue Pierre Fanchamps 34 Verviers Li\u00e8ge 4800",
    "addr:housenumber":"34",
    "addr:postcode":"4800",
    "addr:street":"Rue Pierre Fanchamps",
    "iso:country":"BE",
    "sg:address":"Rue Pierre Fanchamps 34",
    "sg:city":"Verviers",
    "sg:classifiers":[
        {
            "category":"Food & Beverages",
            "subcategory":"Fruits & Vegetables",
            "type":"Retail Goods"
        }
    ],
    "sg:phone":"+32 87 33 85 91",
    "sg:postcode":"4800",
    "sg:province":"Li\u00e8ge",
    "sg:tags":[
        "groenten"
    ],
    "wof:name":"Cordonnier Rene & Jean",
    "wof:placetype":"venue"
},
  "geometry": {"coordinates":[5.8474111557,50.5962333679],"type":"Point"}
}