{
  "type": "Feature",
  "properties": {
    "addr:full":"Rue De Mallais 57 Gedinne Namur 5575",
    "addr:housenumber":"57",
    "addr:postcode":"5575",
    "addr:street":"Rue De Mallais",
    "iso:country":"BE",
    "sg:address":"Rue De Mallais 57",
    "sg:city":"Gedinne",
    "sg:orig_category":"Eleveurs de bovins",
    "sg:phone":"+32 61 58 95 65",
    "sg:postcode":"5575",
    "sg:province":"Namur",
    "wof:name":"Marcellin Demars",
    "wof:placetype":"venue"
},
  "geometry": {"coordinates":[4.8607201576,50.0237197876],"type":"Point"}
}