{
  "type": "Feature",
  "properties": {
    "addr:full":"Hoogstraat 26 Meeuwen-gruitrode Limburg 3670",
    "addr:housenumber":"26",
    "addr:postcode":"3670",
    "addr:street":"Hoogstraat",
    "iso:country":"BE",
    "sg:address":"Hoogstraat 26",
    "sg:city":"Meeuwen-gruitrode",
    "sg:classifiers":[
        {
            "category":"Food & Beverages",
            "subcategory":"Fruits & Vegetables",
            "type":"Retail Goods"
        }
    ],
    "sg:phone":"+32 11 79 27 27",
    "sg:postcode":"3670",
    "sg:province":"Limburg",
    "sg:tags":[
        "groenten"
    ],
    "wof:name":"Huis Vitamientje",
    "wof:placetype":"venue"
},
  "geometry": {"coordinates":[5.5220470428,51.0944976807],"type":"Point"}
}