{
  "type": "Feature",
  "properties": {
    "addr:full":"Rue Du Limbourg Mouscron Hainaut 7700",
    "addr:postcode":"7700",
    "addr:street":"Rue Du Limbourg;Hainaut",
    "iso:country":"BE",
    "sg:address":"Rue Du Limbourg",
    "sg:city":"Mouscron",
    "sg:classifiers":[
        {
            "category":"Manufacturing",
            "subcategory":"Textiles",
            "type":"Manufacturing & Wholesale Goods"
        }
    ],
    "sg:phone":"+32 56 33 39 82",
    "sg:postcode":"7700",
    "sg:province":"Hainaut",
    "sg:tags":[
        "linen",
        "clothing",
        "fabric"
    ],
    "wof:name":"Vernier Andre Et Fils Sa",
    "wof:placetype":"venue"
},
  "geometry": {"coordinates":[3.2216119766,50.7364311218],"type":"Point"}
}