{
  "type": "Feature",
  "properties": {
    "addr:full":"Voorheide 65 Wetteren Oost-Vlaanderen 9230",
    "addr:housenumber":"65",
    "addr:postcode":"9230",
    "addr:street":"Voorheide",
    "iso:country":"BE",
    "sg:address":"Voorheide 65",
    "sg:city":"Wetteren",
    "sg:orig_category":"Diverse persoonlijke diensten Taxi's speciale diensten Voertuigen",
    "sg:phone":"+32 9 369 31 14",
    "sg:postcode":"9230",
    "sg:province":"Oost-Vlaanderen",
    "wof:name":"Gentiel Wierinck",
    "wof:placetype":"venue"
},
  "geometry": {"coordinates":[3.8514900208,50.9844474792],"type":"Point"}
}