{
  "type": "Feature",
  "properties": {
    "iso:country":"BE",
    "sg:address":"Amandus - De - Vosstraat 4",
    "sg:city":"Geel",
    "sg:classifiers":[
        {
            "category":"Health Services",
            "subcategory":"Doctor",
            "type":"Services"
        }
    ],
    "sg:phone":"+32 14 58 66 06",
    "sg:postcode":"2440",
    "sg:province":"Antwerpen",
    "sg:tags":[
        "medicinephysicians",
        "surgeon"
    ],
    "wof:name":"Heyns P",
    "wof:placetype":"venue"
},
  "geometry": {"coordinates":[4.9998898506,51.163848877],"type":"Point"}
}