{
  "type": "Feature",
  "properties": {
    "iso:country":"BE",
    "sg:address":"Dorpskring 13 Bus 1",
    "sg:city":"Lubbeek",
    "sg:orig_category":"Foto-uitrusting Fotografen and fotostudio's",
    "sg:phone":"+32 16 63 30 22",
    "sg:postcode":"3210",
    "sg:province":"Vlaams-Brabant",
    "wof:name":"Foto Paul Turcksin",
    "wof:placetype":"venue"
},
  "geometry": {"coordinates":[4.841574192,50.8818435669],"type":"Point"}
}