{
  "type": "Feature",
  "properties": {
    "iso:country":"BE",
    "sg:address":"Rue Crocq 48",
    "sg:city":"Bruxelles (woluwe-saint-lambert)",
    "sg:classifiers":[
        {
            "category":"Health Services",
            "subcategory":"Doctor",
            "type":"Services"
        }
    ],
    "sg:phone":"+32 2 772 90 78",
    "sg:postcode":"1200",
    "sg:province":"Bruxelles-Capitale",
    "sg:tags":[
        "medicinephysicians",
        "surgeon"
    ],
    "wof:name":"Brumagne A",
    "wof:placetype":"venue"
},
  "geometry": {"coordinates":[4.422399044,50.8467216492],"type":"Point"}
}