{
  "type": "Feature",
  "properties": {
    "addr:full":"Sionkloosterlaan 56 Brasschaat Antwerpen 2930",
    "addr:housenumber":"56",
    "addr:postcode":"2930",
    "addr:street":"Sionkloosterlaan",
    "iso:country":"BE",
    "sg:address":"Sionkloosterlaan 56",
    "sg:city":"Brasschaat",
    "sg:classifiers":[
        {
            "category":"Sports & Exercise",
            "subcategory":"Stables",
            "type":"Entertainment"
        }
    ],
    "sg:phone":"+32 3 633 22 16",
    "sg:postcode":"2930",
    "sg:province":"Antwerpen",
    "sg:tags":[
        "riding",
        "school"
    ],
    "wof:name":"Romanshoeve Bvba",
    "wof:placetype":"venue"
},
  "geometry": {"coordinates":[4.4951868057,51.3269920349],"type":"Point"}
}