{
  "type": "Feature",
  "properties": {
    "iso:country":"BE",
    "sg:address":"Route D'arville 6",
    "sg:city":"Saint-hubert (arville)",
    "sg:classifiers":[
        {
            "category":"Health Services",
            "subcategory":"Health Practitioner",
            "type":"Services"
        }
    ],
    "sg:phone":"+32 61 61 24 12",
    "sg:postcode":"6870",
    "sg:province":"Luxembourg",
    "sg:tags":[
        "therapist",
        "speech"
    ],
    "wof:name":"Guerisse M",
    "wof:placetype":"venue"
},
  "geometry": {"coordinates":[5.3418259621,50.029209137],"type":"Point"}
}