{
  "type": "Feature",
  "properties": {
    "addr:full":"Pijphoekstraat 60 Gent Oost-Vlaanderen 9041",
    "addr:housenumber":"60",
    "addr:postcode":"9041",
    "addr:street":"Pijphoekstraat;Oost-Vlaanderen",
    "iso:country":"BE",
    "sg:address":"Pijphoekstraat 60",
    "sg:city":"Gent",
    "sg:orig_category":"Pain, p\u00e2tisseries and confiseries",
    "sg:phone":"+32 9 251 06 72",
    "sg:postcode":"9041",
    "sg:province":"Oost-Vlaanderen",
    "wof:name":"Roland Lamont",
    "wof:placetype":"venue"
},
  "geometry": {"coordinates":[3.7621090412,51.1011009216],"type":"Point"}
}