{
  "type": "Feature",
  "properties": {
    "addr:full":"Landegemstraat 35 Zingem Oost-Vlaanderen 9750",
    "addr:housenumber":"35",
    "addr:postcode":"9750",
    "addr:street":"Landegemstraat",
    "iso:country":"BE",
    "sg:address":"Landegemstraat 35",
    "sg:city":"Zingem",
    "sg:orig_category":"Banques and organismes de cr\u00e9dit",
    "sg:phone":"+32 9 384 73 82",
    "sg:postcode":"9750",
    "sg:province":"Oost-Vlaanderen",
    "wof:name":"Citibank",
    "wof:placetype":"venue"
},
  "geometry": {"coordinates":[3.6519870758,50.9060554504],"type":"Point"}
}