{
  "type": "Feature",
  "properties": {
    "addr:full":"Waterlelielaan 16 Oostende (stene) West-Vlaanderen 8400",
    "addr:housenumber":"16",
    "addr:postcode":"8400",
    "addr:street":"Waterlelielaan",
    "iso:country":"BE",
    "sg:address":"Waterlelielaan 16",
    "sg:city":"Oostende (stene)",
    "sg:classifiers":[
        {
            "category":"Health Services",
            "subcategory":"Health Practitioner",
            "type":"Services"
        }
    ],
    "sg:phone":"+32 59 50 68 58",
    "sg:postcode":"8400",
    "sg:province":"West-Vlaanderen",
    "sg:tags":[
        "physiotherapist"
    ],
    "wof:name":"Declerck Martine",
    "wof:placetype":"venue"
},
  "geometry": {"coordinates":[2.9126999378,51.2312583923],"type":"Point"}
}