{
  "type": "Feature",
  "properties": {
    "addr:full":"Kl\u00f6cknerstraat 1 Hamont-achel (hamont) Limburg 3930",
    "addr:housenumber":"1",
    "addr:postcode":"3930",
    "addr:street":"Kloecknerstraat",
    "iso:country":"BE",
    "sg:address":"Kl\u00f6cknerstraat 1",
    "sg:city":"Hamont-achel (hamont)",
    "sg:classifiers":[
        {
            "category":"Professional",
            "type":"Services"
        }
    ],
    "sg:phone":"+32 11 44 01 11",
    "sg:postcode":"3930",
    "sg:province":"Limburg",
    "sg:tags":[
        "packing",
        "-"
    ],
    "wof:name":"Budelpack Hamont Nv",
    "wof:placetype":"venue"
},
  "geometry": {"coordinates":[5.5450549126,51.2511863708],"type":"Point"}
}