{
  "type": "Feature",
  "properties": {
    "addr:full":"Overwinningsstraat 87 Willebroek Antwerpen 2830",
    "addr:housenumber":"87",
    "addr:postcode":"2830",
    "addr:street":"Overwinningsstraat",
    "iso:country":"BE",
    "sg:address":"Overwinningsstraat 87",
    "sg:city":"Willebroek",
    "sg:orig_category":"Banques and organismes de cr\u00e9dit",
    "sg:phone":"+32 3 886 43 39",
    "sg:postcode":"2830",
    "sg:province":"Antwerpen",
    "wof:name":"De Vaderlandsche",
    "wof:placetype":"venue"
},
  "geometry": {"coordinates":[4.3597297668,51.0587806702],"type":"Point"}
}