{
  "type": "Feature",
  "properties": {
    "addr:full":"Chauss\u00c9e De Lodelinsart 56 Charleroi Hainaut 6060",
    "addr:housenumber":"56",
    "addr:postcode":"6060",
    "addr:street":"Chausse\u0301E De Lodelinsart;Hainaut",
    "iso:country":"BE",
    "sg:address":"Chauss\u00c9e De Lodelinsart 56",
    "sg:city":"Charleroi",
    "sg:orig_category":"Banken and kredietinstellingen",
    "sg:phone":"+32 71 41 12 96",
    "sg:postcode":"6060",
    "sg:province":"Hainaut",
    "wof:name":"Citibank",
    "wof:placetype":"venue"
},
  "geometry": {"coordinates":[4.4497418404,50.4203147888],"type":"Point"}
}