{
  "type": "Feature",
  "properties": {
    "iso:country":"BE",
    "sg:address":"Nijverheidsstraat 12",
    "sg:city":"Waarschoot",
    "sg:orig_category":"Decoratieve kunst and kunstbenodigdheden Foto-uitrusting Fotografen and fotostudio's",
    "sg:phone":"+32 9 378 04 65",
    "sg:postcode":"9950",
    "sg:province":"Oost-Vlaanderen",
    "wof:name":"Foto Rudesign",
    "wof:placetype":"venue"
},
  "geometry": {"coordinates":[3.6048409939,51.1532745361],"type":"Point"}
}