{
  "type": "Feature",
  "properties": {
    "addr:full":"Attenhovenstraat 105 Landen Vlaams-Brabant 3404",
    "addr:housenumber":"105",
    "addr:postcode":"3404",
    "addr:street":"Attenhovenstraat",
    "iso:country":"BE",
    "sg:address":"Attenhovenstraat 105",
    "sg:city":"Landen",
    "sg:orig_category":"Producteurs de fruits",
    "sg:phone":"+32 11 88 57 36",
    "sg:postcode":"3404",
    "sg:province":"Vlaams-Brabant",
    "wof:name":"Gunther Leonard",
    "wof:placetype":"venue"
},
  "geometry": {"coordinates":[5.0856571198,50.7597732544],"type":"Point"}
}