{
  "type": "Feature",
  "properties": {
    "iso:country":"BE",
    "sg:address":"Rue Du Progr\u00c8s 84bb",
    "sg:city":"Schaarbeek/schaerbeek",
    "sg:orig_category":"Boucheries",
    "sg:phone":"+32 2 203 14 62",
    "sg:postcode":"1030",
    "sg:province":"Bruxelles-Capitale",
    "wof:name":"Boucherie Alpeva",
    "wof:placetype":"venue"
},
  "geometry": {"coordinates":[4.3601899147,50.8618812561],"type":"Point"}
}