{
  "type": "Feature",
  "properties": {
    "addr:full":"Rue Des Cottages 82 Bruxelles (uccle) Bruxelles-Capitale 1180",
    "addr:housenumber":"82",
    "addr:postcode":"1180",
    "addr:street":"Rue Des Cottages",
    "iso:country":"BE",
    "sg:address":"Rue Des Cottages 82",
    "sg:city":"Bruxelles (uccle)",
    "sg:classifiers":[
        {
            "category":"Travel",
            "subcategory":"Travel Agent",
            "type":"Entertainment"
        }
    ],
    "sg:phone":"+32 2 343 40 00",
    "sg:postcode":"1180",
    "sg:province":"Bruxelles-Capitale",
    "sg:tags":[
        "agency"
    ],
    "wof:name":"Kx International Sprl",
    "wof:placetype":"venue"
},
  "geometry": {"coordinates":[4.3424320221,50.8117218018],"type":"Point"}
}