{
  "type": "Feature",
  "properties": {
    "addr:full":"Diestsesteenweg 72 Kessel-lo Vlaams-Brabant 3010",
    "addr:housenumber":"72",
    "addr:postcode":"3010",
    "addr:street":"Diestsesteenweg",
    "iso:country":"BE",
    "sg:address":"Diestsesteenweg 72",
    "sg:city":"Kessel-lo",
    "sg:orig_category":"Verhuur televisie- and audiovisuele apparatuur",
    "sg:phone":"+32 16 26 03 01",
    "sg:postcode":"3010",
    "sg:province":"Vlaams-Brabant",
    "wof:name":"R.p.a.",
    "wof:placetype":"venue"
},
  "geometry": {"coordinates":[4.7188038826,50.8835411072],"type":"Point"}
}