{
  "type": "Feature",
  "properties": {
    "addr:full":"Av Andr\u00e9 Ernst Petit-rechain Li\u00e8ge 4800",
    "addr:postcode":"4800",
    "addr:street":"Av Andre\u0301 Ernst",
    "iso:country":"BE",
    "sg:address":"Av Andr\u00e9 Ernst",
    "sg:city":"Petit-rechain",
    "sg:classifiers":[
        {
            "category":"Wholesale",
            "subcategory":"Medical Equipment & Supplies",
            "type":"Manufacturing & Wholesale Goods"
        }
    ],
    "sg:phone":"+32 87 31 02 51",
    "sg:postcode":"4800",
    "sg:province":"Li\u00e8ge",
    "sg:tags":[
        "instrument",
        "health",
        "-",
        "precision"
    ],
    "wof:name":"Tw Electronic Sa",
    "wof:placetype":"venue"
},
  "geometry": {"coordinates":[5.8313059807,50.623500824],"type":"Point"}
}