{
  "type": "Feature",
  "properties": {
    "iso:country":"BE",
    "sg:address":"Bld Jean-th\u00c9odore Radoux 47",
    "sg:city":"Li\u00c8ge",
    "sg:classifiers":[
        {
            "category":"Arena",
            "subcategory":"Sports Club",
            "type":"Entertainment"
        }
    ],
    "sg:phone":"+32 4 252 61 87",
    "sg:postcode":"4000",
    "sg:province":"Li\u00e8ge",
    "sg:tags":[
        "de"
    ],
    "wof:name":"Ju Jitsu Club Bushido",
    "wof:placetype":"venue"
},
  "geometry": {"coordinates":[5.5547032356,50.652797699],"type":"Point"}
}