{
  "type": "Feature",
  "properties": {
    "addr:full":"Rue De La Jolie Cense 17 Manage Hainaut 7170",
    "addr:housenumber":"17",
    "addr:postcode":"7170",
    "addr:street":"Rue De La Jolie Cense",
    "iso:country":"BE",
    "sg:address":"Rue De La Jolie Cense 17",
    "sg:city":"Manage",
    "sg:orig_category":"Eleveurs de bovins",
    "sg:phone":"+32 64 22 18 46",
    "sg:postcode":"7170",
    "sg:province":"Hainaut",
    "wof:name":"Hugo Vermeulen",
    "wof:placetype":"venue"
},
  "geometry": {"coordinates":[4.2327899933,50.5008239746],"type":"Point"}
}