{
  "type": "Feature",
  "properties": {
    "iso:country":"BE",
    "sg:address":"Markt 34",
    "sg:city":"Oudenaarde",
    "sg:orig_category":"V\u00eatements pour Hommes",
    "sg:phone":"+32 55 31 10 23",
    "sg:postcode":"9700",
    "sg:province":"Oost-Vlaanderen",
    "wof:name":"Andre Vanwambeke",
    "wof:placetype":"venue"
},
  "geometry": {"coordinates":[3.604172945,50.8425827026],"type":"Point"}
}