{
  "type": "Feature",
  "properties": {
    "addr:full":"Rue Albert I 39 Hannut Li\u00e8ge 4280",
    "addr:housenumber":"39",
    "addr:postcode":"4280",
    "addr:street":"Rue Albert I",
    "iso:country":"BE",
    "sg:address":"Rue Albert I 39",
    "sg:city":"Hannut",
    "sg:classifiers":[
        {
            "category":"Shopping",
            "subcategory":"Bridal",
            "type":"Retail Goods"
        }
    ],
    "sg:phone":"+32 19 51 51 21",
    "sg:postcode":"4280",
    "sg:province":"Li\u00e8ge",
    "sg:tags":[
        "list",
        "-",
        "present",
        "wedding"
    ],
    "wof:name":"Tendance Miel",
    "wof:placetype":"venue"
},
  "geometry": {"coordinates":[5.0809698105,50.6702308655],"type":"Point"}
}