{
  "type": "Feature",
  "properties": {
    "addr:full":"Avenue Des Cerisiers 10 Bruxelles (schaerbeek) Bruxelles-Capitale 1030",
    "addr:housenumber":"10",
    "addr:postcode":"1030",
    "addr:street":"Avenue Des Cerisiers",
    "iso:country":"BE",
    "sg:address":"Avenue Des Cerisiers 10",
    "sg:city":"Bruxelles (schaerbeek)",
    "sg:classifiers":[
        {
            "category":"Health Services",
            "subcategory":"Health Practitioner",
            "type":"Services"
        }
    ],
    "sg:phone":"+32 2 734 16 88",
    "sg:postcode":"1030",
    "sg:province":"Bruxelles-Capitale",
    "sg:tags":[
        "physiotherapist"
    ],
    "wof:name":"Ectors Viviane",
    "wof:placetype":"venue"
},
  "geometry": {"coordinates":[4.4037427902,50.8489074707],"type":"Point"}
}