{
  "type": "Feature",
  "properties": {
    "addr:full":"Trieststraat 126 Assenede Oost-Vlaanderen 9960",
    "addr:housenumber":"126",
    "addr:postcode":"9960",
    "addr:street":"Trieststraat",
    "iso:country":"BE",
    "sg:address":"Trieststraat 126",
    "sg:city":"Assenede",
    "sg:orig_category":"Rundveehouders",
    "sg:phone":"+32 9 344 52 15",
    "sg:postcode":"9960",
    "sg:province":"Oost-Vlaanderen",
    "wof:name":"Remi De Weweire",
    "wof:placetype":"venue"
},
  "geometry": {"coordinates":[3.7622790337,51.210395813],"type":"Point"}
}