{
  "type": "Feature",
  "properties": {
    "iso:country":"BE",
    "sg:address":"Eug\u00c8ne Keymplein 18",
    "sg:city":"Watermaal-bosvoorde/watermael-boitsfort",
    "sg:orig_category":"Artsen and specialisten",
    "sg:phone":"+32 2 673 08 88",
    "sg:postcode":"1170",
    "sg:province":"Bruxelles-Capitale",
    "wof:name":"Jean Simon",
    "wof:placetype":"venue"
},
  "geometry": {"coordinates":[4.4034690857,50.8091430664],"type":"Point"}
}