{
  "type": "Feature",
  "properties": {
    "addr:full":"Brugse Heirweg 70 Stekene Oost-Vlaanderen 9190",
    "addr:housenumber":"70",
    "addr:postcode":"9190",
    "addr:street":"Brugse Heirweg",
    "iso:country":"BE",
    "sg:address":"Brugse Heirweg 70",
    "sg:city":"Stekene",
    "sg:orig_category":"Pain, p\u00e2tisseries and confiseries",
    "sg:phone":"+32 9 346 83 56",
    "sg:postcode":"9190",
    "sg:province":"Oost-Vlaanderen",
    "wof:name":"Hubert Van Goethem",
    "wof:placetype":"venue"
},
  "geometry": {"coordinates":[4.016658783,51.1892166138],"type":"Point"}
}