{
  "type": "Feature",
  "properties": {
    "iso:country":"BE",
    "sg:address":"Rue Emile Vandervelde 15",
    "sg:city":"Le Roeulx",
    "sg:orig_category":"Banques and organismes de cr\u00e9dit",
    "sg:phone":"+32 64 67 92 00",
    "sg:postcode":"7070",
    "sg:province":"Hainaut",
    "wof:name":"Dexia",
    "wof:placetype":"venue"
},
  "geometry": {"coordinates":[4.1093029976,50.5033836365],"type":"Point"}
}