{
  "type": "Feature",
  "properties": {
    "addr:full":"Z.i.-al Centrale Charleroi Hainaut 6040",
    "addr:postcode":"6040",
    "addr:street":"Hainaut",
    "iso:country":"BE",
    "sg:address":"Z.i.-al Centrale",
    "sg:city":"Charleroi",
    "sg:orig_category":"Mat\u00e9riel \u00e9lectrique and \u00e9lectronique Gr",
    "sg:phone":"+32 71 34 31 31",
    "sg:postcode":"6040",
    "sg:province":"Hainaut",
    "wof:name":"Bernard Emco",
    "wof:placetype":"venue"
},
  "geometry": {"coordinates":[4.4558048248,50.4553108215],"type":"Point"}
}