{
  "type": "Feature",
  "properties": {
    "iso:country":"BE",
    "sg:address":"Grand Rue 96",
    "sg:city":"Pecq (obigies)",
    "sg:classifiers":[
        {
            "category":"Real Estate",
            "subcategory":"Surveying",
            "type":"Services"
        }
    ],
    "sg:phone":"+32 69 55 70 24",
    "sg:postcode":"7743",
    "sg:province":"Hainaut",
    "sg:tags":[
        "surveyor",
        "land"
    ],
    "wof:name":"Daelman C",
    "wof:placetype":"venue"
},
  "geometry": {"coordinates":[3.3640060425,50.6596755981],"type":"Point"}
}