{
  "type": "Feature",
  "properties": {
    "addr:full":"Brielstraat 29 Berlare Oost-Vlaanderen 9290",
    "addr:housenumber":"29",
    "addr:postcode":"9290",
    "addr:street":"Brielstraat",
    "iso:country":"BE",
    "sg:address":"Brielstraat 29",
    "sg:city":"Berlare",
    "sg:orig_category":"Kampeerterreinen",
    "sg:phone":"+32 9 367 99 29",
    "sg:postcode":"9290",
    "sg:province":"Oost-Vlaanderen",
    "wof:name":"De Donkere Wolke",
    "wof:placetype":"venue"
},
  "geometry": {"coordinates":[4.005710125,51.0165214539],"type":"Point"}
}