{
  "type": "Feature",
  "properties": {
    "iso:country":"BE",
    "sg:address":"Grand-place 4",
    "sg:city":"Neufch\u00c2teau",
    "sg:classifiers":[
        {
            "category":"Government",
            "subcategory":"Police Station",
            "type":"Public Place"
        }
    ],
    "sg:phone":"+32 61 27 81 55",
    "sg:postcode":"6840",
    "sg:province":"Luxembourg",
    "sg:tags":[
        "gendarmerie"
    ],
    "wof:name":"Police F\u00c9d\u00c9rale/federale Politie",
    "wof:placetype":"venue"
},
  "geometry": {"coordinates":[5.4360499382,49.8405380249],"type":"Point"}
}