{
  "type": "Feature",
  "properties": {
    "addr:full":"Legrandlaan 86 Elsene/ixelles Bruxelles-Capitale 1180",
    "addr:housenumber":"86",
    "addr:postcode":"1180",
    "addr:street":"Legrandlaan",
    "iso:country":"BE",
    "sg:address":"Legrandlaan 86",
    "sg:city":"Elsene/ixelles",
    "sg:orig_category":"Kapsalons",
    "sg:phone":"+32 2 640 74 75",
    "sg:postcode":"1180",
    "sg:province":"Bruxelles-Capitale",
    "wof:name":"Coiffure Gina",
    "wof:placetype":"venue"
},
  "geometry": {"coordinates":[4.3319702148,50.8036155701],"type":"Point"}
}