{
  "type": "Feature",
  "properties": {
    "addr:full":"Sint-hubertuslaan 19 Schilde ('s Gravenwezel) Antwerpen 2970",
    "addr:housenumber":"19",
    "addr:postcode":"2970",
    "addr:street":"Sint-Hubertuslaan;S",
    "iso:country":"BE",
    "sg:address":"Sint-hubertuslaan 19",
    "sg:city":"Schilde ('s Gravenwezel)",
    "sg:classifiers":[
        {
            "category":"Professional",
            "subcategory":"Accounting & Tax Preparation",
            "type":"Services"
        }
    ],
    "sg:phone":"+32 3 658 90 58",
    "sg:postcode":"2970",
    "sg:province":"Antwerpen",
    "sg:tags":[
        "bookkeeper"
    ],
    "wof:name":"Cop R",
    "wof:placetype":"venue"
},
  "geometry": {"coordinates":[4.558380127,51.2553367615],"type":"Point"}
}