{
  "type": "Feature",
  "properties": {
    "addr:full":"Place Du Centre 2 Ottignies-louvain-la-neuve Brabant Wallon 1340",
    "addr:housenumber":"2",
    "addr:postcode":"1340",
    "addr:street":"Place Du Centre",
    "iso:country":"BE",
    "sg:address":"Place Du Centre 2",
    "sg:city":"Ottignies-louvain-la-neuve",
    "sg:orig_category":"Kansspelen",
    "sg:phone":"+32 10 41 55 82",
    "sg:postcode":"1340",
    "sg:province":"Brabant Wallon",
    "wof:name":"Ladbrokes",
    "wof:placetype":"venue"
},
  "geometry": {"coordinates":[4.5688500404,50.6664543152],"type":"Point"}
}