{
  "type": "Feature",
  "properties": {
    "iso:country":"BE",
    "sg:address":"Lotsestraat 62",
    "sg:city":"Beersel",
    "sg:orig_category":"Producteurs de fruits. Eleveurs de bovins",
    "sg:phone":"+32 2 331 06 48",
    "sg:postcode":"1650",
    "sg:province":"Vlaams-Brabant",
    "wof:name":"Raymond Thielemans",
    "wof:placetype":"venue"
},
  "geometry": {"coordinates":[4.3004331589,50.7665634155],"type":"Point"}
}