{
  "type": "Feature",
  "properties": {
    "addr:full":"Leuvensesteenweg 605 Nossegem Vlaams-Brabant 1930",
    "addr:housenumber":"605",
    "addr:postcode":"1930",
    "addr:street":"Leuvensesteenweg",
    "iso:country":"BE",
    "sg:address":"Leuvensesteenweg 605",
    "sg:city":"Nossegem",
    "sg:classifiers":[
        {
            "category":"Professional",
            "subcategory":"Engineering",
            "type":"Services"
        }
    ],
    "sg:phone":"+32 2 757 90 75",
    "sg:postcode":"1930",
    "sg:province":"Vlaams-Brabant",
    "sg:tags":[
        "machine",
        "-",
        "mechanical"
    ],
    "wof:name":"Mycom Europe Nv",
    "wof:placetype":"venue"
},
  "geometry": {"coordinates":[4.4998221397,50.8766822815],"type":"Point"}
}