{
  "type": "Feature",
  "properties": {
    "addr:full":"Passage Du Centre 19 Mons Hainaut 7000",
    "addr:housenumber":"19",
    "addr:postcode":"7000",
    "addr:street":"Passage Du Centre;Hainaut",
    "iso:country":"BE",
    "sg:address":"Passage Du Centre 19",
    "sg:city":"Mons",
    "sg:orig_category":"Schoonheidssalons",
    "sg:phone":"+32 65 33 85 94",
    "sg:postcode":"7000",
    "sg:province":"Hainaut",
    "wof:name":"Institut Nicole",
    "wof:placetype":"venue"
},
  "geometry": {"coordinates":[3.9487769604,50.4511642456],"type":"Point"}
}