{
  "type": "Feature",
  "properties": {
    "iso:country":"BE",
    "sg:address":"Hyacintenlaan 13",
    "sg:city":"Schoten",
    "sg:orig_category":"Sportclubs",
    "sg:phone":"+32 3 658 13 20",
    "sg:postcode":"2900",
    "sg:province":"Antwerpen",
    "wof:name":"Volmar Ekeren",
    "wof:placetype":"venue"
},
  "geometry": {"coordinates":[4.5083408356,51.2588195801],"type":"Point"}
}