{
  "type": "Feature",
  "properties": {
    "addr:full":"Venelle Vivaldi 7 Bruxelles (ganshoren) Bruxelles-Capitale 1083",
    "addr:housenumber":"7",
    "addr:postcode":"1083",
    "addr:street":"Venelle Vivaldi",
    "iso:country":"BE",
    "sg:address":"Venelle Vivaldi 7",
    "sg:city":"Bruxelles (ganshoren)",
    "sg:classifiers":[
        {
            "category":"Professional",
            "subcategory":"Accounting & Tax Preparation",
            "type":"Services"
        }
    ],
    "sg:phone":"+32 2 469 48 50",
    "sg:postcode":"1083",
    "sg:province":"Bruxelles-Capitale",
    "sg:tags":[
        "bookkeeper"
    ],
    "wof:name":"Henrotin Ph",
    "wof:placetype":"venue"
},
  "geometry": {"coordinates":[4.3005847931,50.874206543],"type":"Point"}
}