{
  "type": "Feature",
  "properties": {
    "iso:country":"BE",
    "sg:address":"Rue Edmond Leburton 29",
    "sg:city":"Waremme (oleye)",
    "sg:classifiers":[
        {
            "category":"Professional",
            "subcategory":"Lawyer & Legal Services",
            "type":"Services"
        }
    ],
    "sg:phone":"+32 19 32 29 10",
    "sg:postcode":"4300",
    "sg:province":"Li\u00e8ge",
    "sg:tags":[
        "notary"
    ],
    "wof:name":"De Laminne De Bex O",
    "wof:placetype":"venue"
},
  "geometry": {"coordinates":[5.2926011086,50.7085151672],"type":"Point"}
}