{
  "type": "Feature",
  "properties": {
    "iso:country":"BE",
    "sg:address":"Rue De L'eglise 16",
    "sg:city":"Ittre",
    "sg:orig_category":"Sportclubs Sportterreinen and installaties behalve sportcentra",
    "sg:phone":"+32 67 84 44 04",
    "sg:postcode":"1461",
    "sg:province":"Brabant Wallon",
    "wof:name":"J.s. Ittroise",
    "wof:placetype":"venue"
},
  "geometry": {"coordinates":[4.297811985,50.6523895264],"type":"Point"}
}