{
  "type": "Feature",
  "properties": {
    "iso:country":"BE",
    "sg:address":"Leeuwstraat 26",
    "sg:city":"Lichtervelde",
    "sg:classifiers":[
        {
            "category":"Retail",
            "subcategory":"Veterinary Services",
            "type":"Services"
        }
    ],
    "sg:phone":"+32 51 72 21 40",
    "sg:postcode":"8810",
    "sg:province":"West-Vlaanderen",
    "sg:tags":[
        "veterinarian"
    ],
    "wof:name":"Denys R",
    "wof:placetype":"venue"
},
  "geometry": {"coordinates":[3.125013113,51.0291099548],"type":"Point"}
}