{
  "type": "Feature",
  "properties": {
    "addr:full":"Rue Donveau 1a Florennes (morialm\u00e9) Namur 5621",
    "addr:housenumber":"1a",
    "addr:postcode":"5621",
    "addr:street":"Rue Donveau",
    "iso:country":"BE",
    "sg:address":"Rue Donveau 1a",
    "sg:city":"Florennes (morialm\u00e9)",
    "sg:classifiers":[
        {
            "category":"Building & Trades",
            "subcategory":"Electrical",
            "type":"Services"
        }
    ],
    "sg:phone":"+32 71 68 52 78",
    "sg:postcode":"5621",
    "sg:province":"Namur",
    "sg:tags":[
        "-",
        "electric",
        "contractor"
    ],
    "wof:name":"Technic's Home",
    "wof:placetype":"venue"
},
  "geometry": {"coordinates":[4.5651698112,50.282699585],"type":"Point"}
}