{
  "type": "Feature",
  "properties": {
    "iso:country":"BE",
    "sg:address":"Molenweg 156",
    "sg:city":"Zonhoven",
    "sg:orig_category":"Apotheken",
    "sg:phone":"+32 11 81 61 30",
    "sg:postcode":"3520",
    "sg:province":"Limburg",
    "wof:name":"Apotheek De Ketelaere",
    "wof:placetype":"venue"
},
  "geometry": {"coordinates":[5.4286899567,50.9804382324],"type":"Point"}
}