{
  "type": "Feature",
  "properties": {
    "addr:full":"Kleine Dries 29a Diksmuide West-Vlaanderen 8600",
    "addr:housenumber":"29a",
    "addr:postcode":"8600",
    "addr:street":"Kleine Dries",
    "iso:country":"BE",
    "sg:address":"Kleine Dries 29a",
    "sg:city":"Diksmuide",
    "sg:classifiers":[
        {
            "category":"Freight",
            "type":"Transportation"
        }
    ],
    "sg:phone":"+32 51 50 25 79",
    "sg:postcode":"8600",
    "sg:province":"West-Vlaanderen",
    "sg:tags":[
        "-",
        "transport"
    ],
    "wof:name":"Deneire Nv",
    "wof:placetype":"venue"
},
  "geometry": {"coordinates":[2.8614370823,51.0181312561],"type":"Point"}
}