{
  "type": "Feature",
  "properties": {
    "iso:country":"BE",
    "sg:address":"Grand'place 9",
    "sg:city":"Hannut",
    "sg:orig_category":"Banques and organismes de cr\u00e9dit",
    "sg:phone":"+32 19 51 25 53",
    "sg:postcode":"4280",
    "sg:province":"Li\u00e8ge",
    "wof:name":"Bacob",
    "wof:placetype":"venue"
},
  "geometry": {"coordinates":[5.0776910782,50.6725883484],"type":"Point"}
}