{
  "type": "Feature",
  "properties": {
    "iso:country":"BE",
    "sg:address":"Hasseltsesteenweg 31a",
    "sg:city":"Kortessem",
    "sg:classifiers":[
        {
            "category":"Farming",
            "subcategory":"Fish & Marine Products",
            "type":"Manufacturing & Wholesale Goods"
        }
    ],
    "sg:phone":"+32 11 37 54 37",
    "sg:postcode":"3720",
    "sg:province":"Limburg",
    "sg:tags":[
        "retail",
        "-",
        "shellfish"
    ],
    "wof:name":"Mangetout",
    "wof:placetype":"venue"
},
  "geometry": {"coordinates":[5.3840308189,50.8599014282],"type":"Point"}
}