{
  "type": "Feature",
  "properties": {
    "addr:full":"Sint-hubertstraat 3 Deinze (petegem-aan-de-leie) Oost-Vlaanderen 9800",
    "addr:housenumber":"3",
    "addr:postcode":"9800",
    "addr:street":"Sint-Hubertstraat;Oost-Vlaanderen",
    "iso:country":"BE",
    "sg:address":"Sint-hubertstraat 3",
    "sg:city":"Deinze (petegem-aan-de-leie)",
    "sg:classifiers":[
        {
            "category":"Food & Beverages",
            "subcategory":"Liquor & Beverages",
            "type":"Retail Goods"
        }
    ],
    "sg:phone":"+32 9 386 13 20",
    "sg:postcode":"9800",
    "sg:province":"Oost-Vlaanderen",
    "sg:tags":[
        "-",
        "spirit",
        "wine"
    ],
    "wof:name":"Bierhandel Govaert Nv",
    "wof:placetype":"venue"
},
  "geometry": {"coordinates":[3.5252990723,50.9750671387],"type":"Point"}
}