{
  "type": "Feature",
  "properties": {
    "iso:country":"BE",
    "sg:address":"Rue Am\u00e9ricaine 76",
    "sg:city":"Bruxelles (ixelles)",
    "sg:classifiers":[
        {
            "category":"Home & Garden",
            "subcategory":"Carpets & Floor Coverings",
            "type":"Retail Goods"
        }
    ],
    "sg:phone":"+32 2 537 99 53",
    "sg:postcode":"1050",
    "sg:province":"Bruxelles-Capitale",
    "sg:tags":[
        "automobile",
        "-",
        "upholstering",
        "cover"
    ],
    "wof:name":"V-top Line Sprl",
    "wof:placetype":"venue"
},
  "geometry": {"coordinates":[4.3582458496,50.8236351013],"type":"Point"}
}