{
  "type": "Feature",
  "properties": {
    "iso:country":"BE",
    "sg:address":"Rue Des Haies 36",
    "sg:city":"Charleroi (marcinelle)",
    "sg:classifiers":[
        {
            "category":"Professional",
            "subcategory":"Business Services",
            "type":"Services"
        }
    ],
    "sg:phone":"+32 71 43 33 33",
    "sg:postcode":"6001",
    "sg:province":"Hainaut",
    "sg:tags":[
        "automobile",
        "-",
        "assessor"
    ],
    "wof:name":"Doucy J-f-e2+",
    "wof:placetype":"venue"
},
  "geometry": {"coordinates":[4.4500541687,50.3977622986],"type":"Point"}
}