{
  "type": "Feature",
  "properties": {
    "iso:country":"BE",
    "sg:address":"Molenstraat 107",
    "sg:city":"Eeklo",
    "sg:classifiers":[
        {
            "category":"Home & Garden",
            "subcategory":"Hardware",
            "type":"Retail Goods"
        }
    ],
    "sg:phone":"+32 9 377 22 44",
    "sg:postcode":"9900",
    "sg:province":"Oost-Vlaanderen",
    "sg:tags":[
        "quincailleries",
        "bois",
        "gr"
    ],
    "wof:name":"Van Tornhout-hermesse",
    "wof:placetype":"venue"
},
  "geometry": {"coordinates":[3.5598568916,51.1876182556],"type":"Point"}
}