{
  "type": "Feature",
  "properties": {
    "addr:full":"Dumpelstraat 1 Westerlo (oevel) Antwerpen 2260",
    "addr:housenumber":"1",
    "addr:postcode":"2260",
    "addr:street":"Dumpelstraat",
    "iso:country":"BE",
    "sg:address":"Dumpelstraat 1",
    "sg:city":"Westerlo (oevel)",
    "sg:classifiers":[
        {
            "category":"Health Services",
            "subcategory":"Health Practitioner",
            "type":"Services"
        }
    ],
    "sg:phone":"+32 14 23 45 95",
    "sg:postcode":"2260",
    "sg:province":"Antwerpen",
    "sg:tags":[
        "physiotherapist"
    ],
    "wof:name":"Vanheusden Raf",
    "wof:placetype":"venue"
},
  "geometry": {"coordinates":[4.9040389061,51.1341552734],"type":"Point"}
}