{
  "type": "Feature",
  "properties": {
    "addr:full":"Excelsiorlaan 48-50 Zaventem Vlaams-Brabant 1930",
    "addr:housenumber":"48-50",
    "addr:postcode":"1930",
    "addr:street":"Excelsiorlaan",
    "iso:country":"BE",
    "sg:address":"Excelsiorlaan 48-50",
    "sg:city":"Zaventem",
    "sg:orig_category":"Non-Classified Establishments",
    "sg:phone":"+32 2 718 11 11",
    "sg:postcode":"1930",
    "sg:province":"Vlaams-Brabant",
    "wof:name":"Sca Packaging",
    "wof:placetype":"venue"
},
  "geometry": {"coordinates":[4.4543128014,50.8818778992],"type":"Point"}
}