{
  "type": "Feature",
  "properties": {
    "addr:full":"Tramstationstraat 35 Diksmuide (leke) West-Vlaanderen 8600",
    "addr:housenumber":"35",
    "addr:postcode":"8600",
    "addr:street":"Tramstationstraat",
    "iso:country":"BE",
    "sg:address":"Tramstationstraat 35",
    "sg:city":"Diksmuide (leke)",
    "sg:classifiers":[
        {
            "category":"Personal",
            "type":"Services"
        }
    ],
    "sg:phone":"+32 51 50 11 01",
    "sg:postcode":"8600",
    "sg:province":"West-Vlaanderen",
    "sg:tags":[
        "party",
        "planning"
    ],
    "wof:name":"Marlo",
    "wof:placetype":"venue"
},
  "geometry": {"coordinates":[2.8657801151,51.0334663391],"type":"Point"}
}