{
  "type": "Feature",
  "properties": {
    "iso:country":"BE",
    "sg:address":"Konijnenbergpad 9",
    "sg:city":"Vosselaar",
    "sg:orig_category":"Cr\u00e8ches and garderies d'enfants",
    "sg:phone":"+32 14 61 83 09",
    "sg:postcode":"2350",
    "sg:province":"Antwerpen",
    "wof:name":"Kinderopv. De Konijntjes",
    "wof:placetype":"venue"
},
  "geometry": {"coordinates":[4.8840899467,51.3122329712],"type":"Point"}
}