{
  "type": "Feature",
  "properties": {
    "addr:full":"Vital Decosterstraat 66ba9 Leuven Vlaams-Brabant 3000",
    "addr:postcode":"3000",
    "addr:street":"Vital Decosterstraat 66Ba9",
    "iso:country":"BE",
    "sg:address":"Vital Decosterstraat 66ba9",
    "sg:city":"Leuven",
    "sg:orig_category":"Cabinets d\u00b4huissiers",
    "sg:phone":"+32 16 29 42 22",
    "sg:postcode":"3000",
    "sg:province":"Vlaams-Brabant",
    "wof:name":"Johan Stroobants",
    "wof:placetype":"venue"
},
  "geometry": {"coordinates":[4.7035961151,50.8820800781],"type":"Point"}
}