{
  "type": "Feature",
  "properties": {
    "addr:full":"Autolei 317 Wommelgem Antwerpen 2160",
    "addr:housenumber":"317",
    "addr:postcode":"2160",
    "iso:country":"BE",
    "sg:address":"Autolei 317",
    "sg:city":"Wommelgem",
    "sg:orig_category":"Verlichting and huishoudartikelen",
    "sg:phone":"+32 3 354 26 86",
    "sg:postcode":"2160",
    "sg:province":"Antwerpen",
    "wof:name":"Longchair",
    "wof:placetype":"venue"
},
  "geometry": {"coordinates":[4.493516922,51.2127685547],"type":"Point"}
}