{
  "type": "Feature",
  "properties": {
    "iso:country":"BE",
    "sg:address":"Chauss\u00c9e D\u00b4ixelles 94",
    "sg:city":"Ixelles",
    "sg:orig_category":"Mobistar Centres. Mat\u00e9riel de T\u00e9l\u00e9communication",
    "sg:phone":"+32 2 503 03 63",
    "sg:postcode":"1050",
    "sg:province":"Bruxelles-Capitale",
    "wof:name":"Mobistar Center Mobistyle",
    "wof:placetype":"venue"
},
  "geometry": {"coordinates":[4.3636870384,50.8357162476],"type":"Point"}
}