{
  "type": "Feature",
  "properties": {
    "iso:country":"BE",
    "sg:address":"Grand Route 19",
    "sg:city":"Tournai (gaurain-ramecroix)",
    "sg:classifiers":[
        {
            "category":"Mining & Drilling",
            "type":"Manufacturing & Wholesale Goods"
        }
    ],
    "sg:phone":"+32 69 25 14 73",
    "sg:postcode":"7530",
    "sg:province":"Hainaut",
    "sg:tags":[
        "quarry"
    ],
    "wof:name":"Societ\u00e9 Des Carri\u00e8res Du Tournaisis Sa",
    "wof:placetype":"venue"
},
  "geometry": {"coordinates":[3.4578781128,50.5978431702],"type":"Point"}
}