{
  "type": "Feature",
  "properties": {
    "addr:full":"Leopoldstraat 24 Mechelen Antwerpen 2800",
    "addr:housenumber":"24",
    "addr:postcode":"2800",
    "addr:street":"Leopoldstraat",
    "iso:country":"BE",
    "sg:address":"Leopoldstraat 24",
    "sg:city":"Mechelen",
    "sg:classifiers":[
        {
            "category":"Social Services",
            "type":"Services"
        }
    ],
    "sg:phone":"+32 15 20 95 14",
    "sg:postcode":"2800",
    "sg:province":"Antwerpen",
    "wof:name":"Justitieel Welzijnswerk",
    "wof:placetype":"venue"
},
  "geometry": {"coordinates":[4.4777770042,51.0198516846],"type":"Point"}
}