{
  "type": "Feature",
  "properties": {
    "addr:full":"Hollebeekstraat 23 Brakel (parike) Oost-Vlaanderen 9661",
    "addr:housenumber":"23",
    "addr:postcode":"9661",
    "addr:street":"Hollebeekstraat",
    "iso:country":"BE",
    "sg:address":"Hollebeekstraat 23",
    "sg:city":"Brakel (parike)",
    "sg:orig_category":"Autombile concessionaires",
    "sg:phone":"+32 55 42 45 83",
    "sg:postcode":"9661",
    "sg:province":"Oost-Vlaanderen",
    "wof:name":"Thomas",
    "wof:placetype":"venue"
},
  "geometry": {"coordinates":[3.8010571003,50.7867774963],"type":"Point"}
}