{
  "type": "Feature",
  "properties": {
    "iso:country":"BE",
    "sg:address":"Rue De Plainevaux 2",
    "sg:city":"Paliseul",
    "sg:orig_category":"M\u00e9decins and sp\u00e9cialistes",
    "sg:phone":"+32 61 53 56 93",
    "sg:postcode":"6851",
    "sg:province":"Luxembourg",
    "wof:name":"Nicole Maillard",
    "wof:placetype":"venue"
},
  "geometry": {"coordinates":[5.1208949089,49.8696746826],"type":"Point"}
}