{
  "type": "Feature",
  "properties": {
    "iso:country":"BE",
    "sg:address":"Vogelzangstraat 19",
    "sg:city":"Nijlen",
    "sg:orig_category":"Pain, p\u00e2tisseries and confiseries",
    "sg:phone":"+32 3 481 83 67",
    "sg:postcode":"2560",
    "sg:province":"Antwerpen",
    "wof:name":"Luc Van Tendeloo",
    "wof:placetype":"venue"
},
  "geometry": {"coordinates":[4.638988018,51.1708526611],"type":"Point"}
}