{
  "type": "Feature",
  "properties": {
    "addr:full":"Rue De L'industrie 43 Nivelles Brabant Wallon 1400",
    "addr:housenumber":"43",
    "addr:postcode":"1400",
    "addr:street":"Rue De L'Industrie",
    "iso:country":"BE",
    "sg:address":"Rue De L'industrie 43",
    "sg:city":"Nivelles",
    "sg:classifiers":[
        {
            "category":"Manufacturing",
            "subcategory":"Motor Vehicles & Parts",
            "type":"Manufacturing & Wholesale Goods"
        }
    ],
    "sg:phone":"+32 67 28 81 11",
    "sg:postcode":"1400",
    "sg:province":"Brabant Wallon",
    "sg:tags":[
        "energy",
        "unit",
        "supply"
    ],
    "wof:name":"Westinghouse Electric Europe S.a.",
    "wof:placetype":"venue"
},
  "geometry": {"coordinates":[4.353662014,50.5802841187],"type":"Point"}
}