{
  "type": "Feature",
  "properties": {
    "addr:full":"Rue Du Mar\u00e9chal 25 Leuze-en-hainaut (pipaix) Hainaut 7904",
    "addr:housenumber":"25",
    "addr:postcode":"7904",
    "addr:street":"Rue Du Mare\u0301Chal;Hainaut",
    "iso:country":"BE",
    "sg:address":"Rue Du Mar\u00e9chal 25",
    "sg:city":"Leuze-en-hainaut (pipaix)",
    "sg:classifiers":[
        {
            "category":"Farming",
            "subcategory":"Livestock Farm",
            "type":"Manufacturing & Wholesale Goods"
        }
    ],
    "sg:phone":"+32 69 66 33 14",
    "sg:postcode":"7904",
    "sg:province":"Hainaut",
    "sg:tags":[
        "horse"
    ],
    "wof:name":"Horse Of Belgium Sc",
    "wof:placetype":"venue"
},
  "geometry": {"coordinates":[3.5823450089,50.5860176086],"type":"Point"}
}