{
  "type": "Feature",
  "properties": {
    "addr:full":"Rattenhaus 9 Raeren Li\u00e8ge 4731",
    "addr:housenumber":"9",
    "addr:postcode":"4731",
    "addr:street":"Rattenhaus",
    "iso:country":"BE",
    "sg:address":"Rattenhaus 9",
    "sg:city":"Raeren",
    "sg:orig_category":"Eleveurs de bovins",
    "sg:phone":"+32 87 85 27 79",
    "sg:postcode":"4731",
    "sg:province":"Li\u00e8ge",
    "wof:name":"Hick",
    "wof:placetype":"venue"
},
  "geometry": {"coordinates":[6.1062169075,50.6893386841],"type":"Point"}
}