{
  "type": "Feature",
  "properties": {
    "iso:country":"BE",
    "sg:address":"Zuidstraat 161",
    "sg:city":"Brussel/bruxelles",
    "sg:orig_category":"Kapsalons",
    "sg:phone":"+32 2 514 32 26",
    "sg:postcode":"1000",
    "sg:province":"Bruxelles-Capitale",
    "wof:name":"New Gillis",
    "wof:placetype":"venue"
},
  "geometry": {"coordinates":[4.3464269638,50.8434677124],"type":"Point"}
}