{
  "type": "Feature",
  "properties": {
    "iso:country":"BE",
    "sg:address":"Dorpsstraat 16",
    "sg:city":"Mortsel",
    "sg:orig_category":"Drogisterijen",
    "sg:phone":"+32 3 449 91 95",
    "sg:postcode":"2640",
    "sg:province":"Antwerpen",
    "wof:name":"Walter De Meyer",
    "wof:placetype":"venue"
},
  "geometry": {"coordinates":[4.4636330605,51.1651611328],"type":"Point"}
}