{
  "type": "Feature",
  "properties": {
    "iso:country":"BE",
    "sg:address":"Bouquette 65",
    "sg:city":"Verviers",
    "sg:orig_category":"Installation \u00e9lectrique r\u00e9sidentielle",
    "sg:phone":"+32 87 22 81 20",
    "sg:postcode":"4800",
    "sg:province":"Li\u00e8ge",
    "wof:name":"Jean Melotte",
    "wof:placetype":"venue"
},
  "geometry": {"coordinates":[5.8594508171,50.5917663574],"type":"Point"}
}