{
  "type": "Feature",
  "properties": {
    "addr:full":"Rue Henri Vieuxtemps 12 Bruxelles (anderlecht) Bruxelles-Capitale 1070",
    "addr:housenumber":"12",
    "addr:postcode":"1070",
    "addr:street":"Rue Henri Vieuxtemps",
    "iso:country":"BE",
    "sg:address":"Rue Henri Vieuxtemps 12",
    "sg:city":"Bruxelles (anderlecht)",
    "sg:classifiers":[
        {
            "category":"Transit Center",
            "subcategory":"Freight",
            "type":"Transportation"
        }
    ],
    "sg:phone":"+32 2 524 24 02",
    "sg:postcode":"1070",
    "sg:province":"Bruxelles-Capitale",
    "sg:tags":[
        "import",
        "export",
        "-"
    ],
    "wof:name":"Armady",
    "wof:placetype":"venue"
},
  "geometry": {"coordinates":[4.3030328751,50.8309326172],"type":"Point"}
}