{
  "type": "Feature",
  "properties": {
    "addr:full":"Rue De L'egalit\u00c9 46 Frameries Hainaut 7080",
    "addr:housenumber":"46",
    "addr:postcode":"7080",
    "addr:street":"Rue De L'Egalite \u0301",
    "iso:country":"BE",
    "sg:address":"Rue De L'egalit\u00c9 46",
    "sg:city":"Frameries",
    "sg:orig_category":"Installation \u00e9lectrique r\u00e9sidentielle",
    "sg:phone":"+32 65 67 60 98",
    "sg:postcode":"7080",
    "sg:province":"Hainaut",
    "wof:name":"Elgebat",
    "wof:placetype":"venue"
},
  "geometry": {"coordinates":[3.8894450665,50.3937149048],"type":"Point"}
}