{
  "type": "Feature",
  "properties": {
    "iso:country":"BE",
    "sg:address":"Tommestraat 58",
    "sg:city":"Huldenberg",
    "sg:orig_category":"M\u00e9decins and sp\u00e9cialistes",
    "sg:phone":"+32 16 47 25 77",
    "sg:postcode":"3040",
    "sg:province":"Vlaams-Brabant",
    "wof:name":"Isabelle Rymenhoudt",
    "wof:placetype":"venue"
},
  "geometry": {"coordinates":[4.6230239868,50.7491569519],"type":"Point"}
}