{
  "type": "Feature",
  "properties": {
    "iso:country":"BE",
    "sg:address":"Itterbeekse Laan 461",
    "sg:city":"Anderlecht",
    "sg:classifiers":[
        {
            "category":"Insurance",
            "subcategory":"Insurance Agent",
            "type":"Services"
        }
    ],
    "sg:phone":"+32 2 521 15 39",
    "sg:postcode":"1070",
    "sg:province":"Bruxelles-Capitale",
    "sg:tags":[
        "verzekeringsmakelaars",
        "expert"
    ],
    "wof:name":"Cobafi",
    "wof:placetype":"venue"
},
  "geometry": {"coordinates":[4.2795739174,50.8352584839],"type":"Point"}
}