{
  "type": "Feature",
  "properties": {
    "iso:country":"BE",
    "sg:address":"Rue Rittweger 4",
    "sg:city":"Sint-genesius-rode/rhode-saint-genese",
    "sg:orig_category":"Imprimeries and copyshops. Studios photographiques. Secr\u00e9tariats",
    "sg:phone":"+32 2 380 88 16",
    "sg:postcode":"1640",
    "sg:province":"Vlaams-Brabant",
    "wof:name":"Fa. Ever Art Design",
    "wof:placetype":"venue"
},
  "geometry": {"coordinates":[4.3596868515,50.7480392456],"type":"Point"}
}