{
  "type": "Feature",
  "properties": {
    "iso:country":"BE",
    "sg:address":"Grote Molenweg 40",
    "sg:city":"Stabroek",
    "sg:classifiers":[
        {
            "category":"Home & Garden",
            "subcategory":"Kitchen Supply",
            "type":"Retail Goods"
        }
    ],
    "sg:phone":"+32 3 568 12 43",
    "sg:postcode":"2940",
    "sg:province":"Antwerpen",
    "sg:tags":[
        "installation"
    ],
    "wof:name":"Leysen Keuken & Sanitair",
    "wof:placetype":"venue"
},
  "geometry": {"coordinates":[4.3746871948,51.3339271545],"type":"Point"}
}