{
  "type": "Feature",
  "properties": {
    "iso:country":"BE",
    "sg:address":"Hochstrasse 81",
    "sg:city":"Eupen",
    "sg:orig_category":"Installatie van houten of kunststof schrijnwerk MEUBELONTWERP AND -INSTALLATIE Verzekeringsmakelaars",
    "sg:phone":"+32 87 55 36 36",
    "sg:postcode":"4700",
    "sg:province":"Li\u00e8ge",
    "wof:name":"Reul Fr\u00c8res",
    "wof:placetype":"venue"
},
  "geometry": {"coordinates":[6.015955925,50.6355934143],"type":"Point"}
}