{
  "type": "Feature",
  "properties": {
    "iso:country":"BE",
    "sg:address":"Adegemstraat 10",
    "sg:city":"Mechelen",
    "sg:orig_category":"Epiceries",
    "sg:phone":"+32 15 26 19 45",
    "sg:postcode":"2800",
    "sg:province":"Antwerpen",
    "wof:name":"Night Shop",
    "wof:placetype":"venue"
},
  "geometry": {"coordinates":[4.4763350487,51.0253639221],"type":"Point"}
}