{
  "type": "Feature",
  "properties": {
    "iso:country":"BE",
    "sg:address":"Bruggestraat 193",
    "sg:city":"Menen",
    "sg:classifiers":[
        {
            "category":"Restaurant",
            "type":"Food & Drink"
        }
    ],
    "sg:phone":"+32 56 51 20 56",
    "sg:postcode":"8930",
    "sg:province":"West-Vlaanderen",
    "wof:name":"'t Hoekske",
    "wof:placetype":"venue"
},
  "geometry": {"coordinates":[3.1235940456,50.8025283813],"type":"Point"}
}