{
  "type": "Feature",
  "properties": {
    "addr:full":"Oevelseweg 24 Olen Antwerpen 2250",
    "addr:housenumber":"24",
    "addr:postcode":"2250",
    "addr:street":"Oevelseweg",
    "iso:country":"BE",
    "sg:address":"Oevelseweg 24",
    "sg:city":"Olen",
    "sg:orig_category":"Biblioth\u00e8ques and archives publiques",
    "sg:phone":"+32 14 25 74 44",
    "sg:postcode":"2250",
    "sg:province":"Antwerpen",
    "wof:name":"Plaatselijke Openbare Bibliotheek",
    "wof:placetype":"venue"
},
  "geometry": {"coordinates":[4.9006509781,51.1652336121],"type":"Point"}
}