{
  "type": "Feature",
  "properties": {
    "addr:full":"Pont D'amercoeur 75 Li\u00e8ge 1 (li\u00e8ge 2) Li\u00e8ge 4020",
    "addr:housenumber":"75;1;2",
    "addr:postcode":"4020",
    "addr:street":"Pont D'Amercoeur",
    "iso:country":"BE",
    "sg:address":"Pont D'amercoeur 75",
    "sg:city":"Li\u00e8ge 1 (li\u00e8ge 2)",
    "sg:classifiers":[
        {
            "category":"Bakery",
            "type":"Food & Drink"
        }
    ],
    "sg:phone":"+32 4 343 32 98",
    "sg:postcode":"4020",
    "sg:province":"Li\u00e8ge",
    "sg:tags":[
        "confectioner",
        "baker"
    ],
    "wof:name":"Mouton W",
    "wof:placetype":"venue"
},
  "geometry": {"coordinates":[5.5906867981,50.6359367371],"type":"Point"}
}