{
  "type": "Feature",
  "properties": {
    "iso:country":"BE",
    "sg:address":"Oplombeekstraat 11",
    "sg:city":"Gooik",
    "sg:orig_category":"Eleveurs and marchands de porcs. Eleveurs de bovins",
    "sg:phone":"+32 2 532 51 82",
    "sg:postcode":"1755",
    "sg:province":"Vlaams-Brabant",
    "wof:name":"Rene Peeters",
    "wof:placetype":"venue"
},
  "geometry": {"coordinates":[4.1220941544,50.8090362549],"type":"Point"}
}