{
  "type": "Feature",
  "properties": {
    "iso:country":"BE",
    "sg:address":"Nobeekstraat 87",
    "sg:city":"Kruibeke",
    "sg:orig_category":"Produits c\u00e9r\u00e9aliers Fab",
    "sg:phone":"+32 3 774 10 53",
    "sg:postcode":"9150",
    "sg:province":"Oost-Vlaanderen",
    "wof:name":"Hanewijkmolen",
    "wof:placetype":"venue"
},
  "geometry": {"coordinates":[4.287861824,51.1381759644],"type":"Point"}
}