{
  "type": "Feature",
  "properties": {
    "addr:full":"Rue G\u00e9n\u00e9raux Cuvelier 16 Florenville Luxembourg 6820",
    "addr:housenumber":"16",
    "addr:postcode":"6820",
    "addr:street":"Rue Ge\u0301Ne\u0301Raux Cuvelier",
    "iso:country":"BE",
    "sg:address":"Rue G\u00e9n\u00e9raux Cuvelier 16",
    "sg:city":"Florenville",
    "sg:classifiers":[
        {
            "category":"Shopping",
            "subcategory":"Clothing, Apparel, & Fashions",
            "type":"Retail Goods"
        }
    ],
    "sg:phone":"+32 61 31 12 88",
    "sg:postcode":"6820",
    "sg:province":"Luxembourg",
    "sg:tags":[
        "milliner"
    ],
    "wof:name":"Paris Modes",
    "wof:placetype":"venue"
},
  "geometry": {"coordinates":[5.3091421127,49.6980056763],"type":"Point"}
}