{
  "type": "Feature",
  "properties": {
    "iso:country":"BE",
    "sg:address":"Gill\u00c8s De P\u00c9lichylei 69",
    "sg:city":"Schilde",
    "sg:orig_category":"M\u00e9decins and sp\u00e9cialistes",
    "sg:phone":"+32 3 685 17 02",
    "sg:postcode":"2970",
    "sg:province":"Antwerpen",
    "wof:name":"A. Buyle",
    "wof:placetype":"venue"
},
  "geometry": {"coordinates":[4.5596327782,51.2559165955],"type":"Point"}
}