{
  "type": "Feature",
  "properties": {
    "addr:full":"Rue Kwadeplas 35 Rhode-saint-gen\u00e8se Vlaams-Brabant 1640",
    "addr:housenumber":"35",
    "addr:postcode":"1640",
    "addr:street":"Rue Kwadeplas",
    "iso:country":"BE",
    "sg:address":"Rue Kwadeplas 35",
    "sg:city":"Rhode-saint-gen\u00e8se",
    "sg:classifiers":[
        {
            "category":"Professional",
            "subcategory":"Management & Consulting",
            "type":"Services"
        }
    ],
    "sg:phone":"+32 2 380 28 24",
    "sg:postcode":"1640",
    "sg:province":"Vlaams-Brabant",
    "sg:tags":[
        "consultant",
        "promotion",
        "-",
        "sale"
    ],
    "wof:name":"Corbisier Consult",
    "wof:placetype":"venue"
},
  "geometry": {"coordinates":[4.3478221893,50.7396125793],"type":"Point"}
}