{
  "type": "Feature",
  "properties": {
    "addr:full":"Avenue De Fr\u00c9 209 Ukkel/uccle Bruxelles-Capitale 1180",
    "addr:housenumber":"209",
    "addr:postcode":"1180",
    "addr:street":"Avenue De Fre\u0301;/",
    "iso:country":"BE",
    "sg:address":"Avenue De Fr\u00c9 209",
    "sg:city":"Ukkel/uccle",
    "sg:orig_category":"Pain, p\u00e2tisseries and confiseries",
    "sg:phone":"+32 2 372 02 22",
    "sg:postcode":"1180",
    "sg:province":"Bruxelles-Capitale",
    "wof:name":"Maison Des Pains",
    "wof:placetype":"venue"
},
  "geometry": {"coordinates":[4.3579411507,50.804019928],"type":"Point"}
}