{
  "type": "Feature",
  "properties": {
    "addr:full":"Heindonksesteenweg 128 Willebroek Antwerpen 2830",
    "addr:housenumber":"128",
    "addr:postcode":"2830",
    "addr:street":"Heindonksesteenweg",
    "iso:country":"BE",
    "sg:address":"Heindonksesteenweg 128",
    "sg:city":"Willebroek",
    "sg:orig_category":"Brood, gebak and snoepgoed",
    "sg:phone":"+32 3 886 88 49",
    "sg:postcode":"2830",
    "sg:province":"Antwerpen",
    "wof:name":"Louis De Buyser",
    "wof:placetype":"venue"
},
  "geometry": {"coordinates":[4.3745250702,51.0656242371],"type":"Point"}
}