{
  "type": "Feature",
  "properties": {
    "addr:full":"Rue Hallez 23 La Louvi\u00e8re (trivi\u00e8res) Hainaut 7100",
    "addr:housenumber":"23",
    "addr:postcode":"7100",
    "addr:street":"Rue Hallez",
    "iso:country":"BE",
    "sg:address":"Rue Hallez 23",
    "sg:city":"La Louvi\u00e8re (trivi\u00e8res)",
    "sg:classifiers":[
        {
            "category":"Shopping",
            "subcategory":"Bicycles & Sporting Goods",
            "type":"Retail Goods"
        }
    ],
    "sg:phone":"+32 64 28 58 58",
    "sg:postcode":"7100",
    "sg:province":"Hainaut",
    "sg:tags":[
        "sport",
        "-"
    ],
    "wof:name":"Alfasport Sprl",
    "wof:placetype":"venue"
},
  "geometry": {"coordinates":[4.1850848198,50.4748649597],"type":"Point"}
}