{
  "type": "Feature",
  "properties": {
    "iso:country":"BE",
    "sg:address":"Rue Albert I 10",
    "sg:city":"Hannut",
    "sg:classifiers":[
        {
            "category":"Shopping",
            "subcategory":"Optician",
            "type":"Retail Goods"
        }
    ],
    "sg:phone":"+32 19 51 20 98",
    "sg:postcode":"4280",
    "sg:province":"Li\u00e8ge",
    "sg:tags":[
        "-"
    ],
    "wof:name":"Dorz\u00e9e Opticiens",
    "wof:placetype":"venue"
},
  "geometry": {"coordinates":[5.0800790787,50.671081543],"type":"Point"}
}