{
  "type": "Feature",
  "properties": {
    "iso:country":"BE",
    "sg:address":"Rue De Plainevaux 3",
    "sg:city":"Bouillon",
    "sg:classifiers":[
        {
            "category":"Restaurant",
            "type":"Food & Drink"
        }
    ],
    "sg:phone":"+32 61 46 76 24",
    "sg:postcode":"6834",
    "sg:province":"Luxembourg",
    "wof:name":"Le Foru",
    "wof:placetype":"venue"
},
  "geometry": {"coordinates":[5.1092801094,49.8381462097],"type":"Point"}
}