{
  "type": "Feature",
  "properties": {
    "iso:country":"BE",
    "sg:address":"Rue De Clabecq 60",
    "sg:city":"Ittre",
    "sg:classifiers":[
        {
            "category":"Insurance",
            "subcategory":"Insurance Agent",
            "type":"Services"
        }
    ],
    "sg:phone":"+32 2 390 98 60",
    "sg:postcode":"1460",
    "sg:province":"Brabant Wallon",
    "sg:tags":[
        "broker"
    ],
    "wof:name":"Lepoivre M",
    "wof:placetype":"venue"
},
  "geometry": {"coordinates":[4.2354822159,50.6656265259],"type":"Point"}
}