{
  "type": "Feature",
  "properties": {
    "addr:full":"Avenue Louise 193 Box 23 Bruxelles (ixelles) Bruxelles-Capitale 1050",
    "addr:housenumber":"193 box 23",
    "addr:postcode":"1050",
    "addr:street":"Avenue Louise",
    "iso:country":"BE",
    "sg:address":"Avenue Louise 193 Box 23",
    "sg:city":"Bruxelles (ixelles)",
    "sg:classifiers":[
        {
            "category":"Real Estate",
            "subcategory":"Real Estate Services",
            "type":"Services"
        }
    ],
    "sg:phone":"+32 2 649 82 32",
    "sg:postcode":"1050",
    "sg:province":"Bruxelles-Capitale",
    "wof:name":"Groupinvest",
    "wof:placetype":"venue"
},
  "geometry": {"coordinates":[4.3635182381,50.8270835876],"type":"Point"}
}