{
  "type": "Feature",
  "properties": {
    "addr:full":"Spoorwegstraat 22 Turnhout Antwerpen 2300",
    "addr:housenumber":"22",
    "addr:postcode":"2300",
    "addr:street":"Spoorwegstraat",
    "iso:country":"BE",
    "sg:address":"Spoorwegstraat 22",
    "sg:city":"Turnhout",
    "sg:orig_category":"Overheidsdiensten",
    "sg:phone":"+32 14 44 38 70",
    "sg:postcode":"2300",
    "sg:province":"Antwerpen",
    "wof:name":"Admin. Directe Belast.",
    "wof:placetype":"venue"
},
  "geometry": {"coordinates":[4.9366898537,51.3195571899],"type":"Point"}
}