{
  "type": "Feature",
  "properties": {
    "addr:full":"Rue Michel Beckers 30 Vis\u00e9 (argenteau) Li\u00e8ge 4601",
    "addr:housenumber":"30",
    "addr:postcode":"4601",
    "addr:street":"Rue Michel Beckers;Argenteau",
    "iso:country":"BE",
    "sg:address":"Rue Michel Beckers 30",
    "sg:city":"Vis\u00e9 (argenteau)",
    "sg:classifiers":[
        {
            "category":"Professional",
            "subcategory":"Computer Services",
            "type":"Services"
        }
    ],
    "sg:phone":"+32 4 379 34 69",
    "sg:postcode":"4601",
    "sg:province":"Li\u00e8ge",
    "sg:tags":[
        "webdesign",
        "-",
        "internet"
    ],
    "wof:name":"Creation-studio.be",
    "wof:placetype":"venue"
},
  "geometry": {"coordinates":[5.6874017715,50.6957092285],"type":"Point"}
}