{
  "type": "Feature",
  "properties": {
    "addr:full":"Place Vanderkindere 1 Ukkel/uccle Bruxelles-Capitale 1180",
    "addr:housenumber":"1",
    "addr:postcode":"1180",
    "addr:street":"Place Vanderkindere;/",
    "iso:country":"BE",
    "sg:address":"Place Vanderkindere 1",
    "sg:city":"Ukkel/uccle",
    "sg:classifiers":[
        {
            "category":"Restaurant",
            "type":"Food & Drink"
        }
    ],
    "sg:phone":"+32 2 346 94 14",
    "sg:postcode":"1180",
    "sg:province":"Bruxelles-Capitale",
    "wof:name":"Crock'in",
    "wof:placetype":"venue"
},
  "geometry": {"coordinates":[4.3392210007,50.8134078979],"type":"Point"}
}