{
  "type": "Feature",
  "properties": {
    "addr:full":"Latemstraat 173 Bus 6 Sint-martens-latem Oost-Vlaanderen 9830",
    "addr:housenumber":"173 bus 6",
    "addr:postcode":"9830",
    "addr:street":"Latemstraat;Sint-Martens-Latem Oost-Vlaanderen",
    "iso:country":"BE",
    "sg:address":"Latemstraat 173 Bus 6",
    "sg:city":"Sint-martens-latem",
    "sg:classifiers":[
        {
            "category":"Food & Beverages",
            "subcategory":"Meat & Fish",
            "type":"Retail Goods"
        }
    ],
    "sg:phone":"+32 9 384 64 44",
    "sg:postcode":"9830",
    "sg:province":"Oost-Vlaanderen",
    "sg:tags":[
        "product"
    ],
    "wof:name":"Qualifood B.v.b.a.",
    "wof:placetype":"venue"
},
  "geometry": {"coordinates":[3.6169800758,51.012840271],"type":"Point"}
}