{
  "type": "Feature",
  "properties": {
    "addr:full":"Hulsdonk 20 Box 5 Gent (desteldonk) Oost-Vlaanderen 9042",
    "addr:housenumber":"20;5",
    "addr:postcode":"9042",
    "addr:street":"Hulsdonk;Box",
    "iso:country":"BE",
    "sg:address":"Hulsdonk 20 Box 5",
    "sg:city":"Gent (desteldonk)",
    "sg:classifiers":[
        {
            "category":"Building & Trades",
            "subcategory":"Cleaning & Sanitation",
            "type":"Services"
        }
    ],
    "sg:phone":"+32 9 345 63 23",
    "sg:postcode":"9042",
    "sg:province":"Oost-Vlaanderen",
    "sg:tags":[
        "asbestos",
        "removal"
    ],
    "wof:name":"Verstraeten-verbrugge Nv",
    "wof:placetype":"venue"
},
  "geometry": {"coordinates":[3.7816700935,51.1223831177],"type":"Point"}
}