{
  "type": "Feature",
  "properties": {
    "iso:country":"BE",
    "sg:address":"Kerkstraat 69",
    "sg:city":"Lokeren",
    "sg:classifiers":[
        {
            "category":"Tea Room",
            "subcategory":"None",
            "type":"Food & Drink"
        }
    ],
    "sg:phone":"+32 9 348 98 65",
    "sg:postcode":"9160",
    "sg:province":"Oost-Vlaanderen",
    "wof:name":"Papillon",
    "wof:placetype":"venue"
},
  "geometry": {"coordinates":[3.9939630032,51.1025390625],"type":"Point"}
}