{
  "type": "Feature",
  "properties": {
    "iso:country":"BE",
    "sg:address":"Rue Des Ecoles 63",
    "sg:city":"Vis\u00c9",
    "sg:classifiers":[
        {
            "category":"Shopping Center",
            "type":"Public Place"
        }
    ],
    "sg:phone":"+32 4 374 12 14",
    "sg:postcode":"4600",
    "sg:province":"Li\u00e8ge",
    "sg:tags":[
        "enseignement",
        "formation"
    ],
    "wof:name":"Philippe De Brogniez",
    "wof:placetype":"venue"
},
  "geometry": {"coordinates":[5.6850671768,50.7402915955],"type":"Point"}
}