{
  "type": "Feature",
  "properties": {
    "iso:country":"BE",
    "sg:address":"Hogesteenweg 22",
    "sg:city":"Grimbergen",
    "sg:orig_category":"Banques and organismes de cr\u00e9dit",
    "sg:phone":"+32 2 270 95 07",
    "sg:postcode":"1850",
    "sg:province":"Vlaams-Brabant",
    "wof:name":"Fortis",
    "wof:placetype":"venue"
},
  "geometry": {"coordinates":[4.3722472191,50.9331665039],"type":"Point"}
}