{
  "type": "Feature",
  "properties": {
    "iso:country":"BE",
    "sg:address":"Bargeweg 15",
    "sg:city":"Brugge",
    "sg:classifiers":[
        {
            "category":"Travel",
            "subcategory":"Hotels & Motels",
            "type":"Entertainment"
        }
    ],
    "sg:phone":"+32 50 38 51 50",
    "sg:postcode":"8000",
    "sg:province":"West-Vlaanderen",
    "wof:name":"De Barge Boot",
    "wof:placetype":"venue"
},
  "geometry": {"coordinates":[3.2255930901,51.1978721619],"type":"Point"}
}