{
  "type": "Feature",
  "properties": {
    "iso:country":"BE",
    "sg:address":"Meerhoutsebaan 73",
    "sg:city":"Mol",
    "sg:classifiers":[
        {
            "category":"Building & Trades",
            "subcategory":"Landscaping Services",
            "type":"Services"
        }
    ],
    "sg:phone":"+32 14 31 21 97",
    "sg:postcode":"2400",
    "sg:province":"Antwerpen",
    "sg:tags":[
        "gardening",
        "garden",
        "maintenance"
    ],
    "wof:name":"Degelin Tuinarchitectuur",
    "wof:placetype":"venue"
},
  "geometry": {"coordinates":[5.1068592072,51.1693458557],"type":"Point"}
}