{
  "type": "Feature",
  "properties": {
    "addr:full":"Hoogstraat 29 Harelbeke West-Vlaanderen 8531",
    "addr:housenumber":"29",
    "addr:postcode":"8531",
    "addr:street":"Hoogstraat",
    "iso:country":"BE",
    "sg:address":"Hoogstraat 29",
    "sg:city":"Harelbeke",
    "sg:orig_category":"Pain, p\u00e2tisseries and confiseries",
    "sg:phone":"+32 56 71 07 64",
    "sg:postcode":"8531",
    "sg:province":"West-Vlaanderen",
    "wof:name":"Bakkerij 't Ovenbuur",
    "wof:placetype":"venue"
},
  "geometry": {"coordinates":[3.3121130466,50.881187439],"type":"Point"}
}