{
  "type": "Feature",
  "properties": {
    "addr:full":"Groenendries 8 Lubbeek (binkom) Vlaams-Brabant 3211",
    "addr:housenumber":"8",
    "addr:postcode":"3211",
    "addr:street":"Groenendries",
    "iso:country":"BE",
    "sg:address":"Groenendries 8",
    "sg:city":"Lubbeek (binkom)",
    "sg:classifiers":[
        {
            "category":"Building & Trades",
            "subcategory":"Landscaping Services",
            "type":"Services"
        }
    ],
    "sg:phone":"+32 16 63 03 16",
    "sg:postcode":"3211",
    "sg:province":"Vlaams-Brabant",
    "sg:tags":[
        "gardening",
        "garden",
        "maintenance"
    ],
    "wof:name":"Den Hovenier",
    "wof:placetype":"venue"
},
  "geometry": {"coordinates":[4.8969907761,50.8623886108],"type":"Point"}
}