{
  "type": "Feature",
  "properties": {
    "addr:full":"Diksmuidesteenweg 93 Staden West-Vlaanderen 8840",
    "addr:housenumber":"93",
    "addr:postcode":"8840",
    "addr:street":"Diksmuidesteenweg",
    "iso:country":"BE",
    "sg:address":"Diksmuidesteenweg 93",
    "sg:city":"Staden",
    "sg:orig_category":"Enseignement maternel and primaire",
    "sg:phone":"+32 51 70 39 52",
    "sg:postcode":"8840",
    "sg:province":"West-Vlaanderen",
    "wof:name":"Vrije Basisschool",
    "wof:placetype":"venue"
},
  "geometry": {"coordinates":[3.0085270405,50.9798622131],"type":"Point"}
}