{
  "type": "Feature",
  "properties": {
    "addr:full":"Steenweg Naar Halle 1 Beersel (alsemberg) Vlaams-Brabant 1652",
    "addr:housenumber":"1",
    "addr:postcode":"1652",
    "addr:street":"Steenweg Naar Halle",
    "iso:country":"BE",
    "sg:address":"Steenweg Naar Halle 1",
    "sg:city":"Beersel (alsemberg)",
    "sg:classifiers":[
        {
            "category":"Home & Garden",
            "subcategory":"Carpets & Floor Coverings",
            "type":"Retail Goods"
        }
    ],
    "sg:phone":"+32 2 383 06 01",
    "sg:postcode":"1652",
    "sg:province":"Vlaams-Brabant",
    "sg:tags":[
        "-",
        "rug"
    ],
    "wof:name":"Kitchen Vastiau-godeau",
    "wof:placetype":"venue"
},
  "geometry": {"coordinates":[4.3242602348,50.7340583801],"type":"Point"}
}