{
  "type": "Feature",
  "properties": {
    "iso:country":"BE",
    "sg:address":"Heidelaan 37bb",
    "sg:city":"Lint",
    "sg:orig_category":"Administration d'immeubles",
    "sg:phone":"+32 3 455 64 32",
    "sg:postcode":"2547",
    "sg:province":"Antwerpen",
    "wof:name":"Vastgoedbeheer Degros J.",
    "wof:placetype":"venue"
},
  "geometry": {"coordinates":[4.486975193,51.1250915527],"type":"Point"}
}