{
  "type": "Feature",
  "properties": {
    "iso:country":"BE",
    "sg:address":"Steenweg Op Ukkel 208",
    "sg:city":"Beersel",
    "sg:orig_category":"Experts-comptables",
    "sg:phone":"+32 2 377 32 06",
    "sg:postcode":"1650",
    "sg:province":"Vlaams-Brabant",
    "wof:name":"Vincent Delvaux",
    "wof:placetype":"venue"
},
  "geometry": {"coordinates":[4.3184580803,50.7749214172],"type":"Point"}
}