{
  "type": "Feature",
  "properties": {
    "addr:full":"Velodreef 150 Essen Antwerpen 2910",
    "addr:housenumber":"150",
    "addr:postcode":"2910",
    "addr:street":"Velodreef",
    "iso:country":"BE",
    "sg:address":"Velodreef 150",
    "sg:city":"Essen",
    "sg:classifiers":[
        {
            "category":"Banks & Credit Unions",
            "subcategory":"Investment Brokerage",
            "type":"Services"
        }
    ],
    "sg:phone":"+32 3 677 22 10",
    "sg:postcode":"2910",
    "sg:province":"Antwerpen",
    "sg:tags":[
        "fence"
    ],
    "wof:name":"Aj Afsluitingen & Karweiwerken",
    "wof:placetype":"venue"
},
  "geometry": {"coordinates":[4.4432148933,51.4362564087],"type":"Point"}
}