{
  "type": "Feature",
  "properties": {
    "addr:full":"Steenweg 35 Herk-de-stad (berbroek) Limburg 3540",
    "addr:housenumber":"35",
    "addr:postcode":"3540",
    "addr:street":"Steenweg",
    "iso:country":"BE",
    "sg:address":"Steenweg 35",
    "sg:city":"Herk-de-stad (berbroek)",
    "sg:classifiers":[
        {
            "category":"Bars & Pubs",
            "type":"Food & Drink"
        }
    ],
    "sg:phone":"+32 13 55 36 46",
    "sg:postcode":"3540",
    "sg:province":"Limburg",
    "wof:name":"Majestic (taverne)",
    "wof:placetype":"venue"
},
  "geometry": {"coordinates":[5.2116727829,50.9479217529],"type":"Point"}
}