{
  "type": "Feature",
  "properties": {
    "iso:country":"BE",
    "sg:address":"Rue Des Amours 14",
    "sg:city":"La Louviere",
    "sg:orig_category":"WAPENS AND MUNITIE",
    "sg:phone":"+32 64 22 14 91",
    "sg:postcode":"7100",
    "sg:province":"Hainaut",
    "wof:name":"Bailly Armes & Munition",
    "wof:placetype":"venue"
},
  "geometry": {"coordinates":[4.1853671074,50.4741210938],"type":"Point"}
}