{
  "type": "Feature",
  "properties": {
    "addr:full":"Tiensesteenweg 152 Bierbeek (korbeek-lo) Vlaams-Brabant 3360",
    "addr:housenumber":"152",
    "addr:postcode":"3360",
    "addr:street":"Tiensesteenweg",
    "iso:country":"BE",
    "sg:address":"Tiensesteenweg 152",
    "sg:city":"Bierbeek (korbeek-lo)",
    "sg:classifiers":[
        {
            "category":"Personal",
            "subcategory":"Nail Salon",
            "type":"Services"
        }
    ],
    "sg:phone":"+32 16 46 23 41",
    "sg:postcode":"3360",
    "sg:province":"Vlaams-Brabant",
    "sg:tags":[
        "pedicure"
    ],
    "wof:name":"Minnoye L",
    "wof:placetype":"venue"
},
  "geometry": {"coordinates":[4.7659010887,50.8615760803],"type":"Point"}
}