{
  "type": "Feature",
  "properties": {
    "iso:country":"BE",
    "sg:address":"Rozemarijnstraat 122-128",
    "sg:city":"Gent-centrum",
    "sg:orig_category":"Advocaten and juridische adviseurs Balie van Gent",
    "sg:phone":"+32 9 233 28 02",
    "sg:postcode":"9000",
    "sg:province":"Oost-Vlaanderen",
    "wof:name":"Hulsbosch Jacques",
    "wof:placetype":"venue"
},
  "geometry": {"coordinates":[3.7072980404,51.0498428345],"type":"Point"}
}