{
  "type": "Feature",
  "properties": {
    "addr:full":"Rue De L'echelle 197 Seraing Li\u00e8ge 4100",
    "addr:housenumber":"197",
    "addr:postcode":"4100",
    "addr:street":"Rue De L'Echelle",
    "iso:country":"BE",
    "sg:address":"Rue De L'echelle 197",
    "sg:city":"Seraing",
    "sg:orig_category":"G\u00e9om\u00e8tres",
    "sg:phone":"+32 4 337 19 90",
    "sg:postcode":"4100",
    "sg:province":"Li\u00e8ge",
    "wof:name":"Martial Penoit",
    "wof:placetype":"venue"
},
  "geometry": {"coordinates":[5.505988121,50.6016120911],"type":"Point"}
}