{
  "type": "Feature",
  "properties": {
    "iso:country":"BE",
    "sg:address":"Avenue Blonden 52",
    "sg:city":"Li\u00e8ge 1",
    "sg:classifiers":[
        {
            "category":"Shopping",
            "subcategory":"Pets & Pet Supplies",
            "type":"Retail Goods"
        }
    ],
    "sg:phone":"+32 4 253 68 16",
    "sg:postcode":"4000",
    "sg:province":"Li\u00e8ge",
    "sg:tags":[
        "aquarium",
        "accessory"
    ],
    "wof:name":"Syn Rj Sprl",
    "wof:placetype":"venue"
},
  "geometry": {"coordinates":[5.5703639984,50.6287498474],"type":"Point"}
}