{
  "type": "Feature",
  "properties": {
    "iso:country":"BE",
    "sg:address":"Rue De La Halette 129",
    "sg:city":"Seraing (jemeppe-sur-meuse)",
    "sg:classifiers":[
        {
            "category":"Real Estate",
            "subcategory":"Architect",
            "type":"Services"
        }
    ],
    "sg:phone":"+32 4 233 26 47",
    "sg:postcode":"4101",
    "sg:province":"Li\u00e8ge",
    "wof:name":"Valerio E",
    "wof:placetype":"venue"
},
  "geometry": {"coordinates":[5.5086970329,50.6218719482],"type":"Point"}
}