{
  "type": "Feature",
  "properties": {
    "addr:full":"Morkhovenseweg 114 Herentals (noorderwijk) Antwerpen 2200",
    "addr:housenumber":"114",
    "addr:postcode":"2200",
    "addr:street":"Morkhovenseweg",
    "iso:country":"BE",
    "sg:address":"Morkhovenseweg 114",
    "sg:city":"Herentals (noorderwijk)",
    "sg:classifiers":[
        {
            "category":"Shopping",
            "subcategory":"Computers & Home Electronics",
            "type":"Retail Goods"
        }
    ],
    "sg:phone":"+32 14 26 16 76",
    "sg:postcode":"2200",
    "sg:province":"Antwerpen",
    "sg:tags":[
        "-",
        "television",
        "radio"
    ],
    "wof:name":"Flieger",
    "wof:placetype":"venue"
},
  "geometry": {"coordinates":[4.8272662163,51.1267662048],"type":"Point"}
}