{
  "type": "Feature",
  "properties": {
    "iso:country":"BE",
    "sg:address":"Rue Des Communes 10",
    "sg:city":"Genappe",
    "sg:orig_category":"Jardinage",
    "sg:phone":"+32 67 79 00 89",
    "sg:postcode":"1470",
    "sg:province":"Brabant Wallon",
    "wof:name":"Marc Plumley",
    "wof:placetype":"venue"
},
  "geometry": {"coordinates":[4.5088977814,50.6036186218],"type":"Point"}
}