{
  "type": "Feature",
  "properties": {
    "addr:full":"Bosstraat 24b5 Maaseik Limburg 3680",
    "addr:housenumber":"24b5",
    "addr:postcode":"3680",
    "addr:street":"Bosstraat",
    "iso:country":"BE",
    "sg:address":"Bosstraat 24b5",
    "sg:city":"Maaseik",
    "sg:classifiers":[
        {
            "category":"Restaurant",
            "type":"Food & Drink"
        }
    ],
    "sg:phone":"+32 89 56 18 16",
    "sg:postcode":"3680",
    "sg:province":"Limburg",
    "wof:name":"Brasserie Kloostertuin",
    "wof:placetype":"venue"
},
  "geometry": {"coordinates":[5.7896099091,51.0950164795],"type":"Point"}
}