{
  "type": "Feature",
  "properties": {
    "addr:full":"Paddegatstraat 2 Jabbeke West-Vlaanderen 8490",
    "addr:housenumber":"2",
    "addr:postcode":"8490",
    "addr:street":"Paddegatstraat",
    "iso:country":"BE",
    "sg:address":"Paddegatstraat 2",
    "sg:city":"Jabbeke",
    "sg:orig_category":"Eleveurs d'\u00e9quid\u00e9s",
    "sg:phone":"+32 50 81 43 68",
    "sg:postcode":"8490",
    "sg:province":"West-Vlaanderen",
    "wof:name":"Paddegat",
    "wof:placetype":"venue"
},
  "geometry": {"coordinates":[3.0649240017,51.2130012512],"type":"Point"}
}