{
  "type": "Feature",
  "properties": {
    "addr:full":"Ambachtenlaan 54 Heverlee Vlaams-Brabant 3001",
    "addr:housenumber":"54",
    "addr:postcode":"3001",
    "addr:street":"Ambachtenlaan",
    "iso:country":"BE",
    "sg:address":"Ambachtenlaan 54",
    "sg:city":"Heverlee",
    "sg:classifiers":[
        {
            "category":"Professional",
            "subcategory":"Management & Consulting",
            "type":"Services"
        }
    ],
    "sg:phone":"+32 16 38 75 70",
    "sg:postcode":"3001",
    "sg:province":"Vlaams-Brabant",
    "sg:tags":[
        "purchasing"
    ],
    "wof:name":"Goodex France-benelux",
    "wof:placetype":"venue"
},
  "geometry": {"coordinates":[4.7175779343,50.8474884033],"type":"Point"}
}