{
  "type": "Feature",
  "properties": {
    "addr:full":"Melkerijstraat 10 Langemark-poelkapelle (langemark) West-Vlaanderen 8920",
    "addr:housenumber":"10",
    "addr:postcode":"8920",
    "addr:street":"Melkerijstraat",
    "iso:country":"BE",
    "sg:address":"Melkerijstraat 10",
    "sg:city":"Langemark-poelkapelle (langemark)",
    "sg:classifiers":[
        {
            "category":"Ice Cream",
            "type":"Food & Drink"
        }
    ],
    "sg:phone":"+32 57 49 03 00",
    "sg:postcode":"8920",
    "sg:province":"West-Vlaanderen",
    "wof:name":"Ysco Nv",
    "wof:placetype":"venue"
},
  "geometry": {"coordinates":[2.919770956,50.9132423401],"type":"Point"}
}