{
  "type": "Feature",
  "properties": {
    "addr:full":"Voortstraat 55 Kampenhout Vlaams-Brabant 1910",
    "addr:housenumber":"55",
    "addr:postcode":"1910",
    "addr:street":"Voortstraat",
    "iso:country":"BE",
    "sg:address":"Voortstraat 55",
    "sg:city":"Kampenhout",
    "sg:orig_category":"Architectes",
    "sg:phone":"+32 16 65 52 18",
    "sg:postcode":"1910",
    "sg:province":"Vlaams-Brabant",
    "wof:name":"Godts P. & M.",
    "wof:placetype":"venue"
},
  "geometry": {"coordinates":[4.5681152344,50.9326553345],"type":"Point"}
}