{
  "type": "Feature",
  "properties": {
    "addr:full":"Chauss\u00c9e De Wavre 100 Jodoigne Brabant Wallon 1370",
    "addr:postcode":"100;1370",
    "addr:street":"Chausse\u0301E De Wavre",
    "iso:country":"BE",
    "sg:address":"Chauss\u00c9e De Wavre 100",
    "sg:city":"Jodoigne",
    "sg:orig_category":"Rundveehouders",
    "sg:phone":"+32 10 81 35 43",
    "sg:postcode":"1370",
    "sg:province":"Brabant Wallon",
    "wof:name":"Eric Teerlinck",
    "wof:placetype":"venue"
},
  "geometry": {"coordinates":[4.8536100388,50.7256851196],"type":"Point"}
}