{
  "type": "Feature",
  "properties": {
    "iso:country":"BE",
    "sg:address":"Avenue De Scheut 238",
    "sg:city":"Bruxelles (anderlecht)",
    "sg:classifiers":[
        {
            "category":"Arena",
            "subcategory":"Sports Club",
            "type":"Entertainment"
        }
    ],
    "sg:phone":"+32 2 523 96 25",
    "sg:postcode":"1070",
    "sg:province":"Bruxelles-Capitale",
    "sg:tags":[
        "federation"
    ],
    "wof:name":"National And Brussels Dart",
    "wof:placetype":"venue"
},
  "geometry": {"coordinates":[4.3098249435,50.8460693359],"type":"Point"}
}