{
  "type": "Feature",
  "properties": {
    "iso:country":"BE",
    "sg:address":"Rue Sur Les Dos 63",
    "sg:city":"Anhee",
    "sg:orig_category":"Woningbouw",
    "sg:phone":"+32 71 79 80 47",
    "sg:postcode":"5537",
    "sg:province":"Namur",
    "wof:name":"Ladouce Et Fils",
    "wof:placetype":"venue"
},
  "geometry": {"coordinates":[4.8141598701,50.3414115906],"type":"Point"}
}