{
  "type": "Feature",
  "properties": {
    "addr:full":"Demerstraat 68 Hasselt Limburg 3500",
    "addr:housenumber":"68",
    "addr:postcode":"3500",
    "addr:street":"Demerstraat",
    "iso:country":"BE",
    "sg:address":"Demerstraat 68",
    "sg:city":"Hasselt",
    "sg:classifiers":[
        {
            "category":"Personal",
            "subcategory":"Beauty Salon",
            "type":"Services"
        }
    ],
    "sg:phone":"+32 11 22 10 19",
    "sg:postcode":"3500",
    "sg:province":"Limburg",
    "sg:tags":[
        "paint",
        "grease",
        "make-up"
    ],
    "wof:name":"Valckeneers E",
    "wof:placetype":"venue"
},
  "geometry": {"coordinates":[5.3385400772,50.9331092834],"type":"Point"}
}