{
  "type": "Feature",
  "properties": {
    "addr:full":"Avenue Th\u00e9odule Gonda 135 Fl\u00e9malle Li\u00e8ge 4400",
    "addr:housenumber":"135",
    "addr:postcode":"4400",
    "addr:street":"Avenue The\u0301Odule Gonda",
    "iso:country":"BE",
    "sg:address":"Avenue Th\u00e9odule Gonda 135",
    "sg:city":"Fl\u00e9malle",
    "sg:classifiers":[
        {
            "category":"Real Estate",
            "subcategory":"Architect",
            "type":"Services"
        }
    ],
    "sg:phone":"+32 4 250 25 58",
    "sg:postcode":"4400",
    "sg:province":"Li\u00e8ge",
    "wof:name":"Lamisse J-c Entr'axes",
    "wof:placetype":"venue"
},
  "geometry": {"coordinates":[5.4514732361,50.6048927307],"type":"Point"}
}