{
  "type": "Feature",
  "properties": {
    "addr:full":"Tennisbaanstraat 74 Gent Oost-Vlaanderen 9000",
    "addr:housenumber":"74",
    "addr:postcode":"9000",
    "addr:street":"Tennisbaanstraat;Oost-Vlaanderen",
    "iso:country":"BE",
    "sg:address":"Tennisbaanstraat 74",
    "sg:city":"Gent",
    "sg:orig_category":"Vertalers and tolken",
    "sg:phone":"+32 9 220 58 03",
    "sg:postcode":"9000",
    "sg:province":"Oost-Vlaanderen",
    "wof:name":"Weyne W. Cbtip/bkvtf",
    "wof:placetype":"venue"
},
  "geometry": {"coordinates":[3.7086820602,51.0418930054],"type":"Point"}
}