{
  "type": "Feature",
  "properties": {
    "iso:country":"BE",
    "sg:address":"Varing 20",
    "sg:city":"Roosdaal",
    "sg:classifiers":[
        {
            "category":"Recreation",
            "type":"Entertainment"
        }
    ],
    "sg:phone":"+32 54 33 85 46",
    "sg:postcode":"1760",
    "sg:province":"Vlaams-Brabant",
    "sg:tags":[
        "diver",
        "amusement"
    ],
    "wof:name":"Discobar Flash",
    "wof:placetype":"venue"
},
  "geometry": {"coordinates":[4.0790791512,50.8429946899],"type":"Point"}
}