{
  "type": "Feature",
  "properties": {
    "addr:full":"Stationsstraat 36 Wachtebeke Oost-Vlaanderen 9185",
    "addr:housenumber":"36",
    "addr:postcode":"9185",
    "addr:street":"Stationsstraat",
    "iso:country":"BE",
    "sg:address":"Stationsstraat 36",
    "sg:city":"Wachtebeke",
    "sg:orig_category":"Grands magasins",
    "sg:phone":"+32 9 345 09 58",
    "sg:postcode":"9185",
    "sg:province":"Oost-Vlaanderen",
    "wof:name":"Henri Braeckman",
    "wof:placetype":"venue"
},
  "geometry": {"coordinates":[3.8615779877,51.1724853516],"type":"Point"}
}