{
  "type": "Feature",
  "properties": {
    "addr:full":"Rue Van Artevelde 124 Bruxelles Bruxelles-Capitale 1000",
    "addr:housenumber":"124",
    "addr:postcode":"1000",
    "addr:street":"Rue Van Artevelde",
    "iso:country":"BE",
    "sg:address":"Rue Van Artevelde 124",
    "sg:city":"Bruxelles",
    "sg:classifiers":[
        {
            "category":"Government",
            "subcategory":"Office",
            "type":"Public Place"
        }
    ],
    "sg:phone":"+32 2 218 38 78",
    "sg:postcode":"1000",
    "sg:province":"Bruxelles-Capitale",
    "sg:tags":[
        "-",
        "tourism",
        "federation"
    ],
    "wof:name":"Brukselbinnenstebuiten",
    "wof:placetype":"venue"
},
  "geometry": {"coordinates":[4.3435487747,50.8463439941],"type":"Point"}
}