{
  "type": "Feature",
  "properties": {
    "addr:full":"Rue Grande 114 Dinant Namur 5500",
    "addr:housenumber":"114",
    "addr:postcode":"5500",
    "addr:street":"Rue Grande",
    "iso:country":"BE",
    "sg:address":"Rue Grande 114",
    "sg:city":"Dinant",
    "sg:classifiers":[
        {
            "category":"Shopping",
            "subcategory":"Used Merchandise",
            "type":"Retail Goods"
        }
    ],
    "sg:phone":"+32 82 22 29 99",
    "sg:postcode":"5500",
    "sg:province":"Namur",
    "sg:tags":[
        "salvage",
        "surplus"
    ],
    "wof:name":"Bruno Solde Sprl",
    "wof:placetype":"venue"
},
  "geometry": {"coordinates":[4.913146019,50.2594566345],"type":"Point"}
}