{
  "type": "Feature",
  "properties": {
    "iso:country":"BE",
    "sg:address":"Boulevard Roosevelt 17",
    "sg:city":"Soignies",
    "sg:classifiers":[
        {
            "category":"Health Services",
            "subcategory":"Hospital",
            "type":"Services"
        }
    ],
    "sg:phone":"+32 67 34 84 11",
    "sg:postcode":"7060",
    "sg:province":"Hainaut",
    "wof:name":"Centre Hospitalier Regional De La Haute Senne",
    "wof:placetype":"venue"
},
  "geometry": {"coordinates":[4.0656938553,50.5749015808],"type":"Point"}
}