{
  "type": "Feature",
  "properties": {
    "iso:country":"BE",
    "sg:address":"Rue Georges Lemoine 102",
    "sg:city":"Charleroi (ransart)",
    "sg:classifiers":[
        {
            "category":"Building & Trades",
            "subcategory":"Construction",
            "type":"Services"
        }
    ],
    "sg:phone":"+32 71 88 69 44",
    "sg:postcode":"6043",
    "sg:province":"Hainaut",
    "sg:tags":[
        "installation",
        "-",
        "central",
        "heating"
    ],
    "wof:name":"Lambois Stephane Chauffage-sanitaire",
    "wof:placetype":"venue"
},
  "geometry": {"coordinates":[4.492043972,50.4524917603],"type":"Point"}
}