{
  "type": "Feature",
  "properties": {
    "addr:full":"Rue Haute 37 Vise Li\u00e8ge 4600",
    "addr:housenumber":"37",
    "addr:postcode":"4600",
    "addr:street":"Rue Haute",
    "iso:country":"BE",
    "sg:address":"Rue Haute 37",
    "sg:city":"Vise",
    "sg:orig_category":"Mat\u00e9riel de T\u00e9l\u00e9communication",
    "sg:phone":"+32 800 33 800",
    "sg:postcode":"4600",
    "sg:province":"Li\u00e8ge",
    "wof:name":"T\u00c9l\u00c9boutique",
    "wof:placetype":"venue"
},
  "geometry": {"coordinates":[5.6963429451,50.7341346741],"type":"Point"}
}