{
  "type": "Feature",
  "properties": {
    "iso:country":"BE",
    "sg:address":"Chauss\u00c9e De Charleroi 108",
    "sg:city":"Sint-gillis/saint-gilles",
    "sg:orig_category":"Editeurs de journaux. Editeurs de revues and p\u00e9riodiques. Services divers aux entreprises",
    "sg:phone":"+32 2 538 41 08",
    "sg:postcode":"1060",
    "sg:province":"Bruxelles-Capitale",
    "wof:name":"Editions Artvox-artexpo",
    "wof:placetype":"venue"
},
  "geometry": {"coordinates":[4.3554801941,50.8280639648],"type":"Point"}
}