{
  "type": "Feature",
  "properties": {
    "addr:full":"Rue Colo Hugues 69 Braine L'alleud (braine-l'alleud) Brabant Wallon 1420",
    "addr:housenumber":"69",
    "addr:postcode":"1420",
    "addr:street":"Rue Colo Hugues",
    "iso:country":"BE",
    "sg:address":"Rue Colo Hugues 69",
    "sg:city":"Braine L'alleud (braine-l'alleud)",
    "sg:classifiers":[
        {
            "category":"Home & Garden",
            "subcategory":"Carpets & Floor Coverings",
            "type":"Retail Goods"
        }
    ],
    "sg:phone":"+32 2 384 25 63",
    "sg:postcode":"1420",
    "sg:province":"Brabant Wallon",
    "sg:tags":[
        "automobile",
        "-",
        "upholstering",
        "cover"
    ],
    "wof:name":"Becker H",
    "wof:placetype":"venue"
},
  "geometry": {"coordinates":[-105.5509109497,38.9978408813],"type":"Point"}
}