{
  "type": "Feature",
  "properties": {
    "iso:country":"BE",
    "sg:address":"Dorpsstraat 1",
    "sg:city":"Boortmeerbeek",
    "sg:orig_category":"Banken and kredietinstellingen",
    "sg:phone":"+32 15 51 23 88",
    "sg:postcode":"3190",
    "sg:province":"Vlaams-Brabant",
    "wof:name":"Kbc",
    "wof:placetype":"venue"
},
  "geometry": {"coordinates":[4.5727472305,50.9808120728],"type":"Point"}
}