{
  "type": "Feature",
  "properties": {
    "addr:full":"Lognoul 6 Ferri\u00e8res Li\u00e8ge 4190",
    "addr:housenumber":"6",
    "addr:postcode":"4190",
    "addr:street":"Lognoul",
    "iso:country":"BE",
    "sg:address":"Lognoul 6",
    "sg:city":"Ferri\u00e8res",
    "sg:classifiers":[
        {
            "category":"Museum",
            "type":"Entertainment"
        }
    ],
    "sg:phone":"+32 86 40 01 98",
    "sg:postcode":"4190",
    "sg:province":"Li\u00e8ge",
    "wof:name":"Mus\u00e9e Du Jouet Asbl",
    "wof:placetype":"venue"
},
  "geometry": {"coordinates":[5.6079139709,50.4007339478],"type":"Point"}
}