{
  "type": "Feature",
  "properties": {
    "addr:full":"Mgr. Roelensstraat 15 Ardooie West-Vlaanderen 8850",
    "addr:housenumber":"15",
    "addr:postcode":"8850",
    "addr:street":"Mgr. Roelensstraat",
    "iso:country":"BE",
    "sg:address":"Mgr. Roelensstraat 15",
    "sg:city":"Ardooie",
    "sg:orig_category":"Assurances. Bureaux de poste",
    "sg:phone":"+32 51 74 41 68",
    "sg:postcode":"8850",
    "sg:province":"West-Vlaanderen",
    "wof:name":"De Post",
    "wof:placetype":"venue"
},
  "geometry": {"coordinates":[3.1991961002,50.9772987366],"type":"Point"}
}