{
  "type": "Feature",
  "properties": {
    "iso:country":"BE",
    "sg:address":"Kerkstraat 78",
    "sg:city":"Mortsel",
    "sg:orig_category":"Advocaten and juridische adviseurs",
    "sg:phone":"+32 3 448 28 84",
    "sg:postcode":"2640",
    "sg:province":"Antwerpen",
    "wof:name":"M. Huysmans",
    "wof:placetype":"venue"
},
  "geometry": {"coordinates":[4.4635310173,51.1681022644],"type":"Point"}
}