{
  "type": "Feature",
  "properties": {
    "iso:country":"BE",
    "sg:address":"Hoeledensebaan 35",
    "sg:city":"Kortenaken",
    "sg:classifiers":[
        {
            "category":"Autos & Motor Vehicles",
            "subcategory":"Fuel & Gas Station",
            "type":"Retail Goods"
        }
    ],
    "sg:phone":"+32 16 77 82 21",
    "sg:postcode":"3471",
    "sg:province":"Vlaams-Brabant",
    "sg:tags":[
        "stations-service",
        "carburants"
    ],
    "wof:name":"Marcel Vannoppen",
    "wof:placetype":"venue"
},
  "geometry": {"coordinates":[4.9809069633,50.8637161255],"type":"Point"}
}