{
  "type": "Feature",
  "properties": {
    "iso:country":"BE",
    "sg:address":"Chauss\u00e9e De Forest 60",
    "sg:city":"Bruxelles (saint-gilles)",
    "sg:classifiers":[
        {
            "category":"Retail",
            "subcategory":"Repair Shop",
            "type":"Services"
        }
    ],
    "sg:phone":"+32 2 544 01 17",
    "sg:postcode":"1060",
    "sg:province":"Bruxelles-Capitale",
    "sg:tags":[
        "-",
        "clothing",
        "alteration"
    ],
    "wof:name":"Quickly Service System Sprl",
    "wof:placetype":"venue"
},
  "geometry": {"coordinates":[4.3406419754,50.8315963745],"type":"Point"}
}