{
  "type": "Feature",
  "properties": {
    "iso:country":"BE",
    "sg:address":"Vroentestraat 15",
    "sg:city":"Halen",
    "sg:orig_category":"Hypotheken and hypotheekbanken Verzekeringsmakelaars and experts",
    "sg:phone":"+32 13 44 17 02",
    "sg:postcode":"3545",
    "sg:province":"Limburg",
    "wof:name":"Kantoor Vanbergen - Nation. Hypotheekkas",
    "wof:placetype":"venue"
},
  "geometry": {"coordinates":[5.1264071465,50.923248291],"type":"Point"}
}