{
  "type": "Feature",
  "properties": {
    "iso:country":"BE",
    "sg:address":"Stationsstraat 95",
    "sg:city":"Berlaar",
    "sg:orig_category":"Boucheries",
    "sg:phone":"+32 3 482 10 82",
    "sg:postcode":"2590",
    "sg:province":"Antwerpen",
    "wof:name":"Wijns Roger",
    "wof:placetype":"venue"
},
  "geometry": {"coordinates":[4.6455669403,51.1150398254],"type":"Point"}
}