{
  "type": "Feature",
  "properties": {
    "addr:full":"Nederenamestraat 215 Oudenaarde Oost-Vlaanderen 9700",
    "addr:housenumber":"215",
    "addr:postcode":"9700",
    "addr:street":"Nederenamestraat",
    "iso:country":"BE",
    "sg:address":"Nederenamestraat 215",
    "sg:city":"Oudenaarde",
    "sg:classifiers":[
        {
            "category":"Personal",
            "subcategory":"Beauty Salon",
            "type":"Services"
        }
    ],
    "sg:phone":"+32 55 31 50 03",
    "sg:postcode":"9700",
    "sg:province":"Oost-Vlaanderen",
    "sg:tags":[
        "lady",
        "-",
        "hairdressing"
    ],
    "wof:name":"Serge",
    "wof:placetype":"venue"
},
  "geometry": {"coordinates":[3.6545000076,50.8692207336],"type":"Point"}
}