{
  "type": "Feature",
  "properties": {
    "addr:full":"Zone Artisanale Weyler 0 Arlon Luxembourg 6706",
    "addr:housenumber":"0",
    "addr:postcode":"6706",
    "addr:street":"Zone Artisanale Weyler",
    "iso:country":"BE",
    "sg:address":"Zone Artisanale Weyler 0",
    "sg:city":"Arlon",
    "sg:orig_category":"Onderdelen and accessoires voor auto's",
    "sg:phone":"+32 63 22 82 11",
    "sg:postcode":"6706",
    "sg:province":"Luxembourg",
    "wof:name":"Nutal-arlon",
    "wof:placetype":"venue"
},
  "geometry": {"coordinates":[5.8697757721,49.6491928101],"type":"Point"}
}