{
  "type": "Feature",
  "properties": {
    "addr:full":"Zeedijk-het Zoute 811 Knokke-heist (knokke) West-Vlaanderen 8300",
    "addr:housenumber":"811",
    "addr:postcode":"8300",
    "addr:street":"Zoute",
    "iso:country":"BE",
    "sg:address":"Zeedijk-het Zoute 811",
    "sg:city":"Knokke-heist (knokke)",
    "sg:classifiers":[
        {
            "category":"Shopping",
            "subcategory":"Clothing, Apparel, & Fashions",
            "type":"Retail Goods"
        }
    ],
    "sg:phone":"+32 50 62 64 96",
    "sg:postcode":"8300",
    "sg:province":"West-Vlaanderen",
    "sg:tags":[
        "leather",
        "-",
        "buckskin",
        "clothing"
    ],
    "wof:name":"People Of The Labyrinths",
    "wof:placetype":"venue"
},
  "geometry": {"coordinates":[3.287694931,51.3467254639],"type":"Point"}
}