{
  "type": "Feature",
  "properties": {
    "iso:country":"BE",
    "sg:address":"Route De Bastogne 26",
    "sg:city":"Ferri\u00e8res",
    "sg:classifiers":[
        {
            "category":"Arts & Performance",
            "subcategory":"Arts Center",
            "type":"Entertainment"
        }
    ],
    "sg:phone":"+32 86 43 32 75",
    "sg:postcode":"4190",
    "sg:province":"Li\u00e8ge",
    "sg:tags":[
        "inspection",
        "automobile",
        "-",
        "examination"
    ],
    "wof:name":"As Station D'inspection",
    "wof:placetype":"venue"
},
  "geometry": {"coordinates":[5.6749601364,50.3685188293],"type":"Point"}
}