{
  "type": "Feature",
  "properties": {
    "addr:full":"Kortrijksesteenweg 380 Gent Oost-Vlaanderen 9000",
    "addr:housenumber":"380",
    "addr:postcode":"9000",
    "addr:street":"Kortrijksesteenweg;Oost-Vlaanderen",
    "iso:country":"BE",
    "sg:address":"Kortrijksesteenweg 380",
    "sg:city":"Gent",
    "sg:orig_category":"Artiesten and kunstenaars",
    "sg:phone":"+32 9 221 01 11",
    "sg:postcode":"9000",
    "sg:province":"Oost-Vlaanderen",
    "wof:name":"R. Van Der Hagen",
    "wof:placetype":"venue"
},
  "geometry": {"coordinates":[3.7160689831,51.0362205505],"type":"Point"}
}