{
  "type": "Feature",
  "properties": {
    "iso:country":"BE",
    "sg:address":"Bourse 1",
    "sg:city":"Bruxelles",
    "sg:classifiers":[
        {
            "category":"Arena",
            "subcategory":"Sports Club",
            "type":"Entertainment"
        }
    ],
    "sg:phone":"+32 2 513 21 23",
    "sg:postcode":"1000",
    "sg:province":"Bruxelles-Capitale",
    "wof:name":"Bureau Sport Contact",
    "wof:placetype":"venue"
},
  "geometry": {"coordinates":[4.3517532349,50.8459815979],"type":"Point"}
}