{
  "type": "Feature",
  "properties": {
    "addr:full":"Stationsstraat 32 Haaltert Oost-Vlaanderen 9450",
    "addr:housenumber":"32",
    "addr:postcode":"9450",
    "addr:street":"Stationsstraat",
    "iso:country":"BE",
    "sg:address":"Stationsstraat 32",
    "sg:city":"Haaltert",
    "sg:orig_category":"Blanchisseries and teintureries",
    "sg:phone":"+32 53 83 56 16",
    "sg:postcode":"9450",
    "sg:province":"Oost-Vlaanderen",
    "wof:name":"Primo Shop",
    "wof:placetype":"venue"
},
  "geometry": {"coordinates":[4.0089712143,50.902141571],"type":"Point"}
}