{
  "type": "Feature",
  "properties": {
    "addr:full":"Langelede 109-111 Wachtebeke Oost-Vlaanderen 9185",
    "addr:postcode":"109-111;9185",
    "iso:country":"BE",
    "sg:address":"Langelede 109-111",
    "sg:city":"Wachtebeke",
    "sg:classifiers":[
        {
            "category":"Airport",
            "subcategory":"International",
            "type":"Transportation"
        }
    ],
    "sg:phone":"+32 9 345 05 28",
    "sg:postcode":"9185",
    "sg:province":"Oost-Vlaanderen",
    "sg:tags":[
        "-",
        "transport"
    ],
    "wof:name":"Van Den Hende A",
    "wof:placetype":"venue"
},
  "geometry": {"coordinates":[3.8586599827,51.1925201416],"type":"Point"}
}