{
  "type": "Feature",
  "properties": {
    "addr:full":"Bergensesteenweg 572ba Halle Vlaams-Brabant 1502",
    "addr:postcode":"1502",
    "addr:street":"Bergensesteenweg 572Ba",
    "iso:country":"BE",
    "sg:address":"Bergensesteenweg 572ba",
    "sg:city":"Halle",
    "sg:orig_category":"Banques and organismes de cr\u00e9dit",
    "sg:phone":"+32 2 356 43 47",
    "sg:postcode":"1502",
    "sg:province":"Vlaams-Brabant",
    "wof:name":"Kbc",
    "wof:placetype":"venue"
},
  "geometry": {"coordinates":[4.2215309143,50.7168464661],"type":"Point"}
}