{
  "type": "Feature",
  "properties": {
    "addr:full":"Beauvoordestraat 24 Veurne West-Vlaanderen 8630",
    "addr:housenumber":"24",
    "addr:postcode":"8630",
    "addr:street":"Beauvoordestraat",
    "iso:country":"BE",
    "sg:address":"Beauvoordestraat 24",
    "sg:city":"Veurne",
    "sg:orig_category":"Slagers",
    "sg:phone":"+32 58 31 54 47",
    "sg:postcode":"8630",
    "sg:province":"West-Vlaanderen",
    "wof:name":"Bruno Cottry",
    "wof:placetype":"venue"
},
  "geometry": {"coordinates":[2.6617588997,51.072681427],"type":"Point"}
}