{
  "type": "Feature",
  "properties": {
    "iso:country":"BE",
    "sg:address":"Rue D'horrues 78",
    "sg:city":"Braine-le-comte",
    "sg:orig_category":"Binnenhuisarchitecten Installatie van houten of kunststof schrijnwerk",
    "sg:phone":"+32 67 56 16 75",
    "sg:postcode":"7090",
    "sg:province":"Hainaut",
    "wof:name":"Guy Maetens",
    "wof:placetype":"venue"
},
  "geometry": {"coordinates":[4.0905909538,50.6249694824],"type":"Point"}
}