{
  "type": "Feature",
  "properties": {
    "iso:country":"BE",
    "sg:address":"Drapstraat 41a",
    "sg:city":"Nazareth",
    "sg:classifiers":[
        {
            "category":"Retail",
            "subcategory":"Laundry & Dry Cleaning",
            "type":"Services"
        }
    ],
    "sg:phone":"+32 9 385 41 54",
    "sg:postcode":"9810",
    "sg:province":"Oost-Vlaanderen",
    "wof:name":"Langeraert M",
    "wof:placetype":"venue"
},
  "geometry": {"coordinates":[3.60364604,50.9596138],"type":"Point"}
}