{
  "type": "Feature",
  "properties": {
    "addr:full":"Bourgognedreef 2 Ichtegem West-Vlaanderen 8480",
    "addr:housenumber":"2",
    "addr:postcode":"8480",
    "addr:street":"Bourgognedreef",
    "iso:country":"BE",
    "sg:address":"Bourgognedreef 2",
    "sg:city":"Ichtegem",
    "sg:classifiers":[
        {
            "category":"Building & Trades",
            "subcategory":"Construction",
            "type":"Services"
        }
    ],
    "sg:phone":"+32 59 29 81 10",
    "sg:postcode":"8480",
    "sg:province":"West-Vlaanderen",
    "sg:tags":[
        "ventilation",
        "conditionn\u00e9",
        "air"
    ],
    "wof:name":"Coolservice",
    "wof:placetype":"venue"
},
  "geometry": {"coordinates":[3.0247159004,51.1437454224],"type":"Point"}
}