{
  "type": "Feature",
  "properties": {
    "addr:full":"Avenue De L\u00b4exposition 339 Jette Bruxelles-Capitale 1090",
    "addr:housenumber":"339",
    "addr:postcode":"1090",
    "addr:street":"Avenue De L\u00b4Exposition",
    "iso:country":"BE",
    "sg:address":"Avenue De L\u00b4exposition 339",
    "sg:city":"Jette",
    "sg:classifiers":[
        {
            "category":"Autos & Motor Vehicles",
            "subcategory":"Fuel & Gas Station",
            "type":"Retail Goods"
        }
    ],
    "sg:phone":"+32 2 479 50 67",
    "sg:postcode":"1090",
    "sg:province":"Bruxelles-Capitale",
    "sg:tags":[
        "stations-service",
        "carburants"
    ],
    "wof:name":"Jet",
    "wof:placetype":"venue"
},
  "geometry": {"coordinates":[4.3167910576,50.886680603],"type":"Point"}
}