{
  "type": "Feature",
  "properties": {
    "addr:full":"Chauss\u00e9e De Stockel 387 Bruxelles (woluwe-saint-pierre) Bruxelles-Capitale 1150",
    "addr:housenumber":"387",
    "addr:postcode":"1150",
    "addr:street":"Chausse\u0301E De Stockel",
    "iso:country":"BE",
    "sg:address":"Chauss\u00e9e De Stockel 387",
    "sg:city":"Bruxelles (woluwe-saint-pierre)",
    "sg:classifiers":[
        {
            "category":"Retail",
            "subcategory":"Auto Repair",
            "type":"Services"
        }
    ],
    "sg:phone":"+32 2 770 88 32",
    "sg:postcode":"1150",
    "sg:province":"Bruxelles-Capitale",
    "sg:tags":[
        "garage"
    ],
    "wof:name":"Auto A V H Sprl",
    "wof:placetype":"venue"
},
  "geometry": {"coordinates":[4.4554390907,50.8425254822],"type":"Point"}
}