{
  "type": "Feature",
  "properties": {
    "addr:full":"Rue De Rochefort 233 Beauraing Namur 5570",
    "addr:housenumber":"233",
    "addr:postcode":"5570",
    "addr:street":"Rue De Rochefort",
    "iso:country":"BE",
    "sg:address":"Rue De Rochefort 233",
    "sg:city":"Beauraing",
    "sg:classifiers":[
        {
            "category":"Manufacturing",
            "subcategory":"Building Materials",
            "type":"Manufacturing & Wholesale Goods"
        }
    ],
    "sg:phone":"+32 82 71 14 44",
    "sg:postcode":"5570",
    "sg:province":"Namur",
    "sg:tags":[
        "cement"
    ],
    "wof:name":"Sokao S.a.",
    "wof:placetype":"venue"
},
  "geometry": {"coordinates":[4.979847908,50.1208229065],"type":"Point"}
}