{
  "type": "Feature",
  "properties": {
    "addr:full":"Avenue Des Faisans 15 Rhode-saint-gen\u00e8se Vlaams-Brabant 1640",
    "addr:housenumber":"15",
    "addr:postcode":"1640",
    "addr:street":"Avenue Des Faisans",
    "iso:country":"BE",
    "sg:address":"Avenue Des Faisans 15",
    "sg:city":"Rhode-saint-gen\u00e8se",
    "sg:classifiers":[
        {
            "category":"Health Services",
            "subcategory":"Doctor",
            "type":"Services"
        }
    ],
    "sg:phone":"+32 2 340 42 40",
    "sg:postcode":"1640",
    "sg:province":"Vlaams-Brabant",
    "sg:tags":[
        "medicinephysicians",
        "surgeon"
    ],
    "wof:name":"Ballet Thierry",
    "wof:placetype":"venue"
},
  "geometry": {"coordinates":[4.372423172,50.7618103027],"type":"Point"}
}