{
  "type": "Feature",
  "properties": {
    "iso:country":"BE",
    "sg:address":"Avenue De Stalingrad 61",
    "sg:city":"Bruxelles",
    "sg:orig_category":"Non-Classified Establishments",
    "sg:phone":"+32 2 514 33 34",
    "sg:postcode":"1000",
    "sg:province":"Bruxelles-Capitale",
    "wof:name":"Arthur",
    "wof:placetype":"venue"
},
  "geometry": {"coordinates":[4.3430070877,50.8409080505],"type":"Point"}
}