{
  "type": "Feature",
  "properties": {
    "iso:country":"BE",
    "sg:address":"Deken Habrakenlaan 12",
    "sg:city":"Beringen",
    "sg:orig_category":"Gespecialiseerde residenti\u00eble bouw",
    "sg:phone":"+32 11 43 27 19",
    "sg:postcode":"3580",
    "sg:province":"Limburg",
    "wof:name":"Louis Aerts",
    "wof:placetype":"venue"
},
  "geometry": {"coordinates":[5.2329349518,51.0465278625],"type":"Point"}
}