{
  "type": "Feature",
  "properties": {
    "iso:country":"BE",
    "sg:address":"Knesselarestraat 143",
    "sg:city":"Beernem (oedelem)",
    "sg:classifiers":[
        {
            "category":"Building & Trades",
            "subcategory":"Landscaping Services",
            "type":"Services"
        }
    ],
    "sg:phone":"+32 50 79 21 06",
    "sg:postcode":"8730",
    "sg:province":"West-Vlaanderen",
    "sg:tags":[
        "moss",
        "removal"
    ],
    "wof:name":"D & F",
    "wof:placetype":"venue"
},
  "geometry": {"coordinates":[3.3578240871,51.1657600403],"type":"Point"}
}