{
  "type": "Feature",
  "properties": {
    "addr:full":"Gaversesteenweg 188 Deinze (petegem-aan-de-leie) Oost-Vlaanderen 9800",
    "addr:housenumber":"188",
    "addr:postcode":"9800",
    "addr:street":"Gaversesteenweg;Oost-Vlaanderen",
    "iso:country":"BE",
    "sg:address":"Gaversesteenweg 188",
    "sg:city":"Deinze (petegem-aan-de-leie)",
    "sg:classifiers":[
        {
            "category":"Banks & Credit Unions",
            "subcategory":"Investment Brokerage",
            "type":"Services"
        }
    ],
    "sg:phone":"+32 478 97 14 18",
    "sg:postcode":"9800",
    "sg:province":"Oost-Vlaanderen",
    "sg:tags":[
        "rental",
        "-",
        "yacht",
        "boat",
        "pleasure"
    ],
    "wof:name":"Van Haver G",
    "wof:placetype":"venue"
},
  "geometry": {"coordinates":[3.530174017,50.9863166809],"type":"Point"}
}