{
  "type": "Feature",
  "properties": {
    "iso:country":"BE",
    "sg:address":"Rue Armand Den\u00e9e 23",
    "sg:city":"Andenne",
    "sg:classifiers":[
        {
            "category":"Freight",
            "type":"Transportation"
        }
    ],
    "sg:phone":"+32 85 84 13 74",
    "sg:postcode":"5300",
    "sg:province":"Namur",
    "sg:tags":[
        "-",
        "transport"
    ],
    "wof:name":"Petitjean Et Fils",
    "wof:placetype":"venue"
},
  "geometry": {"coordinates":[5.0935029984,50.4869613647],"type":"Point"}
}