{
  "type": "Feature",
  "properties": {
    "addr:full":"Wolvenstraat 21 Kortrijk West-Vlaanderen 8500",
    "addr:housenumber":"21",
    "addr:postcode":"8500",
    "addr:street":"Wolvenstraat",
    "iso:country":"BE",
    "sg:address":"Wolvenstraat 21",
    "sg:city":"Kortrijk",
    "sg:classifiers":[
        {
            "category":"Freight",
            "type":"Transportation"
        }
    ],
    "sg:phone":"+32 56 67 37 00",
    "sg:postcode":"8500",
    "sg:province":"West-Vlaanderen",
    "sg:tags":[
        "-",
        "transport"
    ],
    "wof:name":"Fidex Nv",
    "wof:placetype":"venue"
},
  "geometry": {"coordinates":[3.2649400234,50.8137207031],"type":"Point"}
}