{
  "type": "Feature",
  "properties": {
    "addr:full":"Kartuizersvest 67 Lier Antwerpen 2500",
    "addr:housenumber":"67",
    "addr:postcode":"2500",
    "addr:street":"Kartuizersvest",
    "iso:country":"BE",
    "sg:address":"Kartuizersvest 67",
    "sg:city":"Lier",
    "sg:classifiers":[
        {
            "category":"Personal",
            "subcategory":"Barber",
            "type":"Services"
        }
    ],
    "sg:phone":"+32 3 290 89 01",
    "sg:postcode":"2500",
    "sg:province":"Antwerpen",
    "sg:tags":[
        "gentleman",
        "salon",
        "-",
        "hairdressing"
    ],
    "wof:name":"Noeton Haarmode",
    "wof:placetype":"venue"
},
  "geometry": {"coordinates":[4.5696759224,51.134437561],"type":"Point"}
}