{
  "type": "Feature",
  "properties": {
    "iso:country":"BE",
    "sg:address":"Erasme Ruelensvest 7ba",
    "sg:city":"Leuven",
    "sg:orig_category":"Artsen and specialisten",
    "sg:phone":"+32 16 23 67 91",
    "sg:postcode":"3001",
    "sg:province":"Vlaams-Brabant",
    "wof:name":"A. Ausloos",
    "wof:placetype":"venue"
},
  "geometry": {"coordinates":[4.699034214,50.868106842],"type":"Point"}
}