{
  "type": "Feature",
  "properties": {
    "addr:full":"Stationsstraat 52a Nazareth (eke) Oost-Vlaanderen 9810",
    "addr:housenumber":"52a",
    "addr:postcode":"9810",
    "addr:street":"Stationsstraat",
    "iso:country":"BE",
    "sg:address":"Stationsstraat 52a",
    "sg:city":"Nazareth (eke)",
    "sg:classifiers":[
        {
            "category":"Health Services",
            "subcategory":"Doctor",
            "type":"Services"
        }
    ],
    "sg:phone":"+32 9 385 81 81",
    "sg:postcode":"9810",
    "sg:province":"Oost-Vlaanderen",
    "sg:tags":[
        "medicinephysicians",
        "surgeon"
    ],
    "wof:name":"Lampens Inge",
    "wof:placetype":"venue"
},
  "geometry": {"coordinates":[3.6346209049,50.9587173462],"type":"Point"}
}