{
  "type": "Feature",
  "properties": {
    "addr:full":"Rue De L'eglise 7 Linkebeek Vlaams-Brabant 1630",
    "addr:housenumber":"7",
    "addr:postcode":"1630",
    "addr:street":"Rue De L'Eglise",
    "iso:country":"BE",
    "sg:address":"Rue De L'eglise 7",
    "sg:city":"Linkebeek",
    "sg:classifiers":[
        {
            "category":"Professional",
            "subcategory":"Art Services",
            "type":"Services"
        }
    ],
    "sg:phone":"+32 2 380 45 65",
    "sg:postcode":"1630",
    "sg:province":"Vlaams-Brabant",
    "sg:tags":[
        "interior",
        "designer"
    ],
    "wof:name":"Laurent L",
    "wof:placetype":"venue"
},
  "geometry": {"coordinates":[4.3365740776,50.7720947266],"type":"Point"}
}