{
  "type": "Feature",
  "properties": {
    "iso:country":"BE",
    "sg:address":"Rue Libert Lanis 39",
    "sg:city":"Braine-le-ch\u00e2teau",
    "sg:classifiers":[
        {
            "category":"Retail",
            "subcategory":"Event Space",
            "type":"Services"
        }
    ],
    "sg:phone":"+32 2 366 37 17",
    "sg:postcode":"1440",
    "sg:province":"Brabant Wallon",
    "sg:tags":[
        "pipeline"
    ],
    "wof:name":"Soudorent",
    "wof:placetype":"venue"
},
  "geometry": {"coordinates":[4.2753429413,50.6824226379],"type":"Point"}
}