{
  "type": "Feature",
  "properties": {
    "addr:full":"Nieuwe Molenstraat 1ba Sint-niklaas Oost-Vlaanderen 9100",
    "addr:housenumber":"1ba",
    "addr:postcode":"9100",
    "addr:street":"Nieuwe Molenstraat",
    "iso:country":"BE",
    "sg:address":"Nieuwe Molenstraat 1ba",
    "sg:city":"Sint-niklaas",
    "sg:orig_category":"Verhuur cateringmateriaal and evenementuitrusting Winkelinrichting and handelsuitrusting Gh",
    "sg:phone":"+32 3 780 70 53",
    "sg:postcode":"9100",
    "sg:province":"Oost-Vlaanderen",
    "wof:name":"Euro Tap Rent",
    "wof:placetype":"venue"
},
  "geometry": {"coordinates":[4.1524448395,51.1758155823],"type":"Point"}
}