{
  "type": "Feature",
  "properties": {
    "addr:full":"Geluwestraat 92 Zonnebeke West-Vlaanderen 8980",
    "addr:housenumber":"92",
    "addr:postcode":"8980",
    "addr:street":"Geluwestraat",
    "iso:country":"BE",
    "sg:address":"Geluwestraat 92",
    "sg:city":"Zonnebeke",
    "sg:orig_category":"Herstellingen and onderhoud van auto's",
    "sg:phone":"+32 57 46 61 03",
    "sg:postcode":"8980",
    "sg:province":"West-Vlaanderen",
    "wof:name":"Garage Degrande",
    "wof:placetype":"venue"
},
  "geometry": {"coordinates":[3.0367848873,50.8397941589],"type":"Point"}
}