{
  "type": "Feature",
  "properties": {
    "addr:full":"Rue Saint-nicolas 91 Li\u00c8ge Li\u00e8ge 4000",
    "addr:housenumber":"91",
    "addr:postcode":"4000",
    "addr:street":"Rue Saint-Nicolas",
    "iso:country":"BE",
    "sg:address":"Rue Saint-nicolas 91",
    "sg:city":"Li\u00c8ge",
    "sg:orig_category":"Artistes ind\u00e9pendants",
    "sg:phone":"+32 4 252 64 10",
    "sg:postcode":"4000",
    "sg:province":"Li\u00e8ge",
    "wof:name":"Habsch",
    "wof:placetype":"venue"
},
  "geometry": {"coordinates":[5.5456390381,50.6350440979],"type":"Point"}
}