{
  "type": "Feature",
  "properties": {
    "addr:full":"Avenue Van Crombrugghe 20 Bruxelles (woluwe-saint-pierre) Bruxelles-Capitale 1150",
    "addr:housenumber":"20",
    "addr:postcode":"1150",
    "addr:street":"Avenue Van Crombrugghe",
    "iso:country":"BE",
    "sg:address":"Avenue Van Crombrugghe 20",
    "sg:city":"Bruxelles (woluwe-saint-pierre)",
    "sg:classifiers":[
        {
            "category":"Professional",
            "subcategory":"Management & Consulting",
            "type":"Services"
        }
    ],
    "sg:phone":"+32 2 772 90 19",
    "sg:postcode":"1150",
    "sg:province":"Bruxelles-Capitale",
    "sg:tags":[
        "consultant"
    ],
    "wof:name":"Caroben Sprl",
    "wof:placetype":"venue"
},
  "geometry": {"coordinates":[4.4572019577,50.8271484375],"type":"Point"}
}