{
  "type": "Feature",
  "properties": {
    "iso:country":"BE",
    "sg:address":"Hogeweg 411",
    "sg:city":"Brugge",
    "sg:orig_category":"Producteurs de l\u00e9gumes",
    "sg:phone":"+32 50 31 65 37",
    "sg:postcode":"8200",
    "sg:province":"West-Vlaanderen",
    "wof:name":"Marc Lootens",
    "wof:placetype":"venue"
},
  "geometry": {"coordinates":[3.1941399574,51.2070503235],"type":"Point"}
}