{
  "type": "Feature",
  "properties": {
    "addr:full":"Rue Joseph Wauters 34 Amay Li\u00e8ge 4540",
    "addr:housenumber":"34",
    "addr:postcode":"4540",
    "addr:street":"Rue Joseph Wauters",
    "iso:country":"BE",
    "sg:address":"Rue Joseph Wauters 34",
    "sg:city":"Amay",
    "sg:orig_category":"S\u00e9curit\u00e9 sociale",
    "sg:phone":"+32 85 31 41 62",
    "sg:postcode":"4540",
    "sg:province":"Li\u00e8ge",
    "wof:name":"Mutualit\u00c9 Socialiste",
    "wof:placetype":"venue"
},
  "geometry": {"coordinates":[5.3203110695,50.5469589233],"type":"Point"}
}