{
  "type": "Feature",
  "properties": {
    "iso:country":"BE",
    "sg:address":"Weyerstraat 22",
    "sg:city":"Nieuwerkerken",
    "sg:orig_category":"Kapsalons",
    "sg:phone":"+32 11 31 40 95",
    "sg:postcode":"3850",
    "sg:province":"Limburg",
    "wof:name":"Coiffure Patricia",
    "wof:placetype":"venue"
},
  "geometry": {"coordinates":[5.2396087646,50.8771324158],"type":"Point"}
}