{
  "type": "Feature",
  "properties": {
    "iso:country":"BE",
    "sg:address":"Brugsesteenweg 223",
    "sg:city":"Kuurne",
    "sg:orig_category":"Immobili\u00ebnkantoren",
    "sg:phone":"+32 56 35 28 62",
    "sg:postcode":"8520",
    "sg:province":"West-Vlaanderen",
    "wof:name":"Binolux",
    "wof:placetype":"venue"
},
  "geometry": {"coordinates":[3.2701981068,50.8578605652],"type":"Point"}
}