{
  "type": "Feature",
  "properties": {
    "iso:country":"BE",
    "sg:address":"Kerkstraat 11",
    "sg:city":"Baarle-hertog",
    "sg:orig_category":"Openbare veiligheid",
    "sg:phone":"+32 14 69 80 70",
    "sg:postcode":"2387",
    "sg:province":"Antwerpen",
    "wof:name":"Federale Politie",
    "wof:placetype":"venue"
},
  "geometry": {"coordinates":[4.9292497635,51.4418373108],"type":"Point"}
}