{
  "type": "Feature",
  "properties": {
    "addr:full":"Grimbergsesteenweg 253 Vilvoorde Vlaams-Brabant 1800",
    "addr:housenumber":"253",
    "addr:postcode":"1800",
    "addr:street":"Grimbergsesteenweg",
    "iso:country":"BE",
    "sg:address":"Grimbergsesteenweg 253",
    "sg:city":"Vilvoorde",
    "sg:classifiers":[
        {
            "category":"Cafe",
            "type":"Food & Drink"
        }
    ],
    "sg:phone":"+32 2 252 34 39",
    "sg:postcode":"1800",
    "sg:province":"Vlaams-Brabant",
    "sg:tags":[
        "caf\u00e9s"
    ],
    "wof:name":"Marie-jeanne Wyns",
    "wof:placetype":"venue"
},
  "geometry": {"coordinates":[4.4050002098,50.9252090454],"type":"Point"}
}