{
  "type": "Feature",
  "properties": {
    "iso:country":"BE",
    "sg:address":"Neerstraat 103",
    "sg:city":"Appelterre-eichem",
    "sg:classifiers":[
        {
            "category":"Shopping",
            "subcategory":"Tobacco",
            "type":"Retail Goods"
        }
    ],
    "sg:phone":"+32 54 31 98 98",
    "sg:postcode":"9400",
    "sg:province":"Oost-Vlaanderen",
    "sg:tags":[
        "cigarette"
    ],
    "wof:name":"Torrekens Tabaksindustrie Nv",
    "wof:placetype":"venue"
},
  "geometry": {"coordinates":[3.9666690826,50.8090896606],"type":"Point"}
}