{
  "type": "Feature",
  "properties": {
    "iso:country":"BE",
    "sg:address":"Oudenaardsesteenweg 245",
    "sg:city":"Avelgem",
    "sg:orig_category":"Transports routiers de marchandises",
    "sg:phone":"+32 55 38 83 50",
    "sg:postcode":"8581",
    "sg:province":"West-Vlaanderen",
    "wof:name":"Transport W H L",
    "wof:placetype":"venue"
},
  "geometry": {"coordinates":[3.4701399803,50.7861595154],"type":"Point"}
}