{
  "type": "Feature",
  "properties": {
    "iso:country":"BE",
    "sg:address":"Medialaan 36",
    "sg:city":"Vilvoorde",
    "sg:classifiers":[
        {
            "category":"Internet Cafe",
            "subcategory":"None",
            "type":"Food & Drink"
        }
    ],
    "sg:phone":"+32 2 418 40 00",
    "sg:postcode":"1800",
    "sg:province":"Vlaams-Brabant",
    "sg:tags":[
        "access",
        "-",
        "provider"
    ],
    "wof:name":"At&t",
    "wof:placetype":"venue"
},
  "geometry": {"coordinates":[4.3995919228,50.9150123596],"type":"Point"}
}