{
  "type": "Feature",
  "properties": {
    "addr:full":"Avenue De Houffalize 38 Libramont-chevigny (libramont) Luxembourg 6800",
    "addr:housenumber":"38",
    "addr:postcode":"6800",
    "addr:street":"Avenue De Houffalize",
    "iso:country":"BE",
    "sg:address":"Avenue De Houffalize 38",
    "sg:city":"Libramont-chevigny (libramont)",
    "sg:classifiers":[
        {
            "category":"Home & Garden",
            "subcategory":"Carpets & Floor Coverings",
            "type":"Retail Goods"
        }
    ],
    "sg:phone":"+32 61 22 20 45",
    "sg:postcode":"6800",
    "sg:province":"Luxembourg",
    "sg:tags":[
        "delivery",
        "-",
        "van"
    ],
    "wof:name":"Milard",
    "wof:placetype":"venue"
},
  "geometry": {"coordinates":[5.3761348724,49.9199943542],"type":"Point"}
}