{
  "type": "Feature",
  "properties": {
    "iso:country":"BE",
    "sg:address":"Kruishoutemstraat 16",
    "sg:city":"Zulte",
    "sg:orig_category":"Zuivelproducten and spijsolie Gh",
    "sg:phone":"+32 9 380 12 24",
    "sg:postcode":"9870",
    "sg:province":"Oost-Vlaanderen",
    "wof:name":"Gedo",
    "wof:placetype":"venue"
},
  "geometry": {"coordinates":[3.4989750385,50.9504890442],"type":"Point"}
}