{
  "type": "Feature",
  "properties": {
    "addr:full":"Av. Gloires Nationales 126 Ganshoren/ganshoren Bruxelles-Capitale 1083",
    "addr:housenumber":"126",
    "addr:postcode":"1083",
    "addr:street":"Av. Gloires Nationales",
    "iso:country":"BE",
    "sg:address":"Av. Gloires Nationales 126",
    "sg:city":"Ganshoren/ganshoren",
    "sg:orig_category":"Formation permanente",
    "sg:phone":"+32 2 420 10 26",
    "sg:postcode":"1083",
    "sg:province":"Bruxelles-Capitale",
    "wof:name":"Leerg.taal-handelsstudie",
    "wof:placetype":"venue"
},
  "geometry": {"coordinates":[4.31478405,50.8677787781],"type":"Point"}
}