{
  "type": "Feature",
  "properties": {
    "addr:full":"Statiestraat 2 Lichtervelde West-Vlaanderen 8810",
    "addr:housenumber":"2",
    "addr:postcode":"8810",
    "addr:street":"Statiestraat",
    "iso:country":"BE",
    "sg:address":"Statiestraat 2",
    "sg:city":"Lichtervelde",
    "sg:orig_category":"Schoenen",
    "sg:phone":"+32 51 72 76 94",
    "sg:postcode":"8810",
    "sg:province":"West-Vlaanderen",
    "wof:name":"Huis Napos",
    "wof:placetype":"venue"
},
  "geometry": {"coordinates":[3.1411089897,51.0263137817],"type":"Point"}
}