{
  "type": "Feature",
  "properties": {
    "iso:country":"BE",
    "sg:address":"Rue Du Condroz 3",
    "sg:city":"Ciney",
    "sg:classifiers":[
        {
            "category":"Organizations",
            "subcategory":"Membership Organization",
            "type":"Services"
        }
    ],
    "sg:phone":"+32 83 21 65 25",
    "sg:postcode":"5590",
    "sg:province":"Namur",
    "sg:tags":[
        "de",
        "food",
        "organisation",
        "\u00c0",
        "fast",
        "catering",
        "emporter",
        "f\u00cates",
        "restaurants"
    ],
    "wof:name":"Le Creta",
    "wof:placetype":"venue"
},
  "geometry": {"coordinates":[5.1029210091,50.2972793579],"type":"Point"}
}