{
  "type": "Feature",
  "properties": {
    "addr:full":"Merelbekestationplein 2a Gent (ledeberg) Oost-Vlaanderen 9050",
    "addr:housenumber":"2a",
    "addr:postcode":"9050",
    "addr:street":"Merelbekestationplein",
    "iso:country":"BE",
    "sg:address":"Merelbekestationplein 2a",
    "sg:city":"Gent (ledeberg)",
    "sg:classifiers":[
        {
            "category":"Real Estate",
            "subcategory":"Real Estate Services",
            "type":"Services"
        }
    ],
    "sg:phone":"+32 9 230 58 58",
    "sg:postcode":"9050",
    "sg:province":"Oost-Vlaanderen",
    "wof:name":"Statimmo Nv",
    "wof:placetype":"venue"
},
  "geometry": {"coordinates":[3.7635610104,51.0195617676],"type":"Point"}
}