{
  "type": "Feature",
  "properties": {
    "addr:full":"Kon Boudewijnstraat 142 Kuurne West-Vlaanderen 8520",
    "addr:housenumber":"142",
    "addr:postcode":"8520",
    "addr:street":"Kon Boudewijnstraat",
    "iso:country":"BE",
    "sg:address":"Kon Boudewijnstraat 142",
    "sg:city":"Kuurne",
    "sg:orig_category":"Diverse bedrijfsbeheeradviesbureaus",
    "sg:phone":"+32 56 70 04 67",
    "sg:postcode":"8520",
    "sg:province":"West-Vlaanderen",
    "wof:name":"G.de Vreese",
    "wof:placetype":"venue"
},
  "geometry": {"coordinates":[3.280121088,50.8621368408],"type":"Point"}
}