{
  "type": "Feature",
  "properties": {
    "addr:full":"Hoogstraat 64 Box 5 Haaltert Oost-Vlaanderen 9450",
    "addr:housenumber":"64;5",
    "addr:postcode":"9450",
    "addr:street":"Hoogstraat;Box",
    "iso:country":"BE",
    "sg:address":"Hoogstraat 64 Box 5",
    "sg:city":"Haaltert",
    "sg:classifiers":[
        {
            "category":"Professional",
            "subcategory":"Lawyer & Legal Services",
            "type":"Services"
        }
    ],
    "sg:phone":"+32 53 83 25 52",
    "sg:postcode":"9450",
    "sg:province":"Oost-Vlaanderen",
    "wof:name":"Boeykens Marc",
    "wof:placetype":"venue"
},
  "geometry": {"coordinates":[4.0031328201,50.8985061646],"type":"Point"}
}