{
  "type": "Feature",
  "properties": {
    "iso:country":"BE",
    "sg:address":"Oudenaardestraat 75",
    "sg:city":"Zulte",
    "sg:orig_category":"Dakwerken Industri\u00eble and commerci\u00eble bouw",
    "sg:phone":"+32 9 388 75 51",
    "sg:postcode":"9870",
    "sg:province":"Oost-Vlaanderen",
    "wof:name":"Devicon",
    "wof:placetype":"venue"
},
  "geometry": {"coordinates":[3.4755558968,50.9288482666],"type":"Point"}
}