{
  "type": "Feature",
  "properties": {
    "iso:country":"BE",
    "sg:address":"Rue Hamoir 197",
    "sg:city":"La Louviere",
    "sg:orig_category":"Onderdelen and accessoires voor auto's",
    "sg:phone":"+32 64 26 52 14",
    "sg:postcode":"7100",
    "sg:province":"Hainaut",
    "wof:name":"Technicar La Louviere",
    "wof:placetype":"venue"
},
  "geometry": {"coordinates":[4.1962127686,50.4750061035],"type":"Point"}
}