{
  "type": "Feature",
  "properties": {
    "addr:full":"Lange Reeschapstraat 45 Maaseik Limburg 3680",
    "addr:housenumber":"45",
    "addr:postcode":"3680",
    "addr:street":"Lange Reeschapstraat",
    "iso:country":"BE",
    "sg:address":"Lange Reeschapstraat 45",
    "sg:city":"Maaseik",
    "sg:classifiers":[
        {
            "category":"Arena",
            "subcategory":"Sports Club",
            "type":"Entertainment"
        }
    ],
    "sg:phone":"+32 89 86 39 98",
    "sg:postcode":"3680",
    "sg:province":"Limburg",
    "sg:tags":[
        "de"
    ],
    "wof:name":"Neeroeteren Bc Fv",
    "wof:placetype":"venue"
},
  "geometry": {"coordinates":[5.791285038,51.0954208374],"type":"Point"}
}