{
  "type": "Feature",
  "properties": {
    "addr:full":"Koolmijnlaan 431 Heusden-zolder Limburg 3550",
    "addr:housenumber":"431",
    "addr:postcode":"3550",
    "addr:street":"Koolmijnlaan",
    "iso:country":"BE",
    "sg:address":"Koolmijnlaan 431",
    "sg:city":"Heusden-zolder",
    "sg:classifiers":[
        {
            "category":"Fast Food",
            "type":"Food & Drink"
        }
    ],
    "sg:phone":"+32 11 57 17 97",
    "sg:postcode":"3550",
    "sg:province":"Limburg",
    "sg:tags":[
        "meeneem",
        "restaurant"
    ],
    "wof:name":"Frituur Rena",
    "wof:placetype":"venue"
},
  "geometry": {"coordinates":[5.3375310898,51.0359802246],"type":"Point"}
}