{
  "type": "Feature",
  "properties": {
    "addr:full":"Chauss\u00e9e De Bruxelles 105 Bruxelles (forest) Bruxelles-Capitale 1190",
    "addr:housenumber":"105",
    "addr:postcode":"1190",
    "addr:street":"Chausse\u0301E De Bruxelles",
    "iso:country":"BE",
    "sg:address":"Chauss\u00e9e De Bruxelles 105",
    "sg:city":"Bruxelles (forest)",
    "sg:classifiers":[
        {
            "category":"Health Services",
            "subcategory":"Doctor",
            "type":"Services"
        }
    ],
    "sg:phone":"+32 2 347 41 19",
    "sg:postcode":"1190",
    "sg:province":"Bruxelles-Capitale",
    "sg:tags":[
        "medicinephysicians",
        "surgeon"
    ],
    "wof:name":"Bazi Akram-michel",
    "wof:placetype":"venue"
},
  "geometry": {"coordinates":[4.3237800598,50.8128700256],"type":"Point"}
}