{
  "type": "Feature",
  "properties": {
    "iso:country":"BE",
    "sg:address":"Sint-antoniusstraat 7ba",
    "sg:city":"Riemst",
    "sg:orig_category":"Herstellingen and onderhoud van auto's",
    "sg:phone":"+32 12 45 21 80",
    "sg:postcode":"3770",
    "sg:province":"Limburg",
    "wof:name":"Michel Tilkin",
    "wof:placetype":"venue"
},
  "geometry": {"coordinates":[5.5882940292,50.7908096313],"type":"Point"}
}