{
  "type": "Feature",
  "properties": {
    "iso:country":"BE",
    "sg:address":"Rue De La Motte 119",
    "sg:city":"Huy",
    "sg:classifiers":[
        {
            "category":"Fast Food",
            "type":"Food & Drink"
        }
    ],
    "sg:phone":"+32 85 21 59 22",
    "sg:postcode":"4500",
    "sg:province":"Li\u00e8ge",
    "sg:tags":[
        "meeneem",
        "restaurant"
    ],
    "wof:name":"Friterie Chez Sonia",
    "wof:placetype":"venue"
},
  "geometry": {"coordinates":[5.2539582253,50.5261497498],"type":"Point"}
}