{
  "type": "Feature",
  "properties": {
    "iso:country":"BE",
    "sg:address":"Duinenlaan 128",
    "sg:city":"Middelkerke",
    "sg:orig_category":"Schoonheidssalons",
    "sg:phone":"+32 59 30 44 34",
    "sg:postcode":"8434",
    "sg:province":"West-Vlaanderen",
    "wof:name":"Fabienne Coucke/westende",
    "wof:placetype":"venue"
},
  "geometry": {"coordinates":[2.7708508968,51.1648445129],"type":"Point"}
}