{
  "type": "Feature",
  "properties": {
    "iso:country":"BE",
    "sg:address":"Vlierboomlaan 5",
    "sg:city":"Grimbergen",
    "sg:classifiers":[
        {
            "category":"Health Services",
            "subcategory":"Dentist",
            "type":"Services"
        }
    ],
    "sg:phone":"+32 2 270 93 93",
    "sg:postcode":"1850",
    "sg:province":"Vlaams-Brabant",
    "wof:name":"Pelgrim H",
    "wof:placetype":"venue"
},
  "geometry": {"coordinates":[4.37647295,50.9296455383],"type":"Point"}
}