{
  "type": "Feature",
  "properties": {
    "iso:country":"BE",
    "sg:address":"Avenue Chant Des Oiseaux 4",
    "sg:city":"Jurbeke",
    "sg:classifiers":[
        {
            "category":"Arena",
            "subcategory":"Sports Club",
            "type":"Entertainment"
        }
    ],
    "sg:phone":"+32 475 26 04 96",
    "sg:postcode":"7050",
    "sg:province":"Hainaut",
    "sg:tags":[
        "de"
    ],
    "wof:name":"Centre Jurbise",
    "wof:placetype":"venue"
},
  "geometry": {"coordinates":[3.9068210125,50.5252532959],"type":"Point"}
}