{
  "type": "Feature",
  "properties": {
    "iso:country":"BE",
    "sg:address":"Wespelaarsebaan 300",
    "sg:city":"Boortmeerbeek",
    "sg:orig_category":"Boekhouders",
    "sg:phone":"+32 16 60 14 90",
    "sg:postcode":"3190",
    "sg:province":"Vlaams-Brabant",
    "wof:name":"Magda Maes",
    "wof:placetype":"venue"
},
  "geometry": {"coordinates":[4.6043071747,50.9653434753],"type":"Point"}
}