{
  "type": "Feature",
  "properties": {
    "addr:full":"Benedenstraat 112 Geraardsbergen (zandbergen) Oost-Vlaanderen 9506",
    "addr:housenumber":"112",
    "addr:postcode":"9506",
    "addr:street":"Benedenstraat;Zandbergen Oost-Vlaanderen",
    "iso:country":"BE",
    "sg:address":"Benedenstraat 112",
    "sg:city":"Geraardsbergen (zandbergen)",
    "sg:classifiers":[
        {
            "category":"Health Services",
            "subcategory":"Health Practitioner",
            "type":"Services"
        }
    ],
    "sg:phone":"+32 54 32 22 41",
    "sg:postcode":"9506",
    "sg:province":"Oost-Vlaanderen",
    "sg:tags":[
        "physiotherapist"
    ],
    "wof:name":"De Deyn J",
    "wof:placetype":"venue"
},
  "geometry": {"coordinates":[3.960160017,50.8053321838],"type":"Point"}
}