{
  "type": "Feature",
  "properties": {
    "iso:country":"BE",
    "sg:address":"Zeeweg 61",
    "sg:city":"Oudenburg",
    "sg:classifiers":[
        {
            "category":"Autos & Motor Vehicles",
            "subcategory":"Auto Supplies",
            "type":"Retail Goods"
        }
    ],
    "sg:postcode":"8460",
    "sg:province":"West-Vlaanderen",
    "sg:tags":[
        "automobile",
        "-",
        "equipment",
        "air conditioning"
    ],
    "wof:name":"Autotechniek Meyns",
    "wof:placetype":"venue"
},
  "geometry": {"coordinates":[3.0210769176,51.1760292053],"type":"Point"}
}