{
  "type": "Feature",
  "properties": {
    "addr:full":"Pinchet 41 Philippeville (jamagne) Namur 5600",
    "addr:housenumber":"41",
    "addr:postcode":"5600",
    "addr:street":"Pinchet",
    "iso:country":"BE",
    "sg:address":"Pinchet 41",
    "sg:city":"Philippeville (jamagne)",
    "sg:classifiers":[
        {
            "category":"Animal Shelter",
            "type":"Public Place"
        }
    ],
    "sg:phone":"+32 71 66 61 56",
    "sg:postcode":"5600",
    "sg:province":"Namur",
    "wof:name":"Chenil De Pinchet",
    "wof:placetype":"venue"
},
  "geometry": {"coordinates":[4.5094370842,50.2258338928],"type":"Point"}
}