{
  "type": "Feature",
  "properties": {
    "iso:country":"BE",
    "sg:address":"Veldstraat 321",
    "sg:city":"Temse",
    "sg:orig_category":"Varkenskwekers",
    "sg:phone":"+32 3 771 08 58",
    "sg:postcode":"9140",
    "sg:province":"Oost-Vlaanderen",
    "wof:name":"Maria Van Hoey",
    "wof:placetype":"venue"
},
  "geometry": {"coordinates":[4.2145829201,51.1521987915],"type":"Point"}
}