{
  "type": "Feature",
  "properties": {
    "addr:full":"Chemin De Sn\u00e9viot 47 Bouillon (poupehan) Luxembourg 6830",
    "addr:housenumber":"47",
    "addr:postcode":"6830",
    "addr:street":"Chemin De Sne\u0301Viot",
    "iso:country":"BE",
    "sg:address":"Chemin De Sn\u00e9viot 47",
    "sg:city":"Bouillon (poupehan)",
    "sg:classifiers":[
        {
            "category":"Wholesale",
            "subcategory":"Fruits & Vegetables",
            "type":"Manufacturing & Wholesale Goods"
        }
    ],
    "sg:phone":"+32 61 46 72 07",
    "sg:postcode":"6830",
    "sg:province":"Luxembourg",
    "sg:tags":[
        "whol",
        "-"
    ],
    "wof:name":"Debune Alain-fruidor",
    "wof:placetype":"venue"
},
  "geometry": {"coordinates":[5.0699849129,49.7954597473],"type":"Point"}
}