{
  "type": "Feature",
  "properties": {
    "iso:country":"BE",
    "sg:address":"Rue Du Ch\u00c2teau 55",
    "sg:city":"Houyet",
    "sg:orig_category":"Bloemen and planten Geschenken and souvenirs Tuinbenodigdheden",
    "sg:phone":"+32 82 66 65 03",
    "sg:postcode":"5564",
    "sg:province":"Namur",
    "wof:name":"Jardilesse",
    "wof:placetype":"venue"
},
  "geometry": {"coordinates":[5.0614261627,50.1595497131],"type":"Point"}
}