{
  "type": "Feature",
  "properties": {
    "addr:full":"Chauss\u00c9e D'ecaussinnes 100 Braine-le-comte Hainaut 7090",
    "addr:housenumber":"100",
    "addr:postcode":"7090",
    "addr:street":"Chausse\u0301E D'Ecaussinnes",
    "iso:country":"BE",
    "sg:address":"Chauss\u00c9e D'ecaussinnes 100",
    "sg:city":"Braine-le-comte",
    "sg:orig_category":"Fitnesscentra Sportclubs",
    "sg:phone":"+32 67 55 36 28",
    "sg:postcode":"7090",
    "sg:province":"Hainaut",
    "wof:name":"Mondial Fit Gym",
    "wof:placetype":"venue"
},
  "geometry": {"coordinates":[4.1323227882,50.6010246277],"type":"Point"}
}