{
  "type": "Feature",
  "properties": {
    "addr:full":"Stationsstraat 89 Hulshout Antwerpen 2235",
    "addr:housenumber":"89",
    "addr:postcode":"2235",
    "addr:street":"Stationsstraat",
    "iso:country":"BE",
    "sg:address":"Stationsstraat 89",
    "sg:city":"Hulshout",
    "sg:classifiers":[
        {
            "category":"Insurance",
            "subcategory":"Life Insurance",
            "type":"Services"
        }
    ],
    "sg:phone":"+32 16 69 93 76",
    "sg:postcode":"2235",
    "sg:province":"Antwerpen",
    "sg:tags":[
        "assurance"
    ],
    "wof:name":"Zakenkantoor Thys",
    "wof:placetype":"venue"
},
  "geometry": {"coordinates":[4.8268771172,51.0591392517],"type":"Point"}
}