{
  "type": "Feature",
  "properties": {
    "iso:country":"BE",
    "sg:address":"Sint-salvatorstraat 100",
    "sg:city":"Gent",
    "sg:classifiers":[
        {
            "category":"Cafe",
            "type":"Food & Drink"
        }
    ],
    "sg:phone":"+32 9 233 70 14",
    "sg:postcode":"9000",
    "sg:province":"Oost-Vlaanderen",
    "sg:tags":[
        "caf\u00e9s"
    ],
    "wof:name":"Anita Van Messem",
    "wof:placetype":"venue"
},
  "geometry": {"coordinates":[3.7295389175,51.0672225952],"type":"Point"}
}