{
  "type": "Feature",
  "properties": {
    "addr:full":"Rue Des Remparts 43bb Bastogne Luxembourg 6600",
    "addr:housenumber":"43bb",
    "addr:postcode":"6600",
    "addr:street":"Rue Des Remparts",
    "iso:country":"BE",
    "sg:address":"Rue Des Remparts 43bb",
    "sg:city":"Bastogne",
    "sg:orig_category":"Enseignement maternel and primaire",
    "sg:phone":"+32 61 21 23 91",
    "sg:postcode":"6600",
    "sg:province":"Luxembourg",
    "wof:name":"E.f.l. Notre-dame",
    "wof:placetype":"venue"
},
  "geometry": {"coordinates":[5.7172417641,50.0038414001],"type":"Point"}
}