{
  "type": "Feature",
  "properties": {
    "iso:country":"BE",
    "sg:address":"Kerkstraat 92",
    "sg:city":"Lochristi",
    "sg:classifiers":[
        {
            "category":"Insurance",
            "subcategory":"Life Insurance",
            "type":"Services"
        }
    ],
    "sg:phone":"+32 9 355 57 98",
    "sg:postcode":"9080",
    "sg:province":"Oost-Vlaanderen",
    "sg:tags":[
        "assurance"
    ],
    "wof:name":"Kantoor Van Waes En Co",
    "wof:placetype":"venue"
},
  "geometry": {"coordinates":[3.8664059639,51.1238021851],"type":"Point"}
}