{
  "type": "Feature",
  "properties": {
    "iso:country":"BE",
    "sg:address":"Rue De M\u00e9rode 266",
    "sg:city":"Bruxelles (forest)",
    "sg:classifiers":[
        {
            "category":"Home & Garden",
            "subcategory":"Hardware",
            "type":"Retail Goods"
        }
    ],
    "sg:phone":"+32 2 538 92 68",
    "sg:postcode":"1190",
    "sg:province":"Bruxelles-Capitale",
    "sg:tags":[
        "gate",
        "opener",
        "door",
        "automatic"
    ],
    "wof:name":"*faac*-e.f. Belgium Sprl",
    "wof:placetype":"venue"
},
  "geometry": {"coordinates":[4.3317480087,50.8287773132],"type":"Point"}
}