{
  "type": "Feature",
  "properties": {
    "iso:country":"BE",
    "sg:address":"Grasbos 32",
    "sg:city":"Diest (molenstede)",
    "sg:classifiers":[
        {
            "category":"Real Estate",
            "subcategory":"Architect",
            "type":"Services"
        }
    ],
    "sg:phone":"+32 13 31 25 01",
    "sg:postcode":"3294",
    "sg:province":"Vlaams-Brabant",
    "wof:name":"Van Gorp V",
    "wof:placetype":"venue"
},
  "geometry": {"coordinates":[5.0133299828,51.0038795471],"type":"Point"}
}