{
  "type": "Feature",
  "properties": {
    "addr:full":"Velmerlaan 159 Sint-truiden Limburg 3806",
    "addr:housenumber":"159",
    "addr:postcode":"sint-truiden;3806",
    "addr:street":"Velmerlaan",
    "iso:country":"BE",
    "sg:address":"Velmerlaan 159",
    "sg:city":"Sint-truiden",
    "sg:orig_category":"Plaatsen van vloer- and muurbekleding",
    "sg:phone":"+32 11 68 36 73",
    "sg:postcode":"3806",
    "sg:province":"Limburg",
    "wof:name":"Albert Massin",
    "wof:placetype":"venue"
},
  "geometry": {"coordinates":[5.1364130974,50.7844963074],"type":"Point"}
}