{
  "type": "Feature",
  "properties": {
    "addr:full":"Fazantenstraat 14 Harelbeke West-Vlaanderen 8530",
    "addr:housenumber":"14",
    "addr:postcode":"8530",
    "addr:street":"Fazantenstraat",
    "iso:country":"BE",
    "sg:address":"Fazantenstraat 14",
    "sg:city":"Harelbeke",
    "sg:classifiers":[
        {
            "category":"Real Estate",
            "subcategory":"Architect",
            "type":"Services"
        }
    ],
    "sg:phone":"+32 56 71 99 59",
    "sg:postcode":"8530",
    "sg:province":"West-Vlaanderen",
    "wof:name":"Vereecke L",
    "wof:placetype":"venue"
},
  "geometry": {"coordinates":[3.3223700523,50.8518295288],"type":"Point"}
}