{
  "type": "Feature",
  "properties": {
    "iso:country":"BE",
    "sg:address":"Lauwsestraat 176",
    "sg:city":"Kortrijk",
    "sg:orig_category":"Fotografen and fotostudio's",
    "sg:phone":"+32 56 42 31 00",
    "sg:postcode":"8511",
    "sg:province":"West-Vlaanderen",
    "wof:name":"Van Rafelghem Gerarld",
    "wof:placetype":"venue"
},
  "geometry": {"coordinates":[3.2159221172,50.7835884094],"type":"Point"}
}