{
  "type": "Feature",
  "properties": {
    "addr:full":"Veldweg 45 Essen Antwerpen 2910",
    "addr:housenumber":"45",
    "addr:postcode":"2910",
    "addr:street":"Veldweg",
    "iso:country":"BE",
    "sg:address":"Veldweg 45",
    "sg:city":"Essen",
    "sg:classifiers":[
        {
            "category":"Arena",
            "subcategory":"Sports Club",
            "type":"Entertainment"
        }
    ],
    "sg:phone":"+32 3 667 10 95",
    "sg:postcode":"2910",
    "sg:province":"Antwerpen",
    "sg:tags":[
        "de"
    ],
    "wof:name":"Fudo Shin",
    "wof:placetype":"venue"
},
  "geometry": {"coordinates":[4.4531931877,51.4577407837],"type":"Point"}
}