{
  "type": "Feature",
  "properties": {
    "addr:full":"Westerlosesteenweg 146 Herselt Antwerpen 2230",
    "addr:housenumber":"146",
    "addr:postcode":"2230",
    "addr:street":"Westerlosesteenweg",
    "iso:country":"BE",
    "sg:address":"Westerlosesteenweg 146",
    "sg:city":"Herselt",
    "sg:orig_category":"HUISBRANDOLIE",
    "sg:phone":"+32 14 54 63 32",
    "sg:postcode":"2230",
    "sg:province":"Antwerpen",
    "wof:name":"Carens - Mulders",
    "wof:placetype":"venue"
},
  "geometry": {"coordinates":[4.8940200806,51.0687103271],"type":"Point"}
}