{
  "type": "Feature",
  "properties": {
    "iso:country":"BE",
    "sg:address":"Spinnersstraat 60",
    "sg:city":"Roeselare",
    "sg:orig_category":"Motos",
    "sg:phone":"+32 51 22 17 54",
    "sg:postcode":"8800",
    "sg:province":"West-Vlaanderen",
    "wof:name":"Bikers Outfit Store",
    "wof:placetype":"venue"
},
  "geometry": {"coordinates":[3.1347410679,50.9485664368],"type":"Point"}
}