{
  "type": "Feature",
  "properties": {
    "addr:full":"Rue De La Station 80 Moeskroen/mouscron Hainaut 7700",
    "addr:housenumber":"80",
    "addr:postcode":"7700",
    "addr:street":"Rue De La Station",
    "iso:country":"BE",
    "sg:address":"Rue De La Station 80",
    "sg:city":"Moeskroen/mouscron",
    "sg:orig_category":"Notaires",
    "sg:phone":"+32 56 34 22 60",
    "sg:postcode":"7700",
    "sg:province":"Hainaut",
    "wof:name":"L. Du Faux",
    "wof:placetype":"venue"
},
  "geometry": {"coordinates":[3.2323200703,50.7400932312],"type":"Point"}
}