{
  "type": "Feature",
  "properties": {
    "iso:country":"BE",
    "sg:address":"Klerkenstraat 9a",
    "sg:city":"Kortemark (zarren-werken)",
    "sg:classifiers":[
        {
            "category":"Building & Trades",
            "subcategory":"Construction",
            "type":"Services"
        }
    ],
    "sg:phone":"+32 51 56 93 69",
    "sg:postcode":"8610",
    "sg:province":"West-Vlaanderen",
    "sg:tags":[
        "installation",
        "-",
        "central",
        "heating"
    ],
    "wof:name":"Van Zwam C",
    "wof:placetype":"venue"
},
  "geometry": {"coordinates":[2.9505190849,51.0134391785],"type":"Point"}
}