{
  "type": "Feature",
  "properties": {
    "addr:full":"Ravenshout 3325 Tessenderlo Limburg 3980",
    "addr:postcode":"3325 tessenderlo;3980",
    "addr:street":"Ravenshout",
    "iso:country":"BE",
    "sg:address":"Ravenshout 3325",
    "sg:city":"Tessenderlo",
    "sg:orig_category":"HUISBRANDOLIE",
    "sg:phone":"+32 13 66 35 00",
    "sg:postcode":"3980",
    "sg:province":"Limburg",
    "wof:name":"Reynders Brandstoffen",
    "wof:placetype":"venue"
},
  "geometry": {"coordinates":[5.1427359581,51.0711669922],"type":"Point"}
}