{
  "type": "Feature",
  "properties": {
    "addr:full":"Boeimeerstraat 10 Bonheiden Antwerpen 2820",
    "addr:housenumber":"10",
    "addr:postcode":"2820",
    "addr:street":"Boeimeerstraat",
    "iso:country":"BE",
    "sg:address":"Boeimeerstraat 10",
    "sg:city":"Bonheiden",
    "sg:orig_category":"Artiesten and kunstenaars",
    "sg:phone":"+32 15 51 15 62",
    "sg:postcode":"2820",
    "sg:province":"Antwerpen",
    "wof:name":"Tuyls",
    "wof:placetype":"venue"
},
  "geometry": {"coordinates":[4.5632472038,51.0185012817],"type":"Point"}
}