{
  "type": "Feature",
  "properties": {
    "addr:full":"Professor Nelisstraat 14 Zedelgem (aartrijke) West-Vlaanderen 8211",
    "addr:housenumber":"14",
    "addr:postcode":"8211",
    "addr:street":"Professor Nelisstraat",
    "iso:country":"BE",
    "sg:address":"Professor Nelisstraat 14",
    "sg:city":"Zedelgem (aartrijke)",
    "sg:classifiers":[
        {
            "category":"Freight",
            "type":"Transportation"
        }
    ],
    "sg:phone":"+32 50 24 02 09",
    "sg:postcode":"8211",
    "sg:province":"West-Vlaanderen",
    "sg:tags":[
        "-",
        "transport"
    ],
    "wof:name":"Deloddere Gery Transport Bvba",
    "wof:placetype":"venue"
},
  "geometry": {"coordinates":[3.0889649391,51.1200408936],"type":"Point"}
}