{
  "type": "Feature",
  "properties": {
    "addr:full":"Rue La Ringe 36 Vresse-sur-semois Namur 5550",
    "addr:housenumber":"36",
    "addr:postcode":"5550",
    "addr:street":"Rue La Ringe",
    "iso:country":"BE",
    "sg:address":"Rue La Ringe 36",
    "sg:city":"Vresse-sur-semois",
    "sg:orig_category":"Pain, p\u00e2tisseries and confiseries",
    "sg:phone":"+32 61 50 05 42",
    "sg:postcode":"5550",
    "sg:province":"Namur",
    "wof:name":"Robert Delogne",
    "wof:placetype":"venue"
},
  "geometry": {"coordinates":[4.9336900711,49.8729820251],"type":"Point"}
}