{
  "type": "Feature",
  "properties": {
    "iso:country":"BE",
    "sg:address":"Knoktstraat 3",
    "sg:city":"Kluisbergen",
    "sg:orig_category":"Eleveurs and marchands de porcs. Eleveurs de bovins",
    "sg:phone":"+32 55 38 83 73",
    "sg:postcode":"9690",
    "sg:province":"Oost-Vlaanderen",
    "wof:name":"Andre De Weer",
    "wof:placetype":"venue"
},
  "geometry": {"coordinates":[3.528512001,50.7647132874],"type":"Point"}
}