{
  "type": "Feature",
  "properties": {
    "addr:full":"Henry Fordlaan 62a Genk Limburg 3600",
    "addr:housenumber":"62a",
    "addr:postcode":"3600",
    "addr:street":"Henry Fordlaan",
    "iso:country":"BE",
    "sg:address":"Henry Fordlaan 62a",
    "sg:city":"Genk",
    "sg:classifiers":[
        {
            "category":"Freight",
            "type":"Transportation"
        }
    ],
    "sg:phone":"+32 89 86 92 10",
    "sg:postcode":"3600",
    "sg:province":"Limburg",
    "sg:tags":[
        "-",
        "transport"
    ],
    "wof:name":"Edwards Logistics Nv",
    "wof:placetype":"venue"
},
  "geometry": {"coordinates":[5.4765019417,50.9290084839],"type":"Point"}
}