{
  "type": "Feature",
  "properties": {
    "iso:country":"BE",
    "sg:address":"Wetterensteenweg 86b2",
    "sg:city":"Wetteren",
    "sg:classifiers":[
        {
            "category":"Insurance",
            "subcategory":"Life Insurance",
            "type":"Services"
        }
    ],
    "sg:phone":"+32 9 368 22 60",
    "sg:postcode":"9230",
    "sg:province":"Oost-Vlaanderen",
    "sg:tags":[
        "assurance"
    ],
    "wof:name":"Valama",
    "wof:placetype":"venue"
},
  "geometry": {"coordinates":[3.8313260078,50.9748001099],"type":"Point"}
}