{
  "type": "Feature",
  "properties": {
    "addr:full":"Merodestraat 97-125 Beveren Oost-Vlaanderen 9130",
    "addr:postcode":"97-125;9130",
    "addr:street":"Merodestraat",
    "iso:country":"BE",
    "sg:address":"Merodestraat 97-125",
    "sg:city":"Beveren",
    "sg:classifiers":[
        {
            "category":"Food & Beverages",
            "subcategory":"Meat & Fish",
            "type":"Retail Goods"
        }
    ],
    "sg:phone":"+32 3 773 42 34",
    "sg:postcode":"9130",
    "sg:province":"Oost-Vlaanderen",
    "sg:tags":[
        "vi",
        "zeevruchten"
    ],
    "wof:name":"Praet",
    "wof:placetype":"venue"
},
  "geometry": {"coordinates":[4.1670680046,51.2912750244],"type":"Point"}
}