{
  "type": "Feature",
  "properties": {
    "iso:country":"BE",
    "sg:address":"Hogebaan 2",
    "sg:city":"Brecht (sint-job-in-'t Goor)",
    "sg:classifiers":[
        {
            "category":"Education",
            "subcategory":"School",
            "type":"Public Place"
        }
    ],
    "sg:phone":"+32 3 636 12 29",
    "sg:postcode":"2960",
    "sg:province":"Antwerpen",
    "sg:tags":[
        "primary"
    ],
    "wof:name":"Maria Middelares",
    "wof:placetype":"venue"
},
  "geometry": {"coordinates":[4.5722842216,51.2981796265],"type":"Point"}
}