{
  "type": "Feature",
  "properties": {
    "addr:full":"Houtekietstraat 10 Deerlijk West-Vlaanderen 8540",
    "addr:housenumber":"10",
    "addr:postcode":"8540",
    "addr:street":"Houtekietstraat",
    "iso:country":"BE",
    "sg:address":"Houtekietstraat 10",
    "sg:city":"Deerlijk",
    "sg:orig_category":"Rev\u00eatements pour sols and murs. Construction industrielle and commerciale",
    "sg:phone":"+32 56 77 34 78",
    "sg:postcode":"8540",
    "sg:province":"West-Vlaanderen",
    "wof:name":"Beyaert A & W",
    "wof:placetype":"venue"
},
  "geometry": {"coordinates":[3.3733360767,50.8174057007],"type":"Point"}
}