{
  "type": "Feature",
  "properties": {
    "iso:country":"BE",
    "sg:address":"Parvis Sainte-alix 27",
    "sg:city":"Sint-pieters-woluwe/woluwe-saint-pierre",
    "sg:orig_category":"Supermarch\u00e9s",
    "sg:phone":"+32 2 779 81 52",
    "sg:postcode":"1150",
    "sg:province":"Bruxelles-Capitale",
    "wof:name":"Louis Delhaize",
    "wof:placetype":"venue"
},
  "geometry": {"coordinates":[4.4621491432,50.8276290894],"type":"Point"}
}