{
  "type": "Feature",
  "properties": {
    "iso:country":"BE",
    "sg:address":"Sint-godelievestraat 28",
    "sg:city":"Oostkamp",
    "sg:classifiers":[
        {
            "category":"Building & Trades",
            "subcategory":"Construction",
            "type":"Services"
        }
    ],
    "sg:phone":"+32 50 82 74 64",
    "sg:postcode":"8020",
    "sg:province":"West-Vlaanderen",
    "sg:tags":[
        "carpenter"
    ],
    "wof:name":"Alg Aannemingsbedrijf Pupe-becelaere Nv",
    "wof:placetype":"venue"
},
  "geometry": {"coordinates":[3.2621490955,51.1612052917],"type":"Point"}
}