{
  "type": "Feature",
  "properties": {
    "iso:country":"BE",
    "sg:address":"Rue De L'agneau 0",
    "sg:city":"Sprimont",
    "sg:orig_category":"Salles de conf\u00e9rences and de r\u00e9ceptions",
    "sg:phone":"+32 4 382 22 24",
    "sg:postcode":"4140",
    "sg:province":"Li\u00e8ge",
    "wof:name":"Salle St-martin",
    "wof:placetype":"venue"
},
  "geometry": {"coordinates":[5.6635379791,50.5046386719],"type":"Point"}
}