{
  "type": "Feature",
  "properties": {
    "iso:country":"BE",
    "sg:address":"Leegzakstraat 62",
    "sg:city":"Nazareth",
    "sg:classifiers":[
        {
            "category":"Building & Trades",
            "subcategory":"Electrical",
            "type":"Services"
        }
    ],
    "sg:phone":"+32 9 385 87 74",
    "sg:postcode":"9810",
    "sg:province":"Oost-Vlaanderen",
    "sg:tags":[
        "electric",
        "-",
        "housewiring",
        "contractor"
    ],
    "wof:name":"Haerts C",
    "wof:placetype":"venue"
},
  "geometry": {"coordinates":[3.6061530113,50.9504928589],"type":"Point"}
}