{
  "type": "Feature",
  "properties": {
    "addr:full":"Vrijheid 194 Hoogstraten Antwerpen 2320",
    "addr:housenumber":"194",
    "addr:postcode":"2320",
    "addr:street":"Vrijheid",
    "iso:country":"BE",
    "sg:address":"Vrijheid 194",
    "sg:city":"Hoogstraten",
    "sg:classifiers":[
        {
            "category":"Fast Food",
            "type":"Food & Drink"
        }
    ],
    "sg:phone":"+32 3 314 52 34",
    "sg:postcode":"2320",
    "sg:province":"Antwerpen",
    "sg:tags":[
        "\u00c0",
        "emporter",
        "restaurants"
    ],
    "wof:name":"Frituur Roma",
    "wof:placetype":"venue"
},
  "geometry": {"coordinates":[4.7609000206,51.4008255005],"type":"Point"}
}