{
  "type": "Feature",
  "properties": {
    "iso:country":"BE",
    "sg:address":"Kapellestraat 41",
    "sg:city":"Aartselaar",
    "sg:classifiers":[
        {
            "category":"Fast Food",
            "type":"Food & Drink"
        }
    ],
    "sg:phone":"+32 3 887 98 69",
    "sg:postcode":"2630",
    "sg:province":"Antwerpen",
    "sg:tags":[
        "\u00c0",
        "restaurants",
        "emporter",
        "restaurant"
    ],
    "wof:name":"Pang For Cheong",
    "wof:placetype":"venue"
},
  "geometry": {"coordinates":[4.3889951706,51.1324996948],"type":"Point"}
}