{
  "type": "Feature",
  "properties": {
    "iso:country":"BE",
    "sg:address":"Zwevegemsestraat 65a",
    "sg:city":"Kortrijk",
    "sg:classifiers":[
        {
            "category":"Retail",
            "subcategory":"Auto Repair",
            "type":"Services"
        }
    ],
    "sg:phone":"+32 56 21 53 46",
    "sg:postcode":"8500",
    "sg:province":"West-Vlaanderen",
    "sg:tags":[
        "garage"
    ],
    "wof:name":"Moyaert",
    "wof:placetype":"venue"
},
  "geometry": {"coordinates":[3.2738959789,50.824016571],"type":"Point"}
}