{
  "type": "Feature",
  "properties": {
    "addr:full":"Bavikhoofsestraat 46 Kuurne West-Vlaanderen 8520",
    "addr:housenumber":"46",
    "addr:postcode":"8520",
    "addr:street":"Bavikhoofsestraat",
    "iso:country":"BE",
    "sg:address":"Bavikhoofsestraat 46",
    "sg:city":"Kuurne",
    "sg:orig_category":"Kapsalons",
    "sg:phone":"+32 56 71 45 58",
    "sg:postcode":"8520",
    "sg:province":"West-Vlaanderen",
    "wof:name":"Marcel Lebon",
    "wof:placetype":"venue"
},
  "geometry": {"coordinates":[3.2894310951,50.8552055359],"type":"Point"}
}