{
  "type": "Feature",
  "properties": {
    "addr:full":"Eegene 56 Dendermonde Oost-Vlaanderen 9200",
    "addr:housenumber":"56",
    "addr:postcode":"9200",
    "addr:street":"Eegene;Oost-Vlaanderen",
    "iso:country":"BE",
    "sg:address":"Eegene 56",
    "sg:city":"Dendermonde",
    "sg:classifiers":[
        {
            "category":"Insurance",
            "subcategory":"Insurance Agent",
            "type":"Services"
        }
    ],
    "sg:phone":"+32 52 42 32 23",
    "sg:postcode":"9200",
    "sg:province":"Oost-Vlaanderen",
    "sg:tags":[
        "verzekeringsmakelaars",
        "expert"
    ],
    "wof:name":"Bureau Van Acoleyen",
    "wof:placetype":"venue"
},
  "geometry": {"coordinates":[4.0231099129,51.0087814331],"type":"Point"}
}