{
  "type": "Feature",
  "properties": {
    "addr:full":"Brouwerijstraat 14 Harelbeke West-Vlaanderen 8530",
    "addr:housenumber":"14",
    "addr:postcode":"8530",
    "addr:street":"Brouwerijstraat",
    "iso:country":"BE",
    "sg:address":"Brouwerijstraat 14",
    "sg:city":"Harelbeke",
    "sg:classifiers":[
        {
            "category":"Cafe",
            "type":"Food & Drink"
        }
    ],
    "sg:phone":"+32 56 22 51 70",
    "sg:postcode":"8530",
    "sg:province":"West-Vlaanderen",
    "sg:tags":[
        "caf\u00e9s"
    ],
    "wof:name":"Caf\u00c9 Brouwershof",
    "wof:placetype":"venue"
},
  "geometry": {"coordinates":[3.3157200813,50.8308334351],"type":"Point"}
}