{
  "type": "Feature",
  "properties": {
    "iso:country":"BE",
    "sg:address":"Rue De La Bawette 103",
    "sg:city":"Bertrix",
    "sg:classifiers":[
        {
            "category":"Building & Trades",
            "subcategory":"Landscaping Services",
            "type":"Services"
        }
    ],
    "sg:phone":"+32 61 41 13 62",
    "sg:postcode":"6880",
    "sg:province":"Luxembourg",
    "sg:tags":[
        "forestry"
    ],
    "wof:name":"Servais M",
    "wof:placetype":"venue"
},
  "geometry": {"coordinates":[5.2536711693,49.861240387],"type":"Point"}
}