{
  "type": "Feature",
  "properties": {
    "iso:country":"BE",
    "sg:address":"Maaltebruggestraat 54",
    "sg:city":"Gent",
    "sg:orig_category":"Paramedische behandelingen",
    "sg:phone":"+32 9 245 23 52",
    "sg:postcode":"9000",
    "sg:province":"Oost-Vlaanderen",
    "wof:name":"M. De Letter",
    "wof:placetype":"venue"
},
  "geometry": {"coordinates":[3.7119760513,51.0310096741],"type":"Point"}
}