{
  "type": "Feature",
  "properties": {
    "iso:country":"BE",
    "sg:address":"Gasthuisstraat 31",
    "sg:city":"Aarschot",
    "sg:orig_category":"D\u00e9taillants en pi\u00e8ces and accessoires de voitures",
    "sg:phone":"+32 16 57 15 87",
    "sg:postcode":"3200",
    "sg:province":"Vlaams-Brabant",
    "wof:name":"Van Noten",
    "wof:placetype":"venue"
},
  "geometry": {"coordinates":[4.8398518562,50.9876708984],"type":"Point"}
}