{
  "type": "Feature",
  "properties": {
    "addr:full":"Demerlaan 15 Bilzen Limburg 3740",
    "addr:housenumber":"15",
    "addr:postcode":"3740",
    "addr:street":"Demerlaan",
    "iso:country":"BE",
    "sg:address":"Demerlaan 15",
    "sg:city":"Bilzen",
    "sg:classifiers":[
        {
            "category":"Communications",
            "type":"Services"
        }
    ],
    "sg:phone":"+32 89 51 55 34",
    "sg:postcode":"3740",
    "sg:province":"Limburg",
    "sg:tags":[
        "translator"
    ],
    "wof:name":"Jackers Marie",
    "wof:placetype":"venue"
},
  "geometry": {"coordinates":[5.515868187,50.8692016602],"type":"Point"}
}