{
  "type": "Feature",
  "properties": {
    "iso:country":"BE",
    "sg:address":"Schoonaardebaan 92",
    "sg:city":"Dendermonde (schoonaarde)",
    "sg:classifiers":[
        {
            "category":"Home & Garden",
            "subcategory":"Household Appliances",
            "type":"Retail Goods"
        }
    ],
    "sg:phone":"+32 52 42 75 35",
    "sg:postcode":"9200",
    "sg:province":"Oost-Vlaanderen",
    "sg:tags":[
        "repair",
        "stove",
        "-"
    ],
    "wof:name":"Bosmans Bvba",
    "wof:placetype":"venue"
},
  "geometry": {"coordinates":[4.0169119835,51.0054206848],"type":"Point"}
}