{
  "type": "Feature",
  "properties": {
    "addr:full":"Rue Du Tilleul 205-207 Bruxelles Bruxelles-Capitale 1140",
    "addr:postcode":"205-207;1140",
    "addr:street":"Rue Du Tilleul",
    "iso:country":"BE",
    "sg:address":"Rue Du Tilleul 205-207",
    "sg:city":"Bruxelles",
    "sg:classifiers":[
        {
            "category":"Shopping",
            "type":"Retail Goods"
        }
    ],
    "sg:phone":"+32 2 240 03 60",
    "sg:postcode":"1140",
    "sg:province":"Bruxelles-Capitale",
    "sg:tags":[
        "metallurgy",
        "finished",
        "-",
        "metalworking",
        "metallic"
    ],
    "wof:name":"Silent Gliss Benelux Sa",
    "wof:placetype":"venue"
},
  "geometry": {"coordinates":[4.394630909,50.8723526001],"type":"Point"}
}