{
  "type": "Feature",
  "properties": {
    "addr:full":"Dok-zuid 3 Gent Oost-Vlaanderen 9000",
    "addr:housenumber":"3",
    "addr:postcode":"9000",
    "addr:street":"Dok-Zuid;Oost-Vlaanderen",
    "iso:country":"BE",
    "sg:address":"Dok-zuid 3",
    "sg:city":"Gent",
    "sg:classifiers":[
        {
            "category":"Personal",
            "subcategory":"Barber",
            "type":"Services"
        }
    ],
    "sg:phone":"+32 9 233 30 78",
    "sg:postcode":"9000",
    "sg:province":"Oost-Vlaanderen",
    "sg:tags":[
        "gentleman",
        "salon",
        "-",
        "hairdressing"
    ],
    "wof:name":"Scissors",
    "wof:placetype":"venue"
},
  "geometry": {"coordinates":[3.7381649017,51.0570449829],"type":"Point"}
}