{
  "type": "Feature",
  "properties": {
    "addr:full":"Rue Culot-reine 22 Ch\u00c2telet Hainaut 6200",
    "addr:housenumber":"22",
    "addr:postcode":"6200",
    "addr:street":"Rue Culot-Reine",
    "iso:country":"BE",
    "sg:address":"Rue Culot-reine 22",
    "sg:city":"Ch\u00c2telet",
    "sg:orig_category":"Voertuigen",
    "sg:phone":"+32 71 39 64 14",
    "sg:postcode":"6200",
    "sg:province":"Hainaut",
    "wof:name":"Garage Mickey",
    "wof:placetype":"venue"
},
  "geometry": {"coordinates":[4.5137748718,50.4175682068],"type":"Point"}
}