{
  "type": "Feature",
  "properties": {
    "addr:full":"Klapperbeekstraat 156 Sint-niklaas Oost-Vlaanderen 9100",
    "addr:housenumber":"156",
    "addr:postcode":"9100",
    "addr:street":"Klapperbeekstraat",
    "iso:country":"BE",
    "sg:address":"Klapperbeekstraat 156",
    "sg:city":"Sint-niklaas",
    "sg:classifiers":[
        {
            "category":"Health Services",
            "subcategory":"Health Practitioner",
            "type":"Services"
        }
    ],
    "sg:phone":"+32 3 776 04 72",
    "sg:postcode":"9100",
    "sg:province":"Oost-Vlaanderen",
    "sg:tags":[
        "therapist",
        "speech"
    ],
    "wof:name":"Hylebos C",
    "wof:placetype":"venue"
},
  "geometry": {"coordinates":[4.1609559059,51.1844024658],"type":"Point"}
}