{
  "type": "Feature",
  "properties": {
    "iso:country":"BE",
    "sg:address":"Waterloose Steenweg 651",
    "sg:city":"Elsene/ixelles",
    "sg:classifiers":[
        {
            "category":"Restaurant",
            "type":"Food & Drink"
        }
    ],
    "sg:phone":"+32 2 343 06 54",
    "sg:postcode":"1050",
    "sg:province":"Bruxelles-Capitale",
    "wof:name":"Snack Galerie",
    "wof:placetype":"venue"
},
  "geometry": {"coordinates":[4.365696907,50.8171920776],"type":"Point"}
}