{
  "type": "Feature",
  "properties": {
    "addr:full":"Rue Lesoinne 13 Li\u00e8ge 1 Li\u00e8ge 4000",
    "addr:housenumber":"13;1",
    "addr:postcode":"4000",
    "addr:street":"Rue Lesoinne",
    "iso:country":"BE",
    "sg:address":"Rue Lesoinne 13",
    "sg:city":"Li\u00e8ge 1",
    "sg:classifiers":[
        {
            "category":"Wholesale",
            "subcategory":"Machinery & Supplies",
            "type":"Manufacturing & Wholesale Goods"
        }
    ],
    "sg:phone":"+32 4 252 30 02",
    "sg:postcode":"4000",
    "sg:province":"Li\u00e8ge",
    "sg:tags":[
        "refrigeration",
        "-",
        "industrial",
        "commercial",
        "equipment"
    ],
    "wof:name":"Saccongel Sprl",
    "wof:placetype":"venue"
},
  "geometry": {"coordinates":[5.5719680786,50.6219367981],"type":"Point"}
}