{
  "type": "Feature",
  "properties": {
    "iso:country":"BE",
    "sg:address":"Rue Des Mineurs 31",
    "sg:city":"Seraing",
    "sg:orig_category":"Catering and organisatie van feesten",
    "sg:phone":"+32 4 234 44 94",
    "sg:postcode":"4101",
    "sg:province":"Li\u00e8ge",
    "wof:name":"Mon Repas Quotidien",
    "wof:placetype":"venue"
},
  "geometry": {"coordinates":[5.4986271858,50.6150817871],"type":"Point"}
}