{
  "type": "Feature",
  "properties": {
    "addr:full":"Rue Porte Haute 16-18 Marche-en-famenne Luxembourg 6900",
    "addr:postcode":"16-18;6900",
    "addr:street":"Rue Porte Haute",
    "iso:country":"BE",
    "sg:address":"Rue Porte Haute 16-18",
    "sg:city":"Marche-en-famenne",
    "sg:orig_category":"Microsoft. Mat\u00e9riel de T\u00e9l\u00e9communication. R\u00e9parations d'appareils \u00e9lectrom\u00e9nagers. Electrom\u00e9nager, t",
    "sg:phone":"+32 84 31 12 12",
    "sg:postcode":"6900",
    "sg:province":"Luxembourg",
    "wof:name":"Thirion",
    "wof:placetype":"venue"
},
  "geometry": {"coordinates":[5.345102787,50.2262191772],"type":"Point"}
}