{
  "type": "Feature",
  "properties": {
    "addr:full":"Waversesteenweg 84 Bierbeek (honsem) Vlaams-Brabant 3360",
    "addr:housenumber":"84",
    "addr:postcode":"3360",
    "addr:street":"Waversesteenweg",
    "iso:country":"BE",
    "sg:address":"Waversesteenweg 84",
    "sg:city":"Bierbeek (honsem)",
    "sg:classifiers":[
        {
            "category":"Personal",
            "subcategory":"Nail Salon",
            "type":"Services"
        }
    ],
    "sg:phone":"+32 16 72 09 90",
    "sg:postcode":"3360",
    "sg:province":"Vlaams-Brabant",
    "sg:tags":[
        "pedicure"
    ],
    "wof:name":"Anja",
    "wof:placetype":"venue"
},
  "geometry": {"coordinates":[4.7899727821,50.8115005493],"type":"Point"}
}