{
  "type": "Feature",
  "properties": {
    "iso:country":"BE",
    "sg:address":"Grauwwerkersstraat 15",
    "sg:city":"Brugge",
    "sg:classifiers":[
        {
            "category":"Bars & Pubs",
            "type":"Food & Drink"
        }
    ],
    "sg:phone":"+32 50 34 51 15",
    "sg:postcode":"8000",
    "sg:province":"West-Vlaanderen",
    "wof:name":"Vino-vino",
    "wof:placetype":"venue"
},
  "geometry": {"coordinates":[3.222933054,51.2113418579],"type":"Point"}
}