{
  "type": "Feature",
  "properties": {
    "iso:country":"BE",
    "sg:address":"Rue Emile-parfonry 19",
    "sg:city":"Hotton",
    "sg:orig_category":"Jeux de hasard",
    "sg:phone":"+32 84 46 65 86",
    "sg:postcode":"6990",
    "sg:province":"Luxembourg",
    "wof:name":"Ladbroke",
    "wof:placetype":"venue"
},
  "geometry": {"coordinates":[5.4458260536,50.267162323],"type":"Point"}
}