{
  "type": "Feature",
  "properties": {
    "iso:country":"BE",
    "sg:address":"Rue De Buay 34",
    "sg:city":"Wasseiges (meeffe)",
    "sg:classifiers":[
        {
            "category":"Farming",
            "subcategory":"Farm & Veterinary Services",
            "type":"Manufacturing & Wholesale Goods"
        }
    ],
    "sg:phone":"+32 81 85 52 64",
    "sg:postcode":"4219",
    "sg:province":"Li\u00e8ge",
    "sg:tags":[
        "agricultural",
        "contractor"
    ],
    "wof:name":"Buay Begon",
    "wof:placetype":"venue"
},
  "geometry": {"coordinates":[5.0415787697,50.6185073853],"type":"Point"}
}