{
  "type": "Feature",
  "properties": {
    "addr:full":"Rue De L'ecole 10 Somme-leuze Namur 5377",
    "addr:housenumber":"10",
    "addr:postcode":"5377",
    "addr:street":"Rue De L'Ecole",
    "iso:country":"BE",
    "sg:address":"Rue De L'ecole 10",
    "sg:city":"Somme-leuze",
    "sg:orig_category":"Enseignement maternel and primaire",
    "sg:phone":"+32 86 32 27 21",
    "sg:postcode":"5377",
    "sg:province":"Namur",
    "wof:name":"Ecole Prim. Communale",
    "wof:placetype":"venue"
},
  "geometry": {"coordinates":[5.369890213,50.3404312134],"type":"Point"}
}