{
  "type": "Feature",
  "properties": {
    "addr:full":"Frans Halsvest 4 Mechelen Antwerpen 2800",
    "addr:housenumber":"4",
    "addr:postcode":"2800",
    "addr:street":"Frans Halsvest",
    "iso:country":"BE",
    "sg:address":"Frans Halsvest 4",
    "sg:city":"Mechelen",
    "sg:orig_category":"Sportclubs",
    "sg:phone":"+32 15 21 64 68",
    "sg:postcode":"2800",
    "sg:province":"Antwerpen",
    "wof:name":"Ni Shi Get Su Lier",
    "wof:placetype":"venue"
},
  "geometry": {"coordinates":[4.4842481613,51.0335273743],"type":"Point"}
}