{
  "type": "Feature",
  "properties": {
    "addr:full":"Sint-christianastraat 25 Dendermonde Oost-Vlaanderen 9200",
    "addr:housenumber":"25",
    "addr:postcode":"9200",
    "addr:street":"Sint-Christianastraat;Oost-Vlaanderen",
    "iso:country":"BE",
    "sg:address":"Sint-christianastraat 25",
    "sg:city":"Dendermonde",
    "sg:orig_category":"Technische studies and ingenieursactiviteiten",
    "sg:phone":"+32 52 21 37 23",
    "sg:postcode":"9200",
    "sg:province":"Oost-Vlaanderen",
    "wof:name":"Swbo",
    "wof:placetype":"venue"
},
  "geometry": {"coordinates":[4.0900101662,51.0324783325],"type":"Point"}
}