{
  "type": "Feature",
  "properties": {
    "iso:country":"BE",
    "sg:address":"Grand Place 26",
    "sg:city":"Mons",
    "sg:classifiers":[
        {
            "category":"Restaurant",
            "type":"Food & Drink"
        }
    ],
    "sg:phone":"+32 65 33 70 57",
    "sg:postcode":"7000",
    "sg:province":"Hainaut",
    "wof:name":"La Petite Provence",
    "wof:placetype":"venue"
},
  "geometry": {"coordinates":[3.9518299103,50.4545555115],"type":"Point"}
}