{
  "type": "Feature",
  "properties": {
    "iso:country":"BE",
    "sg:address":"Portfort 128",
    "sg:city":"Retie",
    "sg:classifiers":[
        {
            "category":"Farming",
            "subcategory":"Farm & Veterinary Services",
            "type":"Manufacturing & Wholesale Goods"
        }
    ],
    "sg:phone":"+32 14 37 74 83",
    "sg:postcode":"2470",
    "sg:province":"Antwerpen",
    "sg:tags":[
        "feed",
        "meal",
        "cattle"
    ],
    "wof:name":"Navobi Nv",
    "wof:placetype":"venue"
},
  "geometry": {"coordinates":[5.0843849182,51.2674407959],"type":"Point"}
}