{
  "type": "Feature",
  "properties": {
    "addr:full":"Winkelbaan 22 Asse (mollem) Vlaams-Brabant 1730",
    "addr:housenumber":"22",
    "addr:postcode":"1730",
    "addr:street":"Winkelbaan",
    "iso:country":"BE",
    "sg:address":"Winkelbaan 22",
    "sg:city":"Asse (mollem)",
    "sg:classifiers":[
        {
            "category":"Museum",
            "type":"Entertainment"
        }
    ],
    "sg:phone":"+32 2 452 50 08",
    "sg:postcode":"1730",
    "sg:province":"Vlaams-Brabant",
    "wof:name":"Kiekeboe Museum",
    "wof:placetype":"venue"
},
  "geometry": {"coordinates":[4.2142329216,50.934928894],"type":"Point"}
}