{
  "type": "Feature",
  "properties": {
    "iso:country":"BE",
    "sg:address":"Rue Aux Laines 29",
    "sg:city":"Verviers",
    "sg:orig_category":"Dansscholen",
    "sg:phone":"+32 87 55 55 75",
    "sg:postcode":"4800",
    "sg:province":"Li\u00e8ge",
    "wof:name":"Studio K.danse",
    "wof:placetype":"venue"
},
  "geometry": {"coordinates":[5.8514580727,50.5893287659],"type":"Point"}
}