{
  "type": "Feature",
  "properties": {
    "iso:country":"BE",
    "sg:address":"Frederik Wouterslaan 38",
    "sg:city":"Kampenhout",
    "sg:classifiers":[
        {
            "category":"Personal",
            "subcategory":"Beauty Salon",
            "type":"Services"
        }
    ],
    "sg:phone":"+32 16 65 15 15",
    "sg:postcode":"1910",
    "sg:province":"Vlaams-Brabant",
    "wof:name":"Winnepenninckx N",
    "wof:placetype":"venue"
},
  "geometry": {"coordinates":[4.5516891479,50.9400558472],"type":"Point"}
}