{
  "type": "Feature",
  "properties": {
    "iso:country":"BE",
    "sg:address":"Rue Du Soldat Joseph Dethier 2",
    "sg:city":"Dalhem",
    "sg:classifiers":[
        {
            "category":"Real Estate",
            "subcategory":"Architect",
            "type":"Services"
        }
    ],
    "sg:phone":"+32 4 379 62 26",
    "sg:postcode":"4607",
    "sg:province":"Li\u00e8ge",
    "wof:name":"Maes P",
    "wof:placetype":"venue"
},
  "geometry": {"coordinates":[5.7234959602,50.713634491],"type":"Point"}
}