{
  "type": "Feature",
  "properties": {
    "addr:full":"Rue De La Gare 25 Plombieres Li\u00e8ge 4850",
    "addr:housenumber":"25",
    "addr:postcode":"4850",
    "addr:street":"Rue De La Gare",
    "iso:country":"BE",
    "sg:address":"Rue De La Gare 25",
    "sg:city":"Plombieres",
    "sg:orig_category":"Woningbouw",
    "sg:phone":"+32 87 78 58 83",
    "sg:postcode":"4850",
    "sg:province":"Li\u00e8ge",
    "wof:name":"P. Franssen",
    "wof:placetype":"venue"
},
  "geometry": {"coordinates":[5.9605197906,50.7154312134],"type":"Point"}
}