{
  "type": "Feature",
  "properties": {
    "iso:country":"BE",
    "sg:address":"Rue Elveau 46",
    "sg:city":"Sombreffe",
    "sg:orig_category":"Traitements param\u00e9dicaux",
    "sg:phone":"+32 71 88 98 21",
    "sg:postcode":"5140",
    "sg:province":"Namur",
    "wof:name":"L. Page",
    "wof:placetype":"venue"
},
  "geometry": {"coordinates":[4.592031002,50.5293464661],"type":"Point"}
}