{
  "type": "Feature",
  "properties": {
    "addr:full":"Memlingdreef 21 Overijse Vlaams-Brabant 3090",
    "addr:housenumber":"21",
    "addr:postcode":"3090",
    "addr:street":"Memlingdreef",
    "iso:country":"BE",
    "sg:address":"Memlingdreef 21",
    "sg:city":"Overijse",
    "sg:orig_category":"Loodgieterij, verwarming and sanitaire installaties",
    "sg:phone":"+32 2 687 65 22",
    "sg:postcode":"3090",
    "sg:province":"Vlaams-Brabant",
    "wof:name":"Charles Eraerts",
    "wof:placetype":"venue"
},
  "geometry": {"coordinates":[4.5040211678,50.7890625],"type":"Point"}
}