{
  "type": "Feature",
  "properties": {
    "addr:full":"Promenade Hanrion 11 Spa Li\u00e8ge 4900",
    "addr:housenumber":"11",
    "addr:postcode":"4900",
    "addr:street":"Promenade Hanrion",
    "iso:country":"BE",
    "sg:address":"Promenade Hanrion 11",
    "sg:city":"Spa",
    "sg:classifiers":[
        {
            "category":"Real Estate",
            "subcategory":"Architect",
            "type":"Services"
        }
    ],
    "sg:phone":"+32 87 77 27 01",
    "sg:postcode":"4900",
    "sg:province":"Li\u00e8ge",
    "wof:name":"Haesbroeck L",
    "wof:placetype":"venue"
},
  "geometry": {"coordinates":[5.8768630028,50.4915237427],"type":"Point"}
}