{
  "type": "Feature",
  "properties": {
    "addr:full":"Stationsstraat 99 Geel Antwerpen 2440",
    "addr:housenumber":"99",
    "addr:postcode":"2440",
    "addr:street":"Stationsstraat",
    "iso:country":"BE",
    "sg:address":"Stationsstraat 99",
    "sg:city":"Geel",
    "sg:classifiers":[
        {
            "category":"Building & Trades",
            "subcategory":"Cleaning & Sanitation",
            "type":"Services"
        }
    ],
    "sg:phone":"+32 14 58 20 44",
    "sg:postcode":"2440",
    "sg:province":"Antwerpen",
    "sg:tags":[
        "janitor"
    ],
    "wof:name":"Gks Bvba",
    "wof:placetype":"venue"
},
  "geometry": {"coordinates":[4.9893689156,51.1661834717],"type":"Point"}
}