{
  "type": "Feature",
  "properties": {
    "addr:full":"Assenois 15 Vaux-sur-s\u00dbre Luxembourg 6640",
    "addr:housenumber":"15",
    "addr:postcode":"6640",
    "addr:street":"Assenois",
    "iso:country":"BE",
    "sg:address":"Assenois 15",
    "sg:city":"Vaux-sur-s\u00dbre",
    "sg:orig_category":"Banken and kredietinstellingen",
    "sg:phone":"+32 61 26 62 23",
    "sg:postcode":"6640",
    "sg:province":"Luxembourg",
    "wof:name":"Axa",
    "wof:placetype":"venue"
},
  "geometry": {"coordinates":[5.5671000481,49.91065979],"type":"Point"}
}