{
  "type": "Feature",
  "properties": {
    "addr:full":"Huffelplein 8 Wuustwezel Antwerpen 2990",
    "addr:housenumber":"8",
    "addr:postcode":"2990",
    "addr:street":"Huffelplein",
    "iso:country":"BE",
    "sg:address":"Huffelplein 8",
    "sg:city":"Wuustwezel",
    "sg:orig_category":"HERSTELLING ELEKTRISCHE HUISHOUDAPPARATEN Huishoudapparaten, televisies and radio's Verlichting and ",
    "sg:phone":"+32 3 669 61 65",
    "sg:postcode":"2990",
    "sg:province":"Antwerpen",
    "wof:name":"Huis Roovers",
    "wof:placetype":"venue"
},
  "geometry": {"coordinates":[4.6430368423,51.3987884521],"type":"Point"}
}