{
  "type": "Feature",
  "properties": {
    "iso:country":"BE",
    "sg:address":"Bellestraat 31",
    "sg:city":"Sint-niklaas",
    "sg:orig_category":"Eleveurs de bovins",
    "sg:phone":"+32 3 777 02 58",
    "sg:postcode":"9100",
    "sg:province":"Oost-Vlaanderen",
    "wof:name":"Hector Maes",
    "wof:placetype":"venue"
},
  "geometry": {"coordinates":[4.1692881584,51.1733818054],"type":"Point"}
}