{
  "type": "Feature",
  "properties": {
    "addr:full":"Avenue Des Croix Du Feu 29 Box 5 Bruxelles Bruxelles-Capitale 1020",
    "addr:housenumber":"29;5",
    "addr:postcode":"1020",
    "addr:street":"Avenue Des Croix Du Feu;Box",
    "iso:country":"BE",
    "sg:address":"Avenue Des Croix Du Feu 29 Box 5",
    "sg:city":"Bruxelles",
    "sg:classifiers":[
        {
            "category":"Building & Trades",
            "subcategory":"Plumbing",
            "type":"Services"
        }
    ],
    "sg:phone":"+32 2 770 12 81",
    "sg:postcode":"1020",
    "sg:province":"Bruxelles-Capitale",
    "sg:tags":[
        "contractor"
    ],
    "wof:name":"Jacquet D",
    "wof:placetype":"venue"
},
  "geometry": {"coordinates":[4.3721928596,50.8904647827],"type":"Point"}
}