{
  "type": "Feature",
  "properties": {
    "iso:country":"BE",
    "sg:address":"Rue Du Saupont 173",
    "sg:city":"Bertrix",
    "sg:orig_category":"Voertuigen",
    "sg:phone":"+32 61 41 11 20",
    "sg:postcode":"6880",
    "sg:province":"Luxembourg",
    "wof:name":"Garage Bourg",
    "wof:placetype":"venue"
},
  "geometry": {"coordinates":[5.2664499283,49.8538703918],"type":"Point"}
}