{
  "type": "Feature",
  "properties": {
    "addr:full":"Nederkouter 73 Gent Oost-Vlaanderen 9000",
    "addr:housenumber":"73",
    "addr:postcode":"9000",
    "addr:street":"Nederkouter;Oost-Vlaanderen",
    "iso:country":"BE",
    "sg:address":"Nederkouter 73",
    "sg:city":"Gent",
    "sg:orig_category":"Informaticaconsulenten",
    "sg:phone":"+32 9 269 00 53",
    "sg:postcode":"9000",
    "sg:province":"Oost-Vlaanderen",
    "wof:name":"The Net",
    "wof:placetype":"venue"
},
  "geometry": {"coordinates":[3.7220580578,51.0472106934],"type":"Point"}
}