{
  "type": "Feature",
  "properties": {
    "addr:full":"Tuinwijklaan 61 Gent Oost-Vlaanderen 9000",
    "addr:housenumber":"61",
    "addr:postcode":"9000",
    "addr:street":"Tuinwijklaan;Oost-Vlaanderen",
    "iso:country":"BE",
    "sg:address":"Tuinwijklaan 61",
    "sg:city":"Gent",
    "sg:classifiers":[
        {
            "category":"Real Estate",
            "subcategory":"Architect",
            "type":"Services"
        }
    ],
    "sg:phone":"+32 9 223 60 52",
    "sg:postcode":"9000",
    "sg:province":"Oost-Vlaanderen",
    "wof:name":"Hondekyn F",
    "wof:placetype":"venue"
},
  "geometry": {"coordinates":[3.709528923,51.031288147],"type":"Point"}
}