{
  "type": "Feature",
  "properties": {
    "addr:full":"Gasthuisstraat 11 Kontich (waarloos) Antwerpen 2550",
    "addr:housenumber":"11",
    "addr:postcode":"2550",
    "addr:street":"Gasthuisstraat",
    "iso:country":"BE",
    "sg:address":"Gasthuisstraat 11",
    "sg:city":"Kontich (waarloos)",
    "sg:classifiers":[
        {
            "category":"Real Estate",
            "subcategory":"Developer",
            "type":"Services"
        }
    ],
    "sg:phone":"+32 15 31 46 43",
    "sg:postcode":"2550",
    "sg:province":"Antwerpen",
    "sg:tags":[
        "project"
    ],
    "wof:name":"Ilex Nv",
    "wof:placetype":"venue"
},
  "geometry": {"coordinates":[4.4675798416,51.1038551331],"type":"Point"}
}