{
  "type": "Feature",
  "properties": {
    "iso:country":"BE",
    "sg:address":"Brouwersvliet 15",
    "sg:city":"Antwerpen",
    "sg:orig_category":"Agences d'exp\u00e9dition",
    "sg:phone":"+32 3 202 48 48",
    "sg:postcode":"2000",
    "sg:province":"Antwerpen",
    "wof:name":"Navex & Van Meerbeeck",
    "wof:placetype":"venue"
},
  "geometry": {"coordinates":[4.4027471542,51.2272453308],"type":"Point"}
}