{
  "type": "Feature",
  "properties": {
    "addr:full":"Rue Pierre Flamand 87 Braine-l'alleud Brabant Wallon 1420",
    "addr:housenumber":"87",
    "addr:postcode":"1420",
    "addr:street":"Rue Pierre Flamand",
    "iso:country":"BE",
    "sg:address":"Rue Pierre Flamand 87",
    "sg:city":"Braine-l'alleud",
    "sg:orig_category":"M\u00e9decins and sp\u00e9cialistes",
    "sg:phone":"+32 2 384 33 60",
    "sg:postcode":"1420",
    "sg:province":"Brabant Wallon",
    "wof:name":"Marie-eve Flamme",
    "wof:placetype":"venue"
},
  "geometry": {"coordinates":[-75.60595703120001,37.7877616882],"type":"Point"}
}