{
  "type": "Feature",
  "properties": {
    "iso:country":"BE",
    "sg:address":"Lispersteenweg 349a",
    "sg:city":"Lier",
    "sg:classifiers":[
        {
            "category":"Personal",
            "subcategory":"Beauty Salon",
            "type":"Services"
        }
    ],
    "sg:phone":"+32 3 480 66 67",
    "sg:postcode":"2500",
    "sg:province":"Antwerpen",
    "sg:tags":[
        "de",
        "coiffure"
    ],
    "wof:name":"Coiffure Lomar",
    "wof:placetype":"venue"
},
  "geometry": {"coordinates":[4.5758199692,51.1470451355],"type":"Point"}
}