{
  "type": "Feature",
  "properties": {
    "addr:full":"Lange Kievitstraat 124 Antwerpen Antwerpen 2018",
    "addr:housenumber":"124",
    "addr:postcode":"2018",
    "addr:street":"Lange Kievitstraat",
    "iso:country":"BE",
    "sg:address":"Lange Kievitstraat 124",
    "sg:city":"Antwerpen",
    "sg:orig_category":"Epiceries",
    "sg:phone":"+32 3 231 27 64",
    "sg:postcode":"2018",
    "sg:province":"Antwerpen",
    "wof:name":"Weingarten",
    "wof:placetype":"venue"
},
  "geometry": {"coordinates":[4.4249172211,51.213470459],"type":"Point"}
}