{
  "type": "Feature",
  "properties": {
    "iso:country":"BE",
    "sg:address":"Kerkstraat 51",
    "sg:city":"Balen",
    "sg:classifiers":[
        {
            "category":"Health Services",
            "subcategory":"Health Practitioner",
            "type":"Services"
        }
    ],
    "sg:phone":"+32 14 82 03 06",
    "sg:postcode":"2490",
    "sg:province":"Antwerpen",
    "sg:tags":[
        "physiotherapist"
    ],
    "wof:name":"Trimpeneers Inge",
    "wof:placetype":"venue"
},
  "geometry": {"coordinates":[5.1711678505,51.1748161316],"type":"Point"}
}