{
  "type": "Feature",
  "properties": {
    "iso:country":"BE",
    "sg:address":"Place D'hastedon 3",
    "sg:city":"Namur",
    "sg:classifiers":[
        {
            "category":"Bars & Pubs",
            "type":"Food & Drink"
        }
    ],
    "sg:phone":"+32 81 73 07 96",
    "sg:postcode":"5000",
    "sg:province":"Namur",
    "wof:name":"Condor (le)",
    "wof:placetype":"venue"
},
  "geometry": {"coordinates":[4.8524532318,50.4707107544],"type":"Point"}
}