{
  "type": "Feature",
  "properties": {
    "iso:country":"BE",
    "sg:address":"Luikerstraat 79",
    "sg:city":"Sint-truiden",
    "sg:classifiers":[
        {
            "category":"Shopping",
            "subcategory":"Clothing, Apparel, & Fashions",
            "type":"Retail Goods"
        }
    ],
    "sg:phone":"+32 11 68 64 73",
    "sg:postcode":"3800",
    "sg:province":"Limburg",
    "sg:tags":[
        "-",
        "clothing",
        "child"
    ],
    "wof:name":"Popov",
    "wof:placetype":"venue"
},
  "geometry": {"coordinates":[5.1925768852,50.8095779419],"type":"Point"}
}