{
  "type": "Feature",
  "properties": {
    "iso:country":"BE",
    "sg:address":"Kerkstraat 13",
    "sg:city":"Boom",
    "sg:classifiers":[
        {
            "category":"Bars & Pubs",
            "type":"Food & Drink"
        }
    ],
    "sg:phone":"+32 3 844 91 11",
    "sg:postcode":"2850",
    "sg:province":"Antwerpen",
    "wof:name":"Bacchus (den)",
    "wof:placetype":"venue"
},
  "geometry": {"coordinates":[4.3639268875,51.0866012573],"type":"Point"}
}