{
  "type": "Feature",
  "properties": {
    "iso:country":"BE",
    "sg:address":"Steenweg Van Aalst 48",
    "sg:city":"Dendermonde",
    "sg:orig_category":"Imprimeries and copyshops. Activit\u00e9s diverses d'imprimerie",
    "sg:phone":"+32 52 21 48 71",
    "sg:postcode":"9200",
    "sg:province":"Oost-Vlaanderen",
    "wof:name":"Hedwig Heuninck",
    "wof:placetype":"venue"
},
  "geometry": {"coordinates":[4.0707139969,51.0293502808],"type":"Point"}
}