{
  "type": "Feature",
  "properties": {
    "iso:country":"BE",
    "sg:address":"Rue Des Combattants 73b",
    "sg:city":"Andenne (sclayn)",
    "sg:classifiers":[
        {
            "category":"Bars & Pubs",
            "type":"Food & Drink"
        }
    ],
    "sg:phone":"+32 81 58 17 23",
    "sg:postcode":"5300",
    "sg:province":"Namur",
    "wof:name":"Cocktail Du Baratin",
    "wof:placetype":"venue"
},
  "geometry": {"coordinates":[5.0251832008,50.487953186],"type":"Point"}
}