{
  "type": "Feature",
  "properties": {
    "addr:full":"Chemin De Nivelles 1 Lasne (plancenoit) Brabant Wallon 1380",
    "addr:housenumber":"1",
    "addr:postcode":"1380",
    "addr:street":"Chemin De Nivelles",
    "iso:country":"BE",
    "sg:address":"Chemin De Nivelles 1",
    "sg:city":"Lasne (plancenoit)",
    "sg:classifiers":[
        {
            "category":"Health Services",
            "subcategory":"Doctor",
            "type":"Services"
        }
    ],
    "sg:phone":"+32 2 384 66 48",
    "sg:postcode":"1380",
    "sg:province":"Brabant Wallon",
    "sg:tags":[
        "medicinephysicians",
        "surgeon"
    ],
    "wof:name":"Delwart B",
    "wof:placetype":"venue"
},
  "geometry": {"coordinates":[4.404750824,50.6461105347],"type":"Point"}
}