{
  "type": "Feature",
  "properties": {
    "addr:full":"Rue Des Ecoles 5 Aiseau-presles Hainaut 6250",
    "addr:housenumber":"5",
    "addr:postcode":"6250",
    "addr:street":"Rue Des Ecoles;Hainaut",
    "iso:country":"BE",
    "sg:address":"Rue Des Ecoles 5",
    "sg:city":"Aiseau-presles",
    "sg:orig_category":"Enseignement maternel and primaire",
    "sg:phone":"+32 71 74 03 13",
    "sg:postcode":"6250",
    "sg:province":"Hainaut",
    "wof:name":"Ecole Prim. Communale",
    "wof:placetype":"venue"
},
  "geometry": {"coordinates":[4.5971860886,50.4236907959],"type":"Point"}
}