{
  "type": "Feature",
  "properties": {
    "addr:full":"Boulevard Anspach 150 Brussel/bruxelles Bruxelles-Capitale 1000",
    "addr:housenumber":"150",
    "addr:postcode":"1000",
    "addr:street":"Boulevard Anspach;/",
    "iso:country":"BE",
    "sg:address":"Boulevard Anspach 150",
    "sg:city":"Brussel/bruxelles",
    "sg:orig_category":"Architectes",
    "sg:phone":"+32 2 502 73 87",
    "sg:postcode":"1000",
    "sg:province":"Bruxelles-Capitale",
    "wof:name":"Mustapha Firouchane",
    "wof:placetype":"venue"
},
  "geometry": {"coordinates":[4.3478579521,50.846321106],"type":"Point"}
}