{
  "type": "Feature",
  "properties": {
    "iso:country":"BE",
    "sg:address":"Damse Vaart-zuid 4",
    "sg:city":"Damme",
    "sg:classifiers":[
        {
            "category":"Restaurant",
            "type":"Food & Drink"
        }
    ],
    "sg:phone":"+32 50 35 32 99",
    "sg:postcode":"8340",
    "sg:province":"West-Vlaanderen",
    "wof:name":"Napoleon",
    "wof:placetype":"venue"
},
  "geometry": {"coordinates":[3.2792301178,51.2507400513],"type":"Point"}
}