{
  "type": "Feature",
  "properties": {
    "iso:country":"BE",
    "sg:address":"Langestraat 259",
    "sg:city":"Affligem (hekelgem)",
    "sg:classifiers":[
        {
            "category":"Personal",
            "subcategory":"Nail Salon",
            "type":"Services"
        }
    ],
    "sg:phone":"+32 53 66 32 41",
    "sg:postcode":"1790",
    "sg:province":"Vlaams-Brabant",
    "sg:tags":[
        "pedicure"
    ],
    "wof:name":"Arys L",
    "wof:placetype":"venue"
},
  "geometry": {"coordinates":[4.1121020317,50.9209861755],"type":"Point"}
}