{
  "type": "Feature",
  "properties": {
    "addr:full":"Moerestraat 34 Koekelare West-Vlaanderen 8680",
    "addr:housenumber":"34",
    "addr:postcode":"8680",
    "addr:street":"Moerestraat",
    "iso:country":"BE",
    "sg:address":"Moerestraat 34",
    "sg:city":"Koekelare",
    "sg:orig_category":"Rev\u00eatements pour sols and murs. Peinture",
    "sg:phone":"+32 51 58 88 41",
    "sg:postcode":"8680",
    "sg:province":"West-Vlaanderen",
    "wof:name":"Gilbert Seys",
    "wof:placetype":"venue"
},
  "geometry": {"coordinates":[2.9803750515,51.0945854187],"type":"Point"}
}