{
  "type": "Feature",
  "properties": {
    "addr:full":"Eikendreef 5 Leopoldsburg Limburg 3970",
    "addr:housenumber":"5",
    "addr:postcode":"3970",
    "addr:street":"Eikendreef",
    "iso:country":"BE",
    "sg:address":"Eikendreef 5",
    "sg:city":"Leopoldsburg",
    "sg:orig_category":"HUISBRANDOLIE",
    "sg:phone":"+32 11 40 14 76",
    "sg:postcode":"3970",
    "sg:province":"Limburg",
    "wof:name":"Jacobs",
    "wof:placetype":"venue"
},
  "geometry": {"coordinates":[5.2569670677,51.1052284241],"type":"Point"}
}