{
  "type": "Feature",
  "properties": {
    "iso:country":"BE",
    "sg:address":"Desselgemseweg 137",
    "sg:city":"Waregem",
    "sg:classifiers":[
        {
            "category":"Building & Trades",
            "subcategory":"Pest Control",
            "type":"Services"
        }
    ],
    "sg:phone":"+32 478 58 88 50",
    "sg:postcode":"8790",
    "sg:province":"West-Vlaanderen",
    "sg:tags":[
        "painting",
        "contractor"
    ],
    "wof:name":"Glenn Vervalle",
    "wof:placetype":"venue"
},
  "geometry": {"coordinates":[3.4032690525,50.881023407],"type":"Point"}
}