{
  "type": "Feature",
  "properties": {
    "addr:full":"Oude Heirbaan 112 Deinze Oost-Vlaanderen 9800",
    "addr:housenumber":"112",
    "addr:postcode":"9800",
    "addr:street":"Oude Heirbaan",
    "iso:country":"BE",
    "sg:address":"Oude Heirbaan 112",
    "sg:city":"Deinze",
    "sg:orig_category":"Rev\u00eatements pour sols and murs",
    "sg:phone":"+32 51 63 54 05",
    "sg:postcode":"9800",
    "sg:province":"Oost-Vlaanderen",
    "wof:name":"Rony De Groote",
    "wof:placetype":"venue"
},
  "geometry": {"coordinates":[3.4618470669,50.9659233093],"type":"Point"}
}