{
  "type": "Feature",
  "properties": {
    "iso:country":"BE",
    "sg:address":"Tabaartstraat 24",
    "sg:city":"Bilzen",
    "sg:orig_category":"Boekenuitgeverijen",
    "sg:phone":"+32 89 41 72 71",
    "sg:postcode":"3740",
    "sg:province":"Limburg",
    "wof:name":"Tom Vuerstaek",
    "wof:placetype":"venue"
},
  "geometry": {"coordinates":[5.523443222,50.8680419922],"type":"Point"}
}