{
  "type": "Feature",
  "properties": {
    "addr:full":"Rue De Rengies 25 P\u00e9ruwelz (wiers) Hainaut 7608",
    "addr:housenumber":"25",
    "addr:postcode":"7608",
    "addr:street":"Rue De Rengies",
    "iso:country":"BE",
    "sg:address":"Rue De Rengies 25",
    "sg:city":"P\u00e9ruwelz (wiers)",
    "sg:classifiers":[
        {
            "category":"Building & Trades",
            "subcategory":"Construction",
            "type":"Services"
        }
    ],
    "sg:phone":"+32 69 77 46 55",
    "sg:postcode":"7608",
    "sg:province":"Hainaut",
    "sg:tags":[
        "paper",
        "hanger"
    ],
    "wof:name":"Cocu J-m",
    "wof:placetype":"venue"
},
  "geometry": {"coordinates":[3.5525410175,50.4999732971],"type":"Point"}
}