{
  "type": "Feature",
  "properties": {
    "addr:full":"Muurveld 31 Asse Vlaams-Brabant 1730",
    "addr:housenumber":"31",
    "addr:postcode":"1730",
    "addr:street":"Muurveld",
    "iso:country":"BE",
    "sg:address":"Muurveld 31",
    "sg:city":"Asse",
    "sg:classifiers":[
        {
            "category":"Health Services",
            "subcategory":"Doctor",
            "type":"Services"
        }
    ],
    "sg:phone":"+32 2 453 14 85",
    "sg:postcode":"1730",
    "sg:province":"Vlaams-Brabant",
    "sg:tags":[
        "medicinephysicians",
        "surgeon"
    ],
    "wof:name":"Bravo P",
    "wof:placetype":"venue"
},
  "geometry": {"coordinates":[4.1962709427,50.9082565308],"type":"Point"}
}