{
  "type": "Feature",
  "properties": {
    "iso:country":"BE",
    "sg:address":"Verrebroekstraat 13",
    "sg:city":"Beveren",
    "sg:orig_category":"Varkenskwekers",
    "sg:phone":"+32 3 773 41 10",
    "sg:postcode":"9130",
    "sg:province":"Oost-Vlaanderen",
    "wof:name":"Werner Van Gysel",
    "wof:placetype":"venue"
},
  "geometry": {"coordinates":[4.189414978,51.2512321472],"type":"Point"}
}