{
  "type": "Feature",
  "properties": {
    "addr:full":"Bredabaan 889 Brasschaat Antwerpen 2930",
    "addr:housenumber":"889",
    "addr:postcode":"2930",
    "addr:street":"Bredabaan",
    "iso:country":"BE",
    "sg:address":"Bredabaan 889",
    "sg:city":"Brasschaat",
    "sg:classifiers":[
        {
            "category":"Organizations",
            "subcategory":"Professional Association",
            "type":"Services"
        }
    ],
    "sg:phone":"+32 3 663 28 40",
    "sg:postcode":"2930",
    "sg:province":"Antwerpen",
    "sg:tags":[
        "organisation",
        "seminar"
    ],
    "wof:name":"De Groene Jager",
    "wof:placetype":"venue"
},
  "geometry": {"coordinates":[4.5121498108,51.3122596741],"type":"Point"}
}