{
  "type": "Feature",
  "properties": {
    "addr:full":"Rue Des Marronniers 15 Onhaye (weillen) Namur 5523",
    "addr:housenumber":"15",
    "addr:postcode":"5523",
    "addr:street":"Rue Des Marronniers;Weillen",
    "iso:country":"BE",
    "sg:address":"Rue Des Marronniers 15",
    "sg:city":"Onhaye (weillen)",
    "sg:classifiers":[
        {
            "category":"Personal",
            "subcategory":"Beauty Salon",
            "type":"Services"
        }
    ],
    "sg:phone":"+32 82 69 97 29",
    "sg:postcode":"5523",
    "sg:province":"Namur",
    "sg:tags":[
        "lady",
        "-",
        "hairdressing"
    ],
    "wof:name":"Nicole (coiffure)",
    "wof:placetype":"venue"
},
  "geometry": {"coordinates":[4.8271818161,50.260597229],"type":"Point"}
}