{
  "type": "Feature",
  "properties": {
    "addr:full":"Snapperstraat 62 Hasselt (kuringen) Limburg 3511",
    "addr:housenumber":"62",
    "addr:postcode":"3511",
    "addr:street":"Snapperstraat",
    "iso:country":"BE",
    "sg:address":"Snapperstraat 62",
    "sg:city":"Hasselt (kuringen)",
    "sg:classifiers":[
        {
            "category":"Health Services",
            "subcategory":"Nursing And Care Facility",
            "type":"Services"
        }
    ],
    "sg:phone":"+32 11 25 24 78",
    "sg:postcode":"3511",
    "sg:province":"Limburg",
    "sg:tags":[
        "home"
    ],
    "wof:name":"Piccard D",
    "wof:placetype":"venue"
},
  "geometry": {"coordinates":[5.2607150078,50.957901001],"type":"Point"}
}