{
  "type": "Feature",
  "properties": {
    "iso:country":"BE",
    "sg:address":"De Hutten 17",
    "sg:city":"Genk",
    "sg:orig_category":"Etalage- and showroomontwerpers",
    "sg:phone":"+32 89 36 24 85",
    "sg:postcode":"3600",
    "sg:province":"Limburg",
    "wof:name":"Etalages Helena",
    "wof:placetype":"venue"
},
  "geometry": {"coordinates":[5.4549798965,50.9422111511],"type":"Point"}
}