{
  "type": "Feature",
  "properties": {
    "addr:full":"Rue Emile Wauquier 37 Quevy Hainaut 7040",
    "addr:housenumber":"37",
    "addr:postcode":"7040",
    "addr:street":"Rue Emile Wauquier;Hainaut",
    "iso:country":"BE",
    "sg:address":"Rue Emile Wauquier 37",
    "sg:city":"Quevy",
    "sg:orig_category":"Tuinbenodigdheden",
    "sg:phone":"+32 65 33 47 12",
    "sg:postcode":"7040",
    "sg:province":"Hainaut",
    "wof:name":"Ladeuze B",
    "wof:placetype":"venue"
},
  "geometry": {"coordinates":[3.9649538994,50.3938484192],"type":"Point"}
}