{
  "type": "Feature",
  "properties": {
    "addr:full":"Ter Goedingen 3 Aalter Oost-Vlaanderen 9881",
    "addr:housenumber":"3",
    "addr:postcode":"9881",
    "addr:street":"Goedingen",
    "iso:country":"BE",
    "sg:address":"Ter Goedingen 3",
    "sg:city":"Aalter",
    "sg:orig_category":"Elektrische installaties voor woningen Industri\u00eble elektrische installaties",
    "sg:phone":"+32 9 374 05 65",
    "sg:postcode":"9881",
    "sg:province":"Oost-Vlaanderen",
    "wof:name":"Hooreweghe Elektro",
    "wof:placetype":"venue"
},
  "geometry": {"coordinates":[3.4991049767,51.0936546326],"type":"Point"}
}