{
  "type": "Feature",
  "properties": {
    "addr:full":"Rue Haute Franchise 27b Rebecq Brabant Wallon 1430",
    "addr:housenumber":"27b",
    "addr:postcode":"1430",
    "addr:street":"Rue Haute Franchise",
    "iso:country":"BE",
    "sg:address":"Rue Haute Franchise 27b",
    "sg:city":"Rebecq",
    "sg:orig_category":"Informaticaconsulenten Software ontwikkeling and ontwerp",
    "sg:phone":"+32 67 63 72 31",
    "sg:postcode":"1430",
    "sg:province":"Brabant Wallon",
    "wof:name":"Softech Consulting",
    "wof:placetype":"venue"
},
  "geometry": {"coordinates":[4.1057648659,50.6527023315],"type":"Point"}
}