{
  "type": "Feature",
  "properties": {
    "addr:full":"Chemin De L'angl\u00e9e 523 Pecq (h\u00e9rinnes-lez-pecq) Hainaut 7742",
    "addr:housenumber":"523",
    "addr:postcode":"7742",
    "addr:street":"Chemin De L'Angle \u0301E",
    "iso:country":"BE",
    "sg:address":"Chemin De L'angl\u00e9e 523",
    "sg:city":"Pecq (h\u00e9rinnes-lez-pecq)",
    "sg:classifiers":[
        {
            "category":"Building & Trades",
            "subcategory":"Landscaping Services",
            "type":"Services"
        }
    ],
    "sg:phone":"+32 69 55 85 73",
    "sg:postcode":"7742",
    "sg:province":"Hainaut",
    "sg:tags":[
        "-",
        "lopping",
        "work",
        "tree",
        "felling"
    ],
    "wof:name":"Van Renterghem B",
    "wof:placetype":"venue"
},
  "geometry": {"coordinates":[3.379956007,50.7064933777],"type":"Point"}
}