{
  "type": "Feature",
  "properties": {
    "addr:full":"Hoge Mauw 24 Arendonk Antwerpen 2370",
    "addr:housenumber":"24",
    "addr:postcode":"2370",
    "addr:street":"Hoge Mauw",
    "iso:country":"BE",
    "sg:address":"Hoge Mauw 24",
    "sg:city":"Arendonk",
    "sg:orig_category":"Boekhouders",
    "sg:phone":"+32 14 67 22 28",
    "sg:postcode":"2370",
    "sg:province":"Antwerpen",
    "wof:name":"T. Vancraenendonck",
    "wof:placetype":"venue"
},
  "geometry": {"coordinates":[5.110101223,51.2995376587],"type":"Point"}
}