{
  "type": "Feature",
  "properties": {
    "addr:full":"Rue De La Station 90 Herve Li\u00e8ge 4650",
    "addr:housenumber":"90",
    "addr:postcode":"4650",
    "addr:street":"Rue De La Station",
    "iso:country":"BE",
    "sg:address":"Rue De La Station 90",
    "sg:city":"Herve",
    "sg:classifiers":[
        {
            "category":"Banks & Credit Unions",
            "subcategory":"Bank",
            "type":"Services"
        }
    ],
    "sg:phone":"+32 87 66 06 06",
    "sg:postcode":"4650",
    "sg:province":"Li\u00e8ge",
    "sg:tags":[
        "savings-banks"
    ],
    "wof:name":"Centea",
    "wof:placetype":"venue"
},
  "geometry": {"coordinates":[5.7916889191,50.6419258118],"type":"Point"}
}