{
  "type": "Feature",
  "properties": {
    "addr:full":"Spoorweglaan 44 Oudenaarde Oost-Vlaanderen 9700",
    "addr:housenumber":"44",
    "addr:postcode":"9700",
    "addr:street":"Spoorweglaan",
    "iso:country":"BE",
    "sg:address":"Spoorweglaan 44",
    "sg:city":"Oudenaarde",
    "sg:classifiers":[
        {
            "category":"Shopping",
            "subcategory":"Baby Store",
            "type":"Retail Goods"
        }
    ],
    "sg:phone":"+32 55 31 81 99",
    "sg:postcode":"9700",
    "sg:province":"Oost-Vlaanderen",
    "sg:tags":[
        "midwife"
    ],
    "wof:name":"Biasino M",
    "wof:placetype":"venue"
},
  "geometry": {"coordinates":[3.610049963,50.8282318115],"type":"Point"}
}