{
  "type": "Feature",
  "properties": {
    "addr:full":"Adolphe Maxlaan 61 Brussel/bruxelles Bruxelles-Capitale 1000",
    "addr:housenumber":"61",
    "addr:postcode":"1000",
    "addr:street":"Adolphe Maxlaan;/",
    "iso:country":"BE",
    "sg:address":"Adolphe Maxlaan 61",
    "sg:city":"Brussel/bruxelles",
    "sg:classifiers":[
        {
            "category":"Restaurant",
            "type":"Food & Drink"
        }
    ],
    "sg:phone":"+32 2 223 38 03",
    "sg:postcode":"1000",
    "sg:province":"Bruxelles-Capitale",
    "wof:name":"Snack Hamburger Sumela",
    "wof:placetype":"venue"
},
  "geometry": {"coordinates":[4.3557682037,50.8535003662],"type":"Point"}
}