{
  "type": "Feature",
  "properties": {
    "addr:full":"Rue Des Grands-pres 145 Ch\u00ean\u00e9e Li\u00e8ge 4032",
    "addr:housenumber":"145",
    "addr:postcode":"4032",
    "addr:street":"Rue Des Grands-Pres",
    "iso:country":"BE",
    "sg:address":"Rue Des Grands-pres 145",
    "sg:city":"Ch\u00ean\u00e9e",
    "sg:classifiers":[
        {
            "category":"Wholesale",
            "subcategory":"Metals & Minerals",
            "type":"Manufacturing & Wholesale Goods"
        }
    ],
    "sg:phone":"+32 4 365 39 56",
    "sg:postcode":"4032",
    "sg:province":"Li\u00e8ge",
    "sg:tags":[
        "non-ferrous"
    ],
    "wof:name":"Ets Close Et Fils S.a.",
    "wof:placetype":"venue"
},
  "geometry": {"coordinates":[5.6207971573,50.6058883667],"type":"Point"}
}