{
  "type": "Feature",
  "properties": {
    "addr:full":"Chauss\u00e9e De Ninove 153 Bruxelles (molenbeek-saint-jean) Bruxelles-Capitale 1080",
    "addr:housenumber":"153",
    "addr:postcode":"1080",
    "addr:street":"Chausse\u0301E De Ninove",
    "iso:country":"BE",
    "sg:address":"Chauss\u00e9e De Ninove 153",
    "sg:city":"Bruxelles (molenbeek-saint-jean)",
    "sg:classifiers":[
        {
            "category":"Professional",
            "subcategory":"Lawyer & Legal Services",
            "type":"Services"
        }
    ],
    "sg:phone":"+32 2 270 07 50",
    "sg:postcode":"1080",
    "sg:province":"Bruxelles-Capitale",
    "wof:name":"Van Genderen-naar Joyce",
    "wof:placetype":"venue"
},
  "geometry": {"coordinates":[4.3265900612,50.849395752],"type":"Point"}
}