{
  "type": "Feature",
  "properties": {
    "iso:country":"BE",
    "sg:address":"Hoogstraat 5b19",
    "sg:city":"Zaventem",
    "sg:orig_category":"Mat\u00e9riel de contr\u00f4le des processus industriels Fab",
    "sg:phone":"+32 2 725 86 58",
    "sg:postcode":"1930",
    "sg:province":"Vlaams-Brabant",
    "wof:name":"A.t.s.",
    "wof:placetype":"venue"
},
  "geometry": {"coordinates":[4.4774389267,50.8828315735],"type":"Point"}
}