{
  "type": "Feature",
  "properties": {
    "addr:full":"Walzegem 6 Oosterzele Oost-Vlaanderen 9860",
    "addr:housenumber":"6",
    "addr:postcode":"9860",
    "addr:street":"Walzegem;Oost-Vlaanderen",
    "iso:country":"BE",
    "sg:address":"Walzegem 6",
    "sg:city":"Oosterzele",
    "sg:classifiers":[
        {
            "category":"Cafe",
            "type":"Food & Drink"
        }
    ],
    "sg:phone":"+32 9 360 37 89",
    "sg:postcode":"9860",
    "sg:province":"Oost-Vlaanderen",
    "sg:tags":[
        "caf\u00e9s"
    ],
    "wof:name":"Haesebeyt Nikolaas",
    "wof:placetype":"venue"
},
  "geometry": {"coordinates":[3.804240942,50.9045944214],"type":"Point"}
}