{
  "type": "Feature",
  "properties": {
    "addr:full":"Meensestraat 32 Ieper West-Vlaanderen 8900",
    "addr:housenumber":"32",
    "addr:postcode":"8900",
    "addr:street":"Meensestraat",
    "iso:country":"BE",
    "sg:address":"Meensestraat 32",
    "sg:city":"Ieper",
    "sg:orig_category":"Dameskledingzaken",
    "sg:phone":"+32 57 20 07 52",
    "sg:postcode":"8900",
    "sg:province":"West-Vlaanderen",
    "wof:name":"Huis Toppio",
    "wof:placetype":"venue"
},
  "geometry": {"coordinates":[2.8897049427,50.8516082764],"type":"Point"}
}