{
  "type": "Feature",
  "properties": {
    "iso:country":"BE",
    "sg:address":"Kakebeekstraat 10",
    "sg:city":"Bocholt",
    "sg:classifiers":[
        {
            "category":"Industrial Area",
            "type":"Public Place"
        }
    ],
    "sg:phone":"+32 89 71 91 00",
    "sg:postcode":"3950",
    "sg:province":"Limburg",
    "sg:tags":[
        "-",
        "laser"
    ],
    "wof:name":"Virtek Europe Nv",
    "wof:placetype":"venue"
},
  "geometry": {"coordinates":[5.6126260757,51.1846847534],"type":"Point"}
}