{
  "type": "Feature",
  "properties": {
    "iso:country":"BE",
    "sg:address":"Zeswegestraat 42",
    "sg:city":"Wingene",
    "sg:orig_category":"Voertuigen",
    "sg:phone":"+32 51 61 10 44",
    "sg:postcode":"8750",
    "sg:province":"West-Vlaanderen",
    "wof:name":"Garage De Keyzer",
    "wof:placetype":"venue"
},
  "geometry": {"coordinates":[3.1881821156,51.0404777527],"type":"Point"}
}