{
  "type": "Feature",
  "properties": {
    "addr:full":"Avenue Joseph Wauters 145bb Mons Hainaut 7000",
    "addr:housenumber":"145bb",
    "addr:postcode":"7000",
    "addr:street":"Avenue Joseph Wauters;Hainaut",
    "iso:country":"BE",
    "sg:address":"Avenue Joseph Wauters 145bb",
    "sg:city":"Mons",
    "sg:orig_category":"D\u00e9taillants en pi\u00e8ces and accessoires de voitures. Pi\u00e8ces and accessoires de v\u00e9hicules automobiles G",
    "sg:phone":"+32 65 35 32 44",
    "sg:postcode":"7000",
    "sg:province":"Hainaut",
    "wof:name":"B.g.",
    "wof:placetype":"venue"
},
  "geometry": {"coordinates":[3.9354391098,50.4486122131],"type":"Point"}
}