{
  "type": "Feature",
  "properties": {
    "iso:country":"BE",
    "sg:address":"Beerveldedorp 68",
    "sg:city":"Lochristi",
    "sg:orig_category":"Postkantoren Verzekeringsmakelaars and experts",
    "sg:phone":"+32 9 355 59 25",
    "sg:postcode":"9080",
    "sg:province":"Oost-Vlaanderen",
    "wof:name":"De Post",
    "wof:placetype":"venue"
},
  "geometry": {"coordinates":[3.8789849281,51.0799179077],"type":"Point"}
}