{
  "type": "Feature",
  "properties": {
    "addr:full":"Hogenhovestr 59 Tielt West-Vlaanderen 8700",
    "addr:housenumber":"59",
    "addr:postcode":"8700",
    "addr:street":"Hogenhovestr",
    "iso:country":"BE",
    "sg:address":"Hogenhovestr 59",
    "sg:city":"Tielt",
    "sg:classifiers":[
        {
            "category":"Bakery",
            "type":"Food & Drink"
        }
    ],
    "sg:phone":"+32 51 63 34 89",
    "sg:postcode":"8700",
    "sg:province":"West-Vlaanderen",
    "sg:tags":[
        "cake",
        "product",
        "related",
        "bread"
    ],
    "wof:name":"Bakkerij Ranson-canniere Bvba",
    "wof:placetype":"venue"
},
  "geometry": {"coordinates":[3.4186680317,50.9859848022],"type":"Point"}
}