{
  "type": "Feature",
  "properties": {
    "iso:country":"BE",
    "sg:address":"Weg Naar As 200",
    "sg:city":"Genk",
    "sg:classifiers":[
        {
            "category":"Fast Food",
            "type":"Food & Drink"
        }
    ],
    "sg:phone":"+32 89 35 09 57",
    "sg:postcode":"3600",
    "sg:province":"Limburg",
    "sg:tags":[
        "fried",
        "stand",
        "potato"
    ],
    "wof:name":"Brethof",
    "wof:placetype":"venue"
},
  "geometry": {"coordinates":[5.5211291313,50.9749336243],"type":"Point"}
}