{
  "type": "Feature",
  "properties": {
    "addr:full":"Rue Saint-roch 1ba Modave Li\u00e8ge 4577",
    "addr:housenumber":"1ba",
    "addr:postcode":"4577",
    "addr:street":"Rue Saint-Roch",
    "iso:country":"BE",
    "sg:address":"Rue Saint-roch 1ba",
    "sg:city":"Modave",
    "sg:orig_category":"Boomkwekerijen",
    "sg:phone":"+32 85 51 36 08",
    "sg:postcode":"4577",
    "sg:province":"Li\u00e8ge",
    "wof:name":"P\u00c9pini\u00c8re St.genevi\u00c8ve",
    "wof:placetype":"venue"
},
  "geometry": {"coordinates":[5.2979922295,50.4443855286],"type":"Point"}
}