{
  "type": "Feature",
  "properties": {
    "iso:country":"BE",
    "sg:address":"Rue Des Ecoles 10",
    "sg:city":"Saint-nicolas",
    "sg:orig_category":"Woningbouw",
    "sg:phone":"+32 4 247 12 41",
    "sg:postcode":"4420",
    "sg:province":"Li\u00e8ge",
    "wof:name":"Mirabella",
    "wof:placetype":"venue"
},
  "geometry": {"coordinates":[5.5202350616,50.6426773071],"type":"Point"}
}