{
  "type": "Feature",
  "properties": {
    "addr:full":"Berkenstraat 11 Oostkamp West-Vlaanderen 8020",
    "addr:housenumber":"11",
    "addr:postcode":"8020",
    "addr:street":"Berkenstraat",
    "iso:country":"BE",
    "sg:address":"Berkenstraat 11",
    "sg:city":"Oostkamp",
    "sg:classifiers":[
        {
            "category":"Real Estate",
            "subcategory":"Architect",
            "type":"Services"
        }
    ],
    "sg:phone":"+32 50 35 61 94",
    "sg:postcode":"8020",
    "sg:province":"West-Vlaanderen",
    "wof:name":"Lamsens S",
    "wof:placetype":"venue"
},
  "geometry": {"coordinates":[3.2420859337,51.1778755188],"type":"Point"}
}