{
  "type": "Feature",
  "properties": {
    "addr:full":"33 Avenue Jules Cesar - Brussels Bruxelles-Capitale 1150",
    "addr:housenumber":"33",
    "addr:postcode":"1150",
    "addr:street":"Avenue Jules Cesar Brussels",
    "iso:country":"BE",
    "sg:address":"33 Avenue Jules Cesar -",
    "sg:city":"Brussels",
    "sg:classifiers":[
        {
            "category":"Professional",
            "subcategory":"Art Services",
            "type":"Services"
        }
    ],
    "sg:phone":"+32 2 771 68 15",
    "sg:postcode":"1150",
    "sg:province":"Bruxelles-Capitale",
    "sg:tags":[
        "export-import"
    ],
    "wof:name":"Poland Embassy",
    "wof:placetype":"venue"
},
  "geometry": {"coordinates":[4.4189047813,50.8328018188],"type":"Point"}
}