{
  "type": "Feature",
  "properties": {
    "addr:full":"Rue Mitoyenne 340 Lontzen Li\u00e8ge 4710",
    "addr:housenumber":"340",
    "addr:postcode":"4710",
    "addr:street":"Rue Mitoyenne",
    "iso:country":"BE",
    "sg:address":"Rue Mitoyenne 340",
    "sg:city":"Lontzen",
    "sg:classifiers":[
        {
            "category":"Wholesale",
            "subcategory":"Farm Supplies",
            "type":"Manufacturing & Wholesale Goods"
        }
    ],
    "sg:phone":"+32 87 88 18 17",
    "sg:postcode":"4710",
    "sg:province":"Li\u00e8ge",
    "sg:tags":[
        "machine",
        "agricoles",
        "mat\u00e9riel",
        "gr"
    ],
    "wof:name":"Joskin Herbesthal",
    "wof:placetype":"venue"
},
  "geometry": {"coordinates":[5.9656300545,50.6769104004],"type":"Point"}
}