{
  "type": "Feature",
  "properties": {
    "addr:full":"Driesstraat 22 Waregem West-Vlaanderen 8790",
    "addr:housenumber":"22",
    "addr:postcode":"8790",
    "addr:street":"Driesstraat",
    "iso:country":"BE",
    "sg:address":"Driesstraat 22",
    "sg:city":"Waregem",
    "sg:classifiers":[
        {
            "category":"Communications",
            "subcategory":"Radio Station",
            "type":"Services"
        }
    ],
    "sg:phone":"+32 56 60 67 38",
    "sg:postcode":"8790",
    "sg:province":"West-Vlaanderen",
    "sg:tags":[
        "diffusion",
        "production",
        "de",
        "programme"
    ],
    "wof:name":"Radio Diamant",
    "wof:placetype":"venue"
},
  "geometry": {"coordinates":[3.4533920288,50.8822059631],"type":"Point"}
}