{
  "type": "Feature",
  "properties": {
    "addr:full":"Karel Oomsstraat 32 Antwerpen Antwerpen 2018",
    "addr:housenumber":"32",
    "addr:postcode":"2018",
    "addr:street":"Karel Oomsstraat",
    "iso:country":"BE",
    "sg:address":"Karel Oomsstraat 32",
    "sg:city":"Antwerpen",
    "sg:classifiers":[
        {
            "category":"Professional",
            "subcategory":"Credit Reporting & Collection",
            "type":"Services"
        }
    ],
    "sg:phone":"+32 3 216 33 31",
    "sg:postcode":"2018",
    "sg:province":"Antwerpen",
    "sg:tags":[
        "bailiff"
    ],
    "wof:name":"Wellens M",
    "wof:placetype":"venue"
},
  "geometry": {"coordinates":[4.4091939926,51.1960868835],"type":"Point"}
}