{
  "type": "Feature",
  "properties": {
    "addr:full":"Square Edmond Machtens 1 Bruxelles (molenbeek-saint-jean) Bruxelles-Capitale 1080",
    "addr:housenumber":"1",
    "addr:postcode":"1080",
    "addr:street":"Square Edmond Machtens",
    "iso:country":"BE",
    "sg:address":"Square Edmond Machtens 1",
    "sg:city":"Bruxelles (molenbeek-saint-jean)",
    "sg:orig_category":"Solariums",
    "sg:phone":"+32 2 410 68 18",
    "sg:postcode":"1080",
    "sg:province":"Bruxelles-Capitale",
    "wof:name":"Bruma Sprl",
    "wof:placetype":"venue"
},
  "geometry": {"coordinates":[4.3127689362,50.8517799377],"type":"Point"}
}