{
  "type": "Feature",
  "properties": {
    "iso:country":"BE",
    "sg:address":"Rue Bierque 21",
    "sg:city":"Thuin (goz\u00e9e)",
    "sg:classifiers":[
        {
            "category":"Insurance",
            "subcategory":"Insurance Agent",
            "type":"Services"
        }
    ],
    "sg:phone":"+32 71 51 90 10",
    "sg:postcode":"6534",
    "sg:province":"Hainaut",
    "sg:tags":[
        "broker"
    ],
    "wof:name":"Assurances Patrick Roba Sprl",
    "wof:placetype":"venue"
},
  "geometry": {"coordinates":[4.3559799194,50.3431282043],"type":"Point"}
}