{
  "type": "Feature",
  "properties": {
    "addr:full":"Homerusstraat 44 Anderlecht Bruxelles-Capitale 1070",
    "addr:housenumber":"44",
    "addr:postcode":"1070",
    "addr:street":"Homerusstraat",
    "iso:country":"BE",
    "sg:address":"Homerusstraat 44",
    "sg:city":"Anderlecht",
    "sg:orig_category":"Artsen and specialisten",
    "sg:phone":"+32 2 522 11 05",
    "sg:postcode":"1070",
    "sg:province":"Bruxelles-Capitale",
    "wof:name":"Consultation Nourrissons",
    "wof:placetype":"venue"
},
  "geometry": {"coordinates":[4.2871928215,50.8430900574],"type":"Point"}
}