{
  "type": "Feature",
  "properties": {
    "iso:country":"BE",
    "sg:address":"Route De Paifve 4",
    "sg:city":"Bassenge (glons)",
    "sg:classifiers":[
        {
            "category":"Education",
            "subcategory":"School",
            "type":"Public Place"
        }
    ],
    "sg:phone":"+32 4 286 42 46",
    "sg:postcode":"4690",
    "sg:province":"Li\u00e8ge",
    "sg:tags":[
        "-",
        "private"
    ],
    "wof:name":"C.d.t.p",
    "wof:placetype":"venue"
},
  "geometry": {"coordinates":[5.5338177681,50.7513237],"type":"Point"}
}