{
  "type": "Feature",
  "properties": {
    "addr:full":"Boulevard Emile De Laveleye 191 Li\u00c8ge Li\u00e8ge 4020",
    "addr:housenumber":"191",
    "addr:postcode":"4020",
    "addr:street":"Boulevard Emile De Laveleye",
    "iso:country":"BE",
    "sg:address":"Boulevard Emile De Laveleye 191",
    "sg:city":"Li\u00c8ge",
    "sg:orig_category":"Sociale secretariaten",
    "sg:phone":"+32 4 341 09 74",
    "sg:postcode":"4020",
    "sg:province":"Li\u00e8ge",
    "wof:name":"Secr\u00c9tariat Soc. Seco-m",
    "wof:placetype":"venue"
},
  "geometry": {"coordinates":[5.5917029381,50.6196784973],"type":"Point"}
}