{
  "type": "Feature",
  "properties": {
    "iso:country":"BE",
    "sg:address":"Nachtegaalstraat 29",
    "sg:city":"Ingelmunster",
    "sg:classifiers":[
        {
            "category":"Building & Trades",
            "subcategory":"Construction",
            "type":"Services"
        }
    ],
    "sg:phone":"+32 51 32 18 10",
    "sg:postcode":"8770",
    "sg:province":"West-Vlaanderen",
    "sg:tags":[
        "carpenter"
    ],
    "wof:name":"Vermeersch K",
    "wof:placetype":"venue"
},
  "geometry": {"coordinates":[3.2509799004,50.9117584229],"type":"Point"}
}