{
  "type": "Feature",
  "properties": {
    "iso:country":"BE",
    "sg:address":"All\u00e9e Des Sports 12",
    "sg:city":"Gerpinnes (loverval)",
    "sg:classifiers":[
        {
            "category":"Arena",
            "subcategory":"Sports Club",
            "type":"Entertainment"
        }
    ],
    "sg:phone":"+32 71 60 11 60",
    "sg:postcode":"6280",
    "sg:province":"Hainaut",
    "wof:name":"Adeps-centre Sportif La Ferme Du Ch\u00e2teau",
    "wof:placetype":"venue"
},
  "geometry": {"coordinates":[4.5276851654,50.3365364075],"type":"Point"}
}