{
  "type": "Feature",
  "properties": {
    "addr:full":"Musschaverstraat 45 Nevele Oost-Vlaanderen 9850",
    "addr:housenumber":"45",
    "addr:postcode":"9850",
    "addr:street":"Musschaverstraat",
    "iso:country":"BE",
    "sg:address":"Musschaverstraat 45",
    "sg:city":"Nevele",
    "sg:orig_category":"Eleveurs and marchands de porcs",
    "sg:phone":"+32 9 371 53 40",
    "sg:postcode":"9850",
    "sg:province":"Oost-Vlaanderen",
    "wof:name":"Johan De Cooman",
    "wof:placetype":"venue"
},
  "geometry": {"coordinates":[3.6069219112,51.0577354431],"type":"Point"}
}