{
  "type": "Feature",
  "properties": {
    "iso:country":"BE",
    "sg:address":"Burggr. Vande Vyvereln 13",
    "sg:city":"Tielt",
    "sg:orig_category":"HUISBRANDOLIE",
    "sg:phone":"+32 51 40 06 00",
    "sg:postcode":"8700",
    "sg:province":"West-Vlaanderen",
    "wof:name":"Frans Hallaert",
    "wof:placetype":"venue"
},
  "geometry": {"coordinates":[3.3203239441,51.0039558411],"type":"Point"}
}