{
  "type": "Feature",
  "properties": {
    "addr:full":"Wagenmakersstraat 46 Kortrijk West-Vlaanderen 8500",
    "addr:housenumber":"46",
    "addr:postcode":"8500",
    "addr:street":"Wagenmakersstraat",
    "iso:country":"BE",
    "sg:address":"Wagenmakersstraat 46",
    "sg:city":"Kortrijk",
    "sg:classifiers":[
        {
            "category":"Manufacturing",
            "subcategory":"Chemicals & Compounds",
            "type":"Manufacturing & Wholesale Goods"
        }
    ],
    "sg:phone":"+32 56 20 29 11",
    "sg:postcode":"8500",
    "sg:province":"West-Vlaanderen",
    "sg:tags":[
        "pharmaceutical",
        "chemistry",
        "-",
        "by-product"
    ],
    "wof:name":"Duthoo-costeur Nv",
    "wof:placetype":"venue"
},
  "geometry": {"coordinates":[3.2736029625,50.8190078735],"type":"Point"}
}