{
  "type": "Feature",
  "properties": {
    "addr:full":"Pastoor Legrandstraat 61 Leuven (wilsele) Vlaams-Brabant 3012",
    "addr:housenumber":"61",
    "addr:postcode":"3012",
    "addr:street":"Pastoor Legrandstraat",
    "iso:country":"BE",
    "sg:address":"Pastoor Legrandstraat 61",
    "sg:city":"Leuven (wilsele)",
    "sg:classifiers":[
        {
            "category":"Health Services",
            "subcategory":"Health Practitioner",
            "type":"Services"
        }
    ],
    "sg:phone":"+32 16 29 50 59",
    "sg:postcode":"3012",
    "sg:province":"Vlaams-Brabant",
    "sg:tags":[
        "physiotherapist"
    ],
    "wof:name":"Schollen E",
    "wof:placetype":"venue"
},
  "geometry": {"coordinates":[4.7055101395,50.895980835],"type":"Point"}
}