{
  "type": "Feature",
  "properties": {
    "iso:country":"BE",
    "sg:address":"Stationsstraat 28",
    "sg:city":"Zelzate",
    "sg:orig_category":"Supermarkten",
    "sg:phone":"+32 9 345 50 16",
    "sg:postcode":"9060",
    "sg:province":"Oost-Vlaanderen",
    "wof:name":"Samgo",
    "wof:placetype":"venue"
},
  "geometry": {"coordinates":[3.8072879314,51.1999206543],"type":"Point"}
}