{
  "type": "Feature",
  "properties": {
    "iso:country":"BE",
    "sg:address":"Chauss\u00e9e De Namur 33",
    "sg:city":"Villers-la-ville (sart-dames-avelines)",
    "sg:classifiers":[
        {
            "category":"Retail",
            "subcategory":"Auto Repair",
            "type":"Services"
        }
    ],
    "sg:phone":"+32 71 87 93 19",
    "sg:postcode":"1495",
    "sg:province":"Brabant Wallon",
    "sg:tags":[
        "breakdown",
        "automobile",
        "-",
        "recovery"
    ],
    "wof:name":"Vanden Elsen M",
    "wof:placetype":"venue"
},
  "geometry": {"coordinates":[4.481156826,50.5605697632],"type":"Point"}
}