{
  "type": "Feature",
  "properties": {
    "addr:full":"Eikelbosstraat 14 Hechtel-eksel Limburg 3941",
    "addr:housenumber":"14",
    "addr:postcode":"3941",
    "addr:street":"Eikelbosstraat",
    "iso:country":"BE",
    "sg:address":"Eikelbosstraat 14",
    "sg:city":"Hechtel-eksel",
    "sg:orig_category":"Gespecialiseerde residenti\u00eble bouw Installatie van metalen schrijnwerk SMEEDWERK, METAALBEWERKING AN",
    "sg:phone":"+32 11 63 55 78",
    "sg:postcode":"3941",
    "sg:province":"Limburg",
    "wof:name":"Japo Hekwerken",
    "wof:placetype":"venue"
},
  "geometry": {"coordinates":[5.4244089127,51.1673316956],"type":"Point"}
}