{
  "type": "Feature",
  "properties": {
    "iso:country":"BE",
    "sg:address":"Bombardonweg 220",
    "sg:city":"Liedekerke",
    "sg:orig_category":"Pain, p\u00e2tisseries and confiseries",
    "sg:phone":"+32 53 68 09 43",
    "sg:postcode":"1770",
    "sg:province":"Vlaams-Brabant",
    "wof:name":"Johan Van Riet",
    "wof:placetype":"venue"
},
  "geometry": {"coordinates":[4.0980291367,50.8635177612],"type":"Point"}
}