{
  "type": "Feature",
  "properties": {
    "addr:full":"Hondstraat 31 Tielt West-Vlaanderen 8700",
    "addr:housenumber":"31",
    "addr:postcode":"8700",
    "addr:street":"Hondstraat",
    "iso:country":"BE",
    "sg:address":"Hondstraat 31",
    "sg:city":"Tielt",
    "sg:classifiers":[
        {
            "category":"Home & Garden",
            "subcategory":"Building Materials",
            "type":"Retail Goods"
        }
    ],
    "sg:phone":"+32 51 40 70 98",
    "sg:postcode":"8700",
    "sg:province":"West-Vlaanderen",
    "sg:tags":[
        "insulation",
        "thermical"
    ],
    "wof:name":"Verbeke-devos Bvba",
    "wof:placetype":"venue"
},
  "geometry": {"coordinates":[3.3169701099,51.0051765442],"type":"Point"}
}