{
  "type": "Feature",
  "properties": {
    "addr:full":"Gebladertelaan 12 Ukkel/uccle Bruxelles-Capitale 1180",
    "addr:housenumber":"12",
    "addr:postcode":"1180",
    "addr:street":"Gebladertelaan;/",
    "iso:country":"BE",
    "sg:address":"Gebladertelaan 12",
    "sg:city":"Ukkel/uccle",
    "sg:orig_category":"Artiesten and kunstenaars",
    "sg:phone":"+32 2 372 07 71",
    "sg:postcode":"1180",
    "sg:province":"Bruxelles-Capitale",
    "wof:name":"Dani\u00c8le Lienart",
    "wof:placetype":"venue"
},
  "geometry": {"coordinates":[4.3775310516,50.7887268066],"type":"Point"}
}