{
  "type": "Feature",
  "properties": {
    "iso:country":"BE",
    "sg:address":"Route De Poix 11 B",
    "sg:city":"Saint-hubert",
    "sg:orig_category":"Timbres, monnaies and troph\u00e9es. Location de v\u00e9hicules sauf voitures. V\u00e9los. Motos. R\u00e9parations and e",
    "sg:phone":"+32 61 61 28 10",
    "sg:postcode":"6870",
    "sg:province":"Luxembourg",
    "wof:name":"Godfroid Cycles Et Sports",
    "wof:placetype":"venue"
},
  "geometry": {"coordinates":[5.3617601395,50.0262031555],"type":"Point"}
}