{
  "type": "Feature",
  "properties": {
    "iso:country":"BE",
    "sg:address":"Avenue De Hinnisdael 55",
    "sg:city":"Bruxelles (woluwe-saint-pierre)",
    "sg:classifiers":[
        {
            "category":"Parking",
            "subcategory":"Bicycle",
            "type":"Transportation"
        }
    ],
    "sg:phone":"+32 2 772 52 83",
    "sg:postcode":"1150",
    "sg:province":"Bruxelles-Capitale",
    "sg:tags":[
        "chiropodist"
    ],
    "wof:name":"Schuer G",
    "wof:placetype":"venue"
},
  "geometry": {"coordinates":[4.4649410248,50.8428001404],"type":"Point"}
}