{
  "type": "Feature",
  "properties": {
    "iso:country":"BE",
    "sg:address":"Rue Scheutveld 60a",
    "sg:city":"Anderlecht",
    "sg:orig_category":"D\u00e9chets and d\u00e9bris Produits chimiques Gr",
    "sg:phone":"+32 2 523 72 78",
    "sg:postcode":"1070",
    "sg:province":"Bruxelles-Capitale",
    "wof:name":"Abes",
    "wof:placetype":"venue"
},
  "geometry": {"coordinates":[4.3144669533,50.8426055908],"type":"Point"}
}