{
  "type": "Feature",
  "properties": {
    "addr:full":"Vlasgaardstraat 9 Assenede Oost-Vlaanderen 9968",
    "addr:housenumber":"9",
    "addr:postcode":"9968",
    "addr:street":"Vlasgaardstraat",
    "iso:country":"BE",
    "sg:address":"Vlasgaardstraat 9",
    "sg:city":"Assenede",
    "sg:orig_category":"Rundveehouders Varkenskwekers",
    "sg:phone":"+32 9 344 69 74",
    "sg:postcode":"9968",
    "sg:province":"Oost-Vlaanderen",
    "wof:name":"Andre De Wever",
    "wof:placetype":"venue"
},
  "geometry": {"coordinates":[3.705589056,51.1901435852],"type":"Point"}
}