{
  "type": "Feature",
  "properties": {
    "addr:full":"Rue Sainte-anne 10 Bruxelles Bruxelles-Capitale 1000",
    "addr:housenumber":"10",
    "addr:postcode":"1000",
    "addr:street":"Rue Sainte-Anne",
    "iso:country":"BE",
    "sg:address":"Rue Sainte-anne 10",
    "sg:city":"Bruxelles",
    "sg:classifiers":[
        {
            "category":"Arts & Performance",
            "subcategory":"Art Gallery",
            "type":"Entertainment"
        }
    ],
    "sg:phone":"+32 2 512 67 77",
    "sg:postcode":"1000",
    "sg:province":"Bruxelles-Capitale",
    "wof:name":"International Art Gallery St Anne",
    "wof:placetype":"venue"
},
  "geometry": {"coordinates":[4.3564248085,50.8416213989],"type":"Point"}
}