{
  "type": "Feature",
  "properties": {
    "addr:full":"Rue Africaine 106 Bruxelles (ixelles) Bruxelles-Capitale 1050",
    "addr:housenumber":"106",
    "addr:postcode":"1050",
    "addr:street":"Rue Africaine",
    "iso:country":"BE",
    "sg:address":"Rue Africaine 106",
    "sg:city":"Bruxelles (ixelles)",
    "sg:classifiers":[
        {
            "category":"Home & Garden",
            "subcategory":"Home Furnishings",
            "type":"Retail Goods"
        }
    ],
    "sg:phone":"+32 2 537 04 96",
    "sg:postcode":"1050",
    "sg:province":"Bruxelles-Capitale",
    "sg:tags":[
        "interior",
        "decoration"
    ],
    "wof:name":"Ethnies Sprl",
    "wof:placetype":"venue"
},
  "geometry": {"coordinates":[4.3550171852,50.8230133057],"type":"Point"}
}