{
  "type": "Feature",
  "properties": {
    "iso:country":"BE",
    "sg:address":"Avenue Reine Astrid 131",
    "sg:city":"Spa",
    "sg:classifiers":[
        {
            "category":"Travel",
            "subcategory":"Resort",
            "type":"Entertainment"
        }
    ],
    "sg:phone":"+32 87 77 41 61",
    "sg:postcode":"4900",
    "sg:province":"Li\u00e8ge",
    "sg:tags":[
        "health"
    ],
    "wof:name":"Heures Claires (les)",
    "wof:placetype":"venue"
},
  "geometry": {"coordinates":[5.8512539864,50.4909057617],"type":"Point"}
}