{
  "type": "Feature",
  "properties": {
    "iso:country":"BE",
    "sg:address":"Tuinwijkstraat 43",
    "sg:city":"Halen (zelem)",
    "sg:classifiers":[
        {
            "category":"Building & Trades",
            "subcategory":"Electrical",
            "type":"Services"
        }
    ],
    "sg:phone":"+32 13 44 18 13",
    "sg:postcode":"3545",
    "sg:province":"Limburg",
    "sg:tags":[
        "-",
        "electric",
        "contractor"
    ],
    "wof:name":"Eda",
    "wof:placetype":"venue"
},
  "geometry": {"coordinates":[5.1234240532,50.9826049805],"type":"Point"}
}