{
  "type": "Feature",
  "properties": {
    "iso:country":"BE",
    "sg:address":"Neerstraat 48",
    "sg:city":"Brakel (nederbrakel)",
    "sg:classifiers":[
        {
            "category":"Tea Room",
            "subcategory":"None",
            "type":"Food & Drink"
        }
    ],
    "sg:phone":"+32 55 42 13 24",
    "sg:postcode":"9660",
    "sg:province":"Oost-Vlaanderen",
    "wof:name":"De Louvre",
    "wof:placetype":"venue"
},
  "geometry": {"coordinates":[3.7667191029,50.8042984009],"type":"Point"}
}