{
  "type": "Feature",
  "properties": {
    "iso:country":"BE",
    "sg:address":"Passage Wellington 165 Box 25",
    "sg:city":"Waterloo",
    "sg:classifiers":[
        {
            "category":"Personal",
            "subcategory":"Beauty Salon",
            "type":"Services"
        }
    ],
    "sg:phone":"+32 2 354 52 94",
    "sg:postcode":"1410",
    "sg:province":"Brabant Wallon",
    "sg:tags":[
        "lady",
        "-",
        "hairdressing"
    ],
    "wof:name":"Caryss Cr\u00e9ation",
    "wof:placetype":"venue"
},
  "geometry": {"coordinates":[4.3995580673,50.7164573669],"type":"Point"}
}