{
  "type": "Feature",
  "properties": {
    "iso:country":"BE",
    "sg:address":"Rue De Neufvilles 482",
    "sg:city":"Soignies",
    "sg:orig_category":"Artsen and specialisten",
    "sg:phone":"+32 67 33 36 73",
    "sg:postcode":"7063",
    "sg:province":"Hainaut",
    "wof:name":"Francis Dassonville",
    "wof:placetype":"venue"
},
  "geometry": {"coordinates":[3.993940115,50.5837898254],"type":"Point"}
}