{
  "type": "Feature",
  "properties": {
    "addr:full":"Koning Leopoldlaan 93 Lommel Limburg 3920",
    "addr:housenumber":"93",
    "addr:postcode":"3920",
    "addr:street":"Koning Leopoldlaan",
    "iso:country":"BE",
    "sg:address":"Koning Leopoldlaan 93",
    "sg:city":"Lommel",
    "sg:orig_category":"Traitements param\u00e9dicaux",
    "sg:phone":"+32 11 54 13 41",
    "sg:postcode":"3920",
    "sg:province":"Limburg",
    "wof:name":"Wit-gele Kruis",
    "wof:placetype":"venue"
},
  "geometry": {"coordinates":[5.3226809502,51.2294998169],"type":"Point"}
}