{
  "type": "Feature",
  "properties": {
    "addr:full":"Rue Du Docq 7 Tongrinne Namur 5140",
    "addr:housenumber":"7",
    "addr:postcode":"5140",
    "addr:street":"Rue Du Docq",
    "iso:country":"BE",
    "sg:address":"Rue Du Docq 7",
    "sg:city":"Tongrinne",
    "sg:orig_category":"Viessmann. Plomberie, chauffage and installations sanitaires. Services de Nettoyage and de D\u00e9sinfect",
    "sg:phone":"+32 71 88 64 90",
    "sg:postcode":"5140",
    "sg:province":"Namur",
    "wof:name":"Dumont",
    "wof:placetype":"venue"
},
  "geometry": {"coordinates":[4.6238408089,50.5173912048],"type":"Point"}
}