{
  "type": "Feature",
  "properties": {
    "addr:full":"Avenue Docteur Zamenhof 14 Box 74 Bruxelles (anderlecht) Bruxelles-Capitale 1070",
    "addr:housenumber":"14 box 74",
    "addr:postcode":"1070",
    "addr:street":"Avenue Docteur Zamenhof",
    "iso:country":"BE",
    "sg:address":"Avenue Docteur Zamenhof 14 Box 74",
    "sg:city":"Bruxelles (anderlecht)",
    "sg:classifiers":[
        {
            "category":"Professional",
            "subcategory":"Engineering",
            "type":"Services"
        }
    ],
    "sg:phone":"+32 2 511 90 98",
    "sg:postcode":"1070",
    "sg:province":"Bruxelles-Capitale",
    "sg:tags":[
        "-"
    ],
    "wof:name":"E C M-design",
    "wof:placetype":"venue"
},
  "geometry": {"coordinates":[4.3070178032,50.8281784058],"type":"Point"}
}