{
  "type": "Feature",
  "properties": {
    "addr:full":"Wildekouter 23 Nevele Oost-Vlaanderen 9850",
    "addr:housenumber":"23",
    "addr:postcode":"9850",
    "addr:street":"Wildekouter",
    "iso:country":"BE",
    "sg:address":"Wildekouter 23",
    "sg:city":"Nevele",
    "sg:classifiers":[
        {
            "category":"Arena",
            "subcategory":"Sports Club",
            "type":"Entertainment"
        }
    ],
    "sg:phone":"+32 9 227 22 37",
    "sg:postcode":"9850",
    "sg:province":"Oost-Vlaanderen",
    "sg:tags":[
        "de"
    ],
    "wof:name":"H.c. Indiana",
    "wof:placetype":"venue"
},
  "geometry": {"coordinates":[3.5494019985,51.0329589844],"type":"Point"}
}