{
  "type": "Feature",
  "properties": {
    "iso:country":"BE",
    "sg:address":"Petit-sart 3a",
    "sg:city":"Lierneux",
    "sg:orig_category":"Tuinen",
    "sg:phone":"+32 80 41 81 82",
    "sg:postcode":"4990",
    "sg:province":"Li\u00e8ge",
    "wof:name":"Rensonnet",
    "wof:placetype":"venue"
},
  "geometry": {"coordinates":[5.8436012268,50.2703781128],"type":"Point"}
}