{
  "type": "Feature",
  "properties": {
    "addr:full":"Stationsstraat 24 Brakel (nederbrakel) Oost-Vlaanderen 9660",
    "addr:housenumber":"24",
    "addr:postcode":"9660",
    "addr:street":"Stationsstraat",
    "iso:country":"BE",
    "sg:address":"Stationsstraat 24",
    "sg:city":"Brakel (nederbrakel)",
    "sg:classifiers":[
        {
            "category":"Health Services",
            "subcategory":"Health Practitioner",
            "type":"Services"
        }
    ],
    "sg:phone":"+32 55 42 29 60",
    "sg:postcode":"9660",
    "sg:province":"Oost-Vlaanderen",
    "sg:tags":[
        "physiotherapist"
    ],
    "wof:name":"Baquet P",
    "wof:placetype":"venue"
},
  "geometry": {"coordinates":[3.7653970718,50.800945282],"type":"Point"}
}