{
  "type": "Feature",
  "properties": {
    "iso:country":"BE",
    "sg:address":"Gros-fays 41",
    "sg:city":"Bievre",
    "sg:orig_category":"Rundveehouders",
    "sg:phone":"+32 61 50 00 79",
    "sg:postcode":"5555",
    "sg:province":"Namur",
    "wof:name":"Fernand Lambot",
    "wof:placetype":"venue"
},
  "geometry": {"coordinates":[4.9815340042,49.8695411682],"type":"Point"}
}