{
  "type": "Feature",
  "properties": {
    "addr:full":"Place Alphonse Bosch 6b1 Wavre Brabant Wallon 1300",
    "addr:housenumber":"6b1;1300",
    "addr:street":"Place Alphonse Bosch",
    "iso:country":"BE",
    "sg:address":"Place Alphonse Bosch 6b1",
    "sg:city":"Wavre",
    "sg:orig_category":"Foto-uitrusting",
    "sg:phone":"+32 10 24 42 97",
    "sg:postcode":"1300",
    "sg:province":"Brabant Wallon",
    "wof:name":"Fnac Service",
    "wof:placetype":"venue"
},
  "geometry": {"coordinates":[4.6112689972,50.7143707275],"type":"Point"}
}