{
  "type": "Feature",
  "properties": {
    "iso:country":"BE",
    "sg:address":"Stoktstraat 11",
    "sg:city":"Brakel (nederbrakel)",
    "sg:classifiers":[
        {
            "category":"Building & Trades",
            "subcategory":"Electrical",
            "type":"Services"
        }
    ],
    "sg:phone":"+32 55 42 13 80",
    "sg:postcode":"9660",
    "sg:province":"Oost-Vlaanderen",
    "sg:tags":[
        "electric",
        "-",
        "housewiring",
        "contractor"
    ],
    "wof:name":"Renard W",
    "wof:placetype":"venue"
},
  "geometry": {"coordinates":[3.7744560242,50.7973632812],"type":"Point"}
}