{
  "type": "Feature",
  "properties": {
    "addr:full":"Rue Is. Meyskens 224 Wemmel Vlaams-Brabant 1780",
    "addr:housenumber":"224",
    "addr:postcode":"1780",
    "addr:street":"Rue Is. Meyskens;Vlaams-Brabant",
    "iso:country":"BE",
    "sg:address":"Rue Is. Meyskens 224",
    "sg:city":"Wemmel",
    "sg:classifiers":[
        {
            "category":"Wholesale",
            "subcategory":"Tobacco Products",
            "type":"Manufacturing & Wholesale Goods"
        }
    ],
    "sg:postcode":"1780",
    "sg:province":"Vlaams-Brabant",
    "sg:tags":[
        "-",
        "biotechnology",
        "installation",
        "equipment"
    ],
    "wof:name":"Nexell International",
    "wof:placetype":"venue"
},
  "geometry": {"coordinates":[4.3124098778,50.8966712952],"type":"Point"}
}