{
  "type": "Feature",
  "properties": {
    "iso:country":"BE",
    "sg:address":"Av. Reine Astrid 1a",
    "sg:city":"Wauthier-braine",
    "sg:orig_category":"Biens d'occasion. Troc International",
    "sg:phone":"+32 2 367 25 50",
    "sg:postcode":"1440",
    "sg:province":"Brabant Wallon",
    "wof:name":"Troc International",
    "wof:placetype":"venue"
},
  "geometry": {"coordinates":[4.3224840164,50.6905593872],"type":"Point"}
}