{
  "type": "Feature",
  "properties": {
    "iso:country":"BE",
    "sg:address":"Volpestr 6",
    "sg:city":"Halle",
    "sg:classifiers":[
        {
            "category":"Food & Beverages",
            "subcategory":"Fruits & Vegetables",
            "type":"Retail Goods"
        }
    ],
    "sg:phone":"+32 57 48 97 70",
    "sg:postcode":"1500",
    "sg:province":"Vlaams-Brabant",
    "sg:tags":[
        "frozen",
        "product",
        "related"
    ],
    "wof:name":"Dejaeghere Nv",
    "wof:placetype":"venue"
},
  "geometry": {"coordinates":[2.9312469959,50.8914489746],"type":"Point"}
}