{
  "type": "Feature",
  "properties": {
    "iso:country":"BE",
    "sg:address":"Avenue Reine Astrid 222",
    "sg:city":"Verviers (heusy)",
    "sg:classifiers":[
        {
            "category":"Health Services",
            "subcategory":"Dentist",
            "type":"Services"
        }
    ],
    "sg:phone":"+32 87 22 40 45",
    "sg:postcode":"4802",
    "sg:province":"Li\u00e8ge",
    "wof:name":"Hanquet J-l",
    "wof:placetype":"venue"
},
  "geometry": {"coordinates":[5.8856239319,50.5836868286],"type":"Point"}
}