{
  "type": "Feature",
  "properties": {
    "iso:country":"BE",
    "sg:address":"Hubaille 19",
    "sg:city":"Houyet",
    "sg:orig_category":"Rundveehouders",
    "sg:phone":"+32 82 66 61 14",
    "sg:postcode":"5561",
    "sg:province":"Namur",
    "wof:name":"Jose Defossez",
    "wof:placetype":"venue"
},
  "geometry": {"coordinates":[5.0096502304,50.229221344],"type":"Point"}
}