{
  "type": "Feature",
  "properties": {
    "addr:full":"Rue De Pontaury 57a Mettet Namur 5640",
    "addr:housenumber":"57a",
    "addr:postcode":"5640",
    "addr:street":"Rue De Pontaury",
    "iso:country":"BE",
    "sg:address":"Rue De Pontaury 57a",
    "sg:city":"Mettet",
    "sg:orig_category":"Catering and organisation de f\u00eates",
    "sg:phone":"+32 71 72 66 93",
    "sg:postcode":"5640",
    "sg:province":"Namur",
    "wof:name":"La Villa Vanille",
    "wof:placetype":"venue"
},
  "geometry": {"coordinates":[4.6683349609,50.3397102356],"type":"Point"}
}