{
  "type": "Feature",
  "properties": {
    "iso:country":"BE",
    "sg:address":"Sint-annaweg 6a",
    "sg:city":"Denderhoutem",
    "sg:orig_category":"Baby Pram And Buggy Nets",
    "sg:phone":"+32 54 33 16 57",
    "sg:postcode":"9450",
    "sg:province":"Oost-Vlaanderen",
    "wof:name":"Hoorens-aero-sleep \u00ae Nv",
    "wof:placetype":"venue"
},
  "geometry": {"coordinates":[4.0150089264,50.8704719543],"type":"Point"}
}