{
  "type": "Feature",
  "properties": {
    "iso:country":"BE",
    "sg:address":"Rue Du Ch\u00e2teau 12",
    "sg:city":"Mettet (saint-g\u00e9rard)",
    "sg:classifiers":[
        {
            "category":"Personal",
            "subcategory":"Nail Salon",
            "type":"Services"
        }
    ],
    "sg:phone":"+32 71 79 99 03",
    "sg:postcode":"5640",
    "sg:province":"Namur",
    "sg:tags":[
        "pedicure"
    ],
    "wof:name":"Genard S",
    "wof:placetype":"venue"
},
  "geometry": {"coordinates":[4.6985120773,50.342590332],"type":"Point"}
}