{
  "type": "Feature",
  "properties": {
    "iso:country":"BE",
    "sg:address":"Route De Mons 34",
    "sg:city":"Bernissart (pommeroeul)",
    "sg:classifiers":[
        {
            "category":"Retail",
            "subcategory":"Veterinary Services",
            "type":"Services"
        }
    ],
    "sg:phone":"+32 65 62 25 84",
    "sg:postcode":"7322",
    "sg:province":"Hainaut",
    "sg:tags":[
        "veterinarian"
    ],
    "wof:name":"Vercouter G",
    "wof:placetype":"venue"
},
  "geometry": {"coordinates":[3.732765913,50.488609314],"type":"Point"}
}