{
  "type": "Feature",
  "properties": {
    "addr:full":"Brusselsesteenweg 479 Gent (gentbrugge) Oost-Vlaanderen 9050",
    "addr:housenumber":"479",
    "addr:postcode":"9050",
    "addr:street":"Brusselsesteenweg",
    "iso:country":"BE",
    "sg:address":"Brusselsesteenweg 479",
    "sg:city":"Gent (gentbrugge)",
    "sg:classifiers":[
        {
            "category":"Professional",
            "subcategory":"Management & Consulting",
            "type":"Services"
        }
    ],
    "sg:phone":"+32 9 230 15 54",
    "sg:postcode":"9050",
    "sg:province":"Oost-Vlaanderen",
    "sg:tags":[
        "consultant",
        "-",
        "legislation",
        "social"
    ],
    "wof:name":"Scheldevallei",
    "wof:placetype":"venue"
},
  "geometry": {"coordinates":[3.7543199062,51.035068512],"type":"Point"}
}