{
  "type": "Feature",
  "properties": {
    "addr:full":"Quai St L\u00c9onard 36 Liege-centre Li\u00e8ge 4000",
    "addr:housenumber":"36",
    "addr:postcode":"4000",
    "addr:street":"Quai St Le\u0301Onard",
    "iso:country":"BE",
    "sg:address":"Quai St L\u00c9onard 36",
    "sg:city":"Liege-centre",
    "sg:classifiers":[
        {
            "category":"Restaurant",
            "type":"Food & Drink"
        }
    ],
    "sg:phone":"+32 4 228 81 11",
    "sg:postcode":"4000",
    "sg:province":"Li\u00e8ge",
    "wof:name":"H\u00d4tel Restaurant Bedford",
    "wof:placetype":"venue"
},
  "geometry": {"coordinates":[6.2250900269,44.0888595581],"type":"Point"}
}