{
  "type": "Feature",
  "properties": {
    "iso:country":"BE",
    "sg:address":"Poststraat 21b1",
    "sg:city":"Halle",
    "sg:orig_category":"Loodgieterij, verwarming and sanitaire installaties Schoonmaakbedrijven and ongediertebestrijding",
    "sg:phone":"+32 2 356 27 26",
    "sg:postcode":"1500",
    "sg:province":"Vlaams-Brabant",
    "wof:name":"Chaufnet",
    "wof:placetype":"venue"
},
  "geometry": {"coordinates":[4.2317910194,50.7340888977],"type":"Point"}
}