{
  "type": "Feature",
  "properties": {
    "addr:full":"Rue Saint-pierre Et Paul 7 Walcourt (thy-le-ch\u00e2teau) Namur 5651",
    "addr:housenumber":"7",
    "addr:postcode":"5651",
    "addr:street":"Rue Saint-Pierre Et Paul",
    "iso:country":"BE",
    "sg:address":"Rue Saint-pierre Et Paul 7",
    "sg:city":"Walcourt (thy-le-ch\u00e2teau)",
    "sg:classifiers":[
        {
            "category":"Insurance",
            "subcategory":"Insurance Agent",
            "type":"Services"
        }
    ],
    "sg:phone":"+32 71 61 10 70",
    "sg:postcode":"5651",
    "sg:province":"Namur",
    "sg:tags":[
        "broker"
    ],
    "wof:name":"Monard P",
    "wof:placetype":"venue"
},
  "geometry": {"coordinates":[4.4297828674,50.2859115601],"type":"Point"}
}