{
  "type": "Feature",
  "properties": {
    "iso:country":"BE",
    "sg:address":"11",
    "sg:city":"Polderstraat 2491 Balen",
    "sg:classifiers":[
        {
            "category":"Shopping",
            "subcategory":"Clothing, Apparel, & Fashions",
            "type":"Retail Goods"
        }
    ],
    "sg:phone":"+32 14 30 00 59",
    "sg:postcode":"11",
    "sg:tags":[
        "textile",
        "clothing",
        "clothes"
    ],
    "wof:name":"Bijlemans Kleding Olmen Bvba",
    "wof:placetype":"venue"
},
  "geometry": {"coordinates":[5.1463470459,51.1407012939],"type":"Point"}
}