{
  "type": "Feature",
  "properties": {
    "addr:full":"Molenstraat 1b Grobbendonk Antwerpen 2288",
    "addr:housenumber":"1b",
    "addr:postcode":"2288",
    "addr:street":"Molenstraat",
    "iso:country":"BE",
    "sg:address":"Molenstraat 1b",
    "sg:city":"Grobbendonk",
    "sg:orig_category":"Fleurs and plantes",
    "sg:phone":"+32 14 51 24 52",
    "sg:postcode":"2288",
    "sg:province":"Antwerpen",
    "wof:name":"Van Eester-deckers",
    "wof:placetype":"venue"
},
  "geometry": {"coordinates":[4.745912075,51.1616973877],"type":"Point"}
}