{
  "type": "Feature",
  "properties": {
    "iso:country":"BE",
    "sg:address":"Rue De La Gaume 66",
    "sg:city":"Leglise",
    "sg:orig_category":"Rundveehouders",
    "sg:phone":"+32 63 43 32 18",
    "sg:postcode":"6860",
    "sg:province":"Luxembourg",
    "wof:name":"Leon Arnould",
    "wof:placetype":"venue"
},
  "geometry": {"coordinates":[5.4621949196,49.8041038513],"type":"Point"}
}