{
  "type": "Feature",
  "properties": {
    "iso:country":"BE",
    "sg:address":"Bellegemstraat 14",
    "sg:city":"Zwevegem",
    "sg:orig_category":"Binnenhuisarchitecten",
    "sg:phone":"+32 56 75 59 56",
    "sg:postcode":"8550",
    "sg:province":"West-Vlaanderen",
    "wof:name":"Steven Wittouck",
    "wof:placetype":"venue"
},
  "geometry": {"coordinates":[3.3423349857,50.8016357422],"type":"Point"}
}