{
  "type": "Feature",
  "properties": {
    "addr:full":"Kerkstraat 79b1 Lommel Limburg 3920",
    "addr:housenumber":"79b1",
    "addr:postcode":"3920",
    "addr:street":"Kerkstraat",
    "iso:country":"BE",
    "sg:address":"Kerkstraat 79b1",
    "sg:city":"Lommel",
    "sg:orig_category":"Articles pour b\u00e9b\u00e9s. V\u00eatements pour b\u00e9b\u00e9s and enfants",
    "sg:phone":"+32 11 54 16 20",
    "sg:postcode":"3920",
    "sg:province":"Limburg",
    "wof:name":"Pr\u00c9maman",
    "wof:placetype":"venue"
},
  "geometry": {"coordinates":[5.3136301041,51.2284584045],"type":"Point"}
}