{
  "type": "Feature",
  "properties": {
    "addr:full":"Place Eug\u00c8ne Derbaix 18b7 Binche Hainaut 7130",
    "addr:housenumber":"18b7",
    "addr:postcode":"7130",
    "addr:street":"Place Euge\u0300Ne Derbaix",
    "iso:country":"BE",
    "sg:address":"Place Eug\u00c8ne Derbaix 18b7",
    "sg:city":"Binche",
    "sg:orig_category":"Location de v\u00eatements, chaussures and textiles",
    "sg:phone":"+32 64 33 10 11",
    "sg:postcode":"7130",
    "sg:province":"Hainaut",
    "wof:name":"Locabi",
    "wof:placetype":"venue"
},
  "geometry": {"coordinates":[4.1716599464,50.4090995789],"type":"Point"}
}