{
  "type": "Feature",
  "properties": {
    "iso:country":"BE",
    "sg:address":"Rue De La Distillerie 23",
    "sg:city":"La Bruyere",
    "sg:classifiers":[
        {
            "category":"Shopping",
            "subcategory":"Clothing, Apparel, & Fashions",
            "type":"Retail Goods"
        }
    ],
    "sg:phone":"+32 81 56 80 01",
    "sg:postcode":"5081",
    "sg:province":"Namur",
    "sg:tags":[
        "v\u00eatements",
        "pour",
        "dame"
    ],
    "wof:name":"Boutique Oke",
    "wof:placetype":"venue"
},
  "geometry": {"coordinates":[4.7806100845,50.5191001892],"type":"Point"}
}