{
  "type": "Feature",
  "properties": {
    "iso:country":"BE",
    "sg:address":"Hoekstraat 39",
    "sg:city":"Lokeren (eksaarde)",
    "sg:classifiers":[
        {
            "category":"Farming",
            "subcategory":"Livestock Farm",
            "type":"Manufacturing & Wholesale Goods"
        }
    ],
    "sg:phone":"+32 9 355 66 41",
    "sg:postcode":"9160",
    "sg:province":"Oost-Vlaanderen",
    "sg:tags":[
        "buyer"
    ],
    "wof:name":"De Kerpel N",
    "wof:placetype":"venue"
},
  "geometry": {"coordinates":[3.9015629292,51.1102828979],"type":"Point"}
}