{
  "type": "Feature",
  "properties": {
    "addr:full":"Ribusstraat 5 Bilzen Limburg 3740",
    "addr:housenumber":"5",
    "addr:postcode":"3740",
    "addr:street":"Ribusstraat",
    "iso:country":"BE",
    "sg:address":"Ribusstraat 5",
    "sg:city":"Bilzen",
    "sg:classifiers":[
        {
            "category":"Professional",
            "subcategory":"Accounting & Tax Preparation",
            "type":"Services"
        }
    ],
    "sg:phone":"+32 89 49 13 10",
    "sg:postcode":"3740",
    "sg:province":"Limburg",
    "sg:tags":[
        "bookkeeper"
    ],
    "wof:name":"Bloemen W",
    "wof:placetype":"venue"
},
  "geometry": {"coordinates":[5.5072097778,50.8833999634],"type":"Point"}
}