{
  "type": "Feature",
  "properties": {
    "iso:country":"BE",
    "sg:address":"Kraaienhof 66",
    "sg:city":"Wielsbeke (sint-baafs-vijve)",
    "sg:classifiers":[
        {
            "category":"Freight",
            "type":"Transportation"
        }
    ],
    "sg:phone":"+32 56 60 89 05",
    "sg:postcode":"8710",
    "sg:province":"West-Vlaanderen",
    "sg:tags":[
        "-",
        "transport"
    ],
    "wof:name":"Destoop Henri Bvba",
    "wof:placetype":"venue"
},
  "geometry": {"coordinates":[3.4027910233,50.9151611328],"type":"Point"}
}