{
  "type": "Feature",
  "properties": {
    "iso:country":"BE",
    "sg:address":"Venderstraat 28",
    "sg:city":"Neerpelt",
    "sg:orig_category":"Rundveehouders Zuivelproducten",
    "sg:phone":"+32 11 64 19 59",
    "sg:postcode":"3910",
    "sg:province":"Limburg",
    "wof:name":"Huis Kwanten-mentens",
    "wof:placetype":"venue"
},
  "geometry": {"coordinates":[5.4832978249,51.233215332],"type":"Point"}
}