{
  "type": "Feature",
  "properties": {
    "iso:country":"BE",
    "sg:address":"Avenue De La Salm 1",
    "sg:city":"Vielsalm",
    "sg:orig_category":"Installatie van metalen schrijnwerk",
    "sg:phone":"+32 80 21 41 30",
    "sg:postcode":"6690",
    "sg:province":"Luxembourg",
    "wof:name":"M K S",
    "wof:placetype":"venue"
},
  "geometry": {"coordinates":[5.9142150879,50.2831192017],"type":"Point"}
}