{
  "type": "Feature",
  "properties": {
    "addr:full":"Koningin Astridstraat 56b Zedelgem (veldegem) West-Vlaanderen 8210",
    "addr:housenumber":"56b",
    "addr:postcode":"8210",
    "addr:street":"Koningin Astridstraat",
    "iso:country":"BE",
    "sg:address":"Koningin Astridstraat 56b",
    "sg:city":"Zedelgem (veldegem)",
    "sg:classifiers":[
        {
            "category":"Home & Garden",
            "subcategory":"Carpets & Floor Coverings",
            "type":"Retail Goods"
        }
    ],
    "sg:phone":"+32 50 28 03 73",
    "sg:postcode":"8210",
    "sg:province":"West-Vlaanderen",
    "sg:tags":[
        "house",
        "prefabricated"
    ],
    "wof:name":"Keirsebilck Bvba",
    "wof:placetype":"venue"
},
  "geometry": {"coordinates":[3.1458399296,51.1376457214],"type":"Point"}
}