{
  "type": "Feature",
  "properties": {
    "iso:country":"BE",
    "sg:address":"Madeliefjesstraat 69",
    "sg:city":"Grimbergen",
    "sg:classifiers":[
        {
            "category":"Shopping Center",
            "type":"Public Place"
        }
    ],
    "sg:phone":"+32 2 270 94 44",
    "sg:postcode":"1850",
    "sg:province":"Vlaams-Brabant",
    "sg:tags":[
        "enseignement",
        "formation"
    ],
    "wof:name":"Consult.opleid.cent.bedr.",
    "wof:placetype":"venue"
},
  "geometry": {"coordinates":[4.3905758858,50.9316978455],"type":"Point"}
}