{
  "type": "Feature",
  "properties": {
    "iso:country":"BE",
    "sg:address":"Grote Leiestraat 187",
    "sg:city":"Anzegem",
    "sg:orig_category":"Fleurs and plantes",
    "sg:phone":"+32 56 68 00 40",
    "sg:postcode":"8570",
    "sg:province":"West-Vlaanderen",
    "wof:name":"Het Rozenhuis",
    "wof:placetype":"venue"
},
  "geometry": {"coordinates":[3.4477488995,50.8586120605],"type":"Point"}
}