{
  "type": "Feature",
  "properties": {
    "addr:full":"Rue De Lustin 19 Andenne Namur 5300",
    "addr:housenumber":"19",
    "addr:postcode":"5300",
    "addr:street":"Rue De Lustin",
    "iso:country":"BE",
    "sg:address":"Rue De Lustin 19",
    "sg:city":"Andenne",
    "sg:classifiers":[
        {
            "category":"Building & Trades",
            "subcategory":"Landscaping Services",
            "type":"Services"
        }
    ],
    "sg:phone":"+32 85 84 20 29",
    "sg:postcode":"5300",
    "sg:province":"Namur",
    "sg:tags":[
        "handicraft"
    ],
    "wof:name":"Javaux C",
    "wof:placetype":"venue"
},
  "geometry": {"coordinates":[5.0848898888,50.4772987366],"type":"Point"}
}