{
  "type": "Feature",
  "properties": {
    "addr:full":"Dieplaan 2be Genk Limburg 3600",
    "addr:postcode":"3600",
    "addr:street":"Dieplaan",
    "iso:country":"BE",
    "sg:address":"Dieplaan 2be",
    "sg:city":"Genk",
    "sg:orig_category":"Sociale huisvestingsmaatschappijen",
    "sg:phone":"+32 89 35 26 34",
    "sg:postcode":"3600",
    "sg:province":"Limburg",
    "wof:name":"Nieuw Dak",
    "wof:placetype":"venue"
},
  "geometry": {"coordinates":[5.4946689606,50.9645271301],"type":"Point"}
}