{
  "type": "Feature",
  "properties": {
    "iso:country":"BE",
    "sg:address":"Rue Osseghem 195",
    "sg:city":"Bruxelles (molenbeek-saint-jean)",
    "sg:classifiers":[
        {
            "category":"Bakery",
            "type":"Food & Drink"
        }
    ],
    "sg:phone":"+32 2 410 11 48",
    "sg:postcode":"1080",
    "sg:province":"Bruxelles-Capitale",
    "sg:tags":[
        "confectioner",
        "baker"
    ],
    "wof:name":"Le Square",
    "wof:placetype":"venue"
},
  "geometry": {"coordinates":[4.3094248772,50.8540916443],"type":"Point"}
}