{
  "type": "Feature",
  "properties": {
    "iso:country":"BE",
    "sg:address":"Rue Du Pont 26",
    "sg:city":"Lessines (deux-acren)",
    "sg:classifiers":[
        {
            "category":"Retail",
            "subcategory":"Auto Repair",
            "type":"Services"
        }
    ],
    "sg:phone":"+32 68 33 34 48",
    "sg:postcode":"7864",
    "sg:province":"Hainaut",
    "sg:tags":[
        "garage"
    ],
    "wof:name":"Megacars Ets",
    "wof:placetype":"venue"
},
  "geometry": {"coordinates":[3.8602778912,50.7276725769],"type":"Point"}
}