{
  "type": "Feature",
  "properties": {
    "iso:country":"BE",
    "sg:address":"Uilegatstraat 11",
    "sg:city":"Poperinge",
    "sg:orig_category":"Rundveehouders",
    "sg:phone":"+32 57 30 05 91",
    "sg:postcode":"8972",
    "sg:province":"West-Vlaanderen",
    "wof:name":"Jozef Verhille",
    "wof:placetype":"venue"
},
  "geometry": {"coordinates":[2.6550700665,50.9054412842],"type":"Point"}
}