{
  "type": "Feature",
  "properties": {
    "addr:full":"Baal 62 Tessenderlo Limburg 3980",
    "addr:housenumber":"62",
    "addr:postcode":"3980",
    "addr:street":"Baal",
    "iso:country":"BE",
    "sg:address":"Baal 62",
    "sg:city":"Tessenderlo",
    "sg:classifiers":[
        {
            "category":"Real Estate",
            "subcategory":"Architect",
            "type":"Services"
        }
    ],
    "sg:phone":"+32 13 66 45 34",
    "sg:postcode":"3980",
    "sg:province":"Limburg",
    "wof:name":"Verwimp K",
    "wof:placetype":"venue"
},
  "geometry": {"coordinates":[5.0722541809,51.0791244507],"type":"Point"}
}