{
  "type": "Feature",
  "properties": {
    "iso:country":"BE",
    "sg:address":"Grote Heerweg 90",
    "sg:city":"Waregem (beveren-leie)",
    "sg:classifiers":[
        {
            "category":"Real Estate",
            "subcategory":"Architect",
            "type":"Services"
        }
    ],
    "sg:phone":"+32 56 71 35 63",
    "sg:postcode":"8791",
    "sg:province":"West-Vlaanderen",
    "wof:name":"Ducatteeuw E",
    "wof:placetype":"venue"
},
  "geometry": {"coordinates":[3.3323180676,50.8759841919],"type":"Point"}
}