{
  "type": "Feature",
  "properties": {
    "addr:full":"Grand-route 126 Ciney (leignon) Namur 5590",
    "addr:housenumber":"126",
    "addr:postcode":"5590",
    "addr:street":"Grand-Route",
    "iso:country":"BE",
    "sg:address":"Grand-route 126",
    "sg:city":"Ciney (leignon)",
    "sg:classifiers":[
        {
            "category":"Building & Trades",
            "subcategory":"Equipment Rental",
            "type":"Services"
        }
    ],
    "sg:phone":"+32 83 21 47 34",
    "sg:postcode":"5590",
    "sg:province":"Namur",
    "sg:tags":[
        "sound",
        "-",
        "system"
    ],
    "wof:name":"Luvison",
    "wof:placetype":"venue"
},
  "geometry": {"coordinates":[5.1022520065,50.297088623],"type":"Point"}
}