{
  "type": "Feature",
  "properties": {
    "addr:full":"Zuidmolenstraat 90 Roeselare West-Vlaanderen 8800",
    "addr:housenumber":"90",
    "addr:postcode":"8800",
    "addr:street":"Zuidmolenstraat",
    "iso:country":"BE",
    "sg:address":"Zuidmolenstraat 90",
    "sg:city":"Roeselare",
    "sg:orig_category":"Jeux de hasard. Epiceries. Journaux. Tabac",
    "sg:phone":"+32 51 22 14 97",
    "sg:postcode":"8800",
    "sg:province":"West-Vlaanderen",
    "wof:name":"'t Labeurkien",
    "wof:placetype":"venue"
},
  "geometry": {"coordinates":[3.1276419163,50.934223175],"type":"Point"}
}