{
  "type": "Feature",
  "properties": {
    "addr:full":"Groenstraat 14 Neerpelt Limburg 3910",
    "addr:housenumber":"14",
    "addr:postcode":"3910",
    "addr:street":"Groenstraat",
    "iso:country":"BE",
    "sg:address":"Groenstraat 14",
    "sg:city":"Neerpelt",
    "sg:orig_category":"Chaussures",
    "sg:phone":"+32 11 64 17 68",
    "sg:postcode":"3910",
    "sg:province":"Limburg",
    "wof:name":"Shoes In The Box",
    "wof:placetype":"venue"
},
  "geometry": {"coordinates":[5.4339680672,51.2291755676],"type":"Point"}
}