{
  "type": "Feature",
  "properties": {
    "addr:full":"Eeklostraat 4 Evergem Oost-Vlaanderen 9940",
    "addr:housenumber":"4",
    "addr:postcode":"9940",
    "addr:street":"Eeklostraat;Oost-Vlaanderen",
    "iso:country":"BE",
    "sg:address":"Eeklostraat 4",
    "sg:city":"Evergem",
    "sg:orig_category":"Banques and organismes de cr\u00e9dit",
    "sg:phone":"+32 9 344 65 53",
    "sg:postcode":"9940",
    "sg:province":"Oost-Vlaanderen",
    "wof:name":"Groep Argenta",
    "wof:placetype":"venue"
},
  "geometry": {"coordinates":[3.745486021,51.1788368225],"type":"Point"}
}