{
  "type": "Feature",
  "properties": {
    "addr:full":"Ganshorenstraat 2 Koekelberg Bruxelles-Capitale 1081",
    "addr:housenumber":"2",
    "addr:postcode":"1081",
    "addr:street":"Ganshorenstraat",
    "iso:country":"BE",
    "sg:address":"Ganshorenstraat 2",
    "sg:city":"Koekelberg",
    "sg:orig_category":"Sportclubs",
    "sg:phone":"+32 2 428 85 89",
    "sg:postcode":"1081",
    "sg:province":"Bruxelles-Capitale",
    "wof:name":"Ganshoren En Koekelberg Roller Club",
    "wof:placetype":"venue"
},
  "geometry": {"coordinates":[4.3297958374,50.8592643738],"type":"Point"}
}