{
  "type": "Feature",
  "properties": {
    "iso:country":"BE",
    "sg:address":"Hoezestraat 1",
    "sg:city":"Aalst",
    "sg:classifiers":[
        {
            "category":"Professional",
            "type":"Services"
        }
    ],
    "sg:phone":"+32 53 77 52 11",
    "sg:postcode":"9300",
    "sg:province":"Oost-Vlaanderen",
    "sg:tags":[
        "entertainer"
    ],
    "wof:name":"Aalsterse Gilles Fv",
    "wof:placetype":"venue"
},
  "geometry": {"coordinates":[4.0429601669,50.9359741211],"type":"Point"}
}