{
  "type": "Feature",
  "properties": {
    "iso:country":"BE",
    "sg:address":"117",
    "sg:city":"Avenue Des Combattants 1340 Ottignies",
    "sg:classifiers":[
        {
            "category":"Professional",
            "subcategory":"Engineering",
            "type":"Services"
        }
    ],
    "sg:phone":"+32 10 41 34 32",
    "sg:postcode":"117",
    "sg:tags":[
        "machine",
        "-",
        "mechanical"
    ],
    "wof:name":"Etablissements Hermand Sprl",
    "wof:placetype":"venue"
},
  "geometry": {"coordinates":[4.5683560371,50.6675033569],"type":"Point"}
}