{
  "type": "Feature",
  "properties": {
    "addr:full":"Arth. Michielsplein 5 Overijse Vlaams-Brabant 3090",
    "addr:housenumber":"5",
    "addr:postcode":"3090",
    "addr:street":"Michielsplein",
    "iso:country":"BE",
    "sg:address":"Arth. Michielsplein 5",
    "sg:city":"Overijse",
    "sg:classifiers":[
        {
            "category":"Bars & Pubs",
            "type":"Food & Drink"
        }
    ],
    "sg:phone":"+32 16 47 74 44",
    "sg:postcode":"3090",
    "sg:province":"Vlaams-Brabant",
    "wof:name":"Trapkens (in De)",
    "wof:placetype":"venue"
},
  "geometry": {"coordinates":[4.6035881042,50.7698097229],"type":"Point"}
}