{
  "type": "Feature",
  "properties": {
    "iso:country":"BE",
    "sg:address":"5",
    "sg:city":"Booiebos 9031 Drongen",
    "sg:classifiers":[
        {
            "category":"Farming",
            "subcategory":"Farm & Veterinary Services",
            "type":"Manufacturing & Wholesale Goods"
        }
    ],
    "sg:phone":"+32 9 280 29 00",
    "sg:postcode":"5",
    "sg:tags":[
        "food",
        "product",
        "breeding",
        "animal",
        "related"
    ],
    "wof:name":"Vitamex Nv",
    "wof:placetype":"venue"
},
  "geometry": {"coordinates":[3.6006689072,51.0410079956],"type":"Point"}
}