{
  "type": "Feature",
  "properties": {
    "iso:country":"BE",
    "sg:address":"Rue Du Charmoie 56",
    "sg:city":"Presles",
    "sg:classifiers":[
        {
            "category":"Government",
            "subcategory":"Department Of Motor Vehicles",
            "type":"Public Place"
        }
    ],
    "sg:phone":"+32 71 39 72 55",
    "sg:postcode":"6250",
    "sg:province":"Hainaut",
    "sg:tags":[
        "equipment",
        "industrial",
        "transport",
        "motor-cars"
    ],
    "wof:name":"Kit Cross Belgium Sprl",
    "wof:placetype":"venue"
},
  "geometry": {"coordinates":[4.5802330971,50.3761711121],"type":"Point"}
}