{
  "type": "Feature",
  "properties": {
    "addr:full":"Rue Baronne Lemonnier 82 Rochefort Namur 5580",
    "addr:housenumber":"82",
    "addr:postcode":"5580",
    "addr:street":"Rue Baronne Lemonnier",
    "iso:country":"BE",
    "sg:address":"Rue Baronne Lemonnier 82",
    "sg:city":"Rochefort",
    "sg:orig_category":"H\u00f4tels",
    "sg:phone":"+32 84 38 72 17",
    "sg:postcode":"5580",
    "sg:province":"Namur",
    "wof:name":"Hotel Lemmonier",
    "wof:placetype":"venue"
},
  "geometry": {"coordinates":[5.0933427811,50.1148300171],"type":"Point"}
}