{
  "type": "Feature",
  "properties": {
    "iso:country":"BE",
    "sg:address":"Chauss\u00e9e De Charleroi 44",
    "sg:city":"Charleroi (montignies-sur-sambre)",
    "sg:classifiers":[
        {
            "category":"Professional",
            "subcategory":"Management & Consulting",
            "type":"Services"
        }
    ],
    "sg:phone":"+32 71 20 60 70",
    "sg:postcode":"6061",
    "sg:province":"Hainaut",
    "sg:tags":[
        "consultant",
        "agency",
        "advertising"
    ],
    "wof:name":"Megalbum Sprl",
    "wof:placetype":"venue"
},
  "geometry": {"coordinates":[4.4763460159,50.4014778137],"type":"Point"}
}