{
  "type": "Feature",
  "properties": {
    "iso:country":"BE",
    "sg:address":"Avenue De L'abbaye De Forest 17",
    "sg:city":"Waterloo",
    "sg:classifiers":[
        {
            "category":"Communications",
            "type":"Services"
        }
    ],
    "sg:phone":"+32 2 351 11 25",
    "sg:postcode":"1410",
    "sg:province":"Brabant Wallon",
    "sg:tags":[
        "translator"
    ],
    "wof:name":"A.a.a. Sprl",
    "wof:placetype":"venue"
},
  "geometry": {"coordinates":[4.3919029236,50.7127418518],"type":"Point"}
}