{
  "type": "Feature",
  "properties": {
    "iso:country":"BE",
    "sg:address":"Brusselbaan 219",
    "sg:city":"Affligem (hekelgem)",
    "sg:classifiers":[
        {
            "category":"Professional",
            "subcategory":"Computer Services",
            "type":"Services"
        }
    ],
    "sg:phone":"+32 53 67 16 43",
    "sg:postcode":"1790",
    "sg:province":"Vlaams-Brabant",
    "sg:tags":[
        "-",
        "processing",
        "data"
    ],
    "wof:name":"Dtm Electro Bvba",
    "wof:placetype":"venue"
},
  "geometry": {"coordinates":[4.1148400307,50.9124755859],"type":"Point"}
}