{
  "type": "Feature",
  "properties": {
    "addr:full":"Nijverheidstraat 45 Mechelen Antwerpen 2800",
    "addr:housenumber":"45",
    "addr:postcode":"2800",
    "addr:street":"Nijverheidstraat",
    "iso:country":"BE",
    "sg:address":"Nijverheidstraat 45",
    "sg:city":"Mechelen",
    "sg:orig_category":"Oldtimers",
    "sg:postcode":"2800",
    "sg:province":"Antwerpen",
    "wof:name":"Atelier Moens Oldtimer Garage",
    "wof:placetype":"venue"
},
  "geometry": {"coordinates":[4.4962778091,51.0340957642],"type":"Point"}
}