{
  "type": "Feature",
  "properties": {
    "addr:full":"Chauss\u00c9e De Mons 30 Nivelles Brabant Wallon 1400",
    "addr:housenumber":"30",
    "addr:postcode":"1400",
    "addr:street":"Chausse\u0301E De Mons",
    "iso:country":"BE",
    "sg:address":"Chauss\u00c9e De Mons 30",
    "sg:city":"Nivelles",
    "sg:orig_category":"Catering and organisatie van feesten Restaurants Ruimtes voor conferenties, recepties and feesten",
    "sg:phone":"+32 67 21 16 37",
    "sg:postcode":"1400",
    "sg:province":"Brabant Wallon",
    "wof:name":"Le Bois D\u00b4arpes",
    "wof:placetype":"venue"
},
  "geometry": {"coordinates":[4.3183851242,50.5936737061],"type":"Point"}
}