{
  "type": "Feature",
  "properties": {
    "addr:full":"Industrieweg 1 Grobbendonk Antwerpen 2280",
    "addr:housenumber":"1",
    "addr:postcode":"2280",
    "addr:street":"Industrieweg",
    "iso:country":"BE",
    "sg:address":"Industrieweg 1",
    "sg:city":"Grobbendonk",
    "sg:orig_category":"Emballages en plastique Fab",
    "sg:phone":"+32 14 50 79 60",
    "sg:postcode":"2280",
    "sg:province":"Antwerpen",
    "wof:name":"Didak Injection",
    "wof:placetype":"venue"
},
  "geometry": {"coordinates":[4.7436242104,51.1781349182],"type":"Point"}
}