{
  "type": "Feature",
  "properties": {
    "addr:full":"Brusselsesteenweg 239 Ninove Oost-Vlaanderen 9402",
    "addr:housenumber":"239",
    "addr:postcode":"9402",
    "addr:street":"Brusselsesteenweg",
    "iso:country":"BE",
    "sg:address":"Brusselsesteenweg 239",
    "sg:city":"Ninove",
    "sg:orig_category":"M\u00e9decins and sp\u00e9cialistes",
    "sg:phone":"+32 54 33 74 00",
    "sg:postcode":"9402",
    "sg:province":"Oost-Vlaanderen",
    "wof:name":"Anne-marie Van Heesvelde",
    "wof:placetype":"venue"
},
  "geometry": {"coordinates":[4.0395750999,50.8249015808],"type":"Point"}
}