{
  "type": "Feature",
  "properties": {
    "iso:country":"BE",
    "sg:address":"Borgerhoutsestraat 34",
    "sg:city":"Antwerpen",
    "sg:classifiers":[
        {
            "category":"Community Center",
            "subcategory":"Youth",
            "type":"Public Place"
        }
    ],
    "sg:phone":"+32 3 272 30 73",
    "sg:postcode":"2018",
    "sg:province":"Antwerpen",
    "sg:tags":[
        "club"
    ],
    "wof:name":"Jeugd En Stad Vzw",
    "wof:placetype":"venue"
},
  "geometry": {"coordinates":[4.427421093,51.2130661011],"type":"Point"}
}