{
  "type": "Feature",
  "properties": {
    "iso:country":"BE",
    "sg:address":"Grote Baan 157",
    "sg:city":"Hasselt",
    "sg:orig_category":"Woningbouw",
    "sg:phone":"+32 11 25 15 54",
    "sg:postcode":"3511",
    "sg:province":"Limburg",
    "wof:name":"Bouwonderneming Feytons",
    "wof:placetype":"venue"
},
  "geometry": {"coordinates":[5.2974362373,50.9420051575],"type":"Point"}
}