{
  "type": "Feature",
  "properties": {
    "iso:country":"BE",
    "sg:address":"Chaussee De Gand 615",
    "sg:city":"Bruxelles",
    "sg:classifiers":[
        {
            "category":"Shopping",
            "subcategory":"Pharmacy",
            "type":"Retail Goods"
        }
    ],
    "sg:phone":"+32 2 464 06 88",
    "sg:postcode":"1080",
    "sg:province":"Bruxelles-Capitale",
    "sg:tags":[
        "preparation",
        "pharmaceutical"
    ],
    "wof:name":"Exel Pharma S.a.",
    "wof:placetype":"venue"
},
  "geometry": {"coordinates":[4.3064389229,50.8605194092],"type":"Point"}
}