{
  "type": "Feature",
  "properties": {
    "addr:full":"Baron De P\u00c9lichystraat 33 Izegem West-Vlaanderen 8870",
    "addr:housenumber":"33",
    "addr:postcode":"8870",
    "addr:street":"Baron De Pe\u0301Lichystraat",
    "iso:country":"BE",
    "sg:address":"Baron De P\u00c9lichystraat 33",
    "sg:city":"Izegem",
    "sg:orig_category":"Brood, gebak and snoepgoed",
    "sg:phone":"+32 51 30 05 24",
    "sg:postcode":"8870",
    "sg:province":"West-Vlaanderen",
    "wof:name":"Bakkerij Ignace",
    "wof:placetype":"venue"
},
  "geometry": {"coordinates":[3.2125160694,50.916431427],"type":"Point"}
}