{
  "type": "Feature",
  "properties": {
    "addr:full":"Parijsstraat 59 Leuven Vlaams-Brabant 3000",
    "addr:housenumber":"59",
    "addr:postcode":"3000",
    "addr:street":"Parijsstraat",
    "iso:country":"BE",
    "sg:address":"Parijsstraat 59",
    "sg:city":"Leuven",
    "sg:classifiers":[
        {
            "category":"Cafe",
            "type":"Food & Drink"
        }
    ],
    "sg:phone":"+32 16 23 12 75",
    "sg:postcode":"3000",
    "sg:province":"Vlaams-Brabant",
    "sg:tags":[
        "snack-bars"
    ],
    "wof:name":"Vorkske ('t)",
    "wof:placetype":"venue"
},
  "geometry": {"coordinates":[4.6988382339,50.8779144287],"type":"Point"}
}