{
  "type": "Feature",
  "properties": {
    "iso:country":"BE",
    "sg:address":"Schuiferskapelle Dorp 13",
    "sg:city":"Tielt (schuiferskapelle)",
    "sg:classifiers":[
        {
            "category":"Health Services",
            "subcategory":"Doctor",
            "type":"Services"
        }
    ],
    "sg:phone":"+32 51 40 36 40",
    "sg:postcode":"8700",
    "sg:province":"West-Vlaanderen",
    "sg:tags":[
        "medicinephysicians",
        "surgeon"
    ],
    "wof:name":"Leliaert R",
    "wof:placetype":"venue"
},
  "geometry": {"coordinates":[3.3270680904,51.0070266724],"type":"Point"}
}