{
  "type": "Feature",
  "properties": {
    "addr:full":"Onze-lieve-vrouwstraat 41 Lebbeke Oost-Vlaanderen 9280",
    "addr:housenumber":"41",
    "addr:postcode":"9280",
    "addr:street":"Onze-Lieve-Vrouwstraat",
    "iso:country":"BE",
    "sg:address":"Onze-lieve-vrouwstraat 41",
    "sg:city":"Lebbeke",
    "sg:orig_category":"Banken and kredietinstellingen",
    "sg:phone":"+32 52 41 04 00",
    "sg:postcode":"9280",
    "sg:province":"Oost-Vlaanderen",
    "wof:name":"Dexia",
    "wof:placetype":"venue"
},
  "geometry": {"coordinates":[4.1315999031,51.0007553101],"type":"Point"}
}