{
  "type": "Feature",
  "properties": {
    "addr:full":"Florent Geversstraat 50 Edegem Antwerpen 2650",
    "addr:housenumber":"50",
    "addr:postcode":"2650",
    "addr:street":"Florent Geversstraat",
    "iso:country":"BE",
    "sg:address":"Florent Geversstraat 50",
    "sg:city":"Edegem",
    "sg:orig_category":"Installation de menuiserie en bois and plastique",
    "sg:phone":"+32 3 458 07 78",
    "sg:postcode":"2650",
    "sg:province":"Antwerpen",
    "wof:name":"De Cock Francois",
    "wof:placetype":"venue"
},
  "geometry": {"coordinates":[4.4480571747,51.1542854309],"type":"Point"}
}