{
  "type": "Feature",
  "properties": {
    "addr:full":"Rue De Stavelot 17 Li\u00c8ge Li\u00e8ge 4020",
    "addr:housenumber":"17",
    "addr:postcode":"4020",
    "addr:street":"Rue De Stavelot",
    "iso:country":"BE",
    "sg:address":"Rue De Stavelot 17",
    "sg:city":"Li\u00c8ge",
    "sg:orig_category":"Boucheries",
    "sg:phone":"+32 4 343 77 57",
    "sg:postcode":"4020",
    "sg:province":"Li\u00e8ge",
    "wof:name":"Boucherie Antoine",
    "wof:placetype":"venue"
},
  "geometry": {"coordinates":[5.5897469521,50.6219406128],"type":"Point"}
}