{
  "type": "Feature",
  "properties": {
    "addr:full":"Rijksweg 95a Zulte (machelen) Oost-Vlaanderen 9870",
    "addr:housenumber":"95a",
    "addr:postcode":"9870",
    "addr:street":"Rijksweg",
    "iso:country":"BE",
    "sg:address":"Rijksweg 95a",
    "sg:city":"Zulte (machelen)",
    "sg:classifiers":[
        {
            "category":"Professional",
            "subcategory":"Computer Services",
            "type":"Services"
        }
    ],
    "sg:phone":"+32 9 386 33 00",
    "sg:postcode":"9870",
    "sg:province":"Oost-Vlaanderen",
    "sg:tags":[
        "-",
        "processing",
        "data",
        "software"
    ],
    "wof:name":"Dhont Wim Computersystemen Nv",
    "wof:placetype":"venue"
},
  "geometry": {"coordinates":[3.494412899,50.9553871155],"type":"Point"}
}