{
  "type": "Feature",
  "properties": {
    "iso:country":"BE",
    "sg:address":"Broekstraat 127",
    "sg:city":"Hamme",
    "sg:orig_category":"Rundveehouders",
    "sg:phone":"+32 52 47 04 33",
    "sg:postcode":"9220",
    "sg:province":"Oost-Vlaanderen",
    "wof:name":"Coppieters",
    "wof:placetype":"venue"
},
  "geometry": {"coordinates":[4.1522369385,51.0870399475],"type":"Point"}
}