{
  "type": "Feature",
  "properties": {
    "addr:full":"Rte De Baprume Rn 30 18 Cambrai 59554",
    "addr:housenumber":"18",
    "addr:postcode":"59554",
    "addr:street":"Rte De Baprume Rn 30",
    "iso:country":"BE",
    "sg:address":"Rte De Baprume Rn 30 18",
    "sg:city":"Cambrai",
    "sg:classifiers":[
        {
            "category":"Shopping",
            "subcategory":"Antiques",
            "type":"Retail Goods"
        }
    ],
    "sg:postcode":"59554",
    "wof:name":"A La Brocante A La Ferme",
    "wof:placetype":"venue"
},
  "geometry": {"coordinates":[3.1673150063,50.1903991699],"type":"Point"}
}