{
  "type": "Feature",
  "properties": {
    "iso:country":"BE",
    "sg:address":"Maalse Steenweg 334",
    "sg:city":"Brugge",
    "sg:orig_category":"R\u00e9parations de chaussures and articles en cuir",
    "sg:phone":"+32 50 37 47 33",
    "sg:postcode":"8310",
    "sg:province":"West-Vlaanderen",
    "wof:name":"Minit Solutions",
    "wof:placetype":"venue"
},
  "geometry": {"coordinates":[3.2648339272,51.2082290649],"type":"Point"}
}