{
  "type": "Feature",
  "properties": {
    "iso:country":"BE",
    "sg:address":"Hemelrijk 3a",
    "sg:city":"Brakel (everbeek)",
    "sg:classifiers":[
        {
            "category":"Farming",
            "subcategory":"Livestock Farm",
            "type":"Manufacturing & Wholesale Goods"
        }
    ],
    "sg:phone":"+32 55 42 33 72",
    "sg:postcode":"9660",
    "sg:province":"Oost-Vlaanderen",
    "sg:tags":[
        "poultry",
        "rabbit"
    ],
    "wof:name":"Haillez A",
    "wof:placetype":"venue"
},
  "geometry": {"coordinates":[3.7642250061,50.8031082153],"type":"Point"}
}