{
  "type": "Feature",
  "properties": {
    "iso:country":"BE",
    "sg:address":"Vlieghavenlaan 134",
    "sg:city":"Keerbergen",
    "sg:classifiers":[
        {
            "category":"Professional",
            "subcategory":"Management & Consulting",
            "type":"Services"
        }
    ],
    "sg:phone":"+32 15 73 08 61",
    "sg:postcode":"3140",
    "sg:province":"Vlaams-Brabant",
    "sg:tags":[
        "consultant",
        "law"
    ],
    "wof:name":"Keer-consult",
    "wof:placetype":"venue"
},
  "geometry": {"coordinates":[4.6869220734,51.0076560974],"type":"Point"}
}