{
  "type": "Feature",
  "properties": {
    "addr:full":"Rue Saint-paul 181 Welkenraedt Li\u00e8ge 4840",
    "addr:housenumber":"181",
    "addr:postcode":"4840",
    "addr:street":"Rue Saint-Paul",
    "iso:country":"BE",
    "sg:address":"Rue Saint-paul 181",
    "sg:city":"Welkenraedt",
    "sg:classifiers":[
        {
            "category":"Government",
            "subcategory":"Fire Station",
            "type":"Public Place"
        }
    ],
    "sg:phone":"+32 87 88 27 30",
    "sg:postcode":"4840",
    "sg:province":"Li\u00e8ge",
    "sg:tags":[
        "installation",
        "-",
        "air conditioning"
    ],
    "wof:name":"Huegaerts E",
    "wof:placetype":"venue"
},
  "geometry": {"coordinates":[5.9477849007,50.663066864],"type":"Point"}
}