{
  "type": "Feature",
  "properties": {
    "addr:full":"Clos Des Cerisiers 5 Waterloo Brabant Wallon 1410",
    "addr:housenumber":"5",
    "addr:postcode":"1410",
    "addr:street":"Clos Des Cerisiers",
    "iso:country":"BE",
    "sg:address":"Clos Des Cerisiers 5",
    "sg:city":"Waterloo",
    "sg:classifiers":[
        {
            "category":"Retail",
            "subcategory":"Animal Services",
            "type":"Services"
        }
    ],
    "sg:phone":"+32 2 351 43 63",
    "sg:postcode":"1410",
    "sg:province":"Brabant Wallon",
    "sg:tags":[
        "grooming",
        "-",
        "dog"
    ],
    "wof:name":"Renardi\u00e8re (la)",
    "wof:placetype":"venue"
},
  "geometry": {"coordinates":[4.3828001022,50.7263183594],"type":"Point"}
}