{
  "type": "Feature",
  "properties": {
    "addr:full":"Avenue De L'europe 2 Antoing Hainaut 7640",
    "addr:housenumber":"2",
    "addr:postcode":"7640",
    "addr:street":"Avenue De L'Europe",
    "iso:country":"BE",
    "sg:address":"Avenue De L'europe 2",
    "sg:city":"Antoing",
    "sg:orig_category":"Advocaten and juridische adviseurs",
    "sg:phone":"+32 69 44 12 66",
    "sg:postcode":"7640",
    "sg:province":"Hainaut",
    "wof:name":"A. Hanard",
    "wof:placetype":"venue"
},
  "geometry": {"coordinates":[3.4510309696,50.5662193298],"type":"Point"}
}