{
  "type": "Feature",
  "properties": {
    "iso:country":"BE",
    "sg:address":"Industriestraat 10",
    "sg:city":"Kampenhout",
    "sg:classifiers":[
        {
            "category":"Home & Garden",
            "subcategory":"Building Materials",
            "type":"Retail Goods"
        }
    ],
    "sg:phone":"+32 16 60 40 31",
    "sg:postcode":"1910",
    "sg:province":"Vlaams-Brabant",
    "sg:tags":[
        "wall",
        "cupboard"
    ],
    "wof:name":"Van Loo Fr Bvba",
    "wof:placetype":"venue"
},
  "geometry": {"coordinates":[4.5981850624,50.9587135315],"type":"Point"}
}