{
  "type": "Feature",
  "properties": {
    "addr:full":"Plejadenlaan 16 Sint-lambrechts-woluwe/woluwe-saint-lambert Bruxelles-Capitale 1200",
    "addr:housenumber":"16",
    "addr:postcode":"1200",
    "addr:street":"Plejadenlaan",
    "iso:country":"BE",
    "sg:address":"Plejadenlaan 16",
    "sg:city":"Sint-lambrechts-woluwe/woluwe-saint-lambert",
    "sg:orig_category":"Dakwerken",
    "sg:phone":"+32 2 772 18 59",
    "sg:postcode":"1200",
    "sg:province":"Bruxelles-Capitale",
    "wof:name":"Eric Pauwels",
    "wof:placetype":"venue"
},
  "geometry": {"coordinates":[4.4189271927,50.8537063599],"type":"Point"}
}