{
  "type": "Feature",
  "properties": {
    "addr:full":"Abdijstraat 12 Antwerpen Antwerpen 2020",
    "addr:housenumber":"12",
    "addr:postcode":"2020",
    "addr:street":"Abdijstraat",
    "iso:country":"BE",
    "sg:address":"Abdijstraat 12",
    "sg:city":"Antwerpen",
    "sg:orig_category":"Dameskledingzaken",
    "sg:phone":"+32 3 238 54 24",
    "sg:postcode":"2020",
    "sg:province":"Antwerpen",
    "wof:name":"Etam",
    "wof:placetype":"venue"
},
  "geometry": {"coordinates":[4.3790078163,51.1899032593],"type":"Point"}
}