{
  "type": "Feature",
  "properties": {
    "addr:full":"Meir 23-25 Antwerpen Antwerpen 2000",
    "addr:postcode":"23-25;2000",
    "addr:street":"Meir",
    "iso:country":"BE",
    "sg:address":"Meir 23-25",
    "sg:city":"Antwerpen",
    "sg:orig_category":"Huishoudapparaten, televisies and radio's Speelgoed Verlichting and huishoudartikelen",
    "sg:phone":"+32 3 213 10 69",
    "sg:postcode":"2000",
    "sg:province":"Antwerpen",
    "wof:name":"Blokker",
    "wof:placetype":"venue"
},
  "geometry": {"coordinates":[4.4067368507,51.2183036804],"type":"Point"}
}