{
  "type": "Feature",
  "properties": {
    "addr:full":"Rue Esseghem 153 Bruxelles (jette) Bruxelles-Capitale 1090",
    "addr:housenumber":"153",
    "addr:postcode":"1090",
    "addr:street":"Rue Esseghem",
    "iso:country":"BE",
    "sg:address":"Rue Esseghem 153",
    "sg:city":"Bruxelles (jette)",
    "sg:classifiers":[
        {
            "category":"Banks & Credit Unions",
            "subcategory":"Investment Brokerage",
            "type":"Services"
        }
    ],
    "sg:phone":"+32 2 426 95 85",
    "sg:postcode":"1090",
    "sg:province":"Bruxelles-Capitale",
    "sg:tags":[
        "pipe",
        "fitting",
        "coupling"
    ],
    "wof:name":"Inter Pipe Tool",
    "wof:placetype":"venue"
},
  "geometry": {"coordinates":[4.3357081413,50.876285553],"type":"Point"}
}