{
  "type": "Feature",
  "properties": {
    "addr:full":"Rue Des Bruy\u00c8res 88 Chaumont-gistoux Brabant Wallon 1325",
    "addr:housenumber":"88",
    "addr:postcode":"1325",
    "addr:street":"Rue Des Bruye\u0300Res",
    "iso:country":"BE",
    "sg:address":"Rue Des Bruy\u00c8res 88",
    "sg:city":"Chaumont-gistoux",
    "sg:classifiers":[
        {
            "category":"Arena",
            "subcategory":"Sports Club",
            "type":"Entertainment"
        }
    ],
    "sg:phone":"+32 10 68 80 22",
    "sg:postcode":"1325",
    "sg:province":"Brabant Wallon",
    "sg:tags":[
        "de"
    ],
    "wof:name":"V.c. Brabancon",
    "wof:placetype":"venue"
},
  "geometry": {"coordinates":[4.701253891,50.6871147156],"type":"Point"}
}