{
  "type": "Feature",
  "properties": {
    "iso:country":"BE",
    "sg:address":"Rue Oswald Ponette 76",
    "sg:city":"Ronse/renaix",
    "sg:classifiers":[
        {
            "category":"Cafe",
            "type":"Food & Drink"
        }
    ],
    "sg:phone":"+32 55 20 75 33",
    "sg:postcode":"9600",
    "sg:province":"Oost-Vlaanderen",
    "sg:tags":[
        "caf\u00e9s"
    ],
    "wof:name":"Caf\u00c9 Nelson",
    "wof:placetype":"venue"
},
  "geometry": {"coordinates":[3.5931830406,50.7453346252],"type":"Point"}
}