{
  "type": "Feature",
  "properties": {
    "addr:full":"Waesdonckstraat 1 Mortsel Antwerpen 2640",
    "addr:housenumber":"1",
    "addr:postcode":"2640",
    "addr:street":"Waesdonckstraat",
    "iso:country":"BE",
    "sg:address":"Waesdonckstraat 1",
    "sg:city":"Mortsel",
    "sg:classifiers":[
        {
            "category":"Government",
            "subcategory":"Customs House",
            "type":"Public Place"
        }
    ],
    "sg:phone":"+32 3 449 39 50",
    "sg:postcode":"2640",
    "sg:province":"Antwerpen",
    "sg:tags":[
        "packing"
    ],
    "wof:name":"De Brug Vzw",
    "wof:placetype":"venue"
},
  "geometry": {"coordinates":[4.4557042122,51.1824645996],"type":"Point"}
}