{
  "type": "Feature",
  "properties": {
    "addr:full":"Peter Benoitlei 8 Brasschaat Antwerpen 2930",
    "addr:housenumber":"8",
    "addr:postcode":"2930",
    "iso:country":"BE",
    "sg:address":"Peter Benoitlei 8",
    "sg:city":"Brasschaat",
    "sg:orig_category":"Woningbouw",
    "sg:phone":"+32 3 651 67 76",
    "sg:postcode":"2930",
    "sg:province":"Antwerpen",
    "wof:name":"Vleeschouwer Luc",
    "wof:placetype":"venue"
},
  "geometry": {"coordinates":[4.4882049561,51.3029441833],"type":"Point"}
}