{
  "type": "Feature",
  "properties": {
    "addr:full":"Avenue De La Couronne 463 Elsene/ixelles Bruxelles-Capitale 1050",
    "addr:housenumber":"463",
    "addr:postcode":"1050",
    "addr:street":"Avenue De La Couronne",
    "iso:country":"BE",
    "sg:address":"Avenue De La Couronne 463",
    "sg:city":"Elsene/ixelles",
    "sg:classifiers":[
        {
            "category":"Restaurant",
            "type":"Food & Drink"
        }
    ],
    "sg:phone":"+32 2 649 87 00",
    "sg:postcode":"1050",
    "sg:province":"Bruxelles-Capitale",
    "wof:name":"Time Caf\u00c9",
    "wof:placetype":"venue"
},
  "geometry": {"coordinates":[4.3902840614,50.8159484863],"type":"Point"}
}