{
  "type": "Feature",
  "properties": {
    "addr:full":"Kerkstraat 43 Middelkerke West-Vlaanderen 8430",
    "addr:housenumber":"43",
    "addr:postcode":"8430",
    "addr:street":"Kerkstraat",
    "iso:country":"BE",
    "sg:address":"Kerkstraat 43",
    "sg:city":"Middelkerke",
    "sg:classifiers":[
        {
            "category":"Restaurant",
            "type":"Food & Drink"
        }
    ],
    "sg:phone":"+32 59 30 41 47",
    "sg:postcode":"8430",
    "sg:province":"West-Vlaanderen",
    "wof:name":"Pizzeria Pinokkio",
    "wof:placetype":"venue"
},
  "geometry": {"coordinates":[2.8203859329,51.18592453],"type":"Point"}
}