{
  "type": "Feature",
  "properties": {
    "addr:full":"Rue De Moulin 52bc Tinlot Li\u00e8ge 4557",
    "addr:housenumber":"52bc",
    "addr:postcode":"4557",
    "addr:street":"Rue De Moulin",
    "iso:country":"BE",
    "sg:address":"Rue De Moulin 52bc",
    "sg:city":"Tinlot",
    "sg:orig_category":"M\u00e9decins and sp\u00e9cialistes",
    "sg:phone":"+32 85 51 21 82",
    "sg:postcode":"4557",
    "sg:province":"Li\u00e8ge",
    "wof:name":"Brigitte Salee",
    "wof:placetype":"venue"
},
  "geometry": {"coordinates":[5.4245839119,50.4801864624],"type":"Point"}
}