{
  "type": "Feature",
  "properties": {
    "addr:full":"Rue De L'ecole-moyenne 5 Fosses-la-ville Namur 5070",
    "addr:housenumber":"5",
    "addr:postcode":"5070",
    "addr:street":"Rue De L'Ecole-Moyenne",
    "iso:country":"BE",
    "sg:address":"Rue De L'ecole-moyenne 5",
    "sg:city":"Fosses-la-ville",
    "sg:orig_category":"Enseignement maternel and primaire",
    "sg:phone":"+32 71 71 22 57",
    "sg:postcode":"5070",
    "sg:province":"Namur",
    "wof:name":"Ecole Fondamentale",
    "wof:placetype":"venue"
},
  "geometry": {"coordinates":[4.6954579353,50.3924636841],"type":"Point"}
}