{
  "type": "Feature",
  "properties": {
    "iso:country":"BE",
    "sg:address":"Rue Des Rotisseurs 3",
    "sg:city":"Huy (grand)",
    "sg:classifiers":[
        {
            "category":"Bars & Pubs",
            "type":"Food & Drink"
        }
    ],
    "sg:phone":"+32 85 61 33 63",
    "sg:postcode":"4500",
    "sg:province":"Li\u00e8ge",
    "wof:name":"Caf\u00c9 Savanah",
    "wof:placetype":"venue"
},
  "geometry": {"coordinates":[5.2406330109,50.5187911987],"type":"Point"}
}