{
  "type": "Feature",
  "properties": {
    "iso:country":"BE",
    "sg:address":"Avenue E. Van Nieuwenhuyse 6",
    "sg:city":"Bruxelles",
    "sg:classifiers":[
        {
            "category":"Transit Center",
            "subcategory":"Passenger",
            "type":"Transportation"
        }
    ],
    "sg:phone":"+32 2 676 92 11",
    "sg:postcode":"1160",
    "sg:province":"Bruxelles-Capitale",
    "sg:tags":[
        "lift",
        "elevator"
    ],
    "wof:name":"Kone International S.a.",
    "wof:placetype":"venue"
},
  "geometry": {"coordinates":[4.4193348885,50.8138084412],"type":"Point"}
}