{
  "type": "Feature",
  "properties": {
    "addr:full":"Maubeugelaan 4 Vilvoorde Vlaams-Brabant 1800",
    "addr:housenumber":"4",
    "addr:postcode":"1800",
    "addr:street":"Maubeugelaan",
    "iso:country":"BE",
    "sg:address":"Maubeugelaan 4",
    "sg:city":"Vilvoorde",
    "sg:classifiers":[
        {
            "category":"Travel",
            "subcategory":"Travel Agent",
            "type":"Entertainment"
        }
    ],
    "sg:phone":"+32 2 253 38 87",
    "sg:postcode":"1800",
    "sg:province":"Vlaams-Brabant",
    "sg:tags":[
        "agency"
    ],
    "wof:name":"Siesta Touring Bvba",
    "wof:placetype":"venue"
},
  "geometry": {"coordinates":[4.4048337936,50.9194335938],"type":"Point"}
}