{
  "type": "Feature",
  "properties": {
    "iso:country":"BE",
    "sg:address":"Chauss\u00c9e De Louvain 257",
    "sg:city":"Eghezee",
    "sg:orig_category":"Eleveurs de bovins",
    "sg:phone":"+32 81 81 17 91",
    "sg:postcode":"5310",
    "sg:province":"Namur",
    "wof:name":"Arthur Romain",
    "wof:placetype":"venue"
},
  "geometry": {"coordinates":[4.9012298584,50.6018600464],"type":"Point"}
}