{
  "type": "Feature",
  "properties": {
    "iso:country":"BE",
    "sg:address":"Drevendaal 7b",
    "sg:city":"Sint-katelijne-waver",
    "sg:orig_category":"Herstellingen and onderhoud van auto's",
    "sg:phone":"+32 15 32 12 64",
    "sg:postcode":"2860",
    "sg:province":"Antwerpen",
    "wof:name":"Veekemans",
    "wof:placetype":"venue"
},
  "geometry": {"coordinates":[4.5159330368,51.0666847229],"type":"Point"}
}