{
  "type": "Feature",
  "properties": {
    "addr:full":"Sint-lambertuslaan 2 Bilzen Limburg 3740",
    "addr:housenumber":"2",
    "addr:postcode":"3740",
    "addr:street":"Sint-Lambertuslaan",
    "iso:country":"BE",
    "sg:address":"Sint-lambertuslaan 2",
    "sg:city":"Bilzen",
    "sg:orig_category":"Pain, p\u00e2tisseries and confiseries",
    "sg:phone":"+32 89 41 26 95",
    "sg:postcode":"3740",
    "sg:province":"Limburg",
    "wof:name":"Bakkerij Philda",
    "wof:placetype":"venue"
},
  "geometry": {"coordinates":[5.5135512352,50.8723449707],"type":"Point"}
}