{
  "type": "Feature",
  "properties": {
    "addr:full":"Rue Centrale 105 Waimes/waimes Li\u00e8ge 4950",
    "addr:housenumber":"105",
    "addr:postcode":"4950",
    "addr:street":"Rue Centrale",
    "iso:country":"BE",
    "sg:address":"Rue Centrale 105",
    "sg:city":"Waimes/waimes",
    "sg:orig_category":"Woningbouw",
    "sg:phone":"+32 80 44 68 08",
    "sg:postcode":"4950",
    "sg:province":"Li\u00e8ge",
    "wof:name":"Alain Kluckers",
    "wof:placetype":"venue"
},
  "geometry": {"coordinates":[6.1406908035,50.4036178589],"type":"Point"}
}