{
  "type": "Feature",
  "properties": {
    "addr:full":"5310 Eghez\u00c9e (groot) Namur 5310",
    "addr:housenumber":"5310",
    "addr:postcode":"5310",
    "addr:street":"Egheze\u0301E Groot Namur",
    "iso:country":"BE",
    "sg:address":"5310",
    "sg:city":"Eghez\u00c9e (groot)",
    "sg:orig_category":"Pharmaciens",
    "sg:phone":"+32 900 10 500",
    "sg:postcode":"5310",
    "sg:province":"Namur",
    "wof:name":"Pharmacies De Garde",
    "wof:placetype":"venue"
},
  "geometry": {"coordinates":[4.9071350098,50.5914764404],"type":"Point"}
}