{
  "type": "Feature",
  "properties": {
    "iso:country":"BE",
    "sg:address":"Rue De La P\u00cacherie 180",
    "sg:city":"Ukkel/uccle",
    "sg:orig_category":"Experts-comptables",
    "sg:phone":"+32 2 374 29 20",
    "sg:postcode":"1180",
    "sg:province":"Bruxelles-Capitale",
    "wof:name":"Madeleine Lefebvre",
    "wof:placetype":"venue"
},
  "geometry": {"coordinates":[4.3544421196,50.7927322388],"type":"Point"}
}