{
  "type": "Feature",
  "properties": {
    "addr:full":"Kortenbergsesteenweg 3b Steenokkerzeel Vlaams-Brabant 1820",
    "addr:housenumber":"3b",
    "addr:postcode":"1820",
    "addr:street":"Kortenbergsesteenweg",
    "iso:country":"BE",
    "sg:address":"Kortenbergsesteenweg 3b",
    "sg:city":"Steenokkerzeel",
    "sg:orig_category":"Diverse bedrijfsbeheeradviesbureaus",
    "sg:phone":"+32 2 757 64 40",
    "sg:postcode":"1820",
    "sg:province":"Vlaams-Brabant",
    "wof:name":"Alliance Michel",
    "wof:placetype":"venue"
},
  "geometry": {"coordinates":[4.5147681236,50.9046897888],"type":"Point"}
}