{
  "type": "Feature",
  "properties": {
    "iso:country":"BE",
    "sg:address":"Rue Defuisseaux 124",
    "sg:city":"Saint-ghislain",
    "sg:classifiers":[
        {
            "category":"Home & Garden",
            "subcategory":"Building Materials",
            "type":"Retail Goods"
        }
    ],
    "sg:phone":"+32 65 64 12 59",
    "sg:postcode":"7330",
    "sg:province":"Hainaut",
    "sg:tags":[
        "aluminium",
        "window"
    ],
    "wof:name":"Menuiserie Roger Dupont S.a.",
    "wof:placetype":"venue"
},
  "geometry": {"coordinates":[3.8077700138,50.4566001892],"type":"Point"}
}