{
  "type": "Feature",
  "properties": {
    "iso:country":"BE",
    "sg:address":"Bessemerstraat 382",
    "sg:city":"Lanaken",
    "sg:orig_category":"Woningbouw",
    "sg:phone":"+32 89 71 65 62",
    "sg:postcode":"3620",
    "sg:province":"Limburg",
    "wof:name":"Dabo",
    "wof:placetype":"venue"
},
  "geometry": {"coordinates":[5.6346921921,50.9003257751],"type":"Point"}
}