{
  "type": "Feature",
  "properties": {
    "iso:country":"BE",
    "sg:address":"Spenningstraat 3",
    "sg:city":"Aalter",
    "sg:orig_category":"Rundveehouders",
    "sg:phone":"+32 9 374 24 38",
    "sg:postcode":"9881",
    "sg:province":"Oost-Vlaanderen",
    "wof:name":"Gabriel Verhelst",
    "wof:placetype":"venue"
},
  "geometry": {"coordinates":[3.5216269493,51.0997695923],"type":"Point"}
}