{
  "type": "Feature",
  "properties": {
    "addr:full":"Madeliefjeslaan 27 Wezembeek-oppem/wezembeek-oppem Vlaams-Brabant 1970",
    "addr:housenumber":"27",
    "addr:postcode":"1970",
    "addr:street":"Madeliefjeslaan",
    "iso:country":"BE",
    "sg:address":"Madeliefjeslaan 27",
    "sg:city":"Wezembeek-oppem/wezembeek-oppem",
    "sg:orig_category":"Landmeters",
    "sg:phone":"+32 2 731 63 95",
    "sg:postcode":"1970",
    "sg:province":"Vlaams-Brabant",
    "wof:name":"Willy Degeest/w. Degeest",
    "wof:placetype":"venue"
},
  "geometry": {"coordinates":[4.480779171,50.8416824341],"type":"Point"}
}