{
  "type": "Feature",
  "properties": {
    "iso:country":"BE",
    "sg:address":"Ambachtenlaan 11",
    "sg:city":"Leuven (heverlee)",
    "sg:orig_category":"Electric transformers, rectifiers, converters",
    "sg:phone":"+32 16 40 84 88",
    "sg:postcode":"3001",
    "sg:province":"Vlaams-Brabant",
    "wof:name":"C.e.+t Cabling & Services Nv",
    "wof:placetype":"venue"
},
  "geometry": {"coordinates":[4.7164177895,50.8488006592],"type":"Point"}
}