{
  "type": "Feature",
  "properties": {
    "addr:full":"Lierbaan 204 Putte Antwerpen 2580",
    "addr:housenumber":"204",
    "addr:postcode":"2580",
    "addr:street":"Lierbaan",
    "iso:country":"BE",
    "sg:address":"Lierbaan 204",
    "sg:city":"Putte",
    "sg:orig_category":"Rundveehouders",
    "sg:phone":"+32 15 75 62 46",
    "sg:postcode":"2580",
    "sg:province":"Antwerpen",
    "wof:name":"Jozef Hoegaerts",
    "wof:placetype":"venue"
},
  "geometry": {"coordinates":[4.6168842316,51.0794296265],"type":"Point"}
}