{
  "type": "Feature",
  "properties": {
    "addr:full":"Nieuwstraat 192 Diepenbeek Limburg 3590",
    "addr:housenumber":"192",
    "addr:postcode":"3590",
    "addr:street":"Nieuwstraat",
    "iso:country":"BE",
    "sg:address":"Nieuwstraat 192",
    "sg:city":"Diepenbeek",
    "sg:orig_category":"Gespecialiseerde residenti\u00eble bouw",
    "sg:phone":"+32 11 22 21 42",
    "sg:postcode":"3590",
    "sg:province":"Limburg",
    "wof:name":"Valkenborgh",
    "wof:placetype":"venue"
},
  "geometry": {"coordinates":[5.4584350586,50.9272537231],"type":"Point"}
}