{
  "type": "Feature",
  "properties": {
    "iso:country":"BE",
    "sg:address":"Rue Porte Neuve 26",
    "sg:city":"Arlon",
    "sg:orig_category":"S\u00e9curit\u00e9 sociale",
    "sg:phone":"+32 63 23 10 00",
    "sg:postcode":"6700",
    "sg:province":"Luxembourg",
    "wof:name":"Mutualit\u00c9 Socialiste",
    "wof:placetype":"venue"
},
  "geometry": {"coordinates":[5.8143849373,49.6848564148],"type":"Point"}
}