{
  "type": "Feature",
  "properties": {
    "addr:full":"Route De Mons 146 Binche (waudrez) Hainaut 7131",
    "addr:housenumber":"146",
    "addr:postcode":"7131",
    "addr:street":"Route De Mons",
    "iso:country":"BE",
    "sg:address":"Route De Mons 146",
    "sg:city":"Binche (waudrez)",
    "sg:classifiers":[
        {
            "category":"Fast Food",
            "type":"Food & Drink"
        }
    ],
    "sg:phone":"+32 64 34 13 19",
    "sg:postcode":"7131",
    "sg:province":"Hainaut",
    "sg:tags":[
        "fried",
        "stand",
        "potato"
    ],
    "wof:name":"Friterie Du Coin",
    "wof:placetype":"venue"
},
  "geometry": {"coordinates":[4.1602520943,50.4135704041],"type":"Point"}
}