{
  "type": "Feature",
  "properties": {
    "addr:full":"Kouterstraat 3 Beveren (kieldrecht) Oost-Vlaanderen 9130",
    "addr:housenumber":"3",
    "addr:postcode":"9130",
    "addr:street":"Kouterstraat",
    "iso:country":"BE",
    "sg:address":"Kouterstraat 3",
    "sg:city":"Beveren (kieldrecht)",
    "sg:classifiers":[
        {
            "category":"Health Services",
            "subcategory":"Health Practitioner",
            "type":"Services"
        }
    ],
    "sg:phone":"+32 3 773 55 91",
    "sg:postcode":"9130",
    "sg:province":"Oost-Vlaanderen",
    "sg:tags":[
        "physiotherapist"
    ],
    "wof:name":"De Paepe Paul",
    "wof:placetype":"venue"
},
  "geometry": {"coordinates":[4.164539814,51.286151886],"type":"Point"}
}