{
  "type": "Feature",
  "properties": {
    "addr:full":"Markt 99 Deinze Oost-Vlaanderen 9800",
    "addr:housenumber":"99",
    "addr:postcode":"9800",
    "addr:street":"Markt",
    "iso:country":"BE",
    "sg:address":"Markt 99",
    "sg:city":"Deinze",
    "sg:orig_category":"V\u00eatements",
    "sg:phone":"+32 9 380 06 97",
    "sg:postcode":"9800",
    "sg:province":"Oost-Vlaanderen",
    "wof:name":"Texas Jeans",
    "wof:placetype":"venue"
},
  "geometry": {"coordinates":[3.5258131027,50.9858589172],"type":"Point"}
}