{
  "type": "Feature",
  "properties": {
    "iso:country":"BE",
    "sg:address":"Rozelaarstraat 11",
    "sg:city":"Ninove",
    "sg:orig_category":"Eleveurs de bovins. Eleveurs and marchands de porcs",
    "sg:phone":"+32 54 33 55 98",
    "sg:postcode":"9400",
    "sg:province":"Oost-Vlaanderen",
    "wof:name":"Marc De Vleminck",
    "wof:placetype":"venue"
},
  "geometry": {"coordinates":[4.0270490646,50.788974762],"type":"Point"}
}