{
  "type": "Feature",
  "properties": {
    "addr:full":"Vilvoordsesteenweg 133 Grimbergen Vlaams-Brabant 1850",
    "addr:housenumber":"133",
    "addr:postcode":"1850",
    "addr:street":"Vilvoordsesteenweg",
    "iso:country":"BE",
    "sg:address":"Vilvoordsesteenweg 133",
    "sg:city":"Grimbergen",
    "sg:classifiers":[
        {
            "category":"Professional",
            "subcategory":"Management & Consulting",
            "type":"Services"
        }
    ],
    "sg:phone":"+32 2 306 40 22",
    "sg:postcode":"1850",
    "sg:province":"Vlaams-Brabant",
    "sg:tags":[
        "consultant"
    ],
    "wof:name":"Verbrugghe Business Coaching",
    "wof:placetype":"venue"
},
  "geometry": {"coordinates":[4.3809108734,50.930141449],"type":"Point"}
}