{
  "type": "Feature",
  "properties": {
    "addr:full":"Rue De La Grande Veine 93 Dour Hainaut 7370",
    "addr:housenumber":"93",
    "addr:postcode":"7370",
    "addr:street":"Rue De La Grande Veine;Hainaut",
    "iso:country":"BE",
    "sg:address":"Rue De La Grande Veine 93",
    "sg:city":"Dour",
    "sg:classifiers":[
        {
            "category":"Personal",
            "subcategory":"Beauty Salon",
            "type":"Services"
        }
    ],
    "sg:phone":"+32 65 65 93 91",
    "sg:postcode":"7370",
    "sg:province":"Hainaut",
    "sg:tags":[
        "de",
        "coiffure"
    ],
    "wof:name":"Stephane Dame",
    "wof:placetype":"venue"
},
  "geometry": {"coordinates":[3.7575469017,50.3983840942],"type":"Point"}
}