{
  "type": "Feature",
  "properties": {
    "iso:country":"BE",
    "sg:address":"Wolskestraat 1",
    "sg:city":"Hasselt",
    "sg:classifiers":[
        {
            "category":"Communications",
            "type":"Services"
        }
    ],
    "sg:phone":"+32 11 22 68 69",
    "sg:postcode":"3500",
    "sg:province":"Limburg",
    "sg:tags":[
        "translator"
    ],
    "wof:name":"Lossmannova Maria",
    "wof:placetype":"venue"
},
  "geometry": {"coordinates":[5.3687782288,50.9254837036],"type":"Point"}
}