{
  "type": "Feature",
  "properties": {
    "iso:country":"BE",
    "sg:address":"Stationsstraat 58",
    "sg:city":"Oosterzele",
    "sg:orig_category":"Cr\u00e8ches and garderies d'enfants",
    "sg:phone":"+32 9 362 12 91",
    "sg:postcode":"9860",
    "sg:province":"Oost-Vlaanderen",
    "wof:name":"De Blokkentoren",
    "wof:placetype":"venue"
},
  "geometry": {"coordinates":[3.7806489468,50.9376564026],"type":"Point"}
}