{
  "type": "Feature",
  "properties": {
    "addr:full":"Hundelgemsesteenweg 847 Merelbeke Oost-Vlaanderen 9820",
    "addr:housenumber":"847",
    "addr:postcode":"9820",
    "addr:street":"Hundelgemsesteenweg",
    "iso:country":"BE",
    "sg:address":"Hundelgemsesteenweg 847",
    "sg:city":"Merelbeke",
    "sg:orig_category":"Catering and organisatie van feesten Fast food and meeneem restaurants Levering aan huis restaurants",
    "sg:phone":"+32 9 362 31 11",
    "sg:postcode":"9820",
    "sg:province":"Oost-Vlaanderen",
    "wof:name":"Hof Van Steenberge",
    "wof:placetype":"venue"
},
  "geometry": {"coordinates":[3.7377130985,50.9651107788],"type":"Point"}
}