{
  "type": "Feature",
  "properties": {
    "iso:country":"BE",
    "sg:address":"R\u00e9sidence Joseph Defaux 43",
    "sg:city":"Tournai (gaurain-ramecroix)",
    "sg:classifiers":[
        {
            "category":"Arts & Performance",
            "subcategory":"Music",
            "type":"Entertainment"
        }
    ],
    "sg:phone":"+32 69 54 89 11",
    "sg:postcode":"7530",
    "sg:province":"Hainaut",
    "sg:tags":[
        "freelance",
        "musician"
    ],
    "wof:name":"Majorettes Laurette",
    "wof:placetype":"venue"
},
  "geometry": {"coordinates":[3.4963788986,50.5867424011],"type":"Point"}
}