{
  "type": "Feature",
  "properties": {
    "addr:full":"Bo\u00eete Postale 10 Bruxelles1 Bruxelles-Capitale 1000",
    "addr:housenumber":"10",
    "addr:postcode":"1000",
    "addr:street":"Bruxelles1",
    "iso:country":"BE",
    "sg:address":"Bo\u00eete Postale 10",
    "sg:city":"Bruxelles1",
    "sg:classifiers":[
        {
            "category":"Government",
            "subcategory":"Post Office",
            "type":"Public Place"
        }
    ],
    "sg:phone":"+32 2 512 31 42",
    "sg:postcode":"1000",
    "sg:province":"Bruxelles-Capitale",
    "sg:tags":[
        "stamp"
    ],
    "wof:name":"Godu J-p",
    "wof:placetype":"venue"
},
  "geometry": {"coordinates":[4.3513898849,50.8584594727],"type":"Point"}
}