{
  "type": "Feature",
  "properties": {
    "addr:full":"Rue Alphonse Vanr\u00f4me 75 Morlanwelz (carni\u00e8res) Hainaut 7141",
    "addr:housenumber":"75",
    "addr:postcode":"7141",
    "addr:street":"Rue Alphonse Vanro\u0302Me",
    "iso:country":"BE",
    "sg:address":"Rue Alphonse Vanr\u00f4me 75",
    "sg:city":"Morlanwelz (carni\u00e8res)",
    "sg:classifiers":[
        {
            "category":"Professional",
            "subcategory":"Accounting & Tax Preparation",
            "type":"Services"
        }
    ],
    "sg:phone":"+32 64 44 92 32",
    "sg:postcode":"7141",
    "sg:province":"Hainaut",
    "sg:tags":[
        "bookkeeper"
    ],
    "wof:name":"Gabeg Scrl",
    "wof:placetype":"venue"
},
  "geometry": {"coordinates":[4.2503252029,50.447769165],"type":"Point"}
}