{
  "type": "Feature",
  "properties": {
    "addr:full":"Lodewijk De Raetlaan 54 Kachtem West-Vlaanderen 8870",
    "addr:housenumber":"54",
    "addr:postcode":"8870",
    "addr:street":"Lodewijk De Raetlaan",
    "iso:country":"BE",
    "sg:address":"Lodewijk De Raetlaan 54",
    "sg:city":"Kachtem",
    "sg:classifiers":[
        {
            "category":"Professional",
            "subcategory":"Engineering",
            "type":"Services"
        }
    ],
    "sg:phone":"+32 51 30 75 21",
    "sg:postcode":"8870",
    "sg:province":"West-Vlaanderen",
    "sg:tags":[
        "machine",
        "-",
        "mechanical"
    ],
    "wof:name":"Dimetal Belgium Nv",
    "wof:placetype":"venue"
},
  "geometry": {"coordinates":[3.188847065,50.9308204651],"type":"Point"}
}