{
  "type": "Feature",
  "properties": {
    "iso:country":"BE",
    "sg:address":"Kippekensstraat 1",
    "sg:city":"Ukkel/uccle",
    "sg:orig_category":"GROENTEN AND FRUIT Kruideniers",
    "sg:phone":"+32 2 376 25 40",
    "sg:postcode":"1180",
    "sg:province":"Bruxelles-Capitale",
    "wof:name":"Maison Joli Vert",
    "wof:placetype":"venue"
},
  "geometry": {"coordinates":[4.334487915,50.7943115234],"type":"Point"}
}