{
  "type": "Feature",
  "properties": {
    "addr:full":"Rue Ovide-decroly 113 Li\u00e8ge 1 (angleur) Li\u00e8ge 4031",
    "addr:housenumber":"113;1",
    "addr:postcode":"4031",
    "addr:street":"Rue Ovide-Decroly",
    "iso:country":"BE",
    "sg:address":"Rue Ovide-decroly 113",
    "sg:city":"Li\u00e8ge 1 (angleur)",
    "sg:classifiers":[
        {
            "category":"Health Services",
            "subcategory":"Nursing And Care Facility",
            "type":"Services"
        }
    ],
    "sg:phone":"+32 4 365 27 38",
    "sg:postcode":"4031",
    "sg:province":"Li\u00e8ge",
    "sg:tags":[
        "home"
    ],
    "wof:name":"Foster Denys W Asbl",
    "wof:placetype":"venue"
},
  "geometry": {"coordinates":[5.5933542252,50.6120185852],"type":"Point"}
}