{
  "type": "Feature",
  "properties": {
    "addr:full":"Terhulpsesteenweg 171 Watermaal-bosvoorde/watermael-boitsfort Bruxelles-Capitale 1170",
    "addr:housenumber":"171;/",
    "addr:postcode":"1170",
    "addr:street":"Terhulpsesteenweg;Watermaal-Bosvoorde",
    "iso:country":"BE",
    "sg:address":"Terhulpsesteenweg 171",
    "sg:city":"Watermaal-bosvoorde/watermael-boitsfort",
    "sg:orig_category":"Landmeters and schatters",
    "sg:phone":"+32 2 673 60 20",
    "sg:postcode":"1170",
    "sg:province":"Bruxelles-Capitale",
    "wof:name":"Wilma-betonimmo-batipont",
    "wof:placetype":"venue"
},
  "geometry": {"coordinates":[4.4016389847,50.7960395813],"type":"Point"}
}