{
  "type": "Feature",
  "properties": {
    "addr:full":"Rue Ferrer 169 Seraing Li\u00e8ge 4100",
    "addr:housenumber":"169",
    "addr:postcode":"4100",
    "addr:street":"Rue Ferrer",
    "iso:country":"BE",
    "sg:address":"Rue Ferrer 169",
    "sg:city":"Seraing",
    "sg:classifiers":[
        {
            "category":"Autos & Motor Vehicles",
            "subcategory":"Fuel & Gas Station",
            "type":"Retail Goods"
        }
    ],
    "sg:phone":"+32 4 337 33 94",
    "sg:postcode":"4100",
    "sg:province":"Li\u00e8ge",
    "sg:tags":[
        "stations-service",
        "carburants"
    ],
    "wof:name":"Missil",
    "wof:placetype":"venue"
},
  "geometry": {"coordinates":[5.5005669594,50.5790634155],"type":"Point"}
}