{
  "type": "Feature",
  "properties": {
    "addr:full":"Monseigneur Cardijnstraat 11 Kasterlee Antwerpen 2460",
    "addr:housenumber":"11",
    "addr:postcode":"2460",
    "addr:street":"Monseigneur Cardijnstraat",
    "iso:country":"BE",
    "sg:address":"Monseigneur Cardijnstraat 11",
    "sg:city":"Kasterlee",
    "sg:classifiers":[
        {
            "category":"Personal",
            "subcategory":"Barber",
            "type":"Services"
        }
    ],
    "sg:phone":"+32 14 85 05 99",
    "sg:postcode":"2460",
    "sg:province":"Antwerpen",
    "sg:tags":[
        "gentleman",
        "salon",
        "-",
        "hairdressing"
    ],
    "wof:name":"Kapper Chris",
    "wof:placetype":"venue"
},
  "geometry": {"coordinates":[4.9672818184,51.2393531799],"type":"Point"}
}