{
  "type": "Feature",
  "properties": {
    "iso:country":"BE",
    "sg:address":"Kloterstraat 37",
    "sg:city":"Bocholt",
    "sg:orig_category":"Installation \u00e9lectrique r\u00e9sidentielle",
    "sg:phone":"+32 11 62 20 90",
    "sg:postcode":"3950",
    "sg:province":"Limburg",
    "wof:name":"Hendrik Custers",
    "wof:placetype":"venue"
},
  "geometry": {"coordinates":[5.5265130997,51.1887931824],"type":"Point"}
}