{
  "type": "Feature",
  "properties": {
    "iso:country":"BE",
    "sg:address":"Oude Ieperstraat 55",
    "sg:city":"Wevelgem",
    "sg:orig_category":"Installation de menuiserie en bois and plastique",
    "sg:phone":"+32 56 32 32 02",
    "sg:postcode":"8560",
    "sg:province":"West-Vlaanderen",
    "wof:name":"Opdeca",
    "wof:placetype":"venue"
},
  "geometry": {"coordinates":[3.2177000046,50.8361930847],"type":"Point"}
}