{
  "type": "Feature",
  "properties": {
    "iso:country":"BE",
    "sg:address":"Keiberg 10",
    "sg:city":"Wemmel",
    "sg:orig_category":"Niet-gespecialiseerde handelsagenten",
    "sg:phone":"+32 2 461 28 68",
    "sg:postcode":"1780",
    "sg:province":"Vlaams-Brabant",
    "wof:name":"P.a. Preisagentur - Allmaco",
    "wof:placetype":"venue"
},
  "geometry": {"coordinates":[4.2929468155,50.9098587036],"type":"Point"}
}