{
  "type": "Feature",
  "properties": {
    "addr:full":"Otegemse Steenweg 84 Deerlijk West-Vlaanderen 8540",
    "addr:housenumber":"84",
    "addr:postcode":"8540",
    "addr:street":"Steenweg",
    "iso:country":"BE",
    "sg:address":"Otegemse Steenweg 84",
    "sg:city":"Deerlijk",
    "sg:classifiers":[
        {
            "category":"Building & Trades",
            "subcategory":"Electrical",
            "type":"Services"
        }
    ],
    "sg:phone":"+32 56 77 41 52",
    "sg:postcode":"8540",
    "sg:province":"West-Vlaanderen",
    "sg:tags":[
        "electric",
        "-",
        "housewiring",
        "contractor"
    ],
    "wof:name":"Elektro Vg",
    "wof:placetype":"venue"
},
  "geometry": {"coordinates":[3.3785369396,50.8154830933],"type":"Point"}
}