{
  "type": "Feature",
  "properties": {
    "addr:full":"Brugsesteenweg 21 Eeklo Oost-Vlaanderen 9900",
    "addr:housenumber":"21",
    "addr:postcode":"9900",
    "addr:street":"Brugsesteenweg",
    "iso:country":"BE",
    "sg:address":"Brugsesteenweg 21",
    "sg:city":"Eeklo",
    "sg:orig_category":"Krantenwinkels Rookartikelen",
    "sg:phone":"+32 9 377 61 71",
    "sg:postcode":"9900",
    "sg:province":"Oost-Vlaanderen",
    "wof:name":"Climax-bookshop",
    "wof:placetype":"venue"
},
  "geometry": {"coordinates":[3.553260088,51.1905555725],"type":"Point"}
}