{
  "type": "Feature",
  "properties": {
    "addr:full":"Rijkmakerlaan 17 Essen Antwerpen 2910",
    "addr:housenumber":"17",
    "addr:postcode":"2910",
    "addr:street":"Rijkmakerlaan",
    "iso:country":"BE",
    "sg:address":"Rijkmakerlaan 17",
    "sg:city":"Essen",
    "sg:classifiers":[
        {
            "category":"Retail",
            "subcategory":"Laundry & Dry Cleaning",
            "type":"Services"
        }
    ],
    "sg:phone":"+32 3 667 25 47",
    "sg:postcode":"2910",
    "sg:province":"Antwerpen",
    "wof:name":"Super Shop",
    "wof:placetype":"venue"
},
  "geometry": {"coordinates":[4.4993128777,51.4458770752],"type":"Point"}
}