{
  "type": "Feature",
  "properties": {
    "iso:country":"BE",
    "sg:address":"Werviksestraat 65",
    "sg:city":"Ieper (zillebeke)",
    "sg:classifiers":[
        {
            "category":"Farming",
            "subcategory":"Livestock Farm",
            "type":"Manufacturing & Wholesale Goods"
        }
    ],
    "sg:phone":"+32 57 20 67 45",
    "sg:postcode":"8902",
    "sg:province":"West-Vlaanderen",
    "sg:tags":[
        "buyer"
    ],
    "wof:name":"Desimpel R",
    "wof:placetype":"venue"
},
  "geometry": {"coordinates":[2.9266269207,50.8309783936],"type":"Point"}
}