{
  "type": "Feature",
  "properties": {
    "iso:country":"BE",
    "sg:address":"Stationsstraat 10",
    "sg:city":"Wachtebeke",
    "sg:classifiers":[
        {
            "category":"Insurance",
            "subcategory":"Insurance Agent",
            "type":"Services"
        }
    ],
    "sg:phone":"+32 9 345 75 47",
    "sg:postcode":"9185",
    "sg:province":"Oost-Vlaanderen",
    "sg:tags":[
        "broker"
    ],
    "wof:name":"De Caluw\u00e9 Geert Bvba",
    "wof:placetype":"venue"
},
  "geometry": {"coordinates":[3.8608679771,51.1715354919],"type":"Point"}
}