{
  "type": "Feature",
  "properties": {
    "addr:full":"Avenue De La M\u00e9tropole 7 Mouscron Hainaut 7700",
    "addr:housenumber":"7",
    "addr:postcode":"7700",
    "addr:street":"Avenue De La Me\u0301Tropole",
    "iso:country":"BE",
    "sg:address":"Avenue De La M\u00e9tropole 7",
    "sg:city":"Mouscron",
    "sg:classifiers":[
        {
            "category":"Bakery",
            "type":"Food & Drink"
        }
    ],
    "sg:phone":"+32 56 85 23 60",
    "sg:postcode":"7700",
    "sg:province":"Hainaut",
    "sg:tags":[
        "confectioner",
        "baker"
    ],
    "wof:name":"Pastrilux",
    "wof:placetype":"venue"
},
  "geometry": {"coordinates":[3.2137539387,50.7232284546],"type":"Point"}
}