{
  "type": "Feature",
  "properties": {
    "iso:country":"BE",
    "sg:address":"Wolterslaan 112",
    "sg:city":"Gent",
    "sg:orig_category":"Belastingconsulenten Diverse juridische dienstverlening",
    "sg:phone":"+32 9 238 19 09",
    "sg:postcode":"9000",
    "sg:province":"Oost-Vlaanderen",
    "wof:name":"De Craene Fiduciaire",
    "wof:placetype":"venue"
},
  "geometry": {"coordinates":[3.7499740124,51.0482673645],"type":"Point"}
}