{
  "type": "Feature",
  "properties": {
    "addr:full":"Rue De Beaumont 45 Grez-doiceau Brabant Wallon 1390",
    "addr:housenumber":"45",
    "addr:postcode":"1390",
    "addr:street":"Rue De Beaumont",
    "iso:country":"BE",
    "sg:address":"Rue De Beaumont 45",
    "sg:city":"Grez-doiceau",
    "sg:orig_category":"Beheer onroerend goed",
    "sg:phone":"+32 10 86 00 65",
    "sg:postcode":"1390",
    "sg:province":"Brabant Wallon",
    "wof:name":"Philippe Pr\u00c9vinaire",
    "wof:placetype":"venue"
},
  "geometry": {"coordinates":[4.6531739235,50.7917823792],"type":"Point"}
}