{
  "type": "Feature",
  "properties": {
    "iso:country":"BE",
    "sg:address":"Faubourg Sainte-anne 1ba1",
    "sg:city":"Nivelles",
    "sg:orig_category":"Persagentschappen",
    "sg:phone":"+32 476 30 66 89",
    "sg:postcode":"1400",
    "sg:province":"Brabant Wallon",
    "wof:name":"C\u00c9dric Lobelle",
    "wof:placetype":"venue"
},
  "geometry": {"coordinates":[4.3219017982,50.5995140076],"type":"Point"}
}