{
  "type": "Feature",
  "properties": {
    "iso:country":"BE",
    "sg:address":"De Conincplein 11",
    "sg:city":"Antwerpen",
    "sg:classifiers":[
        {
            "category":"Bars & Pubs",
            "type":"Food & Drink"
        }
    ],
    "sg:phone":"+32 3 232 53 86",
    "sg:postcode":"2060",
    "sg:province":"Antwerpen",
    "wof:name":"Blackberry Caf\u00e9",
    "wof:placetype":"venue"
},
  "geometry": {"coordinates":[4.4199118614,51.2214813232],"type":"Point"}
}