{
  "type": "Feature",
  "properties": {
    "addr:full":"Zevekootstraat 71 Erpe-mere Oost-Vlaanderen 9420",
    "addr:housenumber":"71",
    "addr:postcode":"9420",
    "addr:street":"Zevekootstraat",
    "iso:country":"BE",
    "sg:address":"Zevekootstraat 71",
    "sg:city":"Erpe-mere",
    "sg:orig_category":"Enseignement maternel and primaire",
    "sg:phone":"+32 53 80 82 97",
    "sg:postcode":"9420",
    "sg:province":"Oost-Vlaanderen",
    "wof:name":"Vrije Kleuterschool",
    "wof:placetype":"venue"
},
  "geometry": {"coordinates":[3.9709339142,50.9375724792],"type":"Point"}
}