{
  "type": "Feature",
  "properties": {
    "iso:country":"BE",
    "sg:address":"Avenue Gustave Demeyer 31",
    "sg:city":"Lessines",
    "sg:orig_category":"Mat\u00e9riel m\u00e9dical and orthop\u00e9dique and proth\u00e8ses Fab",
    "sg:phone":"+32 68 33 37 44",
    "sg:postcode":"7860",
    "sg:province":"Hainaut",
    "wof:name":"Mouligneau J.c.",
    "wof:placetype":"venue"
},
  "geometry": {"coordinates":[3.8296449184,50.7054977417],"type":"Point"}
}