{
  "type": "Feature",
  "properties": {
    "addr:full":"Bulskampstraat 126 Veurne West-Vlaanderen 8630",
    "addr:housenumber":"126",
    "addr:postcode":"8630",
    "addr:street":"Bulskampstraat",
    "iso:country":"BE",
    "sg:address":"Bulskampstraat 126",
    "sg:city":"Veurne",
    "sg:classifiers":[
        {
            "category":"Health Services",
            "subcategory":"Health Practitioner",
            "type":"Services"
        }
    ],
    "sg:phone":"+32 58 31 29 22",
    "sg:postcode":"8630",
    "sg:province":"West-Vlaanderen",
    "sg:tags":[
        "physiotherapist"
    ],
    "wof:name":"Titeca Roger",
    "wof:placetype":"venue"
},
  "geometry": {"coordinates":[2.6489899158,51.0528793335],"type":"Point"}
}