{
  "type": "Feature",
  "properties": {
    "addr:full":"Rue De L'ermitage 57 Wavre Brabant Wallon 1300",
    "addr:housenumber":"57;1300",
    "addr:street":"Rue De L'Ermitage",
    "iso:country":"BE",
    "sg:address":"Rue De L'ermitage 57",
    "sg:city":"Wavre",
    "sg:classifiers":[
        {
            "category":"Health Services",
            "subcategory":"Health Practitioner",
            "type":"Services"
        }
    ],
    "sg:phone":"+32 10 22 33 33",
    "sg:postcode":"1300",
    "sg:province":"Brabant Wallon",
    "sg:tags":[
        "physiotherapist"
    ],
    "wof:name":"Leroy C",
    "wof:placetype":"venue"
},
  "geometry": {"coordinates":[4.6027178764,50.7147483826],"type":"Point"}
}