{
  "type": "Feature",
  "properties": {
    "addr:full":"Rue Des Commer\u00c7ants 37 Brussel/bruxelles Bruxelles-Capitale 1000",
    "addr:housenumber":"37",
    "addr:postcode":"1000",
    "addr:street":"Rue Des Commerc\u0327Ants;/",
    "iso:country":"BE",
    "sg:address":"Rue Des Commer\u00c7ants 37",
    "sg:city":"Brussel/bruxelles",
    "sg:orig_category":"Avocats and conseillers juridiques",
    "sg:phone":"+32 2 219 64 67",
    "sg:postcode":"1000",
    "sg:province":"Bruxelles-Capitale",
    "wof:name":"H\u00c9l\u00c8ne Taintenier",
    "wof:placetype":"venue"
},
  "geometry": {"coordinates":[4.3521900177,50.8564872742],"type":"Point"}
}