{
  "type": "Feature",
  "properties": {
    "iso:country":"BE",
    "sg:address":"Dukestraat 13",
    "sg:city":"Mechelen",
    "sg:orig_category":"Groententeelt",
    "sg:phone":"+32 15 61 60 68",
    "sg:postcode":"2811",
    "sg:province":"Antwerpen",
    "wof:name":"Gebrs Smedts Jean & Luc",
    "wof:placetype":"venue"
},
  "geometry": {"coordinates":[4.3932800293,51.0019607544],"type":"Point"}
}