{
  "type": "Feature",
  "properties": {
    "iso:country":"BE",
    "sg:address":"Rue Du Monument 17",
    "sg:city":"Rendeux",
    "sg:orig_category":"Rundveehouders",
    "sg:phone":"+32 84 47 72 85",
    "sg:postcode":"6987",
    "sg:province":"Luxembourg",
    "wof:name":"Clement Dessy",
    "wof:placetype":"venue"
},
  "geometry": {"coordinates":[5.5263972282,50.2029800415],"type":"Point"}
}