{
  "type": "Feature",
  "properties": {
    "iso:country":"BE",
    "sg:address":"Rue De Rabos\u00e9e 123",
    "sg:city":"Li\u00e8ge 1 (wandre)",
    "sg:classifiers":[
        {
            "category":"Health Services",
            "subcategory":"Health Practitioner",
            "type":"Services"
        }
    ],
    "sg:phone":"+32 4 362 98 73",
    "sg:postcode":"4020",
    "sg:province":"Li\u00e8ge",
    "sg:tags":[
        "physiotherapist"
    ],
    "wof:name":"Gillet Marie-pierre",
    "wof:placetype":"venue"
},
  "geometry": {"coordinates":[5.6697230339,50.6646614075],"type":"Point"}
}