{
  "type": "Feature",
  "properties": {
    "addr:full":"Hoogstraatsebaan 57 Malle Antwerpen 2390",
    "addr:housenumber":"57",
    "addr:postcode":"2390",
    "addr:street":"Hoogstraatsebaan",
    "iso:country":"BE",
    "sg:address":"Hoogstraatsebaan 57",
    "sg:city":"Malle",
    "sg:orig_category":"Maroquinerie and articles de voyage. Chaussures",
    "sg:phone":"+32 3 309 12 88",
    "sg:postcode":"2390",
    "sg:province":"Antwerpen",
    "wof:name":"Huis Gomara",
    "wof:placetype":"venue"
},
  "geometry": {"coordinates":[4.7364292145,51.3048324585],"type":"Point"}
}