{
  "type": "Feature",
  "properties": {
    "iso:country":"BE",
    "sg:address":"Place Aim\u00e9 Delhaye 11",
    "sg:city":"Renaix",
    "sg:classifiers":[
        {
            "category":"Retail",
            "subcategory":"Laundry & Dry Cleaning",
            "type":"Services"
        }
    ],
    "sg:phone":"+32 55 21 21 39",
    "sg:postcode":"9600",
    "sg:province":"Oost-Vlaanderen",
    "sg:tags":[
        "dyer",
        "cleaner"
    ],
    "wof:name":"Avac Bvba",
    "wof:placetype":"venue"
},
  "geometry": {"coordinates":[3.5966799259,50.7500686646],"type":"Point"}
}