{
  "type": "Feature",
  "properties": {
    "addr:full":"Peerschat 48 Haacht (wespelaar) Vlaams-Brabant 3150",
    "addr:housenumber":"48",
    "addr:postcode":"3150",
    "addr:street":"Peerschat",
    "iso:country":"BE",
    "sg:address":"Peerschat 48",
    "sg:city":"Haacht (wespelaar)",
    "sg:classifiers":[
        {
            "category":"Retail",
            "subcategory":"Veterinary Services",
            "type":"Services"
        }
    ],
    "sg:phone":"+32 16 60 81 87",
    "sg:postcode":"3150",
    "sg:province":"Vlaams-Brabant",
    "sg:tags":[
        "veterinarian"
    ],
    "wof:name":"De Coster W",
    "wof:placetype":"venue"
},
  "geometry": {"coordinates":[4.6463241577,50.9571495056],"type":"Point"}
}