{
  "type": "Feature",
  "properties": {
    "iso:country":"BE",
    "sg:address":"Boekweitbaan 20",
    "sg:city":"Retie",
    "sg:orig_category":"Chaussures",
    "sg:phone":"+32 14 37 03 22",
    "sg:postcode":"2470",
    "sg:province":"Antwerpen",
    "wof:name":"Huis Dockx",
    "wof:placetype":"venue"
},
  "geometry": {"coordinates":[5.09349823,51.2674179077],"type":"Point"}
}