{
  "type": "Feature",
  "properties": {
    "iso:country":"BE",
    "sg:address":"Grote Markt 44",
    "sg:city":"Sint-niklaas",
    "sg:classifiers":[
        {
            "category":"Manufacturing",
            "subcategory":"Furniture",
            "type":"Manufacturing & Wholesale Goods"
        }
    ],
    "sg:phone":"+32 3 777 98 18",
    "sg:postcode":"9100",
    "sg:province":"Oost-Vlaanderen",
    "sg:tags":[
        "design",
        "-"
    ],
    "wof:name":"Loft",
    "wof:placetype":"venue"
},
  "geometry": {"coordinates":[4.1410779953,51.164894104],"type":"Point"}
}