{
  "type": "Feature",
  "properties": {
    "addr:full":"Rue Aux Fleurs 8 Brussel/bruxelles Bruxelles-Capitale 1000",
    "addr:housenumber":"8",
    "addr:postcode":"1000",
    "addr:street":"Rue Aux Fleurs;/",
    "iso:country":"BE",
    "sg:address":"Rue Aux Fleurs 8",
    "sg:city":"Brussel/bruxelles",
    "sg:classifiers":[
        {
            "category":"Restaurant",
            "type":"Food & Drink"
        }
    ],
    "sg:phone":"+32 2 217 50 93",
    "sg:postcode":"1000",
    "sg:province":"Bruxelles-Capitale",
    "wof:name":"Restaurant L'echalote",
    "wof:placetype":"venue"
},
  "geometry": {"coordinates":[4.3523159027,50.8527526855],"type":"Point"}
}