{
  "type": "Feature",
  "properties": {
    "iso:country":"BE",
    "sg:address":"Dorpsstraat 2a",
    "sg:city":"Gooik",
    "sg:classifiers":[
        {
            "category":"Bakery",
            "type":"Food & Drink"
        }
    ],
    "sg:phone":"+32 2 532 07 24",
    "sg:postcode":"1755",
    "sg:province":"Vlaams-Brabant",
    "sg:tags":[
        "confectioner",
        "baker"
    ],
    "wof:name":"Krokantje",
    "wof:placetype":"venue"
},
  "geometry": {"coordinates":[4.117934227,50.7955627441],"type":"Point"}
}