{
  "type": "Feature",
  "properties": {
    "iso:country":"BE",
    "sg:address":"Krekelberg 15",
    "sg:city":"Stabroek",
    "sg:orig_category":"Eleveurs de bovins",
    "sg:phone":"+32 3 664 22 96",
    "sg:postcode":"2940",
    "sg:province":"Antwerpen",
    "wof:name":"Leo Van Bouwel",
    "wof:placetype":"venue"
},
  "geometry": {"coordinates":[4.3907198906,51.3125686646],"type":"Point"}
}