{
  "type": "Feature",
  "properties": {
    "iso:country":"BE",
    "sg:address":"Reyderstraat 15",
    "sg:city":"Hasselt",
    "sg:classifiers":[
        {
            "category":"Insurance",
            "subcategory":"Insurance Agent",
            "type":"Services"
        }
    ],
    "sg:phone":"+32 11 22 86 02",
    "sg:postcode":"3511",
    "sg:province":"Limburg",
    "sg:tags":[
        "verzekeringsmakelaars",
        "expert"
    ],
    "wof:name":"W. Motmans",
    "wof:placetype":"venue"
},
  "geometry": {"coordinates":[5.3034238815,50.9432487488],"type":"Point"}
}