{
  "type": "Feature",
  "properties": {
    "iso:country":"BE",
    "sg:address":"Beverlo Dorp 16",
    "sg:city":"Beringen (beverlo)",
    "sg:classifiers":[
        {
            "category":"Retail",
            "subcategory":"Repair Shop",
            "type":"Services"
        }
    ],
    "sg:phone":"+32 11 34 10 21",
    "sg:postcode":"3581",
    "sg:province":"Limburg",
    "sg:tags":[
        "-",
        "clothing",
        "alteration"
    ],
    "wof:name":"De Posthoorn",
    "wof:placetype":"venue"
},
  "geometry": {"coordinates":[5.221683979,51.0878677368],"type":"Point"}
}