{
  "type": "Feature",
  "properties": {
    "iso:country":"BE",
    "sg:address":"Keizerdellestraat 30",
    "sg:city":"Kortenberg",
    "sg:orig_category":"Instellingen voor probleemkinderen Kindertehuizen",
    "sg:phone":"+32 2 757 61 70",
    "sg:postcode":"3071",
    "sg:province":"Vlaams-Brabant",
    "wof:name":"Cidar",
    "wof:placetype":"venue"
},
  "geometry": {"coordinates":[4.5448279381,50.9069976807],"type":"Point"}
}