{
  "type": "Feature",
  "properties": {
    "iso:country":"BE",
    "sg:address":"Holt 17",
    "sg:city":"Bilzen",
    "sg:orig_category":"Fleurs and plantes",
    "sg:phone":"+32 89 41 14 33",
    "sg:postcode":"3740",
    "sg:province":"Limburg",
    "wof:name":"Roebben Appermont",
    "wof:placetype":"venue"
},
  "geometry": {"coordinates":[5.4852089882,50.8845367432],"type":"Point"}
}