{
  "type": "Feature",
  "properties": {
    "iso:country":"BE",
    "sg:address":"Leurestraat 36",
    "sg:city":"Hoeselt",
    "sg:classifiers":[
        {
            "category":"Cafe",
            "type":"Food & Drink"
        }
    ],
    "sg:phone":"+32 12 23 03 69",
    "sg:postcode":"3730",
    "sg:province":"Limburg",
    "sg:tags":[
        "caf\u00e9s"
    ],
    "wof:name":"Marie Voets",
    "wof:placetype":"venue"
},
  "geometry": {"coordinates":[5.4450101852,50.8320159912],"type":"Point"}
}