{
  "type": "Feature",
  "properties": {
    "iso:country":"BE",
    "sg:address":"Moorselbaan 560",
    "sg:city":"Aalst",
    "sg:orig_category":"Avocats and conseillers juridiques",
    "sg:phone":"+32 53 21 24 71",
    "sg:postcode":"9300",
    "sg:province":"Oost-Vlaanderen",
    "wof:name":"Anique No\u00cbl",
    "wof:placetype":"venue"
},
  "geometry": {"coordinates":[4.0812110901,50.9454574585],"type":"Point"}
}