{
  "type": "Feature",
  "properties": {
    "addr:full":"Globelaan 47bb.41 Vorst/forest Bruxelles-Capitale 1190",
    "addr:housenumber":"47bb.41",
    "addr:postcode":"1190",
    "addr:street":"Globelaan;/ Forest",
    "iso:country":"BE",
    "sg:address":"Globelaan 47bb.41",
    "sg:city":"Vorst/forest",
    "sg:orig_category":"Beheer onroerend goed",
    "sg:phone":"+32 2 345 12 16",
    "sg:postcode":"1190",
    "sg:province":"Bruxelles-Capitale",
    "wof:name":"Emile Renson",
    "wof:placetype":"venue"
},
  "geometry": {"coordinates":[4.3255581856,50.8082771301],"type":"Point"}
}