{
  "type": "Feature",
  "properties": {
    "addr:full":"Bergstraat 115 Moeskroen/mouscron Hainaut 7700",
    "addr:housenumber":"115",
    "addr:postcode":"7700",
    "addr:street":"Bergstraat",
    "iso:country":"BE",
    "sg:address":"Bergstraat 115",
    "sg:city":"Moeskroen/mouscron",
    "sg:orig_category":"Afval and schroot Gh",
    "sg:phone":"+32 56 34 49 55",
    "sg:postcode":"7700",
    "sg:province":"Hainaut",
    "wof:name":"Sefitex",
    "wof:placetype":"venue"
},
  "geometry": {"coordinates":[3.231580019,50.737159729],"type":"Point"}
}