{
  "type": "Feature",
  "properties": {
    "iso:country":"BE",
    "sg:address":"Avenue De Broqueville 242b5",
    "sg:city":"Sint-lambrechts-woluwe/woluwe-saint-lambert",
    "sg:orig_category":"Avocats and conseillers juridiques",
    "sg:phone":"+32 2 762 58 22",
    "sg:postcode":"1200",
    "sg:province":"Bruxelles-Capitale",
    "wof:name":"Michel De Radigu\u00c8s",
    "wof:placetype":"venue"
},
  "geometry": {"coordinates":[4.4202637672,50.8424339294],"type":"Point"}
}