{
  "type": "Feature",
  "properties": {
    "iso:country":"BE",
    "sg:address":"Rue Jules Lejeune 70",
    "sg:city":"Ukkel/uccle",
    "sg:orig_category":"M\u00e9decins and sp\u00e9cialistes",
    "sg:phone":"+32 2 345 51 52",
    "sg:postcode":"1180",
    "sg:province":"Bruxelles-Capitale",
    "wof:name":"Marianne Dramaix",
    "wof:placetype":"venue"
},
  "geometry": {"coordinates":[4.361178875,50.8160247803],"type":"Point"}
}