{
  "type": "Feature",
  "properties": {
    "iso:country":"BE",
    "sg:address":"Rue De Champles 3",
    "sg:city":"Wavre (bierges)",
    "sg:classifiers":[
        {
            "category":"Personal",
            "subcategory":"Beauty Salon",
            "type":"Services"
        }
    ],
    "sg:phone":"+32 10 41 60 56",
    "sg:postcode":"1301",
    "sg:province":"Brabant Wallon",
    "sg:tags":[
        "lady",
        "-",
        "hairdressing"
    ],
    "wof:name":"Boucles D'or (les)",
    "wof:placetype":"venue"
},
  "geometry": {"coordinates":[4.5783810616,50.7173614502],"type":"Point"}
}