{
  "type": "Feature",
  "properties": {
    "addr:full":"Ren\u00c9 Verbeecklaan 5 Hove Antwerpen 2540",
    "addr:housenumber":"5",
    "addr:postcode":"2540",
    "addr:street":"Rene\u0301 Verbeecklaan",
    "iso:country":"BE",
    "sg:address":"Ren\u00c9 Verbeecklaan 5",
    "sg:city":"Hove",
    "sg:orig_category":"Rusthuizen and serviceflats",
    "sg:phone":"+32 3 454 02 08",
    "sg:postcode":"2540",
    "sg:province":"Antwerpen",
    "wof:name":"Cantershof",
    "wof:placetype":"venue"
},
  "geometry": {"coordinates":[4.4784197807,51.1545066833],"type":"Point"}
}