{
  "type": "Feature",
  "properties": {
    "addr:full":"Rue De Cond\u00e9 67 Leuze-en-hainaut Hainaut 7900",
    "addr:housenumber":"67",
    "addr:postcode":"7900",
    "addr:street":"Rue De Conde\u0301",
    "iso:country":"BE",
    "sg:address":"Rue De Cond\u00e9 67",
    "sg:city":"Leuze-en-hainaut",
    "sg:classifiers":[
        {
            "category":"Health Services",
            "subcategory":"Health Practitioner",
            "type":"Services"
        }
    ],
    "sg:phone":"+32 69 66 12 68",
    "sg:postcode":"7900",
    "sg:province":"Hainaut",
    "sg:tags":[
        "physiotherapist"
    ],
    "wof:name":"Deffrenne R",
    "wof:placetype":"venue"
},
  "geometry": {"coordinates":[3.6173529625,50.5951690674],"type":"Point"}
}