{
  "type": "Feature",
  "properties": {
    "addr:full":"Vrijheidslaan 28 Koekelberg Bruxelles-Capitale 1081",
    "addr:housenumber":"28",
    "addr:postcode":"1081",
    "addr:street":"Vrijheidslaan",
    "iso:country":"BE",
    "sg:address":"Vrijheidslaan 28",
    "sg:city":"Koekelberg",
    "sg:orig_category":"Diverse bedrijfsbeheeradviesbureaus",
    "sg:phone":"+32 2 411 82 95",
    "sg:postcode":"1081",
    "sg:province":"Bruxelles-Capitale",
    "wof:name":"Antelion",
    "wof:placetype":"venue"
},
  "geometry": {"coordinates":[4.3245301247,50.8625946045],"type":"Point"}
}