{
  "type": "Feature",
  "properties": {
    "iso:country":"BE",
    "sg:address":"Rue Ferrer 20",
    "sg:city":"Frameries",
    "sg:orig_category":"Pain, p\u00e2tisseries and confiseries",
    "sg:phone":"+32 65 67 25 63",
    "sg:postcode":"7080",
    "sg:province":"Hainaut",
    "wof:name":"Au Merveilleux",
    "wof:placetype":"venue"
},
  "geometry": {"coordinates":[3.8968451023,50.4056587219],"type":"Point"}
}