{
  "type": "Feature",
  "properties": {
    "addr:full":"Hoogledestraat 92 Kortemark West-Vlaanderen 8610",
    "addr:housenumber":"92",
    "addr:postcode":"8610",
    "addr:street":"Hoogledestraat",
    "iso:country":"BE",
    "sg:address":"Hoogledestraat 92",
    "sg:city":"Kortemark",
    "sg:orig_category":"Transports routiers de marchandises",
    "sg:phone":"+32 51 57 57 00",
    "sg:postcode":"8610",
    "sg:province":"West-Vlaanderen",
    "wof:name":"Deva - Kort",
    "wof:placetype":"venue"
},
  "geometry": {"coordinates":[3.0463769436,51.0180397034],"type":"Point"}
}