{
  "type": "Feature",
  "properties": {
    "addr:full":"Chauss\u00c9e De Tongres 106 Juprelle Li\u00e8ge 4451",
    "addr:housenumber":"106",
    "addr:postcode":"4451",
    "addr:street":"Chausse\u0301E De Tongres",
    "iso:country":"BE",
    "sg:address":"Chauss\u00c9e De Tongres 106",
    "sg:city":"Juprelle",
    "sg:orig_category":"V\u00e9t\u00e9rinaires",
    "sg:phone":"+32 4 263 64 65",
    "sg:postcode":"4451",
    "sg:province":"Li\u00e8ge",
    "wof:name":"Alex Roppe",
    "wof:placetype":"venue"
},
  "geometry": {"coordinates":[5.5363140106,50.6912231445],"type":"Point"}
}