{
  "type": "Feature",
  "properties": {
    "addr:full":"Rond-point Du Meir 4 Bruxelles (anderlecht) Bruxelles-Capitale 1070",
    "addr:housenumber":"4",
    "addr:postcode":"1070",
    "addr:street":"Rond-Point Du Meir",
    "iso:country":"BE",
    "sg:address":"Rond-point Du Meir 4",
    "sg:city":"Bruxelles (anderlecht)",
    "sg:classifiers":[
        {
            "category":"Bars & Pubs",
            "type":"Food & Drink"
        }
    ],
    "sg:phone":"+32 2 522 00 90",
    "sg:postcode":"1070",
    "sg:province":"Bruxelles-Capitale",
    "sg:tags":[
        "tavern"
    ],
    "wof:name":"Apostrophe (l')",
    "wof:placetype":"venue"
},
  "geometry": {"coordinates":[4.3018717766,50.8322563171],"type":"Point"}
}