{
  "type": "Feature",
  "properties": {
    "iso:country":"BE",
    "sg:address":"Rue De La Halle 9",
    "sg:city":"Mons",
    "sg:orig_category":"Diverse grafische activiteiten",
    "sg:phone":"+32 65 31 91 19",
    "sg:postcode":"7000",
    "sg:province":"Hainaut",
    "wof:name":"Yves Amateis",
    "wof:placetype":"venue"
},
  "geometry": {"coordinates":[3.9542570114,50.4517745972],"type":"Point"}
}