{
  "type": "Feature",
  "properties": {
    "iso:country":"BE",
    "sg:address":"Molenstraat 76",
    "sg:city":"Aalst",
    "sg:orig_category":"D\u00e9molition d\u00b4immeubles and terrassements",
    "sg:phone":"+32 53 66 12 55",
    "sg:postcode":"9310",
    "sg:province":"Oost-Vlaanderen",
    "wof:name":"Mergan",
    "wof:placetype":"venue"
},
  "geometry": {"coordinates":[4.0427951813,50.9398956299],"type":"Point"}
}