{
  "type": "Feature",
  "properties": {
    "iso:country":"BE",
    "sg:address":"Rue Du Petit-rumes 22",
    "sg:city":"Rumes",
    "sg:orig_category":"Travaux de pl\u00e2trage",
    "sg:phone":"+32 69 64 81 57",
    "sg:postcode":"7618",
    "sg:province":"Hainaut",
    "wof:name":"Pascal Foucart",
    "wof:placetype":"venue"
},
  "geometry": {"coordinates":[3.3383951187,50.539604187],"type":"Point"}
}