{
  "type": "Feature",
  "properties": {
    "addr:full":"J. De Windestraat 40 Dilbeek Vlaams-Brabant 1700",
    "addr:housenumber":"40",
    "addr:postcode":"1700",
    "addr:street":"J. De Windestraat",
    "iso:country":"BE",
    "sg:address":"J. De Windestraat 40",
    "sg:city":"Dilbeek",
    "sg:classifiers":[
        {
            "category":"Professional",
            "subcategory":"Accounting & Tax Preparation",
            "type":"Services"
        }
    ],
    "sg:phone":"+32 2 466 69 68",
    "sg:postcode":"1700",
    "sg:province":"Vlaams-Brabant",
    "sg:tags":[
        "bookkeeper"
    ],
    "wof:name":"Leroy H",
    "wof:placetype":"venue"
},
  "geometry": {"coordinates":[4.2636260986,50.8547172546],"type":"Point"}
}