{
  "type": "Feature",
  "properties": {
    "iso:country":"BE",
    "sg:address":"Rue De Vaals 36",
    "sg:city":"Plombieres/plombieres",
    "sg:orig_category":"M\u00e9decins and sp\u00e9cialistes",
    "sg:phone":"+32 87 78 55 58",
    "sg:postcode":"4851",
    "sg:province":"Li\u00e8ge",
    "wof:name":"Toussaint Tychon",
    "wof:placetype":"venue"
},
  "geometry": {"coordinates":[5.9978947639,50.74659729],"type":"Point"}
}