{
  "type": "Feature",
  "properties": {
    "iso:country":"BE",
    "sg:address":"Rue Du Pont Brul\u00c9 5",
    "sg:city":"Aat",
    "sg:orig_category":"Agences d'exp\u00e9dition",
    "sg:phone":"+32 69 68 88 55",
    "sg:postcode":"7802",
    "sg:province":"Hainaut",
    "wof:name":"Isabelles & Hugues",
    "wof:placetype":"venue"
},
  "geometry": {"coordinates":[3.712184906,50.5841598511],"type":"Point"}
}