{
  "type": "Feature",
  "properties": {
    "iso:country":"BE",
    "sg:address":"Dorpsstraat 81",
    "sg:city":"Oud-heverlee",
    "sg:orig_category":"Overheidsdiensten",
    "sg:phone":"+32 16 47 70 22",
    "sg:postcode":"3050",
    "sg:province":"Vlaams-Brabant",
    "wof:name":"O.c.m.w.",
    "wof:placetype":"venue"
},
  "geometry": {"coordinates":[4.6622071266,50.8346252441],"type":"Point"}
}