{
  "type": "Feature",
  "properties": {
    "addr:full":"Gasstraat 14 Antwerpen Antwerpen 2060",
    "addr:housenumber":"14",
    "addr:postcode":"2060",
    "addr:street":"Gasstraat",
    "iso:country":"BE",
    "sg:address":"Gasstraat 14",
    "sg:city":"Antwerpen",
    "sg:classifiers":[
        {
            "category":"Social Services",
            "type":"Services"
        }
    ],
    "sg:phone":"+32 3 231 94 51",
    "sg:postcode":"2060",
    "sg:province":"Antwerpen",
    "wof:name":"Buurtwerk Seefhoek",
    "wof:placetype":"venue"
},
  "geometry": {"coordinates":[4.4249072075,51.2267494202],"type":"Point"}
}