{
  "type": "Feature",
  "properties": {
    "iso:country":"BE",
    "sg:address":"Fr. Dottermansstraat 36b13",
    "sg:city":"Bertem",
    "sg:classifiers":[
        {
            "category":"Arena",
            "subcategory":"Sports Club",
            "type":"Entertainment"
        }
    ],
    "sg:phone":"+32 16 48 14 16",
    "sg:postcode":"3060",
    "sg:province":"Vlaams-Brabant",
    "sg:tags":[
        "de"
    ],
    "wof:name":"V.c. Smash Bertem",
    "wof:placetype":"venue"
},
  "geometry": {"coordinates":[4.6290898323,50.8648262024],"type":"Point"}
}