{
  "type": "Feature",
  "properties": {
    "iso:country":"BE",
    "sg:address":"R\u00e9sidence Du Pachy 53",
    "sg:city":"Morlanwelz (morlanwelz-mariemont)",
    "sg:classifiers":[
        {
            "category":"Health Services",
            "subcategory":"Nursing And Care Facility",
            "type":"Services"
        }
    ],
    "sg:phone":"+32 64 45 14 59",
    "sg:postcode":"7140",
    "sg:province":"Hainaut",
    "sg:tags":[
        "home"
    ],
    "wof:name":"Infirmiere Rmw Sprl",
    "wof:placetype":"venue"
},
  "geometry": {"coordinates":[4.2658390999,50.4704704285],"type":"Point"}
}