{
  "type": "Feature",
  "properties": {
    "addr:full":"Abelestationsstraat 34 Poperinge West-Vlaanderen 8970",
    "addr:housenumber":"34",
    "addr:postcode":"8970",
    "addr:street":"Abelestationsstraat",
    "iso:country":"BE",
    "sg:address":"Abelestationsstraat 34",
    "sg:city":"Poperinge",
    "sg:orig_category":"Sport- and kampeermateriaal Tuinbenodigdheden",
    "sg:phone":"+32 57 33 62 49",
    "sg:postcode":"8970",
    "sg:province":"West-Vlaanderen",
    "wof:name":"Huis Abeelestatie",
    "wof:placetype":"venue"
},
  "geometry": {"coordinates":[2.6795499325,50.8166618347],"type":"Point"}
}