{
  "type": "Feature",
  "properties": {
    "iso:country":"BE",
    "sg:address":"Gebr.van Raemdonckstraat 28",
    "sg:city":"Roeselare",
    "sg:classifiers":[
        {
            "category":"Insurance",
            "subcategory":"Insurance Agent",
            "type":"Services"
        }
    ],
    "sg:phone":"+32 51 21 01 57",
    "sg:postcode":"8800",
    "sg:province":"West-Vlaanderen",
    "sg:tags":[
        "verzekeringsmakelaars",
        "expert"
    ],
    "wof:name":"Verzek. Berteloot Myriam",
    "wof:placetype":"venue"
},
  "geometry": {"coordinates":[3.1661739349,50.9282226562],"type":"Point"}
}