{
  "type": "Feature",
  "properties": {
    "iso:country":"BE",
    "sg:address":"Kerkstraat 32-1",
    "sg:city":"Kasterlee (tielen)",
    "sg:classifiers":[
        {
            "category":"Banks & Credit Unions",
            "subcategory":"Bank",
            "type":"Services"
        }
    ],
    "sg:phone":"+32 14 55 63 53",
    "sg:postcode":"2460",
    "sg:province":"Antwerpen",
    "sg:tags":[
        "savings-banks"
    ],
    "wof:name":"Herremans C",
    "wof:placetype":"venue"
},
  "geometry": {"coordinates":[4.9000267982,51.2428016663],"type":"Point"}
}