{
  "type": "Feature",
  "properties": {
    "addr:full":"Wetterensteenweg 86 Wetteren Oost-Vlaanderen 9230",
    "addr:housenumber":"86",
    "addr:postcode":"9230",
    "addr:street":"Wetterensteenweg",
    "iso:country":"BE",
    "sg:address":"Wetterensteenweg 86",
    "sg:city":"Wetteren",
    "sg:orig_category":"Pr\u00eats hypoth\u00e9caires and cr\u00e9dits immobiliers. Cr\u00e9dit \u00e0 la consommation",
    "sg:phone":"+32 9 368 22 55",
    "sg:postcode":"9230",
    "sg:province":"Oost-Vlaanderen",
    "wof:name":"Vlaams Leenkantoor",
    "wof:placetype":"venue"
},
  "geometry": {"coordinates":[3.8313260078,50.9748001099],"type":"Point"}
}