{
  "type": "Feature",
  "properties": {
    "addr:full":"Rue Paul Janson 270a Gr\u00e2ce-hollogne (gr\u00e2ce-berleur) Li\u00e8ge 4460",
    "addr:housenumber":"270a",
    "addr:postcode":"4460",
    "addr:street":"Rue Paul Janson;Gra\u0302Ce-Berleur",
    "iso:country":"BE",
    "sg:address":"Rue Paul Janson 270a",
    "sg:city":"Gr\u00e2ce-hollogne (gr\u00e2ce-berleur)",
    "sg:classifiers":[
        {
            "category":"Building & Trades",
            "subcategory":"Landscaping Services",
            "type":"Services"
        }
    ],
    "sg:postcode":"4460",
    "sg:province":"Li\u00e8ge",
    "sg:tags":[
        "access",
        "pond",
        "laying-out",
        "-"
    ],
    "wof:name":"Joel Van Brabant",
    "wof:placetype":"venue"
},
  "geometry": {"coordinates":[5.4993991852,50.6248092651],"type":"Point"}
}