{
  "type": "Feature",
  "properties": {
    "addr:full":"Kruisstraat 5 Aalter Oost-Vlaanderen 9880",
    "addr:housenumber":"5",
    "addr:postcode":"9880",
    "addr:street":"Kruisstraat",
    "iso:country":"BE",
    "sg:address":"Kruisstraat 5",
    "sg:city":"Aalter",
    "sg:orig_category":"Medische apparatuur, orthopedische artikelen and prothesen Fab",
    "sg:phone":"+32 9 374 59 04",
    "sg:postcode":"9880",
    "sg:province":"Oost-Vlaanderen",
    "wof:name":"Willy Naert",
    "wof:placetype":"venue"
},
  "geometry": {"coordinates":[3.4398200512,51.0849227905],"type":"Point"}
}