{
  "type": "Feature",
  "properties": {
    "iso:country":"BE",
    "sg:address":"Rue De Spa 11",
    "sg:city":"Li\u00e8ge 1 (li\u00e8ge 2)",
    "sg:classifiers":[
        {
            "category":"Health Services",
            "subcategory":"Doctor",
            "type":"Services"
        }
    ],
    "sg:phone":"+32 4 229 51 75",
    "sg:postcode":"4020",
    "sg:province":"Li\u00e8ge",
    "sg:tags":[
        "medicinephysicians",
        "surgeon"
    ],
    "wof:name":"Goyers Jean-fran\u00e7ois",
    "wof:placetype":"venue"
},
  "geometry": {"coordinates":[5.5883550644,50.6229896545],"type":"Point"}
}