{
  "type": "Feature",
  "properties": {
    "iso:country":"BE",
    "sg:address":"Maalsesteenweg 356",
    "sg:city":"Brugge",
    "sg:classifiers":[
        {
            "category":"Fast Food",
            "type":"Food & Drink"
        }
    ],
    "sg:phone":"+32 50 35 99 89",
    "sg:postcode":"8310",
    "sg:province":"West-Vlaanderen",
    "sg:tags":[
        "meeneem",
        "restaurant"
    ],
    "wof:name":"Quick",
    "wof:placetype":"venue"
},
  "geometry": {"coordinates":[3.2666099072,51.2079315186],"type":"Point"}
}