{
  "type": "Feature",
  "properties": {
    "iso:country":"BE",
    "sg:address":"Au Long Pr\u00e9 124",
    "sg:city":"Chaudfontaine (embourg)",
    "sg:classifiers":[
        {
            "category":"Building & Trades",
            "subcategory":"Cleaning & Sanitation",
            "type":"Services"
        }
    ],
    "sg:phone":"+32 4 367 60 96",
    "sg:postcode":"4053",
    "sg:province":"Li\u00e8ge",
    "sg:tags":[
        "janitor"
    ],
    "wof:name":"Revica Sprl",
    "wof:placetype":"venue"
},
  "geometry": {"coordinates":[5.6244320869,50.5943565369],"type":"Point"}
}