{
  "type": "Feature",
  "properties": {
    "addr:full":"Maalderijstraat 18 Willebroek Antwerpen 2830",
    "addr:housenumber":"18",
    "addr:postcode":"2830",
    "addr:street":"Maalderijstraat",
    "iso:country":"BE",
    "sg:address":"Maalderijstraat 18",
    "sg:city":"Willebroek",
    "sg:classifiers":[
        {
            "category":"Professional",
            "subcategory":"Art Services",
            "type":"Services"
        }
    ],
    "sg:phone":"+32 3 886 94 92",
    "sg:postcode":"2830",
    "sg:province":"Antwerpen",
    "sg:tags":[
        "graphic",
        "designer"
    ],
    "wof:name":"Caluwaerts K",
    "wof:placetype":"venue"
},
  "geometry": {"coordinates":[4.366517067,51.0542869568],"type":"Point"}
}