{
  "type": "Feature",
  "properties": {
    "addr:full":"Gaarveldstraat 134 Hasselt Limburg 3500",
    "addr:housenumber":"134",
    "addr:postcode":"3500",
    "addr:street":"Gaarveldstraat",
    "iso:country":"BE",
    "sg:address":"Gaarveldstraat 134",
    "sg:city":"Hasselt",
    "sg:orig_category":"Instituts de beaut\u00e9",
    "sg:phone":"+32 11 27 39 84",
    "sg:postcode":"3500",
    "sg:province":"Limburg",
    "wof:name":"Schoonheidsinstituut Wendy Gielen",
    "wof:placetype":"venue"
},
  "geometry": {"coordinates":[5.3250689507,50.9258155823],"type":"Point"}
}