{
  "type": "Feature",
  "properties": {
    "addr:full":"Zuidlaan 36 Zwalm Oost-Vlaanderen 9630",
    "addr:housenumber":"36",
    "addr:postcode":"9630",
    "addr:street":"Zuidlaan;Oost-Vlaanderen",
    "iso:country":"BE",
    "sg:address":"Zuidlaan 36",
    "sg:city":"Zwalm",
    "sg:orig_category":"Overheidsdiensten",
    "sg:phone":"+32 55 49 91 91",
    "sg:postcode":"9630",
    "sg:province":"Oost-Vlaanderen",
    "wof:name":"Gemeentebestuur",
    "wof:placetype":"venue"
},
  "geometry": {"coordinates":[3.7328660488,50.8777236938],"type":"Point"}
}