{
  "type": "Feature",
  "properties": {
    "iso:country":"BE",
    "sg:address":"Potterijstraat 18",
    "sg:city":"Tienen",
    "sg:classifiers":[
        {
            "category":"Professional",
            "subcategory":"Testing Lab",
            "type":"Services"
        }
    ],
    "sg:phone":"+32 16 81 21 79",
    "sg:postcode":"3300",
    "sg:province":"Vlaams-Brabant",
    "sg:tags":[
        "chemist"
    ],
    "wof:name":"Gilis-segers Bvba",
    "wof:placetype":"venue"
},
  "geometry": {"coordinates":[4.9395389557,50.8009986877],"type":"Point"}
}