{
  "type": "Feature",
  "properties": {
    "iso:country":"BE",
    "sg:address":"Quai Des Carmes 82-84",
    "sg:city":"Seraing (jemeppe-sur-meuse)",
    "sg:classifiers":[
        {
            "category":"Parking",
            "subcategory":"Garage",
            "type":"Transportation"
        }
    ],
    "sg:phone":"+32 4 233 73 75",
    "sg:postcode":"4101",
    "sg:province":"Li\u00e8ge",
    "sg:tags":[
        "prefabricated",
        "-"
    ],
    "wof:name":"Dantinne",
    "wof:placetype":"venue"
},
  "geometry": {"coordinates":[5.5184049606,50.6188697815],"type":"Point"}
}