{
  "type": "Feature",
  "properties": {
    "iso:country":"BE",
    "sg:address":"Rode Dreef 49",
    "sg:city":"Schilde",
    "sg:orig_category":"Agences d'exp\u00e9dition",
    "sg:phone":"+32 3 354 31 86",
    "sg:postcode":"2970",
    "sg:province":"Antwerpen",
    "wof:name":"Nykei",
    "wof:placetype":"venue"
},
  "geometry": {"coordinates":[4.5504140854,51.2246818542],"type":"Point"}
}