{
  "type": "Feature",
  "properties": {
    "iso:country":"BE",
    "sg:address":"Prins Van Luiklaan 79",
    "sg:city":"Anderlecht",
    "sg:orig_category":"Kapsalons",
    "sg:phone":"+32 2 522 47 42",
    "sg:postcode":"1070",
    "sg:province":"Bruxelles-Capitale",
    "wof:name":"Maricaux",
    "wof:placetype":"venue"
},
  "geometry": {"coordinates":[4.3036708832,50.8411483765],"type":"Point"}
}