{
  "type": "Feature",
  "properties": {
    "iso:country":"BE",
    "sg:address":"Rue Alphonse Thomas 15",
    "sg:city":"Berloz",
    "sg:orig_category":"Services fun\u00e9raires",
    "sg:phone":"+32 19 32 46 72",
    "sg:postcode":"4257",
    "sg:province":"Li\u00e8ge",
    "wof:name":"Jeannine Vaneetveld",
    "wof:placetype":"venue"
},
  "geometry": {"coordinates":[5.2101659775,50.7092170715],"type":"Point"}
}