{
  "type": "Feature",
  "properties": {
    "addr:full":"Rue Emile Vandervelde 53 Charleroi Hainaut 6000",
    "addr:housenumber":"53",
    "addr:postcode":"6000",
    "addr:street":"Rue Emile Vandervelde;Hainaut",
    "iso:country":"BE",
    "sg:address":"Rue Emile Vandervelde 53",
    "sg:city":"Charleroi",
    "sg:classifiers":[
        {
            "category":"Health Services",
            "subcategory":"Health Practitioner",
            "type":"Services"
        }
    ],
    "sg:phone":"+32 71 48 96 58",
    "sg:postcode":"6000",
    "sg:province":"Hainaut",
    "sg:tags":[
        "physiotherapist"
    ],
    "wof:name":"Andr\u00e9 Jacqueline",
    "wof:placetype":"venue"
},
  "geometry": {"coordinates":[4.4543848038,50.4221878052],"type":"Point"}
}