{
  "type": "Feature",
  "properties": {
    "addr:full":"Avenue Emile Digneffe 26 Li\u00e8ge 1 Li\u00e8ge 4000",
    "addr:housenumber":"26;1",
    "addr:postcode":"4000",
    "addr:street":"Avenue Emile Digneffe",
    "iso:country":"BE",
    "sg:address":"Avenue Emile Digneffe 26",
    "sg:city":"Li\u00e8ge 1",
    "sg:classifiers":[
        {
            "category":"Home & Garden",
            "subcategory":"Household Appliances",
            "type":"Retail Goods"
        }
    ],
    "sg:phone":"+32 4 252 71 73",
    "sg:postcode":"4000",
    "sg:province":"Li\u00e8ge",
    "sg:tags":[
        "repair",
        "mainten",
        "-",
        "electric"
    ],
    "wof:name":"Abel Falisse Nv Etn",
    "wof:placetype":"venue"
},
  "geometry": {"coordinates":[5.575594902,50.6199989319],"type":"Point"}
}