{
  "type": "Feature",
  "properties": {
    "addr:full":"Heieindestraat 8 Hulshout Antwerpen 2235",
    "addr:housenumber":"8",
    "addr:postcode":"2235",
    "addr:street":"Heieindestraat",
    "iso:country":"BE",
    "sg:address":"Heieindestraat 8",
    "sg:city":"Hulshout",
    "sg:orig_category":"R\u00e9parations de chaussures and articles en cuir",
    "sg:phone":"+32 16 68 02 35",
    "sg:postcode":"2235",
    "sg:province":"Antwerpen",
    "wof:name":"Schoenmakerij Phil",
    "wof:placetype":"venue"
},
  "geometry": {"coordinates":[4.8438367844,51.0587272644],"type":"Point"}
}