{
  "type": "Feature",
  "properties": {
    "iso:country":"BE",
    "sg:address":"Chauss\u00e9e De Li\u00e8ge 5",
    "sg:city":"Anthisnes",
    "sg:classifiers":[
        {
            "category":"Government",
            "subcategory":"Post Office",
            "type":"Public Place"
        }
    ],
    "sg:phone":"+32 4 342 93 71",
    "sg:postcode":"4160",
    "sg:province":"Li\u00e8ge",
    "sg:tags":[
        "picture",
        "restoring"
    ],
    "wof:name":"Drigo M",
    "wof:placetype":"venue"
},
  "geometry": {"coordinates":[5.5198369026,50.485206604],"type":"Point"}
}