{
  "type": "Feature",
  "properties": {
    "addr:full":"Rue Fosse-saint-jean 12 Komen-waasten/comines-warneton Hainaut 7780",
    "addr:housenumber":"12;7780",
    "addr:street":"Rue Fosse-Saint-Jean",
    "iso:country":"BE",
    "sg:address":"Rue Fosse-saint-jean 12",
    "sg:city":"Komen-waasten/comines-warneton",
    "sg:classifiers":[
        {
            "category":"Personal",
            "subcategory":"Beauty Salon",
            "type":"Services"
        }
    ],
    "sg:phone":"+32 56 55 59 62",
    "sg:postcode":"7780",
    "sg:province":"Hainaut",
    "sg:tags":[
        "de",
        "coiffure"
    ],
    "wof:name":"Marie-benedicte Duthoo",
    "wof:placetype":"venue"
},
  "geometry": {"coordinates":[2.9927148819,50.780254364],"type":"Point"}
}