{
  "type": "Feature",
  "properties": {
    "iso:country":"BE",
    "sg:address":"Itegemseweg 35a",
    "sg:city":"Heist-op-den-berg (wiekevorst)",
    "sg:classifiers":[
        {
            "category":"Health Services",
            "subcategory":"Health Practitioner",
            "type":"Services"
        }
    ],
    "sg:phone":"+32 14 26 03 79",
    "sg:postcode":"2222",
    "sg:province":"Antwerpen",
    "sg:tags":[
        "physiotherapist"
    ],
    "wof:name":"Moens H",
    "wof:placetype":"venue"
},
  "geometry": {"coordinates":[4.7292399406,51.1032218933],"type":"Point"}
}