{
  "type": "Feature",
  "properties": {
    "addr:full":"Speelbroek 2 Grimbergen Vlaams-Brabant 1850",
    "addr:housenumber":"2",
    "addr:postcode":"1850",
    "addr:street":"Speelbroek",
    "iso:country":"BE",
    "sg:address":"Speelbroek 2",
    "sg:city":"Grimbergen",
    "sg:orig_category":"Banken and kredietinstellingen",
    "sg:phone":"+32 2 270 39 60",
    "sg:postcode":"1850",
    "sg:province":"Vlaams-Brabant",
    "wof:name":"Landbouwkrediet",
    "wof:placetype":"venue"
},
  "geometry": {"coordinates":[4.3735499382,50.9330101013],"type":"Point"}
}