{
  "type": "Feature",
  "properties": {
    "iso:country":"BE",
    "sg:address":"Chauss\u00c9e De Givet 39",
    "sg:city":"Couvin",
    "sg:orig_category":"M\u00e9decins and sp\u00e9cialistes",
    "sg:phone":"+32 60 31 12 79",
    "sg:postcode":"5660",
    "sg:province":"Namur",
    "wof:name":"J. Theis",
    "wof:placetype":"venue"
},
  "geometry": {"coordinates":[4.5274701118,50.0922813416],"type":"Point"}
}