{
  "type": "Feature",
  "properties": {
    "iso:country":"BE",
    "sg:address":"Rue Octave Philippot 52",
    "sg:city":"Marchin",
    "sg:classifiers":[
        {
            "category":"Fast Food",
            "type":"Food & Drink"
        }
    ],
    "sg:phone":"+32 85 25 22 25",
    "sg:postcode":"4570",
    "sg:province":"Li\u00e8ge",
    "sg:tags":[
        "fried",
        "stand",
        "potato"
    ],
    "wof:name":"Friterie & Snack Bel-air",
    "wof:placetype":"venue"
},
  "geometry": {"coordinates":[5.2264127731,50.4905929565],"type":"Point"}
}