{
  "type": "Feature",
  "properties": {
    "addr:full":"Rue Du Cimeti\u00e8re 5 Donceel (jeneffe) Li\u00e8ge 4357",
    "addr:housenumber":"5",
    "addr:postcode":"4357",
    "addr:street":"Rue Du Cimetie\u0300Re;Jeneffe",
    "iso:country":"BE",
    "sg:address":"Rue Du Cimeti\u00e8re 5",
    "sg:city":"Donceel (jeneffe)",
    "sg:classifiers":[
        {
            "category":"Professional",
            "subcategory":"Accounting & Tax Preparation",
            "type":"Services"
        }
    ],
    "sg:phone":"+32 4 250 43 84",
    "sg:postcode":"4357",
    "sg:province":"Li\u00e8ge",
    "sg:tags":[
        "bookkeeper"
    ],
    "wof:name":"Houben J-l",
    "wof:placetype":"venue"
},
  "geometry": {"coordinates":[5.3556489944,50.6528892517],"type":"Point"}
}