{
  "type": "Feature",
  "properties": {
    "addr:full":"Korte Heide 76 Diest (deurne) Vlaams-Brabant 3290",
    "addr:housenumber":"76",
    "addr:postcode":"3290",
    "addr:street":"Korte Heide",
    "iso:country":"BE",
    "sg:address":"Korte Heide 76",
    "sg:city":"Diest (deurne)",
    "sg:classifiers":[
        {
            "category":"Autos & Motor Vehicles",
            "subcategory":"Motorcycle Sales",
            "type":"Retail Goods"
        }
    ],
    "sg:phone":"+32 13 66 55 80",
    "sg:postcode":"3290",
    "sg:province":"Vlaams-Brabant",
    "sg:tags":[
        "motorbike"
    ],
    "wof:name":"Hd Shop",
    "wof:placetype":"venue"
},
  "geometry": {"coordinates":[5.0958938599,51.0481414795],"type":"Point"}
}