{
  "type": "Feature",
  "properties": {
    "addr:full":"Rue Du Pavillon 5 Bruxelles (schaerbeek) Bruxelles-Capitale 1030",
    "addr:housenumber":"5",
    "addr:postcode":"1030",
    "addr:street":"Rue Du Pavillon",
    "iso:country":"BE",
    "sg:address":"Rue Du Pavillon 5",
    "sg:city":"Bruxelles (schaerbeek)",
    "sg:classifiers":[
        {
            "category":"Shopping",
            "subcategory":"Party Supplies",
            "type":"Retail Goods"
        }
    ],
    "sg:phone":"+32 2 216 96 01",
    "sg:postcode":"1030",
    "sg:province":"Bruxelles-Capitale",
    "sg:tags":[
        "easter",
        "christmas"
    ],
    "wof:name":"Display Decor Sprl",
    "wof:placetype":"venue"
},
  "geometry": {"coordinates":[4.3658819199,50.8681907654],"type":"Point"}
}