{
  "type": "Feature",
  "properties": {
    "addr:full":"Diestersteenweg 226 Nieuwerkerken Limburg 3850",
    "addr:housenumber":"226",
    "addr:postcode":"3850",
    "addr:street":"Diestersteenweg",
    "iso:country":"BE",
    "sg:address":"Diestersteenweg 226",
    "sg:city":"Nieuwerkerken",
    "sg:classifiers":[
        {
            "category":"Health Services",
            "subcategory":"Health Practitioner",
            "type":"Services"
        }
    ],
    "sg:phone":"+32 11 68 87 80",
    "sg:postcode":"3850",
    "sg:province":"Limburg",
    "sg:tags":[
        "physiotherapist"
    ],
    "wof:name":"Smets A",
    "wof:placetype":"venue"
},
  "geometry": {"coordinates":[5.1866250038,50.8758239746],"type":"Point"}
}