{
  "type": "Feature",
  "properties": {
    "addr:full":"Markt 82 Geel Antwerpen 2440",
    "addr:housenumber":"82",
    "addr:postcode":"2440",
    "addr:street":"Markt",
    "iso:country":"BE",
    "sg:address":"Markt 82",
    "sg:city":"Geel",
    "sg:orig_category":"Diverse kredietdiensten",
    "sg:postcode":"2440",
    "sg:province":"Antwerpen",
    "wof:name":"Bancontact-mister Cash",
    "wof:placetype":"venue"
},
  "geometry": {"coordinates":[4.9898080826,51.1611022949],"type":"Point"}
}