{
  "type": "Feature",
  "properties": {
    "addr:full":"Chauss\u00e9e De Bruxelles 34 Charleroi (lodelinsart) Hainaut 6042",
    "addr:housenumber":"34",
    "addr:postcode":"6042",
    "addr:street":"Chausse\u0301E De Bruxelles",
    "iso:country":"BE",
    "sg:address":"Chauss\u00e9e De Bruxelles 34",
    "sg:city":"Charleroi (lodelinsart)",
    "sg:classifiers":[
        {
            "category":"Health Services",
            "subcategory":"Doctor",
            "type":"Services"
        }
    ],
    "sg:phone":"+32 71 31 69 55",
    "sg:postcode":"6042",
    "sg:province":"Hainaut",
    "sg:tags":[
        "medicinephysicians",
        "surgeon"
    ],
    "wof:name":"Ledoux J M",
    "wof:placetype":"venue"
},
  "geometry": {"coordinates":[4.440018177,50.4362106323],"type":"Point"}
}