{
  "type": "Feature",
  "properties": {
    "iso:country":"BE",
    "sg:address":"Rue Jean Pauly 53",
    "sg:city":"Ans (alleur)",
    "sg:classifiers":[
        {
            "category":"Professional",
            "subcategory":"Management & Consulting",
            "type":"Services"
        }
    ],
    "sg:phone":"+32 4 239 15 04",
    "sg:postcode":"4432",
    "sg:province":"Li\u00e8ge",
    "sg:tags":[
        "-",
        "processing",
        "data",
        "consultant"
    ],
    "wof:name":"Jacari Consultant",
    "wof:placetype":"venue"
},
  "geometry": {"coordinates":[5.5232510567,50.6666908264],"type":"Point"}
}