{
  "type": "Feature",
  "properties": {
    "iso:country":"BE",
    "sg:address":"Eikenlaan 41",
    "sg:city":"Kruibeke (bazel)",
    "sg:classifiers":[
        {
            "category":"Professional",
            "subcategory":"Lawyer & Legal Services",
            "type":"Services"
        }
    ],
    "sg:phone":"+32 3 774 29 42",
    "sg:postcode":"9150",
    "sg:province":"Oost-Vlaanderen",
    "wof:name":"De Roeck C",
    "wof:placetype":"venue"
},
  "geometry": {"coordinates":[4.3015289307,51.1419944763],"type":"Point"}
}