{
  "type": "Feature",
  "properties": {
    "iso:country":"BE",
    "sg:address":"Beekstraat 1",
    "sg:city":"Wortegem-petegem",
    "sg:orig_category":"Rundveehouders",
    "sg:phone":"+32 55 38 83 43",
    "sg:postcode":"9790",
    "sg:province":"Oost-Vlaanderen",
    "wof:name":"Daniel Vernackt",
    "wof:placetype":"venue"
},
  "geometry": {"coordinates":[3.5301640034,50.8173522949],"type":"Point"}
}