{
  "type": "Feature",
  "properties": {
    "addr:full":"Rue Bas Coron 1 Leuze-en-hainaut Hainaut 7904",
    "addr:housenumber":"1",
    "addr:postcode":"7904",
    "addr:street":"Rue Bas Coron",
    "iso:country":"BE",
    "sg:address":"Rue Bas Coron 1",
    "sg:city":"Leuze-en-hainaut",
    "sg:orig_category":"Rev\u00eatements pour sols and murs. Peinture",
    "sg:phone":"+32 69 67 03 92",
    "sg:postcode":"7904",
    "sg:province":"Hainaut",
    "wof:name":"Pictor",
    "wof:placetype":"venue"
},
  "geometry": {"coordinates":[3.6003940105,50.5674171448],"type":"Point"}
}