{
  "type": "Feature",
  "properties": {
    "iso:country":"BE",
    "sg:address":"Route De Waimes 82",
    "sg:city":"Malmedy",
    "sg:classifiers":[
        {
            "category":"Building & Trades",
            "subcategory":"Construction",
            "type":"Services"
        }
    ],
    "sg:phone":"+32 80 67 80 02",
    "sg:postcode":"4960",
    "sg:province":"Li\u00e8ge",
    "sg:tags":[
        "installation",
        "-",
        "central",
        "heating"
    ],
    "wof:name":"Marechal R",
    "wof:placetype":"venue"
},
  "geometry": {"coordinates":[6.0642089844,50.4040908813],"type":"Point"}
}