{
  "type": "Feature",
  "properties": {
    "iso:country":"BE",
    "sg:address":"Edegemsestraat 8-10",
    "sg:city":"Mortsel",
    "sg:orig_category":"Cr\u00e8ches and garderies d'enfants",
    "sg:phone":"+32 3 440 88 00",
    "sg:postcode":"2640",
    "sg:province":"Antwerpen",
    "wof:name":"De Bijenkorf",
    "wof:placetype":"venue"
},
  "geometry": {"coordinates":[4.4484257698,51.170425415],"type":"Point"}
}