{
  "type": "Feature",
  "properties": {
    "addr:full":"De Vironstraat 2a Asse Vlaams-Brabant 1730",
    "addr:housenumber":"2a",
    "addr:postcode":"1730",
    "addr:street":"Vironstraat",
    "iso:country":"BE",
    "sg:address":"De Vironstraat 2a",
    "sg:city":"Asse",
    "sg:classifiers":[
        {
            "category":"Real Estate",
            "subcategory":"Architect",
            "type":"Services"
        }
    ],
    "sg:phone":"+32 2 452 22 72",
    "sg:postcode":"1730",
    "sg:province":"Vlaams-Brabant",
    "wof:name":"Beernaerts F",
    "wof:placetype":"venue"
},
  "geometry": {"coordinates":[4.1978111267,50.9110412598],"type":"Point"}
}