{
  "type": "Feature",
  "properties": {
    "iso:country":"BE",
    "sg:address":"Lange Leemstraat 293",
    "sg:city":"Antwerpen",
    "sg:classifiers":[
        {
            "category":"Food & Beverages",
            "subcategory":"Fruits & Vegetables",
            "type":"Retail Goods"
        }
    ],
    "sg:phone":"+32 3 239 70 49",
    "sg:postcode":"2018",
    "sg:province":"Antwerpen",
    "sg:tags":[
        "l\u00e9gumes"
    ],
    "wof:name":"De Groentenhoek",
    "wof:placetype":"venue"
},
  "geometry": {"coordinates":[4.4214949608,51.2043800354],"type":"Point"}
}