{
  "type": "Feature",
  "properties": {
    "iso:country":"BE",
    "sg:address":"Rue Des Cerisiers 4",
    "sg:city":"Braine-le-comte",
    "sg:classifiers":[
        {
            "category":"Real Estate",
            "subcategory":"Architect",
            "type":"Services"
        }
    ],
    "sg:phone":"+32 67 55 71 46",
    "sg:postcode":"7090",
    "sg:province":"Hainaut",
    "wof:name":"Bayard C",
    "wof:placetype":"venue"
},
  "geometry": {"coordinates":[4.1364660263,50.6049537659],"type":"Point"}
}