{
  "type": "Feature",
  "properties": {
    "iso:country":"BE",
    "sg:address":"Avenue Du Parc 71",
    "sg:city":"Chaudfontaine",
    "sg:classifiers":[
        {
            "category":"Insurance",
            "subcategory":"Life Insurance",
            "type":"Services"
        }
    ],
    "sg:phone":"+32 4 361 35 32",
    "sg:postcode":"4053",
    "sg:province":"Li\u00e8ge",
    "sg:tags":[
        "assurance"
    ],
    "wof:name":"Soc.actuariat Consultants",
    "wof:placetype":"venue"
},
  "geometry": {"coordinates":[5.6014342308,50.5855255127],"type":"Point"}
}