{
  "type": "Feature",
  "properties": {
    "addr:full":"Molign\u00c9estraat 24 Oudergem/auderghem Bruxelles-Capitale 1160",
    "addr:housenumber":"24",
    "addr:postcode":"1160",
    "addr:street":"Moligne\u0301Estraat;/",
    "iso:country":"BE",
    "sg:address":"Molign\u00c9estraat 24",
    "sg:city":"Oudergem/auderghem",
    "sg:orig_category":"Artsen and specialisten",
    "sg:phone":"+32 2 733 27 33",
    "sg:postcode":"1160",
    "sg:province":"Bruxelles-Capitale",
    "wof:name":"Philippe Rombaux",
    "wof:placetype":"venue"
},
  "geometry": {"coordinates":[4.4041361809,50.8249893188],"type":"Point"}
}