{
  "type": "Feature",
  "properties": {
    "addr:full":"Koningin Astridlaan 13 Bornem (hingene) Antwerpen 2880",
    "addr:housenumber":"13",
    "addr:postcode":"2880",
    "addr:street":"Koningin Astridlaan",
    "iso:country":"BE",
    "sg:address":"Koningin Astridlaan 13",
    "sg:city":"Bornem (hingene)",
    "sg:classifiers":[
        {
            "category":"Health Services",
            "subcategory":"Doctor",
            "type":"Services"
        }
    ],
    "sg:phone":"+32 3 889 98 46",
    "sg:postcode":"2880",
    "sg:province":"Antwerpen",
    "sg:tags":[
        "medicinephysicians",
        "surgeon"
    ],
    "wof:name":"Macharis Ann",
    "wof:placetype":"venue"
},
  "geometry": {"coordinates":[4.2959389687,51.1064453125],"type":"Point"}
}