{
  "type": "Feature",
  "properties": {
    "addr:full":"Brabantdam 32b1 Gent Oost-Vlaanderen 9000",
    "addr:housenumber":"32b1",
    "addr:postcode":"9000",
    "addr:street":"Brabantdam;Oost-Vlaanderen",
    "iso:country":"BE",
    "sg:address":"Brabantdam 32b1",
    "sg:city":"Gent",
    "sg:orig_category":"Agences de relations publiques",
    "sg:phone":"+32 9 233 08 97",
    "sg:postcode":"9000",
    "sg:province":"Oost-Vlaanderen",
    "wof:name":"Making Waves",
    "wof:placetype":"venue"
},
  "geometry": {"coordinates":[3.7283389568,51.0504341125],"type":"Point"}
}