{
  "type": "Feature",
  "properties": {
    "iso:country":"BE",
    "sg:address":"Avenue Marie-jos\u00e9 180",
    "sg:city":"Binche (ressaix)",
    "sg:classifiers":[
        {
            "category":"Health Services",
            "subcategory":"Health Practitioner",
            "type":"Services"
        }
    ],
    "sg:phone":"+32 64 33 92 55",
    "sg:postcode":"7134",
    "sg:province":"Hainaut",
    "sg:tags":[
        "physiotherapist"
    ],
    "wof:name":"Colpaert Arnould",
    "wof:placetype":"venue"
},
  "geometry": {"coordinates":[4.1883120537,50.4153137207],"type":"Point"}
}