{
  "type": "Feature",
  "properties": {
    "iso:country":"BE",
    "sg:address":"Louwijn 13",
    "sg:city":"Asse",
    "sg:classifiers":[
        {
            "category":"Freight",
            "type":"Transportation"
        }
    ],
    "sg:phone":"+32 2 452 50 82",
    "sg:postcode":"1730",
    "sg:province":"Vlaams-Brabant",
    "sg:tags":[
        "air"
    ],
    "wof:name":"Ab Europe Nv",
    "wof:placetype":"venue"
},
  "geometry": {"coordinates":[4.1633629799,50.8905601501],"type":"Point"}
}