{
  "type": "Feature",
  "properties": {
    "addr:full":"Nieuwpoortsesteenweg 665 Oostende West-Vlaanderen 8400",
    "addr:housenumber":"665",
    "addr:postcode":"8400",
    "addr:street":"Nieuwpoortsesteenweg",
    "iso:country":"BE",
    "sg:address":"Nieuwpoortsesteenweg 665",
    "sg:city":"Oostende",
    "sg:orig_category":"Quincailleries. Bois Gr. Location de machines-outils and de mat\u00e9riel de bricolage",
    "sg:phone":"+32 59 50 37 38",
    "sg:postcode":"8400",
    "sg:province":"West-Vlaanderen",
    "wof:name":"Gamma",
    "wof:placetype":"venue"
},
  "geometry": {"coordinates":[2.8450210094,51.1960296631],"type":"Point"}
}