{
  "type": "Feature",
  "properties": {
    "iso:country":"BE",
    "sg:address":"Avenue De Jette 296b3",
    "sg:city":"Jette/jette",
    "sg:classifiers":[
        {
            "category":"Cafe",
            "type":"Food & Drink"
        }
    ],
    "sg:phone":"+32 2 424 10 20",
    "sg:postcode":"1090",
    "sg:province":"Bruxelles-Capitale",
    "sg:tags":[
        "caf\u00e9s"
    ],
    "wof:name":"Pierre Vander Steene",
    "wof:placetype":"venue"
},
  "geometry": {"coordinates":[4.3235440254,50.8729553223],"type":"Point"}
}