{
  "type": "Feature",
  "properties": {
    "addr:full":"Osselstraat 14 Merchtem (brussegem) Vlaams-Brabant 1785",
    "addr:housenumber":"14",
    "addr:postcode":"1785",
    "addr:street":"Osselstraat",
    "iso:country":"BE",
    "sg:address":"Osselstraat 14",
    "sg:city":"Merchtem (brussegem)",
    "sg:classifiers":[
        {
            "category":"Shopping",
            "subcategory":"Jewelry",
            "type":"Retail Goods"
        }
    ],
    "sg:phone":"+32 2 461 06 07",
    "sg:postcode":"1785",
    "sg:province":"Vlaams-Brabant",
    "sg:tags":[
        "jeweller",
        "-"
    ],
    "wof:name":"Mac Lafferty Jewellery",
    "wof:placetype":"venue"
},
  "geometry": {"coordinates":[4.2767500877,50.9224090576],"type":"Point"}
}