{
  "type": "Feature",
  "properties": {
    "iso:country":"BE",
    "sg:address":"Veneti\u00cbstraat 2",
    "sg:city":"Elsene/ixelles",
    "sg:orig_category":"Industri\u00eble wasserijen and droogkuis",
    "sg:phone":"+32 2 640 38 57",
    "sg:postcode":"1050",
    "sg:province":"Bruxelles-Capitale",
    "wof:name":"Harikila Souvatzis",
    "wof:placetype":"venue"
},
  "geometry": {"coordinates":[4.3688559532,50.8325157166],"type":"Point"}
}