{
  "type": "Feature",
  "properties": {
    "addr:full":"Rue Lat\u00c9rale 15 Edingen/enghien Hainaut 7850",
    "addr:housenumber":"15",
    "addr:postcode":"7850",
    "addr:street":"Rue Late\u0301Rale",
    "iso:country":"BE",
    "sg:address":"Rue Lat\u00c9rale 15",
    "sg:city":"Edingen/enghien",
    "sg:orig_category":"Installation de menuiserie en bois and plastique",
    "sg:phone":"+32 2 395 97 16",
    "sg:postcode":"7850",
    "sg:province":"Hainaut",
    "wof:name":"Bertrand Amelot",
    "wof:placetype":"venue"
},
  "geometry": {"coordinates":[4.0441250801,50.6963882446],"type":"Point"}
}