{
  "type": "Feature",
  "properties": {
    "addr:full":"Vilvoordsesteenweg 111 Meise Vlaams-Brabant 1860",
    "addr:housenumber":"111",
    "addr:postcode":"1860",
    "addr:street":"Vilvoordsesteenweg",
    "iso:country":"BE",
    "sg:address":"Vilvoordsesteenweg 111",
    "sg:city":"Meise",
    "sg:classifiers":[
        {
            "category":"Food & Beverages",
            "subcategory":"Fruits & Vegetables",
            "type":"Retail Goods"
        }
    ],
    "sg:phone":"+32 2 270 13 17",
    "sg:postcode":"1860",
    "sg:province":"Vlaams-Brabant",
    "sg:tags":[
        "-"
    ],
    "wof:name":"Bradeur",
    "wof:placetype":"venue"
},
  "geometry": {"coordinates":[4.3355221748,50.9424972534],"type":"Point"}
}