{
  "type": "Feature",
  "properties": {
    "addr:full":"Sint-gertrudisplein 18b1 Bilzen Limburg 3740",
    "addr:housenumber":"18b1",
    "addr:postcode":"3740",
    "addr:street":"Sint-Gertrudisplein",
    "iso:country":"BE",
    "sg:address":"Sint-gertrudisplein 18b1",
    "sg:city":"Bilzen",
    "sg:orig_category":"Installatie van houten of kunststof schrijnwerk",
    "sg:phone":"+32 89 41 50 24",
    "sg:postcode":"3740",
    "sg:province":"Limburg",
    "wof:name":"Andre Raskin",
    "wof:placetype":"venue"
},
  "geometry": {"coordinates":[5.4746870995,50.891242981],"type":"Point"}
}