{
  "type": "Feature",
  "properties": {
    "addr:full":"Kaai 21 Nieuwpoort West-Vlaanderen 8620",
    "addr:housenumber":"21",
    "addr:postcode":"8620",
    "addr:street":"Kaai",
    "iso:country":"BE",
    "sg:address":"Kaai 21",
    "sg:city":"Nieuwpoort",
    "sg:classifiers":[
        {
            "category":"Shopping",
            "subcategory":"Bicycles & Sporting Goods",
            "type":"Retail Goods"
        }
    ],
    "sg:phone":"+32 475 60 52 24",
    "sg:postcode":"8620",
    "sg:province":"West-Vlaanderen",
    "sg:tags":[
        "article",
        "de",
        "sport",
        "camping"
    ],
    "wof:name":"A-z Camping Service",
    "wof:placetype":"venue"
},
  "geometry": {"coordinates":[2.7513079643,51.1332855225],"type":"Point"}
}