{
  "type": "Feature",
  "properties": {
    "iso:country":"BE",
    "sg:address":"De Lochtstraat 56",
    "sg:city":"Schaarbeek/schaerbeek",
    "sg:orig_category":"Drogisterijen",
    "sg:phone":"+32 2 241 42 48",
    "sg:postcode":"1030",
    "sg:province":"Bruxelles-Capitale",
    "wof:name":"Andre Mascia",
    "wof:placetype":"venue"
},
  "geometry": {"coordinates":[4.3698568344,50.8643493652],"type":"Point"}
}