{
  "type": "Feature",
  "properties": {
    "addr:full":"Stekelbaarsstraat 27 Beerse Antwerpen 2340",
    "addr:housenumber":"27",
    "addr:postcode":"2340",
    "addr:street":"Stekelbaarsstraat",
    "iso:country":"BE",
    "sg:address":"Stekelbaarsstraat 27",
    "sg:city":"Beerse",
    "sg:orig_category":"Baby- and kinderkleding",
    "sg:phone":"+32 14 61 57 75",
    "sg:postcode":"2340",
    "sg:province":"Antwerpen",
    "wof:name":"Boks",
    "wof:placetype":"venue"
},
  "geometry": {"coordinates":[4.8525590897,51.3116340637],"type":"Point"}
}