{
  "type": "Feature",
  "properties": {
    "iso:country":"BE",
    "sg:address":"Steenberghoekstraat 20",
    "sg:city":"Rumst",
    "sg:orig_category":"Musea and historische gebouwen",
    "sg:phone":"+32 3 844 49 74",
    "sg:postcode":"2840",
    "sg:province":"Antwerpen",
    "wof:name":"Steenbak.museum 't Geleeg",
    "wof:placetype":"venue"
},
  "geometry": {"coordinates":[4.4209179878,51.0800056458],"type":"Point"}
}