{
  "type": "Feature",
  "properties": {
    "iso:country":"BE",
    "sg:address":"Rue Grand Fontaine 21",
    "sg:city":"Beyne-heusay",
    "sg:classifiers":[
        {
            "category":"Organizations",
            "subcategory":"Community Association",
            "type":"Services"
        }
    ],
    "sg:phone":"+32 4 355 08 24",
    "sg:postcode":"4610",
    "sg:province":"Li\u00e8ge",
    "sg:tags":[
        "de",
        "restaurant",
        "organisation",
        "\u00e0",
        "domicile",
        "catering",
        "livraison",
        "f\u00eates"
    ],
    "wof:name":"La Fleur De Sel",
    "wof:placetype":"venue"
},
  "geometry": {"coordinates":[5.6664972305,50.6183929443],"type":"Point"}
}