{
  "type": "Feature",
  "properties": {
    "iso:country":"BE",
    "sg:address":"Groenstraat 5",
    "sg:city":"Lokeren",
    "sg:orig_category":"Instituts de beaut\u00e9",
    "sg:phone":"+32 9 348 05 03",
    "sg:postcode":"9160",
    "sg:province":"Oost-Vlaanderen",
    "wof:name":"Katelijne Ballinckx",
    "wof:placetype":"venue"
},
  "geometry": {"coordinates":[4.022837162,51.1072158813],"type":"Point"}
}