{
  "type": "Feature",
  "properties": {
    "addr:full":"Village 5ba Bievre Namur 5555",
    "addr:postcode":"5555",
    "addr:street":"Village;Namur",
    "iso:country":"BE",
    "sg:address":"Village 5ba",
    "sg:city":"Bievre",
    "sg:orig_category":"Paramedische behandelingen",
    "sg:phone":"+32 61 51 14 74",
    "sg:postcode":"5555",
    "sg:province":"Namur",
    "wof:name":"D. Danjou",
    "wof:placetype":"venue"
},
  "geometry": {"coordinates":[4.9716110229,49.9170608521],"type":"Point"}
}