{
  "type": "Feature",
  "properties": {
    "addr:full":"Rue De Mellery 28 Chastre (gentinnes) Brabant Wallon 1450",
    "addr:housenumber":"28",
    "addr:postcode":"1450",
    "addr:street":"Rue De Mellery;Wallon",
    "iso:country":"BE",
    "sg:address":"Rue De Mellery 28",
    "sg:city":"Chastre (gentinnes)",
    "sg:classifiers":[
        {
            "category":"Shopping",
            "subcategory":"Bicycles & Sporting Goods",
            "type":"Retail Goods"
        }
    ],
    "sg:phone":"+32 71 87 75 70",
    "sg:postcode":"1450",
    "sg:province":"Brabant Wallon",
    "sg:tags":[
        "-"
    ],
    "wof:name":"Delory A",
    "wof:placetype":"venue"
},
  "geometry": {"coordinates":[4.636452198,50.6085243225],"type":"Point"}
}