{
  "type": "Feature",
  "properties": {
    "addr:full":"Aalbroekstraat 38 Gavere Oost-Vlaanderen 9890",
    "addr:housenumber":"38",
    "addr:postcode":"9890",
    "addr:street":"Aalbroekstraat",
    "iso:country":"BE",
    "sg:address":"Aalbroekstraat 38",
    "sg:city":"Gavere",
    "sg:orig_category":"Schoonheidssalons",
    "sg:phone":"+32 9 384 60 85",
    "sg:postcode":"9890",
    "sg:province":"Oost-Vlaanderen",
    "wof:name":"Instituut Veerle",
    "wof:placetype":"venue"
},
  "geometry": {"coordinates":[3.6578299999,50.933429718],"type":"Point"}
}