{
  "type": "Feature",
  "properties": {
    "iso:country":"BE",
    "sg:address":"Kanarieberg 15",
    "sg:city":"Ronse/renaix",
    "sg:orig_category":"Rundveehouders Varkenskwekers",
    "sg:phone":"+32 55 21 14 53",
    "sg:postcode":"9600",
    "sg:province":"Oost-Vlaanderen",
    "wof:name":"Frans Vandenhole",
    "wof:placetype":"venue"
},
  "geometry": {"coordinates":[3.650386095,50.764087677],"type":"Point"}
}