{
  "type": "Feature",
  "properties": {
    "addr:full":"Moerkerkse Steenweg 4 Brugge (sint-kruis) West-Vlaanderen 8310",
    "addr:housenumber":"4",
    "addr:postcode":"8310",
    "addr:street":"Moerkerkse Steenweg",
    "iso:country":"BE",
    "sg:address":"Moerkerkse Steenweg 4",
    "sg:city":"Brugge (sint-kruis)",
    "sg:classifiers":[
        {
            "category":"Autos & Motor Vehicles",
            "subcategory":"Auto Supplies",
            "type":"Retail Goods"
        }
    ],
    "sg:phone":"+32 50 37 20 80",
    "sg:postcode":"8310",
    "sg:province":"West-Vlaanderen",
    "sg:tags":[
        "automobile",
        "-",
        "radio"
    ],
    "wof:name":"Ataf Car Electronics",
    "wof:placetype":"venue"
},
  "geometry": {"coordinates":[3.2418010235,51.2128868103],"type":"Point"}
}