{
  "type": "Feature",
  "properties": {
    "addr:full":"Ommegangstraat 80 Zele Oost-Vlaanderen 9240",
    "addr:housenumber":"80",
    "addr:postcode":"9240",
    "addr:street":"Ommegangstraat",
    "iso:country":"BE",
    "sg:address":"Ommegangstraat 80",
    "sg:city":"Zele",
    "sg:orig_category":"Magasins sp\u00e9cialis\u00e9s. Traitement and fa\u00e7onnage de la pierre",
    "sg:phone":"+32 52 44 58 90",
    "sg:postcode":"9240",
    "sg:province":"Oost-Vlaanderen",
    "wof:name":"Quintelier & Zoon",
    "wof:placetype":"venue"
},
  "geometry": {"coordinates":[4.0424041748,51.0633087158],"type":"Point"}
}