{
  "type": "Feature",
  "properties": {
    "addr:full":"Wingenestraat 32 Aalter Oost-Vlaanderen 9880",
    "addr:housenumber":"32",
    "addr:postcode":"9880",
    "addr:street":"Wingenestraat",
    "iso:country":"BE",
    "sg:address":"Wingenestraat 32",
    "sg:city":"Aalter",
    "sg:orig_category":"Postkantoren Verzekeringsmakelaars and experts",
    "sg:phone":"+32 9 374 16 93",
    "sg:postcode":"9880",
    "sg:province":"Oost-Vlaanderen",
    "wof:name":"De Post",
    "wof:placetype":"venue"
},
  "geometry": {"coordinates":[3.3609399796,51.088973999],"type":"Point"}
}