{
  "type": "Feature",
  "properties": {
    "iso:country":"BE",
    "sg:address":"Rue De Pont \u00e0 Celles 111",
    "sg:city":"Courcelles (trazegnies)",
    "sg:classifiers":[
        {
            "category":"Professional",
            "subcategory":"Accounting & Tax Preparation",
            "type":"Services"
        }
    ],
    "sg:phone":"+32 71 46 08 15",
    "sg:postcode":"6183",
    "sg:province":"Hainaut",
    "sg:tags":[
        "bookkeeper"
    ],
    "wof:name":"Descamps B",
    "wof:placetype":"venue"
},
  "geometry": {"coordinates":[4.3373699188,50.4698257446],"type":"Point"}
}