{
  "type": "Feature",
  "properties": {
    "addr:full":"Alsteen 17 Waregem West-Vlaanderen 8792",
    "addr:housenumber":"17",
    "addr:postcode":"8792",
    "addr:street":"Alsteen",
    "iso:country":"BE",
    "sg:address":"Alsteen 17",
    "sg:city":"Waregem",
    "sg:orig_category":"Non-foodwinkels Sport- and kampeermateriaal",
    "sg:phone":"+32 56 70 58 96",
    "sg:postcode":"8792",
    "sg:province":"West-Vlaanderen",
    "wof:name":"Redijan",
    "wof:placetype":"venue"
},
  "geometry": {"coordinates":[3.3662769794,50.8901138306],"type":"Point"}
}