{
  "type": "Feature",
  "properties": {
    "addr:full":"Rue Tour Notre Dame 13 Frasnes-lez-anvaing Hainaut 7912",
    "addr:housenumber":"13;7912",
    "addr:street":"Rue Tour Notre;Frasnes-Lez-Anvaing Hainaut",
    "iso:country":"BE",
    "sg:address":"Rue Tour Notre Dame 13",
    "sg:city":"Frasnes-lez-anvaing",
    "sg:orig_category":"M\u00e9decins and sp\u00e9cialistes",
    "sg:phone":"+32 69 76 74 44",
    "sg:postcode":"7912",
    "sg:province":"Hainaut",
    "wof:name":"Micha\u00cbl Bruneau",
    "wof:placetype":"venue"
},
  "geometry": {"coordinates":[3.6007270813,50.7089347839],"type":"Point"}
}