{
  "type": "Feature",
  "properties": {
    "addr:full":"Clos Du Poney 3 Braine L'alleud (braine-l'alleud) Brabant Wallon 1420",
    "addr:housenumber":"3",
    "addr:postcode":"1420",
    "addr:street":"Clos Du Poney",
    "iso:country":"BE",
    "sg:address":"Clos Du Poney 3",
    "sg:city":"Braine L'alleud (braine-l'alleud)",
    "sg:classifiers":[
        {
            "category":"Professional",
            "subcategory":"Management & Consulting",
            "type":"Services"
        }
    ],
    "sg:phone":"+32 2 354 35 50",
    "sg:postcode":"1420",
    "sg:province":"Brabant Wallon",
    "sg:tags":[
        "consultant",
        "agency",
        "advertising"
    ],
    "wof:name":"J V M Advertising",
    "wof:placetype":"venue"
},
  "geometry": {"coordinates":[-0.6790779829,47.3779411316],"type":"Point"}
}