{
  "type": "Feature",
  "properties": {
    "iso:country":"BE",
    "sg:address":"Chauss\u00c9e De Tongres 269-271",
    "sg:city":"Li\u00c8ge",
    "sg:orig_category":"V\u00eatements pour Hommes. V\u00eatements pour b\u00e9b\u00e9s and enfants",
    "sg:phone":"+32 4 263 93 32",
    "sg:postcode":"4000",
    "sg:province":"Li\u00e8ge",
    "wof:name":"We Men",
    "wof:placetype":"venue"
},
  "geometry": {"coordinates":[5.5499567986,50.6700172424],"type":"Point"}
}