{
  "type": "Feature",
  "properties": {
    "iso:country":"BE",
    "sg:address":"Sint-truidersteenweg 260",
    "sg:city":"Borgloon",
    "sg:orig_category":"Producteurs de fruits",
    "sg:phone":"+32 12 74 13 75",
    "sg:postcode":"3840",
    "sg:province":"Limburg",
    "wof:name":"Caroline Vandionant",
    "wof:placetype":"venue"
},
  "geometry": {"coordinates":[5.3098840714,50.8055114746],"type":"Point"}
}