{
  "type": "Feature",
  "properties": {
    "addr:full":"Bronnestraat 1 Maarkedal (etikhove) Oost-Vlaanderen 9680",
    "addr:housenumber":"1",
    "addr:postcode":"9680",
    "addr:street":"Bronnestraat",
    "iso:country":"BE",
    "sg:address":"Bronnestraat 1",
    "sg:city":"Maarkedal (etikhove)",
    "sg:classifiers":[
        {
            "category":"Wholesale",
            "subcategory":"Beer",
            "type":"Manufacturing & Wholesale Goods"
        }
    ],
    "sg:phone":"+32 55 31 19 59",
    "sg:postcode":"9680",
    "sg:province":"Oost-Vlaanderen",
    "sg:tags":[
        "ale",
        "-"
    ],
    "wof:name":"Straal Bronnen Bvba",
    "wof:placetype":"venue"
},
  "geometry": {"coordinates":[3.609662056,50.8010597229],"type":"Point"}
}