{
  "type": "Feature",
  "properties": {
    "iso:country":"BE",
    "sg:address":"Steenbakkersweg 62",
    "sg:city":"Overijse",
    "sg:orig_category":"Fruitteelt Rundveehouders",
    "sg:phone":"+32 2 657 44 23",
    "sg:postcode":"3090",
    "sg:province":"Vlaams-Brabant",
    "wof:name":"Joannes Ceusters",
    "wof:placetype":"venue"
},
  "geometry": {"coordinates":[4.5068688393,50.7587051392],"type":"Point"}
}