{
  "type": "Feature",
  "properties": {
    "addr:full":"Frans Thirrystraat 41 Asse Vlaams-Brabant 1731",
    "addr:housenumber":"41",
    "addr:postcode":"1731",
    "addr:street":"Frans Thirrystraat",
    "iso:country":"BE",
    "sg:address":"Frans Thirrystraat 41",
    "sg:city":"Asse",
    "sg:orig_category":"Onderdelen and accessoires voor auto's",
    "sg:phone":"+32 2 466 37 17",
    "sg:postcode":"1731",
    "sg:province":"Vlaams-Brabant",
    "wof:name":"Banden Thielemans",
    "wof:placetype":"venue"
},
  "geometry": {"coordinates":[4.2726449966,50.8870048523],"type":"Point"}
}