{
  "type": "Feature",
  "properties": {
    "iso:country":"BE",
    "sg:address":"Rekestraat 11",
    "sg:city":"Geraardsbergen (zarlardinge)",
    "sg:classifiers":[
        {
            "category":"Professional",
            "subcategory":"Engineering",
            "type":"Services"
        }
    ],
    "sg:phone":"+32 54 41 32 77",
    "sg:postcode":"9500",
    "sg:province":"Oost-Vlaanderen",
    "sg:tags":[
        "technical",
        "equipment",
        "offices-"
    ],
    "wof:name":"Studelco Bvba",
    "wof:placetype":"venue"
},
  "geometry": {"coordinates":[3.8823950291,50.7635650635],"type":"Point"}
}