{
  "type": "Feature",
  "properties": {
    "addr:full":"Rue De Courtrai 21 Tournai Hainaut 7500",
    "addr:housenumber":"21",
    "addr:postcode":"7500",
    "addr:street":"Rue De Courtrai",
    "iso:country":"BE",
    "sg:address":"Rue De Courtrai 21",
    "sg:city":"Tournai",
    "sg:classifiers":[
        {
            "category":"Bars & Pubs",
            "type":"Food & Drink"
        }
    ],
    "sg:phone":"+32 69 22 49 29",
    "sg:postcode":"7500",
    "sg:province":"Hainaut",
    "sg:tags":[
        "tavern"
    ],
    "wof:name":"Chopin (le)",
    "wof:placetype":"venue"
},
  "geometry": {"coordinates":[3.387638092,50.6082611084],"type":"Point"}
}