{
  "type": "Feature",
  "properties": {
    "iso:country":"BE",
    "sg:address":"Kwikstraat 17 Bus 2",
    "sg:city":"Peer",
    "sg:orig_category":"Dakwerken",
    "sg:phone":"+32 11 63 64 91",
    "sg:postcode":"3990",
    "sg:province":"Limburg",
    "wof:name":"Dakwerken Vanhees",
    "wof:placetype":"venue"
},
  "geometry": {"coordinates":[5.4444971085,51.1424636841],"type":"Point"}
}