{
  "type": "Feature",
  "properties": {
    "iso:country":"BE",
    "sg:address":"Avenue Des Chevreuils 6",
    "sg:city":"Ottignies-louvain-la-neuve",
    "sg:orig_category":"Agences de publicit\u00e9. Agences de presse",
    "sg:phone":"+32 2 545 57 27",
    "sg:postcode":"1340",
    "sg:province":"Brabant Wallon",
    "wof:name":"Nicolas Oldenhove",
    "wof:placetype":"venue"
},
  "geometry": {"coordinates":[4.5842690468,50.6703453064],"type":"Point"}
}