{
  "type": "Feature",
  "properties": {
    "iso:country":"BE",
    "sg:address":"Zevensterrenstraat 25",
    "sg:city":"Sint-agatha-berchem/berchem-sainte-agathe",
    "sg:orig_category":"Plaatsen van vloer- and muurbekleding Schilders",
    "sg:phone":"+32 2 465 85 79",
    "sg:postcode":"1082",
    "sg:province":"Bruxelles-Capitale",
    "wof:name":"Antonio Vitanza",
    "wof:placetype":"venue"
},
  "geometry": {"coordinates":[4.2881731987,50.8662147522],"type":"Point"}
}