{
  "type": "Feature",
  "properties": {
    "iso:country":"BE",
    "sg:address":"Avenue F\u00e9lix Deblon 1",
    "sg:city":"Theux (polleur)",
    "sg:classifiers":[
        {
            "category":"Travel",
            "subcategory":"Hotels & Motels",
            "type":"Entertainment"
        }
    ],
    "sg:phone":"+32 87 22 44 26",
    "sg:postcode":"4910",
    "sg:province":"Li\u00e8ge",
    "wof:name":"Hostell. val De Hoegne Sprl",
    "wof:placetype":"venue"
},
  "geometry": {"coordinates":[5.8130488396,50.5356216431],"type":"Point"}
}