{
  "type": "Feature",
  "properties": {
    "addr:full":"Chauss\u00c9e Philippeville 112 Couvin Namur 5660",
    "addr:housenumber":"112",
    "addr:postcode":"5660",
    "addr:street":"Chausse\u0301E Philippeville",
    "iso:country":"BE",
    "sg:address":"Chauss\u00c9e Philippeville 112",
    "sg:city":"Couvin",
    "sg:orig_category":"Quincaillerie Grands magasins",
    "sg:phone":"+32 60 31 11 21",
    "sg:postcode":"5660",
    "sg:province":"Namur",
    "wof:name":"Brico-bazar",
    "wof:placetype":"venue"
},
  "geometry": {"coordinates":[4.5215997696,50.0891494751],"type":"Point"}
}