{
  "type": "Feature",
  "properties": {
    "addr:full":"Kerkstraat 41 Middelkerke West-Vlaanderen 8430",
    "addr:housenumber":"41",
    "addr:postcode":"8430",
    "addr:street":"Kerkstraat",
    "iso:country":"BE",
    "sg:address":"Kerkstraat 41",
    "sg:city":"Middelkerke",
    "sg:orig_category":"Enseignement maternel and primaire",
    "sg:phone":"+32 59 30 19 39",
    "sg:postcode":"8430",
    "sg:province":"West-Vlaanderen",
    "wof:name":"Vrije Basisschool",
    "wof:placetype":"venue"
},
  "geometry": {"coordinates":[2.8203859329,51.18592453],"type":"Point"}
}