{
  "type": "Feature",
  "properties": {
    "addr:full":"Markt 11 Torhout West-Vlaanderen 8820",
    "addr:housenumber":"11",
    "addr:postcode":"8820",
    "addr:street":"Markt",
    "iso:country":"BE",
    "sg:address":"Markt 11",
    "sg:city":"Torhout",
    "sg:classifiers":[
        {
            "category":"Shopping",
            "subcategory":"Clothing, Apparel, & Fashions",
            "type":"Retail Goods"
        }
    ],
    "sg:phone":"+32 50 21 39 15",
    "sg:postcode":"8820",
    "sg:province":"West-Vlaanderen",
    "sg:tags":[
        "-",
        "clothing",
        "child"
    ],
    "wof:name":"Pinkie",
    "wof:placetype":"venue"
},
  "geometry": {"coordinates":[3.1016690731,51.0643234253],"type":"Point"}
}