{
  "type": "Feature",
  "properties": {
    "addr:full":"Parvis Saint-henri 16 Bruxelles (woluwe-saint-lambert) Bruxelles-Capitale 1200",
    "addr:housenumber":"16",
    "addr:postcode":"1200",
    "addr:street":"Parvis Saint-Henri",
    "iso:country":"BE",
    "sg:address":"Parvis Saint-henri 16",
    "sg:city":"Bruxelles (woluwe-saint-lambert)",
    "sg:classifiers":[
        {
            "category":"Professional",
            "subcategory":"Art Services",
            "type":"Services"
        }
    ],
    "sg:phone":"+32 2 733 46 71",
    "sg:postcode":"1200",
    "sg:province":"Bruxelles-Capitale",
    "sg:tags":[
        "photographer"
    ],
    "wof:name":"Chabothier M",
    "wof:placetype":"venue"
},
  "geometry": {"coordinates":[4.4099359512,50.8423843384],"type":"Point"}
}