{
  "type": "Feature",
  "properties": {
    "iso:country":"BE",
    "sg:address":"Kerkstraat 12",
    "sg:city":"Lommel",
    "sg:orig_category":"Banques and organismes de cr\u00e9dit",
    "sg:phone":"+32 11 54 13 32",
    "sg:postcode":"3920",
    "sg:province":"Limburg",
    "wof:name":"Fortis",
    "wof:placetype":"venue"
},
  "geometry": {"coordinates":[5.3104519844,51.2302513123],"type":"Point"}
}