{
  "type": "Feature",
  "properties": {
    "addr:full":"Liersesteenweg 78 Ranst Antwerpen 2520",
    "addr:housenumber":"78",
    "addr:postcode":"2520",
    "addr:street":"Liersesteenweg",
    "iso:country":"BE",
    "sg:address":"Liersesteenweg 78",
    "sg:city":"Ranst",
    "sg:orig_category":"Installatie van houten of kunststof schrijnwerk Speelgoed Tuinbenodigdheden",
    "sg:phone":"+32 3 489 08 48",
    "sg:postcode":"2520",
    "sg:province":"Antwerpen",
    "wof:name":"Ambo",
    "wof:placetype":"venue"
},
  "geometry": {"coordinates":[4.5850348473,51.1548843384],"type":"Point"}
}