{
  "type": "Feature",
  "properties": {
    "iso:country":"BE",
    "sg:address":"Dorp 97",
    "sg:city":"Assenede",
    "sg:orig_category":"HUISBRANDOLIE",
    "sg:phone":"+32 9 373 64 12",
    "sg:postcode":"9968",
    "sg:province":"Oost-Vlaanderen",
    "wof:name":"G Van Zele - Bassevelde",
    "wof:placetype":"venue"
},
  "geometry": {"coordinates":[3.6887938976,51.1923027039],"type":"Point"}
}