{
  "type": "Feature",
  "properties": {
    "iso:country":"BE",
    "sg:address":"Hoogstraatseweg 63",
    "sg:city":"Wuustwezel",
    "sg:orig_category":"Herstellingen and onderhoud van auto's Voertuigen",
    "sg:phone":"+32 3 669 87 30",
    "sg:postcode":"2990",
    "sg:province":"Antwerpen",
    "wof:name":"Garage M Van Hasselt",
    "wof:placetype":"venue"
},
  "geometry": {"coordinates":[4.6520957947,51.4024848938],"type":"Point"}
}