{
  "type": "Feature",
  "properties": {
    "iso:country":"BE",
    "sg:address":"Avenue John-fitzgerald Kennedy 40a",
    "sg:city":"Rixensart",
    "sg:classifiers":[
        {
            "category":"Building & Trades",
            "subcategory":"Electrical",
            "type":"Services"
        }
    ],
    "sg:phone":"+32 2 653 92 14",
    "sg:postcode":"1330",
    "sg:province":"Brabant Wallon",
    "sg:tags":[
        "electric",
        "-",
        "housewiring",
        "contractor"
    ],
    "wof:name":"Boucher Y",
    "wof:placetype":"venue"
},
  "geometry": {"coordinates":[4.5236048698,50.7051811218],"type":"Point"}
}