{
  "type": "Feature",
  "properties": {
    "addr:full":"Oombergenstraat 23 Zottegem Oost-Vlaanderen 9620",
    "addr:housenumber":"23",
    "addr:postcode":"9620",
    "addr:street":"Oombergenstraat",
    "iso:country":"BE",
    "sg:address":"Oombergenstraat 23",
    "sg:city":"Zottegem",
    "sg:orig_category":"Rundveehouders",
    "sg:phone":"+32 9 360 66 80",
    "sg:postcode":"9620",
    "sg:province":"Oost-Vlaanderen",
    "wof:name":"Andre De Cang",
    "wof:placetype":"venue"
},
  "geometry": {"coordinates":[3.8112111092,50.871181488],"type":"Point"}
}