{
  "type": "Feature",
  "properties": {
    "iso:country":"BE",
    "sg:address":"Lange Veldstraat 12",
    "sg:city":"Dilbeek",
    "sg:orig_category":"Woningbouw",
    "sg:phone":"+32 2 569 72 88",
    "sg:postcode":"1700",
    "sg:province":"Vlaams-Brabant",
    "wof:name":"De Beys K",
    "wof:placetype":"venue"
},
  "geometry": {"coordinates":[4.2282519341,50.8602180481],"type":"Point"}
}