{
  "type": "Feature",
  "properties": {
    "iso:country":"BE",
    "sg:address":"Basiliekstraat 56",
    "sg:city":"Halle",
    "sg:orig_category":"Dranken Zuivelproducten",
    "sg:phone":"+32 2 360 15 45",
    "sg:postcode":"1500",
    "sg:province":"Vlaams-Brabant",
    "wof:name":"Cremerie Centrale",
    "wof:placetype":"venue"
},
  "geometry": {"coordinates":[4.2356572151,50.7346572876],"type":"Point"}
}