{
  "type": "Feature",
  "properties": {
    "addr:full":"Rue Grande Triperie 3 Mons Hainaut 7000",
    "addr:housenumber":"3",
    "addr:postcode":"7000",
    "addr:street":"Rue Grande Triperie;Hainaut",
    "iso:country":"BE",
    "sg:address":"Rue Grande Triperie 3",
    "sg:city":"Mons",
    "sg:orig_category":"Avocats and conseillers juridiques",
    "sg:phone":"+32 65 56 90 10",
    "sg:postcode":"7000",
    "sg:province":"Hainaut",
    "wof:name":"Vincent Dieu",
    "wof:placetype":"venue"
},
  "geometry": {"coordinates":[3.9521260262,50.4517745972],"type":"Point"}
}