{
  "type": "Feature",
  "properties": {
    "iso:country":"BE",
    "sg:address":"Omgangstraat 145",
    "sg:city":"Bornem",
    "sg:orig_category":"Boekhouders",
    "sg:phone":"+32 52 33 22 72",
    "sg:postcode":"2880",
    "sg:province":"Antwerpen",
    "wof:name":"Gislaine Maerevoet",
    "wof:placetype":"venue"
},
  "geometry": {"coordinates":[4.1985039711,51.0633888245],"type":"Point"}
}