{
  "type": "Feature",
  "properties": {
    "addr:full":"Rue Dieudonn\u00e9 Jacobs 34 Saint-nicolas (montegn\u00e9e) Li\u00e8ge 4420",
    "addr:housenumber":"34",
    "addr:postcode":"4420",
    "addr:street":"Rue Dieudonne\u0301 Jacobs;Montegne\u0301E",
    "iso:country":"BE",
    "sg:address":"Rue Dieudonn\u00e9 Jacobs 34",
    "sg:city":"Saint-nicolas (montegn\u00e9e)",
    "sg:classifiers":[
        {
            "category":"Real Estate",
            "subcategory":"Architect",
            "type":"Services"
        }
    ],
    "sg:phone":"+32 4 233 19 98",
    "sg:postcode":"4420",
    "sg:province":"Li\u00e8ge",
    "wof:name":"Di Panfilo B",
    "wof:placetype":"venue"
},
  "geometry": {"coordinates":[5.5188231468,50.6293144226],"type":"Point"}
}