{
  "type": "Feature",
  "properties": {
    "addr:full":"Weier 6 Olen Antwerpen 2250",
    "addr:housenumber":"6",
    "addr:postcode":"2250",
    "addr:street":"Weier",
    "iso:country":"BE",
    "sg:address":"Weier 6",
    "sg:city":"Olen",
    "sg:orig_category":"Entretien and r\u00e9parations de voitures",
    "sg:phone":"+32 14 21 39 62",
    "sg:postcode":"2250",
    "sg:province":"Antwerpen",
    "wof:name":"L. Laenen",
    "wof:placetype":"venue"
},
  "geometry": {"coordinates":[4.9099898338,51.170211792],"type":"Point"}
}