{
  "type": "Feature",
  "properties": {
    "addr:full":"Chauss\u00e9e De Bruxelles 404 Enghien (petit-enghien) Hainaut 7850",
    "addr:housenumber":"404",
    "addr:postcode":"7850",
    "addr:street":"Chausse\u0301E De Bruxelles",
    "iso:country":"BE",
    "sg:address":"Chauss\u00e9e De Bruxelles 404",
    "sg:city":"Enghien (petit-enghien)",
    "sg:classifiers":[
        {
            "category":"Building & Trades",
            "subcategory":"Electrical",
            "type":"Services"
        }
    ],
    "sg:phone":"+32 2 395 37 22",
    "sg:postcode":"7850",
    "sg:province":"Hainaut",
    "sg:tags":[
        "electric",
        "-",
        "housewiring",
        "contractor"
    ],
    "wof:name":"Delor Electricity Sprl",
    "wof:placetype":"venue"
},
  "geometry": {"coordinates":[4.0551757812,50.6912269592],"type":"Point"}
}