{
  "type": "Feature",
  "properties": {
    "addr:full":"Baalsebaan 161 Tremelo Vlaams-Brabant 3120",
    "addr:housenumber":"161",
    "addr:postcode":"3120",
    "addr:street":"Baalsebaan",
    "iso:country":"BE",
    "sg:address":"Baalsebaan 161",
    "sg:city":"Tremelo",
    "sg:classifiers":[
        {
            "category":"Real Estate",
            "subcategory":"Architect",
            "type":"Services"
        }
    ],
    "sg:phone":"+32 16 53 20 59",
    "sg:postcode":"3120",
    "sg:province":"Vlaams-Brabant",
    "wof:name":"Torfs Bvba",
    "wof:placetype":"venue"
},
  "geometry": {"coordinates":[4.7298679352,50.9945526123],"type":"Point"}
}