{
  "type": "Feature",
  "properties": {
    "addr:full":"Rijksweg 1 Dilsen-stokkem Limburg 3650",
    "addr:housenumber":"1",
    "addr:postcode":"3650",
    "addr:street":"Rijksweg",
    "iso:country":"BE",
    "sg:address":"Rijksweg 1",
    "sg:city":"Dilsen-stokkem",
    "sg:orig_category":"Eleveurs de bovins",
    "sg:phone":"+32 89 75 66 02",
    "sg:postcode":"3650",
    "sg:province":"Limburg",
    "wof:name":"Pieter Winkels",
    "wof:placetype":"venue"
},
  "geometry": {"coordinates":[5.7266697884,51.0228614807],"type":"Point"}
}