{
  "type": "Feature",
  "properties": {
    "addr:full":"Borreshoefstraat 1bb Dilsen-stokkem Limburg 3650",
    "addr:housenumber":"1bb",
    "addr:postcode":"3650",
    "addr:street":"Borreshoefstraat",
    "iso:country":"BE",
    "sg:address":"Borreshoefstraat 1bb",
    "sg:city":"Dilsen-stokkem",
    "sg:orig_category":"Pain, p\u00e2tisseries and confiseries",
    "sg:phone":"+32 89 75 40 06",
    "sg:postcode":"3650",
    "sg:province":"Limburg",
    "wof:name":"Hendrikus Gonnissen",
    "wof:placetype":"venue"
},
  "geometry": {"coordinates":[5.7274570465,51.0338783264],"type":"Point"}
}