{
  "type": "Feature",
  "properties": {
    "iso:country":"BE",
    "sg:address":"P. Vanderscheldenstraat 38bb",
    "sg:city":"Oudenaarde",
    "sg:orig_category":"Banques and organismes de cr\u00e9dit",
    "sg:phone":"+32 55 30 23 24",
    "sg:postcode":"9700",
    "sg:province":"Oost-Vlaanderen",
    "wof:name":"Bank Van Breda",
    "wof:placetype":"venue"
},
  "geometry": {"coordinates":[3.6045050621,50.8507652283],"type":"Point"}
}