{
  "type": "Feature",
  "properties": {
    "addr:full":"Rue Des Etangs Du Cur\u00c9 13 Braine-le-chateau Brabant Wallon 1440",
    "addr:housenumber":"13",
    "addr:postcode":"1440",
    "addr:street":"Rue Des Etangs Du Cure\u0301;Brabant Wallon",
    "iso:country":"BE",
    "sg:address":"Rue Des Etangs Du Cur\u00c9 13",
    "sg:city":"Braine-le-chateau",
    "sg:orig_category":"Elektrische installaties voor woningen",
    "sg:phone":"+32 2 366 11 69",
    "sg:postcode":"1440",
    "sg:province":"Brabant Wallon",
    "wof:name":"E G C I",
    "wof:placetype":"venue"
},
  "geometry": {"coordinates":[4.3030529022,50.6803398132],"type":"Point"}
}