{
  "type": "Feature",
  "properties": {
    "addr:full":"Lange Lozanastraat 107 Antwerpen Antwerpen 2018",
    "addr:housenumber":"107",
    "addr:postcode":"2018",
    "addr:street":"Lange Lozanastraat",
    "iso:country":"BE",
    "sg:address":"Lange Lozanastraat 107",
    "sg:city":"Antwerpen",
    "sg:classifiers":[
        {
            "category":"Professional",
            "subcategory":"Lawyer & Legal Services",
            "type":"Services"
        }
    ],
    "sg:phone":"+32 3 238 85 57",
    "sg:postcode":"2018",
    "sg:province":"Antwerpen",
    "wof:name":"Bruyninckx F",
    "wof:placetype":"venue"
},
  "geometry": {"coordinates":[4.4052219391,51.2034378052],"type":"Point"}
}