{
  "type": "Feature",
  "properties": {
    "addr:full":"Halstraat 9 Maasmechelen Limburg 3631",
    "addr:housenumber":"9",
    "addr:postcode":"3631",
    "addr:street":"Halstraat",
    "iso:country":"BE",
    "sg:address":"Halstraat 9",
    "sg:city":"Maasmechelen",
    "sg:orig_category":"Bloemen and planten Tuinen",
    "sg:phone":"+32 89 76 56 40",
    "sg:postcode":"3631",
    "sg:province":"Limburg",
    "wof:name":"Fraussen-merlo",
    "wof:placetype":"venue"
},
  "geometry": {"coordinates":[5.7239232063,50.9423713684],"type":"Point"}
}