{
  "type": "Feature",
  "properties": {
    "iso:country":"BE",
    "sg:address":"Dorpsstr 55",
    "sg:city":"Kalmthout",
    "sg:classifiers":[
        {
            "category":"Food & Beverages",
            "subcategory":"Groceries & Convenience Stores",
            "type":"Retail Goods"
        }
    ],
    "sg:phone":"+32 3 666 88 87",
    "sg:postcode":"2920",
    "sg:province":"Antwerpen",
    "sg:tags":[
        "product",
        "related"
    ],
    "wof:name":"Confiserie Luyts Nv",
    "wof:placetype":"venue"
},
  "geometry": {"coordinates":[4.4738588333,51.3953971863],"type":"Point"}
}