{
  "type": "Feature",
  "properties": {
    "addr:full":"Keppestraat 73 Aalst Oost-Vlaanderen 9320",
    "addr:housenumber":"73",
    "addr:postcode":"9320",
    "addr:street":"Keppestraat",
    "iso:country":"BE",
    "sg:address":"Keppestraat 73",
    "sg:city":"Aalst",
    "sg:orig_category":"Activit\u00e9s diverses d'imprimerie. Agences de publicit\u00e9",
    "sg:phone":"+32 53 78 97 65",
    "sg:postcode":"9320",
    "sg:province":"Oost-Vlaanderen",
    "wof:name":"The G.d.s. Touch",
    "wof:placetype":"venue"
},
  "geometry": {"coordinates":[4.0553851128,50.9209976196],"type":"Point"}
}