{
  "type": "Feature",
  "properties": {
    "addr:full":"Avenue Du Roi 22 Sint-gillis/saint-gilles Bruxelles-Capitale 1060",
    "addr:housenumber":"22",
    "addr:postcode":"1060",
    "addr:street":"Avenue Du Roi",
    "iso:country":"BE",
    "sg:address":"Avenue Du Roi 22",
    "sg:city":"Sint-gillis/saint-gilles",
    "sg:orig_category":"Agences d\u00b4interim and personnel temporaire",
    "sg:phone":"+32 2 534 38 00",
    "sg:postcode":"1060",
    "sg:province":"Bruxelles-Capitale",
    "wof:name":"Allo Int\u00c9rim",
    "wof:placetype":"venue"
},
  "geometry": {"coordinates":[4.3336229324,50.8312110901],"type":"Point"}
}