{
  "type": "Feature",
  "properties": {
    "addr:full":"Rue Masson 10bb Verviers Li\u00e8ge 4800",
    "addr:housenumber":"10bb",
    "addr:postcode":"4800",
    "addr:street":"Rue Masson",
    "iso:country":"BE",
    "sg:address":"Rue Masson 10bb",
    "sg:city":"Verviers",
    "sg:orig_category":"Ordinateurs and \u00e9quipement informatique",
    "sg:phone":"+32 87 31 74 26",
    "sg:postcode":"4800",
    "sg:province":"Li\u00e8ge",
    "wof:name":"M.m.b.s. Cash & Carry",
    "wof:placetype":"venue"
},
  "geometry": {"coordinates":[5.8633379936,50.5947914124],"type":"Point"}
}