{
  "type": "Feature",
  "properties": {
    "addr:full":"Stationsstraat 30 Oudenburg West-Vlaanderen 8460",
    "addr:housenumber":"30",
    "addr:postcode":"8460",
    "addr:street":"Stationsstraat",
    "iso:country":"BE",
    "sg:address":"Stationsstraat 30",
    "sg:city":"Oudenburg",
    "sg:classifiers":[
        {
            "category":"Home & Garden",
            "subcategory":"Carpets & Floor Coverings",
            "type":"Retail Goods"
        }
    ],
    "sg:postcode":"8460",
    "sg:province":"West-Vlaanderen",
    "sg:tags":[
        "tile"
    ],
    "wof:name":"Anra",
    "wof:placetype":"venue"
},
  "geometry": {"coordinates":[3.0062589645,51.1969146729],"type":"Point"}
}