{
  "type": "Feature",
  "properties": {
    "addr:full":"La Bouhaye 61 Herve (battice) Li\u00e8ge 4651",
    "addr:housenumber":"61",
    "addr:postcode":"4651",
    "addr:street":"Bouhaye",
    "iso:country":"BE",
    "sg:address":"La Bouhaye 61",
    "sg:city":"Herve (battice)",
    "sg:classifiers":[
        {
            "category":"Building & Trades",
            "subcategory":"Landscaping Services",
            "type":"Services"
        }
    ],
    "sg:phone":"+32 87 67 57 88",
    "sg:postcode":"4651",
    "sg:province":"Li\u00e8ge",
    "sg:tags":[
        "gardening",
        "garden",
        "maintenance"
    ],
    "wof:name":"Homme Vert (l')",
    "wof:placetype":"venue"
},
  "geometry": {"coordinates":[5.8021588326,50.6346855164],"type":"Point"}
}