{
  "type": "Feature",
  "properties": {
    "iso:country":"BE",
    "sg:address":"Naamsestraat 129",
    "sg:city":"Leuven",
    "sg:orig_category":"Krantenwinkels Rookartikelen",
    "sg:phone":"+32 16 22 82 05",
    "sg:postcode":"3000",
    "sg:province":"Vlaams-Brabant",
    "wof:name":"Fa. Rentmeesters",
    "wof:placetype":"venue"
},
  "geometry": {"coordinates":[4.6996469498,50.8712768555],"type":"Point"}
}