{
  "type": "Feature",
  "properties": {
    "addr:full":"Rue Dethy 12 Sint-gillis/saint-gilles Bruxelles-Capitale 1060",
    "addr:housenumber":"12",
    "addr:postcode":"1060",
    "addr:street":"Rue Dethy",
    "iso:country":"BE",
    "sg:address":"Rue Dethy 12",
    "sg:city":"Sint-gillis/saint-gilles",
    "sg:classifiers":[
        {
            "category":"Personal",
            "subcategory":"Beauty Salon",
            "type":"Services"
        }
    ],
    "sg:phone":"+32 2 537 99 10",
    "sg:postcode":"1060",
    "sg:province":"Bruxelles-Capitale",
    "sg:tags":[
        "de",
        "coiffure"
    ],
    "wof:name":"Coiffure Imagine'",
    "wof:placetype":"venue"
},
  "geometry": {"coordinates":[4.3432230949,50.8288230896],"type":"Point"}
}