{
  "type": "Feature",
  "properties": {
    "addr:full":"Patronaatsweg 1 Putte Antwerpen 2580",
    "addr:housenumber":"1",
    "addr:postcode":"2580",
    "addr:street":"Patronaatsweg",
    "iso:country":"BE",
    "sg:address":"Patronaatsweg 1",
    "sg:city":"Putte",
    "sg:orig_category":"M\u00e9decins and sp\u00e9cialistes",
    "sg:phone":"+32 15 76 13 52",
    "sg:postcode":"2580",
    "sg:province":"Antwerpen",
    "wof:name":"Consultatiebur.jonge Kind",
    "wof:placetype":"venue"
},
  "geometry": {"coordinates":[4.6254000664,51.056060791],"type":"Point"}
}