{
  "type": "Feature",
  "properties": {
    "addr:full":"Chauss\u00e9e De Waterloo 1000 Bruxelles (uccle) Bruxelles-Capitale 1180",
    "addr:postcode":"1000;1180",
    "addr:street":"Chausse\u0301E De Waterloo",
    "iso:country":"BE",
    "sg:address":"Chauss\u00e9e De Waterloo 1000",
    "sg:city":"Bruxelles (uccle)",
    "sg:classifiers":[
        {
            "category":"Bars & Pubs",
            "type":"Food & Drink"
        }
    ],
    "sg:phone":"+32 2 375 48 85",
    "sg:postcode":"1180",
    "sg:province":"Bruxelles-Capitale",
    "wof:name":"Coll\u00e8ge (le)",
    "wof:placetype":"venue"
},
  "geometry": {"coordinates":[4.3744158745,50.8008842468],"type":"Point"}
}