{
  "type": "Feature",
  "properties": {
    "iso:country":"BE",
    "sg:address":"Boesbeeklaan 19",
    "sg:city":"Gent",
    "sg:orig_category":"Fotografen and fotostudio's",
    "sg:phone":"+32 9 271 19 03",
    "sg:postcode":"9051",
    "sg:province":"Oost-Vlaanderen",
    "wof:name":"Geert De Vos",
    "wof:placetype":"venue"
},
  "geometry": {"coordinates":[3.6813559532,51.0272407532],"type":"Point"}
}