{
  "type": "Feature",
  "properties": {
    "iso:country":"BE",
    "sg:address":"Pomphuisstraat 19",
    "sg:city":"Sint-truiden",
    "sg:orig_category":"Fruitteelt",
    "sg:phone":"+32 11 68 48 15",
    "sg:postcode":"3806",
    "sg:province":"Limburg",
    "wof:name":"Hugo Nicolai",
    "wof:placetype":"venue"
},
  "geometry": {"coordinates":[5.1319561005,50.7733688354],"type":"Point"}
}