{
  "type": "Feature",
  "properties": {
    "iso:country":"BE",
    "sg:address":"Antwerpsesteenweg 66",
    "sg:city":"Lier",
    "sg:classifiers":[
        {
            "category":"Health Services",
            "subcategory":"Dentist",
            "type":"Services"
        }
    ],
    "sg:phone":"+32 3 480 44 03",
    "sg:postcode":"2500",
    "sg:province":"Antwerpen",
    "wof:name":"Gullentops M",
    "wof:placetype":"venue"
},
  "geometry": {"coordinates":[4.5594801903,51.137928009],"type":"Point"}
}