{
  "type": "Feature",
  "properties": {
    "iso:country":"BE",
    "sg:address":"Roterijstraat 19",
    "sg:city":"Lendelede",
    "sg:orig_category":"Antiquit\u00e9s. Construction de maisons",
    "sg:phone":"+32 51 31 50 90",
    "sg:postcode":"8860",
    "sg:province":"West-Vlaanderen",
    "wof:name":"Dehullu Hugo",
    "wof:placetype":"venue"
},
  "geometry": {"coordinates":[3.2125649452,50.8860664368],"type":"Point"}
}