{
  "type": "Feature",
  "properties": {
    "iso:country":"BE",
    "sg:address":"Achel Statie 97 Box B",
    "sg:city":"Hamont-achel (achel)",
    "sg:classifiers":[
        {
            "category":"Professional",
            "subcategory":"Management & Consulting",
            "type":"Services"
        }
    ],
    "sg:phone":"+32 11 44 07 79",
    "sg:postcode":"3930",
    "sg:province":"Limburg",
    "sg:tags":[
        "consultant",
        "agency",
        "advertising"
    ],
    "wof:name":"Vision Line Bvba",
    "wof:placetype":"venue"
},
  "geometry": {"coordinates":[5.5450549126,51.2511863708],"type":"Point"}
}