{
  "type": "Feature",
  "properties": {
    "iso:country":"BE",
    "sg:address":"Rue De Presles 220",
    "sg:city":"Ch\u00e2telet",
    "sg:classifiers":[
        {
            "category":"Food & Beverages",
            "subcategory":"Fruits & Vegetables",
            "type":"Retail Goods"
        }
    ],
    "sg:phone":"+32 71 38 39 54",
    "sg:postcode":"6200",
    "sg:province":"Hainaut",
    "sg:tags":[
        "-"
    ],
    "wof:name":"Dimanche M",
    "wof:placetype":"venue"
},
  "geometry": {"coordinates":[4.5362138748,50.3878364563],"type":"Point"}
}