{
  "type": "Feature",
  "properties": {
    "iso:country":"BE",
    "sg:address":"Heskeberg 6",
    "sg:city":"Dalhem (neufch\u00e2teau (lez-vis\u00e9))",
    "sg:classifiers":[
        {
            "category":"Building & Trades",
            "subcategory":"Plumbing",
            "type":"Services"
        }
    ],
    "sg:phone":"+32 4 376 73 22",
    "sg:postcode":"4608",
    "sg:province":"Li\u00e8ge",
    "sg:tags":[
        "repair",
        "mainten",
        "-",
        "central",
        "heating"
    ],
    "wof:name":"Lepot G",
    "wof:placetype":"venue"
},
  "geometry": {"coordinates":[5.7779669762,50.7188148499],"type":"Point"}
}