{
  "type": "Feature",
  "properties": {
    "iso:country":"BE",
    "sg:address":"Oudstrijderslaan 39",
    "sg:city":"Kuurne",
    "sg:orig_category":"Zuivelproducten",
    "sg:phone":"+32 56 72 92 77",
    "sg:postcode":"8520",
    "sg:province":"West-Vlaanderen",
    "wof:name":"Johan Loyson",
    "wof:placetype":"venue"
},
  "geometry": {"coordinates":[3.2900099754,50.8547134399],"type":"Point"}
}