{
  "type": "Feature",
  "properties": {
    "iso:country":"BE",
    "sg:address":"Rue Du Nord 21",
    "sg:city":"Courcelles",
    "sg:orig_category":"Traitements param\u00e9dicaux",
    "sg:phone":"+32 71 46 09 38",
    "sg:postcode":"6180",
    "sg:province":"Hainaut",
    "wof:name":"Claude Morue",
    "wof:placetype":"venue"
},
  "geometry": {"coordinates":[4.3610172272,50.4627075195],"type":"Point"}
}