{
  "type": "Feature",
  "properties": {
    "iso:country":"BE",
    "sg:address":"Eduard Robeynslaan 70",
    "sg:city":"Diest",
    "sg:orig_category":"Elektrische installaties voor woningen HERSTELLING ELEKTRISCHE HUISHOUDAPPARATEN Huishoudapparaten, ",
    "sg:phone":"+32 13 31 10 06",
    "sg:postcode":"3290",
    "sg:province":"Vlaams-Brabant",
    "wof:name":"Electro-comfort",
    "wof:placetype":"venue"
},
  "geometry": {"coordinates":[5.0599451065,50.9774398804],"type":"Point"}
}