{
  "type": "Feature",
  "properties": {
    "iso:country":"BE",
    "sg:address":"Rue Du Moulin 64",
    "sg:city":"Quevy",
    "sg:orig_category":"Brood, gebak and snoepgoed",
    "sg:phone":"+32 65 58 63 61",
    "sg:postcode":"7041",
    "sg:province":"Hainaut",
    "wof:name":"Xavier Limbourg",
    "wof:placetype":"venue"
},
  "geometry": {"coordinates":[4.0332989693,50.3759689331],"type":"Point"}
}