{
  "type": "Feature",
  "properties": {
    "iso:country":"BE",
    "sg:address":"Hoogstr 25",
    "sg:city":"Kruishoutem",
    "sg:classifiers":[
        {
            "category":"Food & Beverages",
            "subcategory":"Dairy",
            "type":"Retail Goods"
        }
    ],
    "sg:phone":"+32 9 333 93 99",
    "sg:postcode":"9770",
    "sg:province":"Oost-Vlaanderen",
    "sg:tags":[
        "product",
        "related"
    ],
    "wof:name":"Melk Inricht. Kruishoutem Nv (mik)",
    "wof:placetype":"venue"
},
  "geometry": {"coordinates":[3.5290799141,50.9035415649],"type":"Point"}
}