{
  "type": "Feature",
  "properties": {
    "addr:full":"Penitentenstraat 26 Gent Oost-Vlaanderen 9000",
    "addr:housenumber":"26",
    "addr:postcode":"9000",
    "addr:street":"Penitentenstraat;Oost-Vlaanderen",
    "iso:country":"BE",
    "sg:address":"Penitentenstraat 26",
    "sg:city":"Gent",
    "sg:classifiers":[
        {
            "category":"Health Services",
            "subcategory":"Doctor",
            "type":"Services"
        }
    ],
    "sg:phone":"+32 9 225 77 15",
    "sg:postcode":"9000",
    "sg:province":"Oost-Vlaanderen",
    "sg:tags":[
        "medicinephysicians",
        "surgeon"
    ],
    "wof:name":"Luyten Hilde",
    "wof:placetype":"venue"
},
  "geometry": {"coordinates":[3.7266499996,51.05834198],"type":"Point"}
}