{
  "type": "Feature",
  "properties": {
    "addr:full":"Bredestraat 4 Antwerpen Antwerpen 2000",
    "addr:housenumber":"4",
    "addr:postcode":"2000",
    "addr:street":"Bredestraat",
    "iso:country":"BE",
    "sg:address":"Bredestraat 4",
    "sg:city":"Antwerpen",
    "sg:classifiers":[
        {
            "category":"Professional",
            "subcategory":"Business Services",
            "type":"Services"
        }
    ],
    "sg:phone":"+32 3 233 35 75",
    "sg:postcode":"2000",
    "sg:province":"Antwerpen",
    "sg:tags":[
        "firm"
    ],
    "wof:name":"Lectra Bvba",
    "wof:placetype":"venue"
},
  "geometry": {"coordinates":[4.4020428658,51.2151298523],"type":"Point"}
}