{
  "type": "Feature",
  "properties": {
    "iso:country":"BE",
    "sg:address":"Bergstraat 5",
    "sg:city":"Heuvelland",
    "sg:orig_category":"Eleveurs and marchands de porcs. Eleveurs de bovins",
    "sg:phone":"+32 57 44 47 24",
    "sg:postcode":"8958",
    "sg:province":"West-Vlaanderen",
    "wof:name":"Marc Dumeez",
    "wof:placetype":"venue"
},
  "geometry": {"coordinates":[2.7718191147,50.7820930481],"type":"Point"}
}