{
  "type": "Feature",
  "properties": {
    "addr:full":"Boulevard Du Centenaire 20 Bruxelles Bruxelles-Capitale 1020",
    "addr:housenumber":"20",
    "addr:postcode":"1020",
    "addr:street":"Boulevard Du Centenaire",
    "iso:country":"BE",
    "sg:address":"Boulevard Du Centenaire 20",
    "sg:city":"Bruxelles",
    "sg:classifiers":[
        {
            "category":"Cinema",
            "subcategory":"Movie Theater",
            "type":"Entertainment"
        }
    ],
    "sg:phone":"+32 2 474 26 00",
    "sg:postcode":"1020",
    "sg:province":"Bruxelles-Capitale",
    "wof:name":"Kinepolis",
    "wof:placetype":"venue"
},
  "geometry": {"coordinates":[4.3399200439,50.8963127136],"type":"Point"}
}