{
  "type": "Feature",
  "properties": {
    "addr:full":"Leopoldwal 5 Tongeren Limburg 3700",
    "addr:housenumber":"5",
    "addr:postcode":"3700",
    "addr:street":"Leopoldwal",
    "iso:country":"BE",
    "sg:address":"Leopoldwal 5",
    "sg:city":"Tongeren",
    "sg:orig_category":"Antiek",
    "sg:phone":"+32 12 23 50 93",
    "sg:postcode":"3700",
    "sg:province":"Limburg",
    "wof:name":"Martin Castermans",
    "wof:placetype":"venue"
},
  "geometry": {"coordinates":[5.4704608917,50.7824516296],"type":"Point"}
}