{
  "type": "Feature",
  "properties": {
    "iso:country":"BE",
    "sg:address":"Rue Aviateur Huens 49",
    "sg:city":"Rixensart",
    "sg:classifiers":[
        {
            "category":"Shopping",
            "subcategory":"Pharmacy",
            "type":"Retail Goods"
        }
    ],
    "sg:phone":"+32 2 653 65 44",
    "sg:postcode":"1330",
    "sg:province":"Brabant Wallon",
    "sg:tags":[
        "store",
        "drug"
    ],
    "wof:name":"Drod\u00e9cor Sc",
    "wof:placetype":"venue"
},
  "geometry": {"coordinates":[4.5309300423,50.7156486511],"type":"Point"}
}