{
  "type": "Feature",
  "properties": {
    "addr:full":"Rue Du Broux 12 Beauvechain Brabant Wallon 1320",
    "addr:housenumber":"12",
    "addr:postcode":"1320",
    "addr:street":"Rue Du Broux",
    "iso:country":"BE",
    "sg:address":"Rue Du Broux 12",
    "sg:city":"Beauvechain",
    "sg:classifiers":[
        {
            "category":"Banks & Credit Unions",
            "subcategory":"Investment Brokerage",
            "type":"Services"
        }
    ],
    "sg:phone":"+32 10 86 03 47",
    "sg:postcode":"1320",
    "sg:province":"Brabant Wallon",
    "sg:tags":[
        "repair",
        "-",
        "installation",
        "sanitary",
        "article"
    ],
    "wof:name":"Cantella M",
    "wof:placetype":"venue"
},
  "geometry": {"coordinates":[4.7788629532,50.7787666321],"type":"Point"}
}