{
  "type": "Feature",
  "properties": {
    "iso:country":"BE",
    "sg:address":"Rue Joseph Wauters 11",
    "sg:city":"Charleroi (jumet)",
    "sg:classifiers":[
        {
            "category":"Personal",
            "subcategory":"Nail Salon",
            "type":"Services"
        }
    ],
    "sg:phone":"+32 476 34 76 43",
    "sg:postcode":"6040",
    "sg:province":"Hainaut",
    "sg:tags":[
        "pedicure"
    ],
    "wof:name":"Poty L",
    "wof:placetype":"venue"
},
  "geometry": {"coordinates":[4.4243769646,50.4441452026],"type":"Point"}
}