{
  "type": "Feature",
  "properties": {
    "iso:country":"BE",
    "sg:address":"Rue De L\u00b4etang 24",
    "sg:city":"Seraing",
    "sg:orig_category":"Traitement and fa\u00e7onnage de la pierre. Rev\u00eatements de sols and murs",
    "sg:phone":"+32 4 337 23 49",
    "sg:postcode":"4102",
    "sg:province":"Li\u00e8ge",
    "wof:name":"Granidesign Sprl Hanot",
    "wof:placetype":"venue"
},
  "geometry": {"coordinates":[5.5395140648,50.5978546143],"type":"Point"}
}