{
  "type": "Feature",
  "properties": {
    "iso:country":"BE",
    "sg:address":"Dikkebusseweg 44",
    "sg:city":"Ieper",
    "sg:orig_category":"M\u00e9decins and sp\u00e9cialistes",
    "sg:phone":"+32 57 20 99 58",
    "sg:postcode":"8900",
    "sg:province":"West-Vlaanderen",
    "wof:name":"Jan Capoen",
    "wof:placetype":"venue"
},
  "geometry": {"coordinates":[2.876142025,50.8450164795],"type":"Point"}
}