{
  "type": "Feature",
  "properties": {
    "addr:full":"Rue De Fauquez 21ba Ittre Brabant Wallon 1460",
    "addr:housenumber":"21ba;1460",
    "addr:street":"Rue De Fauquez",
    "iso:country":"BE",
    "sg:address":"Rue De Fauquez 21ba",
    "sg:city":"Ittre",
    "sg:orig_category":"Loodgieterij, verwarming and sanitaire installaties",
    "sg:phone":"+32 67 64 66 40",
    "sg:postcode":"1460",
    "sg:province":"Brabant Wallon",
    "wof:name":"A.n.d. Comfort",
    "wof:placetype":"venue"
},
  "geometry": {"coordinates":[4.2523870468,50.6338768005],"type":"Point"}
}