{
  "type": "Feature",
  "properties": {
    "iso:country":"BE",
    "sg:address":"Dalemhof 28",
    "sg:city":"Leuven",
    "sg:classifiers":[
        {
            "category":"Professional",
            "subcategory":"Computer Services",
            "type":"Services"
        }
    ],
    "sg:phone":"+32 16 29 80 45",
    "sg:postcode":"3000",
    "sg:province":"Vlaams-Brabant",
    "sg:tags":[
        "-",
        "security",
        "processing",
        "data"
    ],
    "wof:name":"Better Access Nv",
    "wof:placetype":"venue"
},
  "geometry": {"coordinates":[4.738779068,50.863986969],"type":"Point"}
}