{
  "type": "Feature",
  "properties": {
    "addr:full":"Puursesteenweg 201 Bornem Antwerpen 2880",
    "addr:housenumber":"201",
    "addr:postcode":"2880",
    "addr:street":"Puursesteenweg",
    "iso:country":"BE",
    "sg:address":"Puursesteenweg 201",
    "sg:city":"Bornem",
    "sg:classifiers":[
        {
            "category":"Professional",
            "subcategory":"Management & Consulting",
            "type":"Services"
        }
    ],
    "sg:phone":"+32 475 50 07 53",
    "sg:postcode":"2880",
    "sg:province":"Antwerpen",
    "sg:tags":[
        "-",
        "processing",
        "data",
        "consultant"
    ],
    "wof:name":"Pcare Bvba",
    "wof:placetype":"venue"
},
  "geometry": {"coordinates":[4.2470631599,51.0933914185],"type":"Point"}
}