{
  "type": "Feature",
  "properties": {
    "iso:country":"BE",
    "sg:address":"Mechelsesteenweg 64",
    "sg:city":"Mortsel",
    "sg:classifiers":[
        {
            "category":"Insurance",
            "subcategory":"Insurance Agent",
            "type":"Services"
        }
    ],
    "sg:phone":"+32 3 449 00 22",
    "sg:postcode":"2640",
    "sg:province":"Antwerpen",
    "sg:tags":[
        "verzekeringsmakelaars",
        "expert"
    ],
    "wof:name":"Lens",
    "wof:placetype":"venue"
},
  "geometry": {"coordinates":[4.4514389038,51.1682052612],"type":"Point"}
}