{
  "type": "Feature",
  "properties": {
    "iso:country":"BE",
    "sg:address":"Boerenkrijglaan 14d",
    "sg:city":"Olen",
    "sg:classifiers":[
        {
            "category":"Personal",
            "subcategory":"Nail Salon",
            "type":"Services"
        }
    ],
    "sg:phone":"+32 14 23 69 80",
    "sg:postcode":"2250",
    "sg:province":"Antwerpen",
    "sg:tags":[
        "pedicure"
    ],
    "wof:name":"Luyten L",
    "wof:placetype":"venue"
},
  "geometry": {"coordinates":[4.8633179665,51.1418876648],"type":"Point"}
}