{
  "type": "Feature",
  "properties": {
    "addr:full":"Hoogbraak 6 Baarle-hertog Antwerpen 2387",
    "addr:housenumber":"6",
    "addr:postcode":"2387",
    "addr:street":"Hoogbraak",
    "iso:country":"BE",
    "sg:address":"Hoogbraak 6",
    "sg:city":"Baarle-hertog",
    "sg:orig_category":"Artiestenbureaus Boekenuitgeverijen Divers amusement Diverse zakelijke dienstverlening",
    "sg:phone":"+32 14 69 99 11",
    "sg:postcode":"2387",
    "sg:province":"Antwerpen",
    "wof:name":"Artiestenbureau Roelen Piet",
    "wof:placetype":"venue"
},
  "geometry": {"coordinates":[4.9316248894,51.4420585632],"type":"Point"}
}