{
  "type": "Feature",
  "properties": {
    "iso:country":"BE",
    "sg:address":"25",
    "sg:city":"Tieltstraat 8760 Meulebeke",
    "sg:orig_category":"Miscellaneous Products",
    "sg:phone":"+32 51 48 88 66",
    "sg:postcode":"25",
    "wof:name":"Moerman Nv",
    "wof:placetype":"venue"
},
  "geometry": {"coordinates":[3.3022549152,50.9678382874],"type":"Point"}
}