{
  "type": "Feature",
  "properties": {
    "iso:country":"BE",
    "sg:address":"Diksmuidelaan 142",
    "sg:city":"Antwerpen",
    "sg:orig_category":"Electrom\u00e9nager, t\u00e9l\u00e9visions and radios. Instruments de musique. Animations diverses",
    "sg:phone":"+32 3 322 52 17",
    "sg:postcode":"2600",
    "sg:province":"Antwerpen",
    "wof:name":"Disco Service",
    "wof:placetype":"venue"
},
  "geometry": {"coordinates":[4.4174151421,51.1974411011],"type":"Point"}
}