{
  "type": "Feature",
  "properties": {
    "iso:country":"BE",
    "sg:address":"Rue Sous Le Chateau 4-6",
    "sg:city":"Hoei",
    "sg:orig_category":"Banken and kredietinstellingen",
    "sg:phone":"+32 85 21 48 36",
    "sg:postcode":"4500",
    "sg:province":"Li\u00e8ge",
    "wof:name":"Banque De Cr\u00c9dit Professionnelles",
    "wof:placetype":"venue"
},
  "geometry": {"coordinates":[5.2389259338,50.5184516907],"type":"Point"}
}