{
  "type": "Feature",
  "properties": {
    "addr:full":"Chauss\u00c9e D'houthem 40 Komen-waasten/comines-warneton Hainaut 7781",
    "addr:housenumber":"40;7781",
    "addr:street":"Chausse\u0301E D'Houthem",
    "iso:country":"BE",
    "sg:address":"Chauss\u00c9e D'houthem 40",
    "sg:city":"Komen-waasten/comines-warneton",
    "sg:orig_category":"Eleveurs de bovins",
    "sg:phone":"+32 56 55 53 91",
    "sg:postcode":"7781",
    "sg:province":"Hainaut",
    "wof:name":"Joseph Vandelannoitte",
    "wof:placetype":"venue"
},
  "geometry": {"coordinates":[2.9796919823,50.7818374634],"type":"Point"}
}