{
  "type": "Feature",
  "properties": {
    "iso:country":"BE",
    "sg:address":"Verbindingstraat 2",
    "sg:city":"Evergem",
    "sg:orig_category":"Gespecialiseerde residenti\u00eble bouw Woningbouw",
    "sg:phone":"+32 9 253 09 63",
    "sg:postcode":"9940",
    "sg:province":"Oost-Vlaanderen",
    "wof:name":"Denis Goethals",
    "wof:placetype":"venue"
},
  "geometry": {"coordinates":[3.7693839073,51.1420478821],"type":"Point"}
}