{
  "type": "Feature",
  "properties": {
    "addr:full":"Rue Grande 9 Honnelles (autreppe) Hainaut 7387",
    "addr:housenumber":"9",
    "addr:postcode":"7387",
    "addr:street":"Rue Grande",
    "iso:country":"BE",
    "sg:address":"Rue Grande 9",
    "sg:city":"Honnelles (autreppe)",
    "sg:classifiers":[
        {
            "category":"Freight",
            "type":"Transportation"
        }
    ],
    "sg:phone":"+32 65 75 04 23",
    "sg:postcode":"7387",
    "sg:province":"Hainaut",
    "sg:tags":[
        "-",
        "transport"
    ],
    "wof:name":"Colot D",
    "wof:placetype":"venue"
},
  "geometry": {"coordinates":[3.7371509075,50.3495407104],"type":"Point"}
}