{
  "type": "Feature",
  "properties": {
    "addr:full":"Rue Des Moulins 41 Binche Hainaut 7134",
    "addr:housenumber":"41",
    "addr:postcode":"7134",
    "addr:street":"Rue Des Moulins",
    "iso:country":"BE",
    "sg:address":"Rue Des Moulins 41",
    "sg:city":"Binche",
    "sg:orig_category":"Articles de jardin",
    "sg:phone":"+32 64 33 60 81",
    "sg:postcode":"7134",
    "sg:province":"Hainaut",
    "wof:name":"Schietecatte",
    "wof:placetype":"venue"
},
  "geometry": {"coordinates":[4.2277488708,50.4231834412],"type":"Point"}
}