{
  "type": "Feature",
  "properties": {
    "addr:full":"Kortrijksestraat 355 Kortrijk West-Vlaanderen 8501",
    "addr:housenumber":"355",
    "addr:postcode":"8501",
    "addr:street":"Kortrijksestraat",
    "iso:country":"BE",
    "sg:address":"Kortrijksestraat 355",
    "sg:city":"Kortrijk",
    "sg:orig_category":"Fietsen",
    "sg:phone":"+32 56 35 43 66",
    "sg:postcode":"8501",
    "sg:province":"West-Vlaanderen",
    "wof:name":"Rijwielen Hallaert",
    "wof:placetype":"venue"
},
  "geometry": {"coordinates":[3.2516379356,50.8344802856],"type":"Point"}
}