{
  "type": "Feature",
  "properties": {
    "addr:full":"Brug Zuid 2a Aalter Oost-Vlaanderen 9880",
    "addr:housenumber":"2a",
    "addr:postcode":"9880",
    "addr:street":"Brug Zuid",
    "iso:country":"BE",
    "sg:address":"Brug Zuid 2a",
    "sg:city":"Aalter",
    "sg:classifiers":[
        {
            "category":"Retail",
            "subcategory":"Storage",
            "type":"Services"
        }
    ],
    "sg:phone":"+32 9 374 51 30",
    "sg:postcode":"9880",
    "sg:province":"Oost-Vlaanderen",
    "sg:tags":[
        "display",
        "cabinet"
    ],
    "wof:name":"Tecnoconcept Nv",
    "wof:placetype":"venue"
},
  "geometry": {"coordinates":[3.4409050941,51.1083297729],"type":"Point"}
}