{
  "type": "Feature",
  "properties": {
    "addr:full":"Wildebornstraat 116 Borgloon Limburg 3840",
    "addr:housenumber":"116",
    "addr:postcode":"3840",
    "addr:street":"Wildebornstraat",
    "iso:country":"BE",
    "sg:address":"Wildebornstraat 116",
    "sg:city":"Borgloon",
    "sg:orig_category":"Producteurs de fruits",
    "sg:phone":"+32 11 68 94 17",
    "sg:postcode":"3840",
    "sg:province":"Limburg",
    "wof:name":"Valere Bergers",
    "wof:placetype":"venue"
},
  "geometry": {"coordinates":[5.3441700935,50.8012466431],"type":"Point"}
}