{
  "type": "Feature",
  "properties": {
    "addr:full":"Eikestraat 21 Herzele Oost-Vlaanderen 9550",
    "addr:housenumber":"21",
    "addr:postcode":"9550",
    "addr:street":"Eikestraat;Oost-Vlaanderen",
    "iso:country":"BE",
    "sg:address":"Eikestraat 21",
    "sg:city":"Herzele",
    "sg:orig_category":"Sportclubs",
    "sg:phone":"+32 54 50 27 01",
    "sg:postcode":"9550",
    "sg:province":"Oost-Vlaanderen",
    "wof:name":"W.c. Unitas",
    "wof:placetype":"venue"
},
  "geometry": {"coordinates":[3.8914239407,50.8379325867],"type":"Point"}
}