{
  "type": "Feature",
  "properties": {
    "iso:country":"BE",
    "sg:address":"Varenstraat 137b130",
    "sg:city":"Houthalen-helchteren",
    "sg:orig_category":"Fietsen",
    "sg:phone":"+32 11 52 60 83",
    "sg:postcode":"3530",
    "sg:province":"Limburg",
    "wof:name":"Maria Mommen",
    "wof:placetype":"venue"
},
  "geometry": {"coordinates":[5.4069571495,51.0233383179],"type":"Point"}
}