{
  "type": "Feature",
  "properties": {
    "addr:full":"Bornedries 12 Sint-truiden Limburg 3800",
    "addr:housenumber":"12",
    "addr:postcode":"3800",
    "addr:street":"Bornedries",
    "iso:country":"BE",
    "sg:address":"Bornedries 12",
    "sg:city":"Sint-truiden",
    "sg:orig_category":"Fruitteelt",
    "sg:phone":"+32 11 68 95 23",
    "sg:postcode":"3800",
    "sg:province":"Limburg",
    "wof:name":"Florent Brans",
    "wof:placetype":"venue"
},
  "geometry": {"coordinates":[5.2035179138,50.8454666138],"type":"Point"}
}