{
  "type": "Feature",
  "properties": {
    "iso:country":"BE",
    "sg:address":"Fabrieksstraat 46",
    "sg:city":"Lebbeke",
    "sg:orig_category":"Fotografen and fotostudio's",
    "sg:phone":"+32 52 35 23 42",
    "sg:postcode":"9280",
    "sg:province":"Oost-Vlaanderen",
    "wof:name":"Frank Bahnmuller",
    "wof:placetype":"venue"
},
  "geometry": {"coordinates":[4.1529750824,50.9928474426],"type":"Point"}
}