{
  "type": "Feature",
  "properties": {
    "addr:full":"Rue Du Chateau D'eau 11 Neupr\u00e9 (rotheux-rimi\u00e8re) Li\u00e8ge 4120",
    "addr:housenumber":"11",
    "addr:postcode":"4120",
    "addr:street":"Rue Du Chateau D'Eau;Rotheux-Rimie\u0300Re",
    "iso:country":"BE",
    "sg:address":"Rue Du Chateau D'eau 11",
    "sg:city":"Neupr\u00e9 (rotheux-rimi\u00e8re)",
    "sg:classifiers":[
        {
            "category":"Building & Trades",
            "subcategory":"Landscaping Services",
            "type":"Services"
        }
    ],
    "sg:phone":"+32 4 246 02 43",
    "sg:postcode":"4120",
    "sg:province":"Li\u00e8ge",
    "sg:tags":[
        "access",
        "pond",
        "laying-out",
        "-"
    ],
    "wof:name":"Aqua Garden Center",
    "wof:placetype":"venue"
},
  "geometry": {"coordinates":[5.4505729675,50.5301933289],"type":"Point"}
}