{
  "type": "Feature",
  "properties": {
    "addr:full":"Place N. D. De La Paix 0 Namur Namur 5101",
    "addr:housenumber":"0",
    "addr:postcode":"5101",
    "addr:street":"Place N. D. De La Paix",
    "iso:country":"BE",
    "sg:address":"Place N. D. De La Paix 0",
    "sg:city":"Namur",
    "sg:orig_category":"Algemeen secundair onderwijs Technisch and beroeps secundair onderwijs",
    "sg:phone":"+32 81 30 19 61",
    "sg:postcode":"5101",
    "sg:province":"Namur",
    "wof:name":"Coll\u00c8ge N.d. De La Paix",
    "wof:placetype":"venue"
},
  "geometry": {"coordinates":[4.904815197,50.4481887817],"type":"Point"}
}