{
  "type": "Feature",
  "properties": {
    "iso:country":"BE",
    "sg:address":"Zeelaan 241",
    "sg:city":"Koksijde",
    "sg:classifiers":[
        {
            "category":"Bars & Pubs",
            "type":"Food & Drink"
        }
    ],
    "sg:phone":"+32 58 51 77 84",
    "sg:postcode":"8670",
    "sg:province":"West-Vlaanderen",
    "sg:tags":[
        "tavern"
    ],
    "wof:name":"Argus",
    "wof:placetype":"venue"
},
  "geometry": {"coordinates":[2.6372849941,51.1167144775],"type":"Point"}
}