{
  "type": "Feature",
  "properties": {
    "iso:country":"BE",
    "sg:address":"Rue Des Bruy\u00e8res 6",
    "sg:city":"Montigny-le-tilleul",
    "sg:classifiers":[
        {
            "category":"Health Services",
            "subcategory":"Doctor",
            "type":"Services"
        }
    ],
    "sg:phone":"+32 71 51 10 72",
    "sg:postcode":"6110",
    "sg:province":"Hainaut",
    "sg:tags":[
        "medicinephysicians",
        "surgeon"
    ],
    "wof:name":"Bultot A",
    "wof:placetype":"venue"
},
  "geometry": {"coordinates":[4.3604340553,50.3686637878],"type":"Point"}
}