{
  "type": "Feature",
  "properties": {
    "iso:country":"BE",
    "sg:address":"Rue Dor\u00e9e 12bis",
    "sg:city":"Tournai (templeuve)",
    "sg:classifiers":[
        {
            "category":"Professional",
            "subcategory":"Lawyer & Legal Services",
            "type":"Services"
        }
    ],
    "sg:phone":"+32 475 91 48 75",
    "sg:postcode":"7520",
    "sg:province":"Hainaut",
    "wof:name":"Gaillet Anne-sophie",
    "wof:placetype":"venue"
},
  "geometry": {"coordinates":[3.2817270756,50.6471099854],"type":"Point"}
}