{
  "type": "Feature",
  "properties": {
    "iso:country":"BE",
    "sg:address":"Clos Du Drossart 40",
    "sg:city":"Bruxelles (uccle)",
    "sg:classifiers":[
        {
            "category":"Utilities",
            "subcategory":"Refuse",
            "type":"Services"
        }
    ],
    "sg:phone":"+32 2 377 56 13",
    "sg:postcode":"1180",
    "sg:province":"Bruxelles-Capitale",
    "sg:tags":[
        "removal"
    ],
    "wof:name":"De Brouwer",
    "wof:placetype":"venue"
},
  "geometry": {"coordinates":[4.3551287651,50.7936134338],"type":"Point"}
}