{
  "type": "Feature",
  "properties": {
    "iso:country":"BE",
    "sg:address":"Rue Aux-fr\u00canes 36",
    "sg:city":"Li\u00c8ge",
    "sg:orig_category":"V\u00e9t\u00e9rinaires",
    "sg:phone":"+32 4 343 11 91",
    "sg:postcode":"4020",
    "sg:province":"Li\u00e8ge",
    "wof:name":"Chantal Beghin",
    "wof:placetype":"venue"
},
  "geometry": {"coordinates":[5.5842552185,50.6407203674],"type":"Point"}
}