{
  "type": "Feature",
  "properties": {
    "iso:country":"BE",
    "sg:address":"Place De L'abattoir 1",
    "sg:city":"Charleroi",
    "sg:classifiers":[
        {
            "category":"Wholesale",
            "subcategory":"Meat",
            "type":"Manufacturing & Wholesale Goods"
        }
    ],
    "sg:phone":"+32 71 42 38 45",
    "sg:postcode":"6000",
    "sg:province":"Hainaut",
    "sg:tags":[
        "whol",
        "-"
    ],
    "wof:name":"Goffin-nicolas",
    "wof:placetype":"venue"
},
  "geometry": {"coordinates":[4.4605550766,50.4290390015],"type":"Point"}
}