{
  "type": "Feature",
  "properties": {
    "addr:full":"Constant Permekestraat 20 Roeselare West-Vlaanderen 8800",
    "addr:housenumber":"20",
    "addr:postcode":"8800",
    "addr:street":"Constant Permekestraat",
    "iso:country":"BE",
    "sg:address":"Constant Permekestraat 20",
    "sg:city":"Roeselare",
    "sg:orig_category":"Fabrication and montage de mobilier. Meubles D\u00e9taillants, Am\u00e9nagement de B\u00e2timents et de Cuisines",
    "sg:phone":"+32 51 22 23 42",
    "sg:postcode":"8800",
    "sg:province":"West-Vlaanderen",
    "wof:name":"Keukens Vancra",
    "wof:placetype":"venue"
},
  "geometry": {"coordinates":[3.1578829288,50.9247016907],"type":"Point"}
}