{
  "type": "Feature",
  "properties": {
    "iso:country":"BE",
    "sg:address":"Rue De Goz\u00c9e 627",
    "sg:city":"Montigny-le-tilleul",
    "sg:orig_category":"Slagers",
    "sg:phone":"+32 71 51 22 37",
    "sg:postcode":"6110",
    "sg:province":"Hainaut",
    "wof:name":"Boucherie Manu",
    "wof:placetype":"venue"
},
  "geometry": {"coordinates":[4.3637690544,50.3662567139],"type":"Point"}
}