{
  "type": "Feature",
  "properties": {
    "addr:full":"Brugsesteenweg 198 Gent Oost-Vlaanderen 9000",
    "addr:housenumber":"198",
    "addr:postcode":"9000",
    "addr:street":"Brugsesteenweg;Oost-Vlaanderen",
    "iso:country":"BE",
    "sg:address":"Brugsesteenweg 198",
    "sg:city":"Gent",
    "sg:orig_category":"Zuivelproducten",
    "sg:phone":"+32 9 226 12 26",
    "sg:postcode":"9000",
    "sg:province":"Oost-Vlaanderen",
    "wof:name":"Meiresonne",
    "wof:placetype":"venue"
},
  "geometry": {"coordinates":[3.6908318996,51.0651054382],"type":"Point"}
}