{
  "type": "Feature",
  "properties": {
    "iso:country":"BE",
    "sg:address":"Van Aerdtstraat 22",
    "sg:city":"Antwerpen",
    "sg:orig_category":"Erotische Etablissementen",
    "sg:phone":"+32 3 233 21 36",
    "sg:postcode":"2060",
    "sg:province":"Antwerpen",
    "wof:name":"The Boots",
    "wof:placetype":"venue"
},
  "geometry": {"coordinates":[4.4157829285,51.2275123596],"type":"Point"}
}