{
  "type": "Feature",
  "properties": {
    "addr:full":"Krijgsbaan 23 Mortsel Antwerpen 2640",
    "addr:housenumber":"23",
    "addr:postcode":"2640",
    "addr:street":"Krijgsbaan",
    "iso:country":"BE",
    "sg:address":"Krijgsbaan 23",
    "sg:city":"Mortsel",
    "sg:orig_category":"Location d'appareils audio-visuels",
    "sg:phone":"+32 3 448 01 60",
    "sg:postcode":"2640",
    "sg:province":"Antwerpen",
    "wof:name":"Audioprof",
    "wof:placetype":"venue"
},
  "geometry": {"coordinates":[4.4554729462,51.1756858826],"type":"Point"}
}