{
  "type": "Feature",
  "properties": {
    "iso:country":"BE",
    "sg:address":"Ijzerhandstraat 3",
    "sg:city":"Stekene",
    "sg:orig_category":"Eleveurs de bovins. Eleveurs and marchands de porcs",
    "sg:phone":"+32 3 779 70 03",
    "sg:postcode":"9190",
    "sg:province":"Oost-Vlaanderen",
    "wof:name":"Marcel Van Buynder",
    "wof:placetype":"venue"
},
  "geometry": {"coordinates":[4.0567321777,51.2028923035],"type":"Point"}
}