{
  "type": "Feature",
  "properties": {
    "addr:full":"Magdalenalei 134 Brasschaat Antwerpen 2930",
    "addr:housenumber":"134",
    "addr:postcode":"2930",
    "iso:country":"BE",
    "sg:address":"Magdalenalei 134",
    "sg:city":"Brasschaat",
    "sg:orig_category":"M\u00e9decins and sp\u00e9cialistes",
    "sg:phone":"+32 3 651 85 90",
    "sg:postcode":"2930",
    "sg:province":"Antwerpen",
    "wof:name":"Bart Garmyn",
    "wof:placetype":"venue"
},
  "geometry": {"coordinates":[4.4847230911,51.2996368408],"type":"Point"}
}