{
  "type": "Feature",
  "properties": {
    "iso:country":"BE",
    "sg:address":"Gyselstraat 160",
    "sg:city":"Sint-niklaas",
    "sg:orig_category":"Assurances. Comptables",
    "sg:phone":"+32 3 766 10 16",
    "sg:postcode":"9100",
    "sg:province":"Oost-Vlaanderen",
    "wof:name":"Kantoor Busschaert",
    "wof:placetype":"venue"
},
  "geometry": {"coordinates":[4.1693329811,51.1964836121],"type":"Point"}
}