{
  "type": "Feature",
  "properties": {
    "addr:full":"Maldingen 9c Burg-reuland Li\u00e8ge 4791",
    "addr:housenumber":"9c",
    "addr:postcode":"4791",
    "addr:street":"Maldingen",
    "iso:country":"BE",
    "sg:address":"Maldingen 9c",
    "sg:city":"Burg-reuland",
    "sg:orig_category":"Installatie van houten of kunststof schrijnwerk",
    "sg:phone":"+32 80 22 86 33",
    "sg:postcode":"4791",
    "sg:province":"Li\u00e8ge",
    "wof:name":"Scheuren",
    "wof:placetype":"venue"
},
  "geometry": {"coordinates":[6.0321798325,50.2336082458],"type":"Point"}
}