{
  "type": "Feature",
  "properties": {
    "iso:country":"BE",
    "sg:address":"Staatsbaan 173",
    "sg:city":"Bekkevoort",
    "sg:classifiers":[
        {
            "category":"Health Services",
            "subcategory":"Doctor",
            "type":"Services"
        }
    ],
    "sg:phone":"+32 13 31 15 21",
    "sg:postcode":"3460",
    "sg:province":"Vlaams-Brabant",
    "sg:tags":[
        "medicinephysicians",
        "surgeon"
    ],
    "wof:name":"Corens M",
    "wof:placetype":"venue"
},
  "geometry": {"coordinates":[4.9779610634,50.9457435608],"type":"Point"}
}