{
  "type": "Feature",
  "properties": {
    "iso:country":"BE",
    "sg:address":"Markt 8-10",
    "sg:city":"Schoten",
    "sg:classifiers":[
        {
            "category":"Communications",
            "subcategory":"Film & Video Production",
            "type":"Services"
        }
    ],
    "sg:phone":"+32 3 658 87 23",
    "sg:postcode":"2900",
    "sg:province":"Antwerpen",
    "sg:tags":[
        "hiring",
        "-"
    ],
    "wof:name":"Videoland",
    "wof:placetype":"venue"
},
  "geometry": {"coordinates":[4.497273922,51.2512626648],"type":"Point"}
}