{
  "type": "Feature",
  "properties": {
    "addr:full":"Rue De Verviers 39 Welkenraedt/welkenraedt Li\u00e8ge 4841",
    "addr:housenumber":"39",
    "addr:postcode":"4841",
    "addr:street":"Rue De Verviers",
    "iso:country":"BE",
    "sg:address":"Rue De Verviers 39",
    "sg:city":"Welkenraedt/welkenraedt",
    "sg:orig_category":"Entretien and r\u00e9parations de voitures",
    "sg:phone":"+32 87 88 32 18",
    "sg:postcode":"4841",
    "sg:province":"Li\u00e8ge",
    "wof:name":"Paul Kersten",
    "wof:placetype":"venue"
},
  "geometry": {"coordinates":[5.9249529839,50.6740112305],"type":"Point"}
}