{
  "type": "Feature",
  "properties": {
    "addr:full":"Grote Markt 37 Lier Antwerpen 2500",
    "addr:housenumber":"37",
    "addr:postcode":"2500",
    "addr:street":"Grote Markt",
    "iso:country":"BE",
    "sg:address":"Grote Markt 37",
    "sg:city":"Lier",
    "sg:classifiers":[
        {
            "category":"Bars & Pubs",
            "type":"Food & Drink"
        }
    ],
    "sg:phone":"+32 3 489 13 62",
    "sg:postcode":"2500",
    "sg:province":"Antwerpen",
    "wof:name":"Groenhuis ('t)",
    "wof:placetype":"venue"
},
  "geometry": {"coordinates":[4.568693161,51.131313324],"type":"Point"}
}