{
  "type": "Feature",
  "properties": {
    "addr:full":"Rue Touvent 33 Sivry-rance Hainaut 6470",
    "addr:housenumber":"33",
    "addr:postcode":"6470",
    "addr:street":"Rue Touvent",
    "iso:country":"BE",
    "sg:address":"Rue Touvent 33",
    "sg:city":"Sivry-rance",
    "sg:orig_category":"Epiceries",
    "sg:phone":"+32 60 45 50 65",
    "sg:postcode":"6470",
    "sg:province":"Hainaut",
    "wof:name":"Gisele Meunier",
    "wof:placetype":"venue"
},
  "geometry": {"coordinates":[4.1423931122,50.1358451843],"type":"Point"}
}