{
  "type": "Feature",
  "properties": {
    "addr:full":"Rue Pire 2 Maisons 7 Edingen/enghien Hainaut 7850",
    "addr:housenumber":"2;7",
    "addr:postcode":"7850",
    "addr:street":"Rue Pire;Maisons",
    "iso:country":"BE",
    "sg:address":"Rue Pire 2 Maisons 7",
    "sg:city":"Edingen/enghien",
    "sg:orig_category":"Eleveurs de bovins",
    "sg:phone":"+32 2 395 32 83",
    "sg:postcode":"7850",
    "sg:province":"Hainaut",
    "wof:name":"Yves Blanpain",
    "wof:placetype":"venue"
},
  "geometry": {"coordinates":[4.079182148,50.6687850952],"type":"Point"}
}