{
  "type": "Feature",
  "properties": {
    "addr:full":"Beatrijslaan 32 Antwerpen Antwerpen 2050",
    "addr:housenumber":"32",
    "addr:postcode":"2050",
    "addr:street":"Beatrijslaan",
    "iso:country":"BE",
    "sg:address":"Beatrijslaan 32",
    "sg:city":"Antwerpen",
    "sg:classifiers":[
        {
            "category":"Fast Food",
            "type":"Food & Drink"
        }
    ],
    "sg:phone":"+32 3 219 20 27",
    "sg:postcode":"2050",
    "sg:province":"Antwerpen",
    "sg:tags":[
        "\u00c0",
        "restaurants",
        "emporter",
        "restaurant"
    ],
    "wof:name":"Kam Hei",
    "wof:placetype":"venue"
},
  "geometry": {"coordinates":[4.3858780861,51.2188339233],"type":"Point"}
}