{
  "type": "Feature",
  "properties": {
    "addr:full":"Ooststraat 7 Veurne West-Vlaanderen 8630",
    "addr:housenumber":"7",
    "addr:postcode":"8630",
    "addr:street":"Ooststraat",
    "iso:country":"BE",
    "sg:address":"Ooststraat 7",
    "sg:city":"Veurne",
    "sg:classifiers":[
        {
            "category":"Shopping",
            "subcategory":"Optician",
            "type":"Retail Goods"
        }
    ],
    "sg:phone":"+32 58 31 64 74",
    "sg:postcode":"8630",
    "sg:province":"West-Vlaanderen",
    "sg:tags":[
        "-"
    ],
    "wof:name":"Optiek An",
    "wof:placetype":"venue"
},
  "geometry": {"coordinates":[2.6629769802,51.0725746155],"type":"Point"}
}