{
  "type": "Feature",
  "properties": {
    "addr:full":"Boulevard G\u00e9n\u00e9ral Wahis 16-g Bruxelles (schaerbeek) Bruxelles-Capitale 1030",
    "addr:housenumber":"16-g",
    "addr:postcode":"1030",
    "addr:street":"Boulevard Ge\u0301Ne\u0301Ral Wahis",
    "iso:country":"BE",
    "sg:address":"Boulevard G\u00e9n\u00e9ral Wahis 16-g",
    "sg:city":"Bruxelles (schaerbeek)",
    "sg:classifiers":[
        {
            "category":"Home & Garden",
            "subcategory":"Carpets & Floor Coverings",
            "type":"Retail Goods"
        }
    ],
    "sg:phone":"+32 2 245 32 77",
    "sg:postcode":"1030",
    "sg:province":"Bruxelles-Capitale",
    "sg:tags":[
        "layer",
        "mosaicists"
    ],
    "wof:name":"Gil Carro Sprl",
    "wof:placetype":"venue"
},
  "geometry": {"coordinates":[4.3749351501,50.8680000305],"type":"Point"}
}