{
  "type": "Feature",
  "properties": {
    "addr:full":"Rue Des Funkias 37 Watermaal-bosvoorde/watermael-boitsfort Bruxelles-Capitale 1170",
    "addr:housenumber":"37",
    "addr:postcode":"1170",
    "addr:street":"Rue Des Funkias",
    "iso:country":"BE",
    "sg:address":"Rue Des Funkias 37",
    "sg:city":"Watermaal-bosvoorde/watermael-boitsfort",
    "sg:orig_category":"Plomberie, chauffage and installations sanitaires",
    "sg:phone":"+32 2 673 17 21",
    "sg:postcode":"1170",
    "sg:province":"Bruxelles-Capitale",
    "wof:name":"Pascal Vankerkhove",
    "wof:placetype":"venue"
},
  "geometry": {"coordinates":[4.4229121208,50.8103561401],"type":"Point"}
}