{
  "type": "Feature",
  "properties": {
    "addr:full":"Rue Notre-dame 26 Namur Namur 5000",
    "addr:housenumber":"26",
    "addr:postcode":"5000",
    "addr:street":"Rue Notre-Dame",
    "iso:country":"BE",
    "sg:address":"Rue Notre-dame 26",
    "sg:city":"Namur",
    "sg:classifiers":[
        {
            "category":"Recreation",
            "subcategory":"Fishing",
            "type":"Entertainment"
        }
    ],
    "sg:phone":"+32 81 22 43 99",
    "sg:postcode":"5000",
    "sg:province":"Namur",
    "sg:tags":[
        "tackle"
    ],
    "wof:name":"Jadot A",
    "wof:placetype":"venue"
},
  "geometry": {"coordinates":[4.8673892021,50.460735321],"type":"Point"}
}