{
  "type": "Feature",
  "properties": {
    "iso:country":"BE",
    "sg:address":"Ninovesteenweg 144",
    "sg:city":"Aalst",
    "sg:orig_category":"Woningbouw",
    "sg:phone":"+32 53 77 90 96",
    "sg:postcode":"9320",
    "sg:province":"Oost-Vlaanderen",
    "wof:name":"Erwin Schelck",
    "wof:placetype":"venue"
},
  "geometry": {"coordinates":[4.0553851128,50.9209976196],"type":"Point"}
}