{
  "type": "Feature",
  "properties": {
    "addr:full":"Galgenveldstraat 6 Industriepark Noord Tielt West-Vlaanderen 8700",
    "addr:postcode":"8700",
    "addr:street":"Galgenveldstraat;Industriepark Noord",
    "iso:country":"BE",
    "sg:address":"Galgenveldstraat 6 Industriepark Noord",
    "sg:city":"Tielt",
    "sg:classifiers":[
        {
            "category":"Manufacturing",
            "subcategory":"Wood Products",
            "type":"Manufacturing & Wholesale Goods"
        }
    ],
    "sg:phone":"+32 51 40 44 11",
    "sg:postcode":"8700",
    "sg:province":"West-Vlaanderen",
    "sg:tags":[
        "professional",
        "furniture"
    ],
    "wof:name":"Jan Moret & Co Cva",
    "wof:placetype":"venue"
},
  "geometry": {"coordinates":[3.3261549473,51.0001182556],"type":"Point"}
}