{
  "type": "Feature",
  "properties": {
    "iso:country":"BE",
    "sg:address":"Route De Spa 129",
    "sg:city":"Stavelot",
    "sg:orig_category":"Brood, gebak and snoepgoed",
    "sg:phone":"+32 87 27 52 51",
    "sg:postcode":"4970",
    "sg:province":"Li\u00e8ge",
    "wof:name":"P\u00c2tisserie Pirson",
    "wof:placetype":"venue"
},
  "geometry": {"coordinates":[5.9303088188,50.4132995605],"type":"Point"}
}