{
  "type": "Feature",
  "properties": {
    "addr:full":"Rue Charles Rittw\u00e9ger 37 Theux Li\u00e8ge 4910",
    "addr:housenumber":"37",
    "addr:postcode":"4910",
    "addr:street":"Rue Charles Rittwe\u0301Ger",
    "iso:country":"BE",
    "sg:address":"Rue Charles Rittw\u00e9ger 37",
    "sg:city":"Theux",
    "sg:classifiers":[
        {
            "category":"Retail",
            "subcategory":"Event Space",
            "type":"Services"
        }
    ],
    "sg:phone":"+32 87 53 90 00",
    "sg:postcode":"4910",
    "sg:province":"Li\u00e8ge",
    "sg:tags":[
        "organisation"
    ],
    "wof:name":"Degecom Sprl",
    "wof:placetype":"venue"
},
  "geometry": {"coordinates":[5.8128099442,50.5392494202],"type":"Point"}
}