{
  "type": "Feature",
  "properties": {
    "iso:country":"BE",
    "sg:address":"Waaibergstraat 82-90",
    "sg:city":"Tienen",
    "sg:classifiers":[
        {
            "category":"Professional",
            "subcategory":"Engineering",
            "type":"Services"
        }
    ],
    "sg:phone":"+32 16 81 94 10",
    "sg:postcode":"3300",
    "sg:province":"Vlaams-Brabant",
    "sg:tags":[
        "environmental",
        "technique",
        "-"
    ],
    "wof:name":"Rimeco Milieu Nv",
    "wof:placetype":"venue"
},
  "geometry": {"coordinates":[4.9401431084,50.8114204407],"type":"Point"}
}