{
  "type": "Feature",
  "properties": {
    "addr:full":"Rue Du Tunnel 4 Charleroi Hainaut 6010",
    "addr:housenumber":"4",
    "addr:postcode":"6010",
    "addr:street":"Rue Du Tunnel;Hainaut",
    "iso:country":"BE",
    "sg:address":"Rue Du Tunnel 4",
    "sg:city":"Charleroi",
    "sg:orig_category":"M\u00e9decins and sp\u00e9cialistes",
    "sg:phone":"+32 71 43 10 53",
    "sg:postcode":"6010",
    "sg:province":"Hainaut",
    "wof:name":"Philippe Rouffiange",
    "wof:placetype":"venue"
},
  "geometry": {"coordinates":[4.4655752182,50.379283905],"type":"Point"}
}