{
  "type": "Feature",
  "properties": {
    "addr:full":"Gentse Steenweg 412 Lokeren Oost-Vlaanderen 9160",
    "addr:housenumber":"412",
    "addr:postcode":"9160",
    "addr:street":"Gentse Steenweg",
    "iso:country":"BE",
    "sg:address":"Gentse Steenweg 412",
    "sg:city":"Lokeren",
    "sg:classifiers":[
        {
            "category":"Personal",
            "subcategory":"Beauty Salon",
            "type":"Services"
        }
    ],
    "sg:phone":"+32 9 355 64 98",
    "sg:postcode":"9160",
    "sg:province":"Oost-Vlaanderen",
    "wof:name":"Annita Hair & Beauty Centrum",
    "wof:placetype":"venue"
},
  "geometry": {"coordinates":[3.9087460041,51.1088523865],"type":"Point"}
}