{
  "type": "Feature",
  "properties": {
    "addr:full":"Chauss\u00e9e De Mons 10 Nivelles Brabant Wallon 1400",
    "addr:housenumber":"10",
    "addr:postcode":"1400",
    "addr:street":"Chausse\u0301E De Mons",
    "iso:country":"BE",
    "sg:address":"Chauss\u00e9e De Mons 10",
    "sg:city":"Nivelles",
    "sg:classifiers":[
        {
            "category":"Retail",
            "subcategory":"Repair Shop",
            "type":"Services"
        }
    ],
    "sg:phone":"+32 67 84 21 40",
    "sg:postcode":"1400",
    "sg:province":"Brabant Wallon",
    "sg:tags":[
        "mainten",
        "-",
        "parquet"
    ],
    "wof:name":"Locmat-promat",
    "wof:placetype":"venue"
},
  "geometry": {"coordinates":[4.3126897812,50.5895233154],"type":"Point"}
}