{
  "type": "Feature",
  "properties": {
    "addr:full":"Rue Des Pecheurs 13 Comblain-au-pont Li\u00e8ge 4170",
    "addr:housenumber":"13",
    "addr:postcode":"4170",
    "addr:street":"Rue Des Pecheurs",
    "iso:country":"BE",
    "sg:address":"Rue Des Pecheurs 13",
    "sg:city":"Comblain-au-pont",
    "sg:classifiers":[
        {
            "category":"Bakery",
            "type":"Food & Drink"
        }
    ],
    "sg:phone":"+32 4 369 10 54",
    "sg:postcode":"4170",
    "sg:province":"Li\u00e8ge",
    "sg:tags":[
        "cake",
        "product",
        "related",
        "bread"
    ],
    "wof:name":"Boulangerie-louviaux Sprl",
    "wof:placetype":"venue"
},
  "geometry": {"coordinates":[5.5928602219,50.4808998108],"type":"Point"}
}