{
  "type": "Feature",
  "properties": {
    "addr:full":"Rue Du Calvaire 9 Eghez\u00e9e (hanret) Namur 5310",
    "addr:housenumber":"9",
    "addr:postcode":"5310",
    "addr:street":"Rue Du Calvaire;Hanret",
    "iso:country":"BE",
    "sg:address":"Rue Du Calvaire 9",
    "sg:city":"Eghez\u00e9e (hanret)",
    "sg:classifiers":[
        {
            "category":"Utilities",
            "subcategory":"Fuel Oil & Lpg",
            "type":"Services"
        }
    ],
    "sg:phone":"+32 81 81 12 41",
    "sg:postcode":"5310",
    "sg:province":"Namur",
    "wof:name":"Fronville A",
    "wof:placetype":"venue"
},
  "geometry": {"coordinates":[4.94668293,50.5895957947],"type":"Point"}
}