{
  "type": "Feature",
  "properties": {
    "addr:full":"Avenue Croix De Lorraine 14 La Hulpe Brabant Wallon 1310",
    "addr:housenumber":"14",
    "addr:postcode":"1310",
    "addr:street":"Avenue Croix De Lorraine",
    "iso:country":"BE",
    "sg:address":"Avenue Croix De Lorraine 14",
    "sg:city":"La Hulpe",
    "sg:classifiers":[
        {
            "category":"Retail",
            "subcategory":"Auto Repair",
            "type":"Services"
        }
    ],
    "sg:phone":"+32 2 653 55 43",
    "sg:postcode":"1310",
    "sg:province":"Brabant Wallon",
    "sg:tags":[
        "breakdown",
        "automobile",
        "-",
        "recovery"
    ],
    "wof:name":"Lambert Michel (d\u00e9pannage)",
    "wof:placetype":"venue"
},
  "geometry": {"coordinates":[4.4925928116,50.7459487915],"type":"Point"}
}