{
  "type": "Feature",
  "properties": {
    "addr:full":"Warande 13a Laarne Oost-Vlaanderen 9270",
    "addr:housenumber":"13a",
    "addr:postcode":"9270",
    "addr:street":"Warande",
    "iso:country":"BE",
    "sg:address":"Warande 13a",
    "sg:city":"Laarne",
    "sg:classifiers":[
        {
            "category":"Professional",
            "subcategory":"Management & Consulting",
            "type":"Services"
        }
    ],
    "sg:phone":"+32 9 366 11 37",
    "sg:postcode":"9270",
    "sg:province":"Oost-Vlaanderen",
    "sg:tags":[
        "-",
        "processing",
        "data",
        "consultant"
    ],
    "wof:name":"Verleye Computer Management Bvba",
    "wof:placetype":"venue"
},
  "geometry": {"coordinates":[3.8509449959,51.0268287659],"type":"Point"}
}