{
  "type": "Feature",
  "properties": {
    "iso:country":"BE",
    "sg:address":"Palmbosstraat 47",
    "sg:city":"Wuustwezel",
    "sg:orig_category":"Installation de menuiserie en bois and plastique",
    "sg:phone":"+32 3 669 82 71",
    "sg:postcode":"2990",
    "sg:province":"Antwerpen",
    "wof:name":"Lucas Schrauwen",
    "wof:placetype":"venue"
},
  "geometry": {"coordinates":[4.639632225,51.396446228],"type":"Point"}
}