{
  "type": "Feature",
  "properties": {
    "addr:full":"Vrijgeweidstraat 55 Wingene West-Vlaanderen 8750",
    "addr:housenumber":"55",
    "addr:postcode":"8750",
    "addr:street":"Vrijgeweidstraat",
    "iso:country":"BE",
    "sg:address":"Vrijgeweidstraat 55",
    "sg:city":"Wingene",
    "sg:orig_category":"Eleveurs de bovins",
    "sg:phone":"+32 51 61 13 89",
    "sg:postcode":"8750",
    "sg:province":"West-Vlaanderen",
    "wof:name":"Loca",
    "wof:placetype":"venue"
},
  "geometry": {"coordinates":[3.1624560356,51.0608634949],"type":"Point"}
}