{
  "type": "Feature",
  "properties": {
    "iso:country":"BE",
    "sg:address":"Kasteeldreef 133",
    "sg:city":"Schilde",
    "sg:classifiers":[
        {
            "category":"Health Services",
            "subcategory":"Dentist",
            "type":"Services"
        }
    ],
    "sg:phone":"+32 3 353 01 66",
    "sg:postcode":"2970",
    "sg:province":"Antwerpen",
    "wof:name":"De Saeytyd Caroline",
    "wof:placetype":"venue"
},
  "geometry": {"coordinates":[4.5533928871,51.2301025391],"type":"Point"}
}