{
  "type": "Feature",
  "properties": {
    "iso:country":"BE",
    "sg:address":"Avenue Du Sacr\u00c9-coeur 79",
    "sg:city":"Jette",
    "sg:orig_category":"Traitements param\u00e9dicaux",
    "sg:phone":"+32 2 479 59 64",
    "sg:postcode":"1090",
    "sg:province":"Bruxelles-Capitale",
    "wof:name":"C. Salv\u00c9",
    "wof:placetype":"venue"
},
  "geometry": {"coordinates":[4.3307299614,50.8842544556],"type":"Point"}
}