{
  "type": "Feature",
  "properties": {
    "iso:country":"BE",
    "sg:address":"Beverlaai 3",
    "sg:city":"Kortrijk",
    "sg:classifiers":[
        {
            "category":"Wholesale",
            "subcategory":"Plants",
            "type":"Manufacturing & Wholesale Goods"
        }
    ],
    "sg:phone":"+32 56 22 30 22",
    "sg:postcode":"8500",
    "sg:province":"West-Vlaanderen",
    "sg:tags":[
        "textile",
        "machine",
        "assembly"
    ],
    "wof:name":"Lecluyse Machines Nv",
    "wof:placetype":"venue"
},
  "geometry": {"coordinates":[3.2678821087,50.8223342896],"type":"Point"}
}