{
  "type": "Feature",
  "properties": {
    "iso:country":"BE",
    "sg:address":"Rue Cesar De Paepe 105",
    "sg:city":"Charleroi",
    "sg:orig_category":"Bloemen and planten",
    "sg:phone":"+32 71 35 69 44",
    "sg:postcode":"6040",
    "sg:province":"Hainaut",
    "wof:name":"Fleuriste Emma",
    "wof:placetype":"venue"
},
  "geometry": {"coordinates":[4.4137268066,50.4357795715],"type":"Point"}
}