{
  "type": "Feature",
  "properties": {
    "addr:full":"Deerlijkstraat 133 Zwevegem West-Vlaanderen 8550",
    "addr:housenumber":"133",
    "addr:postcode":"8550",
    "addr:street":"Deerlijkstraat",
    "iso:country":"BE",
    "sg:address":"Deerlijkstraat 133",
    "sg:city":"Zwevegem",
    "sg:orig_category":"Activit\u00e9s d\u00b4action sociale sans h\u00e9bergement",
    "sg:phone":"+32 56 75 50 73",
    "sg:postcode":"8550",
    "sg:province":"West-Vlaanderen",
    "wof:name":"Vclb-centrum",
    "wof:placetype":"venue"
},
  "geometry": {"coordinates":[3.3394629955,50.8184318542],"type":"Point"}
}