{
  "type": "Feature",
  "properties": {
    "iso:country":"BE",
    "sg:address":"Liersebaan 276",
    "sg:city":"Zandhoven",
    "sg:classifiers":[
        {
            "category":"Cafe",
            "type":"Food & Drink"
        }
    ],
    "sg:phone":"+32 3 485 58 79",
    "sg:postcode":"2240",
    "sg:province":"Antwerpen",
    "sg:tags":[
        "caf\u00e9s"
    ],
    "wof:name":"Verdi",
    "wof:placetype":"venue"
},
  "geometry": {"coordinates":[4.6519298553,51.2068099976],"type":"Point"}
}