{
  "type": "Feature",
  "properties": {
    "iso:country":"BE",
    "sg:address":"Boskant 26",
    "sg:city":"Schilde",
    "sg:classifiers":[
        {
            "category":"Wholesale",
            "subcategory":"Books, Periodicals, & Newspapers",
            "type":"Manufacturing & Wholesale Goods"
        }
    ],
    "sg:phone":"+32 3 383 57 24",
    "sg:postcode":"2970",
    "sg:province":"Antwerpen",
    "sg:tags":[
        "publisher"
    ],
    "wof:name":"Info-books Bvba",
    "wof:placetype":"venue"
},
  "geometry": {"coordinates":[4.6058039665,51.260269165],"type":"Point"}
}