{
  "type": "Feature",
  "properties": {
    "addr:full":"Kleppestraat 52 Moorslede West-Vlaanderen 8890",
    "addr:housenumber":"52",
    "addr:postcode":"8890",
    "addr:street":"Kleppestraat",
    "iso:country":"BE",
    "sg:address":"Kleppestraat 52",
    "sg:city":"Moorslede",
    "sg:orig_category":"Quincailleries",
    "sg:phone":"+32 56 50 55 58",
    "sg:postcode":"8890",
    "sg:province":"West-Vlaanderen",
    "wof:name":"Bad & Meubel",
    "wof:placetype":"venue"
},
  "geometry": {"coordinates":[3.1028161049,50.8508110046],"type":"Point"}
}