{
  "type": "Feature",
  "properties": {
    "addr:full":"En Grande Foxhalle 60 Herstal Li\u00e8ge 4040",
    "addr:housenumber":"60",
    "addr:postcode":"4040",
    "addr:street":"Foxhalle",
    "iso:country":"BE",
    "sg:address":"En Grande Foxhalle 60",
    "sg:city":"Herstal",
    "sg:orig_category":"R\u00e9cup\u00e9ration de mati\u00e8res m\u00e9talliques recyclables and d\u00e9molisseurs de voitures",
    "sg:phone":"+32 497 35 30 96",
    "sg:postcode":"4040",
    "sg:province":"Li\u00e8ge",
    "wof:name":"Maison Schreiner",
    "wof:placetype":"venue"
},
  "geometry": {"coordinates":[5.6225738525,50.6628570557],"type":"Point"}
}