{
  "type": "Feature",
  "properties": {
    "addr:full":"Bruggestraat 3 Koksijde West-Vlaanderen 8670",
    "addr:housenumber":"3",
    "addr:postcode":"8670",
    "addr:street":"Bruggestraat",
    "iso:country":"BE",
    "sg:address":"Bruggestraat 3",
    "sg:city":"Koksijde",
    "sg:classifiers":[
        {
            "category":"Cafe",
            "type":"Food & Drink"
        }
    ],
    "sg:phone":"+32 58 51 16 56",
    "sg:postcode":"8670",
    "sg:province":"West-Vlaanderen",
    "sg:tags":[
        "caf\u00e9s"
    ],
    "wof:name":"Benoit Dorne",
    "wof:placetype":"venue"
},
  "geometry": {"coordinates":[2.67425704,51.1291046143],"type":"Point"}
}