{
  "type": "Feature",
  "properties": {
    "addr:full":"Haachtsesteenweg 1248 Evere/evere Bruxelles-Capitale 1140",
    "addr:housenumber":"1248",
    "addr:postcode":"1140",
    "addr:street":"Haachtsesteenweg",
    "iso:country":"BE",
    "sg:address":"Haachtsesteenweg 1248",
    "sg:city":"Evere/evere",
    "sg:orig_category":"Slagers",
    "sg:phone":"+32 2 215 60 67",
    "sg:postcode":"1140",
    "sg:province":"Bruxelles-Capitale",
    "wof:name":"Renmans",
    "wof:placetype":"venue"
},
  "geometry": {"coordinates":[4.4085431099,50.8770942688],"type":"Point"}
}