{
  "type": "Feature",
  "properties": {
    "addr:full":"Marktweg 19 Avelgem West-Vlaanderen 8580",
    "addr:housenumber":"19",
    "addr:postcode":"8580",
    "addr:street":"Marktweg",
    "iso:country":"BE",
    "sg:address":"Marktweg 19",
    "sg:city":"Avelgem",
    "sg:classifiers":[
        {
            "category":"Insurance",
            "subcategory":"Insurance Agent",
            "type":"Services"
        }
    ],
    "sg:phone":"+32 56 64 67 00",
    "sg:postcode":"8580",
    "sg:province":"West-Vlaanderen",
    "sg:tags":[
        "broker"
    ],
    "wof:name":"Jacobs J",
    "wof:placetype":"venue"
},
  "geometry": {"coordinates":[3.437748909,50.773891449],"type":"Point"}
}