{
  "type": "Feature",
  "properties": {
    "addr:full":"Luikerstraat 52 Sint-truiden Limburg 3800",
    "addr:housenumber":"52",
    "addr:postcode":"3800",
    "addr:street":"Luikerstraat",
    "iso:country":"BE",
    "sg:address":"Luikerstraat 52",
    "sg:city":"Sint-truiden",
    "sg:orig_category":"Disneyland Paris. Agences de voyages",
    "sg:phone":"+32 11 68 08 36",
    "sg:postcode":"3800",
    "sg:province":"Limburg",
    "wof:name":"Neckermann",
    "wof:placetype":"venue"
},
  "geometry": {"coordinates":[5.1886100769,50.8141403198],"type":"Point"}
}