{
  "type": "Feature",
  "properties": {
    "addr:full":"Petit Coo 6 Stavelot Li\u00e8ge 4970",
    "addr:housenumber":"6",
    "addr:postcode":"4970",
    "addr:street":"Petit Coo",
    "iso:country":"BE",
    "sg:address":"Petit Coo 6",
    "sg:city":"Stavelot",
    "sg:classifiers":[
        {
            "category":"Travel",
            "subcategory":"Hotels & Motels",
            "type":"Entertainment"
        }
    ],
    "sg:phone":"+32 80 68 46 76",
    "sg:postcode":"4970",
    "sg:province":"Li\u00e8ge",
    "sg:tags":[
        "restaurant"
    ],
    "wof:name":"Hotel Le Baron",
    "wof:placetype":"venue"
},
  "geometry": {"coordinates":[5.8768491745,50.3929595947],"type":"Point"}
}