{
  "type": "Feature",
  "properties": {
    "iso:country":"BE",
    "sg:address":"Rue Truffaut 118",
    "sg:city":"Ans",
    "sg:orig_category":"Forge, Moulage and Profilage des M\u00e9taux",
    "sg:phone":"+32 4 239 07 72",
    "sg:postcode":"4432",
    "sg:province":"Li\u00e8ge",
    "wof:name":"Scheiber",
    "wof:placetype":"venue"
},
  "geometry": {"coordinates":[5.5156011581,50.6770095825],"type":"Point"}
}