{
  "type": "Feature",
  "properties": {
    "addr:full":"Ninoofsesteenweg 324 Dilbeek Vlaams-Brabant 1700",
    "addr:housenumber":"324",
    "addr:postcode":"1700",
    "addr:street":"Ninoofsesteenweg",
    "iso:country":"BE",
    "sg:address":"Ninoofsesteenweg 324",
    "sg:city":"Dilbeek",
    "sg:classifiers":[
        {
            "category":"Professional",
            "subcategory":"Computer Services",
            "type":"Services"
        }
    ],
    "sg:phone":"+32 2 567 03 03",
    "sg:postcode":"1700",
    "sg:province":"Vlaams-Brabant",
    "sg:tags":[
        "-",
        "processing",
        "data",
        "software"
    ],
    "wof:name":"Krans Software Technology Bvba",
    "wof:placetype":"venue"
},
  "geometry": {"coordinates":[4.2627158165,50.8437232971],"type":"Point"}
}