{
  "type": "Feature",
  "properties": {
    "addr:full":"Nederkouter 120 Gent Oost-Vlaanderen 9000",
    "addr:housenumber":"120",
    "addr:postcode":"9000",
    "addr:street":"Nederkouter;Oost-Vlaanderen",
    "iso:country":"BE",
    "sg:address":"Nederkouter 120",
    "sg:city":"Gent",
    "sg:orig_category":"Reisbureaus",
    "sg:phone":"+32 9 223 90 20",
    "sg:postcode":"9000",
    "sg:province":"Oost-Vlaanderen",
    "wof:name":"Connections",
    "wof:placetype":"venue"
},
  "geometry": {"coordinates":[3.7218570709,51.0466423035],"type":"Point"}
}