{
  "type": "Feature",
  "properties": {
    "addr:full":"Rue Des Pierres 54 Brussel/bruxelles Bruxelles-Capitale 1000",
    "addr:housenumber":"54",
    "addr:postcode":"1000",
    "addr:street":"Rue Des Pierres;/",
    "iso:country":"BE",
    "sg:address":"Rue Des Pierres 54",
    "sg:city":"Brussel/bruxelles",
    "sg:classifiers":[
        {
            "category":"Personal",
            "subcategory":"Beauty Salon",
            "type":"Services"
        }
    ],
    "sg:phone":"+32 2 512 89 70",
    "sg:postcode":"1000",
    "sg:province":"Bruxelles-Capitale",
    "sg:tags":[
        "de",
        "coiffure"
    ],
    "wof:name":"Tignasse (la)",
    "wof:placetype":"venue"
},
  "geometry": {"coordinates":[4.3511509895,50.8467750549],"type":"Point"}
}