{
  "type": "Feature",
  "properties": {
    "addr:full":"Dr\u00c8ve Du Duc 108 Watermaal-bosvoorde/watermael-boitsfort Bruxelles-Capitale 1170",
    "addr:housenumber":"108",
    "addr:postcode":"1170",
    "addr:street":"Dre\u0300Ve Du Duc",
    "iso:country":"BE",
    "sg:address":"Dr\u00c8ve Du Duc 108",
    "sg:city":"Watermaal-bosvoorde/watermael-boitsfort",
    "sg:orig_category":"Agences de publicit\u00e9. Activit\u00e9s diverses d'imprimerie",
    "sg:phone":"+32 2 672 42 47",
    "sg:postcode":"1170",
    "sg:province":"Bruxelles-Capitale",
    "wof:name":"Jean Verscheure",
    "wof:placetype":"venue"
},
  "geometry": {"coordinates":[4.4106431007,50.7962913513],"type":"Point"}
}