{
  "type": "Feature",
  "properties": {
    "iso:country":"BE",
    "sg:address":"Lange Haagstraat 100",
    "sg:city":"Dilbeek",
    "sg:orig_category":"Electrom\u00e9nager, t\u00e9l\u00e9visions and radios",
    "sg:phone":"+32 2 466 70 10",
    "sg:postcode":"1700",
    "sg:province":"Vlaams-Brabant",
    "wof:name":"Cuisinier Pascal",
    "wof:placetype":"venue"
},
  "geometry": {"coordinates":[4.2368822098,50.8595657349],"type":"Point"}
}