{
  "type": "Feature",
  "properties": {
    "iso:country":"BE",
    "sg:address":"Rue De Braives 5",
    "sg:city":"Burdinne (oteppe)",
    "sg:classifiers":[
        {
            "category":"Sports & Exercise",
            "subcategory":"Stables",
            "type":"Entertainment"
        }
    ],
    "sg:phone":"+32 85 71 31 51",
    "sg:postcode":"4210",
    "sg:province":"Li\u00e8ge",
    "sg:tags":[
        "riding",
        "school"
    ],
    "wof:name":"Ecurie De La Burdinalle",
    "wof:placetype":"venue"
},
  "geometry": {"coordinates":[5.1179552078,50.5891456604],"type":"Point"}
}