{
  "type": "Feature",
  "properties": {
    "iso:country":"BE",
    "sg:address":"David Van Beverstraat 6",
    "sg:city":"Sint-pieters-woluwe/woluwe-saint-pierre",
    "sg:orig_category":"Openbare veiligheid",
    "sg:phone":"+32 2 762 93 37",
    "sg:postcode":"1150",
    "sg:province":"Bruxelles-Capitale",
    "wof:name":"Police F\u00c9d\u00c9rale/federale Politie",
    "wof:placetype":"venue"
},
  "geometry": {"coordinates":[4.439907074,50.8338470459],"type":"Point"}
}