{
  "type": "Feature",
  "properties": {
    "iso:country":"BE",
    "sg:address":"Neerstraat 26",
    "sg:city":"Brakel",
    "sg:classifiers":[
        {
            "category":"Food & Beverages",
            "subcategory":"Fruits & Vegetables",
            "type":"Retail Goods"
        }
    ],
    "sg:phone":"+32 55 42 30 74",
    "sg:postcode":"9660",
    "sg:province":"Oost-Vlaanderen",
    "sg:tags":[
        "l\u00e9gumes"
    ],
    "wof:name":"Eric Van Den Bulcke",
    "wof:placetype":"venue"
},
  "geometry": {"coordinates":[3.7656879425,50.8037643433],"type":"Point"}
}