{
  "type": "Feature",
  "properties": {
    "iso:country":"BE",
    "sg:address":"Bloemendalestraat 38",
    "sg:city":"Beernem",
    "sg:orig_category":"Paramedische behandelingen",
    "sg:phone":"+32 50 78 90 24",
    "sg:postcode":"8730",
    "sg:province":"West-Vlaanderen",
    "wof:name":"B. Depr\u00c9",
    "wof:placetype":"venue"
},
  "geometry": {"coordinates":[3.3393549919,51.1416091919],"type":"Point"}
}