{
  "type": "Feature",
  "properties": {
    "iso:country":"BE",
    "sg:address":"Rue Du Moulin 53",
    "sg:city":"Peruwelz",
    "sg:classifiers":[
        {
            "category":"Autos & Motor Vehicles",
            "subcategory":"Fuel & Gas Station",
            "type":"Retail Goods"
        }
    ],
    "sg:phone":"+32 69 77 34 14",
    "sg:postcode":"7600",
    "sg:province":"Hainaut",
    "sg:tags":[
        "stations-service",
        "carburants"
    ],
    "wof:name":"Chantal Bargibant",
    "wof:placetype":"venue"
},
  "geometry": {"coordinates":[3.6066339016,50.508682251],"type":"Point"}
}