{
  "type": "Feature",
  "properties": {
    "addr:full":"Oude Zandstraat 4 Beveren Oost-Vlaanderen 9120",
    "addr:housenumber":"4",
    "addr:postcode":"9120",
    "addr:street":"Oude Zandstraat",
    "iso:country":"BE",
    "sg:address":"Oude Zandstraat 4",
    "sg:city":"Beveren",
    "sg:classifiers":[
        {
            "category":"Food & Beverages",
            "subcategory":"Ethnic Foods",
            "type":"Retail Goods"
        }
    ],
    "sg:phone":"+32 3 775 78 52",
    "sg:postcode":"9120",
    "sg:province":"Oost-Vlaanderen",
    "sg:tags":[
        "article",
        "b\u00e9b\u00e9s",
        "v\u00eatements",
        "pour",
        "dames"
    ],
    "wof:name":"Steefie",
    "wof:placetype":"venue"
},
  "geometry": {"coordinates":[4.2549858093,51.212688446],"type":"Point"}
}