{
  "type": "Feature",
  "properties": {
    "addr:full":"Avenue De La D\u00c9portation 17 Ecaussinnes Hainaut 7190",
    "addr:housenumber":"17",
    "addr:postcode":"7190",
    "addr:street":"Avenue De La De\u0301Portation;Hainaut",
    "iso:country":"BE",
    "sg:address":"Avenue De La D\u00c9portation 17",
    "sg:city":"Ecaussinnes",
    "sg:classifiers":[
        {
            "category":"Cafe",
            "type":"Food & Drink"
        }
    ],
    "sg:phone":"+32 67 44 29 35",
    "sg:postcode":"7190",
    "sg:province":"Hainaut",
    "sg:tags":[
        "caf\u00e9s"
    ],
    "wof:name":"Maison Du Peuple",
    "wof:placetype":"venue"
},
  "geometry": {"coordinates":[4.1602301598,50.563293457],"type":"Point"}
}