{
  "type": "Feature",
  "properties": {
    "iso:country":"BE",
    "sg:address":"Rue De L'invasion 35a",
    "sg:city":"Limbourg (go\u00e9)",
    "sg:classifiers":[
        {
            "category":"Building & Trades",
            "subcategory":"Cleaning & Sanitation",
            "type":"Services"
        }
    ],
    "sg:phone":"+32 87 76 63 73",
    "sg:postcode":"4834",
    "sg:province":"Li\u00e8ge",
    "sg:tags":[
        "janitor"
    ],
    "wof:name":"Zimpali A.g. Sa",
    "wof:placetype":"venue"
},
  "geometry": {"coordinates":[5.9754939079,50.6031188965],"type":"Point"}
}