{
  "type": "Feature",
  "properties": {
    "addr:full":"Dorpsstraat 14 Bierbeek Vlaams-Brabant 3360",
    "addr:housenumber":"14",
    "addr:postcode":"3360",
    "addr:street":"Dorpsstraat",
    "iso:country":"BE",
    "sg:address":"Dorpsstraat 14",
    "sg:city":"Bierbeek",
    "sg:classifiers":[
        {
            "category":"Bars & Pubs",
            "type":"Food & Drink"
        }
    ],
    "sg:phone":"+32 16 46 01 65",
    "sg:postcode":"3360",
    "sg:province":"Vlaams-Brabant",
    "wof:name":"Molen (in De)",
    "wof:placetype":"venue"
},
  "geometry": {"coordinates":[4.7588419914,50.8277015686],"type":"Point"}
}