{
  "type": "Feature",
  "properties": {
    "iso:country":"BE",
    "sg:address":"Houtstraat 100",
    "sg:city":"Gingelom",
    "sg:orig_category":"S\u00e9curit\u00e9 sociale",
    "sg:phone":"+32 11 48 15 28",
    "sg:postcode":"3890",
    "sg:province":"Limburg",
    "wof:name":"De Voorzorg",
    "wof:placetype":"venue"
},
  "geometry": {"coordinates":[5.2091550827,50.7313766479],"type":"Point"}
}