{
  "type": "Feature",
  "properties": {
    "addr:full":"Christinastraat 37b Oostende West-Vlaanderen 8400",
    "addr:housenumber":"37b",
    "addr:postcode":"8400",
    "addr:street":"Christinastraat",
    "iso:country":"BE",
    "sg:address":"Christinastraat 37b",
    "sg:city":"Oostende",
    "sg:classifiers":[
        {
            "category":"Shopping",
            "subcategory":"Clothing, Apparel, & Fashions",
            "type":"Retail Goods"
        }
    ],
    "sg:phone":"+32 59 51 75 89",
    "sg:postcode":"8400",
    "sg:province":"West-Vlaanderen",
    "sg:tags":[
        "clothing",
        "-",
        "gentleman"
    ],
    "wof:name":"Edouard Sport",
    "wof:placetype":"venue"
},
  "geometry": {"coordinates":[2.9158079624,51.23179245],"type":"Point"}
}