{
  "type": "Feature",
  "properties": {
    "addr:full":"Leuvensesteenweg 326 Kortenberg Vlaams-Brabant 3070",
    "addr:housenumber":"326",
    "addr:postcode":"3070",
    "addr:street":"Leuvensesteenweg;Vlaams-Brabant",
    "iso:country":"BE",
    "sg:address":"Leuvensesteenweg 326",
    "sg:city":"Kortenberg",
    "sg:classifiers":[
        {
            "category":"Personal",
            "type":"Services"
        }
    ],
    "sg:phone":"+32 2 751 98 01",
    "sg:postcode":"3070",
    "sg:province":"Vlaams-Brabant",
    "sg:tags":[
        "party",
        "planning"
    ],
    "wof:name":"De Venkel Bvba",
    "wof:placetype":"venue"
},
  "geometry": {"coordinates":[4.5473031998,50.8890266418],"type":"Point"}
}