{
  "type": "Feature",
  "properties": {
    "iso:country":"BE",
    "sg:address":"Rue Neuve 40",
    "sg:city":"Herve",
    "sg:orig_category":"Eclairage et \u00e9quipements du foyer. Souvenirs and objets artisanaux",
    "sg:phone":"+32 87 67 83 84",
    "sg:postcode":"4650",
    "sg:province":"Li\u00e8ge",
    "wof:name":"La Maison De Julie",
    "wof:placetype":"venue"
},
  "geometry": {"coordinates":[5.791246891,50.6387710571],"type":"Point"}
}