{
  "type": "Feature",
  "properties": {
    "addr:full":"Kattestraat 1 Box 1 Asse Vlaams-Brabant 1730",
    "addr:housenumber":"1;1",
    "addr:postcode":"1730",
    "addr:street":"Kattestraat;Box",
    "iso:country":"BE",
    "sg:address":"Kattestraat 1 Box 1",
    "sg:city":"Asse",
    "sg:classifiers":[
        {
            "category":"Real Estate",
            "subcategory":"Architect",
            "type":"Services"
        }
    ],
    "sg:phone":"+32 2 452 20 46",
    "sg:postcode":"1730",
    "sg:province":"Vlaams-Brabant",
    "wof:name":"Moerenhout F",
    "wof:placetype":"venue"
},
  "geometry": {"coordinates":[4.1993188858,50.9104614258],"type":"Point"}
}