{
  "type": "Feature",
  "properties": {
    "iso:country":"BE",
    "sg:address":"Rue De Laloux 44",
    "sg:city":"Ramillies",
    "sg:orig_category":"Artsen and specialisten",
    "sg:phone":"+32 81 87 84 70",
    "sg:postcode":"1367",
    "sg:province":"Brabant Wallon",
    "wof:name":"Georges Raeymaeckers",
    "wof:placetype":"venue"
},
  "geometry": {"coordinates":[4.8744602203,50.6628799438],"type":"Point"}
}