{
  "type": "Feature",
  "properties": {
    "iso:country":"BE",
    "sg:address":"Hanekamlos 20",
    "sg:city":"Destelbergen",
    "sg:orig_category":"Instituts de beaut\u00e9",
    "sg:phone":"+32 9 228 78 11",
    "sg:postcode":"9070",
    "sg:province":"Oost-Vlaanderen",
    "wof:name":"Gerda Van De Velde",
    "wof:placetype":"venue"
},
  "geometry": {"coordinates":[3.7977991104,51.047290802],"type":"Point"}
}