{
  "type": "Feature",
  "properties": {
    "addr:full":"Rue De Bomer\u00c9e 11 Charleroi Hainaut 6032",
    "addr:housenumber":"11",
    "addr:postcode":"6032",
    "addr:street":"Rue De Bomere\u0301E;Hainaut",
    "iso:country":"BE",
    "sg:address":"Rue De Bomer\u00c9e 11",
    "sg:city":"Charleroi",
    "sg:orig_category":"Onderdelen and accessoires voor auto's Voertuigen",
    "sg:phone":"+32 71 36 69 38",
    "sg:postcode":"6032",
    "sg:province":"Hainaut",
    "wof:name":"Cycles Casu",
    "wof:placetype":"venue"
},
  "geometry": {"coordinates":[4.4034318924,50.3863563538],"type":"Point"}
}