{
  "type": "Feature",
  "properties": {
    "addr:full":"Gentsesteenweg 49 Harelbeke West-Vlaanderen 8530",
    "addr:housenumber":"49",
    "addr:postcode":"8530",
    "addr:street":"Gentsesteenweg",
    "iso:country":"BE",
    "sg:address":"Gentsesteenweg 49",
    "sg:city":"Harelbeke",
    "sg:classifiers":[
        {
            "category":"Bars & Pubs",
            "type":"Food & Drink"
        }
    ],
    "sg:phone":"+32 56 72 32 75",
    "sg:postcode":"8530",
    "sg:province":"West-Vlaanderen",
    "wof:name":"Ixia",
    "wof:placetype":"venue"
},
  "geometry": {"coordinates":[3.3195869923,50.8612060547],"type":"Point"}
}