{
  "type": "Feature",
  "properties": {
    "addr:full":"Rue Surlet 5 Li\u00e8ge 1 (li\u00e8ge 2) Li\u00e8ge 4020",
    "addr:housenumber":"5;1;2",
    "addr:postcode":"4020",
    "addr:street":"Rue Surlet",
    "iso:country":"BE",
    "sg:address":"Rue Surlet 5",
    "sg:city":"Li\u00e8ge 1 (li\u00e8ge 2)",
    "sg:classifiers":[
        {
            "category":"Real Estate",
            "subcategory":"Real Estate Services",
            "type":"Services"
        }
    ],
    "sg:phone":"+32 4 342 22 24",
    "sg:postcode":"4020",
    "sg:province":"Li\u00e8ge",
    "wof:name":"Euro R\u00e9sidences",
    "wof:placetype":"venue"
},
  "geometry": {"coordinates":[5.5822458267,50.6410255432],"type":"Point"}
}