{
  "type": "Feature",
  "properties": {
    "iso:country":"BE",
    "sg:address":"Rue Des D\u00c9port\u00c9s 70",
    "sg:city":"Enghien",
    "sg:orig_category":"P\u00e9pini\u00e9ristes. Fleurs and plantes",
    "sg:phone":"+32 2 395 35 40",
    "sg:postcode":"7850",
    "sg:province":"Hainaut",
    "wof:name":"Chez Marie- No\u00cblle",
    "wof:placetype":"venue"
},
  "geometry": {"coordinates":[4.0789351463,50.6845855713],"type":"Point"}
}