{
  "type": "Feature",
  "properties": {
    "addr:full":"Reties Heike 9 Kasterlee Antwerpen 2460",
    "addr:housenumber":"9",
    "addr:postcode":"2460",
    "addr:street":"Heike",
    "iso:country":"BE",
    "sg:address":"Reties Heike 9",
    "sg:city":"Kasterlee",
    "sg:classifiers":[
        {
            "category":"Parking",
            "subcategory":"Lot",
            "type":"Transportation"
        }
    ],
    "sg:phone":"+32 14 85 11 49",
    "sg:postcode":"2460",
    "sg:province":"Antwerpen",
    "sg:tags":[
        "parking-places",
        "laying-out"
    ],
    "wof:name":"Vrins R",
    "wof:placetype":"venue"
},
  "geometry": {"coordinates":[5.0122852325,51.2478675842],"type":"Point"}
}