{
  "type": "Feature",
  "properties": {
    "addr:full":"Hoogstraat 8 Zutendaal Limburg 3690",
    "addr:housenumber":"8",
    "addr:postcode":"3690",
    "addr:street":"Hoogstraat",
    "iso:country":"BE",
    "sg:address":"Hoogstraat 8",
    "sg:city":"Zutendaal",
    "sg:classifiers":[
        {
            "category":"Real Estate",
            "subcategory":"Architect",
            "type":"Services"
        }
    ],
    "sg:phone":"+32 89 62 35 00",
    "sg:postcode":"3690",
    "sg:province":"Limburg",
    "wof:name":"Bijnens & Wouters",
    "wof:placetype":"venue"
},
  "geometry": {"coordinates":[5.5717158318,50.9323196411],"type":"Point"}
}