{
  "type": "Feature",
  "properties": {
    "addr:full":"Nijverheidsln 5 Poperinge West-Vlaanderen 8970",
    "addr:housenumber":"5",
    "addr:postcode":"8970",
    "addr:street":"Nijverheidsln",
    "iso:country":"BE",
    "sg:address":"Nijverheidsln 5",
    "sg:city":"Poperinge",
    "sg:classifiers":[
        {
            "category":"Manufacturing",
            "subcategory":"Printing",
            "type":"Manufacturing & Wholesale Goods"
        }
    ],
    "sg:phone":"+32 57 33 67 21",
    "sg:postcode":"8970",
    "sg:province":"West-Vlaanderen",
    "sg:tags":[
        "publishing"
    ],
    "wof:name":"Drukkerij De Man Nv",
    "wof:placetype":"venue"
},
  "geometry": {"coordinates":[2.7362511158,50.8536872864],"type":"Point"}
}