{
  "type": "Feature",
  "properties": {
    "addr:full":"Boulevard Paepsem 20 Bruxelles (anderlecht) Bruxelles-Capitale 1070",
    "addr:housenumber":"20",
    "addr:postcode":"1070",
    "addr:street":"Boulevard Paepsem",
    "iso:country":"BE",
    "sg:address":"Boulevard Paepsem 20",
    "sg:city":"Bruxelles (anderlecht)",
    "sg:classifiers":[
        {
            "category":"Professional",
            "subcategory":"Engineering",
            "type":"Services"
        }
    ],
    "sg:phone":"+32 2 556 81 11",
    "sg:postcode":"1070",
    "sg:province":"Bruxelles-Capitale",
    "sg:tags":[
        "technical",
        "equipment",
        "offices-"
    ],
    "wof:name":"Westinghouse Electric Europe Sa",
    "wof:placetype":"venue"
},
  "geometry": {"coordinates":[4.3128418922,50.8239364624],"type":"Point"}
}