{
  "type": "Feature",
  "properties": {
    "iso:country":"BE",
    "sg:address":"Tramstraat 36 Box 6",
    "sg:city":"Brugge (assebroek)",
    "sg:classifiers":[
        {
            "category":"Professional",
            "subcategory":"Art Services",
            "type":"Services"
        }
    ],
    "sg:phone":"+32 50 36 24 46",
    "sg:postcode":"8310",
    "sg:province":"West-Vlaanderen",
    "sg:tags":[
        "graphic",
        "designer"
    ],
    "wof:name":"Ydee",
    "wof:placetype":"venue"
},
  "geometry": {"coordinates":[3.2474548817,51.2034263611],"type":"Point"}
}