{
  "type": "Feature",
  "properties": {
    "addr:full":"Hoogstraat 141ba Herzele Oost-Vlaanderen 9550",
    "addr:housenumber":"141ba",
    "addr:postcode":"9550",
    "addr:street":"Hoogstraat;Oost-Vlaanderen",
    "iso:country":"BE",
    "sg:address":"Hoogstraat 141ba",
    "sg:city":"Herzele",
    "sg:classifiers":[
        {
            "category":"Personal",
            "subcategory":"Beauty Salon",
            "type":"Services"
        }
    ],
    "sg:phone":"+32 53 62 65 18",
    "sg:postcode":"9550",
    "sg:province":"Oost-Vlaanderen",
    "sg:tags":[
        "de",
        "coiffure"
    ],
    "wof:name":"Marleen De Schamphelaire",
    "wof:placetype":"venue"
},
  "geometry": {"coordinates":[3.8759009838,50.8806266785],"type":"Point"}
}