{
  "type": "Feature",
  "properties": {
    "iso:country":"BE",
    "sg:address":"Kruishoutemstraat 4",
    "sg:city":"Zulte",
    "sg:orig_category":"Plomberie, chauffage and installations sanitaires. Eclairage et \u00e9quipements du foyer. Art and fourni",
    "sg:phone":"+32 9 386 49 40",
    "sg:postcode":"9870",
    "sg:province":"Oost-Vlaanderen",
    "wof:name":"Lustrerie Wilpa",
    "wof:placetype":"venue"
},
  "geometry": {"coordinates":[3.4985001087,50.9506607056],"type":"Point"}
}