{
  "type": "Feature",
  "properties": {
    "addr:full":"Meerlaan 12 Zottegem Oost-Vlaanderen 9620",
    "addr:housenumber":"12",
    "addr:postcode":"9620",
    "addr:street":"Meerlaan",
    "iso:country":"BE",
    "sg:address":"Meerlaan 12",
    "sg:city":"Zottegem",
    "sg:orig_category":"Beautyfarms, relaxatie and lichamelijk welzijn Kapsalons",
    "sg:phone":"+32 9 360 93 17",
    "sg:postcode":"9620",
    "sg:province":"Oost-Vlaanderen",
    "wof:name":"Coiffure La Beaut\u00c9",
    "wof:placetype":"venue"
},
  "geometry": {"coordinates":[3.8088850975,50.8669891357],"type":"Point"}
}