{
  "type": "Feature",
  "properties": {
    "addr:full":"Heikant 115 Heusden-zolder Limburg 3550",
    "addr:housenumber":"115",
    "addr:postcode":"3550",
    "addr:street":"Heikant",
    "iso:country":"BE",
    "sg:address":"Heikant 115",
    "sg:city":"Heusden-zolder",
    "sg:classifiers":[
        {
            "category":"Restaurant",
            "type":"Food & Drink"
        }
    ],
    "sg:phone":"+32 11 53 68 11",
    "sg:postcode":"3550",
    "sg:province":"Limburg",
    "wof:name":"De Koreander",
    "wof:placetype":"venue"
},
  "geometry": {"coordinates":[5.2927861214,51.0144309998],"type":"Point"}
}