{
  "type": "Feature",
  "properties": {
    "iso:country":"BE",
    "sg:address":"Chauss\u00e9e De Bruxelles 270",
    "sg:city":"Waterloo",
    "sg:classifiers":[
        {
            "category":"Personal",
            "subcategory":"Beauty Salon",
            "type":"Services"
        }
    ],
    "sg:phone":"+32 2 354 62 03",
    "sg:postcode":"1410",
    "sg:province":"Brabant Wallon",
    "wof:name":"Oasis Of Beauty (the)",
    "wof:placetype":"venue"
},
  "geometry": {"coordinates":[4.3986201286,50.7152328491],"type":"Point"}
}