{
  "type": "Feature",
  "properties": {
    "iso:country":"BE",
    "sg:address":"Vinkstraat 137",
    "sg:city":"Watermaal-bosvoorde/watermael-boitsfort",
    "sg:orig_category":"Plaatsen van vloer- and muurbekleding Schilders",
    "sg:phone":"+32 2 672 90 60",
    "sg:postcode":"1170",
    "sg:province":"Bruxelles-Capitale",
    "wof:name":"Brotcorne Raoul",
    "wof:placetype":"venue"
},
  "geometry": {"coordinates":[4.4095730782,50.8008613586],"type":"Point"}
}