{
  "type": "Feature",
  "properties": {
    "addr:full":"Brugsestraat 191 Zedelgem West-Vlaanderen 8210",
    "addr:housenumber":"191",
    "addr:postcode":"8210",
    "addr:street":"Brugsestraat",
    "iso:country":"BE",
    "sg:address":"Brugsestraat 191",
    "sg:city":"Zedelgem",
    "sg:classifiers":[
        {
            "category":"Farming",
            "subcategory":"Livestock Farm",
            "type":"Manufacturing & Wholesale Goods"
        }
    ],
    "sg:phone":"+32 50 20 09 86",
    "sg:postcode":"8210",
    "sg:province":"West-Vlaanderen",
    "sg:tags":[
        "buyer"
    ],
    "wof:name":"Vandenbroucke D",
    "wof:placetype":"venue"
},
  "geometry": {"coordinates":[3.1419129372,51.1276779175],"type":"Point"}
}