{
  "type": "Feature",
  "properties": {
    "iso:country":"BE",
    "sg:address":"Keistraat 3a",
    "sg:city":"Knesselare",
    "sg:classifiers":[
        {
            "category":"Building & Trades",
            "subcategory":"Pest Control",
            "type":"Services"
        }
    ],
    "sg:phone":"+32 9 374 57 39",
    "sg:postcode":"9910",
    "sg:province":"Oost-Vlaanderen",
    "sg:tags":[
        "painting",
        "contractor"
    ],
    "wof:name":"Van Houcke Nv",
    "wof:placetype":"venue"
},
  "geometry": {"coordinates":[3.4293479919,51.1417274475],"type":"Point"}
}