{
  "type": "Feature",
  "properties": {
    "addr:full":"Rue Des Capucins 8 Arlon Luxembourg 6700",
    "addr:housenumber":"8",
    "addr:postcode":"6700",
    "addr:street":"Rue Des Capucins",
    "iso:country":"BE",
    "sg:address":"Rue Des Capucins 8",
    "sg:city":"Arlon",
    "sg:orig_category":"Pain, p\u00e2tisseries and confiseries",
    "sg:phone":"+32 63 23 29 60",
    "sg:postcode":"6700",
    "sg:province":"Luxembourg",
    "wof:name":"Peches Mignons Du Goethe",
    "wof:placetype":"venue"
},
  "geometry": {"coordinates":[5.8136820793,49.6844100952],"type":"Point"}
}