{
  "type": "Feature",
  "properties": {
    "addr:full":"Pastorijstraat 22 Merksplas Antwerpen 2330",
    "addr:housenumber":"22",
    "addr:postcode":"2330",
    "addr:street":"Pastorijstraat",
    "iso:country":"BE",
    "sg:address":"Pastorijstraat 22",
    "sg:city":"Merksplas",
    "sg:orig_category":"Installation de menuiserie en bois and plastique",
    "sg:phone":"+32 14 63 31 58",
    "sg:postcode":"2330",
    "sg:province":"Antwerpen",
    "wof:name":"Jozef Remeysen",
    "wof:placetype":"venue"
},
  "geometry": {"coordinates":[4.8610072136,51.3606414795],"type":"Point"}
}