{
  "type": "Feature",
  "properties": {
    "addr:full":"All\u00e9e Jean De La Fontaine 12 Bruxelles (uccle) Bruxelles-Capitale 1180",
    "addr:housenumber":"12",
    "addr:postcode":"1180",
    "addr:street":"Alle\u0301E Jean De La Fontaine",
    "iso:country":"BE",
    "sg:address":"All\u00e9e Jean De La Fontaine 12",
    "sg:city":"Bruxelles (uccle)",
    "sg:classifiers":[
        {
            "category":"Freight",
            "type":"Transportation"
        }
    ],
    "sg:phone":"+32 2 374 16 62",
    "sg:postcode":"1180",
    "sg:province":"Bruxelles-Capitale",
    "sg:tags":[
        "express",
        "transport"
    ],
    "wof:name":"Multi Transports Service Sprl",
    "wof:placetype":"venue"
},
  "geometry": {"coordinates":[4.3468608856,50.7798118591],"type":"Point"}
}