{
  "type": "Feature",
  "properties": {
    "addr:full":"Voie Cardijn 1 Ottignies-louvain-la-neuve (louvain-la-neuve) Brabant Wallon 1348",
    "addr:housenumber":"1",
    "addr:postcode":"1348",
    "addr:street":"Voie Cardijn",
    "iso:country":"BE",
    "sg:address":"Voie Cardijn 1",
    "sg:city":"Ottignies-louvain-la-neuve (louvain-la-neuve)",
    "sg:classifiers":[
        {
            "category":"Education",
            "subcategory":"School",
            "type":"Public Place"
        }
    ],
    "sg:phone":"+32 10 45 01 02",
    "sg:postcode":"1348",
    "sg:province":"Brabant Wallon",
    "sg:tags":[
        "primary"
    ],
    "wof:name":"Ecole Fondamentale Martin V",
    "wof:placetype":"venue"
},
  "geometry": {"coordinates":[4.610560894,50.6724624634],"type":"Point"}
}