{
  "type": "Feature",
  "properties": {
    "addr:full":"Rue Naimette 39 Li\u00c8ge Li\u00e8ge 4000",
    "addr:housenumber":"39",
    "addr:postcode":"4000",
    "addr:street":"Rue Naimette",
    "iso:country":"BE",
    "sg:address":"Rue Naimette 39",
    "sg:city":"Li\u00c8ge",
    "sg:orig_category":"Agences de presse",
    "sg:phone":"+32 4 226 50 04",
    "sg:postcode":"4000",
    "sg:province":"Li\u00e8ge",
    "wof:name":"Alain Delaunois",
    "wof:placetype":"venue"
},
  "geometry": {"coordinates":[5.5628762245,50.6505470276],"type":"Point"}
}