{
  "type": "Feature",
  "properties": {
    "addr:full":"Kerkhofstraat 631 Boom Antwerpen 2850",
    "addr:housenumber":"631",
    "addr:postcode":"2850",
    "addr:street":"Kerkhofstraat",
    "iso:country":"BE",
    "sg:address":"Kerkhofstraat 631",
    "sg:city":"Boom",
    "sg:classifiers":[
        {
            "category":"Government",
            "subcategory":"Fire Station",
            "type":"Public Place"
        }
    ],
    "sg:phone":"+32 3 888 28 65",
    "sg:postcode":"2850",
    "sg:province":"Antwerpen",
    "sg:tags":[
        "installation",
        "-",
        "air conditioning"
    ],
    "wof:name":"Liekens J",
    "wof:placetype":"venue"
},
  "geometry": {"coordinates":[4.3869428635,51.099899292],"type":"Point"}
}