{
  "type": "Feature",
  "properties": {
    "iso:country":"BE",
    "sg:address":"Warrimont 174",
    "sg:city":"Herve",
    "sg:orig_category":"Installatie van metalen schrijnwerk",
    "sg:phone":"+32 87 66 21 79",
    "sg:postcode":"4654",
    "sg:province":"Li\u00e8ge",
    "wof:name":"V. Mazzulli",
    "wof:placetype":"venue"
},
  "geometry": {"coordinates":[5.8042421341,50.6694908142],"type":"Point"}
}