{
  "type": "Feature",
  "properties": {
    "addr:full":"Rue De Roubaix 1 Doornik Hainaut 7520",
    "addr:housenumber":"1",
    "addr:postcode":"7520",
    "addr:street":"Rue De Roubaix",
    "iso:country":"BE",
    "sg:address":"Rue De Roubaix 1",
    "sg:city":"Doornik",
    "sg:classifiers":[
        {
            "category":"Arena",
            "subcategory":"Sports Club",
            "type":"Entertainment"
        }
    ],
    "sg:phone":"+32 69 35 35 24",
    "sg:postcode":"7520",
    "sg:province":"Hainaut",
    "sg:tags":[
        "de"
    ],
    "wof:name":"Cazeau P\u00c9dale - Templeuve",
    "wof:placetype":"venue"
},
  "geometry": {"coordinates":[3.2827498913,50.6446456909],"type":"Point"}
}