{
  "type": "Feature",
  "properties": {
    "iso:country":"BE",
    "sg:address":"Provincieweg 55",
    "sg:city":"Gistel (moere)",
    "sg:classifiers":[
        {
            "category":"Building & Trades",
            "subcategory":"Electrical",
            "type":"Services"
        }
    ],
    "sg:phone":"+32 59 27 43 77",
    "sg:postcode":"8470",
    "sg:province":"West-Vlaanderen",
    "sg:tags":[
        "electric",
        "-",
        "housewiring",
        "contractor"
    ],
    "wof:name":"Elektriciteit Steen",
    "wof:placetype":"venue"
},
  "geometry": {"coordinates":[2.972276926,51.1269111633],"type":"Point"}
}