{
  "type": "Feature",
  "properties": {
    "iso:country":"BE",
    "sg:address":"Seestrasse 24",
    "sg:city":"B\u00fctgenbach",
    "sg:classifiers":[
        {
            "category":"Bars & Pubs",
            "type":"Food & Drink"
        }
    ],
    "sg:phone":"+32 80 44 03 20",
    "sg:postcode":"4750",
    "sg:province":"Li\u00e8ge",
    "wof:name":"Tupferkeller",
    "wof:placetype":"venue"
},
  "geometry": {"coordinates":[6.2078390121,50.4261131287],"type":"Point"}
}