{
  "type": "Feature",
  "properties": {
    "addr:full":"Rue De La Station 55 Orp-jauche (orp-le-grand) Brabant Wallon 1350",
    "addr:housenumber":"55",
    "addr:postcode":"1350",
    "addr:street":"Rue De La Station",
    "iso:country":"BE",
    "sg:address":"Rue De La Station 55",
    "sg:city":"Orp-jauche (orp-le-grand)",
    "sg:classifiers":[
        {
            "category":"Personal",
            "subcategory":"Beauty Salon",
            "type":"Services"
        }
    ],
    "sg:phone":"+32 19 63 33 40",
    "sg:postcode":"1350",
    "sg:province":"Brabant Wallon",
    "sg:tags":[
        "lady",
        "-",
        "hairdressing"
    ],
    "wof:name":"Visa Coiffure",
    "wof:placetype":"venue"
},
  "geometry": {"coordinates":[4.9876217842,50.6979217529],"type":"Point"}
}