{
  "type": "Feature",
  "properties": {
    "iso:country":"BE",
    "sg:address":"Stationsstraat 176",
    "sg:city":"Ardooie",
    "sg:orig_category":"Non-Classified Establishments",
    "sg:phone":"+32 51 74 51 37",
    "sg:postcode":"8850",
    "sg:province":"West-Vlaanderen",
    "wof:name":"Metafox Nv",
    "wof:placetype":"venue"
},
  "geometry": {"coordinates":[3.2048580647,50.9906196594],"type":"Point"}
}