{
  "type": "Feature",
  "properties": {
    "iso:country":"BE",
    "sg:address":"Chauss\u00c9e De Heusy 77",
    "sg:city":"Verviers",
    "sg:orig_category":"Rusthuizen and serviceflats",
    "sg:phone":"+32 87 22 31 42",
    "sg:postcode":"4800",
    "sg:province":"Li\u00e8ge",
    "wof:name":"R\u00c9sidence St.joseph",
    "wof:placetype":"venue"
},
  "geometry": {"coordinates":[5.8644871712,50.5883216858],"type":"Point"}
}