{
  "type": "Feature",
  "properties": {
    "addr:full":"Paul Housmansstraat 6b12 Antwerpen Antwerpen 2050",
    "addr:housenumber":"6b12",
    "addr:postcode":"2050",
    "addr:street":"Housmansstraat",
    "iso:country":"BE",
    "sg:address":"Paul Housmansstraat 6b12",
    "sg:city":"Antwerpen",
    "sg:classifiers":[
        {
            "category":"Arena",
            "subcategory":"Sports Club",
            "type":"Entertainment"
        }
    ],
    "sg:phone":"+32 3 219 75 17",
    "sg:postcode":"2050",
    "sg:province":"Antwerpen",
    "sg:tags":[
        "de"
    ],
    "wof:name":"Wapper",
    "wof:placetype":"venue"
},
  "geometry": {"coordinates":[4.3766770363,51.2261505127],"type":"Point"}
}