{
  "type": "Feature",
  "properties": {
    "iso:country":"BE",
    "sg:address":"Avenue Albert Ier 83a",
    "sg:city":"Ottignies-louvain-la-neuve",
    "sg:classifiers":[
        {
            "category":"Building & Trades",
            "subcategory":"Construction",
            "type":"Services"
        }
    ],
    "sg:phone":"+32 10 43 89 11",
    "sg:postcode":"1342",
    "sg:province":"Brabant Wallon",
    "sg:tags":[
        "la",
        "de",
        "\u00e9quipement",
        "pour",
        "machine",
        "location"
    ],
    "wof:name":"Benelmat",
    "wof:placetype":"venue"
},
  "geometry": {"coordinates":[4.5727128983,50.6795082092],"type":"Point"}
}