{
  "type": "Feature",
  "properties": {
    "iso:country":"BE",
    "sg:address":"Chauss\u00e9e De Louvain 484",
    "sg:city":"Namur (bouge)",
    "sg:classifiers":[
        {
            "category":"Manufacturing",
            "subcategory":"Wood Products",
            "type":"Manufacturing & Wholesale Goods"
        }
    ],
    "sg:phone":"+32 81 83 59 31",
    "sg:postcode":"5004",
    "sg:province":"Namur",
    "sg:tags":[
        "preservation"
    ],
    "wof:name":"Humi-stop",
    "wof:placetype":"venue"
},
  "geometry": {"coordinates":[4.88956213,50.4852142334],"type":"Point"}
}