{
  "type": "Feature",
  "properties": {
    "addr:full":"Lange Nieuwstraat 67 Antwerpen Antwerpen 2000",
    "addr:housenumber":"67",
    "addr:postcode":"2000",
    "addr:street":"Lange Nieuwstraat",
    "iso:country":"BE",
    "sg:address":"Lange Nieuwstraat 67",
    "sg:city":"Antwerpen",
    "sg:orig_category":"M\u00e9decins and sp\u00e9cialistes",
    "sg:phone":"+32 3 231 46 73",
    "sg:postcode":"2000",
    "sg:province":"Antwerpen",
    "wof:name":"Katrien Piessens",
    "wof:placetype":"venue"
},
  "geometry": {"coordinates":[4.4100008011,51.2197647095],"type":"Point"}
}