{
  "type": "Feature",
  "properties": {
    "iso:country":"BE",
    "sg:address":"Steenhouwersvest 65 A1",
    "sg:city":"Antwerpen",
    "sg:classifiers":[
        {
            "category":"Shopping",
            "subcategory":"Clothing, Apparel, & Fashions",
            "type":"Retail Goods"
        }
    ],
    "sg:phone":"+32 3 234 22 95",
    "sg:postcode":"2000",
    "sg:province":"Antwerpen",
    "sg:tags":[
        "ondergoed",
        "lingerie"
    ],
    "wof:name":"Dobber Bjorn Borg Store Antwerpen",
    "wof:placetype":"venue"
},
  "geometry": {"coordinates":[4.4110541344,51.1906738281],"type":"Point"}
}