{
  "type": "Feature",
  "properties": {
    "iso:country":"BE",
    "sg:address":"Ankerstraat 138",
    "sg:city":"Sint-niklaas",
    "sg:classifiers":[
        {
            "category":"Manufacturing",
            "subcategory":"Textiles",
            "type":"Manufacturing & Wholesale Goods"
        }
    ],
    "sg:phone":"+32 3 776 95 00",
    "sg:postcode":"9100",
    "sg:province":"Oost-Vlaanderen",
    "sg:tags":[
        "retail",
        "-"
    ],
    "wof:name":"Valatex",
    "wof:placetype":"venue"
},
  "geometry": {"coordinates":[4.1478228569,51.1678161621],"type":"Point"}
}