{
  "type": "Feature",
  "properties": {
    "iso:country":"BE",
    "sg:address":"Rue Du Ban-de-villers 7",
    "sg:city":"Etalle",
    "sg:orig_category":"Cabinets d\u00b4huissiers",
    "sg:phone":"+32 63 57 63 86",
    "sg:postcode":"6741",
    "sg:province":"Luxembourg",
    "wof:name":"Patrick Hicguet",
    "wof:placetype":"venue"
},
  "geometry": {"coordinates":[5.6673212051,49.6705703735],"type":"Point"}
}