{
  "type": "Feature",
  "properties": {
    "iso:country":"BE",
    "sg:address":"Van Schoonhovenstraat 44",
    "sg:city":"Antwerpen",
    "sg:classifiers":[
        {
            "category":"Bars & Pubs",
            "type":"Food & Drink"
        }
    ],
    "sg:phone":"+32 3 226 07 64",
    "sg:postcode":"2060",
    "sg:province":"Antwerpen",
    "wof:name":"Toerist",
    "wof:placetype":"venue"
},
  "geometry": {"coordinates":[4.4220209122,51.2202262878],"type":"Point"}
}