{
  "type": "Feature",
  "properties": {
    "addr:full":"Marktplein 13 Oosterzele Oost-Vlaanderen 9860",
    "addr:housenumber":"13",
    "addr:postcode":"9860",
    "addr:street":"Marktplein;Oost-Vlaanderen",
    "iso:country":"BE",
    "sg:address":"Marktplein 13",
    "sg:city":"Oosterzele",
    "sg:orig_category":"Boucheries",
    "sg:phone":"+32 9 362 57 25",
    "sg:postcode":"9860",
    "sg:province":"Oost-Vlaanderen",
    "wof:name":"Vleeswaren Hole",
    "wof:placetype":"venue"
},
  "geometry": {"coordinates":[3.7841858864,50.9380187988],"type":"Point"}
}