{
  "type": "Feature",
  "properties": {
    "addr:full":"Universiteitslaan 2 Kortrijk West-Vlaanderen 8500",
    "addr:housenumber":"2",
    "addr:postcode":"8500",
    "addr:street":"Universiteitslaan",
    "iso:country":"BE",
    "sg:address":"Universiteitslaan 2",
    "sg:city":"Kortrijk",
    "sg:orig_category":"Rev\u00eatements de sols and murs",
    "sg:phone":"+32 56 42 71 10",
    "sg:postcode":"8500",
    "sg:province":"West-Vlaanderen",
    "wof:name":"Multi-step",
    "wof:placetype":"venue"
},
  "geometry": {"coordinates":[3.2817211151,50.8070487976],"type":"Point"}
}