{
  "type": "Feature",
  "properties": {
    "addr:full":"Chauss\u00e9e De Grammont 26 Ath (ghislenghien) Hainaut 7822",
    "addr:housenumber":"26",
    "addr:postcode":"7822",
    "addr:street":"Chausse\u0301E De Grammont",
    "iso:country":"BE",
    "sg:address":"Chauss\u00e9e De Grammont 26",
    "sg:city":"Ath (ghislenghien)",
    "sg:classifiers":[
        {
            "category":"Shopping",
            "subcategory":"Bicycles & Sporting Goods",
            "type":"Retail Goods"
        }
    ],
    "sg:phone":"+32 495 52 26 37",
    "sg:postcode":"7822",
    "sg:province":"Hainaut",
    "sg:tags":[
        "tyre"
    ],
    "wof:name":"Speed Service (chez)",
    "wof:placetype":"venue"
},
  "geometry": {"coordinates":[3.8452620506,50.6482391357],"type":"Point"}
}