{
  "type": "Feature",
  "properties": {
    "iso:country":"BE",
    "sg:address":"Rue Des Croisons 13",
    "sg:city":"Mont-de-l'enclus (amougies)",
    "sg:classifiers":[
        {
            "category":"Health Services",
            "subcategory":"Health Practitioner",
            "type":"Services"
        }
    ],
    "sg:phone":"+32 69 76 89 17",
    "sg:postcode":"7750",
    "sg:province":"Hainaut",
    "sg:tags":[
        "physiotherapist"
    ],
    "wof:name":"Braye Guy",
    "wof:placetype":"venue"
},
  "geometry": {"coordinates":[5.0023469925,50.3222923279],"type":"Point"}
}