{
  "type": "Feature",
  "properties": {
    "addr:full":"Bruggestraat 209 Torhout West-Vlaanderen 8820",
    "addr:housenumber":"209",
    "addr:postcode":"8820",
    "addr:street":"Bruggestraat",
    "iso:country":"BE",
    "sg:address":"Bruggestraat 209",
    "sg:city":"Torhout",
    "sg:orig_category":"Voertuigen",
    "sg:phone":"+32 50 21 12 50",
    "sg:postcode":"8820",
    "sg:province":"West-Vlaanderen",
    "wof:name":"Willy Verplancke",
    "wof:placetype":"venue"
},
  "geometry": {"coordinates":[3.1212940216,51.0851974487],"type":"Point"}
}