{
  "type": "Feature",
  "properties": {
    "addr:full":"Rue Tour Sainte-barbe 9 Quievrain Hainaut 7380",
    "addr:housenumber":"9",
    "addr:postcode":"7380",
    "addr:street":"Rue Tour Sainte-Barbe;Hainaut",
    "iso:country":"BE",
    "sg:address":"Rue Tour Sainte-barbe 9",
    "sg:city":"Quievrain",
    "sg:orig_category":"Slagers",
    "sg:phone":"+32 65 45 73 66",
    "sg:postcode":"7380",
    "sg:province":"Hainaut",
    "wof:name":"Jean Wattier",
    "wof:placetype":"venue"
},
  "geometry": {"coordinates":[3.6828620434,50.4079780579],"type":"Point"}
}