{
  "type": "Feature",
  "properties": {
    "addr:full":"Schapenstraat 66 Lennik Vlaams-Brabant 1750",
    "addr:housenumber":"66;1750",
    "addr:street":"Schapenstraat;Vlaams-Brabant",
    "iso:country":"BE",
    "sg:address":"Schapenstraat 66",
    "sg:city":"Lennik",
    "sg:orig_category":"Banken and kredietinstellingen",
    "sg:phone":"+32 2 532 45 91",
    "sg:postcode":"1750",
    "sg:province":"Vlaams-Brabant",
    "wof:name":"Dexia",
    "wof:placetype":"venue"
},
  "geometry": {"coordinates":[4.1672167778,50.8162765503],"type":"Point"}
}