{
  "type": "Feature",
  "properties": {
    "addr:full":"Rue Des Sartis 46 Hensies Hainaut 7350",
    "addr:housenumber":"46",
    "addr:postcode":"7350",
    "addr:street":"Rue Des Sartis",
    "iso:country":"BE",
    "sg:address":"Rue Des Sartis 46",
    "sg:city":"Hensies",
    "sg:orig_category":"Artistes ind\u00e9pendants",
    "sg:phone":"+32 65 43 16 22",
    "sg:postcode":"7350",
    "sg:province":"Hainaut",
    "wof:name":"Jacques De Bock",
    "wof:placetype":"venue"
},
  "geometry": {"coordinates":[3.6890349388,50.4511947632],"type":"Point"}
}