{
  "type": "Feature",
  "properties": {
    "iso:country":"BE",
    "sg:address":"Prins Van Luiklaan 154",
    "sg:city":"Anderlecht/anderlecht",
    "sg:orig_category":"Artsen and specialisten",
    "sg:phone":"+32 2 522 58 91",
    "sg:postcode":"1070",
    "sg:province":"Bruxelles-Capitale",
    "wof:name":"Graziella Sollami",
    "wof:placetype":"venue"
},
  "geometry": {"coordinates":[4.3026571274,50.8425521851],"type":"Point"}
}