{
  "type": "Feature",
  "properties": {
    "iso:country":"BE",
    "sg:address":"Molenstraat 76",
    "sg:city":"Temse",
    "sg:orig_category":"Banques and organismes de cr\u00e9dit. Assurances habitation compagnies. Assurances vie compagnies",
    "sg:phone":"+32 3 771 16 90",
    "sg:postcode":"9140",
    "sg:province":"Oost-Vlaanderen",
    "wof:name":"De Vaderlandsche",
    "wof:placetype":"venue"
},
  "geometry": {"coordinates":[4.1751642227,51.1295394897],"type":"Point"}
}