{
  "type": "Feature",
  "properties": {
    "iso:country":"BE",
    "sg:address":"Avenue Minerve 31",
    "sg:city":"Vorst/forest",
    "sg:orig_category":"Pain, p\u00e2tisseries and confiseries",
    "sg:phone":"+32 2 344 42 99",
    "sg:postcode":"1190",
    "sg:province":"Bruxelles-Capitale",
    "wof:name":"P\u00c2tisserie Gaudron",
    "wof:placetype":"venue"
},
  "geometry": {"coordinates":[4.3310918808,50.8103027344],"type":"Point"}
}