{
  "type": "Feature",
  "properties": {
    "addr:full":"Rue De L'avenir 8 Frameries (la Bouverie) Hainaut 7080",
    "addr:housenumber":"8",
    "addr:postcode":"7080",
    "addr:street":"Rue De L'Avenir",
    "iso:country":"BE",
    "sg:address":"Rue De L'avenir 8",
    "sg:city":"Frameries (la Bouverie)",
    "sg:classifiers":[
        {
            "category":"Health Services",
            "subcategory":"Nursing And Care Facility",
            "type":"Services"
        }
    ],
    "sg:phone":"+32 65 67 18 74",
    "sg:postcode":"7080",
    "sg:province":"Hainaut",
    "sg:tags":[
        "home",
        "rest"
    ],
    "wof:name":"Magnolias (les)",
    "wof:placetype":"venue"
},
  "geometry": {"coordinates":[3.8871090412,50.4019737244],"type":"Point"}
}