{
  "type": "Feature",
  "properties": {
    "iso:country":"BE",
    "sg:address":"Schanslaan 46",
    "sg:city":"Borsbeek",
    "sg:classifiers":[
        {
            "category":"Utilities",
            "subcategory":"Refuse",
            "type":"Services"
        }
    ],
    "sg:phone":"+32 3 321 56 49",
    "sg:postcode":"2150",
    "sg:province":"Antwerpen",
    "sg:tags":[
        "boiler",
        "-",
        "heating",
        "steam"
    ],
    "wof:name":"Remue Bvba",
    "wof:placetype":"venue"
},
  "geometry": {"coordinates":[4.490694046,51.1915283203],"type":"Point"}
}