{
  "type": "Feature",
  "properties": {
    "iso:country":"BE",
    "sg:address":"Fond De For\u00cat 55",
    "sg:city":"Fleron",
    "sg:orig_category":"Vertalers and tolken",
    "sg:phone":"+32 4 358 68 00",
    "sg:postcode":"4623",
    "sg:province":"Li\u00e8ge",
    "wof:name":"Michaux C. Cbtip",
    "wof:placetype":"venue"
},
  "geometry": {"coordinates":[5.6878008842,50.6002311707],"type":"Point"}
}