{
  "type": "Feature",
  "properties": {
    "addr:full":"Petite Normandie 34 Kraainem/kraainem Vlaams-Brabant 1950",
    "addr:housenumber":"34",
    "addr:postcode":"1950",
    "addr:street":"Petite Normandie",
    "iso:country":"BE",
    "sg:address":"Petite Normandie 34",
    "sg:city":"Kraainem/kraainem",
    "sg:orig_category":"Artistes ind\u00e9pendants",
    "sg:phone":"+32 2 720 39 62",
    "sg:postcode":"1950",
    "sg:province":"Vlaams-Brabant",
    "wof:name":"Marc Tasnier",
    "wof:placetype":"venue"
},
  "geometry": {"coordinates":[4.4634099007,50.8606414795],"type":"Point"}
}