{
  "type": "Feature",
  "properties": {
    "iso:country":"BE",
    "sg:address":"Zagmanstraat 40",
    "sg:city":"Nazareth",
    "sg:orig_category":"Eleveurs de bovins. Eleveurs and marchands de porcs",
    "sg:phone":"+32 9 385 43 86",
    "sg:postcode":"9810",
    "sg:province":"Oost-Vlaanderen",
    "wof:name":"Luc Vandenbossche",
    "wof:placetype":"venue"
},
  "geometry": {"coordinates":[3.6375300884,50.9657402039],"type":"Point"}
}