{
  "type": "Feature",
  "properties": {
    "iso:country":"BE",
    "sg:address":"Route De Liers 2",
    "sg:city":"Herstal",
    "sg:orig_category":"Bouwmaterialen Gh Vloer- and muurbekleding",
    "sg:phone":"+32 4 278 73 25",
    "sg:postcode":"4041",
    "sg:province":"Li\u00e8ge",
    "wof:name":"Van Dijck",
    "wof:placetype":"venue"
},
  "geometry": {"coordinates":[5.5867710114,50.6886253357],"type":"Point"}
}