{
  "type": "Feature",
  "properties": {
    "addr:full":"Rue Du Camp-romain 20 Dinant Namur 5500",
    "addr:housenumber":"20",
    "addr:postcode":"5500",
    "addr:street":"Rue Du Camp-Romain",
    "iso:country":"BE",
    "sg:address":"Rue Du Camp-romain 20",
    "sg:city":"Dinant",
    "sg:orig_category":"H\u00f4tels. Restaurants",
    "sg:phone":"+32 82 22 55 25",
    "sg:postcode":"5500",
    "sg:province":"Namur",
    "wof:name":"Ferme Belles Gourmandes",
    "wof:placetype":"venue"
},
  "geometry": {"coordinates":[4.9119329453,50.2604866028],"type":"Point"}
}