{
  "type": "Feature",
  "properties": {
    "iso:country":"BE",
    "sg:address":"Nicolaylaan 91",
    "sg:city":"Leopoldsburg",
    "sg:classifiers":[
        {
            "category":"Autos & Motor Vehicles",
            "subcategory":"Fuel & Gas Station",
            "type":"Retail Goods"
        }
    ],
    "sg:phone":"+32 11 34 18 54",
    "sg:postcode":"3970",
    "sg:province":"Limburg",
    "sg:tags":[
        "repair",
        "drier",
        "laundry",
        "-",
        "machine",
        "mainten",
        "washing",
        "automatic"
    ],
    "wof:name":"Electro Vandormael",
    "wof:placetype":"venue"
},
  "geometry": {"coordinates":[5.2583928108,51.1183052063],"type":"Point"}
}