{
  "type": "Feature",
  "properties": {
    "iso:country":"BE",
    "sg:address":"Schoolstraat 22",
    "sg:city":"Herselt (ramsel)",
    "sg:classifiers":[
        {
            "category":"Retail",
            "subcategory":"Laundry & Dry Cleaning",
            "type":"Services"
        }
    ],
    "sg:phone":"+32 16 69 95 46",
    "sg:postcode":"2230",
    "sg:province":"Antwerpen",
    "sg:tags":[
        "dyer",
        "cleaner"
    ],
    "wof:name":"Ely Shop",
    "wof:placetype":"venue"
},
  "geometry": {"coordinates":[4.8301229477,51.0294418335],"type":"Point"}
}