{
  "type": "Feature",
  "properties": {
    "iso:country":"BE",
    "sg:address":"Waverse Steenweg 679",
    "sg:city":"Etterbeek/etterbeek",
    "sg:classifiers":[
        {
            "category":"Shopping",
            "subcategory":"Clothing, Apparel, & Fashions",
            "type":"Retail Goods"
        }
    ],
    "sg:phone":"+32 2 649 17 18",
    "sg:postcode":"1040",
    "sg:province":"Bruxelles-Capitale",
    "sg:tags":[
        "ondergoed",
        "lingerie"
    ],
    "wof:name":"Hunkem\u00d6ller",
    "wof:placetype":"venue"
},
  "geometry": {"coordinates":[4.3951997757,50.8335914612],"type":"Point"}
}