{
  "type": "Feature",
  "properties": {
    "iso:country":"BE",
    "sg:address":"A. Nichelsstraat 6",
    "sg:city":"Aalst (groot)",
    "sg:orig_category":"Huishoudapparaten, televisies and radio's",
    "sg:phone":"+32 53 77 36 36",
    "sg:postcode":"9300",
    "sg:province":"Oost-Vlaanderen",
    "wof:name":"Limit Electronics",
    "wof:placetype":"venue"
},
  "geometry": {"coordinates":[4.0448532104,50.9348945618],"type":"Point"}
}