{
  "type": "Feature",
  "properties": {
    "iso:country":"BE",
    "sg:address":"Sint-jansbeekveld 15",
    "sg:city":"Bornem",
    "sg:orig_category":"Plomberie, chauffage and installations sanitaires. Constructions r\u00e9sidentielles sp\u00e9cifiques",
    "sg:phone":"+32 52 34 19 09",
    "sg:postcode":"2880",
    "sg:province":"Antwerpen",
    "wof:name":"Geert Van Praet",
    "wof:placetype":"venue"
},
  "geometry": {"coordinates":[4.1957421303,51.0651626587],"type":"Point"}
}