{
  "type": "Feature",
  "properties": {
    "addr:full":"Mechelsesteenweg 761 Herent Vlaams-Brabant 3020",
    "addr:housenumber":"761",
    "addr:postcode":"3020",
    "addr:street":"Mechelsesteenweg",
    "iso:country":"BE",
    "sg:address":"Mechelsesteenweg 761",
    "sg:city":"Herent",
    "sg:classifiers":[
        {
            "category":"Professional",
            "subcategory":"Accounting & Tax Preparation",
            "type":"Services"
        }
    ],
    "sg:phone":"+32 16 49 97 60",
    "sg:postcode":"3020",
    "sg:province":"Vlaams-Brabant",
    "sg:tags":[
        "accountant"
    ],
    "wof:name":"Fiducial Accountancy Nv",
    "wof:placetype":"venue"
},
  "geometry": {"coordinates":[4.648982048,50.9199867249],"type":"Point"}
}