{
  "type": "Feature",
  "properties": {
    "addr:full":"Rue Saint-pierre 52bb Moeskroen/mouscron Hainaut 7700",
    "addr:housenumber":"52bb moeskroen;mouscron",
    "addr:postcode":"7700",
    "addr:street":"Rue Saint-Pierre;Hainaut",
    "iso:country":"BE",
    "sg:address":"Rue Saint-pierre 52bb",
    "sg:city":"Moeskroen/mouscron",
    "sg:classifiers":[
        {
            "category":"Insurance",
            "subcategory":"Life Insurance",
            "type":"Services"
        }
    ],
    "sg:phone":"+32 56 34 71 27",
    "sg:postcode":"7700",
    "sg:province":"Hainaut",
    "sg:tags":[
        "assurance"
    ],
    "wof:name":"Assurances Geenens Amaury",
    "wof:placetype":"venue"
},
  "geometry": {"coordinates":[3.2323200703,50.7400932312],"type":"Point"}
}