{
  "type": "Feature",
  "properties": {
    "iso:country":"BE",
    "sg:address":"Kokelarestraat 93",
    "sg:city":"Izegem",
    "sg:classifiers":[
        {
            "category":"Insurance",
            "subcategory":"Insurance Agent",
            "type":"Services"
        }
    ],
    "sg:phone":"+32 51 30 78 80",
    "sg:postcode":"8870",
    "sg:province":"West-Vlaanderen",
    "sg:tags":[
        "broker"
    ],
    "wof:name":"Devoldere Jan Bvba",
    "wof:placetype":"venue"
},
  "geometry": {"coordinates":[3.1888530254,50.910068512],"type":"Point"}
}