{
  "type": "Feature",
  "properties": {
    "addr:full":"Liersesteenweg 63 Mortsel Antwerpen 2640",
    "addr:housenumber":"63",
    "addr:postcode":"2640",
    "addr:street":"Liersesteenweg",
    "iso:country":"BE",
    "sg:address":"Liersesteenweg 63",
    "sg:city":"Mortsel",
    "sg:classifiers":[
        {
            "category":"Health Services",
            "subcategory":"Health Practitioner",
            "type":"Services"
        }
    ],
    "sg:phone":"+32 3 440 13 24",
    "sg:postcode":"2640",
    "sg:province":"Antwerpen",
    "sg:tags":[
        "physiotherapist"
    ],
    "wof:name":"Van De Weerd Ang\u00e8le",
    "wof:placetype":"venue"
},
  "geometry": {"coordinates":[4.4616518021,51.1697654724],"type":"Point"}
}