{
  "type": "Feature",
  "properties": {
    "iso:country":"BE",
    "sg:address":"Kortijns Heiken 1",
    "sg:city":"Retie",
    "sg:orig_category":"Sportclubs",
    "sg:phone":"+32 14 67 80 28",
    "sg:postcode":"2470",
    "sg:province":"Antwerpen",
    "wof:name":"J.c. Vosselaar",
    "wof:placetype":"venue"
},
  "geometry": {"coordinates":[5.0470237732,51.2828063965],"type":"Point"}
}