{
  "type": "Feature",
  "properties": {
    "addr:full":"Avenue Chazal 33 Bruxelles (schaerbeek) Bruxelles-Capitale 1030",
    "addr:housenumber":"33",
    "addr:postcode":"1030",
    "addr:street":"Avenue Chazal",
    "iso:country":"BE",
    "sg:address":"Avenue Chazal 33",
    "sg:city":"Bruxelles (schaerbeek)",
    "sg:classifiers":[
        {
            "category":"Bakery",
            "type":"Food & Drink"
        }
    ],
    "sg:phone":"+32 2 734 74 11",
    "sg:postcode":"1030",
    "sg:province":"Bruxelles-Capitale",
    "sg:tags":[
        "confectioner",
        "baker"
    ],
    "wof:name":"Adja Sprl",
    "wof:placetype":"venue"
},
  "geometry": {"coordinates":[4.3890728951,50.8544654846],"type":"Point"}
}