{
  "type": "Feature",
  "properties": {
    "iso:country":"BE",
    "sg:address":"Rue Belliard 20",
    "sg:city":"Bruxelles (etterbeek)",
    "sg:classifiers":[
        {
            "category":"Organizations",
            "subcategory":"Professional Association",
            "type":"Services"
        }
    ],
    "sg:phone":"+32 2 512 36 38",
    "sg:postcode":"1040",
    "sg:province":"Bruxelles-Capitale",
    "sg:tags":[
        "trade-union",
        "federation"
    ],
    "wof:name":"Febelgra",
    "wof:placetype":"venue"
},
  "geometry": {"coordinates":[4.3696541786,50.8423881531],"type":"Point"}
}