{
  "type": "Feature",
  "properties": {
    "iso:country":"BE",
    "sg:address":"Rue Lug\u00e9a 45",
    "sg:city":"Ans (alleur)",
    "sg:classifiers":[
        {
            "category":"Building & Trades",
            "subcategory":"Equipment Rental",
            "type":"Services"
        }
    ],
    "sg:phone":"+32 4 246 37 07",
    "sg:postcode":"4432",
    "sg:province":"Li\u00e8ge",
    "sg:tags":[
        "crane",
        "-"
    ],
    "wof:name":"Germay J Sa",
    "wof:placetype":"venue"
},
  "geometry": {"coordinates":[5.5189499855,50.6743583679],"type":"Point"}
}