{
  "type": "Feature",
  "properties": {
    "addr:full":"Rue Max Fassiaux 11 Soignies Hainaut 7062",
    "addr:housenumber":"11",
    "addr:postcode":"7062",
    "addr:street":"Rue Max Fassiaux",
    "iso:country":"BE",
    "sg:address":"Rue Max Fassiaux 11",
    "sg:city":"Soignies",
    "sg:orig_category":"Pharmaciens",
    "sg:phone":"+32 67 33 23 17",
    "sg:postcode":"7062",
    "sg:province":"Hainaut",
    "wof:name":"Pharmacie Payen",
    "wof:placetype":"venue"
},
  "geometry": {"coordinates":[4.0996851921,50.5541000366],"type":"Point"}
}