{
  "type": "Feature",
  "properties": {
    "iso:country":"BE",
    "sg:address":"Bisdomstraat 19",
    "sg:city":"Sint-laureins (sint-jan-in-eremo)",
    "sg:classifiers":[
        {
            "category":"Government",
            "subcategory":"Fire Station",
            "type":"Public Place"
        }
    ],
    "sg:phone":"+32 9 379 91 25",
    "sg:postcode":"9982",
    "sg:province":"Oost-Vlaanderen",
    "sg:tags":[
        "extinguisher"
    ],
    "wof:name":"Euroflam",
    "wof:placetype":"venue"
},
  "geometry": {"coordinates":[3.5972669125,51.2465705872],"type":"Point"}
}