{
  "type": "Feature",
  "properties": {
    "iso:country":"BE",
    "sg:address":"Rue Des P\u00eacheries 62",
    "sg:city":"Bruxelles (auderghem)",
    "sg:orig_category":"Non-Classified Establishments",
    "sg:phone":"+32 2 672 66 69",
    "sg:postcode":"1160",
    "sg:province":"Bruxelles-Capitale",
    "wof:name":"Travimpec Sprl",
    "wof:placetype":"venue"
},
  "geometry": {"coordinates":[4.4094700813,50.8125114441],"type":"Point"}
}