{
  "type": "Feature",
  "properties": {
    "addr:full":"Rue Des Genets 20 Waimes/waimes Li\u00e8ge 4950",
    "addr:housenumber":"20",
    "addr:postcode":"4950",
    "addr:street":"Rue Des Genets",
    "iso:country":"BE",
    "sg:address":"Rue Des Genets 20",
    "sg:city":"Waimes/waimes",
    "sg:orig_category":"Artsen and specialisten",
    "sg:phone":"+32 80 44 57 44",
    "sg:postcode":"4950",
    "sg:province":"Li\u00e8ge",
    "wof:name":"P. Crutzen",
    "wof:placetype":"venue"
},
  "geometry": {"coordinates":[6.1406908035,50.4036178589],"type":"Point"}
}