{
  "type": "Feature",
  "properties": {
    "iso:country":"BE",
    "sg:address":"Verwilghensingel 100",
    "sg:city":"Hasselt",
    "sg:classifiers":[
        {
            "category":"Banks & Credit Unions",
            "subcategory":"Bank",
            "type":"Services"
        }
    ],
    "sg:phone":"+32 11 24 04 11",
    "sg:postcode":"3500",
    "sg:province":"Limburg",
    "wof:name":"Hasselt Regional Group",
    "wof:placetype":"venue"
},
  "geometry": {"coordinates":[5.3598041534,50.9279327393],"type":"Point"}
}