{
  "type": "Feature",
  "properties": {
    "addr:full":"Zijdelingsestraat 28 Box 2 Tienen Vlaams-Brabant 3300",
    "addr:housenumber":"28;2",
    "addr:postcode":"3300",
    "addr:street":"Zijdelingsestraat;Box",
    "iso:country":"BE",
    "sg:address":"Zijdelingsestraat 28 Box 2",
    "sg:city":"Tienen",
    "sg:classifiers":[
        {
            "category":"Food & Beverages",
            "subcategory":"Liquor & Beverages",
            "type":"Retail Goods"
        }
    ],
    "sg:phone":"+32 16 82 41 51",
    "sg:postcode":"3300",
    "sg:province":"Vlaams-Brabant",
    "sg:tags":[
        "-",
        "spirit",
        "wine"
    ],
    "wof:name":"Coenen Wijnen",
    "wof:placetype":"venue"
},
  "geometry": {"coordinates":[4.9235811234,50.8105506897],"type":"Point"}
}