{
  "type": "Feature",
  "properties": {
    "addr:full":"Wijgmaalsesteenweg 115 Herent Vlaams-Brabant 3020",
    "addr:housenumber":"115",
    "addr:postcode":"3020",
    "addr:street":"Wijgmaalsesteenweg",
    "iso:country":"BE",
    "sg:address":"Wijgmaalsesteenweg 115",
    "sg:city":"Herent",
    "sg:classifiers":[
        {
            "category":"Arena",
            "subcategory":"Sports Club",
            "type":"Entertainment"
        }
    ],
    "sg:phone":"+32 16 23 06 37",
    "sg:postcode":"3020",
    "sg:province":"Vlaams-Brabant",
    "sg:tags":[
        "de"
    ],
    "wof:name":"Kessinton Bc Fv",
    "wof:placetype":"venue"
},
  "geometry": {"coordinates":[4.6819400787,50.9140357971],"type":"Point"}
}