{
  "type": "Feature",
  "properties": {
    "addr:full":"Geraardsbergsestraat 169 Aalst Oost-Vlaanderen 9300",
    "addr:housenumber":"169",
    "addr:postcode":"9300",
    "addr:street":"Geraardsbergsestraat",
    "iso:country":"BE",
    "sg:address":"Geraardsbergsestraat 169",
    "sg:city":"Aalst",
    "sg:classifiers":[
        {
            "category":"Insurance",
            "subcategory":"Life Insurance",
            "type":"Services"
        }
    ],
    "sg:phone":"+32 53 78 99 69",
    "sg:postcode":"9300",
    "sg:province":"Oost-Vlaanderen",
    "sg:tags":[
        "assurance"
    ],
    "wof:name":"Zakenkantoor De Windt R.",
    "wof:placetype":"venue"
},
  "geometry": {"coordinates":[4.0352230072,50.9292106628],"type":"Point"}
}