{
  "type": "Feature",
  "properties": {
    "iso:country":"BE",
    "sg:address":"Patrijspark 49",
    "sg:city":"Deinze",
    "sg:orig_category":"Boekhouders",
    "sg:phone":"+32 9 386 65 86",
    "sg:postcode":"9800",
    "sg:province":"Oost-Vlaanderen",
    "wof:name":"Francis De Groeve",
    "wof:placetype":"venue"
},
  "geometry": {"coordinates":[3.530174017,50.9863166809],"type":"Point"}
}