{
  "type": "Feature",
  "properties": {
    "iso:country":"BE",
    "sg:address":"Zuidmoerstraat 158",
    "sg:city":"Eeklo",
    "sg:orig_category":"Instellingen voor probleemkinderen Kindertehuizen",
    "sg:phone":"+32 9 377 48 49",
    "sg:postcode":"9900",
    "sg:province":"Oost-Vlaanderen",
    "wof:name":"De Waai",
    "wof:placetype":"venue"
},
  "geometry": {"coordinates":[3.5646810532,51.1820907593],"type":"Point"}
}