{
  "type": "Feature",
  "properties": {
    "iso:country":"BE",
    "sg:address":"Torhoutsestraat 141",
    "sg:city":"Oostkamp (ruddervoorde)",
    "sg:classifiers":[
        {
            "category":"Health Services",
            "subcategory":"Nursing And Care Facility",
            "type":"Services"
        }
    ],
    "sg:phone":"+32 50 28 07 53",
    "sg:postcode":"8020",
    "sg:province":"West-Vlaanderen",
    "sg:tags":[
        "home"
    ],
    "wof:name":"Hostijn B",
    "wof:placetype":"venue"
},
  "geometry": {"coordinates":[3.1979289055,51.0873069763],"type":"Point"}
}