{
  "type": "Feature",
  "properties": {
    "iso:country":"BE",
    "sg:address":"Heilig Hartlaan 29",
    "sg:city":"Tessenderlo",
    "sg:orig_category":"Woningbouw",
    "sg:phone":"+32 13 66 12 16",
    "sg:postcode":"3980",
    "sg:province":"Limburg",
    "wof:name":"Bogaerts R",
    "wof:placetype":"venue"
},
  "geometry": {"coordinates":[5.0927457809,51.0556526184],"type":"Point"}
}