{
  "type": "Feature",
  "properties": {
    "addr:full":"Rue Des Bouchers 25 Brussel/bruxelles Bruxelles-Capitale 1000",
    "addr:housenumber":"25",
    "addr:postcode":"1000",
    "addr:street":"Rue Des Bouchers;/",
    "iso:country":"BE",
    "sg:address":"Rue Des Bouchers 25",
    "sg:city":"Brussel/bruxelles",
    "sg:classifiers":[
        {
            "category":"Fast Food",
            "type":"Food & Drink"
        }
    ],
    "sg:phone":"+32 2 511 25 08",
    "sg:postcode":"1000",
    "sg:province":"Bruxelles-Capitale",
    "sg:tags":[
        "\u00c0",
        "restaurants",
        "emporter",
        "restaurant"
    ],
    "wof:name":"Restaurant Shangai",
    "wof:placetype":"venue"
},
  "geometry": {"coordinates":[4.3542399406,50.84790802],"type":"Point"}
}