{
  "type": "Feature",
  "properties": {
    "iso:country":"BE",
    "sg:address":"Chauss\u00e9e De Renaix 44",
    "sg:city":"Frasnes-lez-anvaing (anvaing)",
    "sg:classifiers":[
        {
            "category":"Food & Beverages",
            "subcategory":"Meat & Fish",
            "type":"Retail Goods"
        }
    ],
    "sg:phone":"+32 69 86 80 47",
    "sg:postcode":"7910",
    "sg:province":"Hainaut",
    "sg:tags":[
        "-",
        "livestock"
    ],
    "wof:name":"Jonniaux Scris",
    "wof:placetype":"venue"
},
  "geometry": {"coordinates":[3.5806241035,50.6920547485],"type":"Point"}
}