{
  "type": "Feature",
  "properties": {
    "iso:country":"BE",
    "sg:address":"Stapelstraat 57-61",
    "sg:city":"Sint-truiden (groot)",
    "sg:orig_category":"Peinture. Rev\u00eatements pour sols and murs. Rev\u00eatements de sols and murs. Drogueries",
    "sg:phone":"+32 11 68 21 18",
    "sg:postcode":"3800",
    "sg:province":"Limburg",
    "wof:name":"Schalenbourg",
    "wof:placetype":"venue"
},
  "geometry": {"coordinates":[5.1822748184,50.8152923584],"type":"Point"}
}