{
  "type": "Feature",
  "properties": {
    "iso:country":"BE",
    "sg:address":"Heulestraat 160",
    "sg:city":"Gullegem",
    "sg:classifiers":[
        {
            "category":"Wholesale",
            "subcategory":"Books, Periodicals, & Newspapers",
            "type":"Manufacturing & Wholesale Goods"
        }
    ],
    "sg:phone":"+32 56 37 19 27",
    "sg:postcode":"8560",
    "sg:province":"West-Vlaanderen",
    "sg:tags":[
        "directory",
        "publisher"
    ],
    "wof:name":"Induplan B.v.b.a.",
    "wof:placetype":"venue"
},
  "geometry": {"coordinates":[3.2195990086,50.8431510925],"type":"Point"}
}