{
  "type": "Feature",
  "properties": {
    "iso:country":"BE",
    "sg:address":"Steenweg Asse 139",
    "sg:city":"Herne (herfelingen)",
    "sg:classifiers":[
        {
            "category":"Fast Food",
            "type":"Food & Drink"
        }
    ],
    "sg:phone":"+32 2 396 18 84",
    "sg:postcode":"1540",
    "sg:province":"Vlaams-Brabant",
    "sg:tags":[
        "fried",
        "stand",
        "potato"
    ],
    "wof:name":"Pony-farm",
    "wof:placetype":"venue"
},
  "geometry": {"coordinates":[4.0829539299,50.7258987427],"type":"Point"}
}