{
  "type": "Feature",
  "properties": {
    "iso:country":"BE",
    "sg:address":"Rue Franche Chambre 15",
    "sg:city":"Chatelet",
    "sg:orig_category":"Pain, p\u00e2tisseries and confiseries",
    "sg:phone":"+32 71 38 25 23",
    "sg:postcode":"6200",
    "sg:province":"Hainaut",
    "wof:name":"Chantal Jeanmart",
    "wof:placetype":"venue"
},
  "geometry": {"coordinates":[4.5195069313,50.4057884216],"type":"Point"}
}