{
  "type": "Feature",
  "properties": {
    "addr:full":"Staatsbaan 303 Bekkevoort Vlaams-Brabant 3460",
    "addr:housenumber":"303",
    "addr:postcode":"3460",
    "addr:street":"Staatsbaan",
    "iso:country":"BE",
    "sg:address":"Staatsbaan 303",
    "sg:city":"Bekkevoort",
    "sg:classifiers":[
        {
            "category":"Health Services",
            "subcategory":"Health Practitioner",
            "type":"Services"
        }
    ],
    "sg:phone":"+32 16 63 19 31",
    "sg:postcode":"3460",
    "sg:province":"Vlaams-Brabant",
    "sg:tags":[
        "physiotherapist"
    ],
    "wof:name":"Debus J",
    "wof:placetype":"venue"
},
  "geometry": {"coordinates":[4.9673299789,50.9426612854],"type":"Point"}
}