{
  "type": "Feature",
  "properties": {
    "addr:full":"Avenue De Woluw\u00c9-saint-lambert 38-40 Brussel/bruxelles Bruxelles-Capitale 1200",
    "addr:postcode":"38-40;/ bruxelles;1200",
    "addr:street":"Avenue De Woluwe\u0301-Saint-Lambert",
    "iso:country":"BE",
    "sg:address":"Avenue De Woluw\u00c9-saint-lambert 38-40",
    "sg:city":"Brussel/bruxelles",
    "sg:classifiers":[
        {
            "category":"Restaurant",
            "type":"Food & Drink"
        }
    ],
    "sg:phone":"+32 2 734 72 58",
    "sg:postcode":"1200",
    "sg:province":"Bruxelles-Capitale",
    "wof:name":"La Folie Du Chat",
    "wof:placetype":"venue"
},
  "geometry": {"coordinates":[4.4100990295,50.8400001526],"type":"Point"}
}