{
  "type": "Feature",
  "properties": {
    "addr:full":"Rue Joseph Wauters 5 Engis Li\u00e8ge 4480",
    "addr:housenumber":"5",
    "addr:postcode":"4480",
    "addr:street":"Rue Joseph Wauters",
    "iso:country":"BE",
    "sg:address":"Rue Joseph Wauters 5",
    "sg:city":"Engis",
    "sg:classifiers":[
        {
            "category":"Health Services",
            "subcategory":"Health Practitioner",
            "type":"Services"
        }
    ],
    "sg:phone":"+32 4 275 01 44",
    "sg:postcode":"4480",
    "sg:province":"Li\u00e8ge",
    "sg:tags":[
        "physiotherapist"
    ],
    "wof:name":"Darte Denis",
    "wof:placetype":"venue"
},
  "geometry": {"coordinates":[5.4042768478,50.5809631348],"type":"Point"}
}