{
  "type": "Feature",
  "properties": {
    "addr:full":"Lge Ypermanstr 33 Antwerpen Antwerpen 2060",
    "addr:housenumber":"33",
    "addr:postcode":"2060",
    "addr:street":"Lge",
    "iso:country":"BE",
    "sg:address":"Lge Ypermanstr 33",
    "sg:city":"Antwerpen",
    "sg:orig_category":"V\u00e9hicules automobiles",
    "sg:phone":"+32 3 235 52 09",
    "sg:postcode":"2060",
    "sg:province":"Antwerpen",
    "wof:name":"American Cars Enthusiasts",
    "wof:placetype":"venue"
},
  "geometry": {"coordinates":[4.4324140549,51.2231407166],"type":"Point"}
}