{
  "type": "Feature",
  "properties": {
    "addr:full":"Rue De La Cr\u00cate 2 Chapelle-lez-herlaimont Hainaut 7160",
    "addr:housenumber":"2",
    "addr:postcode":"7160",
    "addr:street":"Rue De La Cre\u0302Te",
    "iso:country":"BE",
    "sg:address":"Rue De La Cr\u00cate 2",
    "sg:city":"Chapelle-lez-herlaimont",
    "sg:orig_category":"Meubelzaken, woning- and keukeninrichting",
    "sg:phone":"+32 64 44 22 34",
    "sg:postcode":"7160",
    "sg:province":"Hainaut",
    "wof:name":"Eric Bricoult",
    "wof:placetype":"venue"
},
  "geometry": {"coordinates":[4.2758860588,50.4758071899],"type":"Point"}
}