{
  "type": "Feature",
  "properties": {
    "iso:country":"BE",
    "sg:address":"Paradijsstraat 14",
    "sg:city":"Alken",
    "sg:orig_category":"Eleveurs and marchands de porcs",
    "sg:phone":"+32 11 31 46 14",
    "sg:postcode":"3570",
    "sg:province":"Limburg",
    "wof:name":"Roger Raymaekers",
    "wof:placetype":"venue"
},
  "geometry": {"coordinates":[5.3032689095,50.8704376221],"type":"Point"}
}