{
  "type": "Feature",
  "properties": {
    "addr:full":"Rue De La Ch\u00e2tellenie 13 Comines-warneton (warneton) Hainaut 7784",
    "addr:housenumber":"13",
    "addr:postcode":"7784",
    "addr:street":"Rue De La Cha\u0302Tellenie",
    "iso:country":"BE",
    "sg:address":"Rue De La Ch\u00e2tellenie 13",
    "sg:city":"Comines-warneton (warneton)",
    "sg:classifiers":[
        {
            "category":"Health Services",
            "subcategory":"Nursing And Care Facility",
            "type":"Services"
        }
    ],
    "sg:phone":"+32 56 55 60 63",
    "sg:postcode":"7784",
    "sg:province":"Hainaut",
    "sg:tags":[
        "home",
        "rest"
    ],
    "wof:name":"La Chatellenie",
    "wof:placetype":"venue"
},
  "geometry": {"coordinates":[2.9510629177,50.7534141541],"type":"Point"}
}