{
  "type": "Feature",
  "properties": {
    "addr:full":"Breydelstraat 1 Lo-reninge (lo) West-Vlaanderen 8647",
    "addr:housenumber":"1",
    "addr:postcode":"8647",
    "addr:street":"Breydelstraat;Lo-Reninge Lo West-Vlaanderen",
    "iso:country":"BE",
    "sg:address":"Breydelstraat 1",
    "sg:city":"Lo-reninge (lo)",
    "sg:classifiers":[
        {
            "category":"Shopping",
            "subcategory":"Bicycles & Sporting Goods",
            "type":"Retail Goods"
        }
    ],
    "sg:phone":"+32 58 28 87 83",
    "sg:postcode":"8647",
    "sg:province":"West-Vlaanderen",
    "sg:tags":[
        "-"
    ],
    "wof:name":"Vanroose D",
    "wof:placetype":"venue"
},
  "geometry": {"coordinates":[2.7486770153,50.9806289673],"type":"Point"}
}