{
  "type": "Feature",
  "properties": {
    "iso:country":"BE",
    "sg:address":"Ankerstraat 123",
    "sg:city":"Sint-niklaas",
    "sg:orig_category":"Non-Classified Establishments",
    "sg:phone":"+32 3 776 78 76",
    "sg:postcode":"9100",
    "sg:province":"Oost-Vlaanderen",
    "wof:name":"Angelique Bruidsmode",
    "wof:placetype":"venue"
},
  "geometry": {"coordinates":[4.1481661797,51.1676483154],"type":"Point"}
}