{
  "type": "Feature",
  "properties": {
    "addr:full":"Hoogstraat 99 Sint-pieters-leeuw Vlaams-Brabant 1600",
    "addr:housenumber":"99",
    "addr:postcode":"1600",
    "addr:street":"Hoogstraat",
    "iso:country":"BE",
    "sg:address":"Hoogstraat 99",
    "sg:city":"Sint-pieters-leeuw",
    "sg:classifiers":[
        {
            "category":"Food & Beverages",
            "subcategory":"Fruits & Vegetables",
            "type":"Retail Goods"
        }
    ],
    "sg:phone":"+32 2 331 11 22",
    "sg:postcode":"1600",
    "sg:province":"Vlaams-Brabant",
    "sg:tags":[
        "oil",
        "-",
        "fat"
    ],
    "wof:name":"Hermes Services",
    "wof:placetype":"venue"
},
  "geometry": {"coordinates":[4.2304201126,50.7842750549],"type":"Point"}
}