{
  "type": "Feature",
  "properties": {
    "iso:country":"BE",
    "sg:address":"Neerstraat 167",
    "sg:city":"Tessenderlo",
    "sg:orig_category":"Mat\u00e9riel m\u00e9dical and orthop\u00e9dique and proth\u00e8ses Fab",
    "sg:phone":"+32 13 66 75 37",
    "sg:postcode":"3980",
    "sg:province":"Limburg",
    "wof:name":"Dental Team",
    "wof:placetype":"venue"
},
  "geometry": {"coordinates":[5.0905580521,51.0795669556],"type":"Point"}
}