{
  "type": "Feature",
  "properties": {
    "addr:full":"Burg. Vandenbogaerdelaan 35bb Izegem West-Vlaanderen 8870",
    "addr:housenumber":"35bb",
    "addr:postcode":"8870",
    "addr:street":"Burg. Vandenbogaerdelaan",
    "iso:country":"BE",
    "sg:address":"Burg. Vandenbogaerdelaan 35bb",
    "sg:city":"Izegem",
    "sg:orig_category":"Apotheken",
    "sg:phone":"+32 51 30 06 20",
    "sg:postcode":"8870",
    "sg:province":"West-Vlaanderen",
    "wof:name":"Lena De Laere",
    "wof:placetype":"venue"
},
  "geometry": {"coordinates":[3.2115929127,50.9148368835],"type":"Point"}
}