{
  "type": "Feature",
  "properties": {
    "addr:full":"Rue Pr\u00c9 Des Haz 1 Sambreville Namur 5060",
    "addr:housenumber":"1",
    "addr:postcode":"5060",
    "addr:street":"Rue Pre\u0301 Des Haz",
    "iso:country":"BE",
    "sg:address":"Rue Pr\u00c9 Des Haz 1",
    "sg:city":"Sambreville",
    "sg:orig_category":"Boucheries",
    "sg:phone":"+32 71 77 87 95",
    "sg:postcode":"5060",
    "sg:province":"Namur",
    "wof:name":"Debroux Christian",
    "wof:placetype":"venue"
},
  "geometry": {"coordinates":[4.6285200119,50.4448738098],"type":"Point"}
}