{
  "type": "Feature",
  "properties": {
    "iso:country":"BE",
    "sg:address":"Rue Du Vent Val 1e",
    "sg:city":"Le Roeulx (ville-sur-haine)",
    "sg:classifiers":[
        {
            "category":"Health Services",
            "subcategory":"Nursing And Care Facility",
            "type":"Services"
        }
    ],
    "sg:phone":"+32 64 67 87 86",
    "sg:postcode":"7070",
    "sg:province":"Hainaut",
    "sg:tags":[
        "home"
    ],
    "wof:name":"Bassette C\u00e9cile",
    "wof:placetype":"venue"
},
  "geometry": {"coordinates":[4.0513000488,50.4939613342],"type":"Point"}
}