{
  "type": "Feature",
  "properties": {
    "addr:full":"Rue Du Pont De Sambre 12 Charleroi Hainaut 6000",
    "addr:housenumber":"12",
    "addr:postcode":"6000",
    "addr:street":"Rue Du Pont De Sambre;Hainaut",
    "iso:country":"BE",
    "sg:address":"Rue Du Pont De Sambre 12",
    "sg:city":"Charleroi",
    "sg:orig_category":"Pain, p\u00e2tisseries and confiseries",
    "sg:phone":"+32 71 32 18 46",
    "sg:postcode":"6000",
    "sg:province":"Hainaut",
    "wof:name":"Neuhaus",
    "wof:placetype":"venue"
},
  "geometry": {"coordinates":[4.4425678253,50.4086494446],"type":"Point"}
}