{
  "type": "Feature",
  "properties": {
    "addr:full":"Chauss\u00e9e De Charleroi 156 Bruxelles (saint-gilles) Bruxelles-Capitale 1060",
    "addr:housenumber":"156",
    "addr:postcode":"1060",
    "addr:street":"Chausse\u0301E De Charleroi",
    "iso:country":"BE",
    "sg:address":"Chauss\u00e9e De Charleroi 156",
    "sg:city":"Bruxelles (saint-gilles)",
    "sg:classifiers":[
        {
            "category":"Personal",
            "subcategory":"Beauty Salon",
            "type":"Services"
        }
    ],
    "sg:phone":"+32 2 534 47 37",
    "sg:postcode":"1060",
    "sg:province":"Bruxelles-Capitale",
    "wof:name":"Pause Beaut\u00e9",
    "wof:placetype":"venue"
},
  "geometry": {"coordinates":[4.3550238609,50.8263587952],"type":"Point"}
}