{
  "type": "Feature",
  "properties": {
    "iso:country":"BE",
    "sg:address":"Rue Du Ch\u00c2teau 28",
    "sg:city":"Anderlues",
    "sg:orig_category":"Artsen and specialisten",
    "sg:phone":"+32 71 52 11 60",
    "sg:postcode":"6150",
    "sg:province":"Hainaut",
    "wof:name":"Martine Cordier",
    "wof:placetype":"venue"
},
  "geometry": {"coordinates":[4.2741551399,50.4032554626],"type":"Point"}
}