{
  "type": "Feature",
  "properties": {
    "iso:country":"BE",
    "sg:address":"Rue Marguerite D'york 8",
    "sg:city":"Binche",
    "sg:orig_category":"Avocats and conseillers juridiques",
    "sg:phone":"+32 64 33 57 85",
    "sg:postcode":"7130",
    "sg:province":"Hainaut",
    "wof:name":"D. Rubens",
    "wof:placetype":"venue"
},
  "geometry": {"coordinates":[4.1786799431,50.4146881104],"type":"Point"}
}