{
  "type": "Feature",
  "properties": {
    "iso:country":"BE",
    "sg:address":"Dokter Dekemelelaan 31",
    "sg:city":"Ieper",
    "sg:classifiers":[
        {
            "category":"Cafe",
            "type":"Food & Drink"
        }
    ],
    "sg:phone":"+32 57 42 25 11",
    "sg:postcode":"8904",
    "sg:province":"West-Vlaanderen",
    "sg:tags":[
        "caf\u00e9s"
    ],
    "wof:name":"Caf\u00c9 De Zee",
    "wof:placetype":"venue"
},
  "geometry": {"coordinates":[2.86165905,50.8959770203],"type":"Point"}
}