{
  "type": "Feature",
  "properties": {
    "addr:full":"Rue De La Station 90 Soignies Hainaut 7060",
    "addr:housenumber":"90",
    "addr:postcode":"7060",
    "addr:street":"Rue De La Station",
    "iso:country":"BE",
    "sg:address":"Rue De La Station 90",
    "sg:city":"Soignies",
    "sg:classifiers":[
        {
            "category":"Bars & Pubs",
            "type":"Food & Drink"
        }
    ],
    "sg:phone":"+32 67 33 00 07",
    "sg:postcode":"7060",
    "sg:province":"Hainaut",
    "wof:name":"Debarcadere (le)",
    "wof:placetype":"venue"
},
  "geometry": {"coordinates":[4.0688037872,50.5742340088],"type":"Point"}
}