{
  "type": "Feature",
  "properties": {
    "iso:country":"BE",
    "sg:address":"Dorpsstraat 50b3",
    "sg:city":"Hoeselt",
    "sg:orig_category":"Advocaten and juridische adviseurs",
    "sg:phone":"+32 89 51 14 10",
    "sg:postcode":"3730",
    "sg:province":"Limburg",
    "wof:name":"H. Verjans",
    "wof:placetype":"venue"
},
  "geometry": {"coordinates":[5.4833550453,50.8498001099],"type":"Point"}
}