{
  "type": "Feature",
  "properties": {
    "addr:full":"Emmanuellaan 7 Machelen Vlaams-Brabant 1830",
    "addr:housenumber":"7",
    "addr:postcode":"1830",
    "addr:street":"Emmanuellaan",
    "iso:country":"BE",
    "sg:address":"Emmanuellaan 7",
    "sg:city":"Machelen",
    "sg:classifiers":[
        {
            "category":"Utilities",
            "subcategory":"Refuse",
            "type":"Services"
        }
    ],
    "sg:phone":"+32 2 253 69 10",
    "sg:postcode":"1830",
    "sg:province":"Vlaams-Brabant",
    "sg:tags":[
        "removal"
    ],
    "wof:name":"Compas International Movers",
    "wof:placetype":"venue"
},
  "geometry": {"coordinates":[4.4187951088,50.9081611633],"type":"Point"}
}