{
  "type": "Feature",
  "properties": {
    "iso:country":"BE",
    "sg:address":"Grote Steenweg 240",
    "sg:city":"Linter (drieslinter)",
    "sg:classifiers":[
        {
            "category":"Bakery",
            "type":"Food & Drink"
        }
    ],
    "sg:phone":"+32 11 78 05 67",
    "sg:postcode":"3350",
    "sg:province":"Vlaams-Brabant",
    "sg:tags":[
        "confectioner",
        "baker"
    ],
    "wof:name":"Holiviers A",
    "wof:placetype":"venue"
},
  "geometry": {"coordinates":[5.0733499527,50.8045387268],"type":"Point"}
}