{
  "type": "Feature",
  "properties": {
    "addr:full":"Rue De La Fronti\u00e8re 128 Dour (blaugies) Hainaut 7370",
    "addr:housenumber":"128",
    "addr:postcode":"7370",
    "addr:street":"Rue De La Frontie\u0300Re;Blaugies Hainaut",
    "iso:country":"BE",
    "sg:address":"Rue De La Fronti\u00e8re 128",
    "sg:city":"Dour (blaugies)",
    "sg:classifiers":[
        {
            "category":"Health Services",
            "subcategory":"Nursing And Care Facility",
            "type":"Services"
        }
    ],
    "sg:phone":"+32 65 65 99 90",
    "sg:postcode":"7370",
    "sg:province":"Hainaut",
    "sg:tags":[
        "home"
    ],
    "wof:name":"Harmegnies C",
    "wof:placetype":"venue"
},
  "geometry": {"coordinates":[3.8125619888,50.3710441589],"type":"Point"}
}