{
  "type": "Feature",
  "properties": {
    "addr:full":"Kapelstr 59 Duffel Antwerpen 2570",
    "addr:housenumber":"59",
    "addr:postcode":"2570",
    "addr:street":"Kapelstr",
    "iso:country":"BE",
    "sg:address":"Kapelstr 59",
    "sg:city":"Duffel",
    "sg:classifiers":[
        {
            "category":"Professional",
            "subcategory":"Advertising",
            "type":"Services"
        }
    ],
    "sg:phone":"+32 15 31 49 35",
    "sg:postcode":"2570",
    "sg:province":"Antwerpen",
    "sg:tags":[
        "information",
        "medium",
        "communication"
    ],
    "wof:name":"Duffel Coat Productions Nv",
    "wof:placetype":"venue"
},
  "geometry": {"coordinates":[4.5114169121,51.093421936],"type":"Point"}
}