{
  "type": "Feature",
  "properties": {
    "iso:country":"BE",
    "sg:address":"Gentsebaan 96",
    "sg:city":"Sint-niklaas",
    "sg:orig_category":"Dancings and bo\u00eetes de nuit",
    "sg:phone":"+32 3 776 28 83",
    "sg:postcode":"9100",
    "sg:province":"Oost-Vlaanderen",
    "wof:name":"The New Ritz",
    "wof:placetype":"venue"
},
  "geometry": {"coordinates":[4.124710083,51.1488494873],"type":"Point"}
}