{
  "type": "Feature",
  "properties": {
    "addr:full":"Eekhoornlaan 11 Tremelo (baal) Vlaams-Brabant 3128",
    "addr:housenumber":"11",
    "addr:postcode":"3128",
    "addr:street":"Eekhoornlaan",
    "iso:country":"BE",
    "sg:address":"Eekhoornlaan 11",
    "sg:city":"Tremelo (baal)",
    "sg:classifiers":[
        {
            "category":"Professional",
            "subcategory":"Management & Consulting",
            "type":"Services"
        }
    ],
    "sg:phone":"+32 16 53 92 67",
    "sg:postcode":"3128",
    "sg:province":"Vlaams-Brabant",
    "sg:tags":[
        "consultant"
    ],
    "wof:name":"Brams D Bvba",
    "wof:placetype":"venue"
},
  "geometry": {"coordinates":[4.7364578247,51.000164032],"type":"Point"}
}