{
  "type": "Feature",
  "properties": {
    "iso:country":"BE",
    "sg:address":"Steenweg 226",
    "sg:city":"Lierde",
    "sg:orig_category":"Installatie van houten of kunststof schrijnwerk",
    "sg:phone":"+32 55 42 23 76",
    "sg:postcode":"9572",
    "sg:province":"Oost-Vlaanderen",
    "wof:name":"Fa. Deluca",
    "wof:placetype":"venue"
},
  "geometry": {"coordinates":[3.798470974,50.8110389709],"type":"Point"}
}