{
  "type": "Feature",
  "properties": {
    "iso:country":"BE",
    "sg:address":"Zoning Industriel Ivoz-ramet 18",
    "sg:city":"Flemalle",
    "sg:orig_category":"Metaalbehandeling and -bekleding",
    "sg:phone":"+32 4 337 86 16",
    "sg:postcode":"4400",
    "sg:province":"Li\u00e8ge",
    "wof:name":"Ateliers No\u00cbl-seret",
    "wof:placetype":"venue"
},
  "geometry": {"coordinates":[5.4623541832,50.5880622864],"type":"Point"}
}