{
  "type": "Feature",
  "properties": {
    "addr:full":"Rue De Bruxelles 35bb Verviers Li\u00e8ge 4800",
    "addr:housenumber":"35bb",
    "addr:postcode":"4800",
    "addr:street":"Rue De Bruxelles",
    "iso:country":"BE",
    "sg:address":"Rue De Bruxelles 35bb",
    "sg:city":"Verviers",
    "sg:orig_category":"Agences d\u00b4interim and personnel temporaire",
    "sg:phone":"+32 87 22 44 86",
    "sg:postcode":"4800",
    "sg:province":"Li\u00e8ge",
    "wof:name":"Mti Interim",
    "wof:placetype":"venue"
},
  "geometry": {"coordinates":[5.8550338745,50.5872192383],"type":"Point"}
}