{
  "type": "Feature",
  "properties": {
    "addr:full":"Rue Duvivier 41 Morlanwelz (carni\u00e8res) Hainaut 7141",
    "addr:housenumber":"41",
    "addr:postcode":"7141",
    "addr:street":"Rue Duvivier",
    "iso:country":"BE",
    "sg:address":"Rue Duvivier 41",
    "sg:city":"Morlanwelz (carni\u00e8res)",
    "sg:classifiers":[
        {
            "category":"Bars & Pubs",
            "type":"Food & Drink"
        }
    ],
    "sg:phone":"+32 64 45 96 08",
    "sg:postcode":"7141",
    "sg:province":"Hainaut",
    "wof:name":"Sports (des)",
    "wof:placetype":"venue"
},
  "geometry": {"coordinates":[4.2577190399,50.4436607361],"type":"Point"}
}