{
  "type": "Feature",
  "properties": {
    "iso:country":"BE",
    "sg:address":"Lembekedorp 41",
    "sg:city":"Kaprijke",
    "sg:orig_category":"Dranken Gh",
    "sg:phone":"+32 9 377 19 07",
    "sg:postcode":"9971",
    "sg:province":"Oost-Vlaanderen",
    "wof:name":"Stockman",
    "wof:placetype":"venue"
},
  "geometry": {"coordinates":[3.632183075,51.1949272156],"type":"Point"}
}