{
  "type": "Feature",
  "properties": {
    "addr:full":"Rue D'en Haut 53 Couvin (gonrieux) Namur 5660",
    "addr:housenumber":"53",
    "addr:postcode":"5660",
    "addr:street":"Rue D'En Haut",
    "iso:country":"BE",
    "sg:address":"Rue D'en Haut 53",
    "sg:city":"Couvin (gonrieux)",
    "sg:classifiers":[
        {
            "category":"Professional",
            "subcategory":"Management & Consulting",
            "type":"Services"
        }
    ],
    "sg:phone":"+32 60 34 73 09",
    "sg:postcode":"5660",
    "sg:province":"Namur",
    "sg:tags":[
        "tax-consultants"
    ],
    "wof:name":"Bodart F",
    "wof:placetype":"venue"
},
  "geometry": {"coordinates":[4.4966697693,50.0532112122],"type":"Point"}
}