{
  "type": "Feature",
  "properties": {
    "iso:country":"BE",
    "sg:address":"Rue Des Fanfares 34",
    "sg:city":"Seraing",
    "sg:orig_category":"Artsen and specialisten",
    "sg:phone":"+32 4 233 90 89",
    "sg:postcode":"4101",
    "sg:province":"Li\u00e8ge",
    "wof:name":"Paul Biquet",
    "wof:placetype":"venue"
},
  "geometry": {"coordinates":[5.4979271889,50.6176872253],"type":"Point"}
}