{
  "type": "Feature",
  "properties": {
    "iso:country":"BE",
    "sg:address":"Gemeentestraat 6",
    "sg:city":"Turnhout",
    "sg:orig_category":"Fotografen and fotostudio's",
    "sg:phone":"+32 14 41 07 71",
    "sg:postcode":"2300",
    "sg:province":"Antwerpen",
    "wof:name":"Studio Koop",
    "wof:placetype":"venue"
},
  "geometry": {"coordinates":[4.9425902367,51.3233833313],"type":"Point"}
}