{
  "type": "Feature",
  "properties": {
    "iso:country":"BE",
    "sg:address":"Rue Jean-laurent 50",
    "sg:city":"Musson",
    "sg:orig_category":"Brood, gebak and snoepgoed",
    "sg:phone":"+32 63 67 78 05",
    "sg:postcode":"6750",
    "sg:province":"Luxembourg",
    "wof:name":"Boulangerie Temps Jadis",
    "wof:placetype":"venue"
},
  "geometry": {"coordinates":[5.698802948,49.5579681396],"type":"Point"}
}