{
  "type": "Feature",
  "properties": {
    "iso:country":"BE",
    "sg:address":"Rozendaalweg 21",
    "sg:city":"Ichtegem",
    "sg:classifiers":[
        {
            "category":"Farming",
            "subcategory":"Farm & Veterinary Services",
            "type":"Manufacturing & Wholesale Goods"
        }
    ],
    "sg:phone":"+32 51 58 89 29",
    "sg:postcode":"8480",
    "sg:province":"West-Vlaanderen",
    "sg:tags":[
        "agricultural",
        "contractor"
    ],
    "wof:name":"Riviere G",
    "wof:placetype":"venue"
},
  "geometry": {"coordinates":[2.9996039867,51.0996398926],"type":"Point"}
}