{
  "type": "Feature",
  "properties": {
    "addr:full":"Simonsstraat 38 Antwerpen Antwerpen 2018",
    "addr:housenumber":"38",
    "addr:postcode":"2018",
    "addr:street":"Simonsstraat",
    "iso:country":"BE",
    "sg:address":"Simonsstraat 38",
    "sg:city":"Antwerpen",
    "sg:classifiers":[
        {
            "category":"Shopping",
            "subcategory":"Jewelry",
            "type":"Retail Goods"
        }
    ],
    "sg:phone":"+32 3 232 09 16",
    "sg:postcode":"2018",
    "sg:province":"Antwerpen",
    "sg:tags":[
        "fab",
        "bijou"
    ],
    "wof:name":"Damen",
    "wof:placetype":"venue"
},
  "geometry": {"coordinates":[4.4212207794,51.2115211487],"type":"Point"}
}