{
  "type": "Feature",
  "properties": {
    "iso:country":"BE",
    "sg:address":"Gellenberg 123",
    "sg:city":"Lubbeek",
    "sg:orig_category":"Fleurs and plantes",
    "sg:phone":"+32 16 62 32 65",
    "sg:postcode":"3210",
    "sg:province":"Vlaams-Brabant",
    "wof:name":"Puur Bvba",
    "wof:placetype":"venue"
},
  "geometry": {"coordinates":[4.8308048248,50.8948822021],"type":"Point"}
}