{
  "type": "Feature",
  "properties": {
    "iso:country":"BE",
    "sg:address":"Rue Sur-les-sarts 2",
    "sg:city":"Sart-bernard",
    "sg:classifiers":[
        {
            "category":"Professional",
            "subcategory":"Art Services",
            "type":"Services"
        }
    ],
    "sg:phone":"+32 81 40 21 45",
    "sg:postcode":"5330",
    "sg:province":"Namur",
    "sg:tags":[
        "framing"
    ],
    "wof:name":"Arcadre S.a.",
    "wof:placetype":"venue"
},
  "geometry": {"coordinates":[4.9727058411,50.4152526855],"type":"Point"}
}