{
  "type": "Feature",
  "properties": {
    "addr:full":"Avenue Houzeau 10 Bruxelles (uccle) Bruxelles-Capitale 1180",
    "addr:housenumber":"10",
    "addr:postcode":"1180",
    "addr:street":"Avenue Houzeau",
    "iso:country":"BE",
    "sg:address":"Avenue Houzeau 10",
    "sg:city":"Bruxelles (uccle)",
    "sg:classifiers":[
        {
            "category":"Health Services",
            "subcategory":"Health Practitioner",
            "type":"Services"
        }
    ],
    "sg:phone":"+32 2 374 03 87",
    "sg:postcode":"1180",
    "sg:province":"Bruxelles-Capitale",
    "sg:tags":[
        "physiotherapist"
    ],
    "wof:name":"Bernimolin D (mme)",
    "wof:placetype":"venue"
},
  "geometry": {"coordinates":[4.358962059,50.8036193848],"type":"Point"}
}