{
  "type": "Feature",
  "properties": {
    "iso:country":"BE",
    "sg:address":"Vlasbloemstraat 4",
    "sg:city":"Ingelmunster",
    "sg:orig_category":"Non-Classified Establishments",
    "sg:phone":"+32 51 30 07 13",
    "sg:postcode":"8770",
    "sg:province":"West-Vlaanderen",
    "wof:name":"Declerq Biscuiterie Nv",
    "wof:placetype":"venue"
},
  "geometry": {"coordinates":[3.2780818939,50.9115486145],"type":"Point"}
}