{
  "type": "Feature",
  "properties": {
    "addr:full":"Motstraat 86 Alken Limburg 3570",
    "addr:housenumber":"86",
    "addr:postcode":"3570",
    "addr:street":"Motstraat",
    "iso:country":"BE",
    "sg:address":"Motstraat 86",
    "sg:city":"Alken",
    "sg:orig_category":"Producteurs de fruits",
    "sg:phone":"+32 11 31 55 44",
    "sg:postcode":"3570",
    "sg:province":"Limburg",
    "wof:name":"Camille Menten",
    "wof:placetype":"venue"
},
  "geometry": {"coordinates":[5.3089752197,50.8673248291],"type":"Point"}
}