{
  "type": "Feature",
  "properties": {
    "addr:full":"Rue De La Chauss\u00c9e 96 Quevy Hainaut 7040",
    "addr:housenumber":"96",
    "addr:postcode":"7040",
    "addr:street":"Rue De La Chausse\u0301E;Hainaut",
    "iso:country":"BE",
    "sg:address":"Rue De La Chauss\u00c9e 96",
    "sg:city":"Quevy",
    "sg:classifiers":[
        {
            "category":"Personal",
            "subcategory":"Beauty Salon",
            "type":"Services"
        }
    ],
    "sg:phone":"+32 65 56 75 61",
    "sg:postcode":"7040",
    "sg:province":"Hainaut",
    "sg:tags":[
        "de",
        "coiffure"
    ],
    "wof:name":"Coiffure Transition",
    "wof:placetype":"venue"
},
  "geometry": {"coordinates":[3.94688797,50.3603591919],"type":"Point"}
}