{
  "type": "Feature",
  "properties": {
    "addr:full":"Toekomstlaan 15 Beerse Antwerpen 2340",
    "addr:housenumber":"15",
    "addr:postcode":"2340",
    "addr:street":"Toekomstlaan",
    "iso:country":"BE",
    "sg:address":"Toekomstlaan 15",
    "sg:city":"Beerse",
    "sg:classifiers":[
        {
            "category":"Retail",
            "subcategory":"Repair Shop",
            "type":"Services"
        }
    ],
    "sg:phone":"+32 14 61 15 35",
    "sg:postcode":"2340",
    "sg:province":"Antwerpen",
    "sg:tags":[
        "mainten",
        "-",
        "parquet"
    ],
    "wof:name":"Vsv Parketvloeren Bvba",
    "wof:placetype":"venue"
},
  "geometry": {"coordinates":[4.8441138268,51.3045768738],"type":"Point"}
}