{
  "type": "Feature",
  "properties": {
    "addr:full":"Rue De La Coop\u00c9ration 70 Saint-nicolas Li\u00e8ge 4420",
    "addr:housenumber":"70",
    "addr:postcode":"4420",
    "addr:street":"Rue De La Coope\u0301Ration",
    "iso:country":"BE",
    "sg:address":"Rue De La Coop\u00c9ration 70",
    "sg:city":"Saint-nicolas",
    "sg:orig_category":"Enseignement maternel and primaire",
    "sg:phone":"+32 4 226 27 85",
    "sg:postcode":"4420",
    "sg:province":"Li\u00e8ge",
    "wof:name":"Ecole Fond. Communale",
    "wof:placetype":"venue"
},
  "geometry": {"coordinates":[5.5333619118,50.6375923157],"type":"Point"}
}