{
  "type": "Feature",
  "properties": {
    "iso:country":"BE",
    "sg:address":"De Theuxstraat 139",
    "sg:city":"Elsene/ixelles",
    "sg:orig_category":"Boekhouders",
    "sg:phone":"+32 2 640 60 85",
    "sg:postcode":"1050",
    "sg:province":"Bruxelles-Capitale",
    "wof:name":"Abdeslam Ouahabi Al Hassani",
    "wof:placetype":"venue"
},
  "geometry": {"coordinates":[4.3804068565,50.8307762146],"type":"Point"}
}