{
  "type": "Feature",
  "properties": {
    "iso:country":"BE",
    "sg:address":"Jetselaan 69",
    "sg:city":"Koekelberg",
    "sg:orig_category":"Fotolaboratoria",
    "sg:phone":"+32 2 420 45 44",
    "sg:postcode":"1081",
    "sg:province":"Bruxelles-Capitale",
    "wof:name":"Pierre Van Elewyck",
    "wof:placetype":"venue"
},
  "geometry": {"coordinates":[4.3267931938,50.8670501709],"type":"Point"}
}