{
  "type": "Feature",
  "properties": {
    "iso:country":"BE",
    "sg:address":"Rue De La Croix 26",
    "sg:city":"Namur",
    "sg:classifiers":[
        {
            "category":"Shopping",
            "subcategory":"Luggage & Leather Goods",
            "type":"Retail Goods"
        }
    ],
    "sg:phone":"+32 81 22 39 69",
    "sg:postcode":"5000",
    "sg:province":"Namur",
    "sg:tags":[
        "-"
    ],
    "wof:name":"Pirlot Maroquineries",
    "wof:placetype":"venue"
},
  "geometry": {"coordinates":[4.8647079468,50.4637794495],"type":"Point"}
}