{
  "type": "Feature",
  "properties": {
    "iso:country":"BE",
    "sg:address":"Quai De La Boverie 30a",
    "sg:city":"Luik (groot)",
    "sg:orig_category":"Kapsalons Mobiele kappers",
    "sg:phone":"+32 4 344 06 92",
    "sg:postcode":"4020",
    "sg:province":"Li\u00e8ge",
    "wof:name":"Artigas Image",
    "wof:placetype":"venue"
},
  "geometry": {"coordinates":[5.5765028,50.6343612671],"type":"Point"}
}