{
  "type": "Feature",
  "properties": {
    "addr:full":"Galloperstraat 37 Koksijde West-Vlaanderen 8670",
    "addr:housenumber":"37",
    "addr:postcode":"8670",
    "addr:street":"Galloperstraat",
    "iso:country":"BE",
    "sg:address":"Galloperstraat 37",
    "sg:city":"Koksijde",
    "sg:orig_category":"Traitements param\u00e9dicaux",
    "sg:phone":"+32 58 51 66 34",
    "sg:postcode":"8670",
    "sg:province":"West-Vlaanderen",
    "wof:name":"Van Leent",
    "wof:placetype":"venue"
},
  "geometry": {"coordinates":[2.6578381062,51.1067810059],"type":"Point"}
}