{
  "type": "Feature",
  "properties": {
    "addr:full":"Billegemstraat 59 Lede Oost-Vlaanderen 9340",
    "addr:housenumber":"59",
    "addr:postcode":"9340",
    "addr:street":"Billegemstraat",
    "iso:country":"BE",
    "sg:address":"Billegemstraat 59",
    "sg:city":"Lede",
    "sg:classifiers":[
        {
            "category":"Arena",
            "subcategory":"Sports Club",
            "type":"Entertainment"
        }
    ],
    "sg:phone":"+32 53 80 18 09",
    "sg:postcode":"9340",
    "sg:province":"Oost-Vlaanderen",
    "sg:tags":[
        "de"
    ],
    "wof:name":"Hoop In De Toekomst",
    "wof:placetype":"venue"
},
  "geometry": {"coordinates":[3.9545469284,50.9808158875],"type":"Point"}
}