{
  "type": "Feature",
  "properties": {
    "addr:full":"Meersstraat 66 Liedekerke Vlaams-Brabant 1770",
    "addr:housenumber":"66",
    "addr:postcode":"1770",
    "addr:street":"Meersstraat;Vlaams-Brabant",
    "iso:country":"BE",
    "sg:address":"Meersstraat 66",
    "sg:city":"Liedekerke",
    "sg:classifiers":[
        {
            "category":"Real Estate",
            "subcategory":"Architect",
            "type":"Services"
        }
    ],
    "sg:phone":"+32 53 66 66 79",
    "sg:postcode":"1770",
    "sg:province":"Vlaams-Brabant",
    "wof:name":"Asselman J",
    "wof:placetype":"venue"
},
  "geometry": {"coordinates":[4.0870380402,50.8755493164],"type":"Point"}
}