{
  "type": "Feature",
  "properties": {
    "addr:full":"Manitobawijk 1 De Haan (wenduine) West-Vlaanderen 8420",
    "addr:housenumber":"1",
    "addr:postcode":"8420",
    "addr:street":"Manitobawijk",
    "iso:country":"BE",
    "sg:address":"Manitobawijk 1",
    "sg:city":"De Haan (wenduine)",
    "sg:classifiers":[
        {
            "category":"Professional",
            "subcategory":"Computer Services",
            "type":"Services"
        }
    ],
    "sg:phone":"+32 475 59 34 88",
    "sg:postcode":"8420",
    "sg:province":"West-Vlaanderen",
    "sg:tags":[
        "-",
        "processing",
        "data"
    ],
    "wof:name":"Firststep",
    "wof:placetype":"venue"
},
  "geometry": {"coordinates":[3.088351965,51.3012695312],"type":"Point"}
}