{
  "type": "Feature",
  "properties": {
    "addr:full":"Zonnekring 3 Kortrijk West-Vlaanderen 8500",
    "addr:housenumber":"3",
    "addr:postcode":"8500",
    "addr:street":"Zonnekring",
    "iso:country":"BE",
    "sg:address":"Zonnekring 3",
    "sg:city":"Kortrijk",
    "sg:orig_category":"Woningbouw",
    "sg:phone":"+32 56 35 86 20",
    "sg:postcode":"8500",
    "sg:province":"West-Vlaanderen",
    "wof:name":"Gino Vanderougstraete",
    "wof:placetype":"venue"
},
  "geometry": {"coordinates":[3.2786970139,50.8402633667],"type":"Point"}
}