{
  "type": "Feature",
  "properties": {
    "addr:full":"Begijnengracht 4 Gent Oost-Vlaanderen 9000",
    "addr:housenumber":"4",
    "addr:postcode":"9000",
    "addr:street":"Begijnengracht;Oost-Vlaanderen",
    "iso:country":"BE",
    "sg:address":"Begijnengracht 4",
    "sg:city":"Gent",
    "sg:orig_category":"Newspapers, magazines, periodicals - Distribution",
    "sg:phone":"+32 9 224 21 63",
    "sg:postcode":"9000",
    "sg:province":"Oost-Vlaanderen",
    "wof:name":"Readers Corner",
    "wof:placetype":"venue"
},
  "geometry": {"coordinates":[3.7138910294,51.0563850403],"type":"Point"}
}