{
  "type": "Feature",
  "properties": {
    "addr:full":"Blekerijvesting 27 Menen West-Vlaanderen 8930",
    "addr:housenumber":"27",
    "addr:postcode":"8930",
    "addr:street":"Blekerijvesting",
    "iso:country":"BE",
    "sg:address":"Blekerijvesting 27",
    "sg:city":"Menen",
    "sg:orig_category":"Loodgieterij, verwarming and sanitaire installaties",
    "sg:phone":"+32 56 51 97 18",
    "sg:postcode":"8930",
    "sg:province":"West-Vlaanderen",
    "wof:name":"Aldo Cooke",
    "wof:placetype":"venue"
},
  "geometry": {"coordinates":[3.1203958988,50.7925376892],"type":"Point"}
}