{
  "type": "Feature",
  "properties": {
    "addr:full":"Stationsstraat 107 Essen Antwerpen 2910",
    "addr:housenumber":"107",
    "addr:postcode":"2910",
    "addr:street":"Stationsstraat",
    "iso:country":"BE",
    "sg:address":"Stationsstraat 107",
    "sg:city":"Essen",
    "sg:orig_category":"Rev\u00eatements pour sols and murs",
    "sg:phone":"+32 3 667 23 63",
    "sg:postcode":"2910",
    "sg:province":"Antwerpen",
    "wof:name":"Eddy Van Loon",
    "wof:placetype":"venue"
},
  "geometry": {"coordinates":[4.4602351189,51.4650764465],"type":"Point"}
}