{
  "type": "Feature",
  "properties": {
    "addr:full":"Venlosesteenweg 7 Maaseik Limburg 3680",
    "addr:housenumber":"7",
    "addr:postcode":"3680",
    "addr:street":"Venlosesteenweg",
    "iso:country":"BE",
    "sg:address":"Venlosesteenweg 7",
    "sg:city":"Maaseik",
    "sg:orig_category":"Brood, gebak and snoepgoed",
    "sg:phone":"+32 89 56 19 19",
    "sg:postcode":"3680",
    "sg:province":"Limburg",
    "wof:name":"Huis De Caramel",
    "wof:placetype":"venue"
},
  "geometry": {"coordinates":[5.7954010963,51.0973930359],"type":"Point"}
}