{
  "type": "Feature",
  "properties": {
    "addr:full":"Rue Des Sept Fontaines 3 Aubange Luxembourg 6792",
    "addr:housenumber":"3",
    "addr:postcode":"6792",
    "addr:street":"Rue Des Sept Fontaines",
    "iso:country":"BE",
    "sg:address":"Rue Des Sept Fontaines 3",
    "sg:city":"Aubange",
    "sg:orig_category":"Charpentes and couvertures",
    "sg:phone":"+32 63 38 87 75",
    "sg:postcode":"6792",
    "sg:province":"Luxembourg",
    "wof:name":"Toiture Et Tradition",
    "wof:placetype":"venue"
},
  "geometry": {"coordinates":[5.7591938972,49.5810508728],"type":"Point"}
}