{
  "type": "Feature",
  "properties": {
    "addr:full":"Rue De Virelles 35 Chimay Hainaut 6460",
    "addr:housenumber":"35",
    "addr:postcode":"6460",
    "addr:street":"Rue De Virelles",
    "iso:country":"BE",
    "sg:address":"Rue De Virelles 35",
    "sg:city":"Chimay",
    "sg:classifiers":[
        {
            "category":"Retail",
            "subcategory":"Veterinary Services",
            "type":"Services"
        }
    ],
    "sg:phone":"+32 60 21 14 66",
    "sg:postcode":"6460",
    "sg:province":"Hainaut",
    "sg:tags":[
        "veterinarian"
    ],
    "wof:name":"Danvoye R",
    "wof:placetype":"venue"
},
  "geometry": {"coordinates":[4.3202290535,50.0496444702],"type":"Point"}
}