{
  "type": "Feature",
  "properties": {
    "addr:full":"Rue Renier Chalon 16 Elsene/ixelles Bruxelles-Capitale 1050",
    "addr:housenumber":"16",
    "addr:postcode":"1050",
    "addr:street":"Rue Renier Chalon",
    "iso:country":"BE",
    "sg:address":"Rue Renier Chalon 16",
    "sg:city":"Elsene/ixelles",
    "sg:classifiers":[
        {
            "category":"Organizations",
            "subcategory":"Community Association",
            "type":"Services"
        }
    ],
    "sg:phone":"+32 2 344 55 73",
    "sg:postcode":"1050",
    "sg:province":"Bruxelles-Capitale",
    "sg:tags":[
        "organisation"
    ],
    "wof:name":"Gr.ind\u00c9p.form.-anim.cult.",
    "wof:placetype":"venue"
},
  "geometry": {"coordinates":[4.3613519669,50.8187828064],"type":"Point"}
}