{
  "type": "Feature",
  "properties": {
    "addr:full":"Route De Hannut 46 Namur (bouge) Namur 5004",
    "addr:housenumber":"46",
    "addr:postcode":"5004",
    "addr:street":"Route De Hannut",
    "iso:country":"BE",
    "sg:address":"Route De Hannut 46",
    "sg:city":"Namur (bouge)",
    "sg:classifiers":[
        {
            "category":"Manufacturing",
            "subcategory":"Metals",
            "type":"Manufacturing & Wholesale Goods"
        }
    ],
    "sg:phone":"+32 81 21 18 48",
    "sg:postcode":"5004",
    "sg:province":"Namur",
    "sg:tags":[
        "ironwork"
    ],
    "wof:name":"Degey Denis",
    "wof:placetype":"venue"
},
  "geometry": {"coordinates":[4.9013471603,50.471534729],"type":"Point"}
}