{
  "type": "Feature",
  "properties": {
    "iso:country":"BE",
    "sg:address":"Stationsplein 8",
    "sg:city":"Lokeren",
    "sg:orig_category":"Services fun\u00e9raires",
    "sg:phone":"+32 9 348 01 44",
    "sg:postcode":"9160",
    "sg:province":"Oost-Vlaanderen",
    "wof:name":"Vanlent",
    "wof:placetype":"venue"
},
  "geometry": {"coordinates":[3.9878869057,51.1058807373],"type":"Point"}
}