{
  "type": "Feature",
  "properties": {
    "addr:full":"Warande 87 Halle Vlaams-Brabant 1500",
    "addr:housenumber":"87",
    "addr:postcode":"1500",
    "addr:street":"Warande",
    "iso:country":"BE",
    "sg:address":"Warande 87",
    "sg:city":"Halle",
    "sg:classifiers":[
        {
            "category":"Professional",
            "subcategory":"Lawyer & Legal Services",
            "type":"Services"
        }
    ],
    "sg:phone":"+32 2 356 98 94",
    "sg:postcode":"1500",
    "sg:province":"Vlaams-Brabant",
    "wof:name":"Roobaert Dominik",
    "wof:placetype":"venue"
},
  "geometry": {"coordinates":[4.2605829239,50.7168006897],"type":"Point"}
}