{
  "type": "Feature",
  "properties": {
    "iso:country":"BE",
    "sg:address":"Rue De Stalle 24",
    "sg:city":"Bruxelles (uccle)",
    "sg:classifiers":[
        {
            "category":"Social Services",
            "type":"Services"
        }
    ],
    "sg:phone":"+32 2 376 10 00",
    "sg:postcode":"1180",
    "sg:province":"Bruxelles-Capitale",
    "wof:name":"Centre De Planning Familial Et De Consultations D'uccle",
    "wof:placetype":"venue"
},
  "geometry": {"coordinates":[4.3363461494,50.8000450134],"type":"Point"}
}