{
  "type": "Feature",
  "properties": {
    "addr:full":"Boulevard De Merckem 36 Namur Namur 5000",
    "addr:housenumber":"36",
    "addr:postcode":"5000",
    "addr:street":"Boulevard De Merckem",
    "iso:country":"BE",
    "sg:address":"Boulevard De Merckem 36",
    "sg:city":"Namur",
    "sg:classifiers":[
        {
            "category":"Professional",
            "subcategory":"Computer Services",
            "type":"Services"
        }
    ],
    "sg:phone":"+32 81 74 71 74",
    "sg:postcode":"5000",
    "sg:province":"Namur",
    "sg:tags":[
        "-",
        "processing",
        "data"
    ],
    "wof:name":"P.c. Budget",
    "wof:placetype":"venue"
},
  "geometry": {"coordinates":[4.8568120003,50.4698791504],"type":"Point"}
}