{
  "type": "Feature",
  "properties": {
    "addr:full":"Rue Des Taxandres 5 Bruxelles (etterbeek) Bruxelles-Capitale 1040",
    "addr:housenumber":"5",
    "addr:postcode":"1040",
    "addr:street":"Rue Des Taxandres",
    "iso:country":"BE",
    "sg:address":"Rue Des Taxandres 5",
    "sg:city":"Bruxelles (etterbeek)",
    "sg:classifiers":[
        {
            "category":"Social Services",
            "type":"Services"
        }
    ],
    "sg:phone":"+32 2 733 06 40",
    "sg:postcode":"1040",
    "sg:province":"Bruxelles-Capitale",
    "wof:name":"Epistola",
    "wof:placetype":"venue"
},
  "geometry": {"coordinates":[4.4026679993,50.8368835449],"type":"Point"}
}