{
  "type": "Feature",
  "properties": {
    "addr:full":"Zwaaidok 2 Oostende West-Vlaanderen 8400",
    "addr:housenumber":"2",
    "addr:postcode":"8400",
    "addr:street":"Zwaaidok",
    "iso:country":"BE",
    "sg:address":"Zwaaidok 2",
    "sg:city":"Oostende",
    "sg:classifiers":[
        {
            "category":"Harbor",
            "type":"Transportation"
        }
    ],
    "sg:phone":"+32 59 33 11 33",
    "sg:postcode":"8400",
    "sg:province":"West-Vlaanderen",
    "sg:tags":[
        "port",
        "facility"
    ],
    "wof:name":"Verhelst Ter Polder",
    "wof:placetype":"venue"
},
  "geometry": {"coordinates":[2.9406650066,51.2183609009],"type":"Point"}
}