{
  "type": "Feature",
  "properties": {
    "addr:full":"Pater Vandersteenestraat 8 Kortrijk (marke) West-Vlaanderen 8510",
    "addr:housenumber":"8",
    "addr:postcode":"8510",
    "addr:street":"Pater Vandersteenestraat",
    "iso:country":"BE",
    "sg:address":"Pater Vandersteenestraat 8",
    "sg:city":"Kortrijk (marke)",
    "sg:classifiers":[
        {
            "category":"Health Services",
            "subcategory":"Dentist",
            "type":"Services"
        }
    ],
    "sg:phone":"+32 56 20 15 14",
    "sg:postcode":"8510",
    "sg:province":"West-Vlaanderen",
    "wof:name":"Mattelaer Jacques",
    "wof:placetype":"venue"
},
  "geometry": {"coordinates":[3.2461829185,50.8069648743],"type":"Point"}
}