{
  "type": "Feature",
  "properties": {
    "iso:country":"BE",
    "sg:address":"Hulshout-veld 57",
    "sg:city":"Hulshout",
    "sg:classifiers":[
        {
            "category":"Fast Food",
            "type":"Food & Drink"
        }
    ],
    "sg:phone":"+32 15 22 35 51",
    "sg:postcode":"2235",
    "sg:province":"Antwerpen",
    "sg:tags":[
        "\u00c0",
        "emporter",
        "restaurants"
    ],
    "wof:name":"Frituur Snackbar Chalet",
    "wof:placetype":"venue"
},
  "geometry": {"coordinates":[4.7828478813,51.0696182251],"type":"Point"}
}