{
  "type": "Feature",
  "properties": {
    "iso:country":"BE",
    "sg:address":"Rue De La Reffe 31",
    "sg:city":"Aywaille",
    "sg:orig_category":"Fotografen and fotostudio's",
    "sg:phone":"+32 4 384 89 74",
    "sg:postcode":"4920",
    "sg:province":"Li\u00e8ge",
    "wof:name":"Photo Art",
    "wof:placetype":"venue"
},
  "geometry": {"coordinates":[5.6782069206,50.4738540649],"type":"Point"}
}