{
  "type": "Feature",
  "properties": {
    "iso:country":"BE",
    "sg:address":"Place Liedts 7",
    "sg:city":"Bruxelles (schaerbeek)",
    "sg:classifiers":[
        {
            "category":"Shopping",
            "subcategory":"Luggage & Leather Goods",
            "type":"Retail Goods"
        }
    ],
    "sg:phone":"+32 2 215 79 20",
    "sg:postcode":"1030",
    "sg:province":"Bruxelles-Capitale",
    "sg:tags":[
        "luggage-carriers"
    ],
    "wof:name":"Autac (l')",
    "wof:placetype":"venue"
},
  "geometry": {"coordinates":[4.3668708801,50.8642883301],"type":"Point"}
}