{
  "type": "Feature",
  "properties": {
    "iso:country":"BE",
    "sg:address":"Van Langenhovestraat 11-13",
    "sg:city":"Aalst",
    "sg:orig_category":"Unclassifiable Establishments",
    "sg:phone":"+32 53 77 12 00",
    "sg:postcode":"9300",
    "sg:province":"Oost-Vlaanderen",
    "wof:name":"Samdam Business Gifts Nv",
    "wof:placetype":"venue"
},
  "geometry": {"coordinates":[4.0447149277,50.9341011047],"type":"Point"}
}