{
  "type": "Feature",
  "properties": {
    "iso:country":"BE",
    "sg:address":"Schoolstraat 24",
    "sg:city":"Buggenhout",
    "sg:orig_category":"Agences de presse",
    "sg:phone":"+32 52 34 12 57",
    "sg:postcode":"9255",
    "sg:province":"Oost-Vlaanderen",
    "wof:name":"Patrick De Cock",
    "wof:placetype":"venue"
},
  "geometry": {"coordinates":[4.1979608536,51.0147666931],"type":"Point"}
}