{
  "type": "Feature",
  "properties": {
    "iso:country":"BE",
    "sg:address":"Dokter Persoonslaan 15c",
    "sg:city":"Willebroek",
    "sg:classifiers":[
        {
            "category":"Shopping",
            "subcategory":"Clothing, Apparel, & Fashions",
            "type":"Retail Goods"
        }
    ],
    "sg:phone":"+32 3 866 07 51",
    "sg:postcode":"2830",
    "sg:province":"Antwerpen",
    "sg:tags":[
        "boutique"
    ],
    "wof:name":"Fashion Urbain",
    "wof:placetype":"venue"
},
  "geometry": {"coordinates":[4.3621959686,51.0597419739],"type":"Point"}
}