{
  "type": "Feature",
  "properties": {
    "addr:full":"Rollegemstraat 197 Ledegem West-Vlaanderen 8880",
    "addr:housenumber":"197",
    "addr:postcode":"8880",
    "addr:street":"Rollegemstraat",
    "iso:country":"BE",
    "sg:address":"Rollegemstraat 197",
    "sg:city":"Ledegem",
    "sg:classifiers":[
        {
            "category":"Health Services",
            "subcategory":"Doctor",
            "type":"Services"
        }
    ],
    "sg:phone":"+32 56 50 58 70",
    "sg:postcode":"8880",
    "sg:province":"West-Vlaanderen",
    "sg:tags":[
        "medicinephysicians",
        "surgeon"
    ],
    "wof:name":"Martens Chris",
    "wof:placetype":"venue"
},
  "geometry": {"coordinates":[3.1376540661,50.8631668091],"type":"Point"}
}