{
  "type": "Feature",
  "properties": {
    "addr:full":"Grand Place 22 Frasnes-lez-anvaing Hainaut 7911",
    "addr:housenumber":"22",
    "addr:postcode":"7911",
    "addr:street":"Grand Place",
    "iso:country":"BE",
    "sg:address":"Grand Place 22",
    "sg:city":"Frasnes-lez-anvaing",
    "sg:orig_category":"Cr\u00e9dit \u00e0 la consommation",
    "sg:phone":"+32 69 86 71 23",
    "sg:postcode":"7911",
    "sg:province":"Hainaut",
    "wof:name":"Comptoir Agricole De Frasnes",
    "wof:placetype":"venue"
},
  "geometry": {"coordinates":[3.6210598946,50.66796875],"type":"Point"}
}