{
  "type": "Feature",
  "properties": {
    "iso:country":"BE",
    "sg:address":"Place Jean D'ardenne 9",
    "sg:city":"Esneux",
    "sg:classifiers":[
        {
            "category":"Health Services",
            "subcategory":"Doctor",
            "type":"Services"
        }
    ],
    "sg:phone":"+32 4 380 25 77",
    "sg:postcode":"4130",
    "sg:province":"Li\u00e8ge",
    "sg:tags":[
        "medicinephysicians",
        "surgeon"
    ],
    "wof:name":"Carlier Nathalie",
    "wof:placetype":"venue"
},
  "geometry": {"coordinates":[5.568628788,50.5332450867],"type":"Point"}
}