{
  "type": "Feature",
  "properties": {
    "iso:country":"BE",
    "sg:address":"Place Saint-roch 35",
    "sg:city":"Chatelet",
    "sg:orig_category":"Meubles D\u00e9taillants, Am\u00e9nagement de B\u00e2timents et de Cuisines",
    "sg:phone":"+32 71 38 07 26",
    "sg:postcode":"6200",
    "sg:province":"Hainaut",
    "wof:name":"Galeries St.roch",
    "wof:placetype":"venue"
},
  "geometry": {"coordinates":[4.5295629501,50.4007072449],"type":"Point"}
}