{
  "type": "Feature",
  "properties": {
    "addr:full":"Rue G\u00c9n\u00c9ral Eenens 31 Schaarbeek/schaerbeek Bruxelles-Capitale 1030",
    "addr:housenumber":"31",
    "addr:postcode":"1030",
    "addr:street":"Rue Ge\u0301Ne\u0301Ral Eenens",
    "iso:country":"BE",
    "sg:address":"Rue G\u00c9n\u00c9ral Eenens 31",
    "sg:city":"Schaarbeek/schaerbeek",
    "sg:orig_category":"Pain, p\u00e2tisseries and confiseries",
    "sg:phone":"+32 2 215 15 26",
    "sg:postcode":"1030",
    "sg:province":"Bruxelles-Capitale",
    "wof:name":"P\u00c2tisserie Boudiba",
    "wof:placetype":"venue"
},
  "geometry": {"coordinates":[4.3756961823,50.8681297302],"type":"Point"}
}