{
  "type": "Feature",
  "properties": {
    "iso:country":"BE",
    "sg:address":"Prof.o.rubbrechtstraat 15",
    "sg:city":"Poperinge",
    "sg:classifiers":[
        {
            "category":"Cafe",
            "type":"Food & Drink"
        }
    ],
    "sg:phone":"+32 57 30 05 22",
    "sg:postcode":"8972",
    "sg:province":"West-Vlaanderen",
    "sg:tags":[
        "caf\u00e9s"
    ],
    "wof:name":"Hof Van Commerce",
    "wof:placetype":"venue"
},
  "geometry": {"coordinates":[2.6247930527,50.9186439514],"type":"Point"}
}