{
  "type": "Feature",
  "properties": {
    "addr:full":"Populierstraat 80 Roeselare West-Vlaanderen 8800",
    "addr:housenumber":"80",
    "addr:postcode":"8800",
    "addr:street":"Populierstraat",
    "iso:country":"BE",
    "sg:address":"Populierstraat 80",
    "sg:city":"Roeselare",
    "sg:classifiers":[
        {
            "category":"Building & Trades",
            "subcategory":"Landscaping Services",
            "type":"Services"
        }
    ],
    "sg:phone":"+32 51 20 05 19",
    "sg:postcode":"8800",
    "sg:province":"West-Vlaanderen",
    "sg:tags":[
        "moss",
        "removal"
    ],
    "wof:name":"Bonny F Bvba",
    "wof:placetype":"venue"
},
  "geometry": {"coordinates":[3.1591570377,50.9482078552],"type":"Point"}
}