{
  "type": "Feature",
  "properties": {
    "iso:country":"BE",
    "sg:address":"Bouwmeestersstraat 28b1",
    "sg:city":"Gent",
    "sg:orig_category":"D\u00e9corateurs d'int\u00e9rieur",
    "sg:phone":"+32 9 228 83 75",
    "sg:postcode":"9040",
    "sg:province":"Oost-Vlaanderen",
    "wof:name":"S2",
    "wof:placetype":"venue"
},
  "geometry": {"coordinates":[3.7480010986,51.0503692627],"type":"Point"}
}