{
  "type": "Feature",
  "properties": {
    "addr:full":"Berlaarsesteenweg 18 Lier Antwerpen 2500",
    "addr:housenumber":"18",
    "addr:postcode":"2500",
    "addr:street":"Berlaarsesteenweg",
    "iso:country":"BE",
    "sg:address":"Berlaarsesteenweg 18",
    "sg:city":"Lier",
    "sg:classifiers":[
        {
            "category":"Health Services",
            "subcategory":"Dentist",
            "type":"Services"
        }
    ],
    "sg:phone":"+32 3 480 83 64",
    "sg:postcode":"2500",
    "sg:province":"Antwerpen",
    "wof:name":"Van Den Daelen M",
    "wof:placetype":"venue"
},
  "geometry": {"coordinates":[4.5841779709,51.1282234192],"type":"Point"}
}