{
  "type": "Feature",
  "properties": {
    "iso:country":"BE",
    "sg:address":"Groenstraat 150",
    "sg:city":"Aalst",
    "sg:orig_category":"Imprimeries and copyshops",
    "sg:phone":"+32 53 21 62 27",
    "sg:postcode":"9300",
    "sg:province":"Oost-Vlaanderen",
    "wof:name":"Drukkerij Impact",
    "wof:placetype":"venue"
},
  "geometry": {"coordinates":[4.0529937744,50.9446678162],"type":"Point"}
}