{
  "type": "Feature",
  "properties": {
    "addr:full":"Chauss\u00c9e De Namur 48 Gembloux Namur 5030",
    "addr:housenumber":"48",
    "addr:postcode":"5030",
    "addr:street":"Chausse\u0301E De Namur;Namur",
    "iso:country":"BE",
    "sg:address":"Chauss\u00c9e De Namur 48",
    "sg:city":"Gembloux",
    "sg:orig_category":"Royal Canin Tuinbenodigdheden",
    "sg:phone":"+32 81 61 12 06",
    "sg:postcode":"5030",
    "sg:province":"Namur",
    "wof:name":"Ets Jardins-loisirs-marchal",
    "wof:placetype":"venue"
},
  "geometry": {"coordinates":[4.7035951614,50.5613174438],"type":"Point"}
}