{
  "type": "Feature",
  "properties": {
    "iso:country":"BE",
    "sg:address":"Kerkstraat 42",
    "sg:city":"Herk-de-stad",
    "sg:classifiers":[
        {
            "category":"Arena",
            "subcategory":"Sports Club",
            "type":"Entertainment"
        }
    ],
    "sg:phone":"+32 13 55 39 33",
    "sg:postcode":"3540",
    "sg:province":"Limburg",
    "sg:tags":[
        "caf\u00e9s",
        "de"
    ],
    "wof:name":"Sporta Tennis Club",
    "wof:placetype":"venue"
},
  "geometry": {"coordinates":[5.1817169189,50.9583015442],"type":"Point"}
}