{
  "type": "Feature",
  "properties": {
    "addr:full":"Jan Baptist Cardijnstraat 21 Sint-pieters-leeuw Vlaams-Brabant 1600",
    "addr:housenumber":"21",
    "addr:postcode":"1600",
    "addr:street":"Jan Baptist Cardijnstraat",
    "iso:country":"BE",
    "sg:address":"Jan Baptist Cardijnstraat 21",
    "sg:city":"Sint-pieters-leeuw",
    "sg:classifiers":[
        {
            "category":"Professional",
            "subcategory":"Accounting & Tax Preparation",
            "type":"Services"
        }
    ],
    "sg:phone":"+32 2 360 28 78",
    "sg:postcode":"1600",
    "sg:province":"Vlaams-Brabant",
    "sg:tags":[
        "accountant"
    ],
    "wof:name":"Van Moer R & Cie",
    "wof:placetype":"venue"
},
  "geometry": {"coordinates":[4.2286438942,50.7621498108],"type":"Point"}
}