{
  "type": "Feature",
  "properties": {
    "addr:full":"Donklaan 77b12 Berlare Oost-Vlaanderen 9290",
    "addr:housenumber":"77b12",
    "addr:postcode":"9290",
    "addr:street":"Donklaan",
    "iso:country":"BE",
    "sg:address":"Donklaan 77b12",
    "sg:city":"Berlare",
    "sg:orig_category":"Avocats and conseillers juridiques",
    "sg:phone":"+32 9 367 61 43",
    "sg:postcode":"9290",
    "sg:province":"Oost-Vlaanderen",
    "wof:name":"Greta Van Keer",
    "wof:placetype":"venue"
},
  "geometry": {"coordinates":[3.9817318916,51.0395088196],"type":"Point"}
}