{
  "type": "Feature",
  "properties": {
    "iso:country":"BE",
    "sg:address":"Rue Du Viaduc 20",
    "sg:city":"Soignies",
    "sg:classifiers":[
        {
            "category":"Health Services",
            "subcategory":"Nursing And Care Facility",
            "type":"Services"
        }
    ],
    "sg:phone":"+32 67 33 54 12",
    "sg:postcode":"7060",
    "sg:province":"Hainaut",
    "sg:tags":[
        "home"
    ],
    "wof:name":"Andrejuk C",
    "wof:placetype":"venue"
},
  "geometry": {"coordinates":[4.0598649979,50.5703086853],"type":"Point"}
}