{
  "type": "Feature",
  "properties": {
    "addr:full":"Poperingseweg 429 Vlamertinge 8968",
    "addr:housenumber":"429",
    "addr:postcode":"8968",
    "addr:street":"Poperingseweg",
    "iso:country":"BE",
    "sg:address":"Poperingseweg 429",
    "sg:city":"Vlamertinge",
    "sg:classifiers":[
        {
            "category":"Banks & Credit Unions",
            "subcategory":"Bank",
            "type":"Services"
        }
    ],
    "sg:phone":"+32 57 20 09 19",
    "sg:postcode":"8968",
    "wof:name":"Aslk-cger Bank",
    "wof:placetype":"venue"
},
  "geometry": {"coordinates":[2.8198668957,50.8548088074],"type":"Point"}
}