{
  "type": "Feature",
  "properties": {
    "iso:country":"BE",
    "sg:address":"Burgemeester Nolfstraat 5",
    "sg:city":"Kortrijk",
    "sg:orig_category":"Beheer onroerend goed",
    "sg:phone":"+32 56 22 38 23",
    "sg:postcode":"8500",
    "sg:province":"West-Vlaanderen",
    "wof:name":"Leon Meerschaert",
    "wof:placetype":"venue"
},
  "geometry": {"coordinates":[3.2600460052,50.8283233643],"type":"Point"}
}