{
  "type": "Feature",
  "properties": {
    "addr:full":"Vrijheid 18 Hoogstraten Antwerpen 2530",
    "addr:housenumber":"18",
    "addr:postcode":"2530",
    "addr:street":"Vrijheid",
    "iso:country":"BE",
    "sg:address":"Vrijheid 18",
    "sg:city":"Hoogstraten",
    "sg:orig_category":"Agences de voyages",
    "sg:phone":"+32 3 314 85 84",
    "sg:postcode":"2530",
    "sg:province":"Antwerpen",
    "wof:name":"Cruise World International",
    "wof:placetype":"venue"
},
  "geometry": {"coordinates":[4.7629179955,51.4047851562],"type":"Point"}
}