{
  "type": "Feature",
  "properties": {
    "iso:country":"BE",
    "sg:address":"27",
    "sg:city":"Rue Du Haut Donjon 7904 Leuze-en-hainaut",
    "sg:classifiers":[
        {
            "category":"Professional",
            "type":"Services"
        }
    ],
    "sg:phone":"+32 69 66 23 03",
    "sg:postcode":"27",
    "sg:tags":[
        "transport"
    ],
    "wof:name":"Baudry Jean-pierre",
    "wof:placetype":"venue"
},
  "geometry": {"coordinates":[3.5876328945,50.5797920227],"type":"Point"}
}