{
  "type": "Feature",
  "properties": {
    "addr:full":"Joseph Wautersstraat 109 Brugge (sint-michiels) West-Vlaanderen 8200",
    "addr:housenumber":"109",
    "addr:postcode":"8200",
    "addr:street":"Joseph Wautersstraat",
    "iso:country":"BE",
    "sg:address":"Joseph Wautersstraat 109",
    "sg:city":"Brugge (sint-michiels)",
    "sg:classifiers":[
        {
            "category":"Education",
            "subcategory":"Dance Studio",
            "type":"Public Place"
        }
    ],
    "sg:phone":"+32 50 38 20 79",
    "sg:postcode":"8200",
    "sg:province":"West-Vlaanderen",
    "sg:tags":[
        "school",
        "dancing"
    ],
    "wof:name":"Vandaele H -dansschool Rose De Leyn",
    "wof:placetype":"venue"
},
  "geometry": {"coordinates":[3.1984701157,51.1924209595],"type":"Point"}
}