{
  "type": "Feature",
  "properties": {
    "addr:full":"Stijn Streuvelsstraat 20 Nazareth (eke) Oost-Vlaanderen 9810",
    "addr:housenumber":"20",
    "addr:postcode":"9810",
    "addr:street":"Stijn Streuvelsstraat",
    "iso:country":"BE",
    "sg:address":"Stijn Streuvelsstraat 20",
    "sg:city":"Nazareth (eke)",
    "sg:classifiers":[
        {
            "category":"Professional",
            "subcategory":"Management & Consulting",
            "type":"Services"
        }
    ],
    "sg:phone":"+32 9 385 58 39",
    "sg:postcode":"9810",
    "sg:province":"Oost-Vlaanderen",
    "sg:tags":[
        "consultant"
    ],
    "wof:name":"Vlaeminck Consulting Bvba",
    "wof:placetype":"venue"
},
  "geometry": {"coordinates":[3.6398200989,50.9605255127],"type":"Point"}
}