{
  "type": "Feature",
  "properties": {
    "iso:country":"BE",
    "sg:address":"Place Blaise Pascal 1",
    "sg:city":"Ottignies-louvain-la-neuve",
    "sg:orig_category":"Hoger onderwijs",
    "sg:phone":"+32 10 47 49 35",
    "sg:postcode":"1348",
    "sg:province":"Brabant Wallon",
    "wof:name":"U.c.l.-d\u00c9p. D\u00b4histoire",
    "wof:placetype":"venue"
},
  "geometry": {"coordinates":[4.6106100082,50.6695709229],"type":"Point"}
}