{
  "type": "Feature",
  "properties": {
    "addr:full":"Laurys Gewatstraat 71 Nijlen Antwerpen 2560",
    "addr:housenumber":"71",
    "addr:postcode":"2560",
    "addr:street":"Laurys Gewatstraat",
    "iso:country":"BE",
    "sg:address":"Laurys Gewatstraat 71",
    "sg:city":"Nijlen",
    "sg:classifiers":[
        {
            "category":"Manufacturing",
            "subcategory":"Signs",
            "type":"Manufacturing & Wholesale Goods"
        }
    ],
    "sg:phone":"+32 3 411 11 27",
    "sg:postcode":"2560",
    "sg:province":"Antwerpen",
    "sg:tags":[
        "signalling",
        "yard",
        "road"
    ],
    "wof:name":"Dlw-c & S",
    "wof:placetype":"venue"
},
  "geometry": {"coordinates":[4.6819019318,51.1690368652],"type":"Point"}
}