{
  "type": "Feature",
  "properties": {
    "iso:country":"BE",
    "sg:address":"Henri Caronstraat 28",
    "sg:city":"Hoeilaart",
    "sg:classifiers":[
        {
            "category":"Shopping",
            "subcategory":"Books",
            "type":"Retail Goods"
        }
    ],
    "sg:phone":"+32 2 657 04 61",
    "sg:postcode":"1560",
    "sg:province":"Vlaams-Brabant",
    "sg:tags":[
        "bookseller"
    ],
    "wof:name":"Karine",
    "wof:placetype":"venue"
},
  "geometry": {"coordinates":[4.4759459496,50.7667007446],"type":"Point"}
}