{
  "type": "Feature",
  "properties": {
    "iso:country":"BE",
    "sg:address":"Oudekerkstraat 10",
    "sg:city":"Kinrooi",
    "sg:orig_category":"Pain, p\u00e2tisseries and confiseries",
    "sg:phone":"+32 89 70 15 27",
    "sg:postcode":"3640",
    "sg:province":"Limburg",
    "wof:name":"Madeleine Wirix",
    "wof:placetype":"venue"
},
  "geometry": {"coordinates":[5.7360057831,51.169506073],"type":"Point"}
}