{
  "type": "Feature",
  "properties": {
    "iso:country":"BE",
    "sg:address":"Rue Du Pont 9",
    "sg:city":"Seraing",
    "sg:classifiers":[
        {
            "category":"Restaurant",
            "type":"Food & Drink"
        }
    ],
    "sg:phone":"+32 4 233 80 42",
    "sg:postcode":"4101",
    "sg:province":"Li\u00e8ge",
    "wof:name":"New China",
    "wof:placetype":"venue"
},
  "geometry": {"coordinates":[5.5080342293,50.6176223755],"type":"Point"}
}