{
  "type": "Feature",
  "properties": {
    "iso:country":"BE",
    "sg:address":"Rue Baille Du Renard 5",
    "sg:city":"Bernissart (blaton)",
    "sg:classifiers":[
        {
            "category":"Health Services",
            "subcategory":"Health Practitioner",
            "type":"Services"
        }
    ],
    "sg:phone":"+32 69 56 16 74",
    "sg:postcode":"7321",
    "sg:province":"Hainaut",
    "sg:tags":[
        "physiotherapist"
    ],
    "wof:name":"Latchoumy V",
    "wof:placetype":"venue"
},
  "geometry": {"coordinates":[3.6889200211,50.4724807739],"type":"Point"}
}