{
  "type": "Feature",
  "properties": {
    "iso:country":"BE",
    "sg:address":"Rue Kamme 21",
    "sg:city":"Bever/bievene",
    "sg:orig_category":"Eleveurs de bovins",
    "sg:phone":"+32 54 58 97 25",
    "sg:postcode":"1547",
    "sg:province":"Vlaams-Brabant",
    "wof:name":"Jean De Herder",
    "wof:placetype":"venue"
},
  "geometry": {"coordinates":[3.9403600693,50.7166404724],"type":"Point"}
}