{
  "type": "Feature",
  "properties": {
    "iso:country":"BE",
    "sg:address":"Koveklaan 16",
    "sg:city":"Essen",
    "sg:classifiers":[
        {
            "category":"Retail",
            "subcategory":"Repair Shop",
            "type":"Services"
        }
    ],
    "sg:phone":"+32 3 677 34 84",
    "sg:postcode":"2910",
    "sg:province":"Antwerpen",
    "sg:tags":[
        "denture"
    ],
    "wof:name":"Costermans D",
    "wof:placetype":"venue"
},
  "geometry": {"coordinates":[4.4423251152,51.4526786804],"type":"Point"}
}