{
  "type": "Feature",
  "properties": {
    "addr:full":"Walenstraat 92 Hasselt Limburg 3500",
    "addr:housenumber":"92",
    "addr:postcode":"3500",
    "addr:street":"Walenstraat",
    "iso:country":"BE",
    "sg:address":"Walenstraat 92",
    "sg:city":"Hasselt",
    "sg:classifiers":[
        {
            "category":"Professional",
            "subcategory":"Advertising",
            "type":"Services"
        }
    ],
    "sg:phone":"+32 11 21 10 15",
    "sg:postcode":"3500",
    "sg:province":"Limburg",
    "sg:tags":[
        "photography"
    ],
    "wof:name":"Studio Truyens",
    "wof:placetype":"venue"
},
  "geometry": {"coordinates":[5.3601198196,50.9536895752],"type":"Point"}
}