{
  "type": "Feature",
  "properties": {
    "addr:full":"Rue De La Marzelle 66 Sivry-rance (sivry) Hainaut 6470",
    "addr:housenumber":"66",
    "addr:postcode":"6470",
    "addr:street":"Rue De La Marzelle",
    "iso:country":"BE",
    "sg:address":"Rue De La Marzelle 66",
    "sg:city":"Sivry-rance (sivry)",
    "sg:classifiers":[
        {
            "category":"Bars & Pubs",
            "type":"Food & Drink"
        }
    ],
    "sg:phone":"+32 60 45 53 49",
    "sg:postcode":"6470",
    "sg:province":"Hainaut",
    "wof:name":"Poteau (au)",
    "wof:placetype":"venue"
},
  "geometry": {"coordinates":[4.1549201012,50.1671600342],"type":"Point"}
}