{
  "type": "Feature",
  "properties": {
    "addr:full":"Sint-elooistraat 53 Zedelgem West-Vlaanderen 8210",
    "addr:housenumber":"53",
    "addr:postcode":"8210",
    "addr:street":"Sint-Elooistraat",
    "iso:country":"BE",
    "sg:address":"Sint-elooistraat 53",
    "sg:city":"Zedelgem",
    "sg:classifiers":[
        {
            "category":"Bakery",
            "type":"Food & Drink"
        }
    ],
    "sg:phone":"+32 50 24 13 27",
    "sg:postcode":"8210",
    "sg:province":"West-Vlaanderen",
    "sg:tags":[
        "confectioner",
        "baker"
    ],
    "wof:name":"Desanghere",
    "wof:placetype":"venue"
},
  "geometry": {"coordinates":[3.1458399296,51.1376457214],"type":"Point"}
}