{
  "type": "Feature",
  "properties": {
    "iso:country":"BE",
    "sg:address":"Rue D'argile 26",
    "sg:city":"Kraainem/kraainem",
    "sg:orig_category":"Catering and organisation de f\u00eates. Alimentation sp\u00e9cialis\u00e9e",
    "sg:phone":"+32 2 731 72 41",
    "sg:postcode":"1950",
    "sg:province":"Vlaams-Brabant",
    "wof:name":"Restauration Et Gestion",
    "wof:placetype":"venue"
},
  "geometry": {"coordinates":[4.4680871964,50.8401451111],"type":"Point"}
}