{
  "type": "Feature",
  "properties": {
    "addr:full":"Oude-afspanningsplein 7 Jette Bruxelles-Capitale 1090",
    "addr:housenumber":"7",
    "addr:postcode":"1090",
    "addr:street":"Oude-Afspanningsplein",
    "iso:country":"BE",
    "sg:address":"Oude-afspanningsplein 7",
    "sg:city":"Jette",
    "sg:orig_category":"Banken and kredietinstellingen",
    "sg:phone":"+32 2 479 55 07",
    "sg:postcode":"1090",
    "sg:province":"Bruxelles-Capitale",
    "wof:name":"Fortis",
    "wof:placetype":"venue"
},
  "geometry": {"coordinates":[4.3183288574,50.8852767944],"type":"Point"}
}