{
  "type": "Feature",
  "properties": {
    "iso:country":"BE",
    "sg:address":"Brugse Heirweg 20",
    "sg:city":"Koekelare",
    "sg:orig_category":"Eleveurs de bovins",
    "sg:phone":"+32 51 58 82 70",
    "sg:postcode":"8680",
    "sg:province":"West-Vlaanderen",
    "wof:name":"Roger Borra",
    "wof:placetype":"venue"
},
  "geometry": {"coordinates":[2.9416360855,51.0773582458],"type":"Point"}
}