{
  "type": "Feature",
  "properties": {
    "addr:full":"Dr. Vanweddingenlaan 10 Herk-de-stad Limburg 3540",
    "addr:housenumber":"10",
    "addr:postcode":"3540",
    "addr:street":"Vanweddingenlaan",
    "iso:country":"BE",
    "sg:address":"Dr. Vanweddingenlaan 10",
    "sg:city":"Herk-de-stad",
    "sg:orig_category":"Enseignement secondaire technique and professionnel",
    "sg:phone":"+32 13 55 17 10",
    "sg:postcode":"3540",
    "sg:province":"Limburg",
    "wof:name":"Middenschool",
    "wof:placetype":"venue"
},
  "geometry": {"coordinates":[5.163672924,50.9395332336],"type":"Point"}
}