{
  "type": "Feature",
  "properties": {
    "iso:country":"BE",
    "sg:address":"Chauss\u00c9e De Huy 243",
    "sg:city":"Chaumont-gistoux",
    "sg:classifiers":[
        {
            "category":"Cafe",
            "type":"Food & Drink"
        }
    ],
    "sg:phone":"+32 10 68 82 42",
    "sg:postcode":"1325",
    "sg:province":"Brabant Wallon",
    "sg:tags":[
        "caf\u00e9s"
    ],
    "wof:name":"Caf\u00c9 De La Poste",
    "wof:placetype":"venue"
},
  "geometry": {"coordinates":[4.6950149536,50.6838798523],"type":"Point"}
}