{
  "type": "Feature",
  "properties": {
    "addr:full":"Kerkstraat 111 Anzegem West-Vlaanderen 8570",
    "addr:housenumber":"111",
    "addr:postcode":"8570",
    "addr:street":"Kerkstraat",
    "iso:country":"BE",
    "sg:address":"Kerkstraat 111",
    "sg:city":"Anzegem",
    "sg:orig_category":"Verplichte sociale verzekeringen",
    "sg:phone":"+32 56 68 81 44",
    "sg:postcode":"8570",
    "sg:province":"West-Vlaanderen",
    "wof:name":"Christelijke Mutualiteit",
    "wof:placetype":"venue"
},
  "geometry": {"coordinates":[3.474462986,50.8384437561],"type":"Point"}
}