{
  "type": "Feature",
  "properties": {
    "iso:country":"BE",
    "sg:address":"Rue Chant Des Oiseaux 13",
    "sg:city":"Welkenraedt",
    "sg:classifiers":[
        {
            "category":"Sports & Exercise",
            "subcategory":"Stables",
            "type":"Entertainment"
        }
    ],
    "sg:phone":"+32 87 33 10 10",
    "sg:postcode":"4840",
    "sg:province":"Li\u00e8ge",
    "sg:tags":[
        "riding",
        "school"
    ],
    "wof:name":"Centre Equestre Euregio",
    "wof:placetype":"venue"
},
  "geometry": {"coordinates":[5.9500770569,50.6596946716],"type":"Point"}
}