{
  "type": "Feature",
  "properties": {
    "addr:full":"Dorpsstraat 102 Knokke-heist West-Vlaanderen 8300",
    "addr:housenumber":"102",
    "addr:postcode":"8300",
    "addr:street":"Dorpsstraat",
    "iso:country":"BE",
    "sg:address":"Dorpsstraat 102",
    "sg:city":"Knokke-heist",
    "sg:classifiers":[
        {
            "category":"Personal",
            "subcategory":"Beauty Salon",
            "type":"Services"
        }
    ],
    "sg:phone":"+32 50 60 76 40",
    "sg:postcode":"8300",
    "sg:province":"West-Vlaanderen",
    "sg:tags":[
        "de",
        "coiffure"
    ],
    "wof:name":"Julien Debrabander",
    "wof:placetype":"venue"
},
  "geometry": {"coordinates":[3.287694931,51.3467254639],"type":"Point"}
}