{
  "type": "Feature",
  "properties": {
    "addr:full":"Rue Du Sablon 55 Bastogne Luxembourg 6600",
    "addr:housenumber":"55",
    "addr:postcode":"6600",
    "addr:street":"Rue Du Sablon",
    "iso:country":"BE",
    "sg:address":"Rue Du Sablon 55",
    "sg:city":"Bastogne",
    "sg:classifiers":[
        {
            "category":"Insurance",
            "subcategory":"Insurance Agent",
            "type":"Services"
        }
    ],
    "sg:phone":"+32 61 21 87 05",
    "sg:postcode":"6600",
    "sg:province":"Luxembourg",
    "sg:tags":[
        "verzekeringsmakelaars",
        "expert"
    ],
    "wof:name":"Les Assurances F\u00c9d\u00c9rales",
    "wof:placetype":"venue"
},
  "geometry": {"coordinates":[5.7176032066,50.0021781921],"type":"Point"}
}