{
  "type": "Feature",
  "properties": {
    "iso:country":"BE",
    "sg:address":"Chauss\u00c9e D'alsemberg 497",
    "sg:city":"Ukkel",
    "sg:classifiers":[
        {
            "category":"Home & Garden",
            "subcategory":"Furniture",
            "type":"Retail Goods"
        }
    ],
    "sg:phone":"+32 2 343 09 08",
    "sg:postcode":"1180",
    "sg:province":"Bruxelles-Capitale",
    "sg:tags":[
        "fab",
        "meubelen",
        "diverse"
    ],
    "wof:name":"Bostandjis M",
    "wof:placetype":"venue"
},
  "geometry": {"coordinates":[4.3377418518,50.8111724854],"type":"Point"}
}