{
  "type": "Feature",
  "properties": {
    "addr:full":"Rue De Baud\u00c9mont 4 Ittre Brabant Wallon 1460",
    "addr:housenumber":"4;1460",
    "addr:street":"Rue De Baude\u0301Mont",
    "iso:country":"BE",
    "sg:address":"Rue De Baud\u00c9mont 4",
    "sg:city":"Ittre",
    "sg:orig_category":"Enseignement maternel and primaire",
    "sg:phone":"+32 67 64 71 22",
    "sg:postcode":"1460",
    "sg:province":"Brabant Wallon",
    "wof:name":"Ecole Fond. Communale",
    "wof:placetype":"venue"
},
  "geometry": {"coordinates":[4.2671108246,50.6487617493],"type":"Point"}
}