{
  "type": "Feature",
  "properties": {
    "addr:full":"Rue De Namur 66 Brussel/bruxelles Bruxelles-Capitale 1000",
    "addr:housenumber":"66",
    "addr:postcode":"1000",
    "addr:street":"Rue De Namur;/",
    "iso:country":"BE",
    "sg:address":"Rue De Namur 66",
    "sg:city":"Brussel/bruxelles",
    "sg:classifiers":[
        {
            "category":"Shopping",
            "subcategory":"Clothing, Apparel, & Fashions",
            "type":"Retail Goods"
        }
    ],
    "sg:phone":"+32 2 502 14 72",
    "sg:postcode":"1000",
    "sg:province":"Bruxelles-Capitale",
    "sg:tags":[
        "v\u00eatements",
        "pour",
        "dame"
    ],
    "wof:name":"Queen\u00b4s City",
    "wof:placetype":"venue"
},
  "geometry": {"coordinates":[4.3607378006,50.8397369385],"type":"Point"}
}