{
  "type": "Feature",
  "properties": {
    "addr:full":"Avenue Everard 18 Vorst/forest Bruxelles-Capitale 1190",
    "addr:housenumber":"18",
    "addr:postcode":"1190",
    "addr:street":"Avenue Everard;/ Forest",
    "iso:country":"BE",
    "sg:address":"Avenue Everard 18",
    "sg:city":"Vorst/forest",
    "sg:orig_category":"Herstelling leer and schoeisel",
    "sg:phone":"+32 2 346 82 63",
    "sg:postcode":"1190",
    "sg:province":"Bruxelles-Capitale",
    "wof:name":"De Geyndt",
    "wof:placetype":"venue"
},
  "geometry": {"coordinates":[4.3383002281,50.816204071],"type":"Point"}
}