{
  "type": "Feature",
  "properties": {
    "iso:country":"BE",
    "sg:address":"Jan Hammeneckerstraat 46",
    "sg:city":"Meise (wolvertem)",
    "sg:classifiers":[
        {
            "category":"Health Services",
            "subcategory":"Doctor",
            "type":"Services"
        }
    ],
    "sg:phone":"+32 52 30 46 07",
    "sg:postcode":"1861",
    "sg:province":"Vlaams-Brabant",
    "sg:tags":[
        "medicinephysicians",
        "surgeon"
    ],
    "wof:name":"Leroy G",
    "wof:placetype":"venue"
},
  "geometry": {"coordinates":[4.3234472275,50.9915733337],"type":"Point"}
}