{
  "type": "Feature",
  "properties": {
    "addr:full":"Oude Bellegemstraat 113 Zwevegem (groot) West-Vlaanderen 8550",
    "addr:housenumber":"113",
    "addr:postcode":"8550",
    "addr:street":"Oude Bellegemstraat;Groot West-Vlaanderen",
    "iso:country":"BE",
    "sg:address":"Oude Bellegemstraat 113",
    "sg:city":"Zwevegem (groot)",
    "sg:orig_category":"Travaux de pl\u00e2trage",
    "sg:phone":"+32 56 75 39 39",
    "sg:postcode":"8550",
    "sg:province":"West-Vlaanderen",
    "wof:name":"Verleye Bart",
    "wof:placetype":"venue"
},
  "geometry": {"coordinates":[3.3368439674,50.799911499],"type":"Point"}
}