{
  "type": "Feature",
  "properties": {
    "addr:full":"Rue Du Pont 22 Namur Namur 5000",
    "addr:housenumber":"22",
    "addr:postcode":"5000",
    "addr:street":"Rue Du Pont",
    "iso:country":"BE",
    "sg:address":"Rue Du Pont 22",
    "sg:city":"Namur",
    "sg:orig_category":"Speelgoed",
    "sg:phone":"+32 81 22 21 34",
    "sg:postcode":"5000",
    "sg:province":"Namur",
    "wof:name":"Boitatrain",
    "wof:placetype":"venue"
},
  "geometry": {"coordinates":[4.8677601814,50.4620704651],"type":"Point"}
}