{
  "type": "Feature",
  "properties": {
    "addr:full":"Chauss\u00e9e De Ramioul 223 Fl\u00e9malle (ivoz-ramet) Li\u00e8ge 4400",
    "addr:housenumber":"223",
    "addr:postcode":"4400",
    "addr:street":"Chausse\u0301E De Ramioul;Ivoz-Ramet",
    "iso:country":"BE",
    "sg:address":"Chauss\u00e9e De Ramioul 223",
    "sg:city":"Fl\u00e9malle (ivoz-ramet)",
    "sg:classifiers":[
        {
            "category":"Fast Food",
            "type":"Food & Drink"
        }
    ],
    "sg:phone":"+32 475 62 36 22",
    "sg:postcode":"4400",
    "sg:province":"Li\u00e8ge",
    "sg:tags":[
        "fried",
        "stand",
        "potato"
    ],
    "wof:name":"Frit'or",
    "wof:placetype":"venue"
},
  "geometry": {"coordinates":[5.4576430321,50.5693130493],"type":"Point"}
}