{
  "type": "Feature",
  "properties": {
    "addr:full":"Perronstraat 28 Bilzen Limburg 3740",
    "addr:housenumber":"28",
    "addr:postcode":"3740",
    "addr:street":"Perronstraat",
    "iso:country":"BE",
    "sg:address":"Perronstraat 28",
    "sg:city":"Bilzen",
    "sg:classifiers":[
        {
            "category":"Fast Food",
            "type":"Food & Drink"
        }
    ],
    "sg:phone":"+32 89 49 15 59",
    "sg:postcode":"3740",
    "sg:province":"Limburg",
    "sg:tags":[
        "meeneem",
        "restaurant"
    ],
    "wof:name":"Snackbar Het Pleintje",
    "wof:placetype":"venue"
},
  "geometry": {"coordinates":[5.5267901421,50.8879814148],"type":"Point"}
}