{
  "type": "Feature",
  "properties": {
    "addr:full":"Kloosterstraat 34 Diepenbeek Limburg 3590",
    "addr:housenumber":"34",
    "addr:postcode":"3590",
    "addr:street":"Kloosterstraat",
    "iso:country":"BE",
    "sg:address":"Kloosterstraat 34",
    "sg:city":"Diepenbeek",
    "sg:classifiers":[
        {
            "category":"Education",
            "subcategory":"School",
            "type":"Public Place"
        }
    ],
    "sg:phone":"+32 11 32 33 68",
    "sg:postcode":"3590",
    "sg:province":"Limburg",
    "sg:tags":[
        "primary"
    ],
    "wof:name":"Gemeentelijke Basisscholen",
    "wof:placetype":"venue"
},
  "geometry": {"coordinates":[5.4190487862,50.9055480957],"type":"Point"}
}