{
  "type": "Feature",
  "properties": {
    "addr:full":"Stevoortse Kiezel 424 Hasselt Limburg 3512",
    "addr:housenumber":"424",
    "addr:postcode":"3512",
    "addr:street":"Stevoortse Kiezel",
    "iso:country":"BE",
    "sg:address":"Stevoortse Kiezel 424",
    "sg:city":"Hasselt",
    "sg:orig_category":"Installation \u00e9lectrique r\u00e9sidentielle",
    "sg:phone":"+32 11 59 11 69",
    "sg:postcode":"3512",
    "sg:province":"Limburg",
    "wof:name":"Hiwo",
    "wof:placetype":"venue"
},
  "geometry": {"coordinates":[5.2498168945,50.9216804504],"type":"Point"}
}