{
  "type": "Feature",
  "properties": {
    "iso:country":"BE",
    "sg:address":"Rue Du Moulin 96",
    "sg:city":"Boussu",
    "sg:classifiers":[
        {
            "category":"Home & Garden",
            "subcategory":"Building Materials",
            "type":"Retail Goods"
        }
    ],
    "sg:phone":"+32 65 77 99 70",
    "sg:postcode":"7300",
    "sg:province":"Hainaut",
    "sg:tags":[
        "shutter"
    ],
    "wof:name":"Alutech Sprl",
    "wof:placetype":"venue"
},
  "geometry": {"coordinates":[3.7952899933,50.441734314],"type":"Point"}
}