{
  "type": "Feature",
  "properties": {
    "iso:country":"BE",
    "sg:address":"Rue Butay 13",
    "sg:city":"Neupre",
    "sg:orig_category":"Secr\u00e9tariats. Imprimeries and copyshops",
    "sg:phone":"+32 4 371 90 46",
    "sg:postcode":"4120",
    "sg:province":"Li\u00e8ge",
    "wof:name":"Buro-services",
    "wof:placetype":"venue"
},
  "geometry": {"coordinates":[5.4627561569,50.533946991],"type":"Point"}
}