{
  "type": "Feature",
  "properties": {
    "addr:full":"Route Provinciale 63a Tournai (mourcourt) Hainaut 7543",
    "addr:housenumber":"63a",
    "addr:postcode":"7543",
    "addr:street":"Route Provinciale",
    "iso:country":"BE",
    "sg:address":"Route Provinciale 63a",
    "sg:city":"Tournai (mourcourt)",
    "sg:classifiers":[
        {
            "category":"Retail",
            "subcategory":"Repair Shop",
            "type":"Services"
        }
    ],
    "sg:phone":"+32 69 23 32 56",
    "sg:postcode":"7543",
    "sg:province":"Hainaut",
    "sg:tags":[
        "-",
        "mainten",
        "watch",
        "clock"
    ],
    "wof:name":"Vanboquestal A",
    "wof:placetype":"venue"
},
  "geometry": {"coordinates":[3.4258489609,50.646484375],"type":"Point"}
}