{
  "type": "Feature",
  "properties": {
    "iso:country":"BE",
    "sg:address":"Rue De La Jonqui\u00c8re 12",
    "sg:city":"Aiseau-presles",
    "sg:orig_category":"Woningbouw",
    "sg:phone":"+32 71 38 63 15",
    "sg:postcode":"6250",
    "sg:province":"Hainaut",
    "wof:name":"Kosecki",
    "wof:placetype":"venue"
},
  "geometry": {"coordinates":[4.5466837883,50.4068183899],"type":"Point"}
}