{
  "type": "Feature",
  "properties": {
    "iso:country":"BE",
    "sg:address":"Quai De L'ambl\u00e8ve 6",
    "sg:city":"Sprimont",
    "sg:classifiers":[
        {
            "category":"Building & Trades",
            "subcategory":"Pest Control",
            "type":"Services"
        }
    ],
    "sg:phone":"+32 4 369 13 62",
    "sg:postcode":"4140",
    "sg:province":"Li\u00e8ge",
    "sg:tags":[
        "painting",
        "contractor"
    ],
    "wof:name":"Petit-jean D",
    "wof:placetype":"venue"
},
  "geometry": {"coordinates":[5.5908517838,50.4821739197],"type":"Point"}
}