{
  "type": "Feature",
  "properties": {
    "addr:full":"Mellestraat 461 Kortrijk (heule) West-Vlaanderen 8501",
    "addr:housenumber":"461",
    "addr:postcode":"8501",
    "addr:street":"Mellestraat",
    "iso:country":"BE",
    "sg:address":"Mellestraat 461",
    "sg:city":"Kortrijk (heule)",
    "sg:classifiers":[
        {
            "category":"Home & Garden",
            "subcategory":"Building Materials",
            "type":"Retail Goods"
        }
    ],
    "sg:phone":"+32 56 37 31 49",
    "sg:postcode":"8501",
    "sg:province":"West-Vlaanderen",
    "sg:tags":[
        "veranda"
    ],
    "wof:name":"Verandas Deceuninck",
    "wof:placetype":"venue"
},
  "geometry": {"coordinates":[3.2132270336,50.8720741272],"type":"Point"}
}