{
  "type": "Feature",
  "properties": {
    "iso:country":"BE",
    "sg:address":"Rue Hamoir 183",
    "sg:city":"La Louvi\u00c8re (groot)",
    "sg:classifiers":[
        {
            "category":"Restaurant",
            "type":"Food & Drink"
        }
    ],
    "sg:phone":"+32 64 84 97 97",
    "sg:postcode":"7100",
    "sg:province":"Hainaut",
    "wof:name":"Il Valentino",
    "wof:placetype":"venue"
},
  "geometry": {"coordinates":[4.1955561638,50.4750137329],"type":"Point"}
}