{
  "type": "Feature",
  "properties": {
    "addr:full":"Rue Des Quatre Vents 110 Sint-jans-molenbeek/molenbeek-saint-jean Bruxelles-Capitale 1080",
    "addr:housenumber":"110",
    "addr:postcode":"1080",
    "addr:street":"Rue Des Quatre Vents",
    "iso:country":"BE",
    "sg:address":"Rue Des Quatre Vents 110",
    "sg:city":"Sint-jans-molenbeek/molenbeek-saint-jean",
    "sg:orig_category":"Pain, p\u00e2tisseries and confiseries",
    "sg:phone":"+32 2 411 52 33",
    "sg:postcode":"1080",
    "sg:province":"Bruxelles-Capitale",
    "wof:name":"P\u00c2tisserie Laroussi",
    "wof:placetype":"venue"
},
  "geometry": {"coordinates":[4.3308639526,50.8525352478],"type":"Point"}
}