{
  "type": "Feature",
  "properties": {
    "iso:country":"BE",
    "sg:address":"Houtemstraat 31",
    "sg:city":"Veurne (houtem)",
    "sg:classifiers":[
        {
            "category":"Building & Trades",
            "subcategory":"Pest Control",
            "type":"Services"
        }
    ],
    "sg:phone":"+32 58 29 91 84",
    "sg:postcode":"8630",
    "sg:province":"West-Vlaanderen",
    "sg:tags":[
        "painting",
        "contractor"
    ],
    "wof:name":"Jonckheere J",
    "wof:placetype":"venue"
},
  "geometry": {"coordinates":[2.6412730217,51.0056838989],"type":"Point"}
}