{
  "type": "Feature",
  "properties": {
    "addr:full":"Place Albert Ier 8 Charleroi Hainaut 6020",
    "addr:housenumber":"8",
    "addr:postcode":"6020",
    "addr:street":"Place Albert Ier;Hainaut",
    "iso:country":"BE",
    "sg:address":"Place Albert Ier 8",
    "sg:city":"Charleroi",
    "sg:orig_category":"Woningbouw",
    "sg:phone":"+32 71 30 00 73",
    "sg:postcode":"6020",
    "sg:province":"Hainaut",
    "wof:name":"Mario D'andrea",
    "wof:placetype":"venue"
},
  "geometry": {"coordinates":[4.4279541969,50.4147758484],"type":"Point"}
}