{
  "type": "Feature",
  "properties": {
    "iso:country":"BE",
    "sg:address":"Lange Zandstraat 35",
    "sg:city":"Mechelen",
    "sg:orig_category":"Centres de relaxation and bien-\u00eatre",
    "sg:phone":"+32 15 20 98 64",
    "sg:postcode":"2800",
    "sg:province":"Antwerpen",
    "wof:name":"Gezondheidscentrum Shiatsulessen En Priv\u00c9 Sauna",
    "wof:placetype":"venue"
},
  "geometry": {"coordinates":[4.4962511063,51.0445022583],"type":"Point"}
}