{
  "type": "Feature",
  "properties": {
    "iso:country":"BE",
    "sg:address":"Antwerpsesteenweg 354",
    "sg:city":"Gent",
    "sg:orig_category":"Pharmaciens",
    "sg:phone":"+32 9 228 39 02",
    "sg:postcode":"9040",
    "sg:province":"Oost-Vlaanderen",
    "wof:name":"Dirk Daemers",
    "wof:placetype":"venue"
},
  "geometry": {"coordinates":[3.7488250732,51.0612754822],"type":"Point"}
}