{
  "type": "Feature",
  "properties": {
    "addr:full":"Sas Vi 14 Mol Antwerpen 2400",
    "addr:housenumber":"14",
    "addr:postcode":"2400",
    "addr:street":"Sas Vi",
    "iso:country":"BE",
    "sg:address":"Sas Vi 14",
    "sg:city":"Mol",
    "sg:classifiers":[
        {
            "category":"Ice Cream",
            "type":"Food & Drink"
        }
    ],
    "sg:phone":"+32 14 31 36 07",
    "sg:postcode":"2400",
    "sg:province":"Antwerpen",
    "wof:name":"Breykenshoeve",
    "wof:placetype":"venue"
},
  "geometry": {"coordinates":[5.0938749313,51.2236251831],"type":"Point"}
}