{
  "type": "Feature",
  "properties": {
    "iso:country":"BE",
    "sg:address":"Dorp 89",
    "sg:city":"Zoersel",
    "sg:classifiers":[
        {
            "category":"Structure",
            "subcategory":"Office Building",
            "type":"Public Place"
        }
    ],
    "sg:phone":"+32 3 311 73 79",
    "sg:postcode":"2980",
    "sg:province":"Antwerpen",
    "sg:tags":[
        "drawing"
    ],
    "wof:name":"Vardis Bvba",
    "wof:placetype":"venue"
},
  "geometry": {"coordinates":[4.7127141953,51.2693939209],"type":"Point"}
}