{
  "type": "Feature",
  "properties": {
    "iso:country":"BE",
    "sg:address":"Terkamerenstraat 237",
    "sg:city":"Sint-pieters-woluwe/woluwe-saint-pierre",
    "sg:orig_category":"Reclamebureaus",
    "sg:phone":"+32 2 771 88 75",
    "sg:postcode":"1150",
    "sg:province":"Bruxelles-Capitale",
    "wof:name":"De Simpelaere En Co",
    "wof:placetype":"venue"
},
  "geometry": {"coordinates":[4.4152760506,50.8382835388],"type":"Point"}
}