{
  "type": "Feature",
  "properties": {
    "iso:country":"BE",
    "sg:address":"Rue De La Station 2",
    "sg:city":"Baelen (membach)",
    "sg:classifiers":[
        {
            "category":"Retail",
            "subcategory":"Auto Repair",
            "type":"Services"
        }
    ],
    "sg:phone":"+32 87 74 26 28",
    "sg:postcode":"4837",
    "sg:province":"Li\u00e8ge",
    "sg:tags":[
        "automobile-body"
    ],
    "wof:name":"Peiffer A & Fils Sa",
    "wof:placetype":"venue"
},
  "geometry": {"coordinates":[5.998003006,50.6137008667],"type":"Point"}
}