{
  "type": "Feature",
  "properties": {
    "addr:full":"Turnhoutsebaan 5 Sh Wijnegem Antwerpen 2110",
    "addr:housenumber":"5",
    "addr:postcode":"2110",
    "addr:street":"Turnhoutsebaan",
    "iso:country":"BE",
    "sg:address":"Turnhoutsebaan 5 Sh",
    "sg:city":"Wijnegem",
    "sg:orig_category":"Telecommunicatieapparaten",
    "sg:phone":"+32 800 22 800",
    "sg:postcode":"2110",
    "sg:province":"Antwerpen",
    "wof:name":"Teleboetiek",
    "wof:placetype":"venue"
},
  "geometry": {"coordinates":[4.5248470306,51.2279434204],"type":"Point"}
}