{
  "type": "Feature",
  "properties": {
    "addr:full":"Grote Baan 399 Hulshout Antwerpen 2235",
    "addr:housenumber":"399",
    "addr:postcode":"2235",
    "addr:street":"Grote Baan",
    "iso:country":"BE",
    "sg:address":"Grote Baan 399",
    "sg:city":"Hulshout",
    "sg:classifiers":[
        {
            "category":"Insurance",
            "subcategory":"Insurance Agent",
            "type":"Services"
        }
    ],
    "sg:phone":"+32 16 69 82 82",
    "sg:postcode":"2235",
    "sg:province":"Antwerpen",
    "sg:tags":[
        "broker"
    ],
    "wof:name":"Cams-cle",
    "wof:placetype":"venue"
},
  "geometry": {"coordinates":[4.8237271309,51.0707130432],"type":"Point"}
}