{
  "type": "Feature",
  "properties": {
    "addr:full":"Rue Des Pr\u00c9s Communs 59b13 Brussel/bruxelles Bruxelles-Capitale 1120",
    "addr:housenumber":"59b13",
    "addr:postcode":"1120",
    "addr:street":"Rue Des Pre\u0301S Communs;/",
    "iso:country":"BE",
    "sg:address":"Rue Des Pr\u00c9s Communs 59b13",
    "sg:city":"Brussel/bruxelles",
    "sg:orig_category":"Animations diverses",
    "sg:phone":"+32 2 241 33 19",
    "sg:postcode":"1120",
    "sg:province":"Bruxelles-Capitale",
    "wof:name":"Attilio",
    "wof:placetype":"venue"
},
  "geometry": {"coordinates":[4.3834347725,50.8900794983],"type":"Point"}
}