{
  "type": "Feature",
  "properties": {
    "addr:full":"Brazilianenstraat 27 Antwerpen Antwerpen 2040",
    "addr:housenumber":"27",
    "addr:postcode":"2040",
    "addr:street":"Brazilianenstraat",
    "iso:country":"BE",
    "sg:address":"Brazilianenstraat 27",
    "sg:city":"Antwerpen",
    "sg:classifiers":[
        {
            "category":"Freight",
            "type":"Transportation"
        }
    ],
    "sg:phone":"+32 3 568 83 10",
    "sg:postcode":"2040",
    "sg:province":"Antwerpen",
    "sg:tags":[
        "-",
        "transport"
    ],
    "wof:name":"Stari Trans",
    "wof:placetype":"venue"
},
  "geometry": {"coordinates":[4.3299050331,51.3621749878],"type":"Point"}
}