{
  "type": "Feature",
  "properties": {
    "addr:full":"Rue Dos-fanchon 4 Li\u00c8ge Li\u00e8ge 4020",
    "addr:housenumber":"4",
    "addr:postcode":"4020",
    "addr:street":"Rue Dos-Fanchon",
    "iso:country":"BE",
    "sg:address":"Rue Dos-fanchon 4",
    "sg:city":"Li\u00c8ge",
    "sg:orig_category":"Schoonmaakbedrijven and ongediertebestrijding Wasserijen, Reiniging and Droogkuis",
    "sg:phone":"+32 4 342 43 03",
    "sg:postcode":"4020",
    "sg:province":"Li\u00e8ge",
    "wof:name":"Peters",
    "wof:placetype":"venue"
},
  "geometry": {"coordinates":[5.5888490677,50.6460762024],"type":"Point"}
}