{
  "type": "Feature",
  "properties": {
    "iso:country":"BE",
    "sg:address":"Twaalfkameren 17",
    "sg:city":"Gent",
    "sg:classifiers":[
        {
            "category":"Professional",
            "subcategory":"Lawyer & Legal Services",
            "type":"Services"
        }
    ],
    "sg:phone":"+32 9 223 50 10",
    "sg:postcode":"9000",
    "sg:province":"Oost-Vlaanderen",
    "wof:name":"Vancaeneghem Philip",
    "wof:placetype":"venue"
},
  "geometry": {"coordinates":[3.7147459984,51.0500411987],"type":"Point"}
}