{
  "type": "Feature",
  "properties": {
    "iso:country":"BE",
    "sg:address":"Rue Wiston Churchill 103",
    "sg:city":"Courcelles",
    "sg:orig_category":"Verlichting and huishoudartikelen",
    "sg:phone":"+32 71 45 21 74",
    "sg:postcode":"6180",
    "sg:province":"Hainaut",
    "wof:name":"Dewals Guy",
    "wof:placetype":"venue"
},
  "geometry": {"coordinates":[4.3856711388,50.461391449],"type":"Point"}
}