{
  "type": "Feature",
  "properties": {
    "iso:country":"BE",
    "sg:address":"Broeckstraat 37",
    "sg:city":"Gavere",
    "sg:orig_category":"Enseignement maternel and primaire",
    "sg:phone":"+32 9 384 17 55",
    "sg:postcode":"9890",
    "sg:province":"Oost-Vlaanderen",
    "wof:name":"Basisschool",
    "wof:placetype":"venue"
},
  "geometry": {"coordinates":[3.6581320763,50.9316177368],"type":"Point"}
}