{
  "type": "Feature",
  "properties": {
    "iso:country":"BE",
    "sg:address":"Brandenberg 17",
    "sg:city":"Grobbendonk",
    "sg:orig_category":"Eclairage et \u00e9quipements du foyer. Installation \u00e9lectrique r\u00e9sidentielle",
    "sg:phone":"+32 14 50 28 64",
    "sg:postcode":"2288",
    "sg:province":"Antwerpen",
    "wof:name":"Samco",
    "wof:placetype":"venue"
},
  "geometry": {"coordinates":[4.7320809364,51.1657028198],"type":"Point"}
}