{
  "type": "Feature",
  "properties": {
    "addr:full":"Geldenaaksebaan 460 Leuven (heverlee) Vlaams-Brabant 3001",
    "addr:housenumber":"460",
    "addr:postcode":"3001",
    "addr:street":"Geldenaaksebaan",
    "iso:country":"BE",
    "sg:address":"Geldenaaksebaan 460",
    "sg:city":"Leuven (heverlee)",
    "sg:classifiers":[
        {
            "category":"Professional",
            "subcategory":"Management & Consulting",
            "type":"Services"
        }
    ],
    "sg:phone":"+32 16 40 10 50",
    "sg:postcode":"3001",
    "sg:province":"Vlaams-Brabant",
    "sg:tags":[
        "consultant"
    ],
    "wof:name":"Athena Consulting Nv",
    "wof:placetype":"venue"
},
  "geometry": {"coordinates":[4.7237157822,50.8483390808],"type":"Point"}
}