{
  "type": "Feature",
  "properties": {
    "addr:full":"Koning Albertln 264 Lanaken Limburg 3620",
    "addr:housenumber":"264",
    "addr:postcode":"3620",
    "addr:street":"Koning Albertln",
    "iso:country":"BE",
    "sg:address":"Koning Albertln 264",
    "sg:city":"Lanaken",
    "sg:classifiers":[
        {
            "category":"Travel",
            "subcategory":"Hotels & Motels",
            "type":"Entertainment"
        }
    ],
    "sg:phone":"+32 89 72 28 22",
    "sg:postcode":"3620",
    "sg:province":"Limburg",
    "sg:tags":[
        "hotels",
        "business",
        "restaurant"
    ],
    "wof:name":"Europ Hotel Nv",
    "wof:placetype":"venue"
},
  "geometry": {"coordinates":[5.6717271805,50.8963470459],"type":"Point"}
}