{
  "type": "Feature",
  "properties": {
    "iso:country":"BE",
    "sg:address":"Chemin Champ De L\u00b4eglise 45",
    "sg:city":"Sint-genesius-rode/rhode-saint-gen\u00c8se",
    "sg:orig_category":"Electrom\u00e9nager, t\u00e9l\u00e9visions and radios. Installation \u00e9lectrique r\u00e9sidentielle. Installation \u00e9lectriq",
    "sg:phone":"+32 2 380 36 81",
    "sg:postcode":"1640",
    "sg:province":"Vlaams-Brabant",
    "wof:name":"Vandendries & Zn",
    "wof:placetype":"venue"
},
  "geometry": {"coordinates":[4.3304300308,50.7353096008],"type":"Point"}
}