{
  "type": "Feature",
  "properties": {
    "addr:full":"J-p Minckelerstraat 130 Leuven Vlaams-Brabant 3000",
    "addr:housenumber":"130",
    "addr:postcode":"3000",
    "addr:street":"Minckelerstraat",
    "iso:country":"BE",
    "sg:address":"J-p Minckelerstraat 130",
    "sg:city":"Leuven",
    "sg:classifiers":[
        {
            "category":"Building & Trades",
            "subcategory":"Plumbing",
            "type":"Services"
        }
    ],
    "sg:phone":"+32 16 22 00 00",
    "sg:postcode":"3000",
    "sg:province":"Vlaams-Brabant",
    "sg:tags":[
        "diver",
        "commerce",
        "gr",
        "pour",
        "equipement"
    ],
    "wof:name":"Koffie Buccauw",
    "wof:placetype":"venue"
},
  "geometry": {"coordinates":[4.7045631409,50.8848228455],"type":"Point"}
}