{
  "type": "Feature",
  "properties": {
    "iso:country":"BE",
    "sg:address":"Opstal 5",
    "sg:city":"Rijkevorsel",
    "sg:orig_category":"Groententeelt",
    "sg:phone":"+32 3 311 68 02",
    "sg:postcode":"2310",
    "sg:province":"Antwerpen",
    "wof:name":"Willy Hermans",
    "wof:placetype":"venue"
},
  "geometry": {"coordinates":[4.776515007,51.3369827271],"type":"Point"}
}