{
  "type": "Feature",
  "properties": {
    "addr:full":"Onze Lieve Vrouwstraat 11 Bilzen Limburg 3740",
    "addr:housenumber":"11",
    "addr:postcode":"3740",
    "addr:street":"Onze Lieve Vrouwstraat",
    "iso:country":"BE",
    "sg:address":"Onze Lieve Vrouwstraat 11",
    "sg:city":"Bilzen",
    "sg:orig_category":"Dameskledingzaken",
    "sg:phone":"+32 89 41 31 00",
    "sg:postcode":"3740",
    "sg:province":"Limburg",
    "wof:name":"Tema",
    "wof:placetype":"venue"
},
  "geometry": {"coordinates":[5.5167970657,50.8701057434],"type":"Point"}
}