{
  "type": "Feature",
  "properties": {
    "addr:full":"Rue Cadu 5 Celles Hainaut 7760",
    "addr:housenumber":"5",
    "addr:postcode":"7760",
    "addr:street":"Rue Cadu",
    "iso:country":"BE",
    "sg:address":"Rue Cadu 5",
    "sg:city":"Celles",
    "sg:orig_category":"Epiceries",
    "sg:phone":"+32 69 45 43 89",
    "sg:postcode":"7760",
    "sg:province":"Hainaut",
    "wof:name":"Alice Quivy",
    "wof:placetype":"venue"
},
  "geometry": {"coordinates":[3.4037621021,50.7243995667],"type":"Point"}
}