{
  "type": "Feature",
  "properties": {
    "iso:country":"BE",
    "sg:address":"Place De La Cath\u00c9drale 14",
    "sg:city":"Li\u00c8ge",
    "sg:orig_category":"Bijouteries and horlogeries",
    "sg:phone":"+32 4 223 70 67",
    "sg:postcode":"4000",
    "sg:province":"Li\u00e8ge",
    "wof:name":"Bijouterie Pierre Carat",
    "wof:placetype":"venue"
},
  "geometry": {"coordinates":[5.5708518028,50.6406822205],"type":"Point"}
}