{
  "type": "Feature",
  "properties": {
    "addr:full":"Rue Des Fr\u00e8res Taymans 34 Box 1 Tubize Brabant Wallon 1480",
    "addr:housenumber":"34;1",
    "addr:postcode":"1480",
    "addr:street":"Rue Des Fre\u0300Res Taymans;Box;Wallon",
    "iso:country":"BE",
    "sg:address":"Rue Des Fr\u00e8res Taymans 34 Box 1",
    "sg:city":"Tubize",
    "sg:classifiers":[
        {
            "category":"Professional",
            "subcategory":"Lawyer & Legal Services",
            "type":"Services"
        }
    ],
    "sg:phone":"+32 2 355 82 14",
    "sg:postcode":"1480",
    "sg:province":"Brabant Wallon",
    "wof:name":"Mahauden Stephane",
    "wof:placetype":"venue"
},
  "geometry": {"coordinates":[4.2064709663,50.6885070801],"type":"Point"}
}