{
  "type": "Feature",
  "properties": {
    "iso:country":"BE",
    "sg:address":"Rue Du Ch\u00c2teau 1",
    "sg:city":"Estinnes",
    "sg:orig_category":"Eleveurs and marchands de porcs",
    "sg:phone":"+32 64 77 11 39",
    "sg:postcode":"7120",
    "sg:province":"Hainaut",
    "wof:name":"Gerard Francois",
    "wof:placetype":"venue"
},
  "geometry": {"coordinates":[4.0823001862,50.3611907959],"type":"Point"}
}