{
  "type": "Feature",
  "properties": {
    "iso:country":"BE",
    "sg:address":"Oudstrijderslaan 63",
    "sg:city":"Zoersel",
    "sg:orig_category":"Elektrische installaties voor woningen",
    "sg:phone":"+32 3 384 02 15",
    "sg:postcode":"2980",
    "sg:province":"Antwerpen",
    "wof:name":"Piet Van Mierlo",
    "wof:placetype":"venue"
},
  "geometry": {"coordinates":[4.6537308693,51.2605323792],"type":"Point"}
}