{
  "type": "Feature",
  "properties": {
    "addr:full":"Zwijnaardsesteenweg 429 Gent Oost-Vlaanderen 9000",
    "addr:housenumber":"429",
    "addr:postcode":"9000",
    "addr:street":"Zwijnaardsesteenweg;Oost-Vlaanderen",
    "iso:country":"BE",
    "sg:address":"Zwijnaardsesteenweg 429",
    "sg:city":"Gent",
    "sg:orig_category":"Solariums",
    "sg:phone":"+32 9 221 37 80",
    "sg:postcode":"9000",
    "sg:province":"Oost-Vlaanderen",
    "wof:name":"La Playa-zonnecenter",
    "wof:placetype":"venue"
},
  "geometry": {"coordinates":[3.7222321033,51.0274543762],"type":"Point"}
}