{
  "type": "Feature",
  "properties": {
    "addr:full":"Grotekievit 10 Geel Antwerpen 2440",
    "addr:housenumber":"10",
    "addr:postcode":"2440",
    "addr:street":"Grotekievit",
    "iso:country":"BE",
    "sg:address":"Grotekievit 10",
    "sg:city":"Geel",
    "sg:orig_category":"Eleveurs and marchands de porcs",
    "sg:phone":"+32 14 85 26 90",
    "sg:postcode":"2440",
    "sg:province":"Antwerpen",
    "wof:name":"Bart Smeyers",
    "wof:placetype":"venue"
},
  "geometry": {"coordinates":[5.0211391449,51.223236084],"type":"Point"}
}