{
  "type": "Feature",
  "properties": {
    "iso:country":"BE",
    "sg:address":"Rue Vaux 18",
    "sg:city":"Vis\u00e9 (lixhe)",
    "sg:classifiers":[
        {
            "category":"Shopping",
            "subcategory":"Computers & Home Electronics",
            "type":"Retail Goods"
        }
    ],
    "sg:phone":"+32 4 379 87 84",
    "sg:postcode":"4600",
    "sg:province":"Li\u00e8ge",
    "sg:tags":[
        "personal",
        "-",
        "processing",
        "data"
    ],
    "wof:name":"I.m. Graphic",
    "wof:placetype":"venue"
},
  "geometry": {"coordinates":[5.6952648163,50.7378158569],"type":"Point"}
}