{
  "type": "Feature",
  "properties": {
    "addr:full":"Eekhoornlaan 10 Schilde ('s Gravenwezel) Antwerpen 2970",
    "addr:housenumber":"10",
    "addr:postcode":"2970",
    "addr:street":"Eekhoornlaan;S",
    "iso:country":"BE",
    "sg:address":"Eekhoornlaan 10",
    "sg:city":"Schilde ('s Gravenwezel)",
    "sg:classifiers":[
        {
            "category":"Health Services",
            "subcategory":"Health Practitioner",
            "type":"Services"
        }
    ],
    "sg:phone":"+32 498 69 12 40",
    "sg:postcode":"2970",
    "sg:province":"Antwerpen",
    "sg:tags":[
        "psychologist"
    ],
    "wof:name":"Vermeiren M",
    "wof:placetype":"venue"
},
  "geometry": {"coordinates":[4.5567908287,51.2525444031],"type":"Point"}
}