{
  "type": "Feature",
  "properties": {
    "addr:full":"Dorpsplein 41 Ledegem West-Vlaanderen 8880",
    "addr:housenumber":"41",
    "addr:postcode":"8880",
    "addr:street":"Dorpsplein",
    "iso:country":"BE",
    "sg:address":"Dorpsplein 41",
    "sg:city":"Ledegem",
    "sg:orig_category":"Banken and kredietinstellingen",
    "sg:phone":"+32 56 50 90 73",
    "sg:postcode":"8880",
    "sg:province":"West-Vlaanderen",
    "wof:name":"Kbc",
    "wof:placetype":"venue"
},
  "geometry": {"coordinates":[3.178178072,50.8771743774],"type":"Point"}
}