{
  "type": "Feature",
  "properties": {
    "addr:full":"Vinkenlaan 17 Sint-genesius-rode Vlaams-Brabant 1640",
    "addr:housenumber":"17",
    "addr:postcode":"1640",
    "addr:street":"Vinkenlaan",
    "iso:country":"BE",
    "sg:address":"Vinkenlaan 17",
    "sg:city":"Sint-genesius-rode",
    "sg:orig_category":"Diverse bedrijfsbeheeradviesbureaus",
    "sg:phone":"+32 2 380 45 89",
    "sg:postcode":"1640",
    "sg:province":"Vlaams-Brabant",
    "wof:name":"J.k. Services",
    "wof:placetype":"venue"
},
  "geometry": {"coordinates":[4.3588938713,50.7368202209],"type":"Point"}
}