{
  "type": "Feature",
  "properties": {
    "addr:full":"Schoolstraat 22 Oosterzele Oost-Vlaanderen 9860",
    "addr:housenumber":"22",
    "addr:postcode":"9860",
    "addr:street":"Schoolstraat;Oost-Vlaanderen",
    "iso:country":"BE",
    "sg:address":"Schoolstraat 22",
    "sg:city":"Oosterzele",
    "sg:orig_category":"Travaux de pl\u00e2trage. Construction de maisons. Travaux de finition and nettoyage de b\u00e2timents. Rev\u00eate",
    "sg:phone":"+32 9 362 10 55",
    "sg:postcode":"9860",
    "sg:province":"Oost-Vlaanderen",
    "wof:name":"I.b.t.",
    "wof:placetype":"venue"
},
  "geometry": {"coordinates":[3.8177230358,50.9714279175],"type":"Point"}
}