{
  "type": "Feature",
  "properties": {
    "addr:full":"Herentalsebaan 13 Ranst Antwerpen 2520",
    "addr:housenumber":"13",
    "addr:postcode":"2520",
    "addr:street":"Herentalsebaan",
    "iso:country":"BE",
    "sg:address":"Herentalsebaan 13",
    "sg:city":"Ranst",
    "sg:classifiers":[
        {
            "category":"Farming",
            "subcategory":"Crops",
            "type":"Manufacturing & Wholesale Goods"
        }
    ],
    "sg:phone":"+32 3 485 65 35",
    "sg:postcode":"2520",
    "sg:province":"Antwerpen",
    "sg:tags":[
        "vegetable",
        "fruit",
        "-",
        "grower"
    ],
    "wof:name":"Van Eccelpoel G",
    "wof:placetype":"venue"
},
  "geometry": {"coordinates":[4.5552859306,51.1803131104],"type":"Point"}
}