{
  "type": "Feature",
  "properties": {
    "addr:full":"Antwerpsedreef 2 Zoersel Antwerpen 2980",
    "addr:housenumber":"2",
    "addr:postcode":"2980",
    "addr:street":"Antwerpsedreef",
    "iso:country":"BE",
    "sg:address":"Antwerpsedreef 2",
    "sg:city":"Zoersel",
    "sg:orig_category":"Pharmaciens",
    "sg:phone":"+32 3 384 05 17",
    "sg:postcode":"2980",
    "sg:province":"Antwerpen",
    "wof:name":"Brigitte Baeyens",
    "wof:placetype":"venue"
},
  "geometry": {"coordinates":[4.6577911377,51.2672348022],"type":"Point"}
}