{
  "type": "Feature",
  "properties": {
    "iso:country":"BE",
    "sg:address":"Route De Beaumont 11",
    "sg:city":"Quevy",
    "sg:orig_category":"Metaalafval, schrootrecyclage and sloperijen Onderdelen and accessoires voor auto's Voertuigen",
    "sg:phone":"+32 65 58 72 45",
    "sg:postcode":"7041",
    "sg:province":"Hainaut",
    "wof:name":"Auto Recup Bie",
    "wof:placetype":"venue"
},
  "geometry": {"coordinates":[4.0316810608,50.3846588135],"type":"Point"}
}