{
  "type": "Feature",
  "properties": {
    "iso:country":"BE",
    "sg:address":"Paniswijerstraat 94",
    "sg:city":"Genk",
    "sg:classifiers":[
        {
            "category":"Manufacturing",
            "subcategory":"Motor Vehicles & Parts",
            "type":"Manufacturing & Wholesale Goods"
        }
    ],
    "sg:phone":"+32 89 32 88 50",
    "sg:postcode":"3600",
    "sg:province":"Limburg",
    "sg:tags":[
        "electromechanical",
        "component"
    ],
    "wof:name":"Src Devices Nv",
    "wof:placetype":"venue"
},
  "geometry": {"coordinates":[5.4738807678,50.938911438],"type":"Point"}
}