{
  "type": "Feature",
  "properties": {
    "iso:country":"BE",
    "sg:address":"Steenweg 732",
    "sg:city":"Denderleeuw",
    "sg:classifiers":[
        {
            "category":"Health Services",
            "subcategory":"Nursing And Care Facility",
            "type":"Services"
        }
    ],
    "sg:phone":"+32 53 67 33 76",
    "sg:postcode":"9470",
    "sg:province":"Oost-Vlaanderen",
    "sg:tags":[
        "home",
        "rest"
    ],
    "wof:name":"Rvt Ter Bake Cv",
    "wof:placetype":"venue"
},
  "geometry": {"coordinates":[4.0573301315,50.8716583252],"type":"Point"}
}