{
  "type": "Feature",
  "properties": {
    "iso:country":"BE",
    "sg:address":"Rue Du Chambge 12",
    "sg:city":"Tournai",
    "sg:classifiers":[
        {
            "category":"Organizations",
            "subcategory":"Community Association",
            "type":"Services"
        }
    ],
    "sg:phone":"+32 69 84 87 17",
    "sg:postcode":"7500",
    "sg:province":"Hainaut",
    "sg:tags":[
        "environment",
        "organisation",
        "-"
    ],
    "wof:name":"Plan\u00e8te-arbres",
    "wof:placetype":"venue"
},
  "geometry": {"coordinates":[3.390889883,50.6020812988],"type":"Point"}
}