{
  "type": "Feature",
  "properties": {
    "addr:full":"Nieuwenrodestraat 8 Meise Vlaams-Brabant 1861",
    "addr:housenumber":"8",
    "addr:postcode":"1861",
    "addr:street":"Nieuwenrodestraat",
    "iso:country":"BE",
    "sg:address":"Nieuwenrodestraat 8",
    "sg:city":"Meise",
    "sg:orig_category":"Produits surgel\u00e9s Gr",
    "sg:phone":"+32 15 71 32 18",
    "sg:postcode":"1861",
    "sg:province":"Vlaams-Brabant",
    "wof:name":"Desideer D'hollander",
    "wof:placetype":"venue"
},
  "geometry": {"coordinates":[4.3455629349,50.9852485657],"type":"Point"}
}