{
  "type": "Feature",
  "properties": {
    "iso:country":"BE",
    "sg:address":"Rue De Tirlemont 8ba",
    "sg:city":"Hannut",
    "sg:orig_category":"V\u00eatements",
    "sg:phone":"+32 19 51 48 00",
    "sg:postcode":"4280",
    "sg:province":"Li\u00e8ge",
    "wof:name":"Le Temple Du Cuir",
    "wof:placetype":"venue"
},
  "geometry": {"coordinates":[5.0768518448,50.6728515625],"type":"Point"}
}