{
  "type": "Feature",
  "properties": {
    "iso:country":"BE",
    "sg:address":"Louis Francklaan 19",
    "sg:city":"Sint-niklaas",
    "sg:orig_category":"Imprimeries and copyshops",
    "sg:phone":"+32 3 766 07 47",
    "sg:postcode":"9100",
    "sg:province":"Oost-Vlaanderen",
    "wof:name":"Flash Action",
    "wof:placetype":"venue"
},
  "geometry": {"coordinates":[4.1321492195,51.178440094],"type":"Point"}
}