{
  "type": "Feature",
  "properties": {
    "iso:country":"BE",
    "sg:address":"Olsenesteenweg 7",
    "sg:city":"Dentergem",
    "sg:orig_category":"Voertuigen",
    "sg:phone":"+32 51 63 72 17",
    "sg:postcode":"8720",
    "sg:province":"West-Vlaanderen",
    "wof:name":"Verlin Cars",
    "wof:placetype":"venue"
},
  "geometry": {"coordinates":[3.4481580257,50.9452857971],"type":"Point"}
}