{
  "type": "Feature",
  "properties": {
    "addr:full":"Theunis Veldstr L 17 Paal Limburg 3940",
    "addr:housenumber":"17",
    "addr:postcode":"3940",
    "addr:street":"L",
    "iso:country":"BE",
    "sg:address":"Theunis Veldstr L 17",
    "sg:city":"Paal",
    "sg:classifiers":[
        {
            "category":"Banks & Credit Unions",
            "subcategory":"Bank",
            "type":"Services"
        }
    ],
    "sg:phone":"+32 11 42 64 60",
    "sg:postcode":"3940",
    "sg:province":"Limburg",
    "wof:name":"Famibank",
    "wof:placetype":"venue"
},
  "geometry": {"coordinates":[145.14767456050001,-38.0995979309],"type":"Point"}
}