{
  "type": "Feature",
  "properties": {
    "addr:full":"Rue Gilbert-lepropre 22bb Gedinne Namur 5575",
    "addr:housenumber":"22bb",
    "addr:postcode":"5575",
    "addr:street":"Rue Gilbert-Lepropre",
    "iso:country":"BE",
    "sg:address":"Rue Gilbert-lepropre 22bb",
    "sg:city":"Gedinne",
    "sg:orig_category":"Boucheries",
    "sg:phone":"+32 61 58 89 37",
    "sg:postcode":"5575",
    "sg:province":"Namur",
    "wof:name":"Boucherie Clarinval H.",
    "wof:placetype":"venue"
},
  "geometry": {"coordinates":[4.8865947723,49.99243927],"type":"Point"}
}