{
  "type": "Feature",
  "properties": {
    "addr:full":"Chemin \u00c0 Baraques 83 Mons Hainaut 7000",
    "addr:housenumber":"83",
    "addr:postcode":"7000",
    "addr:street":"Chemin A\u0300 Baraques;Hainaut",
    "iso:country":"BE",
    "sg:address":"Chemin \u00c0 Baraques 83",
    "sg:city":"Mons",
    "sg:orig_category":"Sportclubs",
    "sg:phone":"+32 65 34 70 35",
    "sg:postcode":"7000",
    "sg:province":"Hainaut",
    "wof:name":"Les Ropieurs",
    "wof:placetype":"venue"
},
  "geometry": {"coordinates":[4.0016298294,50.4529800415],"type":"Point"}
}