{
  "type": "Feature",
  "properties": {
    "iso:country":"BE",
    "sg:address":"Chauss\u00e9e De Gand 397",
    "sg:city":"Bruxelles (molenbeek-saint-jean)",
    "sg:classifiers":[
        {
            "category":"Farming",
            "subcategory":"Fish & Marine Products",
            "type":"Manufacturing & Wholesale Goods"
        }
    ],
    "sg:phone":"+32 2 410 57 62",
    "sg:postcode":"1080",
    "sg:province":"Bruxelles-Capitale",
    "sg:tags":[
        "retail",
        "-",
        "shellfish"
    ],
    "wof:name":"Mareyeur (le)",
    "wof:placetype":"venue"
},
  "geometry": {"coordinates":[4.3206548691,50.8576316833],"type":"Point"}
}