{
  "type": "Feature",
  "properties": {
    "iso:country":"BE",
    "sg:address":"Rue Joseph Wauters 3ba",
    "sg:city":"Huy",
    "sg:orig_category":"Baby- and kinderkleding Dameskledingzaken Herenkledingzaken",
    "sg:phone":"+32 85 25 47 99",
    "sg:postcode":"4500",
    "sg:province":"Li\u00e8ge",
    "wof:name":"Promo Fashion",
    "wof:placetype":"venue"
},
  "geometry": {"coordinates":[5.2188777924,50.5230178833],"type":"Point"}
}