{
  "type": "Feature",
  "properties": {
    "iso:country":"BE",
    "sg:address":"Rue Sauveni\u00c8re 33",
    "sg:city":"Ciney",
    "sg:orig_category":"Installation de menuiserie en bois and plastique. Fabrication and montage de mobilier. Meubles D\u00e9tai",
    "sg:phone":"+32 83 21 33 13",
    "sg:postcode":"5590",
    "sg:province":"Namur",
    "wof:name":"Roland Gerard",
    "wof:placetype":"venue"
},
  "geometry": {"coordinates":[5.1076731682,50.2964477539],"type":"Point"}
}