{
  "type": "Feature",
  "properties": {
    "addr:full":"Munstersestraat 22bc Zutendaal Limburg 3690",
    "addr:housenumber":"22bc",
    "addr:postcode":"3690",
    "addr:street":"Munstersestraat",
    "iso:country":"BE",
    "sg:address":"Munstersestraat 22bc",
    "sg:city":"Zutendaal",
    "sg:orig_category":"Chemicali\u00ebn Gh",
    "sg:phone":"+32 89 61 28 22",
    "sg:postcode":"3690",
    "sg:province":"Limburg",
    "wof:name":"Ha-ra",
    "wof:placetype":"venue"
},
  "geometry": {"coordinates":[5.5518798828,50.9348297119],"type":"Point"}
}