{
  "type": "Feature",
  "properties": {
    "addr:full":"Potbeekstraat 2 Huldenberg Vlaams-Brabant 3040",
    "addr:housenumber":"2",
    "addr:postcode":"3040",
    "addr:street":"Potbeekstraat",
    "iso:country":"BE",
    "sg:address":"Potbeekstraat 2",
    "sg:city":"Huldenberg",
    "sg:orig_category":"M\u00e9decins and sp\u00e9cialistes",
    "sg:phone":"+32 16 47 36 65",
    "sg:postcode":"3040",
    "sg:province":"Vlaams-Brabant",
    "wof:name":"Suzanne Jonckheere",
    "wof:placetype":"venue"
},
  "geometry": {"coordinates":[4.6026492119,50.7484283447],"type":"Point"}
}