{
  "type": "Feature",
  "properties": {
    "iso:country":"BE",
    "sg:address":"Rue De La Tombelle 10",
    "sg:city":"Chatelet",
    "sg:classifiers":[
        {
            "category":"Personal",
            "subcategory":"Beauty Salon",
            "type":"Services"
        }
    ],
    "sg:phone":"+32 71 38 61 73",
    "sg:postcode":"6200",
    "sg:province":"Hainaut",
    "sg:tags":[
        "de",
        "coiffure"
    ],
    "wof:name":"Depasse C",
    "wof:placetype":"venue"
},
  "geometry": {"coordinates":[4.523293972,50.4049263],"type":"Point"}
}