{
  "type": "Feature",
  "properties": {
    "iso:country":"BE",
    "sg:address":"Kasteelstraat 110",
    "sg:city":"Tielt",
    "sg:orig_category":"Herstellingen and onderhoud van auto's",
    "sg:phone":"+32 51 40 55 40",
    "sg:postcode":"8700",
    "sg:province":"West-Vlaanderen",
    "wof:name":"Garage Cappelle",
    "wof:placetype":"venue"
},
  "geometry": {"coordinates":[3.320909977,50.9918212891],"type":"Point"}
}