{
  "type": "Feature",
  "properties": {
    "addr:full":"Provincieweg 440 Herzele Oost-Vlaanderen 9550",
    "addr:housenumber":"440",
    "addr:postcode":"9550",
    "addr:street":"Provincieweg;Oost-Vlaanderen",
    "iso:country":"BE",
    "sg:address":"Provincieweg 440",
    "sg:city":"Herzele",
    "sg:orig_category":"Banques and organismes de cr\u00e9dit",
    "sg:phone":"+32 9 361 11 53",
    "sg:postcode":"9550",
    "sg:province":"Oost-Vlaanderen",
    "wof:name":"Fortis",
    "wof:placetype":"venue"
},
  "geometry": {"coordinates":[3.8787400723,50.8998908997],"type":"Point"}
}