{
  "type": "Feature",
  "properties": {
    "addr:full":"Rue Hors Ch\u00e2teau 138 Li\u00e8ge 1 Li\u00e8ge 4000",
    "addr:housenumber":"138;1",
    "addr:postcode":"4000",
    "addr:street":"Rue Hors Cha\u0302Teau",
    "iso:country":"BE",
    "sg:address":"Rue Hors Ch\u00e2teau 138",
    "sg:city":"Li\u00e8ge 1",
    "sg:classifiers":[
        {
            "category":"Bars & Pubs",
            "type":"Food & Drink"
        }
    ],
    "sg:phone":"+32 4 223 21 72",
    "sg:postcode":"4000",
    "sg:province":"Li\u00e8ge",
    "wof:name":"Disco (le)",
    "wof:placetype":"venue"
},
  "geometry": {"coordinates":[5.5821328163,50.6480140686],"type":"Point"}
}