{
  "type": "Feature",
  "properties": {
    "iso:country":"BE",
    "sg:address":"Justus Lipsiuslaan 9",
    "sg:city":"Hasselt",
    "sg:orig_category":"Architectes",
    "sg:phone":"+32 11 22 98 10",
    "sg:postcode":"3500",
    "sg:province":"Limburg",
    "wof:name":"Jo Broekx",
    "wof:placetype":"venue"
},
  "geometry": {"coordinates":[5.3532629013,50.9265060425],"type":"Point"}
}