{
  "type": "Feature",
  "properties": {
    "addr:full":"Rue De Rodange 1 Aubange (athus) Luxembourg 6791",
    "addr:housenumber":"1",
    "addr:postcode":"6791",
    "addr:street":"Rue De Rodange",
    "iso:country":"BE",
    "sg:address":"Rue De Rodange 1",
    "sg:city":"Aubange (athus)",
    "sg:classifiers":[
        {
            "category":"Professional",
            "subcategory":"Computer Services",
            "type":"Services"
        }
    ],
    "sg:phone":"+32 63 38 34 04",
    "sg:postcode":"6791",
    "sg:province":"Luxembourg",
    "sg:tags":[
        "-",
        "processing",
        "data"
    ],
    "wof:name":"David Informatique",
    "wof:placetype":"venue"
},
  "geometry": {"coordinates":[5.8368301392,49.5627288818],"type":"Point"}
}