{
  "type": "Feature",
  "properties": {
    "iso:country":"BE",
    "sg:address":"Korbeekse Kerkstraat 22",
    "sg:city":"Bertem",
    "sg:orig_category":"Pleisterwerk",
    "sg:phone":"+32 16 47 70 44",
    "sg:postcode":"3060",
    "sg:province":"Vlaams-Brabant",
    "wof:name":"Maurice Meulemans",
    "wof:placetype":"venue"
},
  "geometry": {"coordinates":[4.6295080185,50.8614311218],"type":"Point"}
}