{
  "type": "Feature",
  "properties": {
    "addr:full":"Rue Des Puits 14bb Mons Hainaut 7011",
    "addr:housenumber":"14bb",
    "addr:postcode":"7011",
    "addr:street":"Rue Des Puits;Hainaut",
    "iso:country":"BE",
    "sg:address":"Rue Des Puits 14bb",
    "sg:city":"Mons",
    "sg:orig_category":"M\u00e9decins and sp\u00e9cialistes",
    "sg:phone":"+32 65 84 53 93",
    "sg:postcode":"7011",
    "sg:province":"Hainaut",
    "wof:name":"M.france Wilcox",
    "wof:placetype":"venue"
},
  "geometry": {"coordinates":[3.912539959,50.4712982178],"type":"Point"}
}