{
  "type": "Feature",
  "properties": {
    "iso:country":"BE",
    "sg:address":"Rue De Fosses 150a",
    "sg:city":"Sambreville (arsimont)",
    "sg:classifiers":[
        {
            "category":"Home & Garden",
            "subcategory":"Garden Supply",
            "type":"Retail Goods"
        }
    ],
    "sg:phone":"+32 71 74 38 72",
    "sg:postcode":"5060",
    "sg:province":"Namur",
    "wof:name":"Id\u00e9e Jardins",
    "wof:placetype":"venue"
},
  "geometry": {"coordinates":[4.6285200119,50.4448738098],"type":"Point"}
}