{
  "type": "Feature",
  "properties": {
    "iso:country":"BE",
    "sg:address":"Oude Ieperseweg 80",
    "sg:city":"Kortrijk (heule)",
    "sg:classifiers":[
        {
            "category":"Health Services",
            "subcategory":"Health Practitioner",
            "type":"Services"
        }
    ],
    "sg:phone":"+32 56 37 25 22",
    "sg:postcode":"8501",
    "sg:province":"West-Vlaanderen",
    "sg:tags":[
        "physiotherapist"
    ],
    "wof:name":"Tobler Jacques",
    "wof:placetype":"venue"
},
  "geometry": {"coordinates":[3.2318129539,50.8366699219],"type":"Point"}
}