{
  "type": "Feature",
  "properties": {
    "addr:full":"Wuipelstraat 21 Kluisbergen (ruien) Oost-Vlaanderen 9690",
    "addr:housenumber":"21",
    "addr:postcode":"9690",
    "addr:street":"Wuipelstraat",
    "iso:country":"BE",
    "sg:address":"Wuipelstraat 21",
    "sg:city":"Kluisbergen (ruien)",
    "sg:classifiers":[
        {
            "category":"Wholesale",
            "subcategory":"Beer",
            "type":"Manufacturing & Wholesale Goods"
        }
    ],
    "sg:phone":"+32 55 38 84 21",
    "sg:postcode":"9690",
    "sg:province":"Oost-Vlaanderen",
    "sg:tags":[
        "ale",
        "-"
    ],
    "wof:name":"Verdonckt",
    "wof:placetype":"venue"
},
  "geometry": {"coordinates":[3.4839339256,50.7696838379],"type":"Point"}
}