{
  "type": "Feature",
  "properties": {
    "addr:full":"Oneux 227 Comblain-au-pont Li\u00e8ge 4170",
    "addr:housenumber":"227",
    "addr:postcode":"4170",
    "addr:street":"Oneux",
    "iso:country":"BE",
    "sg:address":"Oneux 227",
    "sg:city":"Comblain-au-pont",
    "sg:orig_category":"Installatie van metalen schrijnwerk",
    "sg:phone":"+32 4 369 27 39",
    "sg:postcode":"4170",
    "sg:province":"Li\u00e8ge",
    "wof:name":"Daniel Degives",
    "wof:placetype":"venue"
},
  "geometry": {"coordinates":[5.5993251801,50.4717636108],"type":"Point"}
}