{
  "type": "Feature",
  "properties": {
    "iso:country":"BE",
    "sg:address":"Rue Regent 1bb",
    "sg:city":"Quevy",
    "sg:orig_category":"Woningbouw",
    "sg:phone":"+32 65 56 89 80",
    "sg:postcode":"7040",
    "sg:province":"Hainaut",
    "wof:name":"Mouton Daniel",
    "wof:placetype":"venue"
},
  "geometry": {"coordinates":[3.9495480061,50.3610687256],"type":"Point"}
}