{
  "type": "Feature",
  "properties": {
    "addr:full":"Rue De Tillier 39 Fernelmont Namur 5380",
    "addr:housenumber":"39",
    "addr:postcode":"5380",
    "addr:street":"Rue De Tillier",
    "iso:country":"BE",
    "sg:address":"Rue De Tillier 39",
    "sg:city":"Fernelmont",
    "sg:orig_category":"Fietsen Motorfietsen",
    "sg:phone":"+32 81 21 39 43",
    "sg:postcode":"5380",
    "sg:province":"Namur",
    "wof:name":"Garage Thomas",
    "wof:placetype":"venue"
},
  "geometry": {"coordinates":[4.9438800812,50.5282936096],"type":"Point"}
}