{
  "type": "Feature",
  "properties": {
    "addr:full":"Buitenstraat 15 Beveren (vrasene) Oost-Vlaanderen 9120",
    "addr:housenumber":"15",
    "addr:postcode":"9120",
    "addr:street":"Buitenstraat",
    "iso:country":"BE",
    "sg:address":"Buitenstraat 15",
    "sg:city":"Beveren (vrasene)",
    "sg:classifiers":[
        {
            "category":"Utilities",
            "subcategory":"Recycling",
            "type":"Services"
        }
    ],
    "sg:phone":"+32 3 775 98 88",
    "sg:postcode":"9120",
    "sg:province":"Oost-Vlaanderen",
    "sg:tags":[
        "rubbish",
        "removal"
    ],
    "wof:name":"Fierens-beck",
    "wof:placetype":"venue"
},
  "geometry": {"coordinates":[4.1808562279,51.2077445984],"type":"Point"}
}