{
  "type": "Feature",
  "properties": {
    "iso:country":"BE",
    "sg:address":"Avenue Charles Quint 333 Box 10",
    "sg:city":"Bruxelles (ganshoren)",
    "sg:classifiers":[
        {
            "category":"Personal",
            "subcategory":"Beauty Salon",
            "type":"Services"
        }
    ],
    "sg:phone":"+32 2 468 54 08",
    "sg:postcode":"1083",
    "sg:province":"Bruxelles-Capitale",
    "sg:tags":[
        "product",
        "-",
        "apparatus"
    ],
    "wof:name":"Van Tilborgh",
    "wof:placetype":"venue"
},
  "geometry": {"coordinates":[4.3010430336,50.8714523315],"type":"Point"}
}