{
  "type": "Feature",
  "properties": {
    "iso:country":"BE",
    "sg:address":"Rue De La Madeleine 33",
    "sg:city":"Tournai",
    "sg:classifiers":[
        {
            "category":"Restaurant",
            "type":"Food & Drink"
        }
    ],
    "sg:phone":"+32 69 84 67 14",
    "sg:postcode":"7500",
    "sg:province":"Hainaut",
    "sg:tags":[
        "organisatie",
        "feesten",
        "van",
        "catering"
    ],
    "wof:name":"La Madeleine",
    "wof:placetype":"venue"
},
  "geometry": {"coordinates":[3.3823800087,50.6111106873],"type":"Point"}
}