{
  "type": "Feature",
  "properties": {
    "iso:country":"BE",
    "sg:address":"Place Du Batty 17",
    "sg:city":"Doische (vodel\u00e9e)",
    "sg:classifiers":[
        {
            "category":"Home & Garden",
            "subcategory":"Building Materials",
            "type":"Retail Goods"
        }
    ],
    "sg:phone":"+32 82 67 81 67",
    "sg:postcode":"5680",
    "sg:province":"Namur",
    "sg:tags":[
        "window"
    ],
    "wof:name":"Menuiserie Scholsem Sprl",
    "wof:placetype":"venue"
},
  "geometry": {"coordinates":[4.7312488556,50.1696357727],"type":"Point"}
}