{
  "type": "Feature",
  "properties": {
    "iso:country":"BE",
    "sg:address":"De Cockplein 27",
    "sg:city":"Machelen",
    "sg:classifiers":[
        {
            "category":"Personal",
            "subcategory":"Beauty Salon",
            "type":"Services"
        }
    ],
    "sg:phone":"+32 2 720 68 60",
    "sg:postcode":"1831",
    "sg:province":"Vlaams-Brabant",
    "sg:tags":[
        "de",
        "coiffure"
    ],
    "wof:name":"Jacaranda",
    "wof:placetype":"venue"
},
  "geometry": {"coordinates":[4.4359431267,50.8944854736],"type":"Point"}
}