{
  "type": "Feature",
  "properties": {
    "iso:country":"BE",
    "sg:address":"Neerlintersesteenweg 59",
    "sg:city":"Tienen",
    "sg:classifiers":[
        {
            "category":"Arena",
            "subcategory":"Sports Club",
            "type":"Entertainment"
        }
    ],
    "sg:phone":"+32 16 81 25 47",
    "sg:postcode":"3300",
    "sg:province":"Vlaams-Brabant",
    "sg:tags":[
        "terrain",
        "hors",
        "de",
        "installation",
        "sportifs"
    ],
    "wof:name":"K. Arsenal Oplinter",
    "wof:placetype":"venue"
},
  "geometry": {"coordinates":[4.9954209328,50.8300018311],"type":"Point"}
}