{
  "type": "Feature",
  "properties": {
    "addr:full":"Rue Du S\u00e9minaire 1 Namur Namur 5000",
    "addr:housenumber":"1",
    "addr:postcode":"5000",
    "addr:street":"Rue Du Se\u0301Minaire",
    "iso:country":"BE",
    "sg:address":"Rue Du S\u00e9minaire 1",
    "sg:city":"Namur",
    "sg:classifiers":[
        {
            "category":"Professional",
            "subcategory":"Lawyer & Legal Services",
            "type":"Services"
        }
    ],
    "sg:phone":"+32 81 23 08 13",
    "sg:postcode":"5000",
    "sg:province":"Namur",
    "wof:name":"Jacques V\u00e9ronique",
    "wof:placetype":"venue"
},
  "geometry": {"coordinates":[4.8595819473,50.4642333984],"type":"Point"}
}