{
  "type": "Feature",
  "properties": {
    "iso:country":"BE",
    "sg:address":"Rue De La Station 23",
    "sg:city":"Lobbes",
    "sg:orig_category":"Medische and orthopedische apparaten Opticiens",
    "sg:phone":"+32 71 59 01 95",
    "sg:postcode":"6540",
    "sg:province":"Hainaut",
    "wof:name":"Optique Wiard",
    "wof:placetype":"venue"
},
  "geometry": {"coordinates":[4.261592865,50.3457603455],"type":"Point"}
}