{
  "type": "Feature",
  "properties": {
    "iso:country":"BE",
    "sg:address":"Rue Arthur Libert 1",
    "sg:city":"Chaumont-gistoux",
    "sg:orig_category":"Catering and organisation de f\u00eates",
    "sg:phone":"+32 10 88 92 02",
    "sg:postcode":"1325",
    "sg:province":"Brabant Wallon",
    "wof:name":"Traiteur Mattart",
    "wof:placetype":"venue"
},
  "geometry": {"coordinates":[4.7223548889,50.6729545593],"type":"Point"}
}