{
  "type": "Feature",
  "properties": {
    "addr:full":"Avenue Bel Air 13 Box 12 Bruxelles (uccle) Bruxelles-Capitale 1180",
    "addr:housenumber":"13 box 12",
    "addr:postcode":"1180",
    "addr:street":"Avenue Bel Air",
    "iso:country":"BE",
    "sg:address":"Avenue Bel Air 13 Box 12",
    "sg:city":"Bruxelles (uccle)",
    "sg:classifiers":[
        {
            "category":"Real Estate",
            "subcategory":"Surveying",
            "type":"Services"
        }
    ],
    "sg:phone":"+32 2 345 69 63",
    "sg:postcode":"1180",
    "sg:province":"Bruxelles-Capitale",
    "sg:tags":[
        "surveyor",
        "land"
    ],
    "wof:name":"De Halloy De Waulsort G",
    "wof:placetype":"venue"
},
  "geometry": {"coordinates":[4.3671388626,50.8135147095],"type":"Point"}
}