{
  "type": "Feature",
  "properties": {
    "iso:country":"BE",
    "sg:address":"Rue Des Converses 4",
    "sg:city":"La Louvi\u00c8re",
    "sg:orig_category":"Installatie van metalen schrijnwerk",
    "sg:phone":"+32 64 22 76 50",
    "sg:postcode":"7100",
    "sg:province":"Hainaut",
    "wof:name":"Gantois Enterprises",
    "wof:placetype":"venue"
},
  "geometry": {"coordinates":[4.1850848198,50.4748649597],"type":"Point"}
}