{
  "type": "Feature",
  "properties": {
    "addr:full":"Heirbaan 4 Merchtem Vlaams-Brabant 1785",
    "addr:housenumber":"4",
    "addr:postcode":"1785",
    "addr:street":"Heirbaan",
    "iso:country":"BE",
    "sg:address":"Heirbaan 4",
    "sg:city":"Merchtem",
    "sg:orig_category":"Bouwmaterialen Gh",
    "sg:phone":"+32 52 37 18 63",
    "sg:postcode":"1785",
    "sg:province":"Vlaams-Brabant",
    "wof:name":"D G Bat",
    "wof:placetype":"venue"
},
  "geometry": {"coordinates":[4.233476162,50.9675178528],"type":"Point"}
}