{
  "type": "Feature",
  "properties": {
    "addr:full":"Rue Du Pont Quelin 6 Ath Hainaut 7800",
    "addr:housenumber":"6",
    "addr:postcode":"7800",
    "addr:street":"Rue Du Pont Quelin",
    "iso:country":"BE",
    "sg:address":"Rue Du Pont Quelin 6",
    "sg:city":"Ath",
    "sg:classifiers":[
        {
            "category":"Home & Garden",
            "subcategory":"Home Furnishings",
            "type":"Retail Goods"
        }
    ],
    "sg:phone":"+32 68 28 20 89",
    "sg:postcode":"7800",
    "sg:province":"Hainaut",
    "sg:tags":[
        "-",
        "furniture"
    ],
    "wof:name":"Navez Meubles Sprl",
    "wof:placetype":"venue"
},
  "geometry": {"coordinates":[3.7778940201,50.6310882568],"type":"Point"}
}