{
  "type": "Feature",
  "properties": {
    "iso:country":"BE",
    "sg:address":"Rue De L'hotellerie 83",
    "sg:city":"Lessines",
    "sg:orig_category":"Schoenen",
    "sg:phone":"+32 68 33 72 32",
    "sg:postcode":"7860",
    "sg:province":"Hainaut",
    "wof:name":"L'accroche-pied",
    "wof:placetype":"venue"
},
  "geometry": {"coordinates":[3.8396980762,50.7099494934],"type":"Point"}
}