{
  "type": "Feature",
  "properties": {
    "addr:full":"Chauss\u00c9e De Louvain 573 Bruxelles Bruxelles-Capitale 1030",
    "addr:housenumber":"573",
    "addr:postcode":"1030",
    "addr:street":"Chausse\u0301E De Louvain",
    "iso:country":"BE",
    "sg:address":"Chauss\u00c9e De Louvain 573",
    "sg:city":"Bruxelles",
    "sg:orig_category":"Arrivero. Restaurants fast food and \u00e0 emporter. Restaurants livraison \u00e0 domicile",
    "sg:phone":"+32 2 705 48 00",
    "sg:postcode":"1030",
    "sg:province":"Bruxelles-Capitale",
    "wof:name":"Arrivero",
    "wof:placetype":"venue"
},
  "geometry": {"coordinates":[4.4017081261,50.8560180664],"type":"Point"}
}