{
  "type": "Feature",
  "properties": {
    "addr:full":"Hoogstraat 37 Mechelen Antwerpen 2800",
    "addr:housenumber":"37",
    "addr:postcode":"2800",
    "addr:street":"Hoogstraat",
    "iso:country":"BE",
    "sg:address":"Hoogstraat 37",
    "sg:city":"Mechelen",
    "sg:classifiers":[
        {
            "category":"Cafe",
            "type":"Food & Drink"
        }
    ],
    "sg:phone":"+32 15 42 40 52",
    "sg:postcode":"2800",
    "sg:province":"Antwerpen",
    "sg:tags":[
        "snack-bars"
    ],
    "wof:name":"Pic Nic",
    "wof:placetype":"venue"
},
  "geometry": {"coordinates":[4.47498703,51.0230484009],"type":"Point"}
}