{
  "type": "Feature",
  "properties": {
    "iso:country":"BE",
    "sg:address":"Avenue Du Forum 11b120",
    "sg:city":"Brussel/bruxelles",
    "sg:orig_category":"Administration d'immeubles",
    "sg:phone":"+32 2 268 21 80",
    "sg:postcode":"1020",
    "sg:province":"Bruxelles-Capitale",
    "wof:name":"C.d.v.i. Immobilier",
    "wof:placetype":"venue"
},
  "geometry": {"coordinates":[4.3532309532,50.8995246887],"type":"Point"}
}