{
  "type": "Feature",
  "properties": {
    "iso:country":"BE",
    "sg:address":"Rue Du Forestier 61",
    "sg:city":"Seraing (boncelles)",
    "sg:classifiers":[
        {
            "category":"Home & Garden",
            "subcategory":"Household Appliances",
            "type":"Retail Goods"
        }
    ],
    "sg:phone":"+32 4 338 27 37",
    "sg:postcode":"4100",
    "sg:province":"Li\u00e8ge",
    "sg:tags":[
        "repair",
        "mainten",
        "-",
        "electric"
    ],
    "wof:name":"Pc Elektro",
    "wof:placetype":"venue"
},
  "geometry": {"coordinates":[5.4910998344,50.571434021],"type":"Point"}
}