{
  "type": "Feature",
  "properties": {
    "iso:country":"BE",
    "sg:address":"Moerbroek 22",
    "sg:city":"Herenthout",
    "sg:classifiers":[
        {
            "category":"Manufacturing",
            "subcategory":"Metals",
            "type":"Manufacturing & Wholesale Goods"
        }
    ],
    "sg:phone":"+32 14 23 36 33",
    "sg:postcode":"2270",
    "sg:province":"Antwerpen",
    "sg:tags":[
        "polishing"
    ],
    "wof:name":"Chromage Voorspoels",
    "wof:placetype":"venue"
},
  "geometry": {"coordinates":[4.7976927757,51.1536064148],"type":"Point"}
}