{
  "type": "Feature",
  "properties": {
    "addr:full":"Rue De Ghlin 27 Mons Hainaut 7012",
    "addr:housenumber":"27",
    "addr:postcode":"7012",
    "addr:street":"Rue De Ghlin;Hainaut",
    "iso:country":"BE",
    "sg:address":"Rue De Ghlin 27",
    "sg:city":"Mons",
    "sg:orig_category":"Travail and traitement du bois",
    "sg:phone":"+32 65 82 20 87",
    "sg:postcode":"7012",
    "sg:province":"Hainaut",
    "wof:name":"Destrait",
    "wof:placetype":"venue"
},
  "geometry": {"coordinates":[3.8894600868,50.4481964111],"type":"Point"}
}