{
  "type": "Feature",
  "properties": {
    "addr:full":"Hellegat 21 Wetteren Oost-Vlaanderen 9230",
    "addr:housenumber":"21",
    "addr:postcode":"9230",
    "addr:street":"Hellegat",
    "iso:country":"BE",
    "sg:address":"Hellegat 21",
    "sg:city":"Wetteren",
    "sg:classifiers":[
        {
            "category":"Shopping",
            "type":"Retail Goods"
        }
    ],
    "sg:phone":"+32 9 369 36 31",
    "sg:postcode":"9230",
    "sg:province":"Oost-Vlaanderen",
    "sg:tags":[
        "product",
        "cleaning",
        "maintenance"
    ],
    "wof:name":"T&b",
    "wof:placetype":"venue"
},
  "geometry": {"coordinates":[3.8521900177,50.9872398376],"type":"Point"}
}