{
  "type": "Feature",
  "properties": {
    "addr:full":"Molenstraat 4 Moorslede West-Vlaanderen 8890",
    "addr:housenumber":"4",
    "addr:postcode":"8890",
    "addr:street":"Molenstraat",
    "iso:country":"BE",
    "sg:address":"Molenstraat 4",
    "sg:city":"Moorslede",
    "sg:orig_category":"Eleveurs de bovins",
    "sg:phone":"+32 51 77 84 61",
    "sg:postcode":"8890",
    "sg:province":"West-Vlaanderen",
    "wof:name":"Hubert Verhaeghe",
    "wof:placetype":"venue"
},
  "geometry": {"coordinates":[3.0458579063,50.8892631531],"type":"Point"}
}