{
  "type": "Feature",
  "properties": {
    "addr:full":"Rue Arthur Roelandt 2a Mouscron (dottignies) Hainaut 7711",
    "addr:housenumber":"2a",
    "addr:postcode":"7711",
    "addr:street":"Rue Arthur Roelandt",
    "iso:country":"BE",
    "sg:address":"Rue Arthur Roelandt 2a",
    "sg:city":"Mouscron (dottignies)",
    "sg:classifiers":[
        {
            "category":"Professional",
            "subcategory":"Testing Lab",
            "type":"Services"
        }
    ],
    "sg:phone":"+32 56 48 82 46",
    "sg:postcode":"7711",
    "sg:province":"Hainaut",
    "sg:tags":[
        "chemist"
    ],
    "wof:name":"Deconinck",
    "wof:placetype":"venue"
},
  "geometry": {"coordinates":[3.3046710491,50.7281532288],"type":"Point"}
}