{
  "type": "Feature",
  "properties": {
    "addr:full":"Rue Provinciale 51 Herstal Li\u00e8ge 4042",
    "addr:housenumber":"51",
    "addr:postcode":"4042",
    "addr:street":"Rue Provinciale",
    "iso:country":"BE",
    "sg:address":"Rue Provinciale 51",
    "sg:city":"Herstal",
    "sg:orig_category":"RESTAURANTS: INSTALLATIONS AND TERRAINS DE SPORT HORS CENTRES SPORTIFS. RESTAURANTS FAST FOOD AND \u00c0 ",
    "sg:phone":"+32 4 278 31 72",
    "sg:postcode":"4042",
    "sg:province":"Li\u00e8ge",
    "wof:name":"Smash 51",
    "wof:placetype":"venue"
},
  "geometry": {"coordinates":[5.5627551079,50.6930389404],"type":"Point"}
}