{
  "type": "Feature",
  "properties": {
    "addr:full":"Rue Vandermeersch 57 Bruxelles (schaerbeek) Bruxelles-Capitale 1030",
    "addr:housenumber":"57",
    "addr:postcode":"1030",
    "addr:street":"Rue Vandermeersch",
    "iso:country":"BE",
    "sg:address":"Rue Vandermeersch 57",
    "sg:city":"Bruxelles (schaerbeek)",
    "sg:classifiers":[
        {
            "category":"Education",
            "subcategory":"Special Training",
            "type":"Public Place"
        }
    ],
    "sg:phone":"+32 2 215 48 58",
    "sg:postcode":"1030",
    "sg:province":"Bruxelles-Capitale",
    "sg:tags":[
        "school",
        "language"
    ],
    "wof:name":"O'shea",
    "wof:placetype":"venue"
},
  "geometry": {"coordinates":[4.3697280884,50.8648071289],"type":"Point"}
}