{
  "type": "Feature",
  "properties": {
    "iso:country":"BE",
    "sg:address":"Rue De La Gaiet\u00c9 6",
    "sg:city":"Binche",
    "sg:orig_category":"Textiel Verlichting and huishoudartikelen",
    "sg:phone":"+32 64 33 80 03",
    "sg:postcode":"7130",
    "sg:province":"Hainaut",
    "wof:name":"Maison Garance",
    "wof:placetype":"venue"
},
  "geometry": {"coordinates":[4.1658978462,50.4116592407],"type":"Point"}
}