{
  "type": "Feature",
  "properties": {
    "iso:country":"BE",
    "sg:address":"Kloosterakker 5",
    "sg:city":"Brecht",
    "sg:orig_category":"Producteurs de l\u00e9gumes",
    "sg:phone":"+32 3 313 70 17",
    "sg:postcode":"2960",
    "sg:province":"Antwerpen",
    "wof:name":"Francine Goossens",
    "wof:placetype":"venue"
},
  "geometry": {"coordinates":[4.5581941605,51.3011283875],"type":"Point"}
}