{
  "type": "Feature",
  "properties": {
    "iso:country":"BE",
    "sg:address":"Moli\u00c8relaan 122",
    "sg:city":"Vorst/forest",
    "sg:orig_category":"Persagentschappen",
    "sg:phone":"+32 2 345 03 11",
    "sg:postcode":"1190",
    "sg:province":"Bruxelles-Capitale",
    "wof:name":"Gilles Toussaint",
    "wof:placetype":"venue"
},
  "geometry": {"coordinates":[4.3498849869,50.816204071],"type":"Point"}
}