{
  "type": "Feature",
  "properties": {
    "addr:full":"Antwerpsesteenweg 227 Malle (westmalle) Antwerpen 2390",
    "addr:housenumber":"227",
    "addr:postcode":"2390",
    "addr:street":"Antwerpsesteenweg",
    "iso:country":"BE",
    "sg:address":"Antwerpsesteenweg 227",
    "sg:city":"Malle (westmalle)",
    "sg:classifiers":[
        {
            "category":"Bars & Pubs",
            "type":"Food & Drink"
        }
    ],
    "sg:phone":"+32 3 312 10 41",
    "sg:postcode":"2390",
    "sg:province":"Antwerpen",
    "wof:name":"Pleintje ('t)",
    "wof:placetype":"venue"
},
  "geometry": {"coordinates":[4.695291996,51.2967071533],"type":"Point"}
}