{
  "type": "Feature",
  "properties": {
    "iso:country":"BE",
    "sg:address":"Rue Sainte-anne 15",
    "sg:city":"Sambreville",
    "sg:orig_category":"Artsen and specialisten",
    "sg:phone":"+32 71 76 06 65",
    "sg:postcode":"5060",
    "sg:province":"Namur",
    "wof:name":"E. Montesi",
    "wof:placetype":"venue"
},
  "geometry": {"coordinates":[4.6191921234,50.4174385071],"type":"Point"}
}