{
  "type": "Feature",
  "properties": {
    "addr:full":"Rue De Fleurjoux 1 Fleurus Hainaut 6220",
    "addr:housenumber":"1",
    "addr:postcode":"6220",
    "addr:street":"Rue De Fleurjoux",
    "iso:country":"BE",
    "sg:address":"Rue De Fleurjoux 1",
    "sg:city":"Fleurus",
    "sg:classifiers":[
        {
            "category":"Cafe",
            "type":"Food & Drink"
        }
    ],
    "sg:phone":"+32 71 81 15 94",
    "sg:postcode":"6220",
    "sg:province":"Hainaut",
    "sg:tags":[
        "caf\u00e9s"
    ],
    "wof:name":"Avenir Royal Colomb.",
    "wof:placetype":"venue"
},
  "geometry": {"coordinates":[4.5501179695,50.4792938232],"type":"Point"}
}