{
  "type": "Feature",
  "properties": {
    "iso:country":"BE",
    "sg:address":"Rue De Gand 1",
    "sg:city":"Ath",
    "sg:orig_category":"Sportcentra Sportclubs Sportterreinen and installaties behalve sportcentra",
    "sg:phone":"+32 68 28 31 41",
    "sg:postcode":"7800",
    "sg:province":"Hainaut",
    "wof:name":"Complexe Sportif",
    "wof:placetype":"venue"
},
  "geometry": {"coordinates":[3.7771730423,50.6279983521],"type":"Point"}
}