{
  "type": "Feature",
  "properties": {
    "addr:full":"Rue Du Monument 39 Limbourg Li\u00e8ge 4834",
    "addr:housenumber":"39",
    "addr:postcode":"4834",
    "addr:street":"Rue Du Monument",
    "iso:country":"BE",
    "sg:address":"Rue Du Monument 39",
    "sg:city":"Limbourg",
    "sg:classifiers":[
        {
            "category":"Arena",
            "subcategory":"Sports Club",
            "type":"Entertainment"
        }
    ],
    "sg:phone":"+32 87 76 22 90",
    "sg:postcode":"4834",
    "sg:province":"Li\u00e8ge",
    "sg:tags":[
        "de"
    ],
    "wof:name":"Les Go\u00c9-lands",
    "wof:placetype":"venue"
},
  "geometry": {"coordinates":[5.9589648247,50.6054763794],"type":"Point"}
}