{
  "type": "Feature",
  "properties": {
    "addr:full":"Hoekstraat 4 Brecht Antwerpen 2960",
    "addr:housenumber":"4",
    "addr:postcode":"2960",
    "addr:street":"Hoekstraat",
    "iso:country":"BE",
    "sg:address":"Hoekstraat 4",
    "sg:city":"Brecht",
    "sg:classifiers":[
        {
            "category":"Retail",
            "subcategory":"Veterinary Services",
            "type":"Services"
        }
    ],
    "sg:phone":"+32 3 313 94 18",
    "sg:postcode":"2960",
    "sg:province":"Antwerpen",
    "sg:tags":[
        "veterinarian"
    ],
    "wof:name":"Denis M",
    "wof:placetype":"venue"
},
  "geometry": {"coordinates":[4.6219630241,51.3567047119],"type":"Point"}
}