{
  "type": "Feature",
  "properties": {
    "addr:full":"Albert Biesmanslaan 1a Hoeilaart Vlaams-Brabant 1560",
    "addr:housenumber":"1a",
    "addr:postcode":"1560",
    "addr:street":"Albert Biesmanslaan",
    "iso:country":"BE",
    "sg:address":"Albert Biesmanslaan 1a",
    "sg:city":"Hoeilaart",
    "sg:orig_category":"Supermarch\u00e9s",
    "sg:phone":"+32 2 657 38 26",
    "sg:postcode":"1560",
    "sg:province":"Vlaams-Brabant",
    "wof:name":"Ad Delhaize",
    "wof:placetype":"venue"
},
  "geometry": {"coordinates":[4.4765272141,50.7682380676],"type":"Point"}
}