{
  "type": "Feature",
  "properties": {
    "addr:full":"Opstalstraat 109 Waregem West-Vlaanderen 8792",
    "addr:housenumber":"109",
    "addr:postcode":"8792",
    "addr:street":"Opstalstraat",
    "iso:country":"BE",
    "sg:address":"Opstalstraat 109",
    "sg:city":"Waregem",
    "sg:orig_category":"Producteurs de l\u00e9gumes",
    "sg:phone":"+32 56 71 11 51",
    "sg:postcode":"8792",
    "sg:province":"West-Vlaanderen",
    "wof:name":"Jose Biebuyck",
    "wof:placetype":"venue"
},
  "geometry": {"coordinates":[3.368573904,50.8923225403],"type":"Point"}
}