{
  "type": "Feature",
  "properties": {
    "addr:full":"Demerstraat 49b2 Hasselt Limburg 3500",
    "addr:housenumber":"49b2",
    "addr:postcode":"3500",
    "addr:street":"Demerstraat",
    "iso:country":"BE",
    "sg:address":"Demerstraat 49b2",
    "sg:city":"Hasselt",
    "sg:classifiers":[
        {
            "category":"Military Area",
            "subcategory":"Armory",
            "type":"Public Place"
        }
    ],
    "sg:phone":"+32 11 22 74 59",
    "sg:postcode":"3500",
    "sg:province":"Limburg",
    "sg:tags":[
        "armes",
        "munition"
    ],
    "wof:name":"Huis Bugro",
    "wof:placetype":"venue"
},
  "geometry": {"coordinates":[5.3381109238,50.9319953918],"type":"Point"}
}