{
  "type": "Feature",
  "properties": {
    "iso:country":"BE",
    "sg:address":"Boulevard Emile Jacqmain",
    "sg:city":"Brussel/bruxelles",
    "sg:orig_category":"Editeurs de journaux. Editeurs de revues and p\u00e9riodiques",
    "sg:phone":"+32 70 23 30 00",
    "sg:postcode":"1000",
    "sg:province":"Bruxelles-Capitale",
    "wof:name":"J'annonce",
    "wof:placetype":"venue"
},
  "geometry": {"coordinates":[4.354364872,50.8543663025],"type":"Point"}
}