{
  "type": "Feature",
  "properties": {
    "addr:full":"Luikersteenweg 424-2 Hasselt Limburg 3500",
    "addr:postcode":"424-2;3500",
    "addr:street":"Luikersteenweg",
    "iso:country":"BE",
    "sg:address":"Luikersteenweg 424-2",
    "sg:city":"Hasselt",
    "sg:classifiers":[
        {
            "category":"Landmark",
            "subcategory":"Ruins",
            "type":"Public Place"
        }
    ],
    "sg:phone":"+32 11 27 26 15",
    "sg:postcode":"3500",
    "sg:province":"Limburg",
    "sg:tags":[
        "conservation",
        "-",
        "archive",
        "destruction"
    ],
    "wof:name":"D&l Logistics",
    "wof:placetype":"venue"
},
  "geometry": {"coordinates":[5.3548398018,50.909450531],"type":"Point"}
}