{
  "type": "Feature",
  "properties": {
    "addr:full":"Rue Willems 14 Box 17-808 Bruxelles (saint-josse-ten-noode) Bruxelles-Capitale 1210",
    "addr:housenumber":"14 box",
    "addr:postcode":"1210",
    "addr:street":"Rue Willems;17-808",
    "iso:country":"BE",
    "sg:address":"Rue Willems 14 Box 17-808",
    "sg:city":"Bruxelles (saint-josse-ten-noode)",
    "sg:classifiers":[
        {
            "category":"Real Estate",
            "subcategory":"Real Estate Services",
            "type":"Services"
        }
    ],
    "sg:phone":"+32 2 230 23 64",
    "sg:postcode":"1210",
    "sg:province":"Bruxelles-Capitale",
    "wof:name":"Immobili\u00e8re Patris Sprl",
    "wof:placetype":"venue"
},
  "geometry": {"coordinates":[4.3695149422,50.8509941101],"type":"Point"}
}