{
  "type": "Feature",
  "properties": {
    "iso:country":"BE",
    "sg:address":"Rue Voie De Li\u00e8ge",
    "sg:city":"Oupeye (hermalle-sous-argenteau)",
    "sg:classifiers":[
        {
            "category":"Autos & Motor Vehicles",
            "subcategory":"Boat Sales",
            "type":"Retail Goods"
        }
    ],
    "sg:phone":"+32 4 374 08 40",
    "sg:postcode":"4681",
    "sg:province":"Li\u00e8ge",
    "sg:tags":[
        "outboard",
        "-"
    ],
    "wof:name":"Garage Des Sports",
    "wof:placetype":"venue"
},
  "geometry": {"coordinates":[5.6696949005,50.7144317627],"type":"Point"}
}