{
  "type": "Feature",
  "properties": {
    "iso:country":"BE",
    "sg:address":"Chauss\u00e9e De Lodelinsart 64",
    "sg:city":"Charleroi (gilly)",
    "sg:classifiers":[
        {
            "category":"Arena",
            "subcategory":"Sports Club",
            "type":"Entertainment"
        }
    ],
    "sg:phone":"+32 71 41 37 29",
    "sg:postcode":"6060",
    "sg:province":"Hainaut",
    "wof:name":"Drive Club",
    "wof:placetype":"venue"
},
  "geometry": {"coordinates":[4.4498310089,50.4204826355],"type":"Point"}
}