{
  "type": "Feature",
  "properties": {
    "addr:full":"Damse Vaart-zuid 9a Damme West-Vlaanderen 8340",
    "addr:housenumber":"9a",
    "addr:postcode":"8340",
    "addr:street":"Damse Vaart-Zuid",
    "iso:country":"BE",
    "sg:address":"Damse Vaart-zuid 9a",
    "sg:city":"Damme",
    "sg:classifiers":[
        {
            "category":"Health Services",
            "subcategory":"Health Practitioner",
            "type":"Services"
        }
    ],
    "sg:phone":"+32 50 35 75 42",
    "sg:postcode":"8340",
    "sg:province":"West-Vlaanderen",
    "sg:tags":[
        "physiotherapist"
    ],
    "wof:name":"Steen C",
    "wof:placetype":"venue"
},
  "geometry": {"coordinates":[3.2799921036,51.2513885498],"type":"Point"}
}