{
  "type": "Feature",
  "properties": {
    "iso:country":"BE",
    "sg:address":"Chauss\u00e9e De Tongres 75",
    "sg:city":"Li\u00e8ge 1 (rocourt)",
    "sg:classifiers":[
        {
            "category":"Building & Trades",
            "subcategory":"Equipment Rental",
            "type":"Services"
        }
    ],
    "sg:phone":"+32 4 224 31 23",
    "sg:postcode":"4000",
    "sg:province":"Li\u00e8ge",
    "sg:tags":[
        "safety",
        "collective",
        "individual",
        "-"
    ],
    "wof:name":"Ets Halleux/pro Job Sprl",
    "wof:placetype":"venue"
},
  "geometry": {"coordinates":[5.5590648651,50.6658782959],"type":"Point"}
}