{
  "type": "Feature",
  "properties": {
    "addr:full":"Quai Du Vignoble 46 Comblain-au-pont Li\u00e8ge 4170",
    "addr:housenumber":"46",
    "addr:postcode":"4170",
    "addr:street":"Quai Du Vignoble",
    "iso:country":"BE",
    "sg:address":"Quai Du Vignoble 46",
    "sg:city":"Comblain-au-pont",
    "sg:classifiers":[
        {
            "category":"Health Services",
            "subcategory":"Doctor",
            "type":"Services"
        }
    ],
    "sg:phone":"+32 4 369 19 54",
    "sg:postcode":"4170",
    "sg:province":"Li\u00e8ge",
    "sg:tags":[
        "medicinephysicians",
        "surgeon"
    ],
    "wof:name":"Haxhe E",
    "wof:placetype":"venue"
},
  "geometry": {"coordinates":[5.5876312256,50.476764679],"type":"Point"}
}