{
  "type": "Feature",
  "properties": {
    "iso:country":"BE",
    "sg:address":"Molenstraat 85",
    "sg:city":"Maasmechelen (leut)",
    "sg:classifiers":[
        {
            "category":"Building & Trades",
            "subcategory":"Landscaping Services",
            "type":"Services"
        }
    ],
    "sg:phone":"+32 89 75 77 88",
    "sg:postcode":"3630",
    "sg:province":"Limburg",
    "sg:tags":[
        "gardening",
        "garden",
        "maintenance"
    ],
    "wof:name":"Cornelissen E",
    "wof:placetype":"venue"
},
  "geometry": {"coordinates":[5.7410187721,50.9999237061],"type":"Point"}
}