{
  "type": "Feature",
  "properties": {
    "addr:full":"Grimbergsesteenweg 123 Vilvoorde Vlaams-Brabant 1800",
    "addr:housenumber":"123",
    "addr:postcode":"1800",
    "addr:street":"Grimbergsesteenweg",
    "iso:country":"BE",
    "sg:address":"Grimbergsesteenweg 123",
    "sg:city":"Vilvoorde",
    "sg:classifiers":[
        {
            "category":"Personal",
            "subcategory":"Beauty Salon",
            "type":"Services"
        }
    ],
    "sg:phone":"+32 2 251 26 19",
    "sg:postcode":"1800",
    "sg:province":"Vlaams-Brabant",
    "sg:tags":[
        "lady",
        "-",
        "hairdressing"
    ],
    "wof:name":"Annie",
    "wof:placetype":"venue"
},
  "geometry": {"coordinates":[4.4112811089,50.9250297546],"type":"Point"}
}