{
  "type": "Feature",
  "properties": {
    "iso:country":"BE",
    "sg:address":"Verbindingsdok Oostkaai 13 Box 11",
    "sg:city":"Antwerpen",
    "sg:classifiers":[
        {
            "category":"Professional",
            "type":"Services"
        }
    ],
    "sg:phone":"+32 3 201 83 50",
    "sg:postcode":"2000",
    "sg:province":"Antwerpen",
    "sg:tags":[
        "forwarding",
        "agency"
    ],
    "wof:name":"Rhenania Intermodel Transport Nv",
    "wof:placetype":"venue"
},
  "geometry": {"coordinates":[4.4080381393,51.2302360535],"type":"Point"}
}