{
  "type": "Feature",
  "properties": {
    "iso:country":"BE",
    "sg:address":"Braamstraat 3",
    "sg:city":"Schilde",
    "sg:orig_category":"Mat\u00e9riel m\u00e9dical and orthop\u00e9dique and proth\u00e8ses Fab",
    "sg:phone":"+32 3 383 56 41",
    "sg:postcode":"2970",
    "sg:province":"Antwerpen",
    "wof:name":"Alex Baert",
    "wof:placetype":"venue"
},
  "geometry": {"coordinates":[4.5811619759,51.2443161011],"type":"Point"}
}