{
  "type": "Feature",
  "properties": {
    "iso:country":"BE",
    "sg:address":"Frans De Peuterstraat 167",
    "sg:city":"Kapellen",
    "sg:orig_category":"Alimentation sp\u00e9cialis\u00e9e",
    "sg:phone":"+32 3 605 21 60",
    "sg:postcode":"2950",
    "sg:province":"Antwerpen",
    "wof:name":"Jozef Embrechts",
    "wof:placetype":"venue"
},
  "geometry": {"coordinates":[4.4225878716,51.3015213013],"type":"Point"}
}