{
  "type": "Feature",
  "properties": {
    "iso:country":"BE",
    "sg:address":"Rue Verte 3",
    "sg:city":"Marche-en-famenne (hargimont)",
    "sg:classifiers":[
        {
            "category":"Farming",
            "subcategory":"Farm & Veterinary Services",
            "type":"Manufacturing & Wholesale Goods"
        }
    ],
    "sg:phone":"+32 84 21 13 66",
    "sg:postcode":"6900",
    "sg:province":"Luxembourg",
    "sg:tags":[
        "agricultural",
        "contractor"
    ],
    "wof:name":"Maldague-lambot Sprl",
    "wof:placetype":"venue"
},
  "geometry": {"coordinates":[5.3430151939,50.2273483276],"type":"Point"}
}