{
  "type": "Feature",
  "properties": {
    "iso:country":"BE",
    "sg:address":"Hal 29",
    "sg:city":"Hoogstraten",
    "sg:orig_category":"Pluimveekwekers",
    "sg:phone":"+32 3 315 73 32",
    "sg:postcode":"2322",
    "sg:province":"Antwerpen",
    "wof:name":"Gustaaf Michielsen",
    "wof:placetype":"venue"
},
  "geometry": {"coordinates":[4.763384819,51.4160041809],"type":"Point"}
}