{
  "type": "Feature",
  "properties": {
    "addr:full":"Grand'rue 73 Thuin Hainaut 6530",
    "addr:housenumber":"73",
    "addr:postcode":"6530",
    "addr:street":"Grand'Rue",
    "iso:country":"BE",
    "sg:address":"Grand'rue 73",
    "sg:city":"Thuin",
    "sg:classifiers":[
        {
            "category":"Health Services",
            "subcategory":"Dentist",
            "type":"Services"
        }
    ],
    "sg:phone":"+32 71 59 11 89",
    "sg:postcode":"6530",
    "sg:province":"Hainaut",
    "wof:name":"Foulart Catherine",
    "wof:placetype":"venue"
},
  "geometry": {"coordinates":[4.2896828651,50.3388442993],"type":"Point"}
}