{
  "type": "Feature",
  "properties": {
    "addr:full":"Kranenberg 15 Asse (zellik) Vlaams-Brabant 1731",
    "addr:housenumber":"15",
    "addr:postcode":"1731",
    "addr:street":"Kranenberg",
    "iso:country":"BE",
    "sg:address":"Kranenberg 15",
    "sg:city":"Asse (zellik)",
    "sg:classifiers":[
        {
            "category":"Home & Garden",
            "subcategory":"Hardware",
            "type":"Retail Goods"
        }
    ],
    "sg:phone":"+32 2 481 79 00",
    "sg:postcode":"1731",
    "sg:province":"Vlaams-Brabant",
    "sg:tags":[
        "garage",
        "supply",
        "-",
        "equipment"
    ],
    "wof:name":"Techno Automotive Equipment Nv",
    "wof:placetype":"venue"
},
  "geometry": {"coordinates":[4.291326046,50.8816642761],"type":"Point"}
}