{
  "type": "Feature",
  "properties": {
    "iso:country":"BE",
    "sg:address":"Peperstraat 21",
    "sg:city":"Mol",
    "sg:classifiers":[
        {
            "category":"Real Estate",
            "subcategory":"Architect",
            "type":"Services"
        }
    ],
    "sg:phone":"+32 14 31 02 10",
    "sg:postcode":"2400",
    "sg:province":"Antwerpen",
    "wof:name":"Vanhoof A",
    "wof:placetype":"venue"
},
  "geometry": {"coordinates":[5.0944800377,51.2060317993],"type":"Point"}
}