{
  "type": "Feature",
  "properties": {
    "addr:full":"Oude Arendonksebaan 47 Retie Antwerpen 2470",
    "addr:housenumber":"47",
    "addr:postcode":"2470",
    "addr:street":"Oude Arendonksebaan",
    "iso:country":"BE",
    "sg:address":"Oude Arendonksebaan 47",
    "sg:city":"Retie",
    "sg:orig_category":"Rundveehouders",
    "sg:phone":"+32 14 37 96 75",
    "sg:postcode":"2470",
    "sg:province":"Antwerpen",
    "wof:name":"Alois Loots",
    "wof:placetype":"venue"
},
  "geometry": {"coordinates":[5.0865540504,51.2799911499],"type":"Point"}
}