{
  "type": "Feature",
  "properties": {
    "addr:full":"Rue De Gesves 181 Ohey Namur 5350",
    "addr:housenumber":"181",
    "addr:postcode":"5350",
    "addr:street":"Rue De Gesves",
    "iso:country":"BE",
    "sg:address":"Rue De Gesves 181",
    "sg:city":"Ohey",
    "sg:classifiers":[
        {
            "category":"Insurance",
            "subcategory":"Insurance Agent",
            "type":"Services"
        }
    ],
    "sg:phone":"+32 85 61 21 40",
    "sg:postcode":"5350",
    "sg:province":"Namur",
    "sg:tags":[
        "broker"
    ],
    "wof:name":"Somville-melot",
    "wof:placetype":"venue"
},
  "geometry": {"coordinates":[5.1237459183,50.4286193848],"type":"Point"}
}