{
  "type": "Feature",
  "properties": {
    "addr:full":"Rue De La D\u00e9portation 159 Tubize Brabant Wallon 1480",
    "addr:housenumber":"159",
    "addr:postcode":"1480",
    "addr:street":"Rue De La De\u0301Portation;Wallon",
    "iso:country":"BE",
    "sg:address":"Rue De La D\u00e9portation 159",
    "sg:city":"Tubize",
    "sg:classifiers":[
        {
            "category":"Retail",
            "subcategory":"Event Space",
            "type":"Services"
        }
    ],
    "sg:phone":"+32 2 355 34 42",
    "sg:postcode":"1480",
    "sg:province":"Brabant Wallon",
    "sg:tags":[
        "organisation"
    ],
    "wof:name":"Belle Elene (la)",
    "wof:placetype":"venue"
},
  "geometry": {"coordinates":[4.2114400864,50.6907310486],"type":"Point"}
}