{
  "type": "Feature",
  "properties": {
    "addr:full":"Berkenlaan 5 Diksmuide West-Vlaanderen 8600",
    "addr:housenumber":"5",
    "addr:postcode":"8600",
    "addr:street":"Berkenlaan",
    "iso:country":"BE",
    "sg:address":"Berkenlaan 5",
    "sg:city":"Diksmuide",
    "sg:orig_category":"Cr\u00e9meries",
    "sg:phone":"+32 51 50 45 61",
    "sg:postcode":"8600",
    "sg:province":"West-Vlaanderen",
    "wof:name":"Pierre Browaeys",
    "wof:placetype":"venue"
},
  "geometry": {"coordinates":[2.8714389801,51.0357475281],"type":"Point"}
}