{
  "type": "Feature",
  "properties": {
    "addr:full":"Avenue De Mai 169b1 Sint-lambrechts-woluwe/woluwe-saint-lambert Bruxelles-Capitale 1200",
    "addr:housenumber":"169b1",
    "addr:postcode":"1200",
    "addr:street":"Avenue De Mai",
    "iso:country":"BE",
    "sg:address":"Avenue De Mai 169b1",
    "sg:city":"Sint-lambrechts-woluwe/woluwe-saint-lambert",
    "sg:orig_category":"Agences de publicit\u00e9",
    "sg:phone":"+32 2 771 89 28",
    "sg:postcode":"1200",
    "sg:province":"Bruxelles-Capitale",
    "wof:name":"Slick",
    "wof:placetype":"venue"
},
  "geometry": {"coordinates":[4.4159388542,50.8484306335],"type":"Point"}
}