{
  "type": "Feature",
  "properties": {
    "addr:full":"Eliksemstraat 14 Linter (wommersom) Vlaams-Brabant 3350",
    "addr:housenumber":"14",
    "addr:postcode":"3350",
    "addr:street":"Eliksemstraat",
    "iso:country":"BE",
    "sg:address":"Eliksemstraat 14",
    "sg:city":"Linter (wommersom)",
    "sg:classifiers":[
        {
            "category":"Health Services",
            "subcategory":"Health Practitioner",
            "type":"Services"
        }
    ],
    "sg:phone":"+32 16 78 84 84",
    "sg:postcode":"3350",
    "sg:province":"Vlaams-Brabant",
    "sg:tags":[
        "physiotherapist"
    ],
    "wof:name":"Vandenputte V",
    "wof:placetype":"venue"
},
  "geometry": {"coordinates":[5.0166020393,50.8067092896],"type":"Point"}
}