{
  "type": "Feature",
  "properties": {
    "addr:full":"Riemeersstraat 2 Sint-niklaas Oost-Vlaanderen 9112",
    "addr:housenumber":"2",
    "addr:postcode":"9112",
    "addr:street":"Riemeersstraat",
    "iso:country":"BE",
    "sg:address":"Riemeersstraat 2",
    "sg:city":"Sint-niklaas",
    "sg:orig_category":"Eleveurs de volaille",
    "sg:phone":"+32 3 772 38 82",
    "sg:postcode":"9112",
    "sg:province":"Oost-Vlaanderen",
    "wof:name":"Robert Van Rentergem",
    "wof:placetype":"venue"
},
  "geometry": {"coordinates":[4.0484747887,51.1377105713],"type":"Point"}
}