{
  "type": "Feature",
  "properties": {
    "addr:full":"Singelweg 47 Dendermonde Oost-Vlaanderen 9200",
    "addr:housenumber":"47",
    "addr:postcode":"9200",
    "addr:street":"Singelweg;Oost-Vlaanderen",
    "iso:country":"BE",
    "sg:address":"Singelweg 47",
    "sg:city":"Dendermonde",
    "sg:orig_category":"Entretien and r\u00e9parations de voitures",
    "sg:phone":"+32 52 21 36 96",
    "sg:postcode":"9200",
    "sg:province":"Oost-Vlaanderen",
    "wof:name":"Peter Noel",
    "wof:placetype":"venue"
},
  "geometry": {"coordinates":[4.0662579536,50.9947891235],"type":"Point"}
}