{
  "type": "Feature",
  "properties": {
    "iso:country":"BE",
    "sg:address":"Werbeek 18",
    "sg:city":"Retie",
    "sg:orig_category":"Installation de menuiserie en bois and plastique. Rev\u00eatements de sols and murs",
    "sg:phone":"+32 14 37 80 45",
    "sg:postcode":"2470",
    "sg:province":"Antwerpen",
    "wof:name":"Jef Geenen",
    "wof:placetype":"venue"
},
  "geometry": {"coordinates":[5.1014480591,51.2585487366],"type":"Point"}
}