{
  "type": "Feature",
  "properties": {
    "addr:full":"Pastoriestraat 41 Bierbeek Vlaams-Brabant 3360",
    "addr:housenumber":"41",
    "addr:postcode":"3360",
    "addr:street":"Pastoriestraat",
    "iso:country":"BE",
    "sg:address":"Pastoriestraat 41",
    "sg:city":"Bierbeek",
    "sg:orig_category":"Secr\u00e9tariats",
    "sg:phone":"+32 16 46 30 47",
    "sg:postcode":"3360",
    "sg:province":"Vlaams-Brabant",
    "wof:name":"Sioen",
    "wof:placetype":"venue"
},
  "geometry": {"coordinates":[4.7657318115,50.8611297607],"type":"Point"}
}