{
  "type": "Feature",
  "properties": {
    "addr:full":"Rue De La Gare 49 Bi\u00e8vre Namur 5555",
    "addr:housenumber":"49",
    "addr:postcode":"5555",
    "addr:street":"Rue De La Gare",
    "iso:country":"BE",
    "sg:address":"Rue De La Gare 49",
    "sg:city":"Bi\u00e8vre",
    "sg:classifiers":[
        {
            "category":"Wholesale",
            "subcategory":"Machinery & Supplies",
            "type":"Manufacturing & Wholesale Goods"
        }
    ],
    "sg:phone":"+32 61 51 11 10",
    "sg:postcode":"5555",
    "sg:province":"Namur",
    "sg:tags":[
        "refrigeration",
        "-",
        "industrial",
        "commercial",
        "equipment"
    ],
    "wof:name":"Collin Lucy Sa",
    "wof:placetype":"venue"
},
  "geometry": {"coordinates":[5.0324220657,49.9351768494],"type":"Point"}
}