{
  "type": "Feature",
  "properties": {
    "addr:full":"Rue De La Source 1 Wavre Brabant Wallon 1300",
    "addr:housenumber":"1;1300",
    "addr:street":"Rue De La Source",
    "iso:country":"BE",
    "sg:address":"Rue De La Source 1",
    "sg:city":"Wavre",
    "sg:classifiers":[
        {
            "category":"Shopping",
            "subcategory":"Books",
            "type":"Retail Goods"
        }
    ],
    "sg:phone":"+32 10 22 55 50",
    "sg:postcode":"1300",
    "sg:province":"Brabant Wallon",
    "sg:tags":[
        "bookseller"
    ],
    "wof:name":"A La Source Du Livre",
    "wof:placetype":"venue"
},
  "geometry": {"coordinates":[4.6110010147,50.7160758972],"type":"Point"}
}