{
  "type": "Feature",
  "properties": {
    "addr:full":"Kortrijksestraat 18 Kuurne West-Vlaanderen 8520",
    "addr:housenumber":"18",
    "addr:postcode":"8520",
    "addr:street":"Kortrijksestraat",
    "iso:country":"BE",
    "sg:address":"Kortrijksestraat 18",
    "sg:city":"Kuurne",
    "sg:classifiers":[
        {
            "category":"Wholesale",
            "subcategory":"Machinery & Supplies",
            "type":"Manufacturing & Wholesale Goods"
        }
    ],
    "sg:phone":"+32 56 70 59 88",
    "sg:postcode":"8520",
    "sg:province":"West-Vlaanderen",
    "sg:tags":[
        "packing"
    ],
    "wof:name":"Derupa Bvba",
    "wof:placetype":"venue"
},
  "geometry": {"coordinates":[3.2854499817,50.84897995],"type":"Point"}
}