{
  "type": "Feature",
  "properties": {
    "iso:country":"BE",
    "sg:address":"Morelgem 59",
    "sg:city":"Sint-lievens-houtem",
    "sg:orig_category":"Producteurs de l\u00e9gumes",
    "sg:phone":"+32 53 63 10 75",
    "sg:postcode":"9520",
    "sg:province":"Oost-Vlaanderen",
    "wof:name":"Karel Gysels",
    "wof:placetype":"venue"
},
  "geometry": {"coordinates":[3.8962879181,50.922039032],"type":"Point"}
}