{
  "type": "Feature",
  "properties": {
    "addr:full":"Hof Ter Wellelaan 8 Beveren (beveren-waas) Oost-Vlaanderen 9120",
    "addr:housenumber":"8",
    "addr:postcode":"9120",
    "addr:street":"Hof;Wellelaan;Oost-Vlaanderen",
    "iso:country":"BE",
    "sg:address":"Hof Ter Wellelaan 8",
    "sg:city":"Beveren (beveren-waas)",
    "sg:classifiers":[
        {
            "category":"Professional",
            "subcategory":"Management & Consulting",
            "type":"Services"
        }
    ],
    "sg:phone":"+32 3 775 20 38",
    "sg:postcode":"9120",
    "sg:province":"Oost-Vlaanderen",
    "sg:tags":[
        "consultant"
    ],
    "wof:name":"Zakenkantoor Luc Rogier Bvba",
    "wof:placetype":"venue"
},
  "geometry": {"coordinates":[4.2561440468,51.208404541],"type":"Point"}
}