{
  "type": "Feature",
  "properties": {
    "iso:country":"BE",
    "sg:address":"Rue De Montignies 31",
    "sg:city":"Quaregnon",
    "sg:orig_category":"Installatie van houten of kunststof schrijnwerk MEUBELONTWERP AND -INSTALLATIE",
    "sg:phone":"+32 65 79 26 39",
    "sg:postcode":"7390",
    "sg:province":"Hainaut",
    "wof:name":"M.g. Style",
    "wof:placetype":"venue"
},
  "geometry": {"coordinates":[3.864773035,50.4391403198],"type":"Point"}
}