{
  "type": "Feature",
  "properties": {
    "iso:country":"BE",
    "sg:address":"Koninginnelaan 12",
    "sg:city":"Koksijde",
    "sg:orig_category":"Studios photographiques",
    "sg:phone":"+32 58 51 23 91",
    "sg:postcode":"8670",
    "sg:province":"West-Vlaanderen",
    "wof:name":"P. Mertens",
    "wof:placetype":"venue"
},
  "geometry": {"coordinates":[2.6276609898,51.1158027649],"type":"Point"}
}