{
  "type": "Feature",
  "properties": {
    "iso:country":"BE",
    "sg:address":"Prins Leopoldsquare 3",
    "sg:city":"Brussel/bruxelles",
    "sg:orig_category":"Artsen and specialisten",
    "sg:phone":"+32 2 478 36 67",
    "sg:postcode":"1020",
    "sg:province":"Bruxelles-Capitale",
    "wof:name":"Guy Collette",
    "wof:placetype":"venue"
},
  "geometry": {"coordinates":[4.3425211906,50.8833999634],"type":"Point"}
}