{
  "type": "Feature",
  "properties": {
    "iso:country":"BE",
    "sg:address":"Lommelsesteenweg 134",
    "sg:city":"Leopoldsburg",
    "sg:orig_category":"Industri\u00eble and commerci\u00eble bouw",
    "sg:phone":"+32 11 40 28 14",
    "sg:postcode":"3970",
    "sg:province":"Limburg",
    "wof:name":"Lambrechts-sodraep",
    "wof:placetype":"venue"
},
  "geometry": {"coordinates":[5.2560319901,51.1309661865],"type":"Point"}
}