{
  "type": "Feature",
  "properties": {
    "addr:full":"Walburgstraat 31 Sint-niklaas Oost-Vlaanderen 9100",
    "addr:housenumber":"31",
    "addr:postcode":"9100",
    "addr:street":"Walburgstraat",
    "iso:country":"BE",
    "sg:address":"Walburgstraat 31",
    "sg:city":"Sint-niklaas",
    "sg:orig_category":"Diverse bedrijfsbeheeradviesbureaus",
    "sg:phone":"+32 3 776 47 30",
    "sg:postcode":"9100",
    "sg:province":"Oost-Vlaanderen",
    "wof:name":"Koslowski Bedijfsadvies",
    "wof:placetype":"venue"
},
  "geometry": {"coordinates":[4.1448202133,51.1636543274],"type":"Point"}
}