{
  "type": "Feature",
  "properties": {
    "addr:full":"Bergbeemdenstraat 21 Houthalen-helchteren (houthalen) Limburg 3530",
    "addr:housenumber":"21",
    "addr:postcode":"3530",
    "addr:street":"Bergbeemdenstraat",
    "iso:country":"BE",
    "sg:address":"Bergbeemdenstraat 21",
    "sg:city":"Houthalen-helchteren (houthalen)",
    "sg:classifiers":[
        {
            "category":"Wholesale",
            "subcategory":"Plants",
            "type":"Manufacturing & Wholesale Goods"
        }
    ],
    "sg:phone":"+32 11 60 61 10",
    "sg:postcode":"3530",
    "sg:province":"Limburg",
    "sg:tags":[
        "decoration",
        "flower",
        "-"
    ],
    "wof:name":"Ideetje ('t)",
    "wof:placetype":"venue"
},
  "geometry": {"coordinates":[5.3648500443,51.0362854004],"type":"Point"}
}