{
  "type": "Feature",
  "properties": {
    "addr:full":"Rue De L'egalit\u00c9 71 Colfontaine Hainaut 7340",
    "addr:housenumber":"71",
    "addr:postcode":"7340",
    "addr:street":"Rue De L'Egalite \u0301",
    "iso:country":"BE",
    "sg:address":"Rue De L'egalit\u00c9 71",
    "sg:city":"Colfontaine",
    "sg:orig_category":"Sportclubs Sportterreinen and installaties behalve sportcentra",
    "sg:phone":"+32 65 67 96 13",
    "sg:postcode":"7340",
    "sg:province":"Hainaut",
    "wof:name":"F. Communaux Juventus",
    "wof:placetype":"venue"
},
  "geometry": {"coordinates":[3.8471739292,50.4111557007],"type":"Point"}
}