{
  "type": "Feature",
  "properties": {
    "iso:country":"BE",
    "sg:address":"Rue Du P\u00c9pin 48",
    "sg:city":"Brussel/bruxelles",
    "sg:classifiers":[
        {
            "category":"Restaurant",
            "type":"Food & Drink"
        }
    ],
    "sg:phone":"+32 2 513 35 25",
    "sg:postcode":"1000",
    "sg:province":"Bruxelles-Capitale",
    "wof:name":"Restaurant L'entrec\u00d4te",
    "wof:placetype":"venue"
},
  "geometry": {"coordinates":[4.3604369164,50.8390312195],"type":"Point"}
}