{
  "type": "Feature",
  "properties": {
    "addr:full":"Tervuursesteenweg 369 Bertem (leefdaal) Vlaams-Brabant 3061",
    "addr:housenumber":"369",
    "addr:postcode":"3061",
    "addr:street":"Tervuursesteenweg",
    "iso:country":"BE",
    "sg:address":"Tervuursesteenweg 369",
    "sg:city":"Bertem (leefdaal)",
    "sg:classifiers":[
        {
            "category":"Retail",
            "subcategory":"Auto Repair",
            "type":"Services"
        }
    ],
    "sg:phone":"+32 2 769 69 69",
    "sg:postcode":"3061",
    "sg:province":"Vlaams-Brabant",
    "sg:tags":[
        "garage"
    ],
    "wof:name":"Mees Garage Nv",
    "wof:placetype":"venue"
},
  "geometry": {"coordinates":[4.5941410065,50.8558311462],"type":"Point"}
}