{
  "type": "Feature",
  "properties": {
    "addr:full":"Chemin De Guimpoux 2 Paliseul Luxembourg 6850",
    "addr:housenumber":"2",
    "addr:postcode":"6850",
    "addr:street":"Chemin De Guimpoux",
    "iso:country":"BE",
    "sg:address":"Chemin De Guimpoux 2",
    "sg:city":"Paliseul",
    "sg:classifiers":[
        {
            "category":"Personal",
            "subcategory":"Beauty Salon",
            "type":"Services"
        }
    ],
    "sg:phone":"+32 61 53 40 67",
    "sg:postcode":"6850",
    "sg:province":"Luxembourg",
    "sg:tags":[
        "lady",
        "-",
        "hairdressing"
    ],
    "wof:name":"Anny",
    "wof:placetype":"venue"
},
  "geometry": {"coordinates":[5.1456899643,49.907875061],"type":"Point"}
}