{
  "type": "Feature",
  "properties": {
    "iso:country":"BE",
    "sg:address":"Vlasmarkt 3",
    "sg:city":"Kortrijk",
    "sg:classifiers":[
        {
            "category":"Shopping",
            "subcategory":"Clothing, Apparel, & Fashions",
            "type":"Retail Goods"
        }
    ],
    "sg:phone":"+32 56 20 41 82",
    "sg:postcode":"8500",
    "sg:province":"West-Vlaanderen",
    "sg:tags":[
        "v\u00eatements",
        "pour",
        "dame"
    ],
    "wof:name":"Boetiek Zenith",
    "wof:placetype":"venue"
},
  "geometry": {"coordinates":[3.2676699162,50.825630188],"type":"Point"}
}