{
  "type": "Feature",
  "properties": {
    "iso:country":"BE",
    "sg:address":"Prins Albertstraat 35",
    "sg:city":"Sint-niklaas",
    "sg:classifiers":[
        {
            "category":"Social Services",
            "type":"Services"
        }
    ],
    "sg:phone":"+32 3 776 82 71",
    "sg:postcode":"9100",
    "sg:province":"Oost-Vlaanderen",
    "wof:name":"Sociaal Centrum Waasland",
    "wof:placetype":"venue"
},
  "geometry": {"coordinates":[4.1435709,51.1695671082],"type":"Point"}
}