{
  "type": "Feature",
  "properties": {
    "addr:full":"Grensstraat 219 Kraainem Vlaams-Brabant 1950",
    "addr:housenumber":"219",
    "addr:postcode":"1950",
    "addr:street":"Grensstraat",
    "iso:country":"BE",
    "sg:address":"Grensstraat 219",
    "sg:city":"Kraainem",
    "sg:orig_category":"Gespecialiseerde residenti\u00eble bouw Tuinen",
    "sg:phone":"+32 2 731 14 24",
    "sg:postcode":"1950",
    "sg:province":"Vlaams-Brabant",
    "wof:name":"Hugot",
    "wof:placetype":"venue"
},
  "geometry": {"coordinates":[4.4620718956,50.8522033691],"type":"Point"}
}