{
  "type": "Feature",
  "properties": {
    "addr:full":"Kapelsesteenweg 308 Brasschaat Antwerpen 2930",
    "addr:housenumber":"308",
    "addr:postcode":"2930",
    "addr:street":"Kapelsesteenweg",
    "iso:country":"BE",
    "sg:address":"Kapelsesteenweg 308",
    "sg:city":"Brasschaat",
    "sg:orig_category":"Huisdieren and benodigdheden Royal Canin",
    "sg:phone":"+32 3 605 30 91",
    "sg:postcode":"2930",
    "sg:province":"Antwerpen",
    "wof:name":"Kennelhof",
    "wof:placetype":"venue"
},
  "geometry": {"coordinates":[4.4457840919,51.2903175354],"type":"Point"}
}