{
  "type": "Feature",
  "properties": {
    "iso:country":"BE",
    "sg:address":"Rue De L'eglise 84",
    "sg:city":"Welkenraedt",
    "sg:classifiers":[
        {
            "category":"Building & Trades",
            "subcategory":"Construction",
            "type":"Services"
        }
    ],
    "sg:phone":"+32 87 89 80 80",
    "sg:postcode":"4840",
    "sg:province":"Li\u00e8ge",
    "sg:tags":[
        "truss-makers"
    ],
    "wof:name":"Instrumentation Difra Sa",
    "wof:placetype":"venue"
},
  "geometry": {"coordinates":[5.9665780067,50.6593170166],"type":"Point"}
}