{
  "type": "Feature",
  "properties": {
    "iso:country":"BE",
    "sg:address":"Rue De L'industrie 1",
    "sg:city":"Nijvel",
    "sg:orig_category":"Meubles de bureaux and de magasins Fab",
    "sg:phone":"+32 67 22 09 50",
    "sg:postcode":"1400",
    "sg:province":"Brabant Wallon",
    "wof:name":"A.p.s. Nivelles",
    "wof:placetype":"venue"
},
  "geometry": {"coordinates":[4.3598999977,50.5962753296],"type":"Point"}
}