{
  "type": "Feature",
  "properties": {
    "iso:country":"BE",
    "sg:address":"Leuvensesteenweg 317",
    "sg:city":"Kortenberg",
    "sg:classifiers":[
        {
            "category":"Bars & Pubs",
            "type":"Food & Drink"
        }
    ],
    "sg:phone":"+32 2 759 69 35",
    "sg:postcode":"3070",
    "sg:province":"Vlaams-Brabant",
    "wof:name":"Novy",
    "wof:placetype":"venue"
},
  "geometry": {"coordinates":[4.5390357971,50.8871231079],"type":"Point"}
}