{
  "type": "Feature",
  "properties": {
    "iso:country":"BE",
    "sg:address":"Mechelbaan 51b",
    "sg:city":"Booischot",
    "sg:classifiers":[
        {
            "category":"Professional",
            "type":"Services"
        }
    ],
    "sg:phone":"+32 15 22 14 82",
    "sg:postcode":"2221",
    "sg:province":"Antwerpen",
    "sg:tags":[
        "transport"
    ],
    "wof:name":"Firma J. Vertommen & Co B.v.b.a.",
    "wof:placetype":"venue"
},
  "geometry": {"coordinates":[4.7549748421,51.0520324707],"type":"Point"}
}