{
  "type": "Feature",
  "properties": {
    "iso:country":"BE",
    "sg:address":"Chauss\u00e9e De Helmet 324",
    "sg:city":"Bruxelles (schaerbeek)",
    "sg:classifiers":[
        {
            "category":"Shopping",
            "subcategory":"Bicycles & Sporting Goods",
            "type":"Retail Goods"
        }
    ],
    "sg:phone":"+32 2 216 56 01",
    "sg:postcode":"1030",
    "sg:province":"Bruxelles-Capitale",
    "sg:tags":[
        "sport",
        "-"
    ],
    "wof:name":"Hobby Sports",
    "wof:placetype":"venue"
},
  "geometry": {"coordinates":[4.3900980949,50.8751106262],"type":"Point"}
}