{
  "type": "Feature",
  "properties": {
    "addr:full":"Quai De Rome 7-72 Li\u00e8ge 1 Li\u00e8ge 4000",
    "addr:housenumber":"7-72;1",
    "addr:postcode":"4000",
    "addr:street":"Quai De Rome",
    "iso:country":"BE",
    "sg:address":"Quai De Rome 7-72",
    "sg:city":"Li\u00e8ge 1",
    "sg:classifiers":[
        {
            "category":"Health Services",
            "subcategory":"Health Practitioner",
            "type":"Services"
        }
    ],
    "sg:phone":"+32 4 252 98 86",
    "sg:postcode":"4000",
    "sg:province":"Li\u00e8ge",
    "sg:tags":[
        "physiotherapist"
    ],
    "wof:name":"Carlier Jacques",
    "wof:placetype":"venue"
},
  "geometry": {"coordinates":[5.5738840103,50.6262321472],"type":"Point"}
}