{
  "type": "Feature",
  "properties": {
    "addr:full":"Vilvoordse Baan 25 Herent (winksele) Vlaams-Brabant 3020",
    "addr:housenumber":"25",
    "addr:postcode":"3020",
    "addr:street":"Vilvoordse Baan",
    "iso:country":"BE",
    "sg:address":"Vilvoordse Baan 25",
    "sg:city":"Herent (winksele)",
    "sg:classifiers":[
        {
            "category":"Health Services",
            "subcategory":"Dentist",
            "type":"Services"
        }
    ],
    "sg:phone":"+32 16 48 89 80",
    "sg:postcode":"3020",
    "sg:province":"Vlaams-Brabant",
    "wof:name":"Vermuyten J",
    "wof:placetype":"venue"
},
  "geometry": {"coordinates":[4.6749200821,50.9079055786],"type":"Point"}
}