{
  "type": "Feature",
  "properties": {
    "iso:country":"BE",
    "sg:address":"G. Van Der Steenstraat 5",
    "sg:city":"Lennik",
    "sg:orig_category":"Cabinets d\u00b4huissiers",
    "sg:phone":"+32 2 532 08 88",
    "sg:postcode":"1750",
    "sg:province":"Vlaams-Brabant",
    "wof:name":"Gerda Debremaeker",
    "wof:placetype":"venue"
},
  "geometry": {"coordinates":[4.1544370651,50.8050117493],"type":"Point"}
}