{
  "type": "Feature",
  "properties": {
    "iso:country":"BE",
    "sg:address":"Jacobuslei 10",
    "sg:city":"Brasschaat",
    "sg:orig_category":"M\u00e9decins and sp\u00e9cialistes",
    "sg:phone":"+32 3 664 60 56",
    "sg:postcode":"2930",
    "sg:province":"Antwerpen",
    "wof:name":"D. Peeraer",
    "wof:placetype":"venue"
},
  "geometry": {"coordinates":[4.4464111328,51.2942085266],"type":"Point"}
}