{
  "type": "Feature",
  "properties": {
    "iso:country":"BE",
    "sg:address":"Platolaan 2",
    "sg:city":"Evere/evere",
    "sg:orig_category":"Krantenwinkels Rookartikelen",
    "sg:phone":"+32 2 726 58 72",
    "sg:postcode":"1140",
    "sg:province":"Bruxelles-Capitale",
    "wof:name":"Librairie Platon",
    "wof:placetype":"venue"
},
  "geometry": {"coordinates":[4.4211292267,50.861492157],"type":"Point"}
}