{
  "type": "Feature",
  "properties": {
    "addr:full":"Avenue Moli\u00e8re 167 Bruxelles (forest) Bruxelles-Capitale 1190",
    "addr:housenumber":"167",
    "addr:postcode":"1190",
    "addr:street":"Avenue Molie\u0300Re",
    "iso:country":"BE",
    "sg:address":"Avenue Moli\u00e8re 167",
    "sg:city":"Bruxelles (forest)",
    "sg:classifiers":[
        {
            "category":"Personal",
            "subcategory":"Psychics & Astrologers",
            "type":"Services"
        }
    ],
    "sg:phone":"+32 2 343 34 15",
    "sg:postcode":"1190",
    "sg:province":"Bruxelles-Capitale",
    "sg:tags":[
        "astrology"
    ],
    "wof:name":"Widmer E",
    "wof:placetype":"venue"
},
  "geometry": {"coordinates":[4.3488202095,50.8161582947],"type":"Point"}
}