{
  "type": "Feature",
  "properties": {
    "addr:full":"Korenveld 9 Merksplas Antwerpen 2330",
    "addr:housenumber":"9",
    "addr:postcode":"2330",
    "addr:street":"Korenveld",
    "iso:country":"BE",
    "sg:address":"Korenveld 9",
    "sg:city":"Merksplas",
    "sg:orig_category":"Rev\u00eatements pour sols and murs",
    "sg:phone":"+32 14 63 56 18",
    "sg:postcode":"2330",
    "sg:province":"Antwerpen",
    "wof:name":"Van Looveren Guy",
    "wof:placetype":"venue"
},
  "geometry": {"coordinates":[4.846514225,51.3610496521],"type":"Point"}
}