{
  "type": "Feature",
  "properties": {
    "iso:country":"BE",
    "sg:address":"Rue Royale 40",
    "sg:city":"Tournai",
    "sg:classifiers":[
        {
            "category":"Bars & Pubs",
            "type":"Food & Drink"
        }
    ],
    "sg:phone":"+32 69 21 11 51",
    "sg:postcode":"7500",
    "sg:province":"Hainaut",
    "sg:tags":[
        "tavern"
    ],
    "wof:name":"Food'rolf (le)",
    "wof:placetype":"venue"
},
  "geometry": {"coordinates":[3.3929219246,50.6099624634],"type":"Point"}
}