{
  "type": "Feature",
  "properties": {
    "iso:country":"BE",
    "sg:address":"Linthout 3",
    "sg:city":"Aalst",
    "sg:orig_category":"Traitements param\u00e9dicaux",
    "sg:phone":"+32 53 70 31 12",
    "sg:postcode":"9300",
    "sg:province":"Oost-Vlaanderen",
    "wof:name":"De Pleister",
    "wof:placetype":"venue"
},
  "geometry": {"coordinates":[4.0800747871,50.930557251],"type":"Point"}
}