{
  "type": "Feature",
  "properties": {
    "iso:country":"BE",
    "sg:address":"Vestingstraat 74",
    "sg:city":"Antwerpen",
    "sg:orig_category":"Produits interm\u00e9diaires Gr",
    "sg:phone":"+32 3 231 48 15",
    "sg:postcode":"2018",
    "sg:province":"Antwerpen",
    "wof:name":"Reliana",
    "wof:placetype":"venue"
},
  "geometry": {"coordinates":[4.4201111794,51.2154541016],"type":"Point"}
}