{
  "type": "Feature",
  "properties": {
    "addr:full":"Everselstraat 141 Beringen Limburg 3580",
    "addr:housenumber":"141",
    "addr:postcode":"3580",
    "addr:street":"Everselstraat",
    "iso:country":"BE",
    "sg:address":"Everselstraat 141",
    "sg:city":"Beringen",
    "sg:orig_category":"DIENSTEN VOOR TELECOMMUNICATIE Elektriciteitsproductie and -distributie",
    "sg:phone":"+32 11 42 20 99",
    "sg:postcode":"3580",
    "sg:province":"Limburg",
    "wof:name":"Interelectra",
    "wof:placetype":"venue"
},
  "geometry": {"coordinates":[5.2289500237,51.0363235474],"type":"Point"}
}