{
  "type": "Feature",
  "properties": {
    "iso:country":"BE",
    "sg:address":"Vladslostraat 36",
    "sg:city":"Werken",
    "sg:classifiers":[
        {
            "category":"Shopping",
            "subcategory":"Crafts & Fabrics",
            "type":"Retail Goods"
        }
    ],
    "sg:phone":"+32 51 56 69 21",
    "sg:postcode":"8610",
    "sg:province":"West-Vlaanderen",
    "sg:tags":[
        "textile",
        "clothing"
    ],
    "wof:name":"A & A Demeulenaere & Co Nv",
    "wof:placetype":"venue"
},
  "geometry": {"coordinates":[2.958327055,51.0336151123],"type":"Point"}
}