{
  "type": "Feature",
  "properties": {
    "addr:full":"Rte De Ploegsteert 23 Comines Hainaut 7784",
    "addr:housenumber":"23",
    "addr:postcode":"7784",
    "addr:street":"Rte De Ploegsteert",
    "iso:country":"BE",
    "sg:address":"Rte De Ploegsteert 23",
    "sg:city":"Comines",
    "sg:classifiers":[
        {
            "category":"Travel",
            "subcategory":"Hotels & Motels",
            "type":"Entertainment"
        }
    ],
    "sg:phone":"+32 56 58 72 74",
    "sg:postcode":"7784",
    "sg:province":"Hainaut",
    "sg:tags":[
        "hotels",
        "business",
        "restaurant"
    ],
    "wof:name":"Pareyn Regis M.",
    "wof:placetype":"venue"
},
  "geometry": {"coordinates":[2.9317200184,50.7410202026],"type":"Point"}
}