{
  "type": "Feature",
  "properties": {
    "addr:full":"Beekstraat 3 Bertem (korbeek-dijle) Vlaams-Brabant 3060",
    "addr:housenumber":"3",
    "addr:postcode":"3060",
    "addr:street":"Beekstraat",
    "iso:country":"BE",
    "sg:address":"Beekstraat 3",
    "sg:city":"Bertem (korbeek-dijle)",
    "sg:classifiers":[
        {
            "category":"Retail",
            "subcategory":"Event Space",
            "type":"Services"
        }
    ],
    "sg:phone":"+32 16 47 90 86",
    "sg:postcode":"3060",
    "sg:province":"Vlaams-Brabant",
    "sg:tags":[
        "organisation"
    ],
    "wof:name":"Dewulf K",
    "wof:placetype":"venue"
},
  "geometry": {"coordinates":[4.6387691498,50.8370475769],"type":"Point"}
}