{
  "type": "Feature",
  "properties": {
    "addr:full":"Graaf Van Hoornlaan 9 Zwijndrecht Antwerpen 2070",
    "addr:housenumber":"9",
    "addr:postcode":"2070",
    "addr:street":"Graaf Van Hoornlaan",
    "iso:country":"BE",
    "sg:address":"Graaf Van Hoornlaan 9",
    "sg:city":"Zwijndrecht",
    "sg:classifiers":[
        {
            "category":"Banks & Credit Unions",
            "subcategory":"Investment Brokerage",
            "type":"Services"
        }
    ],
    "sg:phone":"+32 3 252 53 63",
    "sg:postcode":"2070",
    "sg:province":"Antwerpen",
    "sg:tags":[
        "rental",
        "-",
        "yacht",
        "boat",
        "pleasure"
    ],
    "wof:name":"Kano & Kayak Pat",
    "wof:placetype":"venue"
},
  "geometry": {"coordinates":[4.3161401749,51.2217102051],"type":"Point"}
}