{
  "type": "Feature",
  "properties": {
    "addr:full":"Place Saint-pierre 41 Etterbeek/etterbeek Bruxelles-Capitale 1040",
    "addr:housenumber":"41",
    "addr:postcode":"1040",
    "addr:street":"Place Saint-Pierre",
    "iso:country":"BE",
    "sg:address":"Place Saint-pierre 41",
    "sg:city":"Etterbeek/etterbeek",
    "sg:orig_category":"Drogueries",
    "sg:phone":"+32 2 733 58 21",
    "sg:postcode":"1040",
    "sg:province":"Bruxelles-Capitale",
    "wof:name":"Au Grd St.pierre",
    "wof:placetype":"venue"
},
  "geometry": {"coordinates":[4.3955402374,50.837436676],"type":"Point"}
}