{
  "type": "Feature",
  "properties": {
    "addr:full":"Wolvendreef 12 Kortrijk West-Vlaanderen 8500",
    "addr:housenumber":"12",
    "addr:postcode":"8500",
    "addr:street":"Wolvendreef",
    "iso:country":"BE",
    "sg:address":"Wolvendreef 12",
    "sg:city":"Kortrijk",
    "sg:orig_category":"G\u00e9om\u00e8tres",
    "sg:phone":"+32 56 22 53 54",
    "sg:postcode":"8500",
    "sg:province":"West-Vlaanderen",
    "wof:name":"Willy W. Lapere",
    "wof:placetype":"venue"
},
  "geometry": {"coordinates":[3.2635109425,50.8122711182],"type":"Point"}
}