{
  "type": "Feature",
  "properties": {
    "addr:full":"Rue Doyard 4 Wanze (vinalmont) Li\u00e8ge 4520",
    "addr:housenumber":"4",
    "addr:postcode":"4520",
    "addr:street":"Rue Doyard",
    "iso:country":"BE",
    "sg:address":"Rue Doyard 4",
    "sg:city":"Wanze (vinalmont)",
    "sg:classifiers":[
        {
            "category":"Communications",
            "type":"Services"
        }
    ],
    "sg:phone":"+32 85 21 51 42",
    "sg:postcode":"4520",
    "sg:province":"Li\u00e8ge",
    "sg:tags":[
        "translator"
    ],
    "wof:name":"Paczecha O",
    "wof:placetype":"venue"
},
  "geometry": {"coordinates":[5.2139430046,50.5367546082],"type":"Point"}
}