{
  "type": "Feature",
  "properties": {
    "iso:country":"BE",
    "sg:address":"Rue Joseph Wauters 1",
    "sg:city":"Anderlues",
    "sg:orig_category":"Banken and kredietinstellingen",
    "sg:phone":"+32 71 52 50 71",
    "sg:postcode":"6150",
    "sg:province":"Hainaut",
    "wof:name":"Citibank",
    "wof:placetype":"venue"
},
  "geometry": {"coordinates":[4.2698740959,50.4083061218],"type":"Point"}
}