{
  "type": "Feature",
  "properties": {
    "addr:full":"Molenbergstraat 5 Dilbeek Vlaams-Brabant 1700",
    "addr:housenumber":"5",
    "addr:postcode":"1700",
    "addr:street":"Molenbergstraat",
    "iso:country":"BE",
    "sg:address":"Molenbergstraat 5",
    "sg:city":"Dilbeek",
    "sg:classifiers":[
        {
            "category":"Cafe",
            "type":"Food & Drink"
        }
    ],
    "sg:phone":"+32 2 569 35 42",
    "sg:postcode":"1700",
    "sg:province":"Vlaams-Brabant",
    "sg:tags":[
        "caf\u00e9s"
    ],
    "wof:name":"De Plezanten Hoek",
    "wof:placetype":"venue"
},
  "geometry": {"coordinates":[4.2566680908,50.8436279297],"type":"Point"}
}