{
  "type": "Feature",
  "properties": {
    "addr:full":"Rue Du Pont 1 Comblain-au-pont Li\u00e8ge 4170",
    "addr:housenumber":"1",
    "addr:postcode":"4170",
    "addr:street":"Rue Du Pont",
    "iso:country":"BE",
    "sg:address":"Rue Du Pont 1",
    "sg:city":"Comblain-au-pont",
    "sg:orig_category":"Pain, p\u00e2tisseries and confiseries",
    "sg:phone":"+32 4 369 10 54",
    "sg:postcode":"4170",
    "sg:province":"Li\u00e8ge",
    "wof:name":"Boulangerie Louviaux",
    "wof:placetype":"venue"
},
  "geometry": {"coordinates":[5.5890431404,50.4796104431],"type":"Point"}
}