{
  "type": "Feature",
  "properties": {
    "iso:country":"BE",
    "sg:address":"Rue Du Bosquet 7-p S De Einstein",
    "sg:city":"Louvain-la-neuve",
    "sg:orig_category":"Geiger Counters, Geiger-M\u00fcller Counters",
    "sg:phone":"+32 10 45 63 34",
    "sg:postcode":"1348",
    "sg:province":"Brabant Wallon",
    "wof:name":"Hamamatsu Photonics Belgium S.a.",
    "wof:placetype":"venue"
},
  "geometry": {"coordinates":[4.6171450615,50.670124054],"type":"Point"}
}