{
  "type": "Feature",
  "properties": {
    "addr:full":"Barelstraat 125 Bornem Antwerpen 2880",
    "addr:housenumber":"125",
    "addr:postcode":"2880",
    "addr:street":"Barelstraat",
    "iso:country":"BE",
    "sg:address":"Barelstraat 125",
    "sg:city":"Bornem",
    "sg:classifiers":[
        {
            "category":"Freight",
            "type":"Transportation"
        }
    ],
    "sg:phone":"+32 3 889 07 61",
    "sg:postcode":"2880",
    "sg:province":"Antwerpen",
    "sg:tags":[
        "-",
        "transport"
    ],
    "wof:name":"De Smet J & Co Transportbedrij Bvba",
    "wof:placetype":"venue"
},
  "geometry": {"coordinates":[4.2334499359,51.0913314819],"type":"Point"}
}