{
  "type": "Feature",
  "properties": {
    "iso:country":"BE",
    "sg:address":"Zandvoortstraat 35",
    "sg:city":"Heist-op-den-berg",
    "sg:classifiers":[
        {
            "category":"Organizations",
            "subcategory":"Professional Association",
            "type":"Services"
        }
    ],
    "sg:phone":"+32 15 24 73 70",
    "sg:postcode":"2220",
    "sg:province":"Antwerpen",
    "sg:tags":[
        "artist",
        "make-up"
    ],
    "wof:name":"Alle Smoelwerk",
    "wof:placetype":"venue"
},
  "geometry": {"coordinates":[4.7282481194,51.074672699],"type":"Point"}
}