{
  "type": "Feature",
  "properties": {
    "addr:full":"Rue Du Monument 21 Hotton Luxembourg 6990",
    "addr:housenumber":"21",
    "addr:postcode":"6990",
    "addr:street":"Rue Du Monument",
    "iso:country":"BE",
    "sg:address":"Rue Du Monument 21",
    "sg:city":"Hotton",
    "sg:orig_category":"Entretien and r\u00e9parations de voitures",
    "sg:phone":"+32 84 46 64 96",
    "sg:postcode":"6990",
    "sg:province":"Luxembourg",
    "wof:name":"Garage Henrotin",
    "wof:placetype":"venue"
},
  "geometry": {"coordinates":[5.3955998421,50.3066596985],"type":"Point"}
}