{
  "type": "Feature",
  "properties": {
    "addr:full":"Industrieweg 1506 Herk-de-stad Limburg 3540",
    "addr:housenumber":"1506",
    "addr:postcode":"3540",
    "addr:street":"Industrieweg",
    "iso:country":"BE",
    "sg:address":"Industrieweg 1506",
    "sg:city":"Herk-de-stad",
    "sg:classifiers":[
        {
            "category":"Utilities",
            "subcategory":"Telephone",
            "type":"Services"
        }
    ],
    "sg:phone":"+32 13 53 91 10",
    "sg:postcode":"3540",
    "sg:province":"Limburg",
    "sg:tags":[
        "-",
        "internet"
    ],
    "wof:name":"Cats & Dogs Bvba",
    "wof:placetype":"venue"
},
  "geometry": {"coordinates":[5.1660761833,50.9481277466],"type":"Point"}
}