{
  "type": "Feature",
  "properties": {
    "addr:full":"Tenbosch 128 Elsene/ixelles Bruxelles-Capitale 1050",
    "addr:housenumber":"128",
    "addr:postcode":"1050",
    "addr:street":"Tenbosch",
    "iso:country":"BE",
    "sg:address":"Tenbosch 128",
    "sg:city":"Elsene/ixelles",
    "sg:orig_category":"M\u00e9decins and sp\u00e9cialistes",
    "sg:phone":"+32 2 343 09 83",
    "sg:postcode":"1050",
    "sg:province":"Bruxelles-Capitale",
    "wof:name":"C. Lefebvre",
    "wof:placetype":"venue"
},
  "geometry": {"coordinates":[4.3604211807,50.8203735352],"type":"Point"}
}