{
  "type": "Feature",
  "properties": {
    "iso:country":"BE",
    "sg:address":"Rue Fran\u00c7ois Lefebvre",
    "sg:city":"Rocourt",
    "sg:orig_category":"Rookartikelen",
    "sg:phone":"+32 4 278 21 00",
    "sg:postcode":"4000",
    "sg:province":"Li\u00e8ge",
    "wof:name":"Complexe Appui Logis.sud",
    "wof:placetype":"venue"
},
  "geometry": {"coordinates":[5.5469298363,50.6784591675],"type":"Point"}
}