{
  "type": "Feature",
  "properties": {
    "iso:country":"BE",
    "sg:address":"Rue Des Hirondelles 4",
    "sg:city":"Bruxelles",
    "sg:classifiers":[
        {
            "category":"Manufacturing",
            "subcategory":"Building Materials",
            "type":"Manufacturing & Wholesale Goods"
        }
    ],
    "sg:phone":"+32 2 218 28 47",
    "sg:postcode":"1000",
    "sg:province":"Bruxelles-Capitale",
    "sg:tags":[
        "wig",
        "hairworks"
    ],
    "wof:name":"Stroobants C",
    "wof:placetype":"venue"
},
  "geometry": {"coordinates":[4.3526968956,50.8520202637],"type":"Point"}
}