{
  "type": "Feature",
  "properties": {
    "addr:full":"Winston Churchilllaan 180 Ukkel/uccle Bruxelles-Capitale 1180",
    "addr:housenumber":"180",
    "addr:postcode":"1180",
    "addr:street":"Winston Churchilllaan;/",
    "iso:country":"BE",
    "sg:address":"Winston Churchilllaan 180",
    "sg:city":"Ukkel/uccle",
    "sg:orig_category":"Antiek",
    "sg:phone":"+32 2 344 15 07",
    "sg:postcode":"1180",
    "sg:province":"Bruxelles-Capitale",
    "wof:name":"Hendrickx-delattre",
    "wof:placetype":"venue"
},
  "geometry": {"coordinates":[4.3601841927,50.8115692139],"type":"Point"}
}