{
  "type": "Feature",
  "properties": {
    "iso:country":"BE",
    "sg:address":"Rue Alexandre Daoust 6",
    "sg:city":"Dinant",
    "sg:classifiers":[
        {
            "category":"Health Services",
            "subcategory":"Dentist",
            "type":"Services"
        }
    ],
    "sg:phone":"+32 82 22 63 42",
    "sg:postcode":"5500",
    "sg:province":"Namur",
    "wof:name":"Jadoul Fr\u00e9d\u00e9ric",
    "wof:placetype":"venue"
},
  "geometry": {"coordinates":[4.9173498154,50.2538986206],"type":"Point"}
}