{
  "type": "Feature",
  "properties": {
    "addr:full":"Rue Des Barbouillons 7ba Daverdisse Luxembourg 6929",
    "addr:housenumber":"7ba",
    "addr:postcode":"6929",
    "addr:street":"Rue Des Barbouillons",
    "iso:country":"BE",
    "sg:address":"Rue Des Barbouillons 7ba",
    "sg:city":"Daverdisse",
    "sg:orig_category":"Plomberie, chauffage and installations sanitaires",
    "sg:phone":"+32 84 38 98 26",
    "sg:postcode":"6929",
    "sg:province":"Luxembourg",
    "wof:name":"Jacquemart Et Cie",
    "wof:placetype":"venue"
},
  "geometry": {"coordinates":[5.1203069687,50.0199661255],"type":"Point"}
}