{
  "type": "Feature",
  "properties": {
    "iso:country":"BE",
    "sg:address":"Rue Cardinal Mercier",
    "sg:city":"Mouscron (dottignies)",
    "sg:classifiers":[
        {
            "category":"Food & Beverages",
            "subcategory":"Fruits & Vegetables",
            "type":"Retail Goods"
        }
    ],
    "sg:phone":"+32 56 48 96 84",
    "sg:postcode":"7711",
    "sg:province":"Hainaut",
    "sg:tags":[
        "-"
    ],
    "wof:name":"Rasson R",
    "wof:placetype":"venue"
},
  "geometry": {"coordinates":[3.3017849922,50.7259140015],"type":"Point"}
}