{
  "type": "Feature",
  "properties": {
    "iso:country":"BE",
    "sg:address":"Plaats 26",
    "sg:city":"Heuvelland",
    "sg:orig_category":"Epiceries",
    "sg:phone":"+32 57 44 51 95",
    "sg:postcode":"8951",
    "sg:province":"West-Vlaanderen",
    "wof:name":"Fa. Wittouck-pauwels",
    "wof:placetype":"venue"
},
  "geometry": {"coordinates":[2.7836260796,50.7659416199],"type":"Point"}
}