{
  "type": "Feature",
  "properties": {
    "addr:full":"Place Paul Henri Jouret 5 Flobecq Hainaut 7880",
    "addr:housenumber":"5",
    "addr:postcode":"7880",
    "addr:street":"Place Paul Henri Jouret;Hainaut",
    "iso:country":"BE",
    "sg:address":"Place Paul Henri Jouret 5",
    "sg:city":"Flobecq",
    "sg:classifiers":[
        {
            "category":"Building & Trades",
            "subcategory":"Plumbing",
            "type":"Services"
        }
    ],
    "sg:phone":"+32 68 44 77 55",
    "sg:postcode":"7880",
    "sg:province":"Hainaut",
    "sg:tags":[
        "repair",
        "mainten",
        "-",
        "central",
        "heating"
    ],
    "wof:name":"Marbaix D",
    "wof:placetype":"venue"
},
  "geometry": {"coordinates":[3.7449998856,50.7372322083],"type":"Point"}
}