{
  "type": "Feature",
  "properties": {
    "iso:country":"BE",
    "sg:address":"Rue Du Wainage 194",
    "sg:city":"Fleurus",
    "sg:classifiers":[
        {
            "category":"Arena",
            "subcategory":"Sports Club",
            "type":"Entertainment"
        }
    ],
    "sg:phone":"+32 71 82 03 38",
    "sg:postcode":"6220",
    "sg:province":"Hainaut",
    "sg:tags":[
        "terrain",
        "hors",
        "de",
        "installation",
        "sportifs"
    ],
    "wof:name":"Salle Omnisports Hordies",
    "wof:placetype":"venue"
},
  "geometry": {"coordinates":[4.5590610504,50.4568862915],"type":"Point"}
}