{
  "type": "Feature",
  "properties": {
    "addr:full":"Rue De Renoupr\u00c9 58 Verviers Li\u00e8ge 4800",
    "addr:housenumber":"58",
    "addr:postcode":"4800",
    "addr:street":"Rue De Renoupre\u0301",
    "iso:country":"BE",
    "sg:address":"Rue De Renoupr\u00c9 58",
    "sg:city":"Verviers",
    "sg:classifiers":[
        {
            "category":"Sports & Exercise",
            "subcategory":"Sports Center",
            "type":"Entertainment"
        }
    ],
    "sg:phone":"+32 87 39 20 00",
    "sg:postcode":"4800",
    "sg:province":"Li\u00e8ge",
    "sg:tags":[
        "terrain",
        "hors",
        "de",
        "installation",
        "sportifs"
    ],
    "wof:name":"Kart 2000",
    "wof:placetype":"venue"
},
  "geometry": {"coordinates":[5.8841900826,50.6034889221],"type":"Point"}
}