{
  "type": "Feature",
  "properties": {
    "iso:country":"BE",
    "sg:address":"Bronstraat 54",
    "sg:city":"Oudenaarde",
    "sg:orig_category":"Eleveurs de bovins",
    "sg:phone":"+32 55 45 55 15",
    "sg:postcode":"9700",
    "sg:province":"Oost-Vlaanderen",
    "wof:name":"Jozef Dolvelde",
    "wof:placetype":"venue"
},
  "geometry": {"coordinates":[3.6632859707,50.8551254272],"type":"Point"}
}