{
  "type": "Feature",
  "properties": {
    "iso:country":"BE",
    "sg:address":"Rue Des Carri\u00c8res 57",
    "sg:city":"Charleroi",
    "sg:orig_category":"Woningbouw",
    "sg:phone":"+32 71 34 03 67",
    "sg:postcode":"6040",
    "sg:province":"Hainaut",
    "wof:name":"Ruddy Vannuscoprs",
    "wof:placetype":"venue"
},
  "geometry": {"coordinates":[4.4485330582,50.4468765259],"type":"Point"}
}