{
  "type": "Feature",
  "properties": {
    "iso:country":"BE",
    "sg:address":"Zuiderdijk 6a",
    "sg:city":"Rijkevorsel",
    "sg:classifiers":[
        {
            "category":"Building & Trades",
            "subcategory":"Pest Control",
            "type":"Services"
        }
    ],
    "sg:phone":"+32 3 311 62 22",
    "sg:postcode":"2310",
    "sg:province":"Antwerpen",
    "sg:tags":[
        "drive",
        "chain"
    ],
    "wof:name":"Torremans",
    "wof:placetype":"venue"
},
  "geometry": {"coordinates":[4.7771391869,51.3282356262],"type":"Point"}
}