{
  "type": "Feature",
  "properties": {
    "addr:full":"Rue De Cond\u00c9 45 Leuze-en-hainaut Hainaut 7900",
    "addr:housenumber":"45",
    "addr:postcode":"7900",
    "addr:street":"Rue De Conde\u0301",
    "iso:country":"BE",
    "sg:address":"Rue De Cond\u00c9 45",
    "sg:city":"Leuze-en-hainaut",
    "sg:orig_category":"Banken and kredietinstellingen",
    "sg:phone":"+32 69 66 31 22",
    "sg:postcode":"7900",
    "sg:province":"Hainaut",
    "wof:name":"Bbl",
    "wof:placetype":"venue"
},
  "geometry": {"coordinates":[3.6174590588,50.5961074829],"type":"Point"}
}