{
  "type": "Feature",
  "properties": {
    "iso:country":"BE",
    "sg:address":"Garzebekeveldstraat 24",
    "sg:city":"De Panne",
    "sg:orig_category":"Rookartikelen",
    "sg:phone":"+32 58 42 27 03",
    "sg:postcode":"8660",
    "sg:province":"West-Vlaanderen",
    "wof:name":"Huis All Tabacco",
    "wof:placetype":"venue"
},
  "geometry": {"coordinates":[2.5873849392,51.0955162048],"type":"Point"}
}