{
  "type": "Feature",
  "properties": {
    "iso:country":"BE",
    "sg:address":"Albertlei 22",
    "sg:city":"Kontich",
    "sg:classifiers":[
        {
            "category":"Building & Trades",
            "subcategory":"Landscaping Services",
            "type":"Services"
        }
    ],
    "sg:phone":"+32 3 458 39 43",
    "sg:postcode":"2550",
    "sg:province":"Antwerpen",
    "sg:tags":[
        "gardening",
        "garden",
        "maintenance"
    ],
    "wof:name":"Van Der Vorst L",
    "wof:placetype":"venue"
},
  "geometry": {"coordinates":[4.4387898445,51.1364135742],"type":"Point"}
}