{
  "type": "Feature",
  "properties": {
    "addr:full":"Driesstraat 46 Zingem Oost-Vlaanderen 9750",
    "addr:housenumber":"46",
    "addr:postcode":"9750",
    "addr:street":"Driesstraat",
    "iso:country":"BE",
    "sg:address":"Driesstraat 46",
    "sg:city":"Zingem",
    "sg:orig_category":"Jardinage",
    "sg:phone":"+32 9 383 63 57",
    "sg:postcode":"9750",
    "sg:province":"Oost-Vlaanderen",
    "wof:name":"Polfilet",
    "wof:placetype":"venue"
},
  "geometry": {"coordinates":[3.5857989788,50.8952293396],"type":"Point"}
}