{
  "type": "Feature",
  "properties": {
    "addr:full":"Rue Joseph Muller 1 Dalhem Li\u00e8ge 4608",
    "addr:housenumber":"1",
    "addr:postcode":"4608",
    "addr:street":"Rue Joseph Muller",
    "iso:country":"BE",
    "sg:address":"Rue Joseph Muller 1",
    "sg:city":"Dalhem",
    "sg:orig_category":"Boucheries",
    "sg:phone":"+32 4 376 60 22",
    "sg:postcode":"4608",
    "sg:province":"Li\u00e8ge",
    "wof:name":"Tossens E.",
    "wof:placetype":"venue"
},
  "geometry": {"coordinates":[5.7678408623,50.7354278564],"type":"Point"}
}