{
  "type": "Feature",
  "properties": {
    "addr:full":"Cond\u00c9dreef 27 Kortrijk West-Vlaanderen 8500",
    "addr:housenumber":"27",
    "addr:postcode":"8500",
    "addr:street":"Conde\u0301Dreef",
    "iso:country":"BE",
    "sg:address":"Cond\u00c9dreef 27",
    "sg:city":"Kortrijk",
    "sg:orig_category":"Installation de menuiserie en bois and plastique",
    "sg:phone":"+32 56 25 29 92",
    "sg:postcode":"8500",
    "sg:province":"West-Vlaanderen",
    "wof:name":"Sanctobin L",
    "wof:placetype":"venue"
},
  "geometry": {"coordinates":[3.2586610317,50.8191375732],"type":"Point"}
}