{
  "type": "Feature",
  "properties": {
    "addr:full":"Brusselsesteenweg 355 Asse Vlaams-Brabant 1730",
    "addr:housenumber":"355",
    "addr:postcode":"1730",
    "addr:street":"Brusselsesteenweg",
    "iso:country":"BE",
    "sg:address":"Brusselsesteenweg 355",
    "sg:city":"Asse",
    "sg:orig_category":"Woningbouw",
    "sg:phone":"+32 2 452 64 92",
    "sg:postcode":"1730",
    "sg:province":"Vlaams-Brabant",
    "wof:name":"Brab. Aannemingswerken",
    "wof:placetype":"venue"
},
  "geometry": {"coordinates":[4.2377400398,50.8961982727],"type":"Point"}
}