{
  "type": "Feature",
  "properties": {
    "addr:full":"Leuvensebn 239b Huldenberg Vlaams-Brabant 3040",
    "addr:housenumber":"239b",
    "addr:postcode":"3040",
    "iso:country":"BE",
    "sg:address":"Leuvensebn 239b",
    "sg:city":"Huldenberg",
    "sg:classifiers":[
        {
            "category":"Building & Trades",
            "subcategory":"Landscaping Services",
            "type":"Services"
        }
    ],
    "sg:phone":"+32 16 47 73 58",
    "sg:postcode":"3040",
    "sg:province":"Vlaams-Brabant",
    "sg:tags":[
        "gardening",
        "garden",
        "maintenance"
    ],
    "wof:name":"Depr\u00e9 P",
    "wof:placetype":"venue"
},
  "geometry": {"coordinates":[4.6322388649,50.7764396667],"type":"Point"}
}