{
  "type": "Feature",
  "properties": {
    "addr:full":"Avenue Gaston Biernaux 32 Pecq Hainaut 7740",
    "addr:housenumber":"32",
    "addr:postcode":"7740",
    "addr:street":"Avenue Gaston Biernaux",
    "iso:country":"BE",
    "sg:address":"Avenue Gaston Biernaux 32",
    "sg:city":"Pecq",
    "sg:classifiers":[
        {
            "category":"Health Services",
            "subcategory":"Dentist",
            "type":"Services"
        }
    ],
    "sg:phone":"+32 69 55 62 03",
    "sg:postcode":"7740",
    "sg:province":"Hainaut",
    "wof:name":"Freteur Beatrice",
    "wof:placetype":"venue"
},
  "geometry": {"coordinates":[3.3359339237,50.6880645752],"type":"Point"}
}