{
  "type": "Feature",
  "properties": {
    "addr:full":"Kortrijksepoortstraat 29 Gent Oost-Vlaanderen 9000",
    "addr:housenumber":"29",
    "addr:postcode":"9000",
    "addr:street":"Kortrijksepoortstraat;Oost-Vlaanderen",
    "iso:country":"BE",
    "sg:address":"Kortrijksepoortstraat 29",
    "sg:city":"Gent",
    "sg:classifiers":[
        {
            "category":"Real Estate",
            "subcategory":"Architect",
            "type":"Services"
        }
    ],
    "sg:phone":"+32 9 223 26 17",
    "sg:postcode":"9000",
    "sg:province":"Oost-Vlaanderen",
    "wof:name":"Van Gorp V",
    "wof:placetype":"venue"
},
  "geometry": {"coordinates":[3.7223320007,51.0457649231],"type":"Point"}
}