{
  "type": "Feature",
  "properties": {
    "addr:full":"Avenue Du Marouset 87 Braine-le-comte Hainaut 7090",
    "addr:housenumber":"87",
    "addr:postcode":"7090",
    "addr:street":"Avenue Du Marouset",
    "iso:country":"BE",
    "sg:address":"Avenue Du Marouset 87",
    "sg:city":"Braine-le-comte",
    "sg:classifiers":[
        {
            "category":"Freight",
            "type":"Transportation"
        }
    ],
    "sg:phone":"+32 67 55 77 41",
    "sg:postcode":"7090",
    "sg:province":"Hainaut",
    "sg:tags":[
        "-",
        "transport"
    ],
    "wof:name":"Mecatrans",
    "wof:placetype":"venue"
},
  "geometry": {"coordinates":[4.1634578705,50.6083183289],"type":"Point"}
}