{
  "type": "Feature",
  "properties": {
    "addr:full":"Eendenplasstraat 41 Evergem Oost-Vlaanderen 9940",
    "addr:housenumber":"41",
    "addr:postcode":"9940",
    "addr:street":"Eendenplasstraat;Oost-Vlaanderen",
    "iso:country":"BE",
    "sg:address":"Eendenplasstraat 41",
    "sg:city":"Evergem",
    "sg:orig_category":"Elektrische installaties voor woningen",
    "sg:phone":"+32 9 357 59 01",
    "sg:postcode":"9940",
    "sg:province":"Oost-Vlaanderen",
    "wof:name":"Gilbert D'hooge",
    "wof:placetype":"venue"
},
  "geometry": {"coordinates":[3.7160129547,51.1209030151],"type":"Point"}
}