{
  "type": "Feature",
  "properties": {
    "addr:full":"Avenue Paul Pastur 41 Charleroi Hainaut 6030",
    "addr:housenumber":"41",
    "addr:postcode":"6030",
    "addr:street":"Avenue Paul Pastur;Hainaut",
    "iso:country":"BE",
    "sg:address":"Avenue Paul Pastur 41",
    "sg:city":"Charleroi",
    "sg:classifiers":[
        {
            "category":"Arena",
            "subcategory":"Sports Club",
            "type":"Entertainment"
        }
    ],
    "sg:phone":"+32 71 21 59 62",
    "sg:postcode":"6030",
    "sg:province":"Hainaut",
    "sg:tags":[
        "terrain",
        "hors",
        "de",
        "installation",
        "sportifs"
    ],
    "wof:name":"Vanegdom",
    "wof:placetype":"venue"
},
  "geometry": {"coordinates":[4.3946180344,50.3941040039],"type":"Point"}
}