{
  "type": "Feature",
  "properties": {
    "addr:full":"Meldertstraat 42 Hasselt Limburg 3500",
    "addr:housenumber":"42",
    "addr:postcode":"3500",
    "addr:street":"Meldertstraat",
    "iso:country":"BE",
    "sg:address":"Meldertstraat 42",
    "sg:city":"Hasselt",
    "sg:classifiers":[
        {
            "category":"Bars & Pubs",
            "type":"Food & Drink"
        }
    ],
    "sg:phone":"+32 11 24 20 04",
    "sg:postcode":"3500",
    "sg:province":"Limburg",
    "wof:name":"Caf\u00e9 Caf\u00e9",
    "wof:placetype":"venue"
},
  "geometry": {"coordinates":[5.3424119949,50.9312515259],"type":"Point"}
}