{
  "type": "Feature",
  "properties": {
    "iso:country":"BE",
    "sg:address":"Dessus De La Ville 3",
    "sg:city":"Couvin",
    "sg:classifiers":[
        {
            "category":"Education",
            "subcategory":"School",
            "type":"Public Place"
        }
    ],
    "sg:phone":"+32 60 34 54 60",
    "sg:postcode":"5660",
    "sg:province":"Namur",
    "sg:tags":[
        "boarding"
    ],
    "wof:name":"Internat Auton Pr Jeunes Gens",
    "wof:placetype":"venue"
},
  "geometry": {"coordinates":[4.4909648895,50.0502090454],"type":"Point"}
}