{
  "type": "Feature",
  "properties": {
    "iso:country":"BE",
    "sg:address":"Rue Max Buset 30",
    "sg:city":"Fl\u00e9malle (ivoz-ramet)",
    "sg:classifiers":[
        {
            "category":"Building & Trades",
            "subcategory":"Landscaping Services",
            "type":"Services"
        }
    ],
    "sg:phone":"+32 497 31 89 53",
    "sg:postcode":"4400",
    "sg:province":"Li\u00e8ge",
    "sg:tags":[
        "-",
        "lopping",
        "work",
        "tree",
        "felling"
    ],
    "wof:name":"Nijsten R",
    "wof:placetype":"venue"
},
  "geometry": {"coordinates":[5.4239201546,50.5813980103],"type":"Point"}
}