{
  "type": "Feature",
  "properties": {
    "addr:full":"Rue Des Goutteaux 50 Charleroi (ransart) Hainaut 6043",
    "addr:housenumber":"50",
    "addr:postcode":"6043",
    "addr:street":"Rue Des Goutteaux",
    "iso:country":"BE",
    "sg:address":"Rue Des Goutteaux 50",
    "sg:city":"Charleroi (ransart)",
    "sg:classifiers":[
        {
            "category":"Parking",
            "subcategory":"Lot",
            "type":"Transportation"
        }
    ],
    "sg:phone":"+32 71 35 83 70",
    "sg:postcode":"6043",
    "sg:province":"Hainaut",
    "sg:tags":[
        "armoured",
        "door",
        "fireproof"
    ],
    "wof:name":"E.p.",
    "wof:placetype":"venue"
},
  "geometry": {"coordinates":[4.408343792,50.4378929138],"type":"Point"}
}