{
  "type": "Feature",
  "properties": {
    "addr:full":"Avenue Jean Dubrucq 63 Sint-jans-molenbeek/molenbeek-saint-jean Bruxelles-Capitale 1080",
    "addr:housenumber":"63",
    "addr:postcode":"1080",
    "addr:street":"Avenue Jean Dubrucq",
    "iso:country":"BE",
    "sg:address":"Avenue Jean Dubrucq 63",
    "sg:city":"Sint-jans-molenbeek/molenbeek-saint-jean",
    "sg:orig_category":"Maisons de repos and r\u00e9sidences",
    "sg:phone":"+32 2 427 98 16",
    "sg:postcode":"1080",
    "sg:province":"Bruxelles-Capitale",
    "wof:name":"Home Sequoia",
    "wof:placetype":"venue"
},
  "geometry": {"coordinates":[4.3351569176,50.8654174805],"type":"Point"}
}