{
  "type": "Feature",
  "properties": {
    "iso:country":"BE",
    "sg:address":"Rue De Mont 41",
    "sg:city":"Yvoir",
    "sg:orig_category":"Epiceries",
    "sg:phone":"+32 82 61 43 91",
    "sg:postcode":"5530",
    "sg:province":"Namur",
    "wof:name":"Poids D'or",
    "wof:placetype":"venue"
},
  "geometry": {"coordinates":[4.8743219376,50.3478965759],"type":"Point"}
}