{
  "type": "Feature",
  "properties": {
    "iso:country":"BE",
    "sg:address":"Rue Des Jardins 13",
    "sg:city":"Florenville (lacuisine)",
    "sg:classifiers":[
        {
            "category":"Arts & Performance",
            "subcategory":"Music",
            "type":"Entertainment"
        }
    ],
    "sg:phone":"+32 61 32 04 40",
    "sg:postcode":"6821",
    "sg:province":"Luxembourg",
    "sg:tags":[
        "freelance",
        "musician"
    ],
    "wof:name":"Genet C",
    "wof:placetype":"venue"
},
  "geometry": {"coordinates":[5.3184518814,49.7146644592],"type":"Point"}
}