{
  "type": "Feature",
  "properties": {
    "iso:country":"BE",
    "sg:address":"Rue Aux Fr\u00eanes 36",
    "sg:city":"Li\u00e8ge 1 (bressoux)",
    "sg:classifiers":[
        {
            "category":"Retail",
            "subcategory":"Veterinary Services",
            "type":"Services"
        }
    ],
    "sg:phone":"+32 4 342 92 36",
    "sg:postcode":"4020",
    "sg:province":"Li\u00e8ge",
    "sg:tags":[
        "veterinarian"
    ],
    "wof:name":"Beghin C",
    "wof:placetype":"venue"
},
  "geometry": {"coordinates":[5.59289217,50.6400718689],"type":"Point"}
}