{
  "type": "Feature",
  "properties": {
    "iso:country":"BE",
    "sg:address":"Stationstraat 4",
    "sg:city":"Ardooie",
    "sg:classifiers":[
        {
            "category":"Cafe",
            "type":"Food & Drink"
        }
    ],
    "sg:phone":"+32 51 74 83 50",
    "sg:postcode":"8850",
    "sg:province":"West-Vlaanderen",
    "sg:tags":[
        "caf\u00e9s"
    ],
    "wof:name":"Marijke Remmerie",
    "wof:placetype":"venue"
},
  "geometry": {"coordinates":[3.1989190578,50.9788513184],"type":"Point"}
}