{
  "type": "Feature",
  "properties": {
    "iso:country":"BE",
    "sg:address":"Van Hemelrijcklei 31",
    "sg:city":"Brasschaat",
    "sg:orig_category":"Sportclubs",
    "sg:phone":"+32 3 651 39 84",
    "sg:postcode":"2930",
    "sg:province":"Antwerpen",
    "wof:name":"V.c. Olvek Ekeren",
    "wof:placetype":"venue"
},
  "geometry": {"coordinates":[4.4942097664,51.2939300537],"type":"Point"}
}