{
  "type": "Feature",
  "properties": {
    "iso:country":"BE",
    "sg:address":"R Van Gaverstraat 63",
    "sg:city":"Gavere",
    "sg:orig_category":"D\u00e9molition d\u00b4immeubles and terrassements",
    "sg:phone":"+32 9 384 62 01",
    "sg:postcode":"9890",
    "sg:province":"Oost-Vlaanderen",
    "wof:name":"Heleyn W",
    "wof:placetype":"venue"
},
  "geometry": {"coordinates":[3.6698040962,50.9275054932],"type":"Point"}
}