{
  "type": "Feature",
  "properties": {
    "addr:full":"Rue De Gedinne 2 Gedinne Namur 5575",
    "addr:housenumber":"2",
    "addr:postcode":"5575",
    "addr:street":"Rue De Gedinne",
    "iso:country":"BE",
    "sg:address":"Rue De Gedinne 2",
    "sg:city":"Gedinne",
    "sg:classifiers":[
        {
            "category":"Education",
            "subcategory":"School",
            "type":"Public Place"
        }
    ],
    "sg:phone":"+32 61 58 93 84",
    "sg:postcode":"5575",
    "sg:province":"Namur",
    "sg:tags":[
        "primary"
    ],
    "wof:name":"Ecole De Sart-custinne",
    "wof:placetype":"venue"
},
  "geometry": {"coordinates":[4.9287548065,49.9885673523],"type":"Point"}
}