{
  "type": "Feature",
  "properties": {
    "iso:country":"BE",
    "sg:address":"Diepenbekerweg 51",
    "sg:city":"Hasselt",
    "sg:classifiers":[
        {
            "category":"Home & Garden",
            "subcategory":"Garden Supply",
            "type":"Retail Goods"
        }
    ],
    "sg:phone":"+32 11 24 11 00",
    "sg:postcode":"3500",
    "sg:province":"Limburg",
    "wof:name":"Vanstraelen-priori",
    "wof:placetype":"venue"
},
  "geometry": {"coordinates":[5.3699798584,50.923122406],"type":"Point"}
}