{
  "type": "Feature",
  "properties": {
    "iso:country":"BE",
    "sg:address":"Sint-antoniusstraat 22",
    "sg:city":"Kortenberg (meerbeek)",
    "sg:classifiers":[
        {
            "category":"Food & Beverages",
            "subcategory":"Groceries & Convenience Stores",
            "type":"Retail Goods"
        }
    ],
    "sg:phone":"+32 2 759 62 70",
    "sg:postcode":"3078",
    "sg:province":"Vlaams-Brabant",
    "sg:tags":[
        "grocer"
    ],
    "wof:name":"Giva (huis)",
    "wof:placetype":"venue"
},
  "geometry": {"coordinates":[4.5866189003,50.8816223145],"type":"Point"}
}