{
  "type": "Feature",
  "properties": {
    "iso:country":"BE",
    "sg:address":"Rue De La R\u00e9sistance 80b",
    "sg:city":"Binche (waudrez)",
    "sg:classifiers":[
        {
            "category":"Building & Trades",
            "subcategory":"Plumbing",
            "type":"Services"
        }
    ],
    "sg:phone":"+32 64 34 10 60",
    "sg:postcode":"7131",
    "sg:province":"Hainaut",
    "sg:tags":[
        "repair",
        "mainten",
        "-",
        "central",
        "heating"
    ],
    "wof:name":"Boudart Dominique Noel",
    "wof:placetype":"venue"
},
  "geometry": {"coordinates":[4.1633820534,50.3992881775],"type":"Point"}
}