{
  "type": "Feature",
  "properties": {
    "addr:full":"Rue G. Trasenster 11 Seraing (ougr\u00e9e) Li\u00e8ge 4102",
    "addr:housenumber":"11",
    "addr:postcode":"4102",
    "addr:street":"Rue G. Trasenster",
    "iso:country":"BE",
    "sg:address":"Rue G. Trasenster 11",
    "sg:city":"Seraing (ougr\u00e9e)",
    "sg:classifiers":[
        {
            "category":"Building & Trades",
            "subcategory":"Plumbing",
            "type":"Services"
        }
    ],
    "sg:phone":"+32 4 337 12 77",
    "sg:postcode":"4102",
    "sg:province":"Li\u00e8ge",
    "sg:tags":[
        "contractor"
    ],
    "wof:name":"Esters Maison",
    "wof:placetype":"venue"
},
  "geometry": {"coordinates":[5.5365400314,50.6065101624],"type":"Point"}
}