{
  "type": "Feature",
  "properties": {
    "iso:country":"BE",
    "sg:address":"Rue De Sesselich 83",
    "sg:city":"Arlon",
    "sg:orig_category":"Enseignement maternel and primaire. Enseignement secondaire g\u00e9n\u00e9ral",
    "sg:phone":"+32 63 22 19 47",
    "sg:postcode":"6700",
    "sg:province":"Luxembourg",
    "wof:name":"Ecole Fondamentale",
    "wof:placetype":"venue"
},
  "geometry": {"coordinates":[5.8103308678,49.6752624512],"type":"Point"}
}