{
  "type": "Feature",
  "properties": {
    "iso:country":"BE",
    "sg:address":"Rodendries 30",
    "sg:city":"Waasmunster",
    "sg:classifiers":[
        {
            "category":"Cafe",
            "type":"Food & Drink"
        }
    ],
    "sg:phone":"+32 52 47 86 78",
    "sg:postcode":"9250",
    "sg:province":"Oost-Vlaanderen",
    "sg:tags":[
        "caf\u00e9s"
    ],
    "wof:name":"Eduard Peelman",
    "wof:placetype":"venue"
},
  "geometry": {"coordinates":[4.0893712044,51.0957489014],"type":"Point"}
}