{
  "type": "Feature",
  "properties": {
    "addr:full":"Begoniastraat 44 Brugge (assebroek) West-Vlaanderen 8310",
    "addr:housenumber":"44",
    "addr:postcode":"8310",
    "addr:street":"Begoniastraat",
    "iso:country":"BE",
    "sg:address":"Begoniastraat 44",
    "sg:city":"Brugge (assebroek)",
    "sg:classifiers":[
        {
            "category":"Personal",
            "subcategory":"Beauty Salon",
            "type":"Services"
        }
    ],
    "sg:phone":"+32 50 37 12 20",
    "sg:postcode":"8310",
    "sg:province":"West-Vlaanderen",
    "sg:tags":[
        "lady",
        "-",
        "hairdressing"
    ],
    "wof:name":"Le Clip",
    "wof:placetype":"venue"
},
  "geometry": {"coordinates":[3.2394890785,51.1956825256],"type":"Point"}
}