{
  "type": "Feature",
  "properties": {
    "iso:country":"BE",
    "sg:address":"Eindgracht 1",
    "sg:city":"Genk",
    "sg:orig_category":"Reisbureaus",
    "sg:phone":"+32 89 35 54 64",
    "sg:postcode":"3600",
    "sg:province":"Limburg",
    "wof:name":"Reizen Wasteels",
    "wof:placetype":"venue"
},
  "geometry": {"coordinates":[5.4948167801,50.9641647339],"type":"Point"}
}