{
  "type": "Feature",
  "properties": {
    "iso:country":"BE",
    "sg:address":"Haut-vin\u00c2ve 42",
    "sg:city":"Jalhay",
    "sg:classifiers":[
        {
            "category":"Cafe",
            "type":"Food & Drink"
        }
    ],
    "sg:phone":"+32 87 64 72 23",
    "sg:postcode":"4845",
    "sg:province":"Li\u00e8ge",
    "sg:tags":[
        "caf\u00e9s"
    ],
    "wof:name":"Lemaitre",
    "wof:placetype":"venue"
},
  "geometry": {"coordinates":[5.9625639915,50.5571594238],"type":"Point"}
}