{
  "type": "Feature",
  "properties": {
    "addr:full":"Chemin Vert 7 Celles Hainaut 7760",
    "addr:housenumber":"7",
    "addr:postcode":"7760",
    "addr:street":"Chemin Vert",
    "iso:country":"BE",
    "sg:address":"Chemin Vert 7",
    "sg:city":"Celles",
    "sg:orig_category":"Eleveurs de bovins",
    "sg:phone":"+32 69 45 41 75",
    "sg:postcode":"7760",
    "sg:province":"Hainaut",
    "wof:name":"Daniel Huvenne",
    "wof:placetype":"venue"
},
  "geometry": {"coordinates":[3.4113500118,50.6918144226],"type":"Point"}
}