{
  "type": "Feature",
  "properties": {
    "addr:full":"Hovesstraat 93 Edingen/enghien Hainaut 7850",
    "addr:housenumber":"93",
    "addr:postcode":"7850",
    "addr:street":"Hovesstraat",
    "iso:country":"BE",
    "sg:address":"Hovesstraat 93",
    "sg:city":"Edingen/enghien",
    "sg:orig_category":"Foto-uitrusting Fotografen and fotostudio's",
    "sg:phone":"+32 2 395 14 38",
    "sg:postcode":"7850",
    "sg:province":"Hainaut",
    "wof:name":"E. Hugo",
    "wof:placetype":"venue"
},
  "geometry": {"coordinates":[4.0342469215,50.692035675],"type":"Point"}
}