{
  "type": "Feature",
  "properties": {
    "addr:full":"Chauss\u00e9e De Mons 1055 Bruxelles (anderlecht) Bruxelles-Capitale 1070",
    "addr:postcode":"1055;1070",
    "addr:street":"Chausse\u0301E De Mons",
    "iso:country":"BE",
    "sg:address":"Chauss\u00e9e De Mons 1055",
    "sg:city":"Bruxelles (anderlecht)",
    "sg:classifiers":[
        {
            "category":"Fast Food",
            "type":"Food & Drink"
        }
    ],
    "sg:phone":"+32 2 522 61 73",
    "sg:postcode":"1070",
    "sg:province":"Bruxelles-Capitale",
    "sg:tags":[
        "fried",
        "stand",
        "potato"
    ],
    "wof:name":"Jean Frit (chez)",
    "wof:placetype":"venue"
},
  "geometry": {"coordinates":[4.2961821556,50.8246536255],"type":"Point"}
}