{
  "type": "Feature",
  "properties": {
    "iso:country":"BE",
    "sg:address":"Archimedesstraat 15b3",
    "sg:city":"Oostende",
    "sg:orig_category":"Immobili\u00ebnkantoren",
    "sg:phone":"+32 59 51 99 53",
    "sg:postcode":"8400",
    "sg:province":"West-Vlaanderen",
    "wof:name":"Bureau Forestal",
    "wof:placetype":"venue"
},
  "geometry": {"coordinates":[2.9416429996,51.2117118835],"type":"Point"}
}