{
  "type": "Feature",
  "properties": {
    "addr:full":"Putsesteenweg 188 Bonheiden Antwerpen 2820",
    "addr:housenumber":"188",
    "addr:postcode":"2820",
    "addr:street":"Putsesteenweg",
    "iso:country":"BE",
    "sg:address":"Putsesteenweg 188",
    "sg:city":"Bonheiden",
    "sg:orig_category":"Benzinestations and brandstoffen",
    "sg:phone":"+32 15 55 11 25",
    "sg:postcode":"2820",
    "sg:province":"Antwerpen",
    "wof:name":"Jet",
    "wof:placetype":"venue"
},
  "geometry": {"coordinates":[4.5329761505,51.0356559753],"type":"Point"}
}