{
  "type": "Feature",
  "properties": {
    "addr:full":"287 Av. G.henri Bruxelles Bruxelles-Capitale 1200",
    "addr:postcode":"1200",
    "addr:street":"287 Av. G.Henri",
    "iso:country":"BE",
    "sg:address":"287 Av. G.henri",
    "sg:city":"Bruxelles",
    "sg:orig_category":"Entretien and r\u00e9parations de voitures. V\u00e9hicules automobiles",
    "sg:phone":"+32 2 735 06 19",
    "sg:postcode":"1200",
    "sg:province":"Bruxelles-Capitale",
    "wof:name":"Garage Jp Mooers",
    "wof:placetype":"venue"
},
  "geometry": {"coordinates":[4.4229388237,50.8475914001],"type":"Point"}
}