{
  "type": "Feature",
  "properties": {
    "addr:full":"Rue Saint-g\u00c9ry 3 Brussel/bruxelles Bruxelles-Capitale 1000",
    "addr:housenumber":"3",
    "addr:postcode":"1000",
    "addr:street":"Rue Saint-Ge\u0301Ry;/",
    "iso:country":"BE",
    "sg:address":"Rue Saint-g\u00c9ry 3",
    "sg:city":"Brussel/bruxelles",
    "sg:classifiers":[
        {
            "category":"Restaurant",
            "type":"Food & Drink"
        }
    ],
    "sg:phone":"+32 2 502 02 84",
    "sg:postcode":"1000",
    "sg:province":"Bruxelles-Capitale",
    "sg:tags":[
        "caf\u00e9s"
    ],
    "wof:name":"Taverne La Movida",
    "wof:placetype":"venue"
},
  "geometry": {"coordinates":[4.3476290703,50.8475952148],"type":"Point"}
}