{
  "type": "Feature",
  "properties": {
    "iso:country":"BE",
    "sg:address":"Stationsstraat 90",
    "sg:city":"Linkebeek",
    "sg:orig_category":"Catering and organisatie van feesten Diverse zakelijke dienstverlening Organisatie van beurzen, cong",
    "sg:phone":"+32 2 380 54 90",
    "sg:postcode":"1630",
    "sg:province":"Vlaams-Brabant",
    "wof:name":"Le Saint-sebastien",
    "wof:placetype":"venue"
},
  "geometry": {"coordinates":[4.3354802132,50.7734260559],"type":"Point"}
}