{
  "type": "Feature",
  "properties": {
    "iso:country":"BE",
    "sg:address":"Kapucijnenvoer 76",
    "sg:city":"Leuven",
    "sg:orig_category":"Journaux. Tabac. Librairies. Equipement photographique",
    "sg:phone":"+32 16 22 95 54",
    "sg:postcode":"3000",
    "sg:province":"Vlaams-Brabant",
    "wof:name":"Van Der Bruggen",
    "wof:placetype":"venue"
},
  "geometry": {"coordinates":[4.6905350685,50.8756332397],"type":"Point"}
}