{
  "type": "Feature",
  "properties": {
    "addr:full":"Bredabaan 785 Antwerpen Antwerpen 2170",
    "addr:housenumber":"785",
    "addr:postcode":"2170",
    "addr:street":"Bredabaan",
    "iso:country":"BE",
    "sg:address":"Bredabaan 785",
    "sg:city":"Antwerpen",
    "sg:orig_category":"Verlichting and huishoudartikelen",
    "sg:phone":"+32 3 646 63 21",
    "sg:postcode":"2170",
    "sg:province":"Antwerpen",
    "wof:name":"Jacobs Mia Decoration",
    "wof:placetype":"venue"
},
  "geometry": {"coordinates":[4.4505147934,51.246723175],"type":"Point"}
}