{
  "type": "Feature",
  "properties": {
    "iso:country":"BE",
    "sg:address":"Henri-dunantstraat 34",
    "sg:city":"Izegem",
    "sg:classifiers":[
        {
            "category":"Real Estate",
            "subcategory":"Architect",
            "type":"Services"
        }
    ],
    "sg:phone":"+32 51 30 35 54",
    "sg:postcode":"8870",
    "sg:province":"West-Vlaanderen",
    "wof:name":"Vandommele Kris",
    "wof:placetype":"venue"
},
  "geometry": {"coordinates":[3.2265119553,50.9106826782],"type":"Point"}
}