{
  "type": "Feature",
  "properties": {
    "iso:country":"BE",
    "sg:address":"Vierkeerstraat 121",
    "sg:city":"Harelbeke",
    "sg:orig_category":"Eleveurs and marchands de porcs. Eleveurs de bovins",
    "sg:phone":"+32 56 71 31 74",
    "sg:postcode":"8531",
    "sg:province":"West-Vlaanderen",
    "wof:name":"Patrick Talpe",
    "wof:placetype":"venue"
},
  "geometry": {"coordinates":[3.2978150845,50.8674201965],"type":"Point"}
}