{
  "type": "Feature",
  "properties": {
    "addr:full":"Bunderstraat 10 Kruishoutem Oost-Vlaanderen 9770",
    "addr:housenumber":"10",
    "addr:postcode":"9770",
    "addr:street":"Bunderstraat",
    "iso:country":"BE",
    "sg:address":"Bunderstraat 10",
    "sg:city":"Kruishoutem",
    "sg:classifiers":[
        {
            "category":"Food & Beverages",
            "subcategory":"Meat & Fish",
            "type":"Retail Goods"
        }
    ],
    "sg:phone":"+32 9 388 72 00",
    "sg:postcode":"9770",
    "sg:province":"Oost-Vlaanderen",
    "sg:tags":[
        "-",
        "livestock"
    ],
    "wof:name":"Voeders Lambrecht Nv",
    "wof:placetype":"venue"
},
  "geometry": {"coordinates":[3.519933939,50.935760498],"type":"Point"}
}