{
  "type": "Feature",
  "properties": {
    "iso:country":"BE",
    "sg:address":"Meirhoekstraat 83",
    "sg:city":"Laarne",
    "sg:orig_category":"Installation \u00e9lectrique r\u00e9sidentielle",
    "sg:phone":"+32 9 369 81 79",
    "sg:postcode":"9270",
    "sg:province":"Oost-Vlaanderen",
    "wof:name":"Spruyt Mario",
    "wof:placetype":"venue"
},
  "geometry": {"coordinates":[3.866642952,51.0228118896],"type":"Point"}
}