{
  "type": "Feature",
  "properties": {
    "addr:full":"Avenue De La Lib\u00e9ration 2 Fernelmont (forville) Namur 5380",
    "addr:housenumber":"2",
    "addr:postcode":"5380",
    "addr:street":"Avenue De La Libe\u0301Ration",
    "iso:country":"BE",
    "sg:address":"Avenue De La Lib\u00e9ration 2",
    "sg:city":"Fernelmont (forville)",
    "sg:classifiers":[
        {
            "category":"Retail",
            "subcategory":"Animal Services",
            "type":"Services"
        }
    ],
    "sg:phone":"+32 81 83 35 97",
    "sg:postcode":"5380",
    "sg:province":"Namur",
    "sg:tags":[
        "grooming",
        "-",
        "dog"
    ],
    "wof:name":"Domaine De St-roch",
    "wof:placetype":"venue"
},
  "geometry": {"coordinates":[4.9861078262,50.5531463623],"type":"Point"}
}