{
  "type": "Feature",
  "properties": {
    "addr:full":"Atheneumstraat 1 Elsene/ixelles Bruxelles-Capitale 1050",
    "addr:housenumber":"1",
    "addr:postcode":"1050",
    "addr:street":"Atheneumstraat",
    "iso:country":"BE",
    "sg:address":"Atheneumstraat 1",
    "sg:city":"Elsene/ixelles",
    "sg:orig_category":"Secretariaatsdiensten",
    "sg:phone":"+32 2 512 77 59",
    "sg:postcode":"1050",
    "sg:province":"Bruxelles-Capitale",
    "wof:name":"Gunera",
    "wof:placetype":"venue"
},
  "geometry": {"coordinates":[4.3644762039,50.834854126],"type":"Point"}
}