{
  "type": "Feature",
  "properties": {
    "iso:country":"BE",
    "sg:address":"Kere 101",
    "sg:city":"Waarschoot",
    "sg:classifiers":[
        {
            "category":"Insurance",
            "subcategory":"Insurance Agent",
            "type":"Services"
        }
    ],
    "sg:phone":"+32 9 378 03 03",
    "sg:postcode":"9950",
    "sg:province":"Oost-Vlaanderen",
    "sg:tags":[
        "verzekeringsmakelaars",
        "expert"
    ],
    "wof:name":"Elfride Wille",
    "wof:placetype":"venue"
},
  "geometry": {"coordinates":[3.5923559666,51.1571502686],"type":"Point"}
}