{
  "type": "Feature",
  "properties": {
    "iso:country":"BE",
    "sg:address":"Kouterstraat 72",
    "sg:city":"Temse",
    "sg:orig_category":"Mat\u00e9riel de T\u00e9l\u00e9communication",
    "sg:phone":"+32 3 711 30 53",
    "sg:postcode":"9140",
    "sg:province":"Oost-Vlaanderen",
    "wof:name":"Starcom Europe",
    "wof:placetype":"venue"
},
  "geometry": {"coordinates":[4.217250824,51.1276130676],"type":"Point"}
}