{
  "type": "Feature",
  "properties": {
    "addr:full":"Mechelsesteenweg 121 Heist-op-den-berg Antwerpen 2220",
    "addr:housenumber":"121",
    "addr:postcode":"2220",
    "addr:street":"Mechelsesteenweg",
    "iso:country":"BE",
    "sg:address":"Mechelsesteenweg 121",
    "sg:city":"Heist-op-den-berg",
    "sg:orig_category":"Drukkerijen and copyshops",
    "sg:phone":"+32 15 24 11 78",
    "sg:postcode":"2220",
    "sg:province":"Antwerpen",
    "wof:name":"Alois Hendrickx",
    "wof:placetype":"venue"
},
  "geometry": {"coordinates":[4.6965928078,51.0692253113],"type":"Point"}
}