{
  "type": "Feature",
  "properties": {
    "addr:full":"Dorpsstraat 66 Kapellen Antwerpen 2950",
    "addr:housenumber":"66",
    "addr:postcode":"2950",
    "addr:street":"Dorpsstraat",
    "iso:country":"BE",
    "sg:address":"Dorpsstraat 66",
    "sg:city":"Kapellen",
    "sg:orig_category":"Fotogravure and zetwerk Herstelling leer and schoeisel Herstellingswinkels voor diverse persoonlijke",
    "sg:phone":"+32 3 664 36 85",
    "sg:postcode":"2950",
    "sg:province":"Antwerpen",
    "wof:name":"D'or Shop",
    "wof:placetype":"venue"
},
  "geometry": {"coordinates":[4.4277482033,51.3170776367],"type":"Point"}
}