{
  "type": "Feature",
  "properties": {
    "iso:country":"BE",
    "sg:address":"Mechelsesteenweg 15",
    "sg:city":"Rumst",
    "sg:orig_category":"Industri\u00eble elektrische installaties",
    "sg:phone":"+32 15 30 68 30",
    "sg:postcode":"2840",
    "sg:province":"Antwerpen",
    "wof:name":"Jm Security",
    "wof:placetype":"venue"
},
  "geometry": {"coordinates":[4.4524431229,51.0836410522],"type":"Point"}
}