{
  "type": "Feature",
  "properties": {
    "addr:full":"Sint-anna 63ba Hamme Oost-Vlaanderen 9220",
    "addr:postcode":"9220",
    "addr:street":"Oost-Vlaanderen",
    "iso:country":"BE",
    "sg:address":"Sint-anna 63ba",
    "sg:city":"Hamme",
    "sg:classifiers":[
        {
            "category":"Government",
            "subcategory":"Fire Station",
            "type":"Public Place"
        }
    ],
    "sg:phone":"+32 52 47 25 09",
    "sg:postcode":"9220",
    "sg:province":"Oost-Vlaanderen",
    "sg:tags":[
        "commerce",
        "conditionn\u00e9",
        "equipement",
        "pour",
        "air",
        "ventilation",
        "diver"
    ],
    "wof:name":"Guido Gerlo",
    "wof:placetype":"venue"
},
  "geometry": {"coordinates":[4.0779118538,51.0944671631],"type":"Point"}
}