{
  "type": "Feature",
  "properties": {
    "addr:full":"Grand-rue 19 Florenville Luxembourg 6820",
    "addr:housenumber":"19",
    "addr:postcode":"6820",
    "addr:street":"Grand-Rue",
    "iso:country":"BE",
    "sg:address":"Grand-rue 19",
    "sg:city":"Florenville",
    "sg:classifiers":[
        {
            "category":"Cafe",
            "type":"Food & Drink"
        }
    ],
    "sg:phone":"+32 61 31 16 53",
    "sg:postcode":"6820",
    "sg:province":"Luxembourg",
    "sg:tags":[
        "caf\u00e9s"
    ],
    "wof:name":"Caf\u00c9 Chez Le P\u00b4tit Roger",
    "wof:placetype":"venue"
},
  "geometry": {"coordinates":[5.3101477623,49.6980133057],"type":"Point"}
}