{
  "type": "Feature",
  "properties": {
    "addr:full":"Karel Steverlyncklaan 12 Ieper West-Vlaanderen 8900",
    "addr:housenumber":"12",
    "addr:postcode":"8900",
    "addr:street":"Karel Steverlyncklaan",
    "iso:country":"BE",
    "sg:address":"Karel Steverlyncklaan 12",
    "sg:city":"Ieper",
    "sg:classifiers":[
        {
            "category":"Retail",
            "subcategory":"Auto Repair",
            "type":"Services"
        }
    ],
    "sg:phone":"+32 57 20 58 01",
    "sg:postcode":"8900",
    "sg:province":"West-Vlaanderen",
    "sg:tags":[
        "garage"
    ],
    "wof:name":"Volvo-willaert J",
    "wof:placetype":"venue"
},
  "geometry": {"coordinates":[2.901391983,50.8490180969],"type":"Point"}
}