{
  "type": "Feature",
  "properties": {
    "addr:full":"Oostkouterlaan 95 Deinze Oost-Vlaanderen 9800",
    "addr:housenumber":"95",
    "addr:postcode":"9800",
    "addr:street":"Oostkouterlaan",
    "iso:country":"BE",
    "sg:address":"Oostkouterlaan 95",
    "sg:city":"Deinze",
    "sg:orig_category":"M\u00e9decins and sp\u00e9cialistes",
    "sg:phone":"+32 9 380 27 72",
    "sg:postcode":"9800",
    "sg:province":"Oost-Vlaanderen",
    "wof:name":"Luc Van Braeckel",
    "wof:placetype":"venue"
},
  "geometry": {"coordinates":[3.530174017,50.9863166809],"type":"Point"}
}