{
  "type": "Feature",
  "properties": {
    "iso:country":"BE",
    "sg:address":"Chemin Des Hauts-pr\u00c9s 10",
    "sg:city":"Spa",
    "sg:classifiers":[
        {
            "category":"Arena",
            "subcategory":"Sports Club",
            "type":"Entertainment"
        }
    ],
    "sg:phone":"+32 87 77 15 59",
    "sg:postcode":"4900",
    "sg:province":"Li\u00e8ge",
    "sg:tags":[
        "de"
    ],
    "wof:name":"Hermathenae-ski",
    "wof:placetype":"venue"
},
  "geometry": {"coordinates":[5.8484997749,50.4753608704],"type":"Point"}
}