{
  "type": "Feature",
  "properties": {
    "iso:country":"BE",
    "sg:address":"Rue Des R\u00c9collets 59bb",
    "sg:city":"Vise",
    "sg:orig_category":"Alternatieve geneeskunde",
    "sg:phone":"+32 4 379 77 66",
    "sg:postcode":"4600",
    "sg:province":"Li\u00e8ge",
    "wof:name":"Ost\u00c9opathe Tilman J.",
    "wof:placetype":"venue"
},
  "geometry": {"coordinates":[5.6931548119,50.7367668152],"type":"Point"}
}