{
  "type": "Feature",
  "properties": {
    "addr:full":"Rue De La Gare 132ba Bertrix Luxembourg 6880",
    "addr:postcode":"6880",
    "addr:street":"Rue De La Gare",
    "iso:country":"BE",
    "sg:address":"Rue De La Gare 132ba",
    "sg:city":"Bertrix",
    "sg:orig_category":"Rev\u00eatements pour sols and murs. Peinture. Rev\u00eatements de sols and murs. Travaux de pl\u00e2trage",
    "sg:phone":"+32 61 41 17 05",
    "sg:postcode":"6880",
    "sg:province":"Luxembourg",
    "wof:name":"Bertrix D\u00c9cor",
    "wof:placetype":"venue"
},
  "geometry": {"coordinates":[5.2620439529,49.8565864563],"type":"Point"}
}