{
  "type": "Feature",
  "properties": {
    "iso:country":"BE",
    "sg:address":"Sint-michielslaan 125",
    "sg:city":"Etterbeek",
    "sg:orig_category":"Technische and wetenschappelijke instrumenten Fab",
    "sg:phone":"+32 2 733 11 44",
    "sg:postcode":"1040",
    "sg:province":"Bruxelles-Capitale",
    "wof:name":"Alarm Group V.a.g.",
    "wof:placetype":"venue"
},
  "geometry": {"coordinates":[4.4043869972,50.8320503235],"type":"Point"}
}