{
  "type": "Feature",
  "properties": {
    "iso:country":"BE",
    "sg:address":"Rue Narcisse Evrard 20",
    "sg:city":"Charleroi",
    "sg:orig_category":"Jardinage",
    "sg:phone":"+32 71 41 54 83",
    "sg:postcode":"6060",
    "sg:province":"Hainaut",
    "wof:name":"Lemal",
    "wof:placetype":"venue"
},
  "geometry": {"coordinates":[4.4880981445,50.4251937866],"type":"Point"}
}