{
  "type": "Feature",
  "properties": {
    "addr:full":"Oosteeklodorp 7 Assenede Oost-Vlaanderen 9968",
    "addr:housenumber":"7",
    "addr:postcode":"9968",
    "addr:street":"Oosteeklodorp",
    "iso:country":"BE",
    "sg:address":"Oosteeklodorp 7",
    "sg:city":"Assenede",
    "sg:orig_category":"Artsen and specialisten",
    "sg:phone":"+32 9 373 70 61",
    "sg:postcode":"9968",
    "sg:province":"Oost-Vlaanderen",
    "wof:name":"Mieke De Weweire",
    "wof:placetype":"venue"
},
  "geometry": {"coordinates":[3.6891839504,51.1924667358],"type":"Point"}
}