{
  "type": "Feature",
  "properties": {
    "iso:country":"BE",
    "sg:address":"Steenweg Asse 183",
    "sg:city":"Herfelingen",
    "sg:classifiers":[
        {
            "category":"Food & Beverages",
            "subcategory":"Dairy",
            "type":"Retail Goods"
        }
    ],
    "sg:phone":"+32 54 56 64 23",
    "sg:postcode":"1540",
    "sg:province":"Vlaams-Brabant",
    "sg:tags":[
        "product",
        "related"
    ],
    "wof:name":"Olympia Nv",
    "wof:placetype":"venue"
},
  "geometry": {"coordinates":[4.0947561264,50.7413597107],"type":"Point"}
}