{
  "type": "Feature",
  "properties": {
    "iso:country":"BE",
    "sg:address":"L\u00c9on Th\u00c9odorstraat 181",
    "sg:city":"Jette (brussel)",
    "sg:orig_category":"Kapsalons",
    "sg:phone":"+32 2 425 70 72",
    "sg:postcode":"1090",
    "sg:province":"Bruxelles-Capitale",
    "wof:name":"Coiffure Eliane",
    "wof:placetype":"venue"
},
  "geometry": {"coordinates":[4.3290081024,50.8781242371],"type":"Point"}
}