{
  "type": "Feature",
  "properties": {
    "iso:country":"BE",
    "sg:address":"Chemin De La Poussi\u00c8re 13",
    "sg:city":"Celles",
    "sg:orig_category":"Verhuur cateringmateriaal and evenementuitrusting",
    "sg:phone":"+32 69 45 47 80",
    "sg:postcode":"7760",
    "sg:province":"Hainaut",
    "wof:name":"Willy Hocedez",
    "wof:placetype":"venue"
},
  "geometry": {"coordinates":[3.4432170391,50.7526626587],"type":"Point"}
}