{
  "type": "Feature",
  "properties": {
    "iso:country":"BE",
    "sg:address":"Kaaistraat 50",
    "sg:city":"Eeklo",
    "sg:classifiers":[
        {
            "category":"Health Services",
            "subcategory":"Health Practitioner",
            "type":"Services"
        }
    ],
    "sg:phone":"+32 9 377 21 21",
    "sg:postcode":"9900",
    "sg:province":"Oost-Vlaanderen",
    "sg:tags":[
        "physiotherapist"
    ],
    "wof:name":"De Lange F",
    "wof:placetype":"venue"
},
  "geometry": {"coordinates":[3.5685040951,51.1822509766],"type":"Point"}
}