{
  "type": "Feature",
  "properties": {
    "addr:full":"Menenstraat 333 Zonnebeke West-Vlaanderen 8980",
    "addr:housenumber":"333",
    "addr:postcode":"8980",
    "addr:street":"Menenstraat",
    "iso:country":"BE",
    "sg:address":"Menenstraat 333",
    "sg:city":"Zonnebeke",
    "sg:orig_category":"D\u00e9corateurs d'int\u00e9rieur",
    "sg:phone":"+32 57 46 85 06",
    "sg:postcode":"8980",
    "sg:province":"West-Vlaanderen",
    "wof:name":"Alain Verpoucke",
    "wof:placetype":"venue"
},
  "geometry": {"coordinates":[3.0109729767,50.8289108276],"type":"Point"}
}