{
  "type": "Feature",
  "properties": {
    "iso:country":"BE",
    "sg:address":"Rue Des Wattines 14",
    "sg:city":"Ath (ligne)",
    "sg:orig_category":"Non-Classified Establishments",
    "sg:phone":"+32 68 26 51 11",
    "sg:postcode":"7812",
    "sg:province":"Hainaut",
    "wof:name":"Vitex Europe Sprl",
    "wof:placetype":"venue"
},
  "geometry": {"coordinates":[3.7029209137,50.6218223572],"type":"Point"}
}