{
  "type": "Feature",
  "properties": {
    "addr:full":"Bergstraat 22 Brussel/bruxelles Bruxelles-Capitale 1000",
    "addr:housenumber":"22",
    "addr:postcode":"1000",
    "addr:street":"Bergstraat;/",
    "iso:country":"BE",
    "sg:address":"Bergstraat 22",
    "sg:city":"Brussel/bruxelles",
    "sg:classifiers":[
        {
            "category":"Travel",
            "subcategory":"Hotels & Motels",
            "type":"Entertainment"
        }
    ],
    "sg:phone":"+32 2 513 29 73",
    "sg:postcode":"1000",
    "sg:province":"Bruxelles-Capitale",
    "wof:name":"La Madeleine",
    "wof:placetype":"venue"
},
  "geometry": {"coordinates":[4.3547410965,50.8468093872],"type":"Point"}
}