{
  "type": "Feature",
  "properties": {
    "iso:country":"BE",
    "sg:address":"Ooigemstraat 9",
    "sg:city":"Wielsbeke",
    "sg:orig_category":"Goederenvervoer over de weg",
    "sg:phone":"+32 56 66 67 76",
    "sg:postcode":"8710",
    "sg:province":"West-Vlaanderen",
    "wof:name":"Foronex",
    "wof:placetype":"venue"
},
  "geometry": {"coordinates":[3.3613169193,50.9018249512],"type":"Point"}
}