{
  "type": "Feature",
  "properties": {
    "addr:full":"Kapelstraat 77 Bocholt Limburg 3950",
    "addr:housenumber":"77",
    "addr:postcode":"3950",
    "addr:street":"Kapelstraat",
    "iso:country":"BE",
    "sg:address":"Kapelstraat 77",
    "sg:city":"Bocholt",
    "sg:classifiers":[
        {
            "category":"Retail",
            "subcategory":"Animal Services",
            "type":"Services"
        }
    ],
    "sg:phone":"+32 478 72 39 69",
    "sg:postcode":"3950",
    "sg:province":"Limburg",
    "sg:tags":[
        "farrier"
    ],
    "wof:name":"Geerits B",
    "wof:placetype":"venue"
},
  "geometry": {"coordinates":[5.5638070107,51.1860618591],"type":"Point"}
}