{
  "type": "Feature",
  "properties": {
    "addr:full":"Europaplein 41 Lanaken Limburg 3620",
    "addr:housenumber":"41",
    "addr:postcode":"3620",
    "addr:street":"Europaplein",
    "iso:country":"BE",
    "sg:address":"Europaplein 41",
    "sg:city":"Lanaken",
    "sg:classifiers":[
        {
            "category":"Wholesale",
            "subcategory":"Medical Equipment & Supplies",
            "type":"Manufacturing & Wholesale Goods"
        }
    ],
    "sg:phone":"+32 89 73 99 99",
    "sg:postcode":"3620",
    "sg:province":"Limburg",
    "sg:tags":[
        "instrument",
        "apparatus"
    ],
    "wof:name":"Home Diagnostics International",
    "wof:placetype":"venue"
},
  "geometry": {"coordinates":[5.6511058807,50.8870124817],"type":"Point"}
}