{
  "type": "Feature",
  "properties": {
    "addr:full":"Rue Sombre 18 Sint-lambrechts-woluwe/woluwe-saint-lambert Bruxelles-Capitale 1200",
    "addr:housenumber":"18",
    "addr:postcode":"1200",
    "addr:street":"Rue Sombre",
    "iso:country":"BE",
    "sg:address":"Rue Sombre 18",
    "sg:city":"Sint-lambrechts-woluwe/woluwe-saint-lambert",
    "sg:orig_category":"Artistes ind\u00e9pendants",
    "sg:phone":"+32 2 770 36 75",
    "sg:postcode":"1200",
    "sg:province":"Bruxelles-Capitale",
    "wof:name":"Henri Ruder",
    "wof:placetype":"venue"
},
  "geometry": {"coordinates":[4.4316511154,50.8407058716],"type":"Point"}
}