{
  "type": "Feature",
  "properties": {
    "addr:full":"Ophovenstraat 51 Opglabbeek Limburg 3660",
    "addr:housenumber":"51",
    "addr:postcode":"3660",
    "addr:street":"Ophovenstraat",
    "iso:country":"BE",
    "sg:address":"Ophovenstraat 51",
    "sg:city":"Opglabbeek",
    "sg:orig_category":"Woningbouw",
    "sg:phone":"+32 89 85 47 22",
    "sg:postcode":"3660",
    "sg:province":"Limburg",
    "wof:name":"L. En J.",
    "wof:placetype":"venue"
},
  "geometry": {"coordinates":[5.5705180168,51.0436782837],"type":"Point"}
}