{
  "type": "Feature",
  "properties": {
    "addr:full":"Kortrijksesteenweg 210 Sint-martens-latem Oost-Vlaanderen 9830",
    "addr:housenumber":"210",
    "addr:postcode":"9830",
    "addr:street":"Kortrijksesteenweg",
    "iso:country":"BE",
    "sg:address":"Kortrijksesteenweg 210",
    "sg:city":"Sint-martens-latem",
    "sg:classifiers":[
        {
            "category":"Fast Food",
            "type":"Food & Drink"
        }
    ],
    "sg:phone":"+32 9 282 72 76",
    "sg:postcode":"9830",
    "sg:province":"Oost-Vlaanderen",
    "sg:tags":[
        "meeneem",
        "restaurant"
    ],
    "wof:name":"Frituur Danny",
    "wof:placetype":"venue"
},
  "geometry": {"coordinates":[3.6298110485,51.0072898865],"type":"Point"}
}