{
  "type": "Feature",
  "properties": {
    "iso:country":"BE",
    "sg:address":"Brusselsesteenweg 60",
    "sg:city":"Vilvoorde",
    "sg:classifiers":[
        {
            "category":"Bars & Pubs",
            "type":"Food & Drink"
        }
    ],
    "sg:phone":"+32 2 251 86 46",
    "sg:postcode":"1800",
    "sg:province":"Vlaams-Brabant",
    "sg:tags":[
        "tavern"
    ],
    "wof:name":"The Circle",
    "wof:placetype":"venue"
},
  "geometry": {"coordinates":[4.4173607826,50.9241790771],"type":"Point"}
}