{
  "type": "Feature",
  "properties": {
    "iso:country":"BE",
    "sg:address":"Zoutrootjesstraat 46",
    "sg:city":"Lubbeek (linden)",
    "sg:classifiers":[
        {
            "category":"Personal",
            "subcategory":"Beauty Salon",
            "type":"Services"
        }
    ],
    "sg:phone":"+32 16 62 28 37",
    "sg:postcode":"3210",
    "sg:province":"Vlaams-Brabant",
    "sg:tags":[
        "lady",
        "-",
        "hairdressing"
    ],
    "wof:name":"Germaine",
    "wof:placetype":"venue"
},
  "geometry": {"coordinates":[4.7733139992,50.8899917603],"type":"Point"}
}