{
  "type": "Feature",
  "properties": {
    "iso:country":"BE",
    "sg:address":"Godtschalckstraat 12",
    "sg:city":"Heuvelland",
    "sg:orig_category":"Ordinateurs and \u00e9quipement informatique. Entretien and r\u00e9parations de machines de bureau and ordinat",
    "sg:phone":"+32 57 44 55 43",
    "sg:postcode":"8958",
    "sg:province":"West-Vlaanderen",
    "wof:name":"G.m.l.-soft",
    "wof:placetype":"venue"
},
  "geometry": {"coordinates":[2.7735769749,50.7814750671],"type":"Point"}
}