{
  "type": "Feature",
  "properties": {
    "iso:country":"BE",
    "sg:address":"Ettingen 48-3",
    "sg:city":"Oostrozebeke",
    "sg:orig_category":"Non-Classified Establishments",
    "sg:phone":"+32 56 66 82 45",
    "sg:postcode":"8780",
    "sg:province":"West-Vlaanderen",
    "wof:name":"Filmar",
    "wof:placetype":"venue"
},
  "geometry": {"coordinates":[3.3308908939,50.9222106934],"type":"Point"}
}