{
  "type": "Feature",
  "properties": {
    "iso:country":"BE",
    "sg:address":"Rue Hauzeur 10",
    "sg:city":"Verviers (ensival)",
    "sg:classifiers":[
        {
            "category":"Professional",
            "subcategory":"Accounting & Tax Preparation",
            "type":"Services"
        }
    ],
    "sg:phone":"+32 87 33 50 66",
    "sg:postcode":"4800",
    "sg:province":"Li\u00e8ge",
    "sg:tags":[
        "bookkeeper"
    ],
    "wof:name":"Doome M-j",
    "wof:placetype":"venue"
},
  "geometry": {"coordinates":[5.8659977913,50.5932388306],"type":"Point"}
}