{
  "type": "Feature",
  "properties": {
    "iso:country":"BE",
    "sg:address":"Rue De Neffe 252",
    "sg:city":"Bastenaken",
    "sg:orig_category":"Sportclubs",
    "sg:phone":"+32 61 21 40 51",
    "sg:postcode":"6600",
    "sg:province":"Luxembourg",
    "wof:name":"Ce De Bastogne",
    "wof:placetype":"venue"
},
  "geometry": {"coordinates":[5.7148199081,50.0007820129],"type":"Point"}
}