{
  "type": "Feature",
  "properties": {
    "iso:country":"BE",
    "sg:address":"Schurhovenveld 3408",
    "sg:city":"Sint-truiden",
    "sg:orig_category":"D\u00e9taillants en pi\u00e8ces and accessoires de voitures",
    "sg:phone":"+32 11 69 58 03",
    "sg:postcode":"3800",
    "sg:province":"Limburg",
    "wof:name":"M.j.t./ Car Airco",
    "wof:placetype":"venue"
},
  "geometry": {"coordinates":[5.2136731148,50.8218917847],"type":"Point"}
}