{
  "type": "Feature",
  "properties": {
    "iso:country":"BE",
    "sg:address":"Nieuwstraat 95",
    "sg:city":"Lebbeke (wieze)",
    "sg:classifiers":[
        {
            "category":"Farming",
            "subcategory":"Poultry Farm",
            "type":"Manufacturing & Wholesale Goods"
        }
    ],
    "sg:phone":"+32 53 21 61 54",
    "sg:postcode":"9280",
    "sg:province":"Oost-Vlaanderen",
    "sg:tags":[
        "rabbit",
        "slaughterhouse"
    ],
    "wof:name":"De Meersman J",
    "wof:placetype":"venue"
},
  "geometry": {"coordinates":[4.0919251442,50.9854164124],"type":"Point"}
}