{
  "type": "Feature",
  "properties": {
    "addr:full":"Rue Arthur Descamps 134 Colfontaine (p\u00e2turages) Hainaut 7340",
    "addr:housenumber":"134",
    "addr:postcode":"7340",
    "addr:street":"Rue Arthur Descamps",
    "iso:country":"BE",
    "sg:address":"Rue Arthur Descamps 134",
    "sg:city":"Colfontaine (p\u00e2turages)",
    "sg:classifiers":[
        {
            "category":"Professional",
            "subcategory":"Detective & Security Services",
            "type":"Services"
        }
    ],
    "sg:phone":"+32 65 51 24 50",
    "sg:postcode":"7340",
    "sg:province":"Hainaut",
    "sg:tags":[
        "consultant"
    ],
    "wof:name":"A.c.i. Consult Sprl",
    "wof:placetype":"venue"
},
  "geometry": {"coordinates":[3.8595609665,50.3981285095],"type":"Point"}
}