{
  "type": "Feature",
  "properties": {
    "addr:full":"Dorpsstraat 17a Houthalen-helchteren (houthalen) Limburg 3530",
    "addr:housenumber":"17a",
    "addr:postcode":"3530",
    "addr:street":"Dorpsstraat",
    "iso:country":"BE",
    "sg:address":"Dorpsstraat 17a",
    "sg:city":"Houthalen-helchteren (houthalen)",
    "sg:classifiers":[
        {
            "category":"Personal",
            "subcategory":"Beauty Salon",
            "type":"Services"
        }
    ],
    "sg:phone":"+32 11 60 51 16",
    "sg:postcode":"3530",
    "sg:province":"Limburg",
    "sg:tags":[
        "lady",
        "-",
        "hairdressing"
    ],
    "wof:name":"Gajo",
    "wof:placetype":"venue"
},
  "geometry": {"coordinates":[5.3742470741,51.0308685303],"type":"Point"}
}