{
  "type": "Feature",
  "properties": {
    "iso:country":"BE",
    "sg:address":"Gijsbrecht Van Deurnelaan 22",
    "sg:city":"Antwerpen",
    "sg:orig_category":"R\u00e9alisation de programmes and logiciels",
    "sg:phone":"+32 3 326 50 75",
    "sg:postcode":"2100",
    "sg:province":"Antwerpen",
    "wof:name":"Intris",
    "wof:placetype":"venue"
},
  "geometry": {"coordinates":[4.4415540695,51.2283973694],"type":"Point"}
}