{
  "type": "Feature",
  "properties": {
    "iso:country":"BE",
    "sg:address":"Place Joseph Thiry 16",
    "sg:city":"Aywaille",
    "sg:classifiers":[
        {
            "category":"Fast Food",
            "type":"Food & Drink"
        }
    ],
    "sg:phone":"+32 4 384 64 96",
    "sg:postcode":"4920",
    "sg:province":"Li\u00e8ge",
    "sg:tags":[
        "meeneem",
        "restaurant"
    ],
    "wof:name":"Le Petit Restaurant",
    "wof:placetype":"venue"
},
  "geometry": {"coordinates":[5.6754751205,50.4740409851],"type":"Point"}
}