{
  "type": "Feature",
  "properties": {
    "addr:full":"Alsembergsesteenweg 275 Halle Vlaams-Brabant 1501",
    "addr:housenumber":"275",
    "addr:postcode":"1501",
    "addr:street":"Alsembergsesteenweg",
    "iso:country":"BE",
    "sg:address":"Alsembergsesteenweg 275",
    "sg:city":"Halle",
    "sg:orig_category":"Installation \u00e9lectrique r\u00e9sidentielle",
    "sg:phone":"+32 2 360 22 01",
    "sg:postcode":"1501",
    "sg:province":"Vlaams-Brabant",
    "wof:name":"Philippe Deville",
    "wof:placetype":"venue"
},
  "geometry": {"coordinates":[4.2687501907,50.7446479797],"type":"Point"}
}