{
  "type": "Feature",
  "properties": {
    "iso:country":"BE",
    "sg:address":"Rue Philipville 40",
    "sg:city":"Charleroi (marcinelle)",
    "sg:classifiers":[
        {
            "category":"Manufacturing",
            "subcategory":"Chemicals & Compounds",
            "type":"Manufacturing & Wholesale Goods"
        }
    ],
    "sg:phone":"+32 71 60 13 11",
    "sg:postcode":"6001",
    "sg:province":"Hainaut",
    "sg:tags":[
        "pharmaceutical",
        "product"
    ],
    "wof:name":"Pharma Belgium Sa",
    "wof:placetype":"venue"
},
  "geometry": {"coordinates":[4.4448251724,50.3973655701],"type":"Point"}
}