{
  "type": "Feature",
  "properties": {
    "iso:country":"BE",
    "sg:address":"Maalse Steenweg 204",
    "sg:city":"Brugge",
    "sg:orig_category":"Boucheries",
    "sg:phone":"+32 50 36 36 32",
    "sg:postcode":"8310",
    "sg:province":"West-Vlaanderen",
    "wof:name":"Renmans",
    "wof:placetype":"venue"
},
  "geometry": {"coordinates":[3.2525360584,51.2097892761],"type":"Point"}
}