{
  "type": "Feature",
  "properties": {
    "iso:country":"BE",
    "sg:address":"Chemin Du Gros Sous 44",
    "sg:city":"Namur (w\u00e9pion)",
    "sg:classifiers":[
        {
            "category":"Building & Trades",
            "subcategory":"Landscaping Services",
            "type":"Services"
        }
    ],
    "sg:phone":"+32 81 46 19 37",
    "sg:postcode":"5100",
    "sg:province":"Namur",
    "sg:tags":[
        "gardening",
        "garden",
        "maintenance"
    ],
    "wof:name":"Poulaert Guy Et Fils",
    "wof:placetype":"venue"
},
  "geometry": {"coordinates":[4.8688788414,50.3939743042],"type":"Point"}
}