{
  "type": "Feature",
  "properties": {
    "addr:full":"Rue Du Vivier 26 Etalle Luxembourg 6740",
    "addr:housenumber":"26",
    "addr:postcode":"6740",
    "addr:street":"Rue Du Vivier",
    "iso:country":"BE",
    "sg:address":"Rue Du Vivier 26",
    "sg:city":"Etalle",
    "sg:orig_category":"Bagage and lederwaren Schoenen",
    "sg:phone":"+32 63 45 54 84",
    "sg:postcode":"6740",
    "sg:province":"Luxembourg",
    "wof:name":"Madeleine Didier",
    "wof:placetype":"venue"
},
  "geometry": {"coordinates":[5.6007847786,49.6738510132],"type":"Point"}
}