{
  "type": "Feature",
  "properties": {
    "iso:country":"BE",
    "sg:address":"Rue Visigath 4",
    "sg:city":"Waremme",
    "sg:orig_category":"Paramedische behandelingen Schoonheidssalons",
    "sg:phone":"+32 19 33 07 04",
    "sg:postcode":"4300",
    "sg:province":"Li\u00e8ge",
    "wof:name":"Lange Dominique",
    "wof:placetype":"venue"
},
  "geometry": {"coordinates":[5.2574310303,50.6993408203],"type":"Point"}
}