{
  "type": "Feature",
  "properties": {
    "addr:full":"Jules De Buckstraat 6 Lebbeke Oost-Vlaanderen 9280",
    "addr:housenumber":"6",
    "addr:postcode":"9280",
    "addr:street":"Jules De Buckstraat",
    "iso:country":"BE",
    "sg:address":"Jules De Buckstraat 6",
    "sg:city":"Lebbeke",
    "sg:orig_category":"Slagers",
    "sg:phone":"+32 52 41 03 27",
    "sg:postcode":"9280",
    "sg:province":"Oost-Vlaanderen",
    "wof:name":"Dirk Van Den Vreken",
    "wof:placetype":"venue"
},
  "geometry": {"coordinates":[4.1291699409,50.9999809265],"type":"Point"}
}