{
  "type": "Feature",
  "properties": {
    "addr:full":"Chauss\u00e9e De Tongres 198 Li\u00e8ge 1 (rocourt) Li\u00e8ge 4000",
    "addr:housenumber":"198;1",
    "addr:postcode":"4000",
    "addr:street":"Chausse\u0301E De Tongres",
    "iso:country":"BE",
    "sg:address":"Chauss\u00e9e De Tongres 198",
    "sg:city":"Li\u00e8ge 1 (rocourt)",
    "sg:classifiers":[
        {
            "category":"Shopping",
            "subcategory":"Bicycles & Sporting Goods",
            "type":"Retail Goods"
        }
    ],
    "sg:phone":"+32 4 226 05 45",
    "sg:postcode":"4000",
    "sg:province":"Li\u00e8ge",
    "sg:tags":[
        "sport",
        "-"
    ],
    "wof:name":"Li\u00e8ge Sports Loisirs Sa",
    "wof:placetype":"venue"
},
  "geometry": {"coordinates":[5.5552577972,50.668056488],"type":"Point"}
}