{
  "type": "Feature",
  "properties": {
    "addr:full":"Burgemeester Somerslaan 9 Vosselaar Antwerpen 2350",
    "addr:housenumber":"9",
    "addr:postcode":"2350",
    "addr:street":"Burgemeester Somerslaan",
    "iso:country":"BE",
    "sg:address":"Burgemeester Somerslaan 9",
    "sg:city":"Vosselaar",
    "sg:orig_category":"Woningbouw",
    "sg:phone":"+32 14 61 61 08",
    "sg:postcode":"2350",
    "sg:province":"Antwerpen",
    "wof:name":"Aannemingen Jabo",
    "wof:placetype":"venue"
},
  "geometry": {"coordinates":[4.8817110062,51.3056144714],"type":"Point"}
}