{
  "type": "Feature",
  "properties": {
    "addr:full":"Bolderstraat 94 Riemst Limburg 3770",
    "addr:housenumber":"94",
    "addr:postcode":"3770",
    "addr:street":"Bolderstraat",
    "iso:country":"BE",
    "sg:address":"Bolderstraat 94",
    "sg:city":"Riemst",
    "sg:orig_category":"Woningbouw",
    "sg:phone":"+32 12 45 62 34",
    "sg:postcode":"3770",
    "sg:province":"Limburg",
    "wof:name":"Darco",
    "wof:placetype":"venue"
},
  "geometry": {"coordinates":[5.6003341675,50.7908248901],"type":"Point"}
}