{
  "type": "Feature",
  "properties": {
    "iso:country":"BE",
    "sg:address":"Oude Smidsestraat 11",
    "sg:city":"Dilbeek",
    "sg:orig_category":"Artsen and specialisten",
    "sg:phone":"+32 2 567 24 80",
    "sg:postcode":"1700",
    "sg:province":"Vlaams-Brabant",
    "wof:name":"E. Vertenten",
    "wof:placetype":"venue"
},
  "geometry": {"coordinates":[4.2622909546,50.84425354],"type":"Point"}
}