{
  "type": "Feature",
  "properties": {
    "addr:full":"Bredabaan 835 Anvers (grand) Antwerpen 2170",
    "addr:housenumber":"835",
    "addr:postcode":"2170",
    "addr:street":"Bredabaan;Grand Antwerpen",
    "iso:country":"BE",
    "sg:address":"Bredabaan 835",
    "sg:city":"Anvers (grand)",
    "sg:classifiers":[
        {
            "category":"Sports & Exercise",
            "subcategory":"Sports Center",
            "type":"Entertainment"
        }
    ],
    "sg:phone":"+32 3 646 87 40",
    "sg:postcode":"2170",
    "sg:province":"Antwerpen",
    "sg:tags":[
        "de",
        "fitness"
    ],
    "wof:name":"Planet Fitness",
    "wof:placetype":"venue"
},
  "geometry": {"coordinates":[4.4505147934,51.246723175],"type":"Point"}
}