{
  "type": "Feature",
  "properties": {
    "addr:full":"Stationsstraat 100 Beveren (beveren-waas) Oost-Vlaanderen 9120",
    "addr:housenumber":"100",
    "addr:postcode":"9120",
    "addr:street":"Stationsstraat;Oost-Vlaanderen",
    "iso:country":"BE",
    "sg:address":"Stationsstraat 100",
    "sg:city":"Beveren (beveren-waas)",
    "sg:classifiers":[
        {
            "category":"Personal",
            "subcategory":"Nail Salon",
            "type":"Services"
        }
    ],
    "sg:phone":"+32 3 775 21 12",
    "sg:postcode":"9120",
    "sg:province":"Oost-Vlaanderen",
    "sg:tags":[
        "pedicure"
    ],
    "wof:name":"Verbist B",
    "wof:placetype":"venue"
},
  "geometry": {"coordinates":[4.2582149506,51.2088394165],"type":"Point"}
}