{
  "type": "Feature",
  "properties": {
    "addr:full":"Sint-jozefstraat 12b3 Merelbeke Oost-Vlaanderen 9820",
    "addr:housenumber":"12b3",
    "addr:postcode":"9820",
    "addr:street":"Sint-Jozefstraat",
    "iso:country":"BE",
    "sg:address":"Sint-jozefstraat 12b3",
    "sg:city":"Merelbeke",
    "sg:orig_category":"Persagentschappen",
    "sg:phone":"+32 53 78 38 40",
    "sg:postcode":"9820",
    "sg:province":"Oost-Vlaanderen",
    "wof:name":"Nellie De Hert",
    "wof:placetype":"venue"
},
  "geometry": {"coordinates":[3.7628750801,51.0174789429],"type":"Point"}
}