{
  "type": "Feature",
  "properties": {
    "iso:country":"BE",
    "sg:address":"Passage Lemonnier 29",
    "sg:city":"Li\u00e8ge 1",
    "sg:classifiers":[
        {
            "category":"Shopping",
            "subcategory":"Jewelry",
            "type":"Retail Goods"
        }
    ],
    "sg:phone":"+32 4 250 05 85",
    "sg:postcode":"4000",
    "sg:province":"Li\u00e8ge",
    "sg:tags":[
        "-",
        "imitation"
    ],
    "wof:name":"Guns P",
    "wof:placetype":"venue"
},
  "geometry": {"coordinates":[5.5717539787,50.6422538757],"type":"Point"}
}