{
  "type": "Feature",
  "properties": {
    "iso:country":"BE",
    "sg:address":"Opperstraat 72",
    "sg:city":"Liedekerke",
    "sg:classifiers":[
        {
            "category":"Real Estate",
            "subcategory":"Architect",
            "type":"Services"
        }
    ],
    "sg:phone":"+32 53 68 04 78",
    "sg:postcode":"1770",
    "sg:province":"Vlaams-Brabant",
    "wof:name":"Evenepoel D",
    "wof:placetype":"venue"
},
  "geometry": {"coordinates":[4.087433815,50.8695144653],"type":"Point"}
}