{
  "type": "Feature",
  "properties": {
    "iso:country":"BE",
    "sg:address":"Avenue Monbijou 9",
    "sg:city":"Malmedy",
    "sg:classifiers":[
        {
            "category":"Retail",
            "subcategory":"Veterinary Services",
            "type":"Services"
        }
    ],
    "sg:phone":"+32 80 77 06 20",
    "sg:postcode":"4960",
    "sg:province":"Li\u00e8ge",
    "sg:tags":[
        "veterinarian"
    ],
    "wof:name":"Kalpers U",
    "wof:placetype":"venue"
},
  "geometry": {"coordinates":[6.035422802,50.4231071472],"type":"Point"}
}