{
  "type": "Feature",
  "properties": {
    "addr:full":"Oostendestraat 303a Torhout West-Vlaanderen 8820",
    "addr:housenumber":"303a",
    "addr:postcode":"8820",
    "addr:street":"Oostendestraat",
    "iso:country":"BE",
    "sg:address":"Oostendestraat 303a",
    "sg:city":"Torhout",
    "sg:classifiers":[
        {
            "category":"Building & Trades",
            "subcategory":"Construction",
            "type":"Services"
        }
    ],
    "sg:phone":"+32 50 21 66 01",
    "sg:postcode":"8820",
    "sg:province":"West-Vlaanderen",
    "sg:tags":[
        "stucco",
        "contractor"
    ],
    "wof:name":"Verhaeghe Bart",
    "wof:placetype":"venue"
},
  "geometry": {"coordinates":[3.0679380894,51.0763587952],"type":"Point"}
}