{
  "type": "Feature",
  "properties": {
    "iso:country":"BE",
    "sg:address":"Kerkstraat 62",
    "sg:city":"Affligem (hekelgem)",
    "sg:orig_category":"Ice-cream parlours",
    "sg:phone":"+32 53 68 22 89",
    "sg:postcode":"1790",
    "sg:province":"Vlaams-Brabant",
    "wof:name":"Den Ijsbeer",
    "wof:placetype":"venue"
},
  "geometry": {"coordinates":[4.1064939499,50.9098472595],"type":"Point"}
}