{
  "type": "Feature",
  "properties": {
    "addr:full":"Rue Du W\u00e8rh\u00ea 18 Weismes Li\u00e8ge 4950",
    "addr:housenumber":"18",
    "addr:postcode":"4950",
    "addr:street":"Rue Du We\u0300Rhe\u0302",
    "iso:country":"BE",
    "sg:address":"Rue Du W\u00e8rh\u00ea 18",
    "sg:city":"Weismes",
    "sg:classifiers":[
        {
            "category":"Building & Trades",
            "subcategory":"Landscaping Services",
            "type":"Services"
        }
    ],
    "sg:phone":"+32 80 67 86 23",
    "sg:postcode":"4950",
    "sg:province":"Li\u00e8ge",
    "sg:tags":[
        "gardening",
        "garden",
        "maintenance"
    ],
    "wof:name":"Ferrain F",
    "wof:placetype":"venue"
},
  "geometry": {"coordinates":[6.1008958817,50.3951530457],"type":"Point"}
}