{
  "type": "Feature",
  "properties": {
    "iso:country":"BE",
    "sg:address":"Rue Des Brasseries 12",
    "sg:city":"Wavre",
    "sg:classifiers":[
        {
            "category":"Shopping",
            "subcategory":"Jewelry",
            "type":"Retail Goods"
        }
    ],
    "sg:phone":"+32 10 22 66 50",
    "sg:postcode":"1300",
    "sg:province":"Brabant Wallon",
    "sg:tags":[
        "jeweller",
        "-"
    ],
    "wof:name":"Isocele (bijoux)",
    "wof:placetype":"venue"
},
  "geometry": {"coordinates":[4.6113882065,50.7154541016],"type":"Point"}
}