{
  "type": "Feature",
  "properties": {
    "addr:full":"Oeverstraat 16 Lokeren Oost-Vlaanderen 9160",
    "addr:housenumber":"16",
    "addr:postcode":"9160",
    "addr:street":"Oeverstraat",
    "iso:country":"BE",
    "sg:address":"Oeverstraat 16",
    "sg:city":"Lokeren",
    "sg:orig_category":"Watersport-, Sport- and Kampeerbenodigdheden Verhuur",
    "sg:phone":"+32 9 349 39 50",
    "sg:postcode":"9160",
    "sg:province":"Oost-Vlaanderen",
    "wof:name":"Mountainbike Shop",
    "wof:placetype":"venue"
},
  "geometry": {"coordinates":[4.0184168816,51.0964126587],"type":"Point"}
}