{
  "type": "Feature",
  "properties": {
    "addr:full":"Zoning Industriel Floriffoux Namur 5150",
    "addr:postcode":"5150",
    "addr:street":"Zoning Industriel",
    "iso:country":"BE",
    "sg:address":"Zoning Industriel",
    "sg:city":"Floriffoux",
    "sg:classifiers":[
        {
            "category":"Manufacturing",
            "subcategory":"Wood Products",
            "type":"Manufacturing & Wholesale Goods"
        }
    ],
    "sg:phone":"+32 81 44 54 81",
    "sg:postcode":"5150",
    "sg:province":"Namur",
    "sg:tags":[
        "gate",
        "made",
        "door"
    ],
    "wof:name":"Iso Chassis S.p.r.l.",
    "wof:placetype":"venue"
},
  "geometry": {"coordinates":[4.7696647644,50.4532546997],"type":"Point"}
}