{
  "type": "Feature",
  "properties": {
    "iso:country":"BE",
    "sg:address":"Ploegsebaan 63",
    "sg:city":"Brasschaat",
    "sg:classifiers":[
        {
            "category":"Health Services",
            "subcategory":"Doctor",
            "type":"Services"
        }
    ],
    "sg:phone":"+32 3 633 09 00",
    "sg:postcode":"2930",
    "sg:province":"Antwerpen",
    "sg:tags":[
        "medicinephysicians",
        "surgeon"
    ],
    "wof:name":"Coene Luc",
    "wof:placetype":"venue"
},
  "geometry": {"coordinates":[4.5072350502,51.311794281],"type":"Point"}
}