{
  "type": "Feature",
  "properties": {
    "iso:country":"BE",
    "sg:address":"Avenue Des Pagodes 9",
    "sg:city":"Brussel",
    "sg:orig_category":"Rev\u00eatements de sols and murs",
    "sg:phone":"+32 2 245 16 33",
    "sg:postcode":"1020",
    "sg:province":"Bruxelles-Capitale",
    "wof:name":"Nosratabadi",
    "wof:placetype":"venue"
},
  "geometry": {"coordinates":[4.3752841949,50.8891983032],"type":"Point"}
}