{
  "type": "Feature",
  "properties": {
    "addr:full":"Stationsstr 80 Lendelede West-Vlaanderen 8860",
    "addr:housenumber":"80",
    "addr:postcode":"8860",
    "addr:street":"Stationsstr",
    "iso:country":"BE",
    "sg:address":"Stationsstr 80",
    "sg:city":"Lendelede",
    "sg:classifiers":[
        {
            "category":"Shopping",
            "subcategory":"Crafts & Fabrics",
            "type":"Retail Goods"
        }
    ],
    "sg:phone":"+32 51 33 36 66",
    "sg:postcode":"8860",
    "sg:province":"West-Vlaanderen",
    "sg:tags":[
        "textile",
        "clothing"
    ],
    "wof:name":"Nelca Nv",
    "wof:placetype":"venue"
},
  "geometry": {"coordinates":[3.2487299442,50.8853149414],"type":"Point"}
}