{
  "type": "Feature",
  "properties": {
    "iso:country":"BE",
    "sg:address":"Rue Saremont 2",
    "sg:city":"Herve",
    "sg:orig_category":"Eleveurs and marchands de porcs",
    "sg:phone":"+32 87 67 47 28",
    "sg:postcode":"4653",
    "sg:province":"Li\u00e8ge",
    "wof:name":"Sabine Wangen",
    "wof:placetype":"venue"
},
  "geometry": {"coordinates":[5.7752752304,50.6528968811],"type":"Point"}
}