{
  "type": "Feature",
  "properties": {
    "addr:full":"Kuilstraat 2 Sint-niklaas Oost-Vlaanderen 9111",
    "addr:housenumber":"2",
    "addr:postcode":"9111",
    "addr:street":"Kuilstraat",
    "iso:country":"BE",
    "sg:address":"Kuilstraat 2",
    "sg:city":"Sint-niklaas",
    "sg:orig_category":"Industri\u00eble and commerci\u00eble bouw Woningbouw",
    "sg:phone":"+32 3 772 41 56",
    "sg:postcode":"9111",
    "sg:province":"Oost-Vlaanderen",
    "wof:name":"Van Hauwermeiren",
    "wof:placetype":"venue"
},
  "geometry": {"coordinates":[4.0835299492,51.1519432068],"type":"Point"}
}