{
  "type": "Feature",
  "properties": {
    "addr:full":"Torhoutsesteenweg 36 Oostende West-Vlaanderen 8400",
    "addr:housenumber":"36",
    "addr:postcode":"8400",
    "addr:street":"Torhoutsesteenweg",
    "iso:country":"BE",
    "sg:address":"Torhoutsesteenweg 36",
    "sg:city":"Oostende",
    "sg:orig_category":"Blanchisseries and teintureries",
    "sg:phone":"+32 59 80 30 16",
    "sg:postcode":"8400",
    "sg:province":"West-Vlaanderen",
    "wof:name":"Euro Shop",
    "wof:placetype":"venue"
},
  "geometry": {"coordinates":[2.9098160267,51.2263374329],"type":"Point"}
}