{
  "type": "Feature",
  "properties": {
    "iso:country":"BE",
    "sg:address":"Rue Elise 121",
    "sg:city":"Elsene/ixelles",
    "sg:orig_category":"Informaticaconsulenten",
    "sg:phone":"+32 2 646 00 62",
    "sg:postcode":"1050",
    "sg:province":"Bruxelles-Capitale",
    "wof:name":"Vanden Bossche F",
    "wof:placetype":"venue"
},
  "geometry": {"coordinates":[4.3821120262,50.8174362183],"type":"Point"}
}