{
  "type": "Feature",
  "properties": {
    "addr:full":"Rue Georges Dubreucq 17 Ellezelles Hainaut 7890",
    "addr:housenumber":"17",
    "addr:postcode":"7890",
    "addr:street":"Rue Georges Dubreucq",
    "iso:country":"BE",
    "sg:address":"Rue Georges Dubreucq 17",
    "sg:city":"Ellezelles",
    "sg:classifiers":[
        {
            "category":"Arena",
            "subcategory":"Sports Club",
            "type":"Entertainment"
        }
    ],
    "sg:phone":"+32 68 44 82 50",
    "sg:postcode":"7890",
    "sg:province":"Hainaut",
    "sg:tags":[
        "de"
    ],
    "wof:name":"V\u00c9lo Club Sp. & Loisirs",
    "wof:placetype":"venue"
},
  "geometry": {"coordinates":[3.7426810265,50.7193717957],"type":"Point"}
}