{
  "type": "Feature",
  "properties": {
    "addr:full":"Stationsstraat 2 Zonhoven Limburg 3520",
    "addr:housenumber":"2",
    "addr:postcode":"3520",
    "addr:street":"Stationsstraat",
    "iso:country":"BE",
    "sg:address":"Stationsstraat 2",
    "sg:city":"Zonhoven",
    "sg:classifiers":[
        {
            "category":"Health Services",
            "subcategory":"Health Practitioner",
            "type":"Services"
        }
    ],
    "sg:phone":"+32 11 82 57 84",
    "sg:postcode":"3520",
    "sg:province":"Limburg",
    "sg:tags":[
        "physiotherapist"
    ],
    "wof:name":"Magdelijns Ann",
    "wof:placetype":"venue"
},
  "geometry": {"coordinates":[5.3520569801,50.9838447571],"type":"Point"}
}