{
  "type": "Feature",
  "properties": {
    "addr:full":"Nieuwstraat 4 Gavere Oost-Vlaanderen 9890",
    "addr:housenumber":"4",
    "addr:postcode":"9890",
    "addr:street":"Nieuwstraat",
    "iso:country":"BE",
    "sg:address":"Nieuwstraat 4",
    "sg:city":"Gavere",
    "sg:orig_category":"Brood, gebak and snoepgoed",
    "sg:phone":"+32 9 384 78 43",
    "sg:postcode":"9890",
    "sg:province":"Oost-Vlaanderen",
    "wof:name":"Leonidas",
    "wof:placetype":"venue"
},
  "geometry": {"coordinates":[3.6591699123,50.9290771484],"type":"Point"}
}