{
  "type": "Feature",
  "properties": {
    "iso:country":"BE",
    "sg:address":"Sprimont 4",
    "sg:city":"Sainte-ode (amberloup)",
    "sg:classifiers":[
        {
            "category":"Airport",
            "subcategory":"International",
            "type":"Transportation"
        }
    ],
    "sg:phone":"+32 61 68 84 48",
    "sg:postcode":"6680",
    "sg:province":"Luxembourg",
    "sg:tags":[
        "-",
        "transport"
    ],
    "wof:name":"Witrans Sprl",
    "wof:placetype":"venue"
},
  "geometry": {"coordinates":[5.5304489136,50.0108299255],"type":"Point"}
}