{
  "type": "Feature",
  "properties": {
    "addr:full":"Van Landeghemstraat 49 Sint-niklaas Oost-Vlaanderen 9100",
    "addr:housenumber":"49",
    "addr:postcode":"9100",
    "addr:street":"Van Landeghemstraat",
    "iso:country":"BE",
    "sg:address":"Van Landeghemstraat 49",
    "sg:city":"Sint-niklaas",
    "sg:orig_category":"Installation \u00e9lectrique r\u00e9sidentielle",
    "sg:phone":"+32 3 777 15 24",
    "sg:postcode":"9100",
    "sg:province":"Oost-Vlaanderen",
    "wof:name":"Emiel De Stobbeleir",
    "wof:placetype":"venue"
},
  "geometry": {"coordinates":[4.1808109283,51.1673965454],"type":"Point"}
}