{
  "type": "Feature",
  "properties": {
    "addr:full":"Rijksweg 928 Dilsen-stokkem Limburg 3650",
    "addr:housenumber":"928",
    "addr:postcode":"3650",
    "addr:street":"Rijksweg",
    "iso:country":"BE",
    "sg:address":"Rijksweg 928",
    "sg:city":"Dilsen-stokkem",
    "sg:orig_category":"Magasins sp\u00e9cialis\u00e9s",
    "sg:phone":"+32 89 56 55 57",
    "sg:postcode":"3650",
    "sg:province":"Limburg",
    "wof:name":"Open Haarden Smeulders",
    "wof:placetype":"venue"
},
  "geometry": {"coordinates":[5.7348308563,51.0439147949],"type":"Point"}
}