{
  "type": "Feature",
  "properties": {
    "addr:full":"Square S. Hoedemaekers 24 Bte 47 Etterbeek/etterbeek Bruxelles-Capitale 1040",
    "addr:housenumber":"24 bte 47",
    "addr:postcode":"1040",
    "addr:street":"Square S. Hoedemaekers",
    "iso:country":"BE",
    "sg:address":"Square S. Hoedemaekers 24 Bte 47",
    "sg:city":"Etterbeek/etterbeek",
    "sg:orig_category":"Elektrische installaties voor woningen",
    "sg:phone":"+32 2 216 16 19",
    "sg:postcode":"1040",
    "sg:province":"Bruxelles-Capitale",
    "wof:name":"Etiphone",
    "wof:placetype":"venue"
},
  "geometry": {"coordinates":[4.3951997757,50.8335914612],"type":"Point"}
}