{
  "type": "Feature",
  "properties": {
    "iso:country":"BE",
    "sg:address":"Rue De Hotchamps 9",
    "sg:city":"Sprimont",
    "sg:orig_category":"Eleveurs de bovins",
    "sg:phone":"+32 4 360 85 30",
    "sg:postcode":"4141",
    "sg:province":"Li\u00e8ge",
    "wof:name":"Mathilde Thewissen",
    "wof:placetype":"venue"
},
  "geometry": {"coordinates":[5.7102560997,50.5312538147],"type":"Point"}
}