{
  "type": "Feature",
  "properties": {
    "addr:full":"Rue De La Station 21 Waterloo Brabant Wallon 1410",
    "addr:housenumber":"21",
    "addr:postcode":"1410",
    "addr:street":"Rue De La Station",
    "iso:country":"BE",
    "sg:address":"Rue De La Station 21",
    "sg:city":"Waterloo",
    "sg:orig_category":"G\u00e9om\u00e8tres",
    "sg:phone":"+32 2 354 67 68",
    "sg:postcode":"1410",
    "sg:province":"Brabant Wallon",
    "wof:name":"Jean Tomson",
    "wof:placetype":"venue"
},
  "geometry": {"coordinates":[4.3928399086,50.7168426514],"type":"Point"}
}