{
  "type": "Feature",
  "properties": {
    "addr:full":"Brugsesteenweg 42 Harelbeke (hulste) West-Vlaanderen 8531",
    "addr:housenumber":"42",
    "addr:postcode":"8531",
    "addr:street":"Brugsesteenweg",
    "iso:country":"BE",
    "sg:address":"Brugsesteenweg 42",
    "sg:city":"Harelbeke (hulste)",
    "sg:orig_category":"Non-Classified Establishments",
    "sg:phone":"+32 51 31 47 10",
    "sg:postcode":"8531",
    "sg:province":"West-Vlaanderen",
    "wof:name":"Castellino Nv",
    "wof:placetype":"venue"
},
  "geometry": {"coordinates":[3.271173954,50.8907432556],"type":"Point"}
}