{
  "type": "Feature",
  "properties": {
    "addr:full":"Koekoekstraat 50 Waregem West-Vlaanderen 8793",
    "addr:housenumber":"50",
    "addr:postcode":"8793",
    "addr:street":"Koekoekstraat",
    "iso:country":"BE",
    "sg:address":"Koekoekstraat 50",
    "sg:city":"Waregem",
    "sg:orig_category":"Plomberie, chauffage and installations sanitaires",
    "sg:phone":"+32 56 60 29 64",
    "sg:postcode":"8793",
    "sg:province":"West-Vlaanderen",
    "wof:name":"Sani-elec De Jaegher",
    "wof:placetype":"venue"
},
  "geometry": {"coordinates":[3.4029569626,50.9024581909],"type":"Point"}
}