{
  "type": "Feature",
  "properties": {
    "addr:full":"Uilenspiegelstraat 44 Hooglede West-Vlaanderen 8830",
    "addr:housenumber":"44",
    "addr:postcode":"8830",
    "addr:street":"Uilenspiegelstraat",
    "iso:country":"BE",
    "sg:address":"Uilenspiegelstraat 44",
    "sg:city":"Hooglede",
    "sg:classifiers":[
        {
            "category":"Building & Trades",
            "subcategory":"Plumbing",
            "type":"Services"
        }
    ],
    "sg:phone":"+32 51 24 75 64",
    "sg:postcode":"8830",
    "sg:province":"West-Vlaanderen",
    "sg:tags":[
        "contractor"
    ],
    "wof:name":"Godderis K",
    "wof:placetype":"venue"
},
  "geometry": {"coordinates":[3.0871078968,50.9736595154],"type":"Point"}
}