{
  "type": "Feature",
  "properties": {
    "iso:country":"BE",
    "sg:address":"Chemin Du Happart 3",
    "sg:city":"Bernissart",
    "sg:orig_category":"Industri\u00eble wasserijen and droogkuis",
    "sg:phone":"+32 65 62 23 55",
    "sg:postcode":"7322",
    "sg:province":"Hainaut",
    "wof:name":"John Vervisch",
    "wof:placetype":"venue"
},
  "geometry": {"coordinates":[3.7305009365,50.4901123047],"type":"Point"}
}