{
  "type": "Feature",
  "properties": {
    "addr:full":"Zultseweg 10 Waregem West-Vlaanderen 8790",
    "addr:housenumber":"10",
    "addr:postcode":"8790",
    "addr:street":"Zultseweg",
    "iso:country":"BE",
    "sg:address":"Zultseweg 10",
    "sg:city":"Waregem",
    "sg:classifiers":[
        {
            "category":"Shopping",
            "subcategory":"Computers & Home Electronics",
            "type":"Retail Goods"
        }
    ],
    "sg:phone":"+32 56 60 08 06",
    "sg:postcode":"8790",
    "sg:province":"West-Vlaanderen",
    "sg:tags":[
        "equipment",
        "household",
        "electrical",
        "appliance",
        "electronic"
    ],
    "wof:name":"Inter Spare Parts Nv",
    "wof:placetype":"venue"
},
  "geometry": {"coordinates":[3.4371039867,50.8909683228],"type":"Point"}
}