{
  "type": "Feature",
  "properties": {
    "addr:full":"Markt 25 Lede Oost-Vlaanderen 9340",
    "addr:housenumber":"25",
    "addr:postcode":"9340",
    "addr:street":"Markt",
    "iso:country":"BE",
    "sg:address":"Markt 25",
    "sg:city":"Lede",
    "sg:orig_category":"Banques and organismes de cr\u00e9dit",
    "sg:phone":"+32 53 80 47 14",
    "sg:postcode":"9340",
    "sg:province":"Oost-Vlaanderen",
    "wof:name":"Bbl",
    "wof:placetype":"venue"
},
  "geometry": {"coordinates":[3.9778740406,50.9665527344],"type":"Point"}
}