{
  "type": "Feature",
  "properties": {
    "iso:country":"BE",
    "sg:address":"Kiezelweg 188",
    "sg:city":"Mol",
    "sg:classifiers":[
        {
            "category":"Utilities",
            "subcategory":"Telephone",
            "type":"Services"
        }
    ],
    "sg:phone":"+32 14 71 40 41",
    "sg:postcode":"2400",
    "sg:province":"Antwerpen",
    "sg:tags":[
        "-",
        "internet"
    ],
    "wof:name":"Emwis Bvba",
    "wof:placetype":"venue"
},
  "geometry": {"coordinates":[5.1930098534,51.2158508301],"type":"Point"}
}