{
  "type": "Feature",
  "properties": {
    "iso:country":"BE",
    "sg:address":"Rue De Souvret 62",
    "sg:city":"Courcelles",
    "sg:orig_category":"Herstellingswinkels voor diverse persoonlijke and huishoudartikelen",
    "sg:phone":"+32 71 45 34 60",
    "sg:postcode":"6180",
    "sg:province":"Hainaut",
    "wof:name":"Maison Maracry's",
    "wof:placetype":"venue"
},
  "geometry": {"coordinates":[4.3624181747,50.4554481506],"type":"Point"}
}