{
  "type": "Feature",
  "properties": {
    "addr:full":"Sint-elisabethplein 9 Gent Oost-Vlaanderen 9000",
    "addr:housenumber":"9",
    "addr:postcode":"9000",
    "addr:street":"Sint-Elisabethplein;Oost-Vlaanderen",
    "iso:country":"BE",
    "sg:address":"Sint-elisabethplein 9",
    "sg:city":"Gent",
    "sg:classifiers":[
        {
            "category":"Health Services",
            "subcategory":"Health Practitioner",
            "type":"Services"
        }
    ],
    "sg:phone":"+32 9 224 04 37",
    "sg:postcode":"9000",
    "sg:province":"Oost-Vlaanderen",
    "sg:tags":[
        "physiotherapist"
    ],
    "wof:name":"Roelants Christel",
    "wof:placetype":"venue"
},
  "geometry": {"coordinates":[3.7138719559,51.0371360779],"type":"Point"}
}