{
  "type": "Feature",
  "properties": {
    "iso:country":"BE",
    "sg:address":"Avenue Des Arts 50b14",
    "sg:city":"Brussel",
    "sg:orig_category":"Ambassades and consulaten",
    "sg:phone":"+32 2 500 09 44",
    "sg:postcode":"1000",
    "sg:province":"Bruxelles-Capitale",
    "wof:name":"Ambassade Kroati\u00cb",
    "wof:placetype":"venue"
},
  "geometry": {"coordinates":[4.3671369553,50.8419303894],"type":"Point"}
}