{
  "type": "Feature",
  "properties": {
    "addr:full":"Fran\u00c7ois Bossaertsstraat 70 Schaarbeek/schaerbeek Bruxelles-Capitale 1030",
    "addr:housenumber":"70",
    "addr:postcode":"1030",
    "addr:street":"Franc\u0327Ois Bossaertsstraat",
    "iso:country":"BE",
    "sg:address":"Fran\u00c7ois Bossaertsstraat 70",
    "sg:city":"Schaarbeek/schaerbeek",
    "sg:orig_category":"Sportclubs",
    "sg:phone":"+32 2 241 39 03",
    "sg:postcode":"1030",
    "sg:province":"Bruxelles-Capitale",
    "wof:name":"J.c. Sant\u00c9 Publique",
    "wof:placetype":"venue"
},
  "geometry": {"coordinates":[4.3860988617,50.8552207947],"type":"Point"}
}