{
  "type": "Feature",
  "properties": {
    "addr:full":"Honsfeld 33a B\u00fcllingen Li\u00e8ge 4760",
    "addr:housenumber":"33a",
    "addr:postcode":"4760",
    "addr:street":"Honsfeld",
    "iso:country":"BE",
    "sg:address":"Honsfeld 33a",
    "sg:city":"B\u00fcllingen",
    "sg:classifiers":[
        {
            "category":"Home & Garden",
            "subcategory":"Household Appliances",
            "type":"Retail Goods"
        }
    ],
    "sg:phone":"+32 80 64 20 91",
    "sg:postcode":"4760",
    "sg:province":"Li\u00e8ge",
    "sg:tags":[
        "repair",
        "mainten",
        "-",
        "electric"
    ],
    "wof:name":"Mollers G.",
    "wof:placetype":"venue"
},
  "geometry": {"coordinates":[6.2827768326,50.3811035156],"type":"Point"}
}