{
  "type": "Feature",
  "properties": {
    "addr:full":"Rue Saint-georges 96 Bruxelles (ixelles) Bruxelles-Capitale 1050",
    "addr:housenumber":"96",
    "addr:postcode":"1050",
    "addr:street":"Rue Saint-Georges",
    "iso:country":"BE",
    "sg:address":"Rue Saint-georges 96",
    "sg:city":"Bruxelles (ixelles)",
    "sg:classifiers":[
        {
            "category":"Banks & Credit Unions",
            "subcategory":"Investment Brokerage",
            "type":"Services"
        }
    ],
    "sg:phone":"+32 2 649 03 03",
    "sg:postcode":"1050",
    "sg:province":"Bruxelles-Capitale",
    "sg:tags":[
        "incentive"
    ],
    "wof:name":"Team Spirit International Sprl",
    "wof:placetype":"venue"
},
  "geometry": {"coordinates":[4.3681988716,50.8165168762],"type":"Point"}
}