{
  "type": "Feature",
  "properties": {
    "addr:full":"Rue Gustave Bo\u00ebl 22 La Louvi\u00e8re Hainaut 7100",
    "addr:housenumber":"22",
    "addr:postcode":"7100",
    "addr:street":"Rue Gustave Boe\u0308L",
    "iso:country":"BE",
    "sg:address":"Rue Gustave Bo\u00ebl 22",
    "sg:city":"La Louvi\u00e8re",
    "sg:classifiers":[
        {
            "category":"Home & Garden",
            "subcategory":"Furniture",
            "type":"Retail Goods"
        }
    ],
    "sg:phone":"+32 64 21 47 90",
    "sg:postcode":"7100",
    "sg:province":"Hainaut",
    "sg:tags":[
        "used",
        "-"
    ],
    "wof:name":"Occa Meubles",
    "wof:placetype":"venue"
},
  "geometry": {"coordinates":[4.1770839691,50.4779167175],"type":"Point"}
}