{
  "type": "Feature",
  "properties": {
    "addr:full":"Sint-truidensesteenweg 132 Linter Vlaams-Brabant 3350",
    "addr:housenumber":"132",
    "addr:postcode":"3350",
    "addr:street":"Sint-Truidensesteenweg;Vlaams-Brabant",
    "iso:country":"BE",
    "sg:address":"Sint-truidensesteenweg 132",
    "sg:city":"Linter",
    "sg:orig_category":"Metaalafval, schrootrecyclage and sloperijen",
    "sg:phone":"+32 16 78 80 84",
    "sg:postcode":"3350",
    "sg:province":"Vlaams-Brabant",
    "wof:name":"Mamo",
    "wof:placetype":"venue"
},
  "geometry": {"coordinates":[5.0107297897,50.7979125977],"type":"Point"}
}