{
  "type": "Feature",
  "properties": {
    "iso:country":"BE",
    "sg:address":"Rue Cav\u00c9e 4",
    "sg:city":"Silly",
    "sg:classifiers":[
        {
            "category":"Personal",
            "subcategory":"Beauty Salon",
            "type":"Services"
        }
    ],
    "sg:phone":"+32 68 55 15 19",
    "sg:postcode":"7830",
    "sg:province":"Hainaut",
    "sg:tags":[
        "de",
        "coiffure"
    ],
    "wof:name":"Anne Mahieux",
    "wof:placetype":"venue"
},
  "geometry": {"coordinates":[3.9346909523,50.6756286621],"type":"Point"}
}