{
  "type": "Feature",
  "properties": {
    "iso:country":"BE",
    "sg:address":"Sint-luciastraat 2",
    "sg:city":"Balen",
    "sg:orig_category":"Non-Classified Establishments",
    "sg:phone":"+32 14 31 93 36",
    "sg:postcode":"2490",
    "sg:province":"Antwerpen",
    "wof:name":"Bel-choc Nv",
    "wof:placetype":"venue"
},
  "geometry": {"coordinates":[5.1363749504,51.1701622009],"type":"Point"}
}