{
  "type": "Feature",
  "properties": {
    "addr:full":"Mechelsesteenweg 690 Herent Vlaams-Brabant 3020",
    "addr:housenumber":"690",
    "addr:postcode":"3020",
    "addr:street":"Mechelsesteenweg",
    "iso:country":"BE",
    "sg:address":"Mechelsesteenweg 690",
    "sg:city":"Herent",
    "sg:orig_category":"Antiquit\u00e9s",
    "sg:phone":"+32 16 29 15 52",
    "sg:postcode":"3020",
    "sg:province":"Vlaams-Brabant",
    "wof:name":"Paul Taels",
    "wof:placetype":"venue"
},
  "geometry": {"coordinates":[4.6565790176,50.9148216248],"type":"Point"}
}