{
  "type": "Feature",
  "properties": {
    "iso:country":"BE",
    "sg:address":"Heidestraat 87",
    "sg:city":"Ternat (groot)",
    "sg:classifiers":[
        {
            "category":"Personal",
            "subcategory":"Beauty Salon",
            "type":"Services"
        }
    ],
    "sg:phone":"+32 2 582 24 78",
    "sg:postcode":"1742",
    "sg:province":"Vlaams-Brabant",
    "sg:tags":[
        "de",
        "coiffure"
    ],
    "wof:name":"Coiffure Kathy",
    "wof:placetype":"venue"
},
  "geometry": {"coordinates":[4.1397547722,50.8680915833],"type":"Point"}
}