{
  "type": "Feature",
  "properties": {
    "addr:full":"Ginderbuiten 44 Mol Antwerpen 2400",
    "addr:housenumber":"44",
    "addr:postcode":"2400",
    "addr:street":"Ginderbuiten",
    "iso:country":"BE",
    "sg:address":"Ginderbuiten 44",
    "sg:city":"Mol",
    "sg:classifiers":[
        {
            "category":"Health Services",
            "subcategory":"Health Practitioner",
            "type":"Services"
        }
    ],
    "sg:phone":"+32 14 31 37 87",
    "sg:postcode":"2400",
    "sg:province":"Antwerpen",
    "sg:tags":[
        "physiotherapist"
    ],
    "wof:name":"Willems Marina",
    "wof:placetype":"venue"
},
  "geometry": {"coordinates":[5.1291689873,51.1950263977],"type":"Point"}
}