{
  "type": "Feature",
  "properties": {
    "iso:country":"BE",
    "sg:address":"Breeveldse Masten 5",
    "sg:city":"Schilde",
    "sg:orig_category":"Sportclubs",
    "sg:phone":"+32 3 383 57 75",
    "sg:postcode":"2970",
    "sg:province":"Antwerpen",
    "wof:name":"T.c. Groenhove",
    "wof:placetype":"venue"
},
  "geometry": {"coordinates":[4.6140708923,51.2430801392],"type":"Point"}
}