{
  "type": "Feature",
  "properties": {
    "addr:full":"Leuvensesteenweg 356 Boutersem Vlaams-Brabant 3370",
    "addr:housenumber":"356",
    "addr:postcode":"3370",
    "addr:street":"Leuvensesteenweg",
    "iso:country":"BE",
    "sg:address":"Leuvensesteenweg 356",
    "sg:city":"Boutersem",
    "sg:orig_category":"Installation de menuiserie en bois and plastique",
    "sg:phone":"+32 16 73 35 78",
    "sg:postcode":"3370",
    "sg:province":"Vlaams-Brabant",
    "wof:name":"Andre Coeckelberghs",
    "wof:placetype":"venue"
},
  "geometry": {"coordinates":[4.8301839828,50.8429260254],"type":"Point"}
}