{
  "type": "Feature",
  "properties": {
    "iso:country":"BE",
    "sg:address":"Merellaan 32",
    "sg:city":"Ranst",
    "sg:orig_category":"Plaatsen van vloer- and muurbekleding Schilders",
    "sg:phone":"+32 3 475 03 28",
    "sg:postcode":"2520",
    "sg:province":"Antwerpen",
    "wof:name":"Koenraad Swiers",
    "wof:placetype":"venue"
},
  "geometry": {"coordinates":[4.5553908348,51.1871833801],"type":"Point"}
}