{
  "type": "Feature",
  "properties": {
    "addr:full":"Route De Bambois 48 Fosses-la-ville Namur 5070",
    "addr:housenumber":"48",
    "addr:postcode":"5070",
    "addr:street":"Route De Bambois",
    "iso:country":"BE",
    "sg:address":"Route De Bambois 48",
    "sg:city":"Fosses-la-ville",
    "sg:classifiers":[
        {
            "category":"Fast Food",
            "type":"Food & Drink"
        }
    ],
    "sg:phone":"+32 71 71 18 66",
    "sg:postcode":"5070",
    "sg:province":"Namur",
    "sg:tags":[
        "meeneem",
        "restaurant"
    ],
    "wof:name":"Friterie Rita Deprez",
    "wof:placetype":"venue"
},
  "geometry": {"coordinates":[4.6996331215,50.3896980286],"type":"Point"}
}