{
  "type": "Feature",
  "properties": {
    "addr:full":"Nieuwdreef 23-25 Antwerpen (merksem) Antwerpen 2170",
    "addr:postcode":"23-25;2170",
    "addr:street":"Nieuwdreef",
    "iso:country":"BE",
    "sg:address":"Nieuwdreef 23-25",
    "sg:city":"Antwerpen (merksem)",
    "sg:classifiers":[
        {
            "category":"Professional",
            "type":"Services"
        }
    ],
    "sg:phone":"+32 3 644 50 74",
    "sg:postcode":"2170",
    "sg:province":"Antwerpen",
    "sg:tags":[
        "sharpening"
    ],
    "wof:name":"Anedro-service Bvba",
    "wof:placetype":"venue"
},
  "geometry": {"coordinates":[4.4505147934,51.246723175],"type":"Point"}
}