{
  "type": "Feature",
  "properties": {
    "addr:full":"Rue De L'industrie 1 Box 23 Charleroi Hainaut 6000",
    "addr:housenumber":"1 box 23",
    "addr:postcode":"6000",
    "addr:street":"Rue De L'Industrie;Hainaut",
    "iso:country":"BE",
    "sg:address":"Rue De L'industrie 1 Box 23",
    "sg:city":"Charleroi",
    "sg:classifiers":[
        {
            "category":"Professional",
            "subcategory":"Accounting & Tax Preparation",
            "type":"Services"
        }
    ],
    "sg:phone":"+32 71 31 23 63",
    "sg:postcode":"6000",
    "sg:province":"Hainaut",
    "sg:tags":[
        "accountant"
    ],
    "wof:name":"Delpierre Fiduciaire Sprl",
    "wof:placetype":"venue"
},
  "geometry": {"coordinates":[4.4390439987,50.4068984985],"type":"Point"}
}