{
  "type": "Feature",
  "properties": {
    "addr:full":"Opperstraat 19 Moerbeke (moerbeke-waas) Oost-Vlaanderen 9180",
    "addr:housenumber":"19",
    "addr:postcode":"9180",
    "addr:street":"Opperstraat",
    "iso:country":"BE",
    "sg:address":"Opperstraat 19",
    "sg:city":"Moerbeke (moerbeke-waas)",
    "sg:classifiers":[
        {
            "category":"Health Services",
            "subcategory":"Health Practitioner",
            "type":"Services"
        }
    ],
    "sg:phone":"+32 9 346 57 77",
    "sg:postcode":"9180",
    "sg:province":"Oost-Vlaanderen",
    "sg:tags":[
        "physiotherapist"
    ],
    "wof:name":"Van Damme Gert",
    "wof:placetype":"venue"
},
  "geometry": {"coordinates":[3.9401071072,51.1743774414],"type":"Point"}
}