{
  "type": "Feature",
  "properties": {
    "addr:full":"Rue De L\u00b4eglise 210 Voeren/fourons Limburg 3798",
    "addr:housenumber":"210",
    "addr:postcode":"3798",
    "addr:street":"Rue De L\u00b4Eglise",
    "iso:country":"BE",
    "sg:address":"Rue De L\u00b4eglise 210",
    "sg:city":"Voeren/fourons",
    "sg:orig_category":"Banques and organismes de cr\u00e9dit",
    "sg:phone":"+32 4 381 00 44",
    "sg:postcode":"3798",
    "sg:province":"Limburg",
    "wof:name":"Kbc",
    "wof:placetype":"venue"
},
  "geometry": {"coordinates":[5.7698001862,50.761089325],"type":"Point"}
}