{
  "type": "Feature",
  "properties": {
    "iso:country":"BE",
    "sg:address":"Maaiken 6",
    "sg:city":"Knokke-heist (westkapelle)",
    "sg:classifiers":[
        {
            "category":"Real Estate",
            "subcategory":"Real Estate Agent",
            "type":"Services"
        }
    ],
    "sg:phone":"+32 50 61 36 63",
    "sg:postcode":"8300",
    "sg:province":"West-Vlaanderen",
    "sg:tags":[
        "importer",
        "champagne",
        "-"
    ],
    "wof:name":"Blue Peter",
    "wof:placetype":"venue"
},
  "geometry": {"coordinates":[3.287694931,51.3467254639],"type":"Point"}
}