{
  "type": "Feature",
  "properties": {
    "iso:country":"BE",
    "sg:address":"Baron De P\u00e9lichystraat 23",
    "sg:city":"Izegem",
    "sg:classifiers":[
        {
            "category":"Retail",
            "subcategory":"Animal Services",
            "type":"Services"
        }
    ],
    "sg:phone":"+32 51 30 03 21",
    "sg:postcode":"8870",
    "sg:province":"West-Vlaanderen",
    "sg:tags":[
        "grooming",
        "-",
        "dog"
    ],
    "wof:name":"Marie-lou",
    "wof:placetype":"venue"
},
  "geometry": {"coordinates":[3.2126760483,50.9167137146],"type":"Point"}
}