{
  "type": "Feature",
  "properties": {
    "addr:full":"Gerheiden 34 Olen Antwerpen 2250",
    "addr:housenumber":"34",
    "addr:postcode":"2250",
    "addr:street":"Gerheiden",
    "iso:country":"BE",
    "sg:address":"Gerheiden 34",
    "sg:city":"Olen",
    "sg:classifiers":[
        {
            "category":"Personal",
            "subcategory":"Beauty Salon",
            "type":"Services"
        }
    ],
    "sg:phone":"+32 14 23 29 22",
    "sg:postcode":"2250",
    "sg:province":"Antwerpen",
    "sg:tags":[
        "de",
        "coiffure"
    ],
    "wof:name":"Mariette Ennekens",
    "wof:placetype":"venue"
},
  "geometry": {"coordinates":[4.8882718086,51.1630096436],"type":"Point"}
}