{
  "type": "Feature",
  "properties": {
    "iso:country":"BE",
    "sg:address":"J. Van Arteveldestraat 30",
    "sg:city":"Gent",
    "sg:orig_category":"Dierenartsen",
    "sg:phone":"+32 9 230 44 39",
    "sg:postcode":"9050",
    "sg:province":"Oost-Vlaanderen",
    "wof:name":"Tony Oyaert",
    "wof:placetype":"venue"
},
  "geometry": {"coordinates":[3.7513198853,51.0381546021],"type":"Point"}
}