{
  "type": "Feature",
  "properties": {
    "addr:full":"Rue De Jaunay-clan 14 Peruwelz Hainaut 7600",
    "addr:housenumber":"14",
    "addr:postcode":"7600",
    "addr:street":"Rue De Jaunay-Clan;Hainaut",
    "iso:country":"BE",
    "sg:address":"Rue De Jaunay-clan 14",
    "sg:city":"Peruwelz",
    "sg:orig_category":"Artsen and specialisten",
    "sg:phone":"+32 69 77 21 70",
    "sg:postcode":"7600",
    "sg:province":"Hainaut",
    "wof:name":"Eug\u00c8ne Dits",
    "wof:placetype":"venue"
},
  "geometry": {"coordinates":[3.5886089802,50.5156059265],"type":"Point"}
}