{
  "type": "Feature",
  "properties": {
    "addr:full":"Mechelsesteenweg 18 Antwerpen Antwerpen 2000",
    "addr:housenumber":"18",
    "addr:postcode":"2000",
    "addr:street":"Mechelsesteenweg",
    "iso:country":"BE",
    "sg:address":"Mechelsesteenweg 18",
    "sg:city":"Antwerpen",
    "sg:orig_category":"Banken and kredietinstellingen",
    "sg:phone":"+32 3 227 22 72",
    "sg:postcode":"2000",
    "sg:province":"Antwerpen",
    "wof:name":"Citibank",
    "wof:placetype":"venue"
},
  "geometry": {"coordinates":[4.4074840546,51.2113800049],"type":"Point"}
}