{
  "type": "Feature",
  "properties": {
    "iso:country":"BE",
    "sg:address":"Weg Naar Opoeteren 45",
    "sg:city":"Opglabbeek",
    "sg:classifiers":[
        {
            "category":"Building & Trades",
            "subcategory":"Cleaning & Sanitation",
            "type":"Services"
        }
    ],
    "sg:phone":"+32 89 85 32 19",
    "sg:postcode":"3660",
    "sg:province":"Limburg",
    "sg:tags":[
        "janitor"
    ],
    "wof:name":"Briljant Schoonmaakservice",
    "wof:placetype":"venue"
},
  "geometry": {"coordinates":[5.5907878876,51.0460205078],"type":"Point"}
}