{
  "type": "Feature",
  "properties": {
    "addr:full":"Brugsesteenweg 102 Oudenburg (roksem) West-Vlaanderen 8460",
    "addr:housenumber":"102",
    "addr:postcode":"8460",
    "addr:street":"Brugsesteenweg",
    "iso:country":"BE",
    "sg:address":"Brugsesteenweg 102",
    "sg:city":"Oudenburg (roksem)",
    "sg:classifiers":[
        {
            "category":"Building & Trades",
            "subcategory":"Electrical",
            "type":"Services"
        }
    ],
    "sg:phone":"+32 59 26 81 97",
    "sg:postcode":"8460",
    "sg:province":"West-Vlaanderen",
    "sg:tags":[
        "electric",
        "-",
        "housewiring",
        "contractor"
    ],
    "wof:name":"Messelier O",
    "wof:placetype":"venue"
},
  "geometry": {"coordinates":[3.0023450851,51.1840553284],"type":"Point"}
}