{
  "type": "Feature",
  "properties": {
    "addr:full":"Vrasenestraat 47 Beveren Oost-Vlaanderen 9120",
    "addr:housenumber":"47",
    "addr:postcode":"9120",
    "addr:street":"Vrasenestraat",
    "iso:country":"BE",
    "sg:address":"Vrasenestraat 47",
    "sg:city":"Beveren",
    "sg:orig_category":"Disquaires",
    "sg:phone":"+32 3 755 01 60",
    "sg:postcode":"9120",
    "sg:province":"Oost-Vlaanderen",
    "wof:name":"Fat Beats",
    "wof:placetype":"venue"
},
  "geometry": {"coordinates":[4.2543039322,51.2135429382],"type":"Point"}
}