{
  "type": "Feature",
  "properties": {
    "iso:country":"BE",
    "sg:address":"Knokseweg 33",
    "sg:city":"Knesselare",
    "sg:classifiers":[
        {
            "category":"Personal",
            "subcategory":"Nail Salon",
            "type":"Services"
        }
    ],
    "sg:phone":"+32 9 374 54 65",
    "sg:postcode":"9910",
    "sg:province":"Oost-Vlaanderen",
    "sg:tags":[
        "pedicure"
    ],
    "wof:name":"Carla",
    "wof:placetype":"venue"
},
  "geometry": {"coordinates":[3.4308979511,51.1510696411],"type":"Point"}
}