{
  "type": "Feature",
  "properties": {
    "addr:full":"Guido Gezelleplein 1 Wingene West-Vlaanderen 8750",
    "addr:housenumber":"1",
    "addr:postcode":"8750",
    "addr:street":"Guido Gezelleplein",
    "iso:country":"BE",
    "sg:address":"Guido Gezelleplein 1",
    "sg:city":"Wingene",
    "sg:orig_category":"Brood, gebak and snoepgoed",
    "sg:phone":"+32 51 65 54 86",
    "sg:postcode":"8750",
    "sg:province":"West-Vlaanderen",
    "wof:name":"William Jacobs",
    "wof:placetype":"venue"
},
  "geometry": {"coordinates":[3.2793080807,51.0582046509],"type":"Point"}
}