{
  "type": "Feature",
  "properties": {
    "iso:country":"BE",
    "sg:address":"Chauss\u00e9e De Nivelles 96",
    "sg:city":"Sombreffe",
    "sg:classifiers":[
        {
            "category":"Farming",
            "subcategory":"Farm & Veterinary Services",
            "type":"Manufacturing & Wholesale Goods"
        }
    ],
    "sg:phone":"+32 71 88 81 89",
    "sg:postcode":"5140",
    "sg:province":"Namur",
    "sg:tags":[
        "agricultural",
        "contractor"
    ],
    "wof:name":"Charlier B",
    "wof:placetype":"venue"
},
  "geometry": {"coordinates":[4.5962891579,50.5259552002],"type":"Point"}
}