{
  "type": "Feature",
  "properties": {
    "iso:country":"BE",
    "sg:address":"Alsembergse Steenweg 74",
    "sg:city":"Sint-gillis/saint-gilles",
    "sg:orig_category":"Artsen and specialisten",
    "sg:phone":"+32 2 538 69 38",
    "sg:postcode":"1060",
    "sg:province":"Bruxelles-Capitale",
    "wof:name":"Gis\u00c8le Lukuamusu Bakabukila",
    "wof:placetype":"venue"
},
  "geometry": {"coordinates":[4.3436169624,50.8243255615],"type":"Point"}
}