{
  "type": "Feature",
  "properties": {
    "addr:full":"Avenue Des Volontaires 233 Box 1-2 Bruxelles (woluwe-saint-pierre) Bruxelles-Capitale 1150",
    "addr:housenumber":"233 box 1-2",
    "addr:postcode":"1150",
    "addr:street":"Avenue Des Volontaires",
    "iso:country":"BE",
    "sg:address":"Avenue Des Volontaires 233 Box 1-2",
    "sg:city":"Bruxelles (woluwe-saint-pierre)",
    "sg:orig_category":"Fiduciairies",
    "sg:phone":"+32 2 734 41 56",
    "sg:postcode":"1150",
    "sg:province":"Bruxelles-Capitale",
    "wof:name":"Ami-consultants Sprl",
    "wof:placetype":"venue"
},
  "geometry": {"coordinates":[4.4305348396,50.837020874],"type":"Point"}
}