{
  "type": "Feature",
  "properties": {
    "iso:country":"BE",
    "sg:address":"Kapelstraat 30",
    "sg:city":"Essen",
    "sg:orig_category":"Agences de voyages. Transports ferroviaires",
    "sg:phone":"+32 3 667 32 79",
    "sg:postcode":"2910",
    "sg:province":"Antwerpen",
    "wof:name":"Van Hoof Reisburo",
    "wof:placetype":"venue"
},
  "geometry": {"coordinates":[4.4724597931,51.4639587402],"type":"Point"}
}