{
  "type": "Feature",
  "properties": {
    "addr:full":"Recogne 116 Bastogne (noville) Luxembourg 6600",
    "addr:housenumber":"116",
    "addr:postcode":"6600",
    "addr:street":"Recogne",
    "iso:country":"BE",
    "sg:address":"Recogne 116",
    "sg:city":"Bastogne (noville)",
    "sg:classifiers":[
        {
            "category":"Personal",
            "subcategory":"Barber",
            "type":"Services"
        }
    ],
    "sg:phone":"+32 61 21 23 29",
    "sg:postcode":"6600",
    "sg:province":"Luxembourg",
    "sg:tags":[
        "gentleman",
        "salon",
        "-",
        "hairdressing"
    ],
    "wof:name":"Sac P",
    "wof:placetype":"venue"
},
  "geometry": {"coordinates":[5.7148199081,50.0007820129],"type":"Point"}
}