{
  "type": "Feature",
  "properties": {
    "iso:country":"BE",
    "sg:address":"Bosquet \u00c0 Picots 6",
    "sg:city":"Seneffe",
    "sg:orig_category":"Alimentation sp\u00e9cialis\u00e9e",
    "sg:phone":"+32 64 55 44 20",
    "sg:postcode":"7180",
    "sg:province":"Hainaut",
    "wof:name":"Traiteur Borisalm",
    "wof:placetype":"venue"
},
  "geometry": {"coordinates":[4.2449331284,50.5354385376],"type":"Point"}
}