{
  "type": "Feature",
  "properties": {
    "addr:full":"Rue Alphonse Vande Maele 22 Evere Bruxelles-Capitale 1140",
    "addr:housenumber":"22",
    "addr:postcode":"1140",
    "addr:street":"Rue Alphonse Vande Maele",
    "iso:country":"BE",
    "sg:address":"Rue Alphonse Vande Maele 22",
    "sg:city":"Evere",
    "sg:orig_category":"Banques and organismes de cr\u00e9dit",
    "sg:phone":"+32 2 245 59 85",
    "sg:postcode":"1140",
    "sg:province":"Bruxelles-Capitale",
    "wof:name":"Groep Argenta",
    "wof:placetype":"venue"
},
  "geometry": {"coordinates":[4.3997468948,50.8722763062],"type":"Point"}
}