{
  "type": "Feature",
  "properties": {
    "iso:country":"BE",
    "sg:address":"Chauss\u00c9e D'audenarde 428",
    "sg:city":"Pecq",
    "sg:orig_category":"Eleveurs de bovins",
    "sg:phone":"+32 69 55 84 28",
    "sg:postcode":"7742",
    "sg:province":"Hainaut",
    "wof:name":"Lucien Messian",
    "wof:placetype":"venue"
},
  "geometry": {"coordinates":[3.3762869835,50.7124824524],"type":"Point"}
}