{
  "type": "Feature",
  "properties": {
    "addr:full":"Sint-laureisstraat 63 Antwerpen Antwerpen 2018",
    "addr:housenumber":"63",
    "addr:postcode":"2018",
    "addr:street":"Sint-Laureisstraat",
    "iso:country":"BE",
    "sg:address":"Sint-laureisstraat 63",
    "sg:city":"Antwerpen",
    "sg:orig_category":"Boekhandels",
    "sg:phone":"+32 3 238 95 10",
    "sg:postcode":"2018",
    "sg:province":"Antwerpen",
    "wof:name":"De Stad Gods",
    "wof:placetype":"venue"
},
  "geometry": {"coordinates":[4.3972811699,51.2031593323],"type":"Point"}
}