{
  "type": "Feature",
  "properties": {
    "addr:full":"Rueelstraat 9 Maaseik Limburg 3680",
    "addr:housenumber":"9",
    "addr:postcode":"3680",
    "addr:street":"Rueelstraat",
    "iso:country":"BE",
    "sg:address":"Rueelstraat 9",
    "sg:city":"Maaseik",
    "sg:classifiers":[
        {
            "category":"Shopping",
            "subcategory":"Bicycles & Sporting Goods",
            "type":"Retail Goods"
        }
    ],
    "sg:phone":"+32 89 61 51 24",
    "sg:postcode":"3680",
    "sg:province":"Limburg",
    "sg:tags":[
        "sport",
        "-"
    ],
    "wof:name":"Tri Sport",
    "wof:placetype":"venue"
},
  "geometry": {"coordinates":[5.7877550125,51.0952415466],"type":"Point"}
}