{
  "type": "Feature",
  "properties": {
    "iso:country":"BE",
    "sg:address":"Capucienenstraat 88",
    "sg:city":"Ieper",
    "sg:orig_category":"Artiesten and kunstenaars",
    "sg:phone":"+32 57 20 25 43",
    "sg:postcode":"8900",
    "sg:province":"West-Vlaanderen",
    "wof:name":"Platteeuw",
    "wof:placetype":"venue"
},
  "geometry": {"coordinates":[2.8695850372,50.8458023071],"type":"Point"}
}