{
  "type": "Feature",
  "properties": {
    "iso:country":"BE",
    "sg:address":"Chauss\u00c9e De Wavre 1432",
    "sg:city":"Oudergem/auderghem",
    "sg:orig_category":"Epiceries",
    "sg:phone":"+32 2 672 91 69",
    "sg:postcode":"1160",
    "sg:province":"Bruxelles-Capitale",
    "wof:name":"Maison Pomme D'api",
    "wof:placetype":"venue"
},
  "geometry": {"coordinates":[4.4164180756,50.8187866211],"type":"Point"}
}