{
  "type": "Feature",
  "properties": {
    "addr:full":"Bergstraat 24 Heuvelland West-Vlaanderen 8956",
    "addr:housenumber":"24",
    "addr:postcode":"8956",
    "addr:street":"Bergstraat",
    "iso:country":"BE",
    "sg:address":"Bergstraat 24",
    "sg:city":"Heuvelland",
    "sg:orig_category":"Overheidsdiensten",
    "sg:phone":"+32 57 45 04 80",
    "sg:postcode":"8956",
    "sg:province":"West-Vlaanderen",
    "wof:name":"O.c.m.w.",
    "wof:placetype":"venue"
},
  "geometry": {"coordinates":[2.8236749172,50.7812461853],"type":"Point"}
}