{
  "type": "Feature",
  "properties": {
    "addr:full":"Rue Du Roua 17 Esneux Li\u00e8ge 4130",
    "addr:housenumber":"17",
    "addr:postcode":"4130",
    "addr:street":"Rue Du Roua",
    "iso:country":"BE",
    "sg:address":"Rue Du Roua 17",
    "sg:city":"Esneux",
    "sg:classifiers":[
        {
            "category":"Communications",
            "type":"Services"
        }
    ],
    "sg:phone":"+32 4 380 32 73",
    "sg:postcode":"4130",
    "sg:province":"Li\u00e8ge",
    "sg:tags":[
        "translator"
    ],
    "wof:name":"Moliteur P",
    "wof:placetype":"venue"
},
  "geometry": {"coordinates":[5.5914697647,50.5287742615],"type":"Point"}
}