{
  "type": "Feature",
  "properties": {
    "addr:full":"Nieuwe Steenweg 88 Zuienkerke West-Vlaanderen 8377",
    "addr:housenumber":"88",
    "addr:postcode":"8377",
    "addr:street":"Nieuwe Steenweg",
    "iso:country":"BE",
    "sg:address":"Nieuwe Steenweg 88",
    "sg:city":"Zuienkerke",
    "sg:classifiers":[
        {
            "category":"Personal",
            "subcategory":"Beauty Salon",
            "type":"Services"
        }
    ],
    "sg:phone":"+32 50 41 84 14",
    "sg:postcode":"8377",
    "sg:province":"West-Vlaanderen",
    "sg:tags":[
        "lady",
        "-",
        "hairdressing"
    ],
    "wof:name":"Grego",
    "wof:placetype":"venue"
},
  "geometry": {"coordinates":[3.1538770199,51.2648658752],"type":"Point"}
}