{
  "type": "Feature",
  "properties": {
    "addr:full":"Place Cardinal Mercier 34 Bruxelles (jette) Bruxelles-Capitale 1090",
    "addr:housenumber":"34",
    "addr:postcode":"1090",
    "addr:street":"Place Cardinal Mercier",
    "iso:country":"BE",
    "sg:address":"Place Cardinal Mercier 34",
    "sg:city":"Bruxelles (jette)",
    "sg:classifiers":[
        {
            "category":"Bars & Pubs",
            "type":"Food & Drink"
        }
    ],
    "sg:phone":"+32 2 428 75 21",
    "sg:postcode":"1090",
    "sg:province":"Bruxelles-Capitale",
    "wof:name":"Hoek (op De)",
    "wof:placetype":"venue"
},
  "geometry": {"coordinates":[4.328496933,50.8805084229],"type":"Point"}
}