{
  "type": "Feature",
  "properties": {
    "iso:country":"BE",
    "sg:address":"Broekstraat 59",
    "sg:city":"Hamme",
    "sg:orig_category":"Forge, Moulage and Profilage des M\u00e9taux. Locations de machines and \u00e9quipement pour la construction. ",
    "sg:phone":"+32 52 49 70 35",
    "sg:postcode":"9220",
    "sg:province":"Oost-Vlaanderen",
    "wof:name":"The Blacksmith",
    "wof:placetype":"venue"
},
  "geometry": {"coordinates":[4.1638607979,51.0896339417],"type":"Point"}
}