{
  "type": "Feature",
  "properties": {
    "addr:full":"Bocle 40a Mouscron Hainaut 7700",
    "addr:housenumber":"40a",
    "addr:postcode":"7700",
    "addr:street":"Bocle",
    "iso:country":"BE",
    "sg:address":"Bocle 40a",
    "sg:city":"Mouscron",
    "sg:classifiers":[
        {
            "category":"Banks & Credit Unions",
            "subcategory":"Bank",
            "type":"Services"
        }
    ],
    "sg:phone":"+32 56 84 27 52",
    "sg:postcode":"7700",
    "sg:province":"Hainaut",
    "wof:name":"Banque Bruxelles Lambert Sa",
    "wof:placetype":"venue"
},
  "geometry": {"coordinates":[3.2145800591,50.7437934875],"type":"Point"}
}