{
  "type": "Feature",
  "properties": {
    "iso:country":"BE",
    "sg:address":"Kapellestraat 6",
    "sg:city":"Oostende",
    "sg:classifiers":[
        {
            "category":"Shopping",
            "subcategory":"Clothing, Apparel, & Fashions",
            "type":"Retail Goods"
        }
    ],
    "sg:phone":"+32 59 80 77 35",
    "sg:postcode":"8400",
    "sg:province":"West-Vlaanderen",
    "sg:tags":[
        "clothing",
        "-",
        "gentleman"
    ],
    "wof:name":"Edouard Tailor",
    "wof:placetype":"venue"
},
  "geometry": {"coordinates":[2.9178481102,51.2315292358],"type":"Point"}
}