{
  "type": "Feature",
  "properties": {
    "addr:full":"Rue Du March\u00c9 Au Charbon 60 Brussel/bruxelles Bruxelles-Capitale 1000",
    "addr:housenumber":"60",
    "addr:postcode":"1000",
    "addr:street":"Rue Du Marche\u0301 Au Charbon;/",
    "iso:country":"BE",
    "sg:address":"Rue Du March\u00c9 Au Charbon 60",
    "sg:city":"Brussel/bruxelles",
    "sg:orig_category":"Bars. Dancings and bo\u00eetes de nuit",
    "sg:phone":"+32 2 514 51 49",
    "sg:postcode":"1000",
    "sg:province":"Bruxelles-Capitale",
    "wof:name":"El Pablo Disco Bar",
    "wof:placetype":"venue"
},
  "geometry": {"coordinates":[4.348900795,50.8462562561],"type":"Point"}
}