{
  "type": "Feature",
  "properties": {
    "iso:country":"BE",
    "sg:address":"Guido Gezellelaan 19",
    "sg:city":"Kampenhout",
    "sg:classifiers":[
        {
            "category":"Health Services",
            "subcategory":"Health Practitioner",
            "type":"Services"
        }
    ],
    "sg:phone":"+32 16 65 68 18",
    "sg:postcode":"1910",
    "sg:province":"Vlaams-Brabant",
    "sg:tags":[
        "physiotherapist"
    ],
    "wof:name":"Goovaerts B",
    "wof:placetype":"venue"
},
  "geometry": {"coordinates":[4.5610151291,50.9441757202],"type":"Point"}
}