{
  "type": "Feature",
  "properties": {
    "addr:full":"Avenue De L'arm\u00c9e 108 Etterbeek Bruxelles-Capitale 1040",
    "addr:housenumber":"108",
    "addr:postcode":"1040",
    "addr:street":"Avenue De L'Arme \u0301E",
    "iso:country":"BE",
    "sg:address":"Avenue De L'arm\u00c9e 108",
    "sg:city":"Etterbeek",
    "sg:orig_category":"Eclairage et \u00e9quipements du foyer. Rev\u00eatements pour sols and murs. Peinture",
    "sg:phone":"+32 2 734 55 80",
    "sg:postcode":"1040",
    "sg:province":"Bruxelles-Capitale",
    "wof:name":"Lingand",
    "wof:placetype":"venue"
},
  "geometry": {"coordinates":[4.4030718803,50.8342094421],"type":"Point"}
}