{
  "type": "Feature",
  "properties": {
    "iso:country":"BE",
    "sg:address":"Vieux Chemin De Binche 502",
    "sg:city":"Mons",
    "sg:classifiers":[
        {
            "category":"Arena",
            "subcategory":"Sports Club",
            "type":"Entertainment"
        }
    ],
    "sg:phone":"+32 65 33 83 07",
    "sg:postcode":"7000",
    "sg:province":"Hainaut",
    "sg:tags":[
        "terrain",
        "hors",
        "de",
        "installation",
        "sportifs"
    ],
    "wof:name":"Piscine Sluys",
    "wof:placetype":"venue"
},
  "geometry": {"coordinates":[4.001760006,50.4606246948],"type":"Point"}
}