{
  "type": "Feature",
  "properties": {
    "iso:country":"BE",
    "sg:address":"Budingenweg 2",
    "sg:city":"Zoutleeuw",
    "sg:orig_category":"Enseignement maternel and primaire",
    "sg:phone":"+32 11 78 13 29",
    "sg:postcode":"3440",
    "sg:province":"Vlaams-Brabant",
    "wof:name":"B.s.g.o. Leeuwerveld",
    "wof:placetype":"venue"
},
  "geometry": {"coordinates":[5.1055002213,50.8369293213],"type":"Point"}
}