{
  "type": "Feature",
  "properties": {
    "iso:country":"BE",
    "sg:address":"Schoolstraat 28",
    "sg:city":"Herent",
    "sg:orig_category":"Verplichte sociale verzekeringen",
    "sg:phone":"+32 16 20 70 29",
    "sg:postcode":"3020",
    "sg:province":"Vlaams-Brabant",
    "wof:name":"Kristelijk Ziekenfonds",
    "wof:placetype":"venue"
},
  "geometry": {"coordinates":[4.676129818,50.9070892334],"type":"Point"}
}