{
  "type": "Feature",
  "properties": {
    "iso:country":"BE",
    "sg:address":"Avenue Des Croix De Guerre 197 Box 7",
    "sg:city":"Bruxelles",
    "sg:classifiers":[
        {
            "category":"Professional",
            "subcategory":"Lawyer & Legal Services",
            "type":"Services"
        }
    ],
    "sg:phone":"+32 2 216 55 30",
    "sg:postcode":"1120",
    "sg:province":"Bruxelles-Capitale",
    "wof:name":"Bellen Paul",
    "wof:placetype":"venue"
},
  "geometry": {"coordinates":[4.3854432106,50.8917655945],"type":"Point"}
}