{
  "type": "Feature",
  "properties": {
    "addr:full":"Rue De Genleau 5 Lasne (lasne-chapelle-saint-lambert) Brabant Wallon 1380",
    "addr:housenumber":"5",
    "addr:postcode":"1380",
    "addr:street":"Rue De Genleau;Wallon",
    "iso:country":"BE",
    "sg:address":"Rue De Genleau 5",
    "sg:city":"Lasne (lasne-chapelle-saint-lambert)",
    "sg:classifiers":[
        {
            "category":"Building & Trades",
            "subcategory":"Landscaping Services",
            "type":"Services"
        }
    ],
    "sg:phone":"+32 2 633 56 96",
    "sg:postcode":"1380",
    "sg:province":"Brabant Wallon",
    "sg:tags":[
        "gardening",
        "garden",
        "maintenance"
    ],
    "wof:name":"4 Saisons (les)",
    "wof:placetype":"venue"
},
  "geometry": {"coordinates":[4.4786300659,50.6847991943],"type":"Point"}
}