{
  "type": "Feature",
  "properties": {
    "iso:country":"BE",
    "sg:address":"Rue De Lille 4",
    "sg:city":"Comines-warneton (warneton)",
    "sg:classifiers":[
        {
            "category":"Food & Beverages",
            "subcategory":"Fruits & Vegetables",
            "type":"Retail Goods"
        }
    ],
    "sg:phone":"+32 56 55 59 30",
    "sg:postcode":"7784",
    "sg:province":"Hainaut",
    "sg:tags":[
        "-"
    ],
    "wof:name":"D'hantshotter W",
    "wof:placetype":"venue"
},
  "geometry": {"coordinates":[2.9483098984,50.752620697],"type":"Point"}
}