{
  "type": "Feature",
  "properties": {
    "addr:full":"Kluize 29 Lede Oost-Vlaanderen 9340",
    "addr:housenumber":"29",
    "addr:postcode":"9340",
    "addr:street":"Kluize",
    "iso:country":"BE",
    "sg:address":"Kluize 29",
    "sg:city":"Lede",
    "sg:orig_category":"Groenten and fruit Gh",
    "sg:phone":"+32 9 369 25 89",
    "sg:postcode":"9340",
    "sg:province":"Oost-Vlaanderen",
    "wof:name":"Veiling Land Van Aalst",
    "wof:placetype":"venue"
},
  "geometry": {"coordinates":[3.8912880421,50.9505348206],"type":"Point"}
}