{
  "type": "Feature",
  "properties": {
    "iso:country":"BE",
    "sg:address":"Rue F. Deneumoustier 123",
    "sg:city":"Namur",
    "sg:orig_category":"Boekhandels",
    "sg:phone":"+32 81 74 04 80",
    "sg:postcode":"5001",
    "sg:province":"Namur",
    "wof:name":"Librairie Du Ch\u00c2teau Eau",
    "wof:placetype":"venue"
},
  "geometry": {"coordinates":[4.8257050514,50.4722557068],"type":"Point"}
}