{
  "type": "Feature",
  "properties": {
    "addr:full":"Brabantse Prinsenlaan 57 Watermaal-bosvoorde/watermael-boitsfort Bruxelles-Capitale 1170",
    "addr:housenumber":"57",
    "addr:postcode":"1170",
    "addr:street":"Brabantse Prinsenlaan",
    "iso:country":"BE",
    "sg:address":"Brabantse Prinsenlaan 57",
    "sg:city":"Watermaal-bosvoorde/watermael-boitsfort",
    "sg:orig_category":"Bloemen and planten Tuinbenodigdheden",
    "sg:phone":"+32 2 672 71 15",
    "sg:postcode":"1170",
    "sg:province":"Bruxelles-Capitale",
    "wof:name":"Garden Line",
    "wof:placetype":"venue"
},
  "geometry": {"coordinates":[4.4154567719,50.8100738525],"type":"Point"}
}