{
  "type": "Feature",
  "properties": {
    "iso:country":"BE",
    "sg:address":"Stationsstraat 27",
    "sg:city":"Lommel",
    "sg:classifiers":[
        {
            "category":"Shopping",
            "subcategory":"Gifts & Souvenirs",
            "type":"Retail Goods"
        }
    ],
    "sg:phone":"+32 11 55 21 96",
    "sg:postcode":"3920",
    "sg:province":"Limburg",
    "sg:tags":[
        "-"
    ],
    "wof:name":"Belarte",
    "wof:placetype":"venue"
},
  "geometry": {"coordinates":[5.3145079613,51.2265281677],"type":"Point"}
}