{
  "type": "Feature",
  "properties": {
    "iso:country":"BE",
    "sg:address":"Rue De Berneau 30",
    "sg:city":"Vis\u00e9",
    "sg:classifiers":[
        {
            "category":"Arena",
            "subcategory":"Sports Club",
            "type":"Entertainment"
        }
    ],
    "sg:phone":"+32 4 379 44 26",
    "sg:postcode":"4600",
    "sg:province":"Li\u00e8ge",
    "wof:name":"Hall Omnisport De Vis\u00e9 Asbl",
    "wof:placetype":"venue"
},
  "geometry": {"coordinates":[5.7071399689,50.7372741699],"type":"Point"}
}