{
  "type": "Feature",
  "properties": {
    "iso:country":"BE",
    "sg:address":"Square De Mee\u00fbs 1",
    "sg:city":"Brussels",
    "sg:classifiers":[
        {
            "category":"Banks & Credit Unions",
            "subcategory":"Bank",
            "type":"Services"
        }
    ],
    "sg:postcode":"1000",
    "sg:province":"Bruxelles-Capitale",
    "wof:name":"Distri-invest",
    "wof:placetype":"venue"
},
  "geometry": {"coordinates":[4.3599381447,50.8473167419],"type":"Point"}
}