{
  "type": "Feature",
  "properties": {
    "iso:country":"BE",
    "sg:address":"Neep 60",
    "sg:city":"Ninove",
    "sg:orig_category":"Elektrische installaties voor woningen Huishoudapparaten, televisies and radio's Onderdelen and acce",
    "sg:phone":"+32 54 32 22 52",
    "sg:postcode":"9402",
    "sg:province":"Oost-Vlaanderen",
    "wof:name":"Electro De Bels",
    "wof:placetype":"venue"
},
  "geometry": {"coordinates":[4.0395750999,50.8249015808],"type":"Point"}
}