{
  "type": "Feature",
  "properties": {
    "addr:full":"Boulevard Maurice Lemonnier 79 Bruxelles Bruxelles-Capitale 1000",
    "addr:housenumber":"79",
    "addr:postcode":"1000",
    "addr:street":"Boulevard Maurice Lemonnier",
    "iso:country":"BE",
    "sg:address":"Boulevard Maurice Lemonnier 79",
    "sg:city":"Bruxelles",
    "sg:classifiers":[
        {
            "category":"Bars & Pubs",
            "type":"Food & Drink"
        }
    ],
    "sg:phone":"+32 2 512 35 69",
    "sg:postcode":"1000",
    "sg:province":"Bruxelles-Capitale",
    "sg:tags":[
        "tavern"
    ],
    "wof:name":"Limousine (la)",
    "wof:placetype":"venue"
},
  "geometry": {"coordinates":[4.344244957,50.8433609009],"type":"Point"}
}