{
  "type": "Feature",
  "properties": {
    "addr:full":"Menenstraat 459-463 Wevelgem West-Vlaanderen 8560",
    "addr:housenumber":"459-463",
    "addr:postcode":"8560",
    "addr:street":"Menenstraat",
    "iso:country":"BE",
    "sg:address":"Menenstraat 459-463",
    "sg:city":"Wevelgem",
    "sg:orig_category":"Equipements divers pour l\u00b4industrie Gr. Combustibles",
    "sg:phone":"+32 56 42 34 10",
    "sg:postcode":"8560",
    "sg:province":"West-Vlaanderen",
    "wof:name":"Soligas",
    "wof:placetype":"venue"
},
  "geometry": {"coordinates":[3.1533110142,50.8020706177],"type":"Point"}
}