{
  "type": "Feature",
  "properties": {
    "iso:country":"BE",
    "sg:address":"Grote Heerweg 74",
    "sg:city":"Waregem (beveren-leie)",
    "sg:classifiers":[
        {
            "category":"Manufacturing",
            "subcategory":"Textiles",
            "type":"Manufacturing & Wholesale Goods"
        }
    ],
    "sg:phone":"+32 56 73 54 54",
    "sg:postcode":"8791",
    "sg:province":"West-Vlaanderen",
    "sg:tags":[
        "finishing"
    ],
    "wof:name":"Vanmarcke",
    "wof:placetype":"venue"
},
  "geometry": {"coordinates":[3.3312809467,50.8746109009],"type":"Point"}
}