{
  "type": "Feature",
  "properties": {
    "iso:country":"BE",
    "sg:address":"Brugse Steenweg 146",
    "sg:city":"Blankenberge",
    "sg:orig_category":"Eleveurs de bovins",
    "sg:phone":"+32 50 41 76 02",
    "sg:postcode":"8370",
    "sg:province":"West-Vlaanderen",
    "wof:name":"Raphael Maenhout",
    "wof:placetype":"venue"
},
  "geometry": {"coordinates":[3.159003973,51.2901306152],"type":"Point"}
}