{
  "type": "Feature",
  "properties": {
    "addr:full":"Sluizenstraat 33 Bredene West-Vlaanderen 8450",
    "addr:housenumber":"33",
    "addr:postcode":"8450",
    "addr:street":"Sluizenstraat",
    "iso:country":"BE",
    "sg:address":"Sluizenstraat 33",
    "sg:city":"Bredene",
    "sg:orig_category":"Belastingconsulenten Diverse juridische dienstverlening",
    "sg:phone":"+32 59 32 22 54",
    "sg:postcode":"8450",
    "sg:province":"West-Vlaanderen",
    "wof:name":"Breham",
    "wof:placetype":"venue"
},
  "geometry": {"coordinates":[2.9728019238,51.2323913574],"type":"Point"}
}