{
  "type": "Feature",
  "properties": {
    "iso:country":"BE",
    "sg:address":"Wiemesmeerstraat 105",
    "sg:city":"Genk",
    "sg:classifiers":[
        {
            "category":"Organizations",
            "subcategory":"Professional Association",
            "type":"Services"
        }
    ],
    "sg:phone":"+32 89 35 58 28",
    "sg:postcode":"3600",
    "sg:province":"Limburg",
    "sg:tags":[
        "organisation",
        "seminar"
    ],
    "wof:name":"La R\u00e9sidence (golfhotel)",
    "wof:placetype":"venue"
},
  "geometry": {"coordinates":[5.5533638,50.9695243835],"type":"Point"}
}