{
  "type": "Feature",
  "properties": {
    "addr:full":"Baron Ruzettelaan 140 Brugge (assebroek) West-Vlaanderen 8310",
    "addr:housenumber":"140",
    "addr:postcode":"8310",
    "addr:street":"Baron Ruzettelaan",
    "iso:country":"BE",
    "sg:address":"Baron Ruzettelaan 140",
    "sg:city":"Brugge (assebroek)",
    "sg:classifiers":[
        {
            "category":"Bars & Pubs",
            "type":"Food & Drink"
        }
    ],
    "sg:phone":"+32 50 35 63 33",
    "sg:postcode":"8310",
    "sg:province":"West-Vlaanderen",
    "wof:name":"Toekomst (de)",
    "wof:placetype":"venue"
},
  "geometry": {"coordinates":[3.2319509983,51.192527771],"type":"Point"}
}