{
  "type": "Feature",
  "properties": {
    "addr:full":"Kouter 130 Deinze Oost-Vlaanderen 9800",
    "addr:housenumber":"130",
    "addr:postcode":"9800",
    "addr:street":"Kouter",
    "iso:country":"BE",
    "sg:address":"Kouter 130",
    "sg:city":"Deinze",
    "sg:classifiers":[
        {
            "category":"Arena",
            "subcategory":"Sports Club",
            "type":"Entertainment"
        }
    ],
    "sg:phone":"+32 9 386 34 13",
    "sg:postcode":"9800",
    "sg:province":"Oost-Vlaanderen",
    "sg:tags":[
        "de"
    ],
    "wof:name":"Zwemclub S.o.s.",
    "wof:placetype":"venue"
},
  "geometry": {"coordinates":[3.4990029335,50.9893798828],"type":"Point"}
}