{
  "type": "Feature",
  "properties": {
    "iso:country":"BE",
    "sg:address":"Rue Albert Ier 145bb",
    "sg:city":"Erquelinnes",
    "sg:orig_category":"Drukkerijen and copyshops",
    "sg:phone":"+32 71 55 53 25",
    "sg:postcode":"6560",
    "sg:province":"Hainaut",
    "wof:name":"Imprimerie Deraedt",
    "wof:placetype":"venue"
},
  "geometry": {"coordinates":[4.1174550056,50.3074493408],"type":"Point"}
}