{
  "type": "Feature",
  "properties": {
    "addr:full":"Waverse Steenweg 1301 Oudergem/auderghem Bruxelles-Capitale 1160",
    "addr:housenumber":"1301",
    "addr:postcode":"1160",
    "addr:street":"Waverse Steenweg;/",
    "iso:country":"BE",
    "sg:address":"Waverse Steenweg 1301",
    "sg:city":"Oudergem/auderghem",
    "sg:classifiers":[
        {
            "category":"Cafe",
            "type":"Food & Drink"
        }
    ],
    "sg:phone":"+32 2 675 02 76",
    "sg:postcode":"1160",
    "sg:province":"Bruxelles-Capitale",
    "sg:tags":[
        "caf\u00e9s"
    ],
    "wof:name":"Caf\u00c9 Petit Caveau",
    "wof:placetype":"venue"
},
  "geometry": {"coordinates":[4.4084291458,50.8207893372],"type":"Point"}
}