{
  "type": "Feature",
  "properties": {
    "addr:full":"Rue De Liedekerke 106 Bruxelles (saint-josse-ten-noode) Bruxelles-Capitale 1210",
    "addr:housenumber":"106",
    "addr:postcode":"1210",
    "addr:street":"Rue De Liedekerke",
    "iso:country":"BE",
    "sg:address":"Rue De Liedekerke 106",
    "sg:city":"Bruxelles (saint-josse-ten-noode)",
    "sg:classifiers":[
        {
            "category":"Farming",
            "subcategory":"Fish & Marine Products",
            "type":"Manufacturing & Wholesale Goods"
        }
    ],
    "sg:phone":"+32 2 218 47 96",
    "sg:postcode":"1210",
    "sg:province":"Bruxelles-Capitale",
    "sg:tags":[
        "curers",
        "smoker"
    ],
    "wof:name":"Saumonerie De Bruxelles",
    "wof:placetype":"venue"
},
  "geometry": {"coordinates":[4.3748188019,50.8520965576],"type":"Point"}
}