{
  "type": "Feature",
  "properties": {
    "addr:full":"Maliestraat 77 Elsene/ixelles Bruxelles-Capitale 1050",
    "addr:housenumber":"77",
    "addr:postcode":"1050",
    "addr:street":"Maliestraat",
    "iso:country":"BE",
    "sg:address":"Maliestraat 77",
    "sg:city":"Elsene/ixelles",
    "sg:orig_category":"Immobili\u00ebnkantoren",
    "sg:phone":"+32 2 537 03 70",
    "sg:postcode":"1050",
    "sg:province":"Bruxelles-Capitale",
    "wof:name":"Immobili\u00c8re Petitjean",
    "wof:placetype":"venue"
},
  "geometry": {"coordinates":[4.3591108322,50.8219070435],"type":"Point"}
}