{
  "type": "Feature",
  "properties": {
    "iso:country":"BE",
    "sg:address":"Rumbeeksesteenweg 439",
    "sg:city":"Roeselare",
    "sg:orig_category":"Pain, p\u00e2tisseries and confiseries",
    "sg:phone":"+32 51 22 93 02",
    "sg:postcode":"8800",
    "sg:province":"West-Vlaanderen",
    "wof:name":"Franky Lagein",
    "wof:placetype":"venue"
},
  "geometry": {"coordinates":[3.1415700912,50.937461853],"type":"Point"}
}