{
  "type": "Feature",
  "properties": {
    "iso:country":"BE",
    "sg:address":"Durmakker 12",
    "sg:city":"Evergem",
    "sg:orig_category":"Diepvriesproducten Gh",
    "sg:phone":"+32 9 253 46 90",
    "sg:postcode":"9940",
    "sg:province":"Oost-Vlaanderen",
    "wof:name":"Northfreeze",
    "wof:placetype":"venue"
},
  "geometry": {"coordinates":[3.6880180836,51.098361969],"type":"Point"}
}