{
  "type": "Feature",
  "properties": {
    "iso:country":"BE",
    "sg:address":"Corbiestraat 17",
    "sg:city":"Mol",
    "sg:classifiers":[
        {
            "category":"Cafe",
            "type":"Food & Drink"
        }
    ],
    "sg:phone":"+32 14 31 62 33",
    "sg:postcode":"2400",
    "sg:province":"Antwerpen",
    "sg:tags":[
        "caf\u00e9s"
    ],
    "wof:name":"Tap",
    "wof:placetype":"venue"
},
  "geometry": {"coordinates":[5.1167612076,51.1883964539],"type":"Point"}
}