{
  "type": "Feature",
  "properties": {
    "addr:full":"Astridlaan 33-39 Ninove Oost-Vlaanderen 9400",
    "addr:postcode":"33-39;9400",
    "addr:street":"Astridlaan",
    "iso:country":"BE",
    "sg:address":"Astridlaan 33-39",
    "sg:city":"Ninove",
    "sg:classifiers":[
        {
            "category":"Education",
            "subcategory":"School",
            "type":"Public Place"
        }
    ],
    "sg:phone":"+32 54 33 28 96",
    "sg:postcode":"9400",
    "sg:province":"Oost-Vlaanderen",
    "sg:tags":[
        "secondary"
    ],
    "wof:name":"Middenschool Van Het Gemeenschapsonderwijs",
    "wof:placetype":"venue"
},
  "geometry": {"coordinates":[4.0283889771,50.839138031],"type":"Point"}
}