{
  "type": "Feature",
  "properties": {
    "iso:country":"BE",
    "sg:address":"Robaardstraat 18",
    "sg:city":"Wervik",
    "sg:orig_category":"Eleveurs d'animaux domestiques",
    "sg:phone":"+32 56 31 10 20",
    "sg:postcode":"8940",
    "sg:province":"West-Vlaanderen",
    "wof:name":"Hof Ter Coelenberghe",
    "wof:placetype":"venue"
},
  "geometry": {"coordinates":[3.0468139648,50.8114128113],"type":"Point"}
}