{
  "type": "Feature",
  "properties": {
    "addr:full":"Rue Du Thier 6 Verviers Li\u00e8ge 4801",
    "addr:housenumber":"6",
    "addr:postcode":"4801",
    "addr:street":"Rue Du Thier",
    "iso:country":"BE",
    "sg:address":"Rue Du Thier 6",
    "sg:city":"Verviers",
    "sg:orig_category":"Baby- and kinderkleding",
    "sg:phone":"+32 87 22 38 67",
    "sg:postcode":"4801",
    "sg:province":"Li\u00e8ge",
    "wof:name":"Boutique Dominique",
    "wof:placetype":"venue"
},
  "geometry": {"coordinates":[5.8884348869,50.584487915],"type":"Point"}
}