{
  "type": "Feature",
  "properties": {
    "addr:full":"Rue Des Chantiers 25 Charleroi Hainaut 6030",
    "addr:housenumber":"25",
    "addr:postcode":"6030",
    "addr:street":"Rue Des Chantiers;Hainaut",
    "iso:country":"BE",
    "sg:address":"Rue Des Chantiers 25",
    "sg:city":"Charleroi",
    "sg:orig_category":"Installation de menuiserie m\u00e9tallique. Quincailleries. Mat\u00e9riaux de construction Bois Gr",
    "sg:phone":"+32 71 31 38 46",
    "sg:postcode":"6030",
    "sg:province":"Hainaut",
    "wof:name":"Cougemat",
    "wof:placetype":"venue"
},
  "geometry": {"coordinates":[4.3916730881,50.4077339172],"type":"Point"}
}