{
  "type": "Feature",
  "properties": {
    "addr:full":"Beerzelplein 14 Beerzel Antwerpen 2580",
    "addr:housenumber":"14",
    "addr:postcode":"2580",
    "addr:street":"Beerzelplein",
    "iso:country":"BE",
    "sg:address":"Beerzelplein 14",
    "sg:city":"Beerzel",
    "sg:orig_category":"Pain, p\u00e2tisseries and confiseries",
    "sg:phone":"+32 15 75 54 85",
    "sg:postcode":"2580",
    "sg:province":"Antwerpen",
    "wof:name":"Bakkerij Van Eynde",
    "wof:placetype":"venue"
},
  "geometry": {"coordinates":[4.6721138954,51.0573959351],"type":"Point"}
}