{
  "type": "Feature",
  "properties": {
    "iso:country":"BE",
    "sg:address":"Vinkenpad 62",
    "sg:city":"Rijkevorsel",
    "sg:orig_category":"Eclairage et \u00e9quipements du foyer",
    "sg:phone":"+32 3 314 22 45",
    "sg:postcode":"2310",
    "sg:province":"Antwerpen",
    "wof:name":"Minka",
    "wof:placetype":"venue"
},
  "geometry": {"coordinates":[4.7639040947,51.3451194763],"type":"Point"}
}