{
  "type": "Feature",
  "properties": {
    "addr:full":"Chauss\u00e9e De Waterloo 485 Bruxelles (ixelles) Bruxelles-Capitale 1050",
    "addr:housenumber":"485",
    "addr:postcode":"1050",
    "addr:street":"Chausse\u0301E De Waterloo",
    "iso:country":"BE",
    "sg:address":"Chauss\u00e9e De Waterloo 485",
    "sg:city":"Bruxelles (ixelles)",
    "sg:classifiers":[
        {
            "category":"Parking",
            "subcategory":"Bicycle",
            "type":"Transportation"
        }
    ],
    "sg:phone":"+32 2 347 37 35",
    "sg:postcode":"1050",
    "sg:province":"Bruxelles-Capitale",
    "sg:tags":[
        "chiropodist"
    ],
    "wof:name":"Carpe Diem",
    "wof:placetype":"venue"
},
  "geometry": {"coordinates":[4.3583288193,50.8204917908],"type":"Point"}
}