{
  "type": "Feature",
  "properties": {
    "iso:country":"BE",
    "sg:address":"Brugsesteenweg 65",
    "sg:city":"Kuurne",
    "sg:classifiers":[
        {
            "category":"Health Services",
            "subcategory":"Doctor",
            "type":"Services"
        }
    ],
    "sg:phone":"+32 56 35 79 14",
    "sg:postcode":"8520",
    "sg:province":"West-Vlaanderen",
    "sg:tags":[
        "orthopedist"
    ],
    "wof:name":"Verhaeghe J",
    "wof:placetype":"venue"
},
  "geometry": {"coordinates":[3.2693719864,50.8484420776],"type":"Point"}
}