{
  "type": "Feature",
  "properties": {
    "addr:full":"Stationsstraat 5 Neerpelt Limburg 3910",
    "addr:housenumber":"5",
    "addr:postcode":"3910",
    "addr:street":"Stationsstraat",
    "iso:country":"BE",
    "sg:address":"Stationsstraat 5",
    "sg:city":"Neerpelt",
    "sg:orig_category":"Randstad. Agences d\u00b4interim and personnel temporaire",
    "sg:phone":"+32 11 80 20 30",
    "sg:postcode":"3910",
    "sg:province":"Limburg",
    "wof:name":"Randstad",
    "wof:placetype":"venue"
},
  "geometry": {"coordinates":[5.4348320961,51.2281036377],"type":"Point"}
}