{
  "type": "Feature",
  "properties": {
    "addr:full":"Ambachtsstraat 48 Malle (westmalle) Antwerpen 2390",
    "addr:housenumber":"48",
    "addr:postcode":"2390",
    "addr:street":"Ambachtsstraat",
    "iso:country":"BE",
    "sg:address":"Ambachtsstraat 48",
    "sg:city":"Malle (westmalle)",
    "sg:classifiers":[
        {
            "category":"Sports & Exercise",
            "subcategory":"Gym",
            "type":"Entertainment"
        }
    ],
    "sg:postcode":"2390",
    "sg:province":"Antwerpen",
    "sg:tags":[
        "access",
        "gymnastics",
        "-",
        "apparatus",
        "fitness"
    ],
    "wof:name":"Alles",
    "wof:placetype":"venue"
},
  "geometry": {"coordinates":[4.7081971169,51.2912902832],"type":"Point"}
}