{
  "type": "Feature",
  "properties": {
    "addr:full":"Gemeenteplein 15 Dilbeek Vlaams-Brabant 1700",
    "addr:housenumber":"15",
    "addr:postcode":"1700",
    "addr:street":"Gemeenteplein",
    "iso:country":"BE",
    "sg:address":"Gemeenteplein 15",
    "sg:city":"Dilbeek",
    "sg:orig_category":"Artsen and specialisten",
    "sg:phone":"+32 2 466 28 82",
    "sg:postcode":"1700",
    "sg:province":"Vlaams-Brabant",
    "wof:name":"Luc De Muyter",
    "wof:placetype":"venue"
},
  "geometry": {"coordinates":[4.2652869225,50.8481826782],"type":"Point"}
}