{
  "type": "Feature",
  "properties": {
    "addr:full":"Vleeshouwersstraat 2 Koksijde West-Vlaanderen 8670",
    "addr:housenumber":"2",
    "addr:postcode":"8670",
    "addr:street":"Vleeshouwersstraat",
    "iso:country":"BE",
    "sg:address":"Vleeshouwersstraat 2",
    "sg:city":"Koksijde",
    "sg:orig_category":"Verlichting and huishoudartikelen",
    "sg:phone":"+32 58 31 35 69",
    "sg:postcode":"8670",
    "sg:province":"West-Vlaanderen",
    "wof:name":"Huis Kadorien",
    "wof:placetype":"venue"
},
  "geometry": {"coordinates":[2.6492800713,51.1061401367],"type":"Point"}
}