{
  "type": "Feature",
  "properties": {
    "iso:country":"BE",
    "sg:address":"Dr.-van De Perrestraat 232",
    "sg:city":"Geel",
    "sg:orig_category":"Postkantoren Verzekeringsmakelaars and experts",
    "sg:phone":"+32 14 58 02 32",
    "sg:postcode":"2440",
    "sg:province":"Antwerpen",
    "wof:name":"De Post",
    "wof:placetype":"venue"
},
  "geometry": {"coordinates":[4.9855399132,51.1791305542],"type":"Point"}
}