{
  "type": "Feature",
  "properties": {
    "addr:full":"Struikenstraat 15 Heusden-zolder Limburg 3550",
    "addr:housenumber":"15",
    "addr:postcode":"3550",
    "addr:street":"Struikenstraat",
    "iso:country":"BE",
    "sg:address":"Struikenstraat 15",
    "sg:city":"Heusden-zolder",
    "sg:orig_category":"Boekhouders",
    "sg:phone":"+32 11 57 56 05",
    "sg:postcode":"3550",
    "sg:province":"Limburg",
    "wof:name":"Antonio Mini",
    "wof:placetype":"venue"
},
  "geometry": {"coordinates":[5.3320279121,51.0360603333],"type":"Point"}
}