{
  "type": "Feature",
  "properties": {
    "iso:country":"BE",
    "sg:address":"Avenue Reine Astrid 60",
    "sg:city":"Verviers",
    "sg:orig_category":"Entretien and r\u00e9parations de voitures",
    "sg:phone":"+32 87 33 08 50",
    "sg:postcode":"4802",
    "sg:province":"Li\u00e8ge",
    "wof:name":"Maurice Bovy",
    "wof:placetype":"venue"
},
  "geometry": {"coordinates":[5.8815798759,50.5851287842],"type":"Point"}
}