{
  "type": "Feature",
  "properties": {
    "iso:country":"BE",
    "sg:address":"Bld De Smet De Naeyer 406",
    "sg:city":"Jette/jette",
    "sg:orig_category":"Journaux. Tabac",
    "sg:phone":"+32 2 478 44 41",
    "sg:postcode":"1090",
    "sg:province":"Bruxelles-Capitale",
    "wof:name":"Francine De Cuyper",
    "wof:placetype":"venue"
},
  "geometry": {"coordinates":[4.3356900215,50.8820991516],"type":"Point"}
}