{
  "type": "Feature",
  "properties": {
    "addr:full":"Rue Docteur Parent 381 Andenne (sclayn) Namur 5300",
    "addr:housenumber":"381",
    "addr:postcode":"5300",
    "addr:street":"Rue Docteur Parent",
    "iso:country":"BE",
    "sg:address":"Rue Docteur Parent 381",
    "sg:city":"Andenne (sclayn)",
    "sg:classifiers":[
        {
            "category":"Arena",
            "subcategory":"Sports Club",
            "type":"Entertainment"
        }
    ],
    "sg:phone":"+32 81 58 83 86",
    "sg:postcode":"5300",
    "sg:province":"Namur",
    "wof:name":"R.a.e.c. Sclayn",
    "wof:placetype":"venue"
},
  "geometry": {"coordinates":[5.0343742371,50.4925765991],"type":"Point"}
}