{
  "type": "Feature",
  "properties": {
    "addr:full":"Torhoutsestraat 351 Oostkamp (ruddervoorde) West-Vlaanderen 8020",
    "addr:housenumber":"351",
    "addr:postcode":"8020",
    "addr:street":"Torhoutsestraat",
    "iso:country":"BE",
    "sg:address":"Torhoutsestraat 351",
    "sg:city":"Oostkamp (ruddervoorde)",
    "sg:classifiers":[
        {
            "category":"Shopping",
            "subcategory":"Stationery & Office Supplies",
            "type":"Retail Goods"
        }
    ],
    "sg:phone":"+32 50 28 18 54",
    "sg:postcode":"8020",
    "sg:province":"West-Vlaanderen",
    "sg:tags":[
        "partition"
    ],
    "wof:name":"Vandewiele J",
    "wof:placetype":"venue"
},
  "geometry": {"coordinates":[3.1644439697,51.0737533569],"type":"Point"}
}