{
  "type": "Feature",
  "properties": {
    "addr:full":"Rue Du Petit-ry 7 Namur Namur 5100",
    "addr:housenumber":"7",
    "addr:postcode":"5100",
    "addr:street":"Rue Du Petit-Ry",
    "iso:country":"BE",
    "sg:address":"Rue Du Petit-ry 7",
    "sg:city":"Namur",
    "sg:orig_category":"Schoonheidssalons",
    "sg:phone":"+32 81 30 31 43",
    "sg:postcode":"5100",
    "sg:province":"Namur",
    "wof:name":"Josette Gilles",
    "wof:placetype":"venue"
},
  "geometry": {"coordinates":[4.8722491264,50.4423751831],"type":"Point"}
}