{
  "type": "Feature",
  "properties": {
    "addr:full":"Rue L\u00e9opold 80 Dison Li\u00e8ge 4820",
    "addr:housenumber":"80",
    "addr:postcode":"4820",
    "addr:street":"Rue Le\u0301Opold",
    "iso:country":"BE",
    "sg:address":"Rue L\u00e9opold 80",
    "sg:city":"Dison",
    "sg:classifiers":[
        {
            "category":"Shopping",
            "subcategory":"Books",
            "type":"Retail Goods"
        }
    ],
    "sg:phone":"+32 87 33 23 73",
    "sg:postcode":"4820",
    "sg:province":"Li\u00e8ge",
    "sg:tags":[
        "bookseller"
    ],
    "wof:name":"Fett R",
    "wof:placetype":"venue"
},
  "geometry": {"coordinates":[5.8506231308,50.6104736328],"type":"Point"}
}