{
  "type": "Feature",
  "properties": {
    "addr:full":"Olivierstraat 89 Rotselaar Vlaams-Brabant 3110",
    "addr:housenumber":"89",
    "addr:postcode":"3110",
    "addr:street":"Olivierstraat",
    "iso:country":"BE",
    "sg:address":"Olivierstraat 89",
    "sg:city":"Rotselaar",
    "sg:classifiers":[
        {
            "category":"Professional",
            "subcategory":"Accounting & Tax Preparation",
            "type":"Services"
        }
    ],
    "sg:phone":"+32 16 58 22 51",
    "sg:postcode":"3110",
    "sg:province":"Vlaams-Brabant",
    "sg:tags":[
        "bookkeeper"
    ],
    "wof:name":"Bollen W",
    "wof:placetype":"venue"
},
  "geometry": {"coordinates":[4.7648458481,50.9578361511],"type":"Point"}
}