{
  "type": "Feature",
  "properties": {
    "iso:country":"BE",
    "sg:address":"Mechelsesteenweg 677",
    "sg:city":"Herent",
    "sg:orig_category":"Installatie van houten of kunststof schrijnwerk Installatie van metalen schrijnwerk",
    "sg:phone":"+32 16 23 35 10",
    "sg:postcode":"3020",
    "sg:province":"Vlaams-Brabant",
    "wof:name":"D.g.r.",
    "wof:placetype":"venue"
},
  "geometry": {"coordinates":[4.6872601509,50.8951911926],"type":"Point"}
}