{
  "type": "Feature",
  "properties": {
    "addr:full":"Wirzfeld 22 Bullingen Li\u00e8ge 4760",
    "addr:housenumber":"22",
    "addr:postcode":"4760",
    "addr:street":"Wirzfeld",
    "iso:country":"BE",
    "sg:address":"Wirzfeld 22",
    "sg:city":"Bullingen",
    "sg:orig_category":"Vakantiehuizen",
    "sg:phone":"+32 80 64 76 66",
    "sg:postcode":"4760",
    "sg:province":"Li\u00e8ge",
    "wof:name":"E. Mackels",
    "wof:placetype":"venue"
},
  "geometry": {"coordinates":[6.2557492256,50.4061813354],"type":"Point"}
}