{
  "type": "Feature",
  "properties": {
    "iso:country":"BE",
    "sg:address":"Place Du Man\u00c8ge 1",
    "sg:city":"Charleroi",
    "sg:orig_category":"Dancings and bo\u00eetes de nuit",
    "sg:phone":"+32 71 30 94 70",
    "sg:postcode":"6000",
    "sg:province":"Hainaut",
    "wof:name":"La R\u00c9serve",
    "wof:placetype":"venue"
},
  "geometry": {"coordinates":[4.4428892136,50.4125976562],"type":"Point"}
}