{
  "type": "Feature",
  "properties": {
    "addr:full":"Belseledorp 76 Sint-niklaas Oost-Vlaanderen 9111",
    "addr:housenumber":"76",
    "addr:postcode":"9111",
    "addr:street":"Belseledorp",
    "iso:country":"BE",
    "sg:address":"Belseledorp 76",
    "sg:city":"Sint-niklaas",
    "sg:classifiers":[
        {
            "category":"Government",
            "subcategory":"Police Station",
            "type":"Public Place"
        }
    ],
    "sg:phone":"+32 3 772 58 43",
    "sg:postcode":"9111",
    "sg:province":"Oost-Vlaanderen",
    "sg:tags":[
        "gendarmerie"
    ],
    "wof:name":"Federale Politie",
    "wof:placetype":"venue"
},
  "geometry": {"coordinates":[4.0925478935,51.1462402344],"type":"Point"}
}