{
  "type": "Feature",
  "properties": {
    "iso:country":"BE",
    "sg:address":"Avenue De La R\u00c9sistance 230",
    "sg:city":"Soumagne",
    "sg:orig_category":"Kapsalons",
    "sg:phone":"+32 4 377 40 93",
    "sg:postcode":"4630",
    "sg:province":"Li\u00e8ge",
    "wof:name":"Coiffure Isabelle",
    "wof:placetype":"venue"
},
  "geometry": {"coordinates":[5.7332201004,50.6307907104],"type":"Point"}
}