{
  "type": "Feature",
  "properties": {
    "iso:country":"BE",
    "sg:address":"Sint-hubertusplein 44",
    "sg:city":"Diest",
    "sg:orig_category":"Pain, p\u00e2tisseries and confiseries",
    "sg:phone":"+32 13 31 35 87",
    "sg:postcode":"3290",
    "sg:province":"Vlaams-Brabant",
    "wof:name":"Bakkerij Pelgrims",
    "wof:placetype":"venue"
},
  "geometry": {"coordinates":[5.0820398331,51.0003013611],"type":"Point"}
}