{
  "type": "Feature",
  "properties": {
    "addr:full":"Hezewijk 7 Herentals Antwerpen 2200",
    "addr:housenumber":"7",
    "addr:postcode":"2200",
    "addr:street":"Hezewijk",
    "iso:country":"BE",
    "sg:address":"Hezewijk 7",
    "sg:city":"Herentals",
    "sg:orig_category":"Producteurs de l\u00e9gumes",
    "sg:phone":"+32 14 23 04 35",
    "sg:postcode":"2200",
    "sg:province":"Antwerpen",
    "wof:name":"Alex Engels",
    "wof:placetype":"venue"
},
  "geometry": {"coordinates":[4.8435111046,51.1569824219],"type":"Point"}
}