{
  "type": "Feature",
  "properties": {
    "addr:full":"Merksemsebaan 11 Wijnegem Antwerpen 2110",
    "addr:housenumber":"11",
    "addr:postcode":"2110",
    "addr:street":"Merksemsebaan",
    "iso:country":"BE",
    "sg:address":"Merksemsebaan 11",
    "sg:city":"Wijnegem",
    "sg:classifiers":[
        {
            "category":"Building & Trades",
            "subcategory":"Electrical",
            "type":"Services"
        }
    ],
    "sg:phone":"+32 4 239 07 38",
    "sg:postcode":"2110",
    "sg:province":"Antwerpen",
    "sg:tags":[
        "heating"
    ],
    "wof:name":"Ariston-apt Service",
    "wof:placetype":"venue"
},
  "geometry": {"coordinates":[4.5188288689,51.2278404236],"type":"Point"}
}