{
  "type": "Feature",
  "properties": {
    "addr:full":"Leuvensesteenweg 229 Tielt-winge (sint-joris-winge) Vlaams-Brabant 3390",
    "addr:housenumber":"229",
    "addr:postcode":"3390",
    "addr:street":"Leuvensesteenweg",
    "iso:country":"BE",
    "sg:address":"Leuvensesteenweg 229",
    "sg:city":"Tielt-winge (sint-joris-winge)",
    "sg:classifiers":[
        {
            "category":"Health Services",
            "subcategory":"Dentist",
            "type":"Services"
        }
    ],
    "sg:phone":"+32 16 63 49 13",
    "sg:postcode":"3390",
    "sg:province":"Vlaams-Brabant",
    "wof:name":"Gysemans Isabella",
    "wof:placetype":"venue"
},
  "geometry": {"coordinates":[4.8991470337,50.9160423279],"type":"Point"}
}