{
  "type": "Feature",
  "properties": {
    "iso:country":"BE",
    "sg:address":"Stationstraat 64",
    "sg:city":"Komen-waasten/comines-warneton",
    "sg:orig_category":"Benzinestations and brandstoffen Herstellingen and onderhoud van auto's Voertuigen",
    "sg:phone":"+32 56 55 59 38",
    "sg:postcode":"7780",
    "sg:province":"Hainaut",
    "wof:name":"Garage St.arnold",
    "wof:placetype":"venue"
},
  "geometry": {"coordinates":[2.9984300137,50.7863311768],"type":"Point"}
}