{
  "type": "Feature",
  "properties": {
    "iso:country":"BE",
    "sg:address":"Hogestraat 194",
    "sg:city":"Hooglede",
    "sg:orig_category":"Catering and organisatie van feesten Hotels Restaurants Ruimtes voor conferenties, recepties and fee",
    "sg:phone":"+32 51 70 25 83",
    "sg:postcode":"8830",
    "sg:province":"West-Vlaanderen",
    "wof:name":"De Vossenberg",
    "wof:placetype":"venue"
},
  "geometry": {"coordinates":[3.0643041134,50.983379364],"type":"Point"}
}