{
  "type": "Feature",
  "properties": {
    "addr:full":"Puienbroeklaan 6 Brugge West-Vlaanderen 8310",
    "addr:housenumber":"6",
    "addr:postcode":"8310",
    "addr:street":"Puienbroeklaan",
    "iso:country":"BE",
    "sg:address":"Puienbroeklaan 6",
    "sg:city":"Brugge",
    "sg:orig_category":"Administration d'immeubles",
    "sg:phone":"+32 50 36 36 82",
    "sg:postcode":"8310",
    "sg:province":"West-Vlaanderen",
    "wof:name":"Agem Vastgoedbeheerders",
    "wof:placetype":"venue"
},
  "geometry": {"coordinates":[3.2796599865,51.2128486633],"type":"Point"}
}