{
  "type": "Feature",
  "properties": {
    "iso:country":"BE",
    "sg:address":"Muisbroeklaan 57",
    "sg:city":"Antwerpen",
    "sg:classifiers":[
        {
            "category":"Freight",
            "type":"Transportation"
        }
    ],
    "sg:phone":"+32 3 541 18 99",
    "sg:postcode":"2030",
    "sg:province":"Antwerpen",
    "sg:tags":[
        "-",
        "transport"
    ],
    "wof:name":"Manufert",
    "wof:placetype":"venue"
},
  "geometry": {"coordinates":[4.3364539146,51.2982978821],"type":"Point"}
}