{
  "type": "Feature",
  "properties": {
    "iso:country":"BE",
    "sg:address":"Taemweg 26",
    "sg:city":"Maaseik",
    "sg:orig_category":"Plantes and fleurs Gr",
    "sg:phone":"+32 89 86 46 49",
    "sg:postcode":"3680",
    "sg:province":"Limburg",
    "wof:name":"Arits J",
    "wof:placetype":"venue"
},
  "geometry": {"coordinates":[5.6813650131,51.1099395752],"type":"Point"}
}