{
  "type": "Feature",
  "properties": {
    "iso:country":"BE",
    "sg:address":"Rue De La Bonne Auberge 14",
    "sg:city":"Yvoir",
    "sg:classifiers":[
        {
            "category":"Travel",
            "subcategory":"Hotels & Motels",
            "type":"Entertainment"
        }
    ],
    "sg:phone":"+32 82 61 37 38",
    "sg:postcode":"5530",
    "sg:province":"Namur",
    "sg:tags":[
        "van",
        "restaurant",
        "food",
        "aan",
        "fast",
        "feesten",
        "levering",
        "meeneem",
        "organisatie",
        "rest",
        "catering",
        "huis"
    ],
    "wof:name":"La Bonne Auberge",
    "wof:placetype":"venue"
},
  "geometry": {"coordinates":[4.9299798012,50.33411026],"type":"Point"}
}