{
  "type": "Feature",
  "properties": {
    "iso:country":"BE",
    "sg:address":"Kortrijksestraat 144",
    "sg:city":"Kortrijk",
    "sg:orig_category":"Boucheries",
    "sg:phone":"+32 56 35 80 35",
    "sg:postcode":"8501",
    "sg:province":"West-Vlaanderen",
    "wof:name":"Slagerij Luc & Francine",
    "wof:placetype":"venue"
},
  "geometry": {"coordinates":[3.2402029037,50.8375244141],"type":"Point"}
}