{
  "type": "Feature",
  "properties": {
    "addr:full":"Walhostraat 91 Landen Vlaams-Brabant 3401",
    "addr:housenumber":"91",
    "addr:postcode":"3401",
    "addr:street":"Walhostraat",
    "iso:country":"BE",
    "sg:address":"Walhostraat 91",
    "sg:city":"Landen",
    "sg:orig_category":"Services fun\u00e9raires",
    "sg:phone":"+32 11 88 17 36",
    "sg:postcode":"3401",
    "sg:province":"Vlaams-Brabant",
    "wof:name":"Begrafenissen Wauters R.",
    "wof:placetype":"venue"
},
  "geometry": {"coordinates":[5.0925440788,50.7244415283],"type":"Point"}
}