{
  "type": "Feature",
  "properties": {
    "addr:full":"Kruisstraat 37 Tielt-winge (tielt) Vlaams-Brabant 3390",
    "addr:housenumber":"37",
    "addr:postcode":"3390",
    "addr:street":"Kruisstraat",
    "iso:country":"BE",
    "sg:address":"Kruisstraat 37",
    "sg:city":"Tielt-winge (tielt)",
    "sg:classifiers":[
        {
            "category":"Personal",
            "subcategory":"Beauty Salon",
            "type":"Services"
        }
    ],
    "sg:phone":"+32 16 63 28 10",
    "sg:postcode":"3390",
    "sg:province":"Vlaams-Brabant",
    "sg:tags":[
        "lady",
        "-",
        "hairdressing"
    ],
    "wof:name":"Kristel",
    "wof:placetype":"venue"
},
  "geometry": {"coordinates":[4.9144620895,50.9347114563],"type":"Point"}
}