{
  "type": "Feature",
  "properties": {
    "addr:full":"Mechelsesteenweg 223 Antwerpen Antwerpen 2018",
    "addr:housenumber":"223",
    "addr:postcode":"2018",
    "addr:street":"Mechelsesteenweg",
    "iso:country":"BE",
    "sg:address":"Mechelsesteenweg 223",
    "sg:city":"Antwerpen",
    "sg:orig_category":"Opticiens",
    "sg:phone":"+32 3 230 85 63",
    "sg:postcode":"2018",
    "sg:province":"Antwerpen",
    "wof:name":"Optiek G.fierens",
    "wof:placetype":"venue"
},
  "geometry": {"coordinates":[4.4125361443,51.2025260925],"type":"Point"}
}