{
  "type": "Feature",
  "properties": {
    "iso:country":"BE",
    "sg:address":"Veldsprietstraat 27",
    "sg:city":"Wingene",
    "sg:orig_category":"Producteurs de fruits. Eleveurs and marchands de porcs",
    "sg:phone":"+32 51 61 19 90",
    "sg:postcode":"8750",
    "sg:province":"West-Vlaanderen",
    "wof:name":"Wilfried Decuyper",
    "wof:placetype":"venue"
},
  "geometry": {"coordinates":[3.1765499115,51.060760498],"type":"Point"}
}