{
  "type": "Feature",
  "properties": {
    "iso:country":"BE",
    "sg:address":"Drongenstraat 150",
    "sg:city":"Lokeren",
    "sg:classifiers":[
        {
            "category":"Recreation",
            "type":"Entertainment"
        }
    ],
    "sg:phone":"+32 9 356 81 93",
    "sg:postcode":"9160",
    "sg:province":"Oost-Vlaanderen",
    "sg:tags":[
        "diver",
        "amusement"
    ],
    "wof:name":"Studio Sunshine",
    "wof:placetype":"venue"
},
  "geometry": {"coordinates":[3.9034650326,51.1071090698],"type":"Point"}
}