{
  "type": "Feature",
  "properties": {
    "iso:country":"BE",
    "sg:address":"Molenstraat 93",
    "sg:city":"Sint-laureins",
    "sg:orig_category":"P\u00e9pini\u00e9ristes",
    "sg:phone":"+32 9 379 84 91",
    "sg:postcode":"9988",
    "sg:province":"Oost-Vlaanderen",
    "wof:name":"Koenraad Van Eykeren",
    "wof:placetype":"venue"
},
  "geometry": {"coordinates":[3.6247529984,51.2845191956],"type":"Point"}
}