{
  "type": "Feature",
  "properties": {
    "iso:country":"BE",
    "sg:address":"Winkelom 52",
    "sg:city":"Geel",
    "sg:classifiers":[
        {
            "category":"Arts & Performance",
            "subcategory":"Art Gallery",
            "type":"Entertainment"
        }
    ],
    "sg:phone":"+32 14 58 54 15",
    "sg:postcode":"2440",
    "sg:province":"Antwerpen",
    "sg:tags":[
        "rendering"
    ],
    "wof:name":"Lindekens S",
    "wof:placetype":"venue"
},
  "geometry": {"coordinates":[5.0111780167,51.1347427368],"type":"Point"}
}