{
  "type": "Feature",
  "properties": {
    "iso:country":"BE",
    "sg:address":"Heirbaan 179",
    "sg:city":"Hamme",
    "sg:orig_category":"Imprimeries and copyshops",
    "sg:phone":"+32 52 47 94 99",
    "sg:postcode":"9220",
    "sg:province":"Oost-Vlaanderen",
    "wof:name":"Lauda Graphics",
    "wof:placetype":"venue"
},
  "geometry": {"coordinates":[4.0907869339,51.0804138184],"type":"Point"}
}