{
  "type": "Feature",
  "properties": {
    "iso:country":"BE",
    "sg:address":"Rue De Limbourg 31",
    "sg:city":"Verviers",
    "sg:classifiers":[
        {
            "category":"Wholesale",
            "subcategory":"Auto Parts",
            "type":"Manufacturing & Wholesale Goods"
        }
    ],
    "sg:phone":"+32 87 30 02 00",
    "sg:postcode":"4800",
    "sg:province":"Li\u00e8ge",
    "sg:tags":[
        "body",
        "automobile",
        "supply",
        "equipment"
    ],
    "wof:name":"Rox Auto Sa",
    "wof:placetype":"venue"
},
  "geometry": {"coordinates":[5.8752908707,50.5959205627],"type":"Point"}
}