{
  "type": "Feature",
  "properties": {
    "addr:full":"Noordlaan 19 Roeselare West-Vlaanderen 8800",
    "addr:housenumber":"19",
    "addr:postcode":"8800",
    "addr:street":"Noordlaan",
    "iso:country":"BE",
    "sg:address":"Noordlaan 19",
    "sg:city":"Roeselare",
    "sg:classifiers":[
        {
            "category":"Real Estate",
            "subcategory":"Architect",
            "type":"Services"
        }
    ],
    "sg:phone":"+32 51 24 18 25",
    "sg:postcode":"8800",
    "sg:province":"West-Vlaanderen",
    "wof:name":"Schautteet C",
    "wof:placetype":"venue"
},
  "geometry": {"coordinates":[3.120486021,50.9562606812],"type":"Point"}
}