{
  "type": "Feature",
  "properties": {
    "iso:country":"BE",
    "sg:address":"Rue De Fierlant 123",
    "sg:city":"Bruxelles (forest)",
    "sg:classifiers":[
        {
            "category":"Manufacturing",
            "subcategory":"Furniture",
            "type":"Manufacturing & Wholesale Goods"
        }
    ],
    "sg:phone":"+32 2 538 09 70",
    "sg:postcode":"1190",
    "sg:province":"Bruxelles-Capitale",
    "sg:tags":[
        "made",
        "-",
        "custom"
    ],
    "wof:name":"La Main & L'esprit Asbl",
    "wof:placetype":"venue"
},
  "geometry": {"coordinates":[4.3315520287,50.8248443604],"type":"Point"}
}