{
  "type": "Feature",
  "properties": {
    "iso:country":"BE",
    "sg:address":"Rue Chabotteau 1",
    "sg:city":"Frameries",
    "sg:classifiers":[
        {
            "category":"Insurance",
            "subcategory":"Life Insurance",
            "type":"Services"
        }
    ],
    "sg:phone":"+32 65 61 15 11",
    "sg:postcode":"7080",
    "sg:province":"Hainaut",
    "sg:tags":[
        "assurance"
    ],
    "wof:name":"P&v",
    "wof:placetype":"venue"
},
  "geometry": {"coordinates":[3.8933999538,50.4099998474],"type":"Point"}
}