{
  "type": "Feature",
  "properties": {
    "iso:country":"BE",
    "sg:address":"Heiststeenweg 63",
    "sg:city":"Putte (beerzel)",
    "sg:classifiers":[
        {
            "category":"Home & Garden",
            "subcategory":"Home Furnishings",
            "type":"Retail Goods"
        }
    ],
    "sg:phone":"+32 15 24 29 52",
    "sg:postcode":"2580",
    "sg:province":"Antwerpen",
    "sg:tags":[
        "-",
        "furniture"
    ],
    "wof:name":"Old Pine Shop",
    "wof:placetype":"venue"
},
  "geometry": {"coordinates":[4.675511837,51.0595626831],"type":"Point"}
}