{
  "type": "Feature",
  "properties": {
    "addr:full":"Prins Leopoldlei 79b1 Mortsel Antwerpen 2640",
    "addr:housenumber":"79b1",
    "addr:postcode":"2640",
    "addr:street":"Prins Leopoldlei",
    "iso:country":"BE",
    "sg:address":"Prins Leopoldlei 79b1",
    "sg:city":"Mortsel",
    "sg:orig_category":"Banken and kredietinstellingen",
    "sg:phone":"+32 3 449 19 14",
    "sg:postcode":"2640",
    "sg:province":"Antwerpen",
    "wof:name":"Groep Argenta",
    "wof:placetype":"venue"
},
  "geometry": {"coordinates":[4.4533028603,51.1682281494],"type":"Point"}
}