{
  "type": "Feature",
  "properties": {
    "iso:country":"BE",
    "sg:address":"Sleutelstraat 13",
    "sg:city":"Brussel/bruxelles",
    "sg:orig_category":"Woningbouw",
    "sg:phone":"+32 2 217 25 09",
    "sg:postcode":"1000",
    "sg:province":"Bruxelles-Capitale",
    "wof:name":"Michel Poot",
    "wof:placetype":"venue"
},
  "geometry": {"coordinates":[4.3432350159,50.8526000977],"type":"Point"}
}