{
  "type": "Feature",
  "properties": {
    "addr:full":"Grote Markt 7 Blankenberge West-Vlaanderen 8370",
    "addr:housenumber":"7",
    "addr:postcode":"8370",
    "addr:street":"Grote Markt",
    "iso:country":"BE",
    "sg:address":"Grote Markt 7",
    "sg:city":"Blankenberge",
    "sg:classifiers":[
        {
            "category":"Fast Food",
            "type":"Food & Drink"
        }
    ],
    "sg:phone":"+32 50 41 36 69",
    "sg:postcode":"8370",
    "sg:province":"West-Vlaanderen",
    "sg:tags":[
        "de",
        "restaurant",
        "organisation",
        "\u00c0",
        "domicile",
        "catering",
        "livraison",
        "f\u00cates",
        "restaurants"
    ],
    "wof:name":"'t Karveeltje",
    "wof:placetype":"venue"
},
  "geometry": {"coordinates":[3.1246318817,51.3133163452],"type":"Point"}
}