{
  "type": "Feature",
  "properties": {
    "addr:full":"Liersebaan 58b Zandhoven Antwerpen 2240",
    "addr:housenumber":"58b",
    "addr:postcode":"2240",
    "addr:street":"Liersebaan",
    "iso:country":"BE",
    "sg:address":"Liersebaan 58b",
    "sg:city":"Zandhoven",
    "sg:classifiers":[
        {
            "category":"Personal",
            "subcategory":"Beauty Salon",
            "type":"Services"
        }
    ],
    "sg:phone":"+32 3 484 36 54",
    "sg:postcode":"2240",
    "sg:province":"Antwerpen",
    "wof:name":"La Perla",
    "wof:placetype":"venue"
},
  "geometry": {"coordinates":[4.6562128067,51.212688446],"type":"Point"}
}