{
  "type": "Feature",
  "properties": {
    "iso:country":"BE",
    "sg:address":"Grand'place 62",
    "sg:city":"Verviers (ensival)",
    "sg:classifiers":[
        {
            "category":"Shopping",
            "subcategory":"Jewelry",
            "type":"Retail Goods"
        }
    ],
    "sg:phone":"+32 87 33 17 95",
    "sg:postcode":"4800",
    "sg:province":"Li\u00e8ge",
    "sg:tags":[
        "purchase",
        "-",
        "sale",
        "gold"
    ],
    "wof:name":"Lambert J-c",
    "wof:placetype":"venue"
},
  "geometry": {"coordinates":[5.842634201,50.5815086365],"type":"Point"}
}