{
  "type": "Feature",
  "properties": {
    "addr:full":"Kortrijksesteenweg 527 Gent Oost-Vlaanderen 9000",
    "addr:housenumber":"527",
    "addr:postcode":"9000",
    "addr:street":"Kortrijksesteenweg;Oost-Vlaanderen",
    "iso:country":"BE",
    "sg:address":"Kortrijksesteenweg 527",
    "sg:city":"Gent",
    "sg:orig_category":"Schoonheidssalons",
    "sg:phone":"+32 9 222 97 96",
    "sg:postcode":"9000",
    "sg:province":"Oost-Vlaanderen",
    "wof:name":"Claire Debouvrie",
    "wof:placetype":"venue"
},
  "geometry": {"coordinates":[3.7165009975,51.0359077454],"type":"Point"}
}