{
  "type": "Feature",
  "properties": {
    "addr:full":"Sint-lenaartsebaan 3 Malle Antwerpen 2390",
    "addr:housenumber":"3",
    "addr:postcode":"2390",
    "addr:street":"Sint-Lenaartsebaan",
    "iso:country":"BE",
    "sg:address":"Sint-lenaartsebaan 3",
    "sg:city":"Malle",
    "sg:orig_category":"Textiel",
    "sg:phone":"+32 3 312 18 53",
    "sg:postcode":"2390",
    "sg:province":"Antwerpen",
    "wof:name":"Huis Bourbon",
    "wof:placetype":"venue"
},
  "geometry": {"coordinates":[4.7315530777,51.3012924194],"type":"Point"}
}