{
  "type": "Feature",
  "properties": {
    "addr:full":"Vrijheidstraat 32 Antwerpen Antwerpen 2000",
    "addr:housenumber":"32",
    "addr:postcode":"2000",
    "addr:street":"Vrijheidstraat",
    "iso:country":"BE",
    "sg:address":"Vrijheidstraat 32",
    "sg:city":"Antwerpen",
    "sg:classifiers":[
        {
            "category":"Shopping",
            "subcategory":"Clothing, Apparel, & Fashions",
            "type":"Retail Goods"
        }
    ],
    "sg:phone":"+32 3 257 23 93",
    "sg:postcode":"2000",
    "sg:province":"Antwerpen",
    "sg:tags":[
        "-",
        "clothing",
        "child"
    ],
    "wof:name":"Lalalou",
    "wof:placetype":"venue"
},
  "geometry": {"coordinates":[4.3996710777,51.2110939026],"type":"Point"}
}