{
  "type": "Feature",
  "properties": {
    "iso:country":"BE",
    "sg:address":"Oude Hostartstraat 44",
    "sg:city":"Genk",
    "sg:orig_category":"Brood, gebak and snoepgoed Rookartikelen",
    "sg:phone":"+32 89 35 46 20",
    "sg:postcode":"3600",
    "sg:province":"Limburg",
    "wof:name":"Maria Prodan",
    "wof:placetype":"venue"
},
  "geometry": {"coordinates":[5.4956760406,50.9742698669],"type":"Point"}
}