{
  "type": "Feature",
  "properties": {
    "addr:full":"Jozef Termoniastraat 52 Asse Vlaams-Brabant 1731",
    "addr:housenumber":"52",
    "addr:postcode":"1731",
    "addr:street":"Jozef Termoniastraat",
    "iso:country":"BE",
    "sg:address":"Jozef Termoniastraat 52",
    "sg:city":"Asse",
    "sg:orig_category":"R\u00e9cup\u00e9ration de mati\u00e8res m\u00e9talliques recyclables and d\u00e9molisseurs de voitures. V\u00e9hicules automobiles",
    "sg:phone":"+32 2 463 06 56",
    "sg:postcode":"1731",
    "sg:province":"Vlaams-Brabant",
    "wof:name":"Garage Bosmans",
    "wof:placetype":"venue"
},
  "geometry": {"coordinates":[4.285528183,50.8783836365],"type":"Point"}
}