{
  "type": "Feature",
  "properties": {
    "addr:full":"Avenue Jean Et Pierre Carsoel 76 Bruxelles (uccle) Bruxelles-Capitale 1180",
    "addr:housenumber":"76",
    "addr:postcode":"1180",
    "addr:street":"Avenue Jean Et Pierre Carsoel",
    "iso:country":"BE",
    "sg:address":"Avenue Jean Et Pierre Carsoel 76",
    "sg:city":"Bruxelles (uccle)",
    "sg:classifiers":[
        {
            "category":"Health Services",
            "subcategory":"Doctor",
            "type":"Services"
        }
    ],
    "sg:phone":"+32 2 374 74 61",
    "sg:postcode":"1180",
    "sg:province":"Bruxelles-Capitale",
    "sg:tags":[
        "medicinephysicians",
        "surgeon"
    ],
    "wof:name":"Bricart R",
    "wof:placetype":"venue"
},
  "geometry": {"coordinates":[4.3579320908,50.7945747375],"type":"Point"}
}