{
  "type": "Feature",
  "properties": {
    "addr:full":"Ketelbuisstraat 50 Lichtervelde West-Vlaanderen 8810",
    "addr:housenumber":"50",
    "addr:postcode":"8810",
    "addr:street":"Ketelbuisstraat",
    "iso:country":"BE",
    "sg:address":"Ketelbuisstraat 50",
    "sg:city":"Lichtervelde",
    "sg:orig_category":"Installation de menuiserie en bois and plastique",
    "sg:phone":"+32 51 72 55 50",
    "sg:postcode":"8810",
    "sg:province":"West-Vlaanderen",
    "wof:name":"Vannieuwenhuyse",
    "wof:placetype":"venue"
},
  "geometry": {"coordinates":[3.1285970211,51.0290489197],"type":"Point"}
}