{
  "type": "Feature",
  "properties": {
    "addr:full":"Rue De La Chauss\u00c9e 60 Mons Hainaut 7000",
    "addr:housenumber":"60",
    "addr:postcode":"7000",
    "addr:street":"Rue De La Chausse\u0301E;Hainaut",
    "iso:country":"BE",
    "sg:address":"Rue De La Chauss\u00c9e 60",
    "sg:city":"Mons",
    "sg:orig_category":"Textiel",
    "sg:phone":"+32 65 34 01 34",
    "sg:postcode":"7000",
    "sg:province":"Hainaut",
    "wof:name":"La Fili\u00c8re",
    "wof:placetype":"venue"
},
  "geometry": {"coordinates":[3.9503760338,50.4527435303],"type":"Point"}
}