{
  "type": "Feature",
  "properties": {
    "iso:country":"BE",
    "sg:address":"Chauss\u00c9e De Lille 53",
    "sg:city":"Komen-waasten/comines-warneton",
    "sg:classifiers":[
        {
            "category":"Autos & Motor Vehicles",
            "subcategory":"Fuel & Gas Station",
            "type":"Retail Goods"
        }
    ],
    "sg:phone":"+32 56 58 88 15",
    "sg:postcode":"7784",
    "sg:province":"Hainaut",
    "sg:tags":[
        "stations-service",
        "carburants"
    ],
    "wof:name":"Station Copain",
    "wof:placetype":"venue"
},
  "geometry": {"coordinates":[2.9404909611,50.7490615845],"type":"Point"}
}