{
  "type": "Feature",
  "properties": {
    "iso:country":"BE",
    "sg:address":"Truweelstraat 132",
    "sg:city":"Sint-niklaas",
    "sg:orig_category":"Antiek",
    "sg:phone":"+32 3 777 20 95",
    "sg:postcode":"9100",
    "sg:province":"Oost-Vlaanderen",
    "wof:name":"Christian Van Der Linden",
    "wof:placetype":"venue"
},
  "geometry": {"coordinates":[4.1500201225,51.1717376709],"type":"Point"}
}