{
  "type": "Feature",
  "properties": {
    "addr:full":"A.l. Huxleystraat 35 Aalter (bellem) Oost-Vlaanderen 9881",
    "addr:housenumber":"35",
    "addr:postcode":"9881",
    "addr:street":"Huxleystraat",
    "iso:country":"BE",
    "sg:address":"A.l. Huxleystraat 35",
    "sg:city":"Aalter (bellem)",
    "sg:classifiers":[
        {
            "category":"Communications",
            "type":"Services"
        }
    ],
    "sg:phone":"+32 9 374 62 22",
    "sg:postcode":"9881",
    "sg:province":"Oost-Vlaanderen",
    "sg:tags":[
        "translator"
    ],
    "wof:name":"Rijsselaere G",
    "wof:placetype":"venue"
},
  "geometry": {"coordinates":[3.4882929325,51.0871963501],"type":"Point"}
}