{
  "type": "Feature",
  "properties": {
    "addr:full":"Notelaarsstraat 55 Brussel/bruxelles Bruxelles-Capitale 1000",
    "addr:housenumber":"55",
    "addr:postcode":"1000",
    "addr:street":"Notelaarsstraat;/",
    "iso:country":"BE",
    "sg:address":"Notelaarsstraat 55",
    "sg:city":"Brussel/bruxelles",
    "sg:orig_category":"Diverse juridische dienstverlening",
    "sg:phone":"+32 2 732 63 00",
    "sg:postcode":"1000",
    "sg:province":"Bruxelles-Capitale",
    "wof:name":"H\u00d4tel Des Ventes Mosan",
    "wof:placetype":"venue"
},
  "geometry": {"coordinates":[4.3882222176,50.8498497009],"type":"Point"}
}