{
  "type": "Feature",
  "properties": {
    "addr:full":"Hoge Meentochtstraat 31 Rumst Antwerpen 2840",
    "addr:housenumber":"31",
    "addr:postcode":"2840",
    "addr:street":"Hoge Meentochtstraat",
    "iso:country":"BE",
    "sg:address":"Hoge Meentochtstraat 31",
    "sg:city":"Rumst",
    "sg:classifiers":[
        {
            "category":"Sports & Exercise",
            "subcategory":"Skate Park",
            "type":"Entertainment"
        }
    ],
    "sg:phone":"+32 3 888 84 29",
    "sg:postcode":"2840",
    "sg:province":"Antwerpen",
    "sg:tags":[
        "mushroom"
    ],
    "wof:name":"Vleugels I",
    "wof:placetype":"venue"
},
  "geometry": {"coordinates":[4.4344677925,51.0906715393],"type":"Point"}
}