{
  "type": "Feature",
  "properties": {
    "addr:full":"Turnhoutsebaan 76 Scherpenheuvel-zichem Vlaams-Brabant 3271",
    "addr:housenumber":"76",
    "addr:postcode":"3271",
    "addr:street":"Turnhoutsebaan",
    "iso:country":"BE",
    "sg:address":"Turnhoutsebaan 76",
    "sg:city":"Scherpenheuvel-zichem",
    "sg:classifiers":[
        {
            "category":"Cafe",
            "type":"Food & Drink"
        }
    ],
    "sg:phone":"+32 13 77 70 47",
    "sg:postcode":"3271",
    "sg:province":"Vlaams-Brabant",
    "sg:tags":[
        "caf\u00e9s"
    ],
    "wof:name":"Kris Peeters",
    "wof:placetype":"venue"
},
  "geometry": {"coordinates":[5.0133838654,51.0309524536],"type":"Point"}
}