{
  "type": "Feature",
  "properties": {
    "iso:country":"BE",
    "sg:address":"Parklaan 55b1",
    "sg:city":"Turnhout",
    "sg:orig_category":"Banken and kredietinstellingen",
    "sg:phone":"+32 14 41 84 59",
    "sg:postcode":"2300",
    "sg:province":"Antwerpen",
    "wof:name":"Bank J. Van Breda & Co",
    "wof:placetype":"venue"
},
  "geometry": {"coordinates":[4.949942112,51.3127441406],"type":"Point"}
}