{
  "type": "Feature",
  "properties": {
    "iso:country":"BE",
    "sg:address":"Kleppestraat 19",
    "sg:city":"Moorslede",
    "sg:orig_category":"Drogisterijen Plaatsen van vloer- and muurbekleding Schilders Textiel Verlichting and huishoudartike",
    "sg:phone":"+32 56 50 03 24",
    "sg:postcode":"8890",
    "sg:province":"West-Vlaanderen",
    "wof:name":"Berluc",
    "wof:placetype":"venue"
},
  "geometry": {"coordinates":[3.1002728939,50.8517494202],"type":"Point"}
}