{
  "type": "Feature",
  "properties": {
    "iso:country":"BE",
    "sg:address":"Avenue Jacques Sermon 91",
    "sg:city":"Jette",
    "sg:classifiers":[
        {
            "category":"Restaurant",
            "type":"Food & Drink"
        }
    ],
    "sg:phone":"+32 2 426 89 35",
    "sg:postcode":"1090",
    "sg:province":"Bruxelles-Capitale",
    "wof:name":"Le Sermon",
    "wof:placetype":"venue"
},
  "geometry": {"coordinates":[4.3228588104,50.8700447083],"type":"Point"}
}