{
  "type": "Feature",
  "properties": {
    "addr:full":"Broeder De Saedeleerstraat 57 Lede Oost-Vlaanderen 9340",
    "addr:housenumber":"57",
    "addr:postcode":"9340",
    "addr:street":"Broeder De Saedeleerstraat",
    "iso:country":"BE",
    "sg:address":"Broeder De Saedeleerstraat 57",
    "sg:city":"Lede",
    "sg:orig_category":"Quincailleries. Animaux domestiques and accessoires",
    "sg:phone":"+32 53 80 73 26",
    "sg:postcode":"9340",
    "sg:province":"Oost-Vlaanderen",
    "wof:name":"Hobby Center P.r.s.",
    "wof:placetype":"venue"
},
  "geometry": {"coordinates":[3.9921500683,50.9648094177],"type":"Point"}
}