{
  "type": "Feature",
  "properties": {
    "iso:country":"BE",
    "sg:address":"Neerstraat 105",
    "sg:city":"Tessenderlo",
    "sg:classifiers":[
        {
            "category":"Professional",
            "subcategory":"Computer Services",
            "type":"Services"
        }
    ],
    "sg:phone":"+32 13 66 75 68",
    "sg:postcode":"3980",
    "sg:province":"Limburg",
    "sg:tags":[
        "-",
        "processing",
        "data"
    ],
    "wof:name":"Proline Systems Bvba",
    "wof:placetype":"venue"
},
  "geometry": {"coordinates":[5.0891828537,51.0726776123],"type":"Point"}
}