{
  "type": "Feature",
  "properties": {
    "iso:country":"BE",
    "sg:address":"Romershovenstraat 190b2",
    "sg:city":"Hoeselt",
    "sg:orig_category":"Producteurs de fruits",
    "sg:phone":"+32 89 41 45 94",
    "sg:postcode":"3730",
    "sg:province":"Limburg",
    "wof:name":"Frank Vandormael",
    "wof:placetype":"venue"
},
  "geometry": {"coordinates":[5.4550971985,50.8741989136],"type":"Point"}
}