{
  "type": "Feature",
  "properties": {
    "iso:country":"BE",
    "sg:address":"Kapellenstraat 48",
    "sg:city":"Lebbeke",
    "sg:classifiers":[
        {
            "category":"Restaurant",
            "type":"Food & Drink"
        }
    ],
    "sg:phone":"+32 52 41 16 11",
    "sg:postcode":"9280",
    "sg:province":"Oost-Vlaanderen",
    "wof:name":"Caf\u00c9 't Vat",
    "wof:placetype":"venue"
},
  "geometry": {"coordinates":[4.1281151772,51.0004501343],"type":"Point"}
}