{
  "type": "Feature",
  "properties": {
    "addr:full":"Parc Industriel Zone C Seneffe Hainaut 7180",
    "addr:postcode":"7180",
    "addr:street":"Parc Industriel;C;Hainaut",
    "iso:country":"BE",
    "sg:address":"Parc Industriel Zone C",
    "sg:city":"Seneffe",
    "sg:classifiers":[
        {
            "category":"Manufacturing",
            "subcategory":"Wood Products",
            "type":"Manufacturing & Wholesale Goods"
        }
    ],
    "sg:phone":"+32 53 65 02 11",
    "sg:postcode":"7180",
    "sg:province":"Hainaut",
    "sg:tags":[
        "solid",
        "laminated"
    ],
    "wof:name":"Coplac Nv",
    "wof:placetype":"venue"
},
  "geometry": {"coordinates":[4.0553851128,50.9209976196],"type":"Point"}
}