{
  "type": "Feature",
  "properties": {
    "iso:country":"BE",
    "sg:address":".",
    "sg:city":"Gent",
    "sg:orig_category":"Non-foodwinkels",
    "sg:phone":"+32 9 226 88 23",
    "sg:postcode":"9031",
    "sg:province":"Oost-Vlaanderen",
    "wof:name":"Berlinda",
    "wof:placetype":"venue"
},
  "geometry": {"coordinates":[3.6630249023,51.0503692627],"type":"Point"}
}