{
  "type": "Feature",
  "properties": {
    "iso:country":"BE",
    "sg:address":"Chauss\u00e9e De Wavre 78d",
    "sg:city":"Jodoigne",
    "sg:orig_category":"Solar protection - Outside",
    "sg:phone":"+32 10 81 21 82",
    "sg:postcode":"1370",
    "sg:province":"Brabant Wallon",
    "wof:name":"Lahy M Et C Construction",
    "wof:placetype":"venue"
},
  "geometry": {"coordinates":[4.8597421646,50.7237625122],"type":"Point"}
}