{
  "type": "Feature",
  "properties": {
    "addr:full":"Diestsevest 125 Leuven Vlaams-Brabant 3000",
    "addr:housenumber":"125",
    "addr:postcode":"3000",
    "addr:street":"Diestsevest",
    "iso:country":"BE",
    "sg:address":"Diestsevest 125",
    "sg:city":"Leuven",
    "sg:orig_category":"Action sociale avec h\u00e9bergement",
    "sg:phone":"+32 16 23 59 67",
    "sg:postcode":"3000",
    "sg:province":"Vlaams-Brabant",
    "wof:name":"Halte 51",
    "wof:placetype":"venue"
},
  "geometry": {"coordinates":[4.7093830109,50.8860816956],"type":"Point"}
}