{
  "type": "Feature",
  "properties": {
    "iso:country":"BE",
    "sg:address":"Rue Des P\u00eacheries 12",
    "sg:city":"Ath (ligne)",
    "sg:classifiers":[
        {
            "category":"Home & Garden",
            "subcategory":"Building Materials",
            "type":"Retail Goods"
        }
    ],
    "sg:phone":"+32 68 28 67 38",
    "sg:postcode":"7812",
    "sg:province":"Hainaut",
    "sg:tags":[
        "veranda"
    ],
    "wof:name":"Serry F",
    "wof:placetype":"venue"
},
  "geometry": {"coordinates":[3.705190897,50.6199607849],"type":"Point"}
}