{
  "type": "Feature",
  "properties": {
    "iso:country":"BE",
    "sg:address":"Rue De L'usine 18",
    "sg:city":"Verviers",
    "sg:orig_category":"Charpentes and couvertures",
    "sg:phone":"+32 87 22 12 32",
    "sg:postcode":"4802",
    "sg:province":"Li\u00e8ge",
    "wof:name":"Jules Bolmain",
    "wof:placetype":"venue"
},
  "geometry": {"coordinates":[5.86398983,50.5770149231],"type":"Point"}
}