{
  "type": "Feature",
  "properties": {
    "addr:full":"Rue De Belle Vue 45 La Louvi\u00e8re Hainaut 7100",
    "addr:housenumber":"45",
    "addr:postcode":"7100",
    "addr:street":"Rue De Belle Vue",
    "iso:country":"BE",
    "sg:address":"Rue De Belle Vue 45",
    "sg:city":"La Louvi\u00e8re",
    "sg:classifiers":[
        {
            "category":"Home & Garden",
            "subcategory":"Household Appliances",
            "type":"Retail Goods"
        }
    ],
    "sg:phone":"+32 64 26 01 90",
    "sg:postcode":"7100",
    "sg:province":"Hainaut",
    "sg:tags":[
        "repair",
        "mainten",
        "-",
        "electric"
    ],
    "wof:name":"Bauknecht-abelec",
    "wof:placetype":"venue"
},
  "geometry": {"coordinates":[4.1878919601,50.4738540649],"type":"Point"}
}