{
  "type": "Feature",
  "properties": {
    "addr:full":"Rue Hollebeek 68 Linkebeek Vlaams-Brabant 1630",
    "addr:housenumber":"68",
    "addr:postcode":"1630",
    "addr:street":"Rue Hollebeek",
    "iso:country":"BE",
    "sg:address":"Rue Hollebeek 68",
    "sg:city":"Linkebeek",
    "sg:classifiers":[
        {
            "category":"Insurance",
            "subcategory":"Life Insurance",
            "type":"Services"
        }
    ],
    "sg:phone":"+32 2 380 68 59",
    "sg:postcode":"1630",
    "sg:province":"Vlaams-Brabant",
    "sg:tags":[
        "assurance"
    ],
    "wof:name":"Bureau Velkeneers",
    "wof:placetype":"venue"
},
  "geometry": {"coordinates":[4.3602800369,50.7635383606],"type":"Point"}
}