{
  "type": "Feature",
  "properties": {
    "addr:full":"Guffenslaan 70 Hasselt Limburg 3500",
    "addr:housenumber":"70",
    "addr:postcode":"3500",
    "addr:street":"Guffenslaan",
    "iso:country":"BE",
    "sg:address":"Guffenslaan 70",
    "sg:city":"Hasselt",
    "sg:orig_category":"Diverse zakelijke dienstverlening Fantasieartikelen Verhuur cateringmateriaal and evenementuitrustin",
    "sg:phone":"+32 11 23 18 82",
    "sg:postcode":"3500",
    "sg:province":"Limburg",
    "wof:name":"P & P Events",
    "wof:placetype":"venue"
},
  "geometry": {"coordinates":[5.341381073,50.9281768799],"type":"Point"}
}