{
  "type": "Feature",
  "properties": {
    "addr:full":"Quellinstraat 37 Antwerpen Antwerpen 2018",
    "addr:housenumber":"37",
    "addr:postcode":"2018",
    "addr:street":"Quellinstraat",
    "iso:country":"BE",
    "sg:address":"Quellinstraat 37",
    "sg:city":"Antwerpen",
    "sg:orig_category":"Agences d'exp\u00e9dition",
    "sg:phone":"+32 3 231 69 50",
    "sg:postcode":"2018",
    "sg:province":"Antwerpen",
    "wof:name":"Collchimie",
    "wof:placetype":"venue"
},
  "geometry": {"coordinates":[4.4162168503,51.2157897949],"type":"Point"}
}