{
  "type": "Feature",
  "properties": {
    "iso:country":"BE",
    "sg:address":"Appellaan 12",
    "sg:city":"Zandhoven",
    "sg:classifiers":[
        {
            "category":"Personal",
            "subcategory":"Beauty Salon",
            "type":"Services"
        }
    ],
    "sg:phone":"+32 477 85 00 13",
    "sg:postcode":"2240",
    "sg:province":"Antwerpen",
    "wof:name":"Moda Mani",
    "wof:placetype":"venue"
},
  "geometry": {"coordinates":[4.6522688866,51.2097396851],"type":"Point"}
}