{
  "type": "Feature",
  "properties": {
    "addr:full":"Rue Du Moulin 178 Florennes (morialm\u00e9) Namur 5621",
    "addr:housenumber":"178",
    "addr:postcode":"5621",
    "addr:street":"Rue Du Moulin",
    "iso:country":"BE",
    "sg:address":"Rue Du Moulin 178",
    "sg:city":"Florennes (morialm\u00e9)",
    "sg:classifiers":[
        {
            "category":"Bars & Pubs",
            "type":"Food & Drink"
        }
    ],
    "sg:phone":"+32 71 68 89 05",
    "sg:postcode":"5621",
    "sg:province":"Namur",
    "wof:name":"Esp\u00e9rance (l')",
    "wof:placetype":"venue"
},
  "geometry": {"coordinates":[4.5656957626,50.2750740051],"type":"Point"}
}