{
  "type": "Feature",
  "properties": {
    "addr:full":"Chemin Royal 5 Braine-le-comte Hainaut 7090",
    "addr:housenumber":"5",
    "addr:postcode":"7090",
    "addr:street":"Chemin Royal",
    "iso:country":"BE",
    "sg:address":"Chemin Royal 5",
    "sg:city":"Braine-le-comte",
    "sg:orig_category":"Afbraak- and draineerwerken",
    "sg:phone":"+32 67 44 30 91",
    "sg:postcode":"7090",
    "sg:province":"Hainaut",
    "wof:name":"Fabien Mabille",
    "wof:placetype":"venue"
},
  "geometry": {"coordinates":[4.1265158653,50.5686416626],"type":"Point"}
}