{
  "type": "Feature",
  "properties": {
    "iso:country":"BE",
    "sg:address":"Grote Baan 13",
    "sg:city":"Aalst",
    "sg:orig_category":"Instituts de beaut\u00e9",
    "sg:phone":"+32 53 77 76 47",
    "sg:postcode":"9310",
    "sg:province":"Oost-Vlaanderen",
    "wof:name":"Instituut Machteld",
    "wof:placetype":"venue"
},
  "geometry": {"coordinates":[4.0580821037,50.9621276855],"type":"Point"}
}