{
  "type": "Feature",
  "properties": {
    "iso:country":"BE",
    "sg:address":"Stationsstraat 85",
    "sg:city":"Oostkamp",
    "sg:orig_category":"R\u00e9parations d'appareils \u00e9lectrom\u00e9nagers. Installation \u00e9lectrique r\u00e9sidentielle. Electrom\u00e9nager, t\u00e9l\u00e9",
    "sg:phone":"+32 50 82 67 53",
    "sg:postcode":"8020",
    "sg:province":"West-Vlaanderen",
    "wof:name":"Huis Clevers",
    "wof:placetype":"venue"
},
  "geometry": {"coordinates":[3.2412118912,51.1537857056],"type":"Point"}
}