{
  "type": "Feature",
  "properties": {
    "iso:country":"BE",
    "sg:address":"Rue Du Follet 27",
    "sg:city":"Tournai (kain)",
    "sg:classifiers":[
        {
            "category":"Shopping",
            "subcategory":"Shoes",
            "type":"Retail Goods"
        }
    ],
    "sg:phone":"+32 69 22 21 17",
    "sg:postcode":"7540",
    "sg:province":"Hainaut",
    "sg:tags":[
        "slipper",
        "-"
    ],
    "wof:name":"Liliane",
    "wof:placetype":"venue"
},
  "geometry": {"coordinates":[3.4157600403,50.6289405823],"type":"Point"}
}