{
  "type": "Feature",
  "properties": {
    "iso:country":"BE",
    "sg:address":"Avenue Du Ch\u00e2teau 66",
    "sg:city":"Mouscron",
    "sg:classifiers":[
        {
            "category":"Food & Beverages",
            "subcategory":"Dairy",
            "type":"Retail Goods"
        }
    ],
    "sg:phone":"+32 56 84 06 70",
    "sg:postcode":"7700",
    "sg:province":"Hainaut",
    "sg:tags":[
        "product",
        "-"
    ],
    "wof:name":"Paradis Fermier (le)",
    "wof:placetype":"venue"
},
  "geometry": {"coordinates":[3.2279250622,50.7446899414],"type":"Point"}
}