{
  "type": "Feature",
  "properties": {
    "addr:full":"Markt 29 Lede Oost-Vlaanderen 9340",
    "addr:housenumber":"29",
    "addr:postcode":"9340",
    "addr:street":"Markt",
    "iso:country":"BE",
    "sg:address":"Markt 29",
    "sg:city":"Lede",
    "sg:orig_category":"Bijouteries and horlogeries",
    "sg:phone":"+32 53 80 55 77",
    "sg:postcode":"9340",
    "sg:province":"Oost-Vlaanderen",
    "wof:name":"Jacqueline De Ro",
    "wof:placetype":"venue"
},
  "geometry": {"coordinates":[3.9778740406,50.9665527344],"type":"Point"}
}