{
  "type": "Feature",
  "properties": {
    "iso:country":"BE",
    "sg:address":"Strijdersstraat 9",
    "sg:city":"Sint-agatha-berchem/berchem-sainte-agathe",
    "sg:orig_category":"Landmeters",
    "sg:phone":"+32 2 469 06 79",
    "sg:postcode":"1082",
    "sg:province":"Bruxelles-Capitale",
    "wof:name":"Patrick Verraes",
    "wof:placetype":"venue"
},
  "geometry": {"coordinates":[4.2958979607,50.8663024902],"type":"Point"}
}