{
  "type": "Feature",
  "properties": {
    "iso:country":"BE",
    "sg:address":"Amerikaanse Straat 174",
    "sg:city":"Elsene/ixelles",
    "sg:orig_category":"Advocaten and juridische adviseurs",
    "sg:phone":"+32 2 648 46 81",
    "sg:postcode":"1050",
    "sg:province":"Bruxelles-Capitale",
    "wof:name":"C. Delplancke",
    "wof:placetype":"venue"
},
  "geometry": {"coordinates":[4.3640298843,50.8218421936],"type":"Point"}
}