{
  "type": "Feature",
  "properties": {
    "addr:full":"Reningelstsestraat 4 Heuvelland West-Vlaanderen 8956",
    "addr:housenumber":"4",
    "addr:postcode":"8956",
    "addr:street":"Reningelstsestraat",
    "iso:country":"BE",
    "sg:address":"Reningelstsestraat 4",
    "sg:city":"Heuvelland",
    "sg:orig_category":"Herstellingen and onderhoud van auto's",
    "sg:phone":"+32 57 44 42 03",
    "sg:postcode":"8956",
    "sg:province":"West-Vlaanderen",
    "wof:name":"Garage Bossaert",
    "wof:placetype":"venue"
},
  "geometry": {"coordinates":[2.8300490379,50.7829017639],"type":"Point"}
}