{
  "type": "Feature",
  "properties": {
    "addr:full":"Marktstraat 77 Harelbeke West-Vlaanderen 8530",
    "addr:housenumber":"77",
    "addr:postcode":"8530",
    "addr:street":"Marktstraat",
    "iso:country":"BE",
    "sg:address":"Marktstraat 77",
    "sg:city":"Harelbeke",
    "sg:orig_category":"Meubelzaken, woning- and keukeninrichting",
    "sg:phone":"+32 56 71 31 97",
    "sg:postcode":"8530",
    "sg:province":"West-Vlaanderen",
    "wof:name":"Huis Salembier",
    "wof:placetype":"venue"
},
  "geometry": {"coordinates":[3.3091220856,50.8552742004],"type":"Point"}
}