{
  "type": "Feature",
  "properties": {
    "addr:full":"Place De L'octogone 15 Watermaal-bosvoorde/watermael-boitsfort Bruxelles-Capitale 1170",
    "addr:housenumber":"15",
    "addr:postcode":"1170",
    "addr:street":"Place De L'Octogone",
    "iso:country":"BE",
    "sg:address":"Place De L'octogone 15",
    "sg:city":"Watermaal-bosvoorde/watermael-boitsfort",
    "sg:orig_category":"Editeurs de livres",
    "sg:phone":"+32 2 673 87 56",
    "sg:postcode":"1170",
    "sg:province":"Bruxelles-Capitale",
    "wof:name":"Editions De L'octogone",
    "wof:placetype":"venue"
},
  "geometry": {"coordinates":[4.4098448753,50.8026885986],"type":"Point"}
}