{
  "type": "Feature",
  "properties": {
    "addr:full":"Ten Booye 16 Tielt West-Vlaanderen 8700",
    "addr:housenumber":"16",
    "addr:postcode":"8700",
    "addr:street":"Ten",
    "iso:country":"BE",
    "sg:address":"Ten Booye 16",
    "sg:city":"Tielt",
    "sg:orig_category":"Elektrische installaties voor woningen",
    "sg:phone":"+32 51 40 31 88",
    "sg:postcode":"8700",
    "sg:province":"West-Vlaanderen",
    "wof:name":"Electro B.m.",
    "wof:placetype":"venue"
},
  "geometry": {"coordinates":[3.3141100407,50.9910545349],"type":"Point"}
}