{
  "type": "Feature",
  "properties": {
    "iso:country":"BE",
    "sg:address":"Noordzandstraat 58",
    "sg:city":"Brugge",
    "sg:orig_category":"Bars. Restaurants. Restaurants",
    "sg:phone":"+32 50 34 35 05",
    "sg:postcode":"8000",
    "sg:province":"West-Vlaanderen",
    "wof:name":"Brugse Bistro",
    "wof:placetype":"venue"
},
  "geometry": {"coordinates":[3.2194240093,51.2069664001],"type":"Point"}
}