{
  "type": "Feature",
  "properties": {
    "addr:full":"Blauwe Reigerlaan 3 Wingene West-Vlaanderen 8750",
    "addr:housenumber":"3",
    "addr:postcode":"8750",
    "addr:street":"Blauwe Reigerlaan",
    "iso:country":"BE",
    "sg:address":"Blauwe Reigerlaan 3",
    "sg:city":"Wingene",
    "sg:classifiers":[
        {
            "category":"Arts & Performance",
            "subcategory":"Music",
            "type":"Entertainment"
        }
    ],
    "sg:phone":"+32 51 65 82 62",
    "sg:postcode":"8750",
    "sg:province":"West-Vlaanderen",
    "sg:tags":[
        "disc-jockeys"
    ],
    "wof:name":"Sound & Music",
    "wof:placetype":"venue"
},
  "geometry": {"coordinates":[3.2698049545,51.0541648865],"type":"Point"}
}