{
  "type": "Feature",
  "properties": {
    "iso:country":"BE",
    "sg:address":"Beverstraat 20",
    "sg:city":"Ninove",
    "sg:orig_category":"M\u00e9decins and sp\u00e9cialistes",
    "sg:phone":"+32 54 32 08 66",
    "sg:postcode":"9400",
    "sg:province":"Oost-Vlaanderen",
    "wof:name":"Dirk Van Gysel",
    "wof:placetype":"venue"
},
  "geometry": {"coordinates":[4.021777153,50.8359909058],"type":"Point"}
}