{
  "type": "Feature",
  "properties": {
    "addr:full":"Heerbaan 198 Harelbeke West-Vlaanderen 8530",
    "addr:housenumber":"198",
    "addr:postcode":"8530",
    "addr:street":"Heerbaan",
    "iso:country":"BE",
    "sg:address":"Heerbaan 198",
    "sg:city":"Harelbeke",
    "sg:classifiers":[
        {
            "category":"Travel",
            "subcategory":"Travel Agent",
            "type":"Entertainment"
        }
    ],
    "sg:phone":"+32 56 32 54 01",
    "sg:postcode":"8530",
    "sg:province":"West-Vlaanderen",
    "sg:tags":[
        "agency"
    ],
    "wof:name":"Superservice Nv",
    "wof:placetype":"venue"
},
  "geometry": {"coordinates":[3.3214030266,50.8492050171],"type":"Point"}
}