{
  "type": "Feature",
  "properties": {
    "addr:full":"Rue Antoine Dodion 10 Berloz Li\u00e8ge 4257",
    "addr:housenumber":"10",
    "addr:postcode":"4257",
    "addr:street":"Rue Antoine Dodion",
    "iso:country":"BE",
    "sg:address":"Rue Antoine Dodion 10",
    "sg:city":"Berloz",
    "sg:classifiers":[
        {
            "category":"Health Services",
            "subcategory":"Nursing And Care Facility",
            "type":"Services"
        }
    ],
    "sg:phone":"+32 19 32 61 81",
    "sg:postcode":"4257",
    "sg:province":"Li\u00e8ge",
    "sg:tags":[
        "public"
    ],
    "wof:name":"C.p.a.s.",
    "wof:placetype":"venue"
},
  "geometry": {"coordinates":[5.2111310959,50.6985473633],"type":"Point"}
}