{
  "type": "Feature",
  "properties": {
    "addr:full":"Haanhoutstraat 52 Lochristi (beervelde) Oost-Vlaanderen 9080",
    "addr:housenumber":"52",
    "addr:postcode":"9080",
    "addr:street":"Haanhoutstraat",
    "iso:country":"BE",
    "sg:address":"Haanhoutstraat 52",
    "sg:city":"Lochristi (beervelde)",
    "sg:classifiers":[
        {
            "category":"Building & Trades",
            "subcategory":"Landscaping Services",
            "type":"Services"
        }
    ],
    "sg:phone":"+32 9 355 37 37",
    "sg:postcode":"9080",
    "sg:province":"Oost-Vlaanderen",
    "sg:tags":[
        "nurseryman"
    ],
    "wof:name":"Florarbo Bvba",
    "wof:placetype":"venue"
},
  "geometry": {"coordinates":[3.8650240898,51.0796508789],"type":"Point"}
}