{
  "type": "Feature",
  "properties": {
    "iso:country":"BE",
    "sg:address":"Kloosterstraat 23bc",
    "sg:city":"Herenthout",
    "sg:orig_category":"Diverse organisaties and verenigingen",
    "sg:phone":"+32 14 50 27 29",
    "sg:postcode":"2270",
    "sg:province":"Antwerpen",
    "wof:name":"Jeugdhuis \u00b4t Verschil",
    "wof:placetype":"venue"
},
  "geometry": {"coordinates":[4.7564029694,51.1369132996],"type":"Point"}
}