{
  "type": "Feature",
  "properties": {
    "addr:full":"Esplanade Bruxelles Bruxelles-Capitale 1020",
    "addr:postcode":"1020",
    "addr:street":"Esplanade",
    "iso:country":"BE",
    "sg:address":"Esplanade",
    "sg:city":"Bruxelles",
    "sg:classifiers":[
        {
            "category":"Education",
            "subcategory":"Special Training",
            "type":"Public Place"
        }
    ],
    "sg:phone":"+32 2 476 16 76",
    "sg:postcode":"1020",
    "sg:province":"Bruxelles-Capitale",
    "sg:tags":[
        "professional"
    ],
    "wof:name":"Vormelek",
    "wof:placetype":"venue"
},
  "geometry": {"coordinates":[4.3433609009,50.9003372192],"type":"Point"}
}