{
  "type": "Feature",
  "properties": {
    "addr:full":"Paenhuisstraat 30 Riemst Limburg 3770",
    "addr:housenumber":"30",
    "addr:postcode":"3770",
    "addr:street":"Paenhuisstraat",
    "iso:country":"BE",
    "sg:address":"Paenhuisstraat 30",
    "sg:city":"Riemst",
    "sg:classifiers":[
        {
            "category":"Building & Trades",
            "subcategory":"Cleaning & Sanitation",
            "type":"Services"
        }
    ],
    "sg:phone":"+32 12 45 26 04",
    "sg:postcode":"3770",
    "sg:province":"Limburg",
    "sg:tags":[
        "blast"
    ],
    "wof:name":"Rubens J & A",
    "wof:placetype":"venue"
},
  "geometry": {"coordinates":[5.6066560745,50.8102149963],"type":"Point"}
}