{
  "type": "Feature",
  "properties": {
    "iso:country":"BE",
    "sg:address":"Briahan 34",
    "sg:city":"Bouillon",
    "sg:orig_category":"Rundveehouders",
    "sg:phone":"+32 61 46 68 76",
    "sg:postcode":"6832",
    "sg:province":"Luxembourg",
    "wof:name":"Gaston Demoulin",
    "wof:placetype":"venue"
},
  "geometry": {"coordinates":[5.0727958679,49.8251419067],"type":"Point"}
}