{
  "type": "Feature",
  "properties": {
    "addr:full":"Houtemstraat 68 Herzele Oost-Vlaanderen 9550",
    "addr:housenumber":"68",
    "addr:postcode":"9550",
    "addr:street":"Houtemstraat;Oost-Vlaanderen",
    "iso:country":"BE",
    "sg:address":"Houtemstraat 68",
    "sg:city":"Herzele",
    "sg:classifiers":[
        {
            "category":"Real Estate",
            "subcategory":"Surveying",
            "type":"Services"
        }
    ],
    "sg:phone":"+32 53 62 86 74",
    "sg:postcode":"9550",
    "sg:province":"Oost-Vlaanderen",
    "sg:tags":[
        "surveyor",
        "land"
    ],
    "wof:name":"Meersschaut W",
    "wof:placetype":"venue"
},
  "geometry": {"coordinates":[3.8747150898,50.9040260315],"type":"Point"}
}