{
  "type": "Feature",
  "properties": {
    "addr:full":"Rue De Tournai 19 Moeskroen/mouscron Hainaut 7700",
    "addr:housenumber":"19",
    "addr:postcode":"7700",
    "addr:street":"Rue De Tournai",
    "iso:country":"BE",
    "sg:address":"Rue De Tournai 19",
    "sg:city":"Moeskroen/mouscron",
    "sg:orig_category":"V\u00eatements de mariage and c\u00e9r\u00e9monies. Pain, p\u00e2tisseries and confiseries. V\u00eatements pour Dames",
    "sg:phone":"+32 56 33 02 22",
    "sg:postcode":"7700",
    "sg:province":"Hainaut",
    "wof:name":"Les Mari\u00c9es De Caroline",
    "wof:placetype":"venue"
},
  "geometry": {"coordinates":[3.2323200703,50.7400932312],"type":"Point"}
}