{
  "type": "Feature",
  "properties": {
    "iso:country":"BE",
    "sg:address":"Chauss\u00e9e De Marche 390",
    "sg:city":"Namur (jambes)",
    "sg:classifiers":[
        {
            "category":"Health Services",
            "subcategory":"Health Practitioner",
            "type":"Services"
        }
    ],
    "sg:phone":"+32 81 30 81 82",
    "sg:postcode":"5100",
    "sg:province":"Namur",
    "sg:tags":[
        "dietitian"
    ],
    "wof:name":"Li\u00e9geois G",
    "wof:placetype":"venue"
},
  "geometry": {"coordinates":[4.8713750839,50.4566345215],"type":"Point"}
}