{
  "type": "Feature",
  "properties": {
    "addr:full":"Rue De La Ferme Du Pr\u00e9 14 Ittre (haut-ittre) Brabant Wallon 1461",
    "addr:housenumber":"14;1461",
    "addr:street":"Rue De La Ferme Du Pre\u0301",
    "iso:country":"BE",
    "sg:address":"Rue De La Ferme Du Pr\u00e9 14",
    "sg:city":"Ittre (haut-ittre)",
    "sg:classifiers":[
        {
            "category":"Building & Trades",
            "subcategory":"Construction",
            "type":"Services"
        }
    ],
    "sg:phone":"+32 67 21 83 12",
    "sg:postcode":"1461",
    "sg:province":"Brabant Wallon",
    "sg:tags":[
        "carpenter"
    ],
    "wof:name":"Daenen J",
    "wof:placetype":"venue"
},
  "geometry": {"coordinates":[4.3047242165,50.6457481384],"type":"Point"}
}