{
  "type": "Feature",
  "properties": {
    "iso:country":"BE",
    "sg:address":"Hendrik Van Veldekesingel 150 Box 20",
    "sg:city":"Hasselt",
    "sg:classifiers":[
        {
            "category":"Social Services",
            "subcategory":"Job Training",
            "type":"Services"
        }
    ],
    "sg:phone":"+32 11 87 08 43",
    "sg:postcode":"3500",
    "sg:province":"Limburg",
    "sg:tags":[
        "personnel",
        "-selection",
        "recruitment"
    ],
    "wof:name":"Thema Group Search & Selection Bvba",
    "wof:placetype":"venue"
},
  "geometry": {"coordinates":[5.3152570724,50.9355430603],"type":"Point"}
}