{
  "type": "Feature",
  "properties": {
    "iso:country":"BE",
    "sg:address":"Jan Goovaersstraat 16",
    "sg:city":"Borsbeek",
    "sg:orig_category":"Landmeters",
    "sg:phone":"+32 3 321 44 04",
    "sg:postcode":"2150",
    "sg:province":"Antwerpen",
    "wof:name":"Jozef Mortelmans",
    "wof:placetype":"venue"
},
  "geometry": {"coordinates":[4.4902291298,51.1935386658],"type":"Point"}
}