{
  "type": "Feature",
  "properties": {
    "addr:full":"Eeckhoutstraat 36 Aalst Oost-Vlaanderen 9310",
    "addr:housenumber":"36",
    "addr:postcode":"9310",
    "addr:street":"Eeckhoutstraat",
    "iso:country":"BE",
    "sg:address":"Eeckhoutstraat 36",
    "sg:city":"Aalst",
    "sg:orig_category":"Eleveurs and marchands de porcs",
    "sg:phone":"+32 2 452 88 49",
    "sg:postcode":"9310",
    "sg:province":"Oost-Vlaanderen",
    "wof:name":"Albertus Nuelant",
    "wof:placetype":"venue"
},
  "geometry": {"coordinates":[4.1359257698,50.9260025024],"type":"Point"}
}