{
  "type": "Feature",
  "properties": {
    "iso:country":"BE",
    "sg:address":"Ellestraat 1bb",
    "sg:city":"Zwevegem",
    "sg:classifiers":[
        {
            "category":"Shopping",
            "subcategory":"Clothing, Apparel, & Fashions",
            "type":"Retail Goods"
        }
    ],
    "sg:phone":"+32 56 75 45 65",
    "sg:postcode":"8550",
    "sg:province":"West-Vlaanderen",
    "sg:tags":[
        "v\u00eatements",
        "pour",
        "dame"
    ],
    "wof:name":"Servitex",
    "wof:placetype":"venue"
},
  "geometry": {"coordinates":[3.3397419453,50.8105392456],"type":"Point"}
}