{
  "type": "Feature",
  "properties": {
    "iso:country":"BE",
    "sg:address":"Itali\u00eblaan 14",
    "sg:city":"Geel",
    "sg:classifiers":[
        {
            "category":"Health Services",
            "subcategory":"Doctor",
            "type":"Services"
        }
    ],
    "sg:phone":"+32 14 58 12 30",
    "sg:postcode":"2440",
    "sg:province":"Antwerpen",
    "sg:tags":[
        "medicinephysicians",
        "surgeon"
    ],
    "wof:name":"Deraemaeker C",
    "wof:placetype":"venue"
},
  "geometry": {"coordinates":[5.0376272202,51.1888198853],"type":"Point"}
}