{
  "type": "Feature",
  "properties": {
    "iso:country":"BE",
    "sg:address":"Avenue R. Vandendriessche 23",
    "sg:city":"Sint-pieters-woluwe/woluwe-sai",
    "sg:orig_category":"Gestion de media publicitaires",
    "sg:phone":"+32 2 763 09 12",
    "sg:postcode":"1150",
    "sg:province":"Bruxelles-Capitale",
    "wof:name":"Advertising Outdoor Consultant",
    "wof:placetype":"venue"
},
  "geometry": {"coordinates":[4.413831234,50.8340492249],"type":"Point"}
}