{
  "type": "Feature",
  "properties": {
    "iso:country":"BE",
    "sg:address":"Rue Norbert Ponlot 17",
    "sg:city":"Gembloux-sur-orneau (gembloux)",
    "sg:classifiers":[
        {
            "category":"Banks & Credit Unions",
            "subcategory":"Investment Brokerage",
            "type":"Services"
        }
    ],
    "sg:phone":"+32 81 61 07 84",
    "sg:postcode":"5030",
    "sg:province":"Namur",
    "sg:tags":[
        "printing",
        "-"
    ],
    "wof:name":"Danel Ferry",
    "wof:placetype":"venue"
},
  "geometry": {"coordinates":[4.7244949341,50.5446891785],"type":"Point"}
}