{
  "type": "Feature",
  "properties": {
    "addr:full":"Rue Droits De L'homme 34 Morlanwelz Hainaut 7140",
    "addr:housenumber":"34",
    "addr:postcode":"7140",
    "addr:street":"Rue Droits De L'Homme",
    "iso:country":"BE",
    "sg:address":"Rue Droits De L'homme 34",
    "sg:city":"Morlanwelz",
    "sg:orig_category":"Boissons",
    "sg:phone":"+32 64 45 01 25",
    "sg:postcode":"7140",
    "sg:province":"Hainaut",
    "wof:name":"Drive-in Antoine",
    "wof:placetype":"venue"
},
  "geometry": {"coordinates":[4.2295589447,50.4621772766],"type":"Point"}
}