{
  "type": "Feature",
  "properties": {
    "addr:full":"Uitspanningstraat 2 Antwerpen (wilrijk) Antwerpen 2610",
    "addr:housenumber":"2",
    "addr:postcode":"2610",
    "addr:street":"Uitspanningstraat;Antwerpen",
    "iso:country":"BE",
    "sg:address":"Uitspanningstraat 2",
    "sg:city":"Antwerpen (wilrijk)",
    "sg:classifiers":[
        {
            "category":"Professional",
            "subcategory":"Advertising",
            "type":"Services"
        }
    ],
    "sg:phone":"+32 3 828 51 75",
    "sg:postcode":"2610",
    "sg:province":"Antwerpen",
    "sg:tags":[
        "item",
        "-",
        "business",
        "gift",
        "promotional"
    ],
    "wof:name":"Good News Bvba",
    "wof:placetype":"venue"
},
  "geometry": {"coordinates":[4.3946051598,51.1691131592],"type":"Point"}
}