{
  "type": "Feature",
  "properties": {
    "addr:full":"Boulevard Du Roi Albert 106bb4 Tournai Hainaut 7500",
    "addr:postcode":"7500",
    "addr:street":"Boulevard Du Roi Albert 106Bb4;Hainaut",
    "iso:country":"BE",
    "sg:address":"Boulevard Du Roi Albert 106bb4",
    "sg:city":"Tournai",
    "sg:orig_category":"Artsen and specialisten",
    "sg:phone":"+32 69 23 22 06",
    "sg:postcode":"7500",
    "sg:province":"Hainaut",
    "wof:name":"Gilbert Decostre",
    "wof:placetype":"venue"
},
  "geometry": {"coordinates":[3.3914721012,50.6006469727],"type":"Point"}
}