{
  "type": "Feature",
  "properties": {
    "addr:full":"Avenue Des Volontaires 323 Sint-pieters-woluwe/woluwe-saint-pierre Bruxelles-Capitale 1150",
    "addr:housenumber":"323",
    "addr:postcode":"1150",
    "addr:street":"Avenue Des Volontaires;/",
    "iso:country":"BE",
    "sg:address":"Avenue Des Volontaires 323",
    "sg:city":"Sint-pieters-woluwe/woluwe-saint-pierre",
    "sg:orig_category":"M\u00e9decins and sp\u00e9cialistes",
    "sg:phone":"+32 2 762 02 89",
    "sg:postcode":"1150",
    "sg:province":"Bruxelles-Capitale",
    "wof:name":"Olivier Vermylen",
    "wof:placetype":"venue"
},
  "geometry": {"coordinates":[4.4107680321,50.8297386169],"type":"Point"}
}