{
  "type": "Feature",
  "properties": {
    "addr:full":"Rue Walth\u00c8re Jamar 145 Ans Li\u00e8ge 4430",
    "addr:housenumber":"145",
    "addr:postcode":"4430",
    "addr:street":"Rue Walthe\u0300Re Jamar",
    "iso:country":"BE",
    "sg:address":"Rue Walth\u00c8re Jamar 145",
    "sg:city":"Ans",
    "sg:orig_category":"Salons de coiffure. Centres de relaxation and bien-\u00eatre",
    "sg:phone":"+32 4 226 29 80",
    "sg:postcode":"4430",
    "sg:province":"Li\u00e8ge",
    "wof:name":"Coiff'mod",
    "wof:placetype":"venue"
},
  "geometry": {"coordinates":[5.5401268005,50.6524047852],"type":"Point"}
}