{
  "type": "Feature",
  "properties": {
    "addr:full":"Heymanslaan 15 Gent Oost-Vlaanderen 9000",
    "addr:housenumber":"15",
    "addr:postcode":"9000",
    "addr:street":"Heymanslaan;Oost-Vlaanderen",
    "iso:country":"BE",
    "sg:address":"Heymanslaan 15",
    "sg:city":"Gent",
    "sg:orig_category":"Chaussures",
    "sg:phone":"+32 9 221 13 33",
    "sg:postcode":"9000",
    "sg:province":"Oost-Vlaanderen",
    "wof:name":"Primo",
    "wof:placetype":"venue"
},
  "geometry": {"coordinates":[3.7271580696,51.0272445679],"type":"Point"}
}