{
  "type": "Feature",
  "properties": {
    "iso:country":"BE",
    "sg:address":"Rue L\u00e9on Colleaux 39",
    "sg:city":"Virton (saint-mard)",
    "sg:classifiers":[
        {
            "category":"Bars & Pubs",
            "type":"Food & Drink"
        }
    ],
    "sg:phone":"+32 63 57 78 18",
    "sg:postcode":"6762",
    "sg:province":"Luxembourg",
    "wof:name":"Midi (du)",
    "wof:placetype":"venue"
},
  "geometry": {"coordinates":[5.5325450897,49.5549507141],"type":"Point"}
}