{
  "type": "Feature",
  "properties": {
    "iso:country":"BE",
    "sg:address":"Brugsestraat 80",
    "sg:city":"Zedelgem (aartrijke)",
    "sg:classifiers":[
        {
            "category":"Bars & Pubs",
            "type":"Food & Drink"
        }
    ],
    "sg:phone":"+32 50 20 93 47",
    "sg:postcode":"8211",
    "sg:province":"West-Vlaanderen",
    "wof:name":"Welkom",
    "wof:placetype":"venue"
},
  "geometry": {"coordinates":[3.0889649391,51.1200408936],"type":"Point"}
}