{
  "type": "Feature",
  "properties": {
    "addr:full":"Rue De La Filature 33 Mons (obourg) Hainaut 7034",
    "addr:housenumber":"33",
    "addr:postcode":"7034",
    "addr:street":"Rue De La Filature",
    "iso:country":"BE",
    "sg:address":"Rue De La Filature 33",
    "sg:city":"Mons (obourg)",
    "sg:classifiers":[
        {
            "category":"Home & Garden",
            "subcategory":"Building Materials",
            "type":"Retail Goods"
        }
    ],
    "sg:postcode":"7034",
    "sg:province":"Hainaut",
    "sg:tags":[
        "window"
    ],
    "wof:name":"Boursier (ets)",
    "wof:placetype":"venue"
},
  "geometry": {"coordinates":[4.0086159706,50.4765396118],"type":"Point"}
}