{
  "type": "Feature",
  "properties": {
    "iso:country":"BE",
    "sg:address":"Stationsstraat 28",
    "sg:city":"Kluisbergen",
    "sg:orig_category":"M\u00e9decins and sp\u00e9cialistes",
    "sg:phone":"+32 55 38 81 60",
    "sg:postcode":"9690",
    "sg:province":"Oost-Vlaanderen",
    "wof:name":"Marleen De Nys",
    "wof:placetype":"venue"
},
  "geometry": {"coordinates":[3.5098559856,50.7897033691],"type":"Point"}
}