{
  "type": "Feature",
  "properties": {
    "iso:country":"BE",
    "sg:address":"Douvieweg 14",
    "sg:city":"Poperinge",
    "sg:orig_category":"Maisons de repos and r\u00e9sidences",
    "sg:phone":"+32 57 38 80 28",
    "sg:postcode":"8978",
    "sg:province":"West-Vlaanderen",
    "wof:name":"Rusthuis De Eeuwige Lente",
    "wof:placetype":"venue"
},
  "geometry": {"coordinates":[2.6206049919,50.8592453003],"type":"Point"}
}