{
  "type": "Feature",
  "properties": {
    "iso:country":"BE",
    "sg:address":"Rue Chainisse 50",
    "sg:city":"Gembloux",
    "sg:orig_category":"R\u00e9cup\u00e9ration de mati\u00e8res m\u00e9talliques recyclables and d\u00e9molisseurs de voitures",
    "sg:phone":"+32 81 56 91 08",
    "sg:postcode":"5030",
    "sg:province":"Namur",
    "wof:name":"Thierry Croes",
    "wof:placetype":"venue"
},
  "geometry": {"coordinates":[4.7456321716,50.5298271179],"type":"Point"}
}