{
  "type": "Feature",
  "properties": {
    "addr:full":"Vlasmarkt 15 Kortrijk West-Vlaanderen 8500",
    "addr:housenumber":"15",
    "addr:postcode":"8500",
    "addr:street":"Vlasmarkt",
    "iso:country":"BE",
    "sg:address":"Vlasmarkt 15",
    "sg:city":"Kortrijk",
    "sg:classifiers":[
        {
            "category":"Personal",
            "subcategory":"Beauty Salon",
            "type":"Services"
        }
    ],
    "sg:phone":"+32 479 28 09 70",
    "sg:postcode":"8500",
    "sg:province":"West-Vlaanderen",
    "sg:tags":[
        "lady",
        "-",
        "hairdressing"
    ],
    "wof:name":"Miss V's Boutique",
    "wof:placetype":"venue"
},
  "geometry": {"coordinates":[3.2683150768,50.8257331848],"type":"Point"}
}