{
  "type": "Feature",
  "properties": {
    "iso:country":"BE",
    "sg:address":"Rue De La Maladr\u00c9e 36",
    "sg:city":"La Louvi\u00c8re",
    "sg:orig_category":"Medische apparatuur, orthopedische artikelen and prothesen Fab",
    "sg:phone":"+32 64 21 28 57",
    "sg:postcode":"7110",
    "sg:province":"Hainaut",
    "wof:name":"Staquet",
    "wof:placetype":"venue"
},
  "geometry": {"coordinates":[4.1505050659,50.4826698303],"type":"Point"}
}