{
  "type": "Feature",
  "properties": {
    "iso:country":"BE",
    "sg:address":"Capucienenstraat 87",
    "sg:city":"Ieper",
    "sg:classifiers":[
        {
            "category":"Restaurant",
            "type":"Food & Drink"
        }
    ],
    "sg:phone":"+32 57 20 44 94",
    "sg:postcode":"8900",
    "sg:province":"West-Vlaanderen",
    "wof:name":"Rallye Grill",
    "wof:placetype":"venue"
},
  "geometry": {"coordinates":[2.8689329624,50.8456573486],"type":"Point"}
}