{
  "type": "Feature",
  "properties": {
    "addr:full":"Vanderkinderestraat 151 Ukkel Bruxelles-Capitale 1180",
    "addr:housenumber":"151",
    "addr:postcode":"1180",
    "addr:street":"Vanderkinderestraat",
    "iso:country":"BE",
    "sg:address":"Vanderkinderestraat 151",
    "sg:city":"Ukkel",
    "sg:orig_category":"Boucheries",
    "sg:phone":"+32 2 344 01 50",
    "sg:postcode":"1180",
    "sg:province":"Bruxelles-Capitale",
    "wof:name":"Boucherie Saint-antoine",
    "wof:placetype":"venue"
},
  "geometry": {"coordinates":[4.3485388756,50.8137626648],"type":"Point"}
}