{
  "type": "Feature",
  "properties": {
    "iso:country":"BE",
    "sg:address":"Ledestraat 61",
    "sg:city":"Assenede",
    "sg:orig_category":"Gespecialiseerde residenti\u00eble bouw Woningbouw",
    "sg:phone":"+32 9 373 80 81",
    "sg:postcode":"9968",
    "sg:province":"Oost-Vlaanderen",
    "wof:name":"Bouwonderneming Vadeko",
    "wof:placetype":"venue"
},
  "geometry": {"coordinates":[3.6620268822,51.1873931885],"type":"Point"}
}