{
  "type": "Feature",
  "properties": {
    "addr:full":"Rue Des Bergeries 9 Erquelinnes (bersillies - L'abbaye) Hainaut 6560",
    "addr:housenumber":"9",
    "addr:postcode":"6560",
    "addr:street":"Rue Des Bergeries",
    "iso:country":"BE",
    "sg:address":"Rue Des Bergeries 9",
    "sg:city":"Erquelinnes (bersillies - L'abbaye)",
    "sg:classifiers":[
        {
            "category":"Building & Trades",
            "subcategory":"Electrical",
            "type":"Services"
        }
    ],
    "sg:phone":"+32 71 58 88 50",
    "sg:postcode":"6560",
    "sg:province":"Hainaut",
    "sg:tags":[
        "electric",
        "-",
        "housewiring",
        "contractor"
    ],
    "wof:name":"Lima Y",
    "wof:placetype":"venue"
},
  "geometry": {"coordinates":[4.1448869705,50.2599334717],"type":"Point"}
}