{
  "type": "Feature",
  "properties": {
    "addr:full":"Hendrik Consciencestraat 4 Kortrijk West-Vlaanderen 8500",
    "addr:housenumber":"4",
    "addr:postcode":"8500",
    "addr:street":"Hendrik Consciencestraat",
    "iso:country":"BE",
    "sg:address":"Hendrik Consciencestraat 4",
    "sg:city":"Kortrijk",
    "sg:classifiers":[
        {
            "category":"Professional",
            "subcategory":"Accounting & Tax Preparation",
            "type":"Services"
        }
    ],
    "sg:phone":"+32 56 26 05 65",
    "sg:postcode":"8500",
    "sg:province":"West-Vlaanderen",
    "sg:tags":[
        "accountant"
    ],
    "wof:name":"Van Praet Chr",
    "wof:placetype":"venue"
},
  "geometry": {"coordinates":[3.2598049641,50.8267593384],"type":"Point"}
}