{
  "type": "Feature",
  "properties": {
    "addr:full":"Albertstraat 11 Blankenberge West-Vlaanderen 8370",
    "addr:housenumber":"11",
    "addr:postcode":"8370",
    "addr:street":"Albertstraat",
    "iso:country":"BE",
    "sg:address":"Albertstraat 11",
    "sg:city":"Blankenberge",
    "sg:orig_category":"Avocats and conseillers juridiques",
    "sg:phone":"+32 50 41 03 08",
    "sg:postcode":"8370",
    "sg:province":"West-Vlaanderen",
    "wof:name":"Sabrina Claessens",
    "wof:placetype":"venue"
},
  "geometry": {"coordinates":[3.1307430267,51.3156394958],"type":"Point"}
}