{
  "type": "Feature",
  "properties": {
    "addr:full":"Rue De La Croix De Fer 9 Brussel/bruxelles Bruxelles-Capitale 1000",
    "addr:housenumber":"9",
    "addr:postcode":"1000",
    "addr:street":"Rue De La Croix De Fer;/",
    "iso:country":"BE",
    "sg:address":"Rue De La Croix De Fer 9",
    "sg:city":"Brussel/bruxelles",
    "sg:orig_category":"Fleurs and plantes",
    "sg:phone":"+32 2 511 83 77",
    "sg:postcode":"1000",
    "sg:province":"Bruxelles-Capitale",
    "wof:name":"Palette Fleurie",
    "wof:placetype":"venue"
},
  "geometry": {"coordinates":[4.3636779785,50.8477592468],"type":"Point"}
}