{
  "type": "Feature",
  "properties": {
    "iso:country":"BE",
    "sg:address":"Collegestraat 11",
    "sg:city":"Mol",
    "sg:classifiers":[
        {
            "category":"Building & Trades",
            "subcategory":"Landscaping Services",
            "type":"Services"
        }
    ],
    "sg:phone":"+32 14 70 08 40",
    "sg:postcode":"2400",
    "sg:province":"Antwerpen",
    "sg:tags":[
        "architect",
        "landscape"
    ],
    "wof:name":"Valgaeren J",
    "wof:placetype":"venue"
},
  "geometry": {"coordinates":[5.1124930382,51.1866760254],"type":"Point"}
}