{
  "type": "Feature",
  "properties": {
    "addr:full":"Meerstraat 5 Leuven (wijgmaal) Vlaams-Brabant 3018",
    "addr:housenumber":"5",
    "addr:postcode":"3018",
    "addr:street":"Meerstraat",
    "iso:country":"BE",
    "sg:address":"Meerstraat 5",
    "sg:city":"Leuven (wijgmaal)",
    "sg:classifiers":[
        {
            "category":"Personal",
            "subcategory":"Nail Salon",
            "type":"Services"
        }
    ],
    "sg:phone":"+32 16 44 30 35",
    "sg:postcode":"3018",
    "sg:province":"Vlaams-Brabant",
    "sg:tags":[
        "pedicure"
    ],
    "wof:name":"Dupont Chris",
    "wof:placetype":"venue"
},
  "geometry": {"coordinates":[4.6888628006,50.9350204468],"type":"Point"}
}