{
  "type": "Feature",
  "properties": {
    "addr:full":"Square Cr\u00c9pin 20 Rochefort Namur 5580",
    "addr:housenumber":"20",
    "addr:postcode":"5580",
    "addr:street":"Square Cre\u0301Pin",
    "iso:country":"BE",
    "sg:address":"Square Cr\u00c9pin 20",
    "sg:city":"Rochefort",
    "sg:orig_category":"HERSTELLING ELEKTRISCHE HUISHOUDAPPARATEN Huishoudapparaten, televisies and radio's",
    "sg:phone":"+32 84 21 21 40",
    "sg:postcode":"5580",
    "sg:province":"Namur",
    "wof:name":"Maison Rase",
    "wof:placetype":"venue"
},
  "geometry": {"coordinates":[5.2202558517,50.1576156616],"type":"Point"}
}