{
  "type": "Feature",
  "properties": {
    "addr:full":"Steenstraat 70 Zedelgem (aartrijke) West-Vlaanderen 8211",
    "addr:housenumber":"70",
    "addr:postcode":"8211",
    "addr:street":"Steenstraat",
    "iso:country":"BE",
    "sg:address":"Steenstraat 70",
    "sg:city":"Zedelgem (aartrijke)",
    "sg:classifiers":[
        {
            "category":"Farming",
            "subcategory":"Livestock Farm",
            "type":"Manufacturing & Wholesale Goods"
        }
    ],
    "sg:phone":"+32 50 20 90 54",
    "sg:postcode":"8211",
    "sg:province":"West-Vlaanderen",
    "sg:tags":[
        "buyer"
    ],
    "wof:name":"Lanssens",
    "wof:placetype":"venue"
},
  "geometry": {"coordinates":[3.0802819729,51.1117973328],"type":"Point"}
}