{
  "type": "Feature",
  "properties": {
    "iso:country":"BE",
    "sg:address":"Heirbaan 53",
    "sg:city":"Lanaken (neerharen)",
    "sg:classifiers":[
        {
            "category":"Health Services",
            "subcategory":"Doctor",
            "type":"Services"
        }
    ],
    "sg:phone":"+32 89 72 12 36",
    "sg:postcode":"3620",
    "sg:province":"Limburg",
    "sg:tags":[
        "psychotherapist",
        "psychoanalyst"
    ],
    "wof:name":"Stegen M-c",
    "wof:placetype":"venue"
},
  "geometry": {"coordinates":[5.6840538979,50.906463623],"type":"Point"}
}