{
  "type": "Feature",
  "properties": {
    "iso:country":"BE",
    "sg:address":"Rue De Wergifosse 172",
    "sg:city":"Soumagne",
    "sg:orig_category":"Traitement and rev\u00eatement des m\u00e9taux",
    "sg:phone":"+32 4 377 50 15",
    "sg:postcode":"4630",
    "sg:province":"Li\u00e8ge",
    "wof:name":"Acde",
    "wof:placetype":"venue"
},
  "geometry": {"coordinates":[5.7574567795,50.6312446594],"type":"Point"}
}