{
  "type": "Feature",
  "properties": {
    "addr:full":"Rue De Boussoit 46 La Louviere Hainaut 7110",
    "addr:housenumber":"46",
    "addr:postcode":"7110",
    "addr:street":"Rue De Boussoit",
    "iso:country":"BE",
    "sg:address":"Rue De Boussoit 46",
    "sg:city":"La Louviere",
    "sg:classifiers":[
        {
            "category":"Personal",
            "subcategory":"Beauty Salon",
            "type":"Services"
        }
    ],
    "sg:phone":"+32 64 66 40 95",
    "sg:postcode":"7110",
    "sg:province":"Hainaut",
    "sg:tags":[
        "de",
        "coiffure"
    ],
    "wof:name":"Concettina Maniglia",
    "wof:placetype":"venue"
},
  "geometry": {"coordinates":[4.1505050659,50.4826698303],"type":"Point"}
}