{
  "type": "Feature",
  "properties": {
    "addr:full":"Aarschotsesteenweg 320 Leuven (wilsele) Vlaams-Brabant 3012",
    "addr:housenumber":"320",
    "addr:postcode":"3012",
    "addr:street":"Aarschotsesteenweg",
    "iso:country":"BE",
    "sg:address":"Aarschotsesteenweg 320",
    "sg:city":"Leuven (wilsele)",
    "sg:classifiers":[
        {
            "category":"Retail",
            "subcategory":"Auto Repair",
            "type":"Services"
        }
    ],
    "sg:phone":"+32 476 47 52 27",
    "sg:postcode":"3012",
    "sg:province":"Vlaams-Brabant",
    "sg:tags":[
        "automobile-body"
    ],
    "wof:name":"Servranckx E",
    "wof:placetype":"venue"
},
  "geometry": {"coordinates":[4.7136130333,50.9103507996],"type":"Point"}
}