{
  "type": "Feature",
  "properties": {
    "addr:full":"Zoetenberm 26 Beveren Oost-Vlaanderen 9130",
    "addr:housenumber":"26",
    "addr:postcode":"9130",
    "addr:street":"Zoetenberm",
    "iso:country":"BE",
    "sg:address":"Zoetenberm 26",
    "sg:city":"Beveren",
    "sg:orig_category":"Eleveurs and marchands de porcs",
    "sg:phone":"+32 3 773 52 78",
    "sg:postcode":"9130",
    "sg:province":"Oost-Vlaanderen",
    "wof:name":"Robby De Bock",
    "wof:placetype":"venue"
},
  "geometry": {"coordinates":[4.2290358543,51.3166351318],"type":"Point"}
}