{
  "type": "Feature",
  "properties": {
    "iso:country":"BE",
    "sg:address":"Rue Emile Vandervelde 338",
    "sg:city":"Fontaine-l'ev\u00eaque (forchies-la-marche)",
    "sg:classifiers":[
        {
            "category":"Health Services",
            "subcategory":"Health Practitioner",
            "type":"Services"
        }
    ],
    "sg:phone":"+32 71 52 97 31",
    "sg:postcode":"6141",
    "sg:province":"Hainaut",
    "sg:tags":[
        "psychologist"
    ],
    "wof:name":"Foucart P",
    "wof:placetype":"venue"
},
  "geometry": {"coordinates":[-111.9644622803,46.2507972717],"type":"Point"}
}