{
  "type": "Feature",
  "properties": {
    "addr:full":"Fazantweg 21 Lier Antwerpen 2500",
    "addr:housenumber":"21",
    "addr:postcode":"2500",
    "addr:street":"Fazantweg",
    "iso:country":"BE",
    "sg:address":"Fazantweg 21",
    "sg:city":"Lier",
    "sg:orig_category":"Rev\u00eatements pour sols and murs. Peinture",
    "sg:phone":"+32 3 480 37 75",
    "sg:postcode":"2500",
    "sg:province":"Antwerpen",
    "wof:name":"Nobel",
    "wof:placetype":"venue"
},
  "geometry": {"coordinates":[4.6010069847,51.1458778381],"type":"Point"}
}