{
  "type": "Feature",
  "properties": {
    "addr:full":"Bierbeekstraat 4 Oud-heverlee Vlaams-Brabant 3052",
    "addr:housenumber":"4",
    "addr:postcode":"3052",
    "addr:street":"Bierbeekstraat",
    "iso:country":"BE",
    "sg:address":"Bierbeekstraat 4",
    "sg:city":"Oud-heverlee",
    "sg:orig_category":"Enseignement maternel and primaire",
    "sg:phone":"+32 16 40 08 06",
    "sg:postcode":"3052",
    "sg:province":"Vlaams-Brabant",
    "wof:name":"Gemeentel. Lagere School",
    "wof:placetype":"venue"
},
  "geometry": {"coordinates":[4.7039570808,50.8258399963],"type":"Point"}
}