{
  "type": "Feature",
  "properties": {
    "iso:country":"BE",
    "sg:address":"Berkenstraat 53",
    "sg:city":"Houthalen-helchteren (houthalen)",
    "sg:classifiers":[
        {
            "category":"Building & Trades",
            "subcategory":"Plumbing",
            "type":"Services"
        }
    ],
    "sg:phone":"+32 89 38 61 61",
    "sg:postcode":"3530",
    "sg:province":"Limburg",
    "sg:tags":[
        "repair",
        "mainten",
        "-",
        "central",
        "heating"
    ],
    "wof:name":"Wets G",
    "wof:placetype":"venue"
},
  "geometry": {"coordinates":[5.4674901962,51.0307044983],"type":"Point"}
}