{
  "type": "Feature",
  "properties": {
    "addr:full":"Witte Gracht 105 Heist-op-den-berg Antwerpen 2222",
    "addr:housenumber":"105",
    "addr:postcode":"2222",
    "addr:street":"Witte Gracht",
    "iso:country":"BE",
    "sg:address":"Witte Gracht 105",
    "sg:city":"Heist-op-den-berg",
    "sg:orig_category":"Woningbouw",
    "sg:phone":"+32 14 26 00 14",
    "sg:postcode":"2222",
    "sg:province":"Antwerpen",
    "wof:name":"Beenens Edmond",
    "wof:placetype":"venue"
},
  "geometry": {"coordinates":[4.7292399406,51.1032218933],"type":"Point"}
}