{
  "type": "Feature",
  "properties": {
    "iso:country":"BE",
    "sg:address":"Pontstraat 70",
    "sg:city":"Aalst",
    "sg:classifiers":[
        {
            "category":"Home & Garden",
            "subcategory":"Carpets & Floor Coverings",
            "type":"Retail Goods"
        }
    ],
    "sg:phone":"+32 53 41 04 55",
    "sg:postcode":"9300",
    "sg:province":"Oost-Vlaanderen",
    "sg:tags":[
        "oriental"
    ],
    "wof:name":"De Mol G",
    "wof:placetype":"venue"
},
  "geometry": {"coordinates":[4.0438389778,50.9354438782],"type":"Point"}
}