{
  "type": "Feature",
  "properties": {
    "addr:full":"Groeningenlei 98 Kontich Antwerpen 2550",
    "addr:housenumber":"98",
    "addr:postcode":"2550",
    "addr:street":"Groeningenlei",
    "iso:country":"BE",
    "sg:address":"Groeningenlei 98",
    "sg:city":"Kontich",
    "sg:classifiers":[
        {
            "category":"Manufacturing",
            "subcategory":"Textiles",
            "type":"Manufacturing & Wholesale Goods"
        }
    ],
    "sg:phone":"+32 3 458 25 67",
    "sg:postcode":"2550",
    "sg:province":"Antwerpen",
    "sg:tags":[
        "machinery"
    ],
    "wof:name":"Neveco Int. Trading Bvba",
    "wof:placetype":"venue"
},
  "geometry": {"coordinates":[4.4205107689,51.1411476135],"type":"Point"}
}