{
  "type": "Feature",
  "properties": {
    "addr:full":"Nieuwe Kempen 37 Box 2 Genk (waterschei) Limburg 3600",
    "addr:housenumber":"37;2",
    "addr:postcode":"3600",
    "addr:street":"Nieuwe Kempen;Box",
    "iso:country":"BE",
    "sg:address":"Nieuwe Kempen 37 Box 2",
    "sg:city":"Genk (waterschei)",
    "sg:classifiers":[
        {
            "category":"Real Estate",
            "subcategory":"Architect",
            "type":"Services"
        }
    ],
    "sg:phone":"+32 89 84 14 12",
    "sg:postcode":"3600",
    "sg:province":"Limburg",
    "wof:name":"Palumbo S",
    "wof:placetype":"venue"
},
  "geometry": {"coordinates":[5.48913908,51.0118141174],"type":"Point"}
}