{
  "type": "Feature",
  "properties": {
    "addr:full":"Smidstraat 237 Berlaar Antwerpen 2590",
    "addr:housenumber":"237",
    "addr:postcode":"2590",
    "addr:street":"Smidstraat",
    "iso:country":"BE",
    "sg:address":"Smidstraat 237",
    "sg:city":"Berlaar",
    "sg:orig_category":"Fietsen Motorfietsen",
    "sg:phone":"+32 3 482 18 44",
    "sg:postcode":"2590",
    "sg:province":"Antwerpen",
    "wof:name":"Bertels",
    "wof:placetype":"venue"
},
  "geometry": {"coordinates":[4.6545681953,51.1074981689],"type":"Point"}
}