{
  "type": "Feature",
  "properties": {
    "iso:country":"BE",
    "sg:address":"Vakebuurtstraat 267",
    "sg:city":"Maldegem",
    "sg:orig_category":"Rundveehouders",
    "sg:phone":"+32 50 71 14 42",
    "sg:postcode":"9990",
    "sg:province":"Oost-Vlaanderen",
    "wof:name":"Christiaan Sys",
    "wof:placetype":"venue"
},
  "geometry": {"coordinates":[3.4157140255,51.2262535095],"type":"Point"}
}