{
  "type": "Feature",
  "properties": {
    "addr:full":"Rue D'ostraux 8 Houyet Namur 5560",
    "addr:housenumber":"8",
    "addr:postcode":"5560",
    "addr:street":"Rue D'Ostraux",
    "iso:country":"BE",
    "sg:address":"Rue D'ostraux 8",
    "sg:city":"Houyet",
    "sg:orig_category":"Maisons de vacances",
    "sg:phone":"+32 81 58 03 16",
    "sg:postcode":"5560",
    "sg:province":"Namur",
    "wof:name":"Al Pice",
    "wof:placetype":"venue"
},
  "geometry": {"coordinates":[5.0115861893,50.1823654175],"type":"Point"}
}