{
  "type": "Feature",
  "properties": {
    "iso:country":"BE",
    "sg:address":"Diestersteenweg 312",
    "sg:city":"Hasselt (kermt)",
    "sg:classifiers":[
        {
            "category":"Home & Garden",
            "subcategory":"Carpets & Floor Coverings",
            "type":"Retail Goods"
        }
    ],
    "sg:phone":"+32 11 25 04 10",
    "sg:postcode":"3510",
    "sg:province":"Limburg",
    "sg:tags":[
        "tile"
    ],
    "wof:name":"Belita Nv",
    "wof:placetype":"venue"
},
  "geometry": {"coordinates":[5.2531552315,50.9474906921],"type":"Point"}
}