{
  "type": "Feature",
  "properties": {
    "iso:country":"BE",
    "sg:address":"Jules Lowetlaan 13",
    "sg:city":"Hoegaarden",
    "sg:orig_category":"Dierenartsen",
    "sg:phone":"+32 16 76 77 31",
    "sg:postcode":"3320",
    "sg:province":"Vlaams-Brabant",
    "wof:name":"C. Vernaillen",
    "wof:placetype":"venue"
},
  "geometry": {"coordinates":[4.9060111046,50.7726287842],"type":"Point"}
}