{
  "type": "Feature",
  "properties": {
    "iso:country":"BE",
    "sg:address":"Rue Renier Chalon 16",
    "sg:city":"Bruxelles (ixelles)",
    "sg:classifiers":[
        {
            "category":"Organizations",
            "subcategory":"Community Association",
            "type":"Services"
        }
    ],
    "sg:phone":"+32 2 346 48 21",
    "sg:postcode":"1050",
    "sg:province":"Bruxelles-Capitale",
    "sg:tags":[
        "cultural"
    ],
    "wof:name":"Vacances Jeunes Du Groupe Ifac",
    "wof:placetype":"venue"
},
  "geometry": {"coordinates":[4.3613519669,50.8187828064],"type":"Point"}
}