{
  "type": "Feature",
  "properties": {
    "addr:full":"Kerkhovensesteenweg 301 Lommel Limburg 3920",
    "addr:housenumber":"301",
    "addr:postcode":"3920",
    "addr:street":"Kerkhovensesteenweg",
    "iso:country":"BE",
    "sg:address":"Kerkhovensesteenweg 301",
    "sg:city":"Lommel",
    "sg:orig_category":"Dierenartsen",
    "sg:phone":"+32 11 40 24 95",
    "sg:postcode":"3920",
    "sg:province":"Limburg",
    "wof:name":"Alex Bylemans",
    "wof:placetype":"venue"
},
  "geometry": {"coordinates":[5.2758498192,51.1670951843],"type":"Point"}
}