{
  "type": "Feature",
  "properties": {
    "iso:country":"BE",
    "sg:address":"Zeedijk-centrum 490",
    "sg:city":"Koksijde",
    "sg:orig_category":"Journaux. Tabac",
    "sg:phone":"+32 58 51 32 83",
    "sg:postcode":"8670",
    "sg:province":"West-Vlaanderen",
    "wof:name":"Huis Noordzee",
    "wof:placetype":"venue"
},
  "geometry": {"coordinates":[2.6750299931,51.1339111328],"type":"Point"}
}