{
  "type": "Feature",
  "properties": {
    "iso:country":"BE",
    "sg:address":"Ottergemsesteenweg 456",
    "sg:city":"Gent",
    "sg:classifiers":[
        {
            "category":"Health Services",
            "subcategory":"Hospital",
            "type":"Services"
        }
    ],
    "sg:phone":"+32 9 220 05 20",
    "sg:postcode":"9000",
    "sg:province":"Oost-Vlaanderen",
    "wof:name":"Vlaamse Diabetes Vereniging",
    "wof:placetype":"venue"
},
  "geometry": {"coordinates":[3.7332060337,51.0248260498],"type":"Point"}
}