{
  "type": "Feature",
  "properties": {
    "iso:country":"BE",
    "sg:address":"Maastrichtersteenweg 8 Box 2",
    "sg:city":"Hasselt",
    "sg:classifiers":[
        {
            "category":"Professional",
            "subcategory":"Lawyer & Legal Services",
            "type":"Services"
        }
    ],
    "sg:phone":"+32 11 24 22 72",
    "sg:postcode":"3500",
    "sg:province":"Limburg",
    "wof:name":"Ory Danielle",
    "wof:placetype":"venue"
},
  "geometry": {"coordinates":[5.3446578979,50.9306716919],"type":"Point"}
}