{
  "type": "Feature",
  "properties": {
    "addr:full":"Daelemweld 1113 Herk-de-stad Limburg 3540",
    "addr:postcode":"1113 herk-de-stad;3540",
    "iso:country":"BE",
    "sg:address":"Daelemweld 1113",
    "sg:city":"Herk-de-stad",
    "sg:classifiers":[
        {
            "category":"Train Station",
            "subcategory":"Rail",
            "type":"Transportation"
        }
    ],
    "sg:phone":"+32 13 55 35 13",
    "sg:postcode":"3540",
    "sg:province":"Limburg",
    "sg:tags":[
        "steel",
        "pipe",
        "sheet",
        "metal",
        "metallurgy",
        "metalworking"
    ],
    "wof:name":"Ad Medical Technologies Nv",
    "wof:placetype":"venue"
},
  "geometry": {"coordinates":[5.1659698486,50.9407691956],"type":"Point"}
}