{
  "type": "Feature",
  "properties": {
    "addr:full":"Europalaan 40 Mechelen Antwerpen 2800",
    "addr:housenumber":"40",
    "addr:postcode":"2800",
    "addr:street":"Europalaan",
    "iso:country":"BE",
    "sg:address":"Europalaan 40",
    "sg:city":"Mechelen",
    "sg:classifiers":[
        {
            "category":"Health Services",
            "subcategory":"Health Practitioner",
            "type":"Services"
        }
    ],
    "sg:phone":"+32 15 41 83 57",
    "sg:postcode":"2800",
    "sg:province":"Antwerpen",
    "sg:tags":[
        "physiotherapist"
    ],
    "wof:name":"Iwens W",
    "wof:placetype":"venue"
},
  "geometry": {"coordinates":[4.4697890282,51.0113945007],"type":"Point"}
}