{
  "type": "Feature",
  "properties": {
    "addr:full":"Riemenstr 1 Vorselaar Antwerpen 2290",
    "addr:housenumber":"1",
    "addr:postcode":"2290",
    "addr:street":"Riemenstr",
    "iso:country":"BE",
    "sg:address":"Riemenstr 1",
    "sg:city":"Vorselaar",
    "sg:orig_category":"Miscellaneous Products",
    "sg:phone":"+32 14 51 16 96",
    "sg:postcode":"2290",
    "sg:province":"Antwerpen",
    "wof:name":"Van Den Broeck Bvba",
    "wof:placetype":"venue"
},
  "geometry": {"coordinates":[4.7729940414,51.2027893066],"type":"Point"}
}