{
  "type": "Feature",
  "properties": {
    "addr:full":"Peperstraat 25 Laarne (kalken) Oost-Vlaanderen 9270",
    "addr:housenumber":"25",
    "addr:postcode":"9270",
    "addr:street":"Peperstraat",
    "iso:country":"BE",
    "sg:address":"Peperstraat 25",
    "sg:city":"Laarne (kalken)",
    "sg:classifiers":[
        {
            "category":"Structure",
            "subcategory":"Office Building",
            "type":"Public Place"
        }
    ],
    "sg:phone":"+32 9 369 38 66",
    "sg:postcode":"9270",
    "sg:province":"Oost-Vlaanderen",
    "sg:tags":[
        "-",
        "type",
        "door",
        "sliding",
        "overhead"
    ],
    "wof:name":"Behiels",
    "wof:placetype":"venue"
},
  "geometry": {"coordinates":[3.8923020363,51.0256004333],"type":"Point"}
}