{
  "type": "Feature",
  "properties": {
    "iso:country":"BE",
    "sg:address":"Gemeenteplein 1",
    "sg:city":"Hoegaarden",
    "sg:orig_category":"S\u00e9lection de personnel and placement",
    "sg:phone":"+32 16 76 81 75",
    "sg:postcode":"3320",
    "sg:province":"Vlaams-Brabant",
    "wof:name":"Pwa Hoegaarden",
    "wof:placetype":"venue"
},
  "geometry": {"coordinates":[4.8877401352,50.773765564],"type":"Point"}
}