{
  "type": "Feature",
  "properties": {
    "iso:country":"BE",
    "sg:address":"Grand Chemin 60",
    "sg:city":"Silly",
    "sg:classifiers":[
        {
            "category":"Building & Trades",
            "subcategory":"Construction",
            "type":"Services"
        }
    ],
    "sg:phone":"+32 68 55 27 03",
    "sg:postcode":"7830",
    "sg:province":"Hainaut",
    "sg:tags":[
        "work",
        "public"
    ],
    "wof:name":"Jardins Dhellebecq (les)",
    "wof:placetype":"venue"
},
  "geometry": {"coordinates":[3.9091188908,50.6688156128],"type":"Point"}
}