{
  "type": "Feature",
  "properties": {
    "iso:country":"BE",
    "sg:address":"Avenue Colonel Picquart 51-53",
    "sg:city":"Bruxelles (schaerbeek)",
    "sg:classifiers":[
        {
            "category":"Professional",
            "subcategory":"Computer Services",
            "type":"Services"
        }
    ],
    "sg:phone":"+32 2 242 72 20",
    "sg:postcode":"1030",
    "sg:province":"Bruxelles-Capitale",
    "sg:tags":[
        "-",
        "processing",
        "data",
        "printer"
    ],
    "wof:name":"Tase Research Sa",
    "wof:placetype":"venue"
},
  "geometry": {"coordinates":[4.383043766,50.8775253296],"type":"Point"}
}