{
  "type": "Feature",
  "properties": {
    "addr:full":"Rue De Ry 1 Hamois Namur 5361",
    "addr:housenumber":"1",
    "addr:postcode":"5361",
    "addr:street":"Rue De Ry",
    "iso:country":"BE",
    "sg:address":"Rue De Ry 1",
    "sg:city":"Hamois",
    "sg:orig_category":"Eleveurs de bovins",
    "sg:phone":"+32 83 61 23 74",
    "sg:postcode":"5361",
    "sg:province":"Namur",
    "wof:name":"Roger Guillaume",
    "wof:placetype":"venue"
},
  "geometry": {"coordinates":[5.1854429245,50.3107795715],"type":"Point"}
}