{
  "type": "Feature",
  "properties": {
    "iso:country":"BE",
    "sg:address":"Vestingstraat 69 - 79",
    "sg:city":"Antwerpen",
    "sg:classifiers":[
        {
            "category":"Manufacturing",
            "subcategory":"Jewelry",
            "type":"Manufacturing & Wholesale Goods"
        }
    ],
    "sg:phone":"+32 3 234 39 91",
    "sg:postcode":"2018",
    "sg:province":"Antwerpen",
    "sg:tags":[
        "product",
        "miscellaneous",
        "jewellery"
    ],
    "wof:name":"Bvba Wa Design",
    "wof:placetype":"venue"
},
  "geometry": {"coordinates":[4.4200649261,51.2158966064],"type":"Point"}
}