{
  "type": "Feature",
  "properties": {
    "addr:full":"Rue Henri Aubry 21 La Louvi\u00e8re (haine-saint-paul) Hainaut 7100",
    "addr:housenumber":"21",
    "addr:postcode":"7100",
    "addr:street":"Rue Henri Aubry",
    "iso:country":"BE",
    "sg:address":"Rue Henri Aubry 21",
    "sg:city":"La Louvi\u00e8re (haine-saint-paul)",
    "sg:classifiers":[
        {
            "category":"Bakery",
            "type":"Food & Drink"
        }
    ],
    "sg:phone":"+32 64 22 13 37",
    "sg:postcode":"7100",
    "sg:province":"Hainaut",
    "sg:tags":[
        "confectioner",
        "baker"
    ],
    "wof:name":"Debeur D",
    "wof:placetype":"venue"
},
  "geometry": {"coordinates":[4.1850848198,50.4748649597],"type":"Point"}
}