{
  "type": "Feature",
  "properties": {
    "addr:full":"Walleken 51 Wetteren Oost-Vlaanderen 9230",
    "addr:housenumber":"51",
    "addr:postcode":"9230",
    "addr:street":"Walleken",
    "iso:country":"BE",
    "sg:address":"Walleken 51",
    "sg:city":"Wetteren",
    "sg:classifiers":[
        {
            "category":"Building & Trades",
            "subcategory":"Electrical",
            "type":"Services"
        }
    ],
    "sg:phone":"+32 9 369 55 74",
    "sg:postcode":"9230",
    "sg:province":"Oost-Vlaanderen",
    "sg:tags":[
        "electric",
        "-",
        "housewiring",
        "contractor"
    ],
    "wof:name":"S.e.a. Comfort Bvba",
    "wof:placetype":"venue"
},
  "geometry": {"coordinates":[3.8795850277,51.0182991028],"type":"Point"}
}