{
  "type": "Feature",
  "properties": {
    "iso:country":"BE",
    "sg:address":"Ardooisesteenweg 233",
    "sg:city":"Roeselare",
    "sg:orig_category":"Herstellingen and onderhoud van auto's",
    "sg:phone":"+32 51 20 12 26",
    "sg:postcode":"8800",
    "sg:province":"West-Vlaanderen",
    "wof:name":"Garage Gryspeerdt",
    "wof:placetype":"venue"
},
  "geometry": {"coordinates":[3.141354084,50.952293396],"type":"Point"}
}