{
  "type": "Feature",
  "properties": {
    "addr:full":"Plantenstraat 34 Oostende West-Vlaanderen 8400",
    "addr:housenumber":"34",
    "addr:postcode":"8400",
    "addr:street":"Plantenstraat",
    "iso:country":"BE",
    "sg:address":"Plantenstraat 34",
    "sg:city":"Oostende",
    "sg:orig_category":"Instituts pour enfants en difficult\u00e9. Orphelinats",
    "sg:phone":"+32 59 80 82 48",
    "sg:postcode":"8400",
    "sg:province":"West-Vlaanderen",
    "wof:name":"Home Weid\u00b4 En Wilgen",
    "wof:placetype":"venue"
},
  "geometry": {"coordinates":[2.9104180336,51.2211036682],"type":"Point"}
}