{
  "type": "Feature",
  "properties": {
    "addr:full":"Koningin Astridlaan 44 Box 2 Diest Vlaams-Brabant 3290",
    "addr:housenumber":"44;2",
    "addr:postcode":"3290",
    "addr:street":"Koningin Astridlaan;Box",
    "iso:country":"BE",
    "sg:address":"Koningin Astridlaan 44 Box 2",
    "sg:city":"Diest",
    "sg:classifiers":[
        {
            "category":"Communications",
            "subcategory":"Film & Video Production",
            "type":"Services"
        }
    ],
    "sg:phone":"+32 478 32 00 41",
    "sg:postcode":"3290",
    "sg:province":"Vlaams-Brabant",
    "sg:tags":[
        "multimedia",
        "-",
        "system"
    ],
    "wof:name":"Luts M",
    "wof:placetype":"venue"
},
  "geometry": {"coordinates":[5.0576858521,50.9809532166],"type":"Point"}
}