{
  "type": "Feature",
  "properties": {
    "addr:full":"Rue Omer Thiriar 176 Saint-vaast Hainaut 7100",
    "addr:housenumber":"176",
    "addr:postcode":"7100",
    "addr:street":"Rue Omer Thiriar;Hainaut",
    "iso:country":"BE",
    "sg:address":"Rue Omer Thiriar 176",
    "sg:city":"Saint-vaast",
    "sg:classifiers":[
        {
            "category":"Manufacturing",
            "subcategory":"Textiles",
            "type":"Manufacturing & Wholesale Goods"
        }
    ],
    "sg:phone":"+32 64 21 33 46",
    "sg:postcode":"7100",
    "sg:province":"Hainaut",
    "sg:tags":[
        "fab",
        "diverse",
        "textielproducten"
    ],
    "wof:name":"Jm Brod",
    "wof:placetype":"venue"
},
  "geometry": {"coordinates":[4.1758651733,50.4607124329],"type":"Point"}
}