{
  "type": "Feature",
  "properties": {
    "addr:full":"Rue De La Fontaine 8 Fosses-la-ville (aisemont) Namur 5070",
    "addr:housenumber":"8",
    "addr:postcode":"5070",
    "addr:street":"Rue De La Fontaine",
    "iso:country":"BE",
    "sg:address":"Rue De La Fontaine 8",
    "sg:city":"Fosses-la-ville (aisemont)",
    "sg:classifiers":[
        {
            "category":"Real Estate",
            "subcategory":"Architect",
            "type":"Services"
        }
    ],
    "sg:phone":"+32 71 71 39 60",
    "sg:postcode":"5070",
    "sg:province":"Namur",
    "wof:name":"Capieaux F",
    "wof:placetype":"venue"
},
  "geometry": {"coordinates":[4.6549868584,50.4026641846],"type":"Point"}
}