{
  "type": "Feature",
  "properties": {
    "addr:full":"Zoning Industriel Ruettelatour 13 Virton Luxembourg 6760",
    "addr:housenumber":"13",
    "addr:postcode":"6760",
    "addr:street":"Zoning Industriel Ruettelatour",
    "iso:country":"BE",
    "sg:address":"Zoning Industriel Ruettelatour 13",
    "sg:city":"Virton",
    "sg:classifiers":[
        {
            "category":"Professional",
            "subcategory":"Engineering",
            "type":"Services"
        }
    ],
    "sg:phone":"+32 63 58 29 70",
    "sg:postcode":"6760",
    "sg:province":"Luxembourg",
    "sg:tags":[
        "good",
        "material",
        "-",
        "machine",
        "equipment",
        "wood",
        "mechanical",
        "handling",
        "furniture"
    ],
    "wof:name":"Paletterie Fran\u00c7ois Sa",
    "wof:placetype":"venue"
},
  "geometry": {"coordinates":[5.5347180367,49.5672607422],"type":"Point"}
}