{
  "type": "Feature",
  "properties": {
    "addr:full":"Hannuitstraat 2 Gingelom Limburg 3890",
    "addr:housenumber":"2",
    "addr:postcode":"3890",
    "addr:street":"Hannuitstraat",
    "iso:country":"BE",
    "sg:address":"Hannuitstraat 2",
    "sg:city":"Gingelom",
    "sg:orig_category":"M\u00e9decins and sp\u00e9cialistes",
    "sg:phone":"+32 11 83 29 90",
    "sg:postcode":"3890",
    "sg:province":"Limburg",
    "wof:name":"J. Misigaro",
    "wof:placetype":"venue"
},
  "geometry": {"coordinates":[5.1273860931,50.7202339172],"type":"Point"}
}