{
  "type": "Feature",
  "properties": {
    "addr:full":"Dorpstraat 30 Bree (tongerlo) Limburg 3960",
    "addr:housenumber":"30",
    "addr:postcode":"3960",
    "addr:street":"Dorpstraat",
    "iso:country":"BE",
    "sg:address":"Dorpstraat 30",
    "sg:city":"Bree (tongerlo)",
    "sg:classifiers":[
        {
            "category":"Bars & Pubs",
            "type":"Food & Drink"
        }
    ],
    "sg:phone":"+32 89 86 47 15",
    "sg:postcode":"3960",
    "sg:province":"Limburg",
    "wof:name":"Paxhof",
    "wof:placetype":"venue"
},
  "geometry": {"coordinates":[5.6617269516,51.1273612976],"type":"Point"}
}