{
  "type": "Feature",
  "properties": {
    "addr:full":"Pieter De Smetstraat 9 Lokeren Oost-Vlaanderen 9160",
    "addr:housenumber":"9",
    "addr:postcode":"9160",
    "addr:street":"Pieter De Smetstraat",
    "iso:country":"BE",
    "sg:address":"Pieter De Smetstraat 9",
    "sg:city":"Lokeren",
    "sg:orig_category":"Installatie van houten of kunststof schrijnwerk",
    "sg:phone":"+32 9 348 94 46",
    "sg:postcode":"9160",
    "sg:province":"Oost-Vlaanderen",
    "wof:name":"Luc Welvaert",
    "wof:placetype":"venue"
},
  "geometry": {"coordinates":[3.997428894,51.0910606384],"type":"Point"}
}