{
  "type": "Feature",
  "properties": {
    "iso:country":"BE",
    "sg:address":"Advokaatstraat 10",
    "sg:city":"Hemiksem",
    "sg:orig_category":"Loodgieterij, verwarming and sanitaire installaties",
    "sg:phone":"+32 3 887 06 69",
    "sg:postcode":"2620",
    "sg:province":"Antwerpen",
    "wof:name":"Huybrechts",
    "wof:placetype":"venue"
},
  "geometry": {"coordinates":[4.3357620239,51.1388664246],"type":"Point"}
}