{
  "type": "Feature",
  "properties": {
    "iso:country":"BE",
    "sg:address":"Kalkenstraat 91",
    "sg:city":"Roeselare",
    "sg:classifiers":[
        {
            "category":"Communications",
            "subcategory":"Film & Video Production",
            "type":"Services"
        }
    ],
    "sg:phone":"+32 51 24 00 99",
    "sg:postcode":"8800",
    "sg:province":"West-Vlaanderen",
    "sg:tags":[
        "professional",
        "material",
        "-"
    ],
    "wof:name":"Eldeco Bvba",
    "wof:placetype":"venue"
},
  "geometry": {"coordinates":[3.146130085,50.9493980408],"type":"Point"}
}