{
  "type": "Feature",
  "properties": {
    "iso:country":"BE",
    "sg:address":"Mortierstraat 9",
    "sg:city":"Nevele (poesele)",
    "sg:classifiers":[
        {
            "category":"Wholesale",
            "subcategory":"Plants",
            "type":"Manufacturing & Wholesale Goods"
        }
    ],
    "sg:phone":"+32 9 371 85 36",
    "sg:postcode":"9850",
    "sg:province":"Oost-Vlaanderen",
    "sg:tags":[
        "decoration",
        "flower",
        "-"
    ],
    "wof:name":"Dekens A",
    "wof:placetype":"venue"
},
  "geometry": {"coordinates":[3.511631012,51.0319366455],"type":"Point"}
}