{
  "type": "Feature",
  "properties": {
    "addr:full":"Ghoosstraat 18 Heusden-zolder Limburg 3550",
    "addr:housenumber":"18",
    "addr:postcode":"3550",
    "addr:street":"Ghoosstraat",
    "iso:country":"BE",
    "sg:address":"Ghoosstraat 18",
    "sg:city":"Heusden-zolder",
    "sg:orig_category":"Souvenirs and objets artisanaux. Fleurs and plantes. Machines and mat\u00e9riel agricoles Jardinage",
    "sg:phone":"+32 11 42 46 58",
    "sg:postcode":"3550",
    "sg:province":"Limburg",
    "wof:name":"Groen Design Carmans",
    "wof:placetype":"venue"
},
  "geometry": {"coordinates":[5.2748818398,51.0312919617],"type":"Point"}
}