{
  "type": "Feature",
  "properties": {
    "iso:country":"BE",
    "sg:address":"Avenue Paul Hymans 31",
    "sg:city":"Bruxelles (woluwe-saint-lambert)",
    "sg:classifiers":[
        {
            "category":"Shopping",
            "subcategory":"Adult",
            "type":"Retail Goods"
        }
    ],
    "sg:phone":"+32 2 770 78 31",
    "sg:postcode":"1200",
    "sg:province":"Bruxelles-Capitale",
    "sg:tags":[
        "graphologist"
    ],
    "wof:name":"Troussel M",
    "wof:placetype":"venue"
},
  "geometry": {"coordinates":[4.4254689217,50.8444137573],"type":"Point"}
}