{
  "type": "Feature",
  "properties": {
    "addr:full":"Groendreef 47 Gent Oost-Vlaanderen 9000",
    "addr:housenumber":"47",
    "addr:postcode":"9000",
    "addr:street":"Groendreef;Oost-Vlaanderen",
    "iso:country":"BE",
    "sg:address":"Groendreef 47",
    "sg:city":"Gent",
    "sg:classifiers":[
        {
            "category":"Social Services",
            "type":"Services"
        }
    ],
    "sg:phone":"+32 9 227 98 18",
    "sg:postcode":"9000",
    "sg:province":"Oost-Vlaanderen",
    "wof:name":"Meisjeshuis Brugse Poort-rabot Vzw (pkj)",
    "wof:placetype":"venue"
},
  "geometry": {"coordinates":[3.7029359341,51.0619812012],"type":"Point"}
}