{
  "type": "Feature",
  "properties": {
    "addr:full":"Rue Fond-saint-servais 22 Li\u00e8ge 1 Li\u00e8ge 4000",
    "addr:housenumber":"22;1",
    "addr:postcode":"4000",
    "addr:street":"Rue Fond-Saint-Servais",
    "iso:country":"BE",
    "sg:address":"Rue Fond-saint-servais 22",
    "sg:city":"Li\u00e8ge 1",
    "sg:classifiers":[
        {
            "category":"Banks & Credit Unions",
            "subcategory":"Bureau De Change",
            "type":"Services"
        }
    ],
    "sg:phone":"+32 4 221 23 44",
    "sg:postcode":"4000",
    "sg:province":"Li\u00e8ge",
    "sg:tags":[
        "belgian",
        "-",
        "broker",
        "exchange"
    ],
    "wof:name":"U.b.b.-thoreau-pitti",
    "wof:placetype":"venue"
},
  "geometry": {"coordinates":[5.5698308945,50.6466827393],"type":"Point"}
}