{
  "type": "Feature",
  "properties": {
    "iso:country":"BE",
    "sg:address":"Hildering 9",
    "sg:city":"Vorselaar",
    "sg:classifiers":[
        {
            "category":"Building & Trades",
            "subcategory":"Landscaping Services",
            "type":"Services"
        }
    ],
    "sg:phone":"+32 14 51 46 25",
    "sg:postcode":"2290",
    "sg:province":"Antwerpen",
    "sg:tags":[
        "gardening",
        "garden",
        "maintenance"
    ],
    "wof:name":"I & S",
    "wof:placetype":"venue"
},
  "geometry": {"coordinates":[4.7639861107,51.1996612549],"type":"Point"}
}