{
  "type": "Feature",
  "properties": {
    "iso:country":"BE",
    "sg:address":"Rue De Saint-amand 72",
    "sg:city":"P\u00e9ruwelz (bon-secours)",
    "sg:classifiers":[
        {
            "category":"Building & Trades",
            "subcategory":"Pest Control",
            "type":"Services"
        }
    ],
    "sg:phone":"+32 69 78 11 54",
    "sg:postcode":"7603",
    "sg:province":"Hainaut",
    "sg:tags":[
        "painting",
        "contractor"
    ],
    "wof:name":"Janmart L",
    "wof:placetype":"venue"
},
  "geometry": {"coordinates":[3.6013970375,50.4952964783],"type":"Point"}
}