{
  "type": "Feature",
  "properties": {
    "iso:country":"BE",
    "sg:address":"Avenue Alexandre Deru 12",
    "sg:city":"Verviers",
    "sg:classifiers":[
        {
            "category":"Professional",
            "subcategory":"Computer Services",
            "type":"Services"
        }
    ],
    "sg:phone":"+32 87 22 00 63",
    "sg:postcode":"4800",
    "sg:province":"Li\u00e8ge",
    "sg:tags":[
        "-",
        "processing",
        "data",
        "software"
    ],
    "wof:name":"Passi Belgium Sprl",
    "wof:placetype":"venue"
},
  "geometry": {"coordinates":[5.8746848106,50.5849075317],"type":"Point"}
}