{
  "type": "Feature",
  "properties": {
    "addr:full":"Rue Armand Campenhout 48 Bruxelles (ixelles) Bruxelles-Capitale 1050",
    "addr:housenumber":"48",
    "addr:postcode":"1050",
    "addr:street":"Rue Armand Campenhout",
    "iso:country":"BE",
    "sg:address":"Rue Armand Campenhout 48",
    "sg:city":"Bruxelles (ixelles)",
    "sg:classifiers":[
        {
            "category":"Shopping",
            "subcategory":"Clothing, Apparel, & Fashions",
            "type":"Retail Goods"
        }
    ],
    "sg:phone":"+32 2 343 38 24",
    "sg:postcode":"1050",
    "sg:province":"Bruxelles-Capitale",
    "sg:tags":[
        "designer",
        "stylist"
    ],
    "wof:name":"Mademoiselle Lucien",
    "wof:placetype":"venue"
},
  "geometry": {"coordinates":[4.3626251221,50.8242340088],"type":"Point"}
}