{
  "type": "Feature",
  "properties": {
    "addr:full":"Gapaardstraat 46 Izegem West-Vlaanderen 8870",
    "addr:housenumber":"46",
    "addr:postcode":"8870",
    "addr:street":"Gapaardstraat",
    "iso:country":"BE",
    "sg:address":"Gapaardstraat 46",
    "sg:city":"Izegem",
    "sg:orig_category":"Producteurs de l\u00e9gumes",
    "sg:phone":"+32 51 30 00 19",
    "sg:postcode":"8870",
    "sg:province":"West-Vlaanderen",
    "wof:name":"Carlos Stragier",
    "wof:placetype":"venue"
},
  "geometry": {"coordinates":[3.204679966,50.9020385742],"type":"Point"}
}