{
  "type": "Feature",
  "properties": {
    "addr:full":"Gebouw 706 Zaventem 1931",
    "addr:housenumber":"706",
    "addr:postcode":"1931",
    "iso:country":"BE",
    "sg:address":"Gebouw 706",
    "sg:city":"Zaventem",
    "sg:orig_category":"Banques and organismes de cr\u00e9dit",
    "sg:phone":"+32 2 751 71 00",
    "sg:postcode":"1931",
    "wof:name":"Kbc",
    "wof:placetype":"venue"
},
  "geometry": {"coordinates":[4.4741148949,50.8835449219],"type":"Point"}
}