{
  "type": "Feature",
  "properties": {
    "iso:country":"BE",
    "sg:address":"Huidevettersstraat 54",
    "sg:city":"Antwerpen",
    "sg:classifiers":[
        {
            "category":"Shopping",
            "subcategory":"Clothing, Apparel, & Fashions",
            "type":"Retail Goods"
        }
    ],
    "sg:phone":"+32 3 226 14 16",
    "sg:postcode":"2000",
    "sg:province":"Antwerpen",
    "sg:tags":[
        "boutique"
    ],
    "wof:name":"Two Ply",
    "wof:placetype":"venue"
},
  "geometry": {"coordinates":[4.4050040245,51.2164421082],"type":"Point"}
}