{
  "type": "Feature",
  "properties": {
    "addr:full":"Lauwestraat 65 Menen West-Vlaanderen 8930",
    "addr:housenumber":"65",
    "addr:postcode":"8930",
    "addr:street":"Lauwestraat",
    "iso:country":"BE",
    "sg:address":"Lauwestraat 65",
    "sg:city":"Menen",
    "sg:orig_category":"Instituts de beaut\u00e9. Centres de relaxation and bien-\u00eatre",
    "sg:phone":"+32 56 41 58 45",
    "sg:postcode":"8930",
    "sg:province":"West-Vlaanderen",
    "wof:name":"Instituut Dorine",
    "wof:placetype":"venue"
},
  "geometry": {"coordinates":[3.1681399345,50.7892417908],"type":"Point"}
}