{
  "type": "Feature",
  "properties": {
    "addr:full":"Kloosterstraat 42 Herzele Oost-Vlaanderen 9550",
    "addr:housenumber":"42",
    "addr:postcode":"9550",
    "addr:street":"Kloosterstraat;Oost-Vlaanderen",
    "iso:country":"BE",
    "sg:address":"Kloosterstraat 42",
    "sg:city":"Herzele",
    "sg:orig_category":"Overheidsdiensten",
    "sg:phone":"+32 53 62 74 61",
    "sg:postcode":"9550",
    "sg:province":"Oost-Vlaanderen",
    "wof:name":"O.c.m.w.",
    "wof:placetype":"venue"
},
  "geometry": {"coordinates":[3.892250061,50.8885917664],"type":"Point"}
}