{
  "type": "Feature",
  "properties": {
    "addr:full":"Rue Ferrer 1 Pont-\u00c0-celles Hainaut 6230",
    "addr:housenumber":"1",
    "addr:postcode":"6230",
    "addr:street":"Rue Ferrer",
    "iso:country":"BE",
    "sg:address":"Rue Ferrer 1",
    "sg:city":"Pont-\u00c0-celles",
    "sg:orig_category":"Industri\u00eble and commerci\u00eble bouw Woningbouw",
    "sg:phone":"+32 71 84 44 30",
    "sg:postcode":"6230",
    "sg:province":"Hainaut",
    "wof:name":"D.a.d.construct",
    "wof:placetype":"venue"
},
  "geometry": {"coordinates":[4.3691859245,50.508354187],"type":"Point"}
}