{
  "type": "Feature",
  "properties": {
    "addr:full":"John Kennedylaan 14 Gent Oost-Vlaanderen 9000",
    "addr:housenumber":"14",
    "addr:postcode":"9000",
    "addr:street":"John Kennedylaan;Oost-Vlaanderen",
    "iso:country":"BE",
    "sg:address":"John Kennedylaan 14",
    "sg:city":"Gent",
    "sg:classifiers":[
        {
            "category":"Building & Trades",
            "subcategory":"Construction",
            "type":"Services"
        }
    ],
    "sg:phone":"+32 9 251 01 76",
    "sg:postcode":"9000",
    "sg:province":"Oost-Vlaanderen",
    "sg:tags":[
        "scaffolding"
    ],
    "wof:name":"Tubb Nv",
    "wof:placetype":"venue"
},
  "geometry": {"coordinates":[3.7620968819,51.1081962585],"type":"Point"}
}