{
  "type": "Feature",
  "properties": {
    "addr:full":"Place Du Grand Sablon 45 Brussel/bruxelles Bruxelles-Capitale 1000",
    "addr:housenumber":"45",
    "addr:postcode":"1000",
    "addr:street":"Place Du Grand Sablon;/",
    "iso:country":"BE",
    "sg:address":"Place Du Grand Sablon 45",
    "sg:city":"Brussel/bruxelles",
    "sg:orig_category":"Salles de spectacles",
    "sg:phone":"+32 2 511 88 60",
    "sg:postcode":"1000",
    "sg:province":"Bruxelles-Capitale",
    "wof:name":"Claeys Gallery",
    "wof:placetype":"venue"
},
  "geometry": {"coordinates":[4.3540520668,50.8413238525],"type":"Point"}
}