{
  "type": "Feature",
  "properties": {
    "addr:full":"Ijzerenkruisstraat 59 Brussel/bruxelles Bruxelles-Capitale 1000",
    "addr:housenumber":"59",
    "addr:postcode":"1000",
    "addr:street":"Ijzerenkruisstraat;/",
    "iso:country":"BE",
    "sg:address":"Ijzerenkruisstraat 59",
    "sg:city":"Brussel/bruxelles",
    "sg:classifiers":[
        {
            "category":"Restaurant",
            "type":"Food & Drink"
        }
    ],
    "sg:phone":"+32 2 511 30 54",
    "sg:postcode":"1000",
    "sg:province":"Bruxelles-Capitale",
    "wof:name":"Tea-room Le Salon",
    "wof:placetype":"venue"
},
  "geometry": {"coordinates":[4.3652682304,50.8481254578],"type":"Point"}
}