{
  "type": "Feature",
  "properties": {
    "addr:full":"Pannestraat 128 Lanaken Limburg 3620",
    "addr:housenumber":"128",
    "addr:postcode":"3620",
    "addr:street":"Pannestraat",
    "iso:country":"BE",
    "sg:address":"Pannestraat 128",
    "sg:city":"Lanaken",
    "sg:orig_category":"Rundveehouders",
    "sg:phone":"+32 89 71 49 76",
    "sg:postcode":"3620",
    "sg:province":"Limburg",
    "wof:name":"Charles Herremans",
    "wof:placetype":"venue"
},
  "geometry": {"coordinates":[5.6348838806,50.8904266357],"type":"Point"}
}