{
  "type": "Feature",
  "properties": {
    "addr:full":"Zikkelstraat 46 Wezembeek-oppem Vlaams-Brabant 1970",
    "addr:housenumber":"46",
    "addr:postcode":"1970",
    "addr:street":"Zikkelstraat",
    "iso:country":"BE",
    "sg:address":"Zikkelstraat 46",
    "sg:city":"Wezembeek-oppem",
    "sg:orig_category":"Informaticaconsulenten",
    "sg:phone":"+32 2 731 46 08",
    "sg:postcode":"1970",
    "sg:province":"Vlaams-Brabant",
    "wof:name":"Valcan",
    "wof:placetype":"venue"
},
  "geometry": {"coordinates":[4.4902977943,50.8352508545],"type":"Point"}
}