{
  "type": "Feature",
  "properties": {
    "iso:country":"BE",
    "sg:address":"Kapellestraat 221b223",
    "sg:city":"Bredene",
    "sg:classifiers":[
        {
            "category":"Wholesale",
            "subcategory":"Sporting Goods",
            "type":"Manufacturing & Wholesale Goods"
        }
    ],
    "sg:phone":"+32 59 32 27 94",
    "sg:postcode":"8450",
    "sg:province":"West-Vlaanderen",
    "sg:tags":[
        "sport-",
        "kampeermateriaal"
    ],
    "wof:name":"De Kampeerder",
    "wof:placetype":"venue"
},
  "geometry": {"coordinates":[2.9773340225,51.2523994446],"type":"Point"}
}