{
  "type": "Feature",
  "properties": {
    "iso:country":"BE",
    "sg:address":"Mechelsesteenweg 99",
    "sg:city":"Antwerpen",
    "sg:orig_category":"Eclairage et \u00e9quipements du foyer",
    "sg:phone":"+32 3 239 44 00",
    "sg:postcode":"2018",
    "sg:province":"Antwerpen",
    "wof:name":"Dever & Morseau",
    "wof:placetype":"venue"
},
  "geometry": {"coordinates":[4.4098191261,51.2069320679],"type":"Point"}
}