{
  "type": "Feature",
  "properties": {
    "iso:country":"BE",
    "sg:address":"Rue Moulin \u00e0 Vent 3",
    "sg:city":"Awans",
    "sg:classifiers":[
        {
            "category":"Communications",
            "subcategory":"News Services",
            "type":"Services"
        }
    ],
    "sg:phone":"+32 4 263 85 38",
    "sg:postcode":"4340",
    "sg:province":"Li\u00e8ge",
    "sg:tags":[
        "illustrator"
    ],
    "wof:name":"Delvaux N",
    "wof:placetype":"venue"
},
  "geometry": {"coordinates":[5.4591197968,50.6694602966],"type":"Point"}
}