{
  "type": "Feature",
  "properties": {
    "addr:full":"Van Arteveldestraat 35 Antwerpen Antwerpen 2060",
    "addr:housenumber":"35",
    "addr:postcode":"2060",
    "addr:street":"Van Arteveldestraat",
    "iso:country":"BE",
    "sg:address":"Van Arteveldestraat 35",
    "sg:city":"Antwerpen",
    "sg:orig_category":"Alimentation sp\u00e9cialis\u00e9e",
    "sg:phone":"+32 3 226 99 87",
    "sg:postcode":"2060",
    "sg:province":"Antwerpen",
    "wof:name":"Casa Macedo",
    "wof:placetype":"venue"
},
  "geometry": {"coordinates":[4.4195227623,51.2202835083],"type":"Point"}
}