{
  "type": "Feature",
  "properties": {
    "addr:full":"Ceulamansstraat 23 Schelle Antwerpen 2627",
    "addr:housenumber":"23",
    "addr:postcode":"2627",
    "addr:street":"Ceulamansstraat",
    "iso:country":"BE",
    "sg:address":"Ceulamansstraat 23",
    "sg:city":"Schelle",
    "sg:orig_category":"MBK. Location d'articles de sport, de sport nautique and de camping. V\u00e9los. V\u00e9los Fab",
    "sg:phone":"+32 3 887 42 10",
    "sg:postcode":"2627",
    "sg:province":"Antwerpen",
    "wof:name":"De Nutte",
    "wof:placetype":"venue"
},
  "geometry": {"coordinates":[4.3365988731,51.1254882812],"type":"Point"}
}