{
  "type": "Feature",
  "properties": {
    "iso:country":"BE",
    "sg:address":"Dahliastraat 25",
    "sg:city":"Blankenberge",
    "sg:orig_category":"Boekhouders",
    "sg:phone":"+32 50 41 11 68",
    "sg:postcode":"8370",
    "sg:province":"West-Vlaanderen",
    "wof:name":"Jean Scholier",
    "wof:placetype":"venue"
},
  "geometry": {"coordinates":[3.1338291168,51.3035125732],"type":"Point"}
}