{
  "type": "Feature",
  "properties": {
    "iso:country":"BE",
    "sg:address":"Dweersstraat 4",
    "sg:city":"Koekelare",
    "sg:orig_category":"Eleveurs de bovins. Eleveurs and marchands de porcs",
    "sg:phone":"+32 59 27 73 84",
    "sg:postcode":"8680",
    "sg:province":"West-Vlaanderen",
    "wof:name":"Frans Vanclooster",
    "wof:placetype":"venue"
},
  "geometry": {"coordinates":[2.9781599045,51.0901832581],"type":"Point"}
}