{
  "type": "Feature",
  "properties": {
    "iso:country":"BE",
    "sg:address":"Dorpsstraat 3 Box 2",
    "sg:city":"Meeuwen-gruitrode (meeuwen)",
    "sg:classifiers":[
        {
            "category":"Personal",
            "subcategory":"Beauty Salon",
            "type":"Services"
        }
    ],
    "sg:phone":"+32 11 79 26 03",
    "sg:postcode":"3670",
    "sg:province":"Limburg",
    "wof:name":"Cleo-vandormael L",
    "wof:placetype":"venue"
},
  "geometry": {"coordinates":[5.5185132027,51.0977249146],"type":"Point"}
}