{
  "type": "Feature",
  "properties": {
    "addr:full":"Petit-halleux 25 Vielsalm Luxembourg 6698",
    "addr:housenumber":"25",
    "addr:postcode":"6698",
    "addr:street":"Petit-Halleux",
    "iso:country":"BE",
    "sg:address":"Petit-halleux 25",
    "sg:city":"Vielsalm",
    "sg:orig_category":"Boomkwekerijen",
    "sg:phone":"+32 80 21 65 32",
    "sg:postcode":"6698",
    "sg:province":"Luxembourg",
    "wof:name":"Albert Van Zuylen",
    "wof:placetype":"venue"
},
  "geometry": {"coordinates":[5.9040818214,50.3219985962],"type":"Point"}
}