{
  "type": "Feature",
  "properties": {
    "addr:full":"Tiensesteenweg 206 Glabbeek (bunsbeek) Vlaams-Brabant 3380",
    "addr:housenumber":"206",
    "addr:postcode":"3380",
    "addr:street":"Tiensesteenweg",
    "iso:country":"BE",
    "sg:address":"Tiensesteenweg 206",
    "sg:city":"Glabbeek (bunsbeek)",
    "sg:classifiers":[
        {
            "category":"Arena",
            "subcategory":"Sports Club",
            "type":"Entertainment"
        }
    ],
    "sg:phone":"+32 16 77 85 02",
    "sg:postcode":"3380",
    "sg:province":"Vlaams-Brabant",
    "wof:name":"Voetbalploeg Vz",
    "wof:placetype":"venue"
},
  "geometry": {"coordinates":[4.9596538544,50.8708648682],"type":"Point"}
}