{
  "type": "Feature",
  "properties": {
    "addr:full":"Av W A Mozart 20 Drogenbos Vlaams-Brabant 1620",
    "addr:housenumber":"20",
    "addr:postcode":"1620",
    "addr:street":"Av W A Mozart",
    "iso:country":"BE",
    "sg:address":"Av W A Mozart 20",
    "sg:city":"Drogenbos",
    "sg:classifiers":[
        {
            "category":"Manufacturing",
            "subcategory":"Chemicals & Compounds",
            "type":"Manufacturing & Wholesale Goods"
        }
    ],
    "sg:phone":"+32 2 334 76 75",
    "sg:postcode":"1620",
    "sg:province":"Vlaams-Brabant",
    "sg:tags":[
        "pharmaceutical",
        "chemistry",
        "-",
        "by-product"
    ],
    "wof:name":"Sodicam Benelux Sa",
    "wof:placetype":"venue"
},
  "geometry": {"coordinates":[4.3174529076,50.7868804932],"type":"Point"}
}