{
  "type": "Feature",
  "properties": {
    "addr:full":"Vlassenhove 31 Dentergem (oeselgem) West-Vlaanderen 8720",
    "addr:housenumber":"31",
    "addr:postcode":"8720",
    "addr:street":"Vlassenhove",
    "iso:country":"BE",
    "sg:address":"Vlassenhove 31",
    "sg:city":"Dentergem (oeselgem)",
    "sg:classifiers":[
        {
            "category":"Building & Trades",
            "subcategory":"Construction",
            "type":"Services"
        }
    ],
    "sg:phone":"+32 9 388 38 08",
    "sg:postcode":"8720",
    "sg:province":"West-Vlaanderen",
    "sg:tags":[
        "carpenter"
    ],
    "wof:name":"Dobbels S",
    "wof:placetype":"venue"
},
  "geometry": {"coordinates":[3.4304919243,50.9369544983],"type":"Point"}
}