{
  "type": "Feature",
  "properties": {
    "addr:full":"Ijzerenleen 13 Mechelen Antwerpen 2800",
    "addr:housenumber":"13",
    "addr:postcode":"2800",
    "addr:street":"Ijzerenleen",
    "iso:country":"BE",
    "sg:address":"Ijzerenleen 13",
    "sg:city":"Mechelen",
    "sg:classifiers":[
        {
            "category":"Shopping",
            "subcategory":"Clothing, Apparel, & Fashions",
            "type":"Retail Goods"
        }
    ],
    "sg:phone":"+32 15 20 47 42",
    "sg:postcode":"2800",
    "sg:province":"Antwerpen",
    "sg:tags":[
        "lady",
        "clothing",
        "-"
    ],
    "wof:name":"Maxim",
    "wof:placetype":"venue"
},
  "geometry": {"coordinates":[4.4789347649,51.0266113281],"type":"Point"}
}