{
  "type": "Feature",
  "properties": {
    "addr:full":"Vondelstraat 5 Antwerpen Antwerpen 2060",
    "addr:housenumber":"5",
    "addr:postcode":"2060",
    "addr:street":"Vondelstraat",
    "iso:country":"BE",
    "sg:address":"Vondelstraat 5",
    "sg:city":"Antwerpen",
    "sg:classifiers":[
        {
            "category":"Cafe",
            "type":"Food & Drink"
        }
    ],
    "sg:phone":"+32 3 281 69 48",
    "sg:postcode":"2060",
    "sg:province":"Antwerpen",
    "sg:tags":[
        "caf\u00e9s"
    ],
    "wof:name":"Salvador Duarte",
    "wof:placetype":"venue"
},
  "geometry": {"coordinates":[4.4159030914,51.2247238159],"type":"Point"}
}