{
  "type": "Feature",
  "properties": {
    "addr:full":"Nieuwstraat 13 Dilsen-stokkem (lanklaar) Limburg 3650",
    "addr:housenumber":"13",
    "addr:postcode":"3650",
    "addr:street":"Nieuwstraat",
    "iso:country":"BE",
    "sg:address":"Nieuwstraat 13",
    "sg:city":"Dilsen-stokkem (lanklaar)",
    "sg:classifiers":[
        {
            "category":"Health Services",
            "subcategory":"Doctor",
            "type":"Services"
        }
    ],
    "sg:phone":"+32 89 79 33 40",
    "sg:postcode":"3650",
    "sg:province":"Limburg",
    "sg:tags":[
        "medicinephysicians",
        "surgeon"
    ],
    "wof:name":"Kenens W",
    "wof:placetype":"venue"
},
  "geometry": {"coordinates":[5.724257946,51.015537262],"type":"Point"}
}