{
  "type": "Feature",
  "properties": {
    "iso:country":"BE",
    "sg:address":"Sint-antoniusstraat 1b1",
    "sg:city":"Kortenberg",
    "sg:orig_category":"M\u00e9decins and sp\u00e9cialistes",
    "sg:phone":"+32 2 757 08 10",
    "sg:postcode":"3078",
    "sg:province":"Vlaams-Brabant",
    "wof:name":"Magdalena Lambrechts",
    "wof:placetype":"venue"
},
  "geometry": {"coordinates":[4.5867009163,50.8807258606],"type":"Point"}
}