{
  "type": "Feature",
  "properties": {
    "iso:country":"BE",
    "sg:address":"Pontweg 21",
    "sg:city":"Aalst",
    "sg:orig_category":"Fietsen",
    "sg:phone":"+32 53 77 72 32",
    "sg:postcode":"9310",
    "sg:province":"Oost-Vlaanderen",
    "wof:name":"Huis Goeman",
    "wof:placetype":"venue"
},
  "geometry": {"coordinates":[4.0422320366,50.9364585876],"type":"Point"}
}