{
  "type": "Feature",
  "properties": {
    "iso:country":"BE",
    "sg:address":"Rue Sainte-anne 17",
    "sg:city":"Merbes-le-ch\u00c2teau",
    "sg:orig_category":"Huishoudapparaten, televisies and radio's",
    "sg:phone":"+32 71 55 70 21",
    "sg:postcode":"6567",
    "sg:province":"Hainaut",
    "wof:name":"Baldi Germeau",
    "wof:placetype":"venue"
},
  "geometry": {"coordinates":[4.1871290207,50.317199707],"type":"Point"}
}