{
  "type": "Feature",
  "properties": {
    "addr:full":"Pater Daemsstraat 50 Diest Vlaams-Brabant 3290",
    "addr:housenumber":"50",
    "addr:postcode":"3290",
    "addr:street":"Pater Daemsstraat",
    "iso:country":"BE",
    "sg:address":"Pater Daemsstraat 50",
    "sg:city":"Diest",
    "sg:orig_category":"Woningbouw",
    "sg:phone":"+32 13 32 19 03",
    "sg:postcode":"3290",
    "sg:province":"Vlaams-Brabant",
    "wof:name":"Gebroeders Brugmans",
    "wof:placetype":"venue"
},
  "geometry": {"coordinates":[5.0757369995,51.0023422241],"type":"Point"}
}