{
  "type": "Feature",
  "properties": {
    "iso:country":"BE",
    "sg:address":"Grand Rue 49",
    "sg:city":"Ottignies-louvain-la-neuve (louvain-la-neuve)",
    "sg:classifiers":[
        {
            "category":"Shopping",
            "subcategory":"Clothing, Apparel, & Fashions",
            "type":"Retail Goods"
        }
    ],
    "sg:phone":"+32 10 45 75 33",
    "sg:postcode":"1348",
    "sg:province":"Brabant Wallon",
    "sg:tags":[
        "bathing-",
        "beachwear"
    ],
    "wof:name":"Julie (chez)",
    "wof:placetype":"venue"
},
  "geometry": {"coordinates":[4.6146531105,50.6695251465],"type":"Point"}
}