{
  "type": "Feature",
  "properties": {
    "addr:full":"Naamsevest 125 Leuven Vlaams-Brabant 3000",
    "addr:housenumber":"125",
    "addr:postcode":"3000",
    "addr:street":"Naamsevest",
    "iso:country":"BE",
    "sg:address":"Naamsevest 125",
    "sg:city":"Leuven",
    "sg:orig_category":"Epiceries",
    "sg:postcode":"3000",
    "sg:province":"Vlaams-Brabant",
    "wof:name":"Automatische Muurwinkel",
    "wof:placetype":"venue"
},
  "geometry": {"coordinates":[4.699739933,50.8715438843],"type":"Point"}
}