{
  "type": "Feature",
  "properties": {
    "iso:country":"BE",
    "sg:address":"Rue T Lemal 7",
    "sg:city":"Charleroi",
    "sg:classifiers":[
        {
            "category":"Building & Trades",
            "subcategory":"Plumbing",
            "type":"Services"
        }
    ],
    "sg:phone":"+32 475 83 19 13",
    "sg:postcode":"6043",
    "sg:province":"Hainaut",
    "sg:tags":[
        "diver",
        "commerce",
        "gr",
        "pour",
        "equipement"
    ],
    "wof:name":"A1 Bat",
    "wof:placetype":"venue"
},
  "geometry": {"coordinates":[4.4839549065,50.4479637146],"type":"Point"}
}