{
  "type": "Feature",
  "properties": {
    "iso:country":"BE",
    "sg:address":"Statiestraat 59",
    "sg:city":"Lichtervelde",
    "sg:orig_category":"Banken and kredietinstellingen",
    "sg:phone":"+32 51 72 39 32",
    "sg:postcode":"8810",
    "sg:province":"West-Vlaanderen",
    "wof:name":"Bankunie",
    "wof:placetype":"venue"
},
  "geometry": {"coordinates":[3.1381978989,51.0257568359],"type":"Point"}
}