{
  "type": "Feature",
  "properties": {
    "addr:full":"Rue Les Routures 42 Beaumont Hainaut 6500",
    "addr:housenumber":"42",
    "addr:postcode":"6500",
    "addr:street":"Rue Les Routures;Hainaut",
    "iso:country":"BE",
    "sg:address":"Rue Les Routures 42",
    "sg:city":"Beaumont",
    "sg:orig_category":"Sportclubs",
    "sg:phone":"+32 71 58 90 04",
    "sg:postcode":"6500",
    "sg:province":"Hainaut",
    "wof:name":"Le Jeune Garde",
    "wof:placetype":"venue"
},
  "geometry": {"coordinates":[4.2421298027,50.2704315186],"type":"Point"}
}