{
  "type": "Feature",
  "properties": {
    "addr:full":"Rue M.gemenne 83 Profondeville Namur 5170",
    "addr:housenumber":"83",
    "addr:postcode":"5170",
    "addr:street":"Rue M.Gemenne",
    "iso:country":"BE",
    "sg:address":"Rue M.gemenne 83",
    "sg:city":"Profondeville",
    "sg:orig_category":"Elektrische huishoudapparaten, radio and televisie Gh",
    "sg:phone":"+32 81 41 24 34",
    "sg:postcode":"5170",
    "sg:province":"Namur",
    "wof:name":"Abac-sabva",
    "wof:placetype":"venue"
},
  "geometry": {"coordinates":[4.8566222191,50.3845024109],"type":"Point"}
}