{
  "type": "Feature",
  "properties": {
    "addr:full":"Grand-rue 3 Komen-waasten/comines-warneton Hainaut 7780",
    "addr:housenumber":"3;7780",
    "addr:street":"Grand-Rue",
    "iso:country":"BE",
    "sg:address":"Grand-rue 3",
    "sg:city":"Komen-waasten/comines-warneton",
    "sg:orig_category":"Enseignement maternel and primaire",
    "sg:phone":"+32 56 55 53 21",
    "sg:postcode":"7780",
    "sg:province":"Hainaut",
    "wof:name":"Ecole Fondamentale Libre",
    "wof:placetype":"venue"
},
  "geometry": {"coordinates":[2.9984300137,50.7863311768],"type":"Point"}
}