{
  "type": "Feature",
  "properties": {
    "addr:full":". Weismes Li\u00e8ge 4950",
    "addr:postcode":"4950",
    "iso:country":"BE",
    "sg:address":".",
    "sg:city":"Weismes",
    "sg:orig_category":"Apotheken",
    "sg:phone":"+32 900 10 500",
    "sg:postcode":"4950",
    "sg:province":"Li\u00e8ge",
    "wof:name":"Apothekers Van Wacht",
    "wof:placetype":"venue"
},
  "geometry": {"coordinates":[6.1110301018,50.4149055481],"type":"Point"}
}