{
  "type": "Feature",
  "properties": {
    "iso:country":"BE",
    "sg:address":"Biesemstraat 13",
    "sg:city":"Geetbets",
    "sg:orig_category":"M\u00e9decins and sp\u00e9cialistes",
    "sg:phone":"+32 11 58 84 44",
    "sg:postcode":"3454",
    "sg:province":"Vlaams-Brabant",
    "wof:name":"R. Van Hiel",
    "wof:placetype":"venue"
},
  "geometry": {"coordinates":[5.1570677757,50.8990020752],"type":"Point"}
}