{
  "type": "Feature",
  "properties": {
    "addr:full":"Rubberigtsbank 8 Maarke-kerkem Oost-Vlaanderen 9681",
    "addr:housenumber":"8",
    "addr:postcode":"9681",
    "addr:street":"Rubberigtsbank;Oost-Vlaanderen",
    "iso:country":"BE",
    "sg:address":"Rubberigtsbank 8",
    "sg:city":"Maarke-kerkem",
    "sg:orig_category":"Diverse producten Gh",
    "sg:phone":"+32 55 21 46 57",
    "sg:postcode":"9681",
    "sg:province":"Oost-Vlaanderen",
    "wof:name":"Rogaco Int New Watch",
    "wof:placetype":"venue"
},
  "geometry": {"coordinates":[3.6353840828,50.7732887268],"type":"Point"}
}