{
  "type": "Feature",
  "properties": {
    "addr:full":"Rue De Rochefort 320 Beauraing Namur 5570",
    "addr:housenumber":"320",
    "addr:postcode":"5570",
    "addr:street":"Rue De Rochefort",
    "iso:country":"BE",
    "sg:address":"Rue De Rochefort 320",
    "sg:city":"Beauraing",
    "sg:classifiers":[
        {
            "category":"Building & Trades",
            "subcategory":"Landscaping Services",
            "type":"Services"
        }
    ],
    "sg:phone":"+32 82 71 27 04",
    "sg:postcode":"5570",
    "sg:province":"Namur",
    "sg:tags":[
        "architect",
        "landscape"
    ],
    "wof:name":"Jardin Et Paysage",
    "wof:placetype":"venue"
},
  "geometry": {"coordinates":[4.9850330353,50.1219902039],"type":"Point"}
}