{
  "type": "Feature",
  "properties": {
    "addr:full":"Sint-jansgoed 12 Eeklo Oost-Vlaanderen 9900",
    "addr:housenumber":"12",
    "addr:postcode":"9900",
    "addr:street":"Sint-Jansgoed",
    "iso:country":"BE",
    "sg:address":"Sint-jansgoed 12",
    "sg:city":"Eeklo",
    "sg:orig_category":"Rundveehouders",
    "sg:phone":"+32 9 377 21 57",
    "sg:postcode":"9900",
    "sg:province":"Oost-Vlaanderen",
    "wof:name":"Etienne Haegeman",
    "wof:placetype":"venue"
},
  "geometry": {"coordinates":[3.5512781143,51.1935691833],"type":"Point"}
}