{
  "type": "Feature",
  "properties": {
    "iso:country":"BE",
    "sg:address":"Nervi\u00cbrsstraat 18",
    "sg:city":"Asse",
    "sg:orig_category":"Groenten and fruit Gh",
    "sg:phone":"+32 2 452 87 64",
    "sg:postcode":"1730",
    "sg:province":"Vlaams-Brabant",
    "wof:name":"Ringoot Rene",
    "wof:placetype":"venue"
},
  "geometry": {"coordinates":[4.1918048859,50.9153938293],"type":"Point"}
}