{
  "type": "Feature",
  "properties": {
    "addr:full":"Kempenplein 3 Neerpelt Limburg 3910",
    "addr:housenumber":"3",
    "addr:postcode":"3910",
    "addr:street":"Kempenplein",
    "iso:country":"BE",
    "sg:address":"Kempenplein 3",
    "sg:city":"Neerpelt",
    "sg:classifiers":[
        {
            "category":"Cafe",
            "type":"Food & Drink"
        }
    ],
    "sg:phone":"+32 11 64 37 99",
    "sg:postcode":"3910",
    "sg:province":"Limburg",
    "sg:tags":[
        "snack-bars"
    ],
    "wof:name":"Anita",
    "wof:placetype":"venue"
},
  "geometry": {"coordinates":[5.4326372147,51.2283287048],"type":"Point"}
}