{
  "type": "Feature",
  "properties": {
    "iso:country":"BE",
    "sg:address":"Goudvinklaan 10",
    "sg:city":"Zwijndrecht",
    "sg:classifiers":[
        {
            "category":"Professional",
            "subcategory":"Management & Consulting",
            "type":"Services"
        }
    ],
    "sg:phone":"+32 3 252 45 27",
    "sg:postcode":"2070",
    "sg:province":"Antwerpen",
    "sg:tags":[
        "-",
        "processing",
        "data",
        "consultant"
    ],
    "wof:name":"D&f Consulting",
    "wof:placetype":"venue"
},
  "geometry": {"coordinates":[4.3263912201,51.2125205994],"type":"Point"}
}