{
  "type": "Feature",
  "properties": {
    "addr:full":"Rue De La S\u00e9r\u00e9nade 42 Bruxelles (molenbeek-saint-jean) Bruxelles-Capitale 1080",
    "addr:housenumber":"42",
    "addr:postcode":"1080",
    "addr:street":"Rue De La Se\u0301Re\u0301Nade",
    "iso:country":"BE",
    "sg:address":"Rue De La S\u00e9r\u00e9nade 42",
    "sg:city":"Bruxelles (molenbeek-saint-jean)",
    "sg:classifiers":[
        {
            "category":"Education",
            "subcategory":"Special Training",
            "type":"Public Place"
        }
    ],
    "sg:phone":"+32 475 27 59 75",
    "sg:postcode":"1080",
    "sg:province":"Bruxelles-Capitale",
    "sg:tags":[
        "-",
        "processing",
        "data"
    ],
    "wof:name":"Goli Sa",
    "wof:placetype":"venue"
},
  "geometry": {"coordinates":[4.2850990295,50.847442627],"type":"Point"}
}