{
  "type": "Feature",
  "properties": {
    "addr:full":"Maagd Van Gent 22 Sint-laureins Oost-Vlaanderen 9988",
    "addr:housenumber":"22",
    "addr:postcode":"9988",
    "addr:street":"Maagd Van Gent",
    "iso:country":"BE",
    "sg:address":"Maagd Van Gent 22",
    "sg:city":"Sint-laureins",
    "sg:orig_category":"Producteurs de fruits",
    "sg:phone":"+32 9 379 83 94",
    "sg:postcode":"9988",
    "sg:province":"Oost-Vlaanderen",
    "wof:name":"Ryckaert A.",
    "wof:placetype":"venue"
},
  "geometry": {"coordinates":[3.6825430393,51.2808952332],"type":"Point"}
}