{
  "type": "Feature",
  "properties": {
    "iso:country":"BE",
    "sg:address":"Capucienenlaan 120",
    "sg:city":"Aalst",
    "sg:orig_category":"M\u00e9decins and sp\u00e9cialistes",
    "sg:phone":"+32 53 77 31 31",
    "sg:postcode":"9300",
    "sg:province":"Oost-Vlaanderen",
    "wof:name":"Gerrit Schollaert",
    "wof:placetype":"venue"
},
  "geometry": {"coordinates":[4.0307688713,50.9330482483],"type":"Point"}
}