{
  "type": "Feature",
  "properties": {
    "iso:country":"BE",
    "sg:address":"Diestsestraat 12bd",
    "sg:city":"Kortenaken",
    "sg:orig_category":"Computers and computerapparatuur Onderhoud van kantoor- and computeruitrusting Software ontwikkeling",
    "sg:phone":"+32 11 58 42 55",
    "sg:postcode":"3470",
    "sg:province":"Vlaams-Brabant",
    "wof:name":"Vanpee Consulting",
    "wof:placetype":"venue"
},
  "geometry": {"coordinates":[5.061106205,50.9138183594],"type":"Point"}
}