{
  "type": "Feature",
  "properties": {
    "addr:full":"Chauss\u00e9e Paul Houtart 309 La Louvi\u00e8re (houdeng-goegnies) Hainaut 7110",
    "addr:housenumber":"309",
    "addr:postcode":"7110",
    "addr:street":"Chausse\u0301E Paul Houtart",
    "iso:country":"BE",
    "sg:address":"Chauss\u00e9e Paul Houtart 309",
    "sg:city":"La Louvi\u00e8re (houdeng-goegnies)",
    "sg:classifiers":[
        {
            "category":"Building & Trades",
            "subcategory":"Construction",
            "type":"Services"
        }
    ],
    "sg:phone":"+32 64 22 24 77",
    "sg:postcode":"7110",
    "sg:province":"Hainaut",
    "sg:tags":[
        "installation",
        "-",
        "central",
        "heating"
    ],
    "wof:name":"Vaeremans Ph",
    "wof:placetype":"venue"
},
  "geometry": {"coordinates":[4.1556458473,50.4873924255],"type":"Point"}
}