{
  "type": "Feature",
  "properties": {
    "iso:country":"BE",
    "sg:address":"Romeinsesteenweg 522",
    "sg:city":"Grimbergen",
    "sg:orig_category":"Artsen and specialisten",
    "sg:phone":"+32 2 267 37 33",
    "sg:postcode":"1853",
    "sg:province":"Vlaams-Brabant",
    "wof:name":"J.h. Nijboer",
    "wof:placetype":"venue"
},
  "geometry": {"coordinates":[4.3486728668,50.9015884399],"type":"Point"}
}