{
  "type": "Feature",
  "properties": {
    "addr:full":"Boulevard Louis Schmidt 10 Etterbeek Bruxelles-Capitale 1040",
    "addr:housenumber":"10",
    "addr:postcode":"1040",
    "addr:street":"Boulevard Louis Schmidt",
    "iso:country":"BE",
    "sg:address":"Boulevard Louis Schmidt 10",
    "sg:city":"Etterbeek",
    "sg:orig_category":"Agences d'exp\u00e9dition",
    "sg:phone":"+32 2 732 74 01",
    "sg:postcode":"1040",
    "sg:province":"Bruxelles-Capitale",
    "wof:name":"Bureau Belga Lux",
    "wof:placetype":"venue"
},
  "geometry": {"coordinates":[4.3994421959,50.8277740479],"type":"Point"}
}