{
  "type": "Feature",
  "properties": {
    "addr:full":"Aarle 39 Ravels (poppel) Antwerpen 2382",
    "addr:housenumber":"39",
    "addr:postcode":"2382",
    "addr:street":"Aarle",
    "iso:country":"BE",
    "sg:address":"Aarle 39",
    "sg:city":"Ravels (poppel)",
    "sg:classifiers":[
        {
            "category":"Building & Trades",
            "subcategory":"Construction",
            "type":"Services"
        }
    ],
    "sg:phone":"+32 14 65 86 39",
    "sg:postcode":"2382",
    "sg:province":"Antwerpen",
    "sg:tags":[
        "carpenter"
    ],
    "wof:name":"Velden J",
    "wof:placetype":"venue"
},
  "geometry": {"coordinates":[5.041768074,51.4469108582],"type":"Point"}
}