{
  "type": "Feature",
  "properties": {
    "addr:full":"Bosstraat 45 Kraainem/kraainem Vlaams-Brabant 1950",
    "addr:housenumber":"45",
    "addr:postcode":"1950",
    "addr:street":"Bosstraat",
    "iso:country":"BE",
    "sg:address":"Bosstraat 45",
    "sg:city":"Kraainem/kraainem",
    "sg:orig_category":"Plaatsen van vloer- and muurbekleding Woningbouw",
    "sg:phone":"+32 2 721 21 90",
    "sg:postcode":"1950",
    "sg:province":"Vlaams-Brabant",
    "wof:name":"Daniel Bombaerts",
    "wof:placetype":"venue"
},
  "geometry": {"coordinates":[4.4596300125,50.8592758179],"type":"Point"}
}