{
  "type": "Feature",
  "properties": {
    "iso:country":"BE",
    "sg:address":"Rue De Marchienne 12a",
    "sg:city":"Thuin",
    "sg:orig_category":"Huisdieren and benodigdheden",
    "sg:phone":"+32 71 51 64 53",
    "sg:postcode":"6535",
    "wof:name":"La Maison De Toiletteurs",
    "wof:placetype":"venue"
},
  "geometry": {"coordinates":[4.3520140648,50.3343544006],"type":"Point"}
}