{
  "type": "Feature",
  "properties": {
    "addr:full":"Bilzersteenweg 8 Tongeren Limburg 3700",
    "addr:housenumber":"8",
    "addr:postcode":"3700",
    "addr:street":"Bilzersteenweg",
    "iso:country":"BE",
    "sg:address":"Bilzersteenweg 8",
    "sg:city":"Tongeren",
    "sg:orig_category":"Instituts de beaut\u00e9",
    "sg:phone":"+32 12 23 15 06",
    "sg:postcode":"3700",
    "sg:province":"Limburg",
    "wof:name":"Hubert Bullen",
    "wof:placetype":"venue"
},
  "geometry": {"coordinates":[5.4618968964,50.7834892273],"type":"Point"}
}