{
  "type": "Feature",
  "properties": {
    "iso:country":"BE",
    "sg:address":"Route De Namur 140",
    "sg:city":"Hannut",
    "sg:orig_category":"Installatie van houten of kunststof schrijnwerk",
    "sg:phone":"+32 81 83 43 45",
    "sg:postcode":"4280",
    "sg:province":"Li\u00e8ge",
    "wof:name":"Bourgeois Ets",
    "wof:placetype":"venue"
},
  "geometry": {"coordinates":[5.0797281265,50.6174926758],"type":"Point"}
}