{
  "type": "Feature",
  "properties": {
    "addr:full":"Desmedtstraat 36 Hoogstraten (minderhout) Antwerpen 2322",
    "addr:housenumber":"36",
    "addr:postcode":"2322",
    "addr:street":"Desmedtstraat",
    "iso:country":"BE",
    "sg:address":"Desmedtstraat 36",
    "sg:city":"Hoogstraten (minderhout)",
    "sg:classifiers":[
        {
            "category":"Shopping",
            "subcategory":"Pets & Pet Supplies",
            "type":"Retail Goods"
        }
    ],
    "sg:phone":"+32 3 314 54 50",
    "sg:postcode":"2322",
    "sg:province":"Antwerpen",
    "sg:tags":[
        "shop",
        "-"
    ],
    "wof:name":"Laurijssen Bvba",
    "wof:placetype":"venue"
},
  "geometry": {"coordinates":[4.763384819,51.4160041809],"type":"Point"}
}