{
  "type": "Feature",
  "properties": {
    "addr:full":"De Pintelaan 185 Gent Oost-Vlaanderen 9000",
    "addr:housenumber":"185",
    "addr:postcode":"9000",
    "addr:street":"Pintelaan;Oost-Vlaanderen",
    "iso:country":"BE",
    "sg:address":"De Pintelaan 185",
    "sg:city":"Gent",
    "sg:classifiers":[
        {
            "category":"Wholesale",
            "subcategory":"Medical Equipment & Supplies",
            "type":"Manufacturing & Wholesale Goods"
        }
    ],
    "sg:phone":"+32 9 240 55 10",
    "sg:postcode":"9000",
    "sg:province":"Oost-Vlaanderen",
    "sg:tags":[
        "aid",
        "hearing"
    ],
    "wof:name":"Dialogue Hoorapparaten",
    "wof:placetype":"venue"
},
  "geometry": {"coordinates":[3.7236289978,51.0276527405],"type":"Point"}
}