{
  "type": "Feature",
  "properties": {
    "addr:full":"Rue De L'yser 392 Ans Li\u00e8ge 4430",
    "addr:housenumber":"392",
    "addr:postcode":"4430",
    "addr:street":"Rue De L'Yser",
    "iso:country":"BE",
    "sg:address":"Rue De L'yser 392",
    "sg:city":"Ans",
    "sg:orig_category":"Slagers",
    "sg:phone":"+32 4 246 58 27",
    "sg:postcode":"4430",
    "sg:province":"Li\u00e8ge",
    "wof:name":"Groupe Wauters",
    "wof:placetype":"venue"
},
  "geometry": {"coordinates":[5.5386519432,50.656036377],"type":"Point"}
}