{
  "type": "Feature",
  "properties": {
    "iso:country":"BE",
    "sg:address":"Chauss\u00e9e De Bruxelles 273",
    "sg:city":"Charleroi (lodelinsart)",
    "sg:classifiers":[
        {
            "category":"Retail",
            "subcategory":"Auto Repair",
            "type":"Services"
        }
    ],
    "sg:phone":"+32 71 32 80 04",
    "sg:postcode":"6042",
    "sg:province":"Hainaut",
    "sg:tags":[
        "automobile",
        "-",
        "wrecking"
    ],
    "wof:name":"Martens Ets",
    "wof:placetype":"venue"
},
  "geometry": {"coordinates":[4.435983181,50.4448013306],"type":"Point"}
}