{
  "type": "Feature",
  "properties": {
    "iso:country":"BE",
    "sg:address":"Rogierlaan 28 Box 1",
    "sg:city":"Oostende",
    "sg:classifiers":[
        {
            "category":"Health Services",
            "subcategory":"Doctor",
            "type":"Services"
        }
    ],
    "sg:phone":"+32 59 70 02 14",
    "sg:postcode":"8400",
    "sg:province":"West-Vlaanderen",
    "sg:tags":[
        "medicinephysicians",
        "surgeon"
    ],
    "wof:name":"L\u00e9onard Wilfried",
    "wof:placetype":"venue"
},
  "geometry": {"coordinates":[2.9119489193,51.2267341614],"type":"Point"}
}