{
  "type": "Feature",
  "properties": {
    "iso:country":"BE",
    "sg:address":"Kruindersweg 60",
    "sg:city":"Maasmechelen",
    "sg:orig_category":"Reisbureaus",
    "sg:phone":"+32 89 77 54 13",
    "sg:postcode":"3630",
    "sg:province":"Limburg",
    "wof:name":"Umay Reizen",
    "wof:placetype":"venue"
},
  "geometry": {"coordinates":[5.6961350441,50.963848114],"type":"Point"}
}