{
  "type": "Feature",
  "properties": {
    "iso:country":"BE",
    "sg:address":"Prins Leopoldlei 4",
    "sg:city":"Mortsel",
    "sg:classifiers":[
        {
            "category":"Communications",
            "type":"Services"
        }
    ],
    "sg:phone":"+32 3 297 02 05",
    "sg:postcode":"2640",
    "sg:province":"Antwerpen",
    "sg:tags":[
        "translator"
    ],
    "wof:name":"Cautaert B",
    "wof:placetype":"venue"
},
  "geometry": {"coordinates":[4.4547019005,51.1697845459],"type":"Point"}
}