{
  "type": "Feature",
  "properties": {
    "addr:full":"Rue De Hotton 28 Rendeux Luxembourg 6987",
    "addr:housenumber":"28",
    "addr:postcode":"6987",
    "addr:street":"Rue De Hotton",
    "iso:country":"BE",
    "sg:address":"Rue De Hotton 28",
    "sg:city":"Rendeux",
    "sg:orig_category":"Beautyfarms, relaxatie and lichamelijk welzijn Schoonheidssalons",
    "sg:phone":"+32 84 47 77 89",
    "sg:postcode":"6987",
    "sg:province":"Luxembourg",
    "wof:name":"Institut L'eph\u00c9lide",
    "wof:placetype":"venue"
},
  "geometry": {"coordinates":[5.5046601295,50.2384185791],"type":"Point"}
}