{
  "type": "Feature",
  "properties": {
    "iso:country":"BE",
    "sg:address":"Haterbeekstraat 11",
    "sg:city":"Aarschot",
    "sg:orig_category":"Ordinateurs and \u00e9quipement informatique",
    "sg:phone":"+32 16 57 00 84",
    "sg:postcode":"3200",
    "sg:province":"Vlaams-Brabant",
    "wof:name":"Roggen",
    "wof:placetype":"venue"
},
  "geometry": {"coordinates":[4.8499732018,50.9714927673],"type":"Point"}
}