{
  "type": "Feature",
  "properties": {
    "iso:country":"BE",
    "sg:address":"Avenue Lavoisier 13",
    "sg:city":"Wavre",
    "sg:orig_category":"Installatie van metalen schrijnwerk",
    "sg:phone":"+32 10 22 84 68",
    "sg:postcode":"1300",
    "sg:province":"Brabant Wallon",
    "wof:name":"Art Construct",
    "wof:placetype":"venue"
},
  "geometry": {"coordinates":[4.5930948257,50.7355308533],"type":"Point"}
}