{
  "type": "Feature",
  "properties": {
    "iso:country":"BE",
    "sg:address":"Rue Antoine N\u00c9lis 158",
    "sg:city":"Namur",
    "sg:orig_category":"Catering and organisation de f\u00eates",
    "sg:phone":"+32 81 74 15 17",
    "sg:postcode":"5001",
    "sg:province":"Namur",
    "wof:name":"Traiteur Lamfood",
    "wof:placetype":"venue"
},
  "geometry": {"coordinates":[4.8257050514,50.4722557068],"type":"Point"}
}