{
  "type": "Feature",
  "properties": {
    "addr:full":"Klinkstraat 12 Turnhout Antwerpen 2300",
    "addr:housenumber":"12",
    "addr:postcode":"2300",
    "addr:street":"Klinkstraat",
    "iso:country":"BE",
    "sg:address":"Klinkstraat 12",
    "sg:city":"Turnhout",
    "sg:orig_category":"Cr\u00e9meries",
    "sg:phone":"+32 14 41 20 47",
    "sg:postcode":"2300",
    "sg:province":"Antwerpen",
    "wof:name":"Mertens",
    "wof:placetype":"venue"
},
  "geometry": {"coordinates":[4.9538931847,51.3223152161],"type":"Point"}
}