{
  "type": "Feature",
  "properties": {
    "addr:full":"Place D' Arles 7 Verviers Li\u00e8ge 4800",
    "addr:housenumber":"7",
    "addr:postcode":"4800",
    "addr:street":"Place D ' Arles",
    "iso:country":"BE",
    "sg:address":"Place D' Arles 7",
    "sg:city":"Verviers",
    "sg:orig_category":"Cabinets d\u00b4huissiers",
    "sg:phone":"+32 87 22 89 62",
    "sg:postcode":"4800",
    "sg:province":"Li\u00e8ge",
    "wof:name":"F. Gerarts",
    "wof:placetype":"venue"
},
  "geometry": {"coordinates":[5.872879982,50.5862846375],"type":"Point"}
}