{
  "type": "Feature",
  "properties": {
    "iso:country":"BE",
    "sg:address":"Rue Croix De Pierre 1",
    "sg:city":"Braine-l\u00b4alleud",
    "sg:orig_category":"Ordinateurs and \u00e9quipement informatique",
    "sg:phone":"+32 2 385 24 39",
    "sg:postcode":"1428",
    "sg:province":"Brabant Wallon",
    "wof:name":"Fe. Barsoom",
    "wof:placetype":"venue"
},
  "geometry": {"coordinates":[4.3565011024,50.6422157288],"type":"Point"}
}