{
  "type": "Feature",
  "properties": {
    "addr:full":"Voortstraat 20 Kampenhout Vlaams-Brabant 1910",
    "addr:housenumber":"20",
    "addr:postcode":"1910",
    "addr:street":"Voortstraat",
    "iso:country":"BE",
    "sg:address":"Voortstraat 20",
    "sg:city":"Kampenhout",
    "sg:orig_category":"Groententeelt",
    "sg:phone":"+32 16 65 64 18",
    "sg:postcode":"1910",
    "sg:province":"Vlaams-Brabant",
    "wof:name":"Raymond Van Ingelgom",
    "wof:placetype":"venue"
},
  "geometry": {"coordinates":[4.5639820099,50.9379730225],"type":"Point"}
}