{
  "type": "Feature",
  "properties": {
    "addr:full":"Kleitstraat 19 Zomergem Oost-Vlaanderen 9930",
    "addr:housenumber":"19",
    "addr:postcode":"9930",
    "addr:street":"Kleitstraat",
    "iso:country":"BE",
    "sg:address":"Kleitstraat 19",
    "sg:city":"Zomergem",
    "sg:orig_category":"Slagers",
    "sg:phone":"+32 9 372 77 09",
    "sg:postcode":"9930",
    "sg:province":"Oost-Vlaanderen",
    "wof:name":"Steven Debusschere",
    "wof:placetype":"venue"
},
  "geometry": {"coordinates":[3.5584139824,51.11951828],"type":"Point"}
}