{
  "type": "Feature",
  "properties": {
    "addr:full":"Vichteplaats 12 Anzegem West-Vlaanderen 8570",
    "addr:housenumber":"12",
    "addr:postcode":"8570",
    "addr:street":"Vichteplaats",
    "iso:country":"BE",
    "sg:address":"Vichteplaats 12",
    "sg:city":"Anzegem",
    "sg:orig_category":"Artistes ind\u00e9pendants",
    "sg:phone":"+32 56 77 85 57",
    "sg:postcode":"8570",
    "sg:province":"West-Vlaanderen",
    "wof:name":"Herman Tack",
    "wof:placetype":"venue"
},
  "geometry": {"coordinates":[3.4030339718,50.8369483948],"type":"Point"}
}