{
  "type": "Feature",
  "properties": {
    "iso:country":"BE",
    "sg:address":"Monnikenwerve 117",
    "sg:city":"Brugge",
    "sg:orig_category":"Supermarkten",
    "sg:phone":"+32 50 31 40 97",
    "sg:postcode":"8000",
    "sg:province":"West-Vlaanderen",
    "wof:name":"Maenhout Distributie",
    "wof:placetype":"venue"
},
  "geometry": {"coordinates":[3.2028820515,51.2485733032],"type":"Point"}
}