{
  "type": "Feature",
  "properties": {
    "addr:full":"Rue Du Chatelain 49 Bruxelles Bruxelles-Capitale 1050",
    "addr:housenumber":"49",
    "addr:postcode":"1050",
    "addr:street":"Rue Du Chatelain",
    "iso:country":"BE",
    "sg:address":"Rue Du Chatelain 49",
    "sg:city":"Bruxelles",
    "sg:classifiers":[
        {
            "category":"Wholesale",
            "subcategory":"Books, Periodicals, & Newspapers",
            "type":"Manufacturing & Wholesale Goods"
        }
    ],
    "sg:phone":"+32 2 646 44 44",
    "sg:postcode":"1050",
    "sg:province":"Bruxelles-Capitale",
    "sg:tags":[
        "publisher",
        "book",
        "art"
    ],
    "wof:name":"Edition Racine Departem. Des Editions Lannoo S.a.",
    "wof:placetype":"venue"
},
  "geometry": {"coordinates":[4.3618998528,50.8256263733],"type":"Point"}
}