{
  "type": "Feature",
  "properties": {
    "addr:full":"Chauss\u00c9e Verte 109 Saint-georges-sur-meuse Li\u00e8ge 4470",
    "addr:housenumber":"109",
    "addr:postcode":"4470",
    "addr:street":"Chausse\u0301E Verte",
    "iso:country":"BE",
    "sg:address":"Chauss\u00c9e Verte 109",
    "sg:city":"Saint-georges-sur-meuse",
    "sg:orig_category":"Benzinestations and brandstoffen Herstellingen and onderhoud van auto's",
    "sg:phone":"+32 4 259 51 86",
    "sg:postcode":"4470",
    "sg:province":"Li\u00e8ge",
    "wof:name":"Carros. Van Craeyenest",
    "wof:placetype":"venue"
},
  "geometry": {"coordinates":[5.3475971222,50.6041908264],"type":"Point"}
}