{
  "type": "Feature",
  "properties": {
    "addr:full":"Havenlaan 8 Tessenderlo Limburg 3980",
    "addr:housenumber":"8",
    "addr:postcode":"3980",
    "addr:street":"Havenlaan",
    "iso:country":"BE",
    "sg:address":"Havenlaan 8",
    "sg:city":"Tessenderlo",
    "sg:orig_category":"Bouwmaterialen Gh",
    "sg:phone":"+32 13 66 75 46",
    "sg:postcode":"3980",
    "sg:province":"Limburg",
    "wof:name":"Paulypaint",
    "wof:placetype":"venue"
},
  "geometry": {"coordinates":[5.1546001434,51.0735931396],"type":"Point"}
}