{
  "type": "Feature",
  "properties": {
    "addr:full":"Haantjesstraat 11 Tielt (aarsele) West-Vlaanderen 8700",
    "addr:housenumber":"11",
    "addr:postcode":"8700",
    "addr:street":"Haantjesstraat",
    "iso:country":"BE",
    "sg:address":"Haantjesstraat 11",
    "sg:city":"Tielt (aarsele)",
    "sg:classifiers":[
        {
            "category":"Professional",
            "type":"Services"
        }
    ],
    "sg:phone":"+32 51 63 49 58",
    "sg:postcode":"8700",
    "sg:province":"West-Vlaanderen",
    "sg:tags":[
        "entertainer"
    ],
    "wof:name":"Polini",
    "wof:placetype":"venue"
},
  "geometry": {"coordinates":[3.4205880165,51.0005111694],"type":"Point"}
}