{
  "type": "Feature",
  "properties": {
    "addr:full":"Ruiterstraat 15 Merelbeke Oost-Vlaanderen 9820",
    "addr:housenumber":"15",
    "addr:postcode":"9820",
    "addr:street":"Ruiterstraat",
    "iso:country":"BE",
    "sg:address":"Ruiterstraat 15",
    "sg:city":"Merelbeke",
    "sg:orig_category":"Epiceries",
    "sg:phone":"+32 9 252 36 46",
    "sg:postcode":"9820",
    "sg:province":"Oost-Vlaanderen",
    "wof:name":"Paul Van Audenhove",
    "wof:placetype":"venue"
},
  "geometry": {"coordinates":[3.7673499584,50.9936599731],"type":"Point"}
}