{
  "type": "Feature",
  "properties": {
    "addr:full":"Binnenweg 4ba Lennik Vlaams-Brabant 1750",
    "addr:housenumber":"4ba;1750",
    "addr:street":"Binnenweg;Vlaams-Brabant",
    "iso:country":"BE",
    "sg:address":"Binnenweg 4ba",
    "sg:city":"Lennik",
    "sg:orig_category":"Experts-comptables",
    "sg:phone":"+32 2 532 20 75",
    "sg:postcode":"1750",
    "sg:province":"Vlaams-Brabant",
    "wof:name":"Joseph Oliver",
    "wof:placetype":"venue"
},
  "geometry": {"coordinates":[4.1920351982,50.7984046936],"type":"Point"}
}