{
  "type": "Feature",
  "properties": {
    "addr:full":"Alfons Pieterslaan 32 Oostende West-Vlaanderen 8400",
    "addr:housenumber":"32",
    "addr:postcode":"8400",
    "addr:street":"Alfons Pieterslaan",
    "iso:country":"BE",
    "sg:address":"Alfons Pieterslaan 32",
    "sg:city":"Oostende",
    "sg:classifiers":[
        {
            "category":"Shopping",
            "subcategory":"Optician",
            "type":"Retail Goods"
        }
    ],
    "sg:phone":"+32 59 50 68 60",
    "sg:postcode":"8400",
    "sg:province":"West-Vlaanderen",
    "sg:tags":[
        "-"
    ],
    "wof:name":"Pearle Vision Center",
    "wof:placetype":"venue"
},
  "geometry": {"coordinates":[2.9147338867,51.2261123657],"type":"Point"}
}