{
  "type": "Feature",
  "properties": {
    "iso:country":"BE",
    "sg:address":"Korte Koepoortstraat 7",
    "sg:city":"Antwerpen (groot)",
    "sg:orig_category":"Brood, gebak and snoepgoed",
    "sg:phone":"+32 2 231 03 45",
    "sg:postcode":"2000",
    "sg:province":"Antwerpen",
    "wof:name":"Zwaenepoel",
    "wof:placetype":"venue"
},
  "geometry": {"coordinates":[4.4025578499,51.2213897705],"type":"Point"}
}