{
  "type": "Feature",
  "properties": {
    "iso:country":"BE",
    "sg:address":"Schoolstraat 9",
    "sg:city":"Landen",
    "sg:orig_category":"Artsen and specialisten",
    "sg:phone":"+32 16 78 88 83",
    "sg:postcode":"3400",
    "sg:province":"Vlaams-Brabant",
    "wof:name":"Frank Peeters",
    "wof:placetype":"venue"
},
  "geometry": {"coordinates":[5.0401477814,50.7670211792],"type":"Point"}
}