{
  "type": "Feature",
  "properties": {
    "addr:full":"Steenweg 136 Lanaken Limburg 3621",
    "addr:housenumber":"136",
    "addr:postcode":"3621",
    "addr:street":"Steenweg",
    "iso:country":"BE",
    "sg:address":"Steenweg 136",
    "sg:city":"Lanaken",
    "sg:classifiers":[
        {
            "category":"Communications",
            "subcategory":"Film & Video Production",
            "type":"Services"
        }
    ],
    "sg:phone":"+32 89 71 38 64",
    "sg:postcode":"3621",
    "sg:province":"Limburg",
    "sg:tags":[
        "platen",
        "cassette",
        "cd's"
    ],
    "wof:name":"Marcel Janssen",
    "wof:placetype":"venue"
},
  "geometry": {"coordinates":[5.6859879494,50.9223709106],"type":"Point"}
}