{
  "type": "Feature",
  "properties": {
    "iso:country":"BE",
    "sg:address":"Ridder De Ghellinckstraat 51",
    "sg:city":"Wielsbeke",
    "sg:orig_category":"Non-Classified Establishments",
    "sg:phone":"+32 56 66 62 77",
    "sg:postcode":"8710",
    "sg:province":"West-Vlaanderen",
    "wof:name":"Casaert H",
    "wof:placetype":"venue"
},
  "geometry": {"coordinates":[3.3544840813,50.9145011902],"type":"Point"}
}