{
  "type": "Feature",
  "properties": {
    "iso:country":"BE",
    "sg:address":"Avenue Mostinck 65",
    "sg:city":"Bruxelles (woluwe-saint-pierre)",
    "sg:classifiers":[
        {
            "category":"Communications",
            "subcategory":"Film & Video Production",
            "type":"Services"
        }
    ],
    "sg:phone":"+32 2 771 71 37",
    "sg:postcode":"1150",
    "sg:province":"Bruxelles-Capitale",
    "sg:tags":[
        "producer",
        "realizators"
    ],
    "wof:name":"Man's Films Sprl",
    "wof:placetype":"venue"
},
  "geometry": {"coordinates":[4.4215021133,50.8301277161],"type":"Point"}
}