{
  "type": "Feature",
  "properties": {
    "addr:full":"Rue Arthur Roland 11 Box 6 Bruxelles (schaerbeek) Bruxelles-Capitale 1030",
    "addr:housenumber":"11;6",
    "addr:postcode":"1030",
    "addr:street":"Rue Arthur Roland;Box",
    "iso:country":"BE",
    "sg:address":"Rue Arthur Roland 11 Box 6",
    "sg:city":"Bruxelles (schaerbeek)",
    "sg:classifiers":[
        {
            "category":"Building & Trades",
            "subcategory":"Cleaning & Sanitation",
            "type":"Services"
        }
    ],
    "sg:phone":"+32 2 242 84 22",
    "sg:postcode":"1030",
    "sg:province":"Bruxelles-Capitale",
    "sg:tags":[
        "cleaner",
        "window"
    ],
    "wof:name":"Simon C",
    "wof:placetype":"venue"
},
  "geometry": {"coordinates":[4.3943061829,50.8638916016],"type":"Point"}
}