{
  "type": "Feature",
  "properties": {
    "addr:full":"Rue D'ensival 2 Verviers Li\u00e8ge 4800",
    "addr:housenumber":"2",
    "addr:postcode":"4800",
    "addr:street":"Rue D'Ensival",
    "iso:country":"BE",
    "sg:address":"Rue D'ensival 2",
    "sg:city":"Verviers",
    "sg:classifiers":[
        {
            "category":"Fast Food",
            "type":"Food & Drink"
        }
    ],
    "sg:phone":"+32 87 35 47 35",
    "sg:postcode":"4800",
    "sg:province":"Li\u00e8ge",
    "sg:tags":[
        "fried",
        "stand",
        "potato"
    ],
    "wof:name":"Gare (friterie De La)",
    "wof:placetype":"venue"
},
  "geometry": {"coordinates":[5.8551712036,50.5888710022],"type":"Point"}
}