{
  "type": "Feature",
  "properties": {
    "iso:country":"BE",
    "sg:address":"Place Des Combattants 23",
    "sg:city":"Welkenraedt",
    "sg:orig_category":"Epiceries",
    "sg:phone":"+32 87 88 23 29",
    "sg:postcode":"4840",
    "sg:province":"Li\u00e8ge",
    "wof:name":"Epicerie Palmira",
    "wof:placetype":"venue"
},
  "geometry": {"coordinates":[5.9725680351,50.6610984802],"type":"Point"}
}