{
  "type": "Feature",
  "properties": {
    "addr:full":"Avenue Brugmann 287 Ukkel/uccle Bruxelles-Capitale 1180",
    "addr:housenumber":"287",
    "addr:postcode":"1180",
    "addr:street":"Avenue Brugmann;/",
    "iso:country":"BE",
    "sg:address":"Avenue Brugmann 287",
    "sg:city":"Ukkel/uccle",
    "sg:orig_category":"Avocats and conseillers juridiques",
    "sg:phone":"+32 2 345 55 50",
    "sg:postcode":"1180",
    "sg:province":"Bruxelles-Capitale",
    "wof:name":"Laurent Dachelet",
    "wof:placetype":"venue"
},
  "geometry": {"coordinates":[4.3469347954,50.8122215271],"type":"Point"}
}