{
  "type": "Feature",
  "properties": {
    "addr:full":"Markt 5 Aalter Oost-Vlaanderen 9880",
    "addr:housenumber":"5",
    "addr:postcode":"9880",
    "addr:street":"Markt",
    "iso:country":"BE",
    "sg:address":"Markt 5",
    "sg:city":"Aalter",
    "sg:classifiers":[
        {
            "category":"Shopping",
            "subcategory":"Clothing, Apparel, & Fashions",
            "type":"Retail Goods"
        }
    ],
    "sg:phone":"+32 9 374 07 42",
    "sg:postcode":"9880",
    "sg:province":"Oost-Vlaanderen",
    "sg:tags":[
        "boutique"
    ],
    "wof:name":"Chrizia",
    "wof:placetype":"venue"
},
  "geometry": {"coordinates":[3.4488608837,51.0841674805],"type":"Point"}
}