{
  "type": "Feature",
  "properties": {
    "addr:full":"Kasteeldreef 62 Lovendegem Oost-Vlaanderen 9920",
    "addr:housenumber":"62",
    "addr:postcode":"9920",
    "addr:street":"Kasteeldreef",
    "iso:country":"BE",
    "sg:address":"Kasteeldreef 62",
    "sg:city":"Lovendegem",
    "sg:classifiers":[
        {
            "category":"Shopping",
            "subcategory":"Pets & Pet Supplies",
            "type":"Retail Goods"
        }
    ],
    "sg:phone":"+32 9 372 72 80",
    "sg:postcode":"9920",
    "sg:province":"Oost-Vlaanderen",
    "sg:tags":[
        "shop",
        "-"
    ],
    "wof:name":"D'hous N",
    "wof:placetype":"venue"
},
  "geometry": {"coordinates":[3.6115069389,51.0937805176],"type":"Point"}
}