{
  "type": "Feature",
  "properties": {
    "addr:full":"Raystraat 63 Begijnendijk Vlaams-Brabant 3130",
    "addr:housenumber":"63",
    "addr:postcode":"3130",
    "addr:street":"Raystraat",
    "iso:country":"BE",
    "sg:address":"Raystraat 63",
    "sg:city":"Begijnendijk",
    "sg:orig_category":"Producteurs de l\u00e9gumes",
    "sg:phone":"+32 16 53 43 06",
    "sg:postcode":"3130",
    "sg:province":"Vlaams-Brabant",
    "wof:name":"Achiel Van Nuffelen",
    "wof:placetype":"venue"
},
  "geometry": {"coordinates":[4.7753582001,50.9914665222],"type":"Point"}
}