{
  "type": "Feature",
  "properties": {
    "iso:country":"BE",
    "sg:address":"Stokstraat 35",
    "sg:city":"Halen",
    "sg:orig_category":"Entretien and r\u00e9parations de voitures",
    "sg:phone":"+32 13 44 17 50",
    "sg:postcode":"3545",
    "sg:province":"Limburg",
    "wof:name":"J. Nollet",
    "wof:placetype":"venue"
},
  "geometry": {"coordinates":[5.0566368103,50.9265594482],"type":"Point"}
}