{
  "type": "Feature",
  "properties": {
    "addr:full":"Pauwstraat 6 Beveren Oost-Vlaanderen 9120",
    "addr:housenumber":"6",
    "addr:postcode":"9120",
    "addr:street":"Pauwstraat",
    "iso:country":"BE",
    "sg:address":"Pauwstraat 6",
    "sg:city":"Beveren",
    "sg:orig_category":"Gespecialiseerde residenti\u00eble bouw",
    "sg:phone":"+32 3 775 16 93",
    "sg:postcode":"9120",
    "sg:province":"Oost-Vlaanderen",
    "wof:name":"Fa. Vannerum",
    "wof:placetype":"venue"
},
  "geometry": {"coordinates":[4.2834172249,51.2139511108],"type":"Point"}
}