{
  "type": "Feature",
  "properties": {
    "addr:full":"Albertusplein 21 Scherpenheuvel-zichem Vlaams-Brabant 3270",
    "addr:housenumber":"21",
    "addr:postcode":"3270",
    "addr:street":"Albertusplein",
    "iso:country":"BE",
    "sg:address":"Albertusplein 21",
    "sg:city":"Scherpenheuvel-zichem",
    "sg:classifiers":[
        {
            "category":"Cafe",
            "type":"Food & Drink"
        }
    ],
    "sg:phone":"+32 13 77 12 24",
    "sg:postcode":"3270",
    "sg:province":"Vlaams-Brabant",
    "sg:tags":[
        "caf\u00e9s"
    ],
    "wof:name":"Andre Reynders",
    "wof:placetype":"venue"
},
  "geometry": {"coordinates":[4.9789328575,50.9794540405],"type":"Point"}
}