{
  "type": "Feature",
  "properties": {
    "addr:full":"Rue Brison 9 Soignies Hainaut 7060",
    "addr:housenumber":"9",
    "addr:postcode":"7060",
    "addr:street":"Rue Brison",
    "iso:country":"BE",
    "sg:address":"Rue Brison 9",
    "sg:city":"Soignies",
    "sg:orig_category":"Rundveehouders",
    "sg:phone":"+32 67 33 21 78",
    "sg:postcode":"7060",
    "sg:province":"Hainaut",
    "wof:name":"Eddy Desmecht",
    "wof:placetype":"venue"
},
  "geometry": {"coordinates":[4.0653209686,50.5735626221],"type":"Point"}
}