{
  "type": "Feature",
  "properties": {
    "iso:country":"BE",
    "sg:address":"Leeuwerstraat 7",
    "sg:city":"Zoutleeuw",
    "sg:orig_category":"Groenten and fruit Gh",
    "sg:phone":"+32 11 78 25 66",
    "sg:postcode":"3440",
    "sg:province":"Vlaams-Brabant",
    "wof:name":"Ingrid Vanbrabant",
    "wof:placetype":"venue"
},
  "geometry": {"coordinates":[5.0896639824,50.8456192017],"type":"Point"}
}