{
  "type": "Feature",
  "properties": {
    "iso:country":"BE",
    "sg:address":"Leuvensesteenweg 72",
    "sg:city":"Diest",
    "sg:orig_category":"Kinderopvang",
    "sg:phone":"+32 13 33 77 78",
    "sg:postcode":"3290",
    "sg:province":"Vlaams-Brabant",
    "wof:name":"De Sterrekes",
    "wof:placetype":"venue"
},
  "geometry": {"coordinates":[5.0495457649,50.9816017151],"type":"Point"}
}