{
  "type": "Feature",
  "properties": {
    "iso:country":"BE",
    "sg:address":"Rue Ferdinand Nicolay 24",
    "sg:city":"Seraing",
    "sg:orig_category":"Biens d'occasion",
    "sg:phone":"+32 4 336 53 27",
    "sg:postcode":"4102",
    "sg:province":"Li\u00e8ge",
    "wof:name":"Boutique Terre",
    "wof:placetype":"venue"
},
  "geometry": {"coordinates":[5.5359239578,50.6051979065],"type":"Point"}
}