{
  "type": "Feature",
  "properties": {
    "iso:country":"BE",
    "sg:address":"Quai Edouard Van Beneden 19",
    "sg:city":"Li\u00e8ge 1 (li\u00e8ge 2)",
    "sg:classifiers":[
        {
            "category":"Building & Trades",
            "subcategory":"Construction",
            "type":"Services"
        }
    ],
    "sg:phone":"+32 4 342 83 18",
    "sg:postcode":"4020",
    "sg:province":"Li\u00e8ge",
    "sg:tags":[
        "surveyor",
        "-"
    ],
    "wof:name":"Nelis Guy",
    "wof:placetype":"venue"
},
  "geometry": {"coordinates":[5.5786151886,50.6394500732],"type":"Point"}
}