{
  "type": "Feature",
  "properties": {
    "addr:full":"Dragonderstraat 140 Moeskroen/mouscron Hainaut 7700",
    "addr:housenumber":"140",
    "addr:postcode":"7700",
    "addr:street":"Dragonderstraat",
    "iso:country":"BE",
    "sg:address":"Dragonderstraat 140",
    "sg:city":"Moeskroen/mouscron",
    "sg:orig_category":"Herstellingswinkels voor diverse persoonlijke and huishoudartikelen Installatie van metalen schrijnw",
    "sg:phone":"+32 56 34 86 31",
    "sg:postcode":"7700",
    "sg:province":"Hainaut",
    "wof:name":"Vandermeulen",
    "wof:placetype":"venue"
},
  "geometry": {"coordinates":[3.2323200703,50.7400932312],"type":"Point"}
}