{
  "type": "Feature",
  "properties": {
    "iso:country":"BE",
    "sg:address":"Terhulpensesteenweg 687",
    "sg:city":"Overijse",
    "sg:classifiers":[
        {
            "category":"Building & Trades",
            "subcategory":"Landscaping Services",
            "type":"Services"
        }
    ],
    "sg:phone":"+32 2 688 06 50",
    "sg:postcode":"3090",
    "sg:province":"Vlaams-Brabant",
    "sg:tags":[
        "gardening",
        "garden",
        "maintenance"
    ],
    "wof:name":"Alain Tuinen",
    "wof:placetype":"venue"
},
  "geometry": {"coordinates":[4.5366621017,50.7620811462],"type":"Point"}
}