{
  "type": "Feature",
  "properties": {
    "iso:country":"BE",
    "sg:address":"Groenestraat 7",
    "sg:city":"Zuienkerke",
    "sg:classifiers":[
        {
            "category":"Autos & Motor Vehicles",
            "subcategory":"Automobile Sales",
            "type":"Retail Goods"
        }
    ],
    "sg:phone":"+32 50 41 72 28",
    "sg:postcode":"8377",
    "sg:province":"West-Vlaanderen",
    "sg:tags":[
        "car",
        "used",
        "-"
    ],
    "wof:name":"Meulemeester G",
    "wof:placetype":"venue"
},
  "geometry": {"coordinates":[3.1677880287,51.2782669067],"type":"Point"}
}