{
  "type": "Feature",
  "properties": {
    "iso:country":"BE",
    "sg:address":"Kanaalstraat 65",
    "sg:city":"Lommel",
    "sg:classifiers":[
        {
            "category":"Health Services",
            "subcategory":"Doctor",
            "type":"Services"
        }
    ],
    "sg:phone":"+32 11 39 37 82",
    "sg:postcode":"3920",
    "sg:province":"Limburg",
    "sg:tags":[
        "medicinephysicians",
        "surgeon"
    ],
    "wof:name":"Broux Jos",
    "wof:placetype":"venue"
},
  "geometry": {"coordinates":[5.2636890411,51.1648826599],"type":"Point"}
}