{
  "type": "Feature",
  "properties": {
    "addr:full":"Heirweg 78 Zulte Oost-Vlaanderen 9870",
    "addr:housenumber":"78",
    "addr:postcode":"9870",
    "addr:street":"Heirweg",
    "iso:country":"BE",
    "sg:address":"Heirweg 78",
    "sg:city":"Zulte",
    "sg:orig_category":"Groenten and fruit Gh",
    "sg:phone":"+32 9 388 84 14",
    "sg:postcode":"9870",
    "sg:province":"Oost-Vlaanderen",
    "wof:name":"Wiel",
    "wof:placetype":"venue"
},
  "geometry": {"coordinates":[3.4645910263,50.9435272217],"type":"Point"}
}