{
  "type": "Feature",
  "properties": {
    "iso:country":"BE",
    "sg:address":"Rue Hermant E. 31",
    "sg:city":"Bouffioulx",
    "sg:classifiers":[
        {
            "category":"Utilities",
            "subcategory":"Cable",
            "type":"Services"
        }
    ],
    "sg:phone":"+32 71 38 33 21",
    "sg:postcode":"6200",
    "sg:province":"Hainaut",
    "sg:tags":[
        "laying"
    ],
    "wof:name":"Ade S.a.",
    "wof:placetype":"venue"
},
  "geometry": {"coordinates":[4.515144825,50.3897094727],"type":"Point"}
}