{
  "type": "Feature",
  "properties": {
    "iso:country":"BE",
    "sg:address":"Dungelstraat 37",
    "sg:city":"Zoutleeuw (halle-booienhoven)",
    "sg:orig_category":"Non-Classified Establishments",
    "sg:phone":"+32 11 78 11 95",
    "sg:postcode":"3440",
    "sg:province":"Vlaams-Brabant",
    "wof:name":"Imex Herbots J&m",
    "wof:placetype":"venue"
},
  "geometry": {"coordinates":[5.1105117798,50.8113822937],"type":"Point"}
}