{
  "type": "Feature",
  "properties": {
    "iso:country":"BE",
    "sg:address":"Rue No\u00ebl 3b",
    "sg:city":"Waterloo",
    "sg:classifiers":[
        {
            "category":"Real Estate",
            "subcategory":"Architect",
            "type":"Services"
        }
    ],
    "sg:phone":"+32 2 345 32 62",
    "sg:postcode":"1410",
    "sg:province":"Brabant Wallon",
    "wof:name":"Fostier M",
    "wof:placetype":"venue"
},
  "geometry": {"coordinates":[4.3664698601,50.7050704956],"type":"Point"}
}