{
  "type": "Feature",
  "properties": {
    "iso:country":"BE",
    "sg:address":"Ch\u00c9e De La Seigneurie 42",
    "sg:city":"Verviers",
    "sg:orig_category":"Supermarch\u00e9s",
    "sg:phone":"+32 87 33 15 13",
    "sg:postcode":"4800",
    "sg:province":"Li\u00e8ge",
    "wof:name":"Central Cash",
    "wof:placetype":"venue"
},
  "geometry": {"coordinates":[5.8594508171,50.5917663574],"type":"Point"}
}