{
  "type": "Feature",
  "properties": {
    "addr:full":"Rue Henri Degorge 114 Hornu Hainaut 7301",
    "addr:housenumber":"114",
    "addr:postcode":"7301",
    "addr:street":"Rue Henri Degorge",
    "iso:country":"BE",
    "sg:address":"Rue Henri Degorge 114",
    "sg:city":"Hornu",
    "sg:orig_category":"Special Manufacture Of Wooden Components",
    "sg:phone":"+32 4 365 12 68",
    "sg:postcode":"7301",
    "sg:province":"Hainaut",
    "wof:name":"Ets Delmotte S.p.r.l.",
    "wof:placetype":"venue"
},
  "geometry": {"coordinates":[5.6329321861,50.6303291321],"type":"Point"}
}