{
  "type": "Feature",
  "properties": {
    "addr:full":"Sint-bernadettestraat 75 Gent Oost-Vlaanderen 9000",
    "addr:housenumber":"75",
    "addr:postcode":"9000",
    "addr:street":"Sint-Bernadettestraat;Oost-Vlaanderen",
    "iso:country":"BE",
    "sg:address":"Sint-bernadettestraat 75",
    "sg:city":"Gent",
    "sg:orig_category":"Bouwmaterialen Gh Goederenvervoer over de weg",
    "sg:phone":"+32 9 251 04 97",
    "sg:postcode":"9000",
    "sg:province":"Oost-Vlaanderen",
    "wof:name":"De Vriendt Jozef",
    "wof:placetype":"venue"
},
  "geometry": {"coordinates":[3.7514300346,51.0702705383],"type":"Point"}
}