{
  "type": "Feature",
  "properties": {
    "iso:country":"BE",
    "sg:address":"Rue Vanderkindere 376",
    "sg:city":"Ukkel/uccle",
    "sg:orig_category":"V\u00e9hicules automobiles. Entretien and r\u00e9parations de voitures",
    "sg:phone":"+32 2 344 44 03",
    "sg:postcode":"1180",
    "sg:province":"Bruxelles-Capitale",
    "wof:name":"Garage De L'avenue",
    "wof:placetype":"venue"
},
  "geometry": {"coordinates":[4.3573122025,50.8143692017],"type":"Point"}
}