{
  "type": "Feature",
  "properties": {
    "iso:country":"BE",
    "sg:address":"Molenstraat 72",
    "sg:city":"Zulte (olsene)",
    "sg:orig_category":"Non-Classified Establishments",
    "sg:phone":"+32 9 388 72 80",
    "sg:postcode":"9870",
    "sg:province":"Oost-Vlaanderen",
    "wof:name":"Van Hoecke T",
    "wof:placetype":"venue"
},
  "geometry": {"coordinates":[3.4629371166,50.9302139282],"type":"Point"}
}