{
  "type": "Feature",
  "properties": {
    "addr:full":"Oude Baan 2 Beveren Oost-Vlaanderen 9120",
    "addr:housenumber":"2",
    "addr:postcode":"9120",
    "addr:street":"Oude Baan",
    "iso:country":"BE",
    "sg:address":"Oude Baan 2",
    "sg:city":"Beveren",
    "sg:orig_category":"Woningbouw",
    "sg:phone":"+32 3 775 69 54",
    "sg:postcode":"9120",
    "sg:province":"Oost-Vlaanderen",
    "wof:name":"Roger Fierens",
    "wof:placetype":"venue"
},
  "geometry": {"coordinates":[4.2292132378,51.1978874207],"type":"Point"}
}