{
  "type": "Feature",
  "properties": {
    "iso:country":"BE",
    "sg:address":"Rue Thierbise 93",
    "sg:city":"Saint-nicolas",
    "sg:orig_category":"Blanchisseries and teintureries",
    "sg:phone":"+32 4 263 58 91",
    "sg:postcode":"4420",
    "sg:province":"Li\u00e8ge",
    "wof:name":"Modern Shop",
    "wof:placetype":"venue"
},
  "geometry": {"coordinates":[5.5148429871,50.6405830383],"type":"Point"}
}