{
  "type": "Feature",
  "properties": {
    "iso:country":"BE",
    "sg:address":"Rue Du Midi 156",
    "sg:city":"Brussel/bruxelles",
    "sg:orig_category":"Instruments de musique",
    "sg:phone":"+32 69 22 13 90",
    "sg:postcode":"1000",
    "sg:province":"Bruxelles-Capitale",
    "wof:name":"Music Office",
    "wof:placetype":"venue"
},
  "geometry": {"coordinates":[4.3466491699,50.8432044983],"type":"Point"}
}