{
  "type": "Feature",
  "properties": {
    "iso:country":"BE",
    "sg:address":"Rue De La Clef 57",
    "sg:city":"Soumagne",
    "sg:orig_category":"Quincailleries. Rev\u00eatements de sols and murs. Bois Gr",
    "sg:phone":"+32 4 377 10 35",
    "sg:postcode":"4633",
    "sg:province":"Li\u00e8ge",
    "wof:name":"Biemar-bois",
    "wof:placetype":"venue"
},
  "geometry": {"coordinates":[5.753923893,50.6358680725],"type":"Point"}
}