{
  "type": "Feature",
  "properties": {
    "addr:full":"Booglaan 1 Hoeilaart Vlaams-Brabant 1560",
    "addr:housenumber":"1",
    "addr:postcode":"1560",
    "addr:street":"Booglaan",
    "iso:country":"BE",
    "sg:address":"Booglaan 1",
    "sg:city":"Hoeilaart",
    "sg:classifiers":[
        {
            "category":"Arena",
            "subcategory":"Sports Club",
            "type":"Entertainment"
        }
    ],
    "sg:phone":"+32 2 657 96 81",
    "sg:postcode":"1560",
    "sg:province":"Vlaams-Brabant",
    "sg:tags":[
        "de"
    ],
    "wof:name":"T.c. 1310 La Hulpe",
    "wof:placetype":"venue"
},
  "geometry": {"coordinates":[4.4990429878,50.7654151917],"type":"Point"}
}