{
  "type": "Feature",
  "properties": {
    "iso:country":"BE",
    "sg:address":"Gieterijstraat 16-1",
    "sg:city":"Halle (lembeek)",
    "sg:classifiers":[
        {
            "category":"Juice Bar",
            "subcategory":"None",
            "type":"Food & Drink"
        }
    ],
    "sg:phone":"+32 2 306 32 30",
    "sg:postcode":"1502",
    "sg:province":"Vlaams-Brabant",
    "sg:tags":[
        "water",
        "soft"
    ],
    "wof:name":"Dal Nv",
    "wof:placetype":"venue"
},
  "geometry": {"coordinates":[4.2226610184,50.7160835266],"type":"Point"}
}