{
  "type": "Feature",
  "properties": {
    "iso:country":"BE",
    "sg:address":"Koffiestraat 2bb",
    "sg:city":"Laarne",
    "sg:orig_category":"Pharmaciens",
    "sg:phone":"+32 9 367 57 36",
    "sg:postcode":"9270",
    "sg:province":"Oost-Vlaanderen",
    "wof:name":"Vande Weghe",
    "wof:placetype":"venue"
},
  "geometry": {"coordinates":[3.9177370071,51.0385360718],"type":"Point"}
}