{
  "type": "Feature",
  "properties": {
    "iso:country":"BE",
    "sg:address":"Rue Charles Jaumotte 35",
    "sg:city":"Wavre (limal)",
    "sg:classifiers":[
        {
            "category":"Shopping",
            "subcategory":"Clothing, Apparel, & Fashions",
            "type":"Retail Goods"
        }
    ],
    "sg:phone":"+32 10 41 88 52",
    "sg:postcode":"1300",
    "sg:province":"Brabant Wallon",
    "sg:tags":[
        "-",
        "clothing",
        "child"
    ],
    "wof:name":"Rodrigues",
    "wof:placetype":"venue"
},
  "geometry": {"coordinates":[4.5751919746,50.6958389282],"type":"Point"}
}