{
  "type": "Feature",
  "properties": {
    "iso:country":"BE",
    "sg:address":"Rue Des D\u00c9port\u00c9s 110",
    "sg:city":"Charleroi",
    "sg:orig_category":"Paramedische behandelingen",
    "sg:phone":"+32 478 26 80 40",
    "sg:postcode":"6031",
    "sg:province":"Hainaut",
    "wof:name":"S. Jacquemin",
    "wof:placetype":"venue"
},
  "geometry": {"coordinates":[4.38022995,50.4121742249],"type":"Point"}
}