{
  "type": "Feature",
  "properties": {
    "iso:country":"BE",
    "sg:address":"Erasmuslaan 2",
    "sg:city":"Kortrijk",
    "sg:classifiers":[
        {
            "category":"Arena",
            "subcategory":"Sports Club",
            "type":"Entertainment"
        }
    ],
    "sg:phone":"+32 56 21 56 61",
    "sg:postcode":"8500",
    "sg:province":"West-Vlaanderen",
    "sg:tags":[
        "de"
    ],
    "wof:name":"B.t. Soubry Kortrijk",
    "wof:placetype":"venue"
},
  "geometry": {"coordinates":[3.2812139988,50.8143844604],"type":"Point"}
}