{
  "type": "Feature",
  "properties": {
    "addr:full":"Ninovesteenweg 199 Aalst (erembodegem) Oost-Vlaanderen 9320",
    "addr:housenumber":"199",
    "addr:postcode":"9320",
    "addr:street":"Ninovesteenweg",
    "iso:country":"BE",
    "sg:address":"Ninovesteenweg 199",
    "sg:city":"Aalst (erembodegem)",
    "sg:classifiers":[
        {
            "category":"Professional",
            "subcategory":"Accounting & Tax Preparation",
            "type":"Services"
        }
    ],
    "sg:phone":"+32 53 68 43 80",
    "sg:postcode":"9320",
    "sg:province":"Oost-Vlaanderen",
    "sg:tags":[
        "bookkeeper"
    ],
    "wof:name":"De Clercq E",
    "wof:placetype":"venue"
},
  "geometry": {"coordinates":[4.0553851128,50.9209976196],"type":"Point"}
}