{
  "type": "Feature",
  "properties": {
    "iso:country":"BE",
    "sg:address":"Avenue Du Four \u00e0 Briques 15",
    "sg:city":"Wavre",
    "sg:classifiers":[
        {
            "category":"Professional",
            "subcategory":"Art Services",
            "type":"Services"
        }
    ],
    "sg:phone":"+32 10 22 80 51",
    "sg:postcode":"1300",
    "sg:province":"Brabant Wallon",
    "sg:tags":[
        "graphic",
        "designer"
    ],
    "wof:name":"Denayer Images Sprl",
    "wof:placetype":"venue"
},
  "geometry": {"coordinates":[4.6297287941,50.7185707092],"type":"Point"}
}