{
  "type": "Feature",
  "properties": {
    "iso:country":"BE",
    "sg:address":"Rue Des Cloutiers 34",
    "sg:city":"Fleron",
    "sg:orig_category":"M\u00e9decines alternatives. M\u00e9decins and sp\u00e9cialistes",
    "sg:phone":"+32 4 358 14 24",
    "sg:postcode":"4621",
    "sg:province":"Li\u00e8ge",
    "wof:name":"Jacques Perick",
    "wof:placetype":"venue"
},
  "geometry": {"coordinates":[5.6995310783,50.6229972839],"type":"Point"}
}