{
  "type": "Feature",
  "properties": {
    "iso:country":"BE",
    "sg:address":"Ninoofsesteenweg 920",
    "sg:city":"Dilbeek (schepdaal)",
    "sg:classifiers":[
        {
            "category":"Manufacturing",
            "subcategory":"Electronics",
            "type":"Manufacturing & Wholesale Goods"
        }
    ],
    "sg:phone":"+32 2 569 74 78",
    "sg:postcode":"1703",
    "sg:province":"Vlaams-Brabant",
    "sg:tags":[
        "component",
        "-"
    ],
    "wof:name":"Dataflex Bvba",
    "wof:placetype":"venue"
},
  "geometry": {"coordinates":[4.1998648643,50.8384552002],"type":"Point"}
}