{
  "type": "Feature",
  "properties": {
    "addr:full":"Rue Germain Michiels 12 Beaumont Hainaut 6500",
    "addr:housenumber":"12",
    "addr:postcode":"6500",
    "addr:street":"Rue Germain Michiels;Hainaut",
    "iso:country":"BE",
    "sg:address":"Rue Germain Michiels 12",
    "sg:city":"Beaumont",
    "sg:classifiers":[
        {
            "category":"Insurance",
            "subcategory":"Insurance Agent",
            "type":"Services"
        }
    ],
    "sg:phone":"+32 71 58 82 12",
    "sg:postcode":"6500",
    "sg:province":"Hainaut",
    "sg:tags":[
        "verzekeringsmakelaars",
        "expert"
    ],
    "wof:name":"C. Hannecart",
    "wof:placetype":"venue"
},
  "geometry": {"coordinates":[4.2408080101,50.237651825],"type":"Point"}
}