{
  "type": "Feature",
  "properties": {
    "iso:country":"BE",
    "sg:address":"St-jozefstraat 1",
    "sg:city":"Temse",
    "sg:orig_category":"Verlichting and huishoudartikelen",
    "sg:phone":"+32 3 771 44 70",
    "sg:postcode":"9140",
    "sg:province":"Oost-Vlaanderen",
    "wof:name":"Artis",
    "wof:placetype":"venue"
},
  "geometry": {"coordinates":[4.1750798225,51.1123123169],"type":"Point"}
}