{
  "type": "Feature",
  "properties": {
    "iso:country":"BE",
    "sg:address":"Maastrichterstraat 1 Box 19",
    "sg:city":"Hasselt",
    "sg:classifiers":[
        {
            "category":"Bakery",
            "type":"Food & Drink"
        }
    ],
    "sg:phone":"+32 11 22 76 87",
    "sg:postcode":"3500",
    "sg:province":"Limburg",
    "sg:tags":[
        "confectioner",
        "baker"
    ],
    "wof:name":"Croissanske ('t)",
    "wof:placetype":"venue"
},
  "geometry": {"coordinates":[5.3379402161,50.9291534424],"type":"Point"}
}