{
  "type": "Feature",
  "properties": {
    "iso:country":"BE",
    "sg:address":"Vriesenhof 7ba",
    "sg:city":"Leuven",
    "sg:orig_category":"Cr\u00e8ches and garderies d'enfants",
    "sg:phone":"+32 16 22 51 63",
    "sg:postcode":"3000",
    "sg:province":"Vlaams-Brabant",
    "wof:name":"St.jacob",
    "wof:placetype":"venue"
},
  "geometry": {"coordinates":[4.6921768188,50.8819999695],"type":"Point"}
}