{
  "type": "Feature",
  "properties": {
    "iso:country":"BE",
    "sg:address":"Rue De Merbes 314",
    "sg:city":"Buvrinnes",
    "sg:classifiers":[
        {
            "category":"Food Court",
            "type":"Food & Drink"
        }
    ],
    "sg:phone":"+32 64 33 17 52",
    "sg:postcode":"7133",
    "sg:province":"Hainaut",
    "sg:tags":[
        "product",
        "related"
    ],
    "wof:name":"Leroy Prevot & Fils Sprl",
    "wof:placetype":"venue"
},
  "geometry": {"coordinates":[4.174369812,50.3876609802],"type":"Point"}
}