{
  "type": "Feature",
  "properties": {
    "addr:full":"Sint-katarinaplein 9b2 Hasselt Limburg 3500",
    "addr:housenumber":"9b2",
    "addr:postcode":"3500",
    "addr:street":"Sint-Katarinaplein",
    "iso:country":"BE",
    "sg:address":"Sint-katarinaplein 9b2",
    "sg:city":"Hasselt",
    "sg:classifiers":[
        {
            "category":"Insurance",
            "subcategory":"Life Insurance",
            "type":"Services"
        }
    ],
    "sg:phone":"+32 11 22 15 43",
    "sg:postcode":"3500",
    "sg:province":"Limburg",
    "sg:tags":[
        "assurance"
    ],
    "wof:name":"Noord - Zuid",
    "wof:placetype":"venue"
},
  "geometry": {"coordinates":[5.351331234,50.9264717102],"type":"Point"}
}