{
  "type": "Feature",
  "properties": {
    "addr:full":"Rue Nagelmackers 9 Li\u00e8ge 1 Li\u00e8ge 4000",
    "addr:housenumber":"9;1",
    "addr:postcode":"4000",
    "addr:street":"Rue Nagelmackers",
    "iso:country":"BE",
    "sg:address":"Rue Nagelmackers 9",
    "sg:city":"Li\u00e8ge 1",
    "sg:classifiers":[
        {
            "category":"Bars & Pubs",
            "type":"Food & Drink"
        }
    ],
    "sg:phone":"+32 4 232 18 25",
    "sg:postcode":"4000",
    "sg:province":"Li\u00e8ge",
    "wof:name":"Mehdi A",
    "wof:placetype":"venue"
},
  "geometry": {"coordinates":[5.5777702332,50.6435394287],"type":"Point"}
}