{
  "type": "Feature",
  "properties": {
    "iso:country":"BE",
    "sg:address":"Wellekensvenweg 10",
    "sg:city":"Aarschot",
    "sg:orig_category":"Installation \u00e9lectrique r\u00e9sidentielle",
    "sg:phone":"+32 13 78 52 28",
    "sg:postcode":"3201",
    "sg:province":"Vlaams-Brabant",
    "wof:name":"E.v.a",
    "wof:placetype":"venue"
},
  "geometry": {"coordinates":[4.8698401451,50.9937286377],"type":"Point"}
}