{
  "type": "Feature",
  "properties": {
    "iso:country":"BE",
    "sg:address":"Baljuwstraat 10",
    "sg:city":"Hamme (moerzeke)",
    "sg:classifiers":[
        {
            "category":"Professional",
            "subcategory":"Management & Consulting",
            "type":"Services"
        }
    ],
    "sg:phone":"+32 52 47 06 02",
    "sg:postcode":"9220",
    "sg:province":"Oost-Vlaanderen",
    "sg:tags":[
        "consultant",
        "agency",
        "advertising"
    ],
    "wof:name":"Vermeir G",
    "wof:placetype":"venue"
},
  "geometry": {"coordinates":[4.1533479691,51.0688858032],"type":"Point"}
}