{
  "type": "Feature",
  "properties": {
    "iso:country":"BE",
    "sg:address":"Nijverheidsstraat 34",
    "sg:city":"Gavere (dikkelvenne)",
    "sg:orig_category":"Non-Classified Establishments",
    "sg:phone":"+32 9 384 82 82",
    "sg:postcode":"9890",
    "sg:province":"Oost-Vlaanderen",
    "wof:name":"E & O",
    "wof:placetype":"venue"
},
  "geometry": {"coordinates":[3.6852660179,50.9186553955],"type":"Point"}
}