{
  "type": "Feature",
  "properties": {
    "iso:country":"BE",
    "sg:address":"Naalstraat 40c",
    "sg:city":"Duffel",
    "sg:classifiers":[
        {
            "category":"Building & Trades",
            "subcategory":"Construction",
            "type":"Services"
        }
    ],
    "sg:phone":"+32 15 31 56 17",
    "sg:postcode":"2570",
    "sg:province":"Antwerpen",
    "sg:tags":[
        "surveyor",
        "-"
    ],
    "wof:name":"Belmans Jan",
    "wof:placetype":"venue"
},
  "geometry": {"coordinates":[4.5082039833,51.0841560364],"type":"Point"}
}