{
  "type": "Feature",
  "properties": {
    "addr:full":"Tienne Des Caves 1 Mettet Namur 5646",
    "addr:housenumber":"1",
    "addr:postcode":"5646",
    "addr:street":"Des Caves",
    "iso:country":"BE",
    "sg:address":"Tienne Des Caves 1",
    "sg:city":"Mettet",
    "sg:orig_category":"Enseignement maternel and primaire",
    "sg:phone":"+32 71 72 63 96",
    "sg:postcode":"5646",
    "sg:province":"Namur",
    "wof:name":"Ecole Prim. Communale",
    "wof:placetype":"venue"
},
  "geometry": {"coordinates":[4.6611690521,50.2833747864],"type":"Point"}
}