{
  "type": "Feature",
  "properties": {
    "addr:full":"Kattestraat 25 Aalst Oost-Vlaanderen 9300",
    "addr:housenumber":"25",
    "addr:postcode":"9300",
    "addr:street":"Kattestraat",
    "iso:country":"BE",
    "sg:address":"Kattestraat 25",
    "sg:city":"Aalst",
    "sg:orig_category":"Maroquinerie and articles de voyage",
    "sg:phone":"+32 53 70 47 77",
    "sg:postcode":"9300",
    "sg:province":"Oost-Vlaanderen",
    "wof:name":"F. Van Den Steen",
    "wof:placetype":"venue"
},
  "geometry": {"coordinates":[4.0381522179,50.9392204285],"type":"Point"}
}