{
  "type": "Feature",
  "properties": {
    "addr:full":"Rue Roger Bachelart 1 Ittre Brabant Wallon 1460",
    "addr:housenumber":"1;1460",
    "addr:street":"Rue Roger Bachelart",
    "iso:country":"BE",
    "sg:address":"Rue Roger Bachelart 1",
    "sg:city":"Ittre",
    "sg:orig_category":"Producteurs de l\u00e9gumes",
    "sg:phone":"+32 67 64 89 84",
    "sg:postcode":"1460",
    "sg:province":"Brabant Wallon",
    "wof:name":"Marc Musch",
    "wof:placetype":"venue"
},
  "geometry": {"coordinates":[4.2050909996,50.6367492676],"type":"Point"}
}