{
  "type": "Feature",
  "properties": {
    "addr:full":"Grand'rue 310 Charleroi Hainaut 6000",
    "addr:housenumber":"310",
    "addr:postcode":"6000",
    "addr:street":"Grand'Rue;Hainaut",
    "iso:country":"BE",
    "sg:address":"Grand'rue 310",
    "sg:city":"Charleroi",
    "sg:classifiers":[
        {
            "category":"Banks & Credit Unions",
            "subcategory":"Investment Brokerage",
            "type":"Services"
        }
    ],
    "sg:phone":"+32 71 41 32 16",
    "sg:postcode":"6000",
    "sg:province":"Hainaut",
    "sg:tags":[
        "jean",
        "casual",
        "wear"
    ],
    "wof:name":"Alfa Jeans",
    "wof:placetype":"venue"
},
  "geometry": {"coordinates":[4.4527988434,50.4181480408],"type":"Point"}
}