{
  "type": "Feature",
  "properties": {
    "addr:full":"Sleidinge Dorp 114 Evergem (sleidinge) Oost-Vlaanderen 9940",
    "addr:housenumber":"114",
    "addr:postcode":"9940",
    "addr:street":"Dorp",
    "iso:country":"BE",
    "sg:address":"Sleidinge Dorp 114",
    "sg:city":"Evergem (sleidinge)",
    "sg:classifiers":[
        {
            "category":"Shopping",
            "subcategory":"Crafts & Fabrics",
            "type":"Retail Goods"
        }
    ],
    "sg:phone":"+32 9 357 52 30",
    "sg:postcode":"9940",
    "sg:province":"Oost-Vlaanderen",
    "sg:tags":[
        "silk",
        "-"
    ],
    "wof:name":"Stoffenhuisje ('t)",
    "wof:placetype":"venue"
},
  "geometry": {"coordinates":[3.6802089214,51.1356086731],"type":"Point"}
}