{
  "type": "Feature",
  "properties": {
    "addr:full":"Patronagestraat 5 Zelzate Oost-Vlaanderen 9060",
    "addr:housenumber":"5",
    "addr:postcode":"9060",
    "addr:street":"Patronagestraat",
    "iso:country":"BE",
    "sg:address":"Patronagestraat 5",
    "sg:city":"Zelzate",
    "sg:orig_category":"Fleurs and plantes",
    "sg:phone":"+32 9 342 97 47",
    "sg:postcode":"9060",
    "sg:province":"Oost-Vlaanderen",
    "wof:name":"Esther Van Hulle",
    "wof:placetype":"venue"
},
  "geometry": {"coordinates":[3.8126380444,51.2018966675],"type":"Point"}
}