{
  "type": "Feature",
  "properties": {
    "iso:country":"BE",
    "sg:address":"Brusselsestraat 26",
    "sg:city":"Leuven",
    "sg:classifiers":[
        {
            "category":"Bars & Pubs",
            "subcategory":"Hookah Bar",
            "type":"Food & Drink"
        }
    ],
    "sg:phone":"+32 16 22 54 69",
    "sg:postcode":"3000",
    "sg:province":"Vlaams-Brabant",
    "sg:tags":[
        "scissors",
        "knife"
    ],
    "wof:name":"Lavaerts",
    "wof:placetype":"venue"
},
  "geometry": {"coordinates":[4.6992769241,50.8796844482],"type":"Point"}
}