{
  "type": "Feature",
  "properties": {
    "iso:country":"BE",
    "sg:address":"Ommegangstraat 4",
    "sg:city":"Izegem",
    "sg:orig_category":"Bloemen and planten",
    "sg:phone":"+32 51 30 27 59",
    "sg:postcode":"8870",
    "sg:province":"West-Vlaanderen",
    "wof:name":"Artiflor",
    "wof:placetype":"venue"
},
  "geometry": {"coordinates":[3.2097389698,50.9188804626],"type":"Point"}
}