{
  "type": "Feature",
  "properties": {
    "iso:country":"BE",
    "sg:address":"Rue Haute Voie 91",
    "sg:city":"Li\u00c8ge",
    "sg:orig_category":"Werk and personeelsselectie",
    "sg:phone":"+32 4 252 34 64",
    "sg:postcode":"4000",
    "sg:province":"Li\u00e8ge",
    "wof:name":"Bureau Genty",
    "wof:placetype":"venue"
},
  "geometry": {"coordinates":[5.5515441895,50.6180534363],"type":"Point"}
}