{
  "type": "Feature",
  "properties": {
    "iso:country":"BE",
    "sg:address":"Parklaan 39",
    "sg:city":"Aalst",
    "sg:orig_category":"Non-Classified Establishments",
    "sg:phone":"+32 53 71 10 14",
    "sg:postcode":"9300",
    "sg:province":"Oost-Vlaanderen",
    "wof:name":"Lama",
    "wof:placetype":"venue"
},
  "geometry": {"coordinates":[4.0435819626,50.9314498901],"type":"Point"}
}