{
  "type": "Feature",
  "properties": {
    "iso:country":"BE",
    "sg:address":"Bruul 22",
    "sg:city":"Mechelen",
    "sg:classifiers":[
        {
            "category":"Shopping",
            "subcategory":"Clothing, Apparel, & Fashions",
            "type":"Retail Goods"
        }
    ],
    "sg:phone":"+32 15 21 02 05",
    "sg:postcode":"2800",
    "sg:province":"Antwerpen",
    "sg:tags":[
        "lady",
        "clothing",
        "-"
    ],
    "wof:name":"Fellini Bvba",
    "wof:placetype":"venue"
},
  "geometry": {"coordinates":[4.4806919098,51.02709198],"type":"Point"}
}