{
  "type": "Feature",
  "properties": {
    "iso:country":"BE",
    "sg:address":"Rue Des Prisonniers De Guerre 18",
    "sg:city":"Namur",
    "sg:orig_category":"Afbraak- and draineerwerken",
    "sg:phone":"+32 81 46 29 88",
    "sg:postcode":"5100",
    "sg:province":"Namur",
    "wof:name":"Sogeter",
    "wof:placetype":"venue"
},
  "geometry": {"coordinates":[4.8738260269,50.4203834534],"type":"Point"}
}