{
  "type": "Feature",
  "properties": {
    "addr:full":"R Jean Doinet 40 Dolembreux Li\u00e8ge 4140",
    "addr:housenumber":"40",
    "addr:postcode":"4140",
    "addr:street":"R Jean Doinet",
    "iso:country":"BE",
    "sg:address":"R Jean Doinet 40",
    "sg:city":"Dolembreux",
    "sg:classifiers":[
        {
            "category":"Shopping",
            "subcategory":"Pawn Shop",
            "type":"Retail Goods"
        }
    ],
    "sg:phone":"+32 3 825 00 66",
    "sg:postcode":"4140",
    "sg:province":"Li\u00e8ge",
    "sg:tags":[
        "audiometer"
    ],
    "wof:name":"Medata Nv",
    "wof:placetype":"venue"
},
  "geometry": {"coordinates":[4.3849282265,51.1649894714],"type":"Point"}
}