{
  "type": "Feature",
  "properties": {
    "iso:country":"BE",
    "sg:address":"Leemputstraat 36",
    "sg:city":"Mechelen (muizen)",
    "sg:classifiers":[
        {
            "category":"Health Services",
            "subcategory":"Doctor",
            "type":"Services"
        }
    ],
    "sg:phone":"+32 15 42 12 77",
    "sg:postcode":"2812",
    "sg:province":"Antwerpen",
    "sg:tags":[
        "medicinephysicians",
        "surgeon"
    ],
    "wof:name":"De Clercq J",
    "wof:placetype":"venue"
},
  "geometry": {"coordinates":[4.5048899651,51.0100517273],"type":"Point"}
}