{
  "type": "Feature",
  "properties": {
    "addr:full":"Rue Paul Janson 53 Charleroi Hainaut 6040",
    "addr:housenumber":"53",
    "addr:postcode":"6040",
    "addr:street":"Rue Paul Janson;Hainaut",
    "iso:country":"BE",
    "sg:address":"Rue Paul Janson 53",
    "sg:city":"Charleroi",
    "sg:orig_category":"Kapsalons Schoonheidssalons",
    "sg:phone":"+32 71 35 59 58",
    "sg:postcode":"6040",
    "sg:province":"Hainaut",
    "wof:name":"Claudine Michaux",
    "wof:placetype":"venue"
},
  "geometry": {"coordinates":[4.4121432304,50.4471511841],"type":"Point"}
}