{
  "type": "Feature",
  "properties": {
    "addr:full":"Diksmuidestraat 15 Middelkerke West-Vlaanderen 8433",
    "addr:housenumber":"15",
    "addr:postcode":"8433",
    "addr:street":"Diksmuidestraat",
    "iso:country":"BE",
    "sg:address":"Diksmuidestraat 15",
    "sg:city":"Middelkerke",
    "sg:orig_category":"Herstellingen and onderhoud van auto's",
    "sg:phone":"+32 59 31 22 31",
    "sg:postcode":"8433",
    "sg:province":"West-Vlaanderen",
    "wof:name":"Hans Vermote",
    "wof:placetype":"venue"
},
  "geometry": {"coordinates":[2.8860800266,51.1183242798],"type":"Point"}
}