{
  "type": "Feature",
  "properties": {
    "iso:country":"BE",
    "sg:address":"Zandkuil 31",
    "sg:city":"Herentals",
    "sg:classifiers":[
        {
            "category":"Insurance",
            "subcategory":"Insurance Agent",
            "type":"Services"
        }
    ],
    "sg:phone":"+32 14 26 39 78",
    "sg:postcode":"2200",
    "sg:province":"Antwerpen",
    "sg:tags":[
        "verzekeringsmakelaars",
        "expert"
    ],
    "wof:name":"J. Ven",
    "wof:placetype":"venue"
},
  "geometry": {"coordinates":[4.8311300278,51.1359519958],"type":"Point"}
}