{
  "type": "Feature",
  "properties": {
    "iso:country":"BE",
    "sg:address":"Eerstestraat 34",
    "sg:city":"Sint-laureins",
    "sg:orig_category":"Varkenskwekers",
    "sg:phone":"+32 9 377 37 70",
    "sg:postcode":"9980",
    "sg:province":"Oost-Vlaanderen",
    "wof:name":"Geert Vanderostyne",
    "wof:placetype":"venue"
},
  "geometry": {"coordinates":[3.5513119698,51.2257232666],"type":"Point"}
}