{
  "type": "Feature",
  "properties": {
    "iso:country":"BE",
    "sg:address":"Zuivelmarkt 10",
    "sg:city":"Hasselt",
    "sg:classifiers":[
        {
            "category":"Restaurant",
            "type":"Food & Drink"
        }
    ],
    "sg:phone":"+32 11 22 03 00",
    "sg:postcode":"3500",
    "sg:province":"Limburg",
    "wof:name":"Numero Dieci",
    "wof:placetype":"venue"
},
  "geometry": {"coordinates":[5.3393659592,50.9307594299],"type":"Point"}
}