{
  "type": "Feature",
  "properties": {
    "addr:full":"Schepen Dejonghstraat 14 Sint-truiden Limburg 3800",
    "addr:housenumber":"14",
    "addr:postcode":"3800",
    "addr:street":"Schepen Dejonghstraat",
    "iso:country":"BE",
    "sg:address":"Schepen Dejonghstraat 14",
    "sg:city":"Sint-truiden",
    "sg:classifiers":[
        {
            "category":"Professional",
            "subcategory":"Lawyer & Legal Services",
            "type":"Services"
        }
    ],
    "sg:phone":"+32 11 68 22 54",
    "sg:postcode":"3800",
    "sg:province":"Limburg",
    "sg:tags":[
        "notary"
    ],
    "wof:name":"Vreven R",
    "wof:placetype":"venue"
},
  "geometry": {"coordinates":[5.1891422272,50.8145637512],"type":"Point"}
}