{
  "type": "Feature",
  "properties": {
    "addr:full":"Avenue De Mai 51 Sint-lambrechts-woluwe/woluwe-saint-lambert Bruxelles-Capitale 1200",
    "addr:housenumber":"51",
    "addr:postcode":"1200",
    "addr:street":"Avenue De Mai",
    "iso:country":"BE",
    "sg:address":"Avenue De Mai 51",
    "sg:city":"Sint-lambrechts-woluwe/woluwe-saint-lambert",
    "sg:orig_category":"R\u00e9alisation de programmes and logiciels",
    "sg:phone":"+32 2 772 34 16",
    "sg:postcode":"1200",
    "sg:province":"Bruxelles-Capitale",
    "wof:name":"Din Consult",
    "wof:placetype":"venue"
},
  "geometry": {"coordinates":[4.4220972061,50.8482398987],"type":"Point"}
}