{
  "type": "Feature",
  "properties": {
    "iso:country":"BE",
    "sg:address":"Avenue Charles Quint 60",
    "sg:city":"Ganshoren",
    "sg:orig_category":"Meubles D\u00e9taillants, Am\u00e9nagement de B\u00e2timents et de Cuisines",
    "sg:phone":"+32 2 428 20 94",
    "sg:postcode":"1083",
    "sg:province":"Bruxelles-Capitale",
    "wof:name":"Fathia Touil",
    "wof:placetype":"venue"
},
  "geometry": {"coordinates":[4.3116312027,50.8687553406],"type":"Point"}
}