{
  "type": "Feature",
  "properties": {
    "addr:full":"Dekenijstraat 94 Ukkel/uccle Bruxelles-Capitale 1180",
    "addr:housenumber":"94",
    "addr:postcode":"1180",
    "addr:street":"Dekenijstraat;/",
    "iso:country":"BE",
    "sg:address":"Dekenijstraat 94",
    "sg:city":"Ukkel/uccle",
    "sg:orig_category":"Architecten",
    "sg:phone":"+32 2 347 30 19",
    "sg:postcode":"1180",
    "sg:province":"Bruxelles-Capitale",
    "wof:name":"Beno\u00cet Jacques",
    "wof:placetype":"venue"
},
  "geometry": {"coordinates":[4.3396420479,50.804397583],"type":"Point"}
}