{
  "type": "Feature",
  "properties": {
    "addr:full":"Avenue Du Vossegat 19 Ukkel (brussel) Bruxelles-Capitale 1180",
    "addr:housenumber":"19",
    "addr:postcode":"1180",
    "addr:street":"Avenue Du Vossegat",
    "iso:country":"BE",
    "sg:address":"Avenue Du Vossegat 19",
    "sg:city":"Ukkel (brussel)",
    "sg:orig_category":"Informaticaconsulenten",
    "sg:phone":"+32 2 376 12 21",
    "sg:postcode":"1180",
    "sg:province":"Bruxelles-Capitale",
    "wof:name":"Somewhere Web Theux",
    "wof:placetype":"venue"
},
  "geometry": {"coordinates":[4.3319659233,50.8027458191],"type":"Point"}
}