{
  "type": "Feature",
  "properties": {
    "addr:full":"Dokter Elie Lambottestr. 230 Schaarbeek/schaerbeek Bruxelles-Capitale 1030",
    "addr:housenumber":"230",
    "addr:postcode":"1030",
    "addr:street":"Dokter Elie Lambottestr.",
    "iso:country":"BE",
    "sg:address":"Dokter Elie Lambottestr. 230",
    "sg:city":"Schaarbeek/schaerbeek",
    "sg:orig_category":"Kapsalons",
    "sg:phone":"+32 2 242 17 88",
    "sg:postcode":"1030",
    "sg:province":"Bruxelles-Capitale",
    "wof:name":"Coiffure Anne-marie",
    "wof:placetype":"venue"
},
  "geometry": {"coordinates":[4.3921961784,50.8739624023],"type":"Point"}
}