{
  "type": "Feature",
  "properties": {
    "iso:country":"BE",
    "sg:address":"Steenweg Op Brussel 215",
    "sg:city":"Wemmel/wemmel",
    "sg:orig_category":"Artsen and specialisten",
    "sg:phone":"+32 2 460 41 76",
    "sg:postcode":"1780",
    "sg:province":"Vlaams-Brabant",
    "wof:name":"Philippe De Man",
    "wof:placetype":"venue"
},
  "geometry": {"coordinates":[4.3089017868,50.9009017944],"type":"Point"}
}