{
  "type": "Feature",
  "properties": {
    "addr:full":"Leestsesteenweg 93 Mechelen Antwerpen 2800",
    "addr:housenumber":"93",
    "addr:postcode":"2800",
    "addr:street":"Leestsesteenweg",
    "iso:country":"BE",
    "sg:address":"Leestsesteenweg 93",
    "sg:city":"Mechelen",
    "sg:orig_category":"Babyspullen Fantasieartikelen Geschenken and souvenirs Kantoormateriaal Speelgoed Verhuur textielart",
    "sg:phone":"+32 15 27 72 24",
    "sg:postcode":"2800",
    "sg:province":"Antwerpen",
    "wof:name":"Happyland",
    "wof:placetype":"venue"
},
  "geometry": {"coordinates":[4.4351601601,51.0381278992],"type":"Point"}
}