{
  "type": "Feature",
  "properties": {
    "addr:full":"Kanunnik Duboisplein 1 Oostkamp West-Vlaanderen 8020",
    "addr:housenumber":"1",
    "addr:postcode":"8020",
    "addr:street":"Kanunnik Duboisplein",
    "iso:country":"BE",
    "sg:address":"Kanunnik Duboisplein 1",
    "sg:city":"Oostkamp",
    "sg:orig_category":"Pain, p\u00e2tisseries and confiseries",
    "sg:phone":"+32 50 82 37 41",
    "sg:postcode":"8020",
    "sg:province":"West-Vlaanderen",
    "wof:name":"Johan Degroote",
    "wof:placetype":"venue"
},
  "geometry": {"coordinates":[3.232683897,51.1372032166],"type":"Point"}
}