{
  "type": "Feature",
  "properties": {
    "addr:full":"Rue De La Jonction 9 Bertrix Luxembourg 6880",
    "addr:housenumber":"9",
    "addr:postcode":"6880",
    "addr:street":"Rue De La Jonction",
    "iso:country":"BE",
    "sg:address":"Rue De La Jonction 9",
    "sg:city":"Bertrix",
    "sg:classifiers":[
        {
            "category":"Professional",
            "subcategory":"Testing Lab",
            "type":"Services"
        }
    ],
    "sg:phone":"+32 61 41 09 00",
    "sg:postcode":"6880",
    "sg:province":"Luxembourg",
    "sg:tags":[
        "laboratory",
        "medical"
    ],
    "wof:name":"Laboratoire Bio-semois Sprl",
    "wof:placetype":"venue"
},
  "geometry": {"coordinates":[5.2547688484,49.8556442261],"type":"Point"}
}