{
  "type": "Feature",
  "properties": {
    "iso:country":"BE",
    "sg:address":"Lodewijk De Raetlaan 55-57",
    "sg:city":"Izegem",
    "sg:orig_category":"Non-Classified Establishments",
    "sg:phone":"+32 51 30 01 14",
    "sg:postcode":"8870",
    "sg:province":"West-Vlaanderen",
    "wof:name":"Alverin Nv-sa",
    "wof:placetype":"venue"
},
  "geometry": {"coordinates":[3.1867010593,50.931137085],"type":"Point"}
}