{
  "type": "Feature",
  "properties": {
    "addr:full":"Beelbroekstraat 23 Gent (sint-amandsberg) Oost-Vlaanderen 9040",
    "addr:housenumber":"23",
    "addr:postcode":"9040",
    "addr:street":"Beelbroekstraat",
    "iso:country":"BE",
    "sg:address":"Beelbroekstraat 23",
    "sg:city":"Gent (sint-amandsberg)",
    "sg:classifiers":[
        {
            "category":"Retail",
            "subcategory":"Animal Services",
            "type":"Services"
        }
    ],
    "sg:phone":"+32 9 330 52 76",
    "sg:postcode":"9040",
    "sg:province":"Oost-Vlaanderen",
    "sg:tags":[
        "grooming",
        "-",
        "dog"
    ],
    "wof:name":"Hondenkapster (de)",
    "wof:placetype":"venue"
},
  "geometry": {"coordinates":[3.7805349827,51.0742111206],"type":"Point"}
}