{
  "type": "Feature",
  "properties": {
    "iso:country":"BE",
    "sg:address":"Rue De Huy 83",
    "sg:city":"Villers-le-bouillet",
    "sg:classifiers":[
        {
            "category":"Professional",
            "subcategory":"Art Services",
            "type":"Services"
        }
    ],
    "sg:phone":"+32 85 23 40 57",
    "sg:postcode":"4530",
    "sg:province":"Li\u00e8ge",
    "sg:tags":[
        "photographer",
        "-",
        "portrait"
    ],
    "wof:name":"Masson J.l.",
    "wof:placetype":"venue"
},
  "geometry": {"coordinates":[5.2673430443,50.5606384277],"type":"Point"}
}