{
  "type": "Feature",
  "properties": {
    "iso:country":"BE",
    "sg:address":"Tiensesteenweg 6",
    "sg:city":"Sint-truiden",
    "sg:orig_category":"Epiceries",
    "sg:phone":"+32 11 68 99 56",
    "sg:postcode":"3800",
    "sg:province":"Limburg",
    "wof:name":"Gorashop",
    "wof:placetype":"venue"
},
  "geometry": {"coordinates":[5.184032917,50.8133049011],"type":"Point"}
}