{
  "type": "Feature",
  "properties": {
    "addr:full":"Rue Du R\u00e9servoir 175 Charleroi (gilly) Hainaut 6060",
    "addr:housenumber":"175",
    "addr:postcode":"6060",
    "addr:street":"Rue Du Re\u0301Servoir",
    "iso:country":"BE",
    "sg:address":"Rue Du R\u00e9servoir 175",
    "sg:city":"Charleroi (gilly)",
    "sg:classifiers":[
        {
            "category":"Real Estate",
            "subcategory":"Architect",
            "type":"Services"
        }
    ],
    "sg:phone":"+32 71 48 98 70",
    "sg:postcode":"6060",
    "sg:province":"Hainaut",
    "wof:name":"Leroy P",
    "wof:placetype":"venue"
},
  "geometry": {"coordinates":[4.4880981445,50.4251937866],"type":"Point"}
}