{
  "type": "Feature",
  "properties": {
    "addr:full":"Katwilgweg 7b Antwerpen Antwerpen 2050",
    "addr:housenumber":"7b",
    "addr:postcode":"2050",
    "addr:street":"Katwilgweg",
    "iso:country":"BE",
    "sg:address":"Katwilgweg 7b",
    "sg:city":"Antwerpen",
    "sg:orig_category":"Speciaalzaken",
    "sg:phone":"+32 3 254 04 20",
    "sg:postcode":"2050",
    "sg:province":"Antwerpen",
    "wof:name":"Altera",
    "wof:placetype":"venue"
},
  "geometry": {"coordinates":[4.3552031517,51.2194213867],"type":"Point"}
}