{
  "type": "Feature",
  "properties": {
    "iso:country":"BE",
    "sg:address":"Rue Froide Bise 9",
    "sg:city":"Villers-la-ville",
    "sg:classifiers":[
        {
            "category":"Real Estate",
            "subcategory":"Architect",
            "type":"Services"
        }
    ],
    "sg:phone":"+32 71 87 97 21",
    "sg:postcode":"1495",
    "sg:province":"Brabant Wallon",
    "wof:name":"Nimmegeers D",
    "wof:placetype":"venue"
},
  "geometry": {"coordinates":[4.5342049599,50.5770683289],"type":"Point"}
}