{
  "type": "Feature",
  "properties": {
    "addr:full":"Roesbruggestraat 11ba Poperinge West-Vlaanderen 8972",
    "addr:postcode":"8972",
    "addr:street":"Roesbruggestraat;West-Vlaanderen",
    "iso:country":"BE",
    "sg:address":"Roesbruggestraat 11ba",
    "sg:city":"Poperinge",
    "sg:orig_category":"Studios photographiques",
    "sg:phone":"+32 57 30 03 24",
    "sg:postcode":"8972",
    "sg:province":"West-Vlaanderen",
    "wof:name":"Bernard De Grendel",
    "wof:placetype":"venue"
},
  "geometry": {"coordinates":[2.6479949951,50.8958435059],"type":"Point"}
}