{
  "type": "Feature",
  "properties": {
    "addr:full":"Dijk 31 Koksijde West-Vlaanderen 8670",
    "addr:housenumber":"31",
    "addr:postcode":"8670",
    "addr:street":"Dijk",
    "iso:country":"BE",
    "sg:address":"Dijk 31",
    "sg:city":"Koksijde",
    "sg:orig_category":"Binnenhuisarchitecten",
    "sg:phone":"+32 58 31 29 19",
    "sg:postcode":"8670",
    "sg:province":"West-Vlaanderen",
    "wof:name":"Edward Westerduin",
    "wof:placetype":"venue"
},
  "geometry": {"coordinates":[2.6981799603,51.1043968201],"type":"Point"}
}