{
  "type": "Feature",
  "properties": {
    "iso:country":"BE",
    "sg:address":"Ruitersweg 10",
    "sg:city":"Kortrijk",
    "sg:orig_category":"Location d'articles de sport, de sport nautique and de camping. Clubs de sport",
    "sg:phone":"+32 56 22 38 89",
    "sg:postcode":"8500",
    "sg:province":"West-Vlaanderen",
    "wof:name":"K.k.y.k.c.",
    "wof:placetype":"venue"
},
  "geometry": {"coordinates":[3.2742249966,50.8357772827],"type":"Point"}
}