{
  "type": "Feature",
  "properties": {
    "addr:full":"Tongerlostraat 59 Westerlo Antwerpen 2260",
    "addr:housenumber":"59",
    "addr:postcode":"2260",
    "addr:street":"Tongerlostraat",
    "iso:country":"BE",
    "sg:address":"Tongerlostraat 59",
    "sg:city":"Westerlo",
    "sg:orig_category":"Installation de menuiserie en bois and plastique",
    "sg:phone":"+32 14 23 41 49",
    "sg:postcode":"2260",
    "sg:province":"Antwerpen",
    "wof:name":"Ceulemans Gebr",
    "wof:placetype":"venue"
},
  "geometry": {"coordinates":[4.9055948257,51.1302452087],"type":"Point"}
}