{
  "type": "Feature",
  "properties": {
    "iso:country":"BE",
    "sg:address":"Stationsstraat 6",
    "sg:city":"Diepenbeek",
    "sg:orig_category":"Pharmaciens",
    "sg:phone":"+32 11 32 30 23",
    "sg:postcode":"3590",
    "sg:province":"Limburg",
    "wof:name":"Apotheek De Voorzorg",
    "wof:placetype":"venue"
},
  "geometry": {"coordinates":[5.4196381569,50.9094238281],"type":"Point"}
}