{
  "type": "Feature",
  "properties": {
    "addr:full":"Peter Benoitstraat 6 Halle Vlaams-Brabant 1500",
    "addr:housenumber":"6",
    "addr:postcode":"1500",
    "addr:street":"Peter Benoitstraat",
    "iso:country":"BE",
    "sg:address":"Peter Benoitstraat 6",
    "sg:city":"Halle",
    "sg:orig_category":"DIVERSE RECREATIEVE ACTIVITEITEN",
    "sg:phone":"+32 2 356 49 29",
    "sg:postcode":"1500",
    "sg:province":"Vlaams-Brabant",
    "wof:name":"Halse Bridge Club",
    "wof:placetype":"venue"
},
  "geometry": {"coordinates":[4.2465190887,50.7290306091],"type":"Point"}
}