{
  "type": "Feature",
  "properties": {
    "iso:country":"BE",
    "sg:address":"Froidbermont 7a",
    "sg:city":"Olne",
    "sg:classifiers":[
        {
            "category":"Health Services",
            "subcategory":"Medical Lab",
            "type":"Services"
        }
    ],
    "sg:phone":"+32 87 26 74 78",
    "sg:postcode":"4877",
    "sg:province":"Li\u00e8ge",
    "sg:tags":[
        "laboratory",
        "dental"
    ],
    "wof:name":"Frerotte J",
    "wof:placetype":"venue"
},
  "geometry": {"coordinates":[5.7536687851,50.5894317627],"type":"Point"}
}