{
  "type": "Feature",
  "properties": {
    "iso:country":"BE",
    "sg:address":"Zeeweg 131",
    "sg:city":"Oudenburg",
    "sg:orig_category":"Pluimveekwekers",
    "sg:phone":"+32 59 25 06 05",
    "sg:postcode":"8460",
    "sg:province":"West-Vlaanderen",
    "wof:name":"F. Vandamme",
    "wof:placetype":"venue"
},
  "geometry": {"coordinates":[3.0262789726,51.1694030762],"type":"Point"}
}