{
  "type": "Feature",
  "properties": {
    "iso:country":"BE",
    "sg:address":"Grote Baan 283",
    "sg:city":"Waasmunster",
    "sg:classifiers":[
        {
            "category":"Utilities",
            "subcategory":"Mobile Phone",
            "type":"Services"
        }
    ],
    "sg:phone":"+32 9 349 25 99",
    "sg:postcode":"9250",
    "sg:province":"Oost-Vlaanderen",
    "sg:tags":[
        "access",
        "gsm",
        "-",
        "apparatus"
    ],
    "wof:name":"Mobi-sat Bvba",
    "wof:placetype":"venue"
},
  "geometry": {"coordinates":[4.0335960388,51.1244926453],"type":"Point"}
}