{
  "type": "Feature",
  "properties": {
    "addr:full":"Rue De La Croisette 196 Maurage Hainaut 7110",
    "addr:housenumber":"196",
    "addr:postcode":"7110",
    "addr:street":"Rue De La Croisette",
    "iso:country":"BE",
    "sg:address":"Rue De La Croisette 196",
    "sg:city":"Maurage",
    "sg:orig_category":"Entretien and r\u00e9parations de voitures",
    "sg:phone":"+32 65 75 93 42",
    "sg:postcode":"7110",
    "sg:province":"Hainaut",
    "wof:name":"Pasquale Di Giosia",
    "wof:placetype":"venue"
},
  "geometry": {"coordinates":[4.101418972,50.4595336914],"type":"Point"}
}