{
  "type": "Feature",
  "properties": {
    "iso:country":"BE",
    "sg:address":"Rue Ecosse 5-11",
    "sg:city":"Rumes (taintignies)",
    "sg:classifiers":[
        {
            "category":"Professional",
            "subcategory":"Printing & Photocopies",
            "type":"Services"
        }
    ],
    "sg:phone":"+32 69 64 84 21",
    "sg:postcode":"7618",
    "sg:province":"Hainaut",
    "sg:tags":[
        "-",
        "offset"
    ],
    "wof:name":"Dussart R",
    "wof:placetype":"venue"
},
  "geometry": {"coordinates":[3.3457028866,50.5410575867],"type":"Point"}
}