{
  "type": "Feature",
  "properties": {
    "addr:full":"Kasteeldreef 75 Schilde Antwerpen 2970",
    "addr:housenumber":"75",
    "addr:postcode":"2970",
    "addr:street":"Kasteeldreef",
    "iso:country":"BE",
    "sg:address":"Kasteeldreef 75",
    "sg:city":"Schilde",
    "sg:classifiers":[
        {
            "category":"Professional",
            "subcategory":"Management & Consulting",
            "type":"Services"
        }
    ],
    "sg:phone":"+32 3 354 15 54",
    "sg:postcode":"2970",
    "sg:province":"Antwerpen",
    "sg:tags":[
        "-",
        "processing",
        "data",
        "consultant"
    ],
    "wof:name":"Lins & Co",
    "wof:placetype":"venue"
},
  "geometry": {"coordinates":[4.559445858,51.2277450562],"type":"Point"}
}