{
  "type": "Feature",
  "properties": {
    "iso:country":"BE",
    "sg:address":"Rue Penne De Mont 2",
    "sg:city":"Fl\u00e9malle",
    "sg:classifiers":[
        {
            "category":"Real Estate",
            "subcategory":"Architect",
            "type":"Services"
        }
    ],
    "sg:phone":"+32 4 233 71 44",
    "sg:postcode":"4400",
    "sg:province":"Li\u00e8ge",
    "wof:name":"Canei S",
    "wof:placetype":"venue"
},
  "geometry": {"coordinates":[5.4576368332,50.6093139648],"type":"Point"}
}