{
  "type": "Feature",
  "properties": {
    "addr:full":"R. De L'eglise St.martin 40 Ganshoren/ganshoren Bruxelles-Capitale 1083",
    "addr:housenumber":"40",
    "addr:postcode":"1083",
    "addr:street":"St.Martin",
    "iso:country":"BE",
    "sg:address":"R. De L'eglise St.martin 40",
    "sg:city":"Ganshoren/ganshoren",
    "sg:orig_category":"Cr\u00e8ches and garderies d'enfants",
    "sg:phone":"+32 2 420 65 69",
    "sg:postcode":"1083",
    "sg:province":"Bruxelles-Capitale",
    "wof:name":"Cr\u00c8che Communale",
    "wof:placetype":"venue"
},
  "geometry": {"coordinates":[4.3088898659,50.873588562],"type":"Point"}
}