{
  "type": "Feature",
  "properties": {
    "addr:full":"Quai De Brabant 16br Charleroi Hainaut 6000",
    "addr:housenumber":"16br",
    "addr:postcode":"6000",
    "addr:street":"Quai De Brabant;Hainaut",
    "iso:country":"BE",
    "sg:address":"Quai De Brabant 16br",
    "sg:city":"Charleroi",
    "sg:orig_category":"Banken and kredietinstellingen",
    "sg:phone":"+32 71 70 03 20",
    "sg:postcode":"6000",
    "sg:province":"Hainaut",
    "wof:name":"Deutsche Bank",
    "wof:placetype":"venue"
},
  "geometry": {"coordinates":[4.4419569969,50.4060020447],"type":"Point"}
}