{
  "type": "Feature",
  "properties": {
    "addr:full":"Alsembergse Steenweg 388 Ukkel/uccle Bruxelles-Capitale 1180",
    "addr:housenumber":"388",
    "addr:postcode":"1180",
    "addr:street":"Alsembergse Steenweg;/",
    "iso:country":"BE",
    "sg:address":"Alsembergse Steenweg 388",
    "sg:city":"Ukkel/uccle",
    "sg:orig_category":"Industri\u00eble wasserijen and droogkuis",
    "sg:phone":"+32 2 345 30 44",
    "sg:postcode":"1180",
    "sg:province":"Bruxelles-Capitale",
    "wof:name":"Moderna Shop",
    "wof:placetype":"venue"
},
  "geometry": {"coordinates":[4.3393950462,50.814201355],"type":"Point"}
}