{
  "type": "Feature",
  "properties": {
    "iso:country":"BE",
    "sg:address":"Koningin Astridlaan 49",
    "sg:city":"Maldegem",
    "sg:classifiers":[
        {
            "category":"Taxi",
            "type":"Transportation"
        }
    ],
    "sg:phone":"+32 50 71 26 45",
    "sg:postcode":"9990",
    "sg:province":"Oost-Vlaanderen",
    "sg:tags":[
        "taxicab"
    ],
    "wof:name":"V D B Taxi",
    "wof:placetype":"venue"
},
  "geometry": {"coordinates":[3.4276759624,51.2075958252],"type":"Point"}
}