{
  "type": "Feature",
  "properties": {
    "iso:country":"BE",
    "sg:address":"Ossevenstraat 15",
    "sg:city":"Beerse",
    "sg:orig_category":"Boekhouders",
    "sg:phone":"+32 14 61 79 37",
    "sg:postcode":"2340",
    "sg:province":"Antwerpen",
    "wof:name":"Dirk Sas",
    "wof:placetype":"venue"
},
  "geometry": {"coordinates":[4.8699688911,51.3154182434],"type":"Point"}
}