{
  "type": "Feature",
  "properties": {
    "addr:full":"Place Albert Ier Rochefort Namur 5580",
    "addr:postcode":"5580",
    "addr:street":"Place Albert Ier",
    "iso:country":"BE",
    "sg:address":"Place Albert Ier",
    "sg:city":"Rochefort",
    "sg:orig_category":"Foto-uitrusting Fotografen and fotostudio's",
    "sg:phone":"+32 84 21 44 44",
    "sg:postcode":"5580",
    "sg:province":"Namur",
    "wof:name":"Positif Rochepot Pierlot",
    "wof:placetype":"venue"
},
  "geometry": {"coordinates":[5.2237300873,50.159412384],"type":"Point"}
}