{
  "type": "Feature",
  "properties": {
    "iso:country":"BE",
    "sg:address":"Gammel 91",
    "sg:city":"Rijkevorsel",
    "sg:classifiers":[
        {
            "category":"Food & Beverages",
            "subcategory":"Fruits & Vegetables",
            "type":"Retail Goods"
        }
    ],
    "sg:phone":"+32 3 340 84 00",
    "sg:postcode":"2310",
    "sg:province":"Antwerpen",
    "sg:tags":[
        "preserve",
        "frozen",
        "product",
        "drink",
        "related"
    ],
    "wof:name":"Mondi Foods Nv",
    "wof:placetype":"venue"
},
  "geometry": {"coordinates":[4.7561841011,51.378780365],"type":"Point"}
}