{
  "type": "Feature",
  "properties": {
    "iso:country":"BE",
    "sg:address":"Fu\u00c9risonplaats 10",
    "sg:city":"Steenokkerzeel",
    "sg:orig_category":"Rev\u00eatements de sols and murs",
    "sg:phone":"+32 2 759 67 76",
    "sg:postcode":"1820",
    "sg:province":"Vlaams-Brabant",
    "wof:name":"Magda Janssen",
    "wof:placetype":"venue"
},
  "geometry": {"coordinates":[4.5129270554,50.9097480774],"type":"Point"}
}