{
  "type": "Feature",
  "properties": {
    "iso:country":"BE",
    "sg:address":"Riemsterweg 415",
    "sg:city":"Bilzen",
    "sg:orig_category":"Stations-service and carburants. Entretien and r\u00e9parations de voitures",
    "sg:phone":"+32 12 45 13 08",
    "sg:postcode":"3740",
    "sg:province":"Limburg",
    "wof:name":"Garage Cuenen",
    "wof:placetype":"venue"
},
  "geometry": {"coordinates":[5.5292901993,50.8601989746],"type":"Point"}
}