{
  "type": "Feature",
  "properties": {
    "addr:full":"Brekelen 42 Wuustwezel Antwerpen 2990",
    "addr:housenumber":"42",
    "addr:postcode":"2990",
    "addr:street":"Brekelen",
    "iso:country":"BE",
    "sg:address":"Brekelen 42",
    "sg:city":"Wuustwezel",
    "sg:classifiers":[
        {
            "category":"Food & Beverages",
            "subcategory":"Supermarket",
            "type":"Retail Goods"
        }
    ],
    "sg:phone":"+32 3 669 97 44",
    "sg:postcode":"2990",
    "sg:province":"Antwerpen",
    "sg:tags":[
        "frozen",
        "-"
    ],
    "wof:name":"Van Mengsel J",
    "wof:placetype":"venue"
},
  "geometry": {"coordinates":[4.5812058449,51.3876838684],"type":"Point"}
}