{
  "type": "Feature",
  "properties": {
    "addr:full":"Dr. Armand Rubbensstraat 10 Zele Oost-Vlaanderen 9240",
    "addr:housenumber":"10",
    "addr:postcode":"9240",
    "addr:street":"Dr. Armand Rubbensstraat",
    "iso:country":"BE",
    "sg:address":"Dr. Armand Rubbensstraat 10",
    "sg:city":"Zele",
    "sg:orig_category":"Epiceries",
    "sg:phone":"+32 52 45 30 08",
    "sg:postcode":"9240",
    "sg:province":"Oost-Vlaanderen",
    "wof:name":"Yilmaz E. & Yilmaz M.",
    "wof:placetype":"venue"
},
  "geometry": {"coordinates":[4.037899971,51.0681152344],"type":"Point"}
}