{
  "type": "Feature",
  "properties": {
    "addr:full":"Bld Frankignoul 5 Li\u00e8ge 1 (li\u00e8ge 2) Li\u00e8ge 4020",
    "addr:housenumber":"5;1;2",
    "addr:postcode":"4020",
    "addr:street":"Bld Frankignoul",
    "iso:country":"BE",
    "sg:address":"Bld Frankignoul 5",
    "sg:city":"Li\u00e8ge 1 (li\u00e8ge 2)",
    "sg:classifiers":[
        {
            "category":"Home & Garden",
            "subcategory":"Household Appliances",
            "type":"Retail Goods"
        }
    ],
    "sg:phone":"+32 4 342 30 20",
    "sg:postcode":"4020",
    "sg:province":"Li\u00e8ge",
    "sg:tags":[
        "repair",
        "mainten",
        "-",
        "electric"
    ],
    "wof:name":"Deravet Ets Sa",
    "wof:placetype":"venue"
},
  "geometry": {"coordinates":[5.5866470337,50.6285743713],"type":"Point"}
}