{
  "type": "Feature",
  "properties": {
    "iso:country":"BE",
    "sg:address":"Avenue Alfred Madoux 131",
    "sg:city":"Sint-pieters-woluwe/woluwe-saint-pierre",
    "sg:orig_category":"Notaires",
    "sg:phone":"+32 2 770 60 34",
    "sg:postcode":"1150",
    "sg:province":"Bruxelles-Capitale",
    "wof:name":"Liliane Panneels",
    "wof:placetype":"venue"
},
  "geometry": {"coordinates":[4.4504637718,50.8300094604],"type":"Point"}
}