{
  "type": "Feature",
  "properties": {
    "addr:full":"Fort Ii Straat 135 Wommelgem Antwerpen 2160",
    "addr:housenumber":"135",
    "addr:postcode":"2160",
    "addr:street":"Fort Ii Straat",
    "iso:country":"BE",
    "sg:address":"Fort Ii Straat 135",
    "sg:city":"Wommelgem",
    "sg:orig_category":"V\u00e9hicules automobiles. Entretien and r\u00e9parations de voitures",
    "sg:phone":"+32 3 322 76 43",
    "sg:postcode":"2160",
    "sg:province":"Antwerpen",
    "wof:name":"Garage Erwico",
    "wof:placetype":"venue"
},
  "geometry": {"coordinates":[4.4892659187,51.2041053772],"type":"Point"}
}