{
  "type": "Feature",
  "properties": {
    "iso:country":"BE",
    "sg:address":"Route De Seraing 66",
    "sg:city":"Neupre",
    "sg:orig_category":"Jardinage",
    "sg:phone":"+32 4 371 25 09",
    "sg:postcode":"4122",
    "sg:province":"Li\u00e8ge",
    "wof:name":"Eurojardin",
    "wof:placetype":"venue"
},
  "geometry": {"coordinates":[5.493461132,50.5456848145],"type":"Point"}
}