{
  "type": "Feature",
  "properties": {
    "addr:full":"Tweekerkenstraat 47 Brussel/bruxelles Bruxelles-Capitale 1000",
    "addr:housenumber":"47",
    "addr:postcode":"1000",
    "addr:street":"Tweekerkenstraat;/",
    "iso:country":"BE",
    "sg:address":"Tweekerkenstraat 47",
    "sg:city":"Brussel/bruxelles",
    "sg:orig_category":"Krantenuitgeverijen Tijdschriftenuitgeverijen",
    "sg:phone":"+32 2 282 17 20",
    "sg:postcode":"1000",
    "sg:province":"Bruxelles-Capitale",
    "wof:name":"Bond Beter Leefmilieu Vl.",
    "wof:placetype":"venue"
},
  "geometry": {"coordinates":[4.3732738495,50.8469848633],"type":"Point"}
}