{
  "type": "Feature",
  "properties": {
    "addr:full":"Haachtsesteenweg 84 Machelen Vlaams-Brabant 1831",
    "addr:housenumber":"84",
    "addr:postcode":"1831",
    "addr:street":"Haachtsesteenweg",
    "iso:country":"BE",
    "sg:address":"Haachtsesteenweg 84",
    "sg:city":"Machelen",
    "sg:orig_category":"Bouwmaterialen Gh",
    "sg:phone":"+32 2 720 64 48",
    "sg:postcode":"1831",
    "sg:province":"Vlaams-Brabant",
    "wof:name":"Boermans",
    "wof:placetype":"venue"
},
  "geometry": {"coordinates":[4.4347791672,50.8952865601],"type":"Point"}
}