{
  "type": "Feature",
  "properties": {
    "iso:country":"BE",
    "sg:address":"Lummense-kiezel 51",
    "sg:city":"Hasselt (kermt)",
    "sg:classifiers":[
        {
            "category":"Professional",
            "subcategory":"Art Services",
            "type":"Services"
        }
    ],
    "sg:phone":"+32 11 25 18 73",
    "sg:postcode":"3510",
    "sg:province":"Limburg",
    "sg:tags":[
        "installation",
        "cafe",
        "-",
        "equipment"
    ],
    "wof:name":"Menten-ballet Interieurs Nv",
    "wof:placetype":"venue"
},
  "geometry": {"coordinates":[5.3733267784,50.9285812378],"type":"Point"}
}