{
  "type": "Feature",
  "properties": {
    "iso:country":"BE",
    "sg:address":"Kliniekstraat 17",
    "sg:city":"Lommel",
    "sg:orig_category":"Advocaten and juridische adviseurs",
    "sg:phone":"+32 495 81 14 58",
    "sg:postcode":"3920",
    "sg:province":"Limburg",
    "wof:name":"Gert-jan Wolters",
    "wof:placetype":"venue"
},
  "geometry": {"coordinates":[5.3123822212,51.215007782],"type":"Point"}
}