{
  "type": "Feature",
  "properties": {
    "iso:country":"BE",
    "sg:address":"Rue De La Croix 19",
    "sg:city":"Couvin",
    "sg:orig_category":"Plaatsen van vloer- and muurbekleding Schilders",
    "sg:phone":"+32 60 34 67 25",
    "sg:postcode":"5660",
    "sg:province":"Namur",
    "wof:name":"Baudaux Et Fils",
    "wof:placetype":"venue"
},
  "geometry": {"coordinates":[4.5008168221,50.0502357483],"type":"Point"}
}