{
  "type": "Feature",
  "properties": {
    "addr:full":"St.petrus-en-paulusplein 18 Oostende West-Vlaanderen 8400",
    "addr:housenumber":"18",
    "addr:postcode":"8400",
    "addr:street":"St.Petrus-En-Paulusplein",
    "iso:country":"BE",
    "sg:address":"St.petrus-en-paulusplein 18",
    "sg:city":"Oostende",
    "sg:orig_category":"Poissonniers and \u00e9caillers",
    "sg:phone":"+32 59 50 02 24",
    "sg:postcode":"8400",
    "sg:province":"West-Vlaanderen",
    "wof:name":"Lima",
    "wof:placetype":"venue"
},
  "geometry": {"coordinates":[2.9233319759,51.2299156189],"type":"Point"}
}