{
  "type": "Feature",
  "properties": {
    "addr:full":"Stationsstraat 13 Damme West-Vlaanderen 8340",
    "addr:housenumber":"13",
    "addr:postcode":"8340",
    "addr:street":"Stationsstraat",
    "iso:country":"BE",
    "sg:address":"Stationsstraat 13",
    "sg:city":"Damme",
    "sg:orig_category":"Enseignement maternel and primaire",
    "sg:phone":"+32 50 35 04 15",
    "sg:postcode":"8340",
    "sg:province":"West-Vlaanderen",
    "wof:name":"Gemeentel. Lagere School",
    "wof:placetype":"venue"
},
  "geometry": {"coordinates":[3.3210821152,51.2024307251],"type":"Point"}
}