{
  "type": "Feature",
  "properties": {
    "addr:full":"Rue G\u00e9n\u00e9ral Capiaumont 88 Bruxelles (etterbeek) Bruxelles-Capitale 1040",
    "addr:housenumber":"88",
    "addr:postcode":"1040",
    "addr:street":"Rue Ge\u0301Ne\u0301Ral Capiaumont",
    "iso:country":"BE",
    "sg:address":"Rue G\u00e9n\u00e9ral Capiaumont 88",
    "sg:city":"Bruxelles (etterbeek)",
    "sg:classifiers":[
        {
            "category":"Real Estate",
            "subcategory":"Architect",
            "type":"Services"
        }
    ],
    "sg:phone":"+32 2 646 44 17",
    "sg:postcode":"1040",
    "sg:province":"Bruxelles-Capitale",
    "wof:name":"De Vestele J",
    "wof:placetype":"venue"
},
  "geometry": {"coordinates":[4.3849258423,50.8305053711],"type":"Point"}
}