{
  "type": "Feature",
  "properties": {
    "addr:full":"Rue Du Marais 24 Burdinne Li\u00e8ge 4210",
    "addr:housenumber":"24",
    "addr:postcode":"4210",
    "addr:street":"Rue Du Marais",
    "iso:country":"BE",
    "sg:address":"Rue Du Marais 24",
    "sg:city":"Burdinne",
    "sg:classifiers":[
        {
            "category":"Personal",
            "subcategory":"Beauty Salon",
            "type":"Services"
        }
    ],
    "sg:phone":"+32 85 71 18 84",
    "sg:postcode":"4210",
    "sg:province":"Li\u00e8ge",
    "sg:tags":[
        "de",
        "coiffure"
    ],
    "wof:name":"Marie Verlaine",
    "wof:placetype":"venue"
},
  "geometry": {"coordinates":[5.0663290024,50.5815925598],"type":"Point"}
}