{
  "type": "Feature",
  "properties": {
    "iso:country":"BE",
    "sg:address":"Orveiestraat 26",
    "sg:city":"Zwevegem",
    "sg:orig_category":"Jardins botaniques, zoologiques, observatoires and r\u00e9serves naturelles",
    "sg:phone":"+32 56 75 61 39",
    "sg:postcode":"8552",
    "wof:name":"Oude Spoorwegberm",
    "wof:placetype":"venue"
},
  "geometry": {"coordinates":[3.3631370068,50.79529953],"type":"Point"}
}