{
  "type": "Feature",
  "properties": {
    "addr:full":"Rue Haute 80 Bruxelles Bruxelles-Capitale 1000",
    "addr:housenumber":"80",
    "addr:postcode":"1000",
    "addr:street":"Rue Haute",
    "iso:country":"BE",
    "sg:address":"Rue Haute 80",
    "sg:city":"Bruxelles",
    "sg:classifiers":[
        {
            "category":"Shopping",
            "subcategory":"Discount & Variety Stores",
            "type":"Retail Goods"
        }
    ],
    "sg:phone":"+32 2 548 96 96",
    "sg:postcode":"1000",
    "sg:province":"Bruxelles-Capitale",
    "sg:tags":[
        "shop",
        "clearers",
        "curiosity",
        "furniture"
    ],
    "wof:name":"Baden Baden",
    "wof:placetype":"venue"
},
  "geometry": {"coordinates":[4.3513879776,50.8403549194],"type":"Point"}
}