{
  "type": "Feature",
  "properties": {
    "iso:country":"BE",
    "sg:address":"Antwerpsestraat 244",
    "sg:city":"Boom",
    "sg:orig_category":"Textiel",
    "sg:phone":"+32 3 888 07 29",
    "sg:postcode":"2850",
    "sg:province":"Antwerpen",
    "wof:name":"Ketels",
    "wof:placetype":"venue"
},
  "geometry": {"coordinates":[4.3669362068,51.0957794189],"type":"Point"}
}