{
  "type": "Feature",
  "properties": {
    "iso:country":"BE",
    "sg:address":"Waalborrelaan 20",
    "sg:city":"Asse",
    "sg:classifiers":[
        {
            "category":"Professional",
            "subcategory":"Accounting & Tax Preparation",
            "type":"Services"
        }
    ],
    "sg:phone":"+32 2 452 60 39",
    "sg:postcode":"1730",
    "sg:province":"Vlaams-Brabant",
    "sg:tags":[
        "bookkeeper"
    ],
    "wof:name":"Bogaerts N",
    "wof:placetype":"venue"
},
  "geometry": {"coordinates":[4.2034440041,50.9033088684],"type":"Point"}
}