{
  "type": "Feature",
  "properties": {
    "addr:full":"Jozef Duthoystraat 78 Waregem West-Vlaanderen 8790",
    "addr:housenumber":"78",
    "addr:postcode":"8790",
    "addr:street":"Jozef Duthoystraat",
    "iso:country":"BE",
    "sg:address":"Jozef Duthoystraat 78",
    "sg:city":"Waregem",
    "sg:orig_category":"Pain, p\u00e2tisseries and confiseries",
    "sg:phone":"+32 56 60 27 63",
    "sg:postcode":"8790",
    "sg:province":"West-Vlaanderen",
    "wof:name":"Marnik Van Isacker",
    "wof:placetype":"venue"
},
  "geometry": {"coordinates":[3.4202980995,50.8823814392],"type":"Point"}
}