{
  "type": "Feature",
  "properties": {
    "iso:country":"BE",
    "sg:address":"Maenhoutstraat 42ba",
    "sg:city":"Sint-martens-latem",
    "sg:classifiers":[
        {
            "category":"Personal",
            "subcategory":"Beauty Salon",
            "type":"Services"
        }
    ],
    "sg:phone":"+32 9 281 12 81",
    "sg:postcode":"9830",
    "sg:province":"Oost-Vlaanderen",
    "sg:tags":[
        "de",
        "coiffure"
    ],
    "wof:name":"Hairstudio Il",
    "wof:placetype":"venue"
},
  "geometry": {"coordinates":[3.6447598934,51.0140037537],"type":"Point"}
}