{
  "type": "Feature",
  "properties": {
    "iso:country":"BE",
    "sg:address":"Samr\u00c9e 41",
    "sg:city":"La Roche-en-ardenne",
    "sg:orig_category":"Rundveehouders",
    "sg:phone":"+32 84 44 43 17",
    "sg:postcode":"6982",
    "sg:province":"Luxembourg",
    "wof:name":"Frederic Philippe",
    "wof:placetype":"venue"
},
  "geometry": {"coordinates":[5.638133049,50.2120666504],"type":"Point"}
}