{
  "type": "Feature",
  "properties": {
    "addr:full":"Hasseltsesteenweg 136 Beringen Limburg 3580",
    "addr:housenumber":"136",
    "addr:postcode":"3580",
    "addr:street":"Hasseltsesteenweg",
    "iso:country":"BE",
    "sg:address":"Hasseltsesteenweg 136",
    "sg:city":"Beringen",
    "sg:orig_category":"Advocaten and juridische adviseurs",
    "sg:phone":"+32 11 42 77 66",
    "sg:postcode":"3580",
    "sg:province":"Limburg",
    "wof:name":"V. Ballet",
    "wof:placetype":"venue"
},
  "geometry": {"coordinates":[5.2316718102,51.0428962708],"type":"Point"}
}