{
  "type": "Feature",
  "properties": {
    "addr:full":"Chauss\u00c9e De Ninove 708 Anderlecht/anderlecht Bruxelles-Capitale 1070",
    "addr:housenumber":"708",
    "addr:postcode":"1070",
    "addr:street":"Chausse\u0301E De Ninove",
    "iso:country":"BE",
    "sg:address":"Chauss\u00c9e De Ninove 708",
    "sg:city":"Anderlecht/anderlecht",
    "sg:classifiers":[
        {
            "category":"Fast Food",
            "type":"Food & Drink"
        }
    ],
    "sg:phone":"+32 2 522 33 10",
    "sg:postcode":"1070",
    "sg:province":"Bruxelles-Capitale",
    "sg:tags":[
        "de",
        "restaurant",
        "organisation",
        "\u00c0",
        "catering",
        "emporter",
        "f\u00cates",
        "restaurants"
    ],
    "wof:name":"Legend Hea",
    "wof:placetype":"venue"
},
  "geometry": {"coordinates":[4.2967557907,50.8464698792],"type":"Point"}
}