{
  "type": "Feature",
  "properties": {
    "addr:full":"Rue Henri Evenepoel 100b55 Schaarbeek/schaerbeek Bruxelles-Capitale 1030",
    "addr:housenumber":"100b55",
    "addr:postcode":"1030",
    "addr:street":"Rue Henri Evenepoel",
    "iso:country":"BE",
    "sg:address":"Rue Henri Evenepoel 100b55",
    "sg:city":"Schaarbeek/schaerbeek",
    "sg:orig_category":"M\u00e9decins and sp\u00e9cialistes",
    "sg:phone":"+32 2 736 82 49",
    "sg:postcode":"1030",
    "sg:province":"Bruxelles-Capitale",
    "wof:name":"Amkelteme Nejai",
    "wof:placetype":"venue"
},
  "geometry": {"coordinates":[4.4066748619,50.8552017212],"type":"Point"}
}