{
  "type": "Feature",
  "properties": {
    "iso:country":"BE",
    "sg:address":"De Bosschaertlei 11",
    "sg:city":"Hemiksem",
    "sg:orig_category":"Brood, gebak and snoepgoed",
    "sg:phone":"+32 3 887 46 96",
    "sg:postcode":"2620",
    "sg:province":"Antwerpen",
    "wof:name":"Bakkerij 't Korenveld",
    "wof:placetype":"venue"
},
  "geometry": {"coordinates":[4.3403167725,51.145866394],"type":"Point"}
}