{
  "type": "Feature",
  "properties": {
    "addr:full":"Rue De La Forge 1 Vresse-sur-semois Namur 5550",
    "addr:housenumber":"1",
    "addr:postcode":"vresse-sur-semois;5550",
    "addr:street":"Rue De La Forge",
    "iso:country":"BE",
    "sg:address":"Rue De La Forge 1",
    "sg:city":"Vresse-sur-semois",
    "sg:orig_category":"Epiceries",
    "sg:phone":"+32 61 50 03 55",
    "sg:postcode":"5550",
    "sg:province":"Namur",
    "wof:name":"Louis Delhaize",
    "wof:placetype":"venue"
},
  "geometry": {"coordinates":[4.9336900711,49.8729820251],"type":"Point"}
}