{
  "type": "Feature",
  "properties": {
    "addr:full":"Brugstraat 198 Aalter Oost-Vlaanderen 9880",
    "addr:housenumber":"198",
    "addr:postcode":"9880",
    "addr:street":"Brugstraat",
    "iso:country":"BE",
    "sg:address":"Brugstraat 198",
    "sg:city":"Aalter",
    "sg:orig_category":"V\u00e9hicules automobiles. Entretien and r\u00e9parations de voitures",
    "sg:phone":"+32 9 374 57 75",
    "sg:postcode":"9880",
    "sg:province":"Oost-Vlaanderen",
    "wof:name":"Garage De Wispelaere",
    "wof:placetype":"venue"
},
  "geometry": {"coordinates":[3.4357049465,51.1048164368],"type":"Point"}
}