{
  "type": "Feature",
  "properties": {
    "iso:country":"BE",
    "sg:address":"Rue De La Communale 4",
    "sg:city":"Comblain-au-pont",
    "sg:orig_category":"Gespecialiseerde residenti\u00eble bouw Woningbouw",
    "sg:phone":"+32 4 369 40 55",
    "sg:postcode":"4170",
    "sg:province":"Li\u00e8ge",
    "wof:name":"Albert Simon",
    "wof:placetype":"venue"
},
  "geometry": {"coordinates":[5.572663784,50.4771690369],"type":"Point"}
}