{
  "type": "Feature",
  "properties": {
    "iso:country":"BE",
    "sg:address":"Sint-truidensesteenweg 407",
    "sg:city":"Tienen",
    "sg:orig_category":"Loodgieterij, verwarming and sanitaire installaties",
    "sg:phone":"+32 16 78 11 38",
    "sg:postcode":"3300",
    "sg:province":"Vlaams-Brabant",
    "wof:name":"Victor Boonen",
    "wof:placetype":"venue"
},
  "geometry": {"coordinates":[4.9768199921,50.7986755371],"type":"Point"}
}