{
  "type": "Feature",
  "properties": {
    "iso:country":"BE",
    "sg:address":"Rue Sainte-walburge 89",
    "sg:city":"Li\u00e8ge 1",
    "sg:classifiers":[
        {
            "category":"Retail",
            "subcategory":"Laundry & Dry Cleaning",
            "type":"Services"
        }
    ],
    "sg:phone":"+32 4 226 07 93",
    "sg:postcode":"4000",
    "sg:province":"Li\u00e8ge",
    "sg:tags":[
        "dyer",
        "cleaner"
    ],
    "wof:name":"Eclat (l')",
    "wof:placetype":"venue"
},
  "geometry": {"coordinates":[5.57102108,50.6562156677],"type":"Point"}
}