{
  "type": "Feature",
  "properties": {
    "addr:full":"Pastorijstr 27-29 Tienen Vlaams-Brabant 3300",
    "addr:housenumber":"27-29",
    "addr:postcode":"3300",
    "iso:country":"BE",
    "sg:address":"Pastorijstr 27-29",
    "sg:city":"Tienen",
    "sg:classifiers":[
        {
            "category":"Shopping",
            "subcategory":"Gifts & Souvenirs",
            "type":"Retail Goods"
        }
    ],
    "sg:phone":"+32 16 81 22 27",
    "sg:postcode":"3300",
    "sg:province":"Vlaams-Brabant",
    "sg:tags":[
        "product",
        "miscellaneous"
    ],
    "wof:name":"Paul Jublou En Zoon Bvba",
    "wof:placetype":"venue"
},
  "geometry": {"coordinates":[4.9510688782,50.8021011353],"type":"Point"}
}