{
  "type": "Feature",
  "properties": {
    "iso:country":"BE",
    "sg:address":"Steenweg 29",
    "sg:city":"Opwijk",
    "sg:orig_category":"Journaux. Tabac",
    "sg:phone":"+32 52 35 93 63",
    "sg:postcode":"1745",
    "sg:province":"Vlaams-Brabant",
    "wof:name":"Huis Boekenwurmpje",
    "wof:placetype":"venue"
},
  "geometry": {"coordinates":[4.1723618507,50.940196991],"type":"Point"}
}