{
  "type": "Feature",
  "properties": {
    "addr:full":"Drogenbroodstraat 13 Evergem Oost-Vlaanderen 9940",
    "addr:housenumber":"13",
    "addr:postcode":"9940",
    "addr:street":"Drogenbroodstraat;Oost-Vlaanderen",
    "iso:country":"BE",
    "sg:address":"Drogenbroodstraat 13",
    "sg:city":"Evergem",
    "sg:orig_category":"Studios photographiques",
    "sg:phone":"+32 9 357 52 16",
    "sg:postcode":"9940",
    "sg:province":"Oost-Vlaanderen",
    "wof:name":"Roger Geirnaert",
    "wof:placetype":"venue"
},
  "geometry": {"coordinates":[3.7335829735,51.132232666],"type":"Point"}
}