{
  "type": "Feature",
  "properties": {
    "addr:full":"Sperwerlaan 3 Grobbendonk Antwerpen 2280",
    "addr:housenumber":"3",
    "addr:postcode":"2280",
    "addr:street":"Sperwerlaan",
    "iso:country":"BE",
    "sg:address":"Sperwerlaan 3",
    "sg:city":"Grobbendonk",
    "sg:classifiers":[
        {
            "category":"Personal",
            "subcategory":"Beauty Salon",
            "type":"Services"
        }
    ],
    "sg:phone":"+32 3 481 82 52",
    "sg:postcode":"2280",
    "sg:province":"Antwerpen",
    "sg:tags":[
        "de",
        "coiffure"
    ],
    "wof:name":"Anne-marie Verboven",
    "wof:placetype":"venue"
},
  "geometry": {"coordinates":[4.7077322006,51.170841217],"type":"Point"}
}