{
  "type": "Feature",
  "properties": {
    "addr:full":"Kattenbroekstraat 30a Aalst (moorsel) Oost-Vlaanderen 9310",
    "addr:housenumber":"30a",
    "addr:postcode":"9310",
    "addr:street":"Kattenbroekstraat;Moorsel Oost-Vlaanderen",
    "iso:country":"BE",
    "sg:address":"Kattenbroekstraat 30a",
    "sg:city":"Aalst (moorsel)",
    "sg:orig_category":"Non-Classified Establishments",
    "sg:phone":"+32 53 71 06 29",
    "sg:postcode":"9310",
    "sg:province":"Oost-Vlaanderen",
    "wof:name":"D'hooge W",
    "wof:placetype":"venue"
},
  "geometry": {"coordinates":[4.098400116,50.9477767944],"type":"Point"}
}