{
  "type": "Feature",
  "properties": {
    "iso:country":"BE",
    "sg:address":"Brusselsesteenweg 92",
    "sg:city":"Asse",
    "sg:orig_category":"Herstelling aan huis van huishoudartikelen Herstellingswinkels voor diverse persoonlijke and huishou",
    "sg:phone":"+32 2 453 08 79",
    "sg:postcode":"1730",
    "sg:province":"Vlaams-Brabant",
    "wof:name":"Sleutelexpress",
    "wof:placetype":"venue"
},
  "geometry": {"coordinates":[4.2123308182,50.9033851624],"type":"Point"}
}