{
  "type": "Feature",
  "properties": {
    "iso:country":"BE",
    "sg:address":"Rue De N\u00e9chin 2",
    "sg:city":"Tournai (templeuve)",
    "sg:classifiers":[
        {
            "category":"Personal",
            "subcategory":"Beauty Salon",
            "type":"Services"
        }
    ],
    "sg:phone":"+32 69 35 26 68",
    "sg:postcode":"7520",
    "sg:province":"Hainaut",
    "sg:tags":[
        "lady",
        "-",
        "hairdressing"
    ],
    "wof:name":"Trianon (le)",
    "wof:placetype":"venue"
},
  "geometry": {"coordinates":[3.282681942,50.6451263428],"type":"Point"}
}