{
  "type": "Feature",
  "properties": {
    "addr:full":"Polenlaan 9 Stekene Oost-Vlaanderen 9190",
    "addr:housenumber":"9",
    "addr:postcode":"9190",
    "addr:street":"Polenlaan",
    "iso:country":"BE",
    "sg:address":"Polenlaan 9",
    "sg:city":"Stekene",
    "sg:orig_category":"Dameskledingzaken Herenkledingzaken",
    "sg:phone":"+32 3 779 73 52",
    "sg:postcode":"9190",
    "sg:province":"Oost-Vlaanderen",
    "wof:name":"Kleding Van Hoecke",
    "wof:placetype":"venue"
},
  "geometry": {"coordinates":[4.0412459373,51.2065467834],"type":"Point"}
}