{
  "type": "Feature",
  "properties": {
    "addr:full":"Sint-dionysiusstraat 21ba Gent Oost-Vlaanderen 9051",
    "addr:housenumber":"21ba",
    "addr:postcode":"9051",
    "addr:street":"Sint-Dionysiusstraat;Oost-Vlaanderen",
    "iso:country":"BE",
    "sg:address":"Sint-dionysiusstraat 21ba",
    "sg:city":"Gent",
    "sg:orig_category":"Banques and organismes de cr\u00e9dit",
    "sg:phone":"+32 9 222 54 55",
    "sg:postcode":"9051",
    "sg:province":"Oost-Vlaanderen",
    "wof:name":"Ippa",
    "wof:placetype":"venue"
},
  "geometry": {"coordinates":[3.6692450047,51.019367218],"type":"Point"}
}