{
  "type": "Feature",
  "properties": {
    "addr:full":"Avenue Des Flandres 4 Leuze-en-hainaut Hainaut 7900",
    "addr:housenumber":"4",
    "addr:postcode":"7900",
    "addr:street":"Avenue Des Flandres",
    "iso:country":"BE",
    "sg:address":"Avenue Des Flandres 4",
    "sg:city":"Leuze-en-hainaut",
    "sg:classifiers":[
        {
            "category":"Health Services",
            "subcategory":"Health Practitioner",
            "type":"Services"
        }
    ],
    "sg:phone":"+32 69 66 19 92",
    "sg:postcode":"7900",
    "sg:province":"Hainaut",
    "sg:tags":[
        "therapist",
        "speech"
    ],
    "wof:name":"Connart R",
    "wof:placetype":"venue"
},
  "geometry": {"coordinates":[3.6171619892,50.6055984497],"type":"Point"}
}