{
  "type": "Feature",
  "properties": {
    "addr:full":"Rue Saint-sauveur 290 Wanze Li\u00e8ge 4520",
    "addr:housenumber":"290",
    "addr:postcode":"4520",
    "addr:street":"Rue Saint-Sauveur",
    "iso:country":"BE",
    "sg:address":"Rue Saint-sauveur 290",
    "sg:city":"Wanze",
    "sg:orig_category":"M\u00e9decins and sp\u00e9cialistes",
    "sg:phone":"+32 85 23 31 70",
    "sg:postcode":"4520",
    "sg:province":"Li\u00e8ge",
    "wof:name":"Christine Etienne",
    "wof:placetype":"venue"
},
  "geometry": {"coordinates":[5.1773161888,50.5412940979],"type":"Point"}
}