{
  "type": "Feature",
  "properties": {
    "addr:full":"Rue Marie-th\u00c9r\u00c8se 32 Brussel/bruxelles Bruxelles-Capitale 1000",
    "addr:housenumber":"32",
    "addr:postcode":"1000",
    "addr:street":"Rue Marie-The\u0301Re\u0300Se;/",
    "iso:country":"BE",
    "sg:address":"Rue Marie-th\u00c9r\u00c8se 32",
    "sg:city":"Brussel/bruxelles",
    "sg:orig_category":"Mat\u00e9riel m\u00e9dical and orthop\u00e9dique and proth\u00e8ses Fab",
    "sg:phone":"+32 2 218 47 47",
    "sg:postcode":"1000",
    "sg:province":"Bruxelles-Capitale",
    "wof:name":"Fondu",
    "wof:placetype":"venue"
},
  "geometry": {"coordinates":[4.3718819618,50.8470611572],"type":"Point"}
}