{
  "type": "Feature",
  "properties": {
    "addr:full":"Place De La Vaillance 2 Bruxelles (anderlecht) Bruxelles-Capitale 1070",
    "addr:housenumber":"2",
    "addr:postcode":"1070",
    "addr:street":"Place De La Vaillance",
    "iso:country":"BE",
    "sg:address":"Place De La Vaillance 2",
    "sg:city":"Bruxelles (anderlecht)",
    "sg:classifiers":[
        {
            "category":"Bars & Pubs",
            "type":"Food & Drink"
        }
    ],
    "sg:phone":"+32 2 524 46 13",
    "sg:postcode":"1070",
    "sg:province":"Bruxelles-Capitale",
    "wof:name":"Pigeon Noir (le)",
    "wof:placetype":"venue"
},
  "geometry": {"coordinates":[4.3073368073,50.8353538513],"type":"Point"}
}