{
  "type": "Feature",
  "properties": {
    "iso:country":"BE",
    "sg:address":"Moderne-wijkstraat 43",
    "sg:city":"Sint-agatha-berchem/berchem-sainte-agathe",
    "sg:orig_category":"Woningbouw",
    "sg:phone":"+32 477 72 88 70",
    "sg:postcode":"1082",
    "sg:province":"Bruxelles-Capitale",
    "wof:name":"Roza",
    "wof:placetype":"venue"
},
  "geometry": {"coordinates":[4.3054208755,50.8677406311],"type":"Point"}
}