{
  "type": "Feature",
  "properties": {
    "iso:country":"BE",
    "sg:address":"Rue Du Temple 4",
    "sg:city":"Frameries (eugies)",
    "sg:classifiers":[
        {
            "category":"Real Estate",
            "subcategory":"Surveying",
            "type":"Services"
        }
    ],
    "sg:phone":"+32 65 67 90 57",
    "sg:postcode":"7080",
    "sg:province":"Hainaut",
    "sg:tags":[
        "surveyor",
        "land"
    ],
    "wof:name":"Papin M",
    "wof:placetype":"venue"
},
  "geometry": {"coordinates":[3.8970499039,50.4009895325],"type":"Point"}
}