{
  "type": "Feature",
  "properties": {
    "addr:full":"Molendreef 45 Overijse Vlaams-Brabant 3090",
    "addr:housenumber":"45",
    "addr:postcode":"3090",
    "addr:street":"Molendreef",
    "iso:country":"BE",
    "sg:address":"Molendreef 45",
    "sg:city":"Overijse",
    "sg:orig_category":"Avocats and conseillers juridiques",
    "sg:phone":"+32 2 687 65 60",
    "sg:postcode":"3090",
    "sg:province":"Vlaams-Brabant",
    "wof:name":"L. De Temmerman",
    "wof:placetype":"venue"
},
  "geometry": {"coordinates":[4.5281310081,50.7694816589],"type":"Point"}
}