{
  "type": "Feature",
  "properties": {
    "addr:full":"Klissenhoek 40 Vorselaar Antwerpen 2290",
    "addr:housenumber":"40",
    "addr:postcode":"2290",
    "addr:street":"Klissenhoek",
    "iso:country":"BE",
    "sg:address":"Klissenhoek 40",
    "sg:city":"Vorselaar",
    "sg:orig_category":"Juwelen and edelstenen Fab",
    "sg:phone":"+32 14 51 31 87",
    "sg:postcode":"2290",
    "sg:province":"Antwerpen",
    "wof:name":"Patrick Wolput",
    "wof:placetype":"venue"
},
  "geometry": {"coordinates":[4.7605800629,51.2133331299],"type":"Point"}
}