{
  "type": "Feature",
  "properties": {
    "addr:full":"Rue Paul-reuter 1 Arlon Luxembourg 6700",
    "addr:housenumber":"1",
    "addr:postcode":"6700",
    "addr:street":"Rue Paul-Reuter",
    "iso:country":"BE",
    "sg:address":"Rue Paul-reuter 1",
    "sg:city":"Arlon",
    "sg:orig_category":"Cr\u00e9dits divers",
    "sg:postcode":"6700",
    "sg:province":"Luxembourg",
    "wof:name":"Bancontact-mister Cash",
    "wof:placetype":"venue"
},
  "geometry": {"coordinates":[5.8170380592,49.6832695007],"type":"Point"}
}