{
  "type": "Feature",
  "properties": {
    "addr:full":"Dr\u00e8ve Des Alli\u00e9s 60 Thuin Hainaut 6530",
    "addr:housenumber":"60",
    "addr:postcode":"6530",
    "addr:street":"Dre\u0300Ve Des Allie\u0301S",
    "iso:country":"BE",
    "sg:address":"Dr\u00e8ve Des Alli\u00e9s 60",
    "sg:city":"Thuin",
    "sg:classifiers":[
        {
            "category":"Personal",
            "subcategory":"Beauty Salon",
            "type":"Services"
        }
    ],
    "sg:phone":"+32 71 59 20 52",
    "sg:postcode":"6530",
    "sg:province":"Hainaut",
    "wof:name":"Institut Opaline ('l)",
    "wof:placetype":"venue"
},
  "geometry": {"coordinates":[4.3024082184,50.3397636414],"type":"Point"}
}