{
  "type": "Feature",
  "properties": {
    "addr:full":"Kunstenlaan 34 Ieper West-Vlaanderen 8900",
    "addr:housenumber":"34",
    "addr:postcode":"8900",
    "addr:street":"Kunstenlaan",
    "iso:country":"BE",
    "sg:address":"Kunstenlaan 34",
    "sg:city":"Ieper",
    "sg:orig_category":"Production de films, t\u00e9l\u00e9films and vid\u00e9os. Studios photographiques",
    "sg:phone":"+32 57 21 99 59",
    "sg:postcode":"8900",
    "sg:province":"West-Vlaanderen",
    "wof:name":"Oswald Gryson",
    "wof:placetype":"venue"
},
  "geometry": {"coordinates":[2.8695709705,50.8607635498],"type":"Point"}
}