{
  "type": "Feature",
  "properties": {
    "addr:full":"Rue Puits-en-sock 66 Li\u00e8ge 1 (li\u00e8ge 2) Li\u00e8ge 4020",
    "addr:housenumber":"66;1;2",
    "addr:postcode":"4020",
    "addr:street":"Rue Puits-En-Sock",
    "iso:country":"BE",
    "sg:address":"Rue Puits-en-sock 66",
    "sg:city":"Li\u00e8ge 1 (li\u00e8ge 2)",
    "sg:classifiers":[
        {
            "category":"Shopping",
            "subcategory":"Clothing, Apparel, & Fashions",
            "type":"Retail Goods"
        }
    ],
    "sg:phone":"+32 4 341 72 70",
    "sg:postcode":"4020",
    "sg:province":"Li\u00e8ge",
    "sg:tags":[
        "boutique"
    ],
    "wof:name":"Signature B",
    "wof:placetype":"venue"
},
  "geometry": {"coordinates":[5.5835399628,50.6400527954],"type":"Point"}
}