{
  "type": "Feature",
  "properties": {
    "iso:country":"BE",
    "sg:address":"Zondereigen 104",
    "sg:city":"Baarle-hertog",
    "sg:orig_category":"Eleveurs de bovins",
    "sg:phone":"+32 14 63 33 23",
    "sg:postcode":"2387",
    "sg:province":"Antwerpen",
    "wof:name":"Lucia Aerts",
    "wof:placetype":"venue"
},
  "geometry": {"coordinates":[4.9316248894,51.4420585632],"type":"Point"}
}