{
  "type": "Feature",
  "properties": {
    "iso:country":"BE",
    "sg:address":"Meensesteenweg 209",
    "sg:city":"Kortrijk (bissegem)",
    "sg:classifiers":[
        {
            "category":"Autos & Motor Vehicles",
            "subcategory":"Auto Supplies",
            "type":"Retail Goods"
        }
    ],
    "sg:phone":"+32 56 35 44 58",
    "sg:postcode":"8501",
    "sg:province":"West-Vlaanderen",
    "sg:tags":[
        "automobile",
        "alarm",
        "-",
        "system"
    ],
    "wof:name":"Car & Truck Alarm",
    "wof:placetype":"venue"
},
  "geometry": {"coordinates":[3.2373969555,50.8257904053],"type":"Point"}
}