{
  "type": "Feature",
  "properties": {
    "iso:country":"BE",
    "sg:address":"Avenue Fort Mahon 1a",
    "sg:city":"Wellin",
    "sg:classifiers":[
        {
            "category":"Professional",
            "subcategory":"Lawyer & Legal Services",
            "type":"Services"
        }
    ],
    "sg:phone":"+32 84 34 52 27",
    "sg:postcode":"6920",
    "sg:province":"Luxembourg",
    "wof:name":"Davreux P",
    "wof:placetype":"venue"
},
  "geometry": {"coordinates":[5.1105508804,50.0812034607],"type":"Point"}
}