{
  "type": "Feature",
  "properties": {
    "addr:full":"Rue Des Cayats 56 Charleroi (marcinelle) Hainaut 6001",
    "addr:housenumber":"56",
    "addr:postcode":"6001",
    "addr:street":"Rue Des Cayats",
    "iso:country":"BE",
    "sg:address":"Rue Des Cayats 56",
    "sg:city":"Charleroi (marcinelle)",
    "sg:classifiers":[
        {
            "category":"Home & Garden",
            "subcategory":"Furniture",
            "type":"Retail Goods"
        }
    ],
    "sg:phone":"+32 71 60 04 00",
    "sg:postcode":"6001",
    "sg:province":"Hainaut",
    "sg:tags":[
        "-"
    ],
    "wof:name":"Plastics Wauters Sa",
    "wof:placetype":"venue"
},
  "geometry": {"coordinates":[4.4409871101,50.3915672302],"type":"Point"}
}