{
  "type": "Feature",
  "properties": {
    "addr:full":"Rue Du March\u00e9 35 Li\u00e8ge 1 (li\u00e8ge 2) Li\u00e8ge 4020",
    "addr:housenumber":"35;1;2",
    "addr:postcode":"4020",
    "addr:street":"Rue Du Marche\u0301",
    "iso:country":"BE",
    "sg:address":"Rue Du March\u00e9 35",
    "sg:city":"Li\u00e8ge 1 (li\u00e8ge 2)",
    "sg:classifiers":[
        {
            "category":"Shopping",
            "subcategory":"Gifts & Souvenirs",
            "type":"Retail Goods"
        }
    ],
    "sg:phone":"+32 4 343 77 35",
    "sg:postcode":"4020",
    "sg:province":"Li\u00e8ge",
    "sg:tags":[
        "-"
    ],
    "wof:name":"Ait",
    "wof:placetype":"venue"
},
  "geometry": {"coordinates":[5.5931558609,50.6411590576],"type":"Point"}
}