{
  "type": "Feature",
  "properties": {
    "iso:country":"BE",
    "sg:address":"Moerkerkesteenweg",
    "sg:city":"St-kruis",
    "sg:orig_category":"MBK. Motos. R\u00e9parations and entretien de motos. V\u00e9los",
    "sg:phone":"+32 50 35 33 00",
    "sg:postcode":"8310",
    "sg:province":"West-Vlaanderen",
    "wof:name":"Janssen En Zoon",
    "wof:placetype":"venue"
},
  "geometry": {"coordinates":[3.2888679504,51.2257995605],"type":"Point"}
}