{
  "type": "Feature",
  "properties": {
    "addr:full":"Tervuursesteenweg 389 Leuven Vlaams-Brabant 3001",
    "addr:housenumber":"389",
    "addr:postcode":"3001",
    "addr:street":"Tervuursesteenweg",
    "iso:country":"BE",
    "sg:address":"Tervuursesteenweg 389",
    "sg:city":"Leuven",
    "sg:classifiers":[
        {
            "category":"Wholesale",
            "subcategory":"Sporting Goods",
            "type":"Manufacturing & Wholesale Goods"
        }
    ],
    "sg:phone":"+32 16 23 57 56",
    "sg:postcode":"3001",
    "sg:province":"Vlaams-Brabant",
    "sg:tags":[
        "sport-",
        "kampeermateriaal"
    ],
    "wof:name":"Happy Horses",
    "wof:placetype":"venue"
},
  "geometry": {"coordinates":[4.6669049263,50.8731536865],"type":"Point"}
}