{
  "type": "Feature",
  "properties": {
    "addr:full":"Rue De Moresnet 127 Kelmis/la Calamine Li\u00e8ge 4720",
    "addr:housenumber":"127",
    "addr:postcode":"4720",
    "addr:street":"Rue De Moresnet",
    "iso:country":"BE",
    "sg:address":"Rue De Moresnet 127",
    "sg:city":"Kelmis/la Calamine",
    "sg:orig_category":"Maroquinerie and articles de voyage",
    "sg:phone":"+32 87 65 63 53",
    "sg:postcode":"4720",
    "sg:province":"Li\u00e8ge",
    "wof:name":"Josiane Bosch",
    "wof:placetype":"venue"
},
  "geometry": {"coordinates":[6.0051131248,50.7242889404],"type":"Point"}
}