{
  "type": "Feature",
  "properties": {
    "iso:country":"BE",
    "sg:address":"Dalkruidlaan 5",
    "sg:city":"Antwerpen (wilrijk)",
    "sg:classifiers":[
        {
            "category":"Health Services",
            "subcategory":"Health Practitioner",
            "type":"Services"
        }
    ],
    "sg:phone":"+32 475 36 75 72",
    "sg:postcode":"2610",
    "sg:province":"Antwerpen",
    "sg:tags":[
        "alternative",
        "therapy",
        "treatment"
    ],
    "wof:name":"Lauwers G",
    "wof:placetype":"venue"
},
  "geometry": {"coordinates":[4.4084420204,51.1726379395],"type":"Point"}
}