{
  "type": "Feature",
  "properties": {
    "iso:country":"BE",
    "sg:address":"Kempisch Dok Westkaai 16",
    "sg:city":"Antwerpen",
    "sg:classifiers":[
        {
            "category":"Home & Garden",
            "subcategory":"Building Materials",
            "type":"Retail Goods"
        }
    ],
    "sg:phone":"+32 3 231 77 73",
    "sg:postcode":"2000",
    "sg:province":"Antwerpen",
    "sg:tags":[
        "window"
    ],
    "wof:name":"Claessens S & S Bvba",
    "wof:placetype":"venue"
},
  "geometry": {"coordinates":[4.4063000679,51.2304573059],"type":"Point"}
}