{
  "type": "Feature",
  "properties": {
    "addr:full":"Rue Defuisseaux 97 Saint-ghislain (tertre) Hainaut 7333",
    "addr:housenumber":"97",
    "addr:postcode":"7333",
    "addr:street":"Rue Defuisseaux",
    "iso:country":"BE",
    "sg:address":"Rue Defuisseaux 97",
    "sg:city":"Saint-ghislain (tertre)",
    "sg:classifiers":[
        {
            "category":"Banks & Credit Unions",
            "subcategory":"Investment Brokerage",
            "type":"Services"
        }
    ],
    "sg:phone":"+32 65 64 10 46",
    "sg:postcode":"7333",
    "sg:province":"Hainaut",
    "sg:tags":[
        "railroad",
        "work"
    ],
    "wof:name":"Potiez Michel",
    "wof:placetype":"venue"
},
  "geometry": {"coordinates":[3.8111400604,50.4655151367],"type":"Point"}
}