{
  "type": "Feature",
  "properties": {
    "addr:full":"Warandestraat 45 Gistel West-Vlaanderen 8470",
    "addr:housenumber":"45",
    "addr:postcode":"8470",
    "addr:street":"Warandestraat",
    "iso:country":"BE",
    "sg:address":"Warandestraat 45",
    "sg:city":"Gistel",
    "sg:classifiers":[
        {
            "category":"Personal",
            "subcategory":"Beauty Salon",
            "type":"Services"
        }
    ],
    "sg:phone":"+32 59 27 77 97",
    "sg:postcode":"8470",
    "sg:province":"West-Vlaanderen",
    "sg:tags":[
        "lady",
        "-",
        "hairdressing"
    ],
    "wof:name":"Laurette",
    "wof:placetype":"venue"
},
  "geometry": {"coordinates":[2.9786469936,51.1605987549],"type":"Point"}
}