{
  "type": "Feature",
  "properties": {
    "iso:country":"BE",
    "sg:address":"Ch Brunehault 409",
    "sg:city":"Carni\u00e8res",
    "sg:classifiers":[
        {
            "category":"Shopping",
            "subcategory":"Computers & Home Electronics",
            "type":"Retail Goods"
        }
    ],
    "sg:phone":"+32 64 45 93 41",
    "sg:postcode":"7141",
    "sg:province":"Hainaut",
    "sg:tags":[
        "electric",
        "appliance",
        "household",
        "component",
        "equipment",
        "electrical",
        "electronic"
    ],
    "wof:name":"Bvc Sa",
    "wof:placetype":"venue"
},
  "geometry": {"coordinates":[4.2669267654,50.4581642151],"type":"Point"}
}