{
  "type": "Feature",
  "properties": {
    "iso:country":"BE",
    "sg:address":"Rue De L'eglise 32",
    "sg:city":"Mons",
    "sg:orig_category":"Installation \u00e9lectrique r\u00e9sidentielle. Installation \u00e9lectrique industrielle",
    "sg:phone":"+32 65 34 87 58",
    "sg:postcode":"7034",
    "sg:province":"Hainaut",
    "wof:name":"Electricit\u00c9 Alarme Creuse",
    "wof:placetype":"venue"
},
  "geometry": {"coordinates":[4.0092778206,50.4753112793],"type":"Point"}
}