{
  "type": "Feature",
  "properties": {
    "iso:country":"BE",
    "sg:address":"Avenue Coghen 183",
    "sg:city":"Ukkel/uccle",
    "sg:orig_category":"Accessoires vestimentaires",
    "sg:phone":"+32 2 344 85 86",
    "sg:postcode":"1180",
    "sg:province":"Bruxelles-Capitale",
    "wof:name":"Catherine Pecher",
    "wof:placetype":"venue"
},
  "geometry": {"coordinates":[4.340444088,50.8065567017],"type":"Point"}
}