{
  "type": "Feature",
  "properties": {
    "iso:country":"BE",
    "sg:address":"Bautersemstraat 24",
    "sg:city":"Kontich",
    "sg:orig_category":"Artsen and specialisten",
    "sg:phone":"+32 3 458 13 34",
    "sg:postcode":"2550",
    "sg:province":"Antwerpen",
    "wof:name":"Martine Van Den Eynde",
    "wof:placetype":"venue"
},
  "geometry": {"coordinates":[4.4513258934,51.1366615295],"type":"Point"}
}