{
  "type": "Feature",
  "properties": {
    "iso:country":"BE",
    "sg:address":"Rue F Landrain 26",
    "sg:city":"Wezembeek-oppem",
    "sg:orig_category":"Chaussures. Articles de camping and de sport. Clubs de sport. Installations and terrains de sport ho",
    "sg:phone":"+32 2 731 77 07",
    "sg:postcode":"1970",
    "sg:province":"Vlaams-Brabant",
    "wof:name":"Davis",
    "wof:placetype":"venue"
},
  "geometry": {"coordinates":[4.4763450623,50.8472061157],"type":"Point"}
}