{
  "type": "Feature",
  "properties": {
    "iso:country":"BE",
    "sg:address":"Avenue Des Pagodes 34",
    "sg:city":"Brussel/bruxelles",
    "sg:classifiers":[
        {
            "category":"Arena",
            "subcategory":"Sports Club",
            "type":"Entertainment"
        }
    ],
    "sg:phone":"+32 2 548 57 28",
    "sg:postcode":"1020",
    "sg:province":"Bruxelles-Capitale",
    "sg:tags":[
        "de"
    ],
    "wof:name":"T.c. Acacias",
    "wof:placetype":"venue"
},
  "geometry": {"coordinates":[4.3733658791,50.8906517029],"type":"Point"}
}