{
  "type": "Feature",
  "properties": {
    "iso:country":"BE",
    "sg:address":"Rue Aur\u00e9lien Thibaut 12",
    "sg:city":"Charleroi (marcinelle)",
    "sg:classifiers":[
        {
            "category":"Social Services",
            "type":"Services"
        }
    ],
    "sg:phone":"+32 71 36 48 05",
    "sg:postcode":"6001",
    "sg:province":"Hainaut",
    "wof:name":"Figuier Asbl",
    "wof:placetype":"venue"
},
  "geometry": {"coordinates":[4.4476041794,50.399143219],"type":"Point"}
}