{
  "type": "Feature",
  "properties": {
    "iso:country":"BE",
    "sg:address":"Raapbreukstraat 35",
    "sg:city":"Herentals",
    "sg:orig_category":"Boekhouders",
    "sg:phone":"+32 14 22 09 80",
    "sg:postcode":"2200",
    "sg:province":"Antwerpen",
    "wof:name":"Gunter Van Eyck",
    "wof:placetype":"venue"
},
  "geometry": {"coordinates":[4.8406319618,51.1883430481],"type":"Point"}
}