{
  "type": "Feature",
  "properties": {
    "iso:country":"BE",
    "sg:address":"Rodeborgstraat 59",
    "sg:city":"Schoten",
    "sg:classifiers":[
        {
            "category":"Shopping",
            "subcategory":"Crafts & Fabrics",
            "type":"Retail Goods"
        }
    ],
    "sg:phone":"+32 3 658 13 50",
    "sg:postcode":"2900",
    "sg:province":"Antwerpen",
    "sg:tags":[
        "needlework",
        "lady"
    ],
    "wof:name":"Handwerkcenter",
    "wof:placetype":"venue"
},
  "geometry": {"coordinates":[4.5000481606,51.2541389465],"type":"Point"}
}