{
  "type": "Feature",
  "properties": {
    "addr:full":"Rue De L'ind\u00e9pendance 150 Bruxelles (molenbeek-saint-jean) Bruxelles-Capitale 1080",
    "addr:housenumber":"150",
    "addr:postcode":"1080",
    "addr:street":"Rue De;\u0301Pendance",
    "iso:country":"BE",
    "sg:address":"Rue De L'ind\u00e9pendance 150",
    "sg:city":"Bruxelles (molenbeek-saint-jean)",
    "sg:classifiers":[
        {
            "category":"Retail",
            "subcategory":"Auto Repair",
            "type":"Services"
        }
    ],
    "sg:phone":"+32 2 411 52 82",
    "sg:postcode":"1080",
    "sg:province":"Bruxelles-Capitale",
    "sg:tags":[
        "garage"
    ],
    "wof:name":"Kabo Negro",
    "wof:placetype":"venue"
},
  "geometry": {"coordinates":[4.3274850845,50.8533401489],"type":"Point"}
}