{
  "type": "Feature",
  "properties": {
    "iso:country":"BE",
    "sg:address":"Avenue De Philippeville 229",
    "sg:city":"Charleroi (marcinelle)",
    "sg:orig_category":"Video-Equipment - Mainten. and Repair",
    "sg:phone":"+32 71 23 99 10",
    "sg:postcode":"6001",
    "sg:province":"Hainaut",
    "wof:name":"C. E. Service",
    "wof:placetype":"venue"
},
  "geometry": {"coordinates":[4.456553936,50.3950614929],"type":"Point"}
}