{
  "type": "Feature",
  "properties": {
    "addr:full":"Itali\u00cblei 116 Antwerpen Antwerpen 2000",
    "addr:housenumber":"116",
    "addr:postcode":"2000",
    "addr:street":"Italie\u0308Lei",
    "iso:country":"BE",
    "sg:address":"Itali\u00cblei 116",
    "sg:city":"Antwerpen",
    "sg:orig_category":"Agences de voyages",
    "sg:phone":"+32 3 225 10 15",
    "sg:postcode":"2000",
    "sg:province":"Antwerpen",
    "wof:name":"Paradiso Tours",
    "wof:placetype":"venue"
},
  "geometry": {"coordinates":[4.4160590172,51.220905304],"type":"Point"}
}