{
  "type": "Feature",
  "properties": {
    "addr:full":"Hondzochtstraat 4 Pepingen (bellingen) Vlaams-Brabant 1674",
    "addr:housenumber":"4",
    "addr:postcode":"1674",
    "addr:street":"Hondzochtstraat",
    "iso:country":"BE",
    "sg:address":"Hondzochtstraat 4",
    "sg:city":"Pepingen (bellingen)",
    "sg:classifiers":[
        {
            "category":"Banks & Credit Unions",
            "subcategory":"Investment Brokerage",
            "type":"Services"
        }
    ],
    "sg:phone":"+32 2 360 21 68",
    "sg:postcode":"1674",
    "sg:province":"Vlaams-Brabant",
    "sg:tags":[
        "-",
        "plastic"
    ],
    "wof:name":"Plastiek Fabriekje ('t)",
    "wof:placetype":"venue"
},
  "geometry": {"coordinates":[4.1738638878,50.7241630554],"type":"Point"}
}