{
  "type": "Feature",
  "properties": {
    "addr:full":"Rue Octave Battaille 5 Beloeil Hainaut 7971",
    "addr:housenumber":"5",
    "addr:postcode":"7971",
    "addr:street":"Rue Octave Battaille",
    "iso:country":"BE",
    "sg:address":"Rue Octave Battaille 5",
    "sg:city":"Beloeil",
    "sg:orig_category":"Beautyfarms, relaxatie and lichamelijk welzijn Schoonheidssalons",
    "sg:phone":"+32 69 56 20 71",
    "sg:postcode":"7971",
    "sg:province":"Hainaut",
    "wof:name":"Inst. Rien Que Pour Elle",
    "wof:placetype":"venue"
},
  "geometry": {"coordinates":[3.6455190182,50.526348114],"type":"Point"}
}