{
  "type": "Feature",
  "properties": {
    "addr:full":"Noordstraat 120 Hamme Oost-Vlaanderen 9220",
    "addr:housenumber":"120",
    "addr:postcode":"9220",
    "addr:street":"Noordstraat",
    "iso:country":"BE",
    "sg:address":"Noordstraat 120",
    "sg:city":"Hamme",
    "sg:classifiers":[
        {
            "category":"Bars & Pubs",
            "type":"Food & Drink"
        }
    ],
    "sg:phone":"+32 52 47 96 29",
    "sg:postcode":"9220",
    "sg:province":"Oost-Vlaanderen",
    "wof:name":"Klavertje Vier ('t)",
    "wof:placetype":"venue"
},
  "geometry": {"coordinates":[4.1508569717,51.0973548889],"type":"Point"}
}