{
  "type": "Feature",
  "properties": {
    "iso:country":"BE",
    "sg:address":"Brun Cornet 38",
    "sg:city":"Menen (rekkem)",
    "sg:classifiers":[
        {
            "category":"Professional",
            "type":"Services"
        }
    ],
    "sg:phone":"+32 56 41 39 11",
    "sg:postcode":"8930",
    "sg:province":"West-Vlaanderen",
    "sg:tags":[
        "industrial",
        "automation"
    ],
    "wof:name":"Mercier Technical Management Bvba",
    "wof:placetype":"venue"
},
  "geometry": {"coordinates":[3.1884028912,50.7708473206],"type":"Point"}
}