{
  "type": "Feature",
  "properties": {
    "addr:full":"Avenue Isidore G\u00e9rard 4a Bruxelles (auderghem) Bruxelles-Capitale 1160",
    "addr:housenumber":"4a",
    "addr:postcode":"1160",
    "addr:street":"Avenue Isidore Ge\u0301Rard",
    "iso:country":"BE",
    "sg:address":"Avenue Isidore G\u00e9rard 4a",
    "sg:city":"Bruxelles (auderghem)",
    "sg:classifiers":[
        {
            "category":"Building & Trades",
            "subcategory":"Construction",
            "type":"Services"
        }
    ],
    "sg:phone":"+32 2 772 40 40",
    "sg:postcode":"1160",
    "sg:province":"Bruxelles-Capitale",
    "sg:tags":[
        "surveyor",
        "-"
    ],
    "wof:name":"Donnay De Casteau",
    "wof:placetype":"venue"
},
  "geometry": {"coordinates":[4.4464921951,50.8216056824],"type":"Point"}
}