{
  "type": "Feature",
  "properties": {
    "iso:country":"BE",
    "sg:address":"Grote Baan 222",
    "sg:city":"Beveren (melsele)",
    "sg:classifiers":[
        {
            "category":"Home & Garden",
            "subcategory":"Building Materials",
            "type":"Retail Goods"
        }
    ],
    "sg:phone":"+32 3 775 77 58",
    "sg:postcode":"9120",
    "sg:province":"Oost-Vlaanderen",
    "sg:tags":[
        "bathroom",
        "installation",
        "accessory"
    ],
    "wof:name":"Van Den Keybus Bvba",
    "wof:placetype":"venue"
},
  "geometry": {"coordinates":[4.2804012299,51.2196731567],"type":"Point"}
}