{
  "type": "Feature",
  "properties": {
    "addr:full":"Koningsstraat 11 Brussel/bruxelles Bruxelles-Capitale 1000",
    "addr:housenumber":"11",
    "addr:postcode":"1000",
    "addr:street":"Koningsstraat;/",
    "iso:country":"BE",
    "sg:address":"Koningsstraat 11",
    "sg:city":"Brussel/bruxelles",
    "sg:orig_category":"Zalen voor culturele evenementen",
    "sg:phone":"+32 2 219 53 70",
    "sg:postcode":"1000",
    "sg:province":"Bruxelles-Capitale",
    "wof:name":"Ass. Pour Le Volontariat",
    "wof:placetype":"venue"
},
  "geometry": {"coordinates":[4.3592538834,50.8424873352],"type":"Point"}
}