{
  "type": "Feature",
  "properties": {
    "addr:full":"Afrikalaan 36 Gent Oost-Vlaanderen 9000",
    "addr:housenumber":"36",
    "addr:postcode":"9000",
    "addr:street":"Afrikalaan;Oost-Vlaanderen",
    "iso:country":"BE",
    "sg:address":"Afrikalaan 36",
    "sg:city":"Gent",
    "sg:orig_category":"Agences d'exp\u00e9dition",
    "sg:phone":"+32 9 224 42 59",
    "sg:postcode":"9000",
    "sg:province":"Oost-Vlaanderen",
    "wof:name":"Neptune Econ. Shipstores",
    "wof:placetype":"venue"
},
  "geometry": {"coordinates":[3.7393538952,51.0643310547],"type":"Point"}
}