{
  "type": "Feature",
  "properties": {
    "iso:country":"BE",
    "sg:address":"Grand-route 46",
    "sg:city":"Mons",
    "sg:classifiers":[
        {
            "category":"Professional",
            "subcategory":"Credit Reporting & Collection",
            "type":"Services"
        }
    ],
    "sg:phone":"+32 65 35 17 70",
    "sg:postcode":"7000",
    "sg:province":"Hainaut",
    "sg:tags":[
        "good",
        "publishing",
        "printing",
        "-",
        "finished",
        "paper",
        "cardboard"
    ],
    "wof:name":"Copy Print Minute Sa",
    "wof:placetype":"venue"
},
  "geometry": {"coordinates":[3.9492590427,50.4511756897],"type":"Point"}
}