{
  "type": "Feature",
  "properties": {
    "addr:full":"Tramlaan 96 Zaventem (sterrebeek) Vlaams-Brabant 1933",
    "addr:housenumber":"96",
    "addr:postcode":"1933",
    "addr:street":"Tramlaan",
    "iso:country":"BE",
    "sg:address":"Tramlaan 96",
    "sg:city":"Zaventem (sterrebeek)",
    "sg:classifiers":[
        {
            "category":"Professional",
            "subcategory":"Accounting & Tax Preparation",
            "type":"Services"
        }
    ],
    "sg:phone":"+32 2 731 44 84",
    "sg:postcode":"1933",
    "sg:province":"Vlaams-Brabant",
    "sg:tags":[
        "accountant"
    ],
    "wof:name":"Rebo Account",
    "wof:placetype":"venue"
},
  "geometry": {"coordinates":[4.5081949234,50.8629493713],"type":"Point"}
}