{
  "type": "Feature",
  "properties": {
    "addr:full":"Demerstr 21-22 Aarschot Vlaams-Brabant 3200",
    "addr:postcode":"21-22;3200",
    "iso:country":"BE",
    "sg:address":"Demerstr 21-22",
    "sg:city":"Aarschot",
    "sg:classifiers":[
        {
            "category":"Home & Garden",
            "subcategory":"Furniture",
            "type":"Retail Goods"
        }
    ],
    "sg:phone":"+32 16 56 51 81",
    "sg:postcode":"3200",
    "sg:province":"Vlaams-Brabant",
    "sg:tags":[
        "household",
        "wood"
    ],
    "wof:name":"Swish Benelux Nv",
    "wof:placetype":"venue"
},
  "geometry": {"coordinates":[4.8223319054,50.9859046936],"type":"Point"}
}