{
  "type": "Feature",
  "properties": {
    "addr:full":"Rue Basse Campagne 86 Herstal Li\u00e8ge 4040",
    "addr:housenumber":"86",
    "addr:postcode":"4040",
    "addr:street":"Rue Basse Campagne",
    "iso:country":"BE",
    "sg:address":"Rue Basse Campagne 86",
    "sg:city":"Herstal",
    "sg:classifiers":[
        {
            "category":"Fast Food",
            "type":"Food & Drink"
        }
    ],
    "sg:phone":"+32 4 264 24 26",
    "sg:postcode":"4040",
    "sg:province":"Li\u00e8ge",
    "sg:tags":[
        "\u00c0",
        "restaurants",
        "emporter",
        "restaurant"
    ],
    "wof:name":"Quick",
    "wof:placetype":"venue"
},
  "geometry": {"coordinates":[5.6455349922,50.688041687],"type":"Point"}
}