{
  "type": "Feature",
  "properties": {
    "addr:full":"Rue Sainte-gertrude 58 Court-saint-etienne Brabant Wallon 1490",
    "addr:housenumber":"58;1490",
    "addr:street":"Rue Sainte-Gertrude",
    "iso:country":"BE",
    "sg:address":"Rue Sainte-gertrude 58",
    "sg:city":"Court-saint-etienne",
    "sg:classifiers":[
        {
            "category":"Health Services",
            "subcategory":"Dentist",
            "type":"Services"
        }
    ],
    "sg:phone":"+32 10 61 46 84",
    "sg:postcode":"1490",
    "sg:province":"Brabant Wallon",
    "wof:name":"Dotremont Christian",
    "wof:placetype":"venue"
},
  "geometry": {"coordinates":[4.544549942,50.6066703796],"type":"Point"}
}