{
  "type": "Feature",
  "properties": {
    "iso:country":"BE",
    "sg:address":"Leuvenselaan 172",
    "sg:city":"Tienen",
    "sg:classifiers":[
        {
            "category":"Wholesale",
            "subcategory":"Construction Materials",
            "type":"Manufacturing & Wholesale Goods"
        }
    ],
    "sg:phone":"+32 16 82 57 79",
    "sg:postcode":"3300",
    "sg:province":"Vlaams-Brabant",
    "sg:tags":[
        "joint",
        "packing"
    ],
    "wof:name":"Garlock Sealing Technologies",
    "wof:placetype":"venue"
},
  "geometry": {"coordinates":[4.9303297997,50.8096694946],"type":"Point"}
}