{
  "type": "Feature",
  "properties": {
    "iso:country":"BE",
    "sg:address":"Tichelrij 4",
    "sg:city":"Mechelen",
    "sg:classifiers":[
        {
            "category":"Health Services",
            "subcategory":"Doctor",
            "type":"Services"
        }
    ],
    "sg:phone":"+32 15 33 13 43",
    "sg:postcode":"2800",
    "sg:province":"Antwerpen",
    "sg:tags":[
        "medicinephysicians",
        "surgeon"
    ],
    "wof:name":"Dachelet Josee",
    "wof:placetype":"venue"
},
  "geometry": {"coordinates":[4.4746060371,51.0275764465],"type":"Point"}
}