{
  "type": "Feature",
  "properties": {
    "addr:full":"Lepelstraat 10 Lommel Limburg 3920",
    "addr:housenumber":"10",
    "addr:postcode":"3920",
    "addr:street":"Lepelstraat",
    "iso:country":"BE",
    "sg:address":"Lepelstraat 10",
    "sg:city":"Lommel",
    "sg:classifiers":[
        {
            "category":"Banks & Credit Unions",
            "subcategory":"Bank",
            "type":"Services"
        }
    ],
    "sg:phone":"+32 11 54 33 34",
    "sg:postcode":"3920",
    "sg:province":"Limburg",
    "sg:tags":[
        "savings-banks"
    ],
    "wof:name":"Centea Lommel Centrum Bvba",
    "wof:placetype":"venue"
},
  "geometry": {"coordinates":[5.3100438118,51.2311935425],"type":"Point"}
}