{
  "type": "Feature",
  "properties": {
    "addr:full":"Hoogveld 1 Londerzeel Vlaams-Brabant 1840",
    "addr:housenumber":"1",
    "addr:postcode":"1840",
    "addr:street":"Hoogveld",
    "iso:country":"BE",
    "sg:address":"Hoogveld 1",
    "sg:city":"Londerzeel",
    "sg:classifiers":[
        {
            "category":"Communications",
            "type":"Services"
        }
    ],
    "sg:phone":"+32 52 55 50 12",
    "sg:postcode":"1840",
    "sg:province":"Vlaams-Brabant",
    "sg:tags":[
        "translator"
    ],
    "wof:name":"Laureys E",
    "wof:placetype":"venue"
},
  "geometry": {"coordinates":[4.300262928,50.9941635132],"type":"Point"}
}