{
  "type": "Feature",
  "properties": {
    "iso:country":"BE",
    "sg:address":"Ganzendries 7",
    "sg:city":"Lokeren",
    "sg:classifiers":[
        {
            "category":"Fast Food",
            "type":"Food & Drink"
        }
    ],
    "sg:phone":"+32 9 349 45 55",
    "sg:postcode":"9160",
    "sg:province":"Oost-Vlaanderen",
    "sg:tags":[
        "meeneem",
        "restaurant"
    ],
    "wof:name":"Reza Van Cleemput",
    "wof:placetype":"venue"
},
  "geometry": {"coordinates":[3.9606130123,51.1286735535],"type":"Point"}
}