{
  "type": "Feature",
  "properties": {
    "iso:country":"BE",
    "sg:address":"Veldstraat 14",
    "sg:city":"Meerhout",
    "sg:orig_category":"Banken and kredietinstellingen",
    "sg:phone":"+32 14 30 46 50",
    "sg:postcode":"2450",
    "sg:province":"Antwerpen",
    "wof:name":"Landbouwkrediet",
    "wof:placetype":"venue"
},
  "geometry": {"coordinates":[5.0795350075,51.1318092346],"type":"Point"}
}