{
  "type": "Feature",
  "properties": {
    "iso:country":"BE",
    "sg:address":"Rue De La Jonction 8",
    "sg:city":"Bertrix",
    "sg:orig_category":"Artsen and specialisten",
    "sg:phone":"+32 61 41 09 00",
    "sg:postcode":"6880",
    "sg:province":"Luxembourg",
    "wof:name":"Beno\u00cet Martiat",
    "wof:placetype":"venue"
},
  "geometry": {"coordinates":[5.2549347878,49.8553886414],"type":"Point"}
}