{
  "type": "Feature",
  "properties": {
    "addr:full":"Rue Chatqueue 101 Seraing Li\u00e8ge 4100",
    "addr:housenumber":"101",
    "addr:postcode":"4100",
    "addr:street":"Rue Chatqueue",
    "iso:country":"BE",
    "sg:address":"Rue Chatqueue 101",
    "sg:city":"Seraing",
    "sg:classifiers":[
        {
            "category":"Insurance",
            "subcategory":"Insurance Agent",
            "type":"Services"
        }
    ],
    "sg:phone":"+32 4 336 13 59",
    "sg:postcode":"4100",
    "sg:province":"Li\u00e8ge",
    "sg:tags":[
        "broker"
    ],
    "wof:name":"Feytons J L",
    "wof:placetype":"venue"
},
  "geometry": {"coordinates":[5.5194721222,50.6005592346],"type":"Point"}
}