{
  "type": "Feature",
  "properties": {
    "addr:full":"Tiendagwandlaan 38 Sint-lambrechts-woluwe/woluwe-saint-lambert Bruxelles-Capitale 1200",
    "addr:housenumber":"38",
    "addr:postcode":"1200",
    "addr:street":"Tiendagwandlaan",
    "iso:country":"BE",
    "sg:address":"Tiendagwandlaan 38",
    "sg:city":"Sint-lambrechts-woluwe/woluwe-saint-lambert",
    "sg:orig_category":"Medische apparatuur, orthopedische artikelen and prothesen Fab",
    "sg:phone":"+32 2 770 45 99",
    "sg:postcode":"1200",
    "sg:province":"Bruxelles-Capitale",
    "wof:name":"Henri Crenier",
    "wof:placetype":"venue"
},
  "geometry": {"coordinates":[4.4398379326,50.8566246033],"type":"Point"}
}