{
  "type": "Feature",
  "properties": {
    "addr:full":"Ch D'aelbeke 284-10 Mouscron Hainaut 7700",
    "addr:postcode":"284-10;7700",
    "addr:street":"Hainaut",
    "iso:country":"BE",
    "sg:address":"Ch D'aelbeke 284-10",
    "sg:city":"Mouscron",
    "sg:classifiers":[
        {
            "category":"Shopping",
            "subcategory":"Crafts & Fabrics",
            "type":"Retail Goods"
        }
    ],
    "sg:phone":"+32 56 84 34 50",
    "sg:postcode":"7700",
    "sg:province":"Hainaut",
    "sg:tags":[
        "textile",
        "linen",
        "clothing"
    ],
    "wof:name":"Limited Edition Sprl",
    "wof:placetype":"venue"
},
  "geometry": {"coordinates":[3.2211990356,50.7588386536],"type":"Point"}
}