{
  "type": "Feature",
  "properties": {
    "addr:full":"Rue Cherombou 10 Havelange Namur 5374",
    "addr:housenumber":"10",
    "addr:postcode":"5374",
    "addr:street":"Rue Cherombou",
    "iso:country":"BE",
    "sg:address":"Rue Cherombou 10",
    "sg:city":"Havelange",
    "sg:classifiers":[
        {
            "category":"Restaurant",
            "type":"Food & Drink"
        }
    ],
    "sg:phone":"+32 86 32 23 88",
    "sg:postcode":"5374",
    "sg:province":"Namur",
    "wof:name":"La Qwart A Doz",
    "wof:placetype":"venue"
},
  "geometry": {"coordinates":[5.3158898354,50.3502006531],"type":"Point"}
}