{
  "type": "Feature",
  "properties": {
    "iso:country":"BE",
    "sg:address":"Industrieweg Noord 1119",
    "sg:city":"Opglabbeek",
    "sg:classifiers":[
        {
            "category":"Social Services",
            "subcategory":"Job Training",
            "type":"Services"
        }
    ],
    "sg:phone":"+32 89 81 08 10",
    "sg:postcode":"3660",
    "sg:province":"Limburg",
    "sg:tags":[
        "personnel"
    ],
    "wof:name":"Logis Vzw",
    "wof:placetype":"venue"
},
  "geometry": {"coordinates":[5.5361018181,51.0355491638],"type":"Point"}
}