{
  "type": "Feature",
  "properties": {
    "addr:full":"Rue Defacqz 26 Ath Hainaut 7800",
    "addr:housenumber":"26",
    "addr:postcode":"7800",
    "addr:street":"Rue Defacqz",
    "iso:country":"BE",
    "sg:address":"Rue Defacqz 26",
    "sg:city":"Ath",
    "sg:orig_category":"M\u00e9decins and sp\u00e9cialistes",
    "sg:phone":"+32 68 28 61 02",
    "sg:postcode":"7800",
    "sg:province":"Hainaut",
    "wof:name":"Pierre Lenfant",
    "wof:placetype":"venue"
},
  "geometry": {"coordinates":[3.783919096,50.6302986145],"type":"Point"}
}