{
  "type": "Feature",
  "properties": {
    "addr:full":"Lierseveldstraat 65 Nijlen Antwerpen 2560",
    "addr:housenumber":"65",
    "addr:postcode":"2560",
    "addr:street":"Lierseveldstraat",
    "iso:country":"BE",
    "sg:address":"Lierseveldstraat 65",
    "sg:city":"Nijlen",
    "sg:classifiers":[
        {
            "category":"Building & Trades",
            "subcategory":"Electrical",
            "type":"Services"
        }
    ],
    "sg:phone":"+32 3 481 91 36",
    "sg:postcode":"2560",
    "sg:province":"Antwerpen",
    "sg:tags":[
        "-",
        "electric",
        "contractor"
    ],
    "wof:name":"A.e.d.w. Bvba",
    "wof:placetype":"venue"
},
  "geometry": {"coordinates":[4.6817851067,51.1545372009],"type":"Point"}
}