{
  "type": "Feature",
  "properties": {
    "iso:country":"BE",
    "sg:address":"Avenue Fond Generet 30",
    "sg:city":"Chaumont-gistoux",
    "sg:orig_category":"Rev\u00eatements de sols and murs",
    "sg:phone":"+32 10 24 37 10",
    "sg:postcode":"1325",
    "sg:province":"Brabant Wallon",
    "wof:name":"Eric Buyse",
    "wof:placetype":"venue"
},
  "geometry": {"coordinates":[4.647154808,50.6948280334],"type":"Point"}
}