{
  "type": "Feature",
  "properties": {
    "addr:full":"Limbastraat 2 Gent Oost-Vlaanderen 9000",
    "addr:housenumber":"2",
    "addr:postcode":"9000",
    "addr:street":"Limbastraat;Oost-Vlaanderen",
    "iso:country":"BE",
    "sg:address":"Limbastraat 2",
    "sg:city":"Gent",
    "sg:orig_category":"Epiceries",
    "sg:phone":"+32 9 253 62 16",
    "sg:postcode":"9000",
    "sg:province":"Oost-Vlaanderen",
    "wof:name":"Huis Martine",
    "wof:placetype":"venue"
},
  "geometry": {"coordinates":[3.7248520851,51.0774040222],"type":"Point"}
}