{
  "type": "Feature",
  "properties": {
    "addr:full":"Mandellaan 439 Roeselare West-Vlaanderen 8800",
    "addr:housenumber":"439",
    "addr:postcode":"8800",
    "addr:street":"Mandellaan",
    "iso:country":"BE",
    "sg:address":"Mandellaan 439",
    "sg:city":"Roeselare",
    "sg:orig_category":"Woningbouw",
    "sg:phone":"+32 51 24 18 55",
    "sg:postcode":"8800",
    "sg:province":"West-Vlaanderen",
    "wof:name":"Bouckenhove",
    "wof:placetype":"venue"
},
  "geometry": {"coordinates":[3.1485850811,50.9412193298],"type":"Point"}
}