{
  "type": "Feature",
  "properties": {
    "iso:country":"BE",
    "sg:address":"Geemstraat 18",
    "sg:city":"Hamme",
    "sg:classifiers":[
        {
            "category":"Professional",
            "subcategory":"Art Services",
            "type":"Services"
        }
    ],
    "sg:phone":"+32 52 47 04 29",
    "sg:postcode":"9220",
    "sg:province":"Oost-Vlaanderen",
    "sg:tags":[
        "picture",
        "framer"
    ],
    "wof:name":"Elgi Kader Bvba",
    "wof:placetype":"venue"
},
  "geometry": {"coordinates":[4.1283330917,51.0971870422],"type":"Point"}
}