{
  "type": "Feature",
  "properties": {
    "iso:country":"BE",
    "sg:address":"Albert I-square 18",
    "sg:city":"Anderlecht",
    "sg:orig_category":"Boekhouders",
    "sg:phone":"+32 2 521 07 13",
    "sg:postcode":"1070",
    "sg:province":"Bruxelles-Capitale",
    "wof:name":"Gabrielle Deville",
    "wof:placetype":"venue"
},
  "geometry": {"coordinates":[4.3232679367,50.839099884],"type":"Point"}
}