{
  "type": "Feature",
  "properties": {
    "iso:country":"BE",
    "sg:address":"Beverdijk 14-17",
    "sg:city":"Haacht",
    "sg:orig_category":"Herstellingen and onderhoud van auto's",
    "sg:phone":"+32 16 60 28 48",
    "sg:postcode":"3150",
    "sg:province":"Vlaams-Brabant",
    "wof:name":"Van Bael",
    "wof:placetype":"venue"
},
  "geometry": {"coordinates":[4.6165351868,50.9777030945],"type":"Point"}
}