{
  "type": "Feature",
  "properties": {
    "iso:country":"BE",
    "sg:address":"Rue Du Sabotier 5",
    "sg:city":"Gesves (faulx-les-tombes)",
    "sg:classifiers":[
        {
            "category":"Personal",
            "subcategory":"Beauty Salon",
            "type":"Services"
        }
    ],
    "sg:phone":"+32 81 57 07 78",
    "sg:postcode":"5340",
    "sg:province":"Namur",
    "sg:tags":[
        "lady",
        "-",
        "hairdressing"
    ],
    "wof:name":"Jeanine",
    "wof:placetype":"venue"
},
  "geometry": {"coordinates":[5.0073699951,50.4228210449],"type":"Point"}
}