{
  "type": "Feature",
  "properties": {
    "addr:full":"Rue De Heusy 64 Verviers Li\u00e8ge 4800",
    "addr:housenumber":"64",
    "addr:postcode":"4800",
    "addr:street":"Rue De Heusy",
    "iso:country":"BE",
    "sg:address":"Rue De Heusy 64",
    "sg:city":"Verviers",
    "sg:orig_category":"Bijouteries and horlogeries",
    "sg:phone":"+32 87 31 53 31",
    "sg:postcode":"4800",
    "sg:province":"Li\u00e8ge",
    "wof:name":"Bijoux Or\u00c9gon",
    "wof:placetype":"venue"
},
  "geometry": {"coordinates":[5.8669061661,50.5917320251],"type":"Point"}
}