{
  "type": "Feature",
  "properties": {
    "iso:country":"BE",
    "sg:address":"Vekestraat 83",
    "sg:city":"Zemst",
    "sg:orig_category":"Travaux de pl\u00e2trage",
    "sg:phone":"+32 15 61 06 61",
    "sg:postcode":"1982",
    "sg:province":"Vlaams-Brabant",
    "wof:name":"Ferdinand Geevels",
    "wof:placetype":"venue"
},
  "geometry": {"coordinates":[4.5063939095,50.9650154114],"type":"Point"}
}