{
  "type": "Feature",
  "properties": {
    "iso:country":"BE",
    "sg:address":"Blauwpoort 8",
    "sg:city":"Kortrijk",
    "sg:classifiers":[
        {
            "category":"Personal",
            "subcategory":"Beauty Salon",
            "type":"Services"
        }
    ],
    "sg:phone":"+32 56 35 44 16",
    "sg:postcode":"8501",
    "sg:province":"West-Vlaanderen",
    "sg:tags":[
        "de",
        "coiffure"
    ],
    "wof:name":"Coiffure Georgette",
    "wof:placetype":"venue"
},
  "geometry": {"coordinates":[3.2528190613,50.8391342163],"type":"Point"}
}