{
  "type": "Feature",
  "properties": {
    "iso:country":"BE",
    "sg:address":"Rue Du Culot 52",
    "sg:city":"Beauvechain (tourinnes-la-grosse)",
    "sg:orig_category":"Accumulators",
    "sg:phone":"+32 10 86 09 86",
    "sg:postcode":"1320",
    "sg:province":"Brabant Wallon",
    "wof:name":"Herman L",
    "wof:placetype":"venue"
},
  "geometry": {"coordinates":[4.7499809265,50.7928886414],"type":"Point"}
}