{
  "type": "Feature",
  "properties": {
    "iso:country":"BE",
    "sg:address":"Hoogstraat 72ba",
    "sg:city":"Gent",
    "sg:orig_category":"Studios photographiques. Etudes techniques and ing\u00e9nierie",
    "sg:phone":"+32 9 223 42 83",
    "sg:postcode":"9000",
    "sg:province":"Oost-Vlaanderen",
    "wof:name":"Fabian Van Der Meersche",
    "wof:placetype":"venue"
},
  "geometry": {"coordinates":[3.713465929,51.0549736023],"type":"Point"}
}