{
  "type": "Feature",
  "properties": {
    "addr:full":"Gladiolenstraat 3ba Olen Antwerpen 2250",
    "addr:housenumber":"3ba",
    "addr:postcode":"2250",
    "addr:street":"Gladiolenstraat",
    "iso:country":"BE",
    "sg:address":"Gladiolenstraat 3ba",
    "sg:city":"Olen",
    "sg:orig_category":"Artistes ind\u00e9pendants",
    "sg:phone":"+32 14 23 12 12",
    "sg:postcode":"2250",
    "sg:province":"Antwerpen",
    "wof:name":"Rockband Straight Ahead",
    "wof:placetype":"venue"
},
  "geometry": {"coordinates":[4.8982181549,51.1713104248],"type":"Point"}
}