{
  "type": "Feature",
  "properties": {
    "iso:country":"BE",
    "sg:address":"Mercelisstraat 60",
    "sg:city":"Elsene/ixelles",
    "sg:orig_category":"Artiesten and kunstenaars",
    "sg:phone":"+32 2 649 27 48",
    "sg:postcode":"1050",
    "sg:province":"Bruxelles-Capitale",
    "wof:name":"Alain Montoisy",
    "wof:placetype":"venue"
},
  "geometry": {"coordinates":[4.3635168076,50.8305587769],"type":"Point"}
}