{
  "type": "Feature",
  "properties": {
    "iso:country":"BE",
    "sg:address":"Steenweg Op Perk 21",
    "sg:city":"Steenokkerzeel",
    "sg:orig_category":"Herstellingen and onderhoud van auto's Voertuigen",
    "sg:phone":"+32 2 751 84 14",
    "sg:postcode":"1820",
    "sg:province":"Vlaams-Brabant",
    "wof:name":"Garage Gykiere",
    "wof:placetype":"venue"
},
  "geometry": {"coordinates":[4.488574028,50.9169921875],"type":"Point"}
}