{
  "type": "Feature",
  "properties": {
    "iso:country":"BE",
    "sg:address":"Avenue De Nancy 62",
    "sg:city":"Li\u00c8ge",
    "sg:orig_category":"Kapsalons",
    "sg:phone":"+32 4 342 83 65",
    "sg:postcode":"4020",
    "sg:province":"Li\u00e8ge",
    "wof:name":"Coiffure Jean-pierre",
    "wof:placetype":"venue"
},
  "geometry": {"coordinates":[5.6018400192,50.6446800232],"type":"Point"}
}