{
  "type": "Feature",
  "properties": {
    "iso:country":"BE",
    "sg:address":"Rue Du Castiau 39",
    "sg:city":"Quevy",
    "sg:orig_category":"Epiceries",
    "sg:phone":"+32 65 58 60 40",
    "sg:postcode":"7041",
    "sg:province":"Hainaut",
    "wof:name":"Carat",
    "wof:placetype":"venue"
},
  "geometry": {"coordinates":[4.0359840393,50.3752098083],"type":"Point"}
}