{
  "type": "Feature",
  "properties": {
    "iso:country":"BE",
    "sg:address":"Nieuwstraat 16",
    "sg:city":"Tienen",
    "sg:orig_category":"Rookartikelen",
    "sg:phone":"+32 16 81 20 36",
    "sg:postcode":"3300",
    "sg:province":"Vlaams-Brabant",
    "wof:name":"Huis Massa",
    "wof:placetype":"venue"
},
  "geometry": {"coordinates":[4.9390640259,50.8069152832],"type":"Point"}
}