{
  "type": "Feature",
  "properties": {
    "iso:country":"BE",
    "sg:address":"Rue Danvoie 2",
    "sg:city":"Fleurus (lambusart)",
    "sg:classifiers":[
        {
            "category":"Education",
            "subcategory":"School",
            "type":"Public Place"
        }
    ],
    "sg:phone":"+32 71 81 68 15",
    "sg:postcode":"6220",
    "sg:province":"Hainaut",
    "sg:tags":[
        "primary"
    ],
    "wof:name":"St-laurent",
    "wof:placetype":"venue"
},
  "geometry": {"coordinates":[4.5496749878,50.4825363159],"type":"Point"}
}