{
  "type": "Feature",
  "properties": {
    "addr:full":"Hutstraat 10 Kampenhout Vlaams-Brabant 1910",
    "addr:housenumber":"10",
    "addr:postcode":"1910",
    "addr:street":"Hutstraat",
    "iso:country":"BE",
    "sg:address":"Hutstraat 10",
    "sg:city":"Kampenhout",
    "sg:orig_category":"Diverse bouwafwerking and reiniging",
    "sg:phone":"+32 16 65 79 53",
    "sg:postcode":"1910",
    "sg:province":"Vlaams-Brabant",
    "wof:name":"D.m.p.",
    "wof:placetype":"venue"
},
  "geometry": {"coordinates":[4.5830211639,50.9484863281],"type":"Point"}
}