{
  "type": "Feature",
  "properties": {
    "addr:full":"Avenue De La Tendraie 17 Braine-l\u00b4alleud Brabant Wallon 1421",
    "addr:housenumber":"17;1421",
    "addr:street":"Avenue De La Tendraie;Brabant Wallon",
    "iso:country":"BE",
    "sg:address":"Avenue De La Tendraie 17",
    "sg:city":"Braine-l\u00b4alleud",
    "sg:orig_category":"Schoenen",
    "sg:phone":"+32 2 387 01 16",
    "sg:postcode":"1421",
    "sg:province":"Brabant Wallon",
    "wof:name":"Franado",
    "wof:placetype":"venue"
},
  "geometry": {"coordinates":[4.3812627792,50.6506958008],"type":"Point"}
}