{
  "type": "Feature",
  "properties": {
    "addr:full":"Rue Des Argili\u00e8res 20 Li\u00e8ge 1 (jupille-sur-meuse) Li\u00e8ge 4020",
    "addr:housenumber":"20;1",
    "addr:postcode":"4020",
    "addr:street":"Rue Des Argilie\u0300Res;Jupille-Sur-Meuse Lie\u0300Ge",
    "iso:country":"BE",
    "sg:address":"Rue Des Argili\u00e8res 20",
    "sg:city":"Li\u00e8ge 1 (jupille-sur-meuse)",
    "sg:classifiers":[
        {
            "category":"Building & Trades",
            "subcategory":"Electrical",
            "type":"Services"
        }
    ],
    "sg:phone":"+32 4 362 40 96",
    "sg:postcode":"4020",
    "sg:province":"Li\u00e8ge",
    "sg:tags":[
        "heating"
    ],
    "wof:name":"Hannon",
    "wof:placetype":"venue"
},
  "geometry": {"coordinates":[5.6353240013,50.6433906555],"type":"Point"}
}