{
  "type": "Feature",
  "properties": {
    "addr:full":"Gentsestraat 19 Kortrijk West-Vlaanderen 8500",
    "addr:housenumber":"19",
    "addr:postcode":"8500",
    "addr:street":"Gentsestraat",
    "iso:country":"BE",
    "sg:address":"Gentsestraat 19",
    "sg:city":"Kortrijk",
    "sg:orig_category":"M\u00e9decins and sp\u00e9cialistes",
    "sg:phone":"+32 56 21 68 00",
    "sg:postcode":"8500",
    "sg:province":"West-Vlaanderen",
    "wof:name":"P. Vandaele",
    "wof:placetype":"venue"
},
  "geometry": {"coordinates":[3.2745549679,50.8310089111],"type":"Point"}
}