{
  "type": "Feature",
  "properties": {
    "iso:country":"BE",
    "sg:address":"Le Petit Val 283",
    "sg:city":"Attert (tontelange)",
    "sg:classifiers":[
        {
            "category":"Building & Trades",
            "subcategory":"Landscaping Services",
            "type":"Services"
        }
    ],
    "sg:phone":"+32 63 22 84 00",
    "sg:postcode":"6717",
    "sg:province":"Luxembourg",
    "sg:tags":[
        "gardening",
        "garden",
        "maintenance"
    ],
    "wof:name":"Eischen Jean-paul",
    "wof:placetype":"venue"
},
  "geometry": {"coordinates":[5.8094568253,49.72838974],"type":"Point"}
}