{
  "type": "Feature",
  "properties": {
    "iso:country":"BE",
    "sg:address":"Helleweg 1",
    "sg:city":"Kessel",
    "sg:classifiers":[
        {
            "category":"Home & Garden",
            "subcategory":"Hardware",
            "type":"Retail Goods"
        }
    ],
    "sg:phone":"+32 3 480 89 50",
    "sg:postcode":"2560",
    "sg:province":"Antwerpen",
    "sg:tags":[
        "agricultural",
        "implement"
    ],
    "wof:name":"De Vos C.v.",
    "wof:placetype":"venue"
},
  "geometry": {"coordinates":[4.6627922058,51.1376991272],"type":"Point"}
}