{
  "type": "Feature",
  "properties": {
    "iso:country":"BE",
    "sg:address":"Rue De G\u00c9ronsart 329",
    "sg:city":"Namur",
    "sg:orig_category":"MEUBELONTWERP AND -INSTALLATIE",
    "sg:phone":"+32 81 31 32 80",
    "sg:postcode":"5100",
    "sg:province":"Namur",
    "wof:name":"Cuisines Bruno S.",
    "wof:placetype":"venue"
},
  "geometry": {"coordinates":[4.8713750839,50.4566345215],"type":"Point"}
}