{
  "type": "Feature",
  "properties": {
    "addr:full":"Arisdonkstraatje 6 Waarschoot Oost-Vlaanderen 9950",
    "addr:housenumber":"6",
    "addr:postcode":"9950",
    "addr:street":"Arisdonkstraatje",
    "iso:country":"BE",
    "sg:address":"Arisdonkstraatje 6",
    "sg:city":"Waarschoot",
    "sg:classifiers":[
        {
            "category":"Building & Trades",
            "subcategory":"Landscaping Services",
            "type":"Services"
        }
    ],
    "sg:phone":"+32 9 377 95 59",
    "sg:postcode":"9950",
    "sg:province":"Oost-Vlaanderen",
    "sg:tags":[
        "gardening",
        "garden",
        "maintenance"
    ],
    "wof:name":"Dhaenens G",
    "wof:placetype":"venue"
},
  "geometry": {"coordinates":[3.6313500404,51.1542625427],"type":"Point"}
}