{
  "type": "Feature",
  "properties": {
    "addr:full":"Albert I Laan 173 Nieuwpoort West-Vlaanderen 8620",
    "addr:housenumber":"173",
    "addr:postcode":"8620",
    "addr:street":"Albert I Laan",
    "iso:country":"BE",
    "sg:address":"Albert I Laan 173",
    "sg:city":"Nieuwpoort",
    "sg:orig_category":"Pain, p\u00e2tisseries and confiseries",
    "sg:phone":"+32 58 23 48 43",
    "sg:postcode":"8620",
    "sg:province":"West-Vlaanderen",
    "wof:name":"Huis Bonbon Karamel",
    "wof:placetype":"venue"
},
  "geometry": {"coordinates":[2.7188398838,51.1494140625],"type":"Point"}
}