{
  "type": "Feature",
  "properties": {
    "addr:full":"Rue De Bouzanton 2 Mons Hainaut 7000",
    "addr:housenumber":"2",
    "addr:postcode":"7000",
    "addr:street":"Rue De Bouzanton;Hainaut",
    "iso:country":"BE",
    "sg:address":"Rue De Bouzanton 2",
    "sg:city":"Mons",
    "sg:orig_category":"Herstelling leer and schoeisel",
    "sg:phone":"+32 65 31 31 78",
    "sg:postcode":"7000",
    "sg:province":"Hainaut",
    "wof:name":"J. Wattiez",
    "wof:placetype":"venue"
},
  "geometry": {"coordinates":[3.9469909668,50.4503288269],"type":"Point"}
}