{
  "type": "Feature",
  "properties": {
    "iso:country":"BE",
    "sg:address":"Kriktestraat 58",
    "sg:city":"Lokeren",
    "sg:classifiers":[
        {
            "category":"Recreation",
            "type":"Entertainment"
        }
    ],
    "sg:phone":"+32 9 348 34 71",
    "sg:postcode":"9160",
    "sg:province":"Oost-Vlaanderen",
    "sg:tags":[
        "diver",
        "amusement"
    ],
    "wof:name":"Club Seven",
    "wof:placetype":"venue"
},
  "geometry": {"coordinates":[4.0034332275,51.1244544983],"type":"Point"}
}