{
  "type": "Feature",
  "properties": {
    "addr:full":"Rue De Gouy 15 Chapelle-lez-herlaimont Hainaut 7160",
    "addr:housenumber":"15",
    "addr:postcode":"7160",
    "addr:street":"Rue De Gouy",
    "iso:country":"BE",
    "sg:address":"Rue De Gouy 15",
    "sg:city":"Chapelle-lez-herlaimont",
    "sg:orig_category":"Brood, gebak and snoepgoed",
    "sg:phone":"+32 64 44 49 48",
    "sg:postcode":"7160",
    "sg:province":"Hainaut",
    "wof:name":"Marc Blondeau",
    "wof:placetype":"venue"
},
  "geometry": {"coordinates":[4.2840099335,50.4709854126],"type":"Point"}
}