{
  "type": "Feature",
  "properties": {
    "iso:country":"BE",
    "sg:address":"Diestersteenweg 73",
    "sg:city":"Nieuwerkerken",
    "sg:orig_category":"Installation de menuiserie m\u00e9tallique",
    "sg:phone":"+32 11 69 62 65",
    "sg:postcode":"3850",
    "sg:province":"Limburg",
    "wof:name":"Ruyt - Alu",
    "wof:placetype":"venue"
},
  "geometry": {"coordinates":[5.1884078979,50.8615379333],"type":"Point"}
}