{
  "type": "Feature",
  "properties": {
    "iso:country":"BE",
    "sg:address":"Place Reine Astrid 18",
    "sg:city":"Jette",
    "sg:classifiers":[
        {
            "category":"Fast Food",
            "type":"Food & Drink"
        }
    ],
    "sg:phone":"+32 2 427 19 50",
    "sg:postcode":"1090",
    "sg:province":"Bruxelles-Capitale",
    "sg:tags":[
        "\u00c0",
        "emporter",
        "restaurants"
    ],
    "wof:name":"L\u00b4ardennais",
    "wof:placetype":"venue"
},
  "geometry": {"coordinates":[4.3248062134,50.8724594116],"type":"Point"}
}