{
  "type": "Feature",
  "properties": {
    "iso:country":"BE",
    "sg:address":"Watermolenstraat 95a",
    "sg:city":"Sint-niklaas (belsele)",
    "sg:classifiers":[
        {
            "category":"Personal",
            "subcategory":"Nail Salon",
            "type":"Services"
        }
    ],
    "sg:phone":"+32 3 778 14 44",
    "sg:postcode":"9111",
    "sg:province":"Oost-Vlaanderen",
    "sg:tags":[
        "pedicure"
    ],
    "wof:name":"Meul G",
    "wof:placetype":"venue"
},
  "geometry": {"coordinates":[4.1220598221,51.1665382385],"type":"Point"}
}