{
  "type": "Feature",
  "properties": {
    "iso:country":"BE",
    "sg:address":"Frans Mombaersstraat 51",
    "sg:city":"Kortenberg",
    "sg:orig_category":"Catering and organisation de f\u00eates",
    "sg:phone":"+32 2 759 48 78",
    "sg:postcode":"3071",
    "sg:province":"Vlaams-Brabant",
    "wof:name":"Traiteur Michel",
    "wof:placetype":"venue"
},
  "geometry": {"coordinates":[4.5499129295,50.9012565613],"type":"Point"}
}