{
  "type": "Feature",
  "properties": {
    "addr:full":"Putsesteenweg 36 Lier Antwerpen 2500",
    "addr:housenumber":"36",
    "addr:postcode":"2500",
    "addr:street":"Putsesteenweg",
    "iso:country":"BE",
    "sg:address":"Putsesteenweg 36",
    "sg:city":"Lier",
    "sg:orig_category":"Tuinen",
    "sg:phone":"+32 3 482 01 18",
    "sg:postcode":"2500",
    "sg:province":"Antwerpen",
    "wof:name":"Peter Vermeersch",
    "wof:placetype":"venue"
},
  "geometry": {"coordinates":[4.6160340309,51.0877227783],"type":"Point"}
}