{
  "type": "Feature",
  "properties": {
    "iso:country":"BE",
    "sg:address":"Bld Pr\u00c9sident Kennedy 2",
    "sg:city":"Mons",
    "sg:orig_category":"Kinderopvang",
    "sg:phone":"+32 65 39 29 56",
    "sg:postcode":"7000",
    "sg:province":"Hainaut",
    "wof:name":"Cr\u00c8che Les Ropieurs",
    "wof:placetype":"venue"
},
  "geometry": {"coordinates":[3.961124897,50.4565391541],"type":"Point"}
}