{
  "type": "Feature",
  "properties": {
    "iso:country":"BE",
    "sg:address":"Rue Du Coll\u00c8ge 7-9",
    "sg:city":"Charleroi",
    "sg:orig_category":"Decoratieve kunst and kunstbenodigdheden Foto-uitrusting Fotografen and fotostudio's",
    "sg:phone":"+32 71 32 21 37",
    "sg:postcode":"6000",
    "sg:province":"Hainaut",
    "wof:name":"Clic Clac 1 Heure Espace Cadre",
    "wof:placetype":"venue"
},
  "geometry": {"coordinates":[4.4397912025,50.4073257446],"type":"Point"}
}