{
  "type": "Feature",
  "properties": {
    "addr:full":"Eduard De Cuyperstraat 15 Oostende West-Vlaanderen 8400",
    "addr:housenumber":"15",
    "addr:postcode":"8400",
    "addr:street":"Eduard De Cuyperstraat",
    "iso:country":"BE",
    "sg:address":"Eduard De Cuyperstraat 15",
    "sg:city":"Oostende",
    "sg:classifiers":[
        {
            "category":"Professional",
            "subcategory":"Management & Consulting",
            "type":"Services"
        }
    ],
    "sg:phone":"+32 59 80 04 00",
    "sg:postcode":"8400",
    "sg:province":"West-Vlaanderen",
    "sg:tags":[
        "consultant"
    ],
    "wof:name":"Hosten",
    "wof:placetype":"venue"
},
  "geometry": {"coordinates":[2.9037690163,51.2226295471],"type":"Point"}
}