{
  "type": "Feature",
  "properties": {
    "iso:country":"BE",
    "sg:address":"Bergstraat 29",
    "sg:city":"Kortrijk",
    "sg:orig_category":"V\u00eatements sur mesure Fab",
    "sg:phone":"+32 56 41 69 22",
    "sg:postcode":"8511",
    "sg:province":"West-Vlaanderen",
    "wof:name":"Sabine Lachat",
    "wof:placetype":"venue"
},
  "geometry": {"coordinates":[3.2332599163,50.7775115967],"type":"Point"}
}