{
  "type": "Feature",
  "properties": {
    "addr:full":"Rue Franz Merjay 133 Bruxelles (ixelles) Bruxelles-Capitale 1050",
    "addr:housenumber":"133",
    "addr:postcode":"1050",
    "addr:street":"Rue Franz Merjay",
    "iso:country":"BE",
    "sg:address":"Rue Franz Merjay 133",
    "sg:city":"Bruxelles (ixelles)",
    "sg:classifiers":[
        {
            "category":"Shopping",
            "subcategory":"Antiques",
            "type":"Retail Goods"
        }
    ],
    "sg:phone":"+32 2 345 37 39",
    "sg:postcode":"1050",
    "sg:province":"Bruxelles-Capitale",
    "wof:name":"Essences De Si\u00e8cles",
    "wof:placetype":"venue"
},
  "geometry": {"coordinates":[4.3525300026,50.8178825378],"type":"Point"}
}