{
  "type": "Feature",
  "properties": {
    "addr:full":"Rue De Lessines 119 Ath Hainaut 7800",
    "addr:housenumber":"119",
    "addr:postcode":"7800",
    "addr:street":"Rue De Lessines",
    "iso:country":"BE",
    "sg:address":"Rue De Lessines 119",
    "sg:city":"Ath",
    "sg:orig_category":"Peinture. Rev\u00eatements pour sols and murs",
    "sg:phone":"+32 68 28 39 70",
    "sg:postcode":"7800",
    "sg:province":"Hainaut",
    "wof:name":"Serge Demierbe",
    "wof:placetype":"venue"
},
  "geometry": {"coordinates":[3.7995700836,50.6479110718],"type":"Point"}
}