{
  "type": "Feature",
  "properties": {
    "addr:full":"Rue Belle-vue 18 Villers-le-bouillet Li\u00e8ge 4530",
    "addr:housenumber":"18",
    "addr:postcode":"4530",
    "addr:street":"Rue Belle-Vue",
    "iso:country":"BE",
    "sg:address":"Rue Belle-vue 18",
    "sg:city":"Villers-le-bouillet",
    "sg:orig_category":"G\u00e9om\u00e8tres",
    "sg:phone":"+32 85 23 50 52",
    "sg:postcode":"4530",
    "sg:province":"Li\u00e8ge",
    "wof:name":"Jean Gerard",
    "wof:placetype":"venue"
},
  "geometry": {"coordinates":[5.2692728043,50.5626983643],"type":"Point"}
}