{
  "type": "Feature",
  "properties": {
    "addr:full":"Wipstraat 26 Antwerpen Antwerpen 2018",
    "addr:housenumber":"26",
    "addr:postcode":"2018",
    "addr:street":"Wipstraat",
    "iso:country":"BE",
    "sg:address":"Wipstraat 26",
    "sg:city":"Antwerpen",
    "sg:classifiers":[
        {
            "category":"Manufacturing",
            "subcategory":"Paper Products",
            "type":"Manufacturing & Wholesale Goods"
        }
    ],
    "sg:phone":"+32 3 225 27 88",
    "sg:postcode":"2018",
    "sg:province":"Antwerpen",
    "sg:tags":[
        "packing",
        "cardboard",
        "-"
    ],
    "wof:name":"Noble Fink",
    "wof:placetype":"venue"
},
  "geometry": {"coordinates":[4.4246768951,51.2112693787],"type":"Point"}
}