{
  "type": "Feature",
  "properties": {
    "addr:full":"Bochtstraat 23 Kontich Antwerpen 2550",
    "addr:housenumber":"23",
    "addr:postcode":"2550",
    "addr:street":"Bochtstraat",
    "iso:country":"BE",
    "sg:address":"Bochtstraat 23",
    "sg:city":"Kontich",
    "sg:orig_category":"Pleisterwerk",
    "sg:phone":"+32 3 457 18 02",
    "sg:postcode":"2550",
    "sg:province":"Antwerpen",
    "wof:name":"Marcel Stevens",
    "wof:placetype":"venue"
},
  "geometry": {"coordinates":[4.4476451874,51.1388893127],"type":"Point"}
}