{
  "type": "Feature",
  "properties": {
    "iso:country":"BE",
    "sg:address":"Rue Du Moulin 22",
    "sg:city":"Hamoir",
    "sg:orig_category":"RESTAURANTS: CAF\u00c9S",
    "sg:phone":"+32 86 38 98 58",
    "sg:postcode":"4180",
    "sg:province":"Li\u00e8ge",
    "wof:name":"L\u00b4epuisette C\u00d4t\u00c9 Jardin",
    "wof:placetype":"venue"
},
  "geometry": {"coordinates":[5.5343160629,50.4241752625],"type":"Point"}
}