{
  "type": "Feature",
  "properties": {
    "iso:country":"BE",
    "sg:address":"Meenseweg 403",
    "sg:city":"Ieper",
    "sg:orig_category":"Eleveurs de bovins",
    "sg:phone":"+32 57 20 24 76",
    "sg:postcode":"8902",
    "sg:province":"West-Vlaanderen",
    "wof:name":"Bernard Sercu",
    "wof:placetype":"venue"
},
  "geometry": {"coordinates":[2.921049118,50.8484954834],"type":"Point"}
}