{
  "type": "Feature",
  "properties": {
    "addr:full":"Marnixstraat 4 Antwerpen Antwerpen 2060",
    "addr:housenumber":"4",
    "addr:postcode":"2060",
    "addr:street":"Marnixstraat",
    "iso:country":"BE",
    "sg:address":"Marnixstraat 4",
    "sg:city":"Antwerpen",
    "sg:orig_category":"Etalage- and showroomontwerpers",
    "sg:phone":"+32 3 231 46 24",
    "sg:postcode":"2060",
    "sg:province":"Antwerpen",
    "wof:name":"Herman Adriaensen",
    "wof:placetype":"venue"
},
  "geometry": {"coordinates":[4.4192800522,51.2277297974],"type":"Point"}
}