{
  "type": "Feature",
  "properties": {
    "iso:country":"BE",
    "sg:address":"Kortrijksesteenweg 1097",
    "sg:city":"Gent",
    "sg:orig_category":"Boekbinderijen and afwerking Drukkerijen and copyshops",
    "sg:phone":"+32 9 220 10 64",
    "sg:postcode":"9051",
    "sg:province":"Oost-Vlaanderen",
    "wof:name":"Flanders Digital Color",
    "wof:placetype":"venue"
},
  "geometry": {"coordinates":[3.680991888,51.019569397],"type":"Point"}
}