{
  "type": "Feature",
  "properties": {
    "iso:country":"BE",
    "sg:address":"Ry De Fromont 3",
    "sg:city":"Sivry-rance",
    "sg:orig_category":"RESTAURANTS: CAF\u00c9S",
    "sg:phone":"+32 60 41 29 55",
    "sg:postcode":"6470",
    "sg:province":"Hainaut",
    "wof:name":"Auberge De Ry De Fromont",
    "wof:placetype":"venue"
},
  "geometry": {"coordinates":[4.2270932198,50.1492233276],"type":"Point"}
}