{
  "type": "Feature",
  "properties": {
    "addr:full":"Pieter Reypenslei 73 Mortsel Antwerpen 2640",
    "addr:housenumber":"73",
    "addr:postcode":"2640",
    "addr:street":"Pieter Reypenslei",
    "iso:country":"BE",
    "sg:address":"Pieter Reypenslei 73",
    "sg:city":"Mortsel",
    "sg:orig_category":"S\u00e9curit\u00e9 sociale",
    "sg:phone":"+32 3 449 93 83",
    "sg:postcode":"2640",
    "sg:province":"Antwerpen",
    "wof:name":"Onafhankelijk Ziekenfonds",
    "wof:placetype":"venue"
},
  "geometry": {"coordinates":[4.4522252083,51.1687202454],"type":"Point"}
}