{
  "type": "Feature",
  "properties": {
    "iso:country":"BE",
    "sg:address":"Molenhoek 19",
    "sg:city":"Wachtebeke",
    "sg:orig_category":"Diverse organisaties and verenigingen",
    "sg:phone":"+32 9 345 03 02",
    "sg:postcode":"9185",
    "sg:province":"Oost-Vlaanderen",
    "wof:name":"'t Kasseiken",
    "wof:placetype":"venue"
},
  "geometry": {"coordinates":[3.8638169765,51.1710128784],"type":"Point"}
}