{
  "type": "Feature",
  "properties": {
    "iso:country":"BE",
    "sg:address":"Populierenlaan 12",
    "sg:city":"Bredene",
    "sg:orig_category":"Diensten voor huisdieren",
    "sg:phone":"+32 59 32 17 65",
    "sg:postcode":"8450",
    "sg:province":"West-Vlaanderen",
    "wof:name":"Trimsalon Mormel",
    "wof:placetype":"venue"
},
  "geometry": {"coordinates":[2.967400074,51.2394447327],"type":"Point"}
}