{
  "type": "Feature",
  "properties": {
    "iso:country":"BE",
    "sg:address":"Place Joseph Wauters 9",
    "sg:city":"Watermaal-bosvoorde/watermael-",
    "sg:orig_category":"Sociale huisvestingsmaatschappijen",
    "sg:phone":"+32 2 672 31 42",
    "sg:postcode":"1170",
    "sg:province":"Bruxelles-Capitale",
    "wof:name":"Floreal",
    "wof:placetype":"venue"
},
  "geometry": {"coordinates":[4.4041399956,50.8091392517],"type":"Point"}
}