{
  "type": "Feature",
  "properties": {
    "addr:full":"Merolser Strasse 4 Eupen/eupen Li\u00e8ge 4701",
    "addr:housenumber":"4",
    "addr:postcode":"4701",
    "addr:street":"Merolser Strasse",
    "iso:country":"BE",
    "sg:address":"Merolser Strasse 4",
    "sg:city":"Eupen/eupen",
    "sg:orig_category":"Rundveehouders",
    "sg:phone":"+32 87 74 22 92",
    "sg:postcode":"4701",
    "sg:province":"Li\u00e8ge",
    "wof:name":"Viktor Havenith",
    "wof:placetype":"venue"
},
  "geometry": {"coordinates":[6.0461649895,50.6460838318],"type":"Point"}
}