{
  "type": "Feature",
  "properties": {
    "addr:full":"Boomstraat 78 Bornem Antwerpen 2880",
    "addr:housenumber":"78",
    "addr:postcode":"2880",
    "addr:street":"Boomstraat",
    "iso:country":"BE",
    "sg:address":"Boomstraat 78",
    "sg:city":"Bornem",
    "sg:orig_category":"Pain, p\u00e2tisseries and confiseries",
    "sg:phone":"+32 3 889 95 74",
    "sg:postcode":"2880",
    "sg:province":"Antwerpen",
    "wof:name":"Leonidas",
    "wof:placetype":"venue"
},
  "geometry": {"coordinates":[4.2329630852,51.0971908569],"type":"Point"}
}