{
  "type": "Feature",
  "properties": {
    "iso:country":"BE",
    "sg:address":"Blookstraat 1a-2",
    "sg:city":"Bilzen (mopertingen)",
    "sg:classifiers":[
        {
            "category":"Military Area",
            "subcategory":"Air Force Base",
            "type":"Public Place"
        }
    ],
    "sg:phone":"+32 89 61 34 94",
    "sg:postcode":"3740",
    "sg:province":"Limburg",
    "sg:tags":[
        "water",
        "treatment"
    ],
    "wof:name":"Luxell Bvba",
    "wof:placetype":"venue"
},
  "geometry": {"coordinates":[5.5781669617,50.8672027588],"type":"Point"}
}