{
  "type": "Feature",
  "properties": {
    "iso:country":"BE",
    "sg:address":"Avenue Jules Bordet 120",
    "sg:city":"Renaix",
    "sg:classifiers":[
        {
            "category":"Retail",
            "subcategory":"Laundry & Dry Cleaning",
            "type":"Services"
        }
    ],
    "sg:phone":"+32 55 21 16 49",
    "sg:postcode":"9600",
    "sg:province":"Oost-Vlaanderen",
    "sg:tags":[
        "knitwear",
        "-"
    ],
    "wof:name":"Neyt R",
    "wof:placetype":"venue"
},
  "geometry": {"coordinates":[3.5997951031,50.7394104004],"type":"Point"}
}