{
  "type": "Feature",
  "properties": {
    "iso:country":"BE",
    "sg:address":"Onze-lieve-vrouwestraat 35",
    "sg:city":"Mechelen",
    "sg:orig_category":"Naai- and breimachines",
    "sg:phone":"+32 15 41 57 60",
    "sg:postcode":"2800",
    "sg:province":"Antwerpen",
    "wof:name":"Van Rooy",
    "wof:placetype":"venue"
},
  "geometry": {"coordinates":[4.477973938,51.0242805481],"type":"Point"}
}