{
  "type": "Feature",
  "properties": {
    "iso:country":"BE",
    "sg:address":"Brusselbaan 363",
    "sg:city":"Affligem",
    "sg:orig_category":"Fleurs and plantes",
    "sg:phone":"+32 2 452 37 70",
    "sg:postcode":"1790",
    "sg:province":"Vlaams-Brabant",
    "wof:name":"Johan Vandermaeten",
    "wof:placetype":"venue"
},
  "geometry": {"coordinates":[4.1332669258,50.9122581482],"type":"Point"}
}