{
  "type": "Feature",
  "properties": {
    "addr:full":"Cedronbeekstraat 36 Stekene Oost-Vlaanderen 9190",
    "addr:housenumber":"36",
    "addr:postcode":"9190",
    "addr:street":"Cedronbeekstraat",
    "iso:country":"BE",
    "sg:address":"Cedronbeekstraat 36",
    "sg:city":"Stekene",
    "sg:classifiers":[
        {
            "category":"Arena",
            "subcategory":"Sports Club",
            "type":"Entertainment"
        }
    ],
    "sg:phone":"+32 3 779 67 81",
    "sg:postcode":"9190",
    "sg:province":"Oost-Vlaanderen",
    "sg:tags":[
        "de"
    ],
    "wof:name":"Volley Team Stekene",
    "wof:placetype":"venue"
},
  "geometry": {"coordinates":[4.0451278687,51.2020378113],"type":"Point"}
}