{
  "type": "Feature",
  "properties": {
    "addr:full":"Rue Des Betto 39 Waremme Li\u00e8ge 4300",
    "addr:housenumber":"39",
    "addr:postcode":"4300",
    "addr:street":"Rue Des Betto",
    "iso:country":"BE",
    "sg:address":"Rue Des Betto 39",
    "sg:city":"Waremme",
    "sg:orig_category":"Plaatsen van vloer- and muurbekleding Schilders",
    "sg:phone":"+32 19 32 80 39",
    "sg:postcode":"4300",
    "sg:province":"Li\u00e8ge",
    "wof:name":"Fe. Le Louarn",
    "wof:placetype":"venue"
},
  "geometry": {"coordinates":[5.2351651192,50.7100028992],"type":"Point"}
}