{
  "type": "Feature",
  "properties": {
    "addr:full":"Rue Du Fort 11 Comines-warneton (comines) Hainaut 7780",
    "addr:housenumber":"11",
    "addr:postcode":"7780",
    "addr:street":"Rue Du Fort",
    "iso:country":"BE",
    "sg:address":"Rue Du Fort 11",
    "sg:city":"Comines-warneton (comines)",
    "sg:classifiers":[
        {
            "category":"Bars & Pubs",
            "type":"Food & Drink"
        }
    ],
    "sg:phone":"+32 56 55 96 87",
    "sg:postcode":"7780",
    "sg:province":"Hainaut",
    "wof:name":"Henri",
    "wof:placetype":"venue"
},
  "geometry": {"coordinates":[3.0043849945,50.7659416199],"type":"Point"}
}