{
  "type": "Feature",
  "properties": {
    "iso:country":"BE",
    "sg:address":"Av De For\u00cat De Soignes 327",
    "sg:city":"Rhode-saint-genese",
    "sg:orig_category":"Bouwmaterialen Gh",
    "sg:phone":"+32 2 358 35 56",
    "sg:postcode":"1640",
    "sg:province":"Vlaams-Brabant",
    "wof:name":"Den Braven Belgium",
    "wof:placetype":"venue"
},
  "geometry": {"coordinates":[4.3789339066,50.7569465637],"type":"Point"}
}