{
  "type": "Feature",
  "properties": {
    "addr:full":"Weststraat 13 Moerbeke Oost-Vlaanderen 9180",
    "addr:housenumber":"13",
    "addr:postcode":"9180",
    "addr:street":"Weststraat",
    "iso:country":"BE",
    "sg:address":"Weststraat 13",
    "sg:city":"Moerbeke",
    "sg:orig_category":"Enseignement maternel and primaire",
    "sg:phone":"+32 9 346 98 39",
    "sg:postcode":"9180",
    "sg:province":"Oost-Vlaanderen",
    "wof:name":"Gemeentelijke Basisschool",
    "wof:placetype":"venue"
},
  "geometry": {"coordinates":[3.9342079163,51.2021217346],"type":"Point"}
}