{
  "type": "Feature",
  "properties": {
    "iso:country":"BE",
    "sg:address":"Mechelsesteenweg 30",
    "sg:city":"Kampenhout",
    "sg:classifiers":[
        {
            "category":"Food & Beverages",
            "subcategory":"Meat & Fish",
            "type":"Retail Goods"
        }
    ],
    "sg:phone":"+32 16 61 96 11",
    "sg:postcode":"1910",
    "sg:province":"Vlaams-Brabant",
    "sg:tags":[
        "fresh"
    ],
    "wof:name":"Covee Nv",
    "wof:placetype":"venue"
},
  "geometry": {"coordinates":[4.588283062,50.9589996338],"type":"Point"}
}