{
  "type": "Feature",
  "properties": {
    "iso:country":"BE",
    "sg:address":"Chauss\u00e9e Romaine 216",
    "sg:city":"Waremme",
    "sg:classifiers":[
        {
            "category":"Autos & Motor Vehicles",
            "subcategory":"Automobile Sales",
            "type":"Retail Goods"
        }
    ],
    "sg:phone":"+32 19 33 08 70",
    "sg:postcode":"4300",
    "sg:province":"Li\u00e8ge",
    "sg:tags":[
        "car",
        "used",
        "-"
    ],
    "wof:name":"Jm Service",
    "wof:placetype":"venue"
},
  "geometry": {"coordinates":[5.2783350945,50.6970252991],"type":"Point"}
}