{
  "type": "Feature",
  "properties": {
    "addr:full":"Twaalfde Liniestraat 23 Moeskroen/mouscron Hainaut 7700",
    "addr:housenumber":"23",
    "addr:postcode":"7700",
    "addr:street":"Twaalfde Liniestraat",
    "iso:country":"BE",
    "sg:address":"Twaalfde Liniestraat 23",
    "sg:city":"Moeskroen/mouscron",
    "sg:orig_category":"Sportclubs",
    "sg:phone":"+32 56 34 52 72",
    "sg:postcode":"7700",
    "sg:province":"Hainaut",
    "wof:name":"B.b.c. Estaimpuis",
    "wof:placetype":"venue"
},
  "geometry": {"coordinates":[3.235065937,50.7409324646],"type":"Point"}
}