{
  "type": "Feature",
  "properties": {
    "addr:full":"Rukkelingenstraat 19 Heers Limburg 3870",
    "addr:housenumber":"19",
    "addr:postcode":"3870",
    "addr:street":"Rukkelingenstraat",
    "iso:country":"BE",
    "sg:address":"Rukkelingenstraat 19",
    "sg:city":"Heers",
    "sg:orig_category":"Eleveurs and marchands de porcs",
    "sg:phone":"+32 11 48 47 70",
    "sg:postcode":"3870",
    "sg:province":"Limburg",
    "wof:name":"Edgard Dessart",
    "wof:placetype":"venue"
},
  "geometry": {"coordinates":[5.2549319267,50.7317962646],"type":"Point"}
}