{
  "type": "Feature",
  "properties": {
    "iso:country":"BE",
    "sg:address":"Rue Emile Vandervelde 50",
    "sg:city":"Charleroi",
    "sg:orig_category":"M\u00e9decins and sp\u00e9cialistes",
    "sg:phone":"+32 71 34 43 32",
    "sg:postcode":"6041",
    "sg:province":"Hainaut",
    "wof:name":"D. Burel",
    "wof:placetype":"venue"
},
  "geometry": {"coordinates":[4.4554481506,50.4223327637],"type":"Point"}
}