{
  "type": "Feature",
  "properties": {
    "addr:full":"Avenue Chazal 145 Bruxelles (schaerbeek) Bruxelles-Capitale 1030",
    "addr:housenumber":"145",
    "addr:postcode":"1030",
    "addr:street":"Avenue Chazal",
    "iso:country":"BE",
    "sg:address":"Avenue Chazal 145",
    "sg:city":"Bruxelles (schaerbeek)",
    "sg:classifiers":[
        {
            "category":"Health Services",
            "subcategory":"Health Practitioner",
            "type":"Services"
        }
    ],
    "sg:phone":"+32 2 242 83 04",
    "sg:postcode":"1030",
    "sg:province":"Bruxelles-Capitale",
    "sg:tags":[
        "physiotherapist"
    ],
    "wof:name":"Centre De Kin\u00e9sith\u00e9rapie",
    "wof:placetype":"venue"
},
  "geometry": {"coordinates":[4.3908882141,50.8579864502],"type":"Point"}
}