{
  "type": "Feature",
  "properties": {
    "addr:full":"Tienne De L'europe 14 Dinant Namur 5500",
    "addr:housenumber":"14",
    "addr:postcode":"5500",
    "addr:street":"De L'Europe",
    "iso:country":"BE",
    "sg:address":"Tienne De L'europe 14",
    "sg:city":"Dinant",
    "sg:classifiers":[
        {
            "category":"Wholesale",
            "subcategory":"Seafood",
            "type":"Manufacturing & Wholesale Goods"
        }
    ],
    "sg:phone":"+32 82 22 25 05",
    "sg:postcode":"5500",
    "sg:province":"Namur",
    "sg:tags":[
        "whol",
        "fish",
        "-",
        "shellfish"
    ],
    "wof:name":"Euro Moules Sprl",
    "wof:placetype":"venue"
},
  "geometry": {"coordinates":[4.9351329803,50.2671813965],"type":"Point"}
}