{
  "type": "Feature",
  "properties": {
    "addr:full":"Rue Robert Thoreau 4 Bruxelles (woluwe-saint-pierre) Bruxelles-Capitale 1150",
    "addr:housenumber":"4",
    "addr:postcode":"1150",
    "addr:street":"Rue Robert Thoreau",
    "iso:country":"BE",
    "sg:address":"Rue Robert Thoreau 4",
    "sg:city":"Bruxelles (woluwe-saint-pierre)",
    "sg:classifiers":[
        {
            "category":"Building & Trades",
            "subcategory":"Plumbing",
            "type":"Services"
        }
    ],
    "sg:phone":"+32 2 770 70 12",
    "sg:postcode":"1150",
    "sg:province":"Bruxelles-Capitale",
    "sg:tags":[
        "contractor"
    ],
    "wof:name":"Beckers",
    "wof:placetype":"venue"
},
  "geometry": {"coordinates":[4.4226469994,50.8372306824],"type":"Point"}
}