{
  "type": "Feature",
  "properties": {
    "addr:full":"Avenue Jean Mermoz 30 Charleroi (gosselies) Hainaut 6041",
    "addr:housenumber":"30",
    "addr:postcode":"6041",
    "addr:street":"Avenue Jean Mermoz",
    "iso:country":"BE",
    "sg:address":"Avenue Jean Mermoz 30",
    "sg:city":"Charleroi (gosselies)",
    "sg:classifiers":[
        {
            "category":"Manufacturing",
            "subcategory":"Metals",
            "type":"Manufacturing & Wholesale Goods"
        }
    ],
    "sg:phone":"+32 71 37 55 39",
    "sg:postcode":"6041",
    "sg:province":"Hainaut",
    "sg:tags":[
        "ornamental",
        "work",
        "-"
    ],
    "wof:name":"Ami M\u00e9tals Europe",
    "wof:placetype":"venue"
},
  "geometry": {"coordinates":[4.4716668129,50.4763908386],"type":"Point"}
}