{
  "type": "Feature",
  "properties": {
    "addr:full":"Marktstraat 22 Maldegem Oost-Vlaanderen 9990",
    "addr:housenumber":"22",
    "addr:postcode":"9990",
    "addr:street":"Marktstraat",
    "iso:country":"BE",
    "sg:address":"Marktstraat 22",
    "sg:city":"Maldegem",
    "sg:classifiers":[
        {
            "category":"Banks & Credit Unions",
            "subcategory":"Investment Brokerage",
            "type":"Services"
        }
    ],
    "sg:phone":"+32 50 71 62 94",
    "sg:postcode":"9990",
    "sg:province":"Oost-Vlaanderen",
    "sg:tags":[
        "supply",
        "processing",
        "-",
        "access",
        "carrier",
        "data"
    ],
    "wof:name":"Buro Service Maldegem",
    "wof:placetype":"venue"
},
  "geometry": {"coordinates":[3.4463789463,51.2091178894],"type":"Point"}
}