{
  "type": "Feature",
  "properties": {
    "addr:full":"Rue Emile-vandervelde 292 Li\u00e8ge Li\u00e8ge 4000",
    "addr:housenumber":"292",
    "addr:postcode":"4000",
    "addr:street":"Rue Emile-Vandervelde",
    "iso:country":"BE",
    "sg:address":"Rue Emile-vandervelde 292",
    "sg:city":"Li\u00e8ge",
    "sg:classifiers":[
        {
            "category":"Organizations",
            "subcategory":"Community Association",
            "type":"Services"
        }
    ],
    "sg:phone":"+32 4 224 76 76",
    "sg:postcode":"4000",
    "sg:province":"Li\u00e8ge",
    "sg:tags":[
        "box",
        "cardboard"
    ],
    "wof:name":"Pabecar S.a.",
    "wof:placetype":"venue"
},
  "geometry": {"coordinates":[5.5411229134,50.6469612122],"type":"Point"}
}