{
  "type": "Feature",
  "properties": {
    "iso:country":"BE",
    "sg:address":"Iers Kruisstraat 49",
    "sg:city":"Riemst (vlijtingen)",
    "sg:classifiers":[
        {
            "category":"Home & Garden",
            "subcategory":"Building Materials",
            "type":"Retail Goods"
        }
    ],
    "sg:phone":"+32 12 45 36 17",
    "sg:postcode":"3770",
    "sg:province":"Limburg",
    "sg:tags":[
        "house"
    ],
    "wof:name":"Hendriks Tuincentrum",
    "wof:placetype":"venue"
},
  "geometry": {"coordinates":[5.6199398041,50.8288078308],"type":"Point"}
}