{
  "type": "Feature",
  "properties": {
    "iso:country":"BE",
    "sg:address":"Gansbeekstraat 52",
    "sg:city":"Bilzen",
    "sg:orig_category":"Beheer onroerend goed",
    "sg:phone":"+32 89 49 19 60",
    "sg:postcode":"3740",
    "sg:province":"Limburg",
    "wof:name":"Lufa",
    "wof:placetype":"venue"
},
  "geometry": {"coordinates":[5.5162792206,50.8747444153],"type":"Point"}
}