{
  "type": "Feature",
  "properties": {
    "iso:country":"BE",
    "sg:address":"Rue Des Clairisses 7",
    "sg:city":"Tournai",
    "sg:classifiers":[
        {
            "category":"Cafe",
            "type":"Food & Drink"
        }
    ],
    "sg:phone":"+32 69 66 75 44",
    "sg:postcode":"7500",
    "sg:province":"Hainaut",
    "sg:tags":[
        "snack-bars"
    ],
    "wof:name":"Clairisses (les)",
    "wof:placetype":"venue"
},
  "geometry": {"coordinates":[3.3933598995,50.6044998169],"type":"Point"}
}