{
  "type": "Feature",
  "properties": {
    "iso:country":"BE",
    "sg:address":"Place Du Vieux March\u00c9 4",
    "sg:city":"Edingen/enghien",
    "sg:orig_category":"Installation de menuiserie en bois and plastique. Installation \u00e9lectrique r\u00e9sidentielle",
    "sg:phone":"+32 2 395 71 59",
    "sg:postcode":"7850",
    "sg:province":"Hainaut",
    "wof:name":"Patrick Liart",
    "wof:placetype":"venue"
},
  "geometry": {"coordinates":[4.0428600311,50.6951904297],"type":"Point"}
}