{
  "type": "Feature",
  "properties": {
    "addr:full":"Dr. Van De Perrestraat 125 Geel Antwerpen 2440",
    "addr:housenumber":"125",
    "addr:postcode":"2440",
    "addr:street":"Dr. Van De Perrestraat",
    "iso:country":"BE",
    "sg:address":"Dr. Van De Perrestraat 125",
    "sg:city":"Geel",
    "sg:classifiers":[
        {
            "category":"Professional",
            "subcategory":"Computer Services",
            "type":"Services"
        }
    ],
    "sg:phone":"+32 14 72 00 29",
    "sg:postcode":"2440",
    "sg:province":"Antwerpen",
    "sg:tags":[
        "webdesign",
        "-",
        "internet"
    ],
    "wof:name":"Uneek",
    "wof:placetype":"venue"
},
  "geometry": {"coordinates":[4.9871511459,51.1741333008],"type":"Point"}
}