{
  "type": "Feature",
  "properties": {
    "addr:full":"Chaussee De Maubeuge 287 Hyon Hainaut 7022",
    "addr:housenumber":"287",
    "addr:postcode":"7022",
    "addr:street":"Chaussee De Maubeuge;Hainaut",
    "iso:country":"BE",
    "sg:address":"Chaussee De Maubeuge 287",
    "sg:city":"Hyon",
    "sg:classifiers":[
        {
            "category":"Manufacturing",
            "subcategory":"Glass & Minerals",
            "type":"Manufacturing & Wholesale Goods"
        }
    ],
    "sg:phone":"+32 65 34 07 73",
    "sg:postcode":"7022",
    "sg:province":"Hainaut",
    "sg:tags":[
        "composite",
        "fibre",
        "material"
    ],
    "wof:name":"Drs S.a.",
    "wof:placetype":"venue"
},
  "geometry": {"coordinates":[3.9480719566,50.4287986755],"type":"Point"}
}