{
  "type": "Feature",
  "properties": {
    "iso:country":"BE",
    "sg:address":"Kazandstraat 139",
    "sg:city":"Roeselare",
    "sg:classifiers":[
        {
            "category":"Manufacturing",
            "subcategory":"Motor Vehicles & Parts",
            "type":"Manufacturing & Wholesale Goods"
        }
    ],
    "sg:phone":"+32 51 20 91 05",
    "sg:postcode":"8800",
    "sg:province":"West-Vlaanderen",
    "sg:tags":[
        "bearing"
    ],
    "wof:name":"Coppyn Etn Bvba",
    "wof:placetype":"venue"
},
  "geometry": {"coordinates":[3.1550040245,50.9415359497],"type":"Point"}
}