{
  "type": "Feature",
  "properties": {
    "iso:country":"BE",
    "sg:address":"Chemin De La Croix De Ch\u00f4des 2",
    "sg:city":"Malmedy",
    "sg:classifiers":[
        {
            "category":"Professional",
            "subcategory":"Management & Consulting",
            "type":"Services"
        }
    ],
    "sg:phone":"+32 80 33 94 77",
    "sg:postcode":"4960",
    "sg:province":"Li\u00e8ge",
    "sg:tags":[
        "marketing",
        "-",
        "direct",
        "consultant"
    ],
    "wof:name":"Elmo",
    "wof:placetype":"venue"
},
  "geometry": {"coordinates":[6.0369138718,50.4258308411],"type":"Point"}
}