{
  "type": "Feature",
  "properties": {
    "addr:full":"Luikersteenweg 680 Tongeren Limburg 3700",
    "addr:housenumber":"680",
    "addr:postcode":"3700",
    "addr:street":"Luikersteenweg",
    "iso:country":"BE",
    "sg:address":"Luikersteenweg 680",
    "sg:city":"Tongeren",
    "sg:orig_category":"Eleveurs de bovins",
    "sg:phone":"+32 12 23 28 26",
    "sg:postcode":"3700",
    "sg:province":"Limburg",
    "wof:name":"Ennot & Claes",
    "wof:placetype":"venue"
},
  "geometry": {"coordinates":[5.4735560417,50.7634391785],"type":"Point"}
}