{
  "type": "Feature",
  "properties": {
    "iso:country":"BE",
    "sg:address":"Avenue J S Bach 64",
    "sg:city":"Ukkel/uccle",
    "sg:classifiers":[
        {
            "category":"Taxi",
            "type":"Transportation"
        }
    ],
    "sg:phone":"+32 75661182",
    "sg:postcode":"1083",
    "sg:province":"Bruxelles-Capitale",
    "sg:tags":[
        "taxi's"
    ],
    "wof:name":"Taxi Way",
    "wof:placetype":"venue"
},
  "geometry": {"coordinates":[4.3070411682,50.8699188232],"type":"Point"}
}