{
  "type": "Feature",
  "properties": {
    "iso:country":"BE",
    "sg:address":"Place Albert Ier 8",
    "sg:city":"Malmedy",
    "sg:orig_category":"Villages de vacances",
    "sg:phone":"+32 80 33 08 33",
    "sg:postcode":"4960",
    "sg:province":"Li\u00e8ge",
    "wof:name":"Floreal Club",
    "wof:placetype":"venue"
},
  "geometry": {"coordinates":[6.0289969444,50.425819397],"type":"Point"}
}