{
  "type": "Feature",
  "properties": {
    "iso:country":"BE",
    "sg:address":"Rue De L'esplanade 28",
    "sg:city":"Sprimont",
    "sg:orig_category":"RESTAURANTS: FAST FOOD AND \u00c0 EMPORTER. H\u00d4TELS. SALLES DE CONF\u00c9RENCES AND DE R\u00c9CEPTIONS. RESTAURANTS.",
    "sg:phone":"+32 4 360 81 05",
    "sg:postcode":"4141",
    "sg:province":"Li\u00e8ge",
    "wof:name":"H\u00d4tel Des Nations",
    "wof:placetype":"venue"
},
  "geometry": {"coordinates":[5.7429919243,50.5384254456],"type":"Point"}
}