{
  "type": "Feature",
  "properties": {
    "addr:full":"Rue De Von\u00eache 81 Gedinne (vencimont) Namur 5575",
    "addr:housenumber":"81",
    "addr:postcode":"5575",
    "addr:street":"Rue De Vone\u0302Che",
    "iso:country":"BE",
    "sg:address":"Rue De Von\u00eache 81",
    "sg:city":"Gedinne (vencimont)",
    "sg:classifiers":[
        {
            "category":"Health Services",
            "subcategory":"Dentist",
            "type":"Services"
        }
    ],
    "sg:phone":"+32 61 58 97 42",
    "sg:postcode":"5575",
    "sg:province":"Namur",
    "wof:name":"Demarcin Alain",
    "wof:placetype":"venue"
},
  "geometry": {"coordinates":[4.9387412071,50.0377693176],"type":"Point"}
}