{
  "type": "Feature",
  "properties": {
    "addr:full":"Katteputstraat 10b31 Sint-agatha-berchem/berchem-sainte-agathe Bruxelles-Capitale 1082",
    "addr:housenumber":"10b31",
    "addr:postcode":"1082",
    "addr:street":"Katteputstraat;/",
    "iso:country":"BE",
    "sg:address":"Katteputstraat 10b31",
    "sg:city":"Sint-agatha-berchem/berchem-sainte-agathe",
    "sg:orig_category":"Juwelen and edelstenen Fab",
    "sg:phone":"+32 2 465 30 23",
    "sg:postcode":"1082",
    "sg:province":"Bruxelles-Capitale",
    "wof:name":"Charles Szerman",
    "wof:placetype":"venue"
},
  "geometry": {"coordinates":[4.3056869507,50.8653144836],"type":"Point"}
}