{
  "type": "Feature",
  "properties": {
    "addr:full":"Quai De Coronmeuse 28 Li\u00e8ge 1 Li\u00e8ge 4000",
    "addr:housenumber":"28;1",
    "addr:postcode":"4000",
    "addr:street":"Quai De Coronmeuse",
    "iso:country":"BE",
    "sg:address":"Quai De Coronmeuse 28",
    "sg:city":"Li\u00e8ge 1",
    "sg:classifiers":[
        {
            "category":"Building & Trades",
            "subcategory":"Equipment Rental",
            "type":"Services"
        }
    ],
    "sg:phone":"+32 4 227 44 44",
    "sg:postcode":"4000",
    "sg:province":"Li\u00e8ge",
    "sg:tags":[
        "fried",
        "supply",
        "-",
        "stand",
        "potato"
    ],
    "wof:name":"Sofinor-jacoby",
    "wof:placetype":"venue"
},
  "geometry": {"coordinates":[5.6029930115,50.6518630981],"type":"Point"}
}