{
  "type": "Feature",
  "properties": {
    "addr:full":"Rond-punt Robert Schuman 5 Etterbeek Bruxelles-Capitale 1040",
    "addr:housenumber":"5",
    "addr:postcode":"1040",
    "iso:country":"BE",
    "sg:address":"Rond-punt Robert Schuman 5",
    "sg:city":"Etterbeek",
    "sg:orig_category":"Banken and kredietinstellingen",
    "sg:phone":"+32 2 230 20 99",
    "sg:postcode":"1040",
    "sg:province":"Bruxelles-Capitale",
    "wof:name":"Bbl",
    "wof:placetype":"venue"
},
  "geometry": {"coordinates":[4.3870849609,50.8363609314],"type":"Point"}
}