{
  "type": "Feature",
  "properties": {
    "addr:full":"Place Franklin Roosevelt 14 Renaix Oost-Vlaanderen 9600",
    "addr:housenumber":"14",
    "addr:postcode":"9600",
    "addr:street":"Place Franklin Roosevelt",
    "iso:country":"BE",
    "sg:address":"Place Franklin Roosevelt 14",
    "sg:city":"Renaix",
    "sg:classifiers":[
        {
            "category":"Health Services",
            "subcategory":"Dentist",
            "type":"Services"
        }
    ],
    "sg:phone":"+32 55 21 50 22",
    "sg:postcode":"9600",
    "sg:province":"Oost-Vlaanderen",
    "wof:name":"Bocquet R",
    "wof:placetype":"venue"
},
  "geometry": {"coordinates":[3.5993099213,50.7466468811],"type":"Point"}
}