{
  "type": "Feature",
  "properties": {
    "addr:full":"Rue De La Charit\u00e9 41 Bruxelles (saint-josse-ten-noode) Bruxelles-Capitale 1210",
    "addr:housenumber":"41",
    "addr:postcode":"1210",
    "addr:street":"Rue De La Charite\u0301",
    "iso:country":"BE",
    "sg:address":"Rue De La Charit\u00e9 41",
    "sg:city":"Bruxelles (saint-josse-ten-noode)",
    "sg:classifiers":[
        {
            "category":"Social Services",
            "type":"Services"
        }
    ],
    "sg:phone":"+32 2 229 36 50",
    "sg:postcode":"1210",
    "sg:province":"Bruxelles-Capitale",
    "wof:name":"Serah Asbl",
    "wof:placetype":"venue"
},
  "geometry": {"coordinates":[4.3705039024,50.8475418091],"type":"Point"}
}