{
  "type": "Feature",
  "properties": {
    "addr:full":"Kapelstraat 67 Beerse Antwerpen 2340",
    "addr:housenumber":"67",
    "addr:postcode":"2340",
    "addr:street":"Kapelstraat",
    "iso:country":"BE",
    "sg:address":"Kapelstraat 67",
    "sg:city":"Beerse",
    "sg:classifiers":[
        {
            "category":"Food & Beverages",
            "subcategory":"Candy",
            "type":"Retail Goods"
        }
    ],
    "sg:phone":"+32 14 61 31 13",
    "sg:postcode":"2340",
    "sg:province":"Antwerpen",
    "wof:name":"Driewerf Hoera!!!",
    "wof:placetype":"venue"
},
  "geometry": {"coordinates":[4.8405771255,51.318271637],"type":"Point"}
}