{
  "type": "Feature",
  "properties": {
    "addr:full":"Rue Du Viaduc 19 Luik Li\u00e8ge 4000",
    "addr:housenumber":"19",
    "addr:postcode":"4000",
    "addr:street":"Rue Du Viaduc;Luik Lie\u0300Ge",
    "iso:country":"BE",
    "sg:address":"Rue Du Viaduc 19",
    "sg:city":"Luik",
    "sg:orig_category":"Quincailleries. Constructions non r\u00e9sidentielles sp\u00e9cifiques",
    "sg:phone":"+32 4 253 42 67",
    "sg:postcode":"4000",
    "sg:province":"Li\u00e8ge",
    "wof:name":"Ecomi",
    "wof:placetype":"venue"
},
  "geometry": {"coordinates":[5.5560588837,50.6102104187],"type":"Point"}
}