{
  "type": "Feature",
  "properties": {
    "addr:full":"Prinsbowdewynlaan 86 Antwerpen Antwerpen 2160",
    "addr:housenumber":"86",
    "addr:postcode":"2160",
    "addr:street":"Prinsbowdewynlaan",
    "iso:country":"BE",
    "sg:address":"Prinsbowdewynlaan 86",
    "sg:city":"Antwerpen",
    "sg:classifiers":[
        {
            "category":"Wholesale",
            "subcategory":"Farm Supplies",
            "type":"Manufacturing & Wholesale Goods"
        }
    ],
    "sg:phone":"+32 3 232 80 16",
    "sg:postcode":"2160",
    "sg:province":"Antwerpen",
    "sg:tags":[
        "-",
        "machine",
        "equipment",
        "engineering",
        "machinery",
        "mechanical",
        "agriculture"
    ],
    "wof:name":"Indamerica International Nv",
    "wof:placetype":"venue"
},
  "geometry": {"coordinates":[4.5230050087,51.2034759521],"type":"Point"}
}