{
  "type": "Feature",
  "properties": {
    "addr:full":"Ruelle Corde 5 Leuze-en-hainaut Hainaut 7900",
    "addr:housenumber":"5",
    "addr:postcode":"7900",
    "addr:street":"Ruelle Corde",
    "iso:country":"BE",
    "sg:address":"Ruelle Corde 5",
    "sg:city":"Leuze-en-hainaut",
    "sg:orig_category":"Boekhouders",
    "sg:postcode":"7900",
    "sg:province":"Hainaut",
    "wof:name":"Jos\u00c9 Virlez",
    "wof:placetype":"venue"
},
  "geometry": {"coordinates":[3.6186900139,50.5990180969],"type":"Point"}
}