{
  "type": "Feature",
  "properties": {
    "addr:full":"Avenue Des Grives 6 Waterloo Brabant Wallon 1410",
    "addr:housenumber":"6",
    "addr:postcode":"1410",
    "addr:street":"Avenue Des Grives",
    "iso:country":"BE",
    "sg:address":"Avenue Des Grives 6",
    "sg:city":"Waterloo",
    "sg:classifiers":[
        {
            "category":"Building & Trades",
            "subcategory":"Landscaping Services",
            "type":"Services"
        }
    ],
    "sg:phone":"+32 2 354 88 81",
    "sg:postcode":"1410",
    "sg:province":"Brabant Wallon",
    "sg:tags":[
        "nurseryman"
    ],
    "wof:name":"Waterloo Gardens Sprl",
    "wof:placetype":"venue"
},
  "geometry": {"coordinates":[4.3896341324,50.7316093445],"type":"Point"}
}