{
  "type": "Feature",
  "properties": {
    "addr:full":"Serpentstraat 22 Gent Oost-Vlaanderen 9000",
    "addr:housenumber":"22",
    "addr:postcode":"9000",
    "addr:street":"Serpentstraat;Oost-Vlaanderen",
    "iso:country":"BE",
    "sg:address":"Serpentstraat 22",
    "sg:city":"Gent",
    "sg:classifiers":[
        {
            "category":"Shopping",
            "subcategory":"Gifts & Souvenirs",
            "type":"Retail Goods"
        }
    ],
    "sg:phone":"+32 9 225 93 63",
    "sg:postcode":"9000",
    "sg:province":"Oost-Vlaanderen",
    "sg:tags":[
        "-"
    ],
    "wof:name":"Zsa-zsa Rouge",
    "wof:placetype":"venue"
},
  "geometry": {"coordinates":[3.7260410786,51.0561408997],"type":"Point"}
}