{
  "type": "Feature",
  "properties": {
    "addr:full":"Craenevenne 24 Genk Limburg 3600",
    "addr:housenumber":"24",
    "addr:postcode":"3600",
    "addr:street":"Craenevenne",
    "iso:country":"BE",
    "sg:address":"Craenevenne 24",
    "sg:city":"Genk",
    "sg:orig_category":"Gespecialiseerde residenti\u00eble bouw",
    "sg:phone":"+32 89 35 21 07",
    "sg:postcode":"3600",
    "sg:province":"Limburg",
    "wof:name":"Peter Vierendeels",
    "wof:placetype":"venue"
},
  "geometry": {"coordinates":[5.4300050735,50.9645843506],"type":"Point"}
}