{
  "type": "Feature",
  "properties": {
    "iso:country":"BE",
    "sg:address":"Rue Neuve 59",
    "sg:city":"Pepinster",
    "sg:classifiers":[
        {
            "category":"Fast Food",
            "type":"Food & Drink"
        }
    ],
    "sg:phone":"+32 87 46 06 93",
    "sg:postcode":"4860",
    "sg:province":"Li\u00e8ge",
    "sg:tags":[
        "de",
        "restaurant",
        "organisation",
        "\u00e0",
        "catering",
        "emporter",
        "f\u00eates"
    ],
    "wof:name":"Restaurant Via Nuova",
    "wof:placetype":"venue"
},
  "geometry": {"coordinates":[5.8032360077,50.5663223267],"type":"Point"}
}