{
  "type": "Feature",
  "properties": {
    "iso:country":"BE",
    "sg:address":"Stoffelsbergstraat 2",
    "sg:city":"Genk",
    "sg:orig_category":"Advocaten and juridische adviseurs",
    "sg:phone":"+32 89 35 34 76",
    "sg:postcode":"3600",
    "sg:province":"Limburg",
    "wof:name":"Frans Geukens",
    "wof:placetype":"venue"
},
  "geometry": {"coordinates":[5.4991087914,50.967666626],"type":"Point"}
}