{
  "type": "Feature",
  "properties": {
    "addr:full":"Avenue Bel Horizon 5 La Hulpe Brabant Wallon 1310",
    "addr:housenumber":"5",
    "addr:postcode":"1310",
    "addr:street":"Avenue Bel Horizon",
    "iso:country":"BE",
    "sg:address":"Avenue Bel Horizon 5",
    "sg:city":"La Hulpe",
    "sg:classifiers":[
        {
            "category":"Home & Garden",
            "subcategory":"Carpets & Floor Coverings",
            "type":"Retail Goods"
        }
    ],
    "sg:phone":"+32 2 653 15 93",
    "sg:postcode":"1310",
    "sg:province":"Brabant Wallon",
    "sg:tags":[
        "layer",
        "mosaicists"
    ],
    "wof:name":"Defrenne",
    "wof:placetype":"venue"
},
  "geometry": {"coordinates":[4.4863128662,50.7327194214],"type":"Point"}
}