{
  "type": "Feature",
  "properties": {
    "addr:full":"Ganzestraat 65 Diepenbeek Limburg 3590",
    "addr:housenumber":"65",
    "addr:postcode":"3590",
    "addr:street":"Ganzestraat",
    "iso:country":"BE",
    "sg:address":"Ganzestraat 65",
    "sg:city":"Diepenbeek",
    "sg:orig_category":"Fruitteelt Rundveehouders",
    "sg:phone":"+32 11 33 15 11",
    "sg:postcode":"3590",
    "sg:province":"Limburg",
    "wof:name":"Jules Groven",
    "wof:placetype":"venue"
},
  "geometry": {"coordinates":[5.3836760521,50.8962173462],"type":"Point"}
}