{
  "type": "Feature",
  "properties": {
    "addr:full":"Clos De La Magneroule 18 Charleroi (marcinelle) Hainaut 6001",
    "addr:housenumber":"18",
    "addr:postcode":"6001",
    "addr:street":"Clos De La Magneroule",
    "iso:country":"BE",
    "sg:address":"Clos De La Magneroule 18",
    "sg:city":"Charleroi (marcinelle)",
    "sg:classifiers":[
        {
            "category":"Health Services",
            "subcategory":"Health Practitioner",
            "type":"Services"
        }
    ],
    "sg:phone":"+32 71 47 18 64",
    "sg:postcode":"6001",
    "sg:province":"Hainaut",
    "sg:tags":[
        "physiotherapist"
    ],
    "wof:name":"Philippart Danny",
    "wof:placetype":"venue"
},
  "geometry": {"coordinates":[4.4306049347,50.3730583191],"type":"Point"}
}