{
  "type": "Feature",
  "properties": {
    "addr:full":"Avenue Foch 764 Mons (jemappes) Hainaut 7012",
    "addr:housenumber":"764",
    "addr:postcode":"7012",
    "addr:street":"Avenue Foch",
    "iso:country":"BE",
    "sg:address":"Avenue Foch 764",
    "sg:city":"Mons (jemappes)",
    "sg:classifiers":[
        {
            "category":"Banks & Credit Unions",
            "subcategory":"Financial Services",
            "type":"Services"
        }
    ],
    "sg:phone":"+32 65 88 21 10",
    "sg:postcode":"7012",
    "sg:province":"Hainaut",
    "sg:tags":[
        "financing"
    ],
    "wof:name":"Dumont Yves Sa",
    "wof:placetype":"venue"
},
  "geometry": {"coordinates":[3.8894600868,50.4481964111],"type":"Point"}
}