{
  "type": "Feature",
  "properties": {
    "addr:full":"Chauss\u00e9e De Binche 151 Mons Hainaut 7000",
    "addr:housenumber":"151",
    "addr:postcode":"7000",
    "addr:street":"Chausse\u0301E De Binche;Hainaut",
    "iso:country":"BE",
    "sg:address":"Chauss\u00e9e De Binche 151",
    "sg:city":"Mons",
    "sg:classifiers":[
        {
            "category":"Professional",
            "subcategory":"Business Services",
            "type":"Services"
        }
    ],
    "sg:phone":"+32 65 32 32 11",
    "sg:postcode":"7000",
    "sg:province":"Hainaut",
    "sg:tags":[
        "training",
        "advice"
    ],
    "wof:name":"Facultes Universitaires Catholiques De Mons Asbl",
    "wof:placetype":"venue"
},
  "geometry": {"coordinates":[3.9803500175,50.4521369934],"type":"Point"}
}