{
  "type": "Feature",
  "properties": {
    "addr:full":"Kapellestraat 12 Evergem Oost-Vlaanderen 9940",
    "addr:housenumber":"12",
    "addr:postcode":"9940",
    "addr:street":"Kapellestraat;Oost-Vlaanderen",
    "iso:country":"BE",
    "sg:address":"Kapellestraat 12",
    "sg:city":"Evergem",
    "sg:orig_category":"Slagers",
    "sg:phone":"+32 9 253 81 03",
    "sg:postcode":"9940",
    "sg:province":"Oost-Vlaanderen",
    "wof:name":"Arsene Van De Velde",
    "wof:placetype":"venue"
},
  "geometry": {"coordinates":[3.7100949287,51.1101379395],"type":"Point"}
}