{
  "type": "Feature",
  "properties": {
    "iso:country":"BE",
    "sg:address":"Avenue J. B. Nothomb 8",
    "sg:city":"Arlon",
    "sg:orig_category":"M\u00e9decins and sp\u00e9cialistes",
    "sg:phone":"+32 63 22 63 13",
    "sg:postcode":"6700",
    "sg:province":"Luxembourg",
    "wof:name":"Louis Jamotton",
    "wof:placetype":"venue"
},
  "geometry": {"coordinates":[5.8115158081,49.6821365356],"type":"Point"}
}