{
  "type": "Feature",
  "properties": {
    "iso:country":"BE",
    "sg:address":"Langstraat 33-35",
    "sg:city":"Maasmechelen (eisden)",
    "sg:classifiers":[
        {
            "category":"Home & Garden",
            "subcategory":"Home Furnishings",
            "type":"Retail Goods"
        }
    ],
    "sg:phone":"+32 89 76 41 74",
    "sg:postcode":"3630",
    "sg:province":"Limburg",
    "sg:tags":[
        "curtain",
        "-",
        "fixture"
    ],
    "wof:name":"Tiesters",
    "wof:placetype":"venue"
},
  "geometry": {"coordinates":[5.7117700577,50.9851646423],"type":"Point"}
}