{
  "type": "Feature",
  "properties": {
    "addr:full":"Chauss\u00e9e De Helmet 126 Bruxelles (schaerbeek) Bruxelles-Capitale 1030",
    "addr:housenumber":"126",
    "addr:postcode":"1030",
    "addr:street":"Chausse\u0301E De Helmet",
    "iso:country":"BE",
    "sg:address":"Chauss\u00e9e De Helmet 126",
    "sg:city":"Bruxelles (schaerbeek)",
    "sg:classifiers":[
        {
            "category":"Home & Garden",
            "subcategory":"Home Furnishings",
            "type":"Retail Goods"
        }
    ],
    "sg:phone":"+32 2 216 70 85",
    "sg:postcode":"1030",
    "sg:province":"Bruxelles-Capitale",
    "sg:tags":[
        "curtain",
        "-",
        "fixture"
    ],
    "wof:name":"J. Simon",
    "wof:placetype":"venue"
},
  "geometry": {"coordinates":[4.3848419189,50.8716583252],"type":"Point"}
}