{
  "type": "Feature",
  "properties": {
    "addr:full":"Nederholbeekstraat 17 Maarkedal Oost-Vlaanderen 9680",
    "addr:housenumber":"17",
    "addr:postcode":"9680",
    "addr:street":"Nederholbeekstraat",
    "iso:country":"BE",
    "sg:address":"Nederholbeekstraat 17",
    "sg:city":"Maarkedal",
    "sg:orig_category":"Pain, p\u00e2tisseries and confiseries",
    "sg:phone":"+32 55 31 28 98",
    "sg:postcode":"9680",
    "sg:province":"Oost-Vlaanderen",
    "wof:name":"Jose Opsomer",
    "wof:placetype":"venue"
},
  "geometry": {"coordinates":[3.6241528988,50.8097496033],"type":"Point"}
}