{
  "type": "Feature",
  "properties": {
    "iso:country":"BE",
    "sg:address":"Hollestraat 154",
    "sg:city":"Galmaarden",
    "sg:orig_category":"Eleveurs de bovins",
    "sg:phone":"+32 54 58 93 31",
    "sg:postcode":"1570",
    "sg:province":"Vlaams-Brabant",
    "wof:name":"Theophiel Plasman",
    "wof:placetype":"venue"
},
  "geometry": {"coordinates":[3.9823129177,50.7535400391],"type":"Point"}
}