{
  "type": "Feature",
  "properties": {
    "iso:country":"BE",
    "sg:address":"Avenue Jean Van Horenbeeck 204",
    "sg:city":"Bruxelles (auderghem)",
    "sg:classifiers":[
        {
            "category":"Social Services",
            "subcategory":"Job Training",
            "type":"Services"
        }
    ],
    "sg:phone":"+32 2 660 82 84",
    "sg:postcode":"1160",
    "sg:province":"Bruxelles-Capitale",
    "sg:tags":[
        "interpreter"
    ],
    "wof:name":"Steurs S",
    "wof:placetype":"venue"
},
  "geometry": {"coordinates":[4.4340200424,50.8048667908],"type":"Point"}
}