{
  "type": "Feature",
  "properties": {
    "iso:country":"BE",
    "sg:address":"J. B. Woutersstraat 124",
    "sg:city":"Beersel (alsemberg)",
    "sg:classifiers":[
        {
            "category":"Professional",
            "subcategory":"Computer Services",
            "type":"Services"
        }
    ],
    "sg:phone":"+32 2 381 01 31",
    "sg:postcode":"1652",
    "sg:province":"Vlaams-Brabant",
    "sg:tags":[
        "-",
        "processing",
        "data",
        "software"
    ],
    "wof:name":"Eruca-technical Lab",
    "wof:placetype":"venue"
},
  "geometry": {"coordinates":[4.3182268143,50.7367248535],"type":"Point"}
}