{
  "type": "Feature",
  "properties": {
    "addr:full":"Veldeken 31 Nevele Oost-Vlaanderen 9850",
    "addr:housenumber":"31",
    "addr:postcode":"9850",
    "addr:street":"Veldeken",
    "iso:country":"BE",
    "sg:address":"Veldeken 31",
    "sg:city":"Nevele",
    "sg:classifiers":[
        {
            "category":"Farming",
            "subcategory":"Crops",
            "type":"Manufacturing & Wholesale Goods"
        }
    ],
    "sg:phone":"+32 9 371 57 08",
    "sg:postcode":"9850",
    "sg:province":"Oost-Vlaanderen",
    "sg:tags":[
        "vegetable",
        "fruit",
        "-",
        "grower"
    ],
    "wof:name":"Van Loocke J",
    "wof:placetype":"venue"
},
  "geometry": {"coordinates":[3.5176260471,51.0570335388],"type":"Point"}
}