{
  "type": "Feature",
  "properties": {
    "addr:full":"Rue Winkel 7 Kelmis (hergenrath) Li\u00e8ge 4728",
    "addr:housenumber":"7",
    "addr:postcode":"4728",
    "addr:street":"Rue Winkel",
    "iso:country":"BE",
    "sg:address":"Rue Winkel 7",
    "sg:city":"Kelmis (hergenrath)",
    "sg:classifiers":[
        {
            "category":"Social Services",
            "subcategory":"Job Training",
            "type":"Services"
        }
    ],
    "sg:phone":"+32 87 63 08 10",
    "sg:postcode":"4728",
    "sg:province":"Li\u00e8ge",
    "sg:tags":[
        "personnel"
    ],
    "wof:name":"Adamski Pers\u00f6nlichkeits Entwicklung",
    "wof:placetype":"venue"
},
  "geometry": {"coordinates":[6.0320258141,50.708026886],"type":"Point"}
}