{
  "type": "Feature",
  "properties": {
    "addr:full":"Flor\u00c9allaan 53 Ukkel/uccle Bruxelles-Capitale 1180",
    "addr:housenumber":"53",
    "addr:postcode":"1180",
    "addr:street":"Flore\u0301Allaan;/",
    "iso:country":"BE",
    "sg:address":"Flor\u00c9allaan 53",
    "sg:city":"Ukkel/uccle",
    "sg:orig_category":"Rusthuizen and serviceflats",
    "sg:phone":"+32 2 344 47 84",
    "sg:postcode":"1180",
    "sg:province":"Bruxelles-Capitale",
    "wof:name":"Home Nd De Toutes Graces",
    "wof:placetype":"venue"
},
  "geometry": {"coordinates":[4.3425278664,50.8087463379],"type":"Point"}
}