{
  "type": "Feature",
  "properties": {
    "iso:country":"BE",
    "sg:address":"Dentergemstraat 90",
    "sg:city":"Oostrozebeke",
    "sg:classifiers":[
        {
            "category":"Professional",
            "subcategory":"Engineering",
            "type":"Services"
        }
    ],
    "sg:phone":"+32 56 66 57 02",
    "sg:postcode":"8780",
    "sg:province":"West-Vlaanderen",
    "sg:tags":[
        "technical",
        "equipment",
        "offices-"
    ],
    "wof:name":"Intratech Bvba",
    "wof:placetype":"venue"
},
  "geometry": {"coordinates":[3.360213995,50.9353141785],"type":"Point"}
}