{
  "type": "Feature",
  "properties": {
    "addr:full":"Rue Antoine Dansaert 67-69 Bruxelles Bruxelles-Capitale 1000",
    "addr:postcode":"67-69;1000",
    "addr:street":"Rue Antoine Dansaert",
    "iso:country":"BE",
    "sg:address":"Rue Antoine Dansaert 67-69",
    "sg:city":"Bruxelles",
    "sg:classifiers":[
        {
            "category":"Personal",
            "type":"Services"
        }
    ],
    "sg:phone":"+32 2 511 04 43",
    "sg:postcode":"1000",
    "sg:province":"Bruxelles-Capitale",
    "sg:tags":[
        "clothing",
        "men's",
        "tailor",
        "-"
    ],
    "wof:name":"Ancienne Maison Orlans",
    "wof:placetype":"venue"
},
  "geometry": {"coordinates":[4.346968174,50.8498458862],"type":"Point"}
}