{
  "type": "Feature",
  "properties": {
    "addr:full":"Kaai 1 Antwerpen Antwerpen 2030",
    "addr:housenumber":"1",
    "addr:postcode":"2030",
    "addr:street":"Kaai",
    "iso:country":"BE",
    "sg:address":"Kaai 1",
    "sg:city":"Antwerpen",
    "sg:orig_category":"Onderdelen and accessoires voor auto's",
    "sg:phone":"+32 3 542 31 63",
    "sg:postcode":"2030",
    "sg:province":"Antwerpen",
    "wof:name":"Ats",
    "wof:placetype":"venue"
},
  "geometry": {"coordinates":[4.3637099266,51.2742385864],"type":"Point"}
}