{
  "type": "Feature",
  "properties": {
    "iso:country":"BE",
    "sg:address":"Koning Albertstraat 52",
    "sg:city":"Hasselt",
    "sg:orig_category":"Articles pour b\u00e9b\u00e9s. V\u00eatements pour b\u00e9b\u00e9s and enfants",
    "sg:phone":"+32 11 22 37 54",
    "sg:postcode":"3500",
    "sg:province":"Limburg",
    "wof:name":"Prinsje",
    "wof:placetype":"venue"
},
  "geometry": {"coordinates":[5.3367619514,50.9277458191],"type":"Point"}
}