{
  "type": "Feature",
  "properties": {
    "iso:country":"BE",
    "sg:address":"Rijksweg 21",
    "sg:city":"Wielsbeke",
    "sg:classifiers":[
        {
            "category":"Bakery",
            "type":"Food & Drink"
        }
    ],
    "sg:phone":"+32 56 60 91 36",
    "sg:postcode":"8710",
    "sg:province":"West-Vlaanderen",
    "sg:tags":[
        "confectioner",
        "baker"
    ],
    "wof:name":"Patisserie Geert Pauwels Annemie Claerhout",
    "wof:placetype":"venue"
},
  "geometry": {"coordinates":[3.3838999271,50.9110298157],"type":"Point"}
}