{
  "type": "Feature",
  "properties": {
    "addr:full":"Place Du G\u00c9n\u00c9ral Leman 43 Li\u00c8ge Li\u00e8ge 4000",
    "addr:housenumber":"43",
    "addr:postcode":"4000",
    "addr:street":"Place Du Ge\u0301Ne\u0301Ral Leman",
    "iso:country":"BE",
    "sg:address":"Place Du G\u00c9n\u00c9ral Leman 43",
    "sg:city":"Li\u00c8ge",
    "sg:orig_category":"Assurances. Bureaux de poste",
    "sg:phone":"+32 4 252 83 98",
    "sg:postcode":"4000",
    "sg:province":"Li\u00e8ge",
    "wof:name":"La Poste",
    "wof:placetype":"venue"
},
  "geometry": {"coordinates":[5.5740728378,50.62059021],"type":"Point"}
}