{
  "type": "Feature",
  "properties": {
    "iso:country":"BE",
    "sg:address":"Dorpsstraat 33",
    "sg:city":"Bilzen",
    "sg:orig_category":"Pain, p\u00e2tisseries and confiseries",
    "sg:phone":"+32 89 49 26 66",
    "sg:postcode":"3740",
    "sg:province":"Limburg",
    "wof:name":"Bakkerij Thoonen",
    "wof:placetype":"venue"
},
  "geometry": {"coordinates":[5.5749697685,50.8743247986],"type":"Point"}
}