{
  "type": "Feature",
  "properties": {
    "addr:full":"Grand'place 5 Hannut Li\u00e8ge 4280",
    "addr:housenumber":"5",
    "addr:postcode":"4280",
    "addr:street":"Grand'Place",
    "iso:country":"BE",
    "sg:address":"Grand'place 5",
    "sg:city":"Hannut",
    "sg:orig_category":"Banques and organismes de cr\u00e9dit",
    "sg:phone":"+32 19 51 13 10",
    "sg:postcode":"4280",
    "sg:province":"Li\u00e8ge",
    "wof:name":"Dexia",
    "wof:placetype":"venue"
},
  "geometry": {"coordinates":[5.0776910782,50.6725883484],"type":"Point"}
}