{
  "type": "Feature",
  "properties": {
    "addr:full":"Rue Du Solitaire 42 Leuze-en-hainaut Hainaut 7900",
    "addr:housenumber":"42",
    "addr:postcode":"7900",
    "addr:street":"Rue Du Solitaire",
    "iso:country":"BE",
    "sg:address":"Rue Du Solitaire 42",
    "sg:city":"Leuze-en-hainaut",
    "sg:classifiers":[
        {
            "category":"Real Estate",
            "subcategory":"Architect",
            "type":"Services"
        }
    ],
    "sg:phone":"+32 69 66 24 21",
    "sg:postcode":"7900",
    "sg:province":"Hainaut",
    "wof:name":"Deportemont B",
    "wof:placetype":"venue"
},
  "geometry": {"coordinates":[3.6125810146,50.5975532532],"type":"Point"}
}