{
  "type": "Feature",
  "properties": {
    "iso:country":"BE",
    "sg:address":"Rue Derri\u00c8re-les-haies 6",
    "sg:city":"Fexhe-le-haut-clocher",
    "sg:orig_category":"Artsen and specialisten",
    "sg:phone":"+32 4 250 34 50",
    "sg:postcode":"4347",
    "sg:province":"Li\u00e8ge",
    "wof:name":"L\u00c9opold Renson",
    "wof:placetype":"venue"
},
  "geometry": {"coordinates":[5.4255108833,50.6534729004],"type":"Point"}
}