{
  "type": "Feature",
  "properties": {
    "addr:full":"Chauss\u00c9e De Willemeau 121 Tournai Hainaut 7500",
    "addr:housenumber":"121",
    "addr:postcode":"7500",
    "addr:street":"Chausse\u0301E De Willemeau",
    "iso:country":"BE",
    "sg:address":"Chauss\u00c9e De Willemeau 121",
    "sg:city":"Tournai",
    "sg:orig_category":"Bloemen and planten",
    "sg:phone":"+32 69 22 25 67",
    "sg:postcode":"7500",
    "sg:province":"Hainaut",
    "wof:name":"La Rose Effeuill\u00c9e",
    "wof:placetype":"venue"
},
  "geometry": {"coordinates":[3.3790159225,50.5962562561],"type":"Point"}
}