{
  "type": "Feature",
  "properties": {
    "addr:full":"Place De La Louve 6 La Louvi\u00e8re Hainaut 7100",
    "addr:housenumber":"6",
    "addr:postcode":"7100",
    "addr:street":"Place De La Louve",
    "iso:country":"BE",
    "sg:address":"Place De La Louve 6",
    "sg:city":"La Louvi\u00e8re",
    "sg:classifiers":[
        {
            "category":"Cafe",
            "type":"Food & Drink"
        }
    ],
    "sg:phone":"+32 64 21 11 48",
    "sg:postcode":"7100",
    "sg:province":"Hainaut",
    "sg:tags":[
        "snack-bars"
    ],
    "wof:name":"Crousti (le)",
    "wof:placetype":"venue"
},
  "geometry": {"coordinates":[4.1861357689,50.477481842],"type":"Point"}
}