{
  "type": "Feature",
  "properties": {
    "addr:full":"Hof Van Stade 11 Aarschot Vlaams-Brabant 3200",
    "addr:housenumber":"11",
    "addr:postcode":"3200",
    "addr:street":"Hof Van Stade",
    "iso:country":"BE",
    "sg:address":"Hof Van Stade 11",
    "sg:city":"Aarschot",
    "sg:classifiers":[
        {
            "category":"Professional",
            "subcategory":"Computer Services",
            "type":"Services"
        }
    ],
    "sg:phone":"+32 16 57 08 96",
    "sg:postcode":"3200",
    "sg:province":"Vlaams-Brabant",
    "sg:tags":[
        "-",
        "processing",
        "data",
        "software"
    ],
    "wof:name":"Logic Power M V Bvba",
    "wof:placetype":"venue"
},
  "geometry": {"coordinates":[4.8452911377,50.9892082214],"type":"Point"}
}