{
  "type": "Feature",
  "properties": {
    "addr:full":"Rue Jakob Smits 79 Anderlecht Bruxelles-Capitale 1070",
    "addr:housenumber":"79",
    "addr:postcode":"1070",
    "addr:street":"Rue Jakob Smits",
    "iso:country":"BE",
    "sg:address":"Rue Jakob Smits 79",
    "sg:city":"Anderlecht",
    "sg:orig_category":"Mat\u00e9riel m\u00e9dical and orthop\u00e9dique and proth\u00e8ses Fab",
    "sg:phone":"+32 2 523 35 24",
    "sg:postcode":"1070",
    "sg:province":"Bruxelles-Capitale",
    "wof:name":"Debruyne",
    "wof:placetype":"venue"
},
  "geometry": {"coordinates":[4.306948185,50.8424072266],"type":"Point"}
}