{
  "type": "Feature",
  "properties": {
    "iso:country":"BE",
    "sg:address":"Reuvoortweg 28",
    "sg:city":"Zonhoven",
    "sg:orig_category":"Dameskledingzaken",
    "sg:phone":"+32 11 82 30 50",
    "sg:postcode":"3520",
    "sg:province":"Limburg",
    "wof:name":"2-fashion",
    "wof:placetype":"venue"
},
  "geometry": {"coordinates":[5.377202034,50.9799346924],"type":"Point"}
}