{
  "type": "Feature",
  "properties": {
    "iso:country":"BE",
    "sg:address":"Groendalstraat 11",
    "sg:city":"Antwerpen",
    "sg:classifiers":[
        {
            "category":"Shopping",
            "subcategory":"Clothing, Apparel, & Fashions",
            "type":"Retail Goods"
        }
    ],
    "sg:phone":"+32 3 232 64 15",
    "sg:postcode":"2000",
    "sg:province":"Antwerpen",
    "sg:tags":[
        "ondergoed",
        "lingerie"
    ],
    "wof:name":"Every Wear",
    "wof:placetype":"venue"
},
  "geometry": {"coordinates":[4.4047908783,51.2176742554],"type":"Point"}
}