{
  "type": "Feature",
  "properties": {
    "iso:country":"BE",
    "sg:address":"Boektestraat 30a",
    "sg:city":"Steenokkerzeel",
    "sg:orig_category":"Elektrische installaties voor woningen",
    "sg:phone":"+32 15 62 74 00",
    "sg:postcode":"1820",
    "sg:province":"Vlaams-Brabant",
    "wof:name":"Breban",
    "wof:placetype":"venue"
},
  "geometry": {"coordinates":[4.5128650665,50.9095802307],"type":"Point"}
}