{
  "type": "Feature",
  "properties": {
    "iso:country":"BE",
    "sg:address":"Batterijstraat 10",
    "sg:city":"Bilzen (munsterbilzen)",
    "sg:classifiers":[
        {
            "category":"Banks & Credit Unions",
            "subcategory":"Investment Brokerage",
            "type":"Services"
        }
    ],
    "sg:phone":"+32 475 91 91 39",
    "sg:postcode":"3740",
    "sg:province":"Limburg",
    "sg:tags":[
        "-",
        "sale",
        "yachts",
        "accessory",
        "pleasure",
        "boat"
    ],
    "wof:name":"Wijnen Dekzeilen & Interieur",
    "wof:placetype":"venue"
},
  "geometry": {"coordinates":[5.5286521912,50.899307251],"type":"Point"}
}