{
  "type": "Feature",
  "properties": {
    "iso:country":"BE",
    "sg:address":"Maastrichtersteenweg 226",
    "sg:city":"Tongeren",
    "sg:orig_category":"Industri\u00eble and commerci\u00eble bouw Woningbouw",
    "sg:phone":"+32 12 23 92 23",
    "sg:postcode":"3700",
    "sg:province":"Limburg",
    "wof:name":"Philippe Constructies",
    "wof:placetype":"venue"
},
  "geometry": {"coordinates":[5.4848799706,50.7846603394],"type":"Point"}
}