{
  "type": "Feature",
  "properties": {
    "addr:full":"Leopold I Straat 480 Jette Bruxelles-Capitale 1090",
    "addr:housenumber":"480",
    "addr:postcode":"1090",
    "addr:street":"Leopold I Straat",
    "iso:country":"BE",
    "sg:address":"Leopold I Straat 480",
    "sg:city":"Jette",
    "sg:orig_category":"Banken and kredietinstellingen",
    "sg:phone":"+32 2 428 80 33",
    "sg:postcode":"1090",
    "sg:province":"Bruxelles-Capitale",
    "wof:name":"Fortis",
    "wof:placetype":"venue"
},
  "geometry": {"coordinates":[4.3260579109,50.8727264404],"type":"Point"}
}