{
  "type": "Feature",
  "properties": {
    "iso:country":"BE",
    "sg:address":"Rue Camille Duray 32",
    "sg:city":"Ecaussinnes",
    "sg:orig_category":"Brood, gebak and snoepgoed",
    "sg:phone":"+32 67 44 21 34",
    "sg:postcode":"7190",
    "sg:province":"Hainaut",
    "wof:name":"Eddy Cullus",
    "wof:placetype":"venue"
},
  "geometry": {"coordinates":[4.161149025,50.5610961914],"type":"Point"}
}