{
  "type": "Feature",
  "properties": {
    "addr:full":"Stationsstraat 27 Alken Limburg 3570",
    "addr:housenumber":"27",
    "addr:postcode":"3570",
    "addr:street":"Stationsstraat",
    "iso:country":"BE",
    "sg:address":"Stationsstraat 27",
    "sg:city":"Alken",
    "sg:classifiers":[
        {
            "category":"Manufacturing",
            "subcategory":"Chemicals & Compounds",
            "type":"Manufacturing & Wholesale Goods"
        }
    ],
    "sg:phone":"+32 11 31 26 16",
    "sg:postcode":"3570",
    "sg:province":"Limburg",
    "sg:tags":[
        "pharmaceutical",
        "product"
    ],
    "wof:name":"Infarmed Bvba",
    "wof:placetype":"venue"
},
  "geometry": {"coordinates":[5.303399086,50.8804893494],"type":"Point"}
}