{
  "type": "Feature",
  "properties": {
    "iso:country":"BE",
    "sg:address":"Sportlaan 12",
    "sg:city":"Moerbeke",
    "sg:orig_category":"Schoonheidssalons",
    "sg:phone":"+32 9 346 95 97",
    "sg:postcode":"9180",
    "sg:province":"Oost-Vlaanderen",
    "wof:name":"Christiane De Cleene",
    "wof:placetype":"venue"
},
  "geometry": {"coordinates":[3.9462149143,51.1729774475],"type":"Point"}
}