{
  "type": "Feature",
  "properties": {
    "addr:full":"1770 Liedekerke Vlaams-Brabant 1770",
    "addr:housenumber":"1770;1770",
    "addr:street":"Liedekerke Vlaams-Brabant",
    "iso:country":"BE",
    "sg:address":"1770",
    "sg:city":"Liedekerke",
    "sg:orig_category":"Pharmaciens",
    "sg:phone":"+32 900 10 500",
    "sg:postcode":"1770",
    "sg:province":"Vlaams-Brabant",
    "wof:name":"Pharmacies De Garde",
    "wof:placetype":"venue"
},
  "geometry": {"coordinates":[4.0815901756,50.8708457947],"type":"Point"}
}