{
  "type": "Feature",
  "properties": {
    "iso:country":"BE",
    "sg:address":"Noordstraat 45",
    "sg:city":"Roeselare",
    "sg:orig_category":"M\u00e9decins and sp\u00e9cialistes",
    "sg:phone":"+32 51 22 65 53",
    "sg:postcode":"8800",
    "sg:province":"West-Vlaanderen",
    "wof:name":"J. Peene",
    "wof:placetype":"venue"
},
  "geometry": {"coordinates":[3.1227309704,50.9461517334],"type":"Point"}
}