{
  "type": "Feature",
  "properties": {
    "addr:full":"Beukenlaan 57 Kaprijke Oost-Vlaanderen 9971",
    "addr:housenumber":"57",
    "addr:postcode":"9971",
    "addr:street":"Beukenlaan",
    "iso:country":"BE",
    "sg:address":"Beukenlaan 57",
    "sg:city":"Kaprijke",
    "sg:orig_category":"Plomberie, chauffage and installations sanitaires",
    "sg:phone":"+32 9 378 66 49",
    "sg:postcode":"9971",
    "sg:province":"Oost-Vlaanderen",
    "wof:name":"Pedro Desmet",
    "wof:placetype":"venue"
},
  "geometry": {"coordinates":[3.626210928,51.1824836731],"type":"Point"}
}