{
  "type": "Feature",
  "properties": {
    "addr:full":"Chauss\u00c9e De Bruxelles 14 Genappe Brabant Wallon 1474",
    "addr:housenumber":"14",
    "addr:postcode":"1474",
    "addr:street":"Chausse\u0301E De Bruxelles;Wallon",
    "iso:country":"BE",
    "sg:address":"Chauss\u00c9e De Bruxelles 14",
    "sg:city":"Genappe",
    "sg:orig_category":"Entretien and r\u00e9parations de voitures",
    "sg:phone":"+32 67 77 16 22",
    "sg:postcode":"1474",
    "sg:province":"Brabant Wallon",
    "wof:name":"Van De Velde & Cie",
    "wof:placetype":"venue"
},
  "geometry": {"coordinates":[4.4511580467,50.6129264832],"type":"Point"}
}