{
  "type": "Feature",
  "properties": {
    "iso:country":"BE",
    "sg:address":"Oude Markt 32",
    "sg:city":"Overpelt",
    "sg:orig_category":"Banques and organismes de cr\u00e9dit",
    "sg:phone":"+32 11 44 08 60",
    "sg:postcode":"3900",
    "sg:province":"Limburg",
    "wof:name":"Bbl",
    "wof:placetype":"venue"
},
  "geometry": {"coordinates":[5.4233980179,51.2120285034],"type":"Point"}
}