{
  "type": "Feature",
  "properties": {
    "iso:country":"BE",
    "sg:address":"Geluwestraat 41",
    "sg:city":"Moorslede (dadizele)",
    "sg:classifiers":[
        {
            "category":"Health Services",
            "subcategory":"Health Practitioner",
            "type":"Services"
        }
    ],
    "sg:phone":"+32 56 50 26 10",
    "sg:postcode":"8890",
    "sg:province":"West-Vlaanderen",
    "sg:tags":[
        "physiotherapist"
    ],
    "wof:name":"Milleville Marc",
    "wof:placetype":"venue"
},
  "geometry": {"coordinates":[3.0910680294,50.8467674255],"type":"Point"}
}