{
  "type": "Feature",
  "properties": {
    "addr:full":"Weweler 54 Burg-reuland Li\u00e8ge 4790",
    "addr:housenumber":"54",
    "addr:postcode":"4790",
    "addr:street":"Weweler",
    "iso:country":"BE",
    "sg:address":"Weweler 54",
    "sg:city":"Burg-reuland",
    "sg:classifiers":[
        {
            "category":"Bars & Pubs",
            "type":"Food & Drink"
        }
    ],
    "sg:phone":"+32 80 32 90 75",
    "sg:postcode":"4790",
    "sg:province":"Li\u00e8ge",
    "wof:name":"Weweler M\u00fchle",
    "wof:placetype":"venue"
},
  "geometry": {"coordinates":[6.1315770149,50.1943702698],"type":"Point"}
}