{
  "type": "Feature",
  "properties": {
    "addr:full":"Botestraat 1bc Gent Oost-Vlaanderen 9032",
    "addr:housenumber":"1bc",
    "addr:postcode":"9032",
    "addr:street":"Botestraat;Oost-Vlaanderen",
    "iso:country":"BE",
    "sg:address":"Botestraat 1bc",
    "sg:city":"Gent",
    "sg:orig_category":"Salons de coiffure. Instituts de beaut\u00e9",
    "sg:phone":"+32 9 258 16 55",
    "sg:postcode":"9032",
    "sg:province":"Oost-Vlaanderen",
    "wof:name":"Haarateljee Mike",
    "wof:placetype":"venue"
},
  "geometry": {"coordinates":[3.7253611088,51.0545158386],"type":"Point"}
}