{
  "type": "Feature",
  "properties": {
    "addr:full":"Kantstraat 2a Harelbeke (hulste) West-Vlaanderen 8531",
    "addr:housenumber":"2a",
    "addr:postcode":"8531",
    "addr:street":"Kantstraat",
    "iso:country":"BE",
    "sg:address":"Kantstraat 2a",
    "sg:city":"Harelbeke (hulste)",
    "sg:orig_category":"Non-Classified Establishments",
    "sg:phone":"+32 56 71 44 68",
    "sg:postcode":"8531",
    "sg:province":"West-Vlaanderen",
    "wof:name":"De Poort",
    "wof:placetype":"venue"
},
  "geometry": {"coordinates":[3.2900989056,50.8820457458],"type":"Point"}
}