{
  "type": "Feature",
  "properties": {
    "iso:country":"BE",
    "sg:address":"Roosbroeklaan 10",
    "sg:city":"Wetteren",
    "sg:orig_category":"Sportclubs",
    "sg:phone":"+32 9 366 19 77",
    "sg:postcode":"9230",
    "sg:province":"Oost-Vlaanderen",
    "wof:name":"Real Dames Volley",
    "wof:placetype":"venue"
},
  "geometry": {"coordinates":[3.8795819283,50.9918670654],"type":"Point"}
}