{
  "type": "Feature",
  "properties": {
    "addr:full":"Place A Leemans 2b4 Elsene/ixelles Bruxelles-Capitale 1050",
    "addr:housenumber":"2b4",
    "addr:postcode":"1050",
    "addr:street":"Place A Leemans",
    "iso:country":"BE",
    "sg:address":"Place A Leemans 2b4",
    "sg:city":"Elsene/ixelles",
    "sg:orig_category":"Informaticaconsulenten",
    "sg:phone":"+32 2 537 28 12",
    "sg:postcode":"1050",
    "sg:province":"Bruxelles-Capitale",
    "wof:name":"Meurrens M",
    "wof:placetype":"venue"
},
  "geometry": {"coordinates":[4.3626871109,50.8219871521],"type":"Point"}
}