{
  "type": "Feature",
  "properties": {
    "iso:country":"BE",
    "sg:address":"Nagelstraat 23",
    "sg:city":"Tielt",
    "sg:orig_category":"Installation \u00e9lectrique r\u00e9sidentielle",
    "sg:phone":"+32 51 68 92 35",
    "sg:postcode":"8700",
    "sg:province":"West-Vlaanderen",
    "wof:name":"Norbert Verhooghe",
    "wof:placetype":"venue"
},
  "geometry": {"coordinates":[3.3929009438,51.0201721191],"type":"Point"}
}