{
  "type": "Feature",
  "properties": {
    "addr:full":"Ramstraat 18 Lokeren (eksaarde) Oost-Vlaanderen 9160",
    "addr:housenumber":"18",
    "addr:postcode":"9160",
    "addr:street":"Ramstraat;Lokeren Eksaarde Oost-Vlaanderen",
    "iso:country":"BE",
    "sg:address":"Ramstraat 18",
    "sg:city":"Lokeren (eksaarde)",
    "sg:classifiers":[
        {
            "category":"Parking",
            "subcategory":"Lot",
            "type":"Transportation"
        }
    ],
    "sg:phone":"+32 9 346 72 35",
    "sg:postcode":"9160",
    "sg:province":"Oost-Vlaanderen",
    "sg:tags":[
        "parking-places",
        "laying-out"
    ],
    "wof:name":"Wulteputte B",
    "wof:placetype":"venue"
},
  "geometry": {"coordinates":[3.9906990528,51.1594581604],"type":"Point"}
}