{
  "type": "Feature",
  "properties": {
    "addr:full":"Quellinstraat 48 Antwerpen Antwerpen 2018",
    "addr:housenumber":"48",
    "addr:postcode":"2018",
    "addr:street":"Quellinstraat",
    "iso:country":"BE",
    "sg:address":"Quellinstraat 48",
    "sg:city":"Antwerpen",
    "sg:classifiers":[
        {
            "category":"Shopping",
            "subcategory":"Baby Store",
            "type":"Retail Goods"
        }
    ],
    "sg:phone":"+32 3 226 35 62",
    "sg:postcode":"2018",
    "sg:province":"Antwerpen",
    "sg:tags":[
        "article",
        "b\u00e9b\u00e9s",
        "pour"
    ],
    "wof:name":"Huis Baby & Co",
    "wof:placetype":"venue"
},
  "geometry": {"coordinates":[4.4156928062,51.2155761719],"type":"Point"}
}