{
  "type": "Feature",
  "properties": {
    "addr:full":"Rue Auguste Frison 45 Charleroi Hainaut 6040",
    "addr:housenumber":"45",
    "addr:postcode":"6040",
    "addr:street":"Rue Auguste Frison;Hainaut",
    "iso:country":"BE",
    "sg:address":"Rue Auguste Frison 45",
    "sg:city":"Charleroi",
    "sg:orig_category":"Installation de menuiserie m\u00e9tallique. Installation de menuiserie en bois and plastique",
    "sg:phone":"+32 71 34 46 37",
    "sg:postcode":"6040",
    "sg:province":"Hainaut",
    "wof:name":"Dassy",
    "wof:placetype":"venue"
},
  "geometry": {"coordinates":[4.4314160347,50.4498558044],"type":"Point"}
}