{
  "type": "Feature",
  "properties": {
    "addr:full":"Sint-damiaanstraat 226 Wommelgem Antwerpen 2160",
    "addr:housenumber":"226",
    "addr:postcode":"2160",
    "addr:street":"Sint-Damiaanstraat",
    "iso:country":"BE",
    "sg:address":"Sint-damiaanstraat 226",
    "sg:city":"Wommelgem",
    "sg:classifiers":[
        {
            "category":"Building & Trades",
            "subcategory":"Cleaning & Sanitation",
            "type":"Services"
        }
    ],
    "sg:phone":"+32 3 322 07 47",
    "sg:postcode":"2160",
    "sg:province":"Antwerpen",
    "sg:tags":[
        "cleaner",
        "window"
    ],
    "wof:name":"Blitz Bvba",
    "wof:placetype":"venue"
},
  "geometry": {"coordinates":[4.5156822205,51.197593689],"type":"Point"}
}