{
  "type": "Feature",
  "properties": {
    "iso:country":"BE",
    "sg:address":"Rue Porte Neuve 13",
    "sg:city":"Arlon",
    "sg:orig_category":"Graphologues, astrologues, voyants and radiesth\u00e9sistes. M\u00e9decins and sp\u00e9cialistes",
    "sg:phone":"+32 63 22 40 05",
    "sg:postcode":"6700",
    "sg:province":"Luxembourg",
    "wof:name":"R. Claisse",
    "wof:placetype":"venue"
},
  "geometry": {"coordinates":[5.8147091866,49.6849365234],"type":"Point"}
}