{
  "type": "Feature",
  "properties": {
    "addr:full":"Chauss\u00e9e Paul Houtart 104 La Louvi\u00e8re (houdeng-goegnies) Hainaut 7110",
    "addr:housenumber":"104",
    "addr:postcode":"7110",
    "addr:street":"Chausse\u0301E Paul Houtart",
    "iso:country":"BE",
    "sg:address":"Chauss\u00e9e Paul Houtart 104",
    "sg:city":"La Louvi\u00e8re (houdeng-goegnies)",
    "sg:orig_category":"Non-Classified Establishments",
    "sg:phone":"+32 64 21 69 51",
    "sg:postcode":"7110",
    "sg:province":"Hainaut",
    "wof:name":"Masquelier Aciers",
    "wof:placetype":"venue"
},
  "geometry": {"coordinates":[4.1647968292,50.4833145142],"type":"Point"}
}