{
  "type": "Feature",
  "properties": {
    "addr:full":"Rue Samson 1 Mons Hainaut 7000",
    "addr:housenumber":"1",
    "addr:postcode":"7000",
    "addr:street":"Rue Samson;Hainaut",
    "iso:country":"BE",
    "sg:address":"Rue Samson 1",
    "sg:city":"Mons",
    "sg:classifiers":[
        {
            "category":"Food & Beverages",
            "subcategory":"Fruits & Vegetables",
            "type":"Retail Goods"
        }
    ],
    "sg:phone":"+32 65 84 16 90",
    "sg:postcode":"7000",
    "sg:province":"Hainaut",
    "sg:tags":[
        "groenten"
    ],
    "wof:name":"Aux Halles",
    "wof:placetype":"venue"
},
  "geometry": {"coordinates":[3.9498620033,50.4523658752],"type":"Point"}
}