{
  "type": "Feature",
  "properties": {
    "addr:full":"Keyartstraat 27ba Bree Limburg 3960",
    "addr:housenumber":"27ba",
    "addr:postcode":"3960",
    "addr:street":"Keyartstraat",
    "iso:country":"BE",
    "sg:address":"Keyartstraat 27ba",
    "sg:city":"Bree",
    "sg:orig_category":"Pain, p\u00e2tisseries and confiseries",
    "sg:phone":"+32 89 86 79 62",
    "sg:postcode":"3960",
    "sg:province":"Limburg",
    "wof:name":"Bakkerij Petra",
    "wof:placetype":"venue"
},
  "geometry": {"coordinates":[5.6583819389,51.1261978149],"type":"Point"}
}