{
  "type": "Feature",
  "properties": {
    "addr:full":"Grotehof Mortsel Antwerpen 2640",
    "addr:postcode":"2640",
    "addr:street":"Grotehof",
    "iso:country":"BE",
    "sg:address":"Grotehof",
    "sg:city":"Mortsel",
    "sg:orig_category":"Transports ferroviaires",
    "sg:phone":"+32 3 204 24 93",
    "sg:postcode":"2640",
    "sg:province":"Antwerpen",
    "wof:name":"Station Mortsel Oude God",
    "wof:placetype":"venue"
},
  "geometry": {"coordinates":[4.4538331032,51.1728096008],"type":"Point"}
}