{
  "type": "Feature",
  "properties": {
    "addr:full":"Markt 26 Torhout West-Vlaanderen 8820",
    "addr:housenumber":"26",
    "addr:postcode":"8820",
    "addr:street":"Markt",
    "iso:country":"BE",
    "sg:address":"Markt 26",
    "sg:city":"Torhout",
    "sg:classifiers":[
        {
            "category":"Shopping",
            "subcategory":"Clothing, Apparel, & Fashions",
            "type":"Retail Goods"
        }
    ],
    "sg:phone":"+32 50 21 73 93",
    "sg:postcode":"8820",
    "sg:province":"West-Vlaanderen",
    "sg:tags":[
        "v\u00eatements",
        "pour",
        "dame"
    ],
    "wof:name":"Huis Punta",
    "wof:placetype":"venue"
},
  "geometry": {"coordinates":[3.1018919945,51.0640830994],"type":"Point"}
}