{
  "type": "Feature",
  "properties": {
    "addr:full":"Toekomstlaan 1 Antwerpen (merksem) Antwerpen 2170",
    "addr:housenumber":"1",
    "addr:postcode":"2170",
    "addr:street":"Toekomstlaan",
    "iso:country":"BE",
    "sg:address":"Toekomstlaan 1",
    "sg:city":"Antwerpen (merksem)",
    "sg:classifiers":[
        {
            "category":"Sports & Exercise",
            "subcategory":"Gym",
            "type":"Entertainment"
        }
    ],
    "sg:phone":"+32 3 645 27 21",
    "sg:postcode":"2170",
    "sg:province":"Antwerpen",
    "sg:tags":[
        "fitness"
    ],
    "wof:name":"American Fit & Health Wellness Center",
    "wof:placetype":"venue"
},
  "geometry": {"coordinates":[4.4505147934,51.246723175],"type":"Point"}
}