{
  "type": "Feature",
  "properties": {
    "iso:country":"BE",
    "sg:address":"Rozenstraat 13",
    "sg:city":"Nazareth",
    "sg:orig_category":"Installation \u00e9lectrique r\u00e9sidentielle",
    "sg:phone":"+32 9 385 58 42",
    "sg:postcode":"9810",
    "sg:province":"Oost-Vlaanderen",
    "wof:name":"Christiaan Crucke",
    "wof:placetype":"venue"
},
  "geometry": {"coordinates":[3.6543319225,50.9765014648],"type":"Point"}
}