{
  "type": "Feature",
  "properties": {
    "iso:country":"BE",
    "sg:address":"Koestraat 29",
    "sg:city":"Wervik",
    "sg:classifiers":[
        {
            "category":"Building & Trades",
            "subcategory":"Pest Control",
            "type":"Services"
        }
    ],
    "sg:phone":"+32 56 25 48 54",
    "sg:postcode":"8940",
    "sg:province":"West-Vlaanderen",
    "sg:tags":[
        "machine",
        "vending"
    ],
    "wof:name":"Casier J-cl",
    "wof:placetype":"venue"
},
  "geometry": {"coordinates":[3.0375769138,50.7763977051],"type":"Point"}
}