{
  "type": "Feature",
  "properties": {
    "addr:full":"Rue Octave Battaille 61 Beloeil Hainaut 7971",
    "addr:housenumber":"61",
    "addr:postcode":"7971",
    "addr:street":"Rue Octave Battaille",
    "iso:country":"BE",
    "sg:address":"Rue Octave Battaille 61",
    "sg:city":"Beloeil",
    "sg:orig_category":"Quincailleries",
    "sg:phone":"+32 69 57 93 14",
    "sg:postcode":"7971",
    "sg:province":"Hainaut",
    "wof:name":"Distri-paint",
    "wof:placetype":"venue"
},
  "geometry": {"coordinates":[3.6428871155,50.5280075073],"type":"Point"}
}