{
  "type": "Feature",
  "properties": {
    "addr:full":"Nieuwpoortsesteenweg 26 Oostende West-Vlaanderen 8400",
    "addr:housenumber":"26",
    "addr:postcode":"8400",
    "addr:street":"Nieuwpoortsesteenweg",
    "iso:country":"BE",
    "sg:address":"Nieuwpoortsesteenweg 26",
    "sg:city":"Oostende",
    "sg:orig_category":"Journaux. Tabac",
    "sg:phone":"+32 59 80 26 62",
    "sg:postcode":"8400",
    "sg:province":"West-Vlaanderen",
    "wof:name":"Leeshoekje",
    "wof:placetype":"venue"
},
  "geometry": {"coordinates":[2.9076709747,51.2241477966],"type":"Point"}
}