{
  "type": "Feature",
  "properties": {
    "addr:full":"Lettenburgstraat 16 Zuienkerke West-Vlaanderen 8377",
    "addr:housenumber":"16",
    "addr:postcode":"8377",
    "addr:street":"Lettenburgstraat",
    "iso:country":"BE",
    "sg:address":"Lettenburgstraat 16",
    "sg:city":"Zuienkerke",
    "sg:orig_category":"Schoenen",
    "sg:phone":"+32 50 67 68 35",
    "sg:postcode":"8377",
    "sg:province":"West-Vlaanderen",
    "wof:name":"Kwibus",
    "wof:placetype":"venue"
},
  "geometry": {"coordinates":[3.1851620674,51.255821228],"type":"Point"}
}