{
  "type": "Feature",
  "properties": {
    "iso:country":"BE",
    "sg:address":"D'hondtstraat 14",
    "sg:city":"Ieper",
    "sg:classifiers":[
        {
            "category":"Banks & Credit Unions",
            "subcategory":"Investment Brokerage",
            "type":"Services"
        }
    ],
    "sg:phone":"+32 57 20 13 33",
    "sg:postcode":"8900",
    "sg:province":"West-Vlaanderen",
    "sg:tags":[
        "printing",
        "-"
    ],
    "wof:name":"Deleye Sneldruk Bvba",
    "wof:placetype":"venue"
},
  "geometry": {"coordinates":[2.8869380951,50.8505592346],"type":"Point"}
}