{
  "type": "Feature",
  "properties": {
    "iso:country":"BE",
    "sg:address":"Avenue De Malmaison 27ba",
    "sg:city":"Waterloo",
    "sg:orig_category":"Architecten",
    "sg:phone":"+32 2 351 02 54",
    "sg:postcode":"1410",
    "sg:province":"Brabant Wallon",
    "wof:name":"Jean-philippe Coget",
    "wof:placetype":"venue"
},
  "geometry": {"coordinates":[4.4068870544,50.7195129395],"type":"Point"}
}