{
  "type": "Feature",
  "properties": {
    "iso:country":"BE",
    "sg:address":"1350",
    "sg:city":"Orp-jauche",
    "sg:orig_category":"Pharmaciens",
    "sg:phone":"+32 900 10 500",
    "sg:postcode":"1350",
    "sg:province":"Brabant Wallon",
    "wof:name":"Pharmacies De Garde",
    "wof:placetype":"venue"
},
  "geometry": {"coordinates":[4.9873747826,50.6945457458],"type":"Point"}
}