{
  "type": "Feature",
  "properties": {
    "addr:full":"Landwaartslaan 91 Genk Limburg 3600",
    "addr:housenumber":"91",
    "addr:postcode":"3600",
    "addr:street":"Landwaartslaan",
    "iso:country":"BE",
    "sg:address":"Landwaartslaan 91",
    "sg:city":"Genk",
    "sg:classifiers":[
        {
            "category":"Personal",
            "subcategory":"Beauty Salon",
            "type":"Services"
        }
    ],
    "sg:phone":"+32 89 36 10 02",
    "sg:postcode":"3600",
    "sg:province":"Limburg",
    "sg:tags":[
        "lady",
        "-",
        "hairdressing"
    ],
    "wof:name":"Anneliese",
    "wof:placetype":"venue"
},
  "geometry": {"coordinates":[5.4489541054,50.9678573608],"type":"Point"}
}