{
  "type": "Feature",
  "properties": {
    "iso:country":"BE",
    "sg:address":"Kapelstraat 7",
    "sg:city":"Kortessem",
    "sg:orig_category":"Traitements param\u00e9dicaux",
    "sg:phone":"+32 11 72 31 51",
    "sg:postcode":"3720",
    "sg:province":"Limburg",
    "wof:name":"Vrancken Hilde",
    "wof:placetype":"venue"
},
  "geometry": {"coordinates":[5.3841757774,50.8637733459],"type":"Point"}
}