{
  "type": "Feature",
  "properties": {
    "addr:full":"Rue De La Forge 7 Mont-saint-guibert (corbais) Brabant Wallon 1435",
    "addr:housenumber":"7",
    "addr:postcode":"1435",
    "addr:street":"Rue De La Forge;Corbais;Wallon",
    "iso:country":"BE",
    "sg:address":"Rue De La Forge 7",
    "sg:city":"Mont-saint-guibert (corbais)",
    "sg:classifiers":[
        {
            "category":"Health Services",
            "subcategory":"Health Practitioner",
            "type":"Services"
        }
    ],
    "sg:phone":"+32 10 65 05 56",
    "sg:postcode":"1435",
    "sg:province":"Brabant Wallon",
    "sg:tags":[
        "therapist",
        "speech"
    ],
    "wof:name":"De Schutter P",
    "wof:placetype":"venue"
},
  "geometry": {"coordinates":[4.6511387825,50.6460380554],"type":"Point"}
}