{
  "type": "Feature",
  "properties": {
    "addr:full":"Zandstraat 9 Zoersel Antwerpen 2980",
    "addr:housenumber":"9",
    "addr:postcode":"2980",
    "addr:street":"Zandstraat",
    "iso:country":"BE",
    "sg:address":"Zandstraat 9",
    "sg:city":"Zoersel",
    "sg:orig_category":"V\u00e9t\u00e9rinaires",
    "sg:phone":"+32 3 311 60 22",
    "sg:postcode":"2980",
    "sg:province":"Antwerpen",
    "wof:name":"Jan Verheyen",
    "wof:placetype":"venue"
},
  "geometry": {"coordinates":[4.712580204,51.2670631409],"type":"Point"}
}