{
  "type": "Feature",
  "properties": {
    "iso:country":"BE",
    "sg:address":"Driemasten 85",
    "sg:city":"Wevelgem (gullegem)",
    "sg:classifiers":[
        {
            "category":"Manufacturing",
            "subcategory":"Metals",
            "type":"Manufacturing & Wholesale Goods"
        }
    ],
    "sg:phone":"+32 56 41 99 94",
    "sg:postcode":"8560",
    "sg:province":"West-Vlaanderen",
    "sg:tags":[
        "sheet",
        "machinery",
        "working"
    ],
    "wof:name":"R & C Trading Bvba",
    "wof:placetype":"venue"
},
  "geometry": {"coordinates":[3.1897799969,50.8548736572],"type":"Point"}
}