{
  "type": "Feature",
  "properties": {
    "addr:full":"Oude Smidsestraat 18 Dilbeek Vlaams-Brabant 1700",
    "addr:housenumber":"18",
    "addr:postcode":"1700",
    "addr:street":"Oude Smidsestraat",
    "iso:country":"BE",
    "sg:address":"Oude Smidsestraat 18",
    "sg:city":"Dilbeek",
    "sg:orig_category":"V\u00e9los. Location d'articles de sport, de sport nautique and de camping",
    "sg:phone":"+32 2 569 80 02",
    "sg:postcode":"1700",
    "sg:province":"Vlaams-Brabant",
    "wof:name":"Freddy Sport",
    "wof:placetype":"venue"
},
  "geometry": {"coordinates":[4.2619690895,50.84400177],"type":"Point"}
}