{
  "type": "Feature",
  "properties": {
    "iso:country":"BE",
    "sg:address":"Avenue Du Transvaal 49",
    "sg:city":"Namur (vedrin - Daussoulx)",
    "sg:classifiers":[
        {
            "category":"Health Services",
            "subcategory":"Health Practitioner",
            "type":"Services"
        }
    ],
    "sg:phone":"+32 81 21 45 46",
    "sg:postcode":"5020",
    "sg:province":"Namur",
    "sg:tags":[
        "physiotherapist"
    ],
    "wof:name":"Brasseur B",
    "wof:placetype":"venue"
},
  "geometry": {"coordinates":[4.8632068634,50.4786186218],"type":"Point"}
}