{
  "type": "Feature",
  "properties": {
    "addr:full":"Predikherenrei 26 Brugge West-Vlaanderen 8000",
    "addr:housenumber":"26",
    "addr:postcode":"8000",
    "addr:street":"Predikherenrei",
    "iso:country":"BE",
    "sg:address":"Predikherenrei 26",
    "sg:city":"Brugge",
    "sg:orig_category":"Artsen and specialisten",
    "sg:phone":"+32 50 34 62 32",
    "sg:postcode":"8000",
    "sg:province":"West-Vlaanderen",
    "wof:name":"K. Van Welden",
    "wof:placetype":"venue"
},
  "geometry": {"coordinates":[3.2357521057,51.2068977356],"type":"Point"}
}