{
  "type": "Feature",
  "properties": {
    "addr:full":"Chemin De La Sib\u00c9rie 4 Gembloux Namur 5030",
    "addr:housenumber":"4",
    "addr:postcode":"5030",
    "addr:street":"Chemin De La Sibe\u0301Rie;Namur",
    "iso:country":"BE",
    "sg:address":"Chemin De La Sib\u00c9rie 4",
    "sg:city":"Gembloux",
    "sg:classifiers":[
        {
            "category":"Food & Beverages",
            "subcategory":"Fruits & Vegetables",
            "type":"Retail Goods"
        }
    ],
    "sg:phone":"+32 81 61 00 47",
    "sg:postcode":"5030",
    "sg:province":"Namur",
    "sg:tags":[
        "l\u00e9gumes",
        "gr"
    ],
    "wof:name":"C.i.m.",
    "wof:placetype":"venue"
},
  "geometry": {"coordinates":[4.6746959686,50.552898407],"type":"Point"}
}