{
  "type": "Feature",
  "properties": {
    "iso:country":"BE",
    "sg:address":"Chauss\u00e9e De Huy 306",
    "sg:city":"Chaumont-gistoux",
    "sg:classifiers":[
        {
            "category":"Home & Garden",
            "subcategory":"Garden Supply",
            "type":"Retail Goods"
        }
    ],
    "sg:phone":"+32 10 68 03 10",
    "sg:postcode":"1325",
    "sg:province":"Brabant Wallon",
    "wof:name":"Gonthier\u00ae",
    "wof:placetype":"venue"
},
  "geometry": {"coordinates":[4.7281661034,50.6682739258],"type":"Point"}
}