{
  "type": "Feature",
  "properties": {
    "addr:full":"Hoogstraat 2a Hamme Oost-Vlaanderen 9220",
    "addr:housenumber":"2a",
    "addr:postcode":"9220",
    "addr:street":"Hoogstraat",
    "iso:country":"BE",
    "sg:address":"Hoogstraat 2a",
    "sg:city":"Hamme",
    "sg:classifiers":[
        {
            "category":"Tea Room",
            "subcategory":"None",
            "type":"Food & Drink"
        }
    ],
    "sg:phone":"+32 52 48 07 74",
    "sg:postcode":"9220",
    "sg:province":"Oost-Vlaanderen",
    "wof:name":"Blauwe Poort (de)",
    "wof:placetype":"venue"
},
  "geometry": {"coordinates":[4.1331119537,51.0985527039],"type":"Point"}
}