{
  "type": "Feature",
  "properties": {
    "addr:full":"Rue De Nieuport 4 Mouscron Hainaut 7700",
    "addr:housenumber":"4",
    "addr:postcode":"7700",
    "addr:street":"Rue De Nieuport",
    "iso:country":"BE",
    "sg:address":"Rue De Nieuport 4",
    "sg:city":"Mouscron",
    "sg:classifiers":[
        {
            "category":"Professional",
            "subcategory":"Accounting & Tax Preparation",
            "type":"Services"
        }
    ],
    "sg:phone":"+32 56 33 02 41",
    "sg:postcode":"7700",
    "sg:province":"Hainaut",
    "sg:tags":[
        "accountant"
    ],
    "wof:name":"Devoldere M",
    "wof:placetype":"venue"
},
  "geometry": {"coordinates":[3.2052710056,50.7510566711],"type":"Point"}
}