{
  "type": "Feature",
  "properties": {
    "addr:full":"Avenue De La Couronne 376 Elsene/ixelles Bruxelles-Capitale 1050",
    "addr:housenumber":"376",
    "addr:postcode":"1050",
    "addr:street":"Avenue De La Couronne",
    "iso:country":"BE",
    "sg:address":"Avenue De La Couronne 376",
    "sg:city":"Elsene/ixelles",
    "sg:orig_category":"Industri\u00eble elektrische installaties",
    "sg:phone":"+32 2 640 34 95",
    "sg:postcode":"1050",
    "sg:province":"Bruxelles-Capitale",
    "wof:name":"New Telephone",
    "wof:placetype":"venue"
},
  "geometry": {"coordinates":[4.3875570297,50.8230895996],"type":"Point"}
}