{
  "type": "Feature",
  "properties": {
    "iso:country":"BE",
    "sg:address":"Egenhovenweg 49b1",
    "sg:city":"Leuven",
    "sg:orig_category":"Elektrische installaties voor woningen",
    "sg:phone":"+32 16 22 06 59",
    "sg:postcode":"3001",
    "sg:province":"Vlaams-Brabant",
    "wof:name":"Robert Beauson",
    "wof:placetype":"venue"
},
  "geometry": {"coordinates":[4.6746301651,50.8728485107],"type":"Point"}
}