{
  "type": "Feature",
  "properties": {
    "addr:full":"Brasschaatbaan 3 Brecht Antwerpen 2960",
    "addr:housenumber":"3",
    "addr:postcode":"2960",
    "addr:street":"Brasschaatbaan",
    "iso:country":"BE",
    "sg:address":"Brasschaatbaan 3",
    "sg:city":"Brecht",
    "sg:classifiers":[
        {
            "category":"Structure",
            "subcategory":"Office Building",
            "type":"Public Place"
        }
    ],
    "sg:phone":"+32 3 663 07 69",
    "sg:postcode":"2960",
    "sg:province":"Antwerpen",
    "sg:tags":[
        "roofing",
        "slate"
    ],
    "wof:name":"Havermans Nv",
    "wof:placetype":"venue"
},
  "geometry": {"coordinates":[4.5863780975,51.3418121338],"type":"Point"}
}