{
  "type": "Feature",
  "properties": {
    "iso:country":"BE",
    "sg:address":"Woeringenstraat 12ba",
    "sg:city":"Nijlen",
    "sg:orig_category":"Begrafeniswezen",
    "sg:phone":"+32 3 411 01 38",
    "sg:postcode":"2560",
    "sg:province":"Antwerpen",
    "wof:name":"Rouwcentrum De Winter",
    "wof:placetype":"venue"
},
  "geometry": {"coordinates":[4.6738610268,51.1612014771],"type":"Point"}
}