{
  "type": "Feature",
  "properties": {
    "addr:full":"Haagdoornlaan 10 Kapellen Antwerpen 2950",
    "addr:housenumber":"10",
    "addr:postcode":"2950",
    "addr:street":"Haagdoornlaan",
    "iso:country":"BE",
    "sg:address":"Haagdoornlaan 10",
    "sg:city":"Kapellen",
    "sg:classifiers":[
        {
            "category":"Government",
            "subcategory":"Embassy",
            "type":"Public Place"
        }
    ],
    "sg:phone":"+32 3 665 46 77",
    "sg:postcode":"2950",
    "sg:province":"Antwerpen",
    "sg:tags":[
        "consulate"
    ],
    "wof:name":"Embassy Express",
    "wof:placetype":"venue"
},
  "geometry": {"coordinates":[4.4313359261,51.3219871521],"type":"Point"}
}