{
  "type": "Feature",
  "properties": {
    "iso:country":"BE",
    "sg:address":"Kolonel Bourgstr 123-125",
    "sg:city":"Brussel",
    "sg:classifiers":[
        {
            "category":"Food Court",
            "type":"Food & Drink"
        }
    ],
    "sg:phone":"+32 2 726 20 51",
    "sg:postcode":"1140",
    "sg:province":"Bruxelles-Capitale",
    "sg:tags":[
        "product",
        "related"
    ],
    "wof:name":"Mccain Eurocenter Nv",
    "wof:placetype":"venue"
},
  "geometry": {"coordinates":[4.4160280228,50.8549194336],"type":"Point"}
}