{
  "type": "Feature",
  "properties": {
    "iso:country":"BE",
    "sg:address":"Limbourg Stirumlaan 5",
    "sg:city":"Wemmel",
    "sg:orig_category":"Diensten voor huisdieren Huisdieren and benodigdheden Royal Canin",
    "sg:phone":"+32 2 460 10 17",
    "sg:postcode":"1780",
    "sg:province":"Vlaams-Brabant",
    "wof:name":"Schaerlaekens Van De Velde",
    "wof:placetype":"venue"
},
  "geometry": {"coordinates":[4.3121099472,50.9041213989],"type":"Point"}
}