{
  "type": "Feature",
  "properties": {
    "addr:full":"Grand Rue 11 Habay Luxembourg 6724",
    "addr:housenumber":"11",
    "addr:postcode":"6724",
    "addr:street":"Grand Rue",
    "iso:country":"BE",
    "sg:address":"Grand Rue 11",
    "sg:city":"Habay",
    "sg:orig_category":"Traitement and fa\u00e7onnage de la pierre. Services fun\u00e9raires",
    "sg:phone":"+32 63 41 16 82",
    "sg:postcode":"6724",
    "sg:province":"Luxembourg",
    "wof:name":"Remacle Gilbert",
    "wof:placetype":"venue"
},
  "geometry": {"coordinates":[5.5328731537,49.7191009521],"type":"Point"}
}