{
  "type": "Feature",
  "properties": {
    "iso:country":"BE",
    "sg:address":"Avenue De La Croix-rouge 4",
    "sg:city":"Huy",
    "sg:orig_category":"Sportcentra Sportterreinen and installaties behalve sportcentra",
    "sg:phone":"+32 85 25 50 23",
    "sg:postcode":"4500",
    "sg:province":"Li\u00e8ge",
    "wof:name":"Hall Omnisport",
    "wof:placetype":"venue"
},
  "geometry": {"coordinates":[5.2497549057,50.5289382935],"type":"Point"}
}