{
  "type": "Feature",
  "properties": {
    "addr:full":"Meistraat 121 Dessel Antwerpen 2480",
    "addr:housenumber":"121",
    "addr:postcode":"2480",
    "addr:street":"Meistraat",
    "iso:country":"BE",
    "sg:address":"Meistraat 121",
    "sg:city":"Dessel",
    "sg:classifiers":[
        {
            "category":"Cafe",
            "type":"Food & Drink"
        }
    ],
    "sg:phone":"+32 14 37 17 78",
    "sg:postcode":"2480",
    "sg:province":"Antwerpen",
    "sg:tags":[
        "snack-bars"
    ],
    "wof:name":"Snacky",
    "wof:placetype":"venue"
},
  "geometry": {"coordinates":[5.1433238983,51.2404136658],"type":"Point"}
}