{
  "type": "Feature",
  "properties": {
    "addr:full":"Boulevardstraat 7 Herne Vlaams-Brabant 1541",
    "addr:housenumber":"7",
    "addr:postcode":"1541",
    "addr:street":"Boulevardstraat",
    "iso:country":"BE",
    "sg:address":"Boulevardstraat 7",
    "sg:city":"Herne",
    "sg:orig_category":"Epiceries",
    "sg:phone":"+32 54 58 81 75",
    "sg:postcode":"1541",
    "sg:province":"Vlaams-Brabant",
    "wof:name":"Rene Deblander",
    "wof:placetype":"venue"
},
  "geometry": {"coordinates":[3.9757480621,50.7218894958],"type":"Point"}
}