{
  "type": "Feature",
  "properties": {
    "addr:full":"Rue Vallaville 83 Lens Hainaut 7870",
    "addr:housenumber":"83",
    "addr:postcode":"7870",
    "addr:street":"Rue Vallaville",
    "iso:country":"BE",
    "sg:address":"Rue Vallaville 83",
    "sg:city":"Lens",
    "sg:orig_category":"Notaires",
    "sg:phone":"+32 65 22 55 71",
    "sg:postcode":"7870",
    "sg:province":"Hainaut",
    "wof:name":"Leriche J-p",
    "wof:placetype":"venue"
},
  "geometry": {"coordinates":[3.8980269432,50.5575447083],"type":"Point"}
}