{
  "type": "Feature",
  "properties": {
    "addr:full":"Place De Wagnel\u00e9e 10 Fleurus (wagnel\u00e9e) Hainaut 6223",
    "addr:housenumber":"10",
    "addr:postcode":"6223",
    "addr:street":"Place De Wagnele\u0301E",
    "iso:country":"BE",
    "sg:address":"Place De Wagnel\u00e9e 10",
    "sg:city":"Fleurus (wagnel\u00e9e)",
    "sg:classifiers":[
        {
            "category":"Bars & Pubs",
            "type":"Food & Drink"
        }
    ],
    "sg:phone":"+32 71 85 01 94",
    "sg:postcode":"6223",
    "sg:province":"Hainaut",
    "sg:tags":[
        "tavern"
    ],
    "wof:name":"Chassart (le)",
    "wof:placetype":"venue"
},
  "geometry": {"coordinates":[4.5329079628,50.5228805542],"type":"Point"}
}