{
  "type": "Feature",
  "properties": {
    "addr:full":"Heydehoekstraat 6 Veurne West-Vlaanderen 8630",
    "addr:housenumber":"6",
    "addr:postcode":"8630",
    "addr:street":"Heydehoekstraat",
    "iso:country":"BE",
    "sg:address":"Heydehoekstraat 6",
    "sg:city":"Veurne",
    "sg:orig_category":"Eleveurs and marchands de porcs. Eleveurs de bovins",
    "sg:phone":"+32 58 31 12 51",
    "sg:postcode":"8630",
    "sg:province":"West-Vlaanderen",
    "wof:name":"Johan Melis",
    "wof:placetype":"venue"
},
  "geometry": {"coordinates":[2.7089219093,51.0336227417],"type":"Point"}
}