{
  "type": "Feature",
  "properties": {
    "iso:country":"BE",
    "sg:address":"Vierwinden 5b",
    "sg:city":"Zaventem",
    "sg:classifiers":[
        {
            "category":"Banks & Credit Unions",
            "subcategory":"Investment Brokerage",
            "type":"Services"
        }
    ],
    "sg:phone":"+32 2 720 90 10",
    "sg:postcode":"1930",
    "sg:province":"Vlaams-Brabant",
    "sg:tags":[
        "pump",
        "industrial",
        "-"
    ],
    "wof:name":"Itt Flygt Nv-sa",
    "wof:placetype":"venue"
},
  "geometry": {"coordinates":[4.4886798859,50.8717918396],"type":"Point"}
}