{
  "type": "Feature",
  "properties": {
    "iso:country":"BE",
    "sg:address":"Groenebriel 1",
    "sg:city":"Gent",
    "sg:orig_category":"Artsen and specialisten",
    "sg:phone":"+32 9 223 42 02",
    "sg:postcode":"9000",
    "sg:province":"Oost-Vlaanderen",
    "wof:name":"Jean Van Laethem",
    "wof:placetype":"venue"
},
  "geometry": {"coordinates":[3.7212250233,51.0618591309],"type":"Point"}
}