{
  "type": "Feature",
  "properties": {
    "iso:country":"BE",
    "sg:address":"Turnhoutsebaan 168a",
    "sg:city":"Mol",
    "sg:orig_category":"Location de v\u00e9hicules sauf voitures. Entretien and r\u00e9parations de voitures. D\u00e9taillants en pi\u00e8ces an",
    "sg:phone":"+32 14 31 30 29",
    "sg:postcode":"2400",
    "sg:province":"Antwerpen",
    "wof:name":"Garage Autoquick",
    "wof:placetype":"venue"
},
  "geometry": {"coordinates":[5.1153898239,51.1961212158],"type":"Point"}
}