{
  "type": "Feature",
  "properties": {
    "addr:full":"Rue Du Vallon 17 Bruxelles (saint-josse-ten-noode) Bruxelles-Capitale 1210",
    "addr:housenumber":"17",
    "addr:postcode":"1210",
    "addr:street":"Rue Du Vallon",
    "iso:country":"BE",
    "sg:address":"Rue Du Vallon 17",
    "sg:city":"Bruxelles (saint-josse-ten-noode)",
    "sg:classifiers":[
        {
            "category":"Professional",
            "type":"Services"
        }
    ],
    "sg:phone":"+32 2 223 07 78",
    "sg:postcode":"1210",
    "sg:province":"Bruxelles-Capitale",
    "sg:tags":[
        "writer"
    ],
    "wof:name":"Prestige Biographies",
    "wof:placetype":"venue"
},
  "geometry": {"coordinates":[4.3724298477,50.848903656],"type":"Point"}
}