{
  "type": "Feature",
  "properties": {
    "addr:full":"Langemuren 103 Ninove Oost-Vlaanderen 9400",
    "addr:housenumber":"103",
    "addr:postcode":"9400",
    "iso:country":"BE",
    "sg:address":"Langemuren 103",
    "sg:city":"Ninove",
    "sg:classifiers":[
        {
            "category":"Parking",
            "subcategory":"Lot",
            "type":"Transportation"
        }
    ],
    "sg:phone":"+32 54 33 33 16",
    "sg:postcode":"9400",
    "sg:province":"Oost-Vlaanderen",
    "sg:tags":[
        "parking-places",
        "laying-out"
    ],
    "wof:name":"Sergaco Bvba",
    "wof:placetype":"venue"
},
  "geometry": {"coordinates":[4.0207982063,50.841796875],"type":"Point"}
}