{
  "type": "Feature",
  "properties": {
    "iso:country":"BE",
    "sg:address":"Route De La Clouse",
    "sg:city":"Aubel",
    "sg:classifiers":[
        {
            "category":"Wholesale",
            "subcategory":"Sporting Goods",
            "type":"Manufacturing & Wholesale Goods"
        }
    ],
    "sg:phone":"+32 87 68 79 88",
    "sg:postcode":"4880",
    "sg:province":"Li\u00e8ge",
    "sg:tags":[
        "sport-",
        "kampeermateriaal"
    ],
    "wof:name":"Schreiber M.",
    "wof:placetype":"venue"
},
  "geometry": {"coordinates":[5.8772058487,50.6999740601],"type":"Point"}
}