{
  "type": "Feature",
  "properties": {
    "iso:country":"BE",
    "sg:address":"Rue Naimette 50",
    "sg:city":"Li\u00c8ge",
    "sg:orig_category":"Artsen and specialisten",
    "sg:phone":"+32 4 226 14 42",
    "sg:postcode":"4000",
    "sg:province":"Li\u00e8ge",
    "wof:name":"V\u00c9ronique Thiry",
    "wof:placetype":"venue"
},
  "geometry": {"coordinates":[5.5629858971,50.6508102417],"type":"Point"}
}