{
  "type": "Feature",
  "properties": {
    "addr:full":"Wijngaardstraat 22 Antwerpen Antwerpen 2000",
    "addr:housenumber":"22",
    "addr:postcode":"2000",
    "addr:street":"Wijngaardstraat",
    "iso:country":"BE",
    "sg:address":"Wijngaardstraat 22",
    "sg:city":"Antwerpen",
    "sg:classifiers":[
        {
            "category":"Restaurant",
            "type":"Food & Drink"
        }
    ],
    "sg:phone":"+32 3 233 62 59",
    "sg:postcode":"2000",
    "sg:province":"Antwerpen",
    "wof:name":"Aurelia",
    "wof:placetype":"venue"
},
  "geometry": {"coordinates":[4.404779911,51.2213287354],"type":"Point"}
}