{
  "type": "Feature",
  "properties": {
    "iso:country":"BE",
    "sg:address":"Binkomstraat 50",
    "sg:city":"Tielt-winge",
    "sg:orig_category":"Dranken Verhuur cateringmateriaal and evenementuitrusting Winkelinrichting and handelsuitrusting Gh",
    "sg:phone":"+32 16 63 29 77",
    "sg:postcode":"3391",
    "sg:province":"Vlaams-Brabant",
    "wof:name":"Fa. Pasteyns",
    "wof:placetype":"venue"
},
  "geometry": {"coordinates":[4.9198098183,50.8928985596],"type":"Point"}
}