{
  "type": "Feature",
  "properties": {
    "addr:full":"Boetendaelstraat 132 Ukkel/uccle Bruxelles-Capitale 1180",
    "addr:housenumber":"132",
    "addr:postcode":"1180",
    "addr:street":"Boetendaelstraat;/",
    "iso:country":"BE",
    "sg:address":"Boetendaelstraat 132",
    "sg:city":"Ukkel/uccle",
    "sg:orig_category":"Herstellingen and onderhoud van auto's",
    "sg:phone":"+32 2 345 60 88",
    "sg:postcode":"1180",
    "sg:province":"Bruxelles-Capitale",
    "wof:name":"Carrosserie Longchamp",
    "wof:placetype":"venue"
},
  "geometry": {"coordinates":[4.3426017761,50.8127822876],"type":"Point"}
}