{
  "type": "Feature",
  "properties": {
    "addr:full":"Rue De La Coupe 49-57 Mons Hainaut 7000",
    "addr:housenumber":"49-57",
    "addr:postcode":"7000",
    "addr:street":"Rue De La Coupe;Hainaut",
    "iso:country":"BE",
    "sg:address":"Rue De La Coupe 49-57",
    "sg:city":"Mons",
    "sg:classifiers":[
        {
            "category":"Professional",
            "subcategory":"Printing & Photocopies",
            "type":"Services"
        }
    ],
    "sg:phone":"+32 65 33 64 36",
    "sg:postcode":"7000",
    "sg:province":"Hainaut",
    "sg:tags":[
        "-",
        "plan",
        "reproduction"
    ],
    "wof:name":"Copy Plan",
    "wof:placetype":"venue"
},
  "geometry": {"coordinates":[3.9521870613,50.4523277283],"type":"Point"}
}