{
  "type": "Feature",
  "properties": {
    "addr:full":"Grand` Place 3 Tubize Brabant Wallon 1480",
    "addr:housenumber":"3",
    "addr:postcode":"1480",
    "addr:street":"Wallon",
    "iso:country":"BE",
    "sg:address":"Grand` Place 3",
    "sg:city":"Tubize",
    "sg:orig_category":"Equipement photographique",
    "sg:phone":"+32 2 355 68 82",
    "sg:postcode":"1480",
    "sg:province":"Brabant Wallon",
    "wof:name":"Photo Poley",
    "wof:placetype":"venue"
},
  "geometry": {"coordinates":[4.2051181793,50.6932106018],"type":"Point"}
}