{
  "type": "Feature",
  "properties": {
    "addr:full":"Rue Jean-baptiste Vanp\u00e9 5 Bruxelles (forest) Bruxelles-Capitale 1190",
    "addr:housenumber":"5",
    "addr:postcode":"1190",
    "addr:street":"Rue Jean-Baptiste Vanpe\u0301",
    "iso:country":"BE",
    "sg:address":"Rue Jean-baptiste Vanp\u00e9 5",
    "sg:city":"Bruxelles (forest)",
    "sg:classifiers":[
        {
            "category":"Retail",
            "subcategory":"Repair Shop",
            "type":"Services"
        }
    ],
    "sg:phone":"+32 2 332 43 35",
    "sg:postcode":"1190",
    "sg:province":"Bruxelles-Capitale",
    "sg:tags":[
        "-",
        "clothing",
        "alteration"
    ],
    "wof:name":"Nina Couture",
    "wof:placetype":"venue"
},
  "geometry": {"coordinates":[4.3178768158,50.8096466064],"type":"Point"}
}