{
  "type": "Feature",
  "properties": {
    "addr:full":"Louis Gunsstraat 68 Overijse Vlaams-Brabant 3090",
    "addr:housenumber":"68",
    "addr:postcode":"3090",
    "addr:street":"Louis Gunsstraat",
    "iso:country":"BE",
    "sg:address":"Louis Gunsstraat 68",
    "sg:city":"Overijse",
    "sg:orig_category":"Fruitteelt",
    "sg:phone":"+32 2 657 16 19",
    "sg:postcode":"3090",
    "sg:province":"Vlaams-Brabant",
    "wof:name":"Andre Cordier",
    "wof:placetype":"venue"
},
  "geometry": {"coordinates":[4.499024868,50.7919044495],"type":"Point"}
}