{
  "type": "Feature",
  "properties": {
    "addr:full":"Sint-janstraat 4 Kortrijk West-Vlaanderen 8500",
    "addr:housenumber":"4",
    "addr:postcode":"8500",
    "addr:street":"Sint-Janstraat",
    "iso:country":"BE",
    "sg:address":"Sint-janstraat 4",
    "sg:city":"Kortrijk",
    "sg:orig_category":"Enseignement secondaire technique and professionnel",
    "sg:phone":"+32 56 22 13 18",
    "sg:postcode":"8500",
    "sg:province":"West-Vlaanderen",
    "wof:name":"Pleinschool Bijstand",
    "wof:placetype":"venue"
},
  "geometry": {"coordinates":[3.2705869675,50.8272285461],"type":"Point"}
}