{
  "type": "Feature",
  "properties": {
    "addr:full":"Langlire 23 Gouvy Luxembourg 6674",
    "addr:housenumber":"23",
    "addr:postcode":"6674",
    "addr:street":"Langlire",
    "iso:country":"BE",
    "sg:address":"Langlire 23",
    "sg:city":"Gouvy",
    "sg:orig_category":"Rundveehouders",
    "sg:phone":"+32 80 41 88 39",
    "sg:postcode":"6674",
    "sg:province":"Luxembourg",
    "wof:name":"Georges Pirson",
    "wof:placetype":"venue"
},
  "geometry": {"coordinates":[5.838903904,50.2287788391],"type":"Point"}
}