{
  "type": "Feature",
  "properties": {
    "addr:full":"Wolvengracht 38 Brussel/bruxelles Bruxelles-Capitale 1000",
    "addr:housenumber":"38",
    "addr:postcode":"1000",
    "addr:street":"Wolvengracht;/",
    "iso:country":"BE",
    "sg:address":"Wolvengracht 38",
    "sg:city":"Brussel/bruxelles",
    "sg:orig_category":"Notarissen",
    "sg:phone":"+32 2 217 53 97",
    "sg:postcode":"1000",
    "sg:province":"Bruxelles-Capitale",
    "wof:name":"Corinne Dupont",
    "wof:placetype":"venue"
},
  "geometry": {"coordinates":[4.3550410271,50.8502464294],"type":"Point"}
}