{
  "type": "Feature",
  "properties": {
    "iso:country":"BE",
    "sg:address":"Chauss\u00c9e De Tournai 101",
    "sg:city":"Tournai (grand)",
    "sg:classifiers":[
        {
            "category":"Restaurant",
            "type":"Food & Drink"
        }
    ],
    "sg:phone":"+32 69 21 64 17",
    "sg:postcode":"7520",
    "sg:province":"Hainaut",
    "wof:name":"Les Enfants Du Pir\u00c9e",
    "wof:placetype":"venue"
},
  "geometry": {"coordinates":[3.3433859348,50.6457595825],"type":"Point"}
}