{
  "type": "Feature",
  "properties": {
    "addr:full":"Rue Arthur Pouplier 101bb Ecaussinnes Hainaut 7190",
    "addr:housenumber":"101bb",
    "addr:postcode":"7190",
    "addr:street":"Rue Arthur Pouplier;Hainaut",
    "iso:country":"BE",
    "sg:address":"Rue Arthur Pouplier 101bb",
    "sg:city":"Ecaussinnes",
    "sg:orig_category":"Kapsalons",
    "sg:phone":"+32 67 44 37 50",
    "sg:postcode":"7190",
    "sg:province":"Hainaut",
    "wof:name":"Veronique Willocq",
    "wof:placetype":"venue"
},
  "geometry": {"coordinates":[4.153234005,50.562171936],"type":"Point"}
}