{
  "type": "Feature",
  "properties": {
    "addr:full":"Avenue De Boetendael 124 Bruxelles (uccle) Bruxelles-Capitale 1180",
    "addr:housenumber":"124",
    "addr:postcode":"1180",
    "addr:street":"Avenue De Boetendael",
    "iso:country":"BE",
    "sg:address":"Avenue De Boetendael 124",
    "sg:city":"Bruxelles (uccle)",
    "sg:classifiers":[
        {
            "category":"Wholesale",
            "subcategory":"Books, Periodicals, & Newspapers",
            "type":"Manufacturing & Wholesale Goods"
        }
    ],
    "sg:phone":"+32 2 345 95 66",
    "sg:postcode":"1180",
    "sg:province":"Bruxelles-Capitale",
    "sg:tags":[
        "publisher"
    ],
    "wof:name":"Lebeer Hossmann Sprl",
    "wof:placetype":"venue"
},
  "geometry": {"coordinates":[4.3433279991,50.8073005676],"type":"Point"}
}