{
  "type": "Feature",
  "properties": {
    "addr:full":"Maneshoeve 10 Geel Antwerpen 2440",
    "addr:housenumber":"10",
    "addr:postcode":"2440",
    "addr:street":"Maneshoeve",
    "iso:country":"BE",
    "sg:address":"Maneshoeve 10",
    "sg:city":"Geel",
    "sg:classifiers":[
        {
            "category":"Health Services",
            "subcategory":"Dentist",
            "type":"Services"
        }
    ],
    "sg:phone":"+32 14 58 35 59",
    "sg:postcode":"2440",
    "sg:province":"Antwerpen",
    "wof:name":"Godelaine Chris",
    "wof:placetype":"venue"
},
  "geometry": {"coordinates":[4.9906659126,51.1610794067],"type":"Point"}
}