{
  "type": "Feature",
  "properties": {
    "iso:country":"BE",
    "sg:address":"Handzamestraat 77",
    "sg:city":"Kortemark",
    "sg:orig_category":"Advocaten and juridische adviseurs",
    "sg:phone":"+32 51 56 65 74",
    "sg:postcode":"8610",
    "sg:province":"West-Vlaanderen",
    "wof:name":"Caroline Vandenberghe",
    "wof:placetype":"venue"
},
  "geometry": {"coordinates":[3.0364038944,51.0290298462],"type":"Point"}
}