{
  "type": "Feature",
  "properties": {
    "addr:full":"Rue D'amostrennes 24 Esneux Li\u00e8ge 4130",
    "addr:housenumber":"24",
    "addr:postcode":"4130",
    "addr:street":"Rue D'Amostrennes",
    "iso:country":"BE",
    "sg:address":"Rue D'amostrennes 24",
    "sg:city":"Esneux",
    "sg:orig_category":"Artsen and specialisten",
    "sg:phone":"+32 4 380 08 00",
    "sg:postcode":"4130",
    "sg:province":"Li\u00e8ge",
    "wof:name":"M. Tanghe",
    "wof:placetype":"venue"
},
  "geometry": {"coordinates":[5.546626091,50.5268936157],"type":"Point"}
}