{
  "type": "Feature",
  "properties": {
    "iso:country":"BE",
    "sg:address":"Koning Albertlaan 23-1",
    "sg:city":"Neerpelt",
    "sg:classifiers":[
        {
            "category":"Shopping",
            "subcategory":"Beauty & Cosmetics",
            "type":"Retail Goods"
        }
    ],
    "sg:phone":"+32 11 66 52 83",
    "sg:postcode":"3910",
    "sg:province":"Limburg",
    "sg:tags":[
        "-",
        "perfumery"
    ],
    "wof:name":"J & J Parfumerie",
    "wof:placetype":"venue"
},
  "geometry": {"coordinates":[5.4304699898,51.2262115479],"type":"Point"}
}