{
  "type": "Feature",
  "properties": {
    "addr:full":"Rue Grande 53a Dour Hainaut 7370",
    "addr:housenumber":"53a",
    "addr:postcode":"7370",
    "addr:street":"Rue Grande;Hainaut",
    "iso:country":"BE",
    "sg:address":"Rue Grande 53a",
    "sg:city":"Dour",
    "sg:classifiers":[
        {
            "category":"Shopping",
            "subcategory":"Clothing, Apparel, & Fashions",
            "type":"Retail Goods"
        }
    ],
    "sg:phone":"+32 65 65 29 36",
    "sg:postcode":"7370",
    "sg:province":"Hainaut",
    "sg:tags":[
        "boutique"
    ],
    "wof:name":"Elle (boutique)",
    "wof:placetype":"venue"
},
  "geometry": {"coordinates":[3.7802650928,50.3985443115],"type":"Point"}
}