{
  "type": "Feature",
  "properties": {
    "addr:full":"Diestse Steenweg 93 Aarschot Vlaams-Brabant 3200",
    "addr:housenumber":"93",
    "addr:postcode":"3200",
    "addr:street":"Diestse Steenweg",
    "iso:country":"BE",
    "sg:address":"Diestse Steenweg 93",
    "sg:city":"Aarschot",
    "sg:classifiers":[
        {
            "category":"Farming",
            "subcategory":"Fish & Marine Products",
            "type":"Manufacturing & Wholesale Goods"
        }
    ],
    "sg:phone":"+32 16 50 23 34",
    "sg:postcode":"3200",
    "sg:province":"Vlaams-Brabant",
    "sg:tags":[
        "lime-scale",
        "removing",
        "apparatus"
    ],
    "wof:name":"Omniscala",
    "wof:placetype":"venue"
},
  "geometry": {"coordinates":[4.8601350784,50.9786834717],"type":"Point"}
}