{
  "type": "Feature",
  "properties": {
    "addr:full":"Attenhovenstraat 154 Landen (attenhoven) Vlaams-Brabant 3404",
    "addr:housenumber":"154",
    "addr:postcode":"3404",
    "addr:street":"Attenhovenstraat",
    "iso:country":"BE",
    "sg:address":"Attenhovenstraat 154",
    "sg:city":"Landen (attenhoven)",
    "sg:classifiers":[
        {
            "category":"Shopping",
            "subcategory":"Florist",
            "type":"Retail Goods"
        }
    ],
    "sg:phone":"+32 11 88 32 01",
    "sg:postcode":"3404",
    "sg:province":"Vlaams-Brabant",
    "wof:name":"Botanicus",
    "wof:placetype":"venue"
},
  "geometry": {"coordinates":[5.0876631737,50.7615852356],"type":"Point"}
}