{
  "type": "Feature",
  "properties": {
    "addr:full":"Touwstraat 2 Lokeren Oost-Vlaanderen 9160",
    "addr:housenumber":"2",
    "addr:postcode":"9160",
    "addr:street":"Touwstraat",
    "iso:country":"BE",
    "sg:address":"Touwstraat 2",
    "sg:city":"Lokeren",
    "sg:orig_category":"Kapsalons",
    "sg:phone":"+32 9 348 65 26",
    "sg:postcode":"9160",
    "sg:province":"Oost-Vlaanderen",
    "wof:name":"Isabelle Kint",
    "wof:placetype":"venue"
},
  "geometry": {"coordinates":[3.972867012,51.1036186218],"type":"Point"}
}