{
  "type": "Feature",
  "properties": {
    "addr:full":"Leuzestraat 121 Kortrijk West-Vlaanderen 8510",
    "addr:housenumber":"121",
    "addr:postcode":"8510",
    "addr:street":"Leuzestraat",
    "iso:country":"BE",
    "sg:address":"Leuzestraat 121",
    "sg:city":"Kortrijk",
    "sg:orig_category":"Artsen and specialisten",
    "sg:phone":"+32 56 22 50 09",
    "sg:postcode":"8510",
    "sg:province":"West-Vlaanderen",
    "wof:name":"J. Bouckaert",
    "wof:placetype":"venue"
},
  "geometry": {"coordinates":[3.3040530682,50.7652015686],"type":"Point"}
}