{
  "type": "Feature",
  "properties": {
    "addr:full":"Kasteelstraat 43 Kortenberg (erps-kwerps) Vlaams-Brabant 3071",
    "addr:housenumber":"43",
    "addr:postcode":"3071",
    "addr:street":"Kasteelstraat",
    "iso:country":"BE",
    "sg:address":"Kasteelstraat 43",
    "sg:city":"Kortenberg (erps-kwerps)",
    "sg:classifiers":[
        {
            "category":"Real Estate",
            "subcategory":"Real Estate Services",
            "type":"Services"
        }
    ],
    "sg:phone":"+32 2 759 96 53",
    "sg:postcode":"3071",
    "sg:province":"Vlaams-Brabant",
    "wof:name":"Willems E",
    "wof:placetype":"venue"
},
  "geometry": {"coordinates":[4.5678238869,50.9061317444],"type":"Point"}
}