{
  "type": "Feature",
  "properties": {
    "addr:full":"Statiestraat 47 Dentergem West-Vlaanderen 8720",
    "addr:housenumber":"47",
    "addr:postcode":"8720",
    "addr:street":"Statiestraat",
    "iso:country":"BE",
    "sg:address":"Statiestraat 47",
    "sg:city":"Dentergem",
    "sg:orig_category":"Autombile concessionaires",
    "sg:phone":"+32 51 63 31 25",
    "sg:postcode":"8720",
    "sg:province":"West-Vlaanderen",
    "wof:name":"Gar De Smet W",
    "wof:placetype":"venue"
},
  "geometry": {"coordinates":[3.4160571098,50.9659576416],"type":"Point"}
}