{
  "type": "Feature",
  "properties": {
    "addr:full":"Lakenmakersstraat 11 Mol Antwerpen 2400",
    "addr:housenumber":"11",
    "addr:postcode":"2400",
    "addr:street":"Lakenmakersstraat",
    "iso:country":"BE",
    "sg:address":"Lakenmakersstraat 11",
    "sg:city":"Mol",
    "sg:classifiers":[
        {
            "category":"Shopping",
            "subcategory":"Bicycles & Sporting Goods",
            "type":"Retail Goods"
        }
    ],
    "sg:phone":"+32 14 32 07 19",
    "sg:postcode":"2400",
    "sg:province":"Antwerpen",
    "sg:tags":[
        "sport",
        "-"
    ],
    "wof:name":"Center Shop Sports Wear",
    "wof:placetype":"venue"
},
  "geometry": {"coordinates":[5.1180109978,51.1879425049],"type":"Point"}
}