{
  "type": "Feature",
  "properties": {
    "addr:full":"Avenue De Thiervaux 2 Verviers Li\u00e8ge 4802",
    "addr:housenumber":"2",
    "addr:postcode":"4802",
    "addr:street":"Avenue De Thiervaux",
    "iso:country":"BE",
    "sg:address":"Avenue De Thiervaux 2",
    "sg:city":"Verviers",
    "sg:orig_category":"Postkantoren Verzekeringsmakelaars and experts",
    "sg:phone":"+32 87 22 97 36",
    "sg:postcode":"4802",
    "sg:province":"Li\u00e8ge",
    "wof:name":"La Poste",
    "wof:placetype":"venue"
},
  "geometry": {"coordinates":[5.8722500801,50.5806617737],"type":"Point"}
}