{
  "type": "Feature",
  "properties": {
    "iso:country":"BE",
    "sg:address":"Markt 5",
    "sg:city":"Vorselaar",
    "sg:classifiers":[
        {
            "category":"Banks & Credit Unions",
            "subcategory":"Bank",
            "type":"Services"
        }
    ],
    "sg:phone":"+32 14 51 67 57",
    "sg:postcode":"2290",
    "sg:province":"Antwerpen",
    "wof:name":"Gemeentekrediet",
    "wof:placetype":"venue"
},
  "geometry": {"coordinates":[4.7731609344,51.2023582458],"type":"Point"}
}