{
  "type": "Feature",
  "properties": {
    "iso:country":"BE",
    "sg:address":"Haarsnijderslaan 4",
    "sg:city":"Lokeren",
    "sg:classifiers":[
        {
            "category":"Real Estate",
            "subcategory":"Developer",
            "type":"Services"
        }
    ],
    "sg:phone":"+32 9 348 09 20",
    "sg:postcode":"9160",
    "sg:province":"Oost-Vlaanderen",
    "sg:tags":[
        "project"
    ],
    "wof:name":"Goede Werkmanswoning",
    "wof:placetype":"venue"
},
  "geometry": {"coordinates":[3.9909200668,51.0989875793],"type":"Point"}
}