{
  "type": "Feature",
  "properties": {
    "addr:full":"Vuurkruisenstraat 1 Leopoldsburg Limburg 3970",
    "addr:housenumber":"1",
    "addr:postcode":"3970",
    "addr:street":"Vuurkruisenstraat",
    "iso:country":"BE",
    "sg:address":"Vuurkruisenstraat 1",
    "sg:city":"Leopoldsburg",
    "sg:classifiers":[
        {
            "category":"Arena",
            "subcategory":"Sports Club",
            "type":"Entertainment"
        }
    ],
    "sg:phone":"+32 11 34 64 30",
    "sg:postcode":"3970",
    "sg:province":"Limburg",
    "sg:tags":[
        "de"
    ],
    "wof:name":"J.c. Leopoldsburg",
    "wof:placetype":"venue"
},
  "geometry": {"coordinates":[5.2529430389,51.1117935181],"type":"Point"}
}