{
  "type": "Feature",
  "properties": {
    "addr:full":"Merelbekestraat 41 Melle Oost-Vlaanderen 9090",
    "addr:housenumber":"41",
    "addr:postcode":"9090",
    "addr:street":"Merelbekestraat",
    "iso:country":"BE",
    "sg:address":"Merelbekestraat 41",
    "sg:city":"Melle",
    "sg:orig_category":"Brood, gebak and snoepgoed",
    "sg:phone":"+32 9 231 30 86",
    "sg:postcode":"9090",
    "sg:province":"Oost-Vlaanderen",
    "wof:name":"Patrick Denolf",
    "wof:placetype":"venue"
},
  "geometry": {"coordinates":[3.7707819939,51.0227851868],"type":"Point"}
}