{
  "type": "Feature",
  "properties": {
    "addr:full":"Karmelietenstraat 64b7 Antwerpen Antwerpen 2600",
    "addr:housenumber":"64b7",
    "addr:postcode":"2600",
    "addr:street":"Karmelietenstraat",
    "iso:country":"BE",
    "sg:address":"Karmelietenstraat 64b7",
    "sg:city":"Antwerpen",
    "sg:orig_category":"Sportclubs",
    "sg:phone":"+32 3 449 25 15",
    "sg:postcode":"2600",
    "sg:province":"Antwerpen",
    "wof:name":"H.c. Hyllos",
    "wof:placetype":"venue"
},
  "geometry": {"coordinates":[4.4174151421,51.1974411011],"type":"Point"}
}