{
  "type": "Feature",
  "properties": {
    "addr:full":"Haagstraat 42 Gavere Oost-Vlaanderen 9890",
    "addr:housenumber":"42",
    "addr:postcode":"9890",
    "addr:street":"Haagstraat",
    "iso:country":"BE",
    "sg:address":"Haagstraat 42",
    "sg:city":"Gavere",
    "sg:orig_category":"Elektrische installaties voor woningen",
    "sg:phone":"+32 9 384 79 38",
    "sg:postcode":"9890",
    "sg:province":"Oost-Vlaanderen",
    "wof:name":"Antoine Pessemier Danick",
    "wof:placetype":"venue"
},
  "geometry": {"coordinates":[3.6544349194,50.9117012024],"type":"Point"}
}