{
  "type": "Feature",
  "properties": {
    "iso:country":"BE",
    "sg:address":"Rue Des Flamands 13",
    "sg:city":"Bruxelles (jette)",
    "sg:classifiers":[
        {
            "category":"Education",
            "subcategory":"Dance Studio",
            "type":"Public Place"
        }
    ],
    "sg:phone":"+32 475 32 60 52",
    "sg:postcode":"1090",
    "sg:province":"Bruxelles-Capitale",
    "sg:tags":[
        "school",
        "dancing"
    ],
    "wof:name":"Petit Bolchoi (le)",
    "wof:placetype":"venue"
},
  "geometry": {"coordinates":[4.324244976,50.8753814697],"type":"Point"}
}