{
  "type": "Feature",
  "properties": {
    "addr:full":"Place Fran\u00c7ois Geron 0 Verviers Li\u00e8ge 4800",
    "addr:housenumber":"0",
    "addr:postcode":"4800",
    "addr:street":"Place Franc\u0327Ois Geron",
    "iso:country":"BE",
    "sg:address":"Place Fran\u00c7ois Geron 0",
    "sg:city":"Verviers",
    "sg:orig_category":"Enseignement maternel and primaire",
    "sg:phone":"+32 87 33 56 67",
    "sg:postcode":"4800",
    "sg:province":"Li\u00e8ge",
    "wof:name":"Ecole Matern. Communale",
    "wof:placetype":"venue"
},
  "geometry": {"coordinates":[5.8659248352,50.5977592468],"type":"Point"}
}