{
  "type": "Feature",
  "properties": {
    "addr:full":"Batterijstraat 79 De Haan (klemskerke) West-Vlaanderen 8420",
    "addr:housenumber":"79",
    "addr:postcode":"8420",
    "addr:street":"Batterijstraat",
    "iso:country":"BE",
    "sg:address":"Batterijstraat 79",
    "sg:city":"De Haan (klemskerke)",
    "sg:classifiers":[
        {
            "category":"Personal",
            "subcategory":"Barber",
            "type":"Services"
        }
    ],
    "sg:phone":"+32 59 23 44 45",
    "sg:postcode":"8420",
    "sg:province":"West-Vlaanderen",
    "sg:tags":[
        "gentleman",
        "salon",
        "-",
        "hairdressing"
    ],
    "wof:name":"Sabrina",
    "wof:placetype":"venue"
},
  "geometry": {"coordinates":[2.998003006,51.2478408813],"type":"Point"}
}