{
  "type": "Feature",
  "properties": {
    "addr:full":"Van Praetstraat 1 Damme (moerkerke) West-Vlaanderen 8340",
    "addr:housenumber":"1",
    "addr:postcode":"8340",
    "addr:street":"Van Praetstraat",
    "iso:country":"BE",
    "sg:address":"Van Praetstraat 1",
    "sg:city":"Damme (moerkerke)",
    "sg:classifiers":[
        {
            "category":"Health Services",
            "subcategory":"Health Practitioner",
            "type":"Services"
        }
    ],
    "sg:phone":"+32 50 50 06 88",
    "sg:postcode":"8340",
    "sg:province":"West-Vlaanderen",
    "sg:tags":[
        "physiotherapist"
    ],
    "wof:name":"Heyndrickx Philip",
    "wof:placetype":"venue"
},
  "geometry": {"coordinates":[3.3376228809,51.2450752258],"type":"Point"}
}