{
  "type": "Feature",
  "properties": {
    "addr:full":"Zwartemolenstraat 23 Zele Oost-Vlaanderen 9240",
    "addr:housenumber":"23",
    "addr:postcode":"9240",
    "addr:street":"Zwartemolenstraat",
    "iso:country":"BE",
    "sg:address":"Zwartemolenstraat 23",
    "sg:city":"Zele",
    "sg:orig_category":"Artsen and specialisten",
    "sg:phone":"+32 52 44 67 00",
    "sg:postcode":"9240",
    "sg:province":"Oost-Vlaanderen",
    "wof:name":"Birgit Deprez",
    "wof:placetype":"venue"
},
  "geometry": {"coordinates":[4.0246510506,51.0611076355],"type":"Point"}
}