{
  "type": "Feature",
  "properties": {
    "iso:country":"BE",
    "sg:address":"Leopoldlaan 130",
    "sg:city":"Aalst",
    "sg:orig_category":"Ordinateurs and \u00e9quipement informatique",
    "sg:phone":"+32 53 78 58 12",
    "sg:postcode":"9300",
    "sg:province":"Oost-Vlaanderen",
    "wof:name":"Tricon",
    "wof:placetype":"venue"
},
  "geometry": {"coordinates":[4.0489139557,50.9469337463],"type":"Point"}
}