{
  "type": "Feature",
  "properties": {
    "iso:country":"BE",
    "sg:address":"Meidoornlaan 1",
    "sg:city":"Steenokkerzeel",
    "sg:orig_category":"Plomberie, chauffage and installations sanitaires",
    "sg:phone":"+32 2 751 82 73",
    "sg:postcode":"1820",
    "sg:province":"Vlaams-Brabant",
    "wof:name":"Ecowatt",
    "wof:placetype":"venue"
},
  "geometry": {"coordinates":[4.5088310242,50.9246482849],"type":"Point"}
}