{
  "type": "Feature",
  "properties": {
    "iso:country":"BE",
    "sg:address":"Lotenhullestraat 91",
    "sg:city":"Deinze (vinkt)",
    "sg:classifiers":[
        {
            "category":"Farming",
            "subcategory":"Crops",
            "type":"Manufacturing & Wholesale Goods"
        }
    ],
    "sg:phone":"+32 9 386 38 75",
    "sg:postcode":"9800",
    "sg:province":"Oost-Vlaanderen",
    "sg:tags":[
        "vegetable",
        "fruit",
        "-",
        "grower"
    ],
    "wof:name":"Vansteenkiste A",
    "wof:placetype":"venue"
},
  "geometry": {"coordinates":[3.4747850895,51.0142974854],"type":"Point"}
}