{
  "type": "Feature",
  "properties": {
    "iso:country":"BE",
    "sg:address":"Begijnhof 67",
    "sg:city":"Turnhout",
    "sg:classifiers":[
        {
            "category":"Wholesale",
            "subcategory":"Books, Periodicals, & Newspapers",
            "type":"Manufacturing & Wholesale Goods"
        }
    ],
    "sg:phone":"+32 14 44 80 20",
    "sg:postcode":"2300",
    "sg:province":"Antwerpen",
    "sg:tags":[
        "publisher"
    ],
    "wof:name":"Brepols Publishers Nv",
    "wof:placetype":"venue"
},
  "geometry": {"coordinates":[4.9444379807,51.3268051147],"type":"Point"}
}