{
  "type": "Feature",
  "properties": {
    "iso:country":"BE",
    "sg:address":"Avenue Max Buset 3",
    "sg:city":"La Louviere",
    "sg:orig_category":"Pharmaciens",
    "sg:phone":"+32 64 22 29 41",
    "sg:postcode":"7100",
    "sg:province":"Hainaut",
    "wof:name":"Pol Geurts",
    "wof:placetype":"venue"
},
  "geometry": {"coordinates":[4.201895237,50.4748153687],"type":"Point"}
}