{
  "type": "Feature",
  "properties": {
    "iso:country":"BE",
    "sg:address":"Chauss\u00e9e De Lodelinsart 7",
    "sg:city":"Charleroi (gilly)",
    "sg:classifiers":[
        {
            "category":"Retail",
            "subcategory":"Repair Shop",
            "type":"Services"
        }
    ],
    "sg:phone":"+32 71 42 34 54",
    "sg:postcode":"6060",
    "sg:province":"Hainaut",
    "sg:tags":[
        "radio",
        "television",
        "-",
        "maintenance"
    ],
    "wof:name":"Telektra Trisca Sa",
    "wof:placetype":"venue"
},
  "geometry": {"coordinates":[4.4497041702,50.4185447693],"type":"Point"}
}