{
  "type": "Feature",
  "properties": {
    "iso:country":"BE",
    "sg:address":"Gullegemstraat 74",
    "sg:city":"Wevelgem",
    "sg:orig_category":"Kapsalons",
    "sg:phone":"+32 56 32 31 92",
    "sg:postcode":"8560",
    "sg:province":"West-Vlaanderen",
    "wof:name":"Coiffure Hilde",
    "wof:placetype":"venue"
},
  "geometry": {"coordinates":[3.1869590282,50.8149833679],"type":"Point"}
}