{
  "type": "Feature",
  "properties": {
    "iso:country":"BE",
    "sg:address":"Bredabaan 356",
    "sg:city":"Brasschaat",
    "sg:classifiers":[
        {
            "category":"Shopping",
            "subcategory":"Clothing, Apparel, & Fashions",
            "type":"Retail Goods"
        }
    ],
    "sg:phone":"+32 3 652 19 06",
    "sg:postcode":"2930",
    "sg:province":"Antwerpen",
    "sg:tags":[
        "lady",
        "clothing",
        "-"
    ],
    "wof:name":"La Dame Bvba",
    "wof:placetype":"venue"
},
  "geometry": {"coordinates":[4.4941859245,51.2925987244],"type":"Point"}
}