{
  "type": "Feature",
  "properties": {
    "addr:full":"Sint-corynstraat 9 Lo-reninge West-Vlaanderen 8647",
    "addr:housenumber":"9",
    "addr:postcode":"8647",
    "addr:street":"Sint-Corynstraat",
    "iso:country":"BE",
    "sg:address":"Sint-corynstraat 9",
    "sg:city":"Lo-reninge",
    "sg:orig_category":"Eleveurs de bovins",
    "sg:phone":"+32 57 40 02 80",
    "sg:postcode":"8647",
    "sg:province":"West-Vlaanderen",
    "wof:name":"Hugo Obin",
    "wof:placetype":"venue"
},
  "geometry": {"coordinates":[2.7487149239,50.9805717468],"type":"Point"}
}