{
  "type": "Feature",
  "properties": {
    "iso:country":"BE",
    "sg:address":"Rue Du Val Notre-dame 323",
    "sg:city":"Wanze (antheit)",
    "sg:classifiers":[
        {
            "category":"Bars & Pubs",
            "type":"Food & Drink"
        }
    ],
    "sg:phone":"+32 85 21 35 99",
    "sg:postcode":"4520",
    "sg:province":"Li\u00e8ge",
    "wof:name":"Maison Du Peuple Du Val De Mehaigne",
    "wof:placetype":"venue"
},
  "geometry": {"coordinates":[5.1860880852,50.5509109497],"type":"Point"}
}