{
  "type": "Feature",
  "properties": {
    "iso:country":"BE",
    "sg:address":"Grote Baan 124",
    "sg:city":"Ravels",
    "sg:orig_category":"Plaatsen van vloer- and muurbekleding Schilders",
    "sg:phone":"+32 14 65 53 29",
    "sg:postcode":"2380",
    "sg:province":"Antwerpen",
    "wof:name":"Gustaaf Mertens",
    "wof:placetype":"venue"
},
  "geometry": {"coordinates":[4.9914422035,51.3651123047],"type":"Point"}
}