{
  "type": "Feature",
  "properties": {
    "addr:full":"Zi All\u00e9e Centrale Jumet Hainaut 6040",
    "addr:postcode":"6040",
    "addr:street":"Alle\u0301E Centrale;Hainaut",
    "iso:country":"BE",
    "sg:address":"Zi All\u00e9e Centrale",
    "sg:city":"Jumet",
    "sg:classifiers":[
        {
            "category":"Manufacturing",
            "subcategory":"Glass & Minerals",
            "type":"Manufacturing & Wholesale Goods"
        }
    ],
    "sg:phone":"+32 71 25 81 30",
    "sg:postcode":"6040",
    "sg:province":"Hainaut",
    "sg:tags":[
        "building",
        "material"
    ],
    "wof:name":"Beads Belgium Sa",
    "wof:placetype":"venue"
},
  "geometry": {"coordinates":[4.4558048248,50.4553108215],"type":"Point"}
}