{
  "type": "Feature",
  "properties": {
    "addr:full":"Rue Fran\u00e7ois Dorz\u00e9e 72 Boussu Hainaut 7300",
    "addr:housenumber":"72",
    "addr:postcode":"7300",
    "addr:street":"Rue Franc\u0327Ois Dorze\u0301E",
    "iso:country":"BE",
    "sg:address":"Rue Fran\u00e7ois Dorz\u00e9e 72",
    "sg:city":"Boussu",
    "sg:classifiers":[
        {
            "category":"Shopping",
            "subcategory":"Luggage & Leather Goods",
            "type":"Retail Goods"
        }
    ],
    "sg:phone":"+32 65 78 69 93",
    "sg:postcode":"7300",
    "sg:province":"Hainaut",
    "sg:tags":[
        "-"
    ],
    "wof:name":"Simonart F",
    "wof:placetype":"venue"
},
  "geometry": {"coordinates":[3.8007850647,50.4329872131],"type":"Point"}
}