{
  "type": "Feature",
  "properties": {
    "iso:country":"BE",
    "sg:address":"Hoogstraat 107",
    "sg:city":"Zemst",
    "sg:orig_category":"Plomberie, chauffage and installations sanitaires",
    "sg:phone":"+32 15 61 49 30",
    "sg:postcode":"1980",
    "sg:province":"Vlaams-Brabant",
    "wof:name":"Danny Ferijn",
    "wof:placetype":"venue"
},
  "geometry": {"coordinates":[4.4544329643,50.9902305603],"type":"Point"}
}