{
  "type": "Feature",
  "properties": {
    "iso:country":"BE",
    "sg:address":"Melkmarkt 30",
    "sg:city":"Antwerpen",
    "sg:classifiers":[
        {
            "category":"Shopping",
            "subcategory":"Gifts & Souvenirs",
            "type":"Retail Goods"
        }
    ],
    "sg:phone":"+32 3 213 23 13",
    "sg:postcode":"2000",
    "sg:province":"Antwerpen",
    "sg:tags":[
        "-"
    ],
    "wof:name":"Akot\u00e9e",
    "wof:placetype":"venue"
},
  "geometry": {"coordinates":[4.4025602341,51.2200965881],"type":"Point"}
}