{
  "type": "Feature",
  "properties": {
    "iso:country":"BE",
    "sg:address":"Westerlosesteenweg 37",
    "sg:city":"Heist-op-den-berg",
    "sg:orig_category":"Rusthuizen and serviceflats",
    "sg:phone":"+32 15 24 18 26",
    "sg:postcode":"2220",
    "sg:province":"Antwerpen",
    "wof:name":"Heilige Familie",
    "wof:placetype":"venue"
},
  "geometry": {"coordinates":[4.7341179848,51.0736083984],"type":"Point"}
}