{
  "type": "Feature",
  "properties": {
    "iso:country":"BE",
    "sg:address":"Koning Albertlaan 29",
    "sg:city":"Sint-agatha-berchem/berchem-sainte-agathe",
    "sg:orig_category":"Dierenartsen",
    "sg:phone":"+32 2 468 39 20",
    "sg:postcode":"1082",
    "sg:province":"Bruxelles-Capitale",
    "wof:name":"Didier Geens",
    "wof:placetype":"venue"
},
  "geometry": {"coordinates":[4.2950220108,50.864780426],"type":"Point"}
}