{
  "type": "Feature",
  "properties": {
    "addr:full":"Bosstraat 316 Waarschoot Oost-Vlaanderen 9950",
    "addr:housenumber":"316",
    "addr:postcode":"9950",
    "addr:street":"Bosstraat",
    "iso:country":"BE",
    "sg:address":"Bosstraat 316",
    "sg:city":"Waarschoot",
    "sg:classifiers":[
        {
            "category":"Shopping",
            "subcategory":"Stationery & Office Supplies",
            "type":"Retail Goods"
        }
    ],
    "sg:phone":"+32 9 357 31 45",
    "sg:postcode":"9950",
    "sg:province":"Oost-Vlaanderen",
    "sg:tags":[
        "partition"
    ],
    "wof:name":"Boelaert K",
    "wof:placetype":"venue"
},
  "geometry": {"coordinates":[3.6331501007,51.1571502686],"type":"Point"}
}