{
  "type": "Feature",
  "properties": {
    "addr:full":"Transcontinentaalweg 1 Antwerpen Antwerpen 2030",
    "addr:housenumber":"1",
    "addr:postcode":"2030",
    "addr:street":"Transcontinentaalweg",
    "iso:country":"BE",
    "sg:address":"Transcontinentaalweg 1",
    "sg:city":"Antwerpen",
    "sg:classifiers":[
        {
            "category":"Banks & Credit Unions",
            "subcategory":"Bank",
            "type":"Services"
        }
    ],
    "sg:phone":"+32 3541250709",
    "sg:postcode":"2030",
    "sg:province":"Antwerpen",
    "wof:name":"Rentco Belgium Nv",
    "wof:placetype":"venue"
},
  "geometry": {"coordinates":[4.3981370926,51.2732467651],"type":"Point"}
}