{
  "type": "Feature",
  "properties": {
    "iso:country":"BE",
    "sg:address":"Stokberg 6b1",
    "sg:city":"Laakdal",
    "sg:classifiers":[
        {
            "category":"Building & Trades",
            "subcategory":"Landscaping Services",
            "type":"Services"
        }
    ],
    "sg:phone":"+32 14 86 70 23",
    "sg:postcode":"2430",
    "sg:province":"Antwerpen",
    "sg:tags":[
        "earth",
        "moving"
    ],
    "wof:name":"Couwberghs Algemene Onderneming Nv",
    "wof:placetype":"venue"
},
  "geometry": {"coordinates":[5.0687851906,51.0857543945],"type":"Point"}
}