{
  "type": "Feature",
  "properties": {
    "addr:full":"Bilzersteenweg 363 Tongeren (riksingen) Limburg 3700",
    "addr:housenumber":"363",
    "addr:postcode":"3700",
    "addr:street":"Bilzersteenweg",
    "iso:country":"BE",
    "sg:address":"Bilzersteenweg 363",
    "sg:city":"Tongeren (riksingen)",
    "sg:classifiers":[
        {
            "category":"Health Services",
            "subcategory":"Health Practitioner",
            "type":"Services"
        }
    ],
    "sg:phone":"+32 12 39 26 60",
    "sg:postcode":"3700",
    "sg:province":"Limburg",
    "sg:tags":[
        "physiotherapist"
    ],
    "wof:name":"Driesen Anja",
    "wof:placetype":"venue"
},
  "geometry": {"coordinates":[5.4650249481,50.7939949036],"type":"Point"}
}