{
  "type": "Feature",
  "properties": {
    "iso:country":"BE",
    "sg:address":"Doelhofstraat 6",
    "sg:city":"Zuienkerke",
    "sg:orig_category":"Installation \u00e9lectrique r\u00e9sidentielle",
    "sg:phone":"+32 50 42 66 94",
    "sg:postcode":"8377",
    "sg:province":"West-Vlaanderen",
    "wof:name":"Lucker",
    "wof:placetype":"venue"
},
  "geometry": {"coordinates":[3.094119072,51.2734260559],"type":"Point"}
}