{
  "type": "Feature",
  "properties": {
    "addr:full":"Molenstraat 61 Laarne Oost-Vlaanderen 9270",
    "addr:housenumber":"61",
    "addr:postcode":"9270",
    "addr:street":"Molenstraat",
    "iso:country":"BE",
    "sg:address":"Molenstraat 61",
    "sg:city":"Laarne",
    "sg:classifiers":[
        {
            "category":"Personal",
            "subcategory":"Barber",
            "type":"Services"
        }
    ],
    "sg:phone":"+32 9 369 39 40",
    "sg:postcode":"9270",
    "sg:province":"Oost-Vlaanderen",
    "sg:tags":[
        "gentleman",
        "salon",
        "-",
        "hairdressing"
    ],
    "wof:name":"Dennis Hair Club",
    "wof:placetype":"venue"
},
  "geometry": {"coordinates":[3.8576710224,51.0300941467],"type":"Point"}
}