{
  "type": "Feature",
  "properties": {
    "iso:country":"BE",
    "sg:address":"Mechelsesteenweg 69",
    "sg:city":"Kampenhout",
    "sg:orig_category":"Woningbouw",
    "sg:phone":"+32 16 60 80 38",
    "sg:postcode":"1910",
    "sg:province":"Vlaams-Brabant",
    "wof:name":"Wouters & Co",
    "wof:placetype":"venue"
},
  "geometry": {"coordinates":[4.5866298676,50.9594345093],"type":"Point"}
}