{
  "type": "Feature",
  "properties": {
    "addr:full":"Rue Saint-pierre 16 Huy Li\u00e8ge 4500",
    "addr:housenumber":"16",
    "addr:postcode":"4500",
    "addr:street":"Rue Saint-Pierre",
    "iso:country":"BE",
    "sg:address":"Rue Saint-pierre 16",
    "sg:city":"Huy",
    "sg:orig_category":"Cr\u00e9meries",
    "sg:phone":"+32 85 23 36 33",
    "sg:postcode":"4500",
    "sg:province":"Li\u00e8ge",
    "wof:name":"La Planche \u00c0 Fromages",
    "wof:placetype":"venue"
},
  "geometry": {"coordinates":[5.2355442047,50.5222473145],"type":"Point"}
}