{
  "type": "Feature",
  "properties": {
    "addr:full":"Gracht 43 Genk Limburg 3600",
    "addr:housenumber":"43",
    "addr:postcode":"3600",
    "addr:street":"Gracht",
    "iso:country":"BE",
    "sg:address":"Gracht 43",
    "sg:city":"Genk",
    "sg:classifiers":[
        {
            "category":"Shopping",
            "subcategory":"Baby Store",
            "type":"Retail Goods"
        }
    ],
    "sg:phone":"+32 472 47 67 55",
    "sg:postcode":"3600",
    "sg:province":"Limburg",
    "sg:tags":[
        "midwife"
    ],
    "wof:name":"Marcheval V",
    "wof:placetype":"venue"
},
  "geometry": {"coordinates":[5.4304127693,50.9618492126],"type":"Point"}
}