{
  "type": "Feature",
  "properties": {
    "iso:country":"BE",
    "sg:address":"Route De Gembloux 344b2",
    "sg:city":"Eghezee",
    "sg:orig_category":"Afbraak- and draineerwerken Dakwerken",
    "sg:phone":"+32 81 65 80 36",
    "sg:postcode":"5310",
    "sg:province":"Namur",
    "wof:name":"Joiret",
    "wof:placetype":"venue"
},
  "geometry": {"coordinates":[4.9000458717,50.591129303],"type":"Point"}
}