{
  "type": "Feature",
  "properties": {
    "addr:full":"Rue Longue 129 Ch\u00e2telet (bouffioulx) Hainaut 6200",
    "addr:housenumber":"129",
    "addr:postcode":"6200",
    "addr:street":"Rue Longue",
    "iso:country":"BE",
    "sg:address":"Rue Longue 129",
    "sg:city":"Ch\u00e2telet (bouffioulx)",
    "sg:classifiers":[
        {
            "category":"Professional",
            "subcategory":"Accounting & Tax Preparation",
            "type":"Services"
        }
    ],
    "sg:phone":"+32 71 50 12 11",
    "sg:postcode":"6200",
    "sg:province":"Hainaut",
    "sg:tags":[
        "bookkeeper"
    ],
    "wof:name":"Laffineur R",
    "wof:placetype":"venue"
},
  "geometry": {"coordinates":[4.495059967,50.374786377],"type":"Point"}
}