{
  "type": "Feature",
  "properties": {
    "addr:full":"Rue Jacques Dubois 9 Namur (flawinne) Namur 5020",
    "addr:housenumber":"9",
    "addr:postcode":"5020",
    "addr:street":"Rue Jacques Dubois",
    "iso:country":"BE",
    "sg:address":"Rue Jacques Dubois 9",
    "sg:city":"Namur (flawinne)",
    "sg:classifiers":[
        {
            "category":"Professional",
            "subcategory":"Printing & Photocopies",
            "type":"Services"
        }
    ],
    "sg:phone":"+32 81 73 91 51",
    "sg:postcode":"5020",
    "sg:province":"Namur",
    "sg:tags":[
        "digital"
    ],
    "wof:name":"Boland Sprl",
    "wof:placetype":"venue"
},
  "geometry": {"coordinates":[4.7952418327,50.4352035522],"type":"Point"}
}