{
  "type": "Feature",
  "properties": {
    "iso:country":"BE",
    "sg:address":"All\u00e9e Des Meules 3",
    "sg:city":"Walcourt (chastr\u00e8s)",
    "sg:orig_category":"Non-Classified Establishments",
    "sg:phone":"+32 71 61 58 78",
    "sg:postcode":"5650",
    "sg:province":"Namur",
    "wof:name":"B.b. International Sprl",
    "wof:placetype":"venue"
},
  "geometry": {"coordinates":[4.4313349724,50.2514762878],"type":"Point"}
}