{
  "type": "Feature",
  "properties": {
    "iso:country":"BE",
    "sg:address":"Oscar Van Kesbeeckstraat 79",
    "sg:city":"Mechelen",
    "sg:classifiers":[
        {
            "category":"Health Services",
            "subcategory":"Health Practitioner",
            "type":"Services"
        }
    ],
    "sg:phone":"+32 15 20 52 57",
    "sg:postcode":"2800",
    "sg:province":"Antwerpen",
    "sg:tags":[
        "physiotherapist"
    ],
    "wof:name":"Blavier E",
    "wof:placetype":"venue"
},
  "geometry": {"coordinates":[4.4730000496,51.0388450623],"type":"Point"}
}