{
  "type": "Feature",
  "properties": {
    "addr:full":"Rue D'hurtebise 61 Binche Hainaut 7130",
    "addr:housenumber":"61",
    "addr:postcode":"7130",
    "addr:street":"Rue D'Hurtebise",
    "iso:country":"BE",
    "sg:address":"Rue D'hurtebise 61",
    "sg:city":"Binche",
    "sg:classifiers":[
        {
            "category":"Arts & Performance",
            "subcategory":"Theater",
            "type":"Entertainment"
        }
    ],
    "sg:phone":"+32 64 33 17 76",
    "sg:postcode":"7130",
    "sg:province":"Hainaut",
    "sg:tags":[
        "concert-halls",
        "theatre"
    ],
    "wof:name":"Pave Picard Bainchou (el) Asbl",
    "wof:placetype":"venue"
},
  "geometry": {"coordinates":[4.1687669754,50.4064292908],"type":"Point"}
}