{
  "type": "Feature",
  "properties": {
    "iso:country":"BE",
    "sg:address":"Jan Mahieustraat 37",
    "sg:city":"Roeselare",
    "sg:orig_category":"Agences de voyages",
    "sg:phone":"+32 51 24 75 63",
    "sg:postcode":"8800",
    "sg:province":"West-Vlaanderen",
    "wof:name":"Pluto Reizen",
    "wof:placetype":"venue"
},
  "geometry": {"coordinates":[3.1260659695,50.948097229],"type":"Point"}
}