{
  "type": "Feature",
  "properties": {
    "iso:country":"BE",
    "sg:address":"O.-l.-vrouweplein 9",
    "sg:city":"Boechout",
    "sg:orig_category":"Bijouteries and horlogeries. R\u00e9parations d'horloges, montres and bijoux",
    "sg:phone":"+32 3 455 37 62",
    "sg:postcode":"2530",
    "sg:province":"Antwerpen",
    "wof:name":"Walter Bellens",
    "wof:placetype":"venue"
},
  "geometry": {"coordinates":[4.4913249016,51.1586532593],"type":"Point"}
}