{
  "type": "Feature",
  "properties": {
    "iso:country":"BE",
    "sg:address":"Jacques Bassemstraat 10",
    "sg:city":"Oudergem/auderghem",
    "sg:orig_category":"Artsen and specialisten",
    "sg:phone":"+32 2 673 37 20",
    "sg:postcode":"1160",
    "sg:province":"Bruxelles-Capitale",
    "wof:name":"Annie Degen",
    "wof:placetype":"venue"
},
  "geometry": {"coordinates":[4.4282860756,50.8151550293],"type":"Point"}
}