{
  "type": "Feature",
  "properties": {
    "addr:full":"Oud-dorp 57 Haaltert (heldergem) Oost-Vlaanderen 9450",
    "addr:housenumber":"57",
    "addr:postcode":"9450",
    "addr:street":"Oud-Dorp",
    "iso:country":"BE",
    "sg:address":"Oud-dorp 57",
    "sg:city":"Haaltert (heldergem)",
    "sg:classifiers":[
        {
            "category":"Personal",
            "subcategory":"Beauty Salon",
            "type":"Services"
        }
    ],
    "sg:phone":"+32 53 62 37 25",
    "sg:postcode":"9450",
    "sg:province":"Oost-Vlaanderen",
    "sg:tags":[
        "lady",
        "-",
        "hairdressing"
    ],
    "wof:name":"Rijdend Kapsalon (het)",
    "wof:placetype":"venue"
},
  "geometry": {"coordinates":[4.017988205,50.8711395264],"type":"Point"}
}