{
  "type": "Feature",
  "properties": {
    "iso:country":"BE",
    "sg:address":"Rue De Souvret 83",
    "sg:city":"Courcelles",
    "sg:classifiers":[
        {
            "category":"Banks & Credit Unions",
            "subcategory":"Investment Brokerage",
            "type":"Services"
        }
    ],
    "sg:phone":"+32 71 45 61 10",
    "sg:postcode":"6180",
    "sg:province":"Hainaut",
    "sg:tags":[
        "printing",
        "-"
    ],
    "wof:name":"Ipr Sprl",
    "wof:placetype":"venue"
},
  "geometry": {"coordinates":[4.3632488251,50.4551696777],"type":"Point"}
}