{
  "type": "Feature",
  "properties": {
    "addr:full":"Nieuwplaats 14 Hooglede West-Vlaanderen 8830",
    "addr:housenumber":"14",
    "addr:postcode":"8830",
    "addr:street":"Nieuwplaats",
    "iso:country":"BE",
    "sg:address":"Nieuwplaats 14",
    "sg:city":"Hooglede",
    "sg:orig_category":"Dameskledingzaken",
    "sg:phone":"+32 51 20 27 46",
    "sg:postcode":"8830",
    "sg:province":"West-Vlaanderen",
    "wof:name":"Huis Giddis",
    "wof:placetype":"venue"
},
  "geometry": {"coordinates":[3.0972158909,50.9967002869],"type":"Point"}
}