{
  "type": "Feature",
  "properties": {
    "addr:full":"Avenue Des Martyrs 26 Fl\u00e9ron Li\u00e8ge 4620",
    "addr:housenumber":"26",
    "addr:postcode":"4620",
    "addr:street":"Avenue Des Martyrs",
    "iso:country":"BE",
    "sg:address":"Avenue Des Martyrs 26",
    "sg:city":"Fl\u00e9ron",
    "sg:classifiers":[
        {
            "category":"Building & Trades",
            "subcategory":"Construction",
            "type":"Services"
        }
    ],
    "sg:phone":"+32 4 358 28 22",
    "sg:postcode":"4620",
    "sg:province":"Li\u00e8ge",
    "sg:tags":[
        "installation",
        "-",
        "central",
        "heating"
    ],
    "wof:name":"B\u00e2timents & Maintenance",
    "wof:placetype":"venue"
},
  "geometry": {"coordinates":[5.6705980301,50.6163215637],"type":"Point"}
}