{
  "type": "Feature",
  "properties": {
    "iso:country":"BE",
    "sg:address":"Statielei 19b6",
    "sg:city":"Mortsel",
    "sg:classifiers":[
        {
            "category":"Insurance",
            "subcategory":"Life Insurance",
            "type":"Services"
        }
    ],
    "sg:phone":"+32 3 449 04 42",
    "sg:postcode":"2640",
    "sg:province":"Antwerpen",
    "sg:tags":[
        "assurance"
    ],
    "wof:name":"Verzekeringsk. Dedrie G.",
    "wof:placetype":"venue"
},
  "geometry": {"coordinates":[4.4504289627,51.170841217],"type":"Point"}
}