{
  "type": "Feature",
  "properties": {
    "addr:full":"Rue Robert Ledecq 17ba Braine-le-chateau Brabant Wallon 1440",
    "addr:housenumber":"17ba",
    "addr:postcode":"1440",
    "addr:street":"Rue Robert Ledecq;Brabant Wallon",
    "iso:country":"BE",
    "sg:address":"Rue Robert Ledecq 17ba",
    "sg:city":"Braine-le-chateau",
    "sg:orig_category":"Enseignement maternel and primaire",
    "sg:phone":"+32 2 366 13 58",
    "sg:postcode":"1440",
    "sg:province":"Brabant Wallon",
    "wof:name":"Ecole Fond. Communale",
    "wof:placetype":"venue"
},
  "geometry": {"coordinates":[4.3198747635,50.6858825684],"type":"Point"}
}