{
  "type": "Feature",
  "properties": {
    "addr:full":"Place Joseph Willem 9 Li\u00c8ge Li\u00e8ge 4032",
    "addr:housenumber":"9",
    "addr:postcode":"4032",
    "addr:street":"Place Joseph Willem",
    "iso:country":"BE",
    "sg:address":"Place Joseph Willem 9",
    "sg:city":"Li\u00c8ge",
    "sg:orig_category":"Services pour animaux domestiques",
    "sg:phone":"+32 4 371 91 51",
    "sg:postcode":"4032",
    "sg:province":"Li\u00e8ge",
    "wof:name":"Animal Mon Ami",
    "wof:placetype":"venue"
},
  "geometry": {"coordinates":[5.619579792,50.6117401123],"type":"Point"}
}