{
  "type": "Feature",
  "properties": {
    "addr:full":"Dijver 15 Brugge West-Vlaanderen 8000",
    "addr:housenumber":"15",
    "addr:postcode":"8000",
    "addr:street":"Dijver",
    "iso:country":"BE",
    "sg:address":"Dijver 15",
    "sg:city":"Brugge",
    "sg:classifiers":[
        {
            "category":"Manufacturing",
            "subcategory":"Textiles",
            "type":"Manufacturing & Wholesale Goods"
        }
    ],
    "sg:phone":"+32 50 34 30 54",
    "sg:postcode":"8000",
    "sg:province":"West-Vlaanderen",
    "wof:name":"Gruuthuuse Lace",
    "wof:placetype":"venue"
},
  "geometry": {"coordinates":[3.225771904,51.205783844],"type":"Point"}
}