{
  "type": "Feature",
  "properties": {
    "iso:country":"BE",
    "sg:address":"Bontestierstraat 14",
    "sg:city":"Deerlijk",
    "sg:classifiers":[
        {
            "category":"Home & Garden",
            "subcategory":"Home Furnishings",
            "type":"Retail Goods"
        }
    ],
    "sg:phone":"+32 56 72 69 04",
    "sg:postcode":"8540",
    "sg:province":"West-Vlaanderen",
    "sg:tags":[
        "interior",
        "decoration"
    ],
    "wof:name":"Interior Scherpereel & Zn",
    "wof:placetype":"venue"
},
  "geometry": {"coordinates":[3.3702979088,50.8556213379],"type":"Point"}
}