{
  "type": "Feature",
  "properties": {
    "iso:country":"BE",
    "sg:address":"Rekollettenstraat 27d",
    "sg:city":"Kortrijk",
    "sg:classifiers":[
        {
            "category":"Wholesale",
            "subcategory":"Beer",
            "type":"Manufacturing & Wholesale Goods"
        }
    ],
    "sg:phone":"+32 56 35 17 65",
    "sg:postcode":"8500",
    "sg:province":"West-Vlaanderen",
    "sg:tags":[
        "ale",
        "-"
    ],
    "wof:name":"De Grijse Etn A Nv",
    "wof:placetype":"venue"
},
  "geometry": {"coordinates":[3.2570500374,50.8312721252],"type":"Point"}
}