{
  "type": "Feature",
  "properties": {
    "addr:full":"Huidevettersstraat 29 Antwerpen Antwerpen 2000",
    "addr:housenumber":"29",
    "addr:postcode":"2000",
    "addr:street":"Huidevettersstraat",
    "iso:country":"BE",
    "sg:address":"Huidevettersstraat 29",
    "sg:city":"Antwerpen",
    "sg:classifiers":[
        {
            "category":"Shopping",
            "subcategory":"Clothing, Apparel, & Fashions",
            "type":"Retail Goods"
        }
    ],
    "sg:phone":"+32 3 233 23 53",
    "sg:postcode":"2000",
    "sg:province":"Antwerpen",
    "sg:tags":[
        "lady",
        "clothing",
        "-"
    ],
    "wof:name":"Rochar",
    "wof:placetype":"venue"
},
  "geometry": {"coordinates":[4.4056630135,51.2172966003],"type":"Point"}
}