{
  "type": "Feature",
  "properties": {
    "addr:full":"Rue Du Gouvernement 1 Ath Hainaut 7800",
    "addr:housenumber":"1",
    "addr:postcode":"7800",
    "addr:street":"Rue Du Gouvernement",
    "iso:country":"BE",
    "sg:address":"Rue Du Gouvernement 1",
    "sg:city":"Ath",
    "sg:orig_category":"Beheer van reclamemedia Radioproductie and uitzendingen",
    "sg:phone":"+32 68 28 04 75",
    "sg:postcode":"7800",
    "sg:province":"Hainaut",
    "wof:name":"Radio Contact",
    "wof:placetype":"venue"
},
  "geometry": {"coordinates":[3.7766799927,50.6309204102],"type":"Point"}
}