{
  "type": "Feature",
  "properties": {
    "addr:full":"Rue De La Station 22 Clavier Li\u00e8ge 4560",
    "addr:housenumber":"22",
    "addr:postcode":"4560",
    "addr:street":"Rue De La Station",
    "iso:country":"BE",
    "sg:address":"Rue De La Station 22",
    "sg:city":"Clavier",
    "sg:orig_category":"Installatie van houten of kunststof schrijnwerk",
    "sg:phone":"+32 85 41 26 69",
    "sg:postcode":"4560",
    "sg:province":"Li\u00e8ge",
    "wof:name":"Luc Bastin",
    "wof:placetype":"venue"
},
  "geometry": {"coordinates":[5.3406310081,50.4410858154],"type":"Point"}
}