{
  "type": "Feature",
  "properties": {
    "iso:country":"BE",
    "sg:address":"Advocaat De Backerstraat 53bb",
    "sg:city":"Haaltert",
    "sg:orig_category":"Artsen and specialisten",
    "sg:phone":"+32 54 32 06 66",
    "sg:postcode":"9450",
    "sg:province":"Oost-Vlaanderen",
    "wof:name":"Sigrid Musch",
    "wof:placetype":"venue"
},
  "geometry": {"coordinates":[4.0183739662,50.8754844666],"type":"Point"}
}