{
  "type": "Feature",
  "properties": {
    "addr:full":"Markt 21 Mol Antwerpen 2400",
    "addr:housenumber":"21",
    "addr:postcode":"2400",
    "addr:street":"Markt",
    "iso:country":"BE",
    "sg:address":"Markt 21",
    "sg:city":"Mol",
    "sg:classifiers":[
        {
            "category":"Autos & Motor Vehicles",
            "subcategory":"Boat Sales",
            "type":"Retail Goods"
        }
    ],
    "sg:phone":"+32 14 31 78 67",
    "sg:postcode":"2400",
    "sg:province":"Antwerpen",
    "sg:tags":[
        "balloon"
    ],
    "wof:name":"Speed Lover",
    "wof:placetype":"venue"
},
  "geometry": {"coordinates":[5.116517067,51.1846046448],"type":"Point"}
}