{
  "type": "Feature",
  "properties": {
    "iso:country":"BE",
    "sg:address":"Izegemsestraat 50",
    "sg:city":"Kortrijk",
    "sg:orig_category":"Boekhandels",
    "sg:phone":"+32 56 35 12 49",
    "sg:postcode":"8500",
    "sg:province":"West-Vlaanderen",
    "wof:name":"Boekendraad",
    "wof:placetype":"venue"
},
  "geometry": {"coordinates":[3.2601070404,50.8366127014],"type":"Point"}
}