{
  "type": "Feature",
  "properties": {
    "addr:full":"Lar Blok P 12 Rekkem West-Vlaanderen 8930",
    "addr:housenumber":"12",
    "addr:postcode":"8930",
    "iso:country":"BE",
    "sg:address":"Lar Blok P 12",
    "sg:city":"Rekkem",
    "sg:classifiers":[
        {
            "category":"Professional",
            "subcategory":"Business Services",
            "type":"Services"
        }
    ],
    "sg:phone":"+32 56 43 88 88",
    "sg:postcode":"8930",
    "sg:province":"West-Vlaanderen",
    "sg:tags":[
        "shipping"
    ],
    "wof:name":"Walter & Emmanuel Castelein Nv",
    "wof:placetype":"venue"
},
  "geometry": {"coordinates":[3.1209149361,50.7961845398],"type":"Point"}
}