{
  "type": "Feature",
  "properties": {
    "addr:full":"Circuit De La Clairi\u00c8re 14 Saint-ghislain Hainaut 7331",
    "addr:housenumber":"14",
    "addr:postcode":"7331",
    "addr:street":"Circuit De La Clairie\u0300Re;Hainaut",
    "iso:country":"BE",
    "sg:address":"Circuit De La Clairi\u00c8re 14",
    "sg:city":"Saint-ghislain",
    "sg:orig_category":"Elektrische installaties voor woningen",
    "sg:phone":"+32 65 79 51 00",
    "sg:postcode":"7331",
    "sg:province":"Hainaut",
    "wof:name":"Fe. Denolf",
    "wof:placetype":"venue"
},
  "geometry": {"coordinates":[3.8317780495,50.4982566833],"type":"Point"}
}