{
  "type": "Feature",
  "properties": {
    "iso:country":"BE",
    "sg:address":"Boulevard Du R\u00e9gent 24 Box 8",
    "sg:city":"Bruxelles",
    "sg:classifiers":[
        {
            "category":"Professional",
            "subcategory":"Lawyer & Legal Services",
            "type":"Services"
        }
    ],
    "sg:phone":"+32 2 513 83 45",
    "sg:postcode":"1000",
    "sg:province":"Bruxelles-Capitale",
    "sg:tags":[
        "notary"
    ],
    "wof:name":"Huylebrouck Ch",
    "wof:placetype":"venue"
},
  "geometry": {"coordinates":[4.3671469688,50.8438720703],"type":"Point"}
}