{
  "type": "Feature",
  "properties": {
    "iso:country":"BE",
    "sg:address":"Parklaan 2",
    "sg:city":"Ninove",
    "sg:classifiers":[
        {
            "category":"Cafe",
            "type":"Food & Drink"
        }
    ],
    "sg:phone":"+32 54 32 77 10",
    "sg:postcode":"9400",
    "sg:province":"Oost-Vlaanderen",
    "sg:tags":[
        "caf\u00e9s"
    ],
    "wof:name":"De Ridder Jacques En Tom",
    "wof:placetype":"venue"
},
  "geometry": {"coordinates":[4.0223731995,50.8298568726],"type":"Point"}
}