{
  "type": "Feature",
  "properties": {
    "addr:full":"Stakendijke 3 Damme (sijsele) West-Vlaanderen 8340",
    "addr:housenumber":"3",
    "addr:postcode":"8340",
    "addr:street":"Stakendijke",
    "iso:country":"BE",
    "sg:address":"Stakendijke 3",
    "sg:city":"Damme (sijsele)",
    "sg:classifiers":[
        {
            "category":"Professional",
            "subcategory":"Accounting & Tax Preparation",
            "type":"Services"
        }
    ],
    "sg:phone":"+32 50 67 39 23",
    "sg:postcode":"8340",
    "sg:province":"West-Vlaanderen",
    "sg:tags":[
        "bookkeeper"
    ],
    "wof:name":"Debruyne R",
    "wof:placetype":"venue"
},
  "geometry": {"coordinates":[3.3165090084,51.2077636719],"type":"Point"}
}