{
  "type": "Feature",
  "properties": {
    "addr:full":"Vluchtenburgstr 9 Aartselaar Antwerpen 2630",
    "addr:housenumber":"9",
    "addr:postcode":"2630",
    "addr:street":"Vluchtenburgstr",
    "iso:country":"BE",
    "sg:address":"Vluchtenburgstr 9",
    "sg:city":"Aartselaar",
    "sg:classifiers":[
        {
            "category":"Manufacturing",
            "subcategory":"Building Materials",
            "type":"Manufacturing & Wholesale Goods"
        }
    ],
    "sg:phone":"+32 3 877 06 70",
    "sg:postcode":"2630",
    "sg:province":"Antwerpen",
    "sg:tags":[
        "glass",
        "ceramic"
    ],
    "wof:name":"Van Mechelen Magvam Bvba",
    "wof:placetype":"venue"
},
  "geometry": {"coordinates":[4.3741679192,51.1344299316],"type":"Point"}
}