{
  "type": "Feature",
  "properties": {
    "addr:full":"De Smet De Naeyerlaan 19 Blankenberge West-Vlaanderen 8370",
    "addr:housenumber":"19",
    "addr:postcode":"8370",
    "addr:street":"De Smet De Naeyerlaan",
    "iso:country":"BE",
    "sg:address":"De Smet De Naeyerlaan 19",
    "sg:city":"Blankenberge",
    "sg:classifiers":[
        {
            "category":"Bars & Pubs",
            "type":"Food & Drink"
        }
    ],
    "sg:phone":"+32 50 42 52 57",
    "sg:postcode":"8370",
    "sg:province":"West-Vlaanderen",
    "wof:name":"Kapiteintje ('t)",
    "wof:placetype":"venue"
},
  "geometry": {"coordinates":[3.1223270893,51.3125572205],"type":"Point"}
}