{
  "type": "Feature",
  "properties": {
    "addr:full":"Rue Des Muguets 24 Saint-nicolas Li\u00e8ge 4420",
    "addr:housenumber":"24",
    "addr:postcode":"4420",
    "addr:street":"Rue Des Muguets",
    "iso:country":"BE",
    "sg:address":"Rue Des Muguets 24",
    "sg:city":"Saint-nicolas",
    "sg:orig_category":"Dakwerken Loodgieterij, verwarming and sanitaire installaties Schoonmaakbedrijven and ongediertebest",
    "sg:phone":"+32 4 252 50 52",
    "sg:postcode":"4420",
    "sg:province":"Li\u00e8ge",
    "wof:name":"Marc Weijenberg",
    "wof:placetype":"venue"
},
  "geometry": {"coordinates":[5.5352420807,50.6323394775],"type":"Point"}
}