{
  "type": "Feature",
  "properties": {
    "iso:country":"BE",
    "sg:address":"Adriaan Brouwerstraat 16",
    "sg:city":"Oudenaarde",
    "sg:classifiers":[
        {
            "category":"Utilities",
            "subcategory":"Fuel Oil & Lpg",
            "type":"Services"
        }
    ],
    "sg:phone":"+32 55 33 88 11",
    "sg:postcode":"9700",
    "sg:province":"Oost-Vlaanderen",
    "wof:name":"De Boever's Brandstoffen Nv",
    "wof:placetype":"venue"
},
  "geometry": {"coordinates":[3.6123139858,50.8463668823],"type":"Point"}
}