{
  "type": "Feature",
  "properties": {
    "addr:full":"Avenue Du Pont De Warche 5 Malmedy Li\u00e8ge 4960",
    "addr:housenumber":"5",
    "addr:postcode":"4960",
    "addr:street":"Avenue Du Pont De Warche",
    "iso:country":"BE",
    "sg:address":"Avenue Du Pont De Warche 5",
    "sg:city":"Malmedy",
    "sg:classifiers":[
        {
            "category":"Home & Garden",
            "subcategory":"Home Furnishings",
            "type":"Retail Goods"
        }
    ],
    "sg:phone":"+32 80 79 10 50",
    "sg:postcode":"4960",
    "sg:province":"Li\u00e8ge",
    "sg:tags":[
        "wallpaper",
        "-"
    ],
    "wof:name":"D\u00e9corama Sa",
    "wof:placetype":"venue"
},
  "geometry": {"coordinates":[6.0056490898,50.4187812805],"type":"Point"}
}