{
  "type": "Feature",
  "properties": {
    "addr:full":"Chemin D'h\u00c9rimetz 1 Ath Hainaut 7823",
    "addr:housenumber":"1",
    "addr:postcode":"7823",
    "addr:street":"Chemin D'He \u0301Rimetz",
    "iso:country":"BE",
    "sg:address":"Chemin D'h\u00c9rimetz 1",
    "sg:city":"Ath",
    "sg:orig_category":"Rundveehouders",
    "sg:phone":"+32 68 55 15 77",
    "sg:postcode":"7823",
    "sg:province":"Hainaut",
    "wof:name":"Jean Breda",
    "wof:placetype":"venue"
},
  "geometry": {"coordinates":[3.8718121052,50.630897522],"type":"Point"}
}