{
  "type": "Feature",
  "properties": {
    "addr:full":"Rue Chapelle Valentin 19 Sombreffe Namur 5140",
    "addr:housenumber":"19",
    "addr:postcode":"5140",
    "addr:street":"Rue Chapelle Valentin",
    "iso:country":"BE",
    "sg:address":"Rue Chapelle Valentin 19",
    "sg:city":"Sombreffe",
    "sg:classifiers":[
        {
            "category":"Retail",
            "subcategory":"Veterinary Services",
            "type":"Services"
        }
    ],
    "sg:phone":"+32 71 88 88 98",
    "sg:postcode":"5140",
    "sg:province":"Namur",
    "sg:tags":[
        "veterinarian"
    ],
    "wof:name":"Vallery M",
    "wof:placetype":"venue"
},
  "geometry": {"coordinates":[4.6067409515,50.5279502869],"type":"Point"}
}