{
  "type": "Feature",
  "properties": {
    "addr:full":"Verenigde-nati\u00ebnlaan 17 Tongeren Limburg 3700",
    "addr:housenumber":"17",
    "addr:postcode":"3700",
    "addr:street":"Verenigde-Natie\u0308Nlaan",
    "iso:country":"BE",
    "sg:address":"Verenigde-nati\u00ebnlaan 17",
    "sg:city":"Tongeren",
    "sg:classifiers":[
        {
            "category":"Bakery",
            "type":"Food & Drink"
        }
    ],
    "sg:phone":"+32 12 23 26 08",
    "sg:postcode":"3700",
    "sg:province":"Limburg",
    "sg:tags":[
        "confectioner",
        "baker"
    ],
    "wof:name":"Gilissen",
    "wof:placetype":"venue"
},
  "geometry": {"coordinates":[5.4677791595,50.786907196],"type":"Point"}
}