{
  "type": "Feature",
  "properties": {
    "addr:full":"Weg Naar Meeuwen 40 Opglabbeek Limburg 3660",
    "addr:housenumber":"40",
    "addr:postcode":"3660",
    "addr:street":"Weg Naar Meeuwen",
    "iso:country":"BE",
    "sg:address":"Weg Naar Meeuwen 40",
    "sg:city":"Opglabbeek",
    "sg:classifiers":[
        {
            "category":"Airport",
            "subcategory":"International",
            "type":"Transportation"
        }
    ],
    "sg:phone":"+32 89 85 50 44",
    "sg:postcode":"3660",
    "sg:province":"Limburg",
    "sg:tags":[
        "-",
        "transport"
    ],
    "wof:name":"Jos Siborgs Internationaal Transport Bvba",
    "wof:placetype":"venue"
},
  "geometry": {"coordinates":[5.5294399261,51.0336608887],"type":"Point"}
}