{
  "type": "Feature",
  "properties": {
    "iso:country":"BE",
    "sg:address":"Pittemsesteenweg 13",
    "sg:city":"Tielt",
    "sg:classifiers":[
        {
            "category":"Freight",
            "type":"Transportation"
        }
    ],
    "sg:phone":"+32 51 40 42 52",
    "sg:postcode":"8700",
    "sg:province":"West-Vlaanderen",
    "sg:tags":[
        "-",
        "transport"
    ],
    "wof:name":"Transdeco",
    "wof:placetype":"venue"
},
  "geometry": {"coordinates":[3.3114778996,50.99817276],"type":"Point"}
}