{
  "type": "Feature",
  "properties": {
    "addr:full":"Minderbroedersstraat 5b301 Sint-truiden Limburg 3800",
    "addr:housenumber":"5b301",
    "addr:postcode":"3800",
    "addr:street":"Minderbroedersstraat",
    "iso:country":"BE",
    "sg:address":"Minderbroedersstraat 5b301",
    "sg:city":"Sint-truiden",
    "sg:classifiers":[
        {
            "category":"Food & Beverages",
            "subcategory":"Fruits & Vegetables",
            "type":"Retail Goods"
        }
    ],
    "sg:phone":"+32 11 68 53 25",
    "sg:postcode":"3800",
    "sg:province":"Limburg",
    "sg:tags":[
        "groenten"
    ],
    "wof:name":"Sandrina Vanwelkenhuysen",
    "wof:placetype":"venue"
},
  "geometry": {"coordinates":[5.185945034,50.8144683838],"type":"Point"}
}