{
  "type": "Feature",
  "properties": {
    "iso:country":"BE",
    "sg:address":"Quai Saint-l\u00c9onard 27-33",
    "sg:city":"Liege",
    "sg:orig_category":"Quincailleries",
    "sg:phone":"+32 4 227 10 02",
    "sg:postcode":"4000",
    "sg:province":"Li\u00e8ge",
    "wof:name":"Outili",
    "wof:placetype":"venue"
},
  "geometry": {"coordinates":[5.5897879601,50.6477661133],"type":"Point"}
}