{
  "type": "Feature",
  "properties": {
    "addr:full":"Rue De Namur 19 Namur (beez) Namur 5000",
    "addr:housenumber":"19",
    "addr:postcode":"5000",
    "addr:street":"Rue De Namur",
    "iso:country":"BE",
    "sg:address":"Rue De Namur 19",
    "sg:city":"Namur (beez)",
    "sg:classifiers":[
        {
            "category":"Building & Trades",
            "subcategory":"Construction",
            "type":"Services"
        }
    ],
    "sg:phone":"+32 81 22 44 74",
    "sg:postcode":"5000",
    "sg:province":"Namur",
    "sg:tags":[
        "roofing",
        "material",
        "-"
    ],
    "wof:name":"Andre",
    "wof:placetype":"venue"
},
  "geometry": {"coordinates":[4.8986229897,50.4677276611],"type":"Point"}
}