{
  "type": "Feature",
  "properties": {
    "iso:country":"BE",
    "sg:address":"Vergotesquare 23b11",
    "sg:city":"Sint-lambrechts-woluwe/woluwe-saint-lambert",
    "sg:orig_category":"Beheer onroerend goed",
    "sg:phone":"+32 2 734 15 72",
    "sg:postcode":"1200",
    "sg:province":"Bruxelles-Capitale",
    "wof:name":"Pierre Renaud",
    "wof:placetype":"venue"
},
  "geometry": {"coordinates":[4.4035968781,50.845249176],"type":"Point"}
}