{
  "type": "Feature",
  "properties": {
    "addr:full":"Rue Des 18 Bonniers 90 Grace-hollogne Li\u00e8ge 4460",
    "addr:housenumber":"90",
    "addr:postcode":"4460",
    "addr:street":"Rue Des 18 Bonniers",
    "iso:country":"BE",
    "sg:address":"Rue Des 18 Bonniers 90",
    "sg:city":"Grace-hollogne",
    "sg:orig_category":"Rev\u00eatements pour sols and murs. Peinture. Travaux de finition and nettoyage de b\u00e2timents",
    "sg:phone":"+32 4 246 37 20",
    "sg:postcode":"4460",
    "sg:province":"Li\u00e8ge",
    "wof:name":"Freson Et Fils",
    "wof:placetype":"venue"
},
  "geometry": {"coordinates":[5.487801075,50.6434440613],"type":"Point"}
}