{
  "type": "Feature",
  "properties": {
    "iso:country":"BE",
    "sg:address":"Peter Benoitstraat 1",
    "sg:city":"Antwerpen",
    "sg:orig_category":"Newspapers, magazines, periodicals - Distribution",
    "sg:phone":"+32 15 55 56 17",
    "sg:postcode":"2018",
    "sg:province":"Antwerpen",
    "wof:name":"Gounod",
    "wof:placetype":"venue"
},
  "geometry": {"coordinates":[4.4082407951,51.2053985596],"type":"Point"}
}