{
  "type": "Feature",
  "properties": {
    "addr:full":"Chauss\u00c9e De La Hulpe 563 Watermaal-bosvoorde/watermael-boitsfort Bruxelles-Capitale 1170",
    "addr:housenumber":"563;/",
    "addr:postcode":"1170",
    "addr:street":"Chausse\u0301E De La Hulpe;Watermaal-Bosvoorde",
    "iso:country":"BE",
    "sg:address":"Chauss\u00c9e De La Hulpe 563",
    "sg:city":"Watermaal-bosvoorde/watermael-boitsfort",
    "sg:orig_category":"Rev\u00eatements pour sols and murs. Peinture",
    "sg:phone":"+32 2 660 08 93",
    "sg:postcode":"1170",
    "sg:province":"Bruxelles-Capitale",
    "wof:name":"Michel Masure",
    "wof:placetype":"venue"
},
  "geometry": {"coordinates":[4.4252009392,50.787311554],"type":"Point"}
}