{
  "type": "Feature",
  "properties": {
    "addr:full":"L.hoelenstraat 41 Heusden-zolder (zolder) Limburg 3550",
    "addr:housenumber":"41",
    "addr:postcode":"3550",
    "addr:street":"L.Hoelenstraat",
    "iso:country":"BE",
    "sg:address":"L.hoelenstraat 41",
    "sg:city":"Heusden-zolder (zolder)",
    "sg:classifiers":[
        {
            "category":"Personal",
            "type":"Services"
        }
    ],
    "sg:phone":"+32 11 25 15 05",
    "sg:postcode":"3550",
    "sg:province":"Limburg",
    "sg:tags":[
        "party",
        "planning"
    ],
    "wof:name":"Hostellerie De Kluis Bvba",
    "wof:placetype":"venue"
},
  "geometry": {"coordinates":[5.2731361389,50.991443634],"type":"Point"}
}