{
  "type": "Feature",
  "properties": {
    "iso:country":"BE",
    "sg:address":"Rue Sainte- Marguerite 333",
    "sg:city":"Liege-centre",
    "sg:orig_category":"RESTAURANTS: LIVRAISON \u00c0 DOMICILE",
    "sg:phone":"+32 4 226 48 68",
    "sg:postcode":"4000",
    "sg:province":"Li\u00e8ge",
    "wof:name":"Phone Pizza",
    "wof:placetype":"venue"
},
  "geometry": {"coordinates":[6.2250900269,44.0888595581],"type":"Point"}
}