{
  "type": "Feature",
  "properties": {
    "iso:country":"BE",
    "sg:address":"Avenue Du Commerce 23",
    "sg:city":"Braine-l'alleud",
    "sg:orig_category":"Produits pharmaceutiques Fab",
    "sg:phone":"+32 2 385 05 75",
    "sg:postcode":"1420",
    "sg:province":"Brabant Wallon",
    "wof:name":"Certa",
    "wof:placetype":"venue"
},
  "geometry": {"coordinates":[-0.7004899979,47.369140625],"type":"Point"}
}