{
  "type": "Feature",
  "properties": {
    "addr:full":"Avenue Emile Van Becelaere 26b Box 21 Bruxelles (watermael-boitsfort) Bruxelles-Capitale 1170",
    "addr:housenumber":"26b box 21",
    "addr:postcode":"1170",
    "addr:street":"Avenue Emile Van Becelaere",
    "iso:country":"BE",
    "sg:address":"Avenue Emile Van Becelaere 26b Box 21",
    "sg:city":"Bruxelles (watermael-boitsfort)",
    "sg:classifiers":[
        {
            "category":"Social Services",
            "type":"Services"
        }
    ],
    "sg:phone":"+32 2 675 75 05",
    "sg:postcode":"1170",
    "sg:province":"Bruxelles-Capitale",
    "wof:name":"Autisme Europe",
    "wof:placetype":"venue"
},
  "geometry": {"coordinates":[4.4059329033,50.799041748],"type":"Point"}
}