{
  "type": "Feature",
  "properties": {
    "addr:full":"Gare Du Midi Bruxelles-saint-gilles Bruxelles-Capitale 1060",
    "addr:postcode":"1060",
    "iso:country":"BE",
    "sg:address":"Gare Du Midi",
    "sg:city":"Bruxelles-saint-gilles",
    "sg:orig_category":"Electrom\u00e9nager, t\u00e9l\u00e9visions and radios. Equipement photographique. Mat\u00e9riel de T\u00e9l\u00e9communication",
    "sg:phone":"+32 2 527 14 28",
    "sg:postcode":"1060",
    "sg:province":"Bruxelles-Capitale",
    "wof:name":"Photo Hall",
    "wof:placetype":"venue"
},
  "geometry": {"coordinates":[4.3421602249,50.8302116394],"type":"Point"}
}