{
  "type": "Feature",
  "properties": {
    "addr:full":"Avenue Germain Gilson 48 Chiny Luxembourg 6810",
    "addr:housenumber":"48",
    "addr:postcode":"6810",
    "addr:street":"Avenue Germain Gilson",
    "iso:country":"BE",
    "sg:address":"Avenue Germain Gilson 48",
    "sg:city":"Chiny",
    "sg:orig_category":"Salles de spectacles. Caf\u00e9s",
    "sg:phone":"+32 61 31 31 38",
    "sg:postcode":"6810",
    "sg:province":"Luxembourg",
    "wof:name":"Centre Culturel & Sportif",
    "wof:placetype":"venue"
},
  "geometry": {"coordinates":[5.3405580521,49.7382736206],"type":"Point"}
}