{
  "type": "Feature",
  "properties": {
    "addr:full":"Tremelobaan 57 Keerbergen Vlaams-Brabant 3140",
    "addr:housenumber":"57",
    "addr:postcode":"3140",
    "addr:street":"Tremelobaan",
    "iso:country":"BE",
    "sg:address":"Tremelobaan 57",
    "sg:city":"Keerbergen",
    "sg:classifiers":[
        {
            "category":"Travel",
            "subcategory":"Travel Agent",
            "type":"Entertainment"
        }
    ],
    "sg:phone":"+32 15 52 06 00",
    "sg:postcode":"3140",
    "sg:province":"Vlaams-Brabant",
    "sg:tags":[
        "agency"
    ],
    "wof:name":"Europareizen Beeck Bvba",
    "wof:placetype":"venue"
},
  "geometry": {"coordinates":[4.6410908699,51.0019035339],"type":"Point"}
}