{
  "type": "Feature",
  "properties": {
    "iso:country":"BE",
    "sg:address":"Rue Du Luxembourg 13b",
    "sg:city":"Marche-en-famenne",
    "sg:classifiers":[
        {
            "category":"Autos & Motor Vehicles",
            "subcategory":"Auto Supplies",
            "type":"Retail Goods"
        }
    ],
    "sg:phone":"+32 84 31 21 77",
    "sg:postcode":"6900",
    "sg:province":"Luxembourg",
    "sg:tags":[
        "access",
        "automobile",
        "part",
        "-"
    ],
    "wof:name":"Depierreux",
    "wof:placetype":"venue"
},
  "geometry": {"coordinates":[5.3470191956,50.2250785828],"type":"Point"}
}