{
  "type": "Feature",
  "properties": {
    "addr:full":"Maria Van Bourgondi\u00cblaan 38 Brugge West-Vlaanderen 8000",
    "addr:housenumber":"38",
    "addr:postcode":"8000",
    "addr:street":"Maria Van Bourgondie\u0308Laan",
    "iso:country":"BE",
    "sg:address":"Maria Van Bourgondi\u00cblaan 38",
    "sg:city":"Brugge",
    "sg:orig_category":"Assurances. Banques and organismes de cr\u00e9dit. Pr\u00eats hypoth\u00e9caires and cr\u00e9dits immobiliers",
    "sg:phone":"+32 496 17 84 36",
    "sg:postcode":"8000",
    "sg:province":"West-Vlaanderen",
    "wof:name":"Kantoor Summum",
    "wof:placetype":"venue"
},
  "geometry": {"coordinates":[3.2063670158,51.2128753662],"type":"Point"}
}