{
  "type": "Feature",
  "properties": {
    "addr:full":"Tolbareel 16 Brasschaat Antwerpen 2930",
    "addr:housenumber":"16",
    "addr:postcode":"2930",
    "addr:street":"Tolbareel",
    "iso:country":"BE",
    "sg:address":"Tolbareel 16",
    "sg:city":"Brasschaat",
    "sg:orig_category":"Diverse bouwafwerking and reiniging Schoonmaakbedrijven and ongediertebestrijding",
    "sg:phone":"+32 3 652 05 34",
    "sg:postcode":"2930",
    "sg:province":"Antwerpen",
    "wof:name":"Elite",
    "wof:placetype":"venue"
},
  "geometry": {"coordinates":[4.5040831566,51.3068847656],"type":"Point"}
}