{
  "type": "Feature",
  "properties": {
    "iso:country":"BE",
    "sg:address":"Chemin De La Terre Pel\u00e9e 23",
    "sg:city":"Seneffe",
    "sg:classifiers":[
        {
            "category":"Health Services",
            "subcategory":"Health Practitioner",
            "type":"Services"
        }
    ],
    "sg:phone":"+32 64 55 48 41",
    "sg:postcode":"7180",
    "sg:province":"Hainaut",
    "sg:tags":[
        "therapist",
        "speech"
    ],
    "wof:name":"Hubert N",
    "wof:placetype":"venue"
},
  "geometry": {"coordinates":[4.2432818413,50.5357246399],"type":"Point"}
}