{
  "type": "Feature",
  "properties": {
    "iso:country":"BE",
    "sg:address":"Tabaartstraat 40",
    "sg:city":"Bilzen",
    "sg:orig_category":"Bloemen and planten GROENTEN AND FRUIT",
    "sg:phone":"+32 89 41 23 50",
    "sg:postcode":"3740",
    "sg:province":"Limburg",
    "wof:name":"Joseph Hensen",
    "wof:placetype":"venue"
},
  "geometry": {"coordinates":[5.5242710114,50.8700256348],"type":"Point"}
}