{
  "type": "Feature",
  "properties": {
    "iso:country":"BE",
    "sg:address":"Warloche 21",
    "sg:city":"Frasnes-lez-anvaing",
    "sg:orig_category":"Elektrische installaties voor woningen SMEEDWERK, METAALBEWERKING AND POEDERMETALLURGIE",
    "sg:phone":"+32 69 86 66 79",
    "sg:postcode":"7911",
    "sg:province":"Hainaut",
    "wof:name":"Forgelec",
    "wof:placetype":"venue"
},
  "geometry": {"coordinates":[3.6704199314,50.6741905212],"type":"Point"}
}