{
  "type": "Feature",
  "properties": {
    "iso:country":"BE",
    "sg:address":"Rue De Namur 24",
    "sg:city":"Wavre",
    "sg:classifiers":[
        {
            "category":"Banks & Credit Unions",
            "subcategory":"Bureau De Change",
            "type":"Services"
        }
    ],
    "sg:phone":"+32 10 22 24 90",
    "sg:postcode":"1300",
    "sg:province":"Brabant Wallon",
    "sg:tags":[
        "-",
        "household",
        "gas"
    ],
    "wof:name":"Tricot Ch",
    "wof:placetype":"venue"
},
  "geometry": {"coordinates":[4.6118907928,50.7128143311],"type":"Point"}
}