{
  "type": "Feature",
  "properties": {
    "addr:full":"Kerkplein 11 Mol Antwerpen 2400",
    "addr:housenumber":"11",
    "addr:postcode":"2400",
    "addr:street":"Kerkplein",
    "iso:country":"BE",
    "sg:address":"Kerkplein 11",
    "sg:city":"Mol",
    "sg:orig_category":"Epiceries",
    "sg:phone":"+32 14 81 05 39",
    "sg:postcode":"2400",
    "sg:province":"Antwerpen",
    "wof:name":"J. Faes",
    "wof:placetype":"venue"
},
  "geometry": {"coordinates":[5.2055439949,51.2215805054],"type":"Point"}
}