{
  "type": "Feature",
  "properties": {
    "iso:country":"BE",
    "sg:address":"Oude Baan 106",
    "sg:city":"Essen",
    "sg:classifiers":[
        {
            "category":"Cafe",
            "type":"Food & Drink"
        }
    ],
    "sg:phone":"+32 3 667 27 81",
    "sg:postcode":"2910",
    "sg:province":"Antwerpen",
    "sg:tags":[
        "caf\u00e9s"
    ],
    "wof:name":"Anna Duurloo",
    "wof:placetype":"venue"
},
  "geometry": {"coordinates":[4.464454174,51.4537162781],"type":"Point"}
}