{
  "type": "Feature",
  "properties": {
    "iso:country":"BE",
    "sg:address":"St Jozefstr 14",
    "sg:city":"Rumst",
    "sg:classifiers":[
        {
            "category":"Autos & Motor Vehicles",
            "subcategory":"Automobile Sales",
            "type":"Retail Goods"
        }
    ],
    "sg:phone":"+32 3 880 55 55",
    "sg:postcode":"2840",
    "sg:province":"Antwerpen",
    "sg:tags":[
        "equipment",
        "motor-cars",
        "transport"
    ],
    "wof:name":"Vermant Nv",
    "wof:placetype":"venue"
},
  "geometry": {"coordinates":[4.3832921982,51.1108016968],"type":"Point"}
}