{
  "type": "Feature",
  "properties": {
    "iso:country":"BE",
    "sg:address":"Place Werth 4",
    "sg:city":"Eupen",
    "sg:orig_category":"V\u00eatements pour Dames. V\u00eatements pour Hommes. V\u00eatements pour b\u00e9b\u00e9s and enfants",
    "sg:phone":"+32 87 56 09 42",
    "sg:postcode":"4700",
    "sg:province":"Li\u00e8ge",
    "wof:name":"Esprit Shop",
    "wof:placetype":"venue"
},
  "geometry": {"coordinates":[6.0385270119,50.6328582764],"type":"Point"}
}