{
  "type": "Feature",
  "properties": {
    "iso:country":"BE",
    "sg:address":"Verdunstraat 277",
    "sg:city":"Brussel/bruxelles",
    "sg:orig_category":"Dranken Gh",
    "sg:phone":"+32 2 215 71 63",
    "sg:postcode":"1130",
    "sg:province":"Bruxelles-Capitale",
    "wof:name":"Vanbever",
    "wof:placetype":"venue"
},
  "geometry": {"coordinates":[4.4136152267,50.8885040283],"type":"Point"}
}