{
  "type": "Feature",
  "properties": {
    "addr:full":"Hansbekedorp 58 Nevele (hansbeke) Oost-Vlaanderen 9850",
    "addr:housenumber":"58",
    "addr:postcode":"9850",
    "addr:street":"Hansbekedorp",
    "iso:country":"BE",
    "sg:address":"Hansbekedorp 58",
    "sg:city":"Nevele (hansbeke)",
    "sg:classifiers":[
        {
            "category":"Health Services",
            "subcategory":"Doctor",
            "type":"Services"
        }
    ],
    "sg:phone":"+32 9 371 66 61",
    "sg:postcode":"9850",
    "sg:province":"Oost-Vlaanderen",
    "sg:tags":[
        "medicinephysicians",
        "surgeon"
    ],
    "wof:name":"Bing\u00e9 Luk",
    "wof:placetype":"venue"
},
  "geometry": {"coordinates":[3.5354530811,51.0765571594],"type":"Point"}
}