{
  "type": "Feature",
  "properties": {
    "iso:country":"BE",
    "sg:address":"Chauss\u00e9e De Vilvorde 140",
    "sg:city":"Bruxelles",
    "sg:classifiers":[
        {
            "category":"Autos & Motor Vehicles",
            "subcategory":"Fuel & Gas Station",
            "type":"Retail Goods"
        }
    ],
    "sg:phone":"+32 2 508 91 11",
    "sg:postcode":"1120",
    "sg:province":"Bruxelles-Capitale",
    "sg:tags":[
        "gas-l",
        "p-stations"
    ],
    "wof:name":"Shell Gas - Shell Gaz",
    "wof:placetype":"venue"
},
  "geometry": {"coordinates":[4.395524025,50.8919792175],"type":"Point"}
}