{
  "type": "Feature",
  "properties": {
    "iso:country":"BE",
    "sg:address":"Place De Pottes 24",
    "sg:city":"Celles (pottes)",
    "sg:classifiers":[
        {
            "category":"Food & Beverages",
            "subcategory":"Fruits & Vegetables",
            "type":"Retail Goods"
        }
    ],
    "sg:phone":"+32 69 45 43 63",
    "sg:postcode":"7760",
    "sg:province":"Hainaut",
    "sg:tags":[
        "-"
    ],
    "wof:name":"Pomme D'api",
    "wof:placetype":"venue"
},
  "geometry": {"coordinates":[3.4038751125,50.7304115295],"type":"Point"}
}