{
  "type": "Feature",
  "properties": {
    "addr:full":"Rue De La Barberie 111 Mouscron (herseaux) Hainaut 7712",
    "addr:housenumber":"111",
    "addr:postcode":"7712",
    "addr:street":"Rue De La Barberie",
    "iso:country":"BE",
    "sg:address":"Rue De La Barberie 111",
    "sg:city":"Mouscron (herseaux)",
    "sg:classifiers":[
        {
            "category":"Professional",
            "subcategory":"Art Services",
            "type":"Services"
        }
    ],
    "sg:phone":"+32 56 33 59 23",
    "sg:postcode":"7712",
    "sg:province":"Hainaut",
    "sg:tags":[
        "graphic",
        "designer"
    ],
    "wof:name":"Loiseau P",
    "wof:placetype":"venue"
},
  "geometry": {"coordinates":[3.240267992,50.7296333313],"type":"Point"}
}