{
  "type": "Feature",
  "properties": {
    "iso:country":"BE",
    "sg:address":"Orshagenstraat 11",
    "sg:city":"Heist-op-den-berg",
    "sg:classifiers":[
        {
            "category":"Personal",
            "type":"Services"
        }
    ],
    "sg:phone":"+32 15 24 30 90",
    "sg:postcode":"2220",
    "sg:province":"Antwerpen",
    "sg:tags":[
        "party",
        "planning"
    ],
    "wof:name":"Hof Van Riemen",
    "wof:placetype":"venue"
},
  "geometry": {"coordinates":[4.725880146,51.07006073],"type":"Point"}
}