{
  "type": "Feature",
  "properties": {
    "addr:full":"Boulevard Emile Bockstael 261 Brussel/bruxelles Bruxelles-Capitale 1020",
    "addr:housenumber":"261",
    "addr:postcode":"1020",
    "addr:street":"Boulevard Emile Bockstael;/",
    "iso:country":"BE",
    "sg:address":"Boulevard Emile Bockstael 261",
    "sg:city":"Brussel/bruxelles",
    "sg:orig_category":"Equipement photographique. Studios photographiques",
    "sg:phone":"+32 2 420 04 20",
    "sg:postcode":"1020",
    "sg:province":"Bruxelles-Capitale",
    "wof:name":"Amm Couleur Papier",
    "wof:placetype":"venue"
},
  "geometry": {"coordinates":[4.348004818,50.8796577454],"type":"Point"}
}