{
  "type": "Feature",
  "properties": {
    "addr:full":"Rynsackerstraat 40 Menen West-Vlaanderen 8930",
    "addr:housenumber":"40",
    "addr:postcode":"8930",
    "addr:street":"Rynsackerstraat",
    "iso:country":"BE",
    "sg:address":"Rynsackerstraat 40",
    "sg:city":"Menen",
    "sg:orig_category":"Eleveurs de bovins. Eleveurs and marchands de porcs",
    "sg:phone":"+32 56 51 21 70",
    "sg:postcode":"8930",
    "sg:province":"West-Vlaanderen",
    "wof:name":"Daniel Carbon",
    "wof:placetype":"venue"
},
  "geometry": {"coordinates":[3.1389639378,50.8115272522],"type":"Point"}
}