{
  "type": "Feature",
  "properties": {
    "iso:country":"BE",
    "sg:address":"Bosstraat 101",
    "sg:city":"Erpe-mere",
    "sg:orig_category":"Boomkwekerijen",
    "sg:phone":"+32 53 83 87 85",
    "sg:postcode":"9420",
    "sg:province":"Oost-Vlaanderen",
    "wof:name":"Ivan Walgraef",
    "wof:placetype":"venue"
},
  "geometry": {"coordinates":[3.9625029564,50.9254074097],"type":"Point"}
}