{
  "type": "Feature",
  "properties": {
    "iso:country":"BE",
    "sg:address":"Riddermoerstraat 30",
    "sg:city":"Bornem",
    "sg:orig_category":"Instituts pour adultes moins valides",
    "sg:phone":"+32 3 889 41 35",
    "sg:postcode":"2880",
    "sg:province":"Antwerpen",
    "wof:name":"Huize De Steiger",
    "wof:placetype":"venue"
},
  "geometry": {"coordinates":[4.2042088509,51.0773887634],"type":"Point"}
}