{
  "type": "Feature",
  "properties": {
    "addr:full":"Geneikenstraat 56 Lummen Limburg 3560",
    "addr:housenumber":"56",
    "addr:postcode":"3560",
    "addr:street":"Geneikenstraat",
    "iso:country":"BE",
    "sg:address":"Geneikenstraat 56",
    "sg:city":"Lummen",
    "sg:orig_category":"Non-Classified Establishments",
    "sg:phone":"+32 11 42 53 67",
    "sg:postcode":"3560",
    "sg:province":"Limburg",
    "wof:name":"Muba Nv",
    "wof:placetype":"venue"
},
  "geometry": {"coordinates":[5.2147231102,51.0176620483],"type":"Point"}
}