{
  "type": "Feature",
  "properties": {
    "addr:full":"Antwerpsestraat 344 Boom Antwerpen 2850",
    "addr:housenumber":"344",
    "addr:postcode":"2850",
    "addr:street":"Antwerpsestraat",
    "iso:country":"BE",
    "sg:address":"Antwerpsestraat 344",
    "sg:city":"Boom",
    "sg:classifiers":[
        {
            "category":"Personal",
            "subcategory":"Beauty Salon",
            "type":"Services"
        }
    ],
    "sg:phone":"+32 3 888 35 89",
    "sg:postcode":"2850",
    "sg:province":"Antwerpen",
    "sg:tags":[
        "de",
        "coiffure"
    ],
    "wof:name":"Coiffure Marleen",
    "wof:placetype":"venue"
},
  "geometry": {"coordinates":[4.3681077957,51.0991096497],"type":"Point"}
}