{
  "type": "Feature",
  "properties": {
    "addr:full":"Zoning De Wasmes Colfontaine (wasmes) Hainaut 7340",
    "addr:postcode":"7340",
    "addr:street":"Zoning De Wasmes",
    "iso:country":"BE",
    "sg:address":"Zoning De Wasmes",
    "sg:city":"Colfontaine (wasmes)",
    "sg:classifiers":[
        {
            "category":"Retail",
            "subcategory":"Auto Repair",
            "type":"Services"
        }
    ],
    "sg:phone":"+32 65 79 41 68",
    "sg:postcode":"7340",
    "sg:province":"Hainaut",
    "sg:tags":[
        "automobile-body"
    ],
    "wof:name":"Carrosserie Du Borinage",
    "wof:placetype":"venue"
},
  "geometry": {"coordinates":[3.8435599804,50.4226760864],"type":"Point"}
}