{
  "type": "Feature",
  "properties": {
    "addr:full":"Lippenslaan 385 Knokke-heist West-Vlaanderen 8300",
    "addr:housenumber":"385",
    "addr:postcode":"8300",
    "addr:street":"Lippenslaan",
    "iso:country":"BE",
    "sg:address":"Lippenslaan 385",
    "sg:city":"Knokke-heist",
    "sg:orig_category":"Pharmaciens",
    "sg:phone":"+32 50 60 11 42",
    "sg:postcode":"8300",
    "sg:province":"West-Vlaanderen",
    "wof:name":"Rudolf Verslype",
    "wof:placetype":"venue"
},
  "geometry": {"coordinates":[3.2882900238,51.3466911316],"type":"Point"}
}