{
  "type": "Feature",
  "properties": {
    "iso:country":"BE",
    "sg:address":"Statiestraat 48",
    "sg:city":"Antwerpen",
    "sg:orig_category":"Diverse intermediaire producten Gh Juwelen and horloges",
    "sg:phone":"+32 3 218 99 18",
    "sg:postcode":"2600",
    "sg:province":"Antwerpen",
    "wof:name":"Belgische Goudcentrale",
    "wof:placetype":"venue"
},
  "geometry": {"coordinates":[4.4196619987,51.2179756165],"type":"Point"}
}