{
  "type": "Feature",
  "properties": {
    "iso:country":"BE",
    "sg:address":"Margensault 35",
    "sg:city":"Thimister-clermont",
    "sg:orig_category":"Woningbouw",
    "sg:phone":"+32 87 44 53 91",
    "sg:postcode":"4890",
    "sg:province":"Li\u00e8ge",
    "wof:name":"Maxime Kroonen",
    "wof:placetype":"venue"
},
  "geometry": {"coordinates":[5.8630700111,50.6540870667],"type":"Point"}
}