{
  "type": "Feature",
  "properties": {
    "addr:full":"Chemin De La Plaine 62 Namur Namur 5001",
    "addr:housenumber":"62",
    "addr:postcode":"5001",
    "addr:street":"Chemin De La Plaine",
    "iso:country":"BE",
    "sg:address":"Chemin De La Plaine 62",
    "sg:city":"Namur",
    "sg:orig_category":"Sportclubs",
    "sg:phone":"+32 81 73 47 70",
    "sg:postcode":"5001",
    "sg:province":"Namur",
    "wof:name":"V.c. Belgrade",
    "wof:placetype":"venue"
},
  "geometry": {"coordinates":[4.8257050514,50.4722557068],"type":"Point"}
}