{
  "type": "Feature",
  "properties": {
    "iso:country":"BE",
    "sg:address":"Harelbeekstraat 30",
    "sg:city":"Zwevegem",
    "sg:orig_category":"Bloemen and planten",
    "sg:phone":"+32 56 75 42 87",
    "sg:postcode":"8550",
    "sg:province":"West-Vlaanderen",
    "wof:name":"Huis Decorte",
    "wof:placetype":"venue"
},
  "geometry": {"coordinates":[3.3317060471,50.8143081665],"type":"Point"}
}