{
  "type": "Feature",
  "properties": {
    "iso:country":"BE",
    "sg:address":"Paul Van Ostaijenstraat 34",
    "sg:city":"Zele",
    "sg:orig_category":"Kapsalons",
    "sg:phone":"+32 52 45 10 24",
    "sg:postcode":"9240",
    "sg:province":"Oost-Vlaanderen",
    "wof:name":"Coiffure Daisy",
    "wof:placetype":"venue"
},
  "geometry": {"coordinates":[4.0324239731,51.058013916],"type":"Point"}
}