{
  "type": "Feature",
  "properties": {
    "addr:full":"Rue L\u00c9opold 44 Li\u00c8ge Li\u00e8ge 4000",
    "addr:housenumber":"44",
    "addr:postcode":"4000",
    "addr:street":"Rue Le\u0301Opold",
    "iso:country":"BE",
    "sg:address":"Rue L\u00c9opold 44",
    "sg:city":"Li\u00c8ge",
    "sg:orig_category":"Pharmaciens",
    "sg:phone":"+32 4 223 08 74",
    "sg:postcode":"4000",
    "sg:province":"Li\u00e8ge",
    "wof:name":"Pharmacie Universelle",
    "wof:placetype":"venue"
},
  "geometry": {"coordinates":[5.5770730972,50.6439781189],"type":"Point"}
}