{
  "type": "Feature",
  "properties": {
    "addr:full":"Tichelrijstraat 1 Sint-truiden Limburg 3800",
    "addr:housenumber":"1",
    "addr:postcode":"3800",
    "addr:street":"Tichelrijstraat",
    "iso:country":"BE",
    "sg:address":"Tichelrijstraat 1",
    "sg:city":"Sint-truiden",
    "sg:classifiers":[
        {
            "category":"Insurance",
            "subcategory":"Life Insurance",
            "type":"Services"
        }
    ],
    "sg:phone":"+32 11 67 36 01",
    "sg:postcode":"3800",
    "sg:province":"Limburg",
    "sg:tags":[
        "assurance"
    ],
    "wof:name":"Bureau Vanschoenwinkel",
    "wof:placetype":"venue"
},
  "geometry": {"coordinates":[5.1913228035,50.8173103333],"type":"Point"}
}