{
  "type": "Feature",
  "properties": {
    "addr:full":"Vlootgracht 35 Lanaken (gellik) Limburg 3620",
    "addr:housenumber":"35",
    "addr:postcode":"3620",
    "addr:street":"Vlootgracht",
    "iso:country":"BE",
    "sg:address":"Vlootgracht 35",
    "sg:city":"Lanaken (gellik)",
    "sg:classifiers":[
        {
            "category":"Real Estate",
            "subcategory":"Architect",
            "type":"Services"
        }
    ],
    "sg:phone":"+32 89 71 39 07",
    "sg:postcode":"3620",
    "sg:province":"Limburg",
    "wof:name":"Schiepers M",
    "wof:placetype":"venue"
},
  "geometry": {"coordinates":[5.6551351547,50.8912277222],"type":"Point"}
}