{
  "type": "Feature",
  "properties": {
    "iso:country":"BE",
    "sg:address":"Hogestraat 54a",
    "sg:city":"Kortemark (werken)",
    "sg:classifiers":[
        {
            "category":"Personal",
            "subcategory":"Beauty Salon",
            "type":"Services"
        }
    ],
    "sg:phone":"+32 51 56 78 48",
    "sg:postcode":"8610",
    "sg:province":"West-Vlaanderen",
    "sg:tags":[
        "lady",
        "-",
        "hairdressing"
    ],
    "wof:name":"Josiane",
    "wof:placetype":"venue"
},
  "geometry": {"coordinates":[3.0078439713,51.0482139587],"type":"Point"}
}