{
  "type": "Feature",
  "properties": {
    "iso:country":"BE",
    "sg:address":"Molendreef 15",
    "sg:city":"Aarschot (rillaar)",
    "sg:classifiers":[
        {
            "category":"Retail",
            "subcategory":"Veterinary Services",
            "type":"Services"
        }
    ],
    "sg:phone":"+32 16 50 10 61",
    "sg:postcode":"3202",
    "sg:province":"Vlaams-Brabant",
    "sg:tags":[
        "veterinarian"
    ],
    "wof:name":"Demarsin P",
    "wof:placetype":"venue"
},
  "geometry": {"coordinates":[4.8971891403,50.9754714966],"type":"Point"}
}