{
  "type": "Feature",
  "properties": {
    "addr:full":"Vanneputstraat 2 Wevelgem West-Vlaanderen 8560",
    "addr:housenumber":"2",
    "addr:postcode":"8560",
    "addr:street":"Vanneputstraat",
    "iso:country":"BE",
    "sg:address":"Vanneputstraat 2",
    "sg:city":"Wevelgem",
    "sg:orig_category":"Traitements param\u00e9dicaux",
    "sg:phone":"+32 56 42 32 32",
    "sg:postcode":"8560",
    "sg:province":"West-Vlaanderen",
    "wof:name":"H. Calis",
    "wof:placetype":"venue"
},
  "geometry": {"coordinates":[3.1949601173,50.8240814209],"type":"Point"}
}