{
  "type": "Feature",
  "properties": {
    "iso:country":"BE",
    "sg:address":"Rue Du Biquet 10",
    "sg:city":"Oupeye",
    "sg:classifiers":[
        {
            "category":"Taxi",
            "type":"Transportation"
        }
    ],
    "sg:phone":"+32 4 342 30 30",
    "sg:postcode":"4680",
    "sg:province":"Li\u00e8ge",
    "wof:name":"Dometax",
    "wof:placetype":"venue"
},
  "geometry": {"coordinates":[5.6514902115,50.7092895508],"type":"Point"}
}