{
  "type": "Feature",
  "properties": {
    "iso:country":"BE",
    "sg:address":"Rue Neuve 25",
    "sg:city":"Gerpinnes",
    "sg:classifiers":[
        {
            "category":"Shopping",
            "subcategory":"Clothing, Apparel, & Fashions",
            "type":"Retail Goods"
        }
    ],
    "sg:phone":"+32 71 21 93 84",
    "sg:postcode":"6280",
    "sg:province":"Hainaut",
    "sg:tags":[
        "v\u00eatements",
        "pour",
        "dame"
    ],
    "wof:name":"Maison Intrigue",
    "wof:placetype":"venue"
},
  "geometry": {"coordinates":[4.4714012146,50.3442153931],"type":"Point"}
}