{
  "type": "Feature",
  "properties": {
    "iso:country":"BE",
    "sg:address":"Place Saint-antoine 46",
    "sg:city":"Bruxelles (etterbeek)",
    "sg:classifiers":[
        {
            "category":"Bakery",
            "type":"Food & Drink"
        }
    ],
    "sg:phone":"+32 2 644 08 81",
    "sg:postcode":"1040",
    "sg:province":"Bruxelles-Capitale",
    "sg:tags":[
        "confectioner",
        "baker"
    ],
    "wof:name":"Aux Pains Parisiens",
    "wof:placetype":"venue"
},
  "geometry": {"coordinates":[4.385863781,50.829826355],"type":"Point"}
}