{
  "type": "Feature",
  "properties": {
    "addr:full":"Sterrestraat 244 Lokeren Oost-Vlaanderen 9160",
    "addr:housenumber":"244",
    "addr:postcode":"9160",
    "addr:street":"Sterrestraat",
    "iso:country":"BE",
    "sg:address":"Sterrestraat 244",
    "sg:city":"Lokeren",
    "sg:orig_category":"Quincailleries",
    "sg:phone":"+32 55 36 99 89",
    "sg:postcode":"9160",
    "sg:province":"Oost-Vlaanderen",
    "wof:name":"De Clercq Luco",
    "wof:placetype":"venue"
},
  "geometry": {"coordinates":[3.9867770672,51.0920028687],"type":"Point"}
}