{
  "type": "Feature",
  "properties": {
    "iso:country":"BE",
    "sg:address":"Rue Sous-le-ch\u00e2teau 16",
    "sg:city":"Huy",
    "sg:classifiers":[
        {
            "category":"Shopping",
            "subcategory":"Jewelry",
            "type":"Retail Goods"
        }
    ],
    "sg:phone":"+32 85 21 79 69",
    "sg:postcode":"4500",
    "sg:province":"Li\u00e8ge",
    "sg:tags":[
        "jeweller",
        "-"
    ],
    "wof:name":"Gatot L",
    "wof:placetype":"venue"
},
  "geometry": {"coordinates":[5.2391138077,50.518081665],"type":"Point"}
}