{
  "type": "Feature",
  "properties": {
    "iso:country":"BE",
    "sg:address":"Rue Jean Volders 30",
    "sg:city":"Seraing",
    "sg:orig_category":"Gespecialiseerde residenti\u00eble bouw",
    "sg:phone":"+32 4 344 03 33",
    "sg:postcode":"4100",
    "sg:province":"Li\u00e8ge",
    "wof:name":"Bati-dry",
    "wof:placetype":"venue"
},
  "geometry": {"coordinates":[5.5135550499,50.5880393982],"type":"Point"}
}