{
  "type": "Feature",
  "properties": {
    "addr:full":"Bloemendalestraat 27 Beernem West-Vlaanderen 8730",
    "addr:housenumber":"27",
    "addr:postcode":"8730",
    "addr:street":"Bloemendalestraat",
    "iso:country":"BE",
    "sg:address":"Bloemendalestraat 27",
    "sg:city":"Beernem",
    "sg:orig_category":"Banques and organismes de cr\u00e9dit",
    "sg:phone":"+32 50 78 83 57",
    "sg:postcode":"8730",
    "sg:province":"West-Vlaanderen",
    "wof:name":"Kbc",
    "wof:placetype":"venue"
},
  "geometry": {"coordinates":[3.3397059441,51.141456604],"type":"Point"}
}