{
  "type": "Feature",
  "properties": {
    "iso:country":"BE",
    "sg:address":"Markt 67",
    "sg:city":"Deinze",
    "sg:classifiers":[
        {
            "category":"Personal",
            "subcategory":"Beauty Salon",
            "type":"Services"
        }
    ],
    "sg:phone":"+32 9 386 91 65",
    "sg:postcode":"9800",
    "sg:province":"Oost-Vlaanderen",
    "sg:tags":[
        "de",
        "coiffure"
    ],
    "wof:name":"Hairclub Dirk De Witte",
    "wof:placetype":"venue"
},
  "geometry": {"coordinates":[3.5262539387,50.9855384827],"type":"Point"}
}