{
  "type": "Feature",
  "properties": {
    "addr:full":"Weg Naar Opoeteren 1 Meeuwen-gruitrode Limburg 3670",
    "addr:housenumber":"1",
    "addr:postcode":"3670",
    "addr:street":"Weg Naar Opoeteren",
    "iso:country":"BE",
    "sg:address":"Weg Naar Opoeteren 1",
    "sg:city":"Meeuwen-gruitrode",
    "sg:classifiers":[
        {
            "category":"Restaurant",
            "type":"Food & Drink"
        }
    ],
    "sg:phone":"+32 89 85 33 29",
    "sg:postcode":"3670",
    "sg:province":"Limburg",
    "wof:name":"Eethuis Martine",
    "wof:placetype":"venue"
},
  "geometry": {"coordinates":[5.6187372208,51.0884246826],"type":"Point"}
}