{
  "type": "Feature",
  "properties": {
    "iso:country":"BE",
    "sg:address":"Guldensporenlaan 101",
    "sg:city":"Houthalen-helchteren",
    "sg:orig_category":"Boekhouders",
    "sg:phone":"+32 11 52 57 70",
    "sg:postcode":"3530",
    "sg:province":"Limburg",
    "wof:name":"M.r. Vanderhallen",
    "wof:placetype":"venue"
},
  "geometry": {"coordinates":[5.3607602119,51.0417327881],"type":"Point"}
}