{
  "type": "Feature",
  "properties": {
    "addr:full":"Gistelsesteenweg 1 Oostende West-Vlaanderen 8400",
    "addr:housenumber":"1",
    "addr:postcode":"8400",
    "addr:street":"Gistelsesteenweg",
    "iso:country":"BE",
    "sg:address":"Gistelsesteenweg 1",
    "sg:city":"Oostende",
    "sg:classifiers":[
        {
            "category":"Sports & Exercise",
            "subcategory":"Ice Rink",
            "type":"Entertainment"
        }
    ],
    "sg:phone":"+32 59 56 58 65",
    "sg:postcode":"8400",
    "sg:province":"West-Vlaanderen",
    "sg:tags":[
        "skating"
    ],
    "wof:name":"Satellite",
    "wof:placetype":"venue"
},
  "geometry": {"coordinates":[2.9262011051,51.2159461975],"type":"Point"}
}