{
  "type": "Feature",
  "properties": {
    "iso:country":"BE",
    "sg:address":"Washingtonstraat 44",
    "sg:city":"Elsene/ixelles",
    "sg:orig_category":"Immobili\u00ebnkantoren",
    "sg:phone":"+32 2 649 30 60",
    "sg:postcode":"1050",
    "sg:province":"Bruxelles-Capitale",
    "wof:name":"Terfimmo",
    "wof:placetype":"venue"
},
  "geometry": {"coordinates":[4.3634171486,50.8250541687],"type":"Point"}
}