{
  "type": "Feature",
  "properties": {
    "iso:country":"BE",
    "sg:address":"Rue Louvrex 55-57",
    "sg:city":"Li\u00e8ge 1",
    "sg:classifiers":[
        {
            "category":"Professional",
            "subcategory":"Lawyer & Legal Services",
            "type":"Services"
        }
    ],
    "sg:phone":"+32 4 220 03 03",
    "sg:postcode":"4000",
    "sg:province":"Li\u00e8ge",
    "wof:name":"Babilone P",
    "wof:placetype":"venue"
},
  "geometry": {"coordinates":[5.5638508797,50.6355895996],"type":"Point"}
}