{
  "type": "Feature",
  "properties": {
    "iso:country":"BE",
    "sg:address":"Schansstraat 30",
    "sg:city":"Halen (zelem)",
    "sg:classifiers":[
        {
            "category":"Wholesale",
            "subcategory":"Machinery & Supplies",
            "type":"Manufacturing & Wholesale Goods"
        }
    ],
    "sg:phone":"+32 13 46 26 36",
    "sg:postcode":"3545",
    "sg:province":"Limburg",
    "sg:tags":[
        "refrigeration",
        "-",
        "industrial",
        "commercial",
        "equipment"
    ],
    "wof:name":"Gsf Bvba",
    "wof:placetype":"venue"
},
  "geometry": {"coordinates":[5.1108078957,50.9748420715],"type":"Point"}
}