{
  "type": "Feature",
  "properties": {
    "addr:full":"Rooigemlaan 324 Gent Oost-Vlaanderen 9000",
    "addr:housenumber":"324",
    "addr:postcode":"9000",
    "addr:street":"Rooigemlaan;Oost-Vlaanderen",
    "iso:country":"BE",
    "sg:address":"Rooigemlaan 324",
    "sg:city":"Gent",
    "sg:orig_category":"Installation de menuiserie en bois and plastique. Organisation de salons, expositions and bourses",
    "sg:phone":"+32 9 226 45 45",
    "sg:postcode":"9000",
    "sg:province":"Oost-Vlaanderen",
    "wof:name":"Publiganda",
    "wof:placetype":"venue"
},
  "geometry": {"coordinates":[3.6932229996,51.0597267151],"type":"Point"}
}