{
  "type": "Feature",
  "properties": {
    "addr:full":"Kleitkalseide 6 A Maldegem Oost-Vlaanderen 9990",
    "addr:housenumber":"6 a",
    "addr:postcode":"9990",
    "addr:street":"Kleitkalseide",
    "iso:country":"BE",
    "sg:address":"Kleitkalseide 6 A",
    "sg:city":"Maldegem",
    "sg:orig_category":"Tuinbenodigdheden Tuinen",
    "sg:phone":"+32 50 71 57 09",
    "sg:postcode":"9990",
    "sg:province":"Oost-Vlaanderen",
    "wof:name":"Nautilus",
    "wof:placetype":"venue"
},
  "geometry": {"coordinates":[3.4540579319,51.1924972534],"type":"Point"}
}