{
  "type": "Feature",
  "properties": {
    "iso:country":"BE",
    "sg:address":"Potteriestraat 44",
    "sg:city":"Zonnebeke (beselare)",
    "sg:classifiers":[
        {
            "category":"Home & Garden",
            "subcategory":"Building Materials",
            "type":"Retail Goods"
        }
    ],
    "sg:phone":"+32 57 46 69 30",
    "sg:postcode":"8980",
    "sg:province":"West-Vlaanderen",
    "sg:tags":[
        "house"
    ],
    "wof:name":"Verma Bvba",
    "wof:placetype":"venue"
},
  "geometry": {"coordinates":[2.9872550964,50.8730812073],"type":"Point"}
}