{
  "type": "Feature",
  "properties": {
    "iso:country":"BE",
    "sg:address":"Rue De Reumont 11",
    "sg:city":"Thuin",
    "sg:orig_category":"Afval and schroot Gh",
    "sg:phone":"+32 71 59 30 49",
    "sg:postcode":"6536",
    "sg:province":"Hainaut",
    "wof:name":"Marcel Fourmeau",
    "wof:placetype":"venue"
},
  "geometry": {"coordinates":[4.3267512321,50.3231811523],"type":"Point"}
}