{
  "type": "Feature",
  "properties": {
    "iso:country":"BE",
    "sg:address":"Avenue Des Ch\u00canes 164",
    "sg:city":"Ukkel/uccle",
    "sg:orig_category":"Eclairage et \u00e9quipements du foyer",
    "sg:phone":"+32 2 374 66 59",
    "sg:postcode":"1180",
    "sg:province":"Bruxelles-Capitale",
    "wof:name":"Zebra",
    "wof:placetype":"venue"
},
  "geometry": {"coordinates":[4.3798189163,50.7947807312],"type":"Point"}
}