{
  "type": "Feature",
  "properties": {
    "iso:country":"BE",
    "sg:address":"Notelaarstraat 8",
    "sg:city":"Scherpenheuvel-zichem",
    "sg:orig_category":"Woningbouw",
    "sg:phone":"+32 13 77 23 86",
    "sg:postcode":"3271",
    "sg:province":"Vlaams-Brabant",
    "wof:name":"Karel Adriaensen",
    "wof:placetype":"venue"
},
  "geometry": {"coordinates":[4.9544978142,50.9985809326],"type":"Point"}
}