{
  "type": "Feature",
  "properties": {
    "iso:country":"BE",
    "sg:address":"Kerkstraat 109",
    "sg:city":"Temse",
    "sg:orig_category":"V\u00e9t\u00e9rinaires",
    "sg:phone":"+32 3 711 05 58",
    "sg:postcode":"9140",
    "sg:province":"Oost-Vlaanderen",
    "wof:name":"Peter Mijten",
    "wof:placetype":"venue"
},
  "geometry": {"coordinates":[4.1753540039,51.1202430725],"type":"Point"}
}