{
  "type": "Feature",
  "properties": {
    "addr:full":"Turnhoutsebaan 342 Schilde Antwerpen 2970",
    "addr:housenumber":"342",
    "addr:postcode":"2970",
    "addr:street":"Turnhoutsebaan",
    "iso:country":"BE",
    "sg:address":"Turnhoutsebaan 342",
    "sg:city":"Schilde",
    "sg:classifiers":[
        {
            "category":"Professional",
            "subcategory":"Art Services",
            "type":"Services"
        }
    ],
    "sg:phone":"+32 3 383 25 58",
    "sg:postcode":"2970",
    "sg:province":"Antwerpen",
    "sg:tags":[
        "photography",
        "reporting",
        "-"
    ],
    "wof:name":"Het Fotoatelier",
    "wof:placetype":"venue"
},
  "geometry": {"coordinates":[4.5859088898,51.2417144775],"type":"Point"}
}