{
  "type": "Feature",
  "properties": {
    "iso:country":"BE",
    "sg:address":"Letterbeekstraat 14",
    "sg:city":"Gooik",
    "sg:orig_category":"Maisons de repos and r\u00e9sidences",
    "sg:phone":"+32 54 56 60 70",
    "sg:postcode":"1755",
    "sg:province":"Vlaams-Brabant",
    "wof:name":"Rusthuis Strijland",
    "wof:placetype":"venue"
},
  "geometry": {"coordinates":[4.0906200409,50.7967414856],"type":"Point"}
}