{
  "type": "Feature",
  "properties": {
    "addr:full":"Warande 27 Ieper (elverdinge) West-Vlaanderen 8906",
    "addr:housenumber":"27",
    "addr:postcode":"8906",
    "addr:street":"Warande",
    "iso:country":"BE",
    "sg:address":"Warande 27",
    "sg:city":"Ieper (elverdinge)",
    "sg:classifiers":[
        {
            "category":"Health Services",
            "subcategory":"Nursing And Care Facility",
            "type":"Services"
        }
    ],
    "sg:phone":"+32 57 42 30 50",
    "sg:postcode":"8906",
    "sg:province":"West-Vlaanderen",
    "sg:tags":[
        "home"
    ],
    "wof:name":"Canniere R",
    "wof:placetype":"venue"
},
  "geometry": {"coordinates":[2.8208010197,50.8813209534],"type":"Point"}
}