{
  "type": "Feature",
  "properties": {
    "iso:country":"BE",
    "sg:address":"Langendonkstraat 16",
    "sg:city":"Beernem",
    "sg:orig_category":"Varkenskwekers",
    "sg:phone":"+32 50 79 02 54",
    "sg:postcode":"8730",
    "sg:province":"West-Vlaanderen",
    "wof:name":"Rik Gantois",
    "wof:placetype":"venue"
},
  "geometry": {"coordinates":[3.3851089478,51.1339874268],"type":"Point"}
}