{
  "type": "Feature",
  "properties": {
    "iso:country":"BE",
    "sg:address":"Rue Saint-leger 42",
    "sg:city":"Profondeville",
    "sg:orig_category":"Epiceries",
    "sg:phone":"+32 81 41 30 33",
    "sg:postcode":"5170",
    "sg:province":"Namur",
    "wof:name":"Maison Dochain",
    "wof:placetype":"venue"
},
  "geometry": {"coordinates":[4.8990650177,50.3784103394],"type":"Point"}
}