{
  "type": "Feature",
  "properties": {
    "iso:country":"BE",
    "sg:address":"Rue Monrose 65",
    "sg:city":"Schaarbeek/schaerbeek",
    "sg:orig_category":"R\u00e9paration and restauration de meubles",
    "sg:phone":"+32 2 242 54 43",
    "sg:postcode":"1030",
    "sg:province":"Bruxelles-Capitale",
    "wof:name":"Atelier Garnissage",
    "wof:placetype":"venue"
},
  "geometry": {"coordinates":[4.3794760704,50.8567657471],"type":"Point"}
}