{
  "type": "Feature",
  "properties": {
    "addr:full":"Leuvensesteenweg 219 Tielt-winge (tielt) Vlaams-Brabant 3390",
    "addr:housenumber":"219",
    "addr:postcode":"3390",
    "addr:street":"Leuvensesteenweg",
    "iso:country":"BE",
    "sg:address":"Leuvensesteenweg 219",
    "sg:city":"Tielt-winge (tielt)",
    "sg:classifiers":[
        {
            "category":"Autos & Motor Vehicles",
            "subcategory":"Automobile Sales",
            "type":"Retail Goods"
        }
    ],
    "sg:phone":"+32 16 63 33 00",
    "sg:postcode":"3390",
    "sg:province":"Vlaams-Brabant",
    "sg:tags":[
        "car",
        "used",
        "-"
    ],
    "wof:name":"Leuven Motors Nv",
    "wof:placetype":"venue"
},
  "geometry": {"coordinates":[4.8686699867,50.9063339233],"type":"Point"}
}