{
  "type": "Feature",
  "properties": {
    "addr:full":"Basiliekstraat 64 Halle Vlaams-Brabant 1500",
    "addr:housenumber":"64",
    "addr:postcode":"1500",
    "addr:street":"Basiliekstraat",
    "iso:country":"BE",
    "sg:address":"Basiliekstraat 64",
    "sg:city":"Halle",
    "sg:orig_category":"Vedior. Agences d\u00b4interim and personnel temporaire",
    "sg:phone":"+32 2 362 04 30",
    "sg:postcode":"1500",
    "sg:province":"Vlaams-Brabant",
    "wof:name":"Vedior Interim",
    "wof:placetype":"venue"
},
  "geometry": {"coordinates":[4.2356548309,50.7345275879],"type":"Point"}
}