{
  "type": "Feature",
  "properties": {
    "addr:full":"Avenue Des Belettes 19 Bruxelles (uccle) Bruxelles-Capitale 1180",
    "addr:housenumber":"19",
    "addr:postcode":"1180",
    "addr:street":"Avenue Des Belettes",
    "iso:country":"BE",
    "sg:address":"Avenue Des Belettes 19",
    "sg:city":"Bruxelles (uccle)",
    "sg:classifiers":[
        {
            "category":"Personal",
            "subcategory":"Nail Salon",
            "type":"Services"
        }
    ],
    "sg:phone":"+32 2 375 49 70",
    "sg:postcode":"1180",
    "sg:province":"Bruxelles-Capitale",
    "sg:tags":[
        "pedicure"
    ],
    "wof:name":"Vanherenthals M-j",
    "wof:placetype":"venue"
},
  "geometry": {"coordinates":[4.3438539505,50.7770805359],"type":"Point"}
}