{
  "type": "Feature",
  "properties": {
    "addr:full":"Champs Elys\u00e9es 4 Ciney Namur 5590",
    "addr:housenumber":"4",
    "addr:postcode":"5590",
    "addr:street":"Elyse\u0301Es",
    "iso:country":"BE",
    "sg:address":"Champs Elys\u00e9es 4",
    "sg:city":"Ciney",
    "sg:classifiers":[
        {
            "category":"Farming",
            "subcategory":"Livestock Farm",
            "type":"Manufacturing & Wholesale Goods"
        }
    ],
    "sg:phone":"+32 83 23 06 21",
    "sg:postcode":"5590",
    "sg:province":"Namur",
    "sg:tags":[
        "breeding"
    ],
    "wof:name":"Linalux-ger",
    "wof:placetype":"venue"
},
  "geometry": {"coordinates":[5.0996251106,50.3148384094],"type":"Point"}
}