{
  "type": "Feature",
  "properties": {
    "addr:full":"Boulevard Gustave-kleyer 87 Li\u00e8ge 1 Li\u00e8ge 4000",
    "addr:housenumber":"87;1",
    "addr:postcode":"4000",
    "addr:street":"Boulevard Gustave-Kleyer",
    "iso:country":"BE",
    "sg:address":"Boulevard Gustave-kleyer 87",
    "sg:city":"Li\u00e8ge 1",
    "sg:classifiers":[
        {
            "category":"Autos & Motor Vehicles",
            "subcategory":"Auto Supplies",
            "type":"Retail Goods"
        }
    ],
    "sg:phone":"+32 4 253 11 53",
    "sg:postcode":"4000",
    "sg:province":"Li\u00e8ge",
    "sg:tags":[
        "automobile",
        "absorber",
        "shock",
        "-"
    ],
    "wof:name":"A.t.p. Center Sprl",
    "wof:placetype":"venue"
},
  "geometry": {"coordinates":[5.5495510101,50.6252822876],"type":"Point"}
}