{
  "type": "Feature",
  "properties": {
    "iso:country":"BE",
    "sg:address":"Kleine Hemmenweg 40",
    "sg:city":"Zonhoven",
    "sg:classifiers":[
        {
            "category":"Health Services",
            "subcategory":"Health Practitioner",
            "type":"Services"
        }
    ],
    "sg:phone":"+32 11 81 85 30",
    "sg:postcode":"3520",
    "sg:province":"Limburg",
    "sg:tags":[
        "physiotherapist"
    ],
    "wof:name":"Marx Koen",
    "wof:placetype":"venue"
},
  "geometry": {"coordinates":[5.3767127991,50.9976081848],"type":"Point"}
}