{
  "type": "Feature",
  "properties": {
    "iso:country":"BE",
    "sg:address":"Rue Fosty 103",
    "sg:city":"Genappe",
    "sg:orig_category":"Paramedische behandelingen Schoonheidssalons",
    "sg:phone":"+32 67 78 00 41",
    "sg:postcode":"1470",
    "sg:province":"Brabant Wallon",
    "wof:name":"Marie-claude Cornelis",
    "wof:placetype":"venue"
},
  "geometry": {"coordinates":[4.5032172203,50.5986213684],"type":"Point"}
}