{
  "type": "Feature",
  "properties": {
    "iso:country":"BE",
    "sg:address":"Av Louise 419",
    "sg:city":"Bruxelles",
    "sg:classifiers":[
        {
            "category":"Shopping",
            "subcategory":"Clothing, Apparel, & Fashions",
            "type":"Retail Goods"
        }
    ],
    "sg:phone":"+32 2 639 14 40",
    "sg:postcode":"1050",
    "sg:province":"Bruxelles-Capitale",
    "sg:tags":[
        "textile",
        "clothing",
        "clothes"
    ],
    "wof:name":"Oldiland Sa",
    "wof:placetype":"venue"
},
  "geometry": {"coordinates":[4.3706979752,50.818939209],"type":"Point"}
}