{
  "type": "Feature",
  "properties": {
    "iso:country":"BE",
    "sg:address":"Schaarbeekstraat 40a",
    "sg:city":"Beveren (melsele)",
    "sg:classifiers":[
        {
            "category":"Building & Trades",
            "subcategory":"Pest Control",
            "type":"Services"
        }
    ],
    "sg:phone":"+32 3 250 11 95",
    "sg:postcode":"9120",
    "sg:province":"Oost-Vlaanderen",
    "sg:tags":[
        "painting",
        "contractor"
    ],
    "wof:name":"Cools Hans",
    "wof:placetype":"venue"
},
  "geometry": {"coordinates":[4.313849926,51.2020988464],"type":"Point"}
}