{
  "type": "Feature",
  "properties": {
    "addr:full":"Wellingstraat 42 Destelbergen (heusden) Oost-Vlaanderen 9070",
    "addr:housenumber":"42",
    "addr:postcode":"9070",
    "addr:street":"Wellingstraat",
    "iso:country":"BE",
    "sg:address":"Wellingstraat 42",
    "sg:city":"Destelbergen (heusden)",
    "sg:classifiers":[
        {
            "category":"Health Services",
            "subcategory":"Doctor",
            "type":"Services"
        }
    ],
    "sg:phone":"+32 9 232 44 38",
    "sg:postcode":"9070",
    "sg:province":"Oost-Vlaanderen",
    "sg:tags":[
        "medicinephysicians",
        "surgeon"
    ],
    "wof:name":"Donck J",
    "wof:placetype":"venue"
},
  "geometry": {"coordinates":[3.7974629402,51.0230674744],"type":"Point"}
}