{
  "type": "Feature",
  "properties": {
    "addr:full":"26 Rue Des Trois Entites 4890 Thimister-clermont 26",
    "addr:housenumber":"26;26",
    "addr:postcode":"4890",
    "addr:street":"Rue Des Trois Entites",
    "iso:country":"BE",
    "sg:address":"26",
    "sg:city":"Rue Des Trois Entites 4890 Thimister-clermont",
    "sg:classifiers":[
        {
            "category":"Professional",
            "type":"Services"
        }
    ],
    "sg:phone":"+32 87 44 01 00",
    "sg:postcode":"26",
    "sg:tags":[
        "transport",
        "road"
    ],
    "wof:name":"Transports Lambert Freres Sa",
    "wof:placetype":"venue"
},
  "geometry": {"coordinates":[5.8855748177,50.6361160278],"type":"Point"}
}