{
  "type": "Feature",
  "properties": {
    "iso:country":"BE",
    "sg:address":"Kamershoek 219",
    "sg:city":"Zele",
    "sg:orig_category":"Metaalvrije afvalrecyclage",
    "sg:phone":"+32 52 42 39 32",
    "sg:postcode":"9240",
    "sg:province":"Oost-Vlaanderen",
    "wof:name":"Van Assche & Zoon",
    "wof:placetype":"venue"
},
  "geometry": {"coordinates":[4.0085840225,51.0393371582],"type":"Point"}
}