{
  "type": "Feature",
  "properties": {
    "iso:country":"BE",
    "sg:address":"Rue Paul Pastur 29",
    "sg:city":"Ath",
    "sg:classifiers":[
        {
            "category":"Arena",
            "subcategory":"Sports Club",
            "type":"Entertainment"
        }
    ],
    "sg:phone":"+32 68 28 43 54",
    "sg:postcode":"7800",
    "sg:province":"Hainaut",
    "sg:tags":[
        "de"
    ],
    "wof:name":"R.t.c. Ath",
    "wof:placetype":"venue"
},
  "geometry": {"coordinates":[3.7736079693,50.62159729],"type":"Point"}
}