{
  "type": "Feature",
  "properties": {
    "addr:full":"Warnach 17ba Fauvillers Luxembourg 6637",
    "addr:postcode":"6637",
    "addr:street":"Warnach",
    "iso:country":"BE",
    "sg:address":"Warnach 17ba",
    "sg:city":"Fauvillers",
    "sg:orig_category":"Eleveurs de bovins",
    "sg:phone":"+32 63 60 06 95",
    "sg:postcode":"6637",
    "sg:province":"Luxembourg",
    "wof:name":"Stephane Meyer",
    "wof:placetype":"venue"
},
  "geometry": {"coordinates":[5.7244701385,49.8651008606],"type":"Point"}
}