{
  "type": "Feature",
  "properties": {
    "addr:full":"Emiel Lossystraat 60 Gent Oost-Vlaanderen 9040",
    "addr:housenumber":"60",
    "addr:postcode":"9040",
    "addr:street":"Emiel Lossystraat;Oost-Vlaanderen",
    "iso:country":"BE",
    "sg:address":"Emiel Lossystraat 60",
    "sg:city":"Gent",
    "sg:orig_category":"M\u00e9decins and sp\u00e9cialistes",
    "sg:phone":"+32 9 228 25 28",
    "sg:postcode":"9040",
    "sg:province":"Oost-Vlaanderen",
    "wof:name":"Sorgeloose",
    "wof:placetype":"venue"
},
  "geometry": {"coordinates":[3.759319067,51.0498809814],"type":"Point"}
}