{
  "type": "Feature",
  "properties": {
    "addr:full":"Rue De La Croix 8 Namur Namur 5000",
    "addr:housenumber":"8",
    "addr:postcode":"5000",
    "addr:street":"Rue De La Croix",
    "iso:country":"BE",
    "sg:address":"Rue De La Croix 8",
    "sg:city":"Namur",
    "sg:orig_category":"Juwelen and horloges",
    "sg:phone":"+32 81 22 56 29",
    "sg:postcode":"5000",
    "sg:province":"Namur",
    "wof:name":"Maison Turquoise",
    "wof:placetype":"venue"
},
  "geometry": {"coordinates":[4.8651151657,50.4637260437],"type":"Point"}
}