{
  "type": "Feature",
  "properties": {
    "addr:full":"Kleppestraat 46 Moorslede (dadizele) West-Vlaanderen 8890",
    "addr:housenumber":"46",
    "addr:postcode":"8890",
    "addr:street":"Kleppestraat",
    "iso:country":"BE",
    "sg:address":"Kleppestraat 46",
    "sg:city":"Moorslede (dadizele)",
    "sg:classifiers":[
        {
            "category":"Shopping",
            "subcategory":"Pets & Pet Supplies",
            "type":"Retail Goods"
        }
    ],
    "sg:phone":"+32 56 50 25 70",
    "sg:postcode":"8890",
    "sg:province":"West-Vlaanderen",
    "sg:tags":[
        "shop",
        "-"
    ],
    "wof:name":"Duponzoo Bvba",
    "wof:placetype":"venue"
},
  "geometry": {"coordinates":[3.1015329361,50.8510627747],"type":"Point"}
}