{
  "type": "Feature",
  "properties": {
    "iso:country":"BE",
    "sg:address":"Berkenhagestraat 1",
    "sg:city":"Zedelgem",
    "sg:orig_category":"Openbare veiligheid",
    "sg:phone":"+32 50 20 05 00",
    "sg:postcode":"8210",
    "sg:province":"West-Vlaanderen",
    "wof:name":"Federale Politie",
    "wof:placetype":"venue"
},
  "geometry": {"coordinates":[3.1374700069,51.1409072876],"type":"Point"}
}