{
  "type": "Feature",
  "properties": {
    "iso:country":"BE",
    "sg:address":"Route De Saint-g\u00e9rard 132",
    "sg:city":"Namur (w\u00e9pion)",
    "sg:classifiers":[
        {
            "category":"Bars & Pubs",
            "type":"Food & Drink"
        }
    ],
    "sg:phone":"+32 81 46 01 90",
    "sg:postcode":"5100",
    "sg:province":"Namur",
    "wof:name":"Carrefour (taverne Du)",
    "wof:placetype":"venue"
},
  "geometry": {"coordinates":[4.8631868362,50.4212379456],"type":"Point"}
}