{
  "type": "Feature",
  "properties": {
    "addr:full":"Avenue Emile Vandervelde 118 Chatelet Hainaut 6200",
    "addr:housenumber":"118",
    "addr:postcode":"chatelet;6200",
    "addr:street":"Avenue Emile Vandervelde",
    "iso:country":"BE",
    "sg:address":"Avenue Emile Vandervelde 118",
    "sg:city":"Chatelet",
    "sg:orig_category":"Traitements param\u00e9dicaux",
    "sg:phone":"+32 71 38 65 80",
    "sg:postcode":"6200",
    "sg:province":"Hainaut",
    "wof:name":"M.cl. Chapeau",
    "wof:placetype":"venue"
},
  "geometry": {"coordinates":[4.5205302238,50.396320343],"type":"Point"}
}