{
  "type": "Feature",
  "properties": {
    "addr:full":"Rue De La Cath\u00c9drale 84-86 Liege Li\u00e8ge 4000",
    "addr:housenumber":"84-86",
    "addr:postcode":"4000",
    "addr:street":"Rue De La Cathe\u0301Drale",
    "iso:country":"BE",
    "sg:address":"Rue De La Cath\u00c9drale 84-86",
    "sg:city":"Liege",
    "sg:orig_category":"Graphologues, astrologues, voyants and radiesth\u00e9sistes",
    "sg:phone":"+32 4 232 17 17",
    "sg:postcode":"4000",
    "sg:province":"Li\u00e8ge",
    "wof:name":"Dacx G",
    "wof:placetype":"venue"
},
  "geometry": {"coordinates":[5.5730991364,50.6420021057],"type":"Point"}
}