{
  "type": "Feature",
  "properties": {
    "addr:full":"Kloosterstraat 85 Zedelgem (veldegem) West-Vlaanderen 8210",
    "addr:housenumber":"85",
    "addr:postcode":"8210",
    "addr:street":"Kloosterstraat",
    "iso:country":"BE",
    "sg:address":"Kloosterstraat 85",
    "sg:city":"Zedelgem (veldegem)",
    "sg:classifiers":[
        {
            "category":"Shopping",
            "subcategory":"Crafts & Fabrics",
            "type":"Retail Goods"
        }
    ],
    "sg:phone":"+32 50 27 76 00",
    "sg:postcode":"8210",
    "sg:province":"West-Vlaanderen",
    "sg:tags":[
        "silk",
        "-"
    ],
    "wof:name":"Maelfait P",
    "wof:placetype":"venue"
},
  "geometry": {"coordinates":[3.1458399296,51.1376457214],"type":"Point"}
}