{
  "type": "Feature",
  "properties": {
    "iso:country":"BE",
    "sg:address":"Pijpestraat 7",
    "sg:city":"Spiere-helkijn/espierres-helchin",
    "sg:orig_category":"Slagers",
    "sg:phone":"+32 56 45 53 81",
    "sg:postcode":"8587",
    "sg:province":"West-Vlaanderen",
    "wof:name":"G Deffromont",
    "wof:placetype":"venue"
},
  "geometry": {"coordinates":[3.3462240696,50.7341880798],"type":"Point"}
}