{
  "type": "Feature",
  "properties": {
    "addr:full":"Sleidinge Dorp 67 Evergem (sleidinge) Oost-Vlaanderen 9940",
    "addr:housenumber":"67",
    "addr:postcode":"9940",
    "addr:street":"Dorp",
    "iso:country":"BE",
    "sg:address":"Sleidinge Dorp 67",
    "sg:city":"Evergem (sleidinge)",
    "sg:classifiers":[
        {
            "category":"Shopping",
            "subcategory":"Shoes",
            "type":"Retail Goods"
        }
    ],
    "sg:phone":"+32 9 357 40 74",
    "sg:postcode":"9940",
    "sg:province":"Oost-Vlaanderen",
    "sg:tags":[
        "slipper",
        "-"
    ],
    "wof:name":"Lybaert L",
    "wof:placetype":"venue"
},
  "geometry": {"coordinates":[3.6797420979,51.1345596313],"type":"Point"}
}