{
  "type": "Feature",
  "properties": {
    "addr:full":"Galerie Louise 43 Bruxelles (ixelles) Bruxelles-Capitale 1050",
    "addr:housenumber":"43",
    "addr:postcode":"1050",
    "iso:country":"BE",
    "sg:address":"Galerie Louise 43",
    "sg:city":"Bruxelles (ixelles)",
    "sg:classifiers":[
        {
            "category":"Real Estate",
            "subcategory":"Real Estate Services",
            "type":"Services"
        }
    ],
    "sg:phone":"+32 2 375 79 89",
    "sg:postcode":"1050",
    "sg:province":"Bruxelles-Capitale",
    "wof:name":"Propri\u00e9t\u00e9s Priv\u00e9es",
    "wof:placetype":"venue"
},
  "geometry": {"coordinates":[4.3569221497,50.836025238],"type":"Point"}
}