{
  "type": "Feature",
  "properties": {
    "iso:country":"BE",
    "sg:address":"Ezaart 5",
    "sg:city":"Mol",
    "sg:classifiers":[
        {
            "category":"Building & Trades",
            "subcategory":"Locksmith",
            "type":"Services"
        }
    ],
    "sg:phone":"+32 14 31 26 08",
    "sg:postcode":"2400",
    "sg:province":"Antwerpen",
    "sg:tags":[
        "lock",
        "key"
    ],
    "wof:name":"K & S Security",
    "wof:placetype":"venue"
},
  "geometry": {"coordinates":[5.1018919945,51.1803016663],"type":"Point"}
}