{
  "type": "Feature",
  "properties": {
    "addr:full":"Mollekestraat 1 Wellen Limburg 3830",
    "addr:housenumber":"1",
    "addr:postcode":"3830",
    "addr:street":"Mollekestraat",
    "iso:country":"BE",
    "sg:address":"Mollekestraat 1",
    "sg:city":"Wellen",
    "sg:orig_category":"Sportclubs",
    "sg:phone":"+32 12 74 38 27",
    "sg:postcode":"3830",
    "sg:province":"Limburg",
    "wof:name":"D.c. Free",
    "wof:placetype":"venue"
},
  "geometry": {"coordinates":[5.3593740463,50.8378219604],"type":"Point"}
}