{
  "type": "Feature",
  "properties": {
    "iso:country":"BE",
    "sg:address":"Lindendreef 29",
    "sg:city":"Hoogstraten",
    "sg:classifiers":[
        {
            "category":"Arts & Performance",
            "subcategory":"Music",
            "type":"Entertainment"
        }
    ],
    "sg:phone":"+32 3 314 75 35",
    "sg:postcode":"2320",
    "sg:province":"Antwerpen",
    "sg:tags":[
        "disc-jockeys"
    ],
    "wof:name":"Palladium Deejay-team",
    "wof:placetype":"venue"
},
  "geometry": {"coordinates":[4.7663578987,51.4013252258],"type":"Point"}
}