{
  "type": "Feature",
  "properties": {
    "iso:country":"BE",
    "sg:address":"Rue Du Zoning 1",
    "sg:city":"Tinlot (soheit-tinlot)",
    "sg:classifiers":[
        {
            "category":"Utilities",
            "subcategory":"Natural Gas",
            "type":"Services"
        }
    ],
    "sg:phone":"+32 85 82 88 00",
    "sg:postcode":"4557",
    "sg:province":"Li\u00e8ge",
    "sg:tags":[
        "industrial",
        "-"
    ],
    "wof:name":"F4m Cryoservice Bv",
    "wof:placetype":"venue"
},
  "geometry": {"coordinates":[5.3835048676,50.4731216431],"type":"Point"}
}