{
  "type": "Feature",
  "properties": {
    "iso:country":"BE",
    "sg:address":"Buntstraat 53a",
    "sg:city":"Hamme",
    "sg:classifiers":[
        {
            "category":"Ice Cream",
            "type":"Food & Drink"
        }
    ],
    "sg:phone":"+32 52 47 80 67",
    "sg:postcode":"9220",
    "sg:province":"Oost-Vlaanderen",
    "wof:name":"Van Peteghem A",
    "wof:placetype":"venue"
},
  "geometry": {"coordinates":[4.1457791328,51.1004180908],"type":"Point"}
}