{
  "type": "Feature",
  "properties": {
    "iso:country":"BE",
    "sg:address":"Ieperstraat 50",
    "sg:city":"Poperinge",
    "sg:orig_category":"V\u00eatements pour b\u00e9b\u00e9s and enfants",
    "sg:phone":"+32 57 33 68 30",
    "sg:postcode":"8970",
    "sg:province":"West-Vlaanderen",
    "wof:name":"Huis Kid'z",
    "wof:placetype":"venue"
},
  "geometry": {"coordinates":[2.7296440601,50.8543205261],"type":"Point"}
}