{
  "type": "Feature",
  "properties": {
    "addr:full":"Kapelstraat 44 Hove Antwerpen 2540",
    "addr:housenumber":"44",
    "addr:postcode":"2540",
    "addr:street":"Kapelstraat",
    "iso:country":"BE",
    "sg:address":"Kapelstraat 44",
    "sg:city":"Hove",
    "sg:classifiers":[
        {
            "category":"Wholesale",
            "subcategory":"Beer",
            "type":"Manufacturing & Wholesale Goods"
        }
    ],
    "sg:phone":"+32 3 455 24 84",
    "sg:postcode":"2540",
    "sg:province":"Antwerpen",
    "sg:tags":[
        "ale",
        "-"
    ],
    "wof:name":"Huybrechts J Bvba",
    "wof:placetype":"venue"
},
  "geometry": {"coordinates":[4.4680299759,51.1545219421],"type":"Point"}
}