{
  "type": "Feature",
  "properties": {
    "addr:full":"Rue Forestiere 22 Elsene/ixelles Bruxelles-Capitale 1050",
    "addr:housenumber":"22",
    "addr:postcode":"1050",
    "addr:street":"Rue Forestiere",
    "iso:country":"BE",
    "sg:address":"Rue Forestiere 22",
    "sg:city":"Elsene/ixelles",
    "sg:orig_category":"M\u00e9decins and sp\u00e9cialistes",
    "sg:phone":"+32 2 649 68 95",
    "sg:postcode":"1050",
    "sg:province":"Bruxelles-Capitale",
    "wof:name":"Michel De Cordier",
    "wof:placetype":"venue"
},
  "geometry": {"coordinates":[4.3652257919,50.8220558167],"type":"Point"}
}