{
  "type": "Feature",
  "properties": {
    "addr:full":"Gentweg 56 Kaprijke Oost-Vlaanderen 9971",
    "addr:housenumber":"56",
    "addr:postcode":"9971",
    "addr:street":"Gentweg",
    "iso:country":"BE",
    "sg:address":"Gentweg 56",
    "sg:city":"Kaprijke",
    "sg:orig_category":"Serres and speciale beglazing",
    "sg:phone":"+32 9 377 23 02",
    "sg:postcode":"9971",
    "sg:province":"Oost-Vlaanderen",
    "wof:name":"Willemen",
    "wof:placetype":"venue"
},
  "geometry": {"coordinates":[3.6375870705,51.1939163208],"type":"Point"}
}