{
  "type": "Feature",
  "properties": {
    "iso:country":"BE",
    "sg:address":"Leopold Iii-straat 13",
    "sg:city":"Kortessem (vliermaal)",
    "sg:classifiers":[
        {
            "category":"Bakery",
            "type":"Food & Drink"
        }
    ],
    "sg:phone":"+32 12 23 19 82",
    "sg:postcode":"3724",
    "sg:province":"Limburg",
    "sg:tags":[
        "confectioner",
        "baker"
    ],
    "wof:name":"Albert Bvba",
    "wof:placetype":"venue"
},
  "geometry": {"coordinates":[5.4299330711,50.8401794434],"type":"Point"}
}