{
  "type": "Feature",
  "properties": {
    "iso:country":"BE",
    "sg:address":"Grande Terre 8",
    "sg:city":"Limbourg",
    "sg:orig_category":"Eleveurs de bovins",
    "sg:phone":"+32 87 76 24 35",
    "sg:postcode":"4831",
    "sg:province":"Li\u00e8ge",
    "wof:name":"Philippe Bauduin",
    "wof:placetype":"venue"
},
  "geometry": {"coordinates":[5.9258999825,50.6229782104],"type":"Point"}
}