{
  "type": "Feature",
  "properties": {
    "addr:full":"Cokaifagne 60 Jalhay (sart) Li\u00e8ge 4845",
    "addr:housenumber":"60",
    "addr:postcode":"4845",
    "addr:street":"Cokaifagne;Sart Lie\u0300Ge",
    "iso:country":"BE",
    "sg:address":"Cokaifagne 60",
    "sg:city":"Jalhay (sart)",
    "sg:classifiers":[
        {
            "category":"Retail",
            "subcategory":"Veterinary Services",
            "type":"Services"
        }
    ],
    "sg:phone":"+32 87 47 51 83",
    "sg:postcode":"4845",
    "sg:province":"Li\u00e8ge",
    "sg:tags":[
        "veterinarian"
    ],
    "wof:name":"Caudron I",
    "wof:placetype":"venue"
},
  "geometry": {"coordinates":[5.9643888474,50.4882850647],"type":"Point"}
}