{
  "type": "Feature",
  "properties": {
    "iso:country":"BE",
    "sg:address":"Ambachtelijke Zone De Waerde",
    "sg:city":"Zonhoven",
    "sg:orig_category":"IJzerwaren, bouw- and verfmaterialen Metalen and ertsen Gh",
    "sg:phone":"+32 11 81 35 70",
    "sg:postcode":"3520",
    "sg:province":"Limburg",
    "wof:name":"V.d.r. Industrieletoelevering",
    "wof:placetype":"venue"
},
  "geometry": {"coordinates":[5.3816299438,51.0015068054],"type":"Point"}
}