{
  "type": "Feature",
  "properties": {
    "iso:country":"BE",
    "sg:address":"Rue Dewez 41",
    "sg:city":"Namur",
    "sg:orig_category":"Artsen and specialisten",
    "sg:phone":"+32 81 22 79 57",
    "sg:postcode":"5000",
    "sg:province":"Namur",
    "wof:name":"Jacques Dulieu",
    "wof:placetype":"venue"
},
  "geometry": {"coordinates":[4.8691530228,50.468132019],"type":"Point"}
}