{
  "type": "Feature",
  "properties": {
    "iso:country":"BE",
    "sg:address":"Hernestraat 4",
    "sg:city":"Galmaarden",
    "sg:orig_category":"Installation de menuiserie en bois and plastique",
    "sg:phone":"+32 54 58 81 44",
    "sg:postcode":"1570",
    "sg:province":"Vlaams-Brabant",
    "wof:name":"Johnny Tresinie",
    "wof:placetype":"venue"
},
  "geometry": {"coordinates":[4.0075111389,50.7410202026],"type":"Point"}
}