{
  "type": "Feature",
  "properties": {
    "iso:country":"BE",
    "sg:address":"Voorstraat 44",
    "sg:city":"Kaprijke",
    "sg:orig_category":"Slagers",
    "sg:phone":"+32 9 373 71 71",
    "sg:postcode":"9970",
    "sg:province":"Oost-Vlaanderen",
    "wof:name":"Gilbert Boelens",
    "wof:placetype":"venue"
},
  "geometry": {"coordinates":[3.61156106,51.2179031372],"type":"Point"}
}