{
  "type": "Feature",
  "properties": {
    "iso:country":"BE",
    "sg:address":"Stapelhuisstraat 3",
    "sg:city":"Leuven",
    "sg:classifiers":[
        {
            "category":"Professional",
            "subcategory":"Accounting & Tax Preparation",
            "type":"Services"
        }
    ],
    "sg:phone":"+32 16 20 29 59",
    "sg:postcode":"3000",
    "sg:province":"Vlaams-Brabant",
    "sg:tags":[
        "cupola",
        "-",
        "skylight"
    ],
    "wof:name":"Bouwglas Van Velthem Bvba",
    "wof:placetype":"venue"
},
  "geometry": {"coordinates":[4.7053470612,50.8865280151],"type":"Point"}
}