{
  "type": "Feature",
  "properties": {
    "iso:country":"BE",
    "sg:address":"Rue De L'ecluse 40",
    "sg:city":"Haccourt",
    "sg:classifiers":[
        {
            "category":"Manufacturing",
            "subcategory":"Building Materials",
            "type":"Manufacturing & Wholesale Goods"
        }
    ],
    "sg:phone":"+32 4 379 99 11",
    "sg:postcode":"4684",
    "sg:province":"Li\u00e8ge",
    "sg:tags":[
        "cement"
    ],
    "wof:name":"Ciments De Haccourt S.a.",
    "wof:placetype":"venue"
},
  "geometry": {"coordinates":[5.6747322083,50.7398414612],"type":"Point"}
}