{
  "type": "Feature",
  "properties": {
    "addr:full":"Rue Du Poirier 4 Ottignies-louvain-la-neuve (louvain-la-neuve) Brabant Wallon 1348",
    "addr:housenumber":"4",
    "addr:postcode":"1348",
    "addr:street":"Rue Du Poirier",
    "iso:country":"BE",
    "sg:address":"Rue Du Poirier 4",
    "sg:city":"Ottignies-louvain-la-neuve (louvain-la-neuve)",
    "sg:classifiers":[
        {
            "category":"Real Estate",
            "subcategory":"Architect",
            "type":"Services"
        }
    ],
    "sg:phone":"+32 10 45 18 00",
    "sg:postcode":"1348",
    "sg:province":"Brabant Wallon",
    "wof:name":"Van Hove J-l",
    "wof:placetype":"venue"
},
  "geometry": {"coordinates":[4.6207752228,50.6700439453],"type":"Point"}
}