{
  "type": "Feature",
  "properties": {
    "addr:full":"Leuvensebaan 40 Putte Antwerpen 2580",
    "addr:housenumber":"40",
    "addr:postcode":"2580",
    "addr:street":"Leuvensebaan",
    "iso:country":"BE",
    "sg:address":"Leuvensebaan 40",
    "sg:city":"Putte",
    "sg:orig_category":"Diverse bedrijfsbeheeradviesbureaus",
    "sg:phone":"+32 15 75 75 25",
    "sg:postcode":"2580",
    "sg:province":"Antwerpen",
    "wof:name":"Derom Alin",
    "wof:placetype":"venue"
},
  "geometry": {"coordinates":[4.6294379234,51.0520896912],"type":"Point"}
}