{
  "type": "Feature",
  "properties": {
    "addr:full":"Chenestre 13 Dalhem (saint-andr\u00e9) Li\u00e8ge 4606",
    "addr:housenumber":"13",
    "addr:postcode":"4606",
    "addr:street":"Chenestre",
    "iso:country":"BE",
    "sg:address":"Chenestre 13",
    "sg:city":"Dalhem (saint-andr\u00e9)",
    "sg:classifiers":[
        {
            "category":"Structure",
            "subcategory":"Office Building",
            "type":"Public Place"
        }
    ],
    "sg:phone":"+32 4 379 83 03",
    "sg:postcode":"4606",
    "sg:province":"Li\u00e8ge",
    "sg:tags":[
        "drawing"
    ],
    "wof:name":"Malpas A",
    "wof:placetype":"venue"
},
  "geometry": {"coordinates":[5.7336258888,50.7086791992],"type":"Point"}
}