{
  "type": "Feature",
  "properties": {
    "iso:country":"BE",
    "sg:address":"Stationsstraat 43",
    "sg:city":"Merchtem",
    "sg:orig_category":"Enseignement secondaire technique and professionnel",
    "sg:phone":"+32 52 37 16 47",
    "sg:postcode":"1785",
    "sg:province":"Vlaams-Brabant",
    "wof:name":"Gem.techn. En Beroepssch.",
    "wof:placetype":"venue"
},
  "geometry": {"coordinates":[4.2273359299,50.9579467773],"type":"Point"}
}