{
  "type": "Feature",
  "properties": {
    "iso:country":"BE",
    "sg:address":"Baasrodestraat 6",
    "sg:city":"Dendermonde",
    "sg:orig_category":"Artistes ind\u00e9pendants",
    "sg:phone":"+32 52 33 27 10",
    "sg:postcode":"9200",
    "sg:province":"Oost-Vlaanderen",
    "wof:name":"Tieleman",
    "wof:placetype":"venue"
},
  "geometry": {"coordinates":[4.0983099937,51.0315208435],"type":"Point"}
}