{
  "type": "Feature",
  "properties": {
    "iso:country":"BE",
    "sg:address":"Hoogeind 128",
    "sg:city":"Stabroek",
    "sg:classifiers":[
        {
            "category":"Building & Trades",
            "subcategory":"Construction",
            "type":"Services"
        }
    ],
    "sg:phone":"+32 3 568 75 53",
    "sg:postcode":"2940",
    "sg:province":"Antwerpen",
    "sg:tags":[
        "truss-makers"
    ],
    "wof:name":"Van Den Broucke Orthese Bvba",
    "wof:placetype":"venue"
},
  "geometry": {"coordinates":[4.3850708008,51.3409156799],"type":"Point"}
}