{
  "type": "Feature",
  "properties": {
    "addr:full":"Chauss\u00e9e De Binche 101a Mons Hainaut 7000",
    "addr:housenumber":"101a",
    "addr:postcode":"7000",
    "addr:street":"Chausse\u0301E De Binche;Hainaut",
    "iso:country":"BE",
    "sg:address":"Chauss\u00e9e De Binche 101a",
    "sg:city":"Mons",
    "sg:classifiers":[
        {
            "category":"Real Estate",
            "subcategory":"Architect",
            "type":"Services"
        }
    ],
    "sg:phone":"+32 65 35 17 69",
    "sg:postcode":"7000",
    "sg:province":"Hainaut",
    "wof:name":"Saintenois J-p",
    "wof:placetype":"venue"
},
  "geometry": {"coordinates":[3.9737520218,50.4527206421],"type":"Point"}
}