{
  "type": "Feature",
  "properties": {
    "iso:country":"BE",
    "sg:address":"Rue Malevez 38",
    "sg:city":"Namur",
    "sg:classifiers":[
        {
            "category":"Recreation",
            "type":"Entertainment"
        }
    ],
    "sg:phone":"+32 81 74 04 84",
    "sg:postcode":"5002",
    "sg:province":"Namur",
    "sg:tags":[
        "diver",
        "amusement"
    ],
    "wof:name":"Private Dance Organ.",
    "wof:placetype":"venue"
},
  "geometry": {"coordinates":[4.8462319374,50.4782791138],"type":"Point"}
}