{
  "type": "Feature",
  "properties": {
    "addr:full":"Rue De Gen\u00e8ve 117 Box 6 Bruxelles (evere) Bruxelles-Capitale 1140",
    "addr:housenumber":"117;6",
    "addr:postcode":"1140",
    "addr:street":"Rue De Gene\u0300Ve;Box",
    "iso:country":"BE",
    "sg:address":"Rue De Gen\u00e8ve 117 Box 6",
    "sg:city":"Bruxelles (evere)",
    "sg:classifiers":[
        {
            "category":"Health Services",
            "subcategory":"Dentist",
            "type":"Services"
        }
    ],
    "sg:phone":"+32 2 705 46 08",
    "sg:postcode":"1140",
    "sg:province":"Bruxelles-Capitale",
    "wof:name":"Daou H. Charles",
    "wof:placetype":"venue"
},
  "geometry": {"coordinates":[4.4039769173,50.8608894348],"type":"Point"}
}