{
  "type": "Feature",
  "properties": {
    "addr:full":"Boshuis 5 Tessenderlo Limburg 3980",
    "addr:housenumber":"5",
    "addr:postcode":"3980",
    "addr:street":"Boshuis",
    "iso:country":"BE",
    "sg:address":"Boshuis 5",
    "sg:city":"Tessenderlo",
    "sg:orig_category":"Gespecialiseerde residenti\u00eble bouw",
    "sg:phone":"+32 13 66 17 30",
    "sg:postcode":"3980",
    "sg:province":"Limburg",
    "wof:name":"Jan Theys",
    "wof:placetype":"venue"
},
  "geometry": {"coordinates":[5.0699429512,51.056476593],"type":"Point"}
}