{
  "type": "Feature",
  "properties": {
    "iso:country":"BE",
    "sg:address":"De Bosschaertstraat 141",
    "sg:city":"Antwerpen",
    "sg:classifiers":[
        {
            "category":"Social Services",
            "type":"Services"
        }
    ],
    "sg:phone":"+32 3 825 33 31",
    "sg:postcode":"2020",
    "sg:province":"Antwerpen",
    "wof:name":"Geef Om Te Leven Vzw",
    "wof:placetype":"venue"
},
  "geometry": {"coordinates":[4.3820838928,51.1873855591],"type":"Point"}
}