{
  "type": "Feature",
  "properties": {
    "iso:country":"BE",
    "sg:address":"Westlaan 17",
    "sg:city":"Roeselare",
    "sg:orig_category":"Agences d\u00b4interim and personnel temporaire",
    "sg:phone":"+32 51 24 40 60",
    "sg:postcode":"8800",
    "sg:province":"West-Vlaanderen",
    "wof:name":"Inter Office Select",
    "wof:placetype":"venue"
},
  "geometry": {"coordinates":[3.1197810173,50.9364471436],"type":"Point"}
}