{
  "type": "Feature",
  "properties": {
    "addr:full":"Schoolstraat 53 Sint-truiden Limburg 3800",
    "addr:housenumber":"53",
    "addr:postcode":"3800",
    "addr:street":"Schoolstraat",
    "iso:country":"BE",
    "sg:address":"Schoolstraat 53",
    "sg:city":"Sint-truiden",
    "sg:classifiers":[
        {
            "category":"Real Estate",
            "subcategory":"Architect",
            "type":"Services"
        }
    ],
    "sg:phone":"+32 11 68 68 06",
    "sg:postcode":"3800",
    "sg:province":"Limburg",
    "wof:name":"Paternotte B",
    "wof:placetype":"venue"
},
  "geometry": {"coordinates":[5.2130742073,50.8364562988],"type":"Point"}
}