{
  "type": "Feature",
  "properties": {
    "iso:country":"BE",
    "sg:address":"Avenue De L'ind\u00c9pendance Belge 104",
    "sg:city":"Koekelberg",
    "sg:orig_category":"R\u00e9parations d'appareils \u00e9lectrom\u00e9nagers",
    "sg:phone":"+32 2 415 83 14",
    "sg:postcode":"1081",
    "sg:province":"Bruxelles-Capitale",
    "wof:name":"Provid\u00c9o Service",
    "wof:placetype":"venue"
},
  "geometry": {"coordinates":[4.31833601,50.8633117676],"type":"Point"}
}