{
  "type": "Feature",
  "properties": {
    "addr:full":"Ganzendries 51 Gent Oost-Vlaanderen 9000",
    "addr:housenumber":"51",
    "addr:postcode":"9000",
    "addr:street":"Ganzendries;Oost-Vlaanderen",
    "iso:country":"BE",
    "sg:address":"Ganzendries 51",
    "sg:city":"Gent",
    "sg:orig_category":"Experts-comptables",
    "sg:phone":"+32 9 221 61 26",
    "sg:postcode":"9000",
    "sg:province":"Oost-Vlaanderen",
    "wof:name":"Johan Van De Kerchove",
    "wof:placetype":"venue"
},
  "geometry": {"coordinates":[3.7117450237,51.031917572],"type":"Point"}
}