{
  "type": "Feature",
  "properties": {
    "addr:full":"Koekoekstraat 50 Schelle Antwerpen 2627",
    "addr:housenumber":"50",
    "addr:postcode":"2627",
    "addr:street":"Koekoekstraat",
    "iso:country":"BE",
    "sg:address":"Koekoekstraat 50",
    "sg:city":"Schelle",
    "sg:classifiers":[
        {
            "category":"Retail",
            "subcategory":"Animal Services",
            "type":"Services"
        }
    ],
    "sg:phone":"+32 475 27 37 57",
    "sg:postcode":"2627",
    "sg:province":"Antwerpen",
    "sg:tags":[
        "farrier"
    ],
    "wof:name":"Van Assche F",
    "wof:placetype":"venue"
},
  "geometry": {"coordinates":[4.3651299477,51.1175384521],"type":"Point"}
}