{
  "type": "Feature",
  "properties": {
    "iso:country":"BE",
    "sg:address":"Chauss\u00e9e De Louvain 59-63",
    "sg:city":"Namur",
    "sg:classifiers":[
        {
            "category":"Utilities",
            "subcategory":"Water",
            "type":"Services"
        }
    ],
    "sg:phone":"+32 81 25 76 75",
    "sg:postcode":"5000",
    "sg:province":"Namur",
    "sg:tags":[
        "distribution"
    ],
    "wof:name":"Aquawal",
    "wof:placetype":"venue"
},
  "geometry": {"coordinates":[4.8670282364,50.4711494446],"type":"Point"}
}