{
  "type": "Feature",
  "properties": {
    "iso:country":"BE",
    "sg:address":"W Van Doornyckstraat 64",
    "sg:city":"Beveren",
    "sg:orig_category":"Fleurs and plantes",
    "sg:phone":"+32 3 755 18 01",
    "sg:postcode":"9120",
    "sg:province":"Oost-Vlaanderen",
    "wof:name":"Iris Bloemen",
    "wof:placetype":"venue"
},
  "geometry": {"coordinates":[4.2342219353,51.1799240112],"type":"Point"}
}