{
  "type": "Feature",
  "properties": {
    "addr:full":"La Coul\u00c9e 9 Malmedy/malmedy Li\u00e8ge 4960",
    "addr:housenumber":"9",
    "addr:postcode":"4960",
    "addr:street":"La Coule\u0301E",
    "iso:country":"BE",
    "sg:address":"La Coul\u00c9e 9",
    "sg:city":"Malmedy/malmedy",
    "sg:orig_category":"Quincailleries. Bois Gr",
    "sg:phone":"+32 80 57 00 77",
    "sg:postcode":"4960",
    "sg:province":"Li\u00e8ge",
    "wof:name":"Paul Blaise & Fils",
    "wof:placetype":"venue"
},
  "geometry": {"coordinates":[6.0528330803,50.3777770996],"type":"Point"}
}