{
  "type": "Feature",
  "properties": {
    "addr:full":"Sint-maartenstraat 58 Leuven Vlaams-Brabant 3000",
    "addr:housenumber":"58",
    "addr:postcode":"3000",
    "addr:street":"Sint-Maartenstraat",
    "iso:country":"BE",
    "sg:address":"Sint-maartenstraat 58",
    "sg:city":"Leuven",
    "sg:orig_category":"Advocaten and juridische adviseurs",
    "sg:phone":"+32 16 22 63 16",
    "sg:postcode":"3000",
    "sg:province":"Vlaams-Brabant",
    "wof:name":"V. Boesmans",
    "wof:placetype":"venue"
},
  "geometry": {"coordinates":[4.7030391693,50.8847198486],"type":"Point"}
}