{
  "type": "Feature",
  "properties": {
    "iso:country":"BE",
    "sg:address":"Rue De Marchovelette 1",
    "sg:city":"Namur",
    "sg:orig_category":"Cr\u00e9dits divers",
    "sg:postcode":"5000",
    "sg:province":"Namur",
    "wof:name":"Bancontact-mister Cash",
    "wof:placetype":"venue"
},
  "geometry": {"coordinates":[4.8674678802,50.462802887],"type":"Point"}
}