{
  "type": "Feature",
  "properties": {
    "addr:full":"Havermarkt 14 Hasselt Limburg 3500",
    "addr:housenumber":"14",
    "addr:postcode":"3500",
    "addr:street":"Havermarkt",
    "iso:country":"BE",
    "sg:address":"Havermarkt 14",
    "sg:city":"Hasselt",
    "sg:orig_category":"Antiek Boekhandels Tweedehandsgoederen",
    "sg:phone":"+32 11 22 74 00",
    "sg:postcode":"3500",
    "sg:province":"Limburg",
    "wof:name":"De Sleghte",
    "wof:placetype":"venue"
},
  "geometry": {"coordinates":[5.3355150223,50.9291496277],"type":"Point"}
}