{
  "type": "Feature",
  "properties": {
    "iso:country":"BE",
    "sg:address":"Chauss\u00c9e De Mons 187",
    "sg:city":"Ath",
    "sg:orig_category":"R\u00e9parations d'appareils \u00e9lectrom\u00e9nagers. Electrom\u00e9nager, t\u00e9l\u00e9visions and radios",
    "sg:phone":"+32 68 28 10 95",
    "sg:postcode":"7800",
    "sg:province":"Hainaut",
    "wof:name":"Ets. Coquereau",
    "wof:placetype":"venue"
},
  "geometry": {"coordinates":[3.7801508904,50.6215286255],"type":"Point"}
}