{
  "type": "Feature",
  "properties": {
    "addr:full":"Kapelsesteenweg 403 Box 1 Antwerpen (ekeren) Antwerpen 2180",
    "addr:housenumber":"403;1",
    "addr:postcode":"2180",
    "addr:street":"Kapelsesteenweg;Box",
    "iso:country":"BE",
    "sg:address":"Kapelsesteenweg 403 Box 1",
    "sg:city":"Antwerpen (ekeren)",
    "sg:classifiers":[
        {
            "category":"Shopping",
            "subcategory":"Baby Store",
            "type":"Retail Goods"
        }
    ],
    "sg:phone":"+32 3 644 16 24",
    "sg:postcode":"2180",
    "sg:province":"Antwerpen",
    "sg:tags":[
        "-",
        "accessory"
    ],
    "wof:name":"Amedee & Junior",
    "wof:placetype":"venue"
},
  "geometry": {"coordinates":[4.4586000443,51.2716217041],"type":"Point"}
}