{
  "type": "Feature",
  "properties": {
    "addr:full":"Rue Du Pont 35 Hamoir Li\u00e8ge 4180",
    "addr:housenumber":"35",
    "addr:postcode":"4180",
    "addr:street":"Rue Du Pont",
    "iso:country":"BE",
    "sg:address":"Rue Du Pont 35",
    "sg:city":"Hamoir",
    "sg:orig_category":"Location de cassettes vid\u00e9o and audio. Electrom\u00e9nager, t\u00e9l\u00e9visions and radios",
    "sg:phone":"+32 86 38 90 23",
    "sg:postcode":"4180",
    "sg:province":"Li\u00e8ge",
    "wof:name":"Video Cd-video",
    "wof:placetype":"venue"
},
  "geometry": {"coordinates":[5.5336370468,50.4263114929],"type":"Point"}
}