{
  "type": "Feature",
  "properties": {
    "addr:full":"Avenue De La Braban\u00c7onne 100 Schaarbeek/schaerbeek Bruxelles-Capitale 1030",
    "addr:housenumber":"100",
    "addr:postcode":"1030",
    "addr:street":"Avenue De La Brabanc\u0327Onne",
    "iso:country":"BE",
    "sg:address":"Avenue De La Braban\u00c7onne 100",
    "sg:city":"Schaarbeek/schaerbeek",
    "sg:orig_category":"Entretien and r\u00e9parations de voitures",
    "sg:phone":"+32 2 733 94 24",
    "sg:postcode":"1030",
    "sg:province":"Bruxelles-Capitale",
    "wof:name":"Auto Lavage De Prestige",
    "wof:placetype":"venue"
},
  "geometry": {"coordinates":[4.3870410919,50.8516197205],"type":"Point"}
}