{
  "type": "Feature",
  "properties": {
    "addr:full":"Deerlijkstraat 21 Zwevegem West-Vlaanderen 8550",
    "addr:housenumber":"21",
    "addr:postcode":"8550",
    "addr:street":"Deerlijkstraat",
    "iso:country":"BE",
    "sg:address":"Deerlijkstraat 21",
    "sg:city":"Zwevegem",
    "sg:classifiers":[
        {
            "category":"Home & Garden",
            "subcategory":"Home Furnishings",
            "type":"Retail Goods"
        }
    ],
    "sg:phone":"+32 56 75 79 17",
    "sg:postcode":"8550",
    "sg:province":"West-Vlaanderen",
    "sg:tags":[
        "decoration"
    ],
    "wof:name":"Kreatief",
    "wof:placetype":"venue"
},
  "geometry": {"coordinates":[3.3346230984,50.8148155212],"type":"Point"}
}