{
  "type": "Feature",
  "properties": {
    "addr:full":"Industrielaan 31 Ieper West-Vlaanderen 8900",
    "addr:housenumber":"31",
    "addr:postcode":"8900",
    "addr:street":"Industrielaan",
    "iso:country":"BE",
    "sg:address":"Industrielaan 31",
    "sg:city":"Ieper",
    "sg:classifiers":[
        {
            "category":"Professional",
            "subcategory":"Computer Services",
            "type":"Services"
        }
    ],
    "sg:phone":"+32 57 21 38 24",
    "sg:postcode":"8900",
    "sg:province":"West-Vlaanderen",
    "sg:tags":[
        "-",
        "processing",
        "data",
        "software"
    ],
    "wof:name":"Cypresoft Bvba",
    "wof:placetype":"venue"
},
  "geometry": {"coordinates":[2.8878269196,50.8513641357],"type":"Point"}
}