{
  "type": "Feature",
  "properties": {
    "iso:country":"BE",
    "sg:address":"La Forge 6",
    "sg:city":"Onhaye",
    "sg:classifiers":[
        {
            "category":"Social Services",
            "subcategory":"Job Training",
            "type":"Services"
        }
    ],
    "sg:phone":"+32 82 69 91 36",
    "sg:postcode":"5522",
    "sg:province":"Namur",
    "sg:tags":[
        "de",
        "terrain",
        "camping"
    ],
    "wof:name":"Camping De La Forge",
    "wof:placetype":"venue"
},
  "geometry": {"coordinates":[4.8091020584,50.2925987244],"type":"Point"}
}