{
  "type": "Feature",
  "properties": {
    "iso:country":"BE",
    "sg:address":"Lammerdries 21bb",
    "sg:city":"Olen",
    "sg:orig_category":"Plaatsen van vloer- and muurbekleding Schilders",
    "sg:phone":"+32 14 22 10 02",
    "sg:postcode":"2250",
    "sg:province":"Antwerpen",
    "wof:name":"M.i.s.s.",
    "wof:placetype":"venue"
},
  "geometry": {"coordinates":[4.9147100449,51.1488685608],"type":"Point"}
}