{
  "type": "Feature",
  "properties": {
    "addr:full":"Afrikaansestraat 60 Sint-gillis/saint-gilles Bruxelles-Capitale 1060",
    "addr:housenumber":"60",
    "addr:postcode":"1060",
    "addr:street":"Afrikaansestraat",
    "iso:country":"BE",
    "sg:address":"Afrikaansestraat 60",
    "sg:city":"Sint-gillis/saint-gilles",
    "sg:classifiers":[
        {
            "category":"Professional",
            "subcategory":"Accounting & Tax Preparation",
            "type":"Services"
        }
    ],
    "sg:phone":"+32 2 534 73 26",
    "sg:postcode":"1060",
    "sg:province":"Bruxelles-Capitale",
    "sg:tags":[
        "accountant"
    ],
    "wof:name":"C.d.c.",
    "wof:placetype":"venue"
},
  "geometry": {"coordinates":[4.3559441566,50.8240699768],"type":"Point"}
}