{
  "type": "Feature",
  "properties": {
    "iso:country":"BE",
    "sg:address":"Rue Principale 61",
    "sg:city":"Raeren",
    "sg:classifiers":[
        {
            "category":"Insurance",
            "subcategory":"Life Insurance",
            "type":"Services"
        }
    ],
    "sg:phone":"+32 87 85 02 50",
    "sg:postcode":"4730",
    "sg:province":"Li\u00e8ge",
    "sg:tags":[
        "assurance"
    ],
    "wof:name":"Brandt Versicherungen",
    "wof:placetype":"venue"
},
  "geometry": {"coordinates":[6.1169581413,50.6716804504],"type":"Point"}
}