{
  "type": "Feature",
  "properties": {
    "iso:country":"BE",
    "sg:address":"Munkendoornstraat 101",
    "sg:city":"Kortrijk",
    "sg:classifiers":[
        {
            "category":"Cafe",
            "type":"Food & Drink"
        }
    ],
    "sg:phone":"+32 56 21 41 14",
    "sg:postcode":"8510",
    "sg:province":"West-Vlaanderen",
    "sg:tags":[
        "caf\u00e9s"
    ],
    "wof:name":"Bernard Bille",
    "wof:placetype":"venue"
},
  "geometry": {"coordinates":[3.2728800774,50.7764816284],"type":"Point"}
}