{
  "type": "Feature",
  "properties": {
    "addr:full":"Chauss\u00c9e De Ch\u00c2telet 54 Charleroi Hainaut 6042",
    "addr:housenumber":"54",
    "addr:postcode":"6042",
    "addr:street":"Chausse\u0301E De Cha\u0302Telet;Hainaut",
    "iso:country":"BE",
    "sg:address":"Chauss\u00c9e De Ch\u00c2telet 54",
    "sg:city":"Charleroi",
    "sg:orig_category":"Avocats and conseillers juridiques",
    "sg:phone":"+32 71 32 61 25",
    "sg:postcode":"6042",
    "sg:province":"Hainaut",
    "wof:name":"J.p. Eloy",
    "wof:placetype":"venue"
},
  "geometry": {"coordinates":[4.4490199089,50.4293518066],"type":"Point"}
}