{
  "type": "Feature",
  "properties": {
    "addr:full":"Overslagdijk 27 Wachtebeke Oost-Vlaanderen 9185",
    "addr:housenumber":"27",
    "addr:postcode":"9185",
    "addr:street":"Overslagdijk",
    "iso:country":"BE",
    "sg:address":"Overslagdijk 27",
    "sg:city":"Wachtebeke",
    "sg:orig_category":"Rundveehouders Varkenskwekers",
    "sg:phone":"+32 9 345 72 05",
    "sg:postcode":"9185",
    "sg:province":"Oost-Vlaanderen",
    "wof:name":"Roger Poppe",
    "wof:placetype":"venue"
},
  "geometry": {"coordinates":[3.8878779411,51.2001152039],"type":"Point"}
}