{
  "type": "Feature",
  "properties": {
    "iso:country":"BE",
    "sg:address":"Rue Albert I",
    "sg:city":"La Louviere",
    "sg:orig_category":"Advocaten and juridische adviseurs",
    "sg:phone":"+32 64 84 81 70",
    "sg:postcode":"7100",
    "sg:province":"Hainaut",
    "wof:name":"Ronald Thomas",
    "wof:placetype":"venue"
},
  "geometry": {"coordinates":[4.1869959831,50.4763946533],"type":"Point"}
}