{
  "type": "Feature",
  "properties": {
    "addr:full":"Chemin Des Potays 1424 Spa Li\u00e8ge 4900",
    "addr:housenumber":"1424",
    "addr:postcode":"4900",
    "addr:street":"Chemin Des Potays",
    "iso:country":"BE",
    "sg:address":"Chemin Des Potays 1424",
    "sg:city":"Spa",
    "sg:classifiers":[
        {
            "category":"Arena",
            "subcategory":"Sports Club",
            "type":"Entertainment"
        }
    ],
    "sg:phone":"+32 87 77 33 95",
    "sg:postcode":"4900",
    "sg:province":"Li\u00e8ge",
    "sg:tags":[
        "terrain",
        "hors",
        "de",
        "installation",
        "sportifs"
    ],
    "wof:name":"R. Spa F.c.",
    "wof:placetype":"venue"
},
  "geometry": {"coordinates":[5.8733000755,50.4806404114],"type":"Point"}
}