{
  "type": "Feature",
  "properties": {
    "iso:country":"BE",
    "sg:address":"Sint-annastraat 13",
    "sg:city":"Poperinge",
    "sg:orig_category":"Salles de spectacles",
    "sg:phone":"+32 57 33 85 46",
    "sg:postcode":"8970",
    "sg:province":"West-Vlaanderen",
    "wof:name":"Cultureel Centrum",
    "wof:placetype":"venue"
},
  "geometry": {"coordinates":[2.7215750217,50.8541526794],"type":"Point"}
}