{
  "type": "Feature",
  "properties": {
    "iso:country":"BE",
    "sg:address":"Stoofstraat 29",
    "sg:city":"Merchtem",
    "sg:orig_category":"Advocaten and juridische adviseurs",
    "sg:phone":"+32 2 269 84 40",
    "sg:postcode":"1785",
    "sg:province":"Vlaams-Brabant",
    "wof:name":"Ingrid Van Den Eede",
    "wof:placetype":"venue"
},
  "geometry": {"coordinates":[4.2344169617,50.9567642212],"type":"Point"}
}