{
  "type": "Feature",
  "properties": {
    "addr:full":"Rue De Bruxelles 69a Braine-le-comte Hainaut 7090",
    "addr:housenumber":"69a",
    "addr:postcode":"7090",
    "addr:street":"Rue De Bruxelles",
    "iso:country":"BE",
    "sg:address":"Rue De Bruxelles 69a",
    "sg:city":"Braine-le-comte",
    "sg:classifiers":[
        {
            "category":"Shopping",
            "subcategory":"Antiques",
            "type":"Retail Goods"
        }
    ],
    "sg:phone":"+32 67 56 09 89",
    "sg:postcode":"7090",
    "sg:province":"Hainaut",
    "wof:name":"Antiquit\u00e9s Lempereur",
    "wof:placetype":"venue"
},
  "geometry": {"coordinates":[4.138258934,50.6163902283],"type":"Point"}
}