{
  "type": "Feature",
  "properties": {
    "iso:country":"BE",
    "sg:address":"Achterstehoevestraat 2",
    "sg:city":"Essen",
    "sg:orig_category":"Eleveurs de bovins",
    "sg:phone":"+32 3 677 34 51",
    "sg:postcode":"2910",
    "sg:province":"Antwerpen",
    "wof:name":"Guido Vandenbergh",
    "wof:placetype":"venue"
},
  "geometry": {"coordinates":[4.4164528847,51.4260101318],"type":"Point"}
}