{
  "type": "Feature",
  "properties": {
    "iso:country":"BE",
    "sg:address":"Avenue De Tervueren 363b",
    "sg:city":"Sint-pieters-woluwe/woluwe-sai",
    "sg:orig_category":"Musea and historische gebouwen",
    "sg:phone":"+32 2 513 31 08",
    "sg:postcode":"1150",
    "sg:province":"Bruxelles-Capitale",
    "wof:name":"Mus\u00c9e Du Transport Urbain Bruxellois",
    "wof:placetype":"venue"
},
  "geometry": {"coordinates":[4.4382629395,50.8273277283],"type":"Point"}
}