{
  "type": "Feature",
  "properties": {
    "iso:country":"BE",
    "sg:address":"Aardenburgse Heerweg 5",
    "sg:city":"Knesselare",
    "sg:orig_category":"Software ontwikkeling and ontwerp",
    "sg:phone":"+32 477 78 94 28",
    "sg:postcode":"9910",
    "sg:province":"Oost-Vlaanderen",
    "wof:name":"Soft@net",
    "wof:placetype":"venue"
},
  "geometry": {"coordinates":[3.4420030117,51.125579834],"type":"Point"}
}