{
  "type": "Feature",
  "properties": {
    "iso:country":"BE",
    "sg:address":"Halmaalweg 168",
    "sg:city":"Sint-truiden",
    "sg:orig_category":"Fruitteelt",
    "sg:phone":"+32 11 68 13 05",
    "sg:postcode":"3800",
    "sg:province":"Limburg",
    "wof:name":"Stephan Blavier",
    "wof:placetype":"venue"
},
  "geometry": {"coordinates":[5.1566581726,50.8065834045],"type":"Point"}
}