{
  "type": "Feature",
  "properties": {
    "addr:full":"Avenue Kamerdelle 115 Bruxelles (uccle) Bruxelles-Capitale 1180",
    "addr:housenumber":"115",
    "addr:postcode":"1180",
    "addr:street":"Avenue Kamerdelle",
    "iso:country":"BE",
    "sg:address":"Avenue Kamerdelle 115",
    "sg:city":"Bruxelles (uccle)",
    "sg:classifiers":[
        {
            "category":"Professional",
            "subcategory":"Management & Consulting",
            "type":"Services"
        }
    ],
    "sg:phone":"+32 2 346 92 78",
    "sg:postcode":"1180",
    "sg:province":"Bruxelles-Capitale",
    "sg:tags":[
        "consultant",
        "relation",
        "public"
    ],
    "wof:name":"Jackson Associates",
    "wof:placetype":"venue"
},
  "geometry": {"coordinates":[4.3516287804,50.7977333069],"type":"Point"}
}