{
  "type": "Feature",
  "properties": {
    "addr:full":"Gentstraat 101 Meulebeke West-Vlaanderen 8760",
    "addr:housenumber":"101",
    "addr:postcode":"8760",
    "addr:street":"Gentstraat",
    "iso:country":"BE",
    "sg:address":"Gentstraat 101",
    "sg:city":"Meulebeke",
    "sg:orig_category":"Steel Windows",
    "sg:phone":"+32 3 286 87 60",
    "sg:postcode":"8760",
    "sg:province":"West-Vlaanderen",
    "wof:name":"Ods Nv",
    "wof:placetype":"venue"
},
  "geometry": {"coordinates":[4.4299688339,51.1785430908],"type":"Point"}
}