{
  "type": "Feature",
  "properties": {
    "iso:country":"BE",
    "sg:address":"Eedverbondkaai 109",
    "sg:city":"Gent",
    "sg:orig_category":"Traducteurs and interpr\u00e8tes",
    "sg:phone":"+32 9 220 10 02",
    "sg:postcode":"9000",
    "sg:province":"Oost-Vlaanderen",
    "wof:name":"Cairns J. Cbtip/bkvtf",
    "wof:placetype":"venue"
},
  "geometry": {"coordinates":[3.7157840729,51.0414657593],"type":"Point"}
}