{
  "type": "Feature",
  "properties": {
    "addr:full":"6769 Meix-devant-virton (groot) Luxembourg 6769",
    "addr:housenumber":"6769",
    "addr:postcode":"6769",
    "addr:street":"Meix-Devant-Virton Groot Luxembourg",
    "iso:country":"BE",
    "sg:address":"6769",
    "sg:city":"Meix-devant-virton (groot)",
    "sg:orig_category":"Pharmaciens",
    "sg:phone":"+32 900 10 500",
    "sg:postcode":"6769",
    "sg:province":"Luxembourg",
    "wof:name":"Pharmacies De Garde",
    "wof:placetype":"venue"
},
  "geometry": {"coordinates":[5.4800958633,49.6040344238],"type":"Point"}
}