{
  "type": "Feature",
  "properties": {
    "addr:full":"Rue Des Carri\u00e8res 27 Gembloux-sur-orneau (isnes) Namur 5032",
    "addr:housenumber":"27",
    "addr:postcode":"5032",
    "addr:street":"Rue Des Carrie\u0300Res;Namur",
    "iso:country":"BE",
    "sg:address":"Rue Des Carri\u00e8res 27",
    "sg:city":"Gembloux-sur-orneau (isnes)",
    "sg:classifiers":[
        {
            "category":"Health Services",
            "subcategory":"Doctor",
            "type":"Services"
        }
    ],
    "sg:phone":"+32 81 56 94 82",
    "sg:postcode":"5032",
    "sg:province":"Namur",
    "sg:tags":[
        "medicinephysicians",
        "surgeon"
    ],
    "wof:name":"Fossoul Francine",
    "wof:placetype":"venue"
},
  "geometry": {"coordinates":[4.7468709946,50.5140838623],"type":"Point"}
}