{
  "type": "Feature",
  "properties": {
    "iso:country":"BE",
    "sg:address":"J. Malderusstraat 3",
    "sg:city":"Sint-pieters-leeuw",
    "sg:orig_category":"Installation \u00e9lectrique r\u00e9sidentielle",
    "sg:phone":"+32 2 378 21 88",
    "sg:postcode":"1600",
    "sg:province":"Vlaams-Brabant",
    "wof:name":"Fa. Dobelec",
    "wof:placetype":"venue"
},
  "geometry": {"coordinates":[4.2409777641,50.7786407471],"type":"Point"}
}