{
  "type": "Feature",
  "properties": {
    "iso:country":"BE",
    "sg:address":"Brugsepoortstraat 8",
    "sg:city":"Gent",
    "sg:classifiers":[
        {
            "category":"Shopping",
            "subcategory":"Computers & Home Electronics",
            "type":"Retail Goods"
        }
    ],
    "sg:phone":"+32 9 223 01 52",
    "sg:postcode":"9000",
    "sg:province":"Oost-Vlaanderen",
    "sg:tags":[
        "-",
        "television",
        "radio"
    ],
    "wof:name":"Deweerd F",
    "wof:placetype":"venue"
},
  "geometry": {"coordinates":[3.7108740807,51.0563201904],"type":"Point"}
}