{
  "type": "Feature",
  "properties": {
    "iso:country":"BE",
    "sg:address":"Rue Des Monts 70",
    "sg:city":"Ham-sur-heure-nalinnes (nalinnes)",
    "sg:classifiers":[
        {
            "category":"Real Estate",
            "subcategory":"Architect",
            "type":"Services"
        }
    ],
    "sg:phone":"+32 71 22 01 00",
    "sg:postcode":"6120",
    "sg:province":"Hainaut",
    "wof:name":"Brichaux P",
    "wof:placetype":"venue"
},
  "geometry": {"coordinates":[4.4581432343,50.3286170959],"type":"Point"}
}