{
  "type": "Feature",
  "properties": {
    "iso:country":"BE",
    "sg:address":"Vinkenlaan 23",
    "sg:city":"Asse",
    "sg:orig_category":"Fleurs and plantes",
    "sg:phone":"+32 2 463 29 62",
    "sg:postcode":"1731",
    "sg:province":"Vlaams-Brabant",
    "wof:name":"Wauters",
    "wof:placetype":"venue"
},
  "geometry": {"coordinates":[4.2737379074,50.8870582581],"type":"Point"}
}