{
  "type": "Feature",
  "properties": {
    "iso:country":"BE",
    "sg:address":"Broederstraat 57",
    "sg:city":"Sint-niklaas",
    "sg:orig_category":"Bouwmaterialen Gh Diverse bouwafwerking and reiniging Glaszetten and glaswerk",
    "sg:phone":"+32 3 777 72 59",
    "sg:postcode":"9100",
    "sg:province":"Oost-Vlaanderen",
    "wof:name":"Dresselaers & Zoon",
    "wof:placetype":"venue"
},
  "geometry": {"coordinates":[4.1392908096,51.158744812],"type":"Point"}
}