{
  "type": "Feature",
  "properties": {
    "iso:country":"BE",
    "sg:address":"Rue Antoine Carni\u00e8re 95",
    "sg:city":"Courcelles",
    "sg:classifiers":[
        {
            "category":"Health Services",
            "subcategory":"Dentist",
            "type":"Services"
        }
    ],
    "sg:phone":"+32 71 45 07 51",
    "sg:postcode":"6180",
    "sg:province":"Hainaut",
    "wof:name":"Lema\u00eetre Max",
    "wof:placetype":"venue"
},
  "geometry": {"coordinates":[4.3710632324,50.4559898376],"type":"Point"}
}