{
  "type": "Feature",
  "properties": {
    "addr:full":"Rue De La Glaci\u00e8re 21-23 Bruxelles (saint-gilles) Bruxelles-Capitale 1060",
    "addr:housenumber":"21-23",
    "addr:postcode":"1060",
    "addr:street":"Rue De La Glacie\u0300Re",
    "iso:country":"BE",
    "sg:address":"Rue De La Glaci\u00e8re 21-23",
    "sg:city":"Bruxelles (saint-gilles)",
    "sg:classifiers":[
        {
            "category":"Professional",
            "subcategory":"Art Services",
            "type":"Services"
        }
    ],
    "sg:phone":"+32 2 534 71 73",
    "sg:postcode":"1060",
    "sg:province":"Bruxelles-Capitale",
    "sg:tags":[
        "photographer"
    ],
    "wof:name":"Davister J-synchro",
    "wof:placetype":"venue"
},
  "geometry": {"coordinates":[4.3513097763,50.8227233887],"type":"Point"}
}