{
  "type": "Feature",
  "properties": {
    "iso:country":"BE",
    "sg:address":"Kaardijk 90",
    "sg:city":"Puurs",
    "sg:orig_category":"Diverse bouwafwerking and reiniging",
    "sg:phone":"+32 3 886 38 35",
    "sg:postcode":"2870",
    "sg:province":"Antwerpen",
    "wof:name":"Marc Coeckelbergh",
    "wof:placetype":"venue"
},
  "geometry": {"coordinates":[4.3352570534,51.0842285156],"type":"Point"}
}