{
  "type": "Feature",
  "properties": {
    "addr:full":"Stationsstraat 142 Herzele Oost-Vlaanderen 9550",
    "addr:housenumber":"142",
    "addr:postcode":"9550",
    "addr:street":"Stationsstraat;Oost-Vlaanderen",
    "iso:country":"BE",
    "sg:address":"Stationsstraat 142",
    "sg:city":"Herzele",
    "sg:classifiers":[
        {
            "category":"Health Services",
            "subcategory":"Health Practitioner",
            "type":"Services"
        }
    ],
    "sg:phone":"+32 53 62 21 99",
    "sg:postcode":"9550",
    "sg:province":"Oost-Vlaanderen",
    "sg:tags":[
        "physiotherapist"
    ],
    "wof:name":"De Pooter Griet",
    "wof:placetype":"venue"
},
  "geometry": {"coordinates":[3.8833670616,50.8958702087],"type":"Point"}
}