{
  "type": "Feature",
  "properties": {
    "iso:country":"BE",
    "sg:address":"De Vroente 39",
    "sg:city":"Genk",
    "sg:orig_category":"Activit\u00e9s d\u00b4action sociale sans h\u00e9bergement",
    "sg:phone":"+32 89 30 51 11",
    "sg:postcode":"3600",
    "sg:province":"Limburg",
    "wof:name":"Rode Kruis Genk",
    "wof:placetype":"venue"
},
  "geometry": {"coordinates":[5.4564461708,50.9659729004],"type":"Point"}
}