{
  "type": "Feature",
  "properties": {
    "addr:full":"Stationsstraat 159 Damme West-Vlaanderen 8340",
    "addr:housenumber":"159",
    "addr:postcode":"8340",
    "addr:street":"Stationsstraat",
    "iso:country":"BE",
    "sg:address":"Stationsstraat 159",
    "sg:city":"Damme",
    "sg:orig_category":"Installatie van metalen schrijnwerk Isolatiewerk",
    "sg:phone":"+32 50 36 32 42",
    "sg:postcode":"8340",
    "sg:province":"West-Vlaanderen",
    "wof:name":"Isolatieadvies Kolijn",
    "wof:placetype":"venue"
},
  "geometry": {"coordinates":[3.3144619465,51.2152061462],"type":"Point"}
}