{
  "type": "Feature",
  "properties": {
    "iso:country":"BE",
    "sg:address":"Wakkensteenweg 63",
    "sg:city":"Wielsbeke",
    "sg:orig_category":"Herstellingen and onderhoud van auto's",
    "sg:phone":"+32 56 60 81 21",
    "sg:postcode":"8710",
    "sg:province":"West-Vlaanderen",
    "wof:name":"Autohandel Jacobs",
    "wof:placetype":"venue"
},
  "geometry": {"coordinates":[3.3694550991,50.9095153809],"type":"Point"}
}