{
  "type": "Feature",
  "properties": {
    "iso:country":"BE",
    "sg:address":"Amersveldestraat 26",
    "sg:city":"Hooglede",
    "sg:orig_category":"Entretien and r\u00e9parations de voitures. D\u00e9taillants en pi\u00e8ces and accessoires de voitures",
    "sg:phone":"+32 51 70 33 16",
    "sg:postcode":"8830",
    "sg:province":"West-Vlaanderen",
    "wof:name":"Geert Raes",
    "wof:placetype":"venue"
},
  "geometry": {"coordinates":[3.0544600487,51.0003204346],"type":"Point"}
}