{
  "type": "Feature",
  "properties": {
    "iso:country":"BE",
    "sg:address":"Avenue Jeanne 20",
    "sg:city":"Elsene/ixelles",
    "sg:orig_category":"Agences de presse. M\u00e9decins and sp\u00e9cialistes",
    "sg:phone":"+32 2 648 40 90",
    "sg:postcode":"1050",
    "sg:province":"Bruxelles-Capitale",
    "wof:name":"Maurice Einhorn",
    "wof:placetype":"venue"
},
  "geometry": {"coordinates":[4.3813438416,50.8155822754],"type":"Point"}
}