{
  "type": "Feature",
  "properties": {
    "addr:full":"Antwerpsesteenweg 359b Lier Antwerpen 2500",
    "addr:housenumber":"359b",
    "addr:postcode":"2500",
    "addr:street":"Antwerpsesteenweg",
    "iso:country":"BE",
    "sg:address":"Antwerpsesteenweg 359b",
    "sg:city":"Lier",
    "sg:orig_category":"Installatie van houten of kunststof schrijnwerk Kantoormateriaal",
    "sg:phone":"+32 3 489 03 74",
    "sg:postcode":"2500",
    "sg:province":"Antwerpen",
    "wof:name":"Lierse Kantoormeubelen",
    "wof:placetype":"venue"
},
  "geometry": {"coordinates":[4.548874855,51.1423034668],"type":"Point"}
}