{
  "type": "Feature",
  "properties": {
    "addr:full":"Saksen-coburgstraat 8ba Sint-joost-ten-node/saint-josse-ten-noode Bruxelles-Capitale 1210",
    "addr:housenumber":"8ba",
    "addr:postcode":"1210",
    "addr:street":"Saksen-Coburgstraat",
    "iso:country":"BE",
    "sg:address":"Saksen-coburgstraat 8ba",
    "sg:city":"Sint-joost-ten-node/saint-josse-ten-noode",
    "sg:orig_category":"Industri\u00eble wasserijen and droogkuis",
    "sg:phone":"+32 2 217 61 38",
    "sg:postcode":"1210",
    "sg:province":"Bruxelles-Capitale",
    "wof:name":"Nettoyage \u00c0 Sec Ocean",
    "wof:placetype":"venue"
},
  "geometry": {"coordinates":[4.3726449013,50.8503074646],"type":"Point"}
}