{
  "type": "Feature",
  "properties": {
    "iso:country":"BE",
    "sg:address":"Generaal Lemanlaan 182b1",
    "sg:city":"Brugge",
    "sg:classifiers":[
        {
            "category":"Communications",
            "subcategory":"Radio Station",
            "type":"Services"
        }
    ],
    "sg:phone":"+32 50 37 22 72",
    "sg:postcode":"8310",
    "sg:province":"West-Vlaanderen",
    "sg:tags":[
        "diffusion",
        "production",
        "de",
        "programme"
    ],
    "wof:name":"Radio Swing Fm 105.3",
    "wof:placetype":"venue"
},
  "geometry": {"coordinates":[3.2440679073,51.2009963989],"type":"Point"}
}