{
  "type": "Feature",
  "properties": {
    "addr:full":"Rue Du Perron 20 Vise Li\u00e8ge 4600",
    "addr:housenumber":"20",
    "addr:postcode":"4600",
    "addr:street":"Rue Du Perron",
    "iso:country":"BE",
    "sg:address":"Rue Du Perron 20",
    "sg:city":"Vise",
    "sg:orig_category":"Apotheken",
    "sg:phone":"+32 4 379 10 29",
    "sg:postcode":"4600",
    "sg:province":"Li\u00e8ge",
    "wof:name":"M. Lassance",
    "wof:placetype":"venue"
},
  "geometry": {"coordinates":[5.6948671341,50.7350769043],"type":"Point"}
}