{
  "type": "Feature",
  "properties": {
    "iso:country":"BE",
    "sg:address":"Rue Du Grand Marais 47ba",
    "sg:city":"Mons",
    "sg:orig_category":"Woningbouw",
    "sg:phone":"+32 65 36 23 92",
    "sg:postcode":"7011",
    "sg:province":"Hainaut",
    "wof:name":"Coverber",
    "wof:placetype":"venue"
},
  "geometry": {"coordinates":[3.912539959,50.4712982178],"type":"Point"}
}