{
  "type": "Feature",
  "properties": {
    "iso:country":"BE",
    "sg:address":"Rue De L'eglise 4",
    "sg:city":"Celles",
    "sg:classifiers":[
        {
            "category":"Professional",
            "subcategory":"Advertising",
            "type":"Services"
        }
    ],
    "sg:phone":"+32 19 32 51 35",
    "sg:postcode":"4317",
    "sg:province":"Li\u00e8ge",
    "sg:tags":[
        "painter"
    ],
    "wof:name":"Fiolle Publicit\u00e9",
    "wof:placetype":"venue"
},
  "geometry": {"coordinates":[3.4581139088,50.7125816345],"type":"Point"}
}