{
  "type": "Feature",
  "properties": {
    "addr:full":"Rue Des H\u00c9ros 32 Li\u00c8ge Li\u00e8ge 4000",
    "addr:housenumber":"32",
    "addr:postcode":"4000",
    "addr:street":"Rue Des He\u0301Ros",
    "iso:country":"BE",
    "sg:address":"Rue Des H\u00c9ros 32",
    "sg:city":"Li\u00c8ge",
    "sg:orig_category":"Eleveurs and marchands de porcs. Eleveurs de bovins",
    "sg:phone":"+32 4 263 49 37",
    "sg:postcode":"4000",
    "sg:province":"Li\u00e8ge",
    "wof:name":"Fastre Philippe Et Andre",
    "wof:placetype":"venue"
},
  "geometry": {"coordinates":[5.5887618065,50.6503372192],"type":"Point"}
}