{
  "type": "Feature",
  "properties": {
    "iso:country":"BE",
    "sg:address":"Oude Molenstraat 137",
    "sg:city":"Ukkel/uccle",
    "sg:orig_category":"Artiesten and kunstenaars",
    "sg:phone":"+32 2 375 10 58",
    "sg:postcode":"1180",
    "sg:province":"Bruxelles-Capitale",
    "wof:name":"Beukelaers/fran\u00c7ois Beukelaers",
    "wof:placetype":"venue"
},
  "geometry": {"coordinates":[4.366956234,50.7902183533],"type":"Point"}
}