{
  "type": "Feature",
  "properties": {
    "addr:full":"Melinglaan 3 Moorslede West-Vlaanderen 8890",
    "addr:housenumber":"3",
    "addr:postcode":"8890",
    "addr:street":"Melinglaan",
    "iso:country":"BE",
    "sg:address":"Melinglaan 3",
    "sg:city":"Moorslede",
    "sg:classifiers":[
        {
            "category":"Arena",
            "subcategory":"Sports Club",
            "type":"Entertainment"
        }
    ],
    "sg:phone":"+32 51 77 00 09",
    "sg:postcode":"8890",
    "sg:province":"West-Vlaanderen",
    "sg:tags":[
        "de"
    ],
    "wof:name":"K.c Moorsleede",
    "wof:placetype":"venue"
},
  "geometry": {"coordinates":[3.0646090508,50.8851356506],"type":"Point"}
}