{
  "type": "Feature",
  "properties": {
    "addr:full":"Kortstraat 1 Hasselt Limburg 3500",
    "addr:housenumber":"1",
    "addr:postcode":"3500",
    "addr:street":"Kortstraat",
    "iso:country":"BE",
    "sg:address":"Kortstraat 1",
    "sg:city":"Hasselt",
    "sg:classifiers":[
        {
            "category":"Bars & Pubs",
            "type":"Food & Drink"
        }
    ],
    "sg:phone":"+32 11 21 55 18",
    "sg:postcode":"3500",
    "sg:province":"Limburg",
    "sg:tags":[
        "tavern"
    ],
    "wof:name":"Lord (the)",
    "wof:placetype":"venue"
},
  "geometry": {"coordinates":[5.338039875,50.9294548035],"type":"Point"}
}