{
  "type": "Feature",
  "properties": {
    "iso:country":"BE",
    "sg:address":"Pont D'ile 52",
    "sg:city":"Li\u00e8ge 1",
    "sg:classifiers":[
        {
            "category":"Shopping",
            "subcategory":"Clothing, Apparel, & Fashions",
            "type":"Retail Goods"
        }
    ],
    "sg:phone":"+32 4 221 25 86",
    "sg:postcode":"4000",
    "sg:province":"Li\u00e8ge",
    "sg:tags":[
        "boutique"
    ],
    "wof:name":"City (la)",
    "wof:placetype":"venue"
},
  "geometry": {"coordinates":[5.5708289146,50.6423683167],"type":"Point"}
}