{
  "type": "Feature",
  "properties": {
    "iso:country":"BE",
    "sg:address":"Beverlo Dorp 25",
    "sg:city":"Beringen (beverlo)",
    "sg:classifiers":[
        {
            "category":"Bakery",
            "type":"Food & Drink"
        }
    ],
    "sg:phone":"+32 11 34 15 58",
    "sg:postcode":"3581",
    "sg:province":"Limburg",
    "sg:tags":[
        "confectioner",
        "baker"
    ],
    "wof:name":"Vandermeeren E",
    "wof:placetype":"venue"
},
  "geometry": {"coordinates":[5.2207808495,51.0879096985],"type":"Point"}
}