{
  "type": "Feature",
  "properties": {
    "iso:country":"BE",
    "sg:address":"Place Sainte-gertrude 15",
    "sg:city":"Bl\u00e9gny (trembleur)",
    "sg:classifiers":[
        {
            "category":"Health Services",
            "subcategory":"Health Practitioner",
            "type":"Services"
        }
    ],
    "sg:phone":"+32 474 76 06 96",
    "sg:postcode":"4670",
    "sg:province":"Li\u00e8ge",
    "sg:tags":[
        "physiotherapist"
    ],
    "wof:name":"Heuchenne D\u00e9borah",
    "wof:placetype":"venue"
},
  "geometry": {"coordinates":[5.7257599831,50.6726646423],"type":"Point"}
}