{
  "type": "Feature",
  "properties": {
    "addr:full":"Werfstraat 72ba Galmaarden Vlaams-Brabant 1570",
    "addr:housenumber":"72ba",
    "addr:postcode":"1570",
    "addr:street":"Werfstraat",
    "iso:country":"BE",
    "sg:address":"Werfstraat 72ba",
    "sg:city":"Galmaarden",
    "sg:classifiers":[
        {
            "category":"Insurance",
            "subcategory":"Life Insurance",
            "type":"Services"
        }
    ],
    "sg:phone":"+32 54 58 01 22",
    "sg:postcode":"1570",
    "sg:province":"Vlaams-Brabant",
    "sg:tags":[
        "assurance"
    ],
    "wof:name":"Rudy Suys",
    "wof:placetype":"venue"
},
  "geometry": {"coordinates":[3.9579999447,50.7465362549],"type":"Point"}
}