{
  "type": "Feature",
  "properties": {
    "iso:country":"BE",
    "sg:address":"Rue Haute 35",
    "sg:city":"Frasnes-lez-anvaing",
    "sg:orig_category":"Kapsalons",
    "sg:phone":"+32 69 86 74 19",
    "sg:postcode":"7911",
    "sg:province":"Hainaut",
    "wof:name":"Coiffure Lady",
    "wof:placetype":"venue"
},
  "geometry": {"coordinates":[3.6207799911,50.6676597595],"type":"Point"}
}