{
  "type": "Feature",
  "properties": {
    "addr:full":"Rue Saint-roch 27 Huy (ben-ahin) Li\u00e8ge 4500",
    "addr:housenumber":"27",
    "addr:postcode":"4500",
    "addr:street":"Rue Saint-Roch",
    "iso:country":"BE",
    "sg:address":"Rue Saint-roch 27",
    "sg:city":"Huy (ben-ahin)",
    "sg:classifiers":[
        {
            "category":"Sports & Exercise",
            "subcategory":"Stables",
            "type":"Entertainment"
        }
    ],
    "sg:phone":"+32 476 26 82 23",
    "sg:postcode":"4500",
    "sg:province":"Li\u00e8ge",
    "sg:tags":[
        "riding",
        "school"
    ],
    "wof:name":"Haras Saint-roch",
    "wof:placetype":"venue"
},
  "geometry": {"coordinates":[5.2268481255,50.5237579346],"type":"Point"}
}