{
  "type": "Feature",
  "properties": {
    "iso:country":"BE",
    "sg:address":"Chauss\u00c9e De Bruxelles 36",
    "sg:city":"Charleroi",
    "sg:orig_category":"Entretien and r\u00e9parations de voitures",
    "sg:phone":"+32 71 85 35 21",
    "sg:postcode":"6041",
    "sg:province":"Hainaut",
    "wof:name":"P. Gomand",
    "wof:placetype":"venue"
},
  "geometry": {"coordinates":[4.4399719238,50.4362602234],"type":"Point"}
}