{
  "type": "Feature",
  "properties": {
    "iso:country":"BE",
    "sg:address":"Rue De Lisbonne 75c",
    "sg:city":"Chimay (l'escaill\u00e8re)",
    "sg:orig_category":"Non-Classified Establishments",
    "sg:phone":"+32 60 37 72 28",
    "sg:postcode":"6464",
    "sg:province":"Hainaut",
    "wof:name":"Pralines De Chimay (les)",
    "wof:placetype":"venue"
},
  "geometry": {"coordinates":[4.4111409187,50.01222229],"type":"Point"}
}