{
  "type": "Feature",
  "properties": {
    "addr:full":"Elfbunderslaan 9 Beersel Vlaams-Brabant 1650",
    "addr:housenumber":"9",
    "addr:postcode":"1650",
    "addr:street":"Elfbunderslaan",
    "iso:country":"BE",
    "sg:address":"Elfbunderslaan 9",
    "sg:city":"Beersel",
    "sg:classifiers":[
        {
            "category":"Autos & Motor Vehicles",
            "subcategory":"Boat Sales",
            "type":"Retail Goods"
        }
    ],
    "sg:phone":"+32 2 380 65 49",
    "sg:postcode":"1650",
    "sg:province":"Vlaams-Brabant",
    "sg:tags":[
        "balloon"
    ],
    "wof:name":"Balloon By It's Now",
    "wof:placetype":"venue"
},
  "geometry": {"coordinates":[4.3324298859,50.7648086548],"type":"Point"}
}