{
  "type": "Feature",
  "properties": {
    "addr:full":"Rue Saint-l\u00c9onard 351 Li\u00c8ge Li\u00e8ge 4000",
    "addr:housenumber":"351",
    "addr:postcode":"4000",
    "addr:street":"Rue Saint-Le\u0301Onard",
    "iso:country":"BE",
    "sg:address":"Rue Saint-l\u00c9onard 351",
    "sg:city":"Li\u00c8ge",
    "sg:orig_category":"Enseignement maternel and primaire",
    "sg:phone":"+32 4 227 73 95",
    "sg:postcode":"4000",
    "sg:province":"Li\u00e8ge",
    "wof:name":"Ecole Fondamentale Libre",
    "wof:placetype":"venue"
},
  "geometry": {"coordinates":[5.5988068581,50.6520309448],"type":"Point"}
}