{
  "type": "Feature",
  "properties": {
    "iso:country":"BE",
    "sg:address":"Dokkenstraat 4b",
    "sg:city":"Affligem (essene)",
    "sg:classifiers":[
        {
            "category":"Farming",
            "subcategory":"Fish & Marine Products",
            "type":"Manufacturing & Wholesale Goods"
        }
    ],
    "sg:phone":"+32 475 48 23 84",
    "sg:postcode":"1790",
    "sg:province":"Vlaams-Brabant",
    "sg:tags":[
        "photographer",
        "fashion",
        "-"
    ],
    "wof:name":"Stallaert K",
    "wof:placetype":"venue"
},
  "geometry": {"coordinates":[4.145637989,50.8979797363],"type":"Point"}
}