{
  "type": "Feature",
  "properties": {
    "addr:full":"Van Kalckstraat 30 Sint-jans-molenbeek/molenbeek-saint-jean Bruxelles-Capitale 1080",
    "addr:housenumber":"30",
    "addr:postcode":"1080",
    "addr:street":"Van Kalckstraat",
    "iso:country":"BE",
    "sg:address":"Van Kalckstraat 30",
    "sg:city":"Sint-jans-molenbeek/molenbeek-saint-jean",
    "sg:orig_category":"Rusthuizen and serviceflats",
    "sg:phone":"+32 2 410 03 56",
    "sg:postcode":"1080",
    "sg:province":"Bruxelles-Capitale",
    "wof:name":"R\u00c9sidence Toque D'argent",
    "wof:placetype":"venue"
},
  "geometry": {"coordinates":[4.3138151169,50.8542861938],"type":"Point"}
}