{
  "type": "Feature",
  "properties": {
    "iso:country":"BE",
    "sg:address":"Kardinaal Cardijnlaan 46",
    "sg:city":"Menen",
    "sg:classifiers":[
        {
            "category":"Bars & Pubs",
            "type":"Food & Drink"
        }
    ],
    "sg:phone":"+32 56 51 20 48",
    "sg:postcode":"8930",
    "sg:province":"West-Vlaanderen",
    "wof:name":"Postje ('t)",
    "wof:placetype":"venue"
},
  "geometry": {"coordinates":[3.1069660187,50.803691864],"type":"Point"}
}