{
  "type": "Feature",
  "properties": {
    "addr:full":"Keimolen 3 Aalst Oost-Vlaanderen 9310",
    "addr:housenumber":"3",
    "addr:postcode":"9310",
    "addr:street":"Keimolen",
    "iso:country":"BE",
    "sg:address":"Keimolen 3",
    "sg:city":"Aalst",
    "sg:orig_category":"Fleurs and plantes",
    "sg:phone":"+32 53 77 89 31",
    "sg:postcode":"9310",
    "sg:province":"Oost-Vlaanderen",
    "wof:name":"Fleur Bloemengroothandel",
    "wof:placetype":"venue"
},
  "geometry": {"coordinates":[4.099421978,50.968372345],"type":"Point"}
}