{
  "type": "Feature",
  "properties": {
    "iso:country":"BE",
    "sg:address":"Antwerpsesteenweg 160",
    "sg:city":"Malle (westmalle)",
    "sg:classifiers":[
        {
            "category":"Banks & Credit Unions",
            "subcategory":"Investment Brokerage",
            "type":"Services"
        }
    ],
    "sg:phone":"+32 3 311 53 98",
    "sg:postcode":"2390",
    "sg:province":"Antwerpen",
    "sg:tags":[
        "printing",
        "-"
    ],
    "wof:name":"Wens Renaat",
    "wof:placetype":"venue"
},
  "geometry": {"coordinates":[4.7010879517,51.2976112366],"type":"Point"}
}