{
  "type": "Feature",
  "properties": {
    "addr:full":"Kroonstraat 47 Antwerpen (borgerhout) Antwerpen 2140",
    "addr:housenumber":"47",
    "addr:postcode":"2140",
    "addr:street":"Kroonstraat",
    "iso:country":"BE",
    "sg:address":"Kroonstraat 47",
    "sg:city":"Antwerpen (borgerhout)",
    "sg:classifiers":[
        {
            "category":"Manufacturing",
            "subcategory":"Furniture",
            "type":"Manufacturing & Wholesale Goods"
        }
    ],
    "sg:phone":"+32 3 272 30 50",
    "sg:postcode":"2140",
    "sg:province":"Antwerpen",
    "sg:tags":[
        "made",
        "-",
        "custom"
    ],
    "wof:name":"Houtopia Bvba",
    "wof:placetype":"venue"
},
  "geometry": {"coordinates":[4.4332199097,51.2137565613],"type":"Point"}
}