{
  "type": "Feature",
  "properties": {
    "addr:full":"Pl. Du Jardin Aux Fleurs 7 Brussel/bruxelles Bruxelles-Capitale 1000",
    "addr:housenumber":"7",
    "addr:postcode":"1000",
    "addr:street":"Pl.;/",
    "iso:country":"BE",
    "sg:address":"Pl. Du Jardin Aux Fleurs 7",
    "sg:city":"Brussel/bruxelles",
    "sg:orig_category":"Epiceries",
    "sg:phone":"+32 2 512 25 21",
    "sg:postcode":"1000",
    "sg:province":"Bruxelles-Capitale",
    "wof:name":"Maison Madeleine",
    "wof:placetype":"venue"
},
  "geometry": {"coordinates":[4.3432359695,50.8483467102],"type":"Point"}
}