{
  "type": "Feature",
  "properties": {
    "addr:full":"Torhoutsestraat 130 Oostkamp (ruddervoorde) West-Vlaanderen 8020",
    "addr:housenumber":"130",
    "addr:postcode":"8020",
    "addr:street":"Torhoutsestraat",
    "iso:country":"BE",
    "sg:address":"Torhoutsestraat 130",
    "sg:city":"Oostkamp (ruddervoorde)",
    "sg:classifiers":[
        {
            "category":"Retail",
            "subcategory":"Veterinary Services",
            "type":"Services"
        }
    ],
    "sg:phone":"+32 50 27 80 63",
    "sg:postcode":"8020",
    "sg:province":"West-Vlaanderen",
    "sg:tags":[
        "veterinarian"
    ],
    "wof:name":"Minne A",
    "wof:placetype":"venue"
},
  "geometry": {"coordinates":[3.1995339394,51.0883102417],"type":"Point"}
}