{
  "type": "Feature",
  "properties": {
    "iso:country":"BE",
    "sg:address":"Rue Du Pel\u00c9mont 66",
    "sg:city":"Jemeppe-sur-sambre",
    "sg:orig_category":"Editeurs de livres",
    "sg:phone":"+32 81 63 41 29",
    "sg:postcode":"5190",
    "sg:province":"Namur",
    "wof:name":"Moreau P.c.e.",
    "wof:placetype":"venue"
},
  "geometry": {"coordinates":[4.6703448296,50.4645042419],"type":"Point"}
}