{
  "type": "Feature",
  "properties": {
    "iso:country":"BE",
    "sg:address":"Place Ba\u00cfaux 31",
    "sg:city":"Fleurus",
    "sg:orig_category":"Brood, gebak and snoepgoed",
    "sg:phone":"+32 71 81 19 19",
    "sg:postcode":"6224",
    "sg:province":"Hainaut",
    "wof:name":"Jean-claude Lacroix",
    "wof:placetype":"venue"
},
  "geometry": {"coordinates":[4.5886030197,50.4721565247],"type":"Point"}
}