{
  "type": "Feature",
  "properties": {
    "iso:country":"BE",
    "sg:address":"Van Trierstraat 48",
    "sg:city":"Antwerpen",
    "sg:classifiers":[
        {
            "category":"Manufacturing",
            "subcategory":"Musical Instruments",
            "type":"Manufacturing & Wholesale Goods"
        }
    ],
    "sg:phone":"+32 3 238 78 11",
    "sg:postcode":"2018",
    "sg:province":"Antwerpen",
    "sg:tags":[
        "piano"
    ],
    "wof:name":"Van Den Hemel J",
    "wof:placetype":"venue"
},
  "geometry": {"coordinates":[4.4004759789,51.2002296448],"type":"Point"}
}