{
  "type": "Feature",
  "properties": {
    "addr:full":"Avenue De L'universit\u00c9 36 Elsene/ixelles Bruxelles-Capitale 1050",
    "addr:housenumber":"36",
    "addr:postcode":"1050",
    "addr:street":"Avenue De L'Universite \u0301",
    "iso:country":"BE",
    "sg:address":"Avenue De L'universit\u00c9 36",
    "sg:city":"Elsene/ixelles",
    "sg:classifiers":[
        {
            "category":"Restaurant",
            "type":"Food & Drink"
        }
    ],
    "sg:phone":"+32 2 644 14 98",
    "sg:postcode":"1050",
    "sg:province":"Bruxelles-Capitale",
    "wof:name":"La Table Du March\u00c9",
    "wof:placetype":"venue"
},
  "geometry": {"coordinates":[4.388302803,50.8149642944],"type":"Point"}
}