{
  "type": "Feature",
  "properties": {
    "addr:full":"Avenue Charles-quint 73a Ganshoren/ganshoren Bruxelles-Capitale 1083",
    "addr:housenumber":"73a",
    "addr:postcode":"1083",
    "addr:street":"Avenue Charles-Quint",
    "iso:country":"BE",
    "sg:address":"Avenue Charles-quint 73a",
    "sg:city":"Ganshoren/ganshoren",
    "sg:orig_category":"Banques and organismes de cr\u00e9dit",
    "sg:phone":"+32 2 427 63 68",
    "sg:postcode":"1083",
    "sg:province":"Bruxelles-Capitale",
    "wof:name":"Bacob",
    "wof:placetype":"venue"
},
  "geometry": {"coordinates":[4.3123650551,50.8683395386],"type":"Point"}
}