{
  "type": "Feature",
  "properties": {
    "addr:full":"Rietvoornstraat 3 Zedelgem West-Vlaanderen 8210",
    "addr:housenumber":"3",
    "addr:postcode":"8210",
    "addr:street":"Rietvoornstraat",
    "iso:country":"BE",
    "sg:address":"Rietvoornstraat 3",
    "sg:city":"Zedelgem",
    "sg:orig_category":"Gespecialiseerde residenti\u00eble bouw",
    "sg:phone":"+32 50 27 58 31",
    "sg:postcode":"8210",
    "sg:province":"West-Vlaanderen",
    "wof:name":"Eric Degrande",
    "wof:placetype":"venue"
},
  "geometry": {"coordinates":[3.1458399296,51.1376457214],"type":"Point"}
}