{
  "type": "Feature",
  "properties": {
    "addr:full":"Bergerkampstraat 7 Dilsen-stokkem (elen) Limburg 3650",
    "addr:housenumber":"7",
    "addr:postcode":"3650",
    "addr:street":"Bergerkampstraat;Elen Limburg",
    "iso:country":"BE",
    "sg:address":"Bergerkampstraat 7",
    "sg:city":"Dilsen-stokkem (elen)",
    "sg:classifiers":[
        {
            "category":"Travel",
            "subcategory":"Travel Agent",
            "type":"Entertainment"
        }
    ],
    "sg:phone":"+32 89 79 42 41",
    "sg:postcode":"3650",
    "sg:province":"Limburg",
    "sg:tags":[
        "agency"
    ],
    "wof:name":"Elers Reisburo",
    "wof:placetype":"venue"
},
  "geometry": {"coordinates":[5.727396965,51.0364189148],"type":"Point"}
}