{
  "type": "Feature",
  "properties": {
    "iso:country":"BE",
    "sg:address":"Gabrielle Petitstraat 4b11",
    "sg:city":"Sint-jans-molenbeek/molenbeek-saint-jean",
    "sg:orig_category":"Opinieonderzoekbureaus",
    "sg:phone":"+32 2 519 22 11",
    "sg:postcode":"1080",
    "sg:province":"Bruxelles-Capitale",
    "wof:name":"B-connected",
    "wof:placetype":"venue"
},
  "geometry": {"coordinates":[4.3405170441,50.8681182861],"type":"Point"}
}