{
  "type": "Feature",
  "properties": {
    "addr:full":"Rue Du Paradis 11 Verviers Li\u00e8ge 4800",
    "addr:housenumber":"11",
    "addr:postcode":"4800",
    "addr:street":"Rue Du Paradis",
    "iso:country":"BE",
    "sg:address":"Rue Du Paradis 11",
    "sg:city":"Verviers",
    "sg:classifiers":[
        {
            "category":"Cafe",
            "type":"Food & Drink"
        }
    ],
    "sg:phone":"+32 87 35 22 88",
    "sg:postcode":"4800",
    "sg:province":"Li\u00e8ge",
    "sg:tags":[
        "caf\u00e9s"
    ],
    "wof:name":"Caf\u00c9 Le Chapuis",
    "wof:placetype":"venue"
},
  "geometry": {"coordinates":[5.8594508171,50.5917663574],"type":"Point"}
}