{
  "type": "Feature",
  "properties": {
    "iso:country":"BE",
    "sg:address":"Gebrandhofstraat 7",
    "sg:city":"Halen",
    "sg:classifiers":[
        {
            "category":"Farming",
            "subcategory":"Crops",
            "type":"Manufacturing & Wholesale Goods"
        }
    ],
    "sg:phone":"+32 13 44 27 75",
    "sg:postcode":"3545",
    "sg:province":"Limburg",
    "sg:tags":[
        "vegetable",
        "fruit",
        "-",
        "grower"
    ],
    "wof:name":"Nollet P",
    "wof:placetype":"venue"
},
  "geometry": {"coordinates":[5.049847126,50.932762146],"type":"Point"}
}