{
  "type": "Feature",
  "properties": {
    "iso:country":"BE",
    "sg:address":"Impasse De La Fontaine 14",
    "sg:city":"Charleroi (grand)",
    "sg:orig_category":"Installation \u00e9lectrique r\u00e9sidentielle",
    "sg:phone":"+32 71 45 45 59",
    "sg:postcode":"6044",
    "sg:province":"Hainaut",
    "wof:name":"Forgione A",
    "wof:placetype":"venue"
},
  "geometry": {"coordinates":[4.3856639862,50.4501228333],"type":"Point"}
}