{
  "type": "Feature",
  "properties": {
    "addr:full":"Galerijpad 3 Zwalm (sint-maria-latem) Oost-Vlaanderen 9630",
    "addr:housenumber":"3",
    "addr:postcode":"9630",
    "addr:street":"Galerijpad;Sint-Maria-Latem",
    "iso:country":"BE",
    "sg:address":"Galerijpad 3",
    "sg:city":"Zwalm (sint-maria-latem)",
    "sg:classifiers":[
        {
            "category":"Bars & Pubs",
            "type":"Food & Drink"
        }
    ],
    "sg:phone":"+32 55 49 70 75",
    "sg:postcode":"9630",
    "sg:province":"Oost-Vlaanderen",
    "sg:tags":[
        "tavern"
    ],
    "wof:name":"Klein Zwitserland",
    "wof:placetype":"venue"
},
  "geometry": {"coordinates":[3.7331020832,50.8774833679],"type":"Point"}
}