{
  "type": "Feature",
  "properties": {
    "iso:country":"BE",
    "sg:address":"Lombardenstraat 28",
    "sg:city":"Antwerpen",
    "sg:classifiers":[
        {
            "category":"Social Services",
            "type":"Services"
        }
    ],
    "sg:phone":"+32 3 226 07 37",
    "sg:postcode":"2000",
    "sg:province":"Antwerpen",
    "wof:name":"Vereniging Voor Solidariteit Vzw",
    "wof:placetype":"venue"
},
  "geometry": {"coordinates":[4.4023070335,51.2168426514],"type":"Point"}
}