{
  "type": "Feature",
  "properties": {
    "iso:country":"BE",
    "sg:address":"Slachthuisstraat 31",
    "sg:city":"Sint-truiden",
    "sg:classifiers":[
        {
            "category":"Health Services",
            "subcategory":"Health Practitioner",
            "type":"Services"
        }
    ],
    "sg:phone":"+32 11 69 27 55",
    "sg:postcode":"3800",
    "sg:province":"Limburg",
    "sg:tags":[
        "physiotherapist"
    ],
    "wof:name":"Tabruyn Miet",
    "wof:placetype":"venue"
},
  "geometry": {"coordinates":[5.1923041344,50.8193206787],"type":"Point"}
}