{
  "type": "Feature",
  "properties": {
    "addr:full":"Steenhofstraat 28 Kortenberg Vlaams-Brabant 3078",
    "addr:housenumber":"28",
    "addr:postcode":"3078",
    "addr:street":"Steenhofstraat;Vlaams-Brabant",
    "iso:country":"BE",
    "sg:address":"Steenhofstraat 28",
    "sg:city":"Kortenberg",
    "sg:orig_category":"Librairies. Epiceries. Alimentation sp\u00e9cialis\u00e9e",
    "sg:phone":"+32 2 759 49 79",
    "sg:postcode":"3078",
    "sg:province":"Vlaams-Brabant",
    "wof:name":"Stonemanor Country Club",
    "wof:placetype":"venue"
},
  "geometry": {"coordinates":[4.5665860176,50.8797225952],"type":"Point"}
}