{
  "type": "Feature",
  "properties": {
    "addr:full":"Elenestraat 257 Zottegem Oost-Vlaanderen 9620",
    "addr:housenumber":"257",
    "addr:postcode":"9620",
    "addr:street":"Elenestraat",
    "iso:country":"BE",
    "sg:address":"Elenestraat 257",
    "sg:city":"Zottegem",
    "sg:classifiers":[
        {
            "category":"Cafe",
            "type":"Food & Drink"
        }
    ],
    "sg:phone":"+32 9 360 67 54",
    "sg:postcode":"9620",
    "sg:province":"Oost-Vlaanderen",
    "sg:tags":[
        "caf\u00e9s"
    ],
    "wof:name":"Marc Vekeman",
    "wof:placetype":"venue"
},
  "geometry": {"coordinates":[3.8086929321,50.8774681091],"type":"Point"}
}