{
  "type": "Feature",
  "properties": {
    "addr:full":"Gentpoortstraat 47 Brugge West-Vlaanderen 8000",
    "addr:housenumber":"47",
    "addr:postcode":"8000",
    "addr:street":"Gentpoortstraat",
    "iso:country":"BE",
    "sg:address":"Gentpoortstraat 47",
    "sg:city":"Brugge",
    "sg:orig_category":"Kapsalons",
    "sg:phone":"+32 50 33 46 84",
    "sg:postcode":"8000",
    "sg:province":"West-Vlaanderen",
    "wof:name":"Coiff. Patrick Saint-yves",
    "wof:placetype":"venue"
},
  "geometry": {"coordinates":[3.2331309319,51.2037391663],"type":"Point"}
}