{
  "type": "Feature",
  "properties": {
    "iso:country":"BE",
    "sg:address":"Rue Nigely 27",
    "sg:city":"Florenville (fontenoille)",
    "sg:classifiers":[
        {
            "category":"Bakery",
            "type":"Food & Drink"
        }
    ],
    "sg:phone":"+32 61 31 14 09",
    "sg:postcode":"6820",
    "sg:province":"Luxembourg",
    "sg:tags":[
        "confectioner",
        "baker"
    ],
    "wof:name":"Mathias W",
    "wof:placetype":"venue"
},
  "geometry": {"coordinates":[5.2321548462,49.7148475647],"type":"Point"}
}