{
  "type": "Feature",
  "properties": {
    "iso:country":"BE",
    "sg:address":"Spinnerslaan 3",
    "sg:city":"Lokeren",
    "sg:classifiers":[
        {
            "category":"Building & Trades",
            "subcategory":"Pest Control",
            "type":"Services"
        }
    ],
    "sg:phone":"+32 9 348 49 73",
    "sg:postcode":"9160",
    "sg:province":"Oost-Vlaanderen",
    "sg:tags":[
        "painting",
        "contractor"
    ],
    "wof:name":"Buijsse Bvba",
    "wof:placetype":"venue"
},
  "geometry": {"coordinates":[4.0159330368,51.1109542847],"type":"Point"}
}