{
  "type": "Feature",
  "properties": {
    "addr:full":"Boulevard De Froimond 24 Liege Li\u00e8ge 4020",
    "addr:housenumber":"24",
    "addr:postcode":"4020",
    "addr:street":"Boulevard De Froimond",
    "iso:country":"BE",
    "sg:address":"Boulevard De Froimond 24",
    "sg:city":"Liege",
    "sg:orig_category":"Entretien and r\u00e9parations de voitures. Entretien and r\u00e9parations de voitures",
    "sg:phone":"+32 4 349 00 65",
    "sg:postcode":"4020",
    "sg:province":"Li\u00e8ge",
    "wof:name":"Car Wash",
    "wof:placetype":"venue"
},
  "geometry": {"coordinates":[5.5898051262,50.6247825623],"type":"Point"}
}