{
  "type": "Feature",
  "properties": {
    "iso:country":"BE",
    "sg:address":"Lange Breestraat 29",
    "sg:city":"Lebbeke",
    "sg:classifiers":[
        {
            "category":"Shopping",
            "subcategory":"Florist",
            "type":"Retail Goods"
        }
    ],
    "sg:phone":"+32 52 35 72 31",
    "sg:postcode":"9280",
    "sg:province":"Oost-Vlaanderen",
    "wof:name":"Julco Flower",
    "wof:placetype":"venue"
},
  "geometry": {"coordinates":[4.1529331207,50.9770278931],"type":"Point"}
}