{
  "type": "Feature",
  "properties": {
    "iso:country":"BE",
    "sg:address":"Gouverneur Roppesingel 131",
    "sg:city":"Hasselt",
    "sg:classifiers":[
        {
            "category":"Professional",
            "subcategory":"Lawyer & Legal Services",
            "type":"Services"
        }
    ],
    "sg:phone":"+32 11 28 15 00",
    "sg:postcode":"3500",
    "sg:province":"Limburg",
    "wof:name":"Grouwels Gregory",
    "wof:placetype":"venue"
},
  "geometry": {"coordinates":[5.3501992226,50.9177055359],"type":"Point"}
}