{
  "type": "Feature",
  "properties": {
    "addr:full":"Oordegemsesteenweg 1a Wetteren Oost-Vlaanderen 9230",
    "addr:housenumber":"1a",
    "addr:postcode":"9230",
    "addr:street":"Oordegemsesteenweg",
    "iso:country":"BE",
    "sg:address":"Oordegemsesteenweg 1a",
    "sg:city":"Wetteren",
    "sg:classifiers":[
        {
            "category":"Building & Trades",
            "subcategory":"Landscaping Services",
            "type":"Services"
        }
    ],
    "sg:phone":"+32 9 365 04 27",
    "sg:postcode":"9230",
    "sg:province":"Oost-Vlaanderen",
    "sg:tags":[
        "gardening",
        "garden",
        "maintenance"
    ],
    "wof:name":"De Bruycker S",
    "wof:placetype":"venue"
},
  "geometry": {"coordinates":[3.8850669861,51.0016326904],"type":"Point"}
}