{
  "type": "Feature",
  "properties": {
    "iso:country":"BE",
    "sg:address":"Klein Kolmenstraat 5",
    "sg:city":"Alken",
    "sg:classifiers":[
        {
            "category":"Retail",
            "subcategory":"Auto Repair",
            "type":"Services"
        }
    ],
    "sg:phone":"+32 11 59 64 84",
    "sg:postcode":"3570",
    "sg:province":"Limburg",
    "sg:tags":[
        "automobile",
        "-",
        "wrecking"
    ],
    "wof:name":"Wemar-cars Import-export Bvba",
    "wof:placetype":"venue"
},
  "geometry": {"coordinates":[5.2942280769,50.8866233826],"type":"Point"}
}