{
  "type": "Feature",
  "properties": {
    "iso:country":"BE",
    "sg:address":"Rue Auguste Hainaut 13",
    "sg:city":"Jette/jette",
    "sg:orig_category":"Entretien and r\u00e9parations de voitures. V\u00e9hicules automobiles. D\u00e9taillants en pi\u00e8ces and accessoires ",
    "sg:phone":"+32 2 426 62 15",
    "sg:postcode":"1090",
    "sg:province":"Bruxelles-Capitale",
    "wof:name":"Werrie Motor's",
    "wof:placetype":"venue"
},
  "geometry": {"coordinates":[4.3356528282,50.8683547974],"type":"Point"}
}