{
  "type": "Feature",
  "properties": {
    "addr:full":"Route De Marche 72 Durbuy (barvaux-sur-ourthe) Luxembourg 6940",
    "addr:housenumber":"72",
    "addr:postcode":"6940",
    "addr:street":"Route De Marche",
    "iso:country":"BE",
    "sg:address":"Route De Marche 72",
    "sg:city":"Durbuy (barvaux-sur-ourthe)",
    "sg:classifiers":[
        {
            "category":"Shopping",
            "subcategory":"Pets & Pet Supplies",
            "type":"Retail Goods"
        }
    ],
    "sg:phone":"+32 86 21 25 70",
    "sg:postcode":"6940",
    "sg:province":"Luxembourg",
    "sg:tags":[
        "shop",
        "-"
    ],
    "wof:name":"Martiny Et Cie",
    "wof:placetype":"venue"
},
  "geometry": {"coordinates":[5.4543361664,50.3515777588],"type":"Point"}
}