{
  "type": "Feature",
  "properties": {
    "iso:country":"BE",
    "sg:address":"Nieuwstraat 53",
    "sg:city":"Lummen",
    "sg:orig_category":"Travaux de pl\u00e2trage",
    "sg:phone":"+32 11 42 83 64",
    "sg:postcode":"3560",
    "sg:province":"Limburg",
    "wof:name":"Eddy Wouters",
    "wof:placetype":"venue"
},
  "geometry": {"coordinates":[5.2254347801,51.0102577209],"type":"Point"}
}