{
  "type": "Feature",
  "properties": {
    "addr:full":"Cathilleweg 43 B Stalhille West-Vlaanderen 8490",
    "addr:housenumber":"43 b",
    "addr:postcode":"8490",
    "addr:street":"Cathilleweg;Stalhille West-Vlaanderen",
    "iso:country":"BE",
    "sg:address":"Cathilleweg 43 B",
    "sg:city":"Stalhille",
    "sg:classifiers":[
        {
            "category":"Home & Garden",
            "subcategory":"Furniture",
            "type":"Retail Goods"
        }
    ],
    "sg:phone":"+32 50 81 21 20",
    "sg:postcode":"8490",
    "sg:province":"West-Vlaanderen",
    "sg:tags":[
        "household",
        "wood"
    ],
    "wof:name":"Novifor Nv",
    "wof:placetype":"venue"
},
  "geometry": {"coordinates":[3.0742590427,51.2114219666],"type":"Point"}
}