{
  "type": "Feature",
  "properties": {
    "iso:country":"BE",
    "sg:address":"Avenue Du Marquis 1",
    "sg:city":"Fleurus",
    "sg:orig_category":"Transports routiers de marchandises",
    "sg:phone":"+32 71 81 97 54",
    "sg:postcode":"6220",
    "sg:province":"Hainaut",
    "wof:name":"T.g.p.",
    "wof:placetype":"venue"
},
  "geometry": {"coordinates":[4.5300951004,50.4583282471],"type":"Point"}
}