{
  "type": "Feature",
  "properties": {
    "iso:country":"BE",
    "sg:address":"Koningsbaan 28ba",
    "sg:city":"Putte",
    "sg:classifiers":[
        {
            "category":"Communications",
            "subcategory":"Television Station",
            "type":"Services"
        }
    ],
    "sg:phone":"+32 15 75 54 09",
    "sg:postcode":"2580",
    "sg:province":"Antwerpen",
    "sg:tags":[
        "video",
        "audio",
        "verhuur"
    ],
    "wof:name":"Videotheek Videostar",
    "wof:placetype":"venue"
},
  "geometry": {"coordinates":[4.6731228828,51.0568504333],"type":"Point"}
}