{
  "type": "Feature",
  "properties": {
    "addr:full":"Justitiestraat 85 Antwerpen Antwerpen 2018",
    "addr:housenumber":"85",
    "addr:postcode":"2018",
    "addr:street":"Justitiestraat",
    "iso:country":"BE",
    "sg:address":"Justitiestraat 85",
    "sg:city":"Antwerpen",
    "sg:classifiers":[
        {
            "category":"Restaurant",
            "type":"Food & Drink"
        }
    ],
    "sg:phone":"+32 3 237 07 59",
    "sg:postcode":"2018",
    "sg:province":"Antwerpen",
    "sg:tags":[
        "caf\u00e9s"
    ],
    "wof:name":"Louisa Duden",
    "wof:placetype":"venue"
},
  "geometry": {"coordinates":[4.4033780098,51.2079811096],"type":"Point"}
}