{
  "type": "Feature",
  "properties": {
    "addr:full":"Rue Charles Jaumotte 96 Wavre (limal) Brabant Wallon 1300",
    "addr:housenumber":"96",
    "addr:postcode":"1300",
    "addr:street":"Rue Charles Jaumotte;Wallon",
    "iso:country":"BE",
    "sg:address":"Rue Charles Jaumotte 96",
    "sg:city":"Wavre (limal)",
    "sg:classifiers":[
        {
            "category":"Building & Trades",
            "subcategory":"Landscaping Services",
            "type":"Services"
        }
    ],
    "sg:phone":"+32 10 41 54 49",
    "sg:postcode":"1300",
    "sg:province":"Brabant Wallon",
    "sg:tags":[
        "gardening",
        "garden",
        "maintenance"
    ],
    "wof:name":"Commerman Laurent",
    "wof:placetype":"venue"
},
  "geometry": {"coordinates":[4.578327179,50.6984214783],"type":"Point"}
}