{
  "type": "Feature",
  "properties": {
    "addr:full":"Les Tilleuls 35 Walcourt (somz\u00e9e) Namur 5651",
    "addr:housenumber":"35",
    "addr:postcode":"5651",
    "addr:street":"Somze\u0301E",
    "iso:country":"BE",
    "sg:address":"Les Tilleuls 35",
    "sg:city":"Walcourt (somz\u00e9e)",
    "sg:classifiers":[
        {
            "category":"Professional",
            "subcategory":"Accounting & Tax Preparation",
            "type":"Services"
        }
    ],
    "sg:phone":"+32 71 21 51 43",
    "sg:postcode":"5651",
    "sg:province":"Namur",
    "sg:tags":[
        "bookkeeper"
    ],
    "wof:name":"Mauclet Ch & Cie Sprl",
    "wof:placetype":"venue"
},
  "geometry": {"coordinates":[4.4005570412,50.2859687805],"type":"Point"}
}