{
  "type": "Feature",
  "properties": {
    "addr:full":"Wittestraat 97 Antwerpen Antwerpen 2020",
    "addr:housenumber":"97",
    "addr:postcode":"2020",
    "addr:street":"Wittestraat",
    "iso:country":"BE",
    "sg:address":"Wittestraat 97",
    "sg:city":"Antwerpen",
    "sg:classifiers":[
        {
            "category":"Food & Beverages",
            "subcategory":"Fruits & Vegetables",
            "type":"Retail Goods"
        }
    ],
    "sg:phone":"+32 3 238 87 36",
    "sg:postcode":"2020",
    "sg:province":"Antwerpen",
    "sg:tags":[
        "l\u00e9gumes"
    ],
    "wof:name":"Maria De Vos",
    "wof:placetype":"venue"
},
  "geometry": {"coordinates":[4.3845949173,51.1878013611],"type":"Point"}
}