{
  "type": "Feature",
  "properties": {
    "addr:full":"Leuvenselaan 472 Tienen Vlaams-Brabant 3300",
    "addr:housenumber":"472",
    "addr:postcode":"3300",
    "addr:street":"Leuvenselaan",
    "iso:country":"BE",
    "sg:address":"Leuvenselaan 472",
    "sg:city":"Tienen",
    "sg:classifiers":[
        {
            "category":"Sports & Exercise",
            "subcategory":"Bowling",
            "type":"Entertainment"
        }
    ],
    "sg:phone":"+32 16 82 46 46",
    "sg:postcode":"3300",
    "sg:province":"Vlaams-Brabant",
    "sg:tags":[
        "skittle",
        "alley"
    ],
    "wof:name":"Accro Nv",
    "wof:placetype":"venue"
},
  "geometry": {"coordinates":[4.9067468643,50.8170204163],"type":"Point"}
}