{
  "type": "Feature",
  "properties": {
    "iso:country":"BE",
    "sg:address":"Rue Jean Jaures 42",
    "sg:city":"La Louviere",
    "sg:orig_category":"Advocaten and juridische adviseurs",
    "sg:phone":"+32 64 84 90 25",
    "sg:postcode":"7100",
    "sg:province":"Hainaut",
    "wof:name":"No\u00cbla Bricourt",
    "wof:placetype":"venue"
},
  "geometry": {"coordinates":[4.1874070168,50.4805145264],"type":"Point"}
}