{
  "type": "Feature",
  "properties": {
    "iso:country":"BE",
    "sg:address":"Losweg 13",
    "sg:city":"Gent (mariakerke)",
    "sg:classifiers":[
        {
            "category":"Building & Trades",
            "subcategory":"Landscaping Services",
            "type":"Services"
        }
    ],
    "sg:phone":"+32 9 226 18 56",
    "sg:postcode":"9030",
    "sg:province":"Oost-Vlaanderen",
    "sg:tags":[
        "architect",
        "landscape"
    ],
    "wof:name":"Gleeve",
    "wof:placetype":"venue"
},
  "geometry": {"coordinates":[3.6920130253,51.0788192749],"type":"Point"}
}