{
  "type": "Feature",
  "properties": {
    "addr:full":"Rue Saint-s\u00c9bastien 28 Braine-l\u00b4alleud Brabant Wallon 1420",
    "addr:housenumber":"28",
    "addr:postcode":"1420",
    "addr:street":"Rue Saint-Se\u0301Bastien;Brabant Wallon",
    "iso:country":"BE",
    "sg:address":"Rue Saint-s\u00c9bastien 28",
    "sg:city":"Braine-l\u00b4alleud",
    "sg:orig_category":"D\u00e9corateurs d'int\u00e9rieur",
    "sg:phone":"+32 2 384 88 89",
    "sg:postcode":"1420",
    "sg:province":"Brabant Wallon",
    "wof:name":"Cerqua Groupe",
    "wof:placetype":"venue"
},
  "geometry": {"coordinates":[4.3766441345,50.6787033081],"type":"Point"}
}