{
  "type": "Feature",
  "properties": {
    "addr:full":"Chauss\u00c9e D'alsemberg 575 Bruxelles Bruxelles-Capitale 1180",
    "addr:housenumber":"575",
    "addr:postcode":"1180",
    "addr:street":"Chausse\u0301E D'Alsemberg",
    "iso:country":"BE",
    "sg:address":"Chauss\u00c9e D'alsemberg 575",
    "sg:city":"Bruxelles",
    "sg:orig_category":"Mat\u00e9riel \u00e9lectrique and \u00e9lectronique Gr",
    "sg:phone":"+32 2 343 70 52",
    "sg:postcode":"1180",
    "sg:province":"Bruxelles-Capitale",
    "wof:name":"Usitec",
    "wof:placetype":"venue"
},
  "geometry": {"coordinates":[4.3370609283,50.8091087341],"type":"Point"}
}