{
  "type": "Feature",
  "properties": {
    "addr:full":"Begonialaan 14 Lokeren Oost-Vlaanderen 9160",
    "addr:housenumber":"14",
    "addr:postcode":"9160",
    "addr:street":"Begonialaan",
    "iso:country":"BE",
    "sg:address":"Begonialaan 14",
    "sg:city":"Lokeren",
    "sg:orig_category":"Boekhouders",
    "sg:phone":"+32 9 348 29 54",
    "sg:postcode":"9160",
    "sg:province":"Oost-Vlaanderen",
    "wof:name":"Ediste Rombaut",
    "wof:placetype":"venue"
},
  "geometry": {"coordinates":[3.9919168949,51.1124038696],"type":"Point"}
}