{
  "type": "Feature",
  "properties": {
    "addr:full":"Frans Van Haelenstraat 22 Bornem Antwerpen 2880",
    "addr:housenumber":"22",
    "addr:postcode":"2880",
    "addr:street":"Frans Van Haelenstraat",
    "iso:country":"BE",
    "sg:address":"Frans Van Haelenstraat 22",
    "sg:city":"Bornem",
    "sg:classifiers":[
        {
            "category":"Personal",
            "subcategory":"Beauty Salon",
            "type":"Services"
        }
    ],
    "sg:phone":"+32 3 889 61 49",
    "sg:postcode":"2880",
    "sg:province":"Antwerpen",
    "sg:tags":[
        "de",
        "coiffure"
    ],
    "wof:name":"Coiffure Sandra",
    "wof:placetype":"venue"
},
  "geometry": {"coordinates":[4.267083168,51.1034736633],"type":"Point"}
}