{
  "type": "Feature",
  "properties": {
    "addr:full":"Rue De Mons 129 Quievrain Hainaut 7380",
    "addr:housenumber":"129",
    "addr:postcode":"7380",
    "addr:street":"Rue De Mons;Hainaut",
    "iso:country":"BE",
    "sg:address":"Rue De Mons 129",
    "sg:city":"Quievrain",
    "sg:orig_category":"Entretien and r\u00e9parations de voitures. V\u00e9hicules automobiles",
    "sg:phone":"+32 65 45 74 83",
    "sg:postcode":"7380",
    "sg:province":"Hainaut",
    "wof:name":"Garage Paniez",
    "wof:placetype":"venue"
},
  "geometry": {"coordinates":[3.6938829422,50.4086227417],"type":"Point"}
}