{
  "type": "Feature",
  "properties": {
    "iso:country":"BE",
    "sg:address":"Hendrik Consciencelaan 10",
    "sg:city":"Essen",
    "sg:orig_category":"Rev\u00eatements de sols and murs",
    "sg:phone":"+32 3 667 54 57",
    "sg:postcode":"2910",
    "sg:province":"Antwerpen",
    "wof:name":"Webo",
    "wof:placetype":"venue"
},
  "geometry": {"coordinates":[4.443903923,51.4551506042],"type":"Point"}
}