{
  "type": "Feature",
  "properties": {
    "addr:full":"Rue De Roubaix 96 Mouscron Hainaut 7700",
    "addr:housenumber":"96",
    "addr:postcode":"7700",
    "addr:street":"Rue De Roubaix",
    "iso:country":"BE",
    "sg:address":"Rue De Roubaix 96",
    "sg:city":"Mouscron",
    "sg:classifiers":[
        {
            "category":"Autos & Motor Vehicles",
            "subcategory":"Recreational Vehicle Sales",
            "type":"Retail Goods"
        }
    ],
    "sg:phone":"+32 56 33 25 00",
    "sg:postcode":"7700",
    "sg:province":"Hainaut",
    "sg:tags":[
        "special-purpose"
    ],
    "wof:name":"Saint Christophe S.p.r.l.",
    "wof:placetype":"venue"
},
  "geometry": {"coordinates":[3.2081809044,50.737701416],"type":"Point"}
}