{
  "type": "Feature",
  "properties": {
    "addr:full":"Roelandsveldstraat 53 Dilbeek Vlaams-Brabant 1700",
    "addr:housenumber":"53",
    "addr:postcode":"1700",
    "addr:street":"Roelandsveldstraat",
    "iso:country":"BE",
    "sg:address":"Roelandsveldstraat 53",
    "sg:city":"Dilbeek",
    "sg:classifiers":[
        {
            "category":"Personal",
            "type":"Services"
        }
    ],
    "sg:phone":"+32 2 347 26 98",
    "sg:postcode":"1700",
    "sg:province":"Vlaams-Brabant",
    "sg:tags":[
        "party",
        "planning"
    ],
    "wof:name":"Dominique (traiteur) Sprl",
    "wof:placetype":"venue"
},
  "geometry": {"coordinates":[4.2570548058,50.8438491821],"type":"Point"}
}