{
  "type": "Feature",
  "properties": {
    "addr:full":"Sint-anna 69 Hamme Oost-Vlaanderen 9220",
    "addr:housenumber":"69",
    "addr:postcode":"9220",
    "addr:street":"Sint-Anna",
    "iso:country":"BE",
    "sg:address":"Sint-anna 69",
    "sg:city":"Hamme",
    "sg:orig_category":"Plaatsen van vloer- and muurbekleding Schilders",
    "sg:phone":"+32 52 47 82 22",
    "sg:postcode":"9220",
    "sg:province":"Oost-Vlaanderen",
    "wof:name":"Emiel Van Erdeghem",
    "wof:placetype":"venue"
},
  "geometry": {"coordinates":[4.0773491859,51.0945167542],"type":"Point"}
}