{
  "type": "Feature",
  "properties": {
    "iso:country":"BE",
    "sg:address":"Chauss\u00c9e D'alsemberg 473",
    "sg:city":"Ukkel/uccle",
    "sg:orig_category":"Alimentation sp\u00e9cialis\u00e9e",
    "sg:phone":"+32 2 344 62 43",
    "sg:postcode":"1180",
    "sg:province":"Bruxelles-Capitale",
    "wof:name":"Eurovol",
    "wof:placetype":"venue"
},
  "geometry": {"coordinates":[4.3379449844,50.8116607666],"type":"Point"}
}