{
  "type": "Feature",
  "properties": {
    "iso:country":"BE",
    "sg:address":"Rue Des Cottages 96",
    "sg:city":"Bruxelles (uccle)",
    "sg:classifiers":[
        {
            "category":"Arts & Performance",
            "subcategory":"Music",
            "type":"Entertainment"
        }
    ],
    "sg:phone":"+32 2 343 01 85",
    "sg:postcode":"1180",
    "sg:province":"Bruxelles-Capitale",
    "sg:tags":[
        "freelance",
        "musician"
    ],
    "wof:name":"Chale E",
    "wof:placetype":"venue"
},
  "geometry": {"coordinates":[4.3429927826,50.8116722107],"type":"Point"}
}