{
  "type": "Feature",
  "properties": {
    "addr:full":"2820 Bonheiden (groot) Antwerpen 2820",
    "addr:postcode":"2820;2820",
    "addr:street":"Groot Antwerpen",
    "iso:country":"BE",
    "sg:address":"2820",
    "sg:city":"Bonheiden (groot)",
    "sg:orig_category":"Pharmaciens",
    "sg:phone":"+32 900 10 500",
    "sg:postcode":"2820",
    "sg:province":"Antwerpen",
    "wof:name":"Pharmacies De Garde",
    "wof:placetype":"venue"
},
  "geometry": {"coordinates":[4.5496602058,51.0218009949],"type":"Point"}
}