{
  "type": "Feature",
  "properties": {
    "iso:country":"BE",
    "sg:address":"Kliniekstraat 104",
    "sg:city":"Gent",
    "sg:orig_category":"Geluidsopnames",
    "sg:phone":"+32 2 219 58 63",
    "sg:postcode":"9050",
    "sg:province":"Oost-Vlaanderen",
    "wof:name":"Anna-loog Productions",
    "wof:placetype":"venue"
},
  "geometry": {"coordinates":[3.7543361187,51.0410041809],"type":"Point"}
}