{
  "type": "Feature",
  "properties": {
    "addr:full":"Mgr. Simenonlaan 60 Riemst Limburg 3770",
    "addr:housenumber":"60",
    "addr:postcode":"3770",
    "addr:street":"Mgr. Simenonlaan",
    "iso:country":"BE",
    "sg:address":"Mgr. Simenonlaan 60",
    "sg:city":"Riemst",
    "sg:orig_category":"M\u00e9decins and sp\u00e9cialistes",
    "sg:phone":"+32 12 45 46 56",
    "sg:postcode":"3770",
    "sg:province":"Limburg",
    "wof:name":"Maria-therese Niesten",
    "wof:placetype":"venue"
},
  "geometry": {"coordinates":[5.5969901085,50.8109016418],"type":"Point"}
}