{
  "type": "Feature",
  "properties": {
    "iso:country":"BE",
    "sg:address":"Rue De L'intendant 262",
    "sg:city":"Bruxelles (molenbeek-saint-jean)",
    "sg:classifiers":[
        {
            "category":"Utilities",
            "subcategory":"Telephone",
            "type":"Services"
        }
    ],
    "sg:phone":"+32 2 426 38 02",
    "sg:postcode":"1080",
    "sg:province":"Bruxelles-Capitale",
    "sg:tags":[
        "-",
        "internet"
    ],
    "wof:name":"Cyberwork",
    "wof:placetype":"venue"
},
  "geometry": {"coordinates":[4.3356781006,50.863609314],"type":"Point"}
}