{
  "type": "Feature",
  "properties": {
    "iso:country":"BE",
    "sg:address":"Pont De Tournay 1",
    "sg:city":"Neufch\u00e2teau",
    "sg:classifiers":[
        {
            "category":"Health Services",
            "subcategory":"Doctor",
            "type":"Services"
        }
    ],
    "sg:phone":"+32 61 27 79 55",
    "sg:postcode":"6840",
    "sg:province":"Luxembourg",
    "sg:tags":[
        "medicinephysicians",
        "surgeon"
    ],
    "wof:name":"Bleyenheuft L",
    "wof:placetype":"venue"
},
  "geometry": {"coordinates":[5.4346451759,49.8411598206],"type":"Point"}
}