{
  "type": "Feature",
  "properties": {
    "addr:full":"Vieux Chemin De Binche 507 Mons Hainaut 7000",
    "addr:housenumber":"507",
    "addr:postcode":"7000",
    "addr:street":"Vieux Chemin De Binche;Hainaut",
    "iso:country":"BE",
    "sg:address":"Vieux Chemin De Binche 507",
    "sg:city":"Mons",
    "sg:orig_category":"M\u00e9decins and sp\u00e9cialistes",
    "sg:phone":"+32 65 35 20 74",
    "sg:postcode":"7000",
    "sg:province":"Hainaut",
    "wof:name":"Pol Siraux",
    "wof:placetype":"venue"
},
  "geometry": {"coordinates":[4.0019831657,50.462562561],"type":"Point"}
}