{
  "type": "Feature",
  "properties": {
    "addr:full":"Blauw Huisstraat 39 Izegem West-Vlaanderen 8870",
    "addr:housenumber":"39",
    "addr:postcode":"8870",
    "addr:street":"Blauw Huisstraat",
    "iso:country":"BE",
    "sg:address":"Blauw Huisstraat 39",
    "sg:city":"Izegem",
    "sg:classifiers":[
        {
            "category":"Banks & Credit Unions",
            "subcategory":"Investment Brokerage",
            "type":"Services"
        }
    ],
    "sg:phone":"+32 69 21 19 68",
    "sg:postcode":"8870",
    "sg:province":"West-Vlaanderen",
    "wof:name":"Staver Consulting Sprl",
    "wof:placetype":"venue"
},
  "geometry": {"coordinates":[3.2244570255,50.9140853882],"type":"Point"}
}