{
  "type": "Feature",
  "properties": {
    "addr:full":"Blinde-rodenbachstraat 103 Roeselare West-Vlaanderen 8800",
    "addr:housenumber":"103",
    "addr:postcode":"8800",
    "addr:street":"Blinde-Rodenbachstraat",
    "iso:country":"BE",
    "sg:address":"Blinde-rodenbachstraat 103",
    "sg:city":"Roeselare",
    "sg:orig_category":"Rev\u00eatements pour sols and murs. Peinture",
    "sg:phone":"+32 51 24 37 83",
    "sg:postcode":"8800",
    "sg:province":"West-Vlaanderen",
    "wof:name":"Ivan Soete",
    "wof:placetype":"venue"
},
  "geometry": {"coordinates":[3.1372010708,50.931678772],"type":"Point"}
}