{
  "type": "Feature",
  "properties": {
    "iso:country":"BE",
    "sg:address":"Rue Walth\u00c8re Jamar 2ba",
    "sg:city":"Ans",
    "sg:orig_category":"Artsen and specialisten",
    "sg:phone":"+32 4 226 11 82",
    "sg:postcode":"4430",
    "sg:province":"Li\u00e8ge",
    "wof:name":"Robert Sadet",
    "wof:placetype":"venue"
},
  "geometry": {"coordinates":[5.5475568771,50.6501235962],"type":"Point"}
}