{
  "type": "Feature",
  "properties": {
    "addr:full":"Bissegemstraat 75 Wevelgem (gullegem) West-Vlaanderen 8560",
    "addr:housenumber":"75",
    "addr:postcode":"8560",
    "addr:street":"Bissegemstraat",
    "iso:country":"BE",
    "sg:address":"Bissegemstraat 75",
    "sg:city":"Wevelgem (gullegem)",
    "sg:classifiers":[
        {
            "category":"Shopping",
            "subcategory":"Bicycles & Sporting Goods",
            "type":"Retail Goods"
        }
    ],
    "sg:phone":"+32 56 41 94 68",
    "sg:postcode":"8560",
    "sg:province":"West-Vlaanderen",
    "sg:tags":[
        "-"
    ],
    "wof:name":"Ponseele Rudi",
    "wof:placetype":"venue"
},
  "geometry": {"coordinates":[3.2076039314,50.8407402039],"type":"Point"}
}