{
  "type": "Feature",
  "properties": {
    "addr:full":"Vlamingstraat 10 Knokke-heist (heist-aan-zee) West-Vlaanderen 8301",
    "addr:housenumber":"10",
    "addr:postcode":"8301",
    "addr:street":"Vlamingstraat",
    "iso:country":"BE",
    "sg:address":"Vlamingstraat 10",
    "sg:city":"Knokke-heist (heist-aan-zee)",
    "sg:classifiers":[
        {
            "category":"Bars & Pubs",
            "type":"Food & Drink"
        }
    ],
    "sg:phone":"+32 50 51 18 96",
    "sg:postcode":"8301",
    "sg:province":"West-Vlaanderen",
    "sg:tags":[
        "tavern"
    ],
    "wof:name":"Breughel",
    "wof:placetype":"venue"
},
  "geometry": {"coordinates":[3.2639000416,51.3396911621],"type":"Point"}
}