{
  "type": "Feature",
  "properties": {
    "addr:full":"Rue Des Campeaux 2 Frasnes-lez-anvaing (saint-sauveur) Hainaut 7912",
    "addr:housenumber":"2;7912",
    "addr:street":"Rue Des Campeaux;Frasnes-Lez-Anvaing Saint-Sauveur Hainaut",
    "iso:country":"BE",
    "sg:address":"Rue Des Campeaux 2",
    "sg:city":"Frasnes-lez-anvaing (saint-sauveur)",
    "sg:classifiers":[
        {
            "category":"Landmark",
            "subcategory":"Scenic View",
            "type":"Public Place"
        }
    ],
    "sg:phone":"+32 69 76 64 97",
    "sg:postcode":"7912",
    "sg:province":"Hainaut",
    "sg:tags":[
        "setting",
        "photographic"
    ],
    "wof:name":"Grapho-print",
    "wof:placetype":"venue"
},
  "geometry": {"coordinates":[3.5938699245,50.7053031921],"type":"Point"}
}