{
  "type": "Feature",
  "properties": {
    "addr:full":"Nieuwstraat 59a Keerbergen Vlaams-Brabant 3140",
    "addr:housenumber":"59a",
    "addr:postcode":"3140",
    "addr:street":"Nieuwstraat",
    "iso:country":"BE",
    "sg:address":"Nieuwstraat 59a",
    "sg:city":"Keerbergen",
    "sg:orig_category":"Woningbouw",
    "sg:phone":"+32 15 23 66 73",
    "sg:postcode":"3140",
    "sg:province":"Vlaams-Brabant",
    "wof:name":"Ronald De Leebeeck",
    "wof:placetype":"venue"
},
  "geometry": {"coordinates":[4.6903791428,51.0106735229],"type":"Point"}
}