{
  "type": "Feature",
  "properties": {
    "iso:country":"BE",
    "sg:address":"Rue Des Papeteries 6",
    "sg:city":"Chaumont-gistoux",
    "sg:classifiers":[
        {
            "category":"Health Services",
            "subcategory":"Health Practitioner",
            "type":"Services"
        }
    ],
    "sg:phone":"+32 10 68 99 16",
    "sg:postcode":"1325",
    "sg:province":"Brabant Wallon",
    "sg:tags":[
        "physiotherapist"
    ],
    "wof:name":"Van Den Berghe Jacques",
    "wof:placetype":"venue"
},
  "geometry": {"coordinates":[4.6967377663,50.6810646057],"type":"Point"}
}