{
  "type": "Feature",
  "properties": {
    "iso:country":"BE",
    "sg:address":"30",
    "sg:city":"Guldensporenpark 9820 Gent",
    "sg:classifiers":[
        {
            "category":"Utilities",
            "subcategory":"Electric",
            "type":"Services"
        }
    ],
    "sg:phone":"+32 9 210 38 11",
    "sg:postcode":"30",
    "sg:tags":[
        "electricity",
        "electronic",
        "electrical",
        "equipment"
    ],
    "wof:name":"Ge Power Controls Belgium Bvba",
    "wof:placetype":"venue"
},
  "geometry": {"coordinates":[3.7454690933,50.9947395325],"type":"Point"}
}