{
  "type": "Feature",
  "properties": {
    "addr:full":"Kalvarieberglaan 24 Overijse Vlaams-Brabant 3090",
    "addr:housenumber":"24",
    "addr:postcode":"3090",
    "addr:street":"Kalvarieberglaan",
    "iso:country":"BE",
    "sg:address":"Kalvarieberglaan 24",
    "sg:city":"Overijse",
    "sg:orig_category":"Kapsalons",
    "sg:phone":"+32 2 687 71 96",
    "sg:postcode":"3090",
    "sg:province":"Vlaams-Brabant",
    "wof:name":"Jeanne",
    "wof:placetype":"venue"
},
  "geometry": {"coordinates":[4.5450668335,50.7759513855],"type":"Point"}
}