{
  "type": "Feature",
  "properties": {
    "iso:country":"BE",
    "sg:address":"Voie Des Jardinets 52",
    "sg:city":"Verlaine",
    "sg:classifiers":[
        {
            "category":"Wholesale",
            "subcategory":"Fruits & Vegetables",
            "type":"Manufacturing & Wholesale Goods"
        }
    ],
    "sg:phone":"+32 4 259 65 02",
    "sg:postcode":"4537",
    "sg:province":"Li\u00e8ge",
    "sg:tags":[
        "whol",
        "-",
        "potato"
    ],
    "wof:name":"Grammen Y",
    "wof:placetype":"venue"
},
  "geometry": {"coordinates":[5.3243398666,50.6148414612],"type":"Point"}
}