{
  "type": "Feature",
  "properties": {
    "iso:country":"BE",
    "sg:address":"Chauss\u00c9e De Namur 11",
    "sg:city":"Profondeville",
    "sg:orig_category":"Herstellingen and onderhoud van auto's",
    "sg:phone":"+32 81 41 26 39",
    "sg:postcode":"5170",
    "sg:province":"Namur",
    "wof:name":"Garage Bertrand",
    "wof:placetype":"venue"
},
  "geometry": {"coordinates":[4.8679728508,50.3777656555],"type":"Point"}
}