{
  "type": "Feature",
  "properties": {
    "iso:country":"BE",
    "sg:address":"Chauss\u00c9e De Bruxelles 281",
    "sg:city":"Vorst/forest",
    "sg:orig_category":"M\u00e9decines alternatives",
    "sg:phone":"+32 2 347 48 10",
    "sg:postcode":"1190",
    "sg:province":"Bruxelles-Capitale",
    "wof:name":"Martine Van Avermaet",
    "wof:placetype":"venue"
},
  "geometry": {"coordinates":[4.3320522308,50.8216781616],"type":"Point"}
}