{
  "type": "Feature",
  "properties": {
    "addr:full":"Ferdinand Depuydtlaan 41 Ichtegem (eernegem) West-Vlaanderen 8480",
    "addr:housenumber":"41",
    "addr:postcode":"8480",
    "addr:street":"Depuydtlaan",
    "iso:country":"BE",
    "sg:address":"Ferdinand Depuydtlaan 41",
    "sg:city":"Ichtegem (eernegem)",
    "sg:classifiers":[
        {
            "category":"Retail",
            "subcategory":"Veterinary Services",
            "type":"Services"
        }
    ],
    "sg:phone":"+32 59 29 91 15",
    "sg:postcode":"8480",
    "sg:province":"West-Vlaanderen",
    "sg:tags":[
        "veterinarian"
    ],
    "wof:name":"Delrue P",
    "wof:placetype":"venue"
},
  "geometry": {"coordinates":[3.0184218884,51.1304321289],"type":"Point"}
}