{
  "type": "Feature",
  "properties": {
    "iso:country":"BE",
    "sg:address":"Kardinaal Cardijnstraat 6",
    "sg:city":"Aarschot",
    "sg:orig_category":"Ordinateurs and \u00e9quipement informatique",
    "sg:phone":"+32 16 56 99 07",
    "sg:postcode":"3200",
    "sg:province":"Vlaams-Brabant",
    "wof:name":"Eon Software",
    "wof:placetype":"venue"
},
  "geometry": {"coordinates":[4.8492398262,50.9956245422],"type":"Point"}
}