{
  "type": "Feature",
  "properties": {
    "addr:full":"Maandagmarkt 10 Halle (groot) Vlaams-Brabant 1500",
    "addr:housenumber":"10;1500",
    "addr:street":"Maandagmarkt;Groot Vlaams-Brabant",
    "iso:country":"BE",
    "sg:address":"Maandagmarkt 10",
    "sg:city":"Halle (groot)",
    "sg:classifiers":[
        {
            "category":"Communications",
            "subcategory":"Film & Video Production",
            "type":"Services"
        }
    ],
    "sg:phone":"+32 2 361 21 53",
    "sg:postcode":"1500",
    "sg:province":"Vlaams-Brabant",
    "sg:tags":[
        "platen",
        "cassette",
        "cd's"
    ],
    "wof:name":"Free Record Shop Belgium Nv-sa",
    "wof:placetype":"venue"
},
  "geometry": {"coordinates":[4.2368340492,50.7359199524],"type":"Point"}
}