{
  "type": "Feature",
  "properties": {
    "iso:country":"BE",
    "sg:address":"Weienhout 11c",
    "sg:city":"Genk",
    "sg:classifiers":[
        {
            "category":"Recreation",
            "type":"Entertainment"
        }
    ],
    "sg:phone":"+32 89 61 56 64",
    "sg:postcode":"3600",
    "sg:province":"Limburg",
    "sg:tags":[
        "diver",
        "amusement"
    ],
    "wof:name":"De Beuk Productions",
    "wof:placetype":"venue"
},
  "geometry": {"coordinates":[5.4653301239,50.9437789917],"type":"Point"}
}