{
  "type": "Feature",
  "properties": {
    "iso:country":"BE",
    "sg:address":"Klokhofstraat 0",
    "sg:city":"Oostende",
    "sg:classifiers":[
        {
            "category":"Arena",
            "subcategory":"Sports Club",
            "type":"Entertainment"
        }
    ],
    "sg:phone":"+32 59 70 13 34",
    "sg:postcode":"8400",
    "sg:province":"West-Vlaanderen",
    "sg:tags":[
        "de"
    ],
    "wof:name":"Koninklijke Oostendse Politieschutterskring",
    "wof:placetype":"venue"
},
  "geometry": {"coordinates":[2.9649550915,51.2080612183],"type":"Point"}
}