{
  "type": "Feature",
  "properties": {
    "addr:full":"Pays De Li\u00c8ge 8 Rendeux Luxembourg 6987",
    "addr:postcode":"6987",
    "iso:country":"BE",
    "sg:address":"Pays De Li\u00c8ge 8",
    "sg:city":"Rendeux",
    "sg:orig_category":"Woningbouw",
    "sg:phone":"+32 84 47 73 24",
    "sg:postcode":"6987",
    "sg:province":"Luxembourg",
    "wof:name":"Xhardez Philippe",
    "wof:placetype":"venue"
},
  "geometry": {"coordinates":[5.4877891541,50.2214317322],"type":"Point"}
}