{
  "type": "Feature",
  "properties": {
    "iso:country":"BE",
    "sg:address":"Rue De La Chapelle 49",
    "sg:city":"Vresse-sur-semois",
    "sg:orig_category":"Artsen and specialisten",
    "sg:phone":"+32 61 50 03 05",
    "sg:postcode":"5550",
    "sg:province":"Namur",
    "wof:name":"Jean Fondaire",
    "wof:placetype":"venue"
},
  "geometry": {"coordinates":[4.9295659065,49.8729858398],"type":"Point"}
}