{
  "type": "Feature",
  "properties": {
    "iso:country":"BE",
    "sg:address":"Avenue Reine Elisabeth 29",
    "sg:city":"Waterloo",
    "sg:classifiers":[
        {
            "category":"Building & Trades",
            "subcategory":"Construction",
            "type":"Services"
        }
    ],
    "sg:phone":"+32 2 354 84 36",
    "sg:postcode":"1410",
    "sg:province":"Brabant Wallon",
    "sg:tags":[
        "work",
        "waterproofing"
    ],
    "wof:name":"Richard",
    "wof:placetype":"venue"
},
  "geometry": {"coordinates":[4.4097371101,50.7057151794],"type":"Point"}
}