{
  "type": "Feature",
  "properties": {
    "iso:country":"BE",
    "sg:address":"Kleidallaan 45",
    "sg:city":"Hemiksem",
    "sg:classifiers":[
        {
            "category":"Home & Garden",
            "subcategory":"Carpets & Floor Coverings",
            "type":"Retail Goods"
        }
    ],
    "sg:phone":"+32 3 887 37 40",
    "sg:postcode":"2620",
    "sg:province":"Antwerpen",
    "sg:tags":[
        "layer",
        "mosaicists"
    ],
    "wof:name":"B & O Bvba",
    "wof:placetype":"venue"
},
  "geometry": {"coordinates":[4.3528838158,51.1364097595],"type":"Point"}
}