{
  "type": "Feature",
  "properties": {
    "addr:full":"Blijde-inkomststraat 164 Leuven Vlaams-Brabant 3000",
    "addr:housenumber":"164",
    "addr:postcode":"3000",
    "iso:country":"BE",
    "sg:address":"Blijde-inkomststraat 164",
    "sg:city":"Leuven",
    "sg:orig_category":"Auto-\u00e9coles",
    "sg:phone":"+32 16 23 35 81",
    "sg:postcode":"3000",
    "sg:province":"Vlaams-Brabant",
    "wof:name":"Rijschool Moderna",
    "wof:placetype":"venue"
},
  "geometry": {"coordinates":[4.7136468887,50.8739738464],"type":"Point"}
}