{
  "type": "Feature",
  "properties": {
    "iso:country":"BE",
    "sg:address":"Koningin Astridstraat 70",
    "sg:city":"Zedelgem (veldegem)",
    "sg:classifiers":[
        {
            "category":"Professional",
            "subcategory":"Accounting & Tax Preparation",
            "type":"Services"
        }
    ],
    "sg:phone":"+32 50 27 88 54",
    "sg:postcode":"8210",
    "sg:province":"West-Vlaanderen",
    "sg:tags":[
        "bookkeeper"
    ],
    "wof:name":"Lannoo D",
    "wof:placetype":"venue"
},
  "geometry": {"coordinates":[3.1458399296,51.1376457214],"type":"Point"}
}