{
  "type": "Feature",
  "properties": {
    "iso:country":"BE",
    "sg:address":"Avenue Du V\u00c9n\u00c9zuela 12",
    "sg:city":"Elsene/ixelles",
    "sg:orig_category":"Architectes",
    "sg:phone":"+32 2 673 60 72",
    "sg:postcode":"1050",
    "sg:province":"Bruxelles-Capitale",
    "wof:name":"Cereau",
    "wof:placetype":"venue"
},
  "geometry": {"coordinates":[4.3910541534,50.8021354675],"type":"Point"}
}