{
  "type": "Feature",
  "properties": {
    "addr:full":"Rue Des Maux 20 Tournai Hainaut 7500",
    "addr:housenumber":"20",
    "addr:postcode":"7500",
    "addr:street":"Rue Des Maux",
    "iso:country":"BE",
    "sg:address":"Rue Des Maux 20",
    "sg:city":"Tournai",
    "sg:classifiers":[
        {
            "category":"Personal",
            "subcategory":"Beauty Salon",
            "type":"Services"
        }
    ],
    "sg:phone":"+32 69 22 90 18",
    "sg:postcode":"7500",
    "sg:province":"Hainaut",
    "sg:tags":[
        "lady",
        "-",
        "hairdressing"
    ],
    "wof:name":"Anais",
    "wof:placetype":"venue"
},
  "geometry": {"coordinates":[3.383589983,50.6063919067],"type":"Point"}
}