{
  "type": "Feature",
  "properties": {
    "addr:full":"Gentseheerweg 62 Izegem West-Vlaanderen 8870",
    "addr:housenumber":"62",
    "addr:postcode":"8870",
    "addr:street":"Gentseheerweg",
    "iso:country":"BE",
    "sg:address":"Gentseheerweg 62",
    "sg:city":"Izegem",
    "sg:classifiers":[
        {
            "category":"Shopping",
            "subcategory":"Stationery & Office Supplies",
            "type":"Retail Goods"
        }
    ],
    "sg:phone":"+32 51 30 16 05",
    "sg:postcode":"8870",
    "sg:province":"West-Vlaanderen",
    "sg:tags":[
        "packaging",
        "material"
    ],
    "wof:name":"Van Beylen Icpm-bellagrafica B.v.b.a.",
    "wof:placetype":"venue"
},
  "geometry": {"coordinates":[3.2281470299,50.9166183472],"type":"Point"}
}