{
  "type": "Feature",
  "properties": {
    "addr:full":"Renier Sniedersstraat 20 Turnhout Antwerpen 2300",
    "addr:housenumber":"20",
    "addr:postcode":"2300",
    "addr:street":"Renier Sniedersstraat",
    "iso:country":"BE",
    "sg:address":"Renier Sniedersstraat 20",
    "sg:city":"Turnhout",
    "sg:orig_category":"Artsen and specialisten",
    "sg:phone":"+32 14 41 33 33",
    "sg:postcode":"2300",
    "sg:province":"Antwerpen",
    "wof:name":"B. Poffyn",
    "wof:placetype":"venue"
},
  "geometry": {"coordinates":[4.9411621094,51.3239021301],"type":"Point"}
}