{
  "type": "Feature",
  "properties": {
    "addr:full":"Rue Saint-nicolas 586 Li\u00c8ge Li\u00e8ge 4000",
    "addr:housenumber":"586",
    "addr:postcode":"4000",
    "addr:street":"Rue Saint-Nicolas",
    "iso:country":"BE",
    "sg:address":"Rue Saint-nicolas 586",
    "sg:city":"Li\u00c8ge",
    "sg:orig_category":"Supermarkten",
    "sg:postcode":"4000",
    "sg:province":"Li\u00e8ge",
    "wof:name":"Aldi",
    "wof:placetype":"venue"
},
  "geometry": {"coordinates":[5.5355200768,50.6403884888],"type":"Point"}
}