{
  "type": "Feature",
  "properties": {
    "iso:country":"BE",
    "sg:address":"Zwanestraat 10",
    "sg:city":"Torhout",
    "sg:classifiers":[
        {
            "category":"Shopping",
            "subcategory":"Clothing, Apparel, & Fashions",
            "type":"Retail Goods"
        }
    ],
    "sg:phone":"+32 50 21 20 18",
    "sg:postcode":"8820",
    "sg:province":"West-Vlaanderen",
    "sg:tags":[
        "ondergoed",
        "lingerie"
    ],
    "wof:name":"Huis Siertex",
    "wof:placetype":"venue"
},
  "geometry": {"coordinates":[3.1007320881,51.0653533936],"type":"Point"}
}