{
  "type": "Feature",
  "properties": {
    "iso:country":"BE",
    "sg:address":"Tentoonstellingslaan 54",
    "sg:city":"Gent-centrum",
    "sg:orig_category":"Advocaten and juridische adviseurs Balie van Gent",
    "sg:phone":"+32 9 223 00 34",
    "sg:postcode":"9000",
    "sg:province":"Oost-Vlaanderen",
    "wof:name":"Cornut Michel",
    "wof:placetype":"venue"
},
  "geometry": {"coordinates":[3.7321069241,51.0398483276],"type":"Point"}
}