{
  "type": "Feature",
  "properties": {
    "iso:country":"BE",
    "sg:address":"Philippe De Denterghemlaan 3a",
    "sg:city":"Sint-martens-latem (deurle)",
    "sg:classifiers":[
        {
            "category":"Professional",
            "subcategory":"Accounting & Tax Preparation",
            "type":"Services"
        }
    ],
    "sg:phone":"+32 9 282 86 10",
    "sg:postcode":"9831",
    "sg:province":"Oost-Vlaanderen",
    "sg:tags":[
        "accountant"
    ],
    "wof:name":"Claeys W",
    "wof:placetype":"venue"
},
  "geometry": {"coordinates":[3.6009690762,51.0075492859],"type":"Point"}
}