{
  "type": "Feature",
  "properties": {
    "addr:full":"Rue De La For\u00eat 8 Florenville (lacuisine) Luxembourg 6821",
    "addr:housenumber":"8",
    "addr:postcode":"6821",
    "addr:street":"Rue De La Fore\u0302T",
    "iso:country":"BE",
    "sg:address":"Rue De La For\u00eat 8",
    "sg:city":"Florenville (lacuisine)",
    "sg:classifiers":[
        {
            "category":"Building & Trades",
            "subcategory":"Landscaping Services",
            "type":"Services"
        }
    ],
    "sg:phone":"+32 61 31 25 99",
    "sg:postcode":"6821",
    "sg:province":"Luxembourg",
    "sg:tags":[
        "access",
        "pond",
        "laying-out",
        "-"
    ],
    "wof:name":"Guppy (le)",
    "wof:placetype":"venue"
},
  "geometry": {"coordinates":[5.315928936,49.7174186707],"type":"Point"}
}