{
  "type": "Feature",
  "properties": {
    "addr:full":"Koningin Fabiolalaan 5 De Pinte Oost-Vlaanderen 9840",
    "addr:housenumber":"5",
    "addr:postcode":"9840",
    "addr:street":"Koningin Fabiolalaan",
    "iso:country":"BE",
    "sg:address":"Koningin Fabiolalaan 5",
    "sg:city":"De Pinte",
    "sg:classifiers":[
        {
            "category":"Personal",
            "subcategory":"Beauty Salon",
            "type":"Services"
        }
    ],
    "sg:phone":"+32 9 282 35 69",
    "sg:postcode":"9840",
    "sg:province":"Oost-Vlaanderen",
    "wof:name":"De Moor A",
    "wof:placetype":"venue"
},
  "geometry": {"coordinates":[3.6550738811,50.9893798828],"type":"Point"}
}