{
  "type": "Feature",
  "properties": {
    "iso:country":"BE",
    "sg:address":"Rue Jules Lejeune 59",
    "sg:city":"Elsene/ixelles",
    "sg:orig_category":"Avocats and conseillers juridiques",
    "sg:phone":"+32 2 345 18 15",
    "sg:postcode":"1050",
    "sg:province":"Bruxelles-Capitale",
    "wof:name":"G. Kaisin",
    "wof:placetype":"venue"
},
  "geometry": {"coordinates":[4.3612518311,50.8166503906],"type":"Point"}
}