{
  "type": "Feature",
  "properties": {
    "addr:full":"Heieinde 52 Hoogstraten (meerle) Antwerpen 2328",
    "addr:housenumber":"52",
    "addr:postcode":"2328",
    "addr:street":"Heieinde",
    "iso:country":"BE",
    "sg:address":"Heieinde 52",
    "sg:city":"Hoogstraten (meerle)",
    "sg:classifiers":[
        {
            "category":"Building & Trades",
            "subcategory":"Landscaping Services",
            "type":"Services"
        }
    ],
    "sg:phone":"+32 3 315 03 60",
    "sg:postcode":"2328",
    "sg:province":"Antwerpen",
    "sg:tags":[
        "nurseryman"
    ],
    "wof:name":"Jochems L",
    "wof:placetype":"venue"
},
  "geometry": {"coordinates":[4.7738451958,51.5042152405],"type":"Point"}
}