{
  "type": "Feature",
  "properties": {
    "iso:country":"BE",
    "sg:address":"Messemakersstraat 57",
    "sg:city":"Lille (gierle)",
    "sg:classifiers":[
        {
            "category":"Building & Trades",
            "subcategory":"Construction",
            "type":"Services"
        }
    ],
    "sg:phone":"+32 14 55 57 34",
    "sg:postcode":"2275",
    "sg:province":"Antwerpen",
    "sg:tags":[
        "stucco",
        "contractor"
    ],
    "wof:name":"Vennekens Bvba",
    "wof:placetype":"venue"
},
  "geometry": {"coordinates":[4.8627800941,51.2573318481],"type":"Point"}
}