{
  "type": "Feature",
  "properties": {
    "addr:full":"Rue Notre Dame Du Sommeil 38 Bruxelles Bruxelles-Capitale 1000",
    "addr:housenumber":"38",
    "addr:postcode":"1000",
    "addr:street":"Rue Notre Dame Du Sommeil",
    "iso:country":"BE",
    "sg:address":"Rue Notre Dame Du Sommeil 38",
    "sg:city":"Bruxelles",
    "sg:classifiers":[
        {
            "category":"Food Court",
            "type":"Food & Drink"
        }
    ],
    "sg:phone":"+32 2 512 04 76",
    "sg:postcode":"1000",
    "sg:province":"Bruxelles-Capitale",
    "sg:tags":[
        "product",
        "related"
    ],
    "wof:name":"Tamines Sa",
    "wof:placetype":"venue"
},
  "geometry": {"coordinates":[4.3406910896,50.8498764038],"type":"Point"}
}