{
  "type": "Feature",
  "properties": {
    "addr:full":"Rue De Mettet 185 Florennes Namur 5620",
    "addr:housenumber":"185",
    "addr:postcode":"5620",
    "addr:street":"Rue De Mettet",
    "iso:country":"BE",
    "sg:address":"Rue De Mettet 185",
    "sg:city":"Florennes",
    "sg:classifiers":[
        {
            "category":"Professional",
            "subcategory":"Management & Consulting",
            "type":"Services"
        }
    ],
    "sg:phone":"+32 71 68 92 06",
    "sg:postcode":"5620",
    "sg:province":"Namur",
    "sg:tags":[
        "consultant"
    ],
    "wof:name":"Vandriette A",
    "wof:placetype":"venue"
},
  "geometry": {"coordinates":[4.6198940277,50.266658783],"type":"Point"}
}