{
  "type": "Feature",
  "properties": {
    "addr:full":"Rue Du Foss\u00e9 16 Aubange (halanzy) Luxembourg 6792",
    "addr:housenumber":"16",
    "addr:postcode":"6792",
    "addr:street":"Rue Du Fosse\u0301",
    "iso:country":"BE",
    "sg:address":"Rue Du Foss\u00e9 16",
    "sg:city":"Aubange (halanzy)",
    "sg:classifiers":[
        {
            "category":"Building & Trades",
            "subcategory":"Plumbing",
            "type":"Services"
        }
    ],
    "sg:phone":"+32 63 67 81 22",
    "sg:postcode":"6792",
    "sg:province":"Luxembourg",
    "sg:tags":[
        "repair",
        "mainten",
        "-",
        "central",
        "heating"
    ],
    "wof:name":"Wauthier H",
    "wof:placetype":"venue"
},
  "geometry": {"coordinates":[5.7439842224,49.5610618591],"type":"Point"}
}