{
  "type": "Feature",
  "properties": {
    "iso:country":"BE",
    "sg:address":"Grand'place 10",
    "sg:city":"Braine-le-ch\u00e2teau",
    "sg:classifiers":[
        {
            "category":"Bars & Pubs",
            "type":"Food & Drink"
        }
    ],
    "sg:phone":"+32 2 366 94 67",
    "sg:postcode":"1440",
    "sg:province":"Brabant Wallon",
    "wof:name":"Couronne (la)",
    "wof:placetype":"venue"
},
  "geometry": {"coordinates":[4.2669420242,50.6817054749],"type":"Point"}
}