{
  "type": "Feature",
  "properties": {
    "addr:full":"E. Bockstaellaan 315 Brussel/bruxelles Bruxelles-Capitale 1020",
    "addr:housenumber":"315",
    "addr:postcode":"1020",
    "addr:street":"E. Bockstaellaan;/",
    "iso:country":"BE",
    "sg:address":"E. Bockstaellaan 315",
    "sg:city":"Brussel/bruxelles",
    "sg:classifiers":[
        {
            "category":"Restaurant",
            "type":"Food & Drink"
        }
    ],
    "sg:phone":"+32 2 479 22 60",
    "sg:postcode":"1020",
    "sg:province":"Bruxelles-Capitale",
    "wof:name":"Le Curnonsky",
    "wof:placetype":"venue"
},
  "geometry": {"coordinates":[4.3471288681,50.8821487427],"type":"Point"}
}