{
  "type": "Feature",
  "properties": {
    "addr:full":"Juniorslaan 38 /a Leest Antwerpen 2811",
    "addr:housenumber":"38 / a",
    "addr:postcode":"2811",
    "addr:street":"Juniorslaan",
    "iso:country":"BE",
    "sg:address":"Juniorslaan 38 /a",
    "sg:city":"Leest",
    "sg:classifiers":[
        {
            "category":"Farming",
            "subcategory":"Livestock Farm",
            "type":"Manufacturing & Wholesale Goods"
        }
    ],
    "sg:phone":"+32 15 71 19 73",
    "sg:postcode":"2811",
    "sg:province":"Antwerpen",
    "sg:tags":[
        "agriculture"
    ],
    "wof:name":"Agri Foods Bvba",
    "wof:placetype":"venue"
},
  "geometry": {"coordinates":[4.4443998337,51.014541626],"type":"Point"}
}