{
  "type": "Feature",
  "properties": {
    "addr:full":"Impasse Du Viaduc 1 Jurbise Hainaut 7050",
    "addr:housenumber":"1",
    "addr:postcode":"7050",
    "addr:street":"Impasse Du Viaduc",
    "iso:country":"BE",
    "sg:address":"Impasse Du Viaduc 1",
    "sg:city":"Jurbise",
    "sg:classifiers":[
        {
            "category":"Cafe",
            "type":"Food & Drink"
        }
    ],
    "sg:phone":"+32 65 22 67 18",
    "sg:postcode":"7050",
    "sg:province":"Hainaut",
    "sg:tags":[
        "caf\u00e9s"
    ],
    "wof:name":"Olivier Tranchant",
    "wof:placetype":"venue"
},
  "geometry": {"coordinates":[3.9112300873,50.5325889587],"type":"Point"}
}