{
  "type": "Feature",
  "properties": {
    "iso:country":"BE",
    "sg:address":"Boondaalse Steenweg 44",
    "sg:city":"Elsene/ixelles",
    "sg:orig_category":"Supermarkten",
    "sg:phone":"+32 2 627 05 11",
    "sg:postcode":"1050",
    "sg:province":"Bruxelles-Capitale",
    "wof:name":"Super G.b.",
    "wof:placetype":"venue"
},
  "geometry": {"coordinates":[4.3755559921,50.8265762329],"type":"Point"}
}