{
  "type": "Feature",
  "properties": {
    "addr:full":"Diksmuidsesteenweg 640 Roeselare West-Vlaanderen 8800",
    "addr:housenumber":"640",
    "addr:postcode":"8800",
    "addr:street":"Diksmuidsesteenweg",
    "iso:country":"BE",
    "sg:address":"Diksmuidsesteenweg 640",
    "sg:city":"Roeselare",
    "sg:classifiers":[
        {
            "category":"Retail",
            "subcategory":"Auto Repair",
            "type":"Services"
        }
    ],
    "sg:phone":"+32 51 70 15 21",
    "sg:postcode":"8800",
    "sg:province":"West-Vlaanderen",
    "sg:tags":[
        "breakdown",
        "automobile",
        "-",
        "recovery"
    ],
    "wof:name":"Degrande",
    "wof:placetype":"venue"
},
  "geometry": {"coordinates":[3.0854959488,50.956161499],"type":"Point"}
}