{
  "type": "Feature",
  "properties": {
    "iso:country":"BE",
    "sg:address":"Prinsdomlaan 17",
    "sg:city":"Izegem",
    "sg:classifiers":[
        {
            "category":"Wholesale",
            "subcategory":"Meat",
            "type":"Manufacturing & Wholesale Goods"
        }
    ],
    "sg:phone":"+32 51 30 44 57",
    "sg:postcode":"8870",
    "sg:province":"West-Vlaanderen",
    "sg:tags":[
        "whol",
        "-"
    ],
    "wof:name":"Leflere Vleeshandel Bvba",
    "wof:placetype":"venue"
},
  "geometry": {"coordinates":[3.2235999107,50.910118103],"type":"Point"}
}