{
  "type": "Feature",
  "properties": {
    "iso:country":"BE",
    "sg:address":"Dorpsstraat 6",
    "sg:city":"Boortmeerbeek",
    "sg:orig_category":"Newspapers, magazines, periodicals - Distribution",
    "sg:phone":"+32 15 51 14 23",
    "sg:postcode":"3190",
    "sg:province":"Vlaams-Brabant",
    "wof:name":"Verhoeven G",
    "wof:placetype":"venue"
},
  "geometry": {"coordinates":[4.5731801987,50.9804801941],"type":"Point"}
}