{
  "type": "Feature",
  "properties": {
    "iso:country":"BE",
    "sg:address":"Lossingsweg 21",
    "sg:city":"Lommel",
    "sg:classifiers":[
        {
            "category":"Home & Garden",
            "subcategory":"Carpets & Floor Coverings",
            "type":"Retail Goods"
        }
    ],
    "sg:phone":"+32 11 54 32 84",
    "sg:postcode":"3920",
    "sg:province":"Limburg",
    "sg:tags":[
        "tile"
    ],
    "wof:name":"Engelen Vloer -en Tegelhandel Bvba Bvba",
    "wof:placetype":"venue"
},
  "geometry": {"coordinates":[5.309882164,51.2524795532],"type":"Point"}
}