{
  "type": "Feature",
  "properties": {
    "addr:full":"Gentsesteenweg 25b1 Erpe-mere Oost-Vlaanderen 9420",
    "addr:housenumber":"25b1",
    "addr:postcode":"9420",
    "addr:street":"Gentsesteenweg",
    "iso:country":"BE",
    "sg:address":"Gentsesteenweg 25b1",
    "sg:city":"Erpe-mere",
    "sg:orig_category":"Banques and organismes de cr\u00e9dit",
    "sg:phone":"+32 53 80 22 11",
    "sg:postcode":"9420",
    "sg:province":"Oost-Vlaanderen",
    "wof:name":"Dexia",
    "wof:placetype":"venue"
},
  "geometry": {"coordinates":[3.9930570126,50.9423751831],"type":"Point"}
}