{
  "type": "Feature",
  "properties": {
    "addr:full":"Rue Des Haies 101 Chatelet Hainaut 6200",
    "addr:housenumber":"101",
    "addr:postcode":"chatelet;6200",
    "addr:street":"Rue Des Haies",
    "iso:country":"BE",
    "sg:address":"Rue Des Haies 101",
    "sg:city":"Chatelet",
    "sg:classifiers":[
        {
            "category":"Personal",
            "subcategory":"Beauty Salon",
            "type":"Services"
        }
    ],
    "sg:phone":"+32 71 38 06 95",
    "sg:postcode":"6200",
    "sg:province":"Hainaut",
    "sg:tags":[
        "de",
        "coiffure"
    ],
    "wof:name":"Coiffure Danielle",
    "wof:placetype":"venue"
},
  "geometry": {"coordinates":[4.5128130913,50.4170379639],"type":"Point"}
}