{
  "type": "Feature",
  "properties": {
    "iso:country":"BE",
    "sg:address":"Rue Cl\u00c8rue 30",
    "sg:city":"La Roche-en-ardenne",
    "sg:orig_category":"Epiceries",
    "sg:phone":"+32 84 41 14 30",
    "sg:postcode":"6980",
    "sg:province":"Luxembourg",
    "wof:name":"Malherbe",
    "wof:placetype":"venue"
},
  "geometry": {"coordinates":[5.5767688751,50.1813011169],"type":"Point"}
}