{
  "type": "Feature",
  "properties": {
    "addr:full":"Rue De L'autonomie 1 Bruxelles (anderlecht) Bruxelles-Capitale 1070",
    "addr:housenumber":"1",
    "addr:postcode":"1070",
    "addr:street":"Rue De L'Autonomie",
    "iso:country":"BE",
    "sg:address":"Rue De L'autonomie 1",
    "sg:city":"Bruxelles (anderlecht)",
    "sg:classifiers":[
        {
            "category":"Professional",
            "subcategory":"Computer Services",
            "type":"Services"
        }
    ],
    "sg:phone":"+32 2 522 06 63",
    "sg:postcode":"1070",
    "sg:province":"Bruxelles-Capitale",
    "sg:tags":[
        "-",
        "processing",
        "data",
        "software"
    ],
    "wof:name":"Phidani Software Sprl",
    "wof:placetype":"venue"
},
  "geometry": {"coordinates":[4.3385958672,50.8406944275],"type":"Point"}
}