{
  "type": "Feature",
  "properties": {
    "addr:full":"Mar. Van Vlaanderenstr. 27 Brugge West-Vlaanderen 8310",
    "addr:housenumber":"27",
    "addr:postcode":"8310",
    "addr:street":"Mar. Van Vlaanderenstr.",
    "iso:country":"BE",
    "sg:address":"Mar. Van Vlaanderenstr. 27",
    "sg:city":"Brugge",
    "sg:orig_category":"Bloemen and planten",
    "sg:phone":"+32 50 37 00 03",
    "sg:postcode":"8310",
    "sg:province":"West-Vlaanderen",
    "wof:name":"Noel Portier",
    "wof:placetype":"venue"
},
  "geometry": {"coordinates":[3.2405900955,51.2174568176],"type":"Point"}
}