{
  "type": "Feature",
  "properties": {
    "iso:country":"BE",
    "sg:address":"Rue De La Grand Place 9",
    "sg:city":"Arlon",
    "sg:classifiers":[
        {
            "category":"Personal",
            "subcategory":"Beauty Salon",
            "type":"Services"
        }
    ],
    "sg:phone":"+32 63 22 84 72",
    "sg:postcode":"6700",
    "sg:province":"Luxembourg",
    "sg:tags":[
        "lady",
        "-",
        "hairdressing"
    ],
    "wof:name":"David's",
    "wof:placetype":"venue"
},
  "geometry": {"coordinates":[5.8140649796,49.6839103699],"type":"Point"}
}