{
  "type": "Feature",
  "properties": {
    "addr:full":"Koningin Astridlaan 45 Hasselt Limburg 3500",
    "addr:housenumber":"45",
    "addr:postcode":"3500",
    "addr:street":"Koningin Astridlaan",
    "iso:country":"BE",
    "sg:address":"Koningin Astridlaan 45",
    "sg:city":"Hasselt",
    "sg:classifiers":[
        {
            "category":"Organizations",
            "subcategory":"Professional Association",
            "type":"Services"
        }
    ],
    "sg:phone":"+32 11 30 09 89",
    "sg:postcode":"3500",
    "sg:province":"Limburg",
    "sg:tags":[
        "trade-union",
        "federation"
    ],
    "wof:name":"Acod-tbm",
    "wof:placetype":"venue"
},
  "geometry": {"coordinates":[5.3305869102,50.9317779541],"type":"Point"}
}