{
  "type": "Feature",
  "properties": {
    "addr:full":"Schans 7 Meerhout Antwerpen 2450",
    "addr:housenumber":"7",
    "addr:postcode":"2450",
    "addr:street":"Schans",
    "iso:country":"BE",
    "sg:address":"Schans 7",
    "sg:city":"Meerhout",
    "sg:orig_category":"Kapsalons",
    "sg:phone":"+32 14 30 08 97",
    "sg:postcode":"2450",
    "sg:province":"Antwerpen",
    "wof:name":"Van Eynde",
    "wof:placetype":"venue"
},
  "geometry": {"coordinates":[5.0524010658,51.1222381592],"type":"Point"}
}