{
  "type": "Feature",
  "properties": {
    "addr:full":"Diestse Vest 32 Pb 220 Leuven Vlaams-Brabant 3000",
    "addr:housenumber":"32 pb 220",
    "addr:postcode":"3000",
    "addr:street":"Diestse Vest",
    "iso:country":"BE",
    "sg:address":"Diestse Vest 32 Pb 220",
    "sg:city":"Leuven",
    "sg:classifiers":[
        {
            "category":"Professional",
            "subcategory":"Business Services",
            "type":"Services"
        }
    ],
    "sg:phone":"+32 16 24 56 10",
    "sg:postcode":"3000",
    "sg:province":"Vlaams-Brabant",
    "sg:tags":[
        "information",
        "training",
        "technology",
        "advice"
    ],
    "wof:name":"Abis Trading & Consulting Nv",
    "wof:placetype":"venue"
},
  "geometry": {"coordinates":[4.7036700249,50.8793869019],"type":"Point"}
}