{
  "type": "Feature",
  "properties": {
    "addr:full":"Beersellaan 154 Drogenbos/drogenbos Vlaams-Brabant 1620",
    "addr:housenumber":"154",
    "addr:postcode":"1620",
    "addr:street":"Beersellaan",
    "iso:country":"BE",
    "sg:address":"Beersellaan 154",
    "sg:city":"Drogenbos/drogenbos",
    "sg:orig_category":"Benzinestations and brandstoffen HUISBRANDOLIE",
    "sg:phone":"+32 2 331 07 70",
    "sg:postcode":"1620",
    "sg:province":"Vlaams-Brabant",
    "wof:name":"Jet",
    "wof:placetype":"venue"
},
  "geometry": {"coordinates":[4.3205800056,50.7825088501],"type":"Point"}
}