{
  "type": "Feature",
  "properties": {
    "addr:full":"Groenkloosterstraat 26 Bilzen Limburg 3740",
    "addr:housenumber":"26",
    "addr:postcode":"3740",
    "addr:street":"Groenkloosterstraat",
    "iso:country":"BE",
    "sg:address":"Groenkloosterstraat 26",
    "sg:city":"Bilzen",
    "sg:orig_category":"Bloemen and planten",
    "sg:phone":"+32 89 41 38 60",
    "sg:postcode":"3740",
    "sg:province":"Limburg",
    "wof:name":"Urbaan Stevens",
    "wof:placetype":"venue"
},
  "geometry": {"coordinates":[5.5133070946,50.8699760437],"type":"Point"}
}