{
  "type": "Feature",
  "properties": {
    "addr:full":"G. Vandenheuvelstraat 31 Herselt (ramsel) Antwerpen 2230",
    "addr:housenumber":"31",
    "addr:postcode":"2230",
    "addr:street":"Vandenheuvelstraat",
    "iso:country":"BE",
    "sg:address":"G. Vandenheuvelstraat 31",
    "sg:city":"Herselt (ramsel)",
    "sg:classifiers":[
        {
            "category":"Health Services",
            "subcategory":"Health Practitioner",
            "type":"Services"
        }
    ],
    "sg:phone":"+32 16 57 05 44",
    "sg:postcode":"2230",
    "sg:province":"Antwerpen",
    "sg:tags":[
        "physiotherapist"
    ],
    "wof:name":"Peeters Betty",
    "wof:placetype":"venue"
},
  "geometry": {"coordinates":[4.8334841728,51.0306777954],"type":"Point"}
}