{
  "type": "Feature",
  "properties": {
    "addr:full":"Rue De Huy 19 Waremme Li\u00e8ge 4300",
    "addr:housenumber":"19",
    "addr:postcode":"4300",
    "addr:street":"Rue De Huy",
    "iso:country":"BE",
    "sg:address":"Rue De Huy 19",
    "sg:city":"Waremme",
    "sg:classifiers":[
        {
            "category":"Banks & Credit Unions",
            "subcategory":"Financial Services",
            "type":"Services"
        }
    ],
    "sg:phone":"+32 19 33 02 07",
    "sg:postcode":"4300",
    "sg:province":"Li\u00e8ge",
    "sg:tags":[
        "loan",
        "mortgage"
    ],
    "wof:name":"Argenta",
    "wof:placetype":"venue"
},
  "geometry": {"coordinates":[5.2522859573,50.6943244934],"type":"Point"}
}