{
  "type": "Feature",
  "properties": {
    "iso:country":"BE",
    "sg:address":"Rue De La Poste 59",
    "sg:city":"Chatelet",
    "sg:orig_category":"Tabac",
    "sg:phone":"+32 71 38 05 91",
    "sg:postcode":"6200",
    "sg:province":"Hainaut",
    "wof:name":"Andree Spinette",
    "wof:placetype":"venue"
},
  "geometry": {"coordinates":[4.5195579529,50.4084968567],"type":"Point"}
}