{
  "type": "Feature",
  "properties": {
    "addr:full":"Rue De L'eglise 3 Welkenraedt/welkenraedt Li\u00e8ge 4840",
    "addr:housenumber":"3",
    "addr:postcode":"4840",
    "addr:street":"Rue De L'Eglise",
    "iso:country":"BE",
    "sg:address":"Rue De L'eglise 3",
    "sg:city":"Welkenraedt/welkenraedt",
    "sg:orig_category":"Krantenwinkels Rookartikelen",
    "sg:phone":"+32 87 88 13 53",
    "sg:postcode":"4840",
    "sg:province":"Li\u00e8ge",
    "wof:name":"Maison Grignard",
    "wof:placetype":"venue"
},
  "geometry": {"coordinates":[5.9720048904,50.6606254578],"type":"Point"}
}