{
  "type": "Feature",
  "properties": {
    "addr:full":"Eekhoekstraat 5 Laarne Oost-Vlaanderen 9270",
    "addr:housenumber":"5",
    "addr:postcode":"9270",
    "addr:street":"Eekhoekstraat",
    "iso:country":"BE",
    "sg:address":"Eekhoekstraat 5",
    "sg:city":"Laarne",
    "sg:orig_category":"Mus\u00e9es and patrimoine culturel",
    "sg:phone":"+32 9 230 91 55",
    "sg:postcode":"9270",
    "sg:province":"Oost-Vlaanderen",
    "wof:name":"Museum Slot Van Laarne",
    "wof:placetype":"venue"
},
  "geometry": {"coordinates":[3.831512928,51.0307998657],"type":"Point"}
}