{
  "type": "Feature",
  "properties": {
    "addr:full":"Lorettestraat 186 Ronse/renaix Oost-Vlaanderen 9600",
    "addr:housenumber":"186",
    "addr:postcode":"9600",
    "addr:street":"Lorettestraat",
    "iso:country":"BE",
    "sg:address":"Lorettestraat 186",
    "sg:city":"Ronse/renaix",
    "sg:orig_category":"Pleisterwerk",
    "sg:phone":"+32 55 21 72 36",
    "sg:postcode":"9600",
    "sg:province":"Oost-Vlaanderen",
    "wof:name":"Raes Didier",
    "wof:placetype":"venue"
},
  "geometry": {"coordinates":[3.6321849823,50.7521095276],"type":"Point"}
}