{
  "type": "Feature",
  "properties": {
    "addr:full":"Rue Antoine Dansaert 97 Bruxelles Bruxelles-Capitale 1000",
    "addr:housenumber":"97",
    "addr:postcode":"1000",
    "addr:street":"Rue Antoine Dansaert",
    "iso:country":"BE",
    "sg:address":"Rue Antoine Dansaert 97",
    "sg:city":"Bruxelles",
    "sg:classifiers":[
        {
            "category":"Wholesale",
            "subcategory":"Metals & Minerals",
            "type":"Manufacturing & Wholesale Goods"
        }
    ],
    "sg:phone":"+32 2 511 65 01",
    "sg:postcode":"1000",
    "sg:province":"Bruxelles-Capitale",
    "sg:tags":[
        "precious"
    ],
    "wof:name":"Belgold",
    "wof:placetype":"venue"
},
  "geometry": {"coordinates":[4.3457570076,50.8508300781],"type":"Point"}
}