{
  "type": "Feature",
  "properties": {
    "iso:country":"BE",
    "sg:address":"Rue D\u00b4elouges 124",
    "sg:city":"Dour",
    "sg:orig_category":"Dierenartsen",
    "sg:phone":"+32 65 65 07 28",
    "sg:postcode":"7370",
    "sg:province":"Hainaut",
    "wof:name":"F. Dubray",
    "wof:placetype":"venue"
},
  "geometry": {"coordinates":[3.7697598934,50.3967514038],"type":"Point"}
}