{
  "type": "Feature",
  "properties": {
    "addr:full":"Rue Du Poncia 24 Sambreville Namur 5060",
    "addr:housenumber":"24",
    "addr:postcode":"5060",
    "addr:street":"Rue Du Poncia",
    "iso:country":"BE",
    "sg:address":"Rue Du Poncia 24",
    "sg:city":"Sambreville",
    "sg:orig_category":"Installatie van houten of kunststof schrijnwerk",
    "sg:phone":"+32 71 74 35 82",
    "sg:postcode":"5060",
    "sg:province":"Namur",
    "wof:name":"Rn Pose",
    "wof:placetype":"venue"
},
  "geometry": {"coordinates":[4.5914821625,50.443939209],"type":"Point"}
}