{
  "type": "Feature",
  "properties": {
    "addr:full":"Guldensporenln 5 Houthalen-helchter Limburg 3530",
    "addr:housenumber":"5",
    "addr:postcode":"3530",
    "addr:street":"Guldensporenln",
    "iso:country":"BE",
    "sg:address":"Guldensporenln 5",
    "sg:city":"Houthalen-helchter",
    "sg:classifiers":[
        {
            "category":"Travel",
            "subcategory":"Hotels & Motels",
            "type":"Entertainment"
        }
    ],
    "sg:phone":"+32 11 60 23 04",
    "sg:postcode":"3530",
    "sg:province":"Limburg",
    "sg:tags":[
        "hotels",
        "business",
        "restaurant"
    ],
    "wof:name":"Cruysbergs Paul M.",
    "wof:placetype":"venue"
},
  "geometry": {"coordinates":[5.3719201088,51.0310020447],"type":"Point"}
}