{
  "type": "Feature",
  "properties": {
    "iso:country":"BE",
    "sg:address":"Reckegemstraat 12 B",
    "sg:city":"Gent",
    "sg:classifiers":[
        {
            "category":"Restaurant",
            "type":"Food & Drink"
        }
    ],
    "sg:phone":"+32 55 49 66 74",
    "sg:postcode":"9630",
    "sg:province":"Oost-Vlaanderen",
    "wof:name":"Cateclaerhoeve",
    "wof:placetype":"venue"
},
  "geometry": {"coordinates":[3.7331020832,50.8774833679],"type":"Point"}
}