{
  "type": "Feature",
  "properties": {
    "iso:country":"BE",
    "sg:address":"Rue Aux Hesses 14",
    "sg:city":"Modave",
    "sg:orig_category":"Woningbouw",
    "sg:phone":"+32 85 41 21 70",
    "sg:postcode":"4577",
    "sg:province":"Li\u00e8ge",
    "wof:name":"Lierneux Eric",
    "wof:placetype":"venue"
},
  "geometry": {"coordinates":[5.3027100563,50.4403610229],"type":"Point"}
}