{
  "type": "Feature",
  "properties": {
    "iso:country":"BE",
    "sg:address":"Churchilllaan 256",
    "sg:city":"Schoten",
    "sg:orig_category":"Artsen and specialisten",
    "sg:phone":"+32 3 652 01 02",
    "sg:postcode":"2900",
    "sg:province":"Antwerpen",
    "wof:name":"Johan Salembier",
    "wof:placetype":"venue"
},
  "geometry": {"coordinates":[4.4844107628,51.2499046326],"type":"Point"}
}