{
  "type": "Feature",
  "properties": {
    "addr:full":". Zuienkerke (groot) West-Vlaanderen 8377",
    "addr:postcode":"8377",
    "addr:street":"Groot West-Vlaanderen",
    "iso:country":"BE",
    "sg:address":".",
    "sg:city":"Zuienkerke (groot)",
    "sg:orig_category":"Apotheken",
    "sg:phone":"+32 900 10 500",
    "sg:postcode":"8377",
    "sg:province":"West-Vlaanderen",
    "wof:name":"Apothekers Van Wacht",
    "wof:placetype":"venue"
},
  "geometry": {"coordinates":[3.1532449722,51.2647247314],"type":"Point"}
}