{
  "type": "Feature",
  "properties": {
    "iso:country":"BE",
    "sg:address":"Waggelwater 4",
    "sg:city":"Brugge",
    "sg:orig_category":"Sportclubs",
    "sg:phone":"+32 50 31 70 02",
    "sg:postcode":"8200",
    "sg:province":"West-Vlaanderen",
    "wof:name":"Koninklijke Roeivereniging Brugge",
    "wof:placetype":"venue"
},
  "geometry": {"coordinates":[3.1891698837,51.2171287537],"type":"Point"}
}