{
  "type": "Feature",
  "properties": {
    "addr:full":"Rue Du Rat D'eau 7b Honnelles (athis) Hainaut 7387",
    "addr:housenumber":"7b",
    "addr:postcode":"7387",
    "addr:street":"Rue Du Rat D'Eau",
    "iso:country":"BE",
    "sg:address":"Rue Du Rat D'eau 7b",
    "sg:city":"Honnelles (athis)",
    "sg:classifiers":[
        {
            "category":"Wholesale",
            "subcategory":"Beer",
            "type":"Manufacturing & Wholesale Goods"
        }
    ],
    "sg:phone":"+32 65 63 09 29",
    "sg:postcode":"7387",
    "sg:province":"Hainaut",
    "sg:tags":[
        "ale",
        "-"
    ],
    "wof:name":"Chez Michel Au Relais Franco Sprl",
    "wof:placetype":"venue"
},
  "geometry": {"coordinates":[3.7804169655,50.36095047],"type":"Point"}
}