{
  "type": "Feature",
  "properties": {
    "addr:full":"Avenue Prekelinden 162 Bruxelles (woluwe-saint-lambert) Bruxelles-Capitale 1200",
    "addr:housenumber":"162",
    "addr:postcode":"1200",
    "addr:street":"Avenue Prekelinden",
    "iso:country":"BE",
    "sg:address":"Avenue Prekelinden 162",
    "sg:city":"Bruxelles (woluwe-saint-lambert)",
    "sg:classifiers":[
        {
            "category":"Health Services",
            "subcategory":"Doctor",
            "type":"Services"
        }
    ],
    "sg:phone":"+32 2 731 04 11",
    "sg:postcode":"1200",
    "sg:province":"Bruxelles-Capitale",
    "sg:tags":[
        "medicinephysicians",
        "surgeon"
    ],
    "wof:name":"Flamme Magali",
    "wof:placetype":"venue"
},
  "geometry": {"coordinates":[4.406815052,50.8465042114],"type":"Point"}
}