{
  "type": "Feature",
  "properties": {
    "addr:full":"Chemin Des Fontaines 12 Hotton Luxembourg 6990",
    "addr:housenumber":"12",
    "addr:postcode":"6990",
    "addr:street":"Chemin Des Fontaines",
    "iso:country":"BE",
    "sg:address":"Chemin Des Fontaines 12",
    "sg:city":"Hotton",
    "sg:orig_category":"Epiceries",
    "sg:phone":"+32 84 46 61 23",
    "sg:postcode":"6990",
    "sg:province":"Luxembourg",
    "wof:name":"Jacqueline Colson",
    "wof:placetype":"venue"
},
  "geometry": {"coordinates":[5.4803748131,50.2854423523],"type":"Point"}
}