{
  "type": "Feature",
  "properties": {
    "addr:full":"Rue De L'eglise 21 Vis\u00e9 (cheratte) Li\u00e8ge 4602",
    "addr:housenumber":"21",
    "addr:postcode":"4602",
    "addr:street":"Rue De L'Eglise;Cheratte",
    "iso:country":"BE",
    "sg:address":"Rue De L'eglise 21",
    "sg:city":"Vis\u00e9 (cheratte)",
    "sg:classifiers":[
        {
            "category":"Social Services",
            "subcategory":"Child Care",
            "type":"Services"
        }
    ],
    "sg:phone":"+32 4 362 21 21",
    "sg:postcode":"4602",
    "sg:province":"Li\u00e8ge",
    "sg:tags":[
        "baby",
        "nursery",
        "day",
        "sitting"
    ],
    "wof:name":"Ribambelle (la)",
    "wof:placetype":"venue"
},
  "geometry": {"coordinates":[5.581829071,50.6424331665],"type":"Point"}
}