{
  "type": "Feature",
  "properties": {
    "iso:country":"BE",
    "sg:address":"Steyneveld 26",
    "sg:city":"Diest (kaggevinne)",
    "sg:classifiers":[
        {
            "category":"Autos & Motor Vehicles",
            "subcategory":"Automobile Sales",
            "type":"Retail Goods"
        }
    ],
    "sg:phone":"+32 13 32 37 68",
    "sg:postcode":"3293",
    "sg:province":"Vlaams-Brabant",
    "sg:tags":[
        "wirework",
        "machine"
    ],
    "wof:name":"Gidra Bvba",
    "wof:placetype":"venue"
},
  "geometry": {"coordinates":[5.0352048874,50.9845581055],"type":"Point"}
}