{
  "type": "Feature",
  "properties": {
    "addr:full":"Industrieterrein 2-3 Diest Vlaams-Brabant 3290",
    "addr:housenumber":"2-3",
    "addr:postcode":"3290",
    "addr:street":"Industrieterrein",
    "iso:country":"BE",
    "sg:address":"Industrieterrein 2-3",
    "sg:city":"Diest",
    "sg:classifiers":[
        {
            "category":"Manufacturing",
            "subcategory":"Metals",
            "type":"Manufacturing & Wholesale Goods"
        }
    ],
    "sg:phone":"+32 13 53 17 77",
    "sg:postcode":"3290",
    "sg:province":"Vlaams-Brabant",
    "sg:tags":[
        "work",
        "sheet"
    ],
    "wof:name":"L & D-jet-techniek",
    "wof:placetype":"venue"
},
  "geometry": {"coordinates":[5.0769262314,50.9648323059],"type":"Point"}
}