{
  "type": "Feature",
  "properties": {
    "addr:full":"Avenue Herbofin 1 Libramont-chevigny Luxembourg 6800",
    "addr:housenumber":"1",
    "addr:postcode":"6800",
    "addr:street":"Avenue Herbofin",
    "iso:country":"BE",
    "sg:address":"Avenue Herbofin 1",
    "sg:city":"Libramont-chevigny",
    "sg:orig_category":"S\u00e9curit\u00e9 sociale",
    "sg:postcode":"6800",
    "sg:province":"Luxembourg",
    "wof:name":"Euromut",
    "wof:placetype":"venue"
},
  "geometry": {"coordinates":[5.3761348724,49.9199943542],"type":"Point"}
}