{
  "type": "Feature",
  "properties": {
    "iso:country":"BE",
    "sg:address":"A. Cuppenstraat 15",
    "sg:city":"Beringen",
    "sg:orig_category":"Electrom\u00e9nager, t\u00e9l\u00e9visions and radios. Mat\u00e9riel de T\u00e9l\u00e9communication. R\u00e9parations d'appareils \u00e9lect",
    "sg:phone":"+32 11 43 58 33",
    "sg:postcode":"3580",
    "sg:province":"Limburg",
    "wof:name":"Eldi",
    "wof:placetype":"venue"
},
  "geometry": {"coordinates":[5.2224378586,51.0502624512],"type":"Point"}
}