{
  "type": "Feature",
  "properties": {
    "iso:country":"BE",
    "sg:address":"Rue Du Pairay 45",
    "sg:city":"Seraing",
    "sg:orig_category":"Journaux. Tabac",
    "sg:phone":"+32 4 337 16 60",
    "sg:postcode":"4100",
    "sg:province":"Li\u00e8ge",
    "wof:name":"Librairie Du Pairay",
    "wof:placetype":"venue"
},
  "geometry": {"coordinates":[5.5113649368,50.5975952148],"type":"Point"}
}