{
  "type": "Feature",
  "properties": {
    "addr:full":"Brusselstraat 123 Dilbeek Vlaams-Brabant 1700",
    "addr:housenumber":"123",
    "addr:postcode":"1700",
    "addr:street":"Brusselstraat",
    "iso:country":"BE",
    "sg:address":"Brusselstraat 123",
    "sg:city":"Dilbeek",
    "sg:orig_category":"Maisons de repos and r\u00e9sidences",
    "sg:phone":"+32 2 453 94 41",
    "sg:postcode":"1700",
    "sg:province":"Vlaams-Brabant",
    "wof:name":"Rusthuis De Verlosser",
    "wof:placetype":"venue"
},
  "geometry": {"coordinates":[4.2083501816,50.8759994507],"type":"Point"}
}