{
  "type": "Feature",
  "properties": {
    "iso:country":"BE",
    "sg:address":"Panisstraat 9",
    "sg:city":"Bilzen",
    "sg:orig_category":"Banques and organismes de cr\u00e9dit",
    "sg:phone":"+32 89 41 43 93",
    "sg:postcode":"3740",
    "sg:province":"Limburg",
    "wof:name":"Bacob",
    "wof:placetype":"venue"
},
  "geometry": {"coordinates":[5.5288419724,50.8889350891],"type":"Point"}
}