{
  "type": "Feature",
  "properties": {
    "iso:country":"BE",
    "sg:address":"Rue Nazarethbattice 13",
    "sg:city":"Battice",
    "sg:classifiers":[
        {
            "category":"Home & Garden",
            "subcategory":"Carpets & Floor Coverings",
            "type":"Retail Goods"
        }
    ],
    "sg:phone":"+32 87 67 81 97",
    "sg:postcode":"4651",
    "sg:province":"Li\u00e8ge",
    "sg:tags":[
        "houses",
        "shed"
    ],
    "wof:name":"Decor Et Jardin S.a.",
    "wof:placetype":"venue"
},
  "geometry": {"coordinates":[5.837928772,50.6389312744],"type":"Point"}
}