{
  "type": "Feature",
  "properties": {
    "addr:full":"Haasdonkse Steenweg 119 Sint-niklaas Oost-Vlaanderen 9100",
    "addr:housenumber":"119",
    "addr:postcode":"9100",
    "addr:street":"Steenweg",
    "iso:country":"BE",
    "sg:address":"Haasdonkse Steenweg 119",
    "sg:city":"Sint-niklaas",
    "sg:classifiers":[
        {
            "category":"Banks & Credit Unions",
            "subcategory":"Investment Brokerage",
            "type":"Services"
        }
    ],
    "sg:phone":"+32 3 771 12 55",
    "sg:postcode":"9100",
    "sg:province":"Oost-Vlaanderen",
    "sg:tags":[
        "auditor"
    ],
    "wof:name":"Kegels B",
    "wof:placetype":"venue"
},
  "geometry": {"coordinates":[4.2118620872,51.1679763794],"type":"Point"}
}