{
  "type": "Feature",
  "properties": {
    "addr:full":"Brusselsestraat 19 Dendermonde Oost-Vlaanderen 9200",
    "addr:housenumber":"19",
    "addr:postcode":"9200",
    "addr:street":"Brusselsestraat;Oost-Vlaanderen",
    "iso:country":"BE",
    "sg:address":"Brusselsestraat 19",
    "sg:city":"Dendermonde",
    "sg:classifiers":[
        {
            "category":"Shopping",
            "subcategory":"Clothing, Apparel, & Fashions",
            "type":"Retail Goods"
        }
    ],
    "sg:phone":"+32 52 22 61 00",
    "sg:postcode":"9200",
    "sg:province":"Oost-Vlaanderen",
    "sg:tags":[
        "lady",
        "clothing",
        "-"
    ],
    "wof:name":"Merly",
    "wof:placetype":"venue"
},
  "geometry": {"coordinates":[4.0990462303,51.0285186768],"type":"Point"}
}