{
  "type": "Feature",
  "properties": {
    "iso:country":"BE",
    "sg:address":"Lovenjoelsestraat 67",
    "sg:city":"Bierbeek",
    "sg:orig_category":"Rundveehouders",
    "sg:phone":"+32 16 46 07 09",
    "sg:postcode":"3360",
    "sg:province":"Vlaams-Brabant",
    "wof:name":"Felix Geysens",
    "wof:placetype":"venue"
},
  "geometry": {"coordinates":[4.7884259224,50.8310279846],"type":"Point"}
}