{
  "type": "Feature",
  "properties": {
    "addr:full":"Hazenstraat 21 Maasmechelen Limburg 3630",
    "addr:housenumber":"21",
    "addr:postcode":"3630",
    "addr:street":"Hazenstraat",
    "iso:country":"BE",
    "sg:address":"Hazenstraat 21",
    "sg:city":"Maasmechelen",
    "sg:classifiers":[
        {
            "category":"Arena",
            "subcategory":"Sports Club",
            "type":"Entertainment"
        }
    ],
    "sg:phone":"+32 89 76 33 81",
    "sg:postcode":"3630",
    "sg:province":"Limburg",
    "sg:tags":[
        "de"
    ],
    "wof:name":"H.c. Maasmechelen 65",
    "wof:placetype":"venue"
},
  "geometry": {"coordinates":[5.7011590004,50.9562950134],"type":"Point"}
}