{
  "type": "Feature",
  "properties": {
    "iso:country":"BE",
    "sg:address":"Heilig Bloedlaan 253",
    "sg:city":"Hoogstraten",
    "sg:orig_category":"Verlichting and huishoudartikelen",
    "sg:phone":"+32 3 314 66 62",
    "sg:postcode":"2320",
    "sg:province":"Antwerpen",
    "wof:name":"Huis Stijl",
    "wof:placetype":"venue"
},
  "geometry": {"coordinates":[4.7596588135,51.3976478577],"type":"Point"}
}