{
  "type": "Feature",
  "properties": {
    "addr:full":"Kerkstraat 12 Damme West-Vlaanderen 8340",
    "addr:housenumber":"12",
    "addr:postcode":"8340",
    "addr:street":"Kerkstraat",
    "iso:country":"BE",
    "sg:address":"Kerkstraat 12",
    "sg:city":"Damme",
    "sg:orig_category":"Salles de conf\u00e9rences and de r\u00e9ceptions. Restaurants",
    "sg:phone":"+32 50 35 46 75",
    "sg:postcode":"8340",
    "sg:province":"West-Vlaanderen",
    "wof:name":"Pallieter",
    "wof:placetype":"venue"
},
  "geometry": {"coordinates":[3.2814629078,51.2513427734],"type":"Point"}
}