{
  "type": "Feature",
  "properties": {
    "addr:full":"Hyfte Center 20 Lochristi Oost-Vlaanderen 9080",
    "addr:housenumber":"20",
    "addr:postcode":"9080",
    "iso:country":"BE",
    "sg:address":"Hyfte Center 20",
    "sg:city":"Lochristi",
    "sg:orig_category":"Plantes and fleurs Gr",
    "sg:phone":"+32 9 355 60 62",
    "sg:postcode":"9080",
    "sg:province":"Oost-Vlaanderen",
    "wof:name":"Van De Casserie",
    "wof:placetype":"venue"
},
  "geometry": {"coordinates":[3.8105859756,51.110874176],"type":"Point"}
}