{
  "type": "Feature",
  "properties": {
    "iso:country":"BE",
    "sg:address":"Avenue F Bovesse 138",
    "sg:city":"Chaudfontaine",
    "sg:orig_category":"Secr\u00e9tariats",
    "sg:phone":"+32 4 365 50 31",
    "sg:postcode":"4053",
    "sg:province":"Li\u00e8ge",
    "wof:name":"Text",
    "wof:placetype":"venue"
},
  "geometry": {"coordinates":[5.6063599586,50.5931015015],"type":"Point"}
}