{
  "type": "Feature",
  "properties": {
    "addr:full":"Hoornstraat 3 Halle Vlaams-Brabant 1500",
    "addr:housenumber":"3",
    "addr:postcode":"1500",
    "addr:street":"Hoornstraat",
    "iso:country":"BE",
    "sg:address":"Hoornstraat 3",
    "sg:city":"Halle",
    "sg:classifiers":[
        {
            "category":"Health Services",
            "subcategory":"Doctor",
            "type":"Services"
        }
    ],
    "sg:phone":"+32 2 356 67 14",
    "sg:postcode":"1500",
    "sg:province":"Vlaams-Brabant",
    "sg:tags":[
        "orthopedist"
    ],
    "wof:name":"Vander Roost M",
    "wof:placetype":"venue"
},
  "geometry": {"coordinates":[4.2369117737,50.7363014221],"type":"Point"}
}