{
  "type": "Feature",
  "properties": {
    "iso:country":"BE",
    "sg:address":"Koninklijke Baan 126",
    "sg:city":"Koksijde",
    "sg:orig_category":"Motos",
    "sg:phone":"+32 58 52 26 76",
    "sg:postcode":"8670",
    "sg:province":"West-Vlaanderen",
    "wof:name":"Boss Hoss",
    "wof:placetype":"venue"
},
  "geometry": {"coordinates":[2.6351239681,51.1207504272],"type":"Point"}
}