{
  "type": "Feature",
  "properties": {
    "addr:full":"Philips De Monteplein 22 Edegem Antwerpen 2650",
    "addr:housenumber":"22",
    "addr:postcode":"2650",
    "addr:street":"Philips De Monteplein",
    "iso:country":"BE",
    "sg:address":"Philips De Monteplein 22",
    "sg:city":"Edegem",
    "sg:classifiers":[
        {
            "category":"Insurance",
            "subcategory":"Insurance Agent",
            "type":"Services"
        }
    ],
    "sg:phone":"+32 3 448 16 66",
    "sg:postcode":"2650",
    "sg:province":"Antwerpen",
    "sg:tags":[
        "broker"
    ],
    "wof:name":"De Walsche Luk Bvba",
    "wof:placetype":"venue"
},
  "geometry": {"coordinates":[4.4200129509,51.1640205383],"type":"Point"}
}