{
  "type": "Feature",
  "properties": {
    "iso:country":"BE",
    "sg:address":"Sint-jansberg 39",
    "sg:city":"Maaseik",
    "sg:classifiers":[
        {
            "category":"Education",
            "subcategory":"School",
            "type":"Public Place"
        }
    ],
    "sg:phone":"+32 89 56 30 59",
    "sg:postcode":"3680",
    "sg:province":"Limburg",
    "sg:tags":[
        "secondary"
    ],
    "wof:name":"Technisch Instituut St-jansberg Vzw",
    "wof:placetype":"venue"
},
  "geometry": {"coordinates":[5.7823061943,51.1072463989],"type":"Point"}
}