{
  "type": "Feature",
  "properties": {
    "iso:country":"BE",
    "sg:address":"Zuiderring 22",
    "sg:city":"Genk",
    "sg:orig_category":"Bouwmaterialen Gh Dakwerken Installatie van houten of kunststof schrijnwerk",
    "sg:phone":"+32 89 35 77 65",
    "sg:postcode":"3600",
    "sg:province":"Limburg",
    "wof:name":"Hout Plus",
    "wof:placetype":"venue"
},
  "geometry": {"coordinates":[5.488776207,50.946849823],"type":"Point"}
}