{
  "type": "Feature",
  "properties": {
    "addr:full":"Chemin \u00e0 Baraques 96 Mons Hainaut 7000",
    "addr:housenumber":"96",
    "addr:postcode":"7000",
    "addr:street":"Chemin A\u0300 Baraques;Hainaut",
    "iso:country":"BE",
    "sg:address":"Chemin \u00e0 Baraques 96",
    "sg:city":"Mons",
    "sg:classifiers":[
        {
            "category":"Real Estate",
            "subcategory":"Architect",
            "type":"Services"
        }
    ],
    "sg:phone":"+32 65 35 54 93",
    "sg:postcode":"7000",
    "sg:province":"Hainaut",
    "wof:name":"Bourguet G",
    "wof:placetype":"venue"
},
  "geometry": {"coordinates":[4.0058321953,50.4545555115],"type":"Point"}
}