{
  "type": "Feature",
  "properties": {
    "iso:country":"BE",
    "sg:address":"Bekaflaan 31ba",
    "sg:city":"Aarschot",
    "sg:classifiers":[
        {
            "category":"Insurance",
            "subcategory":"Insurance Agent",
            "type":"Services"
        }
    ],
    "sg:phone":"+32 16 56 29 82",
    "sg:postcode":"3200",
    "sg:province":"Vlaams-Brabant",
    "sg:tags":[
        "verzekeringsmakelaars",
        "expert"
    ],
    "wof:name":"Hendrickx",
    "wof:placetype":"venue"
},
  "geometry": {"coordinates":[4.8413710594,50.9868469238],"type":"Point"}
}