{
  "type": "Feature",
  "properties": {
    "iso:country":"BE",
    "sg:address":"Postelarenweg 86",
    "sg:city":"Mol",
    "sg:orig_category":"Epiceries",
    "sg:phone":"+32 14 31 26 64",
    "sg:postcode":"2400",
    "sg:province":"Antwerpen",
    "wof:name":"Jan Vanhoof",
    "wof:placetype":"venue"
},
  "geometry": {"coordinates":[5.1024270058,51.1931228638],"type":"Point"}
}