{
  "type": "Feature",
  "properties": {
    "iso:country":"BE",
    "sg:address":"Kreuzstrasse 28",
    "sg:city":"Lontzen/lontzen",
    "sg:orig_category":"Loodgieterij, verwarming and sanitaire installaties",
    "sg:phone":"+32 87 65 96 04",
    "sg:postcode":"4711",
    "sg:province":"Li\u00e8ge",
    "wof:name":"Rene Schifflers-charlier/r. Schifflers",
    "wof:placetype":"venue"
},
  "geometry": {"coordinates":[6.047369957,50.6752853394],"type":"Point"}
}