{
  "type": "Feature",
  "properties": {
    "iso:country":"BE",
    "sg:address":"Rue Vanderborght 105",
    "sg:city":"Bruxelles (jette)",
    "sg:classifiers":[
        {
            "category":"Home & Garden",
            "subcategory":"Carpets & Floor Coverings",
            "type":"Retail Goods"
        }
    ],
    "sg:phone":"+32 2 425 16 62",
    "sg:postcode":"1090",
    "sg:province":"Bruxelles-Capitale",
    "sg:tags":[
        "parquet"
    ],
    "wof:name":"Alves Parquets",
    "wof:placetype":"venue"
},
  "geometry": {"coordinates":[4.3243169785,50.8685531616],"type":"Point"}
}