{
  "type": "Feature",
  "properties": {
    "addr:full":"31 Rue J. Wettinck 4101 Seraing 31",
    "addr:housenumber":"31;31",
    "addr:postcode":"4101",
    "addr:street":"Rue J. Wettinck",
    "iso:country":"BE",
    "sg:address":"31",
    "sg:city":"Rue J. Wettinck 4101 Seraing",
    "sg:classifiers":[
        {
            "category":"Manufacturing",
            "subcategory":"Metals",
            "type":"Manufacturing & Wholesale Goods"
        }
    ],
    "sg:phone":"+32 4 234 77 77",
    "sg:postcode":"31",
    "sg:tags":[
        "-",
        "machine",
        "equipment",
        "engineering",
        "machinery",
        "mechanical"
    ],
    "wof:name":"Outilac Sa",
    "wof:placetype":"venue"
},
  "geometry": {"coordinates":[5.5022058487,50.6154212952],"type":"Point"}
}