{
  "type": "Feature",
  "properties": {
    "iso:country":"BE",
    "sg:address":"Bergenstraat 178",
    "sg:city":"Oud-heverlee",
    "sg:orig_category":"Fotografen and fotostudio's",
    "sg:phone":"+32 16 40 26 21",
    "sg:postcode":"3052",
    "sg:province":"Vlaams-Brabant",
    "wof:name":"Luc Struyf",
    "wof:placetype":"venue"
},
  "geometry": {"coordinates":[4.7229399681,50.8235588074],"type":"Point"}
}