{
  "type": "Feature",
  "properties": {
    "addr:full":"Bredabaan 522 Wuustwezel Antwerpen 2990",
    "addr:housenumber":"522",
    "addr:postcode":"2990",
    "addr:street":"Bredabaan",
    "iso:country":"BE",
    "sg:address":"Bredabaan 522",
    "sg:city":"Wuustwezel",
    "sg:orig_category":"Cr\u00e9meries",
    "sg:phone":"+32 3 669 96 22",
    "sg:postcode":"2990",
    "sg:province":"Antwerpen",
    "wof:name":"Huis St.marie",
    "wof:placetype":"venue"
},
  "geometry": {"coordinates":[4.5889811516,51.3880844116],"type":"Point"}
}