{
  "type": "Feature",
  "properties": {
    "addr:full":"President Kennedypark 37 Kortrijk West-Vlaanderen 8500",
    "addr:housenumber":"37",
    "addr:postcode":"8500",
    "addr:street":"President Kennedypark",
    "iso:country":"BE",
    "sg:address":"President Kennedypark 37",
    "sg:city":"Kortrijk",
    "sg:orig_category":"Avocats and conseillers juridiques",
    "sg:phone":"+32 56 23 51 11",
    "sg:postcode":"8500",
    "sg:province":"West-Vlaanderen",
    "wof:name":"Mark De Vlieghere",
    "wof:placetype":"venue"
},
  "geometry": {"coordinates":[3.2745509148,50.7990951538],"type":"Point"}
}