{
  "type": "Feature",
  "properties": {
    "addr:full":"Zandtiende 2 Brugge West-Vlaanderen 8310",
    "addr:housenumber":"2",
    "addr:postcode":"8310",
    "addr:street":"Zandtiende",
    "iso:country":"BE",
    "sg:address":"Zandtiende 2",
    "sg:city":"Brugge",
    "sg:orig_category":"Artistes ind\u00e9pendants",
    "sg:phone":"+32 50 35 18 53",
    "sg:postcode":"8310",
    "sg:province":"West-Vlaanderen",
    "wof:name":"Joseph Innegraeve",
    "wof:placetype":"venue"
},
  "geometry": {"coordinates":[3.2544128895,51.20470047],"type":"Point"}
}