{
  "type": "Feature",
  "properties": {
    "addr:full":"Groenstraat 32 Merelbeke Oost-Vlaanderen 9820",
    "addr:housenumber":"32",
    "addr:postcode":"9820",
    "addr:street":"Groenstraat",
    "iso:country":"BE",
    "sg:address":"Groenstraat 32",
    "sg:city":"Merelbeke",
    "sg:orig_category":"Plantes and fleurs Gr",
    "sg:phone":"+32 9 362 39 40",
    "sg:postcode":"9820",
    "sg:province":"Oost-Vlaanderen",
    "wof:name":"De Munter",
    "wof:placetype":"venue"
},
  "geometry": {"coordinates":[3.7406580448,50.9549827576],"type":"Point"}
}