{
  "type": "Feature",
  "properties": {
    "addr:full":"Avenue Jardin Ecole 23 Dison Li\u00e8ge 4820",
    "addr:housenumber":"23",
    "addr:postcode":"4820",
    "addr:street":"Avenue",
    "iso:country":"BE",
    "sg:address":"Avenue Jardin Ecole 23",
    "sg:city":"Dison",
    "sg:classifiers":[
        {
            "category":"Professional",
            "subcategory":"Art Services",
            "type":"Services"
        }
    ],
    "sg:phone":"+32 87 33 40 69",
    "sg:postcode":"4820",
    "sg:province":"Li\u00e8ge",
    "sg:tags":[
        "-",
        "painter",
        "artist"
    ],
    "wof:name":"Polinard R",
    "wof:placetype":"venue"
},
  "geometry": {"coordinates":[5.8477168083,50.6050987244],"type":"Point"}
}