{
  "type": "Feature",
  "properties": {
    "iso:country":"BE",
    "sg:address":"Brusselsesteenweg 329",
    "sg:city":"Mechelen",
    "sg:orig_category":"Gespecialiseerde residenti\u00eble bouw Installatie van metalen schrijnwerk SMEEDWERK, METAALBEWERKING AN",
    "sg:phone":"+32 15 43 05 56",
    "sg:postcode":"2800",
    "sg:province":"Antwerpen",
    "wof:name":"Edis",
    "wof:placetype":"venue"
},
  "geometry": {"coordinates":[4.4742918015,51.0063552856],"type":"Point"}
}