{
  "type": "Feature",
  "properties": {
    "iso:country":"BE",
    "sg:address":"Rue Du Saupont 91",
    "sg:city":"Bertrix",
    "sg:orig_category":"Begrafeniswezen",
    "sg:phone":"+32 61 41 10 79",
    "sg:postcode":"6880",
    "sg:province":"Luxembourg",
    "wof:name":"Moneau Fr\u00c8res",
    "wof:placetype":"venue"
},
  "geometry": {"coordinates":[5.2782912254,49.8514823914],"type":"Point"}
}