{
  "type": "Feature",
  "properties": {
    "addr:full":"Peulisbaan 76 Bonheiden Antwerpen 2820",
    "addr:housenumber":"76",
    "addr:postcode":"2820",
    "addr:street":"Peulisbaan",
    "iso:country":"BE",
    "sg:address":"Peulisbaan 76",
    "sg:city":"Bonheiden",
    "sg:orig_category":"Herstellingen and onderhoud van auto's",
    "sg:phone":"+32 15 51 38 46",
    "sg:postcode":"2820",
    "sg:province":"Antwerpen",
    "wof:name":"Jan Luytens",
    "wof:placetype":"venue"
},
  "geometry": {"coordinates":[4.5496602058,51.0218009949],"type":"Point"}
}