{
  "type": "Feature",
  "properties": {
    "addr:full":"Zikastraat 48 Geraardsbergen Oost-Vlaanderen 9500",
    "addr:housenumber":"48",
    "addr:postcode":"9500",
    "addr:street":"Zikastraat",
    "iso:country":"BE",
    "sg:address":"Zikastraat 48",
    "sg:city":"Geraardsbergen",
    "sg:orig_category":"Sportclubs Sportterreinen and installaties behalve sportcentra",
    "sg:phone":"+32 54 41 85 67",
    "sg:postcode":"9500",
    "sg:province":"Oost-Vlaanderen",
    "wof:name":"F.c. Eendracht Moerbeke",
    "wof:placetype":"venue"
},
  "geometry": {"coordinates":[3.9110529423,50.7533187866],"type":"Point"}
}