{
  "type": "Feature",
  "properties": {
    "addr:full":"Avenue Charles Thielemans 36 Bruxelles (woluwe-saint-pierre) Bruxelles-Capitale 1150",
    "addr:housenumber":"36",
    "addr:postcode":"1150",
    "addr:street":"Avenue Charles Thielemans",
    "iso:country":"BE",
    "sg:address":"Avenue Charles Thielemans 36",
    "sg:city":"Bruxelles (woluwe-saint-pierre)",
    "sg:classifiers":[
        {
            "category":"Shopping",
            "subcategory":"Clothing, Apparel, & Fashions",
            "type":"Retail Goods"
        }
    ],
    "sg:phone":"+32 2 763 31 11",
    "sg:postcode":"1150",
    "sg:province":"Bruxelles-Capitale",
    "sg:tags":[
        "underwear",
        "lingerie",
        "-"
    ],
    "wof:name":"Princibeaut\u00e9",
    "wof:placetype":"venue"
},
  "geometry": {"coordinates":[4.4302301407,50.8368606567],"type":"Point"}
}