{
  "type": "Feature",
  "properties": {
    "addr:full":"Rue Eug\u00c8ne Renard 1 Anthisnes Li\u00e8ge 4160",
    "addr:housenumber":"1",
    "addr:postcode":"4160",
    "addr:street":"Rue Euge\u0300Ne Renard",
    "iso:country":"BE",
    "sg:address":"Rue Eug\u00c8ne Renard 1",
    "sg:city":"Anthisnes",
    "sg:orig_category":"Eleveurs de bovins",
    "sg:phone":"+32 4 383 62 29",
    "sg:postcode":"4160",
    "sg:province":"Li\u00e8ge",
    "wof:name":"Jules Henry",
    "wof:placetype":"venue"
},
  "geometry": {"coordinates":[5.5194430351,50.4860954285],"type":"Point"}
}