{
  "type": "Feature",
  "properties": {
    "addr:full":"Lef\u00c8vrestraat 160 Brussel Bruxelles-Capitale 1020",
    "addr:housenumber":"160",
    "addr:postcode":"1020",
    "addr:street":"Lefe\u0300Vrestraat",
    "iso:country":"BE",
    "sg:address":"Lef\u00c8vrestraat 160",
    "sg:city":"Brussel",
    "sg:orig_category":"D\u00e9m\u00e9nagements",
    "sg:phone":"+32 2 422 21 20",
    "sg:postcode":"1020",
    "sg:province":"Bruxelles-Capitale",
    "wof:name":"Ziegler",
    "wof:placetype":"venue"
},
  "geometry": {"coordinates":[4.3469018936,50.8707008362],"type":"Point"}
}