{
  "type": "Feature",
  "properties": {
    "addr:full":"Gasstraat 43 Kortrijk West-Vlaanderen 8500",
    "addr:housenumber":"43",
    "addr:postcode":"8500",
    "addr:street":"Gasstraat",
    "iso:country":"BE",
    "sg:address":"Gasstraat 43",
    "sg:city":"Kortrijk",
    "sg:classifiers":[
        {
            "category":"Personal",
            "subcategory":"Barber",
            "type":"Services"
        }
    ],
    "sg:phone":"+32 56 35 16 96",
    "sg:postcode":"8500",
    "sg:province":"West-Vlaanderen",
    "sg:tags":[
        "gentleman",
        "salon",
        "-",
        "hairdressing"
    ],
    "wof:name":"Mattelaer (coiffure)",
    "wof:placetype":"venue"
},
  "geometry": {"coordinates":[3.2557549477,50.831615448],"type":"Point"}
}