{
  "type": "Feature",
  "properties": {
    "addr:full":"Rue Du Brul\u00e9 54 Jemeppe-sur-sambre Namur 5190",
    "addr:housenumber":"54",
    "addr:postcode":"5190",
    "addr:street":"Rue Du Brule\u0301",
    "iso:country":"BE",
    "sg:address":"Rue Du Brul\u00e9 54",
    "sg:city":"Jemeppe-sur-sambre",
    "sg:classifiers":[
        {
            "category":"Personal",
            "subcategory":"Beauty Salon",
            "type":"Services"
        }
    ],
    "sg:phone":"+32 71 78 87 23",
    "sg:postcode":"5190",
    "sg:province":"Namur",
    "sg:tags":[
        "lady",
        "-",
        "hairdressing"
    ],
    "wof:name":"Brigitte",
    "wof:placetype":"venue"
},
  "geometry": {"coordinates":[4.6562738419,50.4516639709],"type":"Point"}
}