{
  "type": "Feature",
  "properties": {
    "iso:country":"BE",
    "sg:address":"Heide 26",
    "sg:city":"Puurs",
    "sg:classifiers":[
        {
            "category":"Building & Trades",
            "subcategory":"Plumbing",
            "type":"Services"
        }
    ],
    "sg:phone":"+32 3 889 01 57",
    "sg:postcode":"2870",
    "sg:province":"Antwerpen",
    "sg:tags":[
        "contractor"
    ],
    "wof:name":"Philips D",
    "wof:placetype":"venue"
},
  "geometry": {"coordinates":[4.2737607956,51.0696258545],"type":"Point"}
}