{
  "type": "Feature",
  "properties": {
    "addr:full":"Boulevard Barth\u00e9l\u00e9my 37 Bruxelles Bruxelles-Capitale 1000",
    "addr:housenumber":"37",
    "addr:postcode":"1000",
    "addr:street":"Boulevard Barthe\u0301Le\u0301My",
    "iso:country":"BE",
    "sg:address":"Boulevard Barth\u00e9l\u00e9my 37",
    "sg:city":"Bruxelles",
    "sg:classifiers":[
        {
            "category":"Communications",
            "subcategory":"Film & Video Production",
            "type":"Services"
        }
    ],
    "sg:phone":"+32 2 512 32 33",
    "sg:postcode":"1000",
    "sg:province":"Bruxelles-Capitale",
    "sg:tags":[
        "hiring",
        "-",
        "equipment"
    ],
    "wof:name":"Stienon",
    "wof:placetype":"venue"
},
  "geometry": {"coordinates":[4.3395957947,50.8509216309],"type":"Point"}
}