{
  "type": "Feature",
  "properties": {
    "iso:country":"BE",
    "sg:address":"Quartier De L'alliance 4",
    "sg:city":"Soumagne",
    "sg:orig_category":"Epiceries",
    "sg:phone":"+32 4 358 78 76",
    "sg:postcode":"4630",
    "sg:province":"Li\u00e8ge",
    "wof:name":"Jacqueline Piron",
    "wof:placetype":"venue"
},
  "geometry": {"coordinates":[5.7136201859,50.6092262268],"type":"Point"}
}