{
  "type": "Feature",
  "properties": {
    "addr:full":"233 Chaussee De Bruxelles 6042 Charleroi 233",
    "addr:housenumber":"233;233",
    "addr:postcode":"6042",
    "addr:street":"Chaussee De Bruxelles;Charleroi",
    "iso:country":"BE",
    "sg:address":"233",
    "sg:city":"Chaussee De Bruxelles 6042 Charleroi",
    "sg:classifiers":[
        {
            "category":"Home & Garden",
            "subcategory":"Furniture",
            "type":"Retail Goods"
        }
    ],
    "sg:phone":"+32 71 32 67 95",
    "sg:postcode":"233",
    "sg:tags":[
        "wood"
    ],
    "wof:name":"Metiers Du Bois Sa",
    "wof:placetype":"venue"
},
  "geometry": {"coordinates":[4.4365448952,50.4123649597],"type":"Point"}
}