{
  "type": "Feature",
  "properties": {
    "addr:full":"Place Communale 9 Plombieres/plombieres Li\u00e8ge 4850",
    "addr:housenumber":"9",
    "addr:postcode":"4850",
    "addr:street":"Place Communale",
    "iso:country":"BE",
    "sg:address":"Place Communale 9",
    "sg:city":"Plombieres/plombieres",
    "sg:classifiers":[
        {
            "category":"Health Services",
            "subcategory":"Nursing And Care Facility",
            "type":"Services"
        }
    ],
    "sg:phone":"+32 87 78 91 30",
    "sg:postcode":"4850",
    "sg:province":"Li\u00e8ge",
    "sg:tags":[
        "public"
    ],
    "wof:name":"Administration Communale",
    "wof:placetype":"venue"
},
  "geometry": {"coordinates":[5.9626002312,50.7068138123],"type":"Point"}
}