{
  "type": "Feature",
  "properties": {
    "addr:full":"Molenstraat 137 Kaprijke Oost-Vlaanderen 9970",
    "addr:housenumber":"137",
    "addr:postcode":"9970",
    "addr:street":"Molenstraat",
    "iso:country":"BE",
    "sg:address":"Molenstraat 137",
    "sg:city":"Kaprijke",
    "sg:orig_category":"Rundveehouders",
    "sg:phone":"+32 9 373 68 97",
    "sg:postcode":"9970",
    "sg:province":"Oost-Vlaanderen",
    "wof:name":"Marnix Somnel",
    "wof:placetype":"venue"
},
  "geometry": {"coordinates":[3.6198608875,51.2303352356],"type":"Point"}
}