{
  "type": "Feature",
  "properties": {
    "iso:country":"BE",
    "sg:address":"Lammekenslaan 6",
    "sg:city":"Knokke-heist",
    "sg:orig_category":"H\u00f4tels",
    "sg:phone":"+32 50 60 38 89",
    "sg:postcode":"8300",
    "sg:province":"West-Vlaanderen",
    "wof:name":"Binnenhof",
    "wof:placetype":"venue"
},
  "geometry": {"coordinates":[3.2965669632,51.349445343],"type":"Point"}
}