{
  "type": "Feature",
  "properties": {
    "iso:country":"BE",
    "sg:address":"Rue Les Cours 236bbis",
    "sg:city":"Theux",
    "sg:orig_category":"Boekhouders",
    "sg:phone":"+32 87 37 67 64",
    "sg:postcode":"4910",
    "sg:province":"Li\u00e8ge",
    "wof:name":"Lucas Luca Pinazo",
    "wof:placetype":"venue"
},
  "geometry": {"coordinates":[5.7979841232,50.4771842957],"type":"Point"}
}