{
  "type": "Feature",
  "properties": {
    "addr:full":"Turnhoutsebaan 619 Wijnegem Antwerpen 2110",
    "addr:housenumber":"619",
    "addr:postcode":"2110",
    "addr:street":"Turnhoutsebaan",
    "iso:country":"BE",
    "sg:address":"Turnhoutsebaan 619",
    "sg:city":"Wijnegem",
    "sg:classifiers":[
        {
            "category":"Professional",
            "subcategory":"Accounting & Tax Preparation",
            "type":"Services"
        }
    ],
    "sg:phone":"+32 3 353 63 73",
    "sg:postcode":"2110",
    "sg:province":"Antwerpen",
    "sg:tags":[
        "bookkeeper"
    ],
    "wof:name":"Byttebier C",
    "wof:placetype":"venue"
},
  "geometry": {"coordinates":[4.5492901802,51.2301025391],"type":"Point"}
}