{
  "type": "Feature",
  "properties": {
    "iso:country":"BE",
    "sg:address":"Eernegemsestraat 75",
    "sg:city":"Zedelgem (aartrijke)",
    "sg:classifiers":[
        {
            "category":"Food & Beverages",
            "subcategory":"Meat & Fish",
            "type":"Retail Goods"
        }
    ],
    "sg:phone":"+32 50 20 90 60",
    "sg:postcode":"8211",
    "sg:province":"West-Vlaanderen",
    "sg:tags":[
        "poultry",
        "whol",
        "game",
        "-"
    ],
    "wof:name":"Maekelbergh J & E",
    "wof:placetype":"venue"
},
  "geometry": {"coordinates":[3.0889649391,51.1200408936],"type":"Point"}
}