{
  "type": "Feature",
  "properties": {
    "addr:full":"Zegersdreef 114 Brasschaat Antwerpen 2930",
    "addr:housenumber":"114",
    "addr:postcode":"2930",
    "iso:country":"BE",
    "sg:address":"Zegersdreef 114",
    "sg:city":"Brasschaat",
    "sg:classifiers":[
        {
            "category":"Insurance",
            "subcategory":"Insurance Agent",
            "type":"Services"
        }
    ],
    "sg:phone":"+32 3 651 54 61",
    "sg:postcode":"2930",
    "sg:province":"Antwerpen",
    "sg:tags":[
        "broker"
    ],
    "wof:name":"Arntz Xavier",
    "wof:placetype":"venue"
},
  "geometry": {"coordinates":[4.4753217697,51.2949485779],"type":"Point"}
}