{
  "type": "Feature",
  "properties": {
    "iso:country":"BE",
    "sg:address":"Rue Hermes Van Wyngene 66",
    "sg:city":"Renaix",
    "sg:classifiers":[
        {
            "category":"Manufacturing",
            "subcategory":"Textiles",
            "type":"Manufacturing & Wholesale Goods"
        }
    ],
    "sg:phone":"+32 55 21 96 09",
    "sg:postcode":"9600",
    "sg:province":"Oost-Vlaanderen",
    "sg:tags":[
        "technical"
    ],
    "wof:name":"Rommens Intertrade Bvba",
    "wof:placetype":"venue"
},
  "geometry": {"coordinates":[3.6101090908,50.7423629761],"type":"Point"}
}