{
  "type": "Feature",
  "properties": {
    "addr:full":"Rue Beaufaux 48 Ellezelles Hainaut 7890",
    "addr:housenumber":"48",
    "addr:postcode":"7890",
    "addr:street":"Rue Beaufaux",
    "iso:country":"BE",
    "sg:address":"Rue Beaufaux 48",
    "sg:city":"Ellezelles",
    "sg:classifiers":[
        {
            "category":"Insurance",
            "subcategory":"Life Insurance",
            "type":"Services"
        }
    ],
    "sg:phone":"+32 68 54 28 51",
    "sg:postcode":"7890",
    "sg:province":"Hainaut",
    "sg:tags":[
        "assurance"
    ],
    "wof:name":"W. Cosijns",
    "wof:placetype":"venue"
},
  "geometry": {"coordinates":[3.6671099663,50.7479667664],"type":"Point"}
}