{
  "type": "Feature",
  "properties": {
    "addr:full":"Berlaarbaan 404 Sint-katelijne-waver (onze-lieve-vrouw-waver) Antwerpen 2861",
    "addr:housenumber":"404",
    "addr:postcode":"2861",
    "addr:street":"Berlaarbaan",
    "iso:country":"BE",
    "sg:address":"Berlaarbaan 404",
    "sg:city":"Sint-katelijne-waver (onze-lieve-vrouw-waver)",
    "sg:classifiers":[
        {
            "category":"Banks & Credit Unions",
            "subcategory":"Investment Brokerage",
            "type":"Services"
        }
    ],
    "sg:phone":"+32 15 75 53 66",
    "sg:postcode":"2861",
    "sg:province":"Antwerpen",
    "sg:tags":[
        "fence"
    ],
    "wof:name":"Jacobs Nv",
    "wof:placetype":"venue"
},
  "geometry": {"coordinates":[4.5722432137,51.0710105896],"type":"Point"}
}