{
  "type": "Feature",
  "properties": {
    "addr:full":"Rechtstraat 130 Lokeren Oost-Vlaanderen 9160",
    "addr:housenumber":"130",
    "addr:postcode":"9160",
    "addr:street":"Rechtstraat",
    "iso:country":"BE",
    "sg:address":"Rechtstraat 130",
    "sg:city":"Lokeren",
    "sg:orig_category":"Jardins botaniques, zoologiques, observatoires and r\u00e9serves naturelles",
    "sg:phone":"+32 9 346 64 68",
    "sg:postcode":"9160",
    "sg:province":"Oost-Vlaanderen",
    "wof:name":"Daknamse Meersen",
    "wof:placetype":"venue"
},
  "geometry": {"coordinates":[3.9426870346,51.1420898438],"type":"Point"}
}