{
  "type": "Feature",
  "properties": {
    "addr:full":"Paul Van Ostaijenlaan 17 Antwerpen Antwerpen 2050",
    "addr:housenumber":"17",
    "addr:postcode":"2050",
    "addr:street":"Paul Van Ostaijenlaan",
    "iso:country":"BE",
    "sg:address":"Paul Van Ostaijenlaan 17",
    "sg:city":"Antwerpen",
    "sg:orig_category":"Instituts de beaut\u00e9",
    "sg:phone":"+32 3 219 48 51",
    "sg:postcode":"2050",
    "sg:province":"Antwerpen",
    "wof:name":"Lieveke Decraemer",
    "wof:placetype":"venue"
},
  "geometry": {"coordinates":[4.3848319054,51.2192382812],"type":"Point"}
}