{
  "type": "Feature",
  "properties": {
    "addr:full":"Avenue Fernand Desonay 93 Verviers Li\u00e8ge 4801",
    "addr:housenumber":"93",
    "addr:postcode":"4801",
    "addr:street":"Avenue Fernand Desonay",
    "iso:country":"BE",
    "sg:address":"Avenue Fernand Desonay 93",
    "sg:city":"Verviers",
    "sg:orig_category":"Pharmaciens",
    "sg:phone":"+32 87 22 02 36",
    "sg:postcode":"4801",
    "sg:province":"Li\u00e8ge",
    "wof:name":"Pharmacie Populaire",
    "wof:placetype":"venue"
},
  "geometry": {"coordinates":[5.8890638351,50.587978363],"type":"Point"}
}