{
  "type": "Feature",
  "properties": {
    "addr:full":"Veldmansbrugstraat 2-5 Hasselt Limburg 3500",
    "addr:housenumber":"2-5",
    "addr:postcode":"3500",
    "addr:street":"Veldmansbrugstraat",
    "iso:country":"BE",
    "sg:address":"Veldmansbrugstraat 2-5",
    "sg:city":"Hasselt",
    "sg:classifiers":[
        {
            "category":"Professional",
            "subcategory":"Art Services",
            "type":"Services"
        }
    ],
    "sg:phone":"+32 11 23 52 09",
    "sg:postcode":"3500",
    "sg:province":"Limburg",
    "sg:tags":[
        "interior",
        "designer"
    ],
    "wof:name":"Vandebosch Geert",
    "wof:placetype":"venue"
},
  "geometry": {"coordinates":[5.3497161865,50.9328727722],"type":"Point"}
}