{
  "type": "Feature",
  "properties": {
    "iso:country":"BE",
    "sg:address":"Herbergstraat 13a",
    "sg:city":"Aalst (moorsel)",
    "sg:classifiers":[
        {
            "category":"Home & Garden",
            "subcategory":"Building Materials",
            "type":"Retail Goods"
        }
    ],
    "sg:phone":"+32 53 78 59 43",
    "sg:postcode":"9310",
    "sg:province":"Oost-Vlaanderen",
    "sg:tags":[
        "window"
    ],
    "wof:name":"Callebaut Schrijnwerkerij Nv",
    "wof:placetype":"venue"
},
  "geometry": {"coordinates":[4.1046051979,50.9652442932],"type":"Point"}
}