{
  "type": "Feature",
  "properties": {
    "addr:full":"Hoogstraat 67 Genk Limburg 3600",
    "addr:housenumber":"67",
    "addr:postcode":"3600",
    "addr:street":"Hoogstraat",
    "iso:country":"BE",
    "sg:address":"Hoogstraat 67",
    "sg:city":"Genk",
    "sg:orig_category":"Agences d\u00b4interim and personnel temporaire",
    "sg:phone":"+32 89 35 77 07",
    "sg:postcode":"3600",
    "sg:province":"Limburg",
    "wof:name":"Asap Interim",
    "wof:placetype":"venue"
},
  "geometry": {"coordinates":[5.5052719116,50.9593315125],"type":"Point"}
}