{
  "type": "Feature",
  "properties": {
    "addr:full":"Rue Du Haut 204 Aubange Luxembourg 6792",
    "addr:housenumber":"204",
    "addr:postcode":"6792",
    "addr:street":"Rue Du Haut",
    "iso:country":"BE",
    "sg:address":"Rue Du Haut 204",
    "sg:city":"Aubange",
    "sg:orig_category":"Catering and organisation de f\u00eates",
    "sg:phone":"+32 63 67 54 11",
    "sg:postcode":"6792",
    "sg:province":"Luxembourg",
    "wof:name":"Traiteur Wolff",
    "wof:placetype":"venue"
},
  "geometry": {"coordinates":[5.7262368202,49.5948410034],"type":"Point"}
}