{
  "type": "Feature",
  "properties": {
    "addr:full":"Turnhoutsebaan 2 Retie Antwerpen 2470",
    "addr:housenumber":"2",
    "addr:postcode":"2470",
    "addr:street":"Turnhoutsebaan",
    "iso:country":"BE",
    "sg:address":"Turnhoutsebaan 2",
    "sg:city":"Retie",
    "sg:orig_category":"Pain, p\u00e2tisseries and confiseries",
    "sg:phone":"+32 14 37 32 05",
    "sg:postcode":"2470",
    "sg:province":"Antwerpen",
    "wof:name":"Vital Melis",
    "wof:placetype":"venue"
},
  "geometry": {"coordinates":[5.0807337761,51.2695426941],"type":"Point"}
}