{
  "type": "Feature",
  "properties": {
    "addr:full":"Chemin Du Bois 1 Thimister-clermont Li\u00e8ge 4890",
    "addr:housenumber":"1",
    "addr:postcode":"4890",
    "addr:street":"Chemin Du Bois",
    "iso:country":"BE",
    "sg:address":"Chemin Du Bois 1",
    "sg:city":"Thimister-clermont",
    "sg:orig_category":"Installatie van houten of kunststof schrijnwerk",
    "sg:phone":"+32 87 44 64 70",
    "sg:postcode":"4890",
    "sg:province":"Li\u00e8ge",
    "wof:name":"Philippe Crutzen",
    "wof:placetype":"venue"
},
  "geometry": {"coordinates":[5.8679571152,50.6680603027],"type":"Point"}
}