{
  "type": "Feature",
  "properties": {
    "iso:country":"BE",
    "sg:address":"Hauptstrasse 12",
    "sg:city":"Sankt Vith",
    "sg:classifiers":[
        {
            "category":"Retail",
            "subcategory":"Auto Rental",
            "type":"Services"
        }
    ],
    "sg:phone":"+32 80 22 66 70",
    "sg:postcode":"4780",
    "sg:province":"Li\u00e8ge",
    "sg:tags":[
        "automobile",
        "-",
        "car",
        "self-drive"
    ],
    "wof:name":"Gima Lease Sprlu",
    "wof:placetype":"venue"
},
  "geometry": {"coordinates":[6.1269030571,50.2796974182],"type":"Point"}
}