{
  "type": "Feature",
  "properties": {
    "iso:country":"BE",
    "sg:address":"Groentemarkt 13",
    "sg:city":"Lokeren",
    "sg:classifiers":[
        {
            "category":"Bars & Pubs",
            "type":"Food & Drink"
        }
    ],
    "sg:phone":"+32 9 339 05 16",
    "sg:postcode":"9160",
    "sg:province":"Oost-Vlaanderen",
    "wof:name":"Fonteyn (de)",
    "wof:placetype":"venue"
},
  "geometry": {"coordinates":[3.9876849651,51.103767395],"type":"Point"}
}