{
  "type": "Feature",
  "properties": {
    "addr:full":"Hellestraat 18 Wervik West-Vlaanderen 8940",
    "addr:housenumber":"18",
    "addr:postcode":"8940",
    "addr:street":"Hellestraat",
    "iso:country":"BE",
    "sg:address":"Hellestraat 18",
    "sg:city":"Wervik",
    "sg:classifiers":[
        {
            "category":"Professional",
            "subcategory":"Testing Lab",
            "type":"Services"
        }
    ],
    "sg:phone":"+32 56 31 12 29",
    "sg:postcode":"8940",
    "sg:province":"West-Vlaanderen",
    "sg:tags":[
        "chemist"
    ],
    "wof:name":"Therssen J",
    "wof:placetype":"venue"
},
  "geometry": {"coordinates":[3.0537159443,50.7826499939],"type":"Point"}
}