{
  "type": "Feature",
  "properties": {
    "addr:full":"Luxemburger Strasse 92 Sankt Vith Li\u00e8ge 4780",
    "addr:housenumber":"92",
    "addr:postcode":"4780",
    "addr:street":"Luxemburger Strasse",
    "iso:country":"BE",
    "sg:address":"Luxemburger Strasse 92",
    "sg:city":"Sankt Vith",
    "sg:classifiers":[
        {
            "category":"Communications",
            "type":"Services"
        }
    ],
    "sg:phone":"+32 80 22 88 97",
    "sg:postcode":"4780",
    "sg:province":"Li\u00e8ge",
    "sg:tags":[
        "translator"
    ],
    "wof:name":"Thannen A",
    "wof:placetype":"venue"
},
  "geometry": {"coordinates":[6.1147608757,50.2686843872],"type":"Point"}
}