{
  "type": "Feature",
  "properties": {
    "iso:country":"BE",
    "sg:address":"Drongenplein 10",
    "sg:city":"Gent",
    "sg:orig_category":"Articles de jardin",
    "sg:phone":"+32 9 227 28 08",
    "sg:postcode":"9031",
    "sg:province":"Oost-Vlaanderen",
    "wof:name":"Impexco",
    "wof:placetype":"venue"
},
  "geometry": {"coordinates":[3.6640100479,51.0507392883],"type":"Point"}
}