{
  "type": "Feature",
  "properties": {
    "addr:full":"Rue De La Fontaine 25 Dour Hainaut 7370",
    "addr:housenumber":"25",
    "addr:postcode":"7370",
    "addr:street":"Rue De La Fontaine;Hainaut",
    "iso:country":"BE",
    "sg:address":"Rue De La Fontaine 25",
    "sg:city":"Dour",
    "sg:orig_category":"Catering and organisatie van feesten Slagers",
    "sg:phone":"+32 65 65 41 37",
    "sg:postcode":"7370",
    "sg:province":"Hainaut",
    "wof:name":"J. Broh\u00c9e",
    "wof:placetype":"venue"
},
  "geometry": {"coordinates":[3.7512350082,50.3966712952],"type":"Point"}
}