{
  "type": "Feature",
  "properties": {
    "iso:country":"BE",
    "sg:address":"Eikerweg 15",
    "sg:city":"Bilzen",
    "sg:orig_category":"Services divers aux personnes. Location de biens divers. Animations diverses",
    "sg:phone":"+32 89 41 59 61",
    "sg:postcode":"3740",
    "sg:province":"Limburg",
    "wof:name":"Ludo's Animatie",
    "wof:placetype":"venue"
},
  "geometry": {"coordinates":[5.5092978477,50.9037322998],"type":"Point"}
}