{
  "type": "Feature",
  "properties": {
    "addr:full":"Langestraat 38 Brugge West-Vlaanderen 8000",
    "addr:housenumber":"38",
    "addr:postcode":"8000",
    "addr:street":"Langestraat",
    "iso:country":"BE",
    "sg:address":"Langestraat 38",
    "sg:city":"Brugge",
    "sg:classifiers":[
        {
            "category":"Travel",
            "subcategory":"Hotels & Motels",
            "type":"Entertainment"
        }
    ],
    "sg:phone":"+32 50 33 88 89",
    "sg:postcode":"8000",
    "sg:province":"West-Vlaanderen",
    "wof:name":"Flanders",
    "wof:placetype":"venue"
},
  "geometry": {"coordinates":[3.2335250378,51.2095146179],"type":"Point"}
}