{
  "type": "Feature",
  "properties": {
    "addr:full":"Chauss\u00e9e De Lille 2 Tournai Hainaut 7500",
    "addr:housenumber":"2",
    "addr:postcode":"7500",
    "addr:street":"Chausse\u0301E De Lille",
    "iso:country":"BE",
    "sg:address":"Chauss\u00e9e De Lille 2",
    "sg:city":"Tournai",
    "sg:classifiers":[
        {
            "category":"Education",
            "subcategory":"School",
            "type":"Public Place"
        }
    ],
    "sg:phone":"+32 69 89 02 50",
    "sg:postcode":"7500",
    "sg:province":"Hainaut",
    "sg:tags":[
        "secondary"
    ],
    "wof:name":"Institut Technique Des M\u00e9tiers De L'alimentation De La Communaut\u00e9 Fran\u00e7aise",
    "wof:placetype":"venue"
},
  "geometry": {"coordinates":[3.3767390251,50.6054000854],"type":"Point"}
}