{
  "type": "Feature",
  "properties": {
    "addr:full":"Kruisveldweg 4 Lier Antwerpen 2500",
    "addr:housenumber":"4",
    "addr:postcode":"2500",
    "addr:street":"Kruisveldweg",
    "iso:country":"BE",
    "sg:address":"Kruisveldweg 4",
    "sg:city":"Lier",
    "sg:orig_category":"HUISBRANDOLIE",
    "sg:phone":"+32 3 488 25 90",
    "sg:postcode":"2500",
    "sg:province":"Antwerpen",
    "wof:name":"Van Baren Coal Trade",
    "wof:placetype":"venue"
},
  "geometry": {"coordinates":[4.5497322083,51.1204071045],"type":"Point"}
}