{
  "type": "Feature",
  "properties": {
    "iso:country":"BE",
    "sg:address":"Rue Du Jardinet 21",
    "sg:city":"Walcourt",
    "sg:orig_category":"Voertuigen",
    "sg:phone":"+32 71 61 19 68",
    "sg:postcode":"5650",
    "sg:province":"Namur",
    "wof:name":"Garage Servo",
    "wof:placetype":"venue"
},
  "geometry": {"coordinates":[4.4341411591,50.2569160461],"type":"Point"}
}