{
  "type": "Feature",
  "properties": {
    "iso:country":"BE",
    "sg:address":"Brugsesteenweg 12",
    "sg:city":"Pittem",
    "sg:classifiers":[
        {
            "category":"Manufacturing",
            "subcategory":"Lumber",
            "type":"Manufacturing & Wholesale Goods"
        }
    ],
    "sg:phone":"+32 51 48 85 98",
    "sg:postcode":"8740",
    "sg:province":"West-Vlaanderen",
    "sg:tags":[
        "timber"
    ],
    "wof:name":"Remmery A & Zn Sv",
    "wof:placetype":"venue"
},
  "geometry": {"coordinates":[3.2355899811,51.0062103271],"type":"Point"}
}