{
  "type": "Feature",
  "properties": {
    "addr:full":"Hanekamlos 15 Destelbergen Oost-Vlaanderen 9070",
    "addr:housenumber":"15",
    "addr:postcode":"9070",
    "addr:street":"Hanekamlos",
    "iso:country":"BE",
    "sg:address":"Hanekamlos 15",
    "sg:city":"Destelbergen",
    "sg:orig_category":"Tuinen",
    "sg:phone":"+32 9 229 18 32",
    "sg:postcode":"9070",
    "sg:province":"Oost-Vlaanderen",
    "wof:name":"Steven Wybaillie",
    "wof:placetype":"venue"
},
  "geometry": {"coordinates":[3.7981390953,51.0470657349],"type":"Point"}
}