{
  "type": "Feature",
  "properties": {
    "iso:country":"BE",
    "sg:address":"Aalstsesteenweg 65",
    "sg:city":"Geraardsbergen (schendelbeke)",
    "sg:classifiers":[
        {
            "category":"Real Estate",
            "subcategory":"Architect",
            "type":"Services"
        }
    ],
    "sg:phone":"+32 54 41 90 36",
    "sg:postcode":"9506",
    "sg:province":"Oost-Vlaanderen",
    "wof:name":"Corijn J",
    "wof:placetype":"venue"
},
  "geometry": {"coordinates":[3.8985300064,50.7987060547],"type":"Point"}
}