{
  "type": "Feature",
  "properties": {
    "addr:full":"Koninklijke Baan 106 Koksijde West-Vlaanderen 8670",
    "addr:housenumber":"106",
    "addr:postcode":"8670",
    "addr:street":"Koninklijke Baan",
    "iso:country":"BE",
    "sg:address":"Koninklijke Baan 106",
    "sg:city":"Koksijde",
    "sg:orig_category":"Immobili\u00ebnkantoren",
    "sg:phone":"+32 58 52 07 92",
    "sg:postcode":"8670",
    "sg:province":"West-Vlaanderen",
    "wof:name":"Agence Ultimmo",
    "wof:placetype":"venue"
},
  "geometry": {"coordinates":[2.6362628937,51.121181488],"type":"Point"}
}