{
  "type": "Feature",
  "properties": {
    "iso:country":"BE",
    "sg:address":"Avenue Jean Mermoz",
    "sg:city":"Gosselies",
    "sg:classifiers":[
        {
            "category":"Professional",
            "subcategory":"Printing & Photocopies",
            "type":"Services"
        }
    ],
    "sg:phone":"+32 71 37 40 18",
    "sg:postcode":"6041",
    "sg:province":"Hainaut",
    "sg:tags":[
        "shop",
        "industrial"
    ],
    "wof:name":"Europrinter S.a.",
    "wof:placetype":"venue"
},
  "geometry": {"coordinates":[4.4753499031,50.4757995605],"type":"Point"}
}