{
  "type": "Feature",
  "properties": {
    "iso:country":"BE",
    "sg:address":"Rue De L'esplanade 52",
    "sg:city":"Sprimont",
    "sg:orig_category":"RESTAURANTS: H\u00d4TELS",
    "sg:phone":"+32 4 360 82 17",
    "sg:postcode":"4141",
    "sg:province":"Li\u00e8ge",
    "wof:name":"H\u00d4tel De La Chapelle",
    "wof:placetype":"venue"
},
  "geometry": {"coordinates":[5.739525795,50.5378112793],"type":"Point"}
}