{
  "type": "Feature",
  "properties": {
    "addr:full":"Dokter Loriersstraat 26 Genk Limburg 3600",
    "addr:housenumber":"26",
    "addr:postcode":"3600",
    "addr:street":"Dokter Loriersstraat",
    "iso:country":"BE",
    "sg:address":"Dokter Loriersstraat 26",
    "sg:city":"Genk",
    "sg:classifiers":[
        {
            "category":"Health Services",
            "subcategory":"Health Practitioner",
            "type":"Services"
        }
    ],
    "sg:phone":"+32 11 22 50 07",
    "sg:postcode":"3600",
    "sg:province":"Limburg",
    "sg:tags":[
        "physiotherapist"
    ],
    "wof:name":"Houben A",
    "wof:placetype":"venue"
},
  "geometry": {"coordinates":[5.4242110252,50.9533004761],"type":"Point"}
}