{
  "type": "Feature",
  "properties": {
    "addr:full":"Avenue Ducp\u00e9tiaux 128 Bruxelles (saint-gilles) Bruxelles-Capitale 1060",
    "addr:housenumber":"128",
    "addr:postcode":"1060",
    "addr:street":"Avenue Ducpe\u0301Tiaux",
    "iso:country":"BE",
    "sg:address":"Avenue Ducp\u00e9tiaux 128",
    "sg:city":"Bruxelles (saint-gilles)",
    "sg:classifiers":[
        {
            "category":"Professional",
            "subcategory":"Art Services",
            "type":"Services"
        }
    ],
    "sg:phone":"+32 2 344 46 00",
    "sg:postcode":"1060",
    "sg:province":"Bruxelles-Capitale",
    "sg:tags":[
        "graphic",
        "designer"
    ],
    "wof:name":"Souris Apprivois\u00e9e (la) Sprl",
    "wof:placetype":"venue"
},
  "geometry": {"coordinates":[4.3442568779,50.8218727112],"type":"Point"}
}