{
  "type": "Feature",
  "properties": {
    "addr:full":"Rue Du Noyer 299 Brussel/bruxelles Bruxelles-Capitale 1000",
    "addr:housenumber":"299",
    "addr:postcode":"1000",
    "addr:street":"Rue Du Noyer;/",
    "iso:country":"BE",
    "sg:address":"Rue Du Noyer 299",
    "sg:city":"Brussel/bruxelles",
    "sg:orig_category":"Magasins de r\u00e9parations d'articles personnels et m\u00e9nagers divers. V\u00eatements sur mesure Fab",
    "sg:phone":"+32 2 733 66 13",
    "sg:postcode":"1000",
    "sg:province":"Bruxelles-Capitale",
    "wof:name":"Maison Miange",
    "wof:placetype":"venue"
},
  "geometry": {"coordinates":[4.3959088326,50.8434791565],"type":"Point"}
}