{
  "type": "Feature",
  "properties": {
    "iso:country":"BE",
    "sg:address":"Rollegemstraat 59",
    "sg:city":"Ledegem",
    "sg:classifiers":[
        {
            "category":"Communications",
            "type":"Services"
        }
    ],
    "sg:phone":"+32 56 50 62 05",
    "sg:postcode":"8880",
    "sg:province":"West-Vlaanderen",
    "sg:tags":[
        "translator"
    ],
    "wof:name":"Techniconsult Nv",
    "wof:placetype":"venue"
},
  "geometry": {"coordinates":[3.1298019886,50.8570213318],"type":"Point"}
}