{
  "type": "Feature",
  "properties": {
    "iso:country":"BE",
    "sg:address":"Rue General Melliertilly 27",
    "sg:city":"Tilly",
    "sg:classifiers":[
        {
            "category":"Parking",
            "subcategory":"Bicycle",
            "type":"Transportation"
        }
    ],
    "sg:phone":"+32 71 87 76 40",
    "sg:postcode":"1495",
    "sg:province":"Brabant Wallon",
    "sg:tags":[
        "wheel",
        "cutting-off",
        "diamond"
    ],
    "wof:name":"Carbodiam S.a.",
    "wof:placetype":"venue"
},
  "geometry": {"coordinates":[4.5524921417,50.5627212524],"type":"Point"}
}