{
  "type": "Feature",
  "properties": {
    "iso:country":"BE",
    "sg:address":"Zilveren-helmenstraat 60ba",
    "sg:city":"Halen",
    "sg:orig_category":"Landmeters",
    "sg:phone":"+32 13 46 10 38",
    "sg:postcode":"3545",
    "sg:province":"Limburg",
    "wof:name":"Dirk Arnauts",
    "wof:placetype":"venue"
},
  "geometry": {"coordinates":[5.07899189,50.935634613],"type":"Point"}
}