{
  "type": "Feature",
  "properties": {
    "addr:full":"Rue Du Coll\u00e8ge 25-27 Namur Namur 5000",
    "addr:postcode":"25-27;5000",
    "addr:street":"Rue Du Colle\u0300Ge",
    "iso:country":"BE",
    "sg:address":"Rue Du Coll\u00e8ge 25-27",
    "sg:city":"Namur",
    "sg:classifiers":[
        {
            "category":"Retail",
            "subcategory":"Event Space",
            "type":"Services"
        }
    ],
    "sg:phone":"+32 81 65 65 81",
    "sg:postcode":"5000",
    "sg:province":"Namur",
    "sg:tags":[
        "rental",
        "-",
        "hall"
    ],
    "wof:name":"Saint Loup Fondue (le)",
    "wof:placetype":"venue"
},
  "geometry": {"coordinates":[4.8629379272,50.4635772705],"type":"Point"}
}