{
  "type": "Feature",
  "properties": {
    "addr:full":"Place Verte 90 Spa Li\u00e8ge 4900",
    "addr:housenumber":"90",
    "addr:postcode":"4900",
    "addr:street":"Place Verte",
    "iso:country":"BE",
    "sg:address":"Place Verte 90",
    "sg:city":"Spa",
    "sg:orig_category":"Boucheries",
    "sg:phone":"+32 87 77 11 21",
    "sg:postcode":"4900",
    "sg:province":"Li\u00e8ge",
    "wof:name":"Jean Gaspar",
    "wof:placetype":"venue"
},
  "geometry": {"coordinates":[5.8633999825,50.4905815125],"type":"Point"}
}