{
  "type": "Feature",
  "properties": {
    "addr:full":"Rue Gustave-delperdange 56 Bastogne Luxembourg 6600",
    "addr:housenumber":"56",
    "addr:postcode":"6600",
    "addr:street":"Rue Gustave-Delperdange",
    "iso:country":"BE",
    "sg:address":"Rue Gustave-delperdange 56",
    "sg:city":"Bastogne",
    "sg:orig_category":"Installatie van houten of kunststof schrijnwerk",
    "sg:phone":"+32 61 21 13 46",
    "sg:postcode":"6600",
    "sg:province":"Luxembourg",
    "wof:name":"Jean Pirnay",
    "wof:placetype":"venue"
},
  "geometry": {"coordinates":[5.7270679474,50.007686615],"type":"Point"}
}