{
  "type": "Feature",
  "properties": {
    "addr:full":"Onderbergen 36 Gent Oost-Vlaanderen 9000",
    "addr:housenumber":"36",
    "addr:postcode":"9000",
    "addr:street":"Onderbergen;Oost-Vlaanderen",
    "iso:country":"BE",
    "sg:address":"Onderbergen 36",
    "sg:city":"Gent",
    "sg:orig_category":"Avocats and conseillers juridiques",
    "sg:phone":"+32 9 225 72 25",
    "sg:postcode":"9000",
    "sg:province":"Oost-Vlaanderen",
    "wof:name":"P. Tielemans",
    "wof:placetype":"venue"
},
  "geometry": {"coordinates":[3.7196230888,51.052318573],"type":"Point"}
}