{
  "type": "Feature",
  "properties": {
    "addr:full":"Naamsestraat 53 Leuven Vlaams-Brabant 3000",
    "addr:housenumber":"53",
    "addr:postcode":"3000",
    "addr:street":"Naamsestraat",
    "iso:country":"BE",
    "sg:address":"Naamsestraat 53",
    "sg:city":"Leuven",
    "sg:classifiers":[
        {
            "category":"Restaurant",
            "type":"Food & Drink"
        }
    ],
    "sg:phone":"+32 16 23 41 21",
    "sg:postcode":"3000",
    "sg:province":"Vlaams-Brabant",
    "wof:name":"De Vlaamsche Reus",
    "wof:placetype":"venue"
},
  "geometry": {"coordinates":[4.7006549835,50.8765144348],"type":"Point"}
}