{
  "type": "Feature",
  "properties": {
    "addr:full":"Grote Markt 9 Leuven Vlaams-Brabant 3000",
    "addr:housenumber":"9",
    "addr:postcode":"3000",
    "addr:street":"Grote Markt",
    "iso:country":"BE",
    "sg:address":"Grote Markt 9",
    "sg:city":"Leuven",
    "sg:classifiers":[
        {
            "category":"Government",
            "subcategory":"Office",
            "type":"Public Place"
        }
    ],
    "sg:phone":"+32 16 21 15 39",
    "sg:postcode":"3000",
    "sg:province":"Vlaams-Brabant",
    "sg:tags":[
        "-",
        "tourism",
        "federation"
    ],
    "wof:name":"Toerisme Leuven",
    "wof:placetype":"venue"
},
  "geometry": {"coordinates":[4.702149868,50.8788909912],"type":"Point"}
}