{
  "type": "Feature",
  "properties": {
    "addr:full":"Pierrelaan 12 Brecht Antwerpen 2960",
    "addr:housenumber":"12",
    "addr:postcode":"2960",
    "addr:street":"Pierrelaan",
    "iso:country":"BE",
    "sg:address":"Pierrelaan 12",
    "sg:city":"Brecht",
    "sg:classifiers":[
        {
            "category":"Building & Trades",
            "subcategory":"Plumbing",
            "type":"Services"
        }
    ],
    "sg:phone":"+32 3 646 41 68",
    "sg:postcode":"2960",
    "sg:province":"Antwerpen",
    "sg:tags":[
        "repair",
        "mainten",
        "-",
        "central",
        "heating"
    ],
    "wof:name":"Helco Bvba",
    "wof:placetype":"venue"
},
  "geometry": {"coordinates":[4.582613945,51.3183097839],"type":"Point"}
}