{
  "type": "Feature",
  "properties": {
    "addr:full":"Koningin Elisabethlaan 48 Gent Oost-Vlaanderen 9000",
    "addr:housenumber":"48",
    "addr:postcode":"9000",
    "addr:street":"Koningin Elisabethlaan;Oost-Vlaanderen",
    "iso:country":"BE",
    "sg:address":"Koningin Elisabethlaan 48",
    "sg:city":"Gent",
    "sg:orig_category":"S\u00e9curit\u00e9 sociale",
    "sg:phone":"+32 9 221 26 42",
    "sg:postcode":"9000",
    "sg:province":"Oost-Vlaanderen",
    "wof:name":"Christelijke Mutualiteit",
    "wof:placetype":"venue"
},
  "geometry": {"coordinates":[3.7144091129,51.0375862122],"type":"Point"}
}