{
  "type": "Feature",
  "properties": {
    "iso:country":"BE",
    "sg:address":"Vissenakenstraat 128/5",
    "sg:city":"Tienen (groot)",
    "sg:orig_category":"Centres sportifs",
    "sg:phone":"+32 16 40 24 72",
    "sg:postcode":"3300",
    "sg:province":"Vlaams-Brabant",
    "wof:name":"Genbukan Ninpo Bugei Belgium",
    "wof:placetype":"venue"
},
  "geometry": {"coordinates":[4.9337692261,50.8178520203],"type":"Point"}
}