{
  "type": "Feature",
  "properties": {
    "addr:full":"Rue Eau Sur Elle 29 Charleroi (ransart) Hainaut 6043",
    "addr:housenumber":"29",
    "addr:postcode":"6043",
    "addr:street":"Rue Eau;Elle",
    "iso:country":"BE",
    "sg:address":"Rue Eau Sur Elle 29",
    "sg:city":"Charleroi (ransart)",
    "sg:classifiers":[
        {
            "category":"Health Services",
            "subcategory":"Health Practitioner",
            "type":"Services"
        }
    ],
    "sg:phone":"+32 71 35 31 61",
    "sg:postcode":"6043",
    "sg:province":"Hainaut",
    "sg:tags":[
        "physiotherapist"
    ],
    "wof:name":"De Roy J",
    "wof:placetype":"venue"
},
  "geometry": {"coordinates":[4.4839549065,50.4479637146],"type":"Point"}
}