{
  "type": "Feature",
  "properties": {
    "addr:full":"Nieuwe Baan 90 Kruibeke (bazel) Oost-Vlaanderen 9150",
    "addr:housenumber":"90",
    "addr:postcode":"9150",
    "addr:street":"Nieuwe Baan",
    "iso:country":"BE",
    "sg:address":"Nieuwe Baan 90",
    "sg:city":"Kruibeke (bazel)",
    "sg:classifiers":[
        {
            "category":"Professional",
            "subcategory":"Engineering",
            "type":"Services"
        }
    ],
    "sg:phone":"+32 3 774 26 24",
    "sg:postcode":"9150",
    "sg:province":"Oost-Vlaanderen",
    "sg:tags":[
        "workshop"
    ],
    "wof:name":"Deprest Nv",
    "wof:placetype":"venue"
},
  "geometry": {"coordinates":[4.2884168625,51.1331825256],"type":"Point"}
}