{
  "type": "Feature",
  "properties": {
    "addr:full":"Rederskaai 9 Poort 13 Brussel Bruxelles-Capitale 1000",
    "addr:housenumber":"9;13",
    "addr:postcode":"1000",
    "addr:street":"Rederskaai;Poort",
    "iso:country":"BE",
    "sg:address":"Rederskaai 9 Poort 13",
    "sg:city":"Brussel",
    "sg:classifiers":[
        {
            "category":"Transit Center",
            "subcategory":"Passenger",
            "type":"Transportation"
        }
    ],
    "sg:phone":"+32 2 270 19 39",
    "sg:postcode":"1000",
    "sg:province":"Bruxelles-Capitale",
    "sg:tags":[
        "sand",
        "gravel"
    ],
    "wof:name":"Belgrasa Nv",
    "wof:placetype":"venue"
},
  "geometry": {"coordinates":[4.3440380096,50.855594635],"type":"Point"}
}