{
  "type": "Feature",
  "properties": {
    "iso:country":"BE",
    "sg:address":"Avenue Princesse Jos\u00e9phine-charlotte 22",
    "sg:city":"Waterloo",
    "sg:classifiers":[
        {
            "category":"Health Services",
            "subcategory":"Health Practitioner",
            "type":"Services"
        }
    ],
    "sg:phone":"+32 2 354 85 51",
    "sg:postcode":"1410",
    "sg:province":"Brabant Wallon",
    "sg:tags":[
        "physiotherapist"
    ],
    "wof:name":"Cr\u00e9mer A-f",
    "wof:placetype":"venue"
},
  "geometry": {"coordinates":[4.3956661224,50.7212905884],"type":"Point"}
}