{
  "type": "Feature",
  "properties": {
    "addr:full":"Jevoumont 30 Theux Li\u00e8ge 4910",
    "addr:housenumber":"30",
    "addr:postcode":"4910",
    "addr:street":"Jevoumont",
    "iso:country":"BE",
    "sg:address":"Jevoumont 30",
    "sg:city":"Theux",
    "sg:classifiers":[
        {
            "category":"Wholesale",
            "subcategory":"Wine & Distilled Alcoholic Beverages",
            "type":"Manufacturing & Wholesale Goods"
        }
    ],
    "sg:phone":"+32 87 53 01 53",
    "sg:postcode":"4910",
    "sg:province":"Li\u00e8ge",
    "sg:tags":[
        "whol",
        "-",
        "spirit",
        "mfg"
    ],
    "wof:name":"Domaine Luc Pirlet Sa",
    "wof:placetype":"venue"
},
  "geometry": {"coordinates":[5.8007202148,50.5204582214],"type":"Point"}
}