{
  "type": "Feature",
  "properties": {
    "iso:country":"BE",
    "sg:address":"90",
    "sg:city":"Meersstraat 9620 Zottegem",
    "sg:classifiers":[
        {
            "category":"Real Estate",
            "subcategory":"Surveying",
            "type":"Services"
        }
    ],
    "sg:phone":"+32 2 361 54 29",
    "sg:postcode":"90",
    "sg:tags":[
        "leather",
        "raw",
        "material",
        "-",
        "shoe"
    ],
    "wof:name":"Capretto Nv",
    "wof:placetype":"venue"
},
  "geometry": {"coordinates":[3.7998199463,50.872051239],"type":"Point"}
}