{
  "type": "Feature",
  "properties": {
    "addr:full":"Chauss\u00e9e De Roodebeek 206 Bruxelles (woluwe-saint-lambert) Bruxelles-Capitale 1200",
    "addr:housenumber":"206",
    "addr:postcode":"1200",
    "addr:street":"Chausse\u0301E De Roodebeek",
    "iso:country":"BE",
    "sg:address":"Chauss\u00e9e De Roodebeek 206",
    "sg:city":"Bruxelles (woluwe-saint-lambert)",
    "sg:classifiers":[
        {
            "category":"Arts & Performance",
            "subcategory":"Arts Center",
            "type":"Entertainment"
        }
    ],
    "sg:phone":"+32 2 770 11 91",
    "sg:postcode":"1200",
    "sg:province":"Bruxelles-Capitale",
    "sg:tags":[
        "slide"
    ],
    "wof:name":"Babylone",
    "wof:placetype":"venue"
},
  "geometry": {"coordinates":[4.4285187721,50.8485069275],"type":"Point"}
}