{
  "type": "Feature",
  "properties": {
    "addr:full":"Rue Du Progr\u00e8s 125 Bi\u00e8vre (graide) Namur 5555",
    "addr:housenumber":"125",
    "addr:postcode":"5555",
    "addr:street":"Rue Du Progre\u0300S",
    "iso:country":"BE",
    "sg:address":"Rue Du Progr\u00e8s 125",
    "sg:city":"Bi\u00e8vre (graide)",
    "sg:classifiers":[
        {
            "category":"Building & Trades",
            "subcategory":"Landscaping Services",
            "type":"Services"
        }
    ],
    "sg:phone":"+32 61 51 13 37",
    "sg:postcode":"5555",
    "sg:province":"Namur",
    "sg:tags":[
        "gardening",
        "garden",
        "maintenance"
    ],
    "wof:name":"Nollevaux Jp",
    "wof:placetype":"venue"
},
  "geometry": {"coordinates":[5.0579609871,49.9402275085],"type":"Point"}
}