{
  "type": "Feature",
  "properties": {
    "iso:country":"BE",
    "sg:address":"Oude Booischotsebaan 11b",
    "sg:city":"Bonheiden (rijmenam)",
    "sg:classifiers":[
        {
            "category":"Personal",
            "subcategory":"Beauty Salon",
            "type":"Services"
        }
    ],
    "sg:phone":"+32 15 52 05 90",
    "sg:postcode":"2820",
    "sg:province":"Antwerpen",
    "wof:name":"Van Camp G",
    "wof:placetype":"venue"
},
  "geometry": {"coordinates":[4.5930509567,51.0211219788],"type":"Point"}
}