{
  "type": "Feature",
  "properties": {
    "addr:full":"Rue Des Bovr\u00c9es 10 Chaumont-gistoux Brabant Wallon 1325",
    "addr:housenumber":"10",
    "addr:postcode":"1325",
    "addr:street":"Rue Des Bovre\u0301Es",
    "iso:country":"BE",
    "sg:address":"Rue Des Bovr\u00c9es 10",
    "sg:city":"Chaumont-gistoux",
    "sg:orig_category":"Boekhouders",
    "sg:phone":"+32 10 68 88 08",
    "sg:postcode":"1325",
    "sg:province":"Brabant Wallon",
    "wof:name":"Luc Lambricht",
    "wof:placetype":"venue"
},
  "geometry": {"coordinates":[4.7057480812,50.6835403442],"type":"Point"}
}