{
  "type": "Feature",
  "properties": {
    "iso:country":"BE",
    "sg:address":"Graaf Boudewijn Ix-laan 46",
    "sg:city":"Kortrijk",
    "sg:orig_category":"Installation de serres, double vitrage and fen\u00eatres",
    "sg:phone":"+32 56 21 43 32",
    "sg:postcode":"8500",
    "sg:province":"West-Vlaanderen",
    "wof:name":"Art Technics Goemaere",
    "wof:placetype":"venue"
},
  "geometry": {"coordinates":[3.2780880928,50.8238296509],"type":"Point"}
}