{
  "type": "Feature",
  "properties": {
    "addr:full":"Hans Memlinglaan 5 De Haan West-Vlaanderen 8420",
    "addr:housenumber":"5",
    "addr:postcode":"8420",
    "addr:street":"Hans Memlinglaan",
    "iso:country":"BE",
    "sg:address":"Hans Memlinglaan 5",
    "sg:city":"De Haan",
    "sg:orig_category":"M\u00e9decins and sp\u00e9cialistes",
    "sg:phone":"+32 59 23 47 67",
    "sg:postcode":"8420",
    "sg:province":"West-Vlaanderen",
    "wof:name":"Christophe Bertrem",
    "wof:placetype":"venue"
},
  "geometry": {"coordinates":[3.0322289467,51.2731323242],"type":"Point"}
}