{
  "type": "Feature",
  "properties": {
    "addr:full":"Boulevard D'ypres 13 Bruxelles Bruxelles-Capitale 1000",
    "addr:housenumber":"13",
    "addr:postcode":"1000",
    "addr:street":"Boulevard D'Ypres",
    "iso:country":"BE",
    "sg:address":"Boulevard D'ypres 13",
    "sg:city":"Bruxelles",
    "sg:classifiers":[
        {
            "category":"Professional",
            "subcategory":"Testing Lab",
            "type":"Services"
        }
    ],
    "sg:phone":"+32 2 217 96 76",
    "sg:postcode":"1000",
    "sg:province":"Bruxelles-Capitale",
    "sg:tags":[
        "chemist"
    ],
    "wof:name":"Niemegeers W",
    "wof:placetype":"venue"
},
  "geometry": {"coordinates":[4.3470201492,50.8561897278],"type":"Point"}
}