{
  "type": "Feature",
  "properties": {
    "addr:full":"Rue Du Ch\u00c2teau D'eau 54 Saint-georges-sur-meuse Li\u00e8ge 4470",
    "addr:housenumber":"54",
    "addr:postcode":"4470",
    "addr:street":"Rue Du Cha\u0302Teau D'Eau",
    "iso:country":"BE",
    "sg:address":"Rue Du Ch\u00c2teau D'eau 54",
    "sg:city":"Saint-georges-sur-meuse",
    "sg:orig_category":"M\u00e9decins and sp\u00e9cialistes",
    "sg:phone":"+32 4 259 71 52",
    "sg:postcode":"4470",
    "sg:province":"Li\u00e8ge",
    "wof:name":"Fran\u00c7oise Godfroid",
    "wof:placetype":"venue"
},
  "geometry": {"coordinates":[5.3436479568,50.5915260315],"type":"Point"}
}