{
  "type": "Feature",
  "properties": {
    "addr:full":"Avenue Pre-aily 10 Angleur Li\u00e8ge 4031",
    "addr:housenumber":"10",
    "addr:postcode":"4031",
    "addr:street":"Avenue Pre-Aily",
    "iso:country":"BE",
    "sg:address":"Avenue Pre-aily 10",
    "sg:city":"Angleur",
    "sg:classifiers":[
        {
            "category":"Health Services",
            "subcategory":"Medical Lab",
            "type":"Services"
        }
    ],
    "sg:phone":"+32 4 361 42 32",
    "sg:postcode":"4031",
    "sg:province":"Li\u00e8ge",
    "sg:tags":[
        "product",
        "diagnostic"
    ],
    "wof:name":"Zentech S.a.",
    "wof:placetype":"venue"
},
  "geometry": {"coordinates":[5.599583149,50.6115036011],"type":"Point"}
}