{
  "type": "Feature",
  "properties": {
    "addr:full":"Chauss\u00c9e D'ottenbourg 22 Wavre Brabant Wallon 1300",
    "addr:housenumber":"22;1300",
    "addr:street":"Chausse\u0301E D'Ottenbourg",
    "iso:country":"BE",
    "sg:address":"Chauss\u00c9e D'ottenbourg 22",
    "sg:city":"Wavre",
    "sg:orig_category":"Elektrische installaties voor woningen",
    "sg:phone":"+32 10 24 29 47",
    "sg:postcode":"1300",
    "sg:province":"Brabant Wallon",
    "wof:name":"Alain Kavari",
    "wof:placetype":"venue"
},
  "geometry": {"coordinates":[4.6155891418,50.7241859436],"type":"Point"}
}