{
  "type": "Feature",
  "properties": {
    "iso:country":"BE",
    "sg:address":"Dr\u00e8ve Du Moulin 42",
    "sg:city":"Waterloo",
    "sg:classifiers":[
        {
            "category":"Arena",
            "subcategory":"Sports Club",
            "type":"Entertainment"
        }
    ],
    "sg:phone":"+32 2 354 38 84",
    "sg:postcode":"1410",
    "sg:province":"Brabant Wallon",
    "sg:tags":[
        "martial art",
        "accessory"
    ],
    "wof:name":"Aikido Waterloo",
    "wof:placetype":"venue"
},
  "geometry": {"coordinates":[4.3902630806,50.7186203003],"type":"Point"}
}