{
  "type": "Feature",
  "properties": {
    "addr:full":"Lostraat 8 Lo-reninge West-Vlaanderen 8647",
    "addr:housenumber":"8",
    "addr:postcode":"8647",
    "addr:street":"Lostraat",
    "iso:country":"BE",
    "sg:address":"Lostraat 8",
    "sg:city":"Lo-reninge",
    "sg:classifiers":[
        {
            "category":"Retail",
            "subcategory":"Animal Services",
            "type":"Services"
        }
    ],
    "sg:phone":"+32 57 40 06 54",
    "sg:postcode":"8647",
    "sg:province":"West-Vlaanderen",
    "sg:tags":[
        "article",
        "veterinary",
        "drug",
        "care"
    ],
    "wof:name":"Dubavo Nv",
    "wof:placetype":"venue"
},
  "geometry": {"coordinates":[2.787446022,50.9484062195],"type":"Point"}
}