{
  "type": "Feature",
  "properties": {
    "iso:country":"BE",
    "sg:address":"Stationsstraat 33",
    "sg:city":"Kapellen",
    "sg:orig_category":"Dameskledingzaken",
    "sg:phone":"+32 3 664 03 77",
    "sg:postcode":"2950",
    "sg:province":"Antwerpen",
    "wof:name":"Pro Decor",
    "wof:placetype":"venue"
},
  "geometry": {"coordinates":[4.4316821098,51.3142242432],"type":"Point"}
}