{
  "type": "Feature",
  "properties": {
    "iso:country":"BE",
    "sg:address":"Place Albert I 12",
    "sg:city":"Charleroi",
    "sg:classifiers":[
        {
            "category":"Personal",
            "subcategory":"Shoe Repair & Shine",
            "type":"Services"
        }
    ],
    "sg:phone":"+32 71 32 52 49",
    "sg:postcode":"6000",
    "sg:province":"Hainaut",
    "sg:tags":[
        "shoemaker"
    ],
    "wof:name":"Dallas",
    "wof:placetype":"venue"
},
  "geometry": {"coordinates":[4.4434351921,50.41015625],"type":"Point"}
}