{
  "type": "Feature",
  "properties": {
    "iso:country":"BE",
    "sg:address":"Chauss\u00c9e De Mons 58",
    "sg:city":"Anderlues",
    "sg:orig_category":"V\u00e9t\u00e9rinaires",
    "sg:phone":"+32 71 54 09 03",
    "sg:postcode":"6150",
    "sg:province":"Hainaut",
    "wof:name":"M.-d. De Jamblinne De Meux",
    "wof:placetype":"venue"
},
  "geometry": {"coordinates":[4.2286968231,50.4077949524],"type":"Point"}
}