{
  "type": "Feature",
  "properties": {
    "iso:country":"BE",
    "sg:address":"Rue Du H\u00e9rou 72",
    "sg:city":"Houffalize (nadrin)",
    "sg:classifiers":[
        {
            "category":"Travel",
            "subcategory":"Hotels & Motels",
            "type":"Entertainment"
        }
    ],
    "sg:phone":"+32 84 44 46 73",
    "sg:postcode":"6660",
    "sg:province":"Luxembourg",
    "wof:name":"Cinq Ourthes (les)",
    "wof:placetype":"venue"
},
  "geometry": {"coordinates":[5.6617798805,50.1554222107],"type":"Point"}
}