{
  "type": "Feature",
  "properties": {
    "addr:full":"Sint-laureysplein 10 Hove Antwerpen 2540",
    "addr:housenumber":"10",
    "addr:postcode":"2540",
    "addr:street":"Sint-Laureysplein",
    "iso:country":"BE",
    "sg:address":"Sint-laureysplein 10",
    "sg:city":"Hove",
    "sg:orig_category":"Newspapers, magazines, periodicals - Distribution",
    "sg:phone":"+32 3 455 31 27",
    "sg:postcode":"2540",
    "sg:province":"Antwerpen",
    "wof:name":"Domino",
    "wof:placetype":"venue"
},
  "geometry": {"coordinates":[4.4722409248,51.1540184021],"type":"Point"}
}