{
  "type": "Feature",
  "properties": {
    "addr:full":"Boulevard Dolez 47 Mons Hainaut 7000",
    "addr:housenumber":"47",
    "addr:postcode":"7000",
    "addr:street":"Boulevard Dolez;Hainaut",
    "iso:country":"BE",
    "sg:address":"Boulevard Dolez 47",
    "sg:city":"Mons",
    "sg:orig_category":"Dansscholen",
    "sg:phone":"+32 65 33 60 56",
    "sg:postcode":"7000",
    "sg:province":"Hainaut",
    "wof:name":"Acad\u00c9mie De Danse",
    "wof:placetype":"venue"
},
  "geometry": {"coordinates":[3.9579679966,50.4507751465],"type":"Point"}
}