{
  "type": "Feature",
  "properties": {
    "iso:country":"BE",
    "sg:address":"Kattebroekstraat 207",
    "sg:city":"Dilbeek",
    "sg:orig_category":"Woningbouw",
    "sg:phone":"+32 2 466 73 63",
    "sg:postcode":"1700",
    "sg:province":"Vlaams-Brabant",
    "wof:name":"Renaat Wilikens",
    "wof:placetype":"venue"
},
  "geometry": {"coordinates":[4.2777729034,50.8579444885],"type":"Point"}
}