{
  "type": "Feature",
  "properties": {
    "addr:full":"Winnezelestraat 53 Poperinge West-Vlaanderen 8978",
    "addr:housenumber":"53",
    "addr:postcode":"8978",
    "addr:street":"Winnezelestraat",
    "iso:country":"BE",
    "sg:address":"Winnezelestraat 53",
    "sg:city":"Poperinge",
    "sg:orig_category":"Articles de jardin. Souvenirs and objets artisanaux. Fleurs and plantes",
    "sg:phone":"+32 57 38 88 38",
    "sg:postcode":"8978",
    "sg:province":"West-Vlaanderen",
    "wof:name":"Tuincentrum Watouplant",
    "wof:placetype":"venue"
},
  "geometry": {"coordinates":[2.6206049919,50.8592453003],"type":"Point"}
}