{
  "type": "Feature",
  "properties": {
    "iso:country":"BE",
    "sg:address":"Paalsteenstraat 28b",
    "sg:city":"Hasselt",
    "sg:classifiers":[
        {
            "category":"Autos & Motor Vehicles",
            "subcategory":"Boat Sales",
            "type":"Retail Goods"
        }
    ],
    "sg:phone":"+32 476 22 09 10",
    "sg:postcode":"3500",
    "sg:province":"Limburg",
    "sg:tags":[
        "balloon"
    ],
    "wof:name":"All Events",
    "wof:placetype":"venue"
},
  "geometry": {"coordinates":[5.3433208466,50.9479484558],"type":"Point"}
}