{
  "type": "Feature",
  "properties": {
    "iso:country":"BE",
    "sg:address":"Avenue A.j. Slegers 32 Box 7",
    "sg:city":"Bruxelles (woluwe-saint-lambert)",
    "sg:classifiers":[
        {
            "category":"Insurance",
            "subcategory":"Insurance Agent",
            "type":"Services"
        }
    ],
    "sg:phone":"+32 2 770 01 96",
    "sg:postcode":"1200",
    "sg:province":"Bruxelles-Capitale",
    "sg:tags":[
        "broker"
    ],
    "wof:name":"Muyldermans Roger Sa",
    "wof:placetype":"venue"
},
  "geometry": {"coordinates":[4.4307751656,50.8412895203],"type":"Point"}
}