{
  "type": "Feature",
  "properties": {
    "iso:country":"BE",
    "sg:address":"Chemin Priv\u00c9 1",
    "sg:city":"Floreffe",
    "sg:orig_category":"Biblioth\u00e8ques and archives publiques",
    "sg:phone":"+32 81 44 14 13",
    "sg:postcode":"5150",
    "sg:province":"Namur",
    "wof:name":"Biblioth\u00c8que Publique",
    "wof:placetype":"venue"
},
  "geometry": {"coordinates":[4.7332501411,50.4357414246],"type":"Point"}
}