{
  "type": "Feature",
  "properties": {
    "iso:country":"BE",
    "sg:address":"Hendrik Muyshondtstraat 14",
    "sg:city":"Bornem",
    "sg:orig_category":"Parfumeries. Instituts de beaut\u00e9",
    "sg:phone":"+32 3 889 66 59",
    "sg:postcode":"2880",
    "sg:province":"Antwerpen",
    "wof:name":"Instituut Sabine",
    "wof:placetype":"venue"
},
  "geometry": {"coordinates":[4.2974061966,51.1085357666],"type":"Point"}
}