{
  "type": "Feature",
  "properties": {
    "addr:full":"Oude Leeuwenrui 26 Antwerpen Antwerpen 2000",
    "addr:housenumber":"26",
    "addr:postcode":"2000",
    "addr:street":"Oude Leeuwenrui",
    "iso:country":"BE",
    "sg:address":"Oude Leeuwenrui 26",
    "sg:city":"Antwerpen",
    "sg:classifiers":[
        {
            "category":"Restaurant",
            "type":"Food & Drink"
        }
    ],
    "sg:phone":"+32 3 234 09 23",
    "sg:postcode":"2000",
    "sg:province":"Antwerpen",
    "wof:name":"Valencia",
    "wof:placetype":"venue"
},
  "geometry": {"coordinates":[4.4075341225,51.2267456055],"type":"Point"}
}