{
  "type": "Feature",
  "properties": {
    "iso:country":"BE",
    "sg:address":"Avenue De Cheremont 56",
    "sg:city":"Wavre",
    "sg:orig_category":"G\u00e9om\u00e8tres",
    "sg:phone":"+32 10 22 24 95",
    "sg:postcode":"1300",
    "sg:province":"Brabant Wallon",
    "wof:name":"E. Herry",
    "wof:placetype":"venue"
},
  "geometry": {"coordinates":[4.6243190765,50.7116889954],"type":"Point"}
}