{
  "type": "Feature",
  "properties": {
    "addr:full":"Chauss\u00c9e De Waterloo 1499 Ukkel Bruxelles-Capitale 1180",
    "addr:housenumber":"1499",
    "addr:postcode":"1180",
    "addr:street":"Chausse\u0301E De Waterloo",
    "iso:country":"BE",
    "sg:address":"Chauss\u00c9e De Waterloo 1499",
    "sg:city":"Ukkel",
    "sg:classifiers":[
        {
            "category":"Cafe",
            "type":"Food & Drink"
        }
    ],
    "sg:phone":"+32 2 375 42 67",
    "sg:postcode":"1180",
    "sg:province":"Bruxelles-Capitale",
    "sg:tags":[
        "caf\u00e9s"
    ],
    "wof:name":"Le Macao",
    "wof:placetype":"venue"
},
  "geometry": {"coordinates":[4.3795490265,50.7826271057],"type":"Point"}
}