{
  "type": "Feature",
  "properties": {
    "addr:full":"Blaesstraat 64 Brussel/bruxelles Bruxelles-Capitale 1000",
    "addr:housenumber":"64",
    "addr:postcode":"1000",
    "addr:street":"Blaesstraat;/",
    "iso:country":"BE",
    "sg:address":"Blaesstraat 64",
    "sg:city":"Brussel/bruxelles",
    "sg:orig_category":"Tweedehandsgoederen",
    "sg:phone":"+32 2 343 82 57",
    "sg:postcode":"1000",
    "sg:province":"Bruxelles-Capitale",
    "wof:name":"D. Dardenne",
    "wof:placetype":"venue"
},
  "geometry": {"coordinates":[4.3495140076,50.8395767212],"type":"Point"}
}