{
  "type": "Feature",
  "properties": {
    "addr:full":"Groenendaallaan 385 Antwerpen Antwerpen 2030",
    "addr:housenumber":"385",
    "addr:postcode":"2030",
    "addr:street":"Groenendaallaan",
    "iso:country":"BE",
    "sg:address":"Groenendaallaan 385",
    "sg:city":"Antwerpen",
    "sg:classifiers":[
        {
            "category":"Travel",
            "subcategory":"Travel Agent",
            "type":"Entertainment"
        }
    ],
    "sg:phone":"+32 3 541 18 57",
    "sg:postcode":"2030",
    "sg:province":"Antwerpen",
    "sg:tags":[
        "agency"
    ],
    "wof:name":"De Polder",
    "wof:placetype":"venue"
},
  "geometry": {"coordinates":[4.4223241806,51.2445373535],"type":"Point"}
}