{
  "type": "Feature",
  "properties": {
    "addr:full":"Rue Du Septi\u00e8me R. I. C. 309 Tintigny (bellefontaine) Luxembourg 6730",
    "addr:housenumber":"309",
    "addr:postcode":"6730",
    "addr:street":"Rue Du Septie\u0300Me R. I. C.",
    "iso:country":"BE",
    "sg:address":"Rue Du Septi\u00e8me R. I. C. 309",
    "sg:city":"Tintigny (bellefontaine)",
    "sg:classifiers":[
        {
            "category":"Building & Trades",
            "subcategory":"Pest Control",
            "type":"Services"
        }
    ],
    "sg:phone":"+32 63 44 44 29",
    "sg:postcode":"6730",
    "sg:province":"Luxembourg",
    "sg:tags":[
        "painting",
        "contractor"
    ],
    "wof:name":"Morel R",
    "wof:placetype":"venue"
},
  "geometry": {"coordinates":[5.4922180176,49.6715507507],"type":"Point"}
}