{
  "type": "Feature",
  "properties": {
    "iso:country":"BE",
    "sg:address":"Lindenstraat 19",
    "sg:city":"Oostkamp",
    "sg:orig_category":"Meubelzaken, woning- and keukeninrichting",
    "sg:phone":"+32 50 35 84 01",
    "sg:postcode":"8020",
    "sg:province":"West-Vlaanderen",
    "wof:name":"Huis Vierstraete",
    "wof:placetype":"venue"
},
  "geometry": {"coordinates":[3.2399849892,51.1778259277],"type":"Point"}
}