{
  "type": "Feature",
  "properties": {
    "iso:country":"BE",
    "sg:address":"Pontbeek 45 Building 320",
    "sg:city":"Zellik",
    "sg:classifiers":[
        {
            "category":"Banks & Credit Unions",
            "subcategory":"Investment Brokerage",
            "type":"Services"
        }
    ],
    "sg:phone":"+32 2 467 03 50",
    "sg:postcode":"1731",
    "sg:province":"Vlaams-Brabant",
    "sg:tags":[
        "measuring",
        "device",
        "analogue"
    ],
    "wof:name":"Cn Rood Nv",
    "wof:placetype":"venue"
},
  "geometry": {"coordinates":[4.2738099098,50.8845901489],"type":"Point"}
}