{
  "type": "Feature",
  "properties": {
    "addr:full":"Rue Des Pucelles 1 Perwez (thorembais-saint-trond) Brabant Wallon 1360",
    "addr:housenumber":"1",
    "addr:postcode":"1360",
    "addr:street":"Rue Des Pucelles;Wallon",
    "iso:country":"BE",
    "sg:address":"Rue Des Pucelles 1",
    "sg:city":"Perwez (thorembais-saint-trond)",
    "sg:classifiers":[
        {
            "category":"Health Services",
            "subcategory":"Nursing And Care Facility",
            "type":"Services"
        }
    ],
    "sg:phone":"+32 4 228 91 60",
    "sg:postcode":"1360",
    "sg:province":"Brabant Wallon",
    "sg:tags":[
        "home",
        "rest"
    ],
    "wof:name":"Residence Maghin-seniorcare",
    "wof:placetype":"venue"
},
  "geometry": {"coordinates":[4.783853054,50.638469696],"type":"Point"}
}