{
  "type": "Feature",
  "properties": {
    "addr:full":"Boulevard Des Combattants 46 Tournai Hainaut 7500",
    "addr:housenumber":"46",
    "addr:postcode":"7500",
    "addr:street":"Boulevard Des Combattants",
    "iso:country":"BE",
    "sg:address":"Boulevard Des Combattants 46",
    "sg:city":"Tournai",
    "sg:classifiers":[
        {
            "category":"Professional",
            "subcategory":"Lawyer & Legal Services",
            "type":"Services"
        }
    ],
    "sg:phone":"+32 69 21 36 42",
    "sg:postcode":"7500",
    "sg:province":"Hainaut",
    "wof:name":"Debetencourt Paul",
    "wof:placetype":"venue"
},
  "geometry": {"coordinates":[3.4022679329,50.60962677],"type":"Point"}
}