{
  "type": "Feature",
  "properties": {
    "iso:country":"BE",
    "sg:address":"Kraanlei 35",
    "sg:city":"Gent",
    "sg:orig_category":"Zalen voor culturele evenementen",
    "sg:phone":"+32 9 223 09 28",
    "sg:postcode":"9000",
    "sg:province":"Oost-Vlaanderen",
    "wof:name":"Galerie Minnepand",
    "wof:placetype":"venue"
},
  "geometry": {"coordinates":[3.722671032,51.0570487976],"type":"Point"}
}