{
  "type": "Feature",
  "properties": {
    "iso:country":"BE",
    "sg:address":"Route Nationale-4 44",
    "sg:city":"Nassogne",
    "sg:classifiers":[
        {
            "category":"Wholesale",
            "subcategory":"Farm Supplies",
            "type":"Manufacturing & Wholesale Goods"
        }
    ],
    "sg:phone":"+32 84 34 45 98",
    "sg:postcode":"6951",
    "sg:province":"Luxembourg",
    "sg:tags":[
        "machine",
        "agricoles",
        "mat\u00e9riel",
        "gr"
    ],
    "wof:name":"Herman Roose",
    "wof:placetype":"venue"
},
  "geometry": {"coordinates":[5.4151701927,50.1667518616],"type":"Point"}
}