{
  "type": "Feature",
  "properties": {
    "iso:country":"BE",
    "sg:address":"Kerkstraat 74",
    "sg:city":"Sint-genesius-rode",
    "sg:orig_category":"Instruments de musique",
    "sg:phone":"+32 2 381 25 81",
    "sg:postcode":"1640",
    "sg:province":"Vlaams-Brabant",
    "wof:name":"Si Bemol",
    "wof:placetype":"venue"
},
  "geometry": {"coordinates":[4.3509688377,50.7441139221],"type":"Point"}
}