{
  "type": "Feature",
  "properties": {
    "iso:country":"BE",
    "sg:address":"Binnenlaan 118",
    "sg:city":"Genk (waterschei)",
    "sg:classifiers":[
        {
            "category":"Juice Bar",
            "subcategory":"None",
            "type":"Food & Drink"
        }
    ],
    "sg:phone":"+32 89 38 15 45",
    "sg:postcode":"3600",
    "sg:province":"Limburg",
    "sg:tags":[
        "water",
        "soft"
    ],
    "wof:name":"Panitti P",
    "wof:placetype":"venue"
},
  "geometry": {"coordinates":[5.516477108,50.9995574951],"type":"Point"}
}