{
  "type": "Feature",
  "properties": {
    "addr:full":"Oost-beertegemstraat 10 Zingem Oost-Vlaanderen 9750",
    "addr:housenumber":"10",
    "addr:postcode":"9750",
    "addr:street":"Oost-Beertegemstraat;Oost-Vlaanderen",
    "iso:country":"BE",
    "sg:address":"Oost-beertegemstraat 10",
    "sg:city":"Zingem",
    "sg:orig_category":"Plomberie, chauffage and installations sanitaires",
    "sg:phone":"+32 9 384 38 19",
    "sg:postcode":"9750",
    "sg:province":"Oost-Vlaanderen",
    "wof:name":"Christian De Jonghe",
    "wof:placetype":"venue"
},
  "geometry": {"coordinates":[3.6055829525,50.9096488953],"type":"Point"}
}