{
  "type": "Feature",
  "properties": {
    "addr:full":"Hasseltweg 327 Genk Limburg 3600",
    "addr:housenumber":"327",
    "addr:postcode":"3600",
    "addr:street":"Hasseltweg",
    "iso:country":"BE",
    "sg:address":"Hasseltweg 327",
    "sg:city":"Genk",
    "sg:classifiers":[
        {
            "category":"Restaurant",
            "type":"Food & Drink"
        }
    ],
    "sg:phone":"+32 89 35 22 90",
    "sg:postcode":"3600",
    "sg:province":"Limburg",
    "wof:name":"Steakhouse Cara",
    "wof:placetype":"venue"
},
  "geometry": {"coordinates":[5.4345149994,50.9573249817],"type":"Point"}
}