{
  "type": "Feature",
  "properties": {
    "addr:full":"Route De L'etat 47 Lasne Brabant Wallon 1380",
    "addr:housenumber":"47",
    "addr:postcode":"1380",
    "addr:street":"Route De L'Etat",
    "iso:country":"BE",
    "sg:address":"Route De L'etat 47",
    "sg:city":"Lasne",
    "sg:orig_category":"Epiceries. Grands magasins",
    "sg:phone":"+32 2 633 11 90",
    "sg:postcode":"1380",
    "sg:province":"Brabant Wallon",
    "wof:name":"Valenduc",
    "wof:placetype":"venue"
},
  "geometry": {"coordinates":[4.4767360687,50.6790847778],"type":"Point"}
}