{
  "type": "Feature",
  "properties": {
    "iso:country":"BE",
    "sg:address":"Herentalse Steenweg 93",
    "sg:city":"Grobbendonk",
    "sg:orig_category":"Entretien and r\u00e9parations de voitures. V\u00e9hicules automobiles",
    "sg:phone":"+32 14 21 21 51",
    "sg:postcode":"2280",
    "sg:province":"Antwerpen",
    "wof:name":"T.a.c.",
    "wof:placetype":"venue"
},
  "geometry": {"coordinates":[4.7669401169,51.1770210266],"type":"Point"}
}