{
  "type": "Feature",
  "properties": {
    "iso:country":"BE",
    "sg:address":"Markt 28 Box 1",
    "sg:city":"Peer",
    "sg:classifiers":[
        {
            "category":"Insurance",
            "subcategory":"Insurance Agent",
            "type":"Services"
        }
    ],
    "sg:phone":"+32 11 61 11 90",
    "sg:postcode":"3990",
    "sg:province":"Limburg",
    "sg:tags":[
        "broker"
    ],
    "wof:name":"Group Assurlim Bvba",
    "wof:placetype":"venue"
},
  "geometry": {"coordinates":[5.4544939995,51.1316604614],"type":"Point"}
}