{
  "type": "Feature",
  "properties": {
    "iso:country":"BE",
    "sg:address":"Kapelstraat 4",
    "sg:city":"Meeuwen-gruitrode",
    "sg:orig_category":"Sportclubs",
    "sg:phone":"+32 11 79 17 27",
    "sg:postcode":"3670",
    "sg:province":"Limburg",
    "wof:name":"B.c. Meeuwen-gruitrode",
    "wof:placetype":"venue"
},
  "geometry": {"coordinates":[5.5076532364,51.0965652466],"type":"Point"}
}