{
  "type": "Feature",
  "properties": {
    "addr:full":"Hillesteenweg 63 Wingene West-Vlaanderen 8750",
    "addr:housenumber":"63",
    "addr:postcode":"8750",
    "addr:street":"Hillesteenweg",
    "iso:country":"BE",
    "sg:address":"Hillesteenweg 63",
    "sg:city":"Wingene",
    "sg:classifiers":[
        {
            "category":"Home & Garden",
            "subcategory":"Garden Supply",
            "type":"Retail Goods"
        }
    ],
    "sg:phone":"+32 51 65 54 79",
    "sg:postcode":"8750",
    "sg:province":"West-Vlaanderen",
    "sg:tags":[
        "machine",
        "agricultural",
        "-"
    ],
    "wof:name":"Quintijn W",
    "wof:placetype":"venue"
},
  "geometry": {"coordinates":[3.2545719147,51.0540504456],"type":"Point"}
}