{
  "type": "Feature",
  "properties": {
    "addr:full":"Route D'ottignies 2 Lasne (lasne-chapelle-saint-lambert) Brabant Wallon 1380",
    "addr:housenumber":"2",
    "addr:postcode":"1380",
    "addr:street":"Route D'Ottignies;Wallon",
    "iso:country":"BE",
    "sg:address":"Route D'ottignies 2",
    "sg:city":"Lasne (lasne-chapelle-saint-lambert)",
    "sg:classifiers":[
        {
            "category":"Building & Trades",
            "subcategory":"Construction",
            "type":"Services"
        }
    ],
    "sg:phone":"+32 2 653 30 05",
    "sg:postcode":"1380",
    "sg:province":"Brabant Wallon",
    "sg:tags":[
        "installation",
        "-",
        "central",
        "heating"
    ],
    "wof:name":"De Paoli-saint Michel",
    "wof:placetype":"venue"
},
  "geometry": {"coordinates":[4.4995779991,50.6984176636],"type":"Point"}
}