{
  "type": "Feature",
  "properties": {
    "iso:country":"BE",
    "sg:address":"Baron Albert Dhuartln 28",
    "sg:city":"St-pieters-woluwe",
    "sg:classifiers":[
        {
            "category":"Autos & Motor Vehicles",
            "subcategory":"Automobile Sales",
            "type":"Retail Goods"
        }
    ],
    "sg:phone":"+32 2 779 29 80",
    "sg:postcode":"1150",
    "sg:province":"Bruxelles-Capitale",
    "sg:tags":[
        "equipment",
        "motor-cars",
        "transport"
    ],
    "wof:name":"Stockel",
    "wof:placetype":"venue"
},
  "geometry": {"coordinates":[4.4663338661,50.8389778137],"type":"Point"}
}