{
  "type": "Feature",
  "properties": {
    "iso:country":"BE",
    "sg:address":"Meerstraat 36",
    "sg:city":"Londerzeel",
    "sg:orig_category":"Diensten voor huisdieren",
    "sg:phone":"+32 52 30 60 56",
    "sg:postcode":"1840",
    "sg:province":"Vlaams-Brabant",
    "wof:name":"Pitou",
    "wof:placetype":"venue"
},
  "geometry": {"coordinates":[4.3040008545,51.0054130554],"type":"Point"}
}