{
  "type": "Feature",
  "properties": {
    "addr:full":"Rue Alfred Defuisseaux 5 Frameries Hainaut 7080",
    "addr:housenumber":"5",
    "addr:postcode":"7080",
    "addr:street":"Rue Alfred Defuisseaux",
    "iso:country":"BE",
    "sg:address":"Rue Alfred Defuisseaux 5",
    "sg:city":"Frameries",
    "sg:classifiers":[
        {
            "category":"Professional",
            "subcategory":"Management & Consulting",
            "type":"Services"
        }
    ],
    "sg:phone":"+32 65 67 37 69",
    "sg:postcode":"7080",
    "sg:province":"Hainaut",
    "sg:tags":[
        "consultant",
        "-",
        "legislation",
        "social"
    ],
    "wof:name":"Famille Secr\u00e9tariat",
    "wof:placetype":"venue"
},
  "geometry": {"coordinates":[3.896228075,50.4061851501],"type":"Point"}
}