{
  "type": "Feature",
  "properties": {
    "iso:country":"BE",
    "sg:address":"Parkstraat 16",
    "sg:city":"Sint-niklaas",
    "sg:orig_category":"Brood, gebak and snoepgoed",
    "sg:phone":"+32 3 776 22 48",
    "sg:postcode":"9100",
    "sg:province":"Oost-Vlaanderen",
    "wof:name":"De Croissanterie",
    "wof:placetype":"venue"
},
  "geometry": {"coordinates":[4.1395368576,51.1651000977],"type":"Point"}
}