{
  "type": "Feature",
  "properties": {
    "addr:full":"Vogelzang 103 Sint-pieters-woluwe Bruxelles-Capitale 1150",
    "addr:housenumber":"103",
    "addr:postcode":"1150",
    "addr:street":"Vogelzang",
    "iso:country":"BE",
    "sg:address":"Vogelzang 103",
    "sg:city":"Sint-pieters-woluwe",
    "sg:orig_category":"Alternatieve geneeskunde Artsen and specialisten",
    "sg:phone":"+32 2 660 30 72",
    "sg:postcode":"1150",
    "sg:province":"Bruxelles-Capitale",
    "wof:name":"Dokter Raedemaeker Marc-andr\u00c9",
    "wof:placetype":"venue"
},
  "geometry": {"coordinates":[4.412735939,50.8234062195],"type":"Point"}
}