{
  "type": "Feature",
  "properties": {
    "iso:country":"BE",
    "sg:address":"Wijngaardstraat 19",
    "sg:city":"Kortrijk",
    "sg:classifiers":[
        {
            "category":"Personal",
            "subcategory":"Beauty Salon",
            "type":"Services"
        }
    ],
    "sg:phone":"+32 56 20 48 22",
    "sg:postcode":"8500",
    "sg:province":"West-Vlaanderen",
    "sg:tags":[
        "lady",
        "-",
        "hairdressing"
    ],
    "wof:name":"Haute Coiffure Des Anges",
    "wof:placetype":"venue"
},
  "geometry": {"coordinates":[3.2695119381,50.8260765076],"type":"Point"}
}