{
  "type": "Feature",
  "properties": {
    "iso:country":"BE",
    "sg:address":"Ind. Park Brechtsebaan 18 /b",
    "sg:city":"Schoten",
    "sg:classifiers":[
        {
            "category":"Manufacturing",
            "subcategory":"Chemicals & Compounds",
            "type":"Manufacturing & Wholesale Goods"
        }
    ],
    "sg:phone":"+32 3 658 57 07",
    "sg:postcode":"2900",
    "sg:province":"Antwerpen",
    "sg:tags":[
        "pharmaceutical",
        "chemistry"
    ],
    "wof:name":"Fagan Bvba",
    "wof:placetype":"venue"
},
  "geometry": {"coordinates":[4.5107097626,51.2652397156],"type":"Point"}
}