{
  "type": "Feature",
  "properties": {
    "addr:full":"Frans Van Cauwelaertlaan 161 Sint-niklaas Oost-Vlaanderen 9100",
    "addr:housenumber":"161",
    "addr:postcode":"9100",
    "addr:street":"Frans Van Cauwelaertlaan",
    "iso:country":"BE",
    "sg:address":"Frans Van Cauwelaertlaan 161",
    "sg:city":"Sint-niklaas",
    "sg:classifiers":[
        {
            "category":"Shopping",
            "subcategory":"Clothing, Apparel, & Fashions",
            "type":"Retail Goods"
        }
    ],
    "sg:phone":"+32 3 780 95 50",
    "sg:postcode":"9100",
    "sg:province":"Oost-Vlaanderen",
    "sg:tags":[
        "supply",
        "material",
        "-",
        "access",
        "ready-made",
        "clothing"
    ],
    "wof:name":"Textra Nv",
    "wof:placetype":"venue"
},
  "geometry": {"coordinates":[4.137556076,51.1813926697],"type":"Point"}
}