{
  "type": "Feature",
  "properties": {
    "addr:full":"Holstraat 68-5 Waregem West-Vlaanderen 8790",
    "addr:housenumber":"68-5",
    "addr:postcode":"8790",
    "addr:street":"Holstraat",
    "iso:country":"BE",
    "sg:address":"Holstraat 68-5",
    "sg:city":"Waregem",
    "sg:classifiers":[
        {
            "category":"Health Services",
            "subcategory":"Doctor",
            "type":"Services"
        }
    ],
    "sg:phone":"+32 56 61 72 84",
    "sg:postcode":"8790",
    "sg:province":"West-Vlaanderen",
    "sg:tags":[
        "psychotherapist",
        "psychoanalyst"
    ],
    "wof:name":"Barbe I",
    "wof:placetype":"venue"
},
  "geometry": {"coordinates":[3.4377920628,50.8836288452],"type":"Point"}
}