{
  "type": "Feature",
  "properties": {
    "addr:full":"Rue Du Doyenn\u00e9 98 Bruxelles (uccle) Bruxelles-Capitale 1180",
    "addr:housenumber":"98",
    "addr:postcode":"1180",
    "addr:street":"Rue Du Doyenne\u0301",
    "iso:country":"BE",
    "sg:address":"Rue Du Doyenn\u00e9 98",
    "sg:city":"Bruxelles (uccle)",
    "sg:classifiers":[
        {
            "category":"Real Estate",
            "subcategory":"Architect",
            "type":"Services"
        }
    ],
    "sg:phone":"+32 2 537 01 40",
    "sg:postcode":"1180",
    "sg:province":"Bruxelles-Capitale",
    "wof:name":"Bourgois C",
    "wof:placetype":"venue"
},
  "geometry": {"coordinates":[4.3398652077,50.8040390015],"type":"Point"}
}