{
  "type": "Feature",
  "properties": {
    "addr:full":"Rue Mar\u00c9chal Foch 9 Dour Hainaut 7370",
    "addr:housenumber":"9",
    "addr:postcode":"7370",
    "addr:street":"Rue Mare\u0301Chal Foch;Hainaut",
    "iso:country":"BE",
    "sg:address":"Rue Mar\u00c9chal Foch 9",
    "sg:city":"Dour",
    "sg:orig_category":"Accessoires vestimentaires. Centres de relaxation and bien-\u00eatre. Parfumeries",
    "sg:phone":"+32 65 63 18 16",
    "sg:postcode":"7370",
    "sg:province":"Hainaut",
    "wof:name":"Distri. Coif.",
    "wof:placetype":"venue"
},
  "geometry": {"coordinates":[3.7829771042,50.3998031616],"type":"Point"}
}