{
  "type": "Feature",
  "properties": {
    "addr:full":"Varenbergstraat 42 Dendermonde (oudegem) Oost-Vlaanderen 9200",
    "addr:housenumber":"42",
    "addr:postcode":"9200",
    "addr:street":"Varenbergstraat",
    "iso:country":"BE",
    "sg:address":"Varenbergstraat 42",
    "sg:city":"Dendermonde (oudegem)",
    "sg:classifiers":[
        {
            "category":"Professional",
            "subcategory":"Accounting & Tax Preparation",
            "type":"Services"
        }
    ],
    "sg:phone":"+32 52 21 33 72",
    "sg:postcode":"9200",
    "sg:province":"Oost-Vlaanderen",
    "sg:tags":[
        "accountant"
    ],
    "wof:name":"Van Herreweghe W",
    "wof:placetype":"venue"
},
  "geometry": {"coordinates":[4.0983099937,51.0315208435],"type":"Point"}
}