{
  "type": "Feature",
  "properties": {
    "iso:country":"BE",
    "sg:address":"Rue Des Bl\u00e9s 1",
    "sg:city":"Mettet (graux)",
    "sg:classifiers":[
        {
            "category":"Health Services",
            "subcategory":"Nursing And Care Facility",
            "type":"Services"
        }
    ],
    "sg:phone":"+32 71 79 81 82",
    "sg:postcode":"5640",
    "sg:province":"Namur",
    "sg:tags":[
        "home"
    ],
    "wof:name":"Barbier J",
    "wof:placetype":"venue"
},
  "geometry": {"coordinates":[4.719974041,50.3249931335],"type":"Point"}
}