{
  "type": "Feature",
  "properties": {
    "addr:full":"Rue Pol Jaspart 4a Wanze Li\u00e8ge 4520",
    "addr:housenumber":"4a",
    "addr:postcode":"4520",
    "addr:street":"Rue Pol Jaspart",
    "iso:country":"BE",
    "sg:address":"Rue Pol Jaspart 4a",
    "sg:city":"Wanze",
    "sg:classifiers":[
        {
            "category":"Building & Trades",
            "subcategory":"Pest Control",
            "type":"Services"
        }
    ],
    "sg:phone":"+32 85 21 57 17",
    "sg:postcode":"4520",
    "sg:province":"Li\u00e8ge",
    "sg:tags":[
        "painting",
        "contractor"
    ],
    "wof:name":"Bodson F",
    "wof:placetype":"venue"
},
  "geometry": {"coordinates":[5.2143068314,50.5353622437],"type":"Point"}
}