{
  "type": "Feature",
  "properties": {
    "addr:full":"Avenue G\u00c9n\u00c9ral Lartigue 66 Sint-lambrechts-woluwe/woluwe-saint-lambert Bruxelles-Capitale 1200",
    "addr:housenumber":"66",
    "addr:postcode":"1200",
    "addr:street":"Avenue Ge\u0301Ne\u0301Ral Lartigue",
    "iso:country":"BE",
    "sg:address":"Avenue G\u00c9n\u00c9ral Lartigue 66",
    "sg:city":"Sint-lambrechts-woluwe/woluwe-saint-lambert",
    "sg:orig_category":"M\u00e9decins and sp\u00e9cialistes",
    "sg:phone":"+32 2 736 74 01",
    "sg:postcode":"1200",
    "sg:province":"Bruxelles-Capitale",
    "wof:name":"E. Ureel",
    "wof:placetype":"venue"
},
  "geometry": {"coordinates":[4.4077091217,50.846157074],"type":"Point"}
}