{
  "type": "Feature",
  "properties": {
    "addr:full":"Chauss\u00c9e De Mons 368 Anderlecht Bruxelles-Capitale 1070",
    "addr:housenumber":"368",
    "addr:postcode":"1070",
    "addr:street":"Chausse\u0301E De Mons",
    "iso:country":"BE",
    "sg:address":"Chauss\u00c9e De Mons 368",
    "sg:city":"Anderlecht",
    "sg:orig_category":"Travaux de pl\u00e2trage",
    "sg:phone":"+32 2 521 80 74",
    "sg:postcode":"1070",
    "sg:province":"Bruxelles-Capitale",
    "wof:name":"Manuel Fonseca Marques",
    "wof:placetype":"venue"
},
  "geometry": {"coordinates":[4.3198161125,50.837688446],"type":"Point"}
}