{
  "type": "Feature",
  "properties": {
    "iso:country":"BE",
    "sg:address":"Rue De La Westr\u00e9e 8",
    "sg:city":"Oreye",
    "sg:classifiers":[
        {
            "category":"Health Services",
            "subcategory":"Health Practitioner",
            "type":"Services"
        }
    ],
    "sg:phone":"+32 19 67 79 89",
    "sg:postcode":"4360",
    "sg:province":"Li\u00e8ge",
    "sg:tags":[
        "physiotherapist"
    ],
    "wof:name":"Garin Martine",
    "wof:placetype":"venue"
},
  "geometry": {"coordinates":[5.3534808159,50.7282485962],"type":"Point"}
}