{
  "type": "Feature",
  "properties": {
    "addr:full":"Lepelstraat 23 Staden (oostnieuwkerke) West-Vlaanderen 8840",
    "addr:housenumber":"23",
    "addr:postcode":"8840",
    "addr:street":"Lepelstraat",
    "iso:country":"BE",
    "sg:address":"Lepelstraat 23",
    "sg:city":"Staden (oostnieuwkerke)",
    "sg:classifiers":[
        {
            "category":"Building & Trades",
            "subcategory":"Plumbing",
            "type":"Services"
        }
    ],
    "sg:phone":"+32 51 20 58 03",
    "sg:postcode":"8840",
    "sg:province":"West-Vlaanderen",
    "sg:tags":[
        "contractor"
    ],
    "wof:name":"Depoortere G",
    "wof:placetype":"venue"
},
  "geometry": {"coordinates":[3.0574800968,50.9411354065],"type":"Point"}
}