{
  "type": "Feature",
  "properties": {
    "iso:country":"BE",
    "sg:address":"Rue De La Tannerie 16",
    "sg:city":"Chi\u00e8vres (tongre-notre-dame)",
    "sg:classifiers":[
        {
            "category":"Professional",
            "subcategory":"Art Services",
            "type":"Services"
        }
    ],
    "sg:phone":"+32 68 57 02 13",
    "sg:postcode":"7951",
    "sg:province":"Hainaut",
    "sg:tags":[
        "graphic",
        "designer"
    ],
    "wof:name":"Iguane Cr\u00e9ation",
    "wof:placetype":"venue"
},
  "geometry": {"coordinates":[3.7782359123,50.583896637],"type":"Point"}
}