{
  "type": "Feature",
  "properties": {
    "iso:country":"BE",
    "sg:address":"Avenue Olivier 8",
    "sg:city":"Bastogne",
    "sg:orig_category":"Agences de marketing",
    "sg:phone":"+32 61 21 50 90",
    "sg:postcode":"6600",
    "sg:province":"Luxembourg",
    "wof:name":"Fairon",
    "wof:placetype":"venue"
},
  "geometry": {"coordinates":[5.7105298042,50.0039901733],"type":"Point"}
}