{
  "type": "Feature",
  "properties": {
    "addr:full":"Wijnendalestraat 35 Torhout West-Vlaanderen 8820",
    "addr:housenumber":"35",
    "addr:postcode":"8820",
    "addr:street":"Wijnendalestraat",
    "iso:country":"BE",
    "sg:address":"Wijnendalestraat 35",
    "sg:city":"Torhout",
    "sg:orig_category":"Gespecialiseerde residenti\u00eble bouw",
    "sg:phone":"+32 50 21 18 80",
    "sg:postcode":"8820",
    "sg:province":"West-Vlaanderen",
    "wof:name":"Roger Crombez",
    "wof:placetype":"venue"
},
  "geometry": {"coordinates":[3.0704669952,51.09375],"type":"Point"}
}