{
  "type": "Feature",
  "properties": {
    "addr:full":"Technologielaan 3 Leuven (heverlee) Vlaams-Brabant 3001",
    "addr:housenumber":"3",
    "addr:postcode":"3001",
    "addr:street":"Technologielaan",
    "iso:country":"BE",
    "sg:address":"Technologielaan 3",
    "sg:city":"Leuven (heverlee)",
    "sg:classifiers":[
        {
            "category":"Professional",
            "subcategory":"Computer Services",
            "type":"Services"
        }
    ],
    "sg:phone":"+32 16 40 27 47",
    "sg:postcode":"3001",
    "sg:province":"Vlaams-Brabant",
    "sg:tags":[
        "-",
        "processing",
        "data",
        "software"
    ],
    "wof:name":"Tesis Software",
    "wof:placetype":"venue"
},
  "geometry": {"coordinates":[4.734609127,50.8507995605],"type":"Point"}
}