{
  "type": "Feature",
  "properties": {
    "addr:full":"Chauss\u00c9e De Stockel 294 Bruxelles-woluwe-saint-lambert Bruxelles-Capitale 1200",
    "addr:housenumber":"294",
    "addr:postcode":"1200",
    "addr:street":"Chausse\u0301E De Stockel",
    "iso:country":"BE",
    "sg:address":"Chauss\u00c9e De Stockel 294",
    "sg:city":"Bruxelles-woluwe-saint-lambert",
    "sg:orig_category":"Fleurs and plantes",
    "sg:phone":"+32 2 770 03 53",
    "sg:postcode":"1200",
    "sg:province":"Bruxelles-Capitale",
    "wof:name":"Le Chalet Fleuri",
    "wof:placetype":"venue"
},
  "geometry": {"coordinates":[4.450512886,50.8416481018],"type":"Point"}
}