{
  "type": "Feature",
  "properties": {
    "addr:full":"Beerststraat 34 Diksmuide West-Vlaanderen 8600",
    "addr:housenumber":"34",
    "addr:postcode":"8600",
    "addr:street":"Beerststraat",
    "iso:country":"BE",
    "sg:address":"Beerststraat 34",
    "sg:city":"Diksmuide",
    "sg:orig_category":"M\u00e9decins and sp\u00e9cialistes",
    "sg:phone":"+32 51 50 11 13",
    "sg:postcode":"8600",
    "sg:province":"West-Vlaanderen",
    "wof:name":"Annemie Boussauw",
    "wof:placetype":"venue"
},
  "geometry": {"coordinates":[2.9130370617,51.0488357544],"type":"Point"}
}