{
  "type": "Feature",
  "properties": {
    "addr:full":"Bondgenotenlaan 81 Leuven Vlaams-Brabant 3000",
    "addr:housenumber":"81",
    "addr:postcode":"3000",
    "addr:street":"Bondgenotenlaan",
    "iso:country":"BE",
    "sg:address":"Bondgenotenlaan 81",
    "sg:city":"Leuven",
    "sg:orig_category":"Bagage and lederwaren",
    "sg:phone":"+32 16 22 50 32",
    "sg:postcode":"3000",
    "sg:province":"Vlaams-Brabant",
    "wof:name":"Huis Delsart",
    "wof:placetype":"venue"
},
  "geometry": {"coordinates":[4.7082209587,50.8802642822],"type":"Point"}
}