{
  "type": "Feature",
  "properties": {
    "addr:full":"Quai Des Charbonnages 30-34 Bruxelles (molenbeek-saint-jean) Bruxelles-Capitale 1080",
    "addr:housenumber":"30-34",
    "addr:postcode":"1080",
    "addr:street":"Quai Des Charbonnages",
    "iso:country":"BE",
    "sg:address":"Quai Des Charbonnages 30-34",
    "sg:city":"Bruxelles (molenbeek-saint-jean)",
    "sg:classifiers":[
        {
            "category":"Museum",
            "type":"Entertainment"
        }
    ],
    "sg:phone":"+32 2 411 36 19",
    "sg:postcode":"1080",
    "sg:province":"Bruxelles-Capitale",
    "wof:name":"Matrix Art Project Brussels",
    "wof:placetype":"venue"
},
  "geometry": {"coordinates":[4.3420372009,50.8548240662],"type":"Point"}
}