{
  "type": "Feature",
  "properties": {
    "addr:full":"Kortrijksebaan 139 Holsbeek Vlaams-Brabant 3220",
    "addr:housenumber":"139",
    "addr:postcode":"3220",
    "addr:street":"Kortrijksebaan",
    "iso:country":"BE",
    "sg:address":"Kortrijksebaan 139",
    "sg:city":"Holsbeek",
    "sg:classifiers":[
        {
            "category":"Food & Beverages",
            "subcategory":"Specialty",
            "type":"Retail Goods"
        }
    ],
    "sg:phone":"+32 16 62 38 57",
    "sg:postcode":"3220",
    "sg:province":"Vlaams-Brabant",
    "sg:tags":[
        "health",
        "dietary",
        "-",
        "biological"
    ],
    "wof:name":"Natuurwinkel Marie",
    "wof:placetype":"venue"
},
  "geometry": {"coordinates":[4.772480011,50.9209098816],"type":"Point"}
}