{
  "type": "Feature",
  "properties": {
    "iso:country":"BE",
    "sg:address":"Spoorstraat 21",
    "sg:city":"Diepenbeek",
    "sg:classifiers":[
        {
            "category":"Health Services",
            "subcategory":"Health Practitioner",
            "type":"Services"
        }
    ],
    "sg:phone":"+32 11 32 32 69",
    "sg:postcode":"3590",
    "sg:province":"Limburg",
    "sg:tags":[
        "physiotherapist"
    ],
    "wof:name":"Debrabandere Adelson",
    "wof:placetype":"venue"
},
  "geometry": {"coordinates":[5.4169559479,50.9106941223],"type":"Point"}
}