{
  "type": "Feature",
  "properties": {
    "iso:country":"BE",
    "sg:address":"Place Des D\u00c9port\u00c9s 3",
    "sg:city":"Ottignies-louvain-la-neuve",
    "sg:orig_category":"Epiceries",
    "sg:phone":"+32 10 40 26 87",
    "sg:postcode":"1340",
    "sg:province":"Brabant Wallon",
    "wof:name":"Maison Led\u00c9 Panneur",
    "wof:placetype":"venue"
},
  "geometry": {"coordinates":[4.5712199211,50.6668395996],"type":"Point"}
}