{
  "type": "Feature",
  "properties": {
    "addr:full":"Oostkerkestraat 42 Knokke-heist (westkapelle) West-Vlaanderen 8300",
    "addr:housenumber":"42",
    "addr:postcode":"8300",
    "addr:street":"Oostkerkestraat",
    "iso:country":"BE",
    "sg:address":"Oostkerkestraat 42",
    "sg:city":"Knokke-heist (westkapelle)",
    "sg:classifiers":[
        {
            "category":"Wholesale",
            "subcategory":"Wine & Distilled Alcoholic Beverages",
            "type":"Manufacturing & Wholesale Goods"
        }
    ],
    "sg:phone":"+32 475 48 63 80",
    "sg:postcode":"8300",
    "sg:province":"West-Vlaanderen",
    "sg:tags":[
        "whol",
        "-",
        "spirit",
        "mfg"
    ],
    "wof:name":"Depauw (wijnen)",
    "wof:placetype":"venue"
},
  "geometry": {"coordinates":[3.287694931,51.3467254639],"type":"Point"}
}