{
  "type": "Feature",
  "properties": {
    "iso:country":"BE",
    "sg:address":"Rue De Cond\u00e9 96",
    "sg:city":"Bernissart (blaton)",
    "sg:classifiers":[
        {
            "category":"Professional",
            "subcategory":"Computer Services",
            "type":"Services"
        }
    ],
    "sg:phone":"+32 69 58 08 78",
    "sg:postcode":"7321",
    "sg:province":"Hainaut",
    "sg:tags":[
        "-",
        "processing",
        "data"
    ],
    "wof:name":"Five Stars Computers",
    "wof:placetype":"venue"
},
  "geometry": {"coordinates":[3.6611618996,50.5015869141],"type":"Point"}
}