{
  "type": "Feature",
  "properties": {
    "addr:full":"Rue Des Bataves 69 Bruxelles (etterbeek) Bruxelles-Capitale 1040",
    "addr:housenumber":"69",
    "addr:postcode":"1040",
    "addr:street":"Rue Des Bataves",
    "iso:country":"BE",
    "sg:address":"Rue Des Bataves 69",
    "sg:city":"Bruxelles (etterbeek)",
    "sg:classifiers":[
        {
            "category":"Professional",
            "subcategory":"Management & Consulting",
            "type":"Services"
        }
    ],
    "sg:phone":"+32 2 732 00 13",
    "sg:postcode":"1040",
    "sg:province":"Bruxelles-Capitale",
    "sg:tags":[
        "-",
        "processing",
        "data",
        "consultant"
    ],
    "wof:name":"Leaf (the)",
    "wof:placetype":"venue"
},
  "geometry": {"coordinates":[4.4043750763,50.8376693726],"type":"Point"}
}