{
  "type": "Feature",
  "properties": {
    "addr:full":"Rue L\u00e9on Fran\u00e7ois 57 Profondeville (bois-de-villers) Namur 5170",
    "addr:housenumber":"57",
    "addr:postcode":"5170",
    "addr:street":"Rue Le\u0301On Franc\u0327Ois",
    "iso:country":"BE",
    "sg:address":"Rue L\u00e9on Fran\u00e7ois 57",
    "sg:city":"Profondeville (bois-de-villers)",
    "sg:classifiers":[
        {
            "category":"Professional",
            "subcategory":"Accounting & Tax Preparation",
            "type":"Services"
        }
    ],
    "sg:phone":"+32 81 43 43 33",
    "sg:postcode":"5170",
    "sg:province":"Namur",
    "sg:tags":[
        "bookkeeper"
    ],
    "wof:name":"De Vreese J-p",
    "wof:placetype":"venue"
},
  "geometry": {"coordinates":[4.8343019485,50.401927948],"type":"Point"}
}