{
  "type": "Feature",
  "properties": {
    "addr:full":"Carrefour De L'europe 3 Brussel/bruxelles Bruxelles-Capitale 1000",
    "addr:housenumber":"3",
    "addr:postcode":"1000",
    "addr:street":"Carrefour De L'Europe;/",
    "iso:country":"BE",
    "sg:address":"Carrefour De L'europe 3",
    "sg:city":"Brussel/bruxelles",
    "sg:orig_category":"H\u00f4tels. Restaurants",
    "sg:phone":"+32 2 548 42 11",
    "sg:postcode":"1000",
    "sg:province":"Bruxelles-Capitale",
    "wof:name":"Le Meridien Bruxelles",
    "wof:placetype":"venue"
},
  "geometry": {"coordinates":[4.356033802,50.845867157],"type":"Point"}
}