{
  "type": "Feature",
  "properties": {
    "iso:country":"BE",
    "sg:address":"Rue C\u00e9sar Franck 53",
    "sg:city":"Bruxelles (ixelles)",
    "sg:orig_category":"Non-Classified Establishments",
    "sg:phone":"+32 2 648 83 10",
    "sg:postcode":"1050",
    "sg:province":"Bruxelles-Capitale",
    "wof:name":"Promotion De Produits Fins",
    "wof:placetype":"venue"
},
  "geometry": {"coordinates":[4.3909621239,50.8179664612],"type":"Point"}
}