{
  "type": "Feature",
  "properties": {
    "iso:country":"BE",
    "sg:address":"Kapittelstraat 12",
    "sg:city":"Appelterre-eichem",
    "sg:orig_category":"Meubles D\u00e9taillants, Am\u00e9nagement de B\u00e2timents et de Cuisines",
    "sg:phone":"+32 54 32 02 59",
    "sg:postcode":"9400",
    "sg:province":"Oost-Vlaanderen",
    "wof:name":"Euro-sleep",
    "wof:placetype":"venue"
},
  "geometry": {"coordinates":[3.9678869247,50.823589325],"type":"Point"}
}