{
  "type": "Feature",
  "properties": {
    "iso:country":"BE",
    "sg:address":"Heernisse 18",
    "sg:city":"Diksmuide",
    "sg:classifiers":[
        {
            "category":"Manufacturing",
            "subcategory":"Motor Vehicles & Parts",
            "type":"Manufacturing & Wholesale Goods"
        }
    ],
    "sg:phone":"+32 51 51 03 22",
    "sg:postcode":"8600",
    "sg:province":"West-Vlaanderen",
    "sg:tags":[
        "synthetic",
        "purely",
        "fibre"
    ],
    "wof:name":"Flanders Industries Nv",
    "wof:placetype":"venue"
},
  "geometry": {"coordinates":[2.8575680256,51.0280418396],"type":"Point"}
}