{
  "type": "Feature",
  "properties": {
    "iso:country":"BE",
    "sg:address":"Rue Albert I 6",
    "sg:city":"Estaimpuis (n\u00e9chin)",
    "sg:classifiers":[
        {
            "category":"Professional",
            "subcategory":"Testing Lab",
            "type":"Services"
        }
    ],
    "sg:phone":"+32 69 35 23 61",
    "sg:postcode":"7730",
    "sg:province":"Hainaut",
    "sg:tags":[
        "chemist"
    ],
    "wof:name":"Merlo F",
    "wof:placetype":"venue"
},
  "geometry": {"coordinates":[3.2698218822,50.6671524048],"type":"Point"}
}