{
  "type": "Feature",
  "properties": {
    "addr:full":"Rue Herman 6 Incourt Brabant Wallon 1315",
    "addr:housenumber":"6",
    "addr:postcode":"1315",
    "addr:street":"Rue Herman",
    "iso:country":"BE",
    "sg:address":"Rue Herman 6",
    "sg:city":"Incourt",
    "sg:orig_category":"Installation de menuiserie en bois and plastique",
    "sg:phone":"+32 10 88 93 65",
    "sg:postcode":"1315",
    "sg:province":"Brabant Wallon",
    "wof:name":"Salvatore Zucca",
    "wof:placetype":"venue"
},
  "geometry": {"coordinates":[4.8031997681,50.6930656433],"type":"Point"}
}