{
  "type": "Feature",
  "properties": {
    "iso:country":"BE",
    "sg:address":"Rue Martin-sandron 156",
    "sg:city":"Doische",
    "sg:orig_category":"Pluimveekwekers",
    "sg:phone":"+32 82 67 81 86",
    "sg:postcode":"5680",
    "sg:province":"Namur",
    "wof:name":"La Censi\u00c8re",
    "wof:placetype":"venue"
},
  "geometry": {"coordinates":[4.7392749786,50.1356582642],"type":"Point"}
}