{
  "type": "Feature",
  "properties": {
    "iso:country":"BE",
    "sg:address":"Boulevard L\u00c9opold Ii 53",
    "sg:city":"Sint-jans-molenbeek/molenbeek-saint-jean",
    "sg:orig_category":"Eclairage et \u00e9quipements du foyer",
    "sg:phone":"+32 2 420 22 30",
    "sg:postcode":"1080",
    "sg:province":"Bruxelles-Capitale",
    "wof:name":"Creation Baumann",
    "wof:placetype":"venue"
},
  "geometry": {"coordinates":[4.3428721428,50.8598442078],"type":"Point"}
}