{
  "type": "Feature",
  "properties": {
    "iso:country":"BE",
    "sg:address":"Rue Des Aub\u00e9pines 3",
    "sg:city":"Aywaille",
    "sg:classifiers":[
        {
            "category":"Professional",
            "subcategory":"Management & Consulting",
            "type":"Services"
        }
    ],
    "sg:phone":"+32 4 384 76 90",
    "sg:postcode":"4920",
    "sg:province":"Li\u00e8ge",
    "sg:tags":[
        "marketing",
        "-",
        "consultant"
    ],
    "wof:name":"Piedboeuf M",
    "wof:placetype":"venue"
},
  "geometry": {"coordinates":[5.6584758759,50.473575592],"type":"Point"}
}