{
  "type": "Feature",
  "properties": {
    "addr:full":"Grote Bosstraat 13 Schaarbeek/schaerbeek Bruxelles-Capitale 1030",
    "addr:housenumber":"13",
    "addr:postcode":"1030",
    "addr:street":"Grote Bosstraat",
    "iso:country":"BE",
    "sg:address":"Grote Bosstraat 13",
    "sg:city":"Schaarbeek/schaerbeek",
    "sg:orig_category":"Loodgieterij, verwarming and sanitaire installaties",
    "sg:phone":"+32 2 241 30 42",
    "sg:postcode":"1030",
    "sg:province":"Bruxelles-Capitale",
    "wof:name":"Pierre Blanpain",
    "wof:placetype":"venue"
},
  "geometry": {"coordinates":[4.3847441673,50.8571357727],"type":"Point"}
}