{
  "type": "Feature",
  "properties": {
    "addr:full":"Leopoldslei 181 Brasschaat Antwerpen 2930",
    "addr:housenumber":"181",
    "addr:postcode":"2930",
    "iso:country":"BE",
    "sg:address":"Leopoldslei 181",
    "sg:city":"Brasschaat",
    "sg:classifiers":[
        {
            "category":"Insurance",
            "subcategory":"Insurance Agent",
            "type":"Services"
        }
    ],
    "sg:phone":"+32 3 651 48 24",
    "sg:postcode":"2930",
    "sg:province":"Antwerpen",
    "sg:tags":[
        "broker"
    ],
    "wof:name":"Van Den Eeckhaut A",
    "wof:placetype":"venue"
},
  "geometry": {"coordinates":[4.4823818207,51.298210144],"type":"Point"}
}