{
  "type": "Feature",
  "properties": {
    "iso:country":"BE",
    "sg:address":"Nachtegalenlaan 4",
    "sg:city":"Kortenberg (everberg)",
    "sg:classifiers":[
        {
            "category":"Professional",
            "subcategory":"Art Services",
            "type":"Services"
        }
    ],
    "sg:phone":"+32 2 757 67 05",
    "sg:postcode":"3078",
    "sg:province":"Vlaams-Brabant",
    "sg:tags":[
        "graphic",
        "designer"
    ],
    "wof:name":"Salender-graphics Bvba",
    "wof:placetype":"venue"
},
  "geometry": {"coordinates":[4.5428981781,50.8722496033],"type":"Point"}
}