{
  "type": "Feature",
  "properties": {
    "iso:country":"BE",
    "sg:address":"Rue De L\u00b4 Etoile 27",
    "sg:city":"Gembloux",
    "sg:orig_category":"Instellingen voor mindervalide volwassenen",
    "sg:phone":"+32 81 63 43 23",
    "sg:postcode":"5032",
    "sg:province":"Namur",
    "wof:name":"Rebjou",
    "wof:placetype":"venue"
},
  "geometry": {"coordinates":[4.7187600136,50.5184745789],"type":"Point"}
}