{
  "type": "Feature",
  "properties": {
    "addr:full":"Rue D'om\u00c9z\u00c9e 13 Philippeville Namur 5600",
    "addr:housenumber":"13",
    "addr:postcode":"5600",
    "addr:street":"Rue D'Ome \u0301Ze\u0301E",
    "iso:country":"BE",
    "sg:address":"Rue D'om\u00c9z\u00c9e 13",
    "sg:city":"Philippeville",
    "sg:orig_category":"Fotografen and fotostudio's Immobili\u00ebnkantoren",
    "sg:phone":"+32 82 67 86 86",
    "sg:postcode":"5600",
    "sg:province":"Namur",
    "wof:name":"Louis Desmanet",
    "wof:placetype":"venue"
},
  "geometry": {"coordinates":[4.5895829201,50.1967544556],"type":"Point"}
}