{
  "type": "Feature",
  "properties": {
    "addr:full":"Rassel 26 Wemmel Vlaams-Brabant 1780",
    "addr:housenumber":"26",
    "addr:postcode":"1780",
    "addr:street":"Rassel;Vlaams-Brabant",
    "iso:country":"BE",
    "sg:address":"Rassel 26",
    "sg:city":"Wemmel",
    "sg:classifiers":[
        {
            "category":"Building & Trades",
            "subcategory":"Electrical",
            "type":"Services"
        }
    ],
    "sg:phone":"+32 2 460 60 24",
    "sg:postcode":"1780",
    "sg:province":"Vlaams-Brabant",
    "sg:tags":[
        "electric",
        "-",
        "housewiring",
        "contractor"
    ],
    "wof:name":"Electro Vdb",
    "wof:placetype":"venue"
},
  "geometry": {"coordinates":[4.2992191315,50.9098091125],"type":"Point"}
}