{
  "type": "Feature",
  "properties": {
    "iso:country":"BE",
    "sg:address":"Frederik Maldersstraat 63",
    "sg:city":"Maaseik",
    "sg:orig_category":"Installation de menuiserie en bois and plastique",
    "sg:phone":"+32 89 56 83 48",
    "sg:postcode":"3680",
    "sg:province":"Limburg",
    "wof:name":"Mulders",
    "wof:placetype":"venue"
},
  "geometry": {"coordinates":[5.7739830017,51.1040687561],"type":"Point"}
}