{
  "type": "Feature",
  "properties": {
    "iso:country":"BE",
    "sg:address":"Koningsstraat 102",
    "sg:city":"Oostende",
    "sg:orig_category":"Artsen and specialisten",
    "sg:phone":"+32 59 50 62 82",
    "sg:postcode":"8400",
    "sg:province":"West-Vlaanderen",
    "wof:name":"A. Fonteyne",
    "wof:placetype":"venue"
},
  "geometry": {"coordinates":[2.908107996,51.227848053],"type":"Point"}
}