{
  "type": "Feature",
  "properties": {
    "iso:country":"BE",
    "sg:address":"Noodlottige Rotsstraat 68",
    "sg:city":"Sint-lambrechts-woluwe/woluwe-saint-lambert",
    "sg:orig_category":"Herstellingen and onderhoud van auto's",
    "sg:phone":"+32 2 771 62 20",
    "sg:postcode":"1200",
    "sg:province":"Bruxelles-Capitale",
    "wof:name":"Wolu Master Car",
    "wof:placetype":"venue"
},
  "geometry": {"coordinates":[4.4189338684,50.843952179],"type":"Point"}
}