{
  "type": "Feature",
  "properties": {
    "addr:full":"Wegvoeringsstraat 26 Aalst (hofstade) Oost-Vlaanderen 9308",
    "addr:housenumber":"26",
    "addr:postcode":"9308",
    "addr:street":"Wegvoeringsstraat",
    "iso:country":"BE",
    "sg:address":"Wegvoeringsstraat 26",
    "sg:city":"Aalst (hofstade)",
    "sg:classifiers":[
        {
            "category":"Personal",
            "subcategory":"Beauty Salon",
            "type":"Services"
        }
    ],
    "sg:phone":"+32 53 70 09 49",
    "sg:postcode":"9308",
    "sg:province":"Oost-Vlaanderen",
    "sg:tags":[
        "lady",
        "-",
        "hairdressing"
    ],
    "wof:name":"Solange",
    "wof:placetype":"venue"
},
  "geometry": {"coordinates":[4.0347590446,50.9603500366],"type":"Point"}
}