{
  "type": "Feature",
  "properties": {
    "iso:country":"BE",
    "sg:address":"Haardstraat 6",
    "sg:city":"Lommel",
    "sg:orig_category":"Enseignement maternel and primaire",
    "sg:phone":"+32 11 54 46 76",
    "sg:postcode":"3920",
    "sg:province":"Limburg",
    "wof:name":"Stedelijke Basisschool",
    "wof:placetype":"venue"
},
  "geometry": {"coordinates":[5.3070878983,51.2076339722],"type":"Point"}
}