{
  "type": "Feature",
  "properties": {
    "addr:full":"Chauss\u00c9e Brunehault 1 Honnelles Hainaut 7387",
    "addr:housenumber":"1",
    "addr:postcode":"7387",
    "addr:street":"Chausse\u0301E Brunehault;Hainaut",
    "iso:country":"BE",
    "sg:address":"Chauss\u00c9e Brunehault 1",
    "sg:city":"Honnelles",
    "sg:orig_category":"Epiceries",
    "sg:phone":"+32 65 75 91 39",
    "sg:postcode":"7387",
    "sg:province":"Hainaut",
    "wof:name":"Anne-marie Rousseau",
    "wof:placetype":"venue"
},
  "geometry": {"coordinates":[3.7461540699,50.3487052917],"type":"Point"}
}