{
  "type": "Feature",
  "properties": {
    "iso:country":"BE",
    "sg:address":"Leuvensesteenweg 445",
    "sg:city":"Boutersem",
    "sg:classifiers":[
        {
            "category":"Parking",
            "subcategory":"Lot",
            "type":"Transportation"
        }
    ],
    "sg:phone":"+32 16 72 04 53",
    "sg:postcode":"3370",
    "sg:province":"Vlaams-Brabant",
    "sg:tags":[
        "pneumatic",
        "automation"
    ],
    "wof:name":"Vanborren Systems Bvba",
    "wof:placetype":"venue"
},
  "geometry": {"coordinates":[4.8225097656,50.8464508057],"type":"Point"}
}