{
  "type": "Feature",
  "properties": {
    "iso:country":"BE",
    "sg:address":"Puttestraat 171",
    "sg:city":"Begijnendijk",
    "sg:classifiers":[
        {
            "category":"Autos & Motor Vehicles",
            "subcategory":"Automobile Sales",
            "type":"Retail Goods"
        }
    ],
    "sg:phone":"+32 16 57 07 18",
    "sg:postcode":"3130",
    "sg:province":"Vlaams-Brabant",
    "sg:tags":[
        "ceremony",
        "car"
    ],
    "wof:name":"Verschueren R",
    "wof:placetype":"venue"
},
  "geometry": {"coordinates":[4.7993998528,51.0150184631],"type":"Point"}
}