{
  "type": "Feature",
  "properties": {
    "iso:country":"BE",
    "sg:address":"Avenue F\u00c9lix Marchal 62",
    "sg:city":"Schaarbeek/schaerbeek",
    "sg:orig_category":"H\u00f4tels",
    "sg:phone":"+32 2 734 95 16",
    "sg:postcode":"1030",
    "sg:province":"Bruxelles-Capitale",
    "wof:name":"Cent.ens.cath.& L.brunner",
    "wof:placetype":"venue"
},
  "geometry": {"coordinates":[4.3920431137,50.8510627747],"type":"Point"}
}