{
  "type": "Feature",
  "properties": {
    "iso:country":"BE",
    "sg:address":"Puvinagestraat 9",
    "sg:city":"Vloesberg/flobecq",
    "sg:orig_category":"Rundveehouders",
    "sg:phone":"+32 68 44 80 04",
    "sg:postcode":"7880",
    "sg:province":"Hainaut",
    "wof:name":"Jose Depretz",
    "wof:placetype":"venue"
},
  "geometry": {"coordinates":[3.7384300232,50.7368011475],"type":"Point"}
}