{
  "type": "Feature",
  "properties": {
    "iso:country":"BE",
    "sg:address":"Sint-rembertlaan 13",
    "sg:city":"Torhout",
    "sg:orig_category":"M\u00e9decins and sp\u00e9cialistes",
    "sg:phone":"+32 50 21 14 69",
    "sg:postcode":"8820",
    "sg:province":"West-Vlaanderen",
    "wof:name":"Paul Santens",
    "wof:placetype":"venue"
},
  "geometry": {"coordinates":[3.0982320309,51.0702590942],"type":"Point"}
}