{
  "type": "Feature",
  "properties": {
    "iso:country":"BE",
    "sg:address":"Heidelaan 14",
    "sg:city":"De Haan (klemskerke)",
    "sg:classifiers":[
        {
            "category":"Retail",
            "subcategory":"Repair Shop",
            "type":"Services"
        }
    ],
    "sg:phone":"+32 59 23 90 44",
    "sg:postcode":"8420",
    "sg:province":"West-Vlaanderen",
    "wof:name":"Rotsaert K",
    "wof:placetype":"venue"
},
  "geometry": {"coordinates":[3.0048260689,51.2605476379],"type":"Point"}
}