{
  "type": "Feature",
  "properties": {
    "iso:country":"BE",
    "sg:address":"Heirweg 17",
    "sg:city":"Maldegem",
    "sg:orig_category":"Installation \u00e9lectrique r\u00e9sidentielle",
    "sg:phone":"+32 50 71 98 71",
    "sg:postcode":"9990",
    "sg:province":"Oost-Vlaanderen",
    "wof:name":"Vanlatum",
    "wof:placetype":"venue"
},
  "geometry": {"coordinates":[3.4072868824,51.2108840942],"type":"Point"}
}