{
  "type": "Feature",
  "properties": {
    "addr:full":"Industrieterrein 1-25c Diest Vlaams-Brabant 3290",
    "addr:housenumber":"1-25c",
    "addr:postcode":"3290",
    "addr:street":"Industrieterrein",
    "iso:country":"BE",
    "sg:address":"Industrieterrein 1-25c",
    "sg:city":"Diest",
    "sg:classifiers":[
        {
            "category":"Building & Trades",
            "subcategory":"Construction",
            "type":"Services"
        }
    ],
    "sg:phone":"+32 13 32 17 78",
    "sg:postcode":"3290",
    "sg:province":"Vlaams-Brabant",
    "sg:tags":[
        "stair"
    ],
    "wof:name":"Escala",
    "wof:placetype":"venue"
},
  "geometry": {"coordinates":[5.0751109123,50.9639320374],"type":"Point"}
}