{
  "type": "Feature",
  "properties": {
    "addr:full":"Brusselse Steenweg 35 Vorst/forest Bruxelles-Capitale 1190",
    "addr:housenumber":"35",
    "addr:postcode":"1190",
    "addr:street":"Brusselse Steenweg;/ Forest",
    "iso:country":"BE",
    "sg:address":"Brusselse Steenweg 35",
    "sg:city":"Vorst/forest",
    "sg:orig_category":"Meubelzaken, woning- and keukeninrichting",
    "sg:phone":"+32 2 332 49 72",
    "sg:postcode":"1190",
    "sg:province":"Bruxelles-Capitale",
    "wof:name":"Meubles Taner",
    "wof:placetype":"venue"
},
  "geometry": {"coordinates":[4.3182020187,50.81067276],"type":"Point"}
}