{
  "type": "Feature",
  "properties": {
    "iso:country":"BE",
    "sg:address":"Oossekouter 38",
    "sg:city":"Nevele",
    "sg:classifiers":[
        {
            "category":"Professional",
            "type":"Services"
        }
    ],
    "sg:phone":"+32 9 280 00 60",
    "sg:postcode":"9850",
    "sg:province":"Oost-Vlaanderen",
    "sg:tags":[
        "surveyor",
        "-",
        "valuer"
    ],
    "wof:name":"B.k. & K.",
    "wof:placetype":"venue"
},
  "geometry": {"coordinates":[3.5549991131,51.0412368774],"type":"Point"}
}