{
  "type": "Feature",
  "properties": {
    "iso:country":"BE",
    "sg:address":"Generaal Bernheimlaan 54",
    "sg:city":"Etterbeek/etterbeek",
    "sg:orig_category":"Krantenwinkels Rookartikelen",
    "sg:phone":"+32 2 647 38 51",
    "sg:postcode":"1040",
    "sg:province":"Bruxelles-Capitale",
    "wof:name":"Too Day",
    "wof:placetype":"venue"
},
  "geometry": {"coordinates":[4.388010025,50.8264427185],"type":"Point"}
}