{
  "type": "Feature",
  "properties": {
    "addr:full":"Rozendaalstraat 57 Ieper West-Vlaanderen 8900",
    "addr:housenumber":"57",
    "addr:postcode":"8900",
    "addr:street":"Rozendaalstraat",
    "iso:country":"BE",
    "sg:address":"Rozendaalstraat 57",
    "sg:city":"Ieper",
    "sg:classifiers":[
        {
            "category":"Travel",
            "subcategory":"Hotels & Motels",
            "type":"Entertainment"
        }
    ],
    "sg:phone":"+32 57 20 00 95",
    "sg:postcode":"8900",
    "sg:province":"West-Vlaanderen",
    "sg:tags":[
        "supply",
        "hotels",
        "catering"
    ],
    "wof:name":"Debergh Nv Kokshop",
    "wof:placetype":"venue"
},
  "geometry": {"coordinates":[2.8780720234,50.8786048889],"type":"Point"}
}