{
  "type": "Feature",
  "properties": {
    "addr:full":"Goethelaan 12 Box 8 De Haan (klemskerke) West-Vlaanderen 8420",
    "addr:housenumber":"12",
    "addr:postcode":"8420",
    "addr:street":"Goethelaan;Box 8 De",
    "iso:country":"BE",
    "sg:address":"Goethelaan 12 Box 8",
    "sg:city":"De Haan (klemskerke)",
    "sg:classifiers":[
        {
            "category":"Real Estate",
            "subcategory":"Real Estate Services",
            "type":"Services"
        }
    ],
    "sg:phone":"+32 59 23 44 48",
    "sg:postcode":"8420",
    "sg:province":"West-Vlaanderen",
    "wof:name":"Vastgoedbeheer Breuer Raoul",
    "wof:placetype":"venue"
},
  "geometry": {"coordinates":[3.0320079327,51.2776565552],"type":"Point"}
}