{
  "type": "Feature",
  "properties": {
    "iso:country":"BE",
    "sg:address":"Avenue De La D\u00c9portation 25",
    "sg:city":"Dinant",
    "sg:orig_category":"Action sociale avec h\u00e9bergement",
    "sg:phone":"+32 82 22 24 36",
    "sg:postcode":"5500",
    "sg:province":"Namur",
    "wof:name":"Les Semailles",
    "wof:placetype":"venue"
},
  "geometry": {"coordinates":[4.9055299759,50.2632293701],"type":"Point"}
}