{
  "type": "Feature",
  "properties": {
    "addr:full":"Willem Tellstraat 1 Blankenberge West-Vlaanderen 8370",
    "addr:housenumber":"1",
    "addr:postcode":"8370",
    "addr:street":"Willem Tellstraat",
    "iso:country":"BE",
    "sg:address":"Willem Tellstraat 1",
    "sg:city":"Blankenberge",
    "sg:orig_category":"Apotheken",
    "sg:phone":"+32 50 41 75 70",
    "sg:postcode":"8370",
    "sg:province":"West-Vlaanderen",
    "wof:name":"Deprez-heleven Apothekers",
    "wof:placetype":"venue"
},
  "geometry": {"coordinates":[3.1336429119,51.3088531494],"type":"Point"}
}