{
  "type": "Feature",
  "properties": {
    "iso:country":"BE",
    "sg:address":"Heirstraat 170",
    "sg:city":"Maasmechelen",
    "sg:classifiers":[
        {
            "category":"Restaurant",
            "type":"Food & Drink"
        }
    ],
    "sg:phone":"+32 89 77 49 92",
    "sg:postcode":"3630",
    "sg:province":"Limburg",
    "sg:tags":[
        "industrial",
        "kitchen",
        "catering"
    ],
    "wof:name":"Asain-food",
    "wof:placetype":"venue"
},
  "geometry": {"coordinates":[5.6992812157,50.966468811],"type":"Point"}
}