{
  "type": "Feature",
  "properties": {
    "iso:country":"BE",
    "sg:address":"Luikersteenweg 32",
    "sg:city":"Sint-truiden",
    "sg:orig_category":"Non-Classified Establishments",
    "sg:phone":"+32 11 64 27 41",
    "sg:postcode":"3800",
    "sg:province":"Limburg",
    "wof:name":"Alders Etn Nv",
    "wof:placetype":"venue"
},
  "geometry": {"coordinates":[5.1900892258,50.8117446899],"type":"Point"}
}