{
  "type": "Feature",
  "properties": {
    "addr:full":"Rue Du Centre 36bb Aywaille Li\u00e8ge 4920",
    "addr:housenumber":"36bb",
    "addr:postcode":"4920",
    "addr:street":"Rue Du Centre",
    "iso:country":"BE",
    "sg:address":"Rue Du Centre 36bb",
    "sg:city":"Aywaille",
    "sg:orig_category":"Production and transformation de viande",
    "sg:phone":"+32 4 384 40 16",
    "sg:postcode":"4920",
    "sg:province":"Li\u00e8ge",
    "wof:name":"Paul Mosbeux",
    "wof:placetype":"venue"
},
  "geometry": {"coordinates":[5.677549839,50.4733886719],"type":"Point"}
}