{
  "type": "Feature",
  "properties": {
    "addr:full":"Lekestraat 112 Koekelare West-Vlaanderen 8680",
    "addr:housenumber":"112",
    "addr:postcode":"8680",
    "addr:street":"Lekestraat",
    "iso:country":"BE",
    "sg:address":"Lekestraat 112",
    "sg:city":"Koekelare",
    "sg:orig_category":"Slagers",
    "sg:phone":"+32 51 58 12 97",
    "sg:postcode":"8680",
    "sg:province":"West-Vlaanderen",
    "wof:name":"Fa. Clement-blomme",
    "wof:placetype":"venue"
},
  "geometry": {"coordinates":[2.9377040863,51.0902175903],"type":"Point"}
}