{
  "type": "Feature",
  "properties": {
    "iso:country":"BE",
    "sg:address":"Rue Du P\u00c9pin 50",
    "sg:city":"Brussel/bruxelles",
    "sg:orig_category":"Dameskledingzaken Kleding",
    "sg:phone":"+32 2 513 58 72",
    "sg:postcode":"1000",
    "sg:province":"Bruxelles-Capitale",
    "wof:name":"La Cigale",
    "wof:placetype":"venue"
},
  "geometry": {"coordinates":[4.3606162071,50.8388290405],"type":"Point"}
}