{
  "type": "Feature",
  "properties": {
    "addr:full":"Baarledorpstraat 4 Gent (drongen) Oost-Vlaanderen 9031",
    "addr:housenumber":"4",
    "addr:postcode":"9031",
    "addr:street":"Baarledorpstraat",
    "iso:country":"BE",
    "sg:address":"Baarledorpstraat 4",
    "sg:city":"Gent (drongen)",
    "sg:classifiers":[
        {
            "category":"Education",
            "subcategory":"School",
            "type":"Public Place"
        }
    ],
    "sg:phone":"+32 9 282 54 92",
    "sg:postcode":"9031",
    "sg:province":"Oost-Vlaanderen",
    "sg:tags":[
        "primary"
    ],
    "wof:name":"Don Bosco-instituut",
    "wof:placetype":"venue"
},
  "geometry": {"coordinates":[3.6204710007,51.0374565125],"type":"Point"}
}