{
  "type": "Feature",
  "properties": {
    "addr:full":"Nerenweg 7 Laarne Oost-Vlaanderen 9270",
    "addr:housenumber":"7",
    "addr:postcode":"9270",
    "addr:street":"Nerenweg",
    "iso:country":"BE",
    "sg:address":"Nerenweg 7",
    "sg:city":"Laarne",
    "sg:orig_category":"Enseignement maternel and primaire",
    "sg:phone":"+32 9 367 56 88",
    "sg:postcode":"9270",
    "sg:province":"Oost-Vlaanderen",
    "wof:name":"B.s.g.o. De Zonnebloem",
    "wof:placetype":"venue"
},
  "geometry": {"coordinates":[3.9165730476,51.0365829468],"type":"Point"}
}