{
  "type": "Feature",
  "properties": {
    "iso:country":"BE",
    "sg:address":"Sint-kristoffelstraat 12",
    "sg:city":"Gent",
    "sg:classifiers":[
        {
            "category":"Social Services",
            "type":"Services"
        }
    ],
    "sg:phone":"+32 9 223 12 09",
    "sg:postcode":"9000",
    "sg:province":"Oost-Vlaanderen",
    "wof:name":"Esmeraldas",
    "wof:placetype":"venue"
},
  "geometry": {"coordinates":[3.7330739498,51.0498313904],"type":"Point"}
}