{
  "type": "Feature",
  "properties": {
    "addr:full":"Velleriestraat 121 Moeskroen/mouscron Hainaut 7700",
    "addr:housenumber":"121",
    "addr:postcode":"7700",
    "addr:street":"Velleriestraat",
    "iso:country":"BE",
    "sg:address":"Velleriestraat 121",
    "sg:city":"Moeskroen/mouscron",
    "sg:orig_category":"Diverse organisaties and verenigingen",
    "sg:phone":"+32 56 34 20 44",
    "sg:postcode":"7700",
    "sg:province":"Hainaut",
    "wof:name":"La Prairie",
    "wof:placetype":"venue"
},
  "geometry": {"coordinates":[3.2323200703,50.7400932312],"type":"Point"}
}