{
  "type": "Feature",
  "properties": {
    "addr:full":"Potiaulaan 11 Dendermonde Oost-Vlaanderen 9200",
    "addr:housenumber":"11",
    "addr:postcode":"9200",
    "addr:street":"Potiaulaan;Oost-Vlaanderen",
    "iso:country":"BE",
    "sg:address":"Potiaulaan 11",
    "sg:city":"Dendermonde",
    "sg:orig_category":"Textiles. Eclairage et \u00e9quipements du foyer",
    "sg:phone":"+32 52 21 35 50",
    "sg:postcode":"9200",
    "sg:province":"Oost-Vlaanderen",
    "wof:name":"Michem Gordijnen Binnenzonwering",
    "wof:placetype":"venue"
},
  "geometry": {"coordinates":[4.0983099937,51.0315208435],"type":"Point"}
}