{
  "type": "Feature",
  "properties": {
    "iso:country":"BE",
    "sg:address":"Rue Emile Vandervelde 24",
    "sg:city":"Beyne-heusay (queue-du-bois)",
    "sg:classifiers":[
        {
            "category":"Social Services",
            "subcategory":"Job Training",
            "type":"Services"
        }
    ],
    "sg:phone":"+32 4 370 94 19",
    "sg:postcode":"4610",
    "sg:province":"Li\u00e8ge",
    "sg:tags":[
        "coordinator",
        "safety"
    ],
    "wof:name":"Bfs Coordination Sprl",
    "wof:placetype":"venue"
},
  "geometry": {"coordinates":[5.6812381744,50.6367073059],"type":"Point"}
}