{
  "type": "Feature",
  "properties": {
    "addr:full":"Dorpsstraat 38 Wellen Limburg 3830",
    "addr:housenumber":"38",
    "addr:postcode":"3830",
    "addr:street":"Dorpsstraat",
    "iso:country":"BE",
    "sg:address":"Dorpsstraat 38",
    "sg:city":"Wellen",
    "sg:classifiers":[
        {
            "category":"Professional",
            "subcategory":"Testing Lab",
            "type":"Services"
        }
    ],
    "sg:phone":"+32 12 74 17 01",
    "sg:postcode":"3830",
    "sg:province":"Limburg",
    "sg:tags":[
        "chemist"
    ],
    "wof:name":"Kempeneers L",
    "wof:placetype":"venue"
},
  "geometry": {"coordinates":[5.3326039314,50.8405265808],"type":"Point"}
}