{
  "type": "Feature",
  "properties": {
    "addr:full":"Rijselstraat 19 Menen West-Vlaanderen 8930",
    "addr:housenumber":"19",
    "addr:postcode":"8930",
    "addr:street":"Rijselstraat",
    "iso:country":"BE",
    "sg:address":"Rijselstraat 19",
    "sg:city":"Menen",
    "sg:classifiers":[
        {
            "category":"Restaurant",
            "type":"Food & Drink"
        }
    ],
    "sg:phone":"+32 56 51 82 68",
    "sg:postcode":"8930",
    "sg:province":"West-Vlaanderen",
    "sg:tags":[
        "de",
        "organisation",
        "\u00e0",
        "fast",
        "catering",
        "emporter",
        "f\u00eates",
        "restaurants"
    ],
    "wof:name":"Peking City",
    "wof:placetype":"venue"
},
  "geometry": {"coordinates":[3.1218059063,50.7952728271],"type":"Point"}
}