{
  "type": "Feature",
  "properties": {
    "iso:country":"BE",
    "sg:address":"Langstraat 21",
    "sg:city":"Hoogstraten",
    "sg:orig_category":"Eleveurs de bovins. Eleveurs and marchands de porcs",
    "sg:phone":"+32 3 315 02 63",
    "sg:postcode":"2328",
    "sg:province":"Antwerpen",
    "wof:name":"Leenaerts Bio-producent",
    "wof:placetype":"venue"
},
  "geometry": {"coordinates":[4.7882800102,51.4723701477],"type":"Point"}
}