{
  "type": "Feature",
  "properties": {
    "iso:country":"BE",
    "sg:address":"Rue Entre-les-ponts 23",
    "sg:city":"Spa",
    "sg:orig_category":"Instituts de beaut\u00e9",
    "sg:phone":"+32 87 77 36 76",
    "sg:postcode":"4900",
    "sg:province":"Li\u00e8ge",
    "wof:name":"Peeters Sylvie",
    "wof:placetype":"venue"
},
  "geometry": {"coordinates":[5.8682889938,50.4915618896],"type":"Point"}
}