{
  "type": "Feature",
  "properties": {
    "iso:country":"BE",
    "sg:address":"Avenue L\u00e9on Fournet 9 Box 101",
    "sg:city":"Ottignies-louvain-la-neuve (limelette)",
    "sg:orig_category":"Fiduciairies",
    "sg:phone":"+32 10 40 07 91",
    "sg:postcode":"1342",
    "sg:province":"Brabant Wallon",
    "wof:name":"Sam & Co",
    "wof:placetype":"venue"
},
  "geometry": {"coordinates":[4.5746002197,50.6839599609],"type":"Point"}
}