{
  "type": "Feature",
  "properties": {
    "addr:full":"Riddersstraat 10 Leuven Vlaams-Brabant 3000",
    "addr:housenumber":"10",
    "addr:postcode":"3000",
    "addr:street":"Riddersstraat",
    "iso:country":"BE",
    "sg:address":"Riddersstraat 10",
    "sg:city":"Leuven",
    "sg:orig_category":"Pre-Press Services",
    "sg:phone":"+32 16 29 08 56",
    "sg:postcode":"3000",
    "sg:province":"Vlaams-Brabant",
    "wof:name":"Textware",
    "wof:placetype":"venue"
},
  "geometry": {"coordinates":[4.6908278465,50.8815574646],"type":"Point"}
}