{
  "type": "Feature",
  "properties": {
    "iso:country":"BE",
    "sg:address":"Noordstraat 103",
    "sg:city":"Roeselare",
    "sg:orig_category":"Tweedehandsgoederen",
    "sg:phone":"+32 51 24 88 72",
    "sg:postcode":"8800",
    "sg:province":"West-Vlaanderen",
    "wof:name":"Huis Sfinx",
    "wof:placetype":"venue"
},
  "geometry": {"coordinates":[3.121516943,50.9480018616],"type":"Point"}
}