{
  "type": "Feature",
  "properties": {
    "addr:full":"Korte Gasthuisstraat 91b5 Turnhout Antwerpen 2300",
    "addr:housenumber":"91b5",
    "addr:postcode":"2300",
    "addr:street":"Korte Gasthuisstraat",
    "iso:country":"BE",
    "sg:address":"Korte Gasthuisstraat 91b5",
    "sg:city":"Turnhout",
    "sg:classifiers":[
        {
            "category":"Personal",
            "subcategory":"Beauty Salon",
            "type":"Services"
        }
    ],
    "sg:phone":"+32 14 42 35 64",
    "sg:postcode":"2300",
    "sg:province":"Antwerpen",
    "sg:tags":[
        "de",
        "coiffure"
    ],
    "wof:name":"Rita Cabanier",
    "wof:placetype":"venue"
},
  "geometry": {"coordinates":[4.9456582069,51.3193092346],"type":"Point"}
}