{
  "type": "Feature",
  "properties": {
    "addr:full":"Rue Saint Martin 107 Tournai Hainaut 7500",
    "addr:housenumber":"107",
    "addr:postcode":"7500",
    "addr:street":"Rue Saint Martin",
    "iso:country":"BE",
    "sg:address":"Rue Saint Martin 107",
    "sg:city":"Tournai",
    "sg:orig_category":"Electrom\u00e9nager, t\u00e9l\u00e9visions and radios. R\u00e9parations d'appareils \u00e9lectrom\u00e9nagers",
    "sg:phone":"+32 69 23 23 13",
    "sg:postcode":"7500",
    "sg:province":"Hainaut",
    "wof:name":"Electro Shop Leclercq",
    "wof:placetype":"venue"
},
  "geometry": {"coordinates":[3.3849029541,50.6031532288],"type":"Point"}
}