{
  "type": "Feature",
  "properties": {
    "iso:country":"BE",
    "sg:address":"Kapellestraat 51-53",
    "sg:city":"Hamme",
    "sg:classifiers":[
        {
            "category":"Home & Garden",
            "subcategory":"Hardware",
            "type":"Retail Goods"
        }
    ],
    "sg:phone":"+32 52 47 71 07",
    "sg:postcode":"9220",
    "sg:province":"Oost-Vlaanderen",
    "sg:tags":[
        "-"
    ],
    "wof:name":"Van Puyvelde Bvba",
    "wof:placetype":"venue"
},
  "geometry": {"coordinates":[4.1426267624,51.0956420898],"type":"Point"}
}