{
  "type": "Feature",
  "properties": {
    "addr:full":"Alsembergse Steenweg 807 Ukkel/uccle Bruxelles-Capitale 1180",
    "addr:housenumber":"807",
    "addr:postcode":"1180",
    "addr:street":"Alsembergse Steenweg;/",
    "iso:country":"BE",
    "sg:address":"Alsembergse Steenweg 807",
    "sg:city":"Ukkel/uccle",
    "sg:orig_category":"Brood, gebak and snoepgoed Restaurants",
    "sg:phone":"+32 2 376 14 69",
    "sg:postcode":"1180",
    "sg:province":"Bruxelles-Capitale",
    "wof:name":"Croquanterie",
    "wof:placetype":"venue"
},
  "geometry": {"coordinates":[4.336438179,50.8019981384],"type":"Point"}
}