{
  "type": "Feature",
  "properties": {
    "iso:country":"BE",
    "sg:address":"Driesheide 34",
    "sg:city":"Zoersel (halle)",
    "sg:classifiers":[
        {
            "category":"Freight",
            "type":"Transportation"
        }
    ],
    "sg:phone":"+32 3 384 03 83",
    "sg:postcode":"2980",
    "sg:province":"Antwerpen",
    "sg:tags":[
        "container",
        "-",
        "transport"
    ],
    "wof:name":"Van Aerde Gebroeders",
    "wof:placetype":"venue"
},
  "geometry": {"coordinates":[4.6340918541,51.2416725159],"type":"Point"}
}