{
  "type": "Feature",
  "properties": {
    "iso:country":"BE",
    "sg:address":"Route De Ch\u00c2telet 251",
    "sg:city":"Charleroi",
    "sg:orig_category":"Apotheken",
    "sg:phone":"+32 71 36 29 44",
    "sg:postcode":"6010",
    "sg:province":"Hainaut",
    "wof:name":"Nathalie Dubuc",
    "wof:placetype":"venue"
},
  "geometry": {"coordinates":[4.4647688866,50.3921966553],"type":"Point"}
}