{
  "type": "Feature",
  "properties": {
    "addr:full":"Rue Saint-gilles 149 Li\u00e8ge 1 Li\u00e8ge 4000",
    "addr:housenumber":"149;1",
    "addr:postcode":"4000",
    "addr:street":"Rue Saint-Gilles",
    "iso:country":"BE",
    "sg:address":"Rue Saint-gilles 149",
    "sg:city":"Li\u00e8ge 1",
    "sg:classifiers":[
        {
            "category":"Bars & Pubs",
            "type":"Food & Drink"
        }
    ],
    "sg:phone":"+32 4 223 18 80",
    "sg:postcode":"4000",
    "sg:province":"Li\u00e8ge",
    "sg:tags":[
        "tavern"
    ],
    "wof:name":"Vaudr\u00e9e 2 (le)",
    "wof:placetype":"venue"
},
  "geometry": {"coordinates":[5.5630569458,50.6378631592],"type":"Point"}
}