{
  "type": "Feature",
  "properties": {
    "iso:country":"BE",
    "sg:address":"Gentsebaan 71",
    "sg:city":"Sint-niklaas",
    "sg:orig_category":"V\u00e9hicules automobiles",
    "sg:phone":"+32 3 780 30 70",
    "sg:postcode":"9100",
    "sg:province":"Oost-Vlaanderen",
    "wof:name":"Rover",
    "wof:placetype":"venue"
},
  "geometry": {"coordinates":[4.1252470016,51.1491127014],"type":"Point"}
}