{
  "type": "Feature",
  "properties": {
    "iso:country":"BE",
    "sg:address":"Gebr De Smetstraat 116",
    "sg:city":"Gent",
    "sg:orig_category":"Zuivelproducten",
    "sg:phone":"+32 9 225 55 84",
    "sg:postcode":"9000",
    "sg:province":"Oost-Vlaanderen",
    "wof:name":"Naessens",
    "wof:placetype":"venue"
},
  "geometry": {"coordinates":[3.7050030231,51.0633659363],"type":"Point"}
}