{
  "type": "Feature",
  "properties": {
    "addr:full":"Dokter Theo Tutsstraat 17 Boechout Antwerpen 2530",
    "addr:housenumber":"17",
    "addr:postcode":"2530",
    "addr:street":"Dokter Theo Tutsstraat",
    "iso:country":"BE",
    "sg:address":"Dokter Theo Tutsstraat 17",
    "sg:city":"Boechout",
    "sg:classifiers":[
        {
            "category":"Professional",
            "subcategory":"Accounting & Tax Preparation",
            "type":"Services"
        }
    ],
    "sg:phone":"+32 3 455 66 00",
    "sg:postcode":"2530",
    "sg:province":"Antwerpen",
    "sg:tags":[
        "bookkeeper"
    ],
    "wof:name":"Van Avermaet L",
    "wof:placetype":"venue"
},
  "geometry": {"coordinates":[4.4918851852,51.1613693237],"type":"Point"}
}