{
  "type": "Feature",
  "properties": {
    "iso:country":"BE",
    "sg:address":"Parmastraat 82",
    "sg:city":"Sint-gillis/saint-gilles",
    "sg:orig_category":"Installatie van houten of kunststof schrijnwerk Plaatsen van vloer- and muurbekleding Schilders",
    "sg:phone":"+32 2 520 27 23",
    "sg:postcode":"1060",
    "sg:province":"Bruxelles-Capitale",
    "wof:name":"Bleu Azur",
    "wof:placetype":"venue"
},
  "geometry": {"coordinates":[4.34851408,50.8282661438],"type":"Point"}
}