{
  "type": "Feature",
  "properties": {
    "iso:country":"BE",
    "sg:address":"Apostelstraat 10 Box 2",
    "sg:city":"Sint-niklaas",
    "sg:classifiers":[
        {
            "category":"Taxi",
            "type":"Transportation"
        }
    ],
    "sg:phone":"+32 3 765 13 13",
    "sg:postcode":"9100",
    "sg:province":"Oost-Vlaanderen",
    "sg:tags":[
        "taxicab"
    ],
    "wof:name":"Euro Taxi Be",
    "wof:placetype":"venue"
},
  "geometry": {"coordinates":[4.1441121101,51.1640777588],"type":"Point"}
}