{
  "type": "Feature",
  "properties": {
    "iso:country":"BE",
    "sg:address":"Rue Mar\u00c9chal Foch 4",
    "sg:city":"Chatelet",
    "sg:classifiers":[
        {
            "category":"Cafe",
            "type":"Food & Drink"
        }
    ],
    "sg:phone":"+32 71 38 43 67",
    "sg:postcode":"6200",
    "sg:province":"Hainaut",
    "sg:tags":[
        "caf\u00e9s"
    ],
    "wof:name":"Georges Rossi",
    "wof:placetype":"venue"
},
  "geometry": {"coordinates":[4.5183501244,50.4110450745],"type":"Point"}
}