{
  "type": "Feature",
  "properties": {
    "addr:full":"Mee\u00cbnweg 22a Genk Limburg 3600",
    "addr:housenumber":"22a",
    "addr:postcode":"3600",
    "addr:street":"Meee\u0308Nweg",
    "iso:country":"BE",
    "sg:address":"Mee\u00cbnweg 22a",
    "sg:city":"Genk",
    "sg:orig_category":"Ordinateurs and \u00e9quipement informatique",
    "sg:phone":"+32 89 32 91 20",
    "sg:postcode":"3600",
    "sg:province":"Limburg",
    "wof:name":"Linfo",
    "wof:placetype":"venue"
},
  "geometry": {"coordinates":[5.4739217758,50.9483528137],"type":"Point"}
}