{
  "type": "Feature",
  "properties": {
    "addr:full":"Koninklijke Baan 80 Koksijde West-Vlaanderen 8670",
    "addr:housenumber":"80",
    "addr:postcode":"8670",
    "addr:street":"Koninklijke Baan",
    "iso:country":"BE",
    "sg:address":"Koninklijke Baan 80",
    "sg:city":"Koksijde",
    "sg:classifiers":[
        {
            "category":"Shopping",
            "subcategory":"Shoes",
            "type":"Retail Goods"
        }
    ],
    "sg:phone":"+32 58 51 28 69",
    "sg:postcode":"8670",
    "sg:province":"West-Vlaanderen",
    "sg:tags":[
        "slipper",
        "-"
    ],
    "wof:name":"Roland Shoe",
    "wof:placetype":"venue"
},
  "geometry": {"coordinates":[2.6376628876,51.1216239929],"type":"Point"}
}