{
  "type": "Feature",
  "properties": {
    "addr:full":"Kapellestraat 66 Oostkamp West-Vlaanderen 8020",
    "addr:housenumber":"66",
    "addr:postcode":"8020",
    "addr:street":"Kapellestraat",
    "iso:country":"BE",
    "sg:address":"Kapellestraat 66",
    "sg:city":"Oostkamp",
    "sg:classifiers":[
        {
            "category":"Personal",
            "subcategory":"Beauty Salon",
            "type":"Services"
        }
    ],
    "sg:phone":"+32 50 84 00 80",
    "sg:postcode":"8020",
    "sg:province":"West-Vlaanderen",
    "sg:tags":[
        "lady",
        "-",
        "hairdressing"
    ],
    "wof:name":"Filip Kapsalon",
    "wof:placetype":"venue"
},
  "geometry": {"coordinates":[3.2392439842,51.1513748169],"type":"Point"}
}