{
  "type": "Feature",
  "properties": {
    "addr:full":"Patrijzenstraat 22 Box 4 Kortenberg (everberg) Vlaams-Brabant 3078",
    "addr:housenumber":"22;4",
    "addr:postcode":"3078",
    "addr:street":"Patrijzenstraat;Box",
    "iso:country":"BE",
    "sg:address":"Patrijzenstraat 22 Box 4",
    "sg:city":"Kortenberg (everberg)",
    "sg:classifiers":[
        {
            "category":"Communications",
            "type":"Services"
        }
    ],
    "sg:phone":"+32 2 306 95 45",
    "sg:postcode":"3078",
    "sg:province":"Vlaams-Brabant",
    "sg:tags":[
        "translator"
    ],
    "wof:name":"Madame Grollmann Chambre Belge Des Traducteurs Asb Asbl",
    "wof:placetype":"venue"
},
  "geometry": {"coordinates":[4.5317020416,50.8714752197],"type":"Point"}
}