{
  "type": "Feature",
  "properties": {
    "iso:country":"BE",
    "sg:address":"Roze 81a",
    "sg:city":"Eeklo",
    "sg:classifiers":[
        {
            "category":"Food & Beverages",
            "subcategory":"Groceries & Convenience Stores",
            "type":"Retail Goods"
        }
    ],
    "sg:phone":"+32 9 378 51 71",
    "sg:postcode":"9900",
    "sg:province":"Oost-Vlaanderen",
    "sg:tags":[
        "grocer"
    ],
    "wof:name":"Kwibus",
    "wof:placetype":"venue"
},
  "geometry": {"coordinates":[3.5742239952,51.1892662048],"type":"Point"}
}