{
  "type": "Feature",
  "properties": {
    "iso:country":"BE",
    "sg:address":"Michiel Jansplein 40",
    "sg:city":"Lommel",
    "sg:classifiers":[
        {
            "category":"Community Center",
            "type":"Public Place"
        }
    ],
    "sg:phone":"+32 11 55 36 55",
    "sg:postcode":"3920",
    "sg:province":"Limburg",
    "sg:tags":[
        "medical"
    ],
    "wof:name":"Diagnosecentrum",
    "wof:placetype":"venue"
},
  "geometry": {"coordinates":[5.3157858849,51.2294387817],"type":"Point"}
}