{
  "type": "Feature",
  "properties": {
    "iso:country":"BE",
    "sg:address":"Hoogstraat 2",
    "sg:city":"Hamme",
    "sg:classifiers":[
        {
            "category":"Health Services",
            "subcategory":"Health Practitioner",
            "type":"Services"
        }
    ],
    "sg:phone":"+32 52 47 78 47",
    "sg:postcode":"9220",
    "sg:province":"Oost-Vlaanderen",
    "sg:tags":[
        "physiotherapist"
    ],
    "wof:name":"De Wilde Lut",
    "wof:placetype":"venue"
},
  "geometry": {"coordinates":[4.1331119537,51.0985527039],"type":"Point"}
}