{
  "type": "Feature",
  "properties": {
    "addr:full":"Rue De La Gare 36 Bertrix Luxembourg 6880",
    "addr:housenumber":"36",
    "addr:postcode":"6880",
    "addr:street":"Rue De La Gare",
    "iso:country":"BE",
    "sg:address":"Rue De La Gare 36",
    "sg:city":"Bertrix",
    "sg:orig_category":"Cr\u00e9dit \u00e0 la consommation",
    "sg:phone":"+32 61 41 33 92",
    "sg:postcode":"6880",
    "sg:province":"Luxembourg",
    "wof:name":"Cr\u00c9dit Pass",
    "wof:placetype":"venue"
},
  "geometry": {"coordinates":[5.2562689781,49.8548355103],"type":"Point"}
}