{
  "type": "Feature",
  "properties": {
    "addr:full":"Avenue Des Tilleuls 24 Bruxelles (uccle) Bruxelles-Capitale 1180",
    "addr:housenumber":"24",
    "addr:postcode":"1180",
    "addr:street":"Avenue Des Tilleuls",
    "iso:country":"BE",
    "sg:address":"Avenue Des Tilleuls 24",
    "sg:city":"Bruxelles (uccle)",
    "sg:classifiers":[
        {
            "category":"Arena",
            "subcategory":"Sports Club",
            "type":"Entertainment"
        }
    ],
    "sg:phone":"+32 2 372 07 39",
    "sg:postcode":"1180",
    "sg:province":"Bruxelles-Capitale",
    "sg:tags":[
        "federation"
    ],
    "wof:name":"F\u00e9d\u00e9ration Sportive De L'enseignement De La Communaut\u00e9 Fran\u00e7aise",
    "wof:placetype":"venue"
},
  "geometry": {"coordinates":[4.3390479088,50.7766151428],"type":"Point"}
}