{
  "type": "Feature",
  "properties": {
    "addr:full":"Missionarissenlaan 2 Anderlecht Bruxelles-Capitale 1070",
    "addr:housenumber":"2",
    "addr:postcode":"1070",
    "addr:street":"Missionarissenlaan",
    "iso:country":"BE",
    "sg:address":"Missionarissenlaan 2",
    "sg:city":"Anderlecht",
    "sg:classifiers":[
        {
            "category":"Insurance",
            "subcategory":"Insurance Agent",
            "type":"Services"
        }
    ],
    "sg:phone":"+32 2 411 24 37",
    "sg:postcode":"1070",
    "sg:province":"Bruxelles-Capitale",
    "sg:tags":[
        "verzekeringsmakelaars",
        "expert"
    ],
    "wof:name":"A.c.t.a. - Terrasi",
    "wof:placetype":"venue"
},
  "geometry": {"coordinates":[4.3076510429,50.8478317261],"type":"Point"}
}