{
  "type": "Feature",
  "properties": {
    "iso:country":"BE",
    "sg:address":"Kapellestraat 89",
    "sg:city":"Oostende",
    "sg:orig_category":"Base Shops. Mat\u00e9riel de T\u00e9l\u00e9communication",
    "sg:phone":"+32 59 80 86 05",
    "sg:postcode":"8400",
    "sg:province":"West-Vlaanderen",
    "wof:name":"Base Oostende",
    "wof:placetype":"venue"
},
  "geometry": {"coordinates":[2.9200849533,51.2288246155],"type":"Point"}
}