{
  "type": "Feature",
  "properties": {
    "addr:full":"Grote Baan 144 Sint-niklaas Oost-Vlaanderen 9100",
    "addr:housenumber":"144",
    "addr:postcode":"9100",
    "addr:street":"Grote Baan",
    "iso:country":"BE",
    "sg:address":"Grote Baan 144",
    "sg:city":"Sint-niklaas",
    "sg:orig_category":"Onderdelen and accessoires voertuigen Gh Onderdelen and accessoires voor auto's",
    "sg:phone":"+32 3 775 18 18",
    "sg:postcode":"9100",
    "sg:province":"Oost-Vlaanderen",
    "wof:name":"Trekhakencenter",
    "wof:placetype":"venue"
},
  "geometry": {"coordinates":[4.2033348083,51.1886978149],"type":"Point"}
}