{
  "type": "Feature",
  "properties": {
    "iso:country":"BE",
    "sg:address":"Rue De Mathon 43",
    "sg:city":"Rouvroy",
    "sg:orig_category":"Rundveehouders",
    "sg:phone":"+32 63 57 85 12",
    "sg:postcode":"6767",
    "sg:province":"Luxembourg",
    "wof:name":"Andre Veriter",
    "wof:placetype":"venue"
},
  "geometry": {"coordinates":[5.4905800819,49.5384864807],"type":"Point"}
}