{
  "type": "Feature",
  "properties": {
    "iso:country":"BE",
    "sg:address":"Keulsebaan 55",
    "sg:city":"Zandhoven",
    "sg:orig_category":"Dakwerken Loodgieterij, verwarming and sanitaire installaties",
    "sg:phone":"+32 3 464 00 65",
    "sg:postcode":"2243",
    "sg:province":"Antwerpen",
    "wof:name":"Nitor Jacques",
    "wof:placetype":"venue"
},
  "geometry": {"coordinates":[4.7150168419,51.2024841309],"type":"Point"}
}