{
  "type": "Feature",
  "properties": {
    "addr:full":"Koning Albertstraat 1 Kuurne West-Vlaanderen 8520",
    "addr:housenumber":"1",
    "addr:postcode":"8520",
    "addr:street":"Koning Albertstraat",
    "iso:country":"BE",
    "sg:address":"Koning Albertstraat 1",
    "sg:city":"Kuurne",
    "sg:orig_category":"Bijoux Fab. Bijouteries and horlogeries",
    "sg:phone":"+32 56 71 71 72",
    "sg:postcode":"8520",
    "sg:province":"West-Vlaanderen",
    "wof:name":"Francis Peelaers",
    "wof:placetype":"venue"
},
  "geometry": {"coordinates":[3.2870960236,50.852481842],"type":"Point"}
}