{
  "type": "Feature",
  "properties": {
    "iso:country":"BE",
    "sg:address":"Quartier Joseph Gailly 59",
    "sg:city":"Charleroi",
    "sg:classifiers":[
        {
            "category":"Arena",
            "subcategory":"Sports Club",
            "type":"Entertainment"
        }
    ],
    "sg:phone":"+32 71 41 91 12",
    "sg:postcode":"6060",
    "sg:province":"Hainaut",
    "sg:tags":[
        "de"
    ],
    "wof:name":"P.c. Les Gueules Noires",
    "wof:placetype":"venue"
},
  "geometry": {"coordinates":[4.4880981445,50.4251937866],"type":"Point"}
}