{
  "type": "Feature",
  "properties": {
    "iso:country":"BE",
    "sg:address":"Tuinwijklaan 37",
    "sg:city":"Kortrijk",
    "sg:orig_category":"Drogisterijen",
    "sg:phone":"+32 56 35 37 35",
    "sg:postcode":"8501",
    "sg:province":"West-Vlaanderen",
    "wof:name":"Jean-marie Verschueren",
    "wof:placetype":"venue"
},
  "geometry": {"coordinates":[3.2212510109,50.8210945129],"type":"Point"}
}