{
  "type": "Feature",
  "properties": {
    "iso:country":"BE",
    "sg:address":"Alfons Smetsplein 7",
    "sg:city":"Leuven",
    "sg:classifiers":[
        {
            "category":"Organizations",
            "subcategory":"Professional Association",
            "type":"Services"
        }
    ],
    "sg:phone":"+32 16 31 76 00",
    "sg:postcode":"3000",
    "sg:province":"Vlaams-Brabant",
    "sg:tags":[
        "organisation",
        "seminar"
    ],
    "wof:name":"Holiday Inn Garden Court",
    "wof:placetype":"venue"
},
  "geometry": {"coordinates":[4.7041230202,50.8772201538],"type":"Point"}
}