{
  "type": "Feature",
  "properties": {
    "addr:full":"Rue Du Bois 36 Charleroi Hainaut 6040",
    "addr:housenumber":"36",
    "addr:postcode":"6040",
    "addr:street":"Rue Du Bois;Hainaut",
    "iso:country":"BE",
    "sg:address":"Rue Du Bois 36",
    "sg:city":"Charleroi",
    "sg:orig_category":"Woningbouw",
    "sg:phone":"+32 71 34 15 09",
    "sg:postcode":"6040",
    "sg:province":"Hainaut",
    "wof:name":"Robert Pirard",
    "wof:placetype":"venue"
},
  "geometry": {"coordinates":[4.4514951706,50.4452476501],"type":"Point"}
}