{
  "type": "Feature",
  "properties": {
    "iso:country":"BE",
    "sg:address":"Rue Des Passages 23",
    "sg:city":"Mons",
    "sg:classifiers":[
        {
            "category":"Health Services",
            "subcategory":"Health Practitioner",
            "type":"Services"
        }
    ],
    "sg:phone":"+32 65 84 77 90",
    "sg:postcode":"7000",
    "sg:province":"Hainaut",
    "sg:tags":[
        "osteopath"
    ],
    "wof:name":"Gall\u00e9e B",
    "wof:placetype":"venue"
},
  "geometry": {"coordinates":[3.9564330578,50.4572906494],"type":"Point"}
}