{
  "type": "Feature",
  "properties": {
    "addr:full":"Waterleidingstraat 3e Heusden-zolder (heusden) Limburg 3550",
    "addr:housenumber":"3e",
    "addr:postcode":"3550",
    "addr:street":"Waterleidingstraat",
    "iso:country":"BE",
    "sg:address":"Waterleidingstraat 3e",
    "sg:city":"Heusden-zolder (heusden)",
    "sg:classifiers":[
        {
            "category":"Personal",
            "subcategory":"Beauty Salon",
            "type":"Services"
        }
    ],
    "sg:phone":"+32 11 57 19 73",
    "sg:postcode":"3550",
    "sg:province":"Limburg",
    "sg:tags":[
        "lady",
        "-",
        "hairdressing"
    ],
    "wof:name":"Haarmode Rc",
    "wof:placetype":"venue"
},
  "geometry": {"coordinates":[5.3021807671,51.0395812988],"type":"Point"}
}