{
  "type": "Feature",
  "properties": {
    "addr:full":"Grand'rue 26 Antoing Hainaut 7640",
    "addr:housenumber":"26",
    "addr:postcode":"7640",
    "addr:street":"Grand'Rue",
    "iso:country":"BE",
    "sg:address":"Grand'rue 26",
    "sg:city":"Antoing",
    "sg:orig_category":"Pain, p\u00e2tisseries and confiseries",
    "sg:phone":"+32 69 44 19 42",
    "sg:postcode":"7640",
    "sg:province":"Hainaut",
    "wof:name":"P. Van Tieghem",
    "wof:placetype":"venue"
},
  "geometry": {"coordinates":[3.4857099056,50.5479736328],"type":"Point"}
}