{
  "type": "Feature",
  "properties": {
    "iso:country":"BE",
    "sg:address":"Rue De Gorhez 64",
    "sg:city":"Aubel",
    "sg:orig_category":"Charpentes and couvertures",
    "sg:phone":"+32 87 68 82 38",
    "sg:postcode":"4880",
    "sg:province":"Li\u00e8ge",
    "wof:name":"B Delhez",
    "wof:placetype":"venue"
},
  "geometry": {"coordinates":[5.8502721786,50.703037262],"type":"Point"}
}