{
  "type": "Feature",
  "properties": {
    "addr:full":"Avenue Montjoie 245 Bruxelles-forest Bruxelles-Capitale 1190",
    "addr:housenumber":"245",
    "addr:postcode":"1190",
    "addr:street":"Avenue Montjoie",
    "iso:country":"BE",
    "sg:address":"Avenue Montjoie 245",
    "sg:city":"Bruxelles-forest",
    "sg:classifiers":[
        {
            "category":"Professional",
            "subcategory":"Computer Services",
            "type":"Services"
        }
    ],
    "sg:phone":"+32 2 333 20 33",
    "sg:postcode":"1190",
    "sg:province":"Bruxelles-Capitale",
    "sg:tags":[
        "informaticaconsulent",
        "fab",
        "diverse",
        "computerapparatuur",
        "informatica-activiteiten"
    ],
    "wof:name":"Add X Computers",
    "wof:placetype":"venue"
},
  "geometry": {"coordinates":[4.3179168701,50.8105926514],"type":"Point"}
}