{
  "type": "Feature",
  "properties": {
    "iso:country":"BE",
    "sg:address":"Rue De Branchon 124",
    "sg:city":"Fernelmont",
    "sg:orig_category":"G\u00e9om\u00e8tres",
    "sg:phone":"+32 81 83 01 53",
    "sg:postcode":"5380",
    "sg:province":"Namur",
    "wof:name":"B. Dufour",
    "wof:placetype":"venue"
},
  "geometry": {"coordinates":[4.9861078262,50.5531463623],"type":"Point"}
}