{
  "type": "Feature",
  "properties": {
    "addr:full":"Rue De La Liberation 48 Sambreville Namur 5060",
    "addr:housenumber":"48",
    "addr:postcode":"5060",
    "addr:street":"Rue De La Liberation",
    "iso:country":"BE",
    "sg:address":"Rue De La Liberation 48",
    "sg:city":"Sambreville",
    "sg:orig_category":"Tijdelijke werkgelegenheid and uitzendkantoren",
    "sg:phone":"+32 71 26 99 20",
    "sg:postcode":"5060",
    "sg:province":"Namur",
    "wof:name":"Adecco",
    "wof:placetype":"venue"
},
  "geometry": {"coordinates":[4.6285200119,50.4448738098],"type":"Point"}
}