{
  "type": "Feature",
  "properties": {
    "addr:full":"Rue Champ Du Roi 145 Bruxelles (etterbeek) Bruxelles-Capitale 1040",
    "addr:housenumber":"145",
    "addr:postcode":"1040",
    "addr:street":"Rue Champ Du Roi",
    "iso:country":"BE",
    "sg:address":"Rue Champ Du Roi 145",
    "sg:city":"Bruxelles (etterbeek)",
    "sg:classifiers":[
        {
            "category":"Education",
            "subcategory":"Special Training",
            "type":"Public Place"
        }
    ],
    "sg:phone":"+32 9 244 64 64",
    "sg:postcode":"1040",
    "sg:province":"Bruxelles-Capitale",
    "sg:tags":[
        "school",
        "language"
    ],
    "wof:name":"Lerian Communications",
    "wof:placetype":"venue"
},
  "geometry": {"coordinates":[4.3939499855,50.8360099792],"type":"Point"}
}