{
  "type": "Feature",
  "properties": {
    "addr:full":"Gelmelstraat 121 Hoogstraten Antwerpen 2320",
    "addr:housenumber":"121",
    "addr:postcode":"2320",
    "addr:street":"Gelmelstraat",
    "iso:country":"BE",
    "sg:address":"Gelmelstraat 121",
    "sg:city":"Hoogstraten",
    "sg:orig_category":"Catering and organisatie van feesten",
    "sg:phone":"+32 3 314 80 44",
    "sg:postcode":"2320",
    "sg:province":"Antwerpen",
    "wof:name":"Traiteur Roelen-aerts",
    "wof:placetype":"venue"
},
  "geometry": {"coordinates":[4.7736339569,51.4032669067],"type":"Point"}
}