{
  "type": "Feature",
  "properties": {
    "iso:country":"BE",
    "sg:address":"Hondstraat 81",
    "sg:city":"Tielt",
    "sg:orig_category":"Antiek",
    "sg:phone":"+32 51 40 21 52",
    "sg:postcode":"8700",
    "sg:province":"West-Vlaanderen",
    "wof:name":"Fine Art Spectrum",
    "wof:placetype":"venue"
},
  "geometry": {"coordinates":[3.3091919422,51.0023155212],"type":"Point"}
}