{
  "type": "Feature",
  "properties": {
    "iso:country":"BE",
    "sg:address":"Keizerskamp 2",
    "sg:city":"Dilsen-stokkem",
    "sg:orig_category":"Brood, gebak and snoepgoed",
    "sg:phone":"+32 89 57 22 19",
    "sg:postcode":"3650",
    "sg:province":"Limburg",
    "wof:name":"Micheline Geerts",
    "wof:placetype":"venue"
},
  "geometry": {"coordinates":[5.727396965,51.0364189148],"type":"Point"}
}