{
  "type": "Feature",
  "properties": {
    "iso:country":"BE",
    "sg:address":"Square Charles-maurice Wiser 9",
    "sg:city":"Bruxelles (etterbeek)",
    "sg:classifiers":[
        {
            "category":"Insurance",
            "subcategory":"Insurance Agent",
            "type":"Services"
        }
    ],
    "sg:phone":"+32 2 230 31 18",
    "sg:postcode":"1040",
    "sg:province":"Bruxelles-Capitale",
    "sg:tags":[
        "broker"
    ],
    "wof:name":"Benetatos",
    "wof:placetype":"venue"
},
  "geometry": {"coordinates":[4.3855400085,50.8385925293],"type":"Point"}
}