{
  "type": "Feature",
  "properties": {
    "iso:country":"BE",
    "sg:address":"Rue De Chaudfontaine 1",
    "sg:city":"Li\u00c8ge",
    "sg:orig_category":"Belastingconsulenten Boekhouders Diverse juridische dienstverlening",
    "sg:phone":"+32 4 342 43 21",
    "sg:postcode":"4020",
    "sg:province":"Li\u00e8ge",
    "wof:name":"Bureau Van Romphey",
    "wof:placetype":"venue"
},
  "geometry": {"coordinates":[5.5845680237,50.6216964722],"type":"Point"}
}