{
  "type": "Feature",
  "properties": {
    "iso:country":"BE",
    "sg:address":"Rue Dampremy 10",
    "sg:city":"Charleroi",
    "sg:orig_category":"Beautyfarms, relaxatie and lichamelijk welzijn Cosmetica and toiletartikelen Schoonheidssalons",
    "sg:phone":"+32 71 32 53 54",
    "sg:postcode":"6000",
    "sg:province":"Hainaut",
    "wof:name":"Planet Parfum",
    "wof:placetype":"venue"
},
  "geometry": {"coordinates":[4.442073822,50.4086761475],"type":"Point"}
}