{
  "type": "Feature",
  "properties": {
    "addr:full":"Veurnseweg 550 Ieper (elverdinge) West-Vlaanderen 8906",
    "addr:housenumber":"550",
    "addr:postcode":"8906",
    "addr:street":"Veurnseweg",
    "iso:country":"BE",
    "sg:address":"Veurnseweg 550",
    "sg:city":"Ieper (elverdinge)",
    "sg:classifiers":[
        {
            "category":"Bars & Pubs",
            "type":"Food & Drink"
        }
    ],
    "sg:phone":"+32 57 42 10 37",
    "sg:postcode":"8906",
    "sg:province":"West-Vlaanderen",
    "wof:name":"Leeuw Van Vlaanderen",
    "wof:placetype":"venue"
},
  "geometry": {"coordinates":[2.8170580864,50.885974884],"type":"Point"}
}