{
  "type": "Feature",
  "properties": {
    "addr:full":"Rue Paul Janson 271ba Grace-hollogne Li\u00e8ge 4460",
    "addr:postcode":"4460",
    "addr:street":"Rue Paul Janson 271Ba",
    "iso:country":"BE",
    "sg:address":"Rue Paul Janson 271ba",
    "sg:city":"Grace-hollogne",
    "sg:orig_category":"Ordinateurs and \u00e9quipement informatique",
    "sg:phone":"+32 4 234 45 34",
    "sg:postcode":"4460",
    "sg:province":"Li\u00e8ge",
    "wof:name":"Alfonso Camizzi",
    "wof:placetype":"venue"
},
  "geometry": {"coordinates":[5.5010738373,50.6271209717],"type":"Point"}
}