{
  "type": "Feature",
  "properties": {
    "addr:full":"Rue Marcel Vandy 45 Namur Namur 5020",
    "addr:housenumber":"45",
    "addr:postcode":"5020",
    "addr:street":"Rue Marcel Vandy",
    "iso:country":"BE",
    "sg:address":"Rue Marcel Vandy 45",
    "sg:city":"Namur",
    "sg:classifiers":[
        {
            "category":"Cafe",
            "type":"Food & Drink"
        }
    ],
    "sg:phone":"+32 81 73 98 85",
    "sg:postcode":"5020",
    "sg:province":"Namur",
    "sg:tags":[
        "caf\u00e9s"
    ],
    "wof:name":"Caf\u00c9 Le Central",
    "wof:placetype":"venue"
},
  "geometry": {"coordinates":[4.7952418327,50.4352035522],"type":"Point"}
}