{
  "type": "Feature",
  "properties": {
    "addr:full":"Forelstraat 129 Gent Oost-Vlaanderen 9000",
    "addr:housenumber":"129",
    "addr:postcode":"9000",
    "addr:street":"Forelstraat;Oost-Vlaanderen",
    "iso:country":"BE",
    "sg:address":"Forelstraat 129",
    "sg:city":"Gent",
    "sg:orig_category":"M\u00e9decins and sp\u00e9cialistes",
    "sg:phone":"+32 9 224 14 70",
    "sg:postcode":"9000",
    "sg:province":"Oost-Vlaanderen",
    "wof:name":"Ines Vanderlinden",
    "wof:placetype":"venue"
},
  "geometry": {"coordinates":[3.7429299355,51.0486907959],"type":"Point"}
}