{
  "type": "Feature",
  "properties": {
    "addr:full":"Rue Haute 15 Rebecq Brabant Wallon 1430",
    "addr:housenumber":"15",
    "addr:postcode":"1430",
    "addr:street":"Rue Haute",
    "iso:country":"BE",
    "sg:address":"Rue Haute 15",
    "sg:city":"Rebecq",
    "sg:orig_category":"Loodgieterij, verwarming and sanitaire installaties",
    "sg:phone":"+32 67 67 09 50",
    "sg:postcode":"1430",
    "sg:province":"Brabant Wallon",
    "wof:name":"Christian Pletinckx",
    "wof:placetype":"venue"
},
  "geometry": {"coordinates":[4.1304402351,50.6486129761],"type":"Point"}
}