{
  "type": "Feature",
  "properties": {
    "iso:country":"BE",
    "sg:address":"Kardinaal Cardijnplein 12b3",
    "sg:city":"Berlaar",
    "sg:orig_category":"Rev\u00eatements de sols and murs. Rev\u00eatements pour sols and murs",
    "sg:phone":"+32 15 24 42 95",
    "sg:postcode":"2590",
    "sg:province":"Antwerpen",
    "wof:name":"Fleerackers-pauwels",
    "wof:placetype":"venue"
},
  "geometry": {"coordinates":[4.6698141098,51.0828132629],"type":"Point"}
}