{
  "type": "Feature",
  "properties": {
    "addr:full":"Dorp 35 Wichelen Oost-Vlaanderen 9260",
    "addr:housenumber":"35",
    "addr:postcode":"9260",
    "addr:street":"Dorp",
    "iso:country":"BE",
    "sg:address":"Dorp 35",
    "sg:city":"Wichelen",
    "sg:classifiers":[
        {
            "category":"Personal",
            "subcategory":"Beauty Salon",
            "type":"Services"
        }
    ],
    "sg:phone":"+32 52 42 61 40",
    "sg:postcode":"9260",
    "sg:province":"Oost-Vlaanderen",
    "sg:tags":[
        "lady",
        "-",
        "hairdressing"
    ],
    "wof:name":"Veerle",
    "wof:placetype":"venue"
},
  "geometry": {"coordinates":[3.9710299969,51.0123062134],"type":"Point"}
}