{
  "type": "Feature",
  "properties": {
    "addr:full":"Bamburgstraat 16 Middelkerke West-Vlaanderen 8434",
    "addr:housenumber":"16",
    "addr:postcode":"8434",
    "addr:street":"Bamburgstraat",
    "iso:country":"BE",
    "sg:address":"Bamburgstraat 16",
    "sg:city":"Middelkerke",
    "sg:orig_category":"Etalage- and showroomontwerpers",
    "sg:phone":"+32 58 23 57 94",
    "sg:postcode":"8434",
    "sg:province":"West-Vlaanderen",
    "wof:name":"Wendy Deramoudt",
    "wof:placetype":"venue"
},
  "geometry": {"coordinates":[2.758024931,51.1485900879],"type":"Point"}
}