{
  "type": "Feature",
  "properties": {
    "iso:country":"BE",
    "sg:address":"Schuitje 12",
    "sg:city":"Berlare",
    "sg:classifiers":[
        {
            "category":"Food & Beverages",
            "subcategory":"Specialty",
            "type":"Retail Goods"
        }
    ],
    "sg:phone":"+32 52 42 35 57",
    "sg:postcode":"9290",
    "sg:province":"Oost-Vlaanderen",
    "sg:tags":[
        "health",
        "dietary",
        "-",
        "biological"
    ],
    "wof:name":"Schuitje (op 't)",
    "wof:placetype":"venue"
},
  "geometry": {"coordinates":[4.0074129105,51.0366172791],"type":"Point"}
}