{
  "type": "Feature",
  "properties": {
    "iso:country":"BE",
    "sg:address":"Rue Du Bois L\u00e0 Haut 15",
    "sg:city":"Mons",
    "sg:classifiers":[
        {
            "category":"Professional",
            "subcategory":"Accounting & Tax Preparation",
            "type":"Services"
        }
    ],
    "sg:phone":"+32 65 33 56 67",
    "sg:postcode":"7000",
    "sg:province":"Hainaut",
    "sg:tags":[
        "accountant"
    ],
    "wof:name":"Philippart A",
    "wof:placetype":"venue"
},
  "geometry": {"coordinates":[3.9842228889,50.4434204102],"type":"Point"}
}