{
  "type": "Feature",
  "properties": {
    "iso:country":"BE",
    "sg:address":"Rue Du Paradis 49",
    "sg:city":"Brunehaut",
    "sg:orig_category":"Bloemen and planten Tuinen",
    "sg:phone":"+32 69 34 68 00",
    "sg:postcode":"7621",
    "sg:province":"Hainaut",
    "wof:name":"Maison Les Rocailles",
    "wof:placetype":"venue"
},
  "geometry": {"coordinates":[3.3875288963,50.5227890015],"type":"Point"}
}