{
  "type": "Feature",
  "properties": {
    "iso:country":"BE",
    "sg:address":"Cathilleweg 36",
    "sg:city":"Jabbeke (stalhille)",
    "sg:classifiers":[
        {
            "category":"Building & Trades",
            "subcategory":"Cleaning & Sanitation",
            "type":"Services"
        }
    ],
    "sg:phone":"+32 50 81 59 39",
    "sg:postcode":"8490",
    "sg:province":"West-Vlaanderen",
    "sg:tags":[
        "janitor"
    ],
    "wof:name":"Veranda Clean",
    "wof:placetype":"venue"
},
  "geometry": {"coordinates":[3.0756220818,51.2103500366],"type":"Point"}
}