{
  "type": "Feature",
  "properties": {
    "addr:full":"Luikersteenweg 330 A Hasselt Limburg 3500",
    "addr:housenumber":"330 a",
    "addr:postcode":"3500",
    "addr:street":"Luikersteenweg",
    "iso:country":"BE",
    "sg:address":"Luikersteenweg 330 A",
    "sg:city":"Hasselt",
    "sg:orig_category":"Ordinateurs and \u00e9quipement informatique",
    "sg:phone":"+32 11 28 47 08",
    "sg:postcode":"3500",
    "sg:province":"Limburg",
    "wof:name":"Logotec Engineering",
    "wof:placetype":"venue"
},
  "geometry": {"coordinates":[5.3548398018,50.909450531],"type":"Point"}
}