{
  "type": "Feature",
  "properties": {
    "iso:country":"BE",
    "sg:address":"Zeelaan 212",
    "sg:city":"Koksijde",
    "sg:classifiers":[
        {
            "category":"Real Estate",
            "subcategory":"Real Estate Services",
            "type":"Services"
        }
    ],
    "sg:phone":"+32 58 51 28 47",
    "sg:postcode":"8670",
    "sg:province":"West-Vlaanderen",
    "wof:name":"Agence Immo Europe",
    "wof:placetype":"venue"
},
  "geometry": {"coordinates":[2.6370060444,51.117401123],"type":"Point"}
}