{
  "type": "Feature",
  "properties": {
    "iso:country":"BE",
    "sg:address":"Kleine Omstraat 11",
    "sg:city":"Lanaken (veldwezelt)",
    "sg:classifiers":[
        {
            "category":"Shopping",
            "subcategory":"Florist",
            "type":"Retail Goods"
        }
    ],
    "sg:phone":"+32 89 71 46 72",
    "sg:postcode":"3620",
    "sg:province":"Limburg",
    "wof:name":"Bloemenweelde",
    "wof:placetype":"venue"
},
  "geometry": {"coordinates":[5.6266732216,50.8866767883],"type":"Point"}
}