{
  "type": "Feature",
  "properties": {
    "addr:full":"Musketstraat 100 Herentals Antwerpen 2200",
    "addr:housenumber":"100",
    "addr:postcode":"2200",
    "addr:street":"Musketstraat",
    "iso:country":"BE",
    "sg:address":"Musketstraat 100",
    "sg:city":"Herentals",
    "sg:orig_category":"Maatschappelijke dienstverlening",
    "sg:phone":"+32 14 22 08 81",
    "sg:postcode":"2200",
    "sg:province":"Antwerpen",
    "wof:name":"Jip",
    "wof:placetype":"venue"
},
  "geometry": {"coordinates":[4.8576359749,51.1806221008],"type":"Point"}
}