{
  "type": "Feature",
  "properties": {
    "addr:full":"Oude Zandstraat 25 Beveren (beveren-waas) Oost-Vlaanderen 9120",
    "addr:housenumber":"25",
    "addr:postcode":"9120",
    "addr:street":"Oude Zandstraat;Oost-Vlaanderen",
    "iso:country":"BE",
    "sg:address":"Oude Zandstraat 25",
    "sg:city":"Beveren (beveren-waas)",
    "sg:classifiers":[
        {
            "category":"Retail",
            "subcategory":"Auto Repair",
            "type":"Services"
        }
    ],
    "sg:phone":"+32 3 750 95 00",
    "sg:postcode":"9120",
    "sg:province":"Oost-Vlaanderen",
    "sg:tags":[
        "garage"
    ],
    "wof:name":"Houttequiet",
    "wof:placetype":"venue"
},
  "geometry": {"coordinates":[4.2539968491,51.2119445801],"type":"Point"}
}