{
  "type": "Feature",
  "properties": {
    "addr:full":"Koning Albertstraat 173 Veldegem West-Vlaanderen 8210",
    "addr:housenumber":"173",
    "addr:postcode":"8210",
    "addr:street":"Koning Albertstraat;West-Vlaanderen",
    "iso:country":"BE",
    "sg:address":"Koning Albertstraat 173",
    "sg:city":"Veldegem",
    "sg:classifiers":[
        {
            "category":"Manufacturing",
            "subcategory":"Metals",
            "type":"Manufacturing & Wholesale Goods"
        }
    ],
    "sg:phone":"+32 50 27 93 89",
    "sg:postcode":"8210",
    "sg:province":"West-Vlaanderen",
    "sg:tags":[
        "metallurgy",
        "steel",
        "metalworking"
    ],
    "wof:name":"Decloedt-decov Nv",
    "wof:placetype":"venue"
},
  "geometry": {"coordinates":[3.1473579407,51.1105766296],"type":"Point"}
}