{
  "type": "Feature",
  "properties": {
    "addr:full":"Jukschot 27 Zoersel Antwerpen 2980",
    "addr:housenumber":"27",
    "addr:postcode":"2980",
    "addr:street":"Jukschot",
    "iso:country":"BE",
    "sg:address":"Jukschot 27",
    "sg:city":"Zoersel",
    "sg:orig_category":"Elektrische installaties voor woningen Industri\u00eble elektrische installaties",
    "sg:phone":"+32 3 383 55 30",
    "sg:postcode":"2980",
    "sg:province":"Antwerpen",
    "wof:name":"E.b.m.",
    "wof:placetype":"venue"
},
  "geometry": {"coordinates":[4.713435173,51.269985199],"type":"Point"}
}