{
  "type": "Feature",
  "properties": {
    "iso:country":"BE",
    "sg:address":"De Wandstraat 275",
    "sg:city":"Brussel/bruxelles",
    "sg:orig_category":"Brood, gebak and snoepgoed",
    "sg:phone":"+32 2 262 08 33",
    "sg:postcode":"1020",
    "sg:province":"Bruxelles-Capitale",
    "wof:name":"Jos De Freyne",
    "wof:placetype":"venue"
},
  "geometry": {"coordinates":[4.3605909348,50.9011192322],"type":"Point"}
}