{
  "type": "Feature",
  "properties": {
    "addr:full":"Zandpoortvest 29 Mechelen Antwerpen 2800",
    "addr:housenumber":"29",
    "addr:postcode":"2800",
    "addr:street":"Zandpoortvest",
    "iso:country":"BE",
    "sg:address":"Zandpoortvest 29",
    "sg:city":"Mechelen",
    "sg:orig_category":"Electrom\u00e9nager, t\u00e9l\u00e9visions and radios. R\u00e9parations d'appareils \u00e9lectrom\u00e9nagers",
    "sg:phone":"+32 15 21 15 90",
    "sg:postcode":"2800",
    "sg:province":"Antwerpen",
    "wof:name":"T.v. Sneldienst",
    "wof:placetype":"venue"
},
  "geometry": {"coordinates":[4.486869812,51.0222206116],"type":"Point"}
}