{
  "type": "Feature",
  "properties": {
    "addr:full":"Chauss\u00e9e De Grammont 19 Ath (ghislenghien) Hainaut 7822",
    "addr:housenumber":"19",
    "addr:postcode":"7822",
    "addr:street":"Chausse\u0301E De Grammont",
    "iso:country":"BE",
    "sg:address":"Chauss\u00e9e De Grammont 19",
    "sg:city":"Ath (ghislenghien)",
    "sg:classifiers":[
        {
            "category":"Shopping",
            "subcategory":"Books",
            "type":"Retail Goods"
        }
    ],
    "sg:phone":"+32 68 55 29 11",
    "sg:postcode":"7822",
    "sg:province":"Hainaut",
    "sg:tags":[
        "bookseller"
    ],
    "wof:name":"Demitri",
    "wof:placetype":"venue"
},
  "geometry": {"coordinates":[3.8731050491,50.6590881348],"type":"Point"}
}