{
  "type": "Feature",
  "properties": {
    "addr:full":"Rue De Serinchamps 6 Somme-leuze (hogne) Namur 5377",
    "addr:housenumber":"6",
    "addr:postcode":"5377",
    "addr:street":"Rue De Serinchamps;Hogne",
    "iso:country":"BE",
    "sg:address":"Rue De Serinchamps 6",
    "sg:city":"Somme-leuze (hogne)",
    "sg:classifiers":[
        {
            "category":"Health Services",
            "subcategory":"Health Practitioner",
            "type":"Services"
        }
    ],
    "sg:phone":"+32 84 31 54 34",
    "sg:postcode":"5377",
    "sg:province":"Namur",
    "sg:tags":[
        "physiotherapist"
    ],
    "wof:name":"Borsus Claude",
    "wof:placetype":"venue"
},
  "geometry": {"coordinates":[5.2740750313,50.2465896606],"type":"Point"}
}