{
  "type": "Feature",
  "properties": {
    "addr:full":"Rue Saint-martin 41 Tournai Hainaut 7500",
    "addr:housenumber":"41",
    "addr:postcode":"7500",
    "addr:street":"Rue Saint-Martin",
    "iso:country":"BE",
    "sg:address":"Rue Saint-martin 41",
    "sg:city":"Tournai",
    "sg:classifiers":[
        {
            "category":"Personal",
            "subcategory":"Beauty Salon",
            "type":"Services"
        }
    ],
    "sg:phone":"+32 69 22 37 95",
    "sg:postcode":"7500",
    "sg:province":"Hainaut",
    "sg:tags":[
        "de",
        "coiffure"
    ],
    "wof:name":"Coiffure Metamorphose",
    "wof:placetype":"venue"
},
  "geometry": {"coordinates":[3.3868250847,50.6046714783],"type":"Point"}
}