{
  "type": "Feature",
  "properties": {
    "iso:country":"BE",
    "sg:address":"Cyriel De Grootelaan 2",
    "sg:city":"Middelkerke",
    "sg:orig_category":"S\u00e9curit\u00e9 sociale",
    "sg:phone":"+32 59 30 06 73",
    "sg:postcode":"8430",
    "sg:province":"West-Vlaanderen",
    "wof:name":"Vlaams Neutraal Ziekenf.",
    "wof:placetype":"venue"
},
  "geometry": {"coordinates":[2.8197600842,51.1882514954],"type":"Point"}
}