{
  "type": "Feature",
  "properties": {
    "iso:country":"BE",
    "sg:address":"Kalfvaart 1",
    "sg:city":"Ieper",
    "sg:classifiers":[
        {
            "category":"Insurance",
            "subcategory":"Life Insurance",
            "type":"Services"
        }
    ],
    "sg:phone":"+32 57 20 87 70",
    "sg:postcode":"8900",
    "sg:province":"West-Vlaanderen",
    "sg:tags":[
        "assurance"
    ],
    "wof:name":"Willaert Stephan",
    "wof:placetype":"venue"
},
  "geometry": {"coordinates":[2.8903479576,50.8558120728],"type":"Point"}
}