{
  "type": "Feature",
  "properties": {
    "iso:country":"BE",
    "sg:address":"Rue De L'arsenal 7bbis",
    "sg:city":"Tournai",
    "sg:orig_category":"Gedistilleerde dranken and aperitieven Fab Wijnen Fab",
    "sg:phone":"+32 69 22 20 51",
    "sg:postcode":"7500",
    "sg:province":"Hainaut",
    "wof:name":"Dubois",
    "wof:placetype":"venue"
},
  "geometry": {"coordinates":[3.3858840466,50.6124534607],"type":"Point"}
}