{
  "type": "Feature",
  "properties": {
    "iso:country":"BE",
    "sg:address":"Gentstraat 36",
    "sg:city":"Meulebeke",
    "sg:orig_category":"Imprimeries and copyshops",
    "sg:phone":"+32 51 48 72 23",
    "sg:postcode":"8760",
    "sg:province":"West-Vlaanderen",
    "wof:name":"Drukkerij Verkest",
    "wof:placetype":"venue"
},
  "geometry": {"coordinates":[3.2936589718,50.9483909607],"type":"Point"}
}