{
  "type": "Feature",
  "properties": {
    "addr:full":"I.p. Drongen 6k Drongen Oost-Vlaanderen 9031",
    "addr:postcode":"9031",
    "addr:street":"Oost-Vlaanderen",
    "iso:country":"BE",
    "sg:address":"I.p. Drongen 6k",
    "sg:city":"Drongen",
    "sg:classifiers":[
        {
            "category":"Recreation",
            "subcategory":"Boat Charter",
            "type":"Entertainment"
        }
    ],
    "sg:phone":"+32 3 646 80 62",
    "sg:postcode":"9031",
    "sg:province":"Oost-Vlaanderen",
    "sg:tags":[
        "engine"
    ],
    "wof:name":"F.s. Dieselengineering Bvba",
    "wof:placetype":"venue"
},
  "geometry": {"coordinates":[4.4452438354,51.2516822815],"type":"Point"}
}