{
  "type": "Feature",
  "properties": {
    "addr:full":"A. Greinerstraat 12 Antwerpen 2660 ",
    "addr:housenumber":"12",
    "addr:postcode":"2660",
    "addr:street":"A. Greinerstraat",
    "iso:country":"BE",
    "sg:address":"A. Greinerstraat 12",
    "sg:city":"Antwerpen",
    "sg:classifiers":[
        {
            "category":"Professional",
            "subcategory":"Computer Services",
            "type":"Services"
        }
    ],
    "sg:postcode":"2660 ",
    "sg:website":"http://10to1.be",
    "wof:name":"10to1",
    "wof:placetype":"venue"
},
  "geometry": {"coordinates":[4.3353896,51.1710646],"type":"Point"}
}