{
  "type": "Feature",
  "properties": {
    "addr:full":"Rue Du Rouge Bouton 39 Braine-le-comte Hainaut 7090",
    "addr:housenumber":"39",
    "addr:postcode":"7090",
    "addr:street":"Rue Du Rouge Bouton",
    "iso:country":"BE",
    "sg:address":"Rue Du Rouge Bouton 39",
    "sg:city":"Braine-le-comte",
    "sg:orig_category":"Dierenartsen",
    "sg:phone":"+32 67 64 91 40",
    "sg:postcode":"7090",
    "sg:province":"Hainaut",
    "wof:name":"Anne Marcotte",
    "wof:placetype":"venue"
},
  "geometry": {"coordinates":[4.2025108337,50.6487083435],"type":"Point"}
}