{
  "type": "Feature",
  "properties": {
    "iso:country":"BE",
    "sg:address":"Meensesteenweg 260",
    "sg:city":"Moorslede (dadizele)",
    "sg:orig_category":"Non-Classified Establishments",
    "sg:phone":"+32 56 50 12 33",
    "sg:postcode":"8890",
    "sg:province":"West-Vlaanderen",
    "wof:name":"Agriplant Nv",
    "wof:placetype":"venue"
},
  "geometry": {"coordinates":[3.112776041,50.8397102356],"type":"Point"}
}