{
  "type": "Feature",
  "properties": {
    "addr:full":"Chemin Des Naux 21 Meix-devant-virton Luxembourg 6769",
    "addr:housenumber":"21",
    "addr:postcode":"6769",
    "addr:street":"Chemin Des Naux",
    "iso:country":"BE",
    "sg:address":"Chemin Des Naux 21",
    "sg:city":"Meix-devant-virton",
    "sg:orig_category":"Installation \u00e9lectrique r\u00e9sidentielle",
    "sg:phone":"+32 63 57 62 50",
    "sg:postcode":"6769",
    "sg:province":"Luxembourg",
    "wof:name":"Christian Dubois",
    "wof:placetype":"venue"
},
  "geometry": {"coordinates":[5.4800958633,49.6040344238],"type":"Point"}
}