{
  "type": "Feature",
  "properties": {
    "addr:full":"Rue Charles Lejeune 6 Waremme Li\u00e8ge 4300",
    "addr:housenumber":"6",
    "addr:postcode":"4300",
    "addr:street":"Rue Charles Lejeune",
    "iso:country":"BE",
    "sg:address":"Rue Charles Lejeune 6",
    "sg:city":"Waremme",
    "sg:classifiers":[
        {
            "category":"Health Services",
            "subcategory":"Dentist",
            "type":"Services"
        }
    ],
    "sg:phone":"+32 19 32 23 05",
    "sg:postcode":"4300",
    "sg:province":"Li\u00e8ge",
    "wof:name":"Caudron D",
    "wof:placetype":"venue"
},
  "geometry": {"coordinates":[5.2567191124,50.6969718933],"type":"Point"}
}