{
  "type": "Feature",
  "properties": {
    "addr:full":"Molenstraat 12ba Aalst Oost-Vlaanderen 9320",
    "addr:housenumber":"12ba",
    "addr:postcode":"9320",
    "addr:street":"Molenstraat",
    "iso:country":"BE",
    "sg:address":"Molenstraat 12ba",
    "sg:city":"Aalst",
    "sg:orig_category":"Banques and organismes de cr\u00e9dit",
    "sg:phone":"+32 53 84 15 33",
    "sg:postcode":"9320",
    "sg:province":"Oost-Vlaanderen",
    "wof:name":"Groep Argenta",
    "wof:placetype":"venue"
},
  "geometry": {"coordinates":[4.0398221016,50.9387893677],"type":"Point"}
}