{
  "type": "Feature",
  "properties": {
    "addr:full":"Sint-antoniusstraat 16 Dentergem West-Vlaanderen 8720",
    "addr:housenumber":"16",
    "addr:postcode":"8720",
    "addr:street":"Sint-Antoniusstraat",
    "iso:country":"BE",
    "sg:address":"Sint-antoniusstraat 16",
    "sg:city":"Dentergem",
    "sg:orig_category":"Elektrische installaties voor woningen",
    "sg:phone":"+32 56 61 00 75",
    "sg:postcode":"8720",
    "sg:province":"West-Vlaanderen",
    "wof:name":"Danny Ninclaus",
    "wof:placetype":"venue"
},
  "geometry": {"coordinates":[3.3941500187,50.9314956665],"type":"Point"}
}