{
  "type": "Feature",
  "properties": {
    "addr:full":"Avenue Des Mille M\u00e8tres 42 Bruxelles (woluwe-saint-pierre) Bruxelles-Capitale 1150",
    "addr:housenumber":"42",
    "addr:postcode":"1150",
    "addr:street":"Avenue Des Mille Me\u0300Tres",
    "iso:country":"BE",
    "sg:address":"Avenue Des Mille M\u00e8tres 42",
    "sg:city":"Bruxelles (woluwe-saint-pierre)",
    "sg:classifiers":[
        {
            "category":"Government",
            "subcategory":"Post Office",
            "type":"Public Place"
        }
    ],
    "sg:phone":"+32 2 770 01 05",
    "sg:postcode":"1150",
    "sg:province":"Bruxelles-Capitale",
    "sg:tags":[
        "parkinggarages",
        "access",
        "-",
        "installation"
    ],
    "wof:name":"Atelier Ergo",
    "wof:placetype":"venue"
},
  "geometry": {"coordinates":[4.4602351189,50.8346443176],"type":"Point"}
}