{
  "type": "Feature",
  "properties": {
    "iso:country":"BE",
    "sg:address":"Quai Des Usines 5-9",
    "sg:city":"Bruxelles",
    "sg:classifiers":[
        {
            "category":"Home & Garden",
            "subcategory":"Hardware",
            "type":"Retail Goods"
        }
    ],
    "sg:phone":"+32 2 274 54 54",
    "sg:postcode":"1000",
    "sg:province":"Bruxelles-Capitale",
    "sg:tags":[
        "soldering",
        "equipment",
        "welding",
        "-",
        "supply"
    ],
    "wof:name":"Clabots",
    "wof:placetype":"venue"
},
  "geometry": {"coordinates":[4.3609452248,50.872505188],"type":"Point"}
}