{
  "type": "Feature",
  "properties": {
    "iso:country":"BE",
    "sg:address":"709",
    "sg:city":"Brucargo 1931 Zaventem Brucargo",
    "sg:classifiers":[
        {
            "category":"Banks & Credit Unions",
            "subcategory":"Investment Brokerage",
            "type":"Services"
        }
    ],
    "sg:phone":"+32 2 753 53 35",
    "sg:postcode":"709",
    "sg:tags":[
        "-",
        "transport",
        "related"
    ],
    "wof:name":"May Courier International Bvba",
    "wof:placetype":"venue"
},
  "geometry": {"coordinates":[4.4787201881,50.8683013916],"type":"Point"}
}