{
  "type": "Feature",
  "properties": {
    "addr:full":"Dauw-defossezlaan 29 Sint-pieters-leeuw Vlaams-Brabant 1600",
    "addr:housenumber":"29",
    "addr:postcode":"1600",
    "addr:street":"Dauw-Defossezlaan",
    "iso:country":"BE",
    "sg:address":"Dauw-defossezlaan 29",
    "sg:city":"Sint-pieters-leeuw",
    "sg:orig_category":"Artistes ind\u00e9pendants",
    "sg:phone":"+32 2 377 15 21",
    "sg:postcode":"1600",
    "sg:province":"Vlaams-Brabant",
    "wof:name":"Van Ruysevelt",
    "wof:placetype":"venue"
},
  "geometry": {"coordinates":[4.2788209915,50.8054237366],"type":"Point"}
}