{
  "type": "Feature",
  "properties": {
    "iso:country":"BE",
    "sg:address":"Rue Des Pierres Rouges 15",
    "sg:city":"Bruxelles (watermael-boitsfort)",
    "sg:classifiers":[
        {
            "category":"Social Services",
            "type":"Services"
        }
    ],
    "sg:phone":"+32 2 675 77 54",
    "sg:postcode":"1170",
    "sg:province":"Bruxelles-Capitale",
    "wof:name":"Espace Mediations Familiales",
    "wof:placetype":"venue"
},
  "geometry": {"coordinates":[4.4008731842,50.8031234741],"type":"Point"}
}