{
  "type": "Feature",
  "properties": {
    "addr:full":"Singellaan 38 Hooglede (gits) West-Vlaanderen 8830",
    "addr:housenumber":"38",
    "addr:postcode":"8830",
    "addr:street":"Singellaan",
    "iso:country":"BE",
    "sg:address":"Singellaan 38",
    "sg:city":"Hooglede (gits)",
    "sg:classifiers":[
        {
            "category":"Health Services",
            "subcategory":"Health Practitioner",
            "type":"Services"
        }
    ],
    "sg:phone":"+32 51 20 44 69",
    "sg:postcode":"8830",
    "sg:province":"West-Vlaanderen",
    "sg:tags":[
        "physiotherapist"
    ],
    "wof:name":"Roelens Gaby",
    "wof:placetype":"venue"
},
  "geometry": {"coordinates":[3.100372076,50.9968109131],"type":"Point"}
}