{
  "type": "Feature",
  "properties": {
    "addr:full":"Kontichhof 5 Kontich Antwerpen 2550",
    "addr:housenumber":"5",
    "addr:postcode":"2550",
    "addr:street":"Kontichhof",
    "iso:country":"BE",
    "sg:address":"Kontichhof 5",
    "sg:city":"Kontich",
    "sg:orig_category":"Eleveurs de bovins",
    "sg:phone":"+32 3 457 04 32",
    "sg:postcode":"2550",
    "sg:province":"Antwerpen",
    "wof:name":"Johannes Dekkers",
    "wof:placetype":"venue"
},
  "geometry": {"coordinates":[4.4151039124,51.1376037598],"type":"Point"}
}