{
  "type": "Feature",
  "properties": {
    "iso:country":"BE",
    "sg:address":"Schoonaardestraat 137",
    "sg:city":"Kortenberg (meerbeek)",
    "sg:classifiers":[
        {
            "category":"Real Estate",
            "subcategory":"Architect",
            "type":"Services"
        }
    ],
    "sg:phone":"+32 2 759 47 37",
    "sg:postcode":"3078",
    "sg:province":"Vlaams-Brabant",
    "wof:name":"Lismont J",
    "wof:placetype":"venue"
},
  "geometry": {"coordinates":[4.5937128067,50.8868904114],"type":"Point"}
}