{
  "type": "Feature",
  "properties": {
    "iso:country":"BE",
    "sg:address":"Manestraat 35",
    "sg:city":"Izegem",
    "sg:orig_category":"Air Flow Profiles For Roofs",
    "sg:phone":"+32 51 30 35 42",
    "sg:postcode":"8870",
    "sg:province":"West-Vlaanderen",
    "wof:name":"Decoutere Profielen Nv",
    "wof:placetype":"venue"
},
  "geometry": {"coordinates":[3.1919240952,50.9448623657],"type":"Point"}
}