{
  "type": "Feature",
  "properties": {
    "iso:country":"BE",
    "sg:address":"Klein Raamstraat 6",
    "sg:city":"Heist-op-den-berg (booischot)",
    "sg:classifiers":[
        {
            "category":"Communications",
            "type":"Services"
        }
    ],
    "sg:phone":"+32 15 22 45 20",
    "sg:postcode":"2221",
    "sg:province":"Antwerpen",
    "sg:tags":[
        "translator"
    ],
    "wof:name":"Kataklop",
    "wof:placetype":"venue"
},
  "geometry": {"coordinates":[4.7640380859,51.0380935669],"type":"Point"}
}