{
  "type": "Feature",
  "properties": {
    "addr:full":"Rue Provinciale 25 Celles Hainaut 7760",
    "addr:housenumber":"25",
    "addr:postcode":"7760",
    "addr:street":"Rue Provinciale",
    "iso:country":"BE",
    "sg:address":"Rue Provinciale 25",
    "sg:city":"Celles",
    "sg:orig_category":"Fruits and l\u00e9gumes Boucheries",
    "sg:phone":"+32 69 45 53 58",
    "sg:postcode":"7760",
    "sg:province":"Hainaut",
    "wof:name":"Guy Delecluse",
    "wof:placetype":"venue"
},
  "geometry": {"coordinates":[3.4621250629,50.7105712891],"type":"Point"}
}