{
  "type": "Feature",
  "properties": {
    "iso:country":"BE",
    "sg:address":"Aarschotsesteenweg 269",
    "sg:city":"Tienen",
    "sg:classifiers":[
        {
            "category":"Arena",
            "subcategory":"Sports Club",
            "type":"Entertainment"
        }
    ],
    "sg:phone":"+32 16 81 67 31",
    "sg:postcode":"3300",
    "sg:province":"Vlaams-Brabant",
    "sg:tags":[
        "de"
    ],
    "wof:name":"B.b.c. Zelia Tienen",
    "wof:placetype":"venue"
},
  "geometry": {"coordinates":[4.9253311157,50.8212089539],"type":"Point"}
}