{
  "type": "Feature",
  "properties": {
    "addr:full":"Dorpsplein 3c Wellen Limburg 3830",
    "addr:housenumber":"3c",
    "addr:postcode":"3830",
    "addr:street":"Dorpsplein",
    "iso:country":"BE",
    "sg:address":"Dorpsplein 3c",
    "sg:city":"Wellen",
    "sg:classifiers":[
        {
            "category":"Airport",
            "subcategory":"International",
            "type":"Transportation"
        }
    ],
    "sg:phone":"+32 12 74 26 74",
    "sg:postcode":"3830",
    "sg:province":"Limburg",
    "sg:tags":[
        "-",
        "transport"
    ],
    "wof:name":"M.g. Trans-belgium Nv",
    "wof:placetype":"venue"
},
  "geometry": {"coordinates":[5.3384242058,50.841003418],"type":"Point"}
}