{
  "type": "Feature",
  "properties": {
    "iso:country":"BE",
    "sg:address":"Chemin Hallaux 42",
    "sg:city":"Wavre",
    "sg:classifiers":[
        {
            "category":"Personal",
            "subcategory":"Barber",
            "type":"Services"
        }
    ],
    "sg:phone":"+32 10 22 48 78",
    "sg:postcode":"1300",
    "sg:province":"Brabant Wallon",
    "sg:tags":[
        "gentleman",
        "salon",
        "-",
        "hairdressing"
    ],
    "wof:name":"Main D'or (la) Coiff Fernand",
    "wof:placetype":"venue"
},
  "geometry": {"coordinates":[4.6018519402,50.7164039612],"type":"Point"}
}