{
  "type": "Feature",
  "properties": {
    "addr:full":"Rue Xavier De Bue 16 Bruxelles (uccle) Bruxelles-Capitale 1180",
    "addr:housenumber":"16",
    "addr:postcode":"1180",
    "addr:street":"Rue Xavier De Bue",
    "iso:country":"BE",
    "sg:address":"Rue Xavier De Bue 16",
    "sg:city":"Bruxelles (uccle)",
    "sg:classifiers":[
        {
            "category":"Health Services",
            "subcategory":"Dentist",
            "type":"Services"
        }
    ],
    "sg:phone":"+32 2 347 21 04",
    "sg:postcode":"1180",
    "sg:province":"Bruxelles-Capitale",
    "wof:name":"Trinite-schillemans Bernard",
    "wof:placetype":"venue"
},
  "geometry": {"coordinates":[4.3358478546,50.8035926819],"type":"Point"}
}