{
  "type": "Feature",
  "properties": {
    "iso:country":"BE",
    "sg:address":"Josephine Charlotte Square 11 -",
    "sg:city":"Brussels",
    "sg:classifiers":[
        {
            "category":"Professional",
            "subcategory":"Art Services",
            "type":"Services"
        }
    ],
    "sg:phone":"+32 2 762 58 08",
    "sg:postcode":"1200",
    "sg:province":"Bruxelles-Capitale",
    "sg:tags":[
        "export-import"
    ],
    "wof:name":"Zimbabwe Embassy",
    "wof:placetype":"venue"
},
  "geometry": {"coordinates":[4.4122409821,50.840385437],"type":"Point"}
}